{
  "type": "Feature",
  "properties": {
    "iso:country":"US",
    "sg:address":"4640 Forbes Blvd",
    "sg:city":"Lanham",
    "sg:classifiers":[
        {
            "category":"Professional",
            "subcategory":"Lawyer & Legal Services",
            "type":"Services"
        }
    ],
    "sg:phone":"+1 301 306 0033",
    "sg:postcode":"20706",
    "sg:province":"MD",
    "wof:name":"Gibbs Edwards C Jr Atty",
    "wof:placetype":"venue"
},
  "geometry": {"coordinates":[-76.83560199999999,38.953499],"type":"Point"}
}