{
  "type": "Feature",
  "properties": {
    "iso:country":"US",
    "sg:address":"7923 Belair Rd",
    "sg:city":"Baltimore",
    "sg:classifiers":[
        {
            "category":"Shopping",
            "subcategory":"Department Store",
            "type":"Retail Goods"
        }
    ],
    "sg:phone":"+1 410 661 4921",
    "sg:postcode":"21236",
    "sg:province":"MD",
    "wof:name":"Kmart",
    "wof:placetype":"venue"
},
  "geometry": {"coordinates":[-76.51007199999999,39.373013],"type":"Point"}
}