{
  "type": "Feature",
  "properties": {
    "iso:country":"US",
    "sg:address":"202 E Madison St",
    "sg:city":"Baltimore",
    "sg:classifiers":[
        {
            "category":"Organizations",
            "subcategory":"Religious Organization",
            "type":"Services"
        }
    ],
    "sg:phone":"+1 410 727 5932",
    "sg:postcode":"21202",
    "sg:province":"MD",
    "sg:tags":[
        "church"
    ],
    "wof:name":"Choice Manna Worship Ctr",
    "wof:placetype":"venue"
},
  "geometry": {"coordinates":[-76.612504,39.2988],"type":"Point"}
}