{
  "type": "Feature",
  "properties": {
    "iso:country":"US",
    "sg:address":"97 Clifton Dr",
    "sg:city":"Oakland",
    "sg:classifiers":[
        {
            "category":"Retail",
            "subcategory":"Auto Repair",
            "type":"Services"
        }
    ],
    "sg:phone":"+1 301 334 4144",
    "sg:postcode":"21550",
    "sg:province":"MD",
    "sg:tags":[
        "body",
        "painting",
        "repairing",
        "automobile"
    ],
    "wof:name":"Porter's Body Shop",
    "wof:placetype":"venue"
},
  "geometry": {"coordinates":[-79.35348999999999,39.424363],"type":"Point"}
}