{
  "type": "Feature",
  "properties": {
    "iso:country":"US",
    "sg:address":"11601 Maddox Ct",
    "sg:city":"Gaithersburg",
    "sg:classifiers":[
        {
            "category":"Professional",
            "type":"Services"
        }
    ],
    "sg:phone":"+1 301 315 6071",
    "sg:postcode":"20878",
    "sg:province":"MD",
    "wof:name":"Anna Hahn",
    "wof:placetype":"venue"
},
  "geometry": {"coordinates":[-77.24016399999999,39.099983],"type":"Point"}
}