{
  "type": "Feature",
  "properties": {
    "iso:country":"US",
    "sg:address":"10542 Metropolitan Ave",
    "sg:city":"Kensington",
    "sg:classifiers":[
        {
            "category":"Building & Trades",
            "subcategory":"Construction",
            "type":"Services"
        }
    ],
    "sg:phone":"+1 301 949 1481",
    "sg:postcode":"20895",
    "sg:province":"MD",
    "sg:tags":[
        "contractor"
    ],
    "wof:name":"Farragut Builders Inc",
    "wof:placetype":"venue"
},
  "geometry": {"coordinates":[-77.072998,39.0284],"type":"Point"}
}