{
  "type": "Feature",
  "properties": {
    "addr:full":"135 National Business Pk Laurel MD 20707",
    "addr:housenumber":"135",
    "addr:postcode":"20707",
    "addr:street":"National Business Pk",
    "iso:country":"US",
    "sg:address":"135 National Business Pk",
    "sg:city":"Laurel",
    "sg:classifiers":[
        {
            "category":"Real Estate",
            "subcategory":"Real Estate Services",
            "type":"Services"
        }
    ],
    "sg:phone":"+1 301 490 5904",
    "sg:postcode":"20707",
    "sg:province":"MD",
    "wof:name":"Contstellation Real Estate",
    "wof:placetype":"venue"
},
  "geometry": {"coordinates":[-76.869202,39.098301],"type":"Point"}
}