{
  "type": "Feature",
  "properties": {
    "iso:country":"US",
    "sg:address":"130 Skipjack Rd",
    "sg:city":"Prince Frederick",
    "sg:classifiers":[
        {
            "category":"Real Estate",
            "subcategory":"Real Estate Agent",
            "type":"Services"
        }
    ],
    "sg:phone":"+1 410 414 3195",
    "sg:postcode":"20678",
    "sg:province":"MD",
    "sg:tags":[
        "agency",
        "rental"
    ],
    "wof:name":"United Rentals",
    "wof:placetype":"venue"
},
  "geometry": {"coordinates":[-76.64181499999999,38.509497],"type":"Point"}
}