{
  "type": "Feature",
  "properties": {
    "iso:country":"US",
    "sg:address":"2614 Woodedge Rd",
    "sg:city":"Silver Spring",
    "sg:classifiers":[
        {
            "category":"Building & Trades",
            "subcategory":"Construction",
            "type":"Services"
        }
    ],
    "sg:phone":"+1 301 949 7800",
    "sg:postcode":"20906",
    "sg:province":"MD",
    "sg:tags":[
        "general",
        "contractor"
    ],
    "wof:name":"PFR",
    "wof:placetype":"venue"
},
  "geometry": {"coordinates":[-77.05576600000001,39.072113],"type":"Point"}
}