{
  "type": "Feature",
  "properties": {
    "iso:country":"US",
    "sg:address":"2465 Frederick Ave",
    "sg:city":"Baltimore",
    "sg:classifiers":[
        {
            "category":"Shopping",
            "subcategory":"Beauty & Cosmetics",
            "type":"Retail Goods"
        }
    ],
    "sg:phone":"+1 410 566 7363",
    "sg:postcode":"21223",
    "sg:province":"MD",
    "sg:tags":[
        "supply"
    ],
    "wof:name":"K C Beatuy Supply",
    "wof:placetype":"venue"
},
  "geometry": {"coordinates":[-76.655304,39.283595],"type":"Point"}
}