{
  "type": "Feature",
  "properties": {
    "iso:country":"US",
    "sg:address":"3414 Olney Laytonsville Rd",
    "sg:city":"Olney",
    "sg:classifiers":[
        {
            "category":"Shopping",
            "subcategory":"Bicycles & Sporting Goods",
            "type":"Retail Goods"
        }
    ],
    "sg:phone":"+1 301 260 0361",
    "sg:postcode":"20832",
    "sg:province":"MD",
    "sg:tags":[
        "equipment",
        "skiing"
    ],
    "wof:name":"Ski Racquet",
    "wof:placetype":"venue"
},
  "geometry": {"coordinates":[-77.06919499999999,39.154524],"type":"Point"}
}