{
  "type": "Feature",
  "properties": {
    "iso:country":"US",
    "sg:address":"9514 Deerfoot Way",
    "sg:city":"Columbia",
    "sg:classifiers":[
        {
            "category":"Professional",
            "subcategory":"Lawyer & Legal Services",
            "type":"Services"
        }
    ],
    "sg:phone":"+1 301 953 9768",
    "sg:postcode":"21046",
    "sg:province":"MD",
    "wof:name":"Aspen Law & Business",
    "wof:placetype":"venue"
},
  "geometry": {"coordinates":[-76.838898,39.160384],"type":"Point"}
}