{
  "type": "Feature",
  "properties": {
    "iso:country":"US",
    "sg:address":"1380 Progress Way",
    "sg:city":"Eldersburg",
    "sg:classifiers":[
        {
            "category":"Health Services",
            "subcategory":"Doctor",
            "type":"Services"
        }
    ],
    "sg:phone":"+1 410 552 0305",
    "sg:postcode":"21784",
    "sg:province":"MD",
    "sg:tags":[
        "physician",
        "surgeon"
    ],
    "wof:name":"Maryland Neurological Ctr",
    "wof:placetype":"venue"
},
  "geometry": {"coordinates":[-76.943806,39.412144],"type":"Point"}
}