{
  "type": "Feature",
  "properties": {
    "addr:full":"9419 Spruce Tree Cir Bethesda MD 20814",
    "addr:housenumber":"9419",
    "addr:postcode":"20814",
    "addr:street":"Spruce Tree Cir",
    "iso:country":"US",
    "sg:address":"9419 Spruce Tree Cir",
    "sg:city":"Bethesda",
    "sg:classifiers":[
        {
            "category":"Professional",
            "subcategory":"Lawyer & Legal Services",
            "type":"Services"
        }
    ],
    "sg:phone":"+1 301 530 6612",
    "sg:postcode":"20814",
    "sg:province":"MD",
    "sg:tags":[
        "law"
    ],
    "wof:name":"Goldstone Mark Law Office of",
    "wof:placetype":"venue"
},
  "geometry": {"coordinates":[-77.10968699999999,39.010164],"type":"Point"}
}