{
  "type": "Feature",
  "properties": {
    "addr:full":"5851 Allentown Rd Suitland MD 20746",
    "addr:housenumber":"5851",
    "addr:postcode":"20746",
    "addr:street":"Allentown Rd",
    "iso:country":"US",
    "sg:address":"5851 Allentown Rd",
    "sg:city":"Suitland",
    "sg:classifiers":[
        {
            "category":"Insurance",
            "subcategory":"Insurance Agent",
            "type":"Services"
        }
    ],
    "sg:phone":"+1 301 899 9222",
    "sg:postcode":"20746",
    "sg:province":"MD",
    "sg:tags":[
        "consultant"
    ],
    "wof:name":"Consolidated Financial Svc",
    "wof:placetype":"venue"
},
  "geometry": {"coordinates":[-76.89543399999999,38.811802],"type":"Point"}
}