{
  "type": "Feature",
  "properties": {
    "iso:country":"US",
    "sg:address":"1347 Wilson Rd",
    "sg:city":"Rising Sun",
    "sg:classifiers":[
        {
            "category":"Building & Trades",
            "subcategory":"Construction",
            "type":"Services"
        }
    ],
    "sg:phone":"+1 410 658 5314",
    "sg:postcode":"21911",
    "sg:province":"MD",
    "wof:name":"Ajax Driverways",
    "wof:placetype":"venue"
},
  "geometry": {"coordinates":[-76.012753,39.717171],"type":"Point"}
}