{
  "type": "Feature",
  "properties": {
    "addr:full":"4054 N Point Rd Dundalk MD 21222",
    "addr:housenumber":"4054",
    "addr:postcode":"21222",
    "addr:street":"N Point Rd",
    "iso:country":"US",
    "sg:address":"4054 N Point Rd",
    "sg:city":"Dundalk",
    "sg:classifiers":[
        {
            "category":"Professional",
            "subcategory":"Business Services",
            "type":"Services"
        },
        {
            "category":"Organizations",
            "subcategory":"Professional Association",
            "type":"Services"
        }
    ],
    "sg:phone":"+1 410 477 1857",
    "sg:postcode":"21222",
    "sg:province":"MD",
    "sg:tags":[
        "referral",
        "contractor"
    ],
    "wof:name":"Titan Industrial Services Inc",
    "wof:placetype":"venue"
},
  "geometry": {"coordinates":[-76.466049,39.268776],"type":"Point"}
}