{
  "type": "Feature",
  "properties": {
    "iso:country":"US",
    "sg:address":"3987 Hampstead Mexico Rd",
    "sg:city":"Hampstead",
    "sg:classifiers":[
        {
            "category":"Manufacturing",
            "subcategory":"Metals",
            "type":"Manufacturing & Wholesale Goods"
        }
    ],
    "sg:phone":"+1 410 239 2030",
    "sg:postcode":"21074",
    "sg:province":"MD",
    "sg:tags":[
        "treating",
        "heat"
    ],
    "wof:name":"Aero Brazing Corp",
    "wof:placetype":"venue"
},
  "geometry": {"coordinates":[-76.856595,39.613646],"type":"Point"}
}