{
  "type": "Feature",
  "properties": {
    "iso:country":"US",
    "sg:address":"3137 W North Ave",
    "sg:city":"Baltimore",
    "sg:classifiers":[
        {
            "category":"Organizations",
            "subcategory":"Religious Organization",
            "type":"Services"
        }
    ],
    "sg:phone":"+1 410 362 8800",
    "sg:postcode":"21216",
    "sg:province":"MD",
    "sg:tags":[
        "church"
    ],
    "wof:name":"True Foundation Baptist Church",
    "wof:placetype":"venue"
},
  "geometry": {"coordinates":[-76.670467,39.308898],"type":"Point"}
}