{
  "type": "Feature",
  "properties": {
    "iso:country":"US",
    "sg:address":"6715 Park Heights Ave",
    "sg:city":"Baltimore",
    "sg:classifiers":[
        {
            "category":"Professional",
            "type":"Services"
        }
    ],
    "sg:phone":"+1 410 627 8426",
    "sg:postcode":"21215",
    "sg:province":"MD",
    "sg:tags":[
        "publication",
        "editorial"
    ],
    "sg:website":"http://www.galeinai.net",
    "wof:name":"Gal Einai",
    "wof:placetype":"venue"
},
  "geometry": {"coordinates":[-76.70066,39.363079],"type":"Point"}
}