{
  "type": "Feature",
  "properties": {
    "addr:full":"13900 Berryville Rd Germantown MD 20874",
    "addr:postcode":"13900;20874",
    "addr:street":"Berryville Rd",
    "iso:country":"US",
    "sg:address":"13900 Berryville Rd",
    "sg:city":"Germantown",
    "sg:classifiers":[
        {
            "category":"Organizations",
            "subcategory":"Religious Organization",
            "type":"Services"
        }
    ],
    "sg:phone":"+1 301 869 9326",
    "sg:postcode":"20874",
    "sg:province":"MD",
    "sg:tags":[
        "christ",
        "churches-community"
    ],
    "wof:name":"Seneca Community Church",
    "wof:placetype":"venue"
},
  "geometry": {"coordinates":[-77.32481199999999,39.082933],"type":"Point"}
}