{
  "type": "Feature",
  "properties": {
    "iso:country":"US",
    "sg:address":"2002 David Dr",
    "sg:city":"Edgewood",
    "sg:classifiers":[
        {
            "category":"Professional",
            "type":"Services"
        }
    ],
    "sg:phone":"+1 443 504 2561",
    "sg:postcode":"21040",
    "sg:province":"MD",
    "sg:tags":[
        "transportation"
    ],
    "wof:name":"Eagle Transportation",
    "wof:placetype":"venue"
},
  "geometry": {"coordinates":[-76.320412,39.438461],"type":"Point"}
}