{
  "type": "Feature",
  "properties": {
    "iso:country":"US",
    "sg:address":"2906 Terry Dr",
    "sg:city":"Baltimore",
    "sg:classifiers":[
        {
            "category":"Wholesale",
            "subcategory":"Computers",
            "type":"Manufacturing & Wholesale Goods"
        }
    ],
    "sg:phone":"+1 443 996 6904",
    "sg:postcode":"21209",
    "sg:province":"MD",
    "sg:tags":[
        "equipment"
    ],
    "wof:name":"A S Computer Solutions",
    "wof:placetype":"venue"
},
  "geometry": {"coordinates":[-76.690276,39.369797],"type":"Point"}
}