{
  "type": "Feature",
  "properties": {
    "iso:country":"US",
    "sg:address":"611 Wood Lot Trail Rd",
    "sg:city":"Annapolis",
    "sg:classifiers":[
        {
            "category":"Health Services",
            "subcategory":"Health Practitioner",
            "type":"Services"
        }
    ],
    "sg:phone":"+1 410 897 1127",
    "sg:postcode":"21401",
    "sg:province":"MD",
    "sg:tags":[
        "business",
        "provider"
    ],
    "wof:name":"Bach Consulting Group",
    "wof:placetype":"venue"
},
  "geometry": {"coordinates":[-76.598198,38.996413],"type":"Point"}
}