{
  "type": "Feature",
  "properties": {
    "addr:full":"1583 Potomac Ave Hagerstown MD 21742",
    "addr:housenumber":"1583",
    "addr:postcode":"21742",
    "addr:street":"Potomac Ave",
    "iso:country":"US",
    "sg:address":"1583 Potomac Ave",
    "sg:city":"Hagerstown",
    "sg:classifiers":[
        {
            "category":"Home & Garden",
            "subcategory":"Furniture",
            "type":"Retail Goods"
        }
    ],
    "sg:phone":"+1 301 733 1670",
    "sg:postcode":"21742",
    "sg:province":"MD",
    "wof:name":"Routzahn's",
    "wof:placetype":"venue"
},
  "geometry": {"coordinates":[-77.701948,39.660579],"type":"Point"}
}