{
  "type": "Feature",
  "properties": {
    "addr:full":"11708 Reisterstown Rd Reisterstown MD 21136",
    "addr:housenumber":"11708",
    "addr:postcode":"21136",
    "addr:street":"Reisterstown Rd",
    "iso:country":"US",
    "sg:address":"11708 Reisterstown Rd",
    "sg:city":"Reisterstown",
    "sg:classifiers":[
        {
            "category":"Retail",
            "subcategory":"Self-service Laundry",
            "type":"Services"
        }
    ],
    "sg:phone":"+1 410 833 6500",
    "sg:postcode":"21136",
    "sg:province":"MD",
    "wof:name":"Tina's Tubs & Suds",
    "wof:placetype":"venue"
},
  "geometry": {"coordinates":[-76.81170299999999,39.444838],"type":"Point"}
}