{
  "type": "Feature",
  "properties": {
    "addr:full":"1901 West St Annapolis MD 21401",
    "addr:housenumber":"1901",
    "addr:postcode":"21401",
    "addr:street":"West St",
    "iso:country":"US",
    "sg:address":"1901 West St",
    "sg:city":"Annapolis",
    "sg:classifiers":[
        {
            "category":"Coffee & Tea",
            "type":"Food & Drink"
        }
    ],
    "sg:menulink":"http://www.allmenus.com/md/annapolis/118957-starbucks-coffee/menu/",
    "sg:phone":"+1 410 295 5136",
    "sg:postcode":"21401",
    "sg:province":"MD",
    "sg:tags":[
        "american"
    ],
    "wof:name":"Starbucks Coffee",
    "wof:placetype":"venue"
},
  "geometry": {"coordinates":[-76.523388,38.980001],"type":"Point"}
}