{
  "type": "Feature",
  "properties": {
    "addr:full":"9861 Brokenland Parkway Suite 204 Columbia MD 21046",
    "addr:housenumber":"9861",
    "addr:postcode":"21046",
    "addr:street":"Brokenland Parkway Suite 204",
    "iso:country":"US",
    "sg:address":"9861 Brokenland Parkway Suite 204",
    "sg:city":"Columbia",
    "sg:classifiers":[
        {
            "category":"Professional",
            "subcategory":"Computer Services",
            "type":"Services"
        }
    ],
    "sg:phone":"+1 410 290 3446",
    "sg:postcode":"21046",
    "sg:province":"MD",
    "sg:website":"http://www.airpatrolcorp.com/",
    "wof:name":"AirPatrol Corporation",
    "wof:placetype":"venue"
},
  "geometry": {"coordinates":[-76.847955,39.17914],"type":"Point"}
}