{
  "type": "Feature",
  "properties": {
    "iso:country":"US",
    "sg:address":"2101 Eastern Ave",
    "sg:city":"Baltimore",
    "sg:classifiers":[
        {
            "category":"Banks & Credit Unions",
            "subcategory":"Bank",
            "type":"Services"
        },
        {
            "category":"Banks & Credit Unions",
            "subcategory":"Financial Services",
            "type":"Services"
        }
    ],
    "sg:phone":"+1 410 276 4905",
    "sg:postcode":"21231",
    "sg:province":"MD",
    "sg:tags":[
        "commercial",
        "loan",
        "saving",
        "broker",
        "mortgage"
    ],
    "sg:website":"http://www.kopernikbank.com",
    "wof:name":"Kopernik Federal Bank",
    "wof:placetype":"venue"
},
  "geometry": {"coordinates":[-76.5868,39.285999],"type":"Point"}
}