{
  "type": "Feature",
  "properties": {
    "iso:country":"US",
    "sg:address":"6201 Old Branch Ave",
    "sg:city":"Temple Hills",
    "sg:classifiers":[
        {
            "category":"Home & Garden",
            "subcategory":"Household Appliances",
            "type":"Retail Goods"
        }
    ],
    "sg:phone":"+1 301 316 1944",
    "sg:postcode":"20748",
    "sg:province":"MD",
    "wof:name":"Boulware Appliances Repair Inc",
    "wof:placetype":"venue"
},
  "geometry": {"coordinates":[-76.908321,38.805133],"type":"Point"}
}