{
  "type": "Feature",
  "properties": {
    "addr:full":"5212 Cedar Ln Columbia MD 21044",
    "addr:housenumber":"5212",
    "addr:postcode":"21044",
    "addr:street":"Cedar Ln",
    "iso:country":"US",
    "sg:address":"5212 Cedar Ln",
    "sg:city":"Columbia",
    "sg:classifiers":[
        {
            "category":"Professional",
            "subcategory":"Credit Reporting & Collection",
            "type":"Services"
        }
    ],
    "sg:phone":"+1 410 997 0017",
    "sg:postcode":"21044",
    "sg:province":"MD",
    "sg:tags":[
        "medical",
        "billing"
    ],
    "wof:name":"Dependable Billing Service",
    "wof:placetype":"venue"
},
  "geometry": {"coordinates":[-76.889791,39.230101],"type":"Point"}
}