{
  "type": "Feature",
  "properties": {
    "addr:full":"600 Wyndhurst Ave Baltimore MD 21210",
    "addr:housenumber":"600",
    "addr:postcode":"21210",
    "addr:street":"Wyndhurst Ave",
    "iso:country":"US",
    "sg:address":"600 Wyndhurst Ave",
    "sg:city":"Baltimore",
    "sg:classifiers":[
        {
            "category":"Professional",
            "subcategory":"Business Services",
            "type":"Services"
        }
    ],
    "sg:phone":"+1 410 323 6336",
    "sg:postcode":"21210",
    "sg:province":"MD",
    "sg:tags":[
        "interior",
        "consultant",
        "design",
        "decorator"
    ],
    "wof:name":"Lee & Niles Interiors",
    "wof:placetype":"venue"
},
  "geometry": {"coordinates":[-76.630291,39.353355],"type":"Point"}
}