{
  "type": "Feature",
  "properties": {
    "addr:full":"1498 Reisterstown Road Pikesville MD 21208",
    "addr:housenumber":"1498",
    "addr:postcode":"21208",
    "addr:street":"Reisterstown Road",
    "iso:country":"US",
    "sg:address":"1498 Reisterstown Road",
    "sg:city":"Pikesville",
    "sg:classifiers":[
        {
            "category":"Professional",
            "subcategory":"Detective & Security Services",
            "type":"Services"
        }
    ],
    "sg:phone":"+1 443 468 5944",
    "sg:postcode":"21208",
    "sg:province":"MD",
    "sg:tags":[
        "bail",
        "bond"
    ],
    "wof:name":"Young Money Bail Bonds",
    "wof:placetype":"venue"
},
  "geometry": {"coordinates":[-76.72532699999999,39.377151],"type":"Point"}
}