{
  "type": "Feature",
  "properties": {
    "iso:country":"US",
    "sg:address":"601 N Hammonds Ferry Rd",
    "sg:city":"Linthicum Heights",
    "sg:classifiers":[
        {
            "category":"Sports & Exercise",
            "subcategory":"Gym",
            "type":"Entertainment"
        }
    ],
    "sg:phone":"+1 410 636 7440",
    "sg:postcode":"21090",
    "sg:province":"MD",
    "sg:tags":[
        "trainer"
    ],
    "wof:name":"Australian Health & Fitness",
    "wof:placetype":"venue"
},
  "geometry": {"coordinates":[-76.663696,39.2178],"type":"Point"}
}