{
  "type": "Feature",
  "properties": {
    "iso:country":"US",
    "sg:address":"3215 Leonardtown Rd",
    "sg:city":"Waldorf",
    "sg:classifiers":[
        {
            "category":"Real Estate",
            "subcategory":"Real Estate Agent",
            "type":"Services"
        }
    ],
    "sg:phone":"+1 301 843 3300",
    "sg:postcode":"20601",
    "sg:province":"MD",
    "wof:name":"Matthews Higdon & Shorter",
    "wof:placetype":"venue"
},
  "geometry": {"coordinates":[-76.904483,38.62252],"type":"Point"}
}