{
  "type": "Feature",
  "properties": {
    "iso:country":"US",
    "sg:address":"5001 Holly Spring St",
    "sg:city":"Suitland",
    "sg:classifiers":[
        {
            "category":"Organizations",
            "subcategory":"Religious Organization",
            "type":"Services"
        }
    ],
    "sg:phone":"+1 301 420 9000",
    "sg:postcode":"20746",
    "sg:province":"MD",
    "sg:tags":[
        "church"
    ],
    "wof:name":"True Way Deliverance Church",
    "wof:placetype":"venue"
},
  "geometry": {"coordinates":[-76.924114,38.862418],"type":"Point"}
}