{
  "type": "Feature",
  "properties": {
    "addr:full":"3522 Hiss Ave Parkville MD 21234",
    "addr:housenumber":"3522",
    "addr:postcode":"21234",
    "addr:street":"Hiss Ave",
    "iso:country":"US",
    "sg:address":"3522 Hiss Ave",
    "sg:city":"Parkville",
    "sg:classifiers":[
        {
            "category":"Professional",
            "subcategory":"Employment Agencies",
            "type":"Services"
        }
    ],
    "sg:phone":"+1 410 661 3419",
    "sg:postcode":"21234",
    "sg:province":"MD",
    "wof:name":"Jobs4Me.biz",
    "wof:placetype":"venue"
},
  "geometry": {"coordinates":[-76.523263,39.373444],"type":"Point"}
}