{
  "type": "Feature",
  "properties": {
    "iso:country":"US",
    "sg:address":"3610 Rosedale Rd",
    "sg:city":"Baltimore",
    "sg:classifiers":[
        {
            "category":"Organizations",
            "subcategory":"Religious Organization",
            "type":"Services"
        }
    ],
    "sg:phone":"+1 410 367 5441",
    "sg:postcode":"21215",
    "sg:province":"MD",
    "sg:tags":[
        "clergy"
    ],
    "wof:name":"Jessie R Halsey",
    "wof:placetype":"venue"
},
  "geometry": {"coordinates":[-76.665828,39.326669],"type":"Point"}
}