{
  "type": "Feature",
  "properties": {
    "iso:country":"US",
    "sg:address":"4700 Lawrence St",
    "sg:city":"Hyattsville",
    "sg:classifiers":[
        {
            "category":"Utilities",
            "subcategory":"Recycling",
            "type":"Services"
        },
        {
            "category":"Wholesale",
            "subcategory":"Scrap",
            "type":"Manufacturing & Wholesale Goods"
        }
    ],
    "sg:phone":"+1 301 779 3170",
    "sg:postcode":"20781",
    "sg:province":"MD",
    "sg:tags":[
        "disposal",
        "waste",
        "metal",
        "equipment"
    ],
    "sg:website":"http://www.recycleone.net",
    "wof:name":"Recycle 1C & D Process Inc",
    "wof:placetype":"venue"
},
  "geometry": {"coordinates":[-76.934898,38.931808],"type":"Point"}
}