{
  "type": "Feature",
  "properties": {
    "addr:full":"9640 Lottsford Ct Upper Marlboro MD 20774",
    "addr:postcode":"9640;20774",
    "addr:street":"Lottsford Ct",
    "iso:country":"US",
    "sg:address":"9640 Lottsford Ct",
    "sg:city":"Upper Marlboro",
    "sg:classifiers":[
        {
            "category":"Shopping",
            "subcategory":"Comic Books",
            "type":"Retail Goods"
        }
    ],
    "sg:phone":"+1 301 322 9035",
    "sg:postcode":"20774",
    "sg:province":"MD",
    "wof:name":"Ben Hoffman",
    "wof:placetype":"venue"
},
  "geometry": {"coordinates":[-76.840199,38.911746],"type":"Point"}
}