{
  "type": "Feature",
  "properties": {
    "addr:full":"2309 Forest Dr Annapolis MD 21401",
    "addr:housenumber":"2309",
    "addr:postcode":"21401",
    "addr:street":"Forest Dr",
    "iso:country":"US",
    "sg:address":"2309 Forest Dr",
    "sg:city":"Annapolis",
    "sg:classifiers":[
        {
            "category":"Shopping",
            "subcategory":"Department Store",
            "type":"Retail Goods"
        }
    ],
    "sg:phone":"+1 410 573 0550",
    "sg:postcode":"21401",
    "sg:province":"MD",
    "sg:website":"www.tjmaxx.com",
    "wof:name":"T J Maxx",
    "wof:placetype":"venue"
},
  "geometry": {"coordinates":[-76.53819799999999,38.978303],"type":"Point"}
}