{
  "type": "Feature",
  "properties": {
    "iso:country":"US",
    "sg:address":"2122 Rose Theatre Cir",
    "sg:city":"Olney",
    "sg:classifiers":[
        {
            "category":"Professional",
            "subcategory":"Advertising",
            "type":"Services"
        }
    ],
    "sg:phone":"+1 301 924 0074",
    "sg:postcode":"20832",
    "sg:province":"MD",
    "sg:tags":[
        "counselor"
    ],
    "wof:name":"Michael J Green-Advertising",
    "wof:placetype":"venue"
},
  "geometry": {"coordinates":[-77.047375,39.146957],"type":"Point"}
}