{
  "type": "Feature",
  "properties": {
    "iso:country":"US",
    "sg:address":"2500 Wallington Way # 208",
    "sg:city":"Marriottsville",
    "sg:classifiers":[
        {
            "category":"Professional",
            "subcategory":"Employment Agencies",
            "type":"Services"
        }
    ],
    "sg:phone":"+1 410 480 8002",
    "sg:postcode":"21104",
    "sg:province":"MD",
    "sg:tags":[
        "opportunity",
        "contractor"
    ],
    "sg:website":"http://www.kjmkmanagement.com",
    "wof:name":"Realstreet Staffing",
    "wof:placetype":"venue"
},
  "geometry": {"coordinates":[-76.897797,39.309399],"type":"Point"}
}