{
  "type": "Feature",
  "properties": {
    "iso:country":"US",
    "sg:address":"716 Parkway Cir",
    "sg:city":"Salisbury",
    "sg:classifiers":[
        {
            "category":"Building & Trades",
            "subcategory":"Construction",
            "type":"Services"
        }
    ],
    "sg:phone":"+1 410 749 4802",
    "sg:postcode":"21804",
    "sg:province":"MD",
    "sg:tags":[
        "altering",
        "remodeling",
        "contractor"
    ],
    "wof:name":"Shore Renovations Ltd",
    "wof:placetype":"venue"
},
  "geometry": {"coordinates":[-75.584188,38.365041],"type":"Point"}
}