{
  "type": "Feature",
  "properties": {
    "addr:full":"5335 Wisconsin Ave NW Washington MD 20015",
    "addr:housenumber":"5335",
    "addr:postcode":"20015",
    "addr:street":"Wisconsin Ave Nw",
    "iso:country":"US",
    "sg:address":"5335 Wisconsin Ave NW",
    "sg:city":"Washington",
    "sg:classifiers":[
        {
            "category":"Professional",
            "subcategory":"Lawyer & Legal Services",
            "type":"Services"
        }
    ],
    "sg:phone":"+1 202 686 4858",
    "sg:postcode":"20015",
    "sg:province":"MD",
    "sg:tags":[
        "attorney"
    ],
    "wof:name":"Chapman & Robinson Law Offices",
    "wof:placetype":"venue"
},
  "geometry": {"coordinates":[-77.084846,38.959041],"type":"Point"}
}