{
  "type": "Feature",
  "properties": {
    "iso:country":"US",
    "sg:address":"7202 McKinney Cir",
    "sg:city":"Frederick",
    "sg:classifiers":[
        {
            "category":"Manufacturing",
            "subcategory":"Chemicals & Compounds",
            "type":"Manufacturing & Wholesale Goods"
        }
    ],
    "sg:phone":"+1 301 695 8500",
    "sg:postcode":"21704",
    "sg:province":"MD",
    "sg:tags":[
        "paint"
    ],
    "wof:name":"Mc Cormick Paints",
    "wof:placetype":"venue"
},
  "geometry": {"coordinates":[-77.418536,39.361641],"type":"Point"}
}