{
  "type": "Feature",
  "properties": {
    "iso:country":"US",
    "sg:address":"5510 Baltimore National Pike",
    "sg:city":"Catonsville",
    "sg:classifiers":[
        {
            "category":"Food & Beverages",
            "subcategory":"Groceries & Convenience Stores",
            "type":"Retail Goods"
        }
    ],
    "sg:phone":"+1 410 788 0398",
    "sg:postcode":"21228",
    "sg:province":"MD",
    "wof:name":"Asia Supermarket",
    "wof:placetype":"venue"
},
  "geometry": {"coordinates":[-76.72159499999999,39.290597],"type":"Point"}
}