{
  "type": "Feature",
  "properties": {
    "addr:full":"1450 Bennett Point Rd Queenstown MD 21658",
    "addr:housenumber":"1450",
    "addr:postcode":"21658",
    "addr:street":"Bennett Point Rd",
    "iso:country":"US",
    "sg:address":"1450 Bennett Point Rd",
    "sg:city":"Queenstown",
    "sg:classifiers":[
        {
            "category":"Building & Trades",
            "subcategory":"Construction",
            "type":"Services"
        }
    ],
    "sg:phone":"+1 410 827 8856",
    "sg:postcode":"21658",
    "sg:province":"MD",
    "sg:tags":[
        "house"
    ],
    "wof:name":"Hammerschlag LLC",
    "wof:placetype":"venue"
},
  "geometry": {"coordinates":[-76.173331,38.932591],"type":"Point"}
}