{
  "type": "Feature",
  "properties": {
    "addr:full":"18200 Georgia Ave Olney MD 20832",
    "addr:housenumber":"18200",
    "addr:postcode":"20832",
    "addr:street":"Georgia Ave",
    "iso:country":"US",
    "sg:address":"18200 Georgia Ave",
    "sg:city":"Olney",
    "sg:classifiers":[
        {
            "category":"Restaurant",
            "type":"Food & Drink"
        }
    ],
    "sg:phone":"+1 301 570 4967",
    "sg:postcode":"20832",
    "sg:province":"MD",
    "wof:name":"Bella Notte",
    "wof:placetype":"venue"
},
  "geometry": {"coordinates":[-77.06639699999999,39.156023],"type":"Point"}
}