{
  "type": "Feature",
  "properties": {
    "addr:full":"750 Sportsman Ct Hampstead MD 21074",
    "addr:housenumber":"750",
    "addr:postcode":"21074",
    "addr:street":"Sportsman Ct",
    "iso:country":"US",
    "sg:address":"750 Sportsman Ct",
    "sg:city":"Hampstead",
    "sg:classifiers":[
        {
            "category":"Professional",
            "subcategory":"Management & Consulting",
            "type":"Services"
        }
    ],
    "sg:phone":"+1 410 374 8393",
    "sg:postcode":"21074",
    "sg:province":"MD",
    "sg:tags":[
        "training",
        "sales"
    ],
    "wof:name":"Victory Morgann Inc",
    "wof:placetype":"venue"
},
  "geometry": {"coordinates":[-76.84166,39.59504],"type":"Point"}
}