{
  "type": "Feature",
  "properties": {
    "iso:country":"US",
    "sg:address":"4400 Stamp Rd Ste 204",
    "sg:city":"Temple Hills",
    "sg:classifiers":[
        {
            "category":"Health Services",
            "subcategory":"Doctor",
            "type":"Services"
        }
    ],
    "sg:phone":"+1 301 420 9475",
    "sg:postcode":"20748",
    "sg:province":"MD",
    "sg:tags":[
        "surgeon",
        "oral"
    ],
    "wof:name":"Brown William C DDS",
    "wof:placetype":"venue"
},
  "geometry": {"coordinates":[-76.943787,38.827603],"type":"Point"}
}