{
  "type": "Feature",
  "properties": {
    "iso:country":"US",
    "sg:address":"929 W Saratoga St",
    "sg:city":"Baltimore",
    "sg:classifiers":[
        {
            "category":"Restaurant",
            "type":"Food & Drink"
        }
    ],
    "sg:phone":"+1 410 728 4850",
    "sg:postcode":"21223",
    "sg:province":"MD",
    "sg:tags":[
        "out"
    ],
    "wof:name":"Dorly Chinese Carry Out",
    "wof:placetype":"venue"
},
  "geometry": {"coordinates":[-76.633851,39.292399],"type":"Point"}
}