{
  "type": "Feature",
  "properties": {
    "iso:country":"US",
    "sg:address":"4816 Lindsay Rd",
    "sg:city":"Baltimore",
    "sg:classifiers":[
        {
            "category":"Shopping",
            "subcategory":"Shoes",
            "type":"Retail Goods"
        }
    ],
    "sg:phone":"+1 410 908 7681",
    "sg:postcode":"21229",
    "sg:province":"MD",
    "wof:name":"Chanel's Impression",
    "wof:placetype":"venue"
},
  "geometry": {"coordinates":[-76.706127,39.295945],"type":"Point"}
}