{
  "type": "Feature",
  "properties": {
    "addr:full":"5401 Radecke Ave Baltimore MD 21206",
    "addr:housenumber":"5401",
    "addr:postcode":"21206",
    "addr:street":"Radecke Ave",
    "iso:country":"US",
    "sg:address":"5401 Radecke Ave",
    "sg:city":"Baltimore",
    "sg:classifiers":[
        {
            "category":"Food & Beverages",
            "subcategory":"Groceries & Convenience Stores",
            "type":"Retail Goods"
        }
    ],
    "sg:phone":"+1 410 483 3188",
    "sg:postcode":"21206",
    "sg:province":"MD",
    "wof:name":"Khalid Abusamaha Dba",
    "wof:placetype":"venue"
},
  "geometry": {"coordinates":[-76.541656,39.328994],"type":"Point"}
}