{
  "type": "Feature",
  "properties": {
    "iso:country":"US",
    "sg:address":"503 S Burhans Blvd E",
    "sg:city":"Hagerstown",
    "sg:classifiers":[
        {
            "category":"Building & Trades",
            "subcategory":"Electrical",
            "type":"Services"
        }
    ],
    "sg:phone":"+1 301 733 8954",
    "sg:postcode":"21740",
    "sg:province":"MD",
    "sg:tags":[
        "electric",
        "contractor"
    ],
    "wof:name":"CBS Electric Co",
    "wof:placetype":"venue"
},
  "geometry": {"coordinates":[-77.735607,39.638463],"type":"Point"}
}