{
  "type": "Feature",
  "properties": {
    "addr:full":"7 Church Ln Pikesville MD 21208",
    "addr:housenumber":"7",
    "addr:postcode":"21208",
    "addr:street":"Church Ln",
    "iso:country":"US",
    "sg:address":"7 Church Ln",
    "sg:city":"Pikesville",
    "sg:classifiers":[
        {
            "category":"Professional",
            "type":"Services"
        }
    ],
    "sg:phone":"+1 410 415 6807",
    "sg:postcode":"21208",
    "sg:province":"MD",
    "sg:tags":[
        "establishment"
    ],
    "wof:name":"Ira Miller & Co Pa",
    "wof:placetype":"venue"
},
  "geometry": {"coordinates":[-76.724452,39.374899],"type":"Point"}
}