{
  "type": "Feature",
  "properties": {
    "addr:full":"7 Pleasant View Church Rd Port Deposit MD 21904",
    "addr:housenumber":"7",
    "addr:postcode":"21904",
    "addr:street":"Church Rd",
    "iso:country":"US",
    "sg:address":"7 Pleasant View Church Rd",
    "sg:city":"Port Deposit",
    "sg:classifiers":[
        {
            "category":"Organizations",
            "subcategory":"Religious Organization",
            "type":"Services"
        }
    ],
    "sg:phone":"+1 410 658 4834",
    "sg:postcode":"21904",
    "sg:province":"MD",
    "sg:tags":[
        "church"
    ],
    "wof:name":"Lighthouse Christian Academy",
    "wof:placetype":"venue"
},
  "geometry": {"coordinates":[-76.07716499999999,39.613276],"type":"Point"}
}