{
  "type": "Feature",
  "properties": {
    "addr:full":"10 Park Ave Gaithersburg MD 20877",
    "addr:housenumber":"10",
    "addr:postcode":"20877",
    "addr:street":"Park Ave",
    "iso:country":"US",
    "sg:address":"10 Park Ave",
    "sg:city":"Gaithersburg",
    "sg:classifiers":[
        {
            "category":"Building & Trades",
            "subcategory":"Construction",
            "type":"Services"
        }
    ],
    "sg:phone":"+1 301 924 4910",
    "sg:postcode":"20877",
    "sg:province":"MD",
    "sg:tags":[
        "concrete",
        "contractor"
    ],
    "sg:website":"www.amconcrete.com",
    "wof:name":"Amcon Inc",
    "wof:placetype":"venue"
},
  "geometry": {"coordinates":[-77.19446499999999,39.145808],"type":"Point"}
}