{
  "type": "Feature",
  "properties": {
    "iso:country":"US",
    "sg:address":"2406 Cooper Ave",
    "sg:city":"Sparrows Point",
    "sg:classifiers":[
        {
            "category":"Freight",
            "type":"Transportation"
        }
    ],
    "sg:phone":"+1 410 388 1727",
    "sg:postcode":"21219",
    "sg:province":"MD",
    "sg:tags":[
        "trucking"
    ],
    "wof:name":"Pointe Trucking",
    "wof:placetype":"venue"
},
  "geometry": {"coordinates":[-76.449623,39.228726],"type":"Point"}
}