{
  "type": "Feature",
  "properties": {
    "addr:full":"9804 Korman Ct Potomac MD 20854",
    "addr:housenumber":"9804",
    "addr:postcode":"20854",
    "addr:street":"Korman Ct",
    "iso:country":"US",
    "sg:address":"9804 Korman Ct",
    "sg:city":"Potomac",
    "sg:classifiers":[
        {
            "category":"Professional",
            "type":"Services"
        }
    ],
    "sg:phone":"+1 301 983 0503",
    "sg:postcode":"20854",
    "sg:province":"MD",
    "sg:tags":[
        "establishment"
    ],
    "wof:name":"N J Greenbaum",
    "wof:placetype":"venue"
},
  "geometry": {"coordinates":[-77.20504699999999,39.041966],"type":"Point"}
}