{
  "type": "Feature",
  "properties": {
    "iso:country":"US",
    "sg:address":"4951 Nicholson Ct",
    "sg:city":"Kensington",
    "sg:classifiers":[
        {
            "category":"Home & Garden",
            "subcategory":"Carpets & Floor Coverings",
            "type":"Retail Goods"
        }
    ],
    "sg:phone":"+1 301 230 0538",
    "sg:postcode":"20895",
    "sg:province":"MD",
    "sg:tags":[
        "carpeting"
    ],
    "wof:name":"Pooshan World of Rugs",
    "wof:placetype":"venue"
},
  "geometry": {"coordinates":[-77.10340100000001,39.044998],"type":"Point"}
}