{
  "type": "Feature",
  "properties": {
    "iso:country":"US",
    "sg:address":"3521 W Belvedere Ave",
    "sg:city":"Baltimore",
    "sg:classifiers":[
        {
            "category":"Real Estate",
            "subcategory":"Developer",
            "type":"Services"
        }
    ],
    "sg:phone":"+1 410 578 7190",
    "sg:postcode":"21215",
    "sg:province":"MD",
    "wof:name":"Development Corp",
    "wof:placetype":"venue"
},
  "geometry": {"coordinates":[-76.678362,39.34739],"type":"Point"}
}