{
  "type": "Feature",
  "properties": {
    "addr:full":"3521 W Belvedere Ave Baltimore MD 21215",
    "addr:housenumber":"3521",
    "addr:postcode":"21215",
    "addr:street":"W Belvedere Ave",
    "iso:country":"US",
    "sg:address":"3521 W Belvedere Ave",
    "sg:city":"Baltimore",
    "sg:classifiers":[
        {
            "category":"Real Estate",
            "subcategory":"Developer",
            "type":"Services"
        }
    ],
    "sg:phone":"+1 410 578 7190",
    "sg:postcode":"21215",
    "sg:province":"MD",
    "wof:name":"Development Corp",
    "wof:placetype":"venue"
},
  "geometry": {"coordinates":[-76.67836200000001,39.34739],"type":"Point"}
}