{
  "type": "Feature",
  "properties": {
    "iso:country":"US",
    "sg:address":"3000 Abingdon Rd",
    "sg:city":"Abingdon",
    "sg:classifiers":[
        {
            "category":"Food & Beverages",
            "subcategory":"Groceries & Convenience Stores",
            "type":"Retail Goods"
        }
    ],
    "sg:phone":"+1 410 569 1699",
    "sg:postcode":"21009",
    "sg:province":"MD",
    "wof:name":"7-Eleven",
    "wof:placetype":"venue"
},
  "geometry": {"coordinates":[-76.309148,39.47751],"type":"Point"}
}