{
  "type": "Feature",
  "properties": {
    "addr:full":"205 Old Bridge Rd Chestertown MD 21620",
    "addr:housenumber":"205",
    "addr:postcode":"21620",
    "addr:street":"Old Bridge Rd",
    "iso:country":"US",
    "sg:address":"205 Old Bridge Rd",
    "sg:city":"Chestertown",
    "sg:classifiers":[
        {
            "category":"Health Services",
            "subcategory":"Clinic",
            "type":"Services"
        }
    ],
    "sg:phone":"+1 410 778 8152",
    "sg:postcode":"21620",
    "sg:province":"MD",
    "sg:tags":[
        "home",
        "care"
    ],
    "wof:name":"Debbie B Ramsey",
    "wof:placetype":"venue"
},
  "geometry": {"coordinates":[-76.054164,39.205083],"type":"Point"}
}