{
  "type": "Feature",
  "properties": {
    "iso:country":"US",
    "sg:address":"8121 Barlowe Rd",
    "sg:city":"Landover",
    "sg:classifiers":[
        {
            "category":"Shopping",
            "subcategory":"Discount & Variety Stores",
            "type":"Retail Goods"
        }
    ],
    "sg:phone":"+1 301 772 1475",
    "sg:postcode":"20785",
    "sg:province":"MD",
    "wof:name":"John S Variety",
    "wof:placetype":"venue"
},
  "geometry": {"coordinates":[-76.866074,38.919193],"type":"Point"}
}