{
  "type": "Feature",
  "properties": {
    "iso:country":"US",
    "sg:address":"54 W Baltimore St",
    "sg:city":"Taneytown",
    "sg:classifiers":[
        {
            "category":"Retail",
            "subcategory":"Repair Shop",
            "type":"Services"
        }
    ],
    "sg:phone":"+1 410 756 2724",
    "sg:postcode":"21787",
    "sg:province":"MD",
    "sg:tags":[
        "upholsterer"
    ],
    "wof:name":"Hans Krogh Upholstering Co",
    "wof:placetype":"venue"
},
  "geometry": {"coordinates":[-77.178134,39.661511],"type":"Point"}
}