{
  "type": "Feature",
  "properties": {
    "addr:full":"1284 Smallwood Dr W Waldorf MD 20603",
    "addr:housenumber":"1284",
    "addr:postcode":"20603",
    "addr:street":"Smallwood Dr W",
    "iso:country":"US",
    "sg:address":"1284 Smallwood Dr W",
    "sg:city":"Waldorf",
    "sg:classifiers":[
        {
            "category":"Health Services",
            "subcategory":"Doctor",
            "type":"Services"
        }
    ],
    "sg:phone":"+1 301 705 9660",
    "sg:postcode":"20603",
    "sg:province":"MD",
    "sg:tags":[
        "dentist"
    ],
    "wof:name":"St Charles Towne Dental Ctr",
    "wof:placetype":"venue"
},
  "geometry": {"coordinates":[-76.926811,38.612552],"type":"Point"}
}