{
  "type": "Feature",
  "properties": {
    "addr:full":"10901 York Rd Cockysvl Hnt Vly MD 21030",
    "addr:housenumber":"10901",
    "addr:postcode":"21030",
    "addr:street":"York Rd;Hnt Vly",
    "iso:country":"US",
    "sg:address":"10901 York Rd",
    "sg:city":"Cockysvl Hnt Vly",
    "sg:classifiers":[
        {
            "category":"Personal",
            "subcategory":"Beauty Salon",
            "type":"Services"
        }
    ],
    "sg:phone":"+1 410 785 0606",
    "sg:postcode":"21030",
    "sg:province":"MD",
    "sg:tags":[
        "manicuring"
    ],
    "wof:name":"Amys Hoof & Nail",
    "wof:placetype":"venue"
},
  "geometry": {"coordinates":[-76.645819,39.48563],"type":"Point"}
}