{
  "type": "Feature",
  "properties": {
    "iso:country":"US",
    "sg:address":"1139 Thompson Ave",
    "sg:city":"Severn",
    "sg:classifiers":[
        {
            "category":"Food & Beverages",
            "subcategory":"Meat & Fish",
            "type":"Retail Goods"
        }
    ],
    "sg:phone":"+1 410 551 9753",
    "sg:postcode":"21144",
    "sg:province":"MD",
    "sg:tags":[
        "seafood"
    ],
    "wof:name":"Oak Grove Inn",
    "wof:placetype":"venue"
},
  "geometry": {"coordinates":[-76.671712,39.12716],"type":"Point"}
}