{
  "type": "Feature",
  "properties": {
    "iso:country":"US",
    "sg:address":"6905 Oakland Mills Rd",
    "sg:city":"Columbia",
    "sg:classifiers":[
        {
            "category":"Personal",
            "subcategory":"Tanning Parlor",
            "type":"Services"
        }
    ],
    "sg:phone":"+1 410 381 6660",
    "sg:postcode":"21045",
    "sg:province":"MD",
    "sg:tags":[
        "salon"
    ],
    "wof:name":"Hot Off The Beach Tan & Tone",
    "wof:placetype":"venue"
},
  "geometry": {"coordinates":[-76.828267,39.179491],"type":"Point"}
}