{
  "type": "Feature",
  "properties": {
    "iso:country":"US",
    "sg:address":"6685 Glen Albin Rd",
    "sg:city":"La Plata",
    "sg:classifiers":[
        {
            "category":"Retail",
            "subcategory":"Veterinary Services",
            "type":"Services"
        }
    ],
    "sg:phone":"+1 301 932 1881",
    "sg:postcode":"20646",
    "sg:province":"MD",
    "sg:tags":[
        "veterinarian"
    ],
    "wof:name":"Animal Clinic Of LA Plata",
    "wof:placetype":"venue"
},
  "geometry": {"coordinates":[-76.980467,38.521051],"type":"Point"}
}