{
  "type": "Feature",
  "properties": {
    "iso:country":"US",
    "sg:address":"2400 E Monument St",
    "sg:city":"Baltimore",
    "sg:classifiers":[
        {
            "category":"Professional",
            "subcategory":"Accounting & Tax Preparation",
            "type":"Services"
        }
    ],
    "sg:phone":"+1 410 276 0285",
    "sg:postcode":"21205",
    "sg:province":"MD",
    "sg:tags":[
        "return",
        "filing"
    ],
    "wof:name":"H & R Block Tax Svc",
    "wof:placetype":"venue"
},
  "geometry": {"coordinates":[-76.58302399999999,39.298829],"type":"Point"}
}