{
  "type": "Feature",
  "properties": {
    "addr:full":"9705 Natalie Dr Upper Marlboro MD 20772",
    "addr:housenumber":"9705",
    "addr:postcode":"20772",
    "addr:street":"Natalie Dr",
    "iso:country":"US",
    "sg:address":"9705 Natalie Dr",
    "sg:city":"Upper Marlboro",
    "sg:classifiers":[
        {
            "category":"Building & Trades",
            "subcategory":"Construction",
            "type":"Services"
        }
    ],
    "sg:phone":"+1 301 877 2498",
    "sg:postcode":"20772",
    "sg:province":"MD",
    "sg:tags":[
        "general",
        "contractor"
    ],
    "wof:name":"MAO Construction",
    "wof:placetype":"venue"
},
  "geometry": {"coordinates":[-76.818854,38.756406],"type":"Point"}
}