{
  "type": "Feature",
  "properties": {
    "iso:country":"US",
    "sg:address":"3512 Kings Point Rd",
    "sg:city":"Randallstown",
    "sg:classifiers":[
        {
            "category":"Organizations",
            "subcategory":"Religious Organization",
            "type":"Services"
        }
    ],
    "sg:phone":"+1 410 655 0975",
    "sg:postcode":"21133",
    "sg:province":"MD",
    "sg:tags":[
        "place",
        "worship",
        "church"
    ],
    "wof:name":"Zion Sacred Church Inc",
    "wof:placetype":"venue"
},
  "geometry": {"coordinates":[-76.83107800000001,39.369881],"type":"Point"}
}