{
  "type": "Feature",
  "properties": {
    "addr:full":"10 Brenda Ct Severna Park MD 21146",
    "addr:housenumber":"10",
    "addr:postcode":"21146",
    "addr:street":"Brenda Ct",
    "iso:country":"US",
    "sg:address":"10 Brenda Ct",
    "sg:city":"Severna Park",
    "sg:classifiers":[
        {
            "category":"Recreation",
            "type":"Entertainment"
        }
    ],
    "sg:phone":"+1 410 647 4536",
    "sg:postcode":"21146",
    "sg:province":"MD",
    "sg:tags":[
        "pool",
        "swimming"
    ],
    "wof:name":"Evergreen Swim Club",
    "wof:placetype":"venue"
},
  "geometry": {"coordinates":[-76.564486,39.07286],"type":"Point"}
}