{
  "type": "Feature",
  "properties": {
    "addr:full":"15609 New Hampshire Ave Colesville MD 20905",
    "addr:housenumber":"15609",
    "addr:postcode":"20905",
    "addr:street":"New Hampshire Ave",
    "iso:country":"US",
    "sg:address":"15609 New Hampshire Ave",
    "sg:city":"Colesville",
    "sg:classifiers":[
        {
            "category":"Professional",
            "subcategory":"Lawyer & Legal Services",
            "type":"Services"
        }
    ],
    "sg:phone":"+1 301 384 1741",
    "sg:postcode":"20905",
    "sg:province":"MD",
    "wof:name":"Barr Michael B Atty",
    "wof:placetype":"venue"
},
  "geometry": {"coordinates":[-76.994418,39.112446],"type":"Point"}
}