{
  "type": "Feature",
  "properties": {
    "addr:full":"326 E Dover St Easton MD 21601",
    "addr:housenumber":"326",
    "addr:postcode":"21601",
    "addr:street":"E Dover St",
    "iso:country":"US",
    "sg:address":"326 E Dover St",
    "sg:city":"Easton",
    "sg:classifiers":[
        {
            "category":"Restaurant",
            "type":"Food & Drink"
        }
    ],
    "sg:phone":"+1 410 819 6677",
    "sg:postcode":"21601",
    "sg:province":"MD",
    "sg:tags":[
        "beverage"
    ],
    "wof:name":"Super Soda Ctr",
    "wof:placetype":"venue"
},
  "geometry": {"coordinates":[-76.07073,38.774097],"type":"Point"}
}