{
  "type": "Feature",
  "properties": {
    "addr:full":"129 Apple Blossom Way Gaithersburg MD 20878",
    "addr:housenumber":"129",
    "addr:postcode":"20878",
    "addr:street":"Apple Blossom Way",
    "iso:country":"US",
    "sg:address":"129 Apple Blossom Way",
    "sg:city":"Gaithersburg",
    "sg:classifiers":[
        {
            "category":"Education",
            "subcategory":"Special Training",
            "type":"Public Place"
        }
    ],
    "sg:phone":"+1 301 216 0368",
    "sg:postcode":"20878",
    "sg:province":"MD",
    "sg:tags":[
        "instructor",
        "language",
        "cantonese"
    ],
    "wof:name":"Wingwah L Wong",
    "wof:placetype":"venue"
},
  "geometry": {"coordinates":[-77.23504200000001,39.147272],"type":"Point"}
}