{
  "type": "Feature",
  "properties": {
    "iso:country":"US",
    "sg:address":"3301 Rocks Rd",
    "sg:city":"Jarrettsville",
    "sg:classifiers":[
        {
            "category":"Farming",
            "subcategory":"Farm",
            "type":"Manufacturing & Wholesale Goods"
        }
    ],
    "sg:phone":"+1 410 838 4876",
    "sg:postcode":"21084",
    "sg:province":"MD",
    "wof:name":"Garden Fence Farm",
    "wof:placetype":"venue"
},
  "geometry": {"coordinates":[-76.400522,39.626037],"type":"Point"}
}