{
  "type": "Feature",
  "properties": {
    "addr:full":"412 Main St Gaithersburg MD 20878",
    "addr:housenumber":"412",
    "addr:postcode":"20878",
    "addr:street":"Main St",
    "iso:country":"US",
    "sg:address":"412 Main St",
    "sg:city":"Gaithersburg",
    "sg:classifiers":[
        {
            "category":"Health Services",
            "subcategory":"Optometrist",
            "type":"Services"
        }
    ],
    "sg:phone":"+1 301 987 9381",
    "sg:postcode":"20878",
    "sg:province":"MD",
    "wof:name":"Crystal Eyes Inc",
    "wof:placetype":"venue"
},
  "geometry": {"coordinates":[-77.23604400000001,39.121007],"type":"Point"}
}