{
  "type": "Feature",
  "properties": {
    "iso:country":"US",
    "sg:address":"3200 Main St",
    "sg:city":"Grasonville",
    "sg:classifiers":[
        {
            "category":"Home & Garden",
            "subcategory":"Furniture",
            "type":"Retail Goods"
        }
    ],
    "sg:phone":"+1 410 827 3299",
    "sg:postcode":"21638",
    "sg:province":"MD",
    "wof:name":"Clabber Hill Furniture Store",
    "wof:placetype":"venue"
},
  "geometry": {"coordinates":[-76.242261,38.968052],"type":"Point"}
}