{
  "type": "Feature",
  "properties": {
    "addr:full":"2739 Garfield Ave Silver Spring MD 20910",
    "addr:housenumber":"2739",
    "addr:postcode":"20910",
    "addr:street":"Garfield Ave",
    "iso:country":"US",
    "sg:address":"2739 Garfield Ave",
    "sg:city":"Silver Spring",
    "sg:classifiers":[
        {
            "category":"Autos & Motor Vehicles",
            "subcategory":"Automobile Sales",
            "type":"Retail Goods"
        }
    ],
    "sg:phone":"+1 301 563 3433",
    "sg:postcode":"20910",
    "sg:province":"MD",
    "sg:tags":[
        "car"
    ],
    "wof:name":"D & J Automotive Inc",
    "wof:placetype":"venue"
},
  "geometry": {"coordinates":[-77.056099,39.001801],"type":"Point"}
}