{
  "type": "Feature",
  "properties": {
    "addr:full":"405 E Joppa Rd Towson MD 21286",
    "addr:housenumber":"405",
    "addr:postcode":"21286",
    "addr:street":"E Joppa Rd",
    "iso:country":"US",
    "sg:address":"405 E Joppa Rd",
    "sg:city":"Towson",
    "sg:classifiers":[
        {
            "category":"Building & Trades",
            "subcategory":"Construction",
            "type":"Services"
        }
    ],
    "sg:phone":"+1 410 494 1777",
    "sg:postcode":"21286",
    "sg:province":"MD",
    "sg:tags":[
        "general",
        "contractor"
    ],
    "wof:name":"Hogg Construction",
    "wof:placetype":"venue"
},
  "geometry": {"coordinates":[-76.595557,39.401683],"type":"Point"}
}