{
  "type": "Feature",
  "properties": {
    "iso:country":"US",
    "sg:address":"2523 Little Vista Ter",
    "sg:city":"Olney",
    "sg:classifiers":[
        {
            "category":"Shopping",
            "subcategory":"Antiques",
            "type":"Retail Goods"
        },
        {
            "category":"Shopping",
            "subcategory":"Catalog Store",
            "type":"Retail Goods"
        },
        {
            "category":"Shopping",
            "type":"Retail Goods"
        }
    ],
    "sg:phone":"+1 301 523 1666",
    "sg:postcode":"20832",
    "sg:province":"MD",
    "sg:tags":[
        "collectible",
        "order",
        "mail",
        "online"
    ],
    "wof:name":"Scott Sports",
    "wof:placetype":"venue"
},
  "geometry": {"coordinates":[-77.052483,39.161415],"type":"Point"}
}