{
  "type": "Feature",
  "properties": {
    "iso:country":"US",
    "sg:address":"3701 Spruell Dr",
    "sg:city":"Silver Spring",
    "sg:classifiers":[
        {
            "category":"Organizations",
            "subcategory":"Religious Organization",
            "type":"Services"
        }
    ],
    "sg:phone":"+1 301 946 6000",
    "sg:postcode":"20902",
    "sg:province":"MD",
    "sg:tags":[
        "church"
    ],
    "wof:name":"Good Shepherd Church of the Brethren",
    "wof:placetype":"venue"
},
  "geometry": {"coordinates":[-77.07746899999999,39.043773],"type":"Point"}
}