{
  "type": "Feature",
  "properties": {
    "addr:full":"808 Baltimore Rd Rockville MD 20851",
    "addr:housenumber":"808",
    "addr:postcode":"20851",
    "addr:street":"Baltimore Rd",
    "iso:country":"US",
    "sg:address":"808 Baltimore Rd",
    "sg:city":"Rockville",
    "sg:classifiers":[
        {
            "category":"Food & Beverages",
            "subcategory":"Groceries & Convenience Stores",
            "type":"Retail Goods"
        }
    ],
    "sg:phone":"+1 301 610 2009",
    "sg:postcode":"20851",
    "sg:province":"MD",
    "sg:tags":[
        "grocer"
    ],
    "wof:name":"Ventura Market",
    "wof:placetype":"venue"
},
  "geometry": {"coordinates":[-77.13463900000001,39.084485],"type":"Point"}
}