{
  "type": "Feature",
  "properties": {
    "addr:full":"1611 Mount Hermon Rd Salisbury MD 21804",
    "addr:housenumber":"1611",
    "addr:postcode":"21804",
    "addr:street":"Mount Hermon Rd",
    "iso:country":"US",
    "sg:address":"1611 Mount Hermon Rd",
    "sg:city":"Salisbury",
    "sg:classifiers":[
        {
            "category":"Professional",
            "subcategory":"Business Services",
            "type":"Services"
        }
    ],
    "sg:phone":"+1 410 543 8718",
    "sg:postcode":"21804",
    "sg:province":"MD",
    "sg:tags":[
        "recording",
        "studio"
    ],
    "wof:name":"Crystal River Productions",
    "wof:placetype":"venue"
},
  "geometry": {"coordinates":[-75.55216299999999,38.360786],"type":"Point"}
}