{
  "type": "Feature",
  "properties": {
    "iso:country":"US",
    "sg:address":"25702 Valley Park Ter",
    "sg:city":"Damascus",
    "sg:classifiers":[
        {
            "category":"Professional",
            "type":"Services"
        }
    ],
    "sg:phone":"+1 301 253 6764",
    "sg:postcode":"20872",
    "sg:province":"MD",
    "wof:name":"A&T Transcription Inc",
    "wof:placetype":"venue"
},
  "geometry": {"coordinates":[-77.205108,39.279584],"type":"Point"}
}