{
  "type": "Feature",
  "properties": {
    "iso:country":"US",
    "sg:address":"1700 Frederick St",
    "sg:city":"Cumberland",
    "sg:classifiers":[
        {
            "category":"Organizations",
            "subcategory":"Religious Organization",
            "type":"Services"
        }
    ],
    "sg:phone":"+1 301 724 1150",
    "sg:postcode":"21502",
    "sg:province":"MD",
    "sg:tags":[
        "church"
    ],
    "wof:name":"New Covenent United Methodist",
    "wof:placetype":"venue"
},
  "geometry": {"coordinates":[-78.742677,39.6745],"type":"Point"}
}