{
  "type": "Feature",
  "properties": {
    "addr:full":"1908 Forest Dr Annapolis MD 21401",
    "addr:housenumber":"1908",
    "addr:postcode":"21401",
    "addr:street":"Forest Dr",
    "iso:country":"US",
    "sg:address":"1908 Forest Dr",
    "sg:city":"Annapolis",
    "sg:classifiers":[
        {
            "category":"Professional",
            "type":"Services"
        },
        {
            "category":"Deli",
            "type":"Food & Drink"
        },
        {
            "category":"Restaurant",
            "type":"Food & Drink"
        }
    ],
    "sg:phone":"+1 443 482 2828",
    "sg:postcode":"21401",
    "sg:province":"MD",
    "sg:tags":[
        "delicatessen",
        "caterer"
    ],
    "sg:website":"http://www.carlscafeandcatering.com",
    "wof:name":"Carl's Cafe And Catering",
    "wof:placetype":"venue"
},
  "geometry": {"coordinates":[-76.52623,38.9744],"type":"Point"}
}