{
  "type": "Feature",
  "properties": {
    "iso:country":"US",
    "sg:address":"500 N Calvert St",
    "sg:city":"Baltimore",
    "sg:classifiers":[
        {
            "category":"Professional",
            "subcategory":"Art Services",
            "type":"Services"
        }
    ],
    "sg:phone":"+1 301 449 6509",
    "sg:postcode":"21202",
    "sg:province":"MD",
    "sg:tags":[
        "designer",
        "display",
        "producer"
    ],
    "wof:name":"Ivilo Beauty Concept",
    "wof:placetype":"venue"
},
  "geometry": {"coordinates":[-76.612717,39.295219],"type":"Point"}
}