{
  "type": "Feature",
  "properties": {
    "addr:full":"2400 Research Blvd Rockville MD 20850",
    "addr:housenumber":"2400",
    "addr:postcode":"20850",
    "addr:street":"Research Blvd",
    "iso:country":"US",
    "sg:address":"2400 Research Blvd",
    "sg:city":"Rockville",
    "sg:classifiers":[
        {
            "category":"Shopping",
            "subcategory":"Clothing, Apparel, & Fashions",
            "type":"Retail Goods"
        }
    ],
    "sg:phone":"+1 240 243 1030",
    "sg:postcode":"20850",
    "sg:province":"MD",
    "wof:name":"CME Outfitters",
    "wof:placetype":"venue"
},
  "geometry": {"coordinates":[-77.187164,39.104312],"type":"Point"}
}