{
  "type": "Feature",
  "properties": {
    "addr:full":"1400 W Joppa Rd Towson MD 21204",
    "addr:housenumber":"1400",
    "addr:postcode":"21204",
    "addr:street":"W Joppa Rd",
    "iso:country":"US",
    "sg:address":"1400 W Joppa Rd",
    "sg:city":"Towson",
    "sg:classifiers":[
        {
            "category":"Building & Trades",
            "subcategory":"Cleaning & Sanitation",
            "type":"Services"
        }
    ],
    "sg:phone":"+1 410 821 7662",
    "sg:postcode":"21204",
    "sg:province":"MD",
    "sg:tags":[
        "snow",
        "removal"
    ],
    "wof:name":"APM Contracting Co",
    "wof:placetype":"venue"
},
  "geometry": {"coordinates":[-76.635572,39.411051],"type":"Point"}
}