{
  "type": "Feature",
  "properties": {
    "iso:country":"US",
    "sg:address":"7305 Old Battle Grove Rd",
    "sg:city":"Dundalk",
    "sg:classifiers":[
        {
            "category":"Building & Trades",
            "subcategory":"Construction",
            "type":"Services"
        }
    ],
    "sg:phone":"+1 410 477 9800",
    "sg:postcode":"21222",
    "sg:province":"MD",
    "sg:tags":[
        "home",
        "improvement"
    ],
    "wof:name":"Bear Creek Home Improvements",
    "wof:placetype":"venue"
},
  "geometry": {"coordinates":[-76.477198,39.265512],"type":"Point"}
}