{
  "type": "Feature",
  "properties": {
    "iso:country":"US",
    "sg:address":"5 Bradley Ct",
    "sg:city":"Pocomoke City",
    "sg:classifiers":[
        {
            "category":"Shopping",
            "subcategory":"Hobbies, Toys, & Games",
            "type":"Retail Goods"
        }
    ],
    "sg:phone":"+1 410 957 6582",
    "sg:postcode":"21851",
    "sg:province":"MD",
    "sg:tags":[
        "craft",
        "supply"
    ],
    "wof:name":"Martin Burton's Art Supply",
    "wof:placetype":"venue"
},
  "geometry": {"coordinates":[-75.56101099999999,38.073434],"type":"Point"}
}