{
  "type": "Feature",
  "properties": {
    "iso:country":"US",
    "sg:address":"12851 Wisteria Dr",
    "sg:city":"Germantown",
    "sg:classifiers":[
        {
            "category":"Health Services",
            "subcategory":"Chiropractor",
            "type":"Services"
        }
    ],
    "sg:phone":"+1 301 515 5300",
    "sg:postcode":"20874",
    "sg:province":"MD",
    "wof:name":"Injury Center Of America",
    "wof:placetype":"venue"
},
  "geometry": {"coordinates":[-77.269261,39.176556],"type":"Point"}
}