{
  "type": "Feature",
  "properties": {
    "addr:full":"1 Bayswater Ct Gaithersburg MD 20878",
    "addr:housenumber":"1",
    "addr:postcode":"20878",
    "addr:street":"Bayswater Ct",
    "iso:country":"US",
    "sg:address":"1 Bayswater Ct",
    "sg:city":"Gaithersburg",
    "sg:classifiers":[
        {
            "category":"Structure",
            "subcategory":"Office Building",
            "type":"Public Place"
        }
    ],
    "sg:phone":"+1 301 869 6563",
    "sg:postcode":"20878",
    "sg:province":"MD",
    "sg:tags":[
        "park"
    ],
    "wof:name":"Kbd Properties",
    "wof:placetype":"venue"
},
  "geometry": {"coordinates":[-77.252899,39.134151],"type":"Point"}
}