{
  "type": "Feature",
  "properties": {
    "iso:country":"US",
    "sg:address":"7401 Van Dusen Rd",
    "sg:city":"Laurel",
    "sg:classifiers":[
        {
            "category":"Restaurant",
            "type":"Food & Drink"
        }
    ],
    "sg:phone":"+1 301 470 1730",
    "sg:postcode":"20707",
    "sg:province":"MD",
    "wof:name":"Panda West",
    "wof:placetype":"venue"
},
  "geometry": {"coordinates":[-76.881192,39.084974],"type":"Point"}
}