{
  "type": "Feature",
  "properties": {
    "iso:country":"US",
    "sg:address":"6740 Business Pkwy",
    "sg:city":"Elkridge",
    "sg:classifiers":[
        {
            "category":"Manufacturing",
            "subcategory":"Chemicals & Compounds",
            "type":"Manufacturing & Wholesale Goods"
        }
    ],
    "sg:phone":"+1 410 796 5400",
    "sg:postcode":"21075",
    "sg:province":"MD",
    "sg:tags":[
        "pharmaceutical",
        "products-wholesale",
        "mfg",
        "solution",
        "ophthalmic",
        "manufacturer"
    ],
    "sg:website":"http://www.alconlabs.com",
    "wof:name":"Alcon Laboratories, Inc.",
    "wof:placetype":"venue"
},
  "geometry": {"coordinates":[-76.772058,39.183479],"type":"Point"}
}