{
  "type": "Feature",
  "properties": {
    "iso:country":"US",
    "sg:address":"6427 Landover Rd",
    "sg:city":"Cheverly",
    "sg:classifiers":[
        {
            "category":"Food & Beverages",
            "subcategory":"Groceries & Convenience Stores",
            "type":"Retail Goods"
        }
    ],
    "sg:phone":"+1 301 772 9401",
    "sg:postcode":"20785",
    "sg:province":"MD",
    "wof:name":"Dove Cot International",
    "wof:placetype":"venue"
},
  "geometry": {"coordinates":[-76.9058,38.932999],"type":"Point"}
}