{
  "type": "Feature",
  "properties": {
    "iso:country":"US",
    "sg:address":"210 Abrecht Pl",
    "sg:city":"Frederick",
    "sg:classifiers":[
        {
            "category":"Freight",
            "type":"Transportation"
        },
        {
            "category":"Building & Trades",
            "subcategory":"Construction",
            "type":"Services"
        }
    ],
    "sg:phone":"+1 301 663 0890",
    "sg:postcode":"21701",
    "sg:province":"MD",
    "sg:tags":[
        "concrete",
        "contractor",
        "storage",
        "facility"
    ],
    "wof:name":"Foland H Frank & Son Inc",
    "wof:placetype":"venue"
},
  "geometry": {"coordinates":[-77.417563,39.414365],"type":"Point"}
}