{
  "type": "Feature",
  "properties": {
    "addr:full":"455 Palmer Ter Westminster MD 21158",
    "addr:housenumber":"455",
    "addr:postcode":"21158",
    "addr:street":"Palmer Ter",
    "iso:country":"US",
    "sg:address":"455 Palmer Ter",
    "sg:city":"Westminster",
    "sg:classifiers":[
        {
            "category":"Building & Trades",
            "subcategory":"Construction",
            "type":"Services"
        }
    ],
    "sg:phone":"+1 410 876 9308",
    "sg:postcode":"21158",
    "sg:province":"MD",
    "sg:tags":[
        "general",
        "contractor"
    ],
    "wof:name":"Demario Construction",
    "wof:placetype":"venue"
},
  "geometry": {"coordinates":[-77.016369,39.578113],"type":"Point"}
}