{
  "type": "Feature",
  "properties": {
    "addr:full":"827 Bayridge Dr Gaithersburg MD 20878",
    "addr:housenumber":"827",
    "addr:postcode":"20878",
    "addr:street":"Bayridge Dr",
    "iso:country":"US",
    "sg:address":"827 Bayridge Dr",
    "sg:city":"Gaithersburg",
    "sg:classifiers":[
        {
            "category":"Professional",
            "subcategory":"Management & Consulting",
            "type":"Services"
        }
    ],
    "sg:phone":"+1 301 975 8598",
    "sg:postcode":"20878",
    "sg:province":"MD",
    "sg:tags":[
        "consultant",
        "scientist"
    ],
    "wof:name":"Mekhontsev Sergey",
    "wof:placetype":"venue"
},
  "geometry": {"coordinates":[-77.234065,39.131371],"type":"Point"}
}