{
  "type": "Feature",
  "properties": {
    "iso:country":"US",
    "sg:address":"6400 Montrose Rd",
    "sg:city":"Rockville",
    "sg:classifiers":[
        {
            "category":"Organizations",
            "subcategory":"Religious Organization",
            "type":"Services"
        }
    ],
    "sg:phone":"+1 301 770 2688",
    "sg:postcode":"20852",
    "sg:province":"MD",
    "wof:name":"Robert Kieval Rev",
    "wof:placetype":"venue"
},
  "geometry": {"coordinates":[-77.131796,39.053245],"type":"Point"}
}