{
  "type": "Feature",
  "properties": {
    "iso:country":"US",
    "sg:address":"101 S Eaton St Ste A",
    "sg:city":"Baltimore",
    "sg:classifiers":[
        {
            "category":"Restaurant",
            "type":"Food & Drink"
        }
    ],
    "sg:phone":"+1 410 534 2222",
    "sg:postcode":"21224",
    "sg:province":"MD",
    "sg:tags":[
        "style",
        "latin",
        "american",
        "family"
    ],
    "wof:name":"Pollo Real",
    "wof:placetype":"venue"
},
  "geometry": {"coordinates":[-76.565359,39.291216],"type":"Point"}
}