{
  "type": "Feature",
  "properties": {
    "iso:country":"US",
    "sg:address":"3197 Main St",
    "sg:city":"Manchester",
    "sg:classifiers":[
        {
            "category":"Retail",
            "subcategory":"Repair Shop",
            "type":"Services"
        }
    ],
    "sg:phone":"+1 410 365 2117",
    "sg:postcode":"21102",
    "sg:province":"MD",
    "wof:name":"Blind Pig",
    "wof:placetype":"venue"
},
  "geometry": {"coordinates":[-76.884669,39.661284],"type":"Point"}
}