{
  "type": "Feature",
  "properties": {
    "iso:country":"US",
    "sg:address":"8717 Yellow Springs Rd",
    "sg:city":"Frederick",
    "sg:classifiers":[
        {
            "category":"Education",
            "subcategory":"School",
            "type":"Public Place"
        }
    ],
    "sg:phone":"+1 301 694 1475",
    "sg:postcode":"21702",
    "sg:province":"MD",
    "sg:tags":[
        "elementary",
        "executive"
    ],
    "sg:website":"http://www.careertech.net",
    "wof:name":"Yellow Springs Elementary Schl",
    "wof:placetype":"venue"
},
  "geometry": {"coordinates":[-77.45395600000001,39.472838],"type":"Point"}
}