{
  "type": "Feature",
  "properties": {
    "addr:full":"18017 Highfield Rd Ashton MD 20861",
    "addr:housenumber":"18017",
    "addr:postcode":"20861",
    "addr:street":"Highfield Rd",
    "iso:country":"US",
    "sg:address":"18017 Highfield Rd",
    "sg:city":"Ashton",
    "sg:classifiers":[
        {
            "category":"Real Estate",
            "subcategory":"Real Estate Agent",
            "type":"Services"
        }
    ],
    "sg:phone":"+1 301 654 2211",
    "sg:postcode":"20861",
    "sg:province":"MD",
    "wof:name":"Ceccone Company",
    "wof:placetype":"venue"
},
  "geometry": {"coordinates":[-76.987836,39.150962],"type":"Point"}
}