{
  "type": "Feature",
  "properties": {
    "addr:full":"3 Federal St Easton MD 21601",
    "addr:housenumber":"3",
    "addr:postcode":"21601",
    "addr:street":"Federal St",
    "iso:country":"US",
    "sg:address":"3 Federal St",
    "sg:city":"Easton",
    "sg:classifiers":[
        {
            "category":"Real Estate",
            "subcategory":"Real Estate Services",
            "type":"Services"
        }
    ],
    "sg:phone":"+1 410 820 8299",
    "sg:postcode":"21601",
    "sg:province":"MD",
    "sg:tags":[
        "company",
        "title"
    ],
    "wof:name":"Shore Abstract & Title Svc Inc",
    "wof:placetype":"venue"
},
  "geometry": {"coordinates":[-76.076358,38.775311],"type":"Point"}
}