{
  "type": "Feature",
  "properties": {
    "iso:country":"US",
    "sg:address":"8855 Veterans Hwy",
    "sg:city":"Millersville",
    "sg:classifiers":[
        {
            "category":"Professional",
            "subcategory":"Secretarial Services",
            "type":"Services"
        }
    ],
    "sg:phone":"+1 443 748 3182",
    "sg:postcode":"21108",
    "sg:province":"MD",
    "sg:tags":[
        "answering",
        "telephone"
    ],
    "wof:name":"Lindsey's Message Service",
    "wof:placetype":"venue"
},
  "geometry": {"coordinates":[-76.629819,39.074274],"type":"Point"}
}