{
  "type": "Feature",
  "properties": {
    "addr:full":"8585 Woodyard Rd Clinton MD 20735",
    "addr:housenumber":"8585",
    "addr:postcode":"20735",
    "addr:street":"Woodyard Rd",
    "iso:country":"US",
    "sg:address":"8585 Woodyard Rd",
    "sg:city":"Clinton",
    "sg:classifiers":[
        {
            "category":"Local Transit",
            "type":"Transportation"
        }
    ],
    "sg:phone":"+1 301 856 6800",
    "sg:postcode":"20735",
    "sg:province":"MD",
    "sg:tags":[
        "limousine"
    ],
    "wof:name":"Co Co Mo's Limousine Svc",
    "wof:placetype":"venue"
},
  "geometry": {"coordinates":[-76.875332,38.771841],"type":"Point"}
}