{
  "type": "Feature",
  "properties": {
    "iso:country":"US",
    "sg:address":"8503 Harford Rd",
    "sg:city":"Parkville",
    "sg:classifiers":[
        {
            "category":"Professional",
            "subcategory":"Lawyer & Legal Services",
            "type":"Services"
        }
    ],
    "sg:phone":"+1 410 665 9256",
    "sg:postcode":"21234",
    "sg:province":"MD",
    "sg:tags":[
        "process",
        "server"
    ],
    "wof:name":"Prompt Process Servers",
    "wof:placetype":"venue"
},
  "geometry": {"coordinates":[-76.536514,39.381146],"type":"Point"}
}