{
  "type": "Feature",
  "properties": {
    "addr:full":"5646 Randolph Rd Rockville MD 20852",
    "addr:housenumber":"5646",
    "addr:postcode":"20852",
    "addr:street":"Randolph Rd",
    "iso:country":"US",
    "sg:address":"5646 Randolph Rd",
    "sg:city":"Rockville",
    "sg:classifiers":[
        {
            "category":"Autos & Motor Vehicles",
            "subcategory":"Auto Supplies",
            "type":"Retail Goods"
        },
        {
            "category":"Retail",
            "subcategory":"Auto Repair",
            "type":"Services"
        }
    ],
    "sg:phone":"+1 301 770 0323",
    "sg:postcode":"20852",
    "sg:province":"MD",
    "sg:tags":[
        "wheel",
        "tire",
        "retread",
        "balancing",
        "wheels-aligning",
        "recap",
        "brake"
    ],
    "sg:website":"http://www.merchantstire.com",
    "wof:name":"Merchant's Tire",
    "wof:placetype":"venue"
},
  "geometry": {"coordinates":[-77.11317200000001,39.053257],"type":"Point"}
}