{
  "type": "Feature",
  "properties": {
    "addr:full":"4405 National Pike Grantsville MD 21536",
    "addr:housenumber":"4405",
    "addr:postcode":"21536",
    "addr:street":"National Pike",
    "iso:country":"US",
    "sg:address":"4405 National Pike",
    "sg:city":"Grantsville",
    "sg:classifiers":[
        {
            "category":"Transit Center",
            "subcategory":"Freight",
            "type":"Transportation"
        },
        {
            "category":"Freight",
            "type":"Transportation"
        }
    ],
    "sg:phone":"+1 301 895 4002",
    "sg:postcode":"21536",
    "sg:province":"MD",
    "sg:tags":[
        "local",
        "trucking-motor",
        "trucking"
    ],
    "wof:name":"John Menges Trucking Inc",
    "wof:placetype":"venue"
},
  "geometry": {"coordinates":[-79.241141,39.695061],"type":"Point"}
}