{
  "type": "Feature",
  "properties": {
    "addr:full":"5908 E Pratt St Baltimore MD 21224",
    "addr:housenumber":"5908",
    "addr:postcode":"21224",
    "addr:street":"E Pratt St",
    "iso:country":"US",
    "sg:address":"5908 E Pratt St",
    "sg:city":"Baltimore",
    "sg:classifiers":[
        {
            "category":"Real Estate",
            "subcategory":"Real Estate Operator",
            "type":"Services"
        }
    ],
    "sg:phone":"+1 410 558 9070",
    "sg:postcode":"21224",
    "sg:province":"MD",
    "sg:tags":[
        "building",
        "apartment"
    ],
    "wof:name":"Professional Staff Apartm",
    "wof:placetype":"venue"
},
  "geometry": {"coordinates":[-76.544518,39.290607],"type":"Point"}
}