{
  "type": "Feature",
  "properties": {
    "addr:full":"1 Gristmill Ct Apt 610 Pikesville MD 21208",
    "addr:housenumber":"1;610",
    "addr:postcode":"21208",
    "addr:street":"Gristmill Ct Apt",
    "iso:country":"US",
    "sg:address":"1 Gristmill Ct Apt 610",
    "sg:city":"Pikesville",
    "sg:classifiers":[
        {
            "category":"Banks & Credit Unions",
            "subcategory":"Financial Services",
            "type":"Services"
        }
    ],
    "sg:phone":"+1 410 486 8645",
    "sg:postcode":"21208",
    "sg:province":"MD",
    "sg:tags":[
        "information",
        "consumer"
    ],
    "wof:name":"David Harans",
    "wof:placetype":"venue"
},
  "geometry": {"coordinates":[-76.724159,39.391151],"type":"Point"}
}