{
  "type": "Feature",
  "properties": {
    "iso:country":"US",
    "sg:address":"11119 Rockville Pike",
    "sg:city":"Rockville",
    "sg:classifiers":[
        {
            "category":"Health Services",
            "subcategory":"Doctor",
            "type":"Services"
        }
    ],
    "sg:phone":"+1 301 984 0012",
    "sg:postcode":"20852",
    "sg:province":"MD",
    "sg:tags":[
        "dentist"
    ],
    "wof:name":"Melvin A Reff DDS",
    "wof:placetype":"venue"
},
  "geometry": {"coordinates":[-77.10930399999999,39.039669],"type":"Point"}
}