{
  "type": "Feature",
  "properties": {
    "iso:country":"US",
    "sg:address":"10630 Riggs Hill Rd",
    "sg:city":"Jessup",
    "sg:classifiers":[
        {
            "category":"Wholesale",
            "subcategory":"Vending Machines",
            "type":"Manufacturing & Wholesale Goods"
        }
    ],
    "sg:phone":"+1 301 604 9804",
    "sg:postcode":"20794",
    "sg:province":"MD",
    "wof:name":"Perfect Break Systems",
    "wof:placetype":"venue"
},
  "geometry": {"coordinates":[-76.80089599999999,39.134894],"type":"Point"}
}