{
  "type": "Feature",
  "properties": {
    "addr:full":"7335 E Furnace Branch Rd Glen Burnie MD 21060",
    "addr:housenumber":"7335",
    "addr:postcode":"21060",
    "addr:street":"E Furnace Branch Rd",
    "iso:country":"US",
    "sg:address":"7335 E Furnace Branch Rd",
    "sg:city":"Glen Burnie",
    "sg:classifiers":[
        {
            "category":"Insurance",
            "subcategory":"Insurance Agent",
            "type":"Services"
        }
    ],
    "sg:phone":"+1 410 768 6760",
    "sg:postcode":"21060",
    "sg:province":"MD",
    "wof:name":"A Action Insurance",
    "wof:placetype":"venue"
},
  "geometry": {"coordinates":[-76.60515599999999,39.170584],"type":"Point"}
}