{
  "type": "Feature",
  "properties": {
    "iso:country":"US",
    "sg:address":"3 Woodthorne Ct",
    "sg:city":"Owings Mills",
    "sg:classifiers":[
        {
            "category":"Building & Trades",
            "subcategory":"Construction",
            "type":"Services"
        }
    ],
    "sg:phone":"+1 410 581 0735",
    "sg:postcode":"21117",
    "sg:province":"MD",
    "sg:tags":[
        "painter"
    ],
    "wof:name":"Lloyd's Painting Inc",
    "wof:placetype":"venue"
},
  "geometry": {"coordinates":[-76.769022,39.413298],"type":"Point"}
}