{
  "type": "Feature",
  "properties": {
    "iso:country":"US",
    "sg:address":"24035 Three Notch Rd",
    "sg:city":"Hollywood",
    "sg:classifiers":[
        {
            "category":"Health Services",
            "subcategory":"Doctor",
            "type":"Services"
        }
    ],
    "sg:phone":"+1 301 373 7600",
    "sg:postcode":"20636",
    "sg:province":"MD",
    "wof:name":"Fritz Kelly L MD",
    "wof:placetype":"venue"
},
  "geometry": {"coordinates":[-76.55422,38.3296],"type":"Point"}
}