{
  "type": "Feature",
  "properties": {
    "addr:full":"711 W 40th St Baltimore MD 21211",
    "addr:housenumber":"711",
    "addr:postcode":"21211",
    "addr:street":"W 40Th St",
    "iso:country":"US",
    "sg:address":"711 W 40th St",
    "sg:city":"Baltimore",
    "sg:classifiers":[
        {
            "category":"Utilities",
            "subcategory":"Mobile Phone",
            "type":"Services"
        },
        {
            "category":"Shopping",
            "subcategory":"Mobile Phones",
            "type":"Retail Goods"
        },
        {
            "category":"Utilities",
            "subcategory":"Telephone",
            "type":"Services"
        },
        {
            "category":"Professional",
            "subcategory":"Computer Services",
            "type":"Services"
        }
    ],
    "sg:phone":"+1 410 366 4820",
    "sg:postcode":"21211",
    "sg:province":"MD",
    "sg:tags":[
        "telecommunication",
        "supply",
        "communication",
        "system",
        "wireless",
        "equipment",
        "cellular"
    ],
    "sg:website":"http://clickserve.dartsearch.net/link/click?lid=43000000308049899",
    "wof:name":"T-Mobile",
    "wof:placetype":"venue"
},
  "geometry": {"coordinates":[-76.628646,39.337208],"type":"Point"}
}