{
  "type": "Feature",
  "properties": {
    "addr:full":"3725 Tanglewood Ln Davidsonville MD 21035",
    "addr:housenumber":"3725",
    "addr:postcode":"21035",
    "addr:street":"Tanglewood Ln",
    "iso:country":"US",
    "sg:address":"3725 Tanglewood Ln",
    "sg:city":"Davidsonville",
    "sg:classifiers":[
        {
            "category":"Retail",
            "subcategory":"Veterinary Services",
            "type":"Services"
        }
    ],
    "sg:phone":"+1 410 956 5733",
    "sg:postcode":"21035",
    "sg:province":"MD",
    "sg:tags":[
        "veterinarian"
    ],
    "sg:website":"www.davidsonvillevet.com",
    "wof:name":"Davidsonville Veterinary Clnc",
    "wof:placetype":"venue"
},
  "geometry": {"coordinates":[-76.664232,38.905381],"type":"Point"}
}