{
  "type": "Feature",
  "properties": {
    "addr:full":"7007 Security Blvd Windsor Mill MD 21244",
    "addr:housenumber":"7007",
    "addr:postcode":"21244",
    "addr:street":"Security Blvd",
    "iso:country":"US",
    "sg:address":"7007 Security Blvd",
    "sg:city":"Windsor Mill",
    "sg:classifiers":[
        {
            "category":"Banks & Credit Unions",
            "subcategory":"Bank",
            "type":"Services"
        }
    ],
    "sg:phone":"+1 410 298 2270",
    "sg:postcode":"21244",
    "sg:province":"MD",
    "sg:website":"www.1stmarinerbank.com",
    "wof:name":"1st Mariner Bank",
    "wof:placetype":"venue"
},
  "geometry": {"coordinates":[-76.7509,39.312801],"type":"Point"}
}