{
  "type": "Feature",
  "properties": {
    "iso:country":"US",
    "sg:address":"14311 Cartwright Way",
    "sg:city":"North Potomac",
    "sg:classifiers":[
        {
            "category":"Banks & Credit Unions",
            "subcategory":"Investment Brokerage",
            "type":"Services"
        }
    ],
    "sg:phone":"+1 301 527 1758",
    "sg:postcode":"20878",
    "sg:province":"MD",
    "sg:tags":[
        "consultant",
        "planning",
        "financial"
    ],
    "wof:name":"ALM Invertment Research",
    "wof:placetype":"venue"
},
  "geometry": {"coordinates":[-77.226482,39.087582],"type":"Point"}
}