{
  "type": "Feature",
  "properties": {
    "addr:full":"2515 Saint Paul St Baltimore MD 21218",
    "addr:housenumber":"2515",
    "addr:postcode":"21218",
    "addr:street":"Saint Paul St",
    "iso:country":"US",
    "sg:address":"2515 Saint Paul St",
    "sg:city":"Baltimore",
    "sg:classifiers":[
        {
            "category":"Arts & Performance",
            "subcategory":"Music",
            "type":"Entertainment"
        }
    ],
    "sg:phone":"+1 410 467 4900",
    "sg:postcode":"21218",
    "sg:province":"MD",
    "sg:tags":[
        "arranger",
        "composer"
    ],
    "wof:name":"Bang N Beat Entertainment",
    "wof:placetype":"venue"
},
  "geometry": {"coordinates":[-76.615444,39.318323],"type":"Point"}
}