{
  "type": "Feature",
  "properties": {
    "addr:full":"1800 Redwood Ter NW Washington MD 20012",
    "addr:housenumber":"1800",
    "addr:postcode":"20012",
    "addr:street":"Redwood Ter Nw",
    "iso:country":"US",
    "sg:address":"1800 Redwood Ter NW",
    "sg:city":"Washington",
    "sg:classifiers":[
        {
            "category":"Professional",
            "subcategory":"Lawyer & Legal Services",
            "type":"Services"
        }
    ],
    "sg:phone":"+1 202 882 0700",
    "sg:postcode":"20012",
    "sg:province":"MD",
    "sg:tags":[
        "attorney"
    ],
    "wof:name":"David L Lowans",
    "wof:placetype":"venue"
},
  "geometry": {"coordinates":[-77.043025,38.988825],"type":"Point"}
}