{
  "type": "Feature",
  "properties": {
    "iso:country":"US",
    "sg:address":"20 Riverview Ave",
    "sg:city":"Annapolis",
    "sg:classifiers":[
        {
            "category":"Shopping",
            "subcategory":"Used Merchandise",
            "type":"Retail Goods"
        }
    ],
    "sg:phone":"+1 410 266 5550",
    "sg:postcode":"21409",
    "sg:province":"MD",
    "sg:tags":[
        "antique"
    ],
    "wof:name":"Annapolis Antique-Consignment",
    "wof:placetype":"venue"
},
  "geometry": {"coordinates":[-76.511288,38.99528],"type":"Point"}
}