{
  "type": "Feature",
  "properties": {
    "iso:country":"US",
    "sg:address":"1645 Liberty Rd Ste 202",
    "sg:city":"Sykesville",
    "sg:classifiers":[
        {
            "category":"Health Services",
            "subcategory":"Doctor",
            "type":"Services"
        },
        {
            "category":"Health Services",
            "subcategory":"Podiatrist",
            "type":"Services"
        }
    ],
    "sg:phone":"+1 410 795 2889",
    "sg:postcode":"21784",
    "sg:province":"MD",
    "sg:tags":[
        "physician",
        "surgeon",
        "surgeons"
    ],
    "wof:name":"Dundlak Office",
    "wof:placetype":"venue"
},
  "geometry": {"coordinates":[-76.937607,39.400341],"type":"Point"}
}