{
  "type": "Feature",
  "properties": {
    "addr:full":"7826 Eastern Ave NW Washington MD 20910",
    "addr:housenumber":"7826",
    "addr:postcode":"20910",
    "addr:street":"Eastern Ave Nw",
    "iso:country":"US",
    "sg:address":"7826 Eastern Ave NW",
    "sg:city":"Washington",
    "sg:classifiers":[
        {
            "category":"Building & Trades",
            "subcategory":"Cleaning & Sanitation",
            "type":"Services"
        }
    ],
    "sg:phone":"+1 202 726 4256",
    "sg:postcode":"20910",
    "sg:province":"MD",
    "sg:tags":[
        "janitor"
    ],
    "wof:name":"Busy Bee Environmental Svc",
    "wof:placetype":"venue"
},
  "geometry": {"coordinates":[-77.027427,38.985158],"type":"Point"}
}