{
  "type": "Feature",
  "properties": {
    "addr:full":"6269 Gay Topaz Laurel MD 20707",
    "addr:housenumber":"6269;topaz",
    "addr:postcode":"20707",
    "addr:street":"Gay",
    "iso:country":"US",
    "sg:address":"6269 Gay Topaz",
    "sg:city":"Laurel",
    "sg:classifiers":[
        {
            "category":"Health Services",
            "subcategory":"Doctor",
            "type":"Services"
        },
        {
            "category":"Health Services",
            "subcategory":"Clinic",
            "type":"Services"
        }
    ],
    "sg:phone":"+1 301 596 2558",
    "sg:postcode":"20707",
    "sg:province":"MD",
    "sg:tags":[
        "counseling",
        "mental"
    ],
    "wof:name":"Carrington Christine PHD",
    "wof:placetype":"venue"
},
  "geometry": {"coordinates":[-76.869202,39.098301],"type":"Point"}
}