{
  "type": "Feature",
  "properties": {
    "iso:country":"US",
    "sg:address":"3527 S River Ter",
    "sg:city":"Edgewater",
    "sg:classifiers":[
        {
            "category":"Shopping",
            "subcategory":"Florist",
            "type":"Retail Goods"
        }
    ],
    "sg:phone":"+1 410 798 7700",
    "sg:postcode":"21037",
    "sg:province":"MD",
    "wof:name":"Silver Stems Distinctive Flrl",
    "wof:placetype":"venue"
},
  "geometry": {"coordinates":[-76.522813,38.924273],"type":"Point"}
}