{
  "type": "Feature",
  "properties": {
    "addr:full":"7517 Cedar Grove Ln Elkridge MD 21075",
    "addr:housenumber":"7517",
    "addr:postcode":"21075",
    "addr:street":"Cedar Grove Ln",
    "iso:country":"US",
    "sg:address":"7517 Cedar Grove Ln",
    "sg:city":"Elkridge",
    "sg:classifiers":[
        {
            "category":"Travel",
            "subcategory":"Hotels & Motels",
            "type":"Entertainment"
        },
        {
            "category":"Personal",
            "type":"Services"
        }
    ],
    "sg:phone":"+1 443 636 0144",
    "sg:postcode":"21075",
    "sg:province":"MD",
    "sg:tags":[
        "assistant",
        "concierge"
    ],
    "wof:name":"Wazito",
    "wof:placetype":"venue"
},
  "geometry": {"coordinates":[-76.780174,39.180388],"type":"Point"}
}