{
  "type": "Feature",
  "properties": {
    "addr:full":"2221 Corsica Rd Essex MD 21221",
    "addr:housenumber":"2221",
    "addr:postcode":"21221",
    "addr:street":"Corsica Rd",
    "iso:country":"US",
    "sg:address":"2221 Corsica Rd",
    "sg:city":"Essex",
    "sg:classifiers":[
        {
            "category":"Recreation",
            "type":"Entertainment"
        }
    ],
    "sg:phone":"+1 410 686 7176",
    "sg:postcode":"21221",
    "sg:province":"MD",
    "sg:tags":[
        "camps-recreational"
    ],
    "wof:name":"Van Camp J",
    "wof:placetype":"venue"
},
  "geometry": {"coordinates":[-76.42130299999999,39.307232],"type":"Point"}
}