{
  "type": "Feature",
  "properties": {
    "iso:country":"US",
    "sg:address":"5214 Reisterstown Rd",
    "sg:city":"Baltimore",
    "sg:classifiers":[
        {
            "category":"Personal",
            "subcategory":"Barber",
            "type":"Services"
        }
    ],
    "sg:phone":"+1 410 542 8494",
    "sg:postcode":"21215",
    "sg:province":"MD",
    "wof:name":"Hands of Power Barbershop",
    "wof:placetype":"venue"
},
  "geometry": {"coordinates":[-76.68409699999999,39.343498],"type":"Point"}
}