{
  "type": "Feature",
  "properties": {
    "iso:country":"US",
    "sg:address":"8000 Stansbury Rd",
    "sg:city":"Baltimore",
    "sg:classifiers":[
        {
            "category":"Manufacturing",
            "subcategory":"Building Materials",
            "type":"Manufacturing & Wholesale Goods"
        }
    ],
    "sg:phone":"+1 410 284 9190",
    "sg:postcode":"21222",
    "sg:province":"MD",
    "sg:tags":[
        "cabinet"
    ],
    "wof:name":"Henry Harvey & Sons Inc",
    "wof:placetype":"venue"
},
  "geometry": {"coordinates":[-76.498685,39.255517],"type":"Point"}
}