{
  "type": "Feature",
  "properties": {
    "addr:full":"45 Waterview Rd Dundalk MD 21222",
    "addr:housenumber":"45",
    "addr:postcode":"21222",
    "addr:street":"Waterview Rd",
    "iso:country":"US",
    "sg:address":"45 Waterview Rd",
    "sg:city":"Dundalk",
    "sg:classifiers":[
        {
            "category":"Building & Trades",
            "subcategory":"Construction",
            "type":"Services"
        }
    ],
    "sg:phone":"+1 410 675 4495",
    "sg:postcode":"21222",
    "sg:province":"MD",
    "sg:tags":[
        "painting",
        "contractor"
    ],
    "wof:name":"Fern, Ireson",
    "wof:placetype":"venue"
},
  "geometry": {"coordinates":[-76.475373,39.259002],"type":"Point"}
}