{
  "type": "Feature",
  "properties": {
    "addr:full":"2400 Boston St #328 Baltimore MD 21224",
    "addr:housenumber":"2400",
    "addr:postcode":"21224",
    "addr:street":"Boston St # 328",
    "iso:country":"US",
    "sg:address":"2400 Boston St #328",
    "sg:city":"Baltimore",
    "sg:classifiers":[
        {
            "category":"Professional",
            "subcategory":"Computer Services",
            "type":"Services"
        }
    ],
    "sg:phone":"+1 443 451 3000",
    "sg:postcode":"21224",
    "sg:province":"MD",
    "sg:tags":[
        "social",
        "calendar",
        "venue",
        "directory",
        "event",
        "software-as-a-service",
        "saas",
        "white-label",
        "blackboard",
        "dormnoise"
    ],
    "sg:website":"http://localist.com",
    "wof:name":"Localist",
    "wof:placetype":"venue"
},
  "geometry": {"coordinates":[-76.581436,39.281243],"type":"Point"}
}