{
  "type": "Feature",
  "properties": {
    "addr:full":"927 E Church St Salisbury MD 21804",
    "addr:housenumber":"927",
    "addr:postcode":"21804",
    "addr:street":"E Church St",
    "iso:country":"US",
    "sg:address":"927 E Church St",
    "sg:city":"Salisbury",
    "sg:classifiers":[
        {
            "category":"Home & Garden",
            "subcategory":"Home Furnishings",
            "type":"Retail Goods"
        }
    ],
    "sg:phone":"+1 410 219 1199",
    "sg:postcode":"21804",
    "sg:province":"MD",
    "sg:tags":[
        "housewares"
    ],
    "wof:name":"D A Enterprises",
    "wof:placetype":"venue"
},
  "geometry": {"coordinates":[-75.581309,38.373025],"type":"Point"}
}