{
  "type": "Feature",
  "properties": {
    "iso:country":"US",
    "sg:address":"5 Dockside Ct",
    "sg:city":"Berlin",
    "sg:classifiers":[
        {
            "category":"Professional",
            "subcategory":"Employment Agencies",
            "type":"Services"
        }
    ],
    "sg:phone":"+1 410 208 2803",
    "sg:postcode":"21811",
    "sg:province":"MD",
    "sg:tags":[
        "help",
        "contractor"
    ],
    "wof:name":"Ocean Pines Clerical Temps",
    "wof:placetype":"venue"
},
  "geometry": {"coordinates":[-75.15375,38.389474],"type":"Point"}
}