{
  "type": "Feature",
  "properties": {
    "addr:full":"5492 Wild Lilac Columbia MD 21045",
    "addr:housenumber":"5492",
    "addr:postcode":"21045",
    "addr:street":"Wild Lilac",
    "iso:country":"US",
    "sg:address":"5492 Wild Lilac",
    "sg:city":"Columbia",
    "sg:classifiers":[
        {
            "category":"Professional",
            "subcategory":"Accounting & Tax Preparation",
            "type":"Services"
        }
    ],
    "sg:phone":"+1 301 596 6562",
    "sg:postcode":"21045",
    "sg:province":"MD",
    "wof:name":"Ellis R Reid Jr CPA Cdp",
    "wof:placetype":"venue"
},
  "geometry": {"coordinates":[-76.821382,39.222411],"type":"Point"}
}