{
  "type": "Feature",
  "properties": {
    "iso:country":"US",
    "sg:address":"7200 Coastal Hwy",
    "sg:city":"Ocean City",
    "sg:classifiers":[
        {
            "category":"Banks & Credit Unions",
            "subcategory":"Bank",
            "type":"Services"
        }
    ],
    "sg:phone":"+1 410 520 0311",
    "sg:postcode":"21842",
    "sg:province":"MD",
    "sg:tags":[
        "loan",
        "real estate"
    ],
    "wof:name":"Fidelity Mortgage Wrhse Inc",
    "wof:placetype":"venue"
},
  "geometry": {"coordinates":[-75.06343,38.393789],"type":"Point"}
}