{
  "type": "Feature",
  "properties": {
    "iso:country":"US",
    "sg:address":"1370 Piccard Dr",
    "sg:city":"Rockville",
    "sg:classifiers":[
        {
            "category":"Professional",
            "subcategory":"Lawyer & Legal Services",
            "type":"Services"
        }
    ],
    "sg:phone":"+1 301 948 3800",
    "sg:postcode":"20850",
    "sg:province":"MD",
    "sg:tags":[
        "attorney"
    ],
    "wof:name":"KARP Frosh Lapidus Wigodsky",
    "wof:placetype":"venue"
},
  "geometry": {"coordinates":[-77.180632,39.107159],"type":"Point"}
}