{
  "type": "Feature",
  "properties": {
    "iso:country":"US",
    "sg:address":"7719 Westfield Rd",
    "sg:city":"Dundalk",
    "sg:classifiers":[
        {
            "category":"Personal",
            "subcategory":"Beauty Salon",
            "type":"Services"
        }
    ],
    "sg:phone":"+1 410 284 4247",
    "sg:postcode":"21222",
    "sg:province":"MD",
    "wof:name":"Dejavu Salon & Spa",
    "wof:placetype":"venue"
},
  "geometry": {"coordinates":[-76.50134300000001,39.271912],"type":"Point"}
}