{
  "type": "Feature",
  "properties": {
    "iso:country":"US",
    "sg:address":"5619 Harford Rd",
    "sg:city":"Baltimore",
    "sg:classifiers":[
        {
            "category":"Retail",
            "subcategory":"Auto Repair",
            "type":"Services"
        }
    ],
    "sg:phone":"+1 410 426 2220",
    "sg:postcode":"21214",
    "sg:province":"MD",
    "sg:tags":[
        "repairing",
        "automobile"
    ],
    "sg:website":"http://www.goodyeartires.com/",
    "wof:name":"Hamilton Tire",
    "wof:placetype":"venue"
},
  "geometry": {"coordinates":[-76.560501,39.3536],"type":"Point"}
}