{
  "type": "Feature",
  "properties": {
    "iso:country":"US",
    "sg:address":"2057 Pulaski Hwy",
    "sg:city":"North East",
    "sg:classifiers":[
        {
            "category":"Freight",
            "type":"Transportation"
        }
    ],
    "sg:phone":"+1 410 642 3800",
    "sg:postcode":"21901",
    "sg:province":"MD",
    "wof:name":"Medical TRANSPORTATION-Mrdc",
    "wof:placetype":"venue"
},
  "geometry": {"coordinates":[-75.932119,39.612297],"type":"Point"}
}