{
  "type": "Feature",
  "properties": {
    "iso:country":"US",
    "sg:address":"1418 Belvidere St",
    "sg:city":"Baltimore",
    "sg:classifiers":[
        {
            "category":"Wholesale",
            "subcategory":"Vending Machines",
            "type":"Manufacturing & Wholesale Goods"
        }
    ],
    "sg:phone":"+1 410 752 6811",
    "sg:postcode":"21202",
    "sg:province":"MD",
    "wof:name":"Venture Vending Co",
    "wof:placetype":"venue"
},
  "geometry": {"coordinates":[-76.608804,39.306976],"type":"Point"}
}