{
  "type": "Feature",
  "properties": {
    "iso:country":"US",
    "sg:address":"818 Geronimo Dr",
    "sg:city":"Frederick",
    "sg:classifiers":[
        {
            "category":"Social Services",
            "subcategory":"Child Care",
            "type":"Services"
        }
    ],
    "sg:phone":"+1 301 662 7734",
    "sg:postcode":"21701",
    "sg:province":"MD",
    "sg:tags":[
        "day"
    ],
    "wof:name":"Miss Carols Day Care",
    "wof:placetype":"venue"
},
  "geometry": {"coordinates":[-77.396145,39.426315],"type":"Point"}
}