{
  "type": "Feature",
  "properties": {
    "addr:full":"414 Westside Blvd Catonsville MD 21228",
    "addr:housenumber":"414",
    "addr:postcode":"21228",
    "addr:street":"Westside Blvd",
    "iso:country":"US",
    "sg:address":"414 Westside Blvd",
    "sg:city":"Catonsville",
    "sg:classifiers":[
        {
            "category":"Arts & Performance",
            "subcategory":"Music",
            "type":"Entertainment"
        }
    ],
    "sg:phone":"+1 410 788 5190",
    "sg:postcode":"21228",
    "sg:province":"MD",
    "sg:tags":[
        "jockey",
        "disc"
    ],
    "wof:name":"Westside Djs",
    "wof:placetype":"venue"
},
  "geometry": {"coordinates":[-76.772976,39.281715],"type":"Point"}
}