{
  "type": "Feature",
  "properties": {
    "iso:country":"US",
    "sg:address":"6231 N Charles St",
    "sg:city":"Baltimore",
    "sg:classifiers":[
        {
            "category":"Health Services",
            "subcategory":"Doctor",
            "type":"Services"
        }
    ],
    "sg:phone":"+1 410 583 1100",
    "sg:postcode":"21212",
    "sg:province":"MD",
    "sg:tags":[
        "physician",
        "surgeon"
    ],
    "wof:name":"Hoover Kelly & Doxanas",
    "wof:placetype":"venue"
},
  "geometry": {"coordinates":[-76.627003,39.378767],"type":"Point"}
}