{
  "type": "Feature",
  "properties": {
    "iso:country":"US",
    "sg:address":"4962 Fairmont Ave",
    "sg:city":"Bethesda",
    "sg:classifiers":[
        {
            "category":"Communications",
            "subcategory":"Newspaper",
            "type":"Services"
        },
        {
            "category":"Professional",
            "subcategory":"Art Services",
            "type":"Services"
        }
    ],
    "sg:phone":"+1 202 674 2428",
    "sg:postcode":"20910",
    "sg:province":"MD",
    "sg:tags":[
        "photographer",
        "advertising"
    ],
    "sg:website":"www.kochfoto.com",
    "wof:name":"Kochfoto llc",
    "wof:placetype":"venue"
},
  "geometry": {"coordinates":[-77.097612,38.987347],"type":"Point"}
}