{
  "type": "Feature",
  "properties": {
    "iso:country":"US",
    "sg:address":"7466 New Ridge Rd Ste 17",
    "sg:city":"Hanover",
    "sg:phone":"+1 410 850 8555",
    "sg:postcode":"21076",
    "sg:province":"MD",
    "sg:website":"http://www.hrmotorcars.net/",
    "wof:name":"HR Motor Cars Incorporated",
    "wof:placetype":"venue"
},
  "geometry": {"coordinates":[-76.70708999999999,39.165422],"type":"Point"}
}