{
  "type": "Feature",
  "properties": {
    "addr:full":"22599 MacArthur Blvd Ste 122 California MD 20619",
    "addr:housenumber":"22599",
    "addr:postcode":"20619",
    "addr:street":"Macarthur Blvd Ste 122",
    "iso:country":"US",
    "sg:address":"22599 MacArthur Blvd Ste 122",
    "sg:city":"California",
    "sg:classifiers":[
        {
            "category":"Banks & Credit Unions",
            "subcategory":"Bank",
            "type":"Services"
        }
    ],
    "sg:phone":"+1 301 737 1165",
    "sg:postcode":"20619",
    "sg:province":"MD",
    "wof:name":"Educational Systems Employees Credit Union",
    "wof:placetype":"venue"
},
  "geometry": {"coordinates":[-76.487099,38.283001],"type":"Point"}
}