{
  "type": "Feature",
  "properties": {
    "iso:country":"US",
    "sg:address":"11890 Old Baltimore Pike Ste I",
    "sg:city":"Beltsville",
    "sg:classifiers":[
        {
            "category":"Health Services",
            "subcategory":"Chiropractor",
            "type":"Services"
        }
    ],
    "sg:phone":"+1 301 937 3338",
    "sg:postcode":"20705",
    "sg:province":"MD",
    "wof:name":"Exchange Club of Washington DC",
    "wof:placetype":"venue"
},
  "geometry": {"coordinates":[-76.888496,39.051601],"type":"Point"}
}