{
  "type": "Feature",
  "properties": {
    "addr:full":"2556 Madison Ave Baltimore MD 21217",
    "addr:housenumber":"2556",
    "addr:postcode":"21217",
    "addr:street":"Madison Ave",
    "iso:country":"US",
    "sg:address":"2556 Madison Ave",
    "sg:city":"Baltimore",
    "sg:classifiers":[
        {
            "category":"Restaurant",
            "type":"Food & Drink"
        }
    ],
    "sg:phone":"+1 410 462 6013",
    "sg:postcode":"21217",
    "sg:province":"MD",
    "wof:name":"Andy's Food Mart Inc",
    "wof:placetype":"venue"
},
  "geometry": {"coordinates":[-76.63980100000001,39.3148],"type":"Point"}
}