{
  "type": "Feature",
  "properties": {
    "addr:full":"176 Dale Rd Pasadena MD 21122",
    "addr:housenumber":"176",
    "addr:postcode":"21122",
    "addr:street":"Dale Rd",
    "iso:country":"US",
    "sg:address":"176 Dale Rd",
    "sg:city":"Pasadena",
    "sg:classifiers":[
        {
            "category":"Shopping",
            "subcategory":"Computers & Home Electronics",
            "type":"Retail Goods"
        }
    ],
    "sg:phone":"+1 410 255 3691",
    "sg:postcode":"21122",
    "sg:province":"MD",
    "sg:tags":[
        "software"
    ],
    "wof:name":"K-9 Bytes Software Inc",
    "wof:placetype":"venue"
},
  "geometry": {"coordinates":[-76.512429,39.163604],"type":"Point"}
}