{
  "type": "Feature",
  "properties": {
    "iso:country":"US",
    "sg:address":"7801 E Collingham Dr",
    "sg:city":"Dundalk",
    "sg:classifiers":[
        {
            "category":"Education",
            "subcategory":"Special Training",
            "type":"Public Place"
        }
    ],
    "sg:phone":"+1 410 887 7000",
    "sg:postcode":"21222",
    "sg:province":"MD",
    "sg:website":"http://www.bcps.org",
    "wof:name":"Battle Monument School",
    "wof:placetype":"venue"
},
  "geometry": {"coordinates":[-76.484703,39.274448],"type":"Point"}
}