{
  "type": "Feature",
  "properties": {
    "iso:country":"US",
    "sg:address":"25146 Porter Mill Rd",
    "sg:city":"Hebron",
    "sg:classifiers":[
        {
            "category":"Manufacturing",
            "subcategory":"Wood Products",
            "type":"Manufacturing & Wholesale Goods"
        }
    ],
    "sg:phone":"+1 410 860 9520",
    "sg:postcode":"21830",
    "sg:province":"MD",
    "sg:tags":[
        "mfg"
    ],
    "wof:name":"Magnolia Manor Trunk Co",
    "wof:placetype":"venue"
},
  "geometry": {"coordinates":[-75.743638,38.420779],"type":"Point"}
}