{
  "type": "Feature",
  "properties": {
    "iso:country":"US",
    "sg:address":"4124 Sharp Rd",
    "sg:city":"Glenelg",
    "sg:classifiers":[
        {
            "category":"Manufacturing",
            "subcategory":"Buildings",
            "type":"Manufacturing & Wholesale Goods"
        },
        {
            "category":"Building & Trades",
            "subcategory":"Construction",
            "type":"Services"
        }
    ],
    "sg:phone":"+1 410 371 5079",
    "sg:postcode":"21737",
    "sg:province":"MD",
    "sg:tags":[
        "home",
        "builder",
        "contractor"
    ],
    "wof:name":"Work At Home United",
    "wof:placetype":"venue"
},
  "geometry": {"coordinates":[-76.999802,39.257568],"type":"Point"}
}