{
  "type": "Feature",
  "properties": {
    "addr:full":"210 Main St Preston MD 21655",
    "addr:housenumber":"210",
    "addr:postcode":"21655",
    "addr:street":"Main St",
    "iso:country":"US",
    "sg:address":"210 Main St",
    "sg:city":"Preston",
    "sg:classifiers":[
        {
            "category":"Retail",
            "subcategory":"Animal Services",
            "type":"Services"
        }
    ],
    "sg:phone":"+1 410 673 7312",
    "sg:postcode":"21655",
    "sg:province":"MD",
    "sg:tags":[
        "pet",
        "grooming",
        "washing"
    ],
    "wof:name":"Ruff Cuts",
    "wof:placetype":"venue"
},
  "geometry": {"coordinates":[-75.907546,38.711345],"type":"Point"}
}