{
  "type": "Feature",
  "properties": {
    "iso:country":"US",
    "sg:address":"12845 Huntsman Way",
    "sg:city":"Potomac",
    "sg:classifiers":[
        {
            "category":"Shopping",
            "subcategory":"Gifts & Souvenirs",
            "type":"Retail Goods"
        }
    ],
    "sg:phone":"+1 301 340 7999",
    "sg:postcode":"20854",
    "sg:province":"MD",
    "wof:name":"Courtside Cards & Collectibles",
    "wof:placetype":"venue"
},
  "geometry": {"coordinates":[-77.188575,39.065451],"type":"Point"}
}