{
  "type": "Feature",
  "properties": {
    "iso:country":"US",
    "sg:address":"8294 Patuxent Range Rd",
    "sg:city":"Jessup",
    "sg:classifiers":[
        {
            "category":"Professional",
            "type":"Services"
        }
    ],
    "sg:phone":"+1 301 210 6889",
    "sg:postcode":"20794",
    "sg:province":"MD",
    "sg:tags":[
        "establishment"
    ],
    "wof:name":"I B Potomac Inc",
    "wof:placetype":"venue"
},
  "geometry": {"coordinates":[-76.79879699999999,39.14834],"type":"Point"}
}