{
  "type": "Feature",
  "properties": {
    "iso:country":"US",
    "sg:address":"9200 Liberty Rd",
    "sg:city":"Randallstown",
    "sg:classifiers":[
        {
            "category":"Wholesale",
            "subcategory":"Durable Goods & Equipment",
            "type":"Manufacturing & Wholesale Goods"
        }
    ],
    "sg:phone":"+1 410 655 9200",
    "sg:postcode":"21133",
    "sg:province":"MD",
    "sg:tags":[
        "exporter"
    ],
    "wof:name":"Wylie Funeral Home",
    "wof:placetype":"venue"
},
  "geometry": {"coordinates":[-76.800191,39.36968],"type":"Point"}
}