{
  "type": "Feature",
  "properties": {
    "addr:full":"1110 S Charles St Baltimore MD 21230",
    "addr:housenumber":"1110",
    "addr:postcode":"21230",
    "addr:street":"S Charles St",
    "iso:country":"US",
    "sg:address":"1110 S Charles St",
    "sg:city":"Baltimore",
    "sg:phone":"+1 410 727 2333",
    "sg:postcode":"21230",
    "sg:province":"MD",
    "wof:name":"Mad River Bar & Grille",
    "wof:placetype":"venue"
},
  "geometry": {"coordinates":[-76.614338,39.276442],"type":"Point"}
}