{
  "type": "Feature",
  "properties": {
    "iso:country":"US",
    "sg:address":"316 N Charles St",
    "sg:city":"Baltimore",
    "sg:classifiers":[
        {
            "category":"Restaurant",
            "type":"Food & Drink"
        }
    ],
    "sg:phone":"+1 410 962 1130",
    "sg:postcode":"21201",
    "sg:province":"MD",
    "sg:website":"www.shogunbalt.com",
    "wof:name":"Shogun Inc",
    "wof:placetype":"venue"
},
  "geometry": {"coordinates":[-76.615516,39.292861],"type":"Point"}
}