{
  "type": "Feature",
  "properties": {
    "addr:full":"10093 Shaker Dr Columbia MD 21046",
    "addr:housenumber":"10093",
    "addr:postcode":"21046",
    "addr:street":"Shaker Dr",
    "iso:country":"US",
    "sg:address":"10093 Shaker Dr",
    "sg:city":"Columbia",
    "sg:classifiers":[
        {
            "category":"Manufacturing",
            "subcategory":"Signs",
            "type":"Manufacturing & Wholesale Goods"
        }
    ],
    "sg:phone":"+1 410 992 5150",
    "sg:postcode":"21046",
    "sg:province":"MD",
    "sg:tags":[
        "graphic",
        "design",
        "advertising"
    ],
    "wof:name":"Holland Design",
    "wof:placetype":"venue"
},
  "geometry": {"coordinates":[-76.86150600000001,39.179947],"type":"Point"}
}