{
  "type": "Feature",
  "properties": {
    "addr:full":"3300 Newkirk Ave District Heights MD 20747",
    "addr:housenumber":"3300",
    "addr:postcode":"20747",
    "addr:street":"Newkirk Ave",
    "iso:country":"US",
    "sg:address":"3300 Newkirk Ave",
    "sg:city":"District Heights",
    "sg:classifiers":[
        {
            "category":"Education",
            "subcategory":"School",
            "type":"Public Place"
        }
    ],
    "sg:phone":"+1 301 372 1840",
    "sg:postcode":"20747",
    "sg:province":"MD",
    "sg:tags":[
        "high",
        "middle",
        "elementary"
    ],
    "wof:name":"Prince George's County Public Schools",
    "wof:placetype":"venue"
},
  "geometry": {"coordinates":[-76.879997,38.8452],"type":"Point"}
}