{
  "type": "Feature",
  "properties": {
    "iso:country":"US",
    "sg:address":"3 Cedar St",
    "sg:city":"Cambridge",
    "sg:classifiers":[
        {
            "category":"Government",
            "subcategory":"Office",
            "type":"Public Place"
        }
    ],
    "sg:phone":"+1 410 221 1899",
    "sg:postcode":"21613",
    "sg:province":"MD",
    "sg:tags":[
        "village"
    ],
    "wof:name":"DHMH Aids Administration",
    "wof:placetype":"venue"
},
  "geometry": {"coordinates":[-76.068445,38.564506],"type":"Point"}
}