{
  "type": "Feature",
  "properties": {
    "addr:full":"22 Allegheny Ave Towson MD 21204",
    "addr:housenumber":"22",
    "addr:postcode":"21204",
    "addr:street":"Allegheny Ave",
    "iso:country":"US",
    "sg:address":"22 Allegheny Ave",
    "sg:city":"Towson",
    "sg:classifiers":[
        {
            "category":"Shopping",
            "type":"Retail Goods"
        }
    ],
    "sg:phone":"+1 410 847 9175",
    "sg:postcode":"21204",
    "sg:province":"MD",
    "sg:tags":[
        "importer"
    ],
    "sg:website":"www.usfoodgroup.com",
    "wof:name":"U S Food Group",
    "wof:placetype":"venue"
},
  "geometry": {"coordinates":[-76.603255,39.401754],"type":"Point"}
}