{
  "type": "Feature",
  "properties": {
    "addr:full":"54 Nerbay Rd Baltimore MD 21221",
    "addr:housenumber":"54",
    "addr:postcode":"21221",
    "addr:street":"Nerbay Rd",
    "iso:country":"US",
    "sg:address":"54 Nerbay Rd",
    "sg:city":"Baltimore",
    "sg:classifiers":[
        {
            "category":"Building & Trades",
            "subcategory":"Construction",
            "type":"Services"
        }
    ],
    "sg:phone":"+1 410 391 9710",
    "sg:postcode":"21221",
    "sg:province":"MD",
    "sg:tags":[
        "designer",
        "dealer",
        "pool",
        "swimming"
    ],
    "wof:name":"East Rock Townhouses Pool",
    "wof:placetype":"venue"
},
  "geometry": {"coordinates":[-76.45838500000001,39.296841],"type":"Point"}
}