{
  "type": "Feature",
  "properties": {
    "iso:country":"US",
    "sg:address":"1208 Congress St SE",
    "sg:city":"Washington",
    "sg:classifiers":[
        {
            "category":"Retail",
            "subcategory":"Repair Shop",
            "type":"Services"
        }
    ],
    "sg:phone":"+1 202 561 1089",
    "sg:postcode":"20032",
    "sg:province":"MD",
    "sg:tags":[
        "audio"
    ],
    "wof:name":"Anacostia Electronics",
    "wof:placetype":"venue"
},
  "geometry": {"coordinates":[-76.98862699999999,38.841894],"type":"Point"}
}