{
  "type": "Feature",
  "properties": {
    "addr:full":"12827 Forest Creek Ct Sykesville MD 21784",
    "addr:housenumber":"12827",
    "addr:postcode":"21784",
    "addr:street":"Forest Creek Ct",
    "iso:country":"US",
    "sg:address":"12827 Forest Creek Ct",
    "sg:city":"Sykesville",
    "sg:classifiers":[
        {
            "category":"Professional",
            "type":"Services"
        }
    ],
    "sg:phone":"+1 410 442 5887",
    "sg:postcode":"21784",
    "sg:province":"MD",
    "sg:tags":[
        "establishment"
    ],
    "wof:name":"Brindisi Search-Research",
    "wof:placetype":"venue"
},
  "geometry": {"coordinates":[-76.961139,39.341324],"type":"Point"}
}