{
  "type": "Feature",
  "properties": {
    "addr:full":"9103 Opossumtown Pike Frederick MD 21702",
    "addr:postcode":"9103;21702",
    "addr:street":"Opossumtown Pike",
    "iso:country":"US",
    "sg:address":"9103 Opossumtown Pike",
    "sg:city":"Frederick",
    "sg:classifiers":[
        {
            "category":"Farming",
            "subcategory":"Livestock Farm",
            "type":"Manufacturing & Wholesale Goods"
        }
    ],
    "sg:phone":"+1 301 663 4876",
    "sg:postcode":"21702",
    "sg:province":"MD",
    "sg:tags":[
        "feedlot",
        "field",
        "crop",
        "beef",
        "cattle"
    ],
    "wof:name":"Howard Wachter",
    "wof:placetype":"venue"
},
  "geometry": {"coordinates":[-77.43044,39.483585],"type":"Point"}
}