{
  "type": "Feature",
  "properties": {
    "addr:full":"704 Shelley Rd Towson MD 21286",
    "addr:housenumber":"704",
    "addr:postcode":"21286",
    "addr:street":"Shelley Rd",
    "iso:country":"US",
    "sg:address":"704 Shelley Rd",
    "sg:city":"Towson",
    "sg:classifiers":[
        {
            "category":"Health Services",
            "subcategory":"Doctor",
            "type":"Services"
        }
    ],
    "sg:phone":"+1 410 377 2771",
    "sg:postcode":"21286",
    "sg:province":"MD",
    "sg:tags":[
        "physician",
        "surgeon"
    ],
    "wof:name":"Stuart B Bell MD",
    "wof:placetype":"venue"
},
  "geometry": {"coordinates":[-76.584992,39.403653],"type":"Point"}
}