{
  "type": "Feature",
  "properties": {
    "addr:full":"111 Howard St La Plata MD 20646",
    "addr:housenumber":"111",
    "addr:postcode":"20646",
    "addr:street":"Howard St",
    "iso:country":"US",
    "sg:address":"111 Howard St",
    "sg:city":"La Plata",
    "sg:classifiers":[
        {
            "category":"Organizations",
            "subcategory":"Religious Organization",
            "type":"Services"
        }
    ],
    "sg:phone":"+1 301 609 8769",
    "sg:postcode":"20646",
    "sg:province":"MD",
    "sg:tags":[
        "mosque"
    ],
    "wof:name":"Masjid Abdul-Moghni",
    "wof:placetype":"venue"
},
  "geometry": {"coordinates":[-76.979056,38.528558],"type":"Point"}
}