{
  "type": "Feature",
  "properties": {
    "addr:full":"8929 Glenarden Pkwy Glenarden MD 20706",
    "addr:housenumber":"8929",
    "addr:postcode":"20706",
    "addr:street":"Glenarden Pkwy",
    "iso:country":"US",
    "sg:address":"8929 Glenarden Pkwy",
    "sg:city":"Glenarden",
    "sg:classifiers":[
        {
            "category":"Building & Trades",
            "subcategory":"Pest Control",
            "type":"Services"
        }
    ],
    "sg:phone":"+1 301 773 0231",
    "sg:postcode":"20706",
    "sg:province":"MD",
    "wof:name":"Bug Master",
    "wof:placetype":"venue"
},
  "geometry": {"coordinates":[-76.853478,38.930752],"type":"Point"}
}