{
  "type": "Feature",
  "properties": {
    "addr:full":"3105 N Ridge Rd Ellicott City MD 21043",
    "addr:housenumber":"3105",
    "addr:postcode":"21043",
    "addr:street":"N Ridge Rd",
    "iso:country":"US",
    "sg:address":"3105 N Ridge Rd",
    "sg:city":"Ellicott City",
    "sg:classifiers":[
        {
            "category":"Health Services",
            "subcategory":"Doctor",
            "type":"Services"
        }
    ],
    "sg:phone":"+1 410 461 7660",
    "sg:postcode":"21043",
    "sg:province":"MD",
    "sg:tags":[
        "dermatologist"
    ],
    "sg:website":"www.mardiney.com",
    "wof:name":"Mardiney Michael R Jr MD",
    "wof:placetype":"venue"
},
  "geometry": {"coordinates":[-76.821198,39.286999],"type":"Point"}
}