{
  "type": "Feature",
  "properties": {
    "addr:full":"14333 Laurel Bowie Rd Ste 201 Laurel MD 20708",
    "addr:housenumber":"14333;201",
    "addr:postcode":"20708",
    "addr:street":"Laurel Bowie Rd Ste",
    "iso:country":"US",
    "sg:address":"14333 Laurel Bowie Rd Ste 201",
    "sg:city":"Laurel",
    "sg:classifiers":[
        {
            "category":"Health Services",
            "subcategory":"Dentist",
            "type":"Services"
        }
    ],
    "sg:phone":"+1 301 776 3066",
    "sg:postcode":"20708",
    "sg:province":"MD",
    "sg:tags":[
        "orthodontist"
    ],
    "wof:name":"Lavine David DDS Ms",
    "wof:placetype":"venue"
},
  "geometry": {"coordinates":[-76.84684300000001,39.085891],"type":"Point"}
}