{
  "type": "Feature",
  "properties": {
    "iso:country":"US",
    "sg:address":"6605 Ellenwood Dr",
    "sg:city":"La Plata",
    "sg:classifiers":[
        {
            "category":"Building & Trades",
            "subcategory":"Electrical",
            "type":"Services"
        }
    ],
    "sg:phone":"+1 301 870 3889",
    "sg:postcode":"20646",
    "sg:province":"MD",
    "sg:tags":[
        "electric",
        "contractor"
    ],
    "wof:name":"Commercial Power Inc",
    "wof:placetype":"venue"
},
  "geometry": {"coordinates":[-76.953893,38.528548],"type":"Point"}
}