{
  "type": "Feature",
  "properties": {
    "addr:full":"6605 Ellenwood Dr La Plata MD 20646",
    "addr:housenumber":"6605",
    "addr:postcode":"20646",
    "addr:street":"Ellenwood Dr",
    "iso:country":"US",
    "sg:address":"6605 Ellenwood Dr",
    "sg:city":"La Plata",
    "sg:classifiers":[
        {
            "category":"Building & Trades",
            "subcategory":"Electrical",
            "type":"Services"
        }
    ],
    "sg:phone":"+1 301 870 3889",
    "sg:postcode":"20646",
    "sg:province":"MD",
    "sg:tags":[
        "electric",
        "contractor"
    ],
    "wof:name":"Commercial Power Inc",
    "wof:placetype":"venue"
},
  "geometry": {"coordinates":[-76.95389299999999,38.528548],"type":"Point"}
}