{
  "type": "Feature",
  "properties": {
    "iso:country":"US",
    "sg:address":"1504 Riverside Dr",
    "sg:city":"Salisbury",
    "sg:classifiers":[
        {
            "category":"Health Services",
            "subcategory":"Nursing And Care Facility",
            "type":"Services"
        }
    ],
    "sg:phone":"+1 410 742 7640",
    "sg:postcode":"21801",
    "sg:province":"MD",
    "sg:tags":[
        "home",
        "retirement",
        "community"
    ],
    "wof:name":"Mac Inc Sheltered Housing",
    "wof:placetype":"venue"
},
  "geometry": {"coordinates":[-75.624693,38.342987],"type":"Point"}
}