{
  "type": "Feature",
  "properties": {
    "iso:country":"US",
    "sg:address":"5705 Newholme Ave",
    "sg:city":"Baltimore",
    "sg:classifiers":[
        {
            "category":"Banks & Credit Unions",
            "subcategory":"Financial Services",
            "type":"Services"
        }
    ],
    "sg:phone":"+1 410 483 6368",
    "sg:postcode":"21206",
    "sg:province":"MD",
    "sg:tags":[
        "financing"
    ],
    "wof:name":"Cbs Funding Company",
    "wof:placetype":"venue"
},
  "geometry": {"coordinates":[-76.53888000000001,39.336818],"type":"Point"}
}