{
  "type": "Feature",
  "properties": {
    "addr:full":"10230 Wesleigh Dr Columbia MD 21046",
    "addr:housenumber":"10230",
    "addr:postcode":"21046",
    "addr:street":"Wesleigh Dr",
    "iso:country":"US",
    "sg:address":"10230 Wesleigh Dr",
    "sg:city":"Columbia",
    "sg:classifiers":[
        {
            "category":"Education",
            "subcategory":"Special Training",
            "type":"Public Place"
        }
    ],
    "sg:phone":"+1 301 854 3976",
    "sg:postcode":"21046",
    "sg:province":"MD",
    "wof:name":"Elementry Math Curiculm Consul",
    "wof:placetype":"venue"
},
  "geometry": {"coordinates":[-76.868559,39.183253],"type":"Point"}
}