{
  "type": "Feature",
  "properties": {
    "addr:full":"516 Spring Hill Rd Salisbury MD 21801",
    "addr:housenumber":"516",
    "addr:postcode":"21801",
    "addr:street":"Spring Hill Rd",
    "iso:country":"US",
    "sg:address":"516 Spring Hill Rd",
    "sg:city":"Salisbury",
    "sg:classifiers":[
        {
            "category":"Food & Beverages",
            "subcategory":"Groceries & Convenience Stores",
            "type":"Retail Goods"
        }
    ],
    "sg:phone":"+1 410 543 8313",
    "sg:postcode":"21801",
    "sg:province":"MD",
    "wof:name":"7-Eleven",
    "wof:placetype":"venue"
},
  "geometry": {"coordinates":[-75.614502,38.370521],"type":"Point"}
}