{
  "type": "Feature",
  "properties": {
    "addr:full":"3736 White Pine Rd Middle River MD 21220",
    "addr:housenumber":"3736",
    "addr:postcode":"21220",
    "addr:street":"White Pine Rd",
    "iso:country":"US",
    "sg:address":"3736 White Pine Rd",
    "sg:city":"Middle River",
    "sg:classifiers":[
        {
            "category":"Real Estate",
            "subcategory":"Real Estate Operator",
            "type":"Services"
        }
    ],
    "sg:phone":"+1 410 335 3900",
    "sg:postcode":"21220",
    "sg:province":"MD",
    "sg:tags":[
        "apartment"
    ],
    "wof:name":"Town & Country",
    "wof:placetype":"venue"
},
  "geometry": {"coordinates":[-76.393919,39.330529],"type":"Point"}
}