{
  "type": "Feature",
  "properties": {
    "addr:full":"1907 Columbia Ave Hyattsville MD 20785",
    "addr:housenumber":"1907",
    "addr:postcode":"20785",
    "addr:street":"Columbia Ave",
    "iso:country":"US",
    "sg:address":"1907 Columbia Ave",
    "sg:city":"Hyattsville",
    "sg:classifiers":[
        {
            "category":"Place Of Worship",
            "type":"Public Place"
        },
        {
            "category":"Organizations",
            "subcategory":"Religious Organization",
            "type":"Services"
        }
    ],
    "sg:phone":"+1 301 773 8680",
    "sg:postcode":"20785",
    "sg:province":"MD",
    "sg:tags":[
        "church"
    ],
    "wof:name":"Victory International Worshipcenter",
    "wof:placetype":"venue"
},
  "geometry": {"coordinates":[-76.89109999999999,38.915646],"type":"Point"}
}