{
  "type": "Feature",
  "properties": {
    "iso:country":"US",
    "sg:address":"5411 Old Frederick Rd Ste 9",
    "sg:city":"Baltimore",
    "sg:classifiers":[
        {
            "category":"Professional",
            "subcategory":"Testing Lab",
            "type":"Services"
        }
    ],
    "sg:phone":"+1 877 685 6570",
    "sg:postcode":"21229",
    "sg:province":"MD",
    "sg:tags":[
        "blood",
        "typing"
    ],
    "wof:name":"Confidential STD Testing - Baltimore",
    "wof:placetype":"venue"
},
  "geometry": {"coordinates":[-76.717326,39.289092],"type":"Point"}
}