{
  "type": "Feature",
  "properties": {
    "iso:country":"US",
    "sg:address":"161 Main St",
    "sg:city":"Grantsville",
    "sg:classifiers":[
        {
            "category":"Shopping",
            "subcategory":"Used Merchandise",
            "type":"Retail Goods"
        }
    ],
    "sg:phone":"+1 301 895 5983",
    "sg:postcode":"21536",
    "sg:province":"MD",
    "sg:tags":[
        "antique"
    ],
    "wof:name":"Dream Weavers Gift Shop",
    "wof:placetype":"venue"
},
  "geometry": {"coordinates":[-79.15635399999999,39.69684],"type":"Point"}
}