{
  "type": "Feature",
  "properties": {
    "addr:full":"8615A McLain Ave Glenarden MD 20706",
    "addr:housenumber":"8615a",
    "addr:postcode":"20706",
    "addr:street":"Mclain Ave",
    "iso:country":"US",
    "sg:address":"8615A McLain Ave",
    "sg:city":"Glenarden",
    "sg:classifiers":[
        {
            "category":"Sports & Exercise",
            "subcategory":"Gym",
            "type":"Entertainment"
        }
    ],
    "sg:phone":"+1 301 772 5515",
    "sg:postcode":"20706",
    "sg:province":"MD",
    "wof:name":"Banks Theresa Aquatics Center",
    "wof:placetype":"venue"
},
  "geometry": {"coordinates":[-76.86560900000001,38.931248],"type":"Point"}
}