{
  "type": "Feature",
  "properties": {
    "addr:full":"520 Baltimore Pike Bel Air MD 21014",
    "addr:housenumber":"520",
    "addr:postcode":"21014",
    "addr:street":"Baltimore Pike",
    "iso:country":"US",
    "sg:address":"520 Baltimore Pike",
    "sg:city":"Bel Air",
    "sg:classifiers":[
        {
            "category":"Travel",
            "subcategory":"Travel Agent",
            "type":"Entertainment"
        }
    ],
    "sg:phone":"+1 410 838 5121",
    "sg:postcode":"21014",
    "sg:province":"MD",
    "sg:tags":[
        "agency",
        "bureau"
    ],
    "wof:name":"AAA Travel Agency",
    "wof:placetype":"venue"
},
  "geometry": {"coordinates":[-76.354715,39.526313],"type":"Point"}
}