{
  "type": "Feature",
  "properties": {
    "iso:country":"US",
    "sg:address":"12620 Greenbriar Rd",
    "sg:city":"Potomac",
    "sg:classifiers":[
        {
            "category":"Social Services",
            "subcategory":"Retirement Home",
            "type":"Services"
        }
    ],
    "sg:phone":"+1 301 983 9446",
    "sg:postcode":"20854",
    "sg:province":"MD",
    "sg:tags":[
        "convalescent",
        "nursing"
    ],
    "wof:name":"Dilrani Elder Care",
    "wof:placetype":"venue"
},
  "geometry": {"coordinates":[-77.241829,39.062726],"type":"Point"}
}