{
  "type": "Feature",
  "properties": {
    "iso:country":"US",
    "sg:address":"1612 Hempstead Ct",
    "sg:city":"Joppa",
    "sg:classifiers":[
        {
            "category":"Professional",
            "subcategory":"Computer Services",
            "type":"Services"
        }
    ],
    "sg:phone":"+1 410 667 3918",
    "sg:postcode":"21085",
    "sg:province":"MD",
    "sg:tags":[
        "consulting"
    ],
    "wof:name":"Microcomm Consulting Inc",
    "wof:placetype":"venue"
},
  "geometry": {"coordinates":[-76.36713,39.438072],"type":"Point"}
}