{
  "type": "Feature",
  "properties": {
    "iso:country":"US",
    "sg:address":"4248 Cherry Valley Dr",
    "sg:city":"Olney",
    "sg:classifiers":[
        {
            "category":"Manufacturing",
            "subcategory":"Retail Goods",
            "type":"Manufacturing & Wholesale Goods"
        }
    ],
    "sg:phone":"+1 301 924 1030",
    "sg:postcode":"20832",
    "sg:province":"MD",
    "sg:tags":[
        "product",
        "mfg"
    ],
    "wof:name":"Enertech Industries Inc",
    "wof:placetype":"venue"
},
  "geometry": {"coordinates":[-77.082949,39.136705],"type":"Point"}
}