{
  "type": "Feature",
  "properties": {
    "iso:country":"US",
    "sg:address":"1325 Annapolis Rd",
    "sg:city":"Odenton",
    "sg:classifiers":[
        {
            "category":"Education",
            "subcategory":"Library",
            "type":"Public Place"
        }
    ],
    "sg:phone":"+1 410 222 6277",
    "sg:postcode":"21113",
    "sg:province":"MD",
    "wof:name":"Odenton Library",
    "wof:placetype":"venue"
},
  "geometry": {"coordinates":[-76.701544,39.088766],"type":"Point"}
}