{
  "type": "Feature",
  "properties": {
    "iso:country":"US",
    "sg:address":"507 W Harbor Rd",
    "sg:city":"St Michaels",
    "sg:classifiers":[
        {
            "category":"Health Services",
            "subcategory":"Doctor",
            "type":"Services"
        }
    ],
    "sg:phone":"+1 410 745 3831",
    "sg:postcode":"21663",
    "sg:province":"MD",
    "sg:tags":[
        "dentist"
    ],
    "wof:name":"M Robert Stang DDS",
    "wof:placetype":"venue"
},
  "geometry": {"coordinates":[-76.218328,38.783284],"type":"Point"}
}