{
  "type": "Feature",
  "properties": {
    "addr:full":"9200 English Meadow Way Gaithersburg MD 20882",
    "addr:housenumber":"9200",
    "addr:postcode":"20882",
    "addr:street":"English Meadow Way",
    "iso:country":"US",
    "sg:address":"9200 English Meadow Way",
    "sg:city":"Gaithersburg",
    "sg:classifiers":[
        {
            "category":"Professional",
            "subcategory":"Management & Consulting",
            "type":"Services"
        }
    ],
    "sg:phone":"+1 240 386 5167",
    "sg:postcode":"20882",
    "sg:province":"MD",
    "sg:tags":[
        "business"
    ],
    "wof:name":"Bytewise Consulting",
    "wof:placetype":"venue"
},
  "geometry": {"coordinates":[-77.19189299999999,39.211914],"type":"Point"}
}