{
  "type": "Feature",
  "properties": {
    "iso:country":"US",
    "sg:address":"3910 W Rogers Ave",
    "sg:city":"Baltimore",
    "sg:classifiers":[
        {
            "category":"Organizations",
            "subcategory":"Religious Organization",
            "type":"Services"
        }
    ],
    "sg:phone":"+1 410 466 8298",
    "sg:postcode":"21215",
    "sg:province":"MD",
    "sg:tags":[
        "place",
        "worship",
        "church"
    ],
    "sg:website":"http://www.beth-eltemple.org",
    "wof:name":"Bethel Temple Church Of Christ, Inc",
    "wof:placetype":"venue"
},
  "geometry": {"coordinates":[-76.68831400000001,39.348934],"type":"Point"}
}