{
  "type": "Feature",
  "properties": {
    "addr:full":"4703 Decatur St Hyattsville MD 20781",
    "addr:housenumber":"4703",
    "addr:postcode":"20781",
    "addr:street":"Decatur St",
    "iso:country":"US",
    "sg:address":"4703 Decatur St",
    "sg:city":"Hyattsville",
    "sg:classifiers":[
        {
            "category":"Social Services",
            "subcategory":"Child Care",
            "type":"Services"
        }
    ],
    "sg:phone":"+1 301 927 2008",
    "sg:postcode":"20781",
    "sg:province":"MD",
    "sg:tags":[
        "day"
    ],
    "wof:name":"Family Tree Child Care Center",
    "wof:placetype":"venue"
},
  "geometry": {"coordinates":[-76.937955,38.950182],"type":"Point"}
}