{
  "type": "Feature",
  "properties": {
    "addr:full":"3062 Solomons Island Rd Edgewater MD 21037",
    "addr:housenumber":"3062",
    "addr:postcode":"21037",
    "addr:street":"Solomons Island Rd",
    "iso:country":"US",
    "sg:address":"3062 Solomons Island Rd",
    "sg:city":"Edgewater",
    "sg:classifiers":[
        {
            "category":"Banks & Credit Unions",
            "subcategory":"Bank",
            "type":"Services"
        }
    ],
    "sg:phone":"+1 410 956 3206",
    "sg:postcode":"21037",
    "sg:province":"MD",
    "wof:name":"B B & T",
    "wof:placetype":"venue"
},
  "geometry": {"coordinates":[-76.561682,38.943064],"type":"Point"}
}