{
  "type": "Feature",
  "properties": {
    "addr:full":"1200 Washington Blvd Baltimore MD 21230",
    "addr:housenumber":"1200",
    "addr:postcode":"21230",
    "addr:street":"Washington Blvd",
    "iso:country":"US",
    "sg:address":"1200 Washington Blvd",
    "sg:city":"Baltimore",
    "sg:classifiers":[
        {
            "category":"Fast Food",
            "type":"Food & Drink"
        },
        {
            "category":"Restaurant",
            "type":"Food & Drink"
        }
    ],
    "sg:phone":"+1 410 727 8828",
    "sg:postcode":"21230",
    "sg:province":"MD",
    "sg:tags":[
        "american"
    ],
    "wof:name":"Smittys Sub Shop",
    "wof:placetype":"venue"
},
  "geometry": {"coordinates":[-76.63401,39.28175],"type":"Point"}
}