{
  "type": "Feature",
  "properties": {
    "iso:country":"US",
    "sg:address":"1927 Park Ave",
    "sg:city":"Baltimore",
    "sg:classifiers":[
        {
            "category":"Social Services",
            "type":"Services"
        },
        {
            "category":"Health Services",
            "subcategory":"Nursing And Care Facility",
            "type":"Services"
        }
    ],
    "sg:phone":"+1 410 523 9400",
    "sg:postcode":"21217",
    "sg:province":"MD",
    "sg:tags":[
        "residential"
    ],
    "wof:name":"Cwc Care With Class",
    "wof:placetype":"venue"
},
  "geometry": {"coordinates":[-76.62806999999999,39.312077],"type":"Point"}
}