{
  "type": "Feature",
  "properties": {
    "addr:full":"1001 W North Ave Baltimore MD 21217",
    "addr:housenumber":"1001",
    "addr:postcode":"21217",
    "addr:street":"W North Ave",
    "iso:country":"US",
    "sg:address":"1001 W North Ave",
    "sg:city":"Baltimore",
    "sg:classifiers":[
        {
            "category":"Autos & Motor Vehicles",
            "subcategory":"Fuel & Gas Station",
            "type":"Retail Goods"
        }
    ],
    "sg:phone":"+1 410 225 0916",
    "sg:postcode":"21217",
    "sg:province":"MD",
    "sg:tags":[
        "oil"
    ],
    "wof:name":"North Avenue Crown",
    "wof:placetype":"venue"
},
  "geometry": {"coordinates":[-76.634399,39.3102],"type":"Point"}
}