{
  "type": "Feature",
  "properties": {
    "iso:country":"US",
    "sg:address":"118 Monroe St",
    "sg:city":"Rockville",
    "sg:classifiers":[
        {
            "category":"Arts & Performance",
            "subcategory":"Theater",
            "type":"Entertainment"
        }
    ],
    "sg:phone":"+1 301 545 0456",
    "sg:postcode":"20850",
    "sg:province":"MD",
    "sg:tags":[
        "voice",
        "for",
        "america",
        "broadcasting"
    ],
    "wof:name":"Maria T Sutadi",
    "wof:placetype":"venue"
},
  "geometry": {"coordinates":[-77.149006,39.082184],"type":"Point"}
}