{
  "type": "Feature",
  "properties": {
    "addr:full":"8830 Stanford Blvd Ste 201 Columbia MD 21045",
    "addr:housenumber":"8830",
    "addr:postcode":"21045",
    "addr:street":"Stanford Blvd Ste 201",
    "iso:country":"US",
    "sg:address":"8830 Stanford Blvd Ste 201",
    "sg:city":"Columbia",
    "sg:classifiers":[
        {
            "category":"Professional",
            "subcategory":"Employment Agencies",
            "type":"Services"
        }
    ],
    "sg:phone":"+1 410 872 9100",
    "sg:postcode":"21045",
    "sg:province":"MD",
    "wof:name":"Accountants Inc",
    "wof:placetype":"venue"
},
  "geometry": {"coordinates":[-76.823898,39.204899],"type":"Point"}
}