{
  "type": "Feature",
  "properties": {
    "iso:country":"US",
    "sg:address":"17301 Valley Mall Rd",
    "sg:city":"Hagerstown",
    "sg:classifiers":[
        {
            "category":"Restaurant",
            "type":"Food & Drink"
        }
    ],
    "sg:menulink":"http://www.allmenus.com/md/halfway/72434-sbarro/menu/",
    "sg:phone":"+1 301 582 9102",
    "sg:postcode":"21740",
    "sg:province":"MD",
    "sg:tags":[
        "american",
        "pizza"
    ],
    "wof:name":"Sbarro",
    "wof:placetype":"venue"
},
  "geometry": {"coordinates":[-77.773015,39.621735],"type":"Point"}
}