{
  "type": "Feature",
  "properties": {
    "iso:country":"US",
    "sg:address":"5399 Enterprise St",
    "sg:city":"Sykesville",
    "sg:classifiers":[
        {
            "category":"Building & Trades",
            "subcategory":"Construction",
            "type":"Services"
        }
    ],
    "sg:phone":"+1 410 795 5566",
    "sg:postcode":"21784",
    "sg:province":"MD",
    "sg:tags":[
        "plastering",
        "altering",
        "contractor",
        "siding",
        "insulation",
        "remodeling"
    ],
    "sg:website":"http://www.skroofing.com",
    "wof:name":"S & K Roofing Siding & Window",
    "wof:placetype":"venue"
},
  "geometry": {"coordinates":[-76.999053,39.427377],"type":"Point"}
}