{
  "type": "Feature",
  "properties": {
    "addr:full":"236 W Cherry Hill Rd Reisterstown MD 21136",
    "addr:housenumber":"236",
    "addr:postcode":"21136",
    "addr:street":"W Cherry Hill Rd",
    "iso:country":"US",
    "sg:address":"236 W Cherry Hill Rd",
    "sg:city":"Reisterstown",
    "sg:classifiers":[
        {
            "category":"Retail",
            "subcategory":"Repair Shop",
            "type":"Services"
        }
    ],
    "sg:phone":"+1 410 833 8031",
    "sg:postcode":"21136",
    "sg:province":"MD",
    "sg:tags":[
        "welding"
    ],
    "wof:name":"Gh Welding",
    "wof:placetype":"venue"
},
  "geometry": {"coordinates":[-76.82062999999999,39.441124],"type":"Point"}
}