{
  "type": "Feature",
  "properties": {
    "addr:full":"11399 York Rd Cockeysville MD 21030",
    "addr:housenumber":"11399",
    "addr:postcode":"21030",
    "addr:street":"York Rd",
    "iso:country":"US",
    "sg:address":"11399 York Rd",
    "sg:city":"Cockeysville",
    "sg:classifiers":[
        {
            "category":"Banks & Credit Unions",
            "subcategory":"Bank",
            "type":"Services"
        }
    ],
    "sg:phone":"+1 410 584 8081",
    "sg:postcode":"21030",
    "sg:province":"MD",
    "sg:tags":[
        "federal",
        "saving",
        "institution"
    ],
    "wof:name":"Chevy Chase Bank",
    "wof:placetype":"venue"
},
  "geometry": {"coordinates":[-76.650497,39.4958],"type":"Point"}
}