{
  "type": "Feature",
  "properties": {
    "addr:full":"3 Seyon Ct Baltimore MD 21228",
    "addr:housenumber":"3",
    "addr:postcode":"21228",
    "addr:street":"Seyon Ct",
    "iso:country":"US",
    "sg:address":"3 Seyon Ct",
    "sg:city":"Baltimore",
    "sg:classifiers":[
        {
            "category":"Organizations",
            "subcategory":"Religious Organization",
            "type":"Services"
        }
    ],
    "sg:phone":"+1 410 747 7335",
    "sg:postcode":"21228",
    "sg:province":"MD",
    "wof:name":"Open Door Bible Church",
    "wof:placetype":"venue"
},
  "geometry": {"coordinates":[-76.774902,39.285582],"type":"Point"}
}