{
  "type": "Feature",
  "properties": {
    "iso:country":"US",
    "sg:address":"1190 Mount Aetna Rd",
    "sg:city":"Hagerstown",
    "sg:classifiers":[
        {
            "category":"Farming",
            "subcategory":"Livestock Farm",
            "type":"Manufacturing & Wholesale Goods"
        }
    ],
    "sg:phone":"+1 301 714 0822",
    "sg:postcode":"21740",
    "sg:province":"MD",
    "sg:tags":[
        "animal",
        "general"
    ],
    "wof:name":"Liberty Farm LLC",
    "wof:placetype":"venue"
},
  "geometry": {"coordinates":[-77.694311,39.622976],"type":"Point"}
}