{
  "type": "Feature",
  "properties": {
    "addr:full":"1360 Gorsuch Ave Baltimore MD 21218",
    "addr:housenumber":"1360",
    "addr:postcode":"21218",
    "addr:street":"Gorsuch Ave",
    "iso:country":"US",
    "sg:address":"1360 Gorsuch Ave",
    "sg:city":"Baltimore",
    "sg:classifiers":[
        {
            "category":"Social Services",
            "subcategory":"Child Care",
            "type":"Services"
        }
    ],
    "sg:phone":"+1 410 467 7335",
    "sg:postcode":"21218",
    "sg:province":"MD",
    "wof:name":"Phyllis Wheatley Child Care",
    "wof:placetype":"venue"
},
  "geometry": {"coordinates":[-76.599515,39.324499],"type":"Point"}
}