{
  "type": "Feature",
  "properties": {
    "iso:country":"US",
    "sg:address":"1205 Windemere Ave",
    "sg:city":"Baltimore",
    "sg:classifiers":[
        {
            "category":"Shopping",
            "subcategory":"Jewelry",
            "type":"Retail Goods"
        }
    ],
    "sg:phone":"+1 410 889 3431",
    "sg:postcode":"21218",
    "sg:province":"MD",
    "sg:tags":[
        "jeweler"
    ],
    "wof:name":"Charm City Charms",
    "wof:placetype":"venue"
},
  "geometry": {"coordinates":[-76.597944,39.330063],"type":"Point"}
}