{
  "type": "Feature",
  "properties": {
    "addr:full":"8297 Elvaton Rd Millersville MD 21108",
    "addr:housenumber":"8297",
    "addr:postcode":"21108",
    "addr:street":"Elvaton Rd",
    "iso:country":"US",
    "sg:address":"8297 Elvaton Rd",
    "sg:city":"Millersville",
    "sg:classifiers":[
        {
            "category":"Freight",
            "type":"Transportation"
        }
    ],
    "sg:phone":"+1 410 761 5356",
    "sg:postcode":"21108",
    "sg:province":"MD",
    "sg:tags":[
        "hauling",
        "trucking"
    ],
    "wof:name":"David J Wood Contract Hauling",
    "wof:placetype":"venue"
},
  "geometry": {"coordinates":[-76.61004200000001,39.12474],"type":"Point"}
}