{
  "type": "Feature",
  "properties": {
    "addr:full":"2050 Fleet St Baltimore MD 21231",
    "addr:housenumber":"2050",
    "addr:postcode":"21231",
    "addr:street":"Fleet St",
    "iso:country":"US",
    "sg:address":"2050 Fleet St",
    "sg:city":"Baltimore",
    "sg:classifiers":[
        {
            "category":"Food & Beverages",
            "subcategory":"Groceries & Convenience Stores",
            "type":"Retail Goods"
        }
    ],
    "sg:phone":"+1 410 342 8012",
    "sg:postcode":"21231",
    "sg:province":"MD",
    "sg:website":"www.royalfarms.com",
    "wof:name":"Royal Farm Stores",
    "wof:placetype":"venue"
},
  "geometry": {"coordinates":[-76.587502,39.284698],"type":"Point"}
}