{
  "type": "Feature",
  "properties": {
    "iso:country":"US",
    "sg:address":"160 Flatland Rd",
    "sg:city":"Chestertown",
    "sg:classifiers":[
        {
            "category":"Social Services",
            "subcategory":"Job Training",
            "type":"Services"
        }
    ],
    "sg:phone":"+1 410 778 9266",
    "sg:postcode":"21620",
    "sg:province":"MD",
    "sg:tags":[
        "rehabilitation"
    ],
    "wof:name":"Gross & Jones",
    "wof:placetype":"venue"
},
  "geometry": {"coordinates":[-76.08260900000001,39.219693],"type":"Point"}
}