{
  "type": "Feature",
  "properties": {
    "iso:country":"US",
    "sg:address":"15 Grandview Ave",
    "sg:city":"North East",
    "sg:classifiers":[
        {
            "category":"Real Estate",
            "subcategory":"Real Estate Agent",
            "type":"Services"
        }
    ],
    "sg:phone":"+1 410 287 7453",
    "sg:postcode":"21901",
    "sg:province":"MD",
    "wof:name":"Robyn Rowe",
    "wof:placetype":"venue"
},
  "geometry": {"coordinates":[-75.948143,39.575847],"type":"Point"}
}