{
  "type": "Feature",
  "properties": {
    "iso:country":"US",
    "sg:address":"141 Main St",
    "sg:city":"Prince Frederick",
    "sg:classifiers":[
        {
            "category":"Professional",
            "subcategory":"Lawyer & Legal Services",
            "type":"Services"
        }
    ],
    "sg:phone":"+1 410 535 5333",
    "sg:postcode":"20678",
    "sg:province":"MD",
    "sg:tags":[
        "attorney"
    ],
    "wof:name":"Wilson & Parlett",
    "wof:placetype":"venue"
},
  "geometry": {"coordinates":[-76.58418399999999,38.539707],"type":"Point"}
}