{
  "type": "Feature",
  "properties": {
    "iso:country":"US",
    "sg:address":"8401 Ramsey Ave",
    "sg:city":"Silver Spring",
    "sg:classifiers":[
        {
            "category":"Professional",
            "type":"Services"
        }
    ],
    "sg:phone":"+1 202 887 5533",
    "sg:postcode":"20910",
    "sg:province":"MD",
    "sg:tags":[
        "establishment"
    ],
    "wof:name":"Goldberg & Finnigan",
    "wof:placetype":"venue"
},
  "geometry": {"coordinates":[-77.029197,38.99451],"type":"Point"}
}