{
  "type": "Feature",
  "properties": {
    "addr:full":"888 Memorial Dr Oakland MD 21550",
    "addr:housenumber":"888",
    "addr:postcode":"21550",
    "addr:street":"Memorial Dr",
    "iso:country":"US",
    "sg:address":"888 Memorial Dr",
    "sg:city":"Oakland",
    "sg:classifiers":[
        {
            "category":"Health Services",
            "subcategory":"Doctor",
            "type":"Services"
        }
    ],
    "sg:phone":"+1 301 334 1146",
    "sg:postcode":"21550",
    "sg:province":"MD",
    "sg:tags":[
        "physician",
        "surgeon"
    ],
    "wof:name":"Regional Eye Ctr",
    "wof:placetype":"venue"
},
  "geometry": {"coordinates":[-79.39567700000001,39.413609],"type":"Point"}
}