{
  "type": "Feature",
  "properties": {
    "iso:country":"US",
    "sg:address":"11116 Lake Victoria Ln",
    "sg:city":"Bowie",
    "sg:classifiers":[
        {
            "category":"Food & Beverages",
            "subcategory":"Specialty",
            "type":"Retail Goods"
        }
    ],
    "sg:phone":"+1 301 860 0016",
    "sg:postcode":"20720",
    "sg:province":"MD",
    "sg:tags":[
        "product",
        "health",
        "diet"
    ],
    "wof:name":"Nutrition Essentials Inc",
    "wof:placetype":"venue"
},
  "geometry": {"coordinates":[-76.815558,38.95363],"type":"Point"}
}