{
  "type": "Feature",
  "properties": {
    "iso:country":"US",
    "sg:address":"1417 Strawflower Rd",
    "sg:city":"Essex",
    "sg:classifiers":[
        {
            "category":"Professional",
            "type":"Services"
        }
    ],
    "sg:phone":"+1 410 574 8810",
    "sg:postcode":"21221",
    "sg:province":"MD",
    "wof:name":"Reu Renal Svc",
    "wof:placetype":"venue"
},
  "geometry": {"coordinates":[-76.443261,39.301576],"type":"Point"}
}