{
  "type": "Feature",
  "properties": {
    "addr:full":"7300 Van Dusen Rd Laurel MD 20707",
    "addr:housenumber":"7300",
    "addr:postcode":"20707",
    "addr:street":"Van Dusen Rd",
    "iso:country":"US",
    "sg:address":"7300 Van Dusen Rd",
    "sg:city":"Laurel",
    "sg:classifiers":[
        {
            "category":"Health Services",
            "subcategory":"Doctor",
            "type":"Services"
        }
    ],
    "sg:phone":"+1 301 317 9761",
    "sg:postcode":"20707",
    "sg:province":"MD",
    "sg:tags":[
        "physician",
        "surgeon"
    ],
    "wof:name":"Werner Murdock & Francis Assoc",
    "wof:placetype":"venue"
},
  "geometry": {"coordinates":[-76.88377699999999,39.083475],"type":"Point"}
}