{
  "type": "Feature",
  "properties": {
    "addr:full":"9902 Dallas Ave Silver Spring MD 20901",
    "addr:housenumber":"9902",
    "addr:postcode":"20901",
    "addr:street":"Dallas Ave",
    "iso:country":"US",
    "sg:address":"9902 Dallas Ave",
    "sg:city":"Silver Spring",
    "sg:classifiers":[
        {
            "category":"Professional",
            "subcategory":"Art Services",
            "type":"Services"
        }
    ],
    "sg:phone":"+1 301 681 7420",
    "sg:postcode":"20901",
    "sg:province":"MD",
    "sg:tags":[
        "commercial",
        "design"
    ],
    "wof:name":"Kenzie Raulin Design",
    "wof:placetype":"venue"
},
  "geometry": {"coordinates":[-77.023492,39.018527],"type":"Point"}
}