{
  "type": "Feature",
  "properties": {
    "iso:country":"US",
    "sg:address":"8181 Professional Pl",
    "sg:city":"Hyattsville",
    "sg:classifiers":[
        {
            "category":"Place Of Worship",
            "subcategory":"Church",
            "type":"Public Place"
        },
        {
            "category":"Place Of Worship",
            "type":"Public Place"
        }
    ],
    "sg:phone":"+1 301 577 7171",
    "sg:postcode":"20785",
    "sg:province":"MD",
    "sg:tags":[
        "churches-interdenominational",
        "denomination",
        "churches-various",
        "churches-non-denominational"
    ],
    "sg:website":"http://www.faithhope1lovechurch.com",
    "wof:name":"Faith Hope & Love Church",
    "wof:placetype":"venue"
},
  "geometry": {"coordinates":[-76.86520899999999,38.949799],"type":"Point"}
}