{
  "type": "Feature",
  "properties": {
    "addr:full":"25 Cedar Ave Baltimore MD 21286",
    "addr:housenumber":"25",
    "addr:postcode":"21286",
    "addr:street":"Cedar Ave",
    "iso:country":"US",
    "sg:address":"25 Cedar Ave",
    "sg:city":"Baltimore",
    "sg:classifiers":[
        {
            "category":"Health Services",
            "subcategory":"Doctor",
            "type":"Services"
        }
    ],
    "sg:phone":"+1 410 825 6624",
    "sg:postcode":"21286",
    "sg:province":"MD",
    "sg:tags":[
        "pediatrician"
    ],
    "wof:name":"Neal A Halsey",
    "wof:placetype":"venue"
},
  "geometry": {"coordinates":[-76.60254500000001,39.390465],"type":"Point"}
}