{
  "type": "Feature",
  "properties": {
    "iso:country":"US",
    "sg:address":"856 Elkridge Landing Rd",
    "sg:city":"Linthicum Heights",
    "sg:classifiers":[
        {
            "category":"Real Estate",
            "subcategory":"Real Estate Services",
            "type":"Services"
        }
    ],
    "sg:phone":"+1 410 691 2662",
    "sg:postcode":"21090",
    "sg:province":"MD",
    "sg:tags":[
        "management",
        "property"
    ],
    "wof:name":"United Management Servies Inc",
    "wof:placetype":"venue"
},
  "geometry": {"coordinates":[-76.68559999999999,39.195599],"type":"Point"}
}