{
  "type": "Feature",
  "properties": {
    "addr:full":"12933 Bridger Dr Germantown MD 20874",
    "addr:housenumber":"12933",
    "addr:postcode":"20874",
    "addr:street":"Bridger Dr",
    "iso:country":"US",
    "sg:address":"12933 Bridger Dr",
    "sg:city":"Germantown",
    "sg:classifiers":[
        {
            "category":"Professional",
            "subcategory":"Computer Services",
            "type":"Services"
        }
    ],
    "sg:phone":"+1 301 972 5699",
    "sg:postcode":"20874",
    "sg:province":"MD",
    "sg:tags":[
        "datum"
    ],
    "wof:name":"Peter Margelis",
    "wof:placetype":"venue"
},
  "geometry": {"coordinates":[-77.270495,39.194434],"type":"Point"}
}