{
  "type": "Feature",
  "properties": {
    "iso:country":"US",
    "sg:address":"6132 Greenbelt Rd",
    "sg:city":"Greenbelt",
    "sg:classifiers":[
        {
            "category":"Shopping",
            "subcategory":"Clothing, Apparel, & Fashions",
            "type":"Retail Goods"
        },
        {
            "category":"Personal",
            "type":"Services"
        }
    ],
    "sg:phone":"+1 301 474 2004",
    "sg:postcode":"20770",
    "sg:province":"MD",
    "sg:tags":[
        "tailoring",
        "alteration",
        "sale",
        "tailor",
        "wear",
        "wedding",
        "rental",
        "formal"
    ],
    "wof:name":"Mode Custom Tailor",
    "wof:placetype":"venue"
},
  "geometry": {"coordinates":[-76.908096,38.997372],"type":"Point"}
}