{
  "type": "Feature",
  "properties": {
    "iso:country":"US",
    "sg:address":"1136 Smallwood Dr W",
    "sg:city":"Waldorf",
    "sg:classifiers":[
        {
            "category":"Professional",
            "type":"Services"
        }
    ],
    "sg:phone":"+1 301 632 9901",
    "sg:postcode":"20603",
    "sg:province":"MD",
    "sg:tags":[
        "establishment"
    ],
    "wof:name":"Sports Zone Inc",
    "wof:placetype":"venue"
},
  "geometry": {"coordinates":[-76.925922,38.61196],"type":"Point"}
}