{
  "type": "Feature",
  "properties": {
    "iso:country":"US",
    "sg:address":"2401 W Belvedere Ave",
    "sg:city":"Baltimore",
    "sg:classifiers":[
        {
            "category":"Health Services",
            "subcategory":"Doctor",
            "type":"Services"
        }
    ],
    "sg:phone":"+1 410 601 1010",
    "sg:postcode":"21215",
    "sg:province":"MD",
    "wof:name":"Fiandaca Massimo Dr Neurosurgery",
    "wof:placetype":"venue"
},
  "geometry": {"coordinates":[-76.662537,39.354078],"type":"Point"}
}