{
  "type": "Feature",
  "properties": {
    "addr:full":"4110 Suitland Rd Suitland MD 20746",
    "addr:housenumber":"4110",
    "addr:postcode":"20746",
    "addr:street":"Suitland Rd",
    "iso:country":"US",
    "sg:address":"4110 Suitland Rd",
    "sg:city":"Suitland",
    "sg:classifiers":[
        {
            "category":"Real Estate",
            "subcategory":"Real Estate Agent",
            "type":"Services"
        }
    ],
    "sg:phone":"+1 301 456 1199",
    "sg:postcode":"20746",
    "sg:province":"MD",
    "sg:tags":[
        "management"
    ],
    "wof:name":"Whitehall Square Rental Office",
    "wof:placetype":"venue"
},
  "geometry": {"coordinates":[-76.943462,38.857496],"type":"Point"}
}