{
  "type": "Feature",
  "properties": {
    "iso:country":"US",
    "sg:address":"5623 Allentown Rd",
    "sg:city":"Suitland",
    "sg:classifiers":[
        {
            "category":"Building & Trades",
            "subcategory":"Electrical",
            "type":"Services"
        }
    ],
    "sg:phone":"+1 301 423 6740",
    "sg:postcode":"20746",
    "sg:province":"MD",
    "sg:tags":[
        "electric",
        "contractor"
    ],
    "wof:name":"W M Electrical",
    "wof:placetype":"venue"
},
  "geometry": {"coordinates":[-76.898094,38.808345],"type":"Point"}
}