{
  "type": "Feature",
  "properties": {
    "iso:country":"US",
    "sg:address":"365 Main St",
    "sg:city":"Reisterstown",
    "sg:classifiers":[
        {
            "category":"Real Estate",
            "subcategory":"Real Estate Agent",
            "type":"Services"
        }
    ],
    "sg:phone":"+1 410 833 7000",
    "sg:postcode":"21136",
    "sg:province":"MD",
    "sg:website":"www.remax-advantage-md.com",
    "wof:name":"Re/Max Advantage Realty",
    "wof:placetype":"venue"
},
  "geometry": {"coordinates":[-76.827875,39.461922],"type":"Point"}
}