{
  "type": "Feature",
  "properties": {
    "addr:full":"2580 Sand Hill Rd Ellicott City MD 21042",
    "addr:housenumber":"2580",
    "addr:postcode":"21042",
    "addr:street":"Sand Hill Rd",
    "iso:country":"US",
    "sg:address":"2580 Sand Hill Rd",
    "sg:city":"Ellicott City",
    "sg:classifiers":[
        {
            "category":"Building & Trades",
            "subcategory":"Construction",
            "type":"Services"
        }
    ],
    "sg:phone":"+1 410 988 9807",
    "sg:postcode":"21042",
    "sg:province":"MD",
    "sg:tags":[
        "house"
    ],
    "wof:name":"Morningstar Building Contrs",
    "wof:placetype":"venue"
},
  "geometry": {"coordinates":[-76.93159,39.302932],"type":"Point"}
}