{
  "type": "Feature",
  "properties": {
    "addr:full":"2006 Middleborough Rd Baltimore MD 21221",
    "addr:housenumber":"2006",
    "addr:postcode":"21221",
    "addr:street":"Middleborough Rd",
    "iso:country":"US",
    "sg:address":"2006 Middleborough Rd",
    "sg:city":"Baltimore",
    "sg:classifiers":[
        {
            "category":"Building & Trades",
            "subcategory":"Construction",
            "type":"Services"
        }
    ],
    "sg:phone":"+1 410 391 1333",
    "sg:postcode":"21221",
    "sg:province":"MD",
    "sg:tags":[
        "floor",
        "laying",
        "contractor"
    ],
    "wof:name":"Charles A Gambrill",
    "wof:placetype":"venue"
},
  "geometry": {"coordinates":[-76.42743299999999,39.308187],"type":"Point"}
}