{
  "type": "Feature",
  "properties": {
    "iso:country":"US",
    "sg:address":"7831 Woodmont Ave",
    "sg:city":"Bethesda",
    "sg:classifiers":[
        {
            "category":"Professional",
            "subcategory":"Computer Services",
            "type":"Services"
        }
    ],
    "sg:phone":"+1 301 230 2745",
    "sg:postcode":"20814",
    "sg:province":"MD",
    "sg:tags":[
        "design",
        "system"
    ],
    "wof:name":"Coremax Digital Renaissance",
    "wof:placetype":"venue"
},
  "geometry": {"coordinates":[-77.09609,38.988649],"type":"Point"}
}