{
  "type": "Feature",
  "properties": {
    "iso:country":"US",
    "sg:address":"9179 Red Branch Rd",
    "sg:city":"Columbia",
    "sg:classifiers":[
        {
            "category":"Wholesale",
            "subcategory":"Durable Goods & Equipment",
            "type":"Manufacturing & Wholesale Goods"
        }
    ],
    "sg:phone":"+1 410 997 8400",
    "sg:postcode":"21045",
    "sg:province":"MD",
    "sg:tags":[
        "importer"
    ],
    "wof:name":"Desi Corp",
    "wof:placetype":"venue"
},
  "geometry": {"coordinates":[-76.825132,39.231201],"type":"Point"}
}