{
  "type": "Feature",
  "properties": {
    "iso:country":"US",
    "sg:address":"3916 Cloverhill Rd",
    "sg:city":"Baltimore",
    "sg:classifiers":[
        {
            "category":"Farming",
            "subcategory":"Fish & Marine Products",
            "type":"Manufacturing & Wholesale Goods"
        },
        {
            "category":"Retail",
            "subcategory":"Storage",
            "type":"Services"
        }
    ],
    "sg:phone":"+1 410 467 9150",
    "sg:postcode":"21218",
    "sg:province":"MD",
    "sg:tags":[
        "box",
        "boxes-used"
    ],
    "wof:name":"Cga Container",
    "wof:placetype":"venue"
},
  "geometry": {"coordinates":[-76.619771,39.336164],"type":"Point"}
}