{
  "type": "Feature",
  "properties": {
    "addr:full":"22178 Three Notch Rd Lexington Park MD 20653",
    "addr:housenumber":"22178",
    "addr:postcode":"20653",
    "addr:street":"Three Notch Rd",
    "iso:country":"US",
    "sg:address":"22178 Three Notch Rd",
    "sg:city":"Lexington Park",
    "sg:classifiers":[
        {
            "category":"Professional",
            "subcategory":"Computer Services",
            "type":"Services"
        }
    ],
    "sg:phone":"+1 301 866 0613",
    "sg:postcode":"20653",
    "sg:province":"MD",
    "sg:tags":[
        "consultant",
        "designer"
    ],
    "sg:website":"www.rg2.com",
    "wof:name":"Rgii Technologies Inc",
    "wof:placetype":"venue"
},
  "geometry": {"coordinates":[-76.46468400000001,38.276977],"type":"Point"}
}