{
  "type": "Feature",
  "properties": {
    "iso:country":"US",
    "sg:address":"2411 W Belvedere Ave",
    "sg:city":"Baltimore",
    "sg:classifiers":[
        {
            "category":"Health Services",
            "subcategory":"Doctor",
            "type":"Services"
        }
    ],
    "sg:phone":"+1 410 466 7611",
    "sg:postcode":"21215",
    "sg:province":"MD",
    "sg:tags":[
        "physician",
        "surgeon"
    ],
    "wof:name":"Sinai Hospital",
    "wof:placetype":"venue"
},
  "geometry": {"coordinates":[-76.662339,39.35454],"type":"Point"}
}