{
  "type": "Feature",
  "properties": {
    "addr:full":"14040 New Acadia Ln Upper Marlboro MD 20774",
    "addr:housenumber":"14040",
    "addr:postcode":"20774",
    "addr:street":"New Acadia Ln",
    "iso:country":"US",
    "sg:address":"14040 New Acadia Ln",
    "sg:city":"Upper Marlboro",
    "sg:classifiers":[
        {
            "category":"Professional",
            "subcategory":"Computer Services",
            "type":"Services"
        }
    ],
    "sg:phone":"+1 301 390 7488",
    "sg:postcode":"20774",
    "sg:province":"MD",
    "sg:tags":[
        "processing",
        "datum"
    ],
    "wof:name":"Services & Data Management",
    "wof:placetype":"venue"
},
  "geometry": {"coordinates":[-76.774406,38.897774],"type":"Point"}
}