{
  "type": "Feature",
  "properties": {
    "iso:country":"US",
    "sg:address":"13917 Bethpage Ln",
    "sg:city":"Silver Spring",
    "sg:classifiers":[
        {
            "category":"Professional",
            "subcategory":"Computer Services",
            "type":"Services"
        }
    ],
    "sg:phone":"+1 301 603 0304",
    "sg:postcode":"20906",
    "sg:province":"MD",
    "sg:tags":[
        "consulting"
    ],
    "wof:name":"Jill Johansen-Staggs",
    "wof:placetype":"venue"
},
  "geometry": {"coordinates":[-77.057726,39.085262],"type":"Point"}
}