{
  "type": "Feature",
  "properties": {
    "addr:full":"10231 Reisterstown Rd Owings Mills MD 21117",
    "addr:housenumber":"10231",
    "addr:postcode":"21117",
    "addr:street":"Reisterstown Rd",
    "iso:country":"US",
    "sg:address":"10231 Reisterstown Rd",
    "sg:city":"Owings Mills",
    "sg:classifiers":[
        {
            "category":"Autos & Motor Vehicles",
            "subcategory":"Fuel & Gas Station",
            "type":"Retail Goods"
        }
    ],
    "sg:phone":"+1 410 363 2520",
    "sg:postcode":"21117",
    "sg:province":"MD",
    "sg:tags":[
        "oil"
    ],
    "wof:name":"Painters Mill Amoco",
    "wof:placetype":"venue"
},
  "geometry": {"coordinates":[-76.775503,39.416338],"type":"Point"}
}