{
  "type": "Feature",
  "properties": {
    "iso:country":"US",
    "sg:address":"909 E Belvedere Ave",
    "sg:city":"Baltimore",
    "sg:classifiers":[
        {
            "category":"Wholesale",
            "subcategory":"Machinery & Supplies",
            "type":"Manufacturing & Wholesale Goods"
        }
    ],
    "sg:phone":"+1 410 435 7360",
    "sg:postcode":"21212",
    "sg:province":"MD",
    "sg:tags":[
        "equipment",
        "plastic"
    ],
    "wof:name":"Rozek Enterprises",
    "wof:placetype":"venue"
},
  "geometry": {"coordinates":[-76.602193,39.361174],"type":"Point"}
}