{
  "type": "Feature",
  "properties": {
    "iso:country":"US",
    "sg:address":"8 Hickory Hill Rd",
    "sg:city":"Cockeysville",
    "sg:classifiers":[
        {
            "category":"Health Services",
            "subcategory":"Doctor",
            "type":"Services"
        }
    ],
    "sg:phone":"+1 410 561 0539",
    "sg:postcode":"21030",
    "sg:province":"MD",
    "wof:name":"Ancona Robert J MD",
    "wof:placetype":"venue"
},
  "geometry": {"coordinates":[-76.696198,39.460201],"type":"Point"}
}