{
  "type": "Feature",
  "properties": {
    "iso:country":"US",
    "sg:address":"11515 Big Piney Way",
    "sg:city":"Potomac",
    "sg:classifiers":[
        {
            "category":"Real Estate",
            "subcategory":"Real Estate Agent",
            "type":"Services"
        }
    ],
    "sg:phone":"+1 301 983 5180",
    "sg:postcode":"20854",
    "sg:province":"MD",
    "wof:name":"Long & Foster Institute RE",
    "wof:placetype":"venue"
},
  "geometry": {"coordinates":[-77.23509900000001,39.040937],"type":"Point"}
}