{
  "type": "Feature",
  "properties": {
    "addr:full":"849 International Dr Linthicum Hts MD 21090",
    "addr:housenumber":"849",
    "addr:postcode":"21090",
    "addr:street":"International Dr",
    "iso:country":"US",
    "sg:address":"849 International Dr",
    "sg:city":"Linthicum Hts",
    "sg:classifiers":[
        {
            "category":"Government",
            "subcategory":"Office",
            "type":"Public Place"
        }
    ],
    "sg:phone":"+1 410 691 1131",
    "sg:postcode":"21090",
    "sg:province":"MD",
    "sg:tags":[
        "federal",
        "affairs",
        "govt",
        "admin"
    ],
    "wof:name":"Us Veterans Affairs Dept",
    "wof:placetype":"venue"
},
  "geometry": {"coordinates":[-76.674485,39.206326],"type":"Point"}
}