{
  "type": "Feature",
  "properties": {
    "iso:country":"US",
    "sg:address":"10714 Pine Haven Ter",
    "sg:city":"Rockville",
    "sg:classifiers":[
        {
            "category":"Real Estate",
            "subcategory":"Real Estate Services",
            "type":"Services"
        },
        {
            "category":"Professional",
            "subcategory":"Business Services",
            "type":"Services"
        },
        {
            "category":"Real Estate",
            "subcategory":"Surveying",
            "type":"Services"
        }
    ],
    "sg:phone":"+1 301 881 8360",
    "sg:postcode":"20852",
    "sg:province":"MD",
    "sg:tags":[
        "commercial",
        "appraisers-business",
        "industrial",
        "appraisers-commercial",
        "appraiser"
    ],
    "wof:name":"Klaris Thompson & Schroed",
    "wof:placetype":"venue"
},
  "geometry": {"coordinates":[-77.117588,39.030342],"type":"Point"}
}