{
  "type": "Feature",
  "properties": {
    "iso:country":"US",
    "sg:address":"15943 Frederick Rd",
    "sg:city":"Lisbon",
    "sg:classifiers":[
        {
            "category":"Autos & Motor Vehicles",
            "subcategory":"Auto Supplies",
            "type":"Retail Goods"
        }
    ],
    "sg:phone":"+1 301 829 0993",
    "sg:postcode":"21797",
    "sg:province":"MD",
    "sg:tags":[
        "tire"
    ],
    "wof:name":"Larry's Towing & Repair",
    "wof:placetype":"venue"
},
  "geometry": {"coordinates":[-77.07132799999999,39.336309],"type":"Point"}
}