{
  "type": "Feature",
  "properties": {
    "iso:country":"US",
    "sg:address":"19 E Fayette St",
    "sg:city":"Baltimore",
    "sg:classifiers":[
        {
            "category":"Professional",
            "subcategory":"Lawyer & Legal Services",
            "type":"Services"
        }
    ],
    "sg:phone":"+1 410 752 3747",
    "sg:postcode":"21202",
    "sg:province":"MD",
    "wof:name":"Harasti Gina M Law Offices of",
    "wof:placetype":"venue"
},
  "geometry": {"coordinates":[-76.614799,39.290401],"type":"Point"}
}