{
  "type": "Feature",
  "properties": {
    "iso:country":"US",
    "sg:address":"45 Westminster Rd",
    "sg:city":"Reisterstown",
    "sg:classifiers":[
        {
            "category":"Professional",
            "subcategory":"Business Services",
            "type":"Services"
        }
    ],
    "sg:phone":"+1 410 526 4300",
    "sg:postcode":"21136",
    "sg:province":"MD",
    "sg:tags":[
        "broker"
    ],
    "wof:name":"Harry Wolf Assoc",
    "wof:placetype":"venue"
},
  "geometry": {"coordinates":[-76.83099799999999,39.47029],"type":"Point"}
}