{
  "type": "Feature",
  "properties": {
    "addr:full":"660 Lofstrand Ln Rockville MD 20850",
    "addr:housenumber":"660",
    "addr:postcode":"20850",
    "addr:street":"Lofstrand Ln",
    "iso:country":"US",
    "sg:address":"660 Lofstrand Ln",
    "sg:city":"Rockville",
    "sg:classifiers":[
        {
            "category":"Building & Trades",
            "subcategory":"Construction",
            "type":"Services"
        }
    ],
    "sg:phone":"+1 301 251 6750",
    "sg:postcode":"20850",
    "sg:province":"MD",
    "sg:tags":[
        "contractor"
    ],
    "sg:website":"www.pandpcontractors.com",
    "wof:name":"P & P Contractors Inc",
    "wof:placetype":"venue"
},
  "geometry": {"coordinates":[-77.140413,39.093823],"type":"Point"}
}