{
  "type": "Feature",
  "properties": {
    "addr:full":"3213 Farmington Dr Chevy Chase MD 20815",
    "addr:housenumber":"3213",
    "addr:postcode":"20815",
    "addr:street":"Farmington Dr",
    "iso:country":"US",
    "sg:address":"3213 Farmington Dr",
    "sg:city":"Chevy Chase",
    "sg:classifiers":[
        {
            "category":"Education",
            "subcategory":"Special Training",
            "type":"Public Place"
        }
    ],
    "sg:phone":"+1 301 215 7946",
    "sg:postcode":"20815",
    "sg:province":"MD",
    "sg:tags":[
        "instruction",
        "music"
    ],
    "sg:website":"www.musikids.com",
    "wof:name":"Musikids",
    "wof:placetype":"venue"
},
  "geometry": {"coordinates":[-77.06824,38.994226],"type":"Point"}
}