{
  "type": "Feature",
  "properties": {
    "addr:full":"3525 Resource Dr Randallstown MD 21133",
    "addr:housenumber":"3525",
    "addr:postcode":"21133",
    "addr:street":"Resource Dr",
    "iso:country":"US",
    "sg:address":"3525 Resource Dr",
    "sg:city":"Randallstown",
    "sg:classifiers":[
        {
            "category":"Professional",
            "type":"Services"
        }
    ],
    "sg:phone":"+1 410 521 7770",
    "sg:postcode":"21133",
    "sg:province":"MD",
    "sg:tags":[
        "establishment"
    ],
    "wof:name":"Sheppard Pratt At Randallstown",
    "wof:placetype":"venue"
},
  "geometry": {"coordinates":[-76.787081,39.364427],"type":"Point"}
}