{
  "type": "Feature",
  "properties": {
    "addr:full":"212 E Hamilton Ave Silver Spring MD 20901",
    "addr:housenumber":"212",
    "addr:postcode":"20901",
    "addr:street":"E Hamilton Ave",
    "iso:country":"US",
    "sg:address":"212 E Hamilton Ave",
    "sg:city":"Silver Spring",
    "sg:classifiers":[
        {
            "category":"Building & Trades",
            "subcategory":"Construction",
            "type":"Services"
        }
    ],
    "sg:phone":"+1 301 585 8668",
    "sg:postcode":"20901",
    "sg:province":"MD",
    "sg:tags":[
        "house"
    ],
    "wof:name":"Obrien Construction Svc",
    "wof:placetype":"venue"
},
  "geometry": {"coordinates":[-77.00474699999999,39.009083],"type":"Point"}
}