{
  "type": "Feature",
  "properties": {
    "addr:full":"7800 Biggs Ford Rd Ste E Frederick MD 21701",
    "addr:housenumber":"7800",
    "addr:postcode":"21701",
    "addr:street":"Biggs Ford Rd Ste E",
    "iso:country":"US",
    "sg:address":"7800 Biggs Ford Rd Ste E",
    "sg:city":"Frederick",
    "sg:classifiers":[
        {
            "category":"Restaurant",
            "type":"Food & Drink"
        }
    ],
    "sg:phone":"+1 301 898 3490",
    "sg:postcode":"21701",
    "sg:province":"MD",
    "wof:name":"Eunice's",
    "wof:placetype":"venue"
},
  "geometry": {"coordinates":[-77.39662199999999,39.481838],"type":"Point"}
}