{
  "type": "Feature",
  "properties": {
    "addr:full":"11845 Scaggsville Rd Fulton MD 20759",
    "addr:housenumber":"11845",
    "addr:postcode":"20759",
    "addr:street":"Scaggsville Rd",
    "iso:country":"US",
    "sg:address":"11845 Scaggsville Rd",
    "sg:city":"Fulton",
    "sg:classifiers":[
        {
            "category":"Health Services",
            "subcategory":"Chiropractor",
            "type":"Services"
        }
    ],
    "sg:phone":"+1 301 490 8550",
    "sg:postcode":"20759",
    "sg:province":"MD",
    "wof:name":"Fulton Family Chiropractic",
    "wof:placetype":"venue"
},
  "geometry": {"coordinates":[-76.924707,39.153691],"type":"Point"}
}