{
  "type": "Feature",
  "properties": {
    "iso:country":"US",
    "sg:address":"10545 Bethesda Church Rd",
    "sg:city":"Damascus",
    "sg:classifiers":[
        {
            "category":"Building & Trades",
            "subcategory":"Construction",
            "type":"Services"
        }
    ],
    "sg:phone":"+1 301 253 6900",
    "sg:postcode":"20872",
    "sg:province":"MD",
    "sg:tags":[
        "house"
    ],
    "wof:name":"Mullaney Construction & Design",
    "wof:placetype":"venue"
},
  "geometry": {"coordinates":[-77.216311,39.285916],"type":"Point"}
}