{
  "type": "Feature",
  "properties": {
    "addr:full":"2100 Hollins Ferry Rd Baltimore MD 21230",
    "addr:housenumber":"2100",
    "addr:postcode":"21230",
    "addr:street":"Hollins Ferry Rd",
    "iso:country":"US",
    "sg:address":"2100 Hollins Ferry Rd",
    "sg:city":"Baltimore",
    "sg:classifiers":[
        {
            "category":"Autos & Motor Vehicles",
            "subcategory":"Auto Supplies",
            "type":"Retail Goods"
        }
    ],
    "sg:phone":"+1 410 727 6512",
    "sg:postcode":"21230",
    "sg:province":"MD",
    "sg:tags":[
        "automobile",
        "part",
        "accessory"
    ],
    "wof:name":"Martys Auto Parts",
    "wof:placetype":"venue"
},
  "geometry": {"coordinates":[-76.645432,39.26741],"type":"Point"}
}