{
  "type": "Feature",
  "properties": {
    "addr:full":"3627 Patterson Ave Gwynn Oak MD 21207",
    "addr:housenumber":"3627",
    "addr:postcode":"21207",
    "addr:street":"Patterson Ave",
    "iso:country":"US",
    "sg:address":"3627 Patterson Ave",
    "sg:city":"Gwynn Oak",
    "sg:classifiers":[
        {
            "category":"Building & Trades",
            "subcategory":"Construction",
            "type":"Services"
        }
    ],
    "sg:phone":"+1 410 944 1866",
    "sg:postcode":"21207",
    "sg:province":"MD",
    "sg:tags":[
        "tile",
        "dealer"
    ],
    "wof:name":"Alvin Weinberg Tile Co",
    "wof:placetype":"venue"
},
  "geometry": {"coordinates":[-76.720803,39.342107],"type":"Point"}
}