{
  "type": "Feature",
  "properties": {
    "iso:country":"US",
    "sg:address":"830 E Pratt St",
    "sg:city":"Baltimore",
    "sg:classifiers":[
        {
            "category":"Communications",
            "type":"Services"
        }
    ],
    "sg:phone":"+1 410 263 1800",
    "sg:postcode":"21202",
    "sg:province":"MD",
    "sg:tags":[
        "web",
        "design"
    ],
    "wof:name":"Education MD State Dept",
    "wof:placetype":"venue"
},
  "geometry": {"coordinates":[-76.603633,39.287302],"type":"Point"}
}