{
  "type": "Feature",
  "properties": {
    "addr:full":"1024 Joppa Farm Rd Joppa MD 21085",
    "addr:housenumber":"1024",
    "addr:postcode":"21085",
    "addr:street":"Joppa Farm Rd",
    "iso:country":"US",
    "sg:address":"1024 Joppa Farm Rd",
    "sg:city":"Joppa",
    "sg:classifiers":[
        {
            "category":"Home & Garden",
            "subcategory":"Furniture",
            "type":"Retail Goods"
        }
    ],
    "sg:phone":"+1 410 538 4862",
    "sg:postcode":"21085",
    "sg:province":"MD",
    "wof:name":"Unclaimed Freight Co Inc",
    "wof:placetype":"venue"
},
  "geometry": {"coordinates":[-76.37026899999999,39.422149],"type":"Point"}
}