{
  "type": "Feature",
  "properties": {
    "iso:country":"US",
    "sg:address":"12 Falls Glen Ct",
    "sg:city":"Parkton",
    "sg:classifiers":[
        {
            "category":"Professional",
            "subcategory":"Computer Services",
            "type":"Services"
        }
    ],
    "sg:phone":"+1 410 357 9100",
    "sg:postcode":"21120",
    "sg:province":"MD",
    "sg:tags":[
        "programing",
        "custom"
    ],
    "wof:name":"Ravsoft Solutions",
    "wof:placetype":"venue"
},
  "geometry": {"coordinates":[-76.67428,39.630375],"type":"Point"}
}