{
  "type": "Feature",
  "properties": {
    "iso:country":"US",
    "sg:address":"7811 Old Georgetown Rd",
    "sg:city":"Bethesda",
    "sg:classifiers":[
        {
            "category":"Professional",
            "subcategory":"Printing & Photocopies",
            "type":"Services"
        }
    ],
    "sg:phone":"+1 301 656 5608",
    "sg:postcode":"20814",
    "sg:province":"MD",
    "sg:tags":[
        "screen"
    ],
    "sg:website":"http://www.embroidme.com",
    "wof:name":"Embroid Me",
    "wof:placetype":"venue"
},
  "geometry": {"coordinates":[-77.099047,38.98762],"type":"Point"}
}