{
  "type": "Feature",
  "properties": {
    "iso:country":"US",
    "sg:address":"1595 Opossumtown Pike",
    "sg:city":"Frederick",
    "sg:classifiers":[
        {
            "category":"Shopping",
            "subcategory":"Florist",
            "type":"Retail Goods"
        }
    ],
    "sg:phone":"+1 301 620 2020",
    "sg:postcode":"21702",
    "sg:province":"MD",
    "wof:name":"Forget Me Not Florist",
    "wof:placetype":"venue"
},
  "geometry": {"coordinates":[-77.410465,39.43942],"type":"Point"}
}