{
  "type": "Feature",
  "properties": {
    "iso:country":"US",
    "sg:address":"910 Binney St",
    "sg:city":"Baltimore",
    "sg:classifiers":[
        {
            "category":"Wholesale",
            "subcategory":"Medical Equipment & Supplies",
            "type":"Manufacturing & Wholesale Goods"
        }
    ],
    "sg:phone":"+1 800 609 9166",
    "sg:postcode":"21224",
    "sg:province":"MD",
    "sg:tags":[
        "instrument",
        "surgical"
    ],
    "wof:name":"Restorative Therapies, Inc.",
    "wof:placetype":"venue"
},
  "geometry": {"coordinates":[-76.57794199999999,39.282027],"type":"Point"}
}