{
  "type": "Feature",
  "properties": {
    "iso:country":"US",
    "sg:address":"5407 Water St",
    "sg:city":"Upper Marlboro",
    "sg:classifiers":[
        {
            "category":"Insurance",
            "subcategory":"Insurance Agent",
            "type":"Services"
        }
    ],
    "sg:phone":"+1 301 574 1574",
    "sg:postcode":"20772",
    "sg:province":"MD",
    "wof:name":"Smith & Assoc",
    "wof:placetype":"venue"
},
  "geometry": {"coordinates":[-76.751074,38.81482],"type":"Point"}
}