{
  "type": "Feature",
  "properties": {
    "iso:country":"US",
    "sg:address":"2115 Hampton Ct",
    "sg:city":"Fallston",
    "sg:classifiers":[
        {
            "category":"Real Estate",
            "subcategory":"Real Estate Agent",
            "type":"Services"
        }
    ],
    "sg:phone":"+1 410 893 5441",
    "sg:postcode":"21047",
    "sg:province":"MD",
    "wof:name":"Novak Appraisal Service",
    "wof:placetype":"venue"
},
  "geometry": {"coordinates":[-76.45132,39.524634],"type":"Point"}
}