{
  "type": "Feature",
  "properties": {
    "addr:full":"1131 Mace Ave Baltimore MD 21221",
    "addr:housenumber":"1131",
    "addr:postcode":"21221",
    "addr:street":"Mace Ave",
    "iso:country":"US",
    "sg:address":"1131 Mace Ave",
    "sg:city":"Baltimore",
    "sg:classifiers":[
        {
            "category":"Organizations",
            "subcategory":"Religious Organization",
            "type":"Services"
        }
    ],
    "sg:phone":"+1 410 687 5531",
    "sg:postcode":"21221",
    "sg:province":"MD",
    "sg:tags":[
        "church"
    ],
    "wof:name":"Holy Trinity Episcopal Church",
    "wof:placetype":"venue"
},
  "geometry": {"coordinates":[-76.47012599999999,39.327458],"type":"Point"}
}