{
  "type": "Feature",
  "properties": {
    "iso:country":"US",
    "sg:address":"8630 Guilford Rd Ste C60",
    "sg:city":"Columbia",
    "sg:classifiers":[
        {
            "category":"Bakery",
            "type":"Food & Drink"
        },
        {
            "category":"Bagels",
            "subcategory":"None",
            "type":"Food & Drink"
        }
    ],
    "sg:phone":"+1 410 381 1730",
    "sg:postcode":"21046",
    "sg:province":"MD",
    "wof:name":"Bagel Bin",
    "wof:placetype":"venue"
},
  "geometry": {"coordinates":[-76.836637,39.165633],"type":"Point"}
}