{
  "type": "Feature",
  "properties": {
    "addr:full":"5306 Forge Rd White Marsh MD 21162",
    "addr:housenumber":"5306",
    "addr:postcode":"21162",
    "addr:street":"Forge Rd",
    "iso:country":"US",
    "sg:address":"5306 Forge Rd",
    "sg:city":"White Marsh",
    "sg:classifiers":[
        {
            "category":"Wholesale",
            "subcategory":"Electrical",
            "type":"Manufacturing & Wholesale Goods"
        }
    ],
    "sg:phone":"+1 410 952 5700",
    "sg:postcode":"21162",
    "sg:province":"MD",
    "sg:tags":[
        "telecommunication"
    ],
    "wof:name":"Port City Communications",
    "wof:placetype":"venue"
},
  "geometry": {"coordinates":[-76.41857899999999,39.414572],"type":"Point"}
}