{
  "type": "Feature",
  "properties": {
    "iso:country":"US",
    "sg:address":"2601 Rose Ln",
    "sg:city":"Fort Washington",
    "sg:classifiers":[
        {
            "category":"Building & Trades",
            "subcategory":"Construction",
            "type":"Services"
        }
    ],
    "sg:phone":"+1 301 248 5623",
    "sg:postcode":"20744",
    "sg:province":"MD",
    "wof:name":"Davids Welding & Ironworks",
    "wof:placetype":"venue"
},
  "geometry": {"coordinates":[-76.96261,38.756491],"type":"Point"}
}