{
  "type": "Feature",
  "properties": {
    "addr:full":"620 Cypress Rd Severna Park MD 21146",
    "addr:housenumber":"620",
    "addr:postcode":"21146",
    "addr:street":"Cypress Rd",
    "iso:country":"US",
    "sg:address":"620 Cypress Rd",
    "sg:city":"Severna Park",
    "sg:classifiers":[
        {
            "category":"Shopping",
            "subcategory":"Computers & Home Electronics",
            "type":"Retail Goods"
        }
    ],
    "sg:phone":"+1 410 647 0963",
    "sg:postcode":"21146",
    "sg:province":"MD",
    "wof:name":"Cypress Computer Service",
    "wof:placetype":"venue"
},
  "geometry": {"coordinates":[-76.530075,39.074351],"type":"Point"}
}