{
  "type": "Feature",
  "properties": {
    "addr:full":"1393 Progress Way Sykesville MD 21784",
    "addr:housenumber":"1393",
    "addr:postcode":"21784",
    "addr:street":"Progress Way",
    "iso:country":"US",
    "sg:address":"1393 Progress Way",
    "sg:city":"Sykesville",
    "sg:classifiers":[
        {
            "category":"Wholesale",
            "subcategory":"Electrical",
            "type":"Manufacturing & Wholesale Goods"
        }
    ],
    "sg:phone":"+1 410 549 4142",
    "sg:postcode":"21784",
    "sg:province":"MD",
    "sg:tags":[
        "fire",
        "equipment",
        "protection"
    ],
    "wof:name":"Home Fire Sales Inc",
    "wof:placetype":"venue"
},
  "geometry": {"coordinates":[-76.944321,39.412205],"type":"Point"}
}