{
  "type": "Feature",
  "properties": {
    "addr:full":"2077 Harvest Farm Rd Sykesville MD 21784",
    "addr:housenumber":"2077",
    "addr:postcode":"21784",
    "addr:street":"Harvest Farm Rd",
    "iso:country":"US",
    "sg:address":"2077 Harvest Farm Rd",
    "sg:city":"Sykesville",
    "sg:classifiers":[
        {
            "category":"Food & Beverages",
            "subcategory":"Groceries & Convenience Stores",
            "type":"Retail Goods"
        }
    ],
    "sg:phone":"+1 410 549 8620",
    "sg:postcode":"21784",
    "sg:province":"MD",
    "wof:name":"Contessa Food Products",
    "wof:placetype":"venue"
},
  "geometry": {"coordinates":[-76.92375,39.389774],"type":"Point"}
}