{
  "type": "Feature",
  "properties": {
    "addr:full":"5069 Columbia Rd Columbia MD 21044",
    "addr:housenumber":"5069",
    "addr:postcode":"21044",
    "addr:street":"Columbia Rd",
    "iso:country":"US",
    "sg:address":"5069 Columbia Rd",
    "sg:city":"Columbia",
    "sg:classifiers":[
        {
            "category":"Real Estate",
            "subcategory":"Real Estate Services",
            "type":"Services"
        },
        {
            "category":"Banks & Credit Unions",
            "subcategory":"Investment Brokerage",
            "type":"Services"
        },
        {
            "category":"Banks & Credit Unions",
            "subcategory":"Financial Services",
            "type":"Services"
        }
    ],
    "sg:phone":"+1 443 506 3502",
    "sg:postcode":"21044",
    "sg:province":"MD",
    "sg:tags":[
        "buyer",
        "advisory",
        "management",
        "broker"
    ],
    "wof:name":"Creative Investment Group",
    "wof:placetype":"venue"
},
  "geometry": {"coordinates":[-76.841807,39.236359],"type":"Point"}
}