{
  "type": "Feature",
  "properties": {
    "iso:country":"US",
    "sg:address":"132 Church Rd",
    "sg:city":"Arnold",
    "sg:classifiers":[
        {
            "category":"Real Estate",
            "subcategory":"Real Estate Agent",
            "type":"Services"
        }
    ],
    "sg:phone":"+1 410 437 1900",
    "sg:postcode":"21012",
    "sg:province":"MD",
    "wof:name":"Bay Properties",
    "wof:placetype":"venue"
},
  "geometry": {"coordinates":[-76.495626,39.034842],"type":"Point"}
}