{
  "type": "Feature",
  "properties": {
    "iso:country":"US",
    "sg:address":"8464 Aveley Farm Rd",
    "sg:city":"Easton",
    "sg:classifiers":[
        {
            "category":"Health Services",
            "subcategory":"Doctor",
            "type":"Services"
        }
    ],
    "sg:phone":"+1 410 770 4548",
    "sg:postcode":"21601",
    "sg:province":"MD",
    "sg:tags":[
        "physician",
        "surgeon",
        "surgeons",
        "surgery-general"
    ],
    "wof:name":"Physician And Surgeon",
    "wof:placetype":"venue"
},
  "geometry": {"coordinates":[-76.13673199999999,38.781721],"type":"Point"}
}