{
  "type": "Feature",
  "properties": {
    "iso:country":"US",
    "sg:address":"8755 Darcy Rd",
    "sg:city":"Forestville",
    "sg:classifiers":[
        {
            "category":"Professional",
            "subcategory":"Business Services",
            "type":"Services"
        }
    ],
    "sg:phone":"+1 301 350 2772",
    "sg:postcode":"20747",
    "sg:province":"MD",
    "sg:tags":[
        "record"
    ],
    "wof:name":"American Office Moving",
    "wof:placetype":"venue"
},
  "geometry": {"coordinates":[-76.853718,38.857743],"type":"Point"}
}