{
  "type": "Feature",
  "properties": {
    "iso:country":"US",
    "sg:address":"9595 Kings Grant Rd",
    "sg:city":"Laurel",
    "sg:classifiers":[
        {
            "category":"Retail",
            "subcategory":"Auto Repair",
            "type":"Services"
        }
    ],
    "sg:phone":"+1 301 490 9626",
    "sg:postcode":"20723",
    "sg:province":"MD",
    "sg:tags":[
        "windshield"
    ],
    "wof:name":"Gfs",
    "wof:placetype":"venue"
},
  "geometry": {"coordinates":[-76.84255899999999,39.128302],"type":"Point"}
}