{
  "type": "Feature",
  "properties": {
    "addr:full":"12515 Caterpillar Rd Bishopville MD 21813",
    "addr:housenumber":"12515",
    "addr:postcode":"21813",
    "addr:street":"Caterpillar Rd",
    "iso:country":"US",
    "sg:address":"12515 Caterpillar Rd",
    "sg:city":"Bishopville",
    "sg:classifiers":[
        {
            "category":"Professional",
            "subcategory":"Engineering",
            "type":"Services"
        }
    ],
    "sg:phone":"+1 410 352 5001",
    "sg:postcode":"21813",
    "sg:province":"MD",
    "sg:tags":[
        "engineer"
    ],
    "wof:name":"Hardin-Kight Assoc Inc",
    "wof:placetype":"venue"
},
  "geometry": {"coordinates":[-75.14045,38.420646],"type":"Point"}
}