{
  "type": "Feature",
  "properties": {
    "addr:full":"101 Hanover St Aberdeen MD 21001",
    "addr:housenumber":"101",
    "addr:postcode":"21001",
    "addr:street":"Hanover St",
    "iso:country":"US",
    "sg:address":"101 Hanover St",
    "sg:city":"Aberdeen",
    "sg:classifiers":[
        {
            "category":"Real Estate",
            "subcategory":"Real Estate Operator",
            "type":"Services"
        }
    ],
    "sg:phone":"+1 410 272 1630",
    "sg:postcode":"21001",
    "sg:province":"MD",
    "sg:tags":[
        "apartment"
    ],
    "wof:name":"Washington Park Apartments",
    "wof:placetype":"venue"
},
  "geometry": {"coordinates":[-76.152452,39.510374],"type":"Point"}
}