{
  "type": "Feature",
  "properties": {
    "iso:country":"US",
    "sg:address":"3801 Sandy Spring Rd",
    "sg:city":"Burtonsville",
    "sg:classifiers":[
        {
            "category":"Home & Garden",
            "subcategory":"Hardware",
            "type":"Retail Goods"
        }
    ],
    "sg:phone":"+1 410 792 4549",
    "sg:postcode":"20866",
    "sg:province":"MD",
    "sg:tags":[
        "store"
    ],
    "sg:website":"www.johndeere.com",
    "wof:name":"Zimmerman's Home Center",
    "wof:placetype":"venue"
},
  "geometry": {"coordinates":[-76.93029799999999,39.111599],"type":"Point"}
}