{
  "type": "Feature",
  "properties": {
    "addr:full":"109 68th St Ocean City MD 21842",
    "addr:housenumber":"109",
    "addr:postcode":"21842",
    "addr:street":"68Th St",
    "iso:country":"US",
    "sg:address":"109 68th St",
    "sg:city":"Ocean City",
    "sg:classifiers":[
        {
            "category":"Professional",
            "type":"Services"
        }
    ],
    "sg:phone":"+1 410 723 2234",
    "sg:postcode":"21842",
    "sg:province":"MD",
    "sg:tags":[
        "establishment"
    ],
    "wof:name":"Drag-N-Fly",
    "wof:placetype":"venue"
},
  "geometry": {"coordinates":[-75.066012,38.389944],"type":"Point"}
}