{
  "type": "Feature",
  "properties": {
    "iso:country":"US",
    "sg:address":"222 W Cold Spring Ln",
    "sg:city":"Baltimore",
    "sg:classifiers":[
        {
            "category":"Professional",
            "type":"Services"
        }
    ],
    "sg:phone":"+1 410 243 7053",
    "sg:postcode":"21210",
    "sg:province":"MD",
    "sg:tags":[
        "establishment"
    ],
    "wof:name":"PQC",
    "wof:placetype":"venue"
},
  "geometry": {"coordinates":[-76.626504,39.345121],"type":"Point"}
}