{
  "type": "Feature",
  "properties": {
    "iso:country":"US",
    "sg:address":"6640 Cristy Acre Cir",
    "sg:city":"Mount Airy",
    "sg:classifiers":[
        {
            "category":"Professional",
            "subcategory":"Research",
            "type":"Services"
        }
    ],
    "sg:phone":"+1 410 795 1652",
    "sg:postcode":"21771",
    "sg:province":"MD",
    "sg:tags":[
        "technician"
    ],
    "wof:name":"Alicia M Ritgert",
    "wof:placetype":"venue"
},
  "geometry": {"coordinates":[-77.141452,39.394954],"type":"Point"}
}