{
  "type": "Feature",
  "properties": {
    "addr:full":"500 W University Pkwy Baltimore MD 21210",
    "addr:housenumber":"500",
    "addr:postcode":"21210",
    "addr:street":"W University Pkwy",
    "iso:country":"US",
    "sg:address":"500 W University Pkwy",
    "sg:city":"Baltimore",
    "sg:classifiers":[
        {
            "category":"Professional",
            "subcategory":"Management & Consulting",
            "type":"Services"
        }
    ],
    "sg:phone":"+1 410 243 6565",
    "sg:postcode":"21210",
    "sg:province":"MD",
    "wof:name":"Richard R Rubin",
    "wof:placetype":"venue"
},
  "geometry": {"coordinates":[-76.62446199999999,39.336881],"type":"Point"}
}