{
  "type": "Feature",
  "properties": {
    "addr:full":"6712 Dogwood Rd Gwynn Oak MD 21207",
    "addr:housenumber":"6712",
    "addr:postcode":"21207",
    "addr:street":"Dogwood Rd",
    "iso:country":"US",
    "sg:address":"6712 Dogwood Rd",
    "sg:city":"Gwynn Oak",
    "sg:classifiers":[
        {
            "category":"Education",
            "subcategory":"School",
            "type":"Public Place"
        }
    ],
    "sg:phone":"+1 410 944 2990",
    "sg:postcode":"21207",
    "sg:province":"MD",
    "wof:name":"Oakridge Education Trust Inc",
    "wof:placetype":"venue"
},
  "geometry": {"coordinates":[-76.742104,39.321499],"type":"Point"}
}