{
  "type": "Feature",
  "properties": {
    "addr:full":"2030 Greenspring Valley Rd Stevenson MD 21117",
    "addr:housenumber":"2030",
    "addr:postcode":"21117",
    "addr:street":"Greenspring Valley Rd",
    "iso:country":"US",
    "sg:address":"2030 Greenspring Valley Rd",
    "sg:city":"Stevenson",
    "sg:classifiers":[
        {
            "category":"Professional",
            "subcategory":"Advertising",
            "type":"Services"
        }
    ],
    "sg:phone":"+1 410 484 6882",
    "sg:postcode":"21117",
    "sg:province":"MD",
    "sg:tags":[
        "counselor"
    ],
    "wof:name":"Smith & Assoc",
    "wof:placetype":"venue"
},
  "geometry": {"coordinates":[-76.719127,39.413907],"type":"Point"}
}