{
  "type": "Feature",
  "properties": {
    "iso:country":"US",
    "sg:address":"9144 Camelia Dr",
    "sg:city":"Easton",
    "sg:classifiers":[
        {
            "category":"Manufacturing",
            "subcategory":"Tools & Machinery",
            "type":"Manufacturing & Wholesale Goods"
        }
    ],
    "sg:phone":"+1 410 726 6949",
    "sg:postcode":"21601",
    "sg:province":"MD",
    "sg:tags":[
        "dry",
        "delivery",
        "cleaning"
    ],
    "wof:name":"Mdi Investments",
    "wof:placetype":"venue"
},
  "geometry": {"coordinates":[-76.056353,38.799195],"type":"Point"}
}