{
  "type": "Feature",
  "properties": {
    "iso:country":"US",
    "sg:address":"7711 Garrison Rd",
    "sg:city":"Landover Hills",
    "sg:classifiers":[
        {
            "category":"Professional",
            "subcategory":"Business Services",
            "type":"Services"
        }
    ],
    "sg:phone":"+1 301 731 4767",
    "sg:postcode":"20784",
    "sg:province":"MD",
    "sg:website":"www.rapidpermits.com",
    "wof:name":"Rapid Permit Svc",
    "wof:placetype":"venue"
},
  "geometry": {"coordinates":[-76.878251,38.950496],"type":"Point"}
}