{
  "type": "Feature",
  "properties": {
    "addr:full":"12619 Grace Max St Rockville MD 20853",
    "addr:housenumber":"12619",
    "addr:postcode":"20853",
    "addr:street":"Grace Max St",
    "iso:country":"US",
    "sg:address":"12619 Grace Max St",
    "sg:city":"Rockville",
    "sg:classifiers":[
        {
            "category":"Freight",
            "type":"Transportation"
        }
    ],
    "sg:phone":"+1 301 946 5071",
    "sg:postcode":"20853",
    "sg:province":"MD",
    "sg:tags":[
        "operator",
        "local",
        "trucking"
    ],
    "wof:name":"Green Light Delivery Inc",
    "wof:placetype":"venue"
},
  "geometry": {"coordinates":[-77.09162600000001,39.064266],"type":"Point"}
}