{
  "type": "Feature",
  "properties": {
    "addr:full":"8503 Marshall Creek Rd Newark MD 21841",
    "addr:housenumber":"8503",
    "addr:postcode":"21841",
    "addr:street":"Marshall Creek Rd",
    "iso:country":"US",
    "sg:address":"8503 Marshall Creek Rd",
    "sg:city":"Newark",
    "sg:classifiers":[
        {
            "category":"Shopping",
            "subcategory":"Hobbies, Toys, & Games",
            "type":"Retail Goods"
        }
    ],
    "sg:phone":"+1 410 632 2345",
    "sg:postcode":"21841",
    "sg:province":"MD",
    "wof:name":"Marshall Creek Junction",
    "wof:placetype":"venue"
},
  "geometry": {"coordinates":[-75.283991,38.24594],"type":"Point"}
}