{
  "type": "Feature",
  "properties": {
    "addr:full":"2728 Pinecrest Dr Riva MD 21140",
    "addr:housenumber":"2728",
    "addr:postcode":"21140",
    "addr:street":"Pinecrest Dr Riva",
    "iso:country":"US",
    "sg:address":"2728 Pinecrest Dr",
    "sg:city":"Riva",
    "sg:classifiers":[
        {
            "category":"Real Estate",
            "subcategory":"Real Estate Agent",
            "type":"Services"
        }
    ],
    "sg:phone":"+1 410 956 6482",
    "sg:postcode":"21140",
    "sg:province":"MD",
    "wof:name":"Homefacts Information Sys",
    "wof:placetype":"venue"
},
  "geometry": {"coordinates":[-76.59005399999999,38.958606],"type":"Point"}
}