{
  "type": "Feature",
  "properties": {
    "addr:full":"12720 Long Green Pike Hydes MD 21082",
    "addr:housenumber":"12720",
    "addr:postcode":"21082",
    "addr:street":"Long Green Pike",
    "iso:country":"US",
    "sg:address":"12720 Long Green Pike",
    "sg:city":"Hydes",
    "sg:classifiers":[
        {
            "category":"Professional",
            "subcategory":"Management & Consulting",
            "type":"Services"
        }
    ],
    "sg:phone":"+1 410 592 2502",
    "sg:postcode":"21082",
    "sg:province":"MD",
    "sg:tags":[
        "farm"
    ],
    "wof:name":"Long Green Farm",
    "wof:placetype":"venue"
},
  "geometry": {"coordinates":[-76.486198,39.47279],"type":"Point"}
}