{
  "type": "Feature",
  "properties": {
    "iso:country":"US",
    "sg:address":"206 N Hickory Ave",
    "sg:city":"Bel Air",
    "sg:classifiers":[
        {
            "category":"Professional",
            "subcategory":"Lawyer & Legal Services",
            "type":"Services"
        }
    ],
    "sg:phone":"+1 410 838 9060",
    "sg:postcode":"21014",
    "sg:province":"MD",
    "sg:tags":[
        "attorney"
    ],
    "wof:name":"Christopher R Van Roden Pa",
    "wof:placetype":"venue"
},
  "geometry": {"coordinates":[-76.34954999999999,39.541564],"type":"Point"}
}