{
  "type": "Feature",
  "properties": {
    "iso:country":"US",
    "sg:address":"32287 Quinn Rd",
    "sg:city":"Massey",
    "sg:classifiers":[
        {
            "category":"Farming",
            "subcategory":"Farm",
            "type":"Manufacturing & Wholesale Goods"
        }
    ],
    "sg:phone":"+1 410 648 5245",
    "sg:postcode":"21650",
    "sg:province":"MD",
    "sg:tags":[
        "crop",
        "general"
    ],
    "wof:name":"Alfred Everett",
    "wof:placetype":"venue"
},
  "geometry": {"coordinates":[-75.817069,39.332067],"type":"Point"}
}