{
  "type": "Feature",
  "properties": {
    "addr:full":"4516 Yorkshire Dr Ellicott City MD 21043",
    "addr:housenumber":"4516",
    "addr:postcode":"21043",
    "addr:street":"Yorkshire Dr",
    "iso:country":"US",
    "sg:address":"4516 Yorkshire Dr",
    "sg:city":"Ellicott City",
    "sg:classifiers":[
        {
            "category":"Wholesale",
            "subcategory":"Furniture",
            "type":"Manufacturing & Wholesale Goods"
        }
    ],
    "sg:phone":"+1 410 313 8261",
    "sg:postcode":"21043",
    "sg:province":"MD",
    "wof:name":"Wright Line",
    "wof:placetype":"venue"
},
  "geometry": {"coordinates":[-76.81425900000001,39.245559],"type":"Point"}
}