{
  "type": "Feature",
  "properties": {
    "iso:country":"US",
    "sg:address":"1614 Farnborn St",
    "sg:city":"Crofton",
    "sg:classifiers":[
        {
            "category":"Real Estate",
            "subcategory":"Real Estate Agent",
            "type":"Services"
        }
    ],
    "sg:phone":"+1 410 721 7757",
    "sg:postcode":"21114",
    "sg:province":"MD",
    "wof:name":"Samuel T Powell III",
    "wof:placetype":"venue"
},
  "geometry": {"coordinates":[-76.681191,39.007383],"type":"Point"}
}