{
  "type": "Feature",
  "properties": {
    "iso:country":"US",
    "sg:address":"311 E Cross St",
    "sg:city":"Baltimore",
    "sg:classifiers":[
        {
            "category":"Building & Trades",
            "subcategory":"Construction",
            "type":"Services"
        }
    ],
    "sg:phone":"+1 410 962 8910",
    "sg:postcode":"21230",
    "sg:province":"MD",
    "sg:tags":[
        "home",
        "improvement"
    ],
    "wof:name":"Baltimore Harbor Remodeling",
    "wof:placetype":"venue"
},
  "geometry": {"coordinates":[-76.60903399999999,39.277376],"type":"Point"}
}