{
  "type": "Feature",
  "properties": {
    "addr:full":"3034 Putty Hill Ave Parkville MD 21234",
    "addr:housenumber":"3034",
    "addr:postcode":"21234",
    "addr:street":"Putty Hill Ave",
    "iso:country":"US",
    "sg:address":"3034 Putty Hill Ave",
    "sg:city":"Parkville",
    "sg:classifiers":[
        {
            "category":"Building & Trades",
            "subcategory":"Construction",
            "type":"Services"
        }
    ],
    "sg:phone":"+1 410 882 3600",
    "sg:postcode":"21234",
    "sg:province":"MD",
    "sg:tags":[
        "masonry",
        "contractor"
    ],
    "wof:name":"Grace Masonary Inc",
    "wof:placetype":"venue"
},
  "geometry": {"coordinates":[-76.532207,39.381495],"type":"Point"}
}