{
  "type": "Feature",
  "properties": {
    "addr:full":"16254 Frederick Rd Gaithersburg MD 20877",
    "addr:housenumber":"16254",
    "addr:postcode":"20877",
    "addr:street":"Frederick Rd",
    "iso:country":"US",
    "sg:address":"16254 Frederick Rd",
    "sg:city":"Gaithersburg",
    "sg:classifiers":[
        {
            "category":"Food & Beverages",
            "subcategory":"Groceries & Convenience Stores",
            "type":"Retail Goods"
        }
    ],
    "sg:phone":"+1 301 330 7327",
    "sg:postcode":"20877",
    "sg:province":"MD",
    "wof:name":"Food Express Store",
    "wof:placetype":"venue"
},
  "geometry": {"coordinates":[-77.17621800000001,39.121492],"type":"Point"}
}