{
  "type": "Feature",
  "properties": {
    "addr:full":"14601 Sandy Ridge Rd Silver Spring MD 20905",
    "addr:housenumber":"14601",
    "addr:postcode":"20905",
    "addr:street":"Sandy Ridge Rd",
    "iso:country":"US",
    "sg:address":"14601 Sandy Ridge Rd",
    "sg:city":"Silver Spring",
    "sg:classifiers":[
        {
            "category":"Wholesale",
            "subcategory":"Sporting Goods",
            "type":"Manufacturing & Wholesale Goods"
        }
    ],
    "sg:phone":"+1 301 384 8976",
    "sg:postcode":"20905",
    "sg:province":"MD",
    "sg:tags":[
        "product",
        "golf"
    ],
    "wof:name":"Stephen M Cullen",
    "wof:placetype":"venue"
},
  "geometry": {"coordinates":[-77.01057299999999,39.095259],"type":"Point"}
}