{
  "type": "Feature",
  "properties": {
    "addr:full":"24 Misty Meadows Ln Port Deposit MD 21904",
    "addr:housenumber":"24",
    "addr:postcode":"21904",
    "addr:street":"Misty Meadows Ln",
    "iso:country":"US",
    "sg:address":"24 Misty Meadows Ln",
    "sg:city":"Port Deposit",
    "sg:classifiers":[
        {
            "category":"Social Services",
            "subcategory":"Adult Care",
            "type":"Services"
        }
    ],
    "sg:phone":"+1 410 658 9307",
    "sg:postcode":"21904",
    "sg:province":"MD",
    "sg:tags":[
        "home",
        "residential"
    ],
    "wof:name":"Golden Legends Group Senior",
    "wof:placetype":"venue"
},
  "geometry": {"coordinates":[-76.076883,39.661453],"type":"Point"}
}