{
  "type": "Feature",
  "properties": {
    "addr:full":"312 Safety Dr Centreville MD 21617",
    "addr:postcode":"21617",
    "addr:street":"Safety Dr",
    "iso:country":"US",
    "sg:address":"312 Safety Dr",
    "sg:city":"Centreville",
    "sg:classifiers":[
        {
            "category":"Government",
            "subcategory":"Office",
            "type":"Public Place"
        }
    ],
    "sg:phone":"+1 410 758 0920",
    "sg:postcode":"21617",
    "sg:province":"MD",
    "wof:name":"Queen Anne's Road Engineer",
    "wof:placetype":"venue"
},
  "geometry": {"coordinates":[-76.015382,39.037075],"type":"Point"}
}