{
  "type": "Feature",
  "properties": {
    "addr:full":"4989 Winchester Blvd Frederick MD 21703",
    "addr:housenumber":"4989",
    "addr:postcode":"21703",
    "addr:street":"Winchester Blvd",
    "iso:country":"US",
    "sg:address":"4989 Winchester Blvd",
    "sg:city":"Frederick",
    "sg:classifiers":[
        {
            "category":"Manufacturing",
            "subcategory":"Building Materials",
            "type":"Manufacturing & Wholesale Goods"
        }
    ],
    "sg:phone":"+1 301 874 1081",
    "sg:postcode":"21703",
    "sg:province":"MD",
    "wof:name":"Frederick Architectural",
    "wof:placetype":"venue"
},
  "geometry": {"coordinates":[-77.496528,39.343648],"type":"Point"}
}