{
  "type": "Feature",
  "properties": {
    "iso:country":"US",
    "sg:address":"432 Banksia Dr",
    "sg:city":"Frederick",
    "sg:classifiers":[
        {
            "category":"Freight",
            "type":"Transportation"
        }
    ],
    "sg:phone":"+1 301 514 3724",
    "sg:postcode":"21701",
    "sg:province":"MD",
    "wof:name":"Valness Transportation",
    "wof:placetype":"venue"
},
  "geometry": {"coordinates":[-77.422351,39.404364],"type":"Point"}
}