{
  "type": "Feature",
  "properties": {
    "iso:country":"US",
    "sg:address":"10851 Shanktown Rd",
    "sg:city":"Big Pool",
    "sg:classifiers":[
        {
            "category":"Retail",
            "subcategory":"Repair Shop",
            "type":"Services"
        }
    ],
    "sg:phone":"+1 301 842 3033",
    "sg:postcode":"21711",
    "sg:province":"MD",
    "sg:tags":[
        "cleaning",
        "drapery"
    ],
    "wof:name":"Essential Fabricare",
    "wof:placetype":"venue"
},
  "geometry": {"coordinates":[-77.992792,39.610644],"type":"Point"}
}