{
  "type": "Feature",
  "properties": {
    "iso:country":"US",
    "sg:address":"10995 Owings Mills Blvd",
    "sg:city":"Owings Mills",
    "sg:classifiers":[
        {
            "category":"Restaurant",
            "type":"Food & Drink"
        }
    ],
    "sg:menulink":"http://www.allmenus.com/md/reisterstown/146763-subway/menu/",
    "sg:phone":"+1 410 363 1341",
    "sg:postcode":"21117",
    "sg:province":"MD",
    "sg:tags":[
        "american",
        "sandwich"
    ],
    "wof:name":"Subway",
    "wof:placetype":"venue"
},
  "geometry": {"coordinates":[-76.781379,39.417171],"type":"Point"}
}