{
  "type": "Feature",
  "properties": {
    "addr:full":"2015 Bear Ridge Rd Baltimore MD 21222",
    "addr:housenumber":"2015",
    "addr:postcode":"21222",
    "addr:street":"Bear Ridge Rd",
    "iso:country":"US",
    "sg:address":"2015 Bear Ridge Rd",
    "sg:city":"Baltimore",
    "sg:classifiers":[
        {
            "category":"Professional",
            "subcategory":"Business Services",
            "type":"Services"
        }
    ],
    "sg:phone":"+1 410 383 9400",
    "sg:postcode":"21222",
    "sg:province":"MD",
    "sg:tags":[
        "decorating",
        "contractor"
    ],
    "wof:name":"MVM Enterprises Inc",
    "wof:placetype":"venue"
},
  "geometry": {"coordinates":[-76.48787,39.255855],"type":"Point"}
}