{
  "type": "Feature",
  "properties": {
    "addr:full":"1220 Key Hwy Baltimore MD 21230",
    "addr:housenumber":"1220",
    "addr:postcode":"21230",
    "addr:street":"Key Hwy",
    "iso:country":"US",
    "sg:address":"1220 Key Hwy",
    "sg:city":"Baltimore",
    "sg:classifiers":[
        {
            "category":"Wholesale",
            "subcategory":"Stationery",
            "type":"Manufacturing & Wholesale Goods"
        }
    ],
    "sg:phone":"+1 410 539 1276",
    "sg:postcode":"21230",
    "sg:province":"MD",
    "sg:tags":[
        "product",
        "paper"
    ],
    "wof:name":"Ris Paper Co Inc",
    "wof:placetype":"venue"
},
  "geometry": {"coordinates":[-76.605771,39.275646],"type":"Point"}
}