{
  "type": "Feature",
  "properties": {
    "addr:full":"17 Montauk Ct Baltimore MD 21234",
    "addr:housenumber":"17",
    "addr:postcode":"21234",
    "addr:street":"Montauk Ct",
    "iso:country":"US",
    "sg:address":"17 Montauk Ct",
    "sg:city":"Baltimore",
    "sg:classifiers":[
        {
            "category":"Retail",
            "subcategory":"Repair Shop",
            "type":"Services"
        }
    ],
    "sg:phone":"+1 410 252 1307",
    "sg:postcode":"21234",
    "sg:province":"MD",
    "sg:tags":[
        "refrigerator",
        "freezer"
    ],
    "wof:name":"Emergency Response Refrig",
    "wof:placetype":"venue"
},
  "geometry": {"coordinates":[-76.49248799999999,39.405777],"type":"Point"}
}