{
  "type": "Feature",
  "properties": {
    "addr:full":"1651 Crofton Blvd Crofton MD 21114",
    "addr:housenumber":"1651",
    "addr:postcode":"21114",
    "addr:street":"Crofton Blvd",
    "iso:country":"US",
    "sg:address":"1651 Crofton Blvd",
    "sg:city":"Crofton",
    "sg:classifiers":[
        {
            "category":"Wholesale",
            "subcategory":"Computers",
            "type":"Manufacturing & Wholesale Goods"
        }
    ],
    "sg:phone":"+1 301 261 0116",
    "sg:postcode":"21114",
    "sg:province":"MD",
    "sg:tags":[
        "communications",
        "datum"
    ],
    "wof:name":"Docutech",
    "wof:placetype":"venue"
},
  "geometry": {"coordinates":[-76.69803,39.015613],"type":"Point"}
}