{
  "type": "Feature",
  "properties": {
    "addr:full":"4004 Rickover Rd Silver Spring MD 20902",
    "addr:housenumber":"4004",
    "addr:postcode":"20902",
    "addr:street":"Rickover Rd",
    "iso:country":"US",
    "sg:address":"4004 Rickover Rd",
    "sg:city":"Silver Spring",
    "sg:classifiers":[
        {
            "category":"Professional",
            "subcategory":"Engineering",
            "type":"Services"
        }
    ],
    "sg:phone":"+1 301 949 7270",
    "sg:postcode":"20902",
    "sg:province":"MD",
    "sg:tags":[
        "engineer"
    ],
    "wof:name":"Advance Programs Development",
    "wof:placetype":"venue"
},
  "geometry": {"coordinates":[-77.07719400000001,39.044615],"type":"Point"}
}