{
  "type": "Feature",
  "properties": {
    "addr:full":"8303 Harford Rd Baltimore MD 21234",
    "addr:housenumber":"8303",
    "addr:postcode":"21234",
    "addr:street":"Harford Rd",
    "iso:country":"US",
    "sg:address":"8303 Harford Rd",
    "sg:city":"Baltimore",
    "sg:classifiers":[
        {
            "category":"Retail",
            "subcategory":"Repair Shop",
            "type":"Services"
        }
    ],
    "sg:phone":"+1 410 254 8484",
    "sg:postcode":"21234",
    "sg:province":"MD",
    "sg:tags":[
        "television",
        "radio"
    ],
    "wof:name":"Hamilton TV",
    "wof:placetype":"venue"
},
  "geometry": {"coordinates":[-76.53795599999999,39.379371],"type":"Point"}
}