{
  "type": "Feature",
  "properties": {
    "iso:country":"US",
    "sg:address":"836 S Main St",
    "sg:city":"Bel Air",
    "sg:classifiers":[
        {
            "category":"Banks & Credit Unions",
            "subcategory":"Investment Brokerage",
            "type":"Services"
        }
    ],
    "sg:phone":"+1 410 838 2992",
    "sg:postcode":"21014",
    "sg:province":"MD",
    "sg:tags":[
        "consultant",
        "planning",
        "financial"
    ],
    "wof:name":"Harford Financial Group",
    "wof:placetype":"venue"
},
  "geometry": {"coordinates":[-76.339922,39.526724],"type":"Point"}
}