{
  "type": "Feature",
  "properties": {
    "addr:full":"4235 Euclid Ave Baltimore MD 21229",
    "addr:housenumber":"4235",
    "addr:postcode":"21229",
    "addr:street":"Euclid Ave",
    "iso:country":"US",
    "sg:address":"4235 Euclid Ave",
    "sg:city":"Baltimore",
    "sg:classifiers":[
        {
            "category":"Health Services",
            "subcategory":"Health Practitioner",
            "type":"Services"
        }
    ],
    "sg:phone":"+1 410 525 0885",
    "sg:postcode":"21229",
    "sg:province":"MD",
    "sg:tags":[
        "therapist",
        "biofeedback"
    ],
    "wof:name":"Beatrice W Haskins",
    "wof:placetype":"venue"
},
  "geometry": {"coordinates":[-76.68673800000001,39.282449],"type":"Point"}
}