{
  "type": "Feature",
  "properties": {
    "iso:country":"US",
    "sg:address":"4235 Euclid Ave",
    "sg:city":"Baltimore",
    "sg:classifiers":[
        {
            "category":"Health Services",
            "subcategory":"Health Practitioner",
            "type":"Services"
        }
    ],
    "sg:phone":"+1 410 525 0885",
    "sg:postcode":"21229",
    "sg:province":"MD",
    "sg:tags":[
        "therapist",
        "biofeedback"
    ],
    "wof:name":"Beatrice W Haskins",
    "wof:placetype":"venue"
},
  "geometry": {"coordinates":[-76.686738,39.282449],"type":"Point"}
}