{
  "type": "Feature",
  "properties": {
    "addr:full":"300 E Lombard St Ste 1400 Baltimore MD 21202",
    "addr:housenumber":"300",
    "addr:postcode":"21202",
    "addr:street":"E Lombard St Ste 1400",
    "iso:country":"US",
    "sg:address":"300 E Lombard St Ste 1400",
    "sg:city":"Baltimore",
    "sg:classifiers":[
        {
            "category":"Professional",
            "subcategory":"Lawyer & Legal Services",
            "type":"Services"
        }
    ],
    "sg:phone":"+1 410 539 2837",
    "sg:postcode":"21202",
    "sg:province":"MD",
    "sg:tags":[
        "attorney",
        "business",
        "corporation",
        "partnership",
        "law"
    ],
    "sg:website":"http://www.ctadvantage.com",
    "wof:name":"Ct Corporation System",
    "wof:placetype":"venue"
},
  "geometry": {"coordinates":[-76.610809,39.28788],"type":"Point"}
}