{
  "type": "Feature",
  "properties": {
    "iso:country":"US",
    "sg:address":"4830 Water Park Dr",
    "sg:city":"Belcamp",
    "sg:classifiers":[
        {
            "category":"Professional",
            "subcategory":"Lawyer & Legal Services",
            "type":"Services"
        }
    ],
    "sg:phone":"+1 410 306 6310",
    "sg:postcode":"21017",
    "sg:province":"MD",
    "sg:tags":[
        "plan"
    ],
    "wof:name":"S Nachman",
    "wof:placetype":"venue"
},
  "geometry": {"coordinates":[-76.23303,39.467011],"type":"Point"}
}