{
  "type": "Feature",
  "properties": {
    "addr:full":"10020 Southern Maryland Blvd Dunkirk MD 20754",
    "addr:housenumber":"10020",
    "addr:postcode":"20754",
    "addr:street":"Southern Maryland Blvd",
    "iso:country":"US",
    "sg:address":"10020 Southern Maryland Blvd",
    "sg:city":"Dunkirk",
    "sg:classifiers":[
        {
            "category":"Real Estate",
            "subcategory":"Real Estate Services",
            "type":"Services"
        }
    ],
    "sg:phone":"+1 301 322 2000",
    "sg:postcode":"20754",
    "sg:province":"MD",
    "sg:tags":[
        "abstract",
        "title"
    ],
    "wof:name":"Atlantic Coast Title Inc",
    "wof:placetype":"venue"
},
  "geometry": {"coordinates":[-76.65787400000001,38.713624],"type":"Point"}
}