{
  "type": "Feature",
  "properties": {
    "addr:full":"10315 Gary Rd Potomac MD 20854",
    "addr:housenumber":"10315",
    "addr:postcode":"20854",
    "addr:street":"Gary Rd",
    "iso:country":"US",
    "sg:address":"10315 Gary Rd",
    "sg:city":"Potomac",
    "sg:classifiers":[
        {
            "category":"Travel",
            "subcategory":"Hotels & Motels",
            "type":"Entertainment"
        }
    ],
    "sg:phone":"+1 301 299 7799",
    "sg:postcode":"20854",
    "sg:province":"MD",
    "wof:name":"Inter-Continental Grp",
    "wof:placetype":"venue"
},
  "geometry": {"coordinates":[-77.20826099999999,39.025111],"type":"Point"}
}