{
  "type": "Feature",
  "properties": {
    "iso:country":"US",
    "sg:address":"1203 N Collington Ave",
    "sg:city":"Baltimore",
    "sg:classifiers":[
        {
            "category":"Recreation",
            "type":"Entertainment"
        }
    ],
    "sg:phone":"+1 410 675 3441",
    "sg:postcode":"21213",
    "sg:province":"MD",
    "sg:tags":[
        "club",
        "membership",
        "sport",
        "center"
    ],
    "wof:name":"Eastside Cb Social Club",
    "wof:placetype":"venue"
},
  "geometry": {"coordinates":[-76.587051,39.30484],"type":"Point"}
}