{
  "type": "Feature",
  "properties": {
    "iso:country":"US",
    "sg:address":"306 Broadwood Dr",
    "sg:city":"Rockville",
    "sg:classifiers":[
        {
            "category":"Building & Trades",
            "subcategory":"Construction",
            "type":"Services"
        }
    ],
    "sg:phone":"+1 301 610 7525",
    "sg:postcode":"20851",
    "sg:province":"MD",
    "sg:tags":[
        "hanging",
        "contractor"
    ],
    "wof:name":"New Colors Group Inc",
    "wof:placetype":"venue"
},
  "geometry": {"coordinates":[-77.12050499999999,39.081255],"type":"Point"}
}