{
  "type": "Feature",
  "properties": {
    "addr:full":"4310 Hawthorne Rd Indian Head MD 20640",
    "addr:housenumber":"4310",
    "addr:postcode":"20640",
    "addr:street":"Hawthorne Rd",
    "iso:country":"US",
    "sg:address":"4310 Hawthorne Rd",
    "sg:city":"Indian Head",
    "sg:classifiers":[
        {
            "category":"Shopping",
            "subcategory":"Bicycles & Sporting Goods",
            "type":"Retail Goods"
        }
    ],
    "sg:phone":"+1 301 743 2111",
    "sg:postcode":"20640",
    "sg:province":"MD",
    "wof:name":"Lee's Market",
    "wof:placetype":"venue"
},
  "geometry": {"coordinates":[-77.12469299999999,38.59675],"type":"Point"}
}