{
  "type": "Feature",
  "properties": {
    "iso:country":"US",
    "sg:address":"5922 Martin Luther King Jr Hwy",
    "sg:city":"Capitol Heights",
    "sg:classifiers":[
        {
            "category":"Shopping",
            "subcategory":"Pharmacy",
            "type":"Retail Goods"
        }
    ],
    "sg:phone":"+1 301 925 8151",
    "sg:postcode":"20743",
    "sg:province":"MD",
    "sg:tags":[
        "drugstore"
    ],
    "wof:name":"Cvs Pharmacy",
    "wof:placetype":"venue"
},
  "geometry": {"coordinates":[-76.90570700000001,38.897512],"type":"Point"}
}