{
  "type": "Feature",
  "properties": {
    "iso:country":"US",
    "sg:address":"227 Main St",
    "sg:city":"Reisterstown",
    "sg:classifiers":[
        {
            "category":"Shopping",
            "subcategory":"Gifts & Souvenirs",
            "type":"Retail Goods"
        }
    ],
    "sg:phone":"+1 410 833 4900",
    "sg:postcode":"21136",
    "sg:province":"MD",
    "sg:tags":[
        "collectible"
    ],
    "wof:name":"Bears In The Attic",
    "wof:placetype":"venue"
},
  "geometry": {"coordinates":[-76.828532,39.463669],"type":"Point"}
}