{
  "type": "Feature",
  "properties": {
    "addr:full":"15600 New Hampshire Ave Silver Spring MD 20905",
    "addr:housenumber":"15600",
    "addr:postcode":"20905",
    "addr:street":"New Hampshire Ave",
    "iso:country":"US",
    "sg:address":"15600 New Hampshire Ave",
    "sg:city":"Silver Spring",
    "sg:classifiers":[
        {
            "category":"Organizations",
            "subcategory":"Religious Organization",
            "type":"Services"
        }
    ],
    "sg:phone":"+1 301 384 0281",
    "sg:postcode":"20905",
    "sg:province":"MD",
    "sg:website":"www.christfellowship.us",
    "wof:name":"Christ Fellowship Church",
    "wof:placetype":"venue"
},
  "geometry": {"coordinates":[-76.994598,39.112598],"type":"Point"}
}