{
  "type": "Feature",
  "properties": {
    "iso:country":"US",
    "sg:address":"21301 Seneca Crossing Dr",
    "sg:city":"Germantown",
    "sg:classifiers":[
        {
            "category":"Education",
            "subcategory":"School",
            "type":"Public Place"
        }
    ],
    "sg:phone":"+1 301 353 0994",
    "sg:postcode":"20876",
    "sg:province":"MD",
    "wof:name":"Sally K Ride Elementary School",
    "wof:placetype":"venue"
},
  "geometry": {"coordinates":[-77.238502,39.206359],"type":"Point"}
}