{
  "type": "Feature",
  "properties": {
    "iso:country":"US",
    "sg:address":"7272 Wisconsin Ave",
    "sg:city":"Bethesda",
    "sg:classifiers":[
        {
            "category":"Professional",
            "subcategory":"Lawyer & Legal Services",
            "type":"Services"
        }
    ],
    "sg:phone":"+1 301 652 0800",
    "sg:postcode":"20814",
    "sg:province":"MD",
    "sg:tags":[
        "attorney"
    ],
    "sg:website":"www.irspros.com",
    "wof:name":"Frank & Assoc",
    "wof:placetype":"venue"
},
  "geometry": {"coordinates":[-77.092955,38.98135],"type":"Point"}
}