{
  "type": "Feature",
  "properties": {
    "addr:full":"12050 Baltimore Ave Beltsville MD 20705",
    "addr:housenumber":"12050",
    "addr:postcode":"20705",
    "addr:street":"Baltimore Ave",
    "iso:country":"US",
    "sg:address":"12050 Baltimore Ave",
    "sg:city":"Beltsville",
    "sg:classifiers":[
        {
            "category":"Shopping",
            "subcategory":"Mobile Phones",
            "type":"Retail Goods"
        }
    ],
    "sg:phone":"+1 301 210 0676",
    "sg:postcode":"20705",
    "sg:province":"MD",
    "wof:name":"Voicestream",
    "wof:placetype":"venue"
},
  "geometry": {"coordinates":[-76.89227099999999,39.055721],"type":"Point"}
}