{
  "type": "Feature",
  "properties": {
    "iso:country":"US",
    "sg:address":"5100 Wisconsin Ave NW",
    "sg:city":"Washington",
    "sg:classifiers":[
        {
            "category":"Organizations",
            "subcategory":"Labor Organization",
            "type":"Services"
        }
    ],
    "sg:phone":"+1 202 244 0628",
    "sg:postcode":"20016",
    "sg:province":"MD",
    "wof:name":"D C Nurses Assn",
    "wof:placetype":"venue"
},
  "geometry": {"coordinates":[-77.083817,38.957024],"type":"Point"}
}