{
  "type": "Feature",
  "properties": {
    "iso:country":"US",
    "sg:address":"311 Byrn St",
    "sg:city":"Cambridge",
    "sg:classifiers":[
        {
            "category":"Professional",
            "subcategory":"Accounting & Tax Preparation",
            "type":"Services"
        }
    ],
    "sg:phone":"+1 410 228 2899",
    "sg:postcode":"21613",
    "sg:province":"MD",
    "sg:tags":[
        "accountant"
    ],
    "wof:name":"Sylvia Brohawn",
    "wof:placetype":"venue"
},
  "geometry": {"coordinates":[-76.068675,38.570813],"type":"Point"}
}