{
  "type": "Feature",
  "properties": {
    "addr:full":"615 Hammonds Ln Brooklyn MD 21225",
    "addr:housenumber":"615",
    "addr:postcode":"21225",
    "addr:street":"Hammonds Ln",
    "iso:country":"US",
    "sg:address":"615 Hammonds Ln",
    "sg:city":"Brooklyn",
    "sg:classifiers":[
        {
            "category":"Health Services",
            "subcategory":"Doctor",
            "type":"Services"
        }
    ],
    "sg:phone":"+1 410 789 1199",
    "sg:postcode":"21225",
    "sg:province":"MD",
    "wof:name":"Wolf Edward J MD",
    "wof:placetype":"venue"
},
  "geometry": {"coordinates":[-76.628304,39.2122],"type":"Point"}
}