{
  "type": "Feature",
  "properties": {
    "addr:full":"709 Atlantic Ave Ocean City MD 21842",
    "addr:housenumber":"709",
    "addr:postcode":"21842",
    "addr:street":"Atlantic Ave",
    "iso:country":"US",
    "sg:address":"709 Atlantic Ave",
    "sg:city":"Ocean City",
    "sg:classifiers":[
        {
            "category":"Restaurant",
            "type":"Food & Drink"
        }
    ],
    "sg:menulink":"http://www.allmenus.com/md/ocean-city/197153-burger-king/menu/",
    "sg:phone":"+1 410 543 1073",
    "sg:postcode":"21842",
    "sg:province":"MD",
    "sg:tags":[
        "burger",
        "american"
    ],
    "wof:name":"Burger King",
    "wof:placetype":"venue"
},
  "geometry": {"coordinates":[-75.08146499999999,38.337795],"type":"Point"}
}