{
  "type": "Feature",
  "properties": {
    "iso:country":"US",
    "sg:address":"4304 Newport Ave",
    "sg:city":"Baltimore",
    "sg:classifiers":[
        {
            "category":"Restaurant",
            "type":"Food & Drink"
        }
    ],
    "sg:phone":"+1 410 889 0778",
    "sg:postcode":"21211",
    "sg:province":"MD",
    "sg:tags":[
        "eating"
    ],
    "wof:name":"Tasty Cake",
    "wof:placetype":"venue"
},
  "geometry": {"coordinates":[-76.641446,39.34338],"type":"Point"}
}