{
  "type": "Feature",
  "properties": {
    "iso:country":"US",
    "sg:address":"7408 Westmore Rd",
    "sg:city":"Rockville",
    "sg:classifiers":[
        {
            "category":"Retail",
            "subcategory":"Auto Repair",
            "type":"Services"
        }
    ],
    "sg:phone":"+1 301 762 1074",
    "sg:postcode":"20850",
    "sg:province":"MD",
    "sg:tags":[
        "repairing",
        "automobile"
    ],
    "wof:name":"Holland Automotive",
    "wof:placetype":"venue"
},
  "geometry": {"coordinates":[-77.147683,39.099804],"type":"Point"}
}