{
  "type": "Feature",
  "properties": {
    "iso:country":"US",
    "sg:address":"1550 Hart Rd",
    "sg:city":"Towson",
    "sg:classifiers":[
        {
            "category":"Communications",
            "subcategory":"Radio Station",
            "type":"Services"
        }
    ],
    "sg:phone":"+1 410 821 9678",
    "sg:postcode":"21286",
    "sg:province":"MD",
    "sg:tags":[
        "company",
        "broadcasting"
    ],
    "sg:website":"www.baltimoresportstalk.com",
    "wof:name":"WNST",
    "wof:placetype":"venue"
},
  "geometry": {"coordinates":[-76.558942,39.41683],"type":"Point"}
}