{
  "type": "Feature",
  "properties": {
    "addr:full":"14301 Layhill Rd Silver Spring MD 20906",
    "addr:housenumber":"14301",
    "addr:postcode":"20906",
    "addr:street":"Layhill Rd",
    "iso:country":"US",
    "sg:address":"14301 Layhill Rd",
    "sg:city":"Silver Spring",
    "sg:classifiers":[
        {
            "category":"Retail",
            "subcategory":"Laundry & Dry Cleaning",
            "type":"Services"
        }
    ],
    "sg:phone":"+1 301 871 0235",
    "sg:postcode":"20906",
    "sg:province":"MD",
    "sg:tags":[
        "cleaners"
    ],
    "wof:name":"199 Dry Cleaners",
    "wof:placetype":"venue"
},
  "geometry": {"coordinates":[-77.04486799999999,39.09148],"type":"Point"}
}