{
  "type": "Feature",
  "properties": {
    "addr:full":"885 Marlboro Rd Lothian MD 20711",
    "addr:housenumber":"885",
    "addr:postcode":"20711",
    "addr:street":"Marlboro Rd",
    "iso:country":"US",
    "sg:address":"885 Marlboro Rd",
    "sg:city":"Lothian",
    "sg:classifiers":[
        {
            "category":"Building & Trades",
            "subcategory":"Landscaping Services",
            "type":"Services"
        },
        {
            "category":"Manufacturing",
            "subcategory":"Wood Products",
            "type":"Manufacturing & Wholesale Goods"
        }
    ],
    "sg:phone":"+1 410 741 0776",
    "sg:postcode":"20711",
    "sg:province":"MD",
    "sg:tags":[
        "stump",
        "firewood",
        "tree",
        "grinding",
        "removal",
        "arborist"
    ],
    "sg:website":"http://www.usgreentree.com",
    "wof:name":"Greentree",
    "wof:placetype":"venue"
},
  "geometry": {"coordinates":[-76.667804,38.819628],"type":"Point"}
}