{
  "type": "Feature",
  "properties": {
    "iso:country":"US",
    "sg:address":"8006 Arrowhead Rd",
    "sg:city":"Baltimore",
    "sg:classifiers":[
        {
            "category":"Retail",
            "subcategory":"Repair Shop",
            "type":"Services"
        }
    ],
    "sg:phone":"+1 410 833 7444",
    "sg:postcode":"21208",
    "sg:province":"MD",
    "sg:tags":[
        "appliance"
    ],
    "wof:name":"Beltway Appliance Svc",
    "wof:placetype":"venue"
},
  "geometry": {"coordinates":[-76.755296,39.368974],"type":"Point"}
}