{
  "type": "Feature",
  "properties": {
    "addr:full":"333 N Calvert St Baltimore MD 21202",
    "addr:housenumber":"333",
    "addr:postcode":"21202",
    "addr:street":"N Calvert St",
    "iso:country":"US",
    "sg:address":"333 N Calvert St",
    "sg:city":"Baltimore",
    "sg:classifiers":[
        {
            "category":"Social Services",
            "subcategory":"Job Training",
            "type":"Services"
        }
    ],
    "sg:phone":"+1 410 554 2318",
    "sg:postcode":"21202",
    "sg:province":"MD",
    "sg:tags":[
        "rehabilitation"
    ],
    "wof:name":"Medstar",
    "wof:placetype":"venue"
},
  "geometry": {"coordinates":[-76.61254700000001,39.292594],"type":"Point"}
}