{
  "type": "Feature",
  "properties": {
    "iso:country":"US",
    "sg:address":"1109 Copley Ave",
    "sg:city":"Waldorf",
    "sg:classifiers":[
        {
            "category":"Education",
            "subcategory":"School",
            "type":"Public Place"
        }
    ],
    "sg:phone":"+1 301 645 3338",
    "sg:postcode":"20602",
    "sg:province":"MD",
    "sg:website":"www.ccboe.com",
    "wof:name":"Arthur Middleton Elementary",
    "wof:placetype":"venue"
},
  "geometry": {"coordinates":[-76.922878,38.603708],"type":"Point"}
}