{
  "type": "Feature",
  "properties": {
    "iso:country":"US",
    "sg:address":"11108 Towood Rd",
    "sg:city":"Kingsville",
    "sg:classifiers":[
        {
            "category":"Recreation",
            "type":"Entertainment"
        }
    ],
    "sg:phone":"+1 410 592 2652",
    "sg:postcode":"21087",
    "sg:province":"MD",
    "sg:tags":[
        "entertainers-family",
        "business"
    ],
    "wof:name":"Mind Design Entertainment",
    "wof:placetype":"venue"
},
  "geometry": {"coordinates":[-76.425653,39.42777],"type":"Point"}
}