{
  "type": "Feature",
  "properties": {
    "addr:full":"107 Chesapeake Blvd Elkton MD 21921",
    "addr:housenumber":"107",
    "addr:postcode":"21921",
    "addr:street":"Chesapeake Blvd",
    "iso:country":"US",
    "sg:address":"107 Chesapeake Blvd",
    "sg:city":"Elkton",
    "sg:classifiers":[
        {
            "category":"Education",
            "subcategory":"School",
            "type":"Public Place"
        }
    ],
    "sg:phone":"+1 410 398 6900",
    "sg:postcode":"21921",
    "sg:province":"MD",
    "wof:name":"High Road School",
    "wof:placetype":"venue"
},
  "geometry": {"coordinates":[-75.787026,39.604918],"type":"Point"}
}