{
  "type": "Feature",
  "properties": {
    "addr:full":"18626 Marion Ct Rawlings MD 21557",
    "addr:housenumber":"18626",
    "addr:postcode":"21557",
    "addr:street":"Marion Ct",
    "iso:country":"US",
    "sg:address":"18626 Marion Ct",
    "sg:city":"Rawlings",
    "sg:classifiers":[
        {
            "category":"Education",
            "subcategory":"Special Training",
            "type":"Public Place"
        }
    ],
    "sg:phone":"+1 301 729 3422",
    "sg:postcode":"21557",
    "sg:province":"MD",
    "wof:name":"Allegany Driving School",
    "wof:placetype":"venue"
},
  "geometry": {"coordinates":[-78.885837,39.537842],"type":"Point"}
}