{
  "type": "Feature",
  "properties": {
    "iso:country":"US",
    "sg:address":"8060 Leishear Rd",
    "sg:city":"Laurel",
    "sg:classifiers":[
        {
            "category":"Building & Trades",
            "subcategory":"Construction",
            "type":"Services"
        }
    ],
    "sg:phone":"+1 301 776 0478",
    "sg:postcode":"20723",
    "sg:province":"MD",
    "sg:tags":[
        "contractor"
    ],
    "wof:name":"Commercial Construction Resources Llc",
    "wof:placetype":"venue"
},
  "geometry": {"coordinates":[-76.871899,39.148618],"type":"Point"}
}