{
  "type": "Feature",
  "properties": {
    "addr:full":"8450 Baltimore National Pike Ste 3 Ellicott City MD 21043",
    "addr:housenumber":"8450",
    "addr:postcode":"21043",
    "addr:street":"Baltimore National Pike Ste 3",
    "iso:country":"US",
    "sg:address":"8450 Baltimore National Pike Ste 3",
    "sg:city":"Ellicott City",
    "sg:classifiers":[
        {
            "category":"Food & Beverages",
            "subcategory":"Groceries & Convenience Stores",
            "type":"Retail Goods"
        }
    ],
    "sg:phone":"+1 410 465 5858",
    "sg:postcode":"21043",
    "sg:province":"MD",
    "sg:website":"shop.safeway.com",
    "wof:name":"Safeway",
    "wof:placetype":"venue"
},
  "geometry": {"coordinates":[-76.805027,39.286085],"type":"Point"}
}