{
  "type": "Feature",
  "properties": {
    "addr:full":"110 Saint Paul St Ste 401 Baltimore MD 21202",
    "addr:housenumber":"110",
    "addr:postcode":"21202",
    "addr:street":"Saint Paul St Ste 401",
    "iso:country":"US",
    "sg:address":"110 Saint Paul St Ste 401",
    "sg:city":"Baltimore",
    "sg:classifiers":[
        {
            "category":"Professional",
            "subcategory":"Accounting & Tax Preparation",
            "type":"Services"
        }
    ],
    "sg:phone":"+1 410 779 2925",
    "sg:postcode":"21202",
    "sg:province":"MD",
    "sg:tags":[
        "accountant"
    ],
    "wof:name":"Adams & Associates Consulting Llc",
    "wof:placetype":"venue"
},
  "geometry": {"coordinates":[-76.6138,39.290501],"type":"Point"}
}