{
  "type": "Feature",
  "properties": {
    "addr:full":"5705 Waterside Dr Berlin MD 21811",
    "addr:housenumber":"5705",
    "addr:postcode":"21811",
    "addr:street":"Waterside Dr",
    "iso:country":"US",
    "sg:address":"5705 Waterside Dr",
    "sg:city":"Berlin",
    "sg:classifiers":[
        {
            "category":"Real Estate",
            "subcategory":"Architect",
            "type":"Services"
        }
    ],
    "sg:phone":"+1 410 629 1464",
    "sg:postcode":"21811",
    "sg:province":"MD",
    "sg:tags":[
        "architectural"
    ],
    "wof:name":"David D Quillin Architecture",
    "wof:placetype":"venue"
},
  "geometry": {"coordinates":[-75.198854,38.215855],"type":"Point"}
}