{
  "type": "Feature",
  "properties": {
    "iso:country":"US",
    "sg:address":"15 Wormans Mill Ct",
    "sg:city":"Frederick",
    "sg:classifiers":[
        {
            "category":"Professional",
            "subcategory":"Research",
            "type":"Services"
        }
    ],
    "sg:phone":"+1 301 663 1644",
    "sg:postcode":"21701",
    "sg:province":"MD",
    "sg:tags":[
        "development",
        "laboratory"
    ],
    "sg:website":"www.crl.com",
    "wof:name":"Pathology Associates Intl Corp",
    "wof:placetype":"venue"
},
  "geometry": {"coordinates":[-77.39999,39.442394],"type":"Point"}
}