{
  "type": "Feature",
  "properties": {
    "iso:country":"US",
    "sg:address":"9322 Furrow Ave",
    "sg:city":"Ellicott City",
    "sg:classifiers":[
        {
            "category":"Professional",
            "subcategory":"Management & Consulting",
            "type":"Services"
        }
    ],
    "sg:phone":"+1 443 864 8643",
    "sg:postcode":"21042",
    "sg:province":"MD",
    "sg:tags":[
        "consultant"
    ],
    "wof:name":"Conway Environmental Inc",
    "wof:placetype":"venue"
},
  "geometry": {"coordinates":[-76.83442,39.304292],"type":"Point"}
}