{
  "type": "Feature",
  "properties": {
    "iso:country":"US",
    "sg:address":"1125 Light St",
    "sg:city":"Baltimore",
    "sg:classifiers":[
        {
            "category":"Shopping",
            "subcategory":"Clothing, Apparel, & Fashions",
            "type":"Retail Goods"
        }
    ],
    "sg:phone":"+1 410 244 7260",
    "sg:postcode":"21230",
    "sg:province":"MD",
    "sg:tags":[
        "men's",
        "clothing",
        "accessory",
        "women's"
    ],
    "sg:website":"www.americanapparel.net",
    "wof:name":"American Apparel",
    "wof:placetype":"venue"
},
  "geometry": {"coordinates":[-76.612009,39.276348],"type":"Point"}
}