{
  "type": "Feature",
  "properties": {
    "addr:full":"8310 Sherwick Ct Jessup MD 20794",
    "addr:postcode":"8310;20794",
    "addr:street":"Sherwick Ct",
    "iso:country":"US",
    "sg:address":"8310 Sherwick Ct",
    "sg:city":"Jessup",
    "sg:classifiers":[
        {
            "category":"Building & Trades",
            "subcategory":"Construction",
            "type":"Services"
        }
    ],
    "sg:phone":"+1 301 604 7202",
    "sg:postcode":"20794",
    "sg:province":"MD",
    "sg:tags":[
        "general",
        "contractor"
    ],
    "wof:name":"VSA Construction",
    "wof:placetype":"venue"
},
  "geometry": {"coordinates":[-76.79734999999999,39.148619],"type":"Point"}
}