{
  "type": "Feature",
  "properties": {
    "addr:full":"32 Summit Ave Hagerstown MD 21740",
    "addr:housenumber":"32",
    "addr:postcode":"21740",
    "addr:street":"Summit Ave",
    "iso:country":"US",
    "sg:address":"32 Summit Ave",
    "sg:city":"Hagerstown",
    "sg:classifiers":[
        {
            "category":"Shopping",
            "subcategory":"Discount & Variety Stores",
            "type":"Retail Goods"
        }
    ],
    "sg:phone":"+1 301 739 7810",
    "sg:postcode":"21740",
    "sg:province":"MD",
    "sg:tags":[
        "merchandise",
        "general"
    ],
    "wof:name":"Summit Bargain Shop",
    "wof:placetype":"venue"
},
  "geometry": {"coordinates":[-77.72362699999999,39.641906],"type":"Point"}
}