{
  "type": "Feature",
  "properties": {
    "addr:full":"5115 Indian Head Hwy Oxon Hill MD 20745",
    "addr:housenumber":"5115",
    "addr:postcode":"20745",
    "addr:street":"Indian Head Hwy",
    "iso:country":"US",
    "sg:address":"5115 Indian Head Hwy",
    "sg:city":"Oxon Hill",
    "sg:classifiers":[
        {
            "category":"Shopping",
            "subcategory":"Clothing, Apparel, & Fashions",
            "type":"Retail Goods"
        }
    ],
    "sg:phone":"+1 301 749 4644",
    "sg:postcode":"20745",
    "sg:province":"MD",
    "sg:tags":[
        "furnishing"
    ],
    "wof:name":"His & Her's",
    "wof:placetype":"venue"
},
  "geometry": {"coordinates":[-77.00059899999999,38.820109],"type":"Point"}
}