{
  "type": "Feature",
  "properties": {
    "addr:full":"2905 Willoughby Beach Rd Edgewood MD 21040",
    "addr:housenumber":"2905",
    "addr:postcode":"21040",
    "addr:street":"Willoughby Beach Rd",
    "iso:country":"US",
    "sg:address":"2905 Willoughby Beach Rd",
    "sg:city":"Edgewood",
    "sg:classifiers":[
        {
            "category":"Health Services",
            "subcategory":"Clinic",
            "type":"Services"
        }
    ],
    "sg:phone":"+1 410 538 6060",
    "sg:postcode":"21040",
    "sg:province":"MD",
    "sg:tags":[
        "home"
    ],
    "wof:name":"Comfort Keepers",
    "wof:placetype":"venue"
},
  "geometry": {"coordinates":[-76.2818,39.428966],"type":"Point"}
}