{
  "type": "Feature",
  "properties": {
    "addr:full":"22043 Three Notch Rd Lexington Park MD 20653",
    "addr:housenumber":"22043",
    "addr:postcode":"20653",
    "addr:street":"Three Notch Rd",
    "iso:country":"US",
    "sg:address":"22043 Three Notch Rd",
    "sg:city":"Lexington Park",
    "sg:classifiers":[
        {
            "category":"Professional",
            "subcategory":"Art Services",
            "type":"Services"
        }
    ],
    "sg:phone":"+1 301 863 2398",
    "sg:postcode":"20653",
    "sg:province":"MD",
    "sg:tags":[
        "graphic",
        "designer"
    ],
    "wof:name":"Inet Internet Solutions Group",
    "wof:placetype":"venue"
},
  "geometry": {"coordinates":[-76.461832,38.272717],"type":"Point"}
}