{
  "type": "Feature",
  "properties": {
    "addr:full":"41950 Swans Ct Leonardtown MD 20650",
    "addr:postcode":"41950;20650",
    "addr:street":"Swans Ct",
    "iso:country":"US",
    "sg:address":"41950 Swans Ct",
    "sg:city":"Leonardtown",
    "sg:classifiers":[
        {
            "category":"Education",
            "subcategory":"School",
            "type":"Public Place"
        }
    ],
    "sg:phone":"+1 301 475 7225",
    "sg:postcode":"20650",
    "sg:province":"MD",
    "wof:name":"Kirsten N Russell Memoria",
    "wof:placetype":"venue"
},
  "geometry": {"coordinates":[-76.61967,38.234529],"type":"Point"}
}