{
  "type": "Feature",
  "properties": {
    "addr:full":"4300 Estate Dr Huntingtown MD 20639",
    "addr:housenumber":"4300",
    "addr:postcode":"20639",
    "addr:street":"Estate Dr",
    "iso:country":"US",
    "sg:address":"4300 Estate Dr",
    "sg:city":"Huntingtown",
    "sg:classifiers":[
        {
            "category":"Communications",
            "type":"Services"
        },
        {
            "category":"Building & Trades",
            "subcategory":"Electrical",
            "type":"Services"
        }
    ],
    "sg:phone":"+1 301 494 3122",
    "sg:postcode":"20639",
    "sg:province":"MD",
    "sg:tags":[
        "television",
        "systems-repair",
        "cable",
        "telephone",
        "contractor",
        "equipment"
    ],
    "wof:name":"Metropolitan Home Theater",
    "wof:placetype":"venue"
},
  "geometry": {"coordinates":[-76.63777899999999,38.617062],"type":"Point"}
}