{
  "type": "Feature",
  "properties": {
    "addr:full":"8600 Snowden River Pkwy Ste 106 Columbia MD 21045",
    "addr:housenumber":"8600",
    "addr:postcode":"21045",
    "addr:street":"Snowden River Pkwy Ste 106",
    "iso:country":"US",
    "sg:address":"8600 Snowden River Pkwy Ste 106",
    "sg:city":"Columbia",
    "sg:classifiers":[
        {
            "category":"Health Services",
            "subcategory":"Dentist",
            "type":"Services"
        }
    ],
    "sg:phone":"+1 410 730 2020",
    "sg:postcode":"21045",
    "sg:province":"MD",
    "sg:website":"www.katkowdentistry.com",
    "wof:name":"Katkow Dentistry Llc",
    "wof:placetype":"venue"
},
  "geometry": {"coordinates":[-76.808515,39.199888],"type":"Point"}
}