{
  "type": "Feature",
  "properties": {
    "addr:full":"1314 Bedford Ave Pikesville MD 21208",
    "addr:housenumber":"1314",
    "addr:postcode":"21208",
    "addr:street":"Bedford Ave",
    "iso:country":"US",
    "sg:address":"1314 Bedford Ave",
    "sg:city":"Pikesville",
    "sg:classifiers":[
        {
            "category":"Social Services",
            "type":"Services"
        }
    ],
    "sg:phone":"+1 410 979 4300",
    "sg:postcode":"21208",
    "sg:province":"MD",
    "sg:tags":[
        "youth",
        "organization",
        "center"
    ],
    "wof:name":"Heroes Of Hope",
    "wof:placetype":"venue"
},
  "geometry": {"coordinates":[-76.726883,39.375896],"type":"Point"}
}