{
  "type": "Feature",
  "properties": {
    "addr:full":"5650 2nd St NE Washington MD 20011",
    "addr:housenumber":"5650",
    "addr:postcode":"20011",
    "addr:street":"2Nd St Ne",
    "iso:country":"US",
    "sg:address":"5650 2nd St NE",
    "sg:city":"Washington",
    "sg:classifiers":[
        {
            "category":"Manufacturing",
            "subcategory":"Printing",
            "type":"Manufacturing & Wholesale Goods"
        }
    ],
    "sg:phone":"+1 202 526 6200",
    "sg:postcode":"20011",
    "sg:province":"MD",
    "sg:tags":[
        "commercial"
    ],
    "wof:name":"Washington Press Printing Co",
    "wof:placetype":"venue"
},
  "geometry": {"coordinates":[-77.00375699999999,38.958827],"type":"Point"}
}