{
  "type": "Feature",
  "properties": {
    "addr:full":"2517 Solomons Island Rd Edgewater MD 21037",
    "addr:housenumber":"2517",
    "addr:postcode":"21037",
    "addr:street":"Solomons Island Rd",
    "iso:country":"US",
    "sg:address":"2517 Solomons Island Rd",
    "sg:city":"Edgewater",
    "sg:classifiers":[
        {
            "category":"Organizations",
            "subcategory":"Community Association",
            "type":"Services"
        }
    ],
    "sg:phone":"+1 410 573 0201",
    "sg:postcode":"21037",
    "sg:province":"MD",
    "sg:tags":[
        "fraternal"
    ],
    "wof:name":"Elks Lodge",
    "wof:placetype":"venue"
},
  "geometry": {"coordinates":[-76.54275199999999,38.971543],"type":"Point"}
}