{
  "type": "Feature",
  "properties": {
    "iso:country":"US",
    "sg:address":"24370 Still Pond Neck Rd",
    "sg:city":"Worton",
    "sg:classifiers":[
        {
            "category":"Travel",
            "subcategory":"Campground",
            "type":"Entertainment"
        }
    ],
    "sg:phone":"+1 410 348 6000",
    "sg:postcode":"21678",
    "sg:province":"MD",
    "sg:tags":[
        "camp"
    ],
    "sg:website":"www.tockwogh.org",
    "wof:name":"Camp Tockwogh",
    "wof:placetype":"venue"
},
  "geometry": {"coordinates":[-76.12915099999999,39.348112],"type":"Point"}
}