{
  "type": "Feature",
  "properties": {
    "iso:country":"US",
    "sg:address":"23 S Carrollton Ave",
    "sg:city":"Baltimore",
    "sg:classifiers":[
        {
            "category":"Food & Beverages",
            "subcategory":"Groceries & Convenience Stores",
            "type":"Retail Goods"
        }
    ],
    "sg:phone":"+1 410 752 7733",
    "sg:postcode":"21223",
    "sg:province":"MD",
    "wof:name":"A & B Discount Mart",
    "wof:placetype":"venue"
},
  "geometry": {"coordinates":[-76.636493,39.287565],"type":"Point"}
}