{
  "type": "Feature",
  "properties": {
    "addr:full":"5007 Aurora Dr Kensington MD 20895",
    "addr:housenumber":"5007",
    "addr:postcode":"20895",
    "addr:street":"Aurora Dr",
    "iso:country":"US",
    "sg:address":"5007 Aurora Dr",
    "sg:city":"Kensington",
    "sg:classifiers":[
        {
            "category":"Education",
            "subcategory":"Music School",
            "type":"Public Place"
        }
    ],
    "sg:phone":"+1 301 946 8863",
    "sg:postcode":"20895",
    "sg:province":"MD",
    "sg:website":"http://www.garrettparkmusic.org",
    "wof:name":"Music Man The",
    "wof:placetype":"venue"
},
  "geometry": {"coordinates":[-77.100568,39.035432],"type":"Point"}
}