{
  "type": "Feature",
  "properties": {
    "iso:country":"US",
    "sg:address":"861 Baltimore Blvd",
    "sg:city":"Westminster",
    "sg:classifiers":[
        {
            "category":"Wholesale",
            "subcategory":"Electrical",
            "type":"Manufacturing & Wholesale Goods"
        }
    ],
    "sg:phone":"+1 301 921 0083",
    "sg:postcode":"21157",
    "sg:province":"MD",
    "sg:tags":[
        "equipment"
    ],
    "wof:name":"Schneider Electric",
    "wof:placetype":"venue"
},
  "geometry": {"coordinates":[-76.966113,39.559321],"type":"Point"}
}