{
  "type": "Feature",
  "properties": {
    "iso:country":"US",
    "sg:address":"30 E Padonia Rd",
    "sg:city":"Lutherville",
    "sg:classifiers":[
        {
            "category":"Banks & Credit Unions",
            "subcategory":"Bank",
            "type":"Services"
        }
    ],
    "sg:phone":"+1 410 308 1304",
    "sg:postcode":"21093",
    "sg:province":"MD",
    "sg:tags":[
        "loan",
        "real estate"
    ],
    "wof:name":"Flagship Mortgage Corp",
    "wof:placetype":"venue"
},
  "geometry": {"coordinates":[-76.629051,39.456386],"type":"Point"}
}