{
  "type": "Feature",
  "properties": {
    "addr:full":"103 Chesapeake Blvd Elkton MD 21921",
    "addr:housenumber":"103",
    "addr:postcode":"21921",
    "addr:street":"Chesapeake Blvd",
    "iso:country":"US",
    "sg:address":"103 Chesapeake Blvd",
    "sg:city":"Elkton",
    "sg:classifiers":[
        {
            "category":"Government",
            "subcategory":"Office",
            "type":"Public Place"
        }
    ],
    "sg:phone":"+1 410 996 0580",
    "sg:postcode":"21921",
    "sg:province":"MD",
    "sg:tags":[
        "state",
        "taxation"
    ],
    "wof:name":"Comptroller Treasury",
    "wof:placetype":"venue"
},
  "geometry": {"coordinates":[-75.78685299999999,39.6045],"type":"Point"}
}