{
  "type": "Feature",
  "properties": {
    "iso:country":"US",
    "sg:address":"8465 Helgerman Ct",
    "sg:city":"Gaithersburg",
    "sg:classifiers":[
        {
            "category":"Manufacturing",
            "subcategory":"Printing",
            "type":"Manufacturing & Wholesale Goods"
        }
    ],
    "sg:phone":"+1 301 990 3100",
    "sg:postcode":"20877",
    "sg:province":"MD",
    "sg:tags":[
        "printer"
    ],
    "sg:website":"www.herronprinting.com",
    "wof:name":"Herron Printing & Graphics",
    "wof:placetype":"venue"
},
  "geometry": {"coordinates":[-77.174088,39.130709],"type":"Point"}
}