{
  "type": "Feature",
  "properties": {
    "addr:full":"8621 Central Ave Capitol Heights MD 20743",
    "addr:housenumber":"8621",
    "addr:postcode":"20743",
    "addr:street":"Central Ave",
    "iso:country":"US",
    "sg:address":"8621 Central Ave",
    "sg:city":"Capitol Heights",
    "sg:classifiers":[
        {
            "category":"Retail",
            "subcategory":"Auto Rental",
            "type":"Services"
        }
    ],
    "sg:phone":"+1 301 324 0500",
    "sg:postcode":"20743",
    "sg:province":"MD",
    "sg:tags":[
        "car"
    ],
    "wof:name":"Autorent",
    "wof:placetype":"venue"
},
  "geometry": {"coordinates":[-76.85700199999999,38.890301],"type":"Point"}
}