{
  "type": "Feature",
  "properties": {
    "addr:full":"500 W Montgomery Ave Rockville MD 20850",
    "addr:housenumber":"500",
    "addr:postcode":"20850",
    "addr:street":"W Montgomery Ave",
    "iso:country":"US",
    "sg:address":"500 W Montgomery Ave",
    "sg:city":"Rockville",
    "sg:classifiers":[
        {
            "category":"Real Estate",
            "subcategory":"Real Estate Agent",
            "type":"Services"
        }
    ],
    "sg:phone":"+1 301 309 8246",
    "sg:postcode":"20850",
    "sg:province":"MD",
    "wof:name":"Chestnut Lodge Properties Inc",
    "wof:placetype":"venue"
},
  "geometry": {"coordinates":[-77.16669400000001,39.085509],"type":"Point"}
}