{
  "type": "Feature",
  "properties": {
    "addr:full":"3885 Branch Ave Temple Hills MD 20748",
    "addr:housenumber":"3885",
    "addr:postcode":"20748",
    "addr:street":"Branch Ave",
    "iso:country":"US",
    "sg:address":"3885 Branch Ave",
    "sg:city":"Temple Hills",
    "sg:classifiers":[
        {
            "category":"Shopping",
            "subcategory":"Department Store",
            "type":"Retail Goods"
        }
    ],
    "sg:phone":"+1 301 899 0797",
    "sg:postcode":"20748",
    "sg:province":"MD",
    "wof:name":"Eth Dollar Store",
    "wof:placetype":"venue"
},
  "geometry": {"coordinates":[-76.945403,38.837649],"type":"Point"}
}