{
  "type": "Feature",
  "properties": {
    "addr:full":"5454 Wisconsin Ave Chevy Chase MD 20815",
    "addr:housenumber":"5454",
    "addr:postcode":"20815",
    "addr:street":"Wisconsin Ave",
    "iso:country":"US",
    "sg:address":"5454 Wisconsin Ave",
    "sg:city":"Chevy Chase",
    "sg:classifiers":[
        {
            "category":"Health Services",
            "subcategory":"Doctor",
            "type":"Services"
        }
    ],
    "sg:phone":"+1 301 657 1996",
    "sg:postcode":"20815",
    "sg:province":"MD",
    "sg:tags":[
        "medicine",
        "sport",
        "orthopedist"
    ],
    "wof:name":"Shaffer Benjamin S MD",
    "wof:placetype":"venue"
},
  "geometry": {"coordinates":[-77.086688,38.962279],"type":"Point"}
}