{
  "type": "Feature",
  "properties": {
    "iso:country":"US",
    "sg:address":"348 W Side Ave",
    "sg:city":"Hagerstown",
    "sg:classifiers":[
        {
            "category":"Banks & Credit Unions",
            "subcategory":"Investment Brokerage",
            "type":"Services"
        },
        {
            "category":"Insurance",
            "subcategory":"Hazard Insurance",
            "type":"Services"
        }
    ],
    "sg:phone":"+1 301 791 0620",
    "sg:postcode":"21740",
    "sg:province":"MD",
    "sg:tags":[
        "agent",
        "resume"
    ],
    "wof:name":"Darrell L Grove",
    "wof:placetype":"venue"
},
  "geometry": {"coordinates":[-77.729938,39.652171],"type":"Point"}
}