{
  "type": "Feature",
  "properties": {
    "addr:full":"460 Fair Meadows Blvd Hagerstown MD 21740",
    "addr:housenumber":"460",
    "addr:postcode":"21740",
    "addr:street":"Fair Meadows Blvd",
    "iso:country":"US",
    "sg:address":"460 Fair Meadows Blvd",
    "sg:city":"Hagerstown",
    "sg:classifiers":[
        {
            "category":"Wholesale",
            "subcategory":"Office Equipment",
            "type":"Manufacturing & Wholesale Goods"
        }
    ],
    "sg:phone":"+1 301 739 3534",
    "sg:postcode":"21740",
    "sg:province":"MD",
    "sg:tags":[
        "sales"
    ],
    "wof:name":"Cfp Office",
    "wof:placetype":"venue"
},
  "geometry": {"coordinates":[-77.675726,39.612386],"type":"Point"}
}