{
  "type": "Feature",
  "properties": {
    "iso:country":"US",
    "sg:address":"3390 Urbana Pike",
    "sg:city":"Frederick",
    "sg:classifiers":[
        {
            "category":"Insurance",
            "subcategory":"Hazard Insurance",
            "type":"Services"
        }
    ],
    "sg:phone":"+1 301 694 0030",
    "sg:postcode":"21704",
    "sg:province":"MD",
    "sg:tags":[
        "bond"
    ],
    "wof:name":"All Frederick 24 Hour Bail Bnd",
    "wof:placetype":"venue"
},
  "geometry": {"coordinates":[-77.345084,39.325858],"type":"Point"}
}