{
  "type": "Feature",
  "properties": {
    "iso:country":"US",
    "sg:address":"6475 Washington Blvd",
    "sg:city":"Elkridge",
    "sg:classifiers":[
        {
            "category":"Autos & Motor Vehicles",
            "subcategory":"Automobile Sales",
            "type":"Retail Goods"
        }
    ],
    "sg:phone":"+1 410 796 1006",
    "sg:postcode":"21075",
    "sg:province":"MD",
    "sg:tags":[
        "limo"
    ],
    "wof:name":"Miles Body Shop",
    "wof:placetype":"venue"
},
  "geometry": {"coordinates":[-76.731191,39.203577],"type":"Point"}
}