{
  "type": "Feature",
  "properties": {
    "iso:country":"US",
    "sg:address":"361 Dorchester Rd",
    "sg:city":"Stevensville",
    "sg:classifiers":[
        {
            "category":"Wholesale",
            "subcategory":"Jewelry",
            "type":"Manufacturing & Wholesale Goods"
        }
    ],
    "sg:phone":"+1 410 643 1423",
    "sg:postcode":"21666",
    "sg:province":"MD",
    "sg:tags":[
        "glass",
        "importer",
        "beads"
    ],
    "wof:name":"Bead More",
    "wof:placetype":"venue"
},
  "geometry": {"coordinates":[-76.338767,38.88865],"type":"Point"}
}