{
  "type": "Feature",
  "properties": {
    "iso:country":"US",
    "sg:address":"55 Derwood Cir",
    "sg:city":"Rockville",
    "sg:classifiers":[
        {
            "category":"Retail",
            "subcategory":"Auto Repair",
            "type":"Services"
        }
    ],
    "sg:phone":"+1 301 774 8174",
    "sg:postcode":"20850",
    "sg:province":"MD",
    "sg:tags":[
        "wrecker"
    ],
    "wof:name":"A & J Towing",
    "wof:placetype":"venue"
},
  "geometry": {"coordinates":[-77.150481,39.104926],"type":"Point"}
}