{
  "type": "Feature",
  "properties": {
    "iso:country":"US",
    "sg:address":"3211 Greenmount Ave",
    "sg:city":"Baltimore",
    "sg:classifiers":[
        {
            "category":"Shopping",
            "subcategory":"Shoes",
            "type":"Retail Goods"
        }
    ],
    "sg:phone":"+1 410 889 8661",
    "sg:postcode":"21218",
    "sg:province":"MD",
    "sg:tags":[
        "store"
    ],
    "wof:name":"Shoe City Sports",
    "wof:placetype":"venue"
},
  "geometry": {"coordinates":[-76.609497,39.327499],"type":"Point"}
}