{
  "type": "Feature",
  "properties": {
    "iso:country":"US",
    "sg:address":"21287 Garrett Hwy",
    "sg:city":"Oakland",
    "sg:classifiers":[
        {
            "category":"Building & Trades",
            "subcategory":"Construction",
            "type":"Services"
        }
    ],
    "sg:phone":"+1 301 387 9198",
    "sg:postcode":"21550",
    "sg:province":"MD",
    "sg:tags":[
        "contractor"
    ],
    "wof:name":"Don Nemith Builders",
    "wof:placetype":"venue"
},
  "geometry": {"coordinates":[-79.33255699999999,39.522338],"type":"Point"}
}