{
  "type": "Feature",
  "properties": {
    "addr:full":"40845 Merchants Ln Leonardtown MD 20650",
    "addr:housenumber":"40845",
    "addr:postcode":"20650",
    "addr:street":"Merchants Ln",
    "iso:country":"US",
    "sg:address":"40845 Merchants Ln",
    "sg:city":"Leonardtown",
    "sg:classifiers":[
        {
            "category":"Retail",
            "subcategory":"Laundry & Dry Cleaning",
            "type":"Services"
        }
    ],
    "sg:phone":"+1 301 475 7004",
    "sg:postcode":"20650",
    "sg:province":"MD",
    "sg:tags":[
        "cleaners"
    ],
    "wof:name":"Royal Cleaners",
    "wof:placetype":"venue"
},
  "geometry": {"coordinates":[-76.661292,38.306813],"type":"Point"}
}