{
  "type": "Feature",
  "properties": {
    "iso:country":"US",
    "sg:address":"6309 Kenwood Ave",
    "sg:city":"Rosedale",
    "sg:classifiers":[
        {
            "category":"Fast Food",
            "type":"Food & Drink"
        },
        {
            "category":"Restaurant",
            "type":"Food & Drink"
        },
        {
            "category":"Professional",
            "type":"Services"
        }
    ],
    "sg:phone":"+1 410 866 8080",
    "sg:postcode":"21237",
    "sg:province":"MD",
    "sg:tags":[
        "delivery",
        "take",
        "pizza"
    ],
    "sg:website":"http://www.dominospizza.com",
    "wof:name":"Domino's Pizza",
    "wof:placetype":"venue"
},
  "geometry": {"coordinates":[-76.505341,39.339439],"type":"Point"}
}