{
  "type": "Feature",
  "properties": {
    "addr:full":"5412 Queens Chapel Rd Hyattsville MD 20782",
    "addr:housenumber":"5412",
    "addr:postcode":"20782",
    "addr:street":"Queens Chapel Rd",
    "iso:country":"US",
    "sg:address":"5412 Queens Chapel Rd",
    "sg:city":"Hyattsville",
    "sg:classifiers":[
        {
            "category":"Shopping",
            "subcategory":"Bicycles & Sporting Goods",
            "type":"Retail Goods"
        }
    ],
    "sg:phone":"+1 301 559 5000",
    "sg:postcode":"20782",
    "sg:province":"MD",
    "sg:tags":[
        "apparel",
        "bowling",
        "accessory"
    ],
    "wof:name":"Twelve In A Row Pro Shop",
    "wof:placetype":"venue"
},
  "geometry": {"coordinates":[-76.961643,38.95627],"type":"Point"}
}