{
  "type": "Feature",
  "properties": {
    "iso:country":"US",
    "sg:address":"6126 Jefferson Pike",
    "sg:city":"Frederick",
    "sg:classifiers":[
        {
            "category":"Building & Trades",
            "subcategory":"Landscaping Services",
            "type":"Services"
        }
    ],
    "sg:phone":"+1 301 624 5525",
    "sg:postcode":"21703",
    "sg:province":"MD",
    "sg:tags":[
        "landscape",
        "contractor"
    ],
    "wof:name":"Creative Landscapes By Gregory",
    "wof:placetype":"venue"
},
  "geometry": {"coordinates":[-77.452514,39.399255],"type":"Point"}
}