{
  "type": "Feature",
  "properties": {
    "iso:country":"US",
    "sg:address":"29685 Vincent Cir",
    "sg:city":"Mechanicsville",
    "sg:classifiers":[
        {
            "category":"Farming",
            "subcategory":"Livestock Farm",
            "type":"Manufacturing & Wholesale Goods"
        }
    ],
    "sg:phone":"+1 301 843 2048",
    "sg:postcode":"20659",
    "sg:province":"MD",
    "sg:tags":[
        "breeder",
        "animal"
    ],
    "wof:name":"Lighthouse Shepherds",
    "wof:placetype":"venue"
},
  "geometry": {"coordinates":[-76.707897,38.486563],"type":"Point"}
}