{
  "type": "Feature",
  "properties": {
    "iso:country":"US",
    "sg:address":"1517 W Patrick St",
    "sg:city":"Frederick",
    "sg:classifiers":[
        {
            "category":"Building & Trades",
            "subcategory":"Electrical",
            "type":"Services"
        }
    ],
    "sg:phone":"+1 301 228 2396",
    "sg:postcode":"21702",
    "sg:province":"MD",
    "sg:tags":[
        "electric",
        "contractor"
    ],
    "wof:name":"IPW Svc",
    "wof:placetype":"venue"
},
  "geometry": {"coordinates":[-77.469449,39.423832],"type":"Point"}
}