{
  "type": "Feature",
  "properties": {
    "iso:country":"US",
    "sg:address":"1104 Taft St",
    "sg:city":"Rockville",
    "sg:classifiers":[
        {
            "category":"Retail",
            "subcategory":"Auto Repair",
            "type":"Services"
        }
    ],
    "sg:phone":"+1 301 610 9341",
    "sg:postcode":"20850",
    "sg:province":"MD",
    "sg:tags":[
        "repairing",
        "automobile",
        "radiator"
    ],
    "wof:name":"Cummins Public Svc Radiator Co",
    "wof:placetype":"venue"
},
  "geometry": {"coordinates":[-77.137185,39.094047],"type":"Point"}
}