{
  "type": "Feature",
  "properties": {
    "iso:country":"US",
    "sg:address":"1517 Ritchie Dr",
    "sg:city":"Arnold",
    "sg:classifiers":[
        {
            "category":"Health Services",
            "subcategory":"Doctor",
            "type":"Services"
        }
    ],
    "sg:phone":"+1 410 757 2200",
    "sg:postcode":"21037",
    "sg:province":"MD",
    "sg:tags":[
        "physician",
        "surgeon"
    ],
    "wof:name":"Annapolis Pediatrics",
    "wof:placetype":"venue"
},
  "geometry": {"coordinates":[-76.492445,38.887294],"type":"Point"}
}