{
  "type": "Feature",
  "properties": {
    "addr:full":"540 Baltimore Pike Bel Air MD 21014",
    "addr:housenumber":"540",
    "addr:postcode":"21014",
    "addr:street":"Baltimore Pike",
    "iso:country":"US",
    "sg:address":"540 Baltimore Pike",
    "sg:city":"Bel Air",
    "sg:classifiers":[
        {
            "category":"Shopping",
            "subcategory":"News",
            "type":"Retail Goods"
        }
    ],
    "sg:phone":"+1 410 879 1175",
    "sg:postcode":"21014",
    "sg:province":"MD",
    "sg:tags":[
        "magazine"
    ],
    "wof:name":"News Center",
    "wof:placetype":"venue"
},
  "geometry": {"coordinates":[-76.35498699999999,39.526064],"type":"Point"}
}