{
  "type": "Feature",
  "properties": {
    "addr:full":"2101 Brightseat Rd Hyattsville MD 20785",
    "addr:housenumber":"2101",
    "addr:postcode":"20785",
    "addr:street":"Brightseat Rd",
    "iso:country":"US",
    "sg:address":"2101 Brightseat Rd",
    "sg:city":"Hyattsville",
    "sg:classifiers":[
        {
            "category":"Retail",
            "subcategory":"Auto Rental",
            "type":"Services"
        }
    ],
    "sg:phone":"+1 301 322 7060",
    "sg:postcode":"20785",
    "sg:province":"MD",
    "sg:tags":[
        "car"
    ],
    "sg:website":"http://www.budgetrentacar.com",
    "wof:name":"Budget Rent A Car",
    "wof:placetype":"venue"
},
  "geometry": {"coordinates":[-76.859932,38.918919],"type":"Point"}
}