{
  "type": "Feature",
  "properties": {
    "iso:country":"US",
    "sg:address":"1005 Butterworth Ln",
    "sg:city":"Upper Marlboro",
    "sg:classifiers":[
        {
            "category":"Health Services",
            "subcategory":"Doctor",
            "type":"Services"
        }
    ],
    "sg:phone":"+1 301 249 8752",
    "sg:postcode":"20774",
    "sg:province":"MD",
    "wof:name":"Nelson Raymon K MD",
    "wof:placetype":"venue"
},
  "geometry": {"coordinates":[-76.83035,38.874593],"type":"Point"}
}