{
  "type": "Feature",
  "properties": {
    "iso:country":"US",
    "sg:address":"433 E Diamond Ave",
    "sg:city":"Gaithersburg",
    "sg:classifiers":[
        {
            "category":"Building & Trades",
            "subcategory":"Construction",
            "type":"Services"
        }
    ],
    "sg:phone":"+1 301 963 0331",
    "sg:postcode":"20877",
    "sg:province":"MD",
    "sg:tags":[
        "maker",
        "cabinet"
    ],
    "wof:name":"Ron Rae & Assoc",
    "wof:placetype":"venue"
},
  "geometry": {"coordinates":[-77.18726599999999,39.141825],"type":"Point"}
}