{
  "type": "Feature",
  "properties": {
    "iso:country":"US",
    "sg:address":"11300 Rockville Pike # 808",
    "sg:city":"Rockville",
    "sg:classifiers":[
        {
            "category":"Wholesale",
            "subcategory":"Medical Equipment & Supplies",
            "type":"Manufacturing & Wholesale Goods"
        },
        {
            "category":"Health Services",
            "subcategory":"Health Practitioner",
            "type":"Services"
        }
    ],
    "sg:phone":"+1 301 770 3231",
    "sg:postcode":"20852",
    "sg:province":"MD",
    "sg:tags":[
        "assistive",
        "device",
        "audiologists",
        "aid",
        "hearing"
    ],
    "wof:name":"Potomic Hearing Professionals",
    "wof:placetype":"venue"
},
  "geometry": {"coordinates":[-77.110162,39.041213],"type":"Point"}
}