{
  "type": "Feature",
  "properties": {
    "addr:full":"10013 Damascus Hill Ct Damascus MD 20872",
    "addr:housenumber":"10013",
    "addr:postcode":"20872",
    "addr:street":"Damascus Hill Ct",
    "iso:country":"US",
    "sg:address":"10013 Damascus Hill Ct",
    "sg:city":"Damascus",
    "sg:classifiers":[
        {
            "category":"Building & Trades",
            "subcategory":"Construction",
            "type":"Services"
        }
    ],
    "sg:phone":"+1 301 774 2191",
    "sg:postcode":"20872",
    "sg:province":"MD",
    "sg:tags":[
        "masonry",
        "contractor"
    ],
    "wof:name":"A & A Masonry Inc",
    "wof:placetype":"venue"
},
  "geometry": {"coordinates":[-77.209057,39.263273],"type":"Point"}
}