{
  "type": "Feature",
  "properties": {
    "iso:country":"US",
    "sg:address":"10010 Colesville Rd",
    "sg:city":"Silver Spring",
    "sg:classifiers":[
        {
            "category":"Professional",
            "subcategory":"Accounting & Tax Preparation",
            "type":"Services"
        }
    ],
    "sg:phone":"+1 301 754 2440",
    "sg:postcode":"20901",
    "sg:province":"MD",
    "sg:tags":[
        "accountant"
    ],
    "wof:name":"Kazim & Assoc",
    "wof:placetype":"venue"
},
  "geometry": {"coordinates":[-77.01358399999999,39.019527],"type":"Point"}
}