{
  "type": "Feature",
  "properties": {
    "addr:full":"31104 Zion Rd Salisbury MD 21804",
    "addr:housenumber":"31104",
    "addr:postcode":"21804",
    "addr:street":"Zion Rd",
    "iso:country":"US",
    "sg:address":"31104 Zion Rd",
    "sg:city":"Salisbury",
    "sg:classifiers":[
        {
            "category":"Organizations",
            "subcategory":"Religious Organization",
            "type":"Services"
        }
    ],
    "sg:phone":"+1 410 543 9491",
    "sg:postcode":"21804",
    "sg:province":"MD",
    "sg:tags":[
        "church"
    ],
    "wof:name":"Zion United Methodist Church",
    "wof:placetype":"venue"
},
  "geometry": {"coordinates":[-75.53017199999999,38.401163],"type":"Point"}
}