{
  "type": "Feature",
  "properties": {
    "iso:country":"US",
    "sg:address":"3838 Annadale Rd",
    "sg:city":"Baltimore",
    "sg:classifiers":[
        {
            "category":"Professional",
            "subcategory":"Business Services",
            "type":"Services"
        }
    ],
    "sg:phone":"+1 410 477 2256",
    "sg:postcode":"21222",
    "sg:province":"MD",
    "wof:name":"Karens Treasures",
    "wof:placetype":"venue"
},
  "geometry": {"coordinates":[-76.47435400000001,39.273928],"type":"Point"}
}