{
  "type": "Feature",
  "properties": {
    "iso:country":"US",
    "sg:address":"16621 Hampton Rd",
    "sg:city":"Williamsport",
    "sg:classifiers":[
        {
            "category":"Building & Trades",
            "subcategory":"Construction",
            "type":"Services"
        }
    ],
    "sg:phone":"+1 301 582 1090",
    "sg:postcode":"21795",
    "sg:province":"MD",
    "sg:tags":[
        "excavation",
        "contractor"
    ],
    "wof:name":"Keplinger's Excavating Inc",
    "wof:placetype":"venue"
},
  "geometry": {"coordinates":[-77.79284,39.61141],"type":"Point"}
}