{
  "type": "Feature",
  "properties": {
    "addr:full":"157 Westway Greenbelt MD 20770",
    "addr:housenumber":"157",
    "addr:postcode":"20770",
    "addr:street":"Westway",
    "iso:country":"US",
    "sg:address":"157 Westway",
    "sg:city":"Greenbelt",
    "sg:classifiers":[
        {
            "category":"Real Estate",
            "subcategory":"Real Estate Operator",
            "type":"Services"
        }
    ],
    "sg:phone":"+1 301 345 7778",
    "sg:postcode":"20770",
    "sg:province":"MD",
    "sg:tags":[
        "apartment"
    ],
    "sg:website":"www.lernerenterprises.com",
    "wof:name":"University Square Apts",
    "wof:placetype":"venue"
},
  "geometry": {"coordinates":[-76.884846,38.998654],"type":"Point"}
}