{
  "type": "Feature",
  "properties": {
    "iso:country":"US",
    "sg:address":"12113 Augusta Dr",
    "sg:city":"Glenn Dale",
    "sg:classifiers":[
        {
            "category":"Professional",
            "subcategory":"Business Services",
            "type":"Services"
        }
    ],
    "sg:phone":"+1 301 805 5676",
    "sg:postcode":"20769",
    "sg:province":"MD",
    "sg:tags":[
        "embroidery"
    ],
    "wof:name":"Hillmeade Embroidery",
    "wof:placetype":"venue"
},
  "geometry": {"coordinates":[-76.795121,38.985983],"type":"Point"}
}