{
  "type": "Feature",
  "properties": {
    "iso:country":"US",
    "sg:address":"11350 McCormick Ep 3 Rd",
    "sg:city":"Cockysvl Hnt Vly",
    "sg:classifiers":[
        {
            "category":"Professional",
            "subcategory":"Management & Consulting",
            "type":"Services"
        }
    ],
    "sg:phone":"+1 410 592 9707",
    "sg:postcode":"21031",
    "sg:province":"MD",
    "sg:tags":[
        "consultant",
        "educational"
    ],
    "sg:website":"www.trainingpro.com",
    "wof:name":"Trainingpro",
    "wof:placetype":"venue"
},
  "geometry": {"coordinates":[-76.659015,39.494913],"type":"Point"}
}