{
  "type": "Feature",
  "properties": {
    "iso:country":"US",
    "sg:address":"11317 Old Baltimore Pike",
    "sg:city":"Beltsville",
    "sg:classifiers":[
        {
            "category":"Retail",
            "subcategory":"Auto Repair",
            "type":"Services"
        }
    ],
    "sg:phone":"+1 301 937 7878",
    "sg:postcode":"20705",
    "sg:province":"MD",
    "sg:tags":[
        "machine",
        "automobile",
        "shop"
    ],
    "wof:name":"Auto Machine Shop",
    "wof:placetype":"venue"
},
  "geometry": {"coordinates":[-76.901438,39.038953],"type":"Point"}
}