{
  "type": "Feature",
  "properties": {
    "addr:full":"23886 Mervell Dean Rd Hollywood MD 20636",
    "addr:postcode":"23886;20636",
    "addr:street":"Mervell Dean Rd",
    "iso:country":"US",
    "sg:address":"23886 Mervell Dean Rd",
    "sg:city":"Hollywood",
    "sg:classifiers":[
        {
            "category":"Organizations",
            "subcategory":"Community Association",
            "type":"Services"
        }
    ],
    "sg:phone":"+1 301 373 3917",
    "sg:postcode":"20636",
    "sg:province":"MD",
    "sg:tags":[
        "club"
    ],
    "wof:name":"Loyal Order Of Moose",
    "wof:placetype":"venue"
},
  "geometry": {"coordinates":[-76.545376,38.322577],"type":"Point"}
}