{
  "type": "Feature",
  "properties": {
    "iso:country":"US",
    "sg:address":"1627 Eastern Ave",
    "sg:city":"Baltimore",
    "sg:classifiers":[
        {
            "category":"Professional",
            "type":"Services"
        }
    ],
    "sg:phone":"+1 410 534 5437",
    "sg:postcode":"21231",
    "sg:province":"MD",
    "sg:tags":[
        "establishment"
    ],
    "wof:name":"Jubilee Baltimore",
    "wof:placetype":"venue"
},
  "geometry": {"coordinates":[-76.593607,39.285501],"type":"Point"}
}