{
  "type": "Feature",
  "properties": {
    "iso:country":"US",
    "sg:address":"2419 Poplar Rd",
    "sg:city":"Essex",
    "sg:classifiers":[
        {
            "category":"Home & Garden",
            "subcategory":"Building Materials",
            "type":"Retail Goods"
        }
    ],
    "sg:phone":"+1 410 686 8614",
    "sg:postcode":"21221",
    "sg:province":"MD",
    "sg:tags":[
        "windows"
    ],
    "wof:name":"Poplar Construction Co",
    "wof:placetype":"venue"
},
  "geometry": {"coordinates":[-76.411039,39.283643],"type":"Point"}
}