{
  "type": "Feature",
  "properties": {
    "iso:country":"US",
    "sg:address":"14212 Brad Dr",
    "sg:city":"Rockville",
    "sg:classifiers":[
        {
            "category":"Social Services",
            "subcategory":"Adult Care",
            "type":"Services"
        }
    ],
    "sg:phone":"+1 301 871 8458",
    "sg:postcode":"20853",
    "sg:province":"MD",
    "sg:tags":[
        "home",
        "residential"
    ],
    "wof:name":"Serenity Assisted Living",
    "wof:placetype":"venue"
},
  "geometry": {"coordinates":[-77.093349,39.088351],"type":"Point"}
}