{
  "type": "Feature",
  "properties": {
    "addr:full":"8145 Baltimore Ave College Park MD 20740",
    "addr:housenumber":"8145",
    "addr:postcode":"20740",
    "addr:street":"Baltimore Ave",
    "iso:country":"US",
    "sg:address":"8145 Baltimore Ave",
    "sg:city":"College Park",
    "sg:classifiers":[
        {
            "category":"Restaurant",
            "type":"Food & Drink"
        }
    ],
    "sg:menulink":"http://www.allmenus.com/md/berwyn/18810-hanami-japanese-restaurant/menu/",
    "sg:phone":"+1 301 982 9899",
    "sg:postcode":"20740",
    "sg:province":"MD",
    "sg:tags":[
        "sushi",
        "japanese",
        "asian"
    ],
    "wof:name":"Hanami Japanese Restaurant",
    "wof:placetype":"venue"
},
  "geometry": {"coordinates":[-76.933632,38.991473],"type":"Point"}
}