{
  "type": "Feature",
  "properties": {
    "iso:country":"US",
    "sg:address":"7104 Loch Lomond Dr",
    "sg:city":"Bethesda",
    "sg:classifiers":[
        {
            "category":"Professional",
            "subcategory":"Lawyer & Legal Services",
            "type":"Services"
        }
    ],
    "sg:phone":"+1 301 229 6030",
    "sg:postcode":"20817",
    "sg:province":"MD",
    "wof:name":"Darneille Hopewell H III Atty",
    "wof:placetype":"venue"
},
  "geometry": {"coordinates":[-77.14830000000001,38.9814],"type":"Point"}
}