{
  "type": "Feature",
  "properties": {
    "iso:country":"US",
    "sg:address":"1200 N Salisbury Blvd",
    "sg:city":"Salisbury",
    "sg:classifiers":[
        {
            "category":"Autos & Motor Vehicles",
            "subcategory":"Automobile Sales",
            "type":"Retail Goods"
        }
    ],
    "sg:phone":"+1 410 543 8331",
    "sg:postcode":"21801",
    "sg:province":"MD",
    "sg:tags":[
        "car",
        "dealer"
    ],
    "wof:name":"First Choice Auto Sales",
    "wof:placetype":"venue"
},
  "geometry": {"coordinates":[-75.590683,38.378175],"type":"Point"}
}