{
  "type": "Feature",
  "properties": {
    "addr:full":"1137 Mermaid Dr Annapolis MD 21409",
    "addr:housenumber":"1137",
    "addr:postcode":"21409",
    "addr:street":"Mermaid Dr",
    "iso:country":"US",
    "sg:address":"1137 Mermaid Dr",
    "sg:city":"Annapolis",
    "sg:classifiers":[
        {
            "category":"Professional",
            "subcategory":"Art Services",
            "type":"Services"
        }
    ],
    "sg:phone":"+1 410 626 7799",
    "sg:postcode":"21409",
    "sg:province":"MD",
    "sg:tags":[
        "interior",
        "designer",
        "decorator"
    ],
    "wof:name":"P Sweet Specialties",
    "wof:placetype":"venue"
},
  "geometry": {"coordinates":[-76.453889,39.046495],"type":"Point"}
}