{
  "type": "Feature",
  "properties": {
    "addr:full":"7945 MacArthur Blvd Bethesda MD 20818",
    "addr:housenumber":"7945",
    "addr:postcode":"20818",
    "addr:street":"Macarthur Blvd",
    "iso:country":"US",
    "sg:address":"7945 MacArthur Blvd",
    "sg:city":"Bethesda",
    "sg:classifiers":[
        {
            "category":"Health Services",
            "subcategory":"Doctor",
            "type":"Services"
        }
    ],
    "sg:phone":"+1 301 229 1004",
    "sg:postcode":"20818",
    "sg:province":"MD",
    "sg:tags":[
        "psychiatrist"
    ],
    "wof:name":"Dworsky Lynn Staton MD",
    "wof:placetype":"venue"
},
  "geometry": {"coordinates":[-77.162831,38.974757],"type":"Point"}
}