{
  "type": "Feature",
  "properties": {
    "iso:country":"US",
    "sg:address":"13220 Falls Rd",
    "sg:city":"Cockeysville",
    "sg:classifiers":[
        {
            "category":"Organizations",
            "subcategory":"Membership Organization",
            "type":"Services"
        }
    ],
    "sg:phone":"+1 410 584 2644",
    "sg:postcode":"21030",
    "sg:province":"MD",
    "wof:name":"Trustees of Education Fun",
    "wof:placetype":"venue"
},
  "geometry": {"coordinates":[-76.707825,39.486756],"type":"Point"}
}