{
  "type": "Feature",
  "properties": {
    "iso:country":"US",
    "sg:address":"515 Apple Grove Rd",
    "sg:city":"Silver Spring",
    "sg:classifiers":[
        {
            "category":"Building & Trades",
            "subcategory":"Construction",
            "type":"Services"
        }
    ],
    "sg:phone":"+1 301 592 8681",
    "sg:postcode":"20904",
    "sg:province":"MD",
    "sg:tags":[
        "home",
        "builder",
        "contractor"
    ],
    "wof:name":"Eden Homes Inc",
    "wof:placetype":"venue"
},
  "geometry": {"coordinates":[-76.99870300000001,39.046398],"type":"Point"}
}