{
  "type": "Feature",
  "properties": {
    "addr:full":"10405 Montrose Ave Bethesda MD 20814",
    "addr:housenumber":"10405",
    "addr:postcode":"20814",
    "addr:street":"Montrose Ave",
    "iso:country":"US",
    "sg:address":"10405 Montrose Ave",
    "sg:city":"Bethesda",
    "sg:classifiers":[
        {
            "category":"Building & Trades",
            "subcategory":"Construction",
            "type":"Services"
        }
    ],
    "sg:phone":"+1 301 493 9534",
    "sg:postcode":"20814",
    "sg:province":"MD",
    "sg:tags":[
        "house"
    ],
    "wof:name":"Bellevue Homes",
    "wof:placetype":"venue"
},
  "geometry": {"coordinates":[-77.100567,39.025996],"type":"Point"}
}