{
  "type": "Feature",
  "properties": {
    "iso:country":"US",
    "sg:address":"850 W 36th St",
    "sg:city":"Baltimore",
    "sg:classifiers":[
        {
            "category":"Restaurant",
            "type":"Food & Drink"
        }
    ],
    "sg:phone":"+1 410 235 2915",
    "sg:postcode":"21211",
    "sg:province":"MD",
    "sg:tags":[
        "eating"
    ],
    "wof:name":"Roland Restaurant",
    "wof:placetype":"venue"
},
  "geometry": {"coordinates":[-76.63110399999999,39.331299],"type":"Point"}
}