{
  "type": "Feature",
  "properties": {
    "addr:full":"4504 Walsh St Ste 200 Chevy Chase MD 20815",
    "addr:housenumber":"4504",
    "addr:postcode":"20815",
    "addr:street":"Walsh St Ste 200",
    "iso:country":"US",
    "sg:address":"4504 Walsh St Ste 200",
    "sg:city":"Chevy Chase",
    "sg:classifiers":[
        {
            "category":"Professional",
            "subcategory":"Lawyer & Legal Services",
            "type":"Services"
        }
    ],
    "sg:phone":"+1 301 961 5300",
    "sg:postcode":"20815",
    "sg:province":"MD",
    "wof:name":"Tenenbaum & Saas PC",
    "wof:placetype":"venue"
},
  "geometry": {"coordinates":[-77.090597,38.979391],"type":"Point"}
}