{
  "type": "Feature",
  "properties": {
    "addr:full":"9603 Glen Way Fort Washington MD 20744",
    "addr:housenumber":"9603",
    "addr:postcode":"20744",
    "addr:street":"Glen Way",
    "iso:country":"US",
    "sg:address":"9603 Glen Way",
    "sg:city":"Fort Washington",
    "sg:classifiers":[
        {
            "category":"Retail",
            "subcategory":"Repair Shop",
            "type":"Services"
        }
    ],
    "sg:phone":"+1 301 248 0821",
    "sg:postcode":"20744",
    "sg:province":"MD",
    "wof:name":"Brawners Repair Company",
    "wof:placetype":"venue"
},
  "geometry": {"coordinates":[-76.961849,38.755589],"type":"Point"}
}