{
  "type": "Feature",
  "properties": {
    "iso:country":"US",
    "sg:address":"2053 E Monument St",
    "sg:city":"Baltimore",
    "sg:classifiers":[
        {
            "category":"Personal",
            "subcategory":"Shoe Repair & Shine",
            "type":"Services"
        }
    ],
    "sg:phone":"+1 410 732 4966",
    "sg:postcode":"21205",
    "sg:province":"MD",
    "wof:name":"Howard Shoe Service",
    "wof:placetype":"venue"
},
  "geometry": {"coordinates":[-76.588402,39.298801],"type":"Point"}
}