{
  "type": "Feature",
  "properties": {
    "addr:full":"510 Washington St Cambridge MD 21613",
    "addr:housenumber":"510",
    "addr:postcode":"21613",
    "addr:street":"Washington St",
    "iso:country":"US",
    "sg:address":"510 Washington St",
    "sg:city":"Cambridge",
    "sg:classifiers":[
        {
            "category":"Shopping",
            "type":"Retail Goods"
        }
    ],
    "sg:phone":"+1 410 228 8220",
    "sg:postcode":"21613",
    "sg:province":"MD",
    "sg:tags":[
        "monument"
    ],
    "wof:name":"Henry Funeral Home",
    "wof:placetype":"venue"
},
  "geometry": {"coordinates":[-76.07925400000001,38.563409],"type":"Point"}
}