{
  "type": "Feature",
  "properties": {
    "iso:country":"US",
    "sg:address":"1021 Dulaney Valley Rd",
    "sg:city":"Towson",
    "sg:classifiers":[
        {
            "category":"Banks & Credit Unions",
            "subcategory":"Financial Services",
            "type":"Services"
        },
        {
            "category":"Education",
            "subcategory":"Special Training",
            "type":"Public Place"
        },
        {
            "category":"Shopping",
            "subcategory":"Books",
            "type":"Retail Goods"
        },
        {
            "category":"Education",
            "subcategory":"University",
            "type":"Public Place"
        },
        {
            "category":"Education",
            "subcategory":"School",
            "type":"Public Place"
        }
    ],
    "sg:phone":"+1 410 337 6000",
    "sg:postcode":"21204",
    "sg:province":"MD",
    "sg:tags":[
        "college",
        "adult",
        "store",
        "scholarship"
    ],
    "sg:website":"http://www.bkstore.com",
    "wof:name":"Goucher College",
    "wof:placetype":"venue"
},
  "geometry": {"coordinates":[-76.600657,39.409404],"type":"Point"}
}