{
  "type": "Feature",
  "properties": {
    "iso:country":"US",
    "sg:address":"11 Friendship Rd",
    "sg:city":"Friendship",
    "sg:classifiers":[
        {
            "category":"Coffee & Tea",
            "type":"Food & Drink"
        },
        {
            "category":"Restaurant",
            "type":"Food & Drink"
        }
    ],
    "sg:phone":"+1 410 286 8799",
    "sg:postcode":"20758",
    "sg:province":"MD",
    "sg:tags":[
        "espresso"
    ],
    "wof:name":"Fabulous Brew Cafe",
    "wof:placetype":"venue"
},
  "geometry": {"coordinates":[-76.589043,38.736599],"type":"Point"}
}