{
  "type": "Feature",
  "properties": {
    "iso:country":"US",
    "sg:address":"97 Monocacy Blvd",
    "sg:city":"Frederick",
    "sg:classifiers":[
        {
            "category":"Professional",
            "type":"Services"
        }
    ],
    "sg:phone":"+1 301 815 5494",
    "sg:postcode":"21701",
    "sg:province":"MD",
    "sg:tags":[
        "establishment"
    ],
    "wof:name":"Infratech",
    "wof:placetype":"venue"
},
  "geometry": {"coordinates":[-77.388188,39.407565],"type":"Point"}
}