{
  "type": "Feature",
  "properties": {
    "iso:country":"US",
    "sg:address":"520 E South St",
    "sg:city":"Frederick",
    "sg:classifiers":[
        {
            "category":"Building & Trades",
            "subcategory":"Plumbing",
            "type":"Services"
        }
    ],
    "sg:phone":"+1 301 694 5340",
    "sg:postcode":"21701",
    "sg:province":"MD",
    "sg:tags":[
        "conditioning",
        "air",
        "system",
        "contractor"
    ],
    "wof:name":"Air Mechanical Systems",
    "wof:placetype":"venue"
},
  "geometry": {"coordinates":[-77.400535,39.408932],"type":"Point"}
}