{
  "type": "Feature",
  "properties": {
    "addr:full":"16176 Murphy Pl Hughesville MD 20637",
    "addr:housenumber":"16176",
    "addr:postcode":"20637",
    "addr:street":"Murphy Pl",
    "iso:country":"US",
    "sg:address":"16176 Murphy Pl",
    "sg:city":"Hughesville",
    "sg:classifiers":[
        {
            "category":"Building & Trades",
            "subcategory":"Construction",
            "type":"Services"
        }
    ],
    "sg:phone":"+1 301 645 3708",
    "sg:postcode":"20637",
    "sg:province":"MD",
    "sg:tags":[
        "contractor"
    ],
    "wof:name":"George H Murphy Construction",
    "wof:placetype":"venue"
},
  "geometry": {"coordinates":[-76.74688399999999,38.549712],"type":"Point"}
}