{
  "type": "Feature",
  "properties": {
    "addr:full":"175 Lazy Hollow Dr Gaithersburg MD 20878",
    "addr:housenumber":"175",
    "addr:postcode":"20878",
    "addr:street":"Lazy Hollow Dr",
    "iso:country":"US",
    "sg:address":"175 Lazy Hollow Dr",
    "sg:city":"Gaithersburg",
    "sg:classifiers":[
        {
            "category":"Professional",
            "type":"Services"
        }
    ],
    "sg:phone":"+1 301 548 0057",
    "sg:postcode":"20878",
    "sg:province":"MD",
    "sg:tags":[
        "establishment"
    ],
    "wof:name":"Gligorovic Reed",
    "wof:placetype":"venue"
},
  "geometry": {"coordinates":[-77.2189,39.111859],"type":"Point"}
}