{
  "type": "Feature",
  "properties": {
    "iso:country":"US",
    "sg:address":"12208 Morning Light Ter",
    "sg:city":"Gaithersburg",
    "sg:classifiers":[
        {
            "category":"Professional",
            "type":"Services"
        }
    ],
    "sg:phone":"+1 301 840 1889",
    "sg:postcode":"20878",
    "sg:province":"MD",
    "wof:name":"Herbert Rosen",
    "wof:placetype":"venue"
},
  "geometry": {"coordinates":[-77.251176,39.135364],"type":"Point"}
}