{
  "type": "Feature",
  "properties": {
    "addr:full":"1841 Shore Dr Annapolis MD 21401",
    "addr:housenumber":"1841",
    "addr:postcode":"21401",
    "addr:street":"Shore Dr",
    "iso:country":"US",
    "sg:address":"1841 Shore Dr",
    "sg:city":"Annapolis",
    "sg:classifiers":[
        {
            "category":"Building & Trades",
            "subcategory":"Construction",
            "type":"Services"
        }
    ],
    "sg:phone":"+1 410 224 2162",
    "sg:postcode":"21401",
    "sg:province":"MD",
    "sg:tags":[
        "repairing",
        "remodeling",
        "contractor"
    ],
    "wof:name":"Paragon Renovations",
    "wof:placetype":"venue"
},
  "geometry": {"coordinates":[-76.53379099999999,39.006181],"type":"Point"}
}