{
  "type": "Feature",
  "properties": {
    "iso:country":"US",
    "sg:address":"8703 Loch Bend Dr",
    "sg:city":"Baltimore",
    "sg:classifiers":[
        {
            "category":"Real Estate",
            "subcategory":"Real Estate Operator",
            "type":"Services"
        }
    ],
    "sg:phone":"+1 410 828 7000",
    "sg:postcode":"21234",
    "sg:province":"MD",
    "sg:tags":[
        "apartment"
    ],
    "wof:name":"Loch Bend Apartments",
    "wof:placetype":"venue"
},
  "geometry": {"coordinates":[-76.562977,39.39854],"type":"Point"}
}