{
  "type": "Feature",
  "properties": {
    "iso:country":"US",
    "sg:address":"350 Mountain Rd",
    "sg:city":"Pasadena",
    "sg:classifiers":[
        {
            "category":"Shopping",
            "subcategory":"Computers & Home Electronics",
            "type":"Retail Goods"
        }
    ],
    "sg:phone":"+1 410 255 1792",
    "sg:postcode":"21122",
    "sg:province":"MD",
    "sg:tags":[
        "equipment",
        "satellite",
        "system"
    ],
    "wof:name":"Dream Wireless",
    "wof:placetype":"venue"
},
  "geometry": {"coordinates":[-76.559,39.130597],"type":"Point"}
}