{
  "type": "Feature",
  "properties": {
    "iso:country":"US",
    "sg:address":"2305 Siena Way",
    "sg:city":"Woodstock",
    "sg:classifiers":[
        {
            "category":"Professional",
            "subcategory":"Art Services",
            "type":"Services"
        }
    ],
    "sg:phone":"+1 410 203 0008",
    "sg:postcode":"21163",
    "sg:province":"MD",
    "sg:tags":[
        "interior",
        "designer",
        "decorator"
    ],
    "wof:name":"Interiors Transformed",
    "wof:placetype":"venue"
},
  "geometry": {"coordinates":[-76.84496,39.32362],"type":"Point"}
}