{
  "type": "Feature",
  "properties": {
    "addr:full":"3603 Chestnut Ave Baltimore MD 21211",
    "addr:housenumber":"3603",
    "addr:postcode":"21211",
    "addr:street":"Chestnut Ave",
    "iso:country":"US",
    "sg:address":"3603 Chestnut Ave",
    "sg:city":"Baltimore",
    "sg:classifiers":[
        {
            "category":"Professional",
            "subcategory":"Lawyer & Legal Services",
            "type":"Services"
        }
    ],
    "sg:phone":"+1 410 889 8884",
    "sg:postcode":"21211",
    "sg:province":"MD",
    "sg:tags":[
        "attorney"
    ],
    "wof:name":"Edward R Jeunette Jr",
    "wof:placetype":"venue"
},
  "geometry": {"coordinates":[-76.62935299999999,39.331593],"type":"Point"}
}