{
  "type": "Feature",
  "properties": {
    "addr:full":"10507 Abingdon Way Woodstock MD 21163",
    "addr:housenumber":"10507",
    "addr:postcode":"21163",
    "addr:street":"Abingdon Way",
    "iso:country":"US",
    "sg:address":"10507 Abingdon Way",
    "sg:city":"Woodstock",
    "sg:classifiers":[
        {
            "category":"Social Services",
            "type":"Services"
        }
    ],
    "sg:phone":"+1 410 872 4758",
    "sg:postcode":"21163",
    "sg:province":"MD",
    "sg:tags":[
        "consultant",
        "security",
        "representative"
    ],
    "sg:website":"http://www.ssa.gov",
    "wof:name":"Social Security Administration",
    "wof:placetype":"venue"
},
  "geometry": {"coordinates":[-76.881547,39.308495],"type":"Point"}
}