{
  "type": "Feature",
  "properties": {
    "addr:full":"7945 Mac Arthur Blvd Bethesda MD 20817",
    "addr:housenumber":"7945",
    "addr:postcode":"20817",
    "addr:street":"Mac Arthur Blvd",
    "iso:country":"US",
    "sg:address":"7945 Mac Arthur Blvd",
    "sg:city":"Bethesda",
    "sg:classifiers":[
        {
            "category":"Building & Trades",
            "subcategory":"Locksmith",
            "type":"Services"
        }
    ],
    "sg:phone":"+1 240 383 5025",
    "sg:postcode":"20817",
    "sg:province":"MD",
    "sg:tags":[
        "key"
    ],
    "wof:name":"Locksmith",
    "wof:placetype":"venue"
},
  "geometry": {"coordinates":[-77.162852,38.974827],"type":"Point"}
}