{
  "type": "Feature",
  "properties": {
    "iso:country":"US",
    "sg:address":"12211 Valerie Ln",
    "sg:city":"Laurel",
    "sg:classifiers":[
        {
            "category":"Home & Garden",
            "subcategory":"Household Appliances",
            "type":"Retail Goods"
        },
        {
            "category":"Professional",
            "subcategory":"Detective & Security Services",
            "type":"Services"
        },
        {
            "category":"Manufacturing",
            "subcategory":"Aerospace",
            "type":"Manufacturing & Wholesale Goods"
        }
    ],
    "sg:phone":"+1 301 490 0239",
    "sg:postcode":"20708",
    "sg:province":"MD",
    "sg:tags":[
        "control",
        "industry",
        "monitoring",
        "thermostat",
        "system"
    ],
    "sg:website":"http://www51.honeywell.com",
    "wof:name":"Honeywell",
    "wof:placetype":"venue"
},
  "geometry": {"coordinates":[-76.848069,39.055774],"type":"Point"}
}