{
  "type": "Feature",
  "properties": {
    "iso:country":"US",
    "sg:address":"1635 Generals Hwy",
    "sg:city":"Annapolis",
    "sg:classifiers":[
        {
            "category":"Professional",
            "subcategory":"Business Services",
            "type":"Services"
        }
    ],
    "sg:phone":"+1 410 849 2111",
    "sg:postcode":"21401",
    "sg:province":"MD",
    "wof:name":"Lentz Enterprises Inc",
    "wof:placetype":"venue"
},
  "geometry": {"coordinates":[-76.575582,39.015089],"type":"Point"}
}