{
  "type": "Feature",
  "properties": {
    "iso:country":"US",
    "sg:address":"3811 Canterbury Rd",
    "sg:city":"Baltimore",
    "sg:classifiers":[
        {
            "category":"Retail",
            "subcategory":"Repair Shop",
            "type":"Services"
        }
    ],
    "sg:phone":"+1 410 889 5809",
    "sg:postcode":"21218",
    "sg:province":"MD",
    "sg:tags":[
        "repairing",
        "piano",
        "refinishing"
    ],
    "wof:name":"Atlantic Piano Svc",
    "wof:placetype":"venue"
},
  "geometry": {"coordinates":[-76.620408,39.335533],"type":"Point"}
}