{
  "type": "Feature",
  "properties": {
    "iso:country":"US",
    "sg:address":"901 Dulaney Valley Rd",
    "sg:city":"Baltimore",
    "sg:classifiers":[
        {
            "category":"Government",
            "subcategory":"Office",
            "type":"Public Place"
        },
        {
            "category":"Professional",
            "subcategory":"Employment Agencies",
            "type":"Services"
        }
    ],
    "sg:phone":"+1 410 887 4400",
    "sg:postcode":"21204",
    "sg:province":"MD",
    "sg:tags":[
        "economic",
        "program",
        "administration",
        "general"
    ],
    "wof:name":"Economic Dev- Employment",
    "wof:placetype":"venue"
},
  "geometry": {"coordinates":[-76.601204,39.406054],"type":"Point"}
}