{
  "type": "Feature",
  "properties": {
    "iso:country":"US",
    "sg:address":"612 Lafayette Ave",
    "sg:city":"Laurel",
    "sg:classifiers":[
        {
            "category":"Building & Trades",
            "subcategory":"Construction",
            "type":"Services"
        }
    ],
    "sg:phone":"+1 301 617 2570",
    "sg:postcode":"20707",
    "sg:province":"MD",
    "sg:tags":[
        "concrete",
        "contractor"
    ],
    "wof:name":"Cel Sue Construction Inc",
    "wof:placetype":"venue"
},
  "geometry": {"coordinates":[-76.846041,39.097295],"type":"Point"}
}