{
  "type": "Feature",
  "properties": {
    "iso:country":"US",
    "sg:address":"312 Railroad Ave",
    "sg:city":"Mardela Springs",
    "sg:classifiers":[
        {
            "category":"Professional",
            "subcategory":"Management & Consulting",
            "type":"Services"
        }
    ],
    "sg:phone":"+1 443 260 1659",
    "sg:postcode":"21837",
    "sg:province":"MD",
    "wof:name":"Synapse Mgmt Svc Inc",
    "wof:placetype":"venue"
},
  "geometry": {"coordinates":[-75.756407,38.461955],"type":"Point"}
}