{
  "type": "Feature",
  "properties": {
    "addr:full":"45156 First Colony Way Lexington Park MD 20653",
    "addr:housenumber":"45156",
    "addr:postcode":"20653",
    "addr:street":"First Colony Way",
    "iso:country":"US",
    "sg:address":"45156 First Colony Way",
    "sg:city":"Lexington Park",
    "sg:classifiers":[
        {
            "category":"Banks & Credit Unions",
            "subcategory":"Bank",
            "type":"Services"
        }
    ],
    "sg:phone":"+1 301 862 5696",
    "sg:postcode":"20653",
    "sg:province":"MD",
    "wof:name":"Suntrust Branch Locations California",
    "wof:placetype":"venue"
},
  "geometry": {"coordinates":[-76.459999,38.257099],"type":"Point"}
}