{
  "type": "Feature",
  "properties": {
    "iso:country":"US",
    "sg:address":"4401 E West Hwy",
    "sg:city":"Bethesda",
    "sg:classifiers":[
        {
            "category":"Professional",
            "subcategory":"Art Services",
            "type":"Services"
        }
    ],
    "sg:phone":"+1 301 986 8824",
    "sg:postcode":"20814",
    "sg:province":"MD",
    "sg:tags":[
        "arts",
        "graphic",
        "typesetting"
    ],
    "wof:name":"Letter Forms",
    "wof:placetype":"venue"
},
  "geometry": {"coordinates":[-77.091064,38.985046],"type":"Point"}
}