{
  "type": "Feature",
  "properties": {
    "iso:country":"US",
    "sg:address":"9123 Riggs Rd",
    "sg:city":"Adelphi",
    "sg:classifiers":[
        {
            "category":"Restaurant",
            "type":"Food & Drink"
        }
    ],
    "sg:phone":"+1 301 434 0100",
    "sg:postcode":"20783",
    "sg:province":"MD",
    "sg:tags":[
        "house",
        "steak",
        "mexican"
    ],
    "wof:name":"Los Antojitos",
    "wof:placetype":"venue"
},
  "geometry": {"coordinates":[-76.97087000000001,39.004642],"type":"Point"}
}