{
  "type": "Feature",
  "properties": {
    "addr:full":"65 Duke St Prince Frederick MD 20678",
    "addr:housenumber":"65",
    "addr:postcode":"20678",
    "addr:street":"Duke St",
    "iso:country":"US",
    "sg:address":"65 Duke St",
    "sg:city":"Prince Frederick",
    "sg:classifiers":[
        {
            "category":"Government",
            "subcategory":"Office",
            "type":"Public Place"
        }
    ],
    "sg:phone":"+1 410 535 1521",
    "sg:postcode":"20678",
    "sg:province":"MD",
    "sg:tags":[
        "federal"
    ],
    "wof:name":"Natural Resources Conservation",
    "wof:placetype":"venue"
},
  "geometry": {"coordinates":[-76.58483200000001,38.536308],"type":"Point"}
}