{
  "type": "Feature",
  "properties": {
    "addr:full":"8 Sebastian Ct Reisterstown MD 21136",
    "addr:housenumber":"8",
    "addr:postcode":"21136",
    "addr:street":"Sebastian Ct",
    "iso:country":"US",
    "sg:address":"8 Sebastian Ct",
    "sg:city":"Reisterstown",
    "sg:classifiers":[
        {
            "category":"Banks & Credit Unions",
            "subcategory":"Bank",
            "type":"Services"
        }
    ],
    "sg:phone":"+1 410 526 1824",
    "sg:postcode":"21136",
    "sg:province":"MD",
    "sg:tags":[
        "saving",
        "commercial"
    ],
    "wof:name":"Codwell Banker",
    "wof:placetype":"venue"
},
  "geometry": {"coordinates":[-76.806749,39.456275],"type":"Point"}
}