{
  "type": "Feature",
  "properties": {
    "iso:country":"US",
    "sg:address":"259 W Patrick St",
    "sg:city":"Frederick",
    "sg:classifiers":[
        {
            "category":"Building & Trades",
            "subcategory":"Construction",
            "type":"Services"
        }
    ],
    "sg:phone":"+1 301 620 7983",
    "sg:postcode":"21701",
    "sg:province":"MD",
    "sg:tags":[
        "contractor"
    ],
    "wof:name":"Allview Builder's Inc",
    "wof:placetype":"venue"
},
  "geometry": {"coordinates":[-77.41681199999999,39.413497],"type":"Point"}
}