{
  "type": "Feature",
  "properties": {
    "addr:full":"3714 Mary Ave Baltimore MD 21206",
    "addr:housenumber":"3714",
    "addr:postcode":"21206",
    "addr:street":"Mary Ave",
    "iso:country":"US",
    "sg:address":"3714 Mary Ave",
    "sg:city":"Baltimore",
    "sg:classifiers":[
        {
            "category":"Social Services",
            "subcategory":"Child Care",
            "type":"Services"
        }
    ],
    "sg:phone":"+1 443 835 3060",
    "sg:postcode":"21206",
    "sg:province":"MD",
    "sg:tags":[
        "nursery",
        "sitting",
        "consultant",
        "sitter",
        "baby",
        "day"
    ],
    "sg:website":"http://jacksonfamilydaycare.com",
    "wof:name":"Jackson Family Daycare",
    "wof:placetype":"venue"
},
  "geometry": {"coordinates":[-76.546949,39.348944],"type":"Point"}
}