{
  "type": "Feature",
  "properties": {
    "addr:full":"4 Executive Park Ct Germantown MD 20874",
    "addr:housenumber":"4",
    "addr:postcode":"20874",
    "addr:street":"Executive Park Ct",
    "iso:country":"US",
    "sg:address":"4 Executive Park Ct",
    "sg:city":"Germantown",
    "sg:classifiers":[
        {
            "category":"Health Services",
            "subcategory":"Doctor",
            "type":"Services"
        }
    ],
    "sg:phone":"+1 301 515 9160",
    "sg:postcode":"20874",
    "sg:province":"MD",
    "sg:tags":[
        "physician",
        "surgeon"
    ],
    "wof:name":"Sonia Rhoden Salmon MD",
    "wof:placetype":"venue"
},
  "geometry": {"coordinates":[-77.273864,39.181015],"type":"Point"}
}