{
  "type": "Feature",
  "properties": {
    "addr:full":"8802 Canberra Dr Clinton MD 20735",
    "addr:housenumber":"8802",
    "addr:postcode":"20735",
    "addr:street":"Canberra Dr",
    "iso:country":"US",
    "sg:address":"8802 Canberra Dr",
    "sg:city":"Clinton",
    "sg:classifiers":[
        {
            "category":"Manufacturing",
            "subcategory":"Furniture",
            "type":"Manufacturing & Wholesale Goods"
        }
    ],
    "sg:phone":"+1 301 868 4331",
    "sg:postcode":"20735",
    "sg:province":"MD",
    "sg:tags":[
        "install"
    ],
    "wof:name":"Instant Office Install",
    "wof:placetype":"venue"
},
  "geometry": {"coordinates":[-76.87396,38.768599],"type":"Point"}
}