{
  "type": "Feature",
  "properties": {
    "addr:full":"716 Melvin Ave Annapolis MD 21401",
    "addr:housenumber":"716",
    "addr:postcode":"21401",
    "addr:street":"Melvin Ave",
    "iso:country":"US",
    "sg:address":"716 Melvin Ave",
    "sg:city":"Annapolis",
    "sg:classifiers":[
        {
            "category":"Social Services",
            "type":"Services"
        }
    ],
    "sg:phone":"+1 410 268 2236",
    "sg:postcode":"21401",
    "sg:province":"MD",
    "sg:tags":[
        "counselor",
        "marriage",
        "family"
    ],
    "wof:name":"Mary Kent Norton",
    "wof:placetype":"venue"
},
  "geometry": {"coordinates":[-76.505309,38.989124],"type":"Point"}
}