{
  "type": "Feature",
  "properties": {
    "iso:country":"US",
    "sg:address":"W Friendship Neighborh",
    "sg:city":"Ellicott City",
    "sg:classifiers":[
        {
            "category":"Health Services",
            "subcategory":"Dentist",
            "type":"Services"
        }
    ],
    "sg:phone":"+1 410 442 1800",
    "sg:postcode":"21043",
    "sg:province":"MD",
    "sg:tags":[
        "orthodontist"
    ],
    "wof:name":"Lawyer Kevin R Dr Orthodntst",
    "wof:placetype":"venue"
},
  "geometry": {"coordinates":[-76.803596,39.2556],"type":"Point"}
}