{
  "type": "Feature",
  "properties": {
    "addr:full":"24508 McIntosh Rd Hollywood MD 20636",
    "addr:housenumber":"24508",
    "addr:postcode":"20636",
    "addr:street":"Mcintosh Rd",
    "iso:country":"US",
    "sg:address":"24508 McIntosh Rd",
    "sg:city":"Hollywood",
    "sg:classifiers":[
        {
            "category":"Building & Trades",
            "subcategory":"Cleaning & Sanitation",
            "type":"Services"
        }
    ],
    "sg:phone":"+1 301 475 9896",
    "sg:postcode":"20636",
    "sg:province":"MD",
    "sg:tags":[
        "maintenance"
    ],
    "wof:name":"Mickey Pro Cleaning Svs",
    "wof:placetype":"venue"
},
  "geometry": {"coordinates":[-76.631944,38.342944],"type":"Point"}
}