{
  "type": "Feature",
  "properties": {
    "addr:full":"21 North Eutaw Street Baltimore MD 21201",
    "addr:housenumber":"21",
    "addr:postcode":"21201",
    "addr:street":"North Eutaw Street",
    "iso:country":"US",
    "sg:address":"21 North Eutaw Street",
    "sg:city":"Baltimore",
    "sg:classifiers":[
        {
            "category":"Restaurant",
            "type":"Food & Drink"
        }
    ],
    "sg:phone":"+1 410 545 5112",
    "sg:postcode":"21201",
    "sg:province":"MD",
    "sg:tags":[
        "new",
        "american"
    ],
    "sg:website":"alewifebaltimore.com/",
    "wof:name":"Alewife",
    "wof:placetype":"venue"
},
  "geometry": {"coordinates":[-76.620723,39.290253],"type":"Point"}
}