{
  "type": "Feature",
  "properties": {
    "addr:full":"18811 Mink Hollow Rd Highland MD 20777",
    "addr:housenumber":"18811",
    "addr:postcode":"20777",
    "addr:street":"Mink Hollow Rd",
    "iso:country":"US",
    "sg:address":"18811 Mink Hollow Rd",
    "sg:city":"Highland",
    "sg:classifiers":[
        {
            "category":"Professional",
            "subcategory":"Engineering",
            "type":"Services"
        }
    ],
    "sg:phone":"+1 301 570 1786",
    "sg:postcode":"20777",
    "sg:province":"MD",
    "sg:tags":[
        "consulting",
        "engineer"
    ],
    "wof:name":"Bauer Environmental Consultants",
    "wof:placetype":"venue"
},
  "geometry": {"coordinates":[-76.998901,39.165589],"type":"Point"}
}