{
  "type": "Feature",
  "properties": {
    "iso:country":"US",
    "sg:address":"8200 Liberty Rd",
    "sg:city":"Baltimore",
    "sg:classifiers":[
        {
            "category":"Autos & Motor Vehicles",
            "subcategory":"Fuel & Gas Station",
            "type":"Retail Goods"
        }
    ],
    "sg:phone":"+1 410 922 6931",
    "sg:postcode":"21244",
    "sg:province":"MD",
    "sg:tags":[
        "oil"
    ],
    "wof:name":"Rockdale Shell",
    "wof:placetype":"venue"
},
  "geometry": {"coordinates":[-76.76391,39.355774],"type":"Point"}
}