{
  "type": "Feature",
  "properties": {
    "addr:full":"21926 Leitersburg Smithsburg Rd Smithsburg MD 21783",
    "addr:housenumber":"21926",
    "addr:postcode":"21783",
    "addr:street":"Leitersburg Smithsburg Rd",
    "iso:country":"US",
    "sg:address":"21926 Leitersburg Smithsburg Rd",
    "sg:city":"Smithsburg",
    "sg:classifiers":[
        {
            "category":"Retail",
            "subcategory":"Repair Shop",
            "type":"Services"
        }
    ],
    "sg:phone":"+1 301 739 1789",
    "sg:postcode":"21783",
    "sg:province":"MD",
    "sg:tags":[
        "water",
        "equipment",
        "softening"
    ],
    "wof:name":"Mr Softee Water Conditioning",
    "wof:placetype":"venue"
},
  "geometry": {"coordinates":[-77.603393,39.675826],"type":"Point"}
}