{
  "type": "Feature",
  "properties": {
    "iso:country":"US",
    "sg:address":"723 Braeside Rd",
    "sg:city":"Baltimore",
    "sg:classifiers":[
        {
            "category":"Manufacturing",
            "subcategory":"Tools & Machinery",
            "type":"Manufacturing & Wholesale Goods"
        },
        {
            "category":"Wholesale",
            "subcategory":"Electrical",
            "type":"Manufacturing & Wholesale Goods"
        },
        {
            "category":"Building & Trades",
            "subcategory":"Electrical",
            "type":"Services"
        }
    ],
    "sg:phone":"+1 410 788 0280",
    "sg:postcode":"21229",
    "sg:province":"MD",
    "sg:tags":[
        "industrial",
        "electrician",
        "electric",
        "supply",
        "equipment",
        "contractors-commercial",
        "supplies-wholesale",
        "manufacturer"
    ],
    "wof:name":"Anytime Electrical Maintenance Inc.",
    "wof:placetype":"venue"
},
  "geometry": {"coordinates":[-76.712835,39.289097],"type":"Point"}
}