{
  "type": "Feature",
  "properties": {
    "iso:country":"US",
    "sg:address":"5360 Quincy Pl",
    "sg:city":"Hyattsville",
    "sg:classifiers":[
        {
            "category":"Real Estate",
            "subcategory":"Real Estate Operator",
            "type":"Services"
        }
    ],
    "sg:phone":"+1 301 927 3721",
    "sg:postcode":"20784",
    "sg:province":"MD",
    "sg:tags":[
        "apartment"
    ],
    "wof:name":"Sawyer Realty Holding",
    "wof:placetype":"venue"
},
  "geometry": {"coordinates":[-76.926985,38.937858],"type":"Point"}
}