{
  "type": "Feature",
  "properties": {
    "addr:full":"9429 Loch Leven Ct Laurel MD 20723",
    "addr:housenumber":"9429",
    "addr:postcode":"20723",
    "addr:street":"Loch Leven Ct",
    "iso:country":"US",
    "sg:address":"9429 Loch Leven Ct",
    "sg:city":"Laurel",
    "sg:classifiers":[
        {
            "category":"Organizations",
            "subcategory":"Religious Organization",
            "type":"Services"
        }
    ],
    "sg:phone":"+1 410 880 1958",
    "sg:postcode":"20723",
    "sg:province":"MD",
    "sg:tags":[
        "clergy"
    ],
    "wof:name":"Gordon Young",
    "wof:placetype":"venue"
},
  "geometry": {"coordinates":[-76.834571,39.130293],"type":"Point"}
}