{
  "type": "Feature",
  "properties": {
    "iso:country":"US",
    "sg:address":"315 River Rd",
    "sg:city":"Elkton",
    "sg:classifiers":[
        {
            "category":"Organizations",
            "subcategory":"Religious Organization",
            "type":"Services"
        }
    ],
    "sg:phone":"+1 410 398 4218",
    "sg:postcode":"21921",
    "sg:province":"MD",
    "sg:tags":[
        "counseling"
    ],
    "wof:name":"Tom Berry",
    "wof:placetype":"venue"
},
  "geometry": {"coordinates":[-75.847342,39.562533],"type":"Point"}
}