{
  "type": "Feature",
  "properties": {
    "iso:country":"US",
    "sg:address":"8600 16th St",
    "sg:city":"Silver Spring",
    "sg:classifiers":[
        {
            "category":"Banks & Credit Unions",
            "subcategory":"Investment Brokerage",
            "type":"Services"
        }
    ],
    "sg:phone":"+1 301 656 6776",
    "sg:postcode":"20910",
    "sg:province":"MD",
    "sg:tags":[
        "advisory",
        "financial"
    ],
    "wof:name":"Financial Management Solutions",
    "wof:placetype":"venue"
},
  "geometry": {"coordinates":[-77.039886,38.999595],"type":"Point"}
}