{
  "type": "Feature",
  "properties": {
    "addr:full":"12610 Grey Eagle Ct Germantown MD 20874",
    "addr:housenumber":"12610",
    "addr:postcode":"20874",
    "addr:street":"Grey;Ct",
    "iso:country":"US",
    "sg:address":"12610 Grey Eagle Ct",
    "sg:city":"Germantown",
    "sg:classifiers":[
        {
            "category":"Shopping",
            "subcategory":"Clothing, Apparel, & Fashions",
            "type":"Retail Goods"
        }
    ],
    "sg:phone":"+1 301 972 5530",
    "sg:postcode":"20874",
    "sg:province":"MD",
    "sg:tags":[
        "accessory"
    ],
    "wof:name":"Fashion Wraps",
    "wof:placetype":"venue"
},
  "geometry": {"coordinates":[-77.26133900000001,39.166937],"type":"Point"}
}