{
  "type": "Feature",
  "properties": {
    "addr:full":"18310 Bluebell Ln Olney MD 20832",
    "addr:housenumber":"18310",
    "addr:postcode":"20832",
    "addr:street":"Bluebell Ln",
    "iso:country":"US",
    "sg:address":"18310 Bluebell Ln",
    "sg:city":"Olney",
    "sg:classifiers":[
        {
            "category":"Professional",
            "subcategory":"Management & Consulting",
            "type":"Services"
        }
    ],
    "sg:phone":"+1 301 570 2060",
    "sg:postcode":"20832",
    "sg:province":"MD",
    "sg:tags":[
        "marketing",
        "program"
    ],
    "wof:name":"Warner Marketing & Comm",
    "wof:placetype":"venue"
},
  "geometry": {"coordinates":[-77.10111000000001,39.156123],"type":"Point"}
}