{
  "type": "Feature",
  "properties": {
    "addr:full":"926 York Rd Baltimore MD 21204",
    "addr:housenumber":"926",
    "addr:postcode":"21204",
    "addr:street":"York Rd",
    "iso:country":"US",
    "sg:address":"926 York Rd",
    "sg:city":"Baltimore",
    "sg:classifiers":[
        {
            "category":"Autos & Motor Vehicles",
            "subcategory":"Automobile Sales",
            "type":"Retail Goods"
        }
    ],
    "sg:phone":"+1 410 823 3131",
    "sg:postcode":"21204",
    "sg:province":"MD",
    "sg:tags":[
        "car",
        "dealer"
    ],
    "sg:website":"www.towsonfordsales.com",
    "wof:name":"Towson Ford",
    "wof:placetype":"venue"
},
  "geometry": {"coordinates":[-76.607512,39.407533],"type":"Point"}
}