{
  "type": "Feature",
  "properties": {
    "iso:country":"US",
    "sg:address":"1819 East West Hwy",
    "sg:city":"Hyattsville",
    "sg:classifiers":[
        {
            "category":"Restaurant",
            "type":"Food & Drink"
        }
    ],
    "sg:menulink":"http://www.allmenus.com/md/chillum/284475-seven-star-restaurant/menu/",
    "sg:phone":"+1 301 422 2288",
    "sg:postcode":"20783",
    "sg:province":"MD",
    "sg:tags":[
        "american",
        "asian",
        "chinese"
    ],
    "wof:name":"Seven Star Restaurant",
    "wof:placetype":"venue"
},
  "geometry": {"coordinates":[-76.980789,38.972619],"type":"Point"}
}