{
  "type": "Feature",
  "properties": {
    "addr:full":"4105 W Cold Spring Ln Baltimore MD 21215",
    "addr:housenumber":"4105",
    "addr:postcode":"21215",
    "addr:street":"W Cold Spring Ln",
    "iso:country":"US",
    "sg:address":"4105 W Cold Spring Ln",
    "sg:city":"Baltimore",
    "sg:classifiers":[
        {
            "category":"Retail",
            "subcategory":"Auto Repair",
            "type":"Services"
        }
    ],
    "sg:phone":"+1 410 578 4311",
    "sg:postcode":"21215",
    "sg:province":"MD",
    "wof:name":"Automotive Wabash",
    "wof:placetype":"venue"
},
  "geometry": {"coordinates":[-76.687111,39.334836],"type":"Point"}
}