{
  "type": "Feature",
  "properties": {
    "addr:full":"362 Reservoir Rd Perryville MD 21903",
    "addr:housenumber":"362",
    "addr:postcode":"21903",
    "addr:street":"Reservoir Rd",
    "iso:country":"US",
    "sg:address":"362 Reservoir Rd",
    "sg:city":"Perryville",
    "sg:classifiers":[
        {
            "category":"Freight",
            "type":"Transportation"
        }
    ],
    "sg:phone":"+1 410 378 3437",
    "sg:postcode":"21903",
    "sg:province":"MD",
    "sg:tags":[
        "operator",
        "local",
        "trucking"
    ],
    "wof:name":"J Sumpter Trucking",
    "wof:placetype":"venue"
},
  "geometry": {"coordinates":[-76.049819,39.585993],"type":"Point"}
}