{
  "type": "Feature",
  "properties": {
    "addr:full":"5430 Grosvenor Ln Bethesda MD 20814",
    "addr:housenumber":"5430",
    "addr:postcode":"20814",
    "addr:street":"Grosvenor Ln",
    "iso:country":"US",
    "sg:address":"5430 Grosvenor Ln",
    "sg:city":"Bethesda",
    "sg:classifiers":[
        {
            "category":"Social Services",
            "subcategory":"Adult Care",
            "type":"Services"
        }
    ],
    "sg:phone":"+1 301 493 6000",
    "sg:postcode":"20814",
    "sg:province":"MD",
    "sg:tags":[
        "home",
        "residential"
    ],
    "wof:name":"Victory Housing Inc",
    "wof:placetype":"venue"
},
  "geometry": {"coordinates":[-77.10752100000001,39.022576],"type":"Point"}
}