{
  "type": "Feature",
  "properties": {
    "iso:country":"US",
    "sg:address":"24219 Ridge Rd",
    "sg:city":"Damascus",
    "sg:classifiers":[
        {
            "category":"Shopping",
            "subcategory":"Used Merchandise",
            "type":"Retail Goods"
        }
    ],
    "sg:phone":"+1 301 253 6980",
    "sg:postcode":"20872",
    "sg:province":"MD",
    "sg:tags":[
        "antique"
    ],
    "wof:name":"Appleby's Antiques",
    "wof:placetype":"venue"
},
  "geometry": {"coordinates":[-77.22966599999999,39.253223],"type":"Point"}
}