{
  "type": "Feature",
  "properties": {
    "addr:full":"1708 Philadelphia Rd Joppa MD 21085",
    "addr:housenumber":"1708",
    "addr:postcode":"21085",
    "addr:street":"Philadelphia Rd",
    "iso:country":"US",
    "sg:address":"1708 Philadelphia Rd",
    "sg:city":"Joppa",
    "sg:classifiers":[
        {
            "category":"Shopping",
            "subcategory":"Pharmacy",
            "type":"Retail Goods"
        }
    ],
    "sg:phone":"+1 410 538 6610",
    "sg:postcode":"21085",
    "sg:province":"MD",
    "sg:tags":[
        "aid",
        "first",
        "supply"
    ],
    "wof:name":"Bay State Safety & Training",
    "wof:placetype":"venue"
},
  "geometry": {"coordinates":[-76.32301,39.440855],"type":"Point"}
}