{
  "type": "Feature",
  "properties": {
    "addr:full":"7810 Cryden Way Forestville MD 20747",
    "addr:housenumber":"7810",
    "addr:postcode":"20747",
    "addr:street":"Cryden Way",
    "iso:country":"US",
    "sg:address":"7810 Cryden Way",
    "sg:city":"Forestville",
    "sg:classifiers":[
        {
            "category":"Wholesale",
            "subcategory":"Vending Machines",
            "type":"Manufacturing & Wholesale Goods"
        }
    ],
    "sg:phone":"+1 301 568 0478",
    "sg:postcode":"20747",
    "sg:province":"MD",
    "wof:name":"VAP Inc",
    "wof:placetype":"venue"
},
  "geometry": {"coordinates":[-76.87021300000001,38.847306],"type":"Point"}
}