{
  "type": "Feature",
  "properties": {
    "addr:full":"2322 Montgomery St Silver Spring MD 20910",
    "addr:housenumber":"2322",
    "addr:postcode":"20910",
    "addr:street":"Montgomery St",
    "iso:country":"US",
    "sg:address":"2322 Montgomery St",
    "sg:city":"Silver Spring",
    "sg:classifiers":[
        {
            "category":"Building & Trades",
            "subcategory":"Construction",
            "type":"Services"
        }
    ],
    "sg:phone":"+1 301 608 0818",
    "sg:postcode":"20910",
    "sg:province":"MD",
    "sg:tags":[
        "marble",
        "terrazzo"
    ],
    "wof:name":"Elegant Floor Svc Inc",
    "wof:placetype":"venue"
},
  "geometry": {"coordinates":[-77.050783,39.007781],"type":"Point"}
}