{
  "type": "Feature",
  "properties": {
    "addr:full":"9215 Limestone Pl College Park MD 20740",
    "addr:housenumber":"9215",
    "addr:postcode":"20740",
    "addr:street":"Limestone Pl",
    "iso:country":"US",
    "sg:address":"9215 Limestone Pl",
    "sg:city":"College Park",
    "sg:classifiers":[
        {
            "category":"Retail",
            "subcategory":"Laundry & Dry Cleaning",
            "type":"Services"
        }
    ],
    "sg:phone":"+1 301 935 5920",
    "sg:postcode":"20740",
    "sg:province":"MD",
    "sg:tags":[
        "cleaners",
        "rug",
        "carpet"
    ],
    "wof:name":"R Faulkner Carpet Cleaning Svc",
    "wof:placetype":"venue"
},
  "geometry": {"coordinates":[-76.946681,39.007744],"type":"Point"}
}