{
  "type": "Feature",
  "properties": {
    "addr:full":"3410 Greenmount Ave Baltimore MD 21218",
    "addr:housenumber":"3410",
    "addr:postcode":"21218",
    "addr:street":"Greenmount Ave",
    "iso:country":"US",
    "sg:address":"3410 Greenmount Ave",
    "sg:city":"Baltimore",
    "sg:classifiers":[
        {
            "category":"Personal",
            "subcategory":"Shoe Repair & Shine",
            "type":"Services"
        }
    ],
    "sg:phone":"+1 410 467 2834",
    "sg:postcode":"21218",
    "sg:province":"MD",
    "wof:name":"Hack's Shoe Repair",
    "wof:placetype":"venue"
},
  "geometry": {"coordinates":[-76.60929899999999,39.330299],"type":"Point"}
}