{
  "type": "Feature",
  "properties": {
    "iso:country":"US",
    "sg:address":"1255 Crummell Ave",
    "sg:city":"Annapolis",
    "sg:classifiers":[
        {
            "category":"Professional",
            "subcategory":"Research",
            "type":"Services"
        }
    ],
    "sg:phone":"+1 301 497 5875",
    "sg:postcode":"21403",
    "sg:province":"MD",
    "wof:name":"Tracy Plunderleith",
    "wof:placetype":"venue"
},
  "geometry": {"coordinates":[-76.47005799999999,38.934246],"type":"Point"}
}