{
  "type": "Feature",
  "properties": {
    "addr:full":"200 Shipping Creek Dr Stevensville MD 21666",
    "addr:housenumber":"200",
    "addr:postcode":"21666",
    "addr:street":"Shipping Creek Dr",
    "iso:country":"US",
    "sg:address":"200 Shipping Creek Dr",
    "sg:city":"Stevensville",
    "sg:classifiers":[
        {
            "category":"Professional",
            "type":"Services"
        }
    ],
    "sg:phone":"+1 410 643 7374",
    "sg:postcode":"21666",
    "sg:province":"MD",
    "sg:tags":[
        "establishment"
    ],
    "wof:name":"DFE Inc",
    "wof:placetype":"venue"
},
  "geometry": {"coordinates":[-76.33985699999999,38.923601],"type":"Point"}
}