{
  "type": "Feature",
  "properties": {
    "iso:country":"US",
    "sg:address":"910 Kimberly Way",
    "sg:city":"Stevensville",
    "sg:classifiers":[
        {
            "category":"Professional",
            "subcategory":"Computer Services",
            "type":"Services"
        }
    ],
    "sg:phone":"+1 410 643 3567",
    "sg:postcode":"21666",
    "sg:province":"MD",
    "sg:tags":[
        "consulting",
        "solution"
    ],
    "wof:name":"Lcm Technology Solutions Inc",
    "wof:placetype":"venue"
},
  "geometry": {"coordinates":[-76.30193300000001,39.005315],"type":"Point"}
}