{
  "type": "Feature",
  "properties": {
    "iso:country":"US",
    "sg:address":"128 Bryans Channel Way",
    "sg:city":"Queenstown",
    "sg:classifiers":[
        {
            "category":"Insurance",
            "subcategory":"Hazard Insurance",
            "type":"Services"
        }
    ],
    "sg:phone":"+1 410 827 5421",
    "sg:postcode":"21658",
    "sg:province":"MD",
    "sg:tags":[
        "commercial",
        "business"
    ],
    "wof:name":"Lawrence L Feehely Jr Insur",
    "wof:placetype":"venue"
},
  "geometry": {"coordinates":[-76.164907,38.96574],"type":"Point"}
}