{
  "type": "Feature",
  "properties": {
    "addr:full":"19 Hanover Rd Reisterstown MD 21136",
    "addr:housenumber":"19",
    "addr:postcode":"21136",
    "addr:street":"Hanover Rd",
    "iso:country":"US",
    "sg:address":"19 Hanover Rd",
    "sg:city":"Reisterstown",
    "sg:classifiers":[
        {
            "category":"Building & Trades",
            "subcategory":"Construction",
            "type":"Services"
        }
    ],
    "sg:phone":"+1 410 526 0778",
    "sg:postcode":"21136",
    "sg:province":"MD",
    "sg:tags":[
        "installs",
        "retail",
        "carpet"
    ],
    "wof:name":"Carpet Guy The",
    "wof:placetype":"venue"
},
  "geometry": {"coordinates":[-76.829457,39.472526],"type":"Point"}
}