{
  "type": "Feature",
  "properties": {
    "addr:full":"3011 Dunbrin Rd Dundalk MD 21222",
    "addr:housenumber":"3011",
    "addr:postcode":"21222",
    "addr:street":"Dunbrin Rd",
    "iso:country":"US",
    "sg:address":"3011 Dunbrin Rd",
    "sg:city":"Dundalk",
    "sg:classifiers":[
        {
            "category":"Building & Trades",
            "subcategory":"Cleaning & Sanitation",
            "type":"Services"
        }
    ],
    "sg:phone":"+1 410 282 8063",
    "sg:postcode":"21222",
    "sg:province":"MD",
    "sg:tags":[
        "carpet"
    ],
    "sg:website":"www.diamondpointinc.com",
    "wof:name":"Diamond Point Carpet & Upholstery Cleaning",
    "wof:placetype":"venue"
},
  "geometry": {"coordinates":[-76.517534,39.25577],"type":"Point"}
}