{
  "type": "Feature",
  "properties": {
    "addr:full":"7525 Greenway Center Dr Greenbelt MD 20770",
    "addr:housenumber":"7525",
    "addr:postcode":"20770",
    "addr:street":"Greenway Center Dr",
    "iso:country":"US",
    "sg:address":"7525 Greenway Center Dr",
    "sg:city":"Greenbelt",
    "sg:classifiers":[
        {
            "category":"Health Services",
            "subcategory":"Doctor",
            "type":"Services"
        }
    ],
    "sg:phone":"+1 301 474 4347",
    "sg:postcode":"20770",
    "sg:province":"MD",
    "sg:tags":[
        "physician",
        "surgeon"
    ],
    "wof:name":"Jessica Ratra MD",
    "wof:placetype":"venue"
},
  "geometry": {"coordinates":[-76.87950600000001,38.991578],"type":"Point"}
}