{
  "type": "Feature",
  "properties": {
    "addr:full":"45106 Nalley Rd Hollywood MD 20636",
    "addr:postcode":"45106;20636",
    "addr:street":"Nalley Rd",
    "iso:country":"US",
    "sg:address":"45106 Nalley Rd",
    "sg:city":"Hollywood",
    "sg:classifiers":[
        {
            "category":"Shopping",
            "type":"Retail Goods"
        }
    ],
    "sg:phone":"+1 301 373 3007",
    "sg:postcode":"20636",
    "sg:province":"MD",
    "sg:tags":[
        "coin",
        "dealer",
        "merchandise",
        "supply"
    ],
    "wof:name":"Parron Coin Company",
    "wof:placetype":"venue"
},
  "geometry": {"coordinates":[-76.51933099999999,38.324275],"type":"Point"}
}