{
  "type": "Feature",
  "properties": {
    "addr:full":"9322 Pardoe Rd Lusby MD 20657",
    "addr:housenumber":"9322",
    "addr:postcode":"20657",
    "addr:street":"Pardoe Rd",
    "iso:country":"US",
    "sg:address":"9322 Pardoe Rd",
    "sg:city":"Lusby",
    "sg:classifiers":[
        {
            "category":"Building & Trades",
            "subcategory":"Plumbing",
            "type":"Services"
        }
    ],
    "sg:phone":"+1 410 326 1810",
    "sg:postcode":"20657",
    "sg:province":"MD",
    "sg:tags":[
        "conditioning",
        "air",
        "system",
        "contractor"
    ],
    "wof:name":"Leitch Heating & Air",
    "wof:placetype":"venue"
},
  "geometry": {"coordinates":[-76.455934,38.410928],"type":"Point"}
}