{
  "type": "Feature",
  "properties": {
    "iso:country":"US",
    "sg:address":"7606 Old Alexandria Ferry Rd",
    "sg:city":"Clinton",
    "sg:classifiers":[
        {
            "category":"Building & Trades",
            "subcategory":"Construction",
            "type":"Services"
        }
    ],
    "sg:phone":"+1 301 868 5222",
    "sg:postcode":"20735",
    "sg:province":"MD",
    "sg:tags":[
        "tile",
        "dealer"
    ],
    "wof:name":"G & W Floor Covering Inc",
    "wof:placetype":"venue"
},
  "geometry": {"coordinates":[-76.875532,38.780305],"type":"Point"}
}