{
  "type": "Feature",
  "properties": {
    "addr:full":"889 Clopper Rd Gaithersburg MD 20878",
    "addr:housenumber":"889",
    "addr:postcode":"20878",
    "addr:street":"Clopper Rd",
    "iso:country":"US",
    "sg:address":"889 Clopper Rd",
    "sg:city":"Gaithersburg",
    "sg:classifiers":[
        {
            "category":"Building & Trades",
            "subcategory":"Construction",
            "type":"Services"
        }
    ],
    "sg:phone":"+1 301 987 0040",
    "sg:postcode":"20878",
    "sg:province":"MD",
    "sg:tags":[
        "roofing",
        "contractor"
    ],
    "wof:name":"2 Brothers Roofing & Paving",
    "wof:placetype":"venue"
},
  "geometry": {"coordinates":[-77.22447099999999,39.143849],"type":"Point"}
}