{
  "type": "Feature",
  "properties": {
    "addr:full":"8822 Tamar Dr Columbia MD 21045",
    "addr:housenumber":"8822",
    "addr:postcode":"21045",
    "addr:street":"Tamar Dr",
    "iso:country":"US",
    "sg:address":"8822 Tamar Dr",
    "sg:city":"Columbia",
    "sg:classifiers":[
        {
            "category":"Communications",
            "subcategory":"Television Station",
            "type":"Services"
        }
    ],
    "sg:phone":"+1 410 715 1532",
    "sg:postcode":"21045",
    "sg:province":"MD",
    "sg:tags":[
        "broadcasting"
    ],
    "wof:name":"Kia N Johnson",
    "wof:placetype":"venue"
},
  "geometry": {"coordinates":[-76.813951,39.207757],"type":"Point"}
}