{
  "type": "Feature",
  "properties": {
    "iso:country":"US",
    "sg:address":"284 N Frederick Ave",
    "sg:city":"Gaithersburg",
    "sg:classifiers":[
        {
            "category":"Restaurant",
            "type":"Food & Drink"
        },
        {
            "category":"Donuts",
            "subcategory":"None",
            "type":"Food & Drink"
        }
    ],
    "sg:phone":"+1 301 926 3853",
    "sg:postcode":"20877",
    "sg:province":"MD",
    "sg:tags":[
        "shop"
    ],
    "wof:name":"Montgmry Donut&Ice Cream",
    "wof:placetype":"venue"
},
  "geometry": {"coordinates":[-77.20223799999999,39.144473],"type":"Point"}
}