{
  "type": "Feature",
  "properties": {
    "iso:country":"US",
    "sg:address":"55 E Padonia Rd",
    "sg:city":"Timonium",
    "sg:classifiers":[
        {
            "category":"Shopping",
            "subcategory":"Used Merchandise",
            "type":"Retail Goods"
        }
    ],
    "sg:phone":"+1 410 667 6897",
    "sg:postcode":"21093",
    "sg:province":"MD",
    "sg:tags":[
        "book",
        "rare",
        "dealer"
    ],
    "wof:name":"Book Rack",
    "wof:placetype":"venue"
},
  "geometry": {"coordinates":[-76.631506,39.456386],"type":"Point"}
}