{
  "type": "Feature",
  "properties": {
    "iso:country":"US",
    "sg:address":"12804 Lost Lake Cir",
    "sg:city":"Fort Washington",
    "sg:classifiers":[
        {
            "category":"Professional",
            "subcategory":"Business Services",
            "type":"Services"
        }
    ],
    "sg:phone":"+1 301 292 9411",
    "sg:postcode":"20744",
    "sg:province":"MD",
    "wof:name":"Executive Cyber Services",
    "wof:placetype":"venue"
},
  "geometry": {"coordinates":[-77.013345,38.714428],"type":"Point"}
}