{
  "type": "Feature",
  "properties": {
    "addr:full":"20011 Tanbark Way Brinklow MD 20862",
    "addr:housenumber":"20011",
    "addr:postcode":"20862",
    "addr:street":"Tanbark Way",
    "iso:country":"US",
    "sg:address":"20011 Tanbark Way",
    "sg:city":"Brinklow",
    "sg:classifiers":[
        {
            "category":"Professional",
            "subcategory":"Accounting & Tax Preparation",
            "type":"Services"
        }
    ],
    "sg:phone":"+1 301 570 2064",
    "sg:postcode":"20862",
    "sg:province":"MD",
    "sg:tags":[
        "bookkeeping",
        "return"
    ],
    "wof:name":"B&B Accounting & Tax Serv",
    "wof:placetype":"venue"
},
  "geometry": {"coordinates":[-77.018401,39.185599],"type":"Point"}
}