{
  "type": "Feature",
  "properties": {
    "addr:full":"1128 Halesworth Dr Potomac MD 20854",
    "addr:housenumber":"1128",
    "addr:postcode":"20854",
    "addr:street":"Halesworth Dr",
    "iso:country":"US",
    "sg:address":"1128 Halesworth Dr",
    "sg:city":"Potomac",
    "sg:classifiers":[
        {
            "category":"Education",
            "subcategory":"Special Training",
            "type":"Public Place"
        }
    ],
    "sg:phone":"+1 301 309 1386",
    "sg:postcode":"20854",
    "sg:province":"MD",
    "sg:tags":[
        "teacher",
        "french"
    ],
    "wof:name":"Omanda-Nambomboza Eulalie",
    "wof:placetype":"venue"
},
  "geometry": {"coordinates":[-77.164208,39.065676],"type":"Point"}
}