{
  "type": "Feature",
  "properties": {
    "iso:country":"US",
    "sg:address":"8250 Beechcraft Ave",
    "sg:city":"Gaithersburg",
    "sg:classifiers":[
        {
            "category":"Wholesale",
            "subcategory":"Machinery & Supplies",
            "type":"Manufacturing & Wholesale Goods"
        }
    ],
    "sg:phone":"+1 301 840 9300",
    "sg:postcode":"20879",
    "sg:province":"MD",
    "sg:tags":[
        "contractor"
    ],
    "wof:name":"Metro Rentals Inc",
    "wof:placetype":"venue"
},
  "geometry": {"coordinates":[-77.168814,39.167053],"type":"Point"}
}