{
  "type": "Feature",
  "properties": {
    "addr:full":"3331 Corridor Marketplace Laurel MD 20724",
    "addr:housenumber":"3331",
    "addr:postcode":"20724",
    "addr:street":"Corridor Marketplace",
    "iso:country":"US",
    "sg:address":"3331 Corridor Marketplace",
    "sg:city":"Laurel",
    "sg:classifiers":[
        {
            "category":"Food & Beverages",
            "subcategory":"Groceries & Convenience Stores",
            "type":"Retail Goods"
        }
    ],
    "sg:phone":"+1 301 483 8030",
    "sg:postcode":"20724",
    "sg:province":"MD",
    "sg:tags":[
        "grocer"
    ],
    "sg:website":"www.weismarkets.com",
    "wof:name":"WEIS Markets Inc",
    "wof:placetype":"venue"
},
  "geometry": {"coordinates":[-76.80638399999999,39.097611],"type":"Point"}
}