{
  "type": "Feature",
  "properties": {
    "iso:country":"US",
    "sg:address":"19803 Cool Hollow Rd",
    "sg:city":"Hagerstown",
    "sg:classifiers":[
        {
            "category":"Real Estate",
            "subcategory":"Developer",
            "type":"Services"
        }
    ],
    "sg:phone":"+1 301 797 4447",
    "sg:postcode":"21740",
    "sg:province":"MD",
    "wof:name":"Churchey Group",
    "wof:placetype":"venue"
},
  "geometry": {"coordinates":[-77.682326,39.571629],"type":"Point"}
}