{
  "type": "Feature",
  "properties": {
    "iso:country":"US",
    "sg:address":"425 E Federal St",
    "sg:city":"Baltimore",
    "sg:classifiers":[
        {
            "category":"Social Services",
            "type":"Services"
        }
    ],
    "sg:phone":"+1 410 396 3552",
    "sg:postcode":"21202",
    "sg:province":"MD",
    "sg:tags":[
        "senior",
        "citizen"
    ],
    "sg:website":"www.gcenter.cjb.net",
    "wof:name":"Green Mount Senior Ctr",
    "wof:placetype":"venue"
},
  "geometry": {"coordinates":[-76.610482,39.307846],"type":"Point"}
}