{
  "type": "Feature",
  "properties": {
    "addr:full":"47 Richardson Ave Crisfield MD 21817",
    "addr:housenumber":"47",
    "addr:postcode":"21817",
    "addr:street":"Richardson Ave",
    "iso:country":"US",
    "sg:address":"47 Richardson Ave",
    "sg:city":"Crisfield",
    "sg:classifiers":[
        {
            "category":"Retail",
            "subcategory":"Car Wash",
            "type":"Services"
        }
    ],
    "sg:phone":"+1 410 968 1961",
    "sg:postcode":"21817",
    "sg:province":"MD",
    "sg:tags":[
        "polishing",
        "washing"
    ],
    "wof:name":"Crisfield Car Wash",
    "wof:placetype":"venue"
},
  "geometry": {"coordinates":[-75.845958,37.989527],"type":"Point"}
}