{
  "type": "Feature",
  "properties": {
    "iso:country":"US",
    "sg:address":"201 N Warwick Ave",
    "sg:city":"Baltimore",
    "sg:classifiers":[
        {
            "category":"Professional",
            "subcategory":"Management & Consulting",
            "type":"Services"
        }
    ],
    "sg:phone":"+1 301 333 3123",
    "sg:postcode":"21223",
    "sg:province":"MD",
    "sg:tags":[
        "consultant",
        "planning",
        "space",
        "facility"
    ],
    "wof:name":"Community Bridge",
    "wof:placetype":"venue"
},
  "geometry": {"coordinates":[-76.65572400000001,39.29026],"type":"Point"}
}