{
  "type": "Feature",
  "properties": {
    "iso:country":"US",
    "sg:address":"211 N 12th St",
    "sg:city":"Oakland",
    "sg:classifiers":[
        {
            "category":"Professional",
            "subcategory":"Business Services",
            "type":"Services"
        }
    ],
    "sg:phone":"+1 301 334 2768",
    "sg:postcode":"21550",
    "sg:province":"MD",
    "sg:tags":[
        "auction"
    ],
    "wof:name":"Dever & Company Inc",
    "wof:placetype":"venue"
},
  "geometry": {"coordinates":[-79.38740300000001,39.40867],"type":"Point"}
}