{
  "type": "Feature",
  "properties": {
    "iso:country":"US",
    "sg:address":"18615 Bay Leaf Way",
    "sg:city":"Germantown",
    "sg:classifiers":[
        {
            "category":"Freight",
            "type":"Transportation"
        }
    ],
    "sg:phone":"+1 301 672 6071",
    "sg:postcode":"20874",
    "sg:province":"MD",
    "sg:tags":[
        "local",
        "trucking"
    ],
    "wof:name":"Brads Moving And Storage",
    "wof:placetype":"venue"
},
  "geometry": {"coordinates":[-77.263605,39.160242],"type":"Point"}
}