{
  "type": "Feature",
  "properties": {
    "iso:country":"US",
    "sg:address":"421 W Saratoga St",
    "sg:city":"Baltimore",
    "sg:classifiers":[
        {
            "category":"Personal",
            "subcategory":"Barber",
            "type":"Services"
        }
    ],
    "sg:phone":"+1 410 244 3009",
    "sg:postcode":"21201",
    "sg:province":"MD",
    "wof:name":"Balitmore's Celebrity Cuts Barbershop",
    "wof:placetype":"venue"
},
  "geometry": {"coordinates":[-76.621878,39.292788],"type":"Point"}
}