{
  "type": "Feature",
  "properties": {
    "addr:full":"2930 James St Baltimore MD 21230",
    "addr:housenumber":"2930",
    "addr:postcode":"21230",
    "addr:street":"James St",
    "iso:country":"US",
    "sg:address":"2930 James St",
    "sg:city":"Baltimore",
    "sg:classifiers":[
        {
            "category":"Retail",
            "subcategory":"Auto Repair",
            "type":"Services"
        }
    ],
    "sg:phone":"+1 410 644 1320",
    "sg:postcode":"21230",
    "sg:province":"MD",
    "sg:tags":[
        "brake"
    ],
    "wof:name":"Wareheim Air Brakes Shop",
    "wof:placetype":"venue"
},
  "geometry": {"coordinates":[-76.66077199999999,39.261204],"type":"Point"}
}