{
  "type": "Feature",
  "properties": {
    "iso:country":"US",
    "sg:address":"9 E Church St",
    "sg:city":"Frederick",
    "sg:classifiers":[
        {
            "category":"Restaurant",
            "type":"Food & Drink"
        }
    ],
    "sg:phone":"+1 301 620 0077",
    "sg:postcode":"21701",
    "sg:province":"MD",
    "sg:tags":[
        "delicatessen"
    ],
    "wof:name":"Vignola Market LLC",
    "wof:placetype":"venue"
},
  "geometry": {"coordinates":[-77.410718,39.415429],"type":"Point"}
}