{
  "type": "Feature",
  "properties": {
    "addr:full":"2712 Crystal Ln Baldwin MD 21013",
    "addr:housenumber":"2712",
    "addr:postcode":"21013",
    "addr:street":"Crystal Ln",
    "iso:country":"US",
    "sg:address":"2712 Crystal Ln",
    "sg:city":"Baldwin",
    "sg:classifiers":[
        {
            "category":"Building & Trades",
            "subcategory":"Landscaping Services",
            "type":"Services"
        }
    ],
    "sg:phone":"+1 410 557 9013",
    "sg:postcode":"21013",
    "sg:province":"MD",
    "sg:tags":[
        "landscape"
    ],
    "wof:name":"Quiet Carviers Landscaping",
    "wof:placetype":"venue"
},
  "geometry": {"coordinates":[-76.489951,39.533077],"type":"Point"}
}