{
  "type": "Feature",
  "properties": {
    "addr:full":"5200 Sunnyside Ave Beltsville MD 20705",
    "addr:housenumber":"5200",
    "addr:postcode":"20705",
    "addr:street":"Sunnyside Ave",
    "iso:country":"US",
    "sg:address":"5200 Sunnyside Ave",
    "sg:city":"Beltsville",
    "sg:classifiers":[
        {
            "category":"Home & Garden",
            "subcategory":"Furniture",
            "type":"Retail Goods"
        }
    ],
    "sg:phone":"+1 301 595 7300",
    "sg:postcode":"20705",
    "sg:province":"MD",
    "sg:tags":[
        "cabinet"
    ],
    "sg:website":"www.kitchensbyckd.com",
    "wof:name":"Kitchen & Bath Warehouse",
    "wof:placetype":"venue"
},
  "geometry": {"coordinates":[-76.91482999999999,39.024505],"type":"Point"}
}