{
  "type": "Feature",
  "properties": {
    "addr:full":"14703 Dunwood Valley Dr Bowie MD 20721",
    "addr:housenumber":"14703",
    "addr:postcode":"20721",
    "addr:street":"Dunwood Valley Dr",
    "iso:country":"US",
    "sg:address":"14703 Dunwood Valley Dr",
    "sg:city":"Bowie",
    "sg:classifiers":[
        {
            "category":"Personal",
            "type":"Services"
        },
        {
            "category":"Professional",
            "subcategory":"Art Services",
            "type":"Services"
        }
    ],
    "sg:phone":"+1 301 390 2355",
    "sg:postcode":"20721",
    "sg:province":"MD",
    "sg:tags":[
        "photography",
        "videography",
        "wedding"
    ],
    "wof:name":"Tq Photographs",
    "wof:placetype":"venue"
},
  "geometry": {"coordinates":[-76.754842,38.929293],"type":"Point"}
}