{
  "type": "Feature",
  "properties": {
    "addr:full":"24 E Roberts St Cumberland MD 21502",
    "addr:housenumber":"24",
    "addr:postcode":"21502",
    "addr:street":"E Roberts St",
    "iso:country":"US",
    "sg:address":"24 E Roberts St",
    "sg:city":"Cumberland",
    "sg:classifiers":[
        {
            "category":"Retail",
            "subcategory":"Auto Repair",
            "type":"Services"
        }
    ],
    "sg:phone":"+1 301 759 9023",
    "sg:postcode":"21502",
    "sg:province":"MD",
    "sg:tags":[
        "body",
        "automobile",
        "painting",
        "repairing"
    ],
    "wof:name":"T & B Body Shop",
    "wof:placetype":"venue"
},
  "geometry": {"coordinates":[-78.76934300000001,39.624649],"type":"Point"}
}