{
  "type": "Feature",
  "properties": {
    "addr:full":"5 6th St Pocomoke City MD 21851",
    "addr:housenumber":"5",
    "addr:postcode":"21851",
    "addr:street":"6Th St",
    "iso:country":"US",
    "sg:address":"5 6th St",
    "sg:city":"Pocomoke City",
    "sg:classifiers":[
        {
            "category":"Retail",
            "subcategory":"Car Wash",
            "type":"Services"
        }
    ],
    "sg:phone":"+1 410 957 2422",
    "sg:postcode":"21851",
    "sg:province":"MD",
    "sg:tags":[
        "polishing",
        "washing"
    ],
    "wof:name":"Pocomoke City Car Wash",
    "wof:placetype":"venue"
},
  "geometry": {"coordinates":[-75.560249,38.075164],"type":"Point"}
}