{
  "type": "Feature",
  "properties": {
    "iso:country":"US",
    "sg:address":"14212 Pear Tree Ln",
    "sg:city":"Silver Spring",
    "sg:classifiers":[
        {
            "category":"Banks & Credit Unions",
            "subcategory":"Investment Brokerage",
            "type":"Services"
        }
    ],
    "sg:phone":"+1 301 529 7736",
    "sg:postcode":"20906",
    "sg:province":"MD",
    "sg:tags":[
        "advisory",
        "financial"
    ],
    "wof:name":"Infinity FSI Corp",
    "wof:placetype":"venue"
},
  "geometry": {"coordinates":[-77.068999,39.090432],"type":"Point"}
}