{
  "type": "Feature",
  "properties": {
    "addr:full":"8030 Main St Ste 34 Ellicott City MD 21043",
    "addr:housenumber":"8030",
    "addr:postcode":"21043",
    "addr:street":"Main St Ste 34",
    "iso:country":"US",
    "sg:address":"8030 Main St Ste 34",
    "sg:city":"Ellicott City",
    "sg:classifiers":[
        {
            "category":"Arts & Performance",
            "subcategory":"Arts Center",
            "type":"Entertainment"
        }
    ],
    "sg:phone":"+1 410 265 6782",
    "sg:postcode":"21043",
    "sg:province":"MD",
    "sg:tags":[
        "performing"
    ],
    "wof:name":"Elifrey Caribbean School",
    "wof:placetype":"venue"
},
  "geometry": {"coordinates":[-76.79517800000001,39.267885],"type":"Point"}
}