{
  "type": "Feature",
  "properties": {
    "addr:full":"3401 Perry St Mt Rainier MD 20712",
    "addr:housenumber":"3401",
    "addr:postcode":"20712",
    "addr:street":"Perry St",
    "iso:country":"US",
    "sg:address":"3401 Perry St",
    "sg:city":"Mt Rainier",
    "sg:classifiers":[
        {
            "category":"Organizations",
            "subcategory":"Religious Organization",
            "type":"Services"
        }
    ],
    "sg:phone":"+1 301 927 1110",
    "sg:postcode":"20712",
    "sg:province":"MD",
    "sg:tags":[
        "church"
    ],
    "wof:name":"Remnant Worship Ctr",
    "wof:placetype":"venue"
},
  "geometry": {"coordinates":[-76.95977999999999,38.936355],"type":"Point"}
}