{
  "type": "Feature",
  "properties": {
    "iso:country":"US",
    "sg:address":"1622 Aliceanna St",
    "sg:city":"Baltimore",
    "sg:classifiers":[
        {
            "category":"Personal",
            "subcategory":"Beauty Salon",
            "type":"Services"
        }
    ],
    "sg:phone":"+1 410 675 1622",
    "sg:postcode":"21231",
    "sg:province":"MD",
    "sg:tags":[
        "hair"
    ],
    "wof:name":"Studio 1622",
    "wof:placetype":"venue"
},
  "geometry": {"coordinates":[-76.59426999999999,39.283684],"type":"Point"}
}