{
  "type": "Feature",
  "properties": {
    "iso:country":"US",
    "sg:address":"3930 Knowles Ave",
    "sg:city":"Kensington",
    "sg:classifiers":[
        {
            "category":"Professional",
            "subcategory":"Accounting & Tax Preparation",
            "type":"Services"
        }
    ],
    "sg:phone":"+1 301 942 9030",
    "sg:postcode":"20895",
    "sg:province":"MD",
    "wof:name":"David W McGraw",
    "wof:placetype":"venue"
},
  "geometry": {"coordinates":[-77.077692,39.027567],"type":"Point"}
}