{
  "type": "Feature",
  "properties": {
    "iso:country":"US",
    "sg:address":"571 Kevins Dr",
    "sg:city":"Arnold",
    "sg:classifiers":[
        {
            "category":"Building & Trades",
            "subcategory":"Landscaping Services",
            "type":"Services"
        }
    ],
    "sg:phone":"+1 410 349 3800",
    "sg:postcode":"21012",
    "sg:province":"MD",
    "sg:tags":[
        "consultant",
        "designer",
        "landscape"
    ],
    "wof:name":"1st Choice Services",
    "wof:placetype":"venue"
},
  "geometry": {"coordinates":[-76.477583,39.048878],"type":"Point"}
}