{
  "type": "Feature",
  "properties": {
    "addr:full":"330 Vierling Dr Silver Spring MD 20904",
    "addr:housenumber":"330",
    "addr:postcode":"20904",
    "addr:street":"Vierling Dr",
    "iso:country":"US",
    "sg:address":"330 Vierling Dr",
    "sg:city":"Silver Spring",
    "sg:classifiers":[
        {
            "category":"Building & Trades",
            "subcategory":"Construction",
            "type":"Services"
        }
    ],
    "sg:phone":"+1 301 879 5160",
    "sg:postcode":"20904",
    "sg:province":"MD",
    "sg:tags":[
        "general",
        "contractor"
    ],
    "wof:name":"NVM",
    "wof:placetype":"venue"
},
  "geometry": {"coordinates":[-77.01671899999999,39.082248],"type":"Point"}
}