{
  "type": "Feature",
  "properties": {
    "iso:country":"US",
    "sg:address":"3900 Liberty Heights Ave",
    "sg:city":"Baltimore",
    "sg:classifiers":[
        {
            "category":"Organizations",
            "subcategory":"Religious Organization",
            "type":"Services"
        }
    ],
    "sg:phone":"+1 410 542 0355",
    "sg:postcode":"21207",
    "sg:province":"MD",
    "sg:tags":[
        "church"
    ],
    "wof:name":"St Mark's United Methodist Chr",
    "wof:placetype":"venue"
},
  "geometry": {"coordinates":[-76.685248,39.328195],"type":"Point"}
}