{
  "type": "Feature",
  "properties": {
    "iso:country":"US",
    "sg:address":"8956 Tilghman Island Rd",
    "sg:city":"Wittman",
    "sg:classifiers":[
        {
            "category":"Travel",
            "subcategory":"Hotels & Motels",
            "type":"Entertainment"
        }
    ],
    "sg:phone":"+1 410 745 2892",
    "sg:postcode":"21676",
    "sg:province":"MD",
    "sg:tags":[
        "breakfast",
        "accommodation",
        "bed"
    ],
    "sg:website":"www.watermarkinn.com",
    "wof:name":"Watermark Bed & Breakfast",
    "wof:placetype":"venue"
},
  "geometry": {"coordinates":[-76.303952,38.799666],"type":"Point"}
}