{
  "type": "Feature",
  "properties": {
    "iso:country":"US",
    "sg:address":"5219 Buckeystown Pike",
    "sg:city":"Frederick",
    "sg:classifiers":[
        {
            "category":"Bakery",
            "type":"Food & Drink"
        }
    ],
    "sg:phone":"+1 240 426 7988",
    "sg:postcode":"21704",
    "sg:province":"MD",
    "wof:name":"G & T Pastries",
    "wof:placetype":"venue"
},
  "geometry": {"coordinates":[-77.41045800000001,39.37356],"type":"Point"}
}