{
  "type": "Feature",
  "properties": {
    "addr:full":"121 Cathedral St Annapolis MD 21401",
    "addr:housenumber":"121",
    "addr:postcode":"21401",
    "addr:street":"Cathedral St",
    "iso:country":"US",
    "sg:address":"121 Cathedral St",
    "sg:city":"Annapolis",
    "sg:classifiers":[
        {
            "category":"Insurance",
            "subcategory":"Insurance Agent",
            "type":"Services"
        }
    ],
    "sg:phone":"+1 410 263 8201",
    "sg:postcode":"21401",
    "sg:province":"MD",
    "sg:tags":[
        "consultant"
    ],
    "sg:website":"www.firstcommand.com",
    "wof:name":"First Command Financial Plan",
    "wof:placetype":"venue"
},
  "geometry": {"coordinates":[-76.495581,38.97804],"type":"Point"}
}