{
  "type": "Feature",
  "properties": {
    "addr:full":"7110 Golden Ring Rd Essex MD 21221",
    "addr:housenumber":"7110",
    "addr:postcode":"21221",
    "addr:street":"Golden Ring Rd",
    "iso:country":"US",
    "sg:address":"7110 Golden Ring Rd",
    "sg:city":"Essex",
    "sg:classifiers":[
        {
            "category":"Retail",
            "subcategory":"Laundry & Dry Cleaning",
            "type":"Services"
        }
    ],
    "sg:phone":"+1 410 893 3393",
    "sg:postcode":"21221",
    "sg:province":"MD",
    "sg:tags":[
        "cleaners",
        "rug",
        "carpet"
    ],
    "wof:name":"Carpet Consultants",
    "wof:placetype":"venue"
},
  "geometry": {"coordinates":[-76.484246,39.330649],"type":"Point"}
}