{
  "type": "Feature",
  "properties": {
    "addr:full":"618 S Exeter St Baltimore MD 21264",
    "addr:housenumber":"618",
    "addr:postcode":"21264",
    "addr:street":"S Exeter St",
    "iso:country":"US",
    "sg:address":"618 S Exeter St",
    "sg:city":"Baltimore",
    "sg:classifiers":[
        {
            "category":"Restaurant",
            "type":"Food & Drink"
        }
    ],
    "sg:phone":"+1 410 234 3782",
    "sg:postcode":"21264",
    "sg:province":"MD",
    "sg:tags":[
        "mexican"
    ],
    "sg:website":"www.tacofiesta.com",
    "wof:name":"Taco Fiesta",
    "wof:placetype":"venue"
},
  "geometry": {"coordinates":[-76.600193,39.283007],"type":"Point"}
}