{
  "type": "Feature",
  "properties": {
    "iso:country":"US",
    "sg:address":"4538 Keswick Rd",
    "sg:city":"Baltimore",
    "sg:classifiers":[
        {
            "category":"Professional",
            "subcategory":"Computer Services",
            "type":"Services"
        }
    ],
    "sg:phone":"+1 410 366 2377",
    "sg:postcode":"21210",
    "sg:province":"MD",
    "sg:tags":[
        "consulting"
    ],
    "wof:name":"Wi-FI Works  LLC",
    "wof:placetype":"venue"
},
  "geometry": {"coordinates":[-76.630128,39.346506],"type":"Point"}
}