{
  "type": "Feature",
  "properties": {
    "iso:country":"US",
    "sg:address":"7401 Jefferson Ct",
    "sg:city":"Hyattsville",
    "sg:classifiers":[
        {
            "category":"Building & Trades",
            "subcategory":"Construction",
            "type":"Services"
        }
    ],
    "sg:phone":"+1 301 306 9420",
    "sg:postcode":"20784",
    "sg:province":"MD",
    "sg:tags":[
        "general",
        "contractor"
    ],
    "wof:name":"Lopes Construction Inc",
    "wof:placetype":"venue"
},
  "geometry": {"coordinates":[-76.88773399999999,38.954609],"type":"Point"}
}