{
  "type": "Feature",
  "properties": {
    "addr:full":"3015 Hutton Rd Oakland MD 21550",
    "addr:housenumber":"3015",
    "addr:postcode":"21550",
    "addr:street":"Hutton Rd",
    "iso:country":"US",
    "sg:address":"3015 Hutton Rd",
    "sg:city":"Oakland",
    "sg:classifiers":[
        {
            "category":"Retail",
            "subcategory":"Auto Repair",
            "type":"Services"
        }
    ],
    "sg:phone":"+1 301 334 2704",
    "sg:postcode":"21550",
    "sg:province":"MD",
    "sg:tags":[
        "general"
    ],
    "wof:name":"S Shaffer Auto Body",
    "wof:placetype":"venue"
},
  "geometry": {"coordinates":[-79.45407,39.388982],"type":"Point"}
}