{
  "type": "Feature",
  "properties": {
    "iso:country":"US",
    "sg:address":"1610 Ruffs Mill Rd",
    "sg:city":"Bel Air",
    "sg:classifiers":[
        {
            "category":"Building & Trades",
            "subcategory":"Plumbing",
            "type":"Services"
        }
    ],
    "sg:phone":"+1 410 838 6695",
    "sg:postcode":"21015",
    "sg:province":"MD",
    "sg:tags":[
        "conditioning",
        "air",
        "system",
        "contractor"
    ],
    "wof:name":"Basic Services Inc",
    "wof:placetype":"venue"
},
  "geometry": {"coordinates":[-76.313499,39.578416],"type":"Point"}
}