{
  "type": "Feature",
  "properties": {
    "addr:full":"1208 Underwood St NW Washington MD 20012",
    "addr:housenumber":"1208",
    "addr:postcode":"20012",
    "addr:street":"Underwood St Nw",
    "iso:country":"US",
    "sg:address":"1208 Underwood St NW",
    "sg:city":"Washington",
    "sg:classifiers":[
        {
            "category":"Personal",
            "subcategory":"Beauty Salon",
            "type":"Services"
        }
    ],
    "sg:phone":"+1 202 829 3693",
    "sg:postcode":"20012",
    "sg:province":"MD",
    "wof:name":"Levines & Son Beauty Ctr",
    "wof:placetype":"venue"
},
  "geometry": {"coordinates":[-77.029538,38.968904],"type":"Point"}
}