{
  "type": "Feature",
  "properties": {
    "iso:country":"US",
    "sg:address":"1700 Gorsuch Ave Ste 1",
    "sg:city":"Baltimore",
    "sg:classifiers":[
        {
            "category":"Place Of Worship",
            "subcategory":"Church",
            "type":"Public Place"
        },
        {
            "category":"Place Of Worship",
            "type":"Public Place"
        }
    ],
    "sg:phone":"+1 410 467 4135",
    "sg:postcode":"21218",
    "sg:province":"MD",
    "sg:tags":[
        "churches-pentecostal-independent",
        "churches-pentecostal"
    ],
    "wof:name":"Fountain Of Lf Ch Liberty Lov",
    "wof:placetype":"venue"
},
  "geometry": {"coordinates":[-76.59423099999999,39.32095],"type":"Point"}
}