{
  "type": "Feature",
  "properties": {
    "addr:full":"10051 N 2nd St Laurel MD 20723",
    "addr:housenumber":"10051",
    "addr:postcode":"20723",
    "addr:street":"N 2Nd St",
    "iso:country":"US",
    "sg:address":"10051 N 2nd St",
    "sg:city":"Laurel",
    "sg:classifiers":[
        {
            "category":"Personal",
            "subcategory":"Tattoo Parlor",
            "type":"Services"
        }
    ],
    "sg:phone":"+1 301 362 4200",
    "sg:postcode":"20723",
    "sg:province":"MD",
    "sg:tags":[
        "tattooing"
    ],
    "wof:name":"Ink This",
    "wof:placetype":"venue"
},
  "geometry": {"coordinates":[-76.836601,39.109001],"type":"Point"}
}