{
  "type": "Feature",
  "properties": {
    "addr:full":"407 Brookletts Ave Easton MD 21601",
    "addr:housenumber":"407",
    "addr:postcode":"21601",
    "addr:street":"Brookletts Ave",
    "iso:country":"US",
    "sg:address":"407 Brookletts Ave",
    "sg:city":"Easton",
    "sg:classifiers":[
        {
            "category":"Professional",
            "type":"Services"
        }
    ],
    "sg:phone":"+1 410 822 0300",
    "sg:postcode":"21601",
    "sg:province":"MD",
    "sg:tags":[
        "establishment"
    ],
    "wof:name":"Cox Management Group LLC",
    "wof:placetype":"venue"
},
  "geometry": {"coordinates":[-76.06948,38.770723],"type":"Point"}
}