{
  "type": "Feature",
  "properties": {
    "iso:country":"US",
    "sg:address":"1215 W North Ave",
    "sg:city":"Baltimore",
    "sg:classifiers":[
        {
            "category":"Restaurant",
            "type":"Food & Drink"
        }
    ],
    "sg:phone":"+1 410 225 7917",
    "sg:postcode":"21217",
    "sg:province":"MD",
    "wof:name":"New York Fried Chicken",
    "wof:placetype":"venue"
},
  "geometry": {"coordinates":[-76.637398,39.3102],"type":"Point"}
}