{
  "type": "Feature",
  "properties": {
    "iso:country":"US",
    "sg:address":"13519 Brandywine Rd",
    "sg:city":"Brandywine",
    "sg:classifiers":[
        {
            "category":"Food & Beverages",
            "subcategory":"Groceries & Convenience Stores",
            "type":"Retail Goods"
        }
    ],
    "sg:phone":"+1 301 782 3660",
    "sg:postcode":"20613",
    "sg:province":"MD",
    "sg:tags":[
        "product"
    ],
    "wof:name":"Food Equipment Warehouse",
    "wof:placetype":"venue"
},
  "geometry": {"coordinates":[-76.88078400000001,38.703548],"type":"Point"}
}