{
  "type": "Feature",
  "properties": {
    "iso:country":"US",
    "sg:address":"230 N Eutaw St",
    "sg:city":"Baltimore",
    "sg:classifiers":[
        {
            "category":"Shopping",
            "subcategory":"Clothing, Apparel, & Fashions",
            "type":"Retail Goods"
        }
    ],
    "sg:phone":"+1 410 234 0053",
    "sg:postcode":"21201",
    "sg:province":"MD",
    "wof:name":"Accessories Plus",
    "wof:placetype":"venue"
},
  "geometry": {"coordinates":[-76.621168,39.292912],"type":"Point"}
}