{
  "type": "Feature",
  "properties": {
    "iso:country":"US",
    "sg:address":"7019 Harford Rd Ste 1",
    "sg:city":"Parkville",
    "sg:classifiers":[
        {
            "category":"Home & Garden",
            "subcategory":"Household Appliances",
            "type":"Retail Goods"
        },
        {
            "category":"Manufacturing",
            "subcategory":"Petroleum Products",
            "type":"Manufacturing & Wholesale Goods"
        },
        {
            "category":"Utilities",
            "subcategory":"Fuel Oil & Lpg",
            "type":"Services"
        },
        {
            "category":"Building & Trades",
            "subcategory":"Construction",
            "type":"Services"
        }
    ],
    "sg:phone":"+1 410 354 3400",
    "sg:postcode":"21234",
    "sg:province":"MD",
    "sg:tags":[
        "dishwashing",
        "refiner",
        "system",
        "machine",
        "oils-fuel",
        "contractor",
        "air conditioning"
    ],
    "sg:website":"http://www.griffthoil.com",
    "wof:name":"Clipper Petroleum Inc",
    "wof:placetype":"venue"
},
  "geometry": {"coordinates":[-76.54894299999999,39.366797],"type":"Point"}
}