{
  "type": "Feature",
  "properties": {
    "iso:country":"US",
    "sg:address":"2113 W Lafayette Ave",
    "sg:city":"Baltimore",
    "sg:phone":"+1 410 566 5000",
    "sg:postcode":"21217",
    "sg:province":"MD",
    "sg:tags":[
        "oil",
        "doctor"
    ],
    "wof:name":"J J Adams Fuel Co",
    "wof:placetype":"venue"
},
  "geometry": {"coordinates":[-76.651703,39.2985],"type":"Point"}
}