{
  "type": "Feature",
  "properties": {
    "addr:full":"1198 Kenly Ave Hagerstown MD 21740",
    "addr:housenumber":"1198",
    "addr:postcode":"21740",
    "addr:street":"Kenly Ave",
    "iso:country":"US",
    "sg:address":"1198 Kenly Ave",
    "sg:city":"Hagerstown",
    "sg:classifiers":[
        {
            "category":"Health Services",
            "subcategory":"Doctor",
            "type":"Services"
        }
    ],
    "sg:phone":"+1 301 733 1320",
    "sg:postcode":"21740",
    "sg:province":"MD",
    "sg:tags":[
        "physician",
        "surgeon"
    ],
    "wof:name":"Mark Jameson MD",
    "wof:placetype":"venue"
},
  "geometry": {"coordinates":[-77.71339999999999,39.617927],"type":"Point"}
}