{
  "type": "Feature",
  "properties": {
    "iso:country":"US",
    "sg:address":"2411 W Belvedere Ave Ste 209",
    "sg:city":"Baltimore",
    "sg:classifiers":[
        {
            "category":"Health Services",
            "subcategory":"Doctor",
            "type":"Services"
        }
    ],
    "sg:phone":"+1 410 367 9600",
    "sg:postcode":"21215",
    "sg:province":"MD",
    "sg:tags":[
        "physician",
        "stomach",
        "gastroenterology",
        "surgeons",
        "surgeon",
        "intestines"
    ],
    "sg:website":"http://www.woodholmegi.com",
    "wof:name":"Woodholme Gastroenterology Associates PA",
    "wof:placetype":"venue"
},
  "geometry": {"coordinates":[-76.662449,39.354415],"type":"Point"}
}