{
  "type": "Feature",
  "properties": {
    "addr:full":"28 S Washington St Easton MD 21601",
    "addr:housenumber":"28",
    "addr:postcode":"21601",
    "addr:street":"S Washington St",
    "iso:country":"US",
    "sg:address":"28 S Washington St",
    "sg:city":"Easton",
    "sg:classifiers":[
        {
            "category":"Restaurant",
            "type":"Food & Drink"
        }
    ],
    "sg:phone":"+1 410 770 5172",
    "sg:postcode":"21601",
    "sg:province":"MD",
    "wof:name":"Columbia Restaurant",
    "wof:placetype":"venue"
},
  "geometry": {"coordinates":[-76.076312,38.774002],"type":"Point"}
}