{
  "type": "Feature",
  "properties": {
    "addr:full":"6231 Main St Queenstown MD 21658",
    "addr:housenumber":"6231",
    "addr:postcode":"21658",
    "addr:street":"Main St",
    "iso:country":"US",
    "sg:address":"6231 Main St",
    "sg:city":"Queenstown",
    "sg:classifiers":[
        {
            "category":"Retail",
            "subcategory":"Car Wash",
            "type":"Services"
        }
    ],
    "sg:phone":"+1 410 827 0007",
    "sg:postcode":"21658",
    "sg:province":"MD",
    "sg:tags":[
        "automobile",
        "detail",
        "clean"
    ],
    "wof:name":"Auto Details LLC",
    "wof:placetype":"venue"
},
  "geometry": {"coordinates":[-76.169465,38.976765],"type":"Point"}
}