{
  "type": "Feature",
  "properties": {
    "iso:country":"US",
    "sg:address":"709 Keith Ln",
    "sg:city":"Owings",
    "sg:classifiers":[
        {
            "category":"Government",
            "subcategory":"Fire Station",
            "type":"Public Place"
        }
    ],
    "sg:phone":"+1 301 855 8787",
    "sg:postcode":"20736",
    "sg:province":"MD",
    "sg:tags":[
        "tanks-removal",
        "installation"
    ],
    "sg:website":"http://www.shoringup.com",
    "wof:name":"L & L Enterprises, Inc.",
    "wof:placetype":"venue"
},
  "geometry": {"coordinates":[-76.614602,38.685254],"type":"Point"}
}