{
  "type": "Feature",
  "properties": {
    "iso:country":"US",
    "sg:address":"5000 Belair Rd",
    "sg:city":"Baltimore",
    "sg:classifiers":[
        {
            "category":"Food & Beverages",
            "subcategory":"Candy",
            "type":"Retail Goods"
        }
    ],
    "sg:phone":"+1 443 919 8102",
    "sg:postcode":"21206",
    "sg:province":"MD",
    "sg:tags":[
        "confectionery"
    ],
    "wof:name":"Balloon Candy Sensations & Creations",
    "wof:placetype":"venue"
},
  "geometry": {"coordinates":[-76.555199,39.335651],"type":"Point"}
}