{
  "type": "Feature",
  "properties": {
    "addr:full":"1101 Clopper Rd Gaithersburg MD 20878",
    "addr:housenumber":"1101",
    "addr:postcode":"20878",
    "addr:street":"Clopper Rd",
    "iso:country":"US",
    "sg:address":"1101 Clopper Rd",
    "sg:city":"Gaithersburg",
    "sg:classifiers":[
        {
            "category":"Sports & Exercise",
            "subcategory":"Bowling",
            "type":"Entertainment"
        }
    ],
    "sg:phone":"+1 301 330 5200",
    "sg:postcode":"20878",
    "sg:province":"MD",
    "sg:tags":[
        "center"
    ],
    "wof:name":"Bowl America Inc",
    "wof:placetype":"venue"
},
  "geometry": {"coordinates":[-77.22986899999999,39.14691],"type":"Point"}
}