{
  "type": "Feature",
  "properties": {
    "iso:country":"US",
    "sg:address":"801 David Dr",
    "sg:city":"Arnold",
    "sg:classifiers":[
        {
            "category":"Building & Trades",
            "subcategory":"Construction",
            "type":"Services"
        }
    ],
    "sg:phone":"+1 410 647 8458",
    "sg:postcode":"21012",
    "sg:province":"MD",
    "sg:tags":[
        "home",
        "improvement"
    ],
    "wof:name":"Jim Amos Contracting Inc",
    "wof:placetype":"venue"
},
  "geometry": {"coordinates":[-76.503763,39.065128],"type":"Point"}
}