{
  "type": "Feature",
  "properties": {
    "addr:full":"1901 Pulaski Hwy Edgewood MD 21040",
    "addr:housenumber":"1901",
    "addr:postcode":"21040",
    "addr:street":"Pulaski Hwy",
    "iso:country":"US",
    "sg:address":"1901 Pulaski Hwy",
    "sg:city":"Edgewood",
    "sg:classifiers":[
        {
            "category":"Bakery",
            "type":"Food & Drink"
        },
        {
            "category":"Shopping",
            "subcategory":"Florist",
            "type":"Retail Goods"
        }
    ],
    "sg:phone":"+1 410 679 7014",
    "sg:postcode":"21040",
    "sg:province":"MD",
    "wof:name":"Giant Food Inc & Giant Discount Drug",
    "wof:placetype":"venue"
},
  "geometry": {"coordinates":[-76.31559799999999,39.4352],"type":"Point"}
}