{
  "type": "Feature",
  "properties": {
    "iso:country":"US",
    "sg:address":"14710 Main St",
    "sg:city":"Upper Marlboro",
    "sg:classifiers":[
        {
            "category":"Restaurant",
            "type":"Food & Drink"
        }
    ],
    "sg:phone":"+1 301 574 4900",
    "sg:postcode":"20772",
    "sg:province":"MD",
    "wof:name":"Olde Courthouse Cafe & Deli",
    "wof:placetype":"venue"
},
  "geometry": {"coordinates":[-76.751049,38.816594],"type":"Point"}
}