{
  "type": "Feature",
  "properties": {
    "addr:full":"11900 Autumnwood Ln Fort Washington MD 20744",
    "addr:housenumber":"11900",
    "addr:postcode":"20744",
    "addr:street":"Autumnwood Ln",
    "iso:country":"US",
    "sg:address":"11900 Autumnwood Ln",
    "sg:city":"Fort Washington",
    "sg:classifiers":[
        {
            "category":"Professional",
            "subcategory":"Management & Consulting",
            "type":"Services"
        }
    ],
    "sg:phone":"+1 301 292 3028",
    "sg:postcode":"20744",
    "sg:province":"MD",
    "sg:tags":[
        "consultant",
        "business"
    ],
    "wof:name":"Sylvia Dayton Jones",
    "wof:placetype":"venue"
},
  "geometry": {"coordinates":[-77.00851900000001,38.729987],"type":"Point"}
}