{
  "type": "Feature",
  "properties": {
    "addr:full":"2300 N Salisbury Blvd Salisbury MD 21801",
    "addr:housenumber":"2300",
    "addr:postcode":"21801",
    "addr:street":"N Salisbury Blvd",
    "iso:country":"US",
    "sg:address":"2300 N Salisbury Blvd",
    "sg:city":"Salisbury",
    "sg:classifiers":[
        {
            "category":"Shopping",
            "subcategory":"Shoes",
            "type":"Retail Goods"
        }
    ],
    "sg:phone":"+1 410 860 1751",
    "sg:postcode":"21801",
    "sg:province":"MD",
    "wof:name":"Journeys",
    "wof:placetype":"venue"
},
  "geometry": {"coordinates":[-75.571454,38.398448],"type":"Point"}
}