{
  "type": "Feature",
  "properties": {
    "addr:full":"12530 Parklawn Dr Rockville MD 20852",
    "addr:housenumber":"12530",
    "addr:postcode":"20852",
    "addr:street":"Parklawn Dr",
    "iso:country":"US",
    "sg:address":"12530 Parklawn Dr",
    "sg:city":"Rockville",
    "sg:classifiers":[
        {
            "category":"Communications",
            "type":"Services"
        }
    ],
    "sg:phone":"+1 301 770 0550",
    "sg:postcode":"20852",
    "sg:province":"MD",
    "wof:name":"Caplan Communications",
    "wof:placetype":"venue"
},
  "geometry": {"coordinates":[-77.117481,39.061637],"type":"Point"}
}