{
  "type": "Feature",
  "properties": {
    "addr:full":"10701 New Georges Creek Rd SW Frostburg MD 21532",
    "addr:housenumber":"10701",
    "addr:postcode":"21532",
    "addr:street":"New Georges Creek Rd Sw",
    "iso:country":"US",
    "sg:address":"10701 New Georges Creek Rd SW",
    "sg:city":"Frostburg",
    "sg:classifiers":[
        {
            "category":"Professional",
            "type":"Services"
        }
    ],
    "sg:phone":"+1 301 687 1700",
    "sg:postcode":"21532",
    "sg:province":"MD",
    "sg:tags":[
        "establishment"
    ],
    "wof:name":"Cyber Rep",
    "wof:placetype":"venue"
},
  "geometry": {"coordinates":[-78.91576499999999,39.618833],"type":"Point"}
}