{
  "type": "Feature",
  "properties": {
    "iso:country":"US",
    "sg:address":"6300 Carnegie Dr",
    "sg:city":"Bethesda",
    "sg:classifiers":[
        {
            "category":"Health Services",
            "subcategory":"Doctor",
            "type":"Services"
        }
    ],
    "sg:phone":"+1 301 530 8877",
    "sg:postcode":"20817",
    "sg:province":"MD",
    "wof:name":"Troshinsky Chas H MD",
    "wof:placetype":"venue"
},
  "geometry": {"coordinates":[-77.12599899999999,39.0172],"type":"Point"}
}