{
  "type": "Feature",
  "properties": {
    "iso:country":"US",
    "sg:address":"2201 Van Deman St",
    "sg:city":"Baltimore",
    "sg:classifiers":[
        {
            "category":"Retail",
            "subcategory":"Repair Shop",
            "type":"Services"
        }
    ],
    "sg:phone":"+1 410 633 6980",
    "sg:postcode":"21224",
    "sg:province":"MD",
    "sg:tags":[
        "reupholstery",
        "furniture"
    ],
    "wof:name":"Thrasher's Custom Built Furniture Inc",
    "wof:placetype":"venue"
},
  "geometry": {"coordinates":[-76.535202,39.264099],"type":"Point"}
}