{
  "type": "Feature",
  "properties": {
    "addr:full":"2429 Frederick Ave Baltimore MD 21223",
    "addr:housenumber":"2429",
    "addr:postcode":"21223",
    "addr:street":"Frederick Ave",
    "iso:country":"US",
    "sg:address":"2429 Frederick Ave",
    "sg:city":"Baltimore",
    "sg:classifiers":[
        {
            "category":"Health Services",
            "subcategory":"Dentist",
            "type":"Services"
        }
    ],
    "sg:phone":"+1 443 957 1615",
    "sg:postcode":"21223",
    "sg:province":"MD",
    "wof:name":"Kool Smiles",
    "wof:placetype":"venue"
},
  "geometry": {"coordinates":[-76.65484499999999,39.283892],"type":"Point"}
}