{
  "type": "Feature",
  "properties": {
    "addr:full":"14500 Melinda Ln Rockville MD 20853",
    "addr:housenumber":"14500",
    "addr:postcode":"20853",
    "addr:street":"Melinda Ln",
    "iso:country":"US",
    "sg:address":"14500 Melinda Ln",
    "sg:city":"Rockville",
    "sg:classifiers":[
        {
            "category":"Professional",
            "type":"Services"
        }
    ],
    "sg:phone":"+1 301 460 1235",
    "sg:postcode":"20853",
    "sg:province":"MD",
    "sg:tags":[
        "establishment"
    ],
    "wof:name":"D'Avis Juan C",
    "wof:placetype":"venue"
},
  "geometry": {"coordinates":[-77.098258,39.09465],"type":"Point"}
}