{
  "type": "Feature",
  "properties": {
    "addr:full":"339 W Washington St Hagerstown MD 21740",
    "addr:housenumber":"339",
    "addr:postcode":"21740",
    "addr:street":"W Washington St",
    "iso:country":"US",
    "sg:address":"339 W Washington St",
    "sg:city":"Hagerstown",
    "sg:classifiers":[
        {
            "category":"Autos & Motor Vehicles",
            "subcategory":"Automobile Sales",
            "type":"Retail Goods"
        }
    ],
    "sg:phone":"+1 301 714 2999",
    "sg:postcode":"21740",
    "sg:province":"MD",
    "sg:tags":[
        "car",
        "dealer"
    ],
    "wof:name":"Kar Korner",
    "wof:placetype":"venue"
},
  "geometry": {"coordinates":[-77.726432,39.644876],"type":"Point"}
}