{
  "type": "Feature",
  "properties": {
    "addr:full":"614 Lighthouse Landing Ln Annapolis MD 21409",
    "addr:housenumber":"614",
    "addr:postcode":"21409",
    "addr:street":"Lighthouse Landing Ln",
    "iso:country":"US",
    "sg:address":"614 Lighthouse Landing Ln",
    "sg:city":"Annapolis",
    "sg:classifiers":[
        {
            "category":"Building & Trades",
            "subcategory":"Construction",
            "type":"Services"
        }
    ],
    "sg:phone":"+1 410 757 5863",
    "sg:postcode":"21409",
    "sg:province":"MD",
    "sg:tags":[
        "home",
        "builder"
    ],
    "wof:name":"Koch Homes St Margaret Landing",
    "wof:placetype":"venue"
},
  "geometry": {"coordinates":[-76.425247,39.017916],"type":"Point"}
}