{
  "type": "Feature",
  "properties": {
    "addr:full":"8261 New Cut Rd Severn MD 21144",
    "addr:housenumber":"8261",
    "addr:postcode":"21144",
    "addr:street":"New Cut Rd",
    "iso:country":"US",
    "sg:address":"8261 New Cut Rd",
    "sg:city":"Severn",
    "sg:classifiers":[
        {
            "category":"Retail",
            "subcategory":"Repair Shop",
            "type":"Services"
        }
    ],
    "sg:phone":"+1 410 987 6990",
    "sg:postcode":"21144",
    "sg:province":"MD",
    "sg:tags":[
        "taxidermist"
    ],
    "wof:name":"Ray Hitchcock Taxidermy",
    "wof:placetype":"venue"
},
  "geometry": {"coordinates":[-76.659063,39.104537],"type":"Point"}
}