{
  "type": "Feature",
  "properties": {
    "addr:full":"8 Bimini Ln Berlin MD 21811",
    "addr:housenumber":"8",
    "addr:postcode":"21811",
    "addr:street":"Bimini Ln",
    "iso:country":"US",
    "sg:address":"8 Bimini Ln",
    "sg:city":"Berlin",
    "sg:classifiers":[
        {
            "category":"Professional",
            "subcategory":"Engineering",
            "type":"Services"
        }
    ],
    "sg:phone":"+1 410 713 9267",
    "sg:postcode":"21811",
    "sg:province":"MD",
    "sg:tags":[
        "consulting",
        "engineer"
    ],
    "wof:name":"Horace T Macey",
    "wof:placetype":"venue"
},
  "geometry": {"coordinates":[-75.15100099999999,38.394862],"type":"Point"}
}