{
  "type": "Feature",
  "properties": {
    "iso:country":"US",
    "sg:address":"5806 Delta Ln",
    "sg:city":"Suitland",
    "sg:classifiers":[
        {
            "category":"Banks & Credit Unions",
            "subcategory":"Investment Brokerage",
            "type":"Services"
        }
    ],
    "sg:phone":"+1 301 899 8797",
    "sg:postcode":"20746",
    "sg:province":"MD",
    "sg:tags":[
        "car",
        "security"
    ],
    "wof:name":"Clifton C Mills",
    "wof:placetype":"venue"
},
  "geometry": {"coordinates":[-76.905111,38.821159],"type":"Point"}
}