{
  "type": "Feature",
  "properties": {
    "addr:full":"715 Pennington Ave Havre De Grace MD 21078",
    "addr:housenumber":"715",
    "addr:postcode":"21078",
    "addr:street":"Pennington Ave",
    "iso:country":"US",
    "sg:address":"715 Pennington Ave",
    "sg:city":"Havre De Grace",
    "sg:classifiers":[
        {
            "category":"Government",
            "subcategory":"Police Station",
            "type":"Public Place"
        }
    ],
    "sg:phone":"+1 410 939 2121",
    "sg:postcode":"21078",
    "sg:province":"MD",
    "sg:tags":[
        "department"
    ],
    "wof:name":"Havre De Grace Police Dept",
    "wof:placetype":"venue"
},
  "geometry": {"coordinates":[-76.094493,39.548795],"type":"Point"}
}