{
  "type": "Feature",
  "properties": {
    "iso:country":"US",
    "sg:address":"3019 Mondawmin Ave",
    "sg:city":"Baltimore",
    "sg:classifiers":[
        {
            "category":"Organizations",
            "subcategory":"Religious Organization",
            "type":"Services"
        }
    ],
    "sg:phone":"+1 410 383 9565",
    "sg:postcode":"21216",
    "sg:province":"MD",
    "wof:name":"Followers of Pentecostal",
    "wof:placetype":"venue"
},
  "geometry": {"coordinates":[-76.669267,39.315217],"type":"Point"}
}