{
  "type": "Feature",
  "properties": {
    "addr:full":"3427 Dundalk Ave Dundalk MD 21222",
    "addr:housenumber":"3427",
    "addr:postcode":"21222",
    "addr:street":"Dundalk Ave",
    "iso:country":"US",
    "sg:address":"3427 Dundalk Ave",
    "sg:city":"Dundalk",
    "sg:classifiers":[
        {
            "category":"Personal",
            "subcategory":"Beauty Salon",
            "type":"Services"
        }
    ],
    "sg:phone":"+1 410 285 5700",
    "sg:postcode":"21222",
    "sg:province":"MD",
    "wof:name":"Heavenly Hair",
    "wof:placetype":"venue"
},
  "geometry": {"coordinates":[-76.51761,39.247791],"type":"Point"}
}