{
  "type": "Feature",
  "properties": {
    "iso:country":"US",
    "sg:address":"1903 Dennis Ave",
    "sg:city":"Silver Spring",
    "sg:classifiers":[
        {
            "category":"Building & Trades",
            "subcategory":"Construction",
            "type":"Services"
        }
    ],
    "sg:phone":"+1 301 754 2384",
    "sg:postcode":"20902",
    "sg:province":"MD",
    "sg:tags":[
        "house"
    ],
    "wof:name":"R G Rupertus",
    "wof:placetype":"venue"
},
  "geometry": {"coordinates":[-77.042664,39.025811],"type":"Point"}
}