{
  "type": "Feature",
  "properties": {
    "addr:full":"402 O St Oakland MD 21550",
    "addr:housenumber":"402",
    "addr:postcode":"21550",
    "addr:street":"O St",
    "iso:country":"US",
    "sg:address":"402 O St",
    "sg:city":"Oakland",
    "sg:classifiers":[
        {
            "category":"Retail",
            "subcategory":"Repair Shop",
            "type":"Services"
        }
    ],
    "sg:phone":"+1 301 387 5597",
    "sg:postcode":"21550",
    "sg:province":"MD",
    "sg:tags":[
        "spa",
        "hot",
        "tub"
    ],
    "wof:name":"Unicorn Express",
    "wof:placetype":"venue"
},
  "geometry": {"coordinates":[-79.374831,39.399924],"type":"Point"}
}