{
  "type": "Feature",
  "properties": {
    "iso:country":"US",
    "sg:address":"892 Kenilworth Dr",
    "sg:city":"Towson",
    "sg:classifiers":[
        {
            "category":"Shopping",
            "type":"Retail Goods"
        }
    ],
    "sg:phone":"+1 410 339 3849",
    "sg:postcode":"21204",
    "sg:province":"MD",
    "sg:tags":[
        "plant",
        "flower",
        "tree",
        "artificial"
    ],
    "wof:name":"Milk House",
    "wof:placetype":"venue"
},
  "geometry": {"coordinates":[-76.616078,39.409971],"type":"Point"}
}