{
  "type": "Feature",
  "properties": {
    "addr:full":"13912 Westview Forest Dr Bowie MD 20720",
    "addr:housenumber":"13912",
    "addr:postcode":"20720",
    "addr:street":"Westview Forest Dr",
    "iso:country":"US",
    "sg:address":"13912 Westview Forest Dr",
    "sg:city":"Bowie",
    "sg:classifiers":[
        {
            "category":"Organizations",
            "subcategory":"Religious Organization",
            "type":"Services"
        }
    ],
    "sg:phone":"+1 301 262 2036",
    "sg:postcode":"20720",
    "sg:province":"MD",
    "wof:name":"Opportnity Missions Ministries",
    "wof:placetype":"venue"
},
  "geometry": {"coordinates":[-76.760334,38.965647],"type":"Point"}
}