{
  "type": "Feature",
  "properties": {
    "iso:country":"US",
    "sg:address":"4 Professional Dr",
    "sg:city":"Gaithersburg",
    "sg:classifiers":[
        {
            "category":"Professional",
            "subcategory":"Management & Consulting",
            "type":"Services"
        }
    ],
    "sg:phone":"+1 301 977 7459",
    "sg:postcode":"20879",
    "sg:province":"MD",
    "sg:tags":[
        "consultant"
    ],
    "wof:name":"Escalation Consultants",
    "wof:placetype":"venue"
},
  "geometry": {"coordinates":[-77.22707699999999,39.160017],"type":"Point"}
}