{
  "type": "Feature",
  "properties": {
    "addr:full":"419 Imla St Baltimore MD 21224",
    "addr:housenumber":"419",
    "addr:postcode":"21224",
    "addr:street":"Imla St",
    "iso:country":"US",
    "sg:address":"419 Imla St",
    "sg:city":"Baltimore",
    "sg:classifiers":[
        {
            "category":"Building & Trades",
            "subcategory":"Construction",
            "type":"Services"
        }
    ],
    "sg:phone":"+1 410 633 3818",
    "sg:postcode":"21224",
    "sg:province":"MD",
    "sg:tags":[
        "remodeling",
        "contractor"
    ],
    "wof:name":"Eastcraft Rmdlg & Cnstr Co",
    "wof:placetype":"venue"
},
  "geometry": {"coordinates":[-76.539023,39.288537],"type":"Point"}
}