{
  "type": "Feature",
  "properties": {
    "addr:full":"9104 Copenhaver Dr Potomac MD 20854",
    "addr:postcode":"9104;20854",
    "addr:street":"Copenhaver Dr",
    "iso:country":"US",
    "sg:address":"9104 Copenhaver Dr",
    "sg:city":"Potomac",
    "sg:classifiers":[
        {
            "category":"Shopping",
            "subcategory":"Gifts & Souvenirs",
            "type":"Retail Goods"
        }
    ],
    "sg:phone":"+1 301 762 0506",
    "sg:postcode":"20854",
    "sg:province":"MD",
    "sg:tags":[
        "shop"
    ],
    "wof:name":"Definitely Different",
    "wof:placetype":"venue"
},
  "geometry": {"coordinates":[-77.186007,39.057357],"type":"Point"}
}