{
  "type": "Feature",
  "properties": {
    "addr:full":"781 Washington Blvd Baltimore MD 21230",
    "addr:housenumber":"781",
    "addr:postcode":"21230",
    "addr:street":"Washington Blvd",
    "iso:country":"US",
    "sg:address":"781 Washington Blvd",
    "sg:city":"Baltimore",
    "sg:classifiers":[
        {
            "category":"Wholesale",
            "subcategory":"Electrical",
            "type":"Manufacturing & Wholesale Goods"
        }
    ],
    "sg:phone":"+1 410 539 3094",
    "sg:postcode":"21230",
    "sg:province":"MD",
    "sg:tags":[
        "alarm",
        "burglar",
        "system"
    ],
    "wof:name":"Unlimited Security Systems",
    "wof:placetype":"venue"
},
  "geometry": {"coordinates":[-76.62875099999999,39.282958],"type":"Point"}
}