{
  "type": "Feature",
  "properties": {
    "addr:full":"30489 Broad St Princess Anne MD 21853",
    "addr:housenumber":"30489",
    "addr:postcode":"21853",
    "addr:street":"Broad St",
    "iso:country":"US",
    "sg:address":"30489 Broad St",
    "sg:city":"Princess Anne",
    "sg:classifiers":[
        {
            "category":"Government",
            "subcategory":"Office",
            "type":"Public Place"
        }
    ],
    "sg:phone":"+1 410 651 1818",
    "sg:postcode":"21853",
    "sg:province":"MD",
    "sg:tags":[
        "village"
    ],
    "wof:name":"Princess Anne Town Commission",
    "wof:placetype":"venue"
},
  "geometry": {"coordinates":[-75.694492,38.205221],"type":"Point"}
}