{
  "type": "Feature",
  "properties": {
    "iso:country":"US",
    "sg:address":"10013 Nearbrook Ln",
    "sg:city":"Baltimore",
    "sg:classifiers":[
        {
            "category":"Manufacturing",
            "subcategory":"Food",
            "type":"Manufacturing & Wholesale Goods"
        }
    ],
    "sg:phone":"+1 410 661 4380",
    "sg:postcode":"21234",
    "sg:province":"MD",
    "sg:tags":[
        "malt",
        "beverage",
        "mfg"
    ],
    "wof:name":"Chuck Mach Miller Brewing",
    "wof:placetype":"venue"
},
  "geometry": {"coordinates":[-76.508356,39.40504],"type":"Point"}
}