{
  "type": "Feature",
  "properties": {
    "iso:country":"US",
    "sg:address":"4825 Bethesda Ave Ste 220",
    "sg:city":"Bethesda",
    "sg:classifiers":[
        {
            "category":"Banks & Credit Unions",
            "subcategory":"Financial Services",
            "type":"Services"
        }
    ],
    "sg:phone":"+1 301 907 3990",
    "sg:postcode":"20814",
    "sg:province":"MD",
    "sg:tags":[
        "broker",
        "mortgage"
    ],
    "wof:name":"Washington Home Mortgage",
    "wof:placetype":"venue"
},
  "geometry": {"coordinates":[-77.097801,38.9809],"type":"Point"}
}