{
  "type": "Feature",
  "properties": {
    "addr:full":"4023 Evergreen Rd Port Republic MD 20676",
    "addr:housenumber":"4023",
    "addr:postcode":"20676",
    "addr:street":"Evergreen Rd",
    "iso:country":"US",
    "sg:address":"4023 Evergreen Rd",
    "sg:city":"Port Republic",
    "sg:classifiers":[
        {
            "category":"Professional",
            "subcategory":"Management & Consulting",
            "type":"Services"
        }
    ],
    "sg:phone":"+1 410 586 9002",
    "sg:postcode":"20676",
    "sg:province":"MD",
    "sg:tags":[
        "business"
    ],
    "wof:name":"Sullivan Consulting",
    "wof:placetype":"venue"
},
  "geometry": {"coordinates":[-76.516603,38.52527],"type":"Point"}
}