{
  "type": "Feature",
  "properties": {
    "iso:country":"US",
    "sg:address":"6200 Westchester Park Dr",
    "sg:city":"College Park",
    "sg:classifiers":[
        {
            "category":"Professional",
            "subcategory":"Management & Consulting",
            "type":"Services"
        }
    ],
    "sg:phone":"+1 301 982 4838",
    "sg:postcode":"20740",
    "sg:province":"MD",
    "sg:tags":[
        "international",
        "consultant"
    ],
    "wof:name":"ITAMER Assoc",
    "wof:placetype":"venue"
},
  "geometry": {"coordinates":[-76.902102,38.991717],"type":"Point"}
}