{
  "type": "Feature",
  "properties": {
    "addr:full":"6316 61st Pl Riverdale MD 20737",
    "addr:housenumber":"6316",
    "addr:postcode":"20737",
    "addr:street":"61St Pl",
    "iso:country":"US",
    "sg:address":"6316 61st Pl",
    "sg:city":"Riverdale",
    "sg:classifiers":[
        {
            "category":"Government",
            "subcategory":"Office",
            "type":"Public Place"
        }
    ],
    "sg:phone":"+1 301 864 6509",
    "sg:postcode":"20737",
    "sg:province":"MD",
    "sg:tags":[
        "national",
        "security"
    ],
    "wof:name":"Yvonne Johnson",
    "wof:placetype":"venue"
},
  "geometry": {"coordinates":[-76.912307,38.964771],"type":"Point"}
}