{
  "type": "Feature",
  "properties": {
    "addr:full":"3262 Superior Ln Bowie MD 20715",
    "addr:housenumber":"3262",
    "addr:postcode":"20715",
    "addr:street":"Superior Ln",
    "iso:country":"US",
    "sg:address":"3262 Superior Ln",
    "sg:city":"Bowie",
    "sg:classifiers":[
        {
            "category":"Professional",
            "subcategory":"Management & Consulting",
            "type":"Services"
        }
    ],
    "sg:phone":"+1 301 805 0074",
    "sg:postcode":"20715",
    "sg:province":"MD",
    "sg:tags":[
        "consultant",
        "business"
    ],
    "wof:name":"HJE Assoc",
    "wof:placetype":"venue"
},
  "geometry": {"coordinates":[-76.732837,38.977428],"type":"Point"}
}