{
  "type": "Feature",
  "properties": {
    "iso:country":"US",
    "sg:address":"884 Chesterfield Rd",
    "sg:city":"Annapolis",
    "sg:classifiers":[
        {
            "category":"Place Of Worship",
            "subcategory":"Church",
            "type":"Public Place"
        },
        {
            "category":"Place Of Worship",
            "type":"Public Place"
        }
    ],
    "sg:phone":"+1 410 544 2222",
    "sg:postcode":"21401",
    "sg:province":"MD",
    "sg:tags":[
        "churches-non-denominational",
        "christ",
        "churches-community"
    ],
    "wof:name":"Bay Area Community Church Inc",
    "wof:placetype":"venue"
},
  "geometry": {"coordinates":[-76.58920999999999,38.995852],"type":"Point"}
}