{
  "type": "Feature",
  "properties": {
    "iso:country":"US",
    "sg:address":"1 Victoria Ct",
    "sg:city":"Reisterstown",
    "sg:classifiers":[
        {
            "category":"Professional",
            "subcategory":"Business Services",
            "type":"Services"
        }
    ],
    "sg:phone":"+1 410 526 2784",
    "sg:postcode":"21136",
    "sg:province":"MD",
    "wof:name":"Sensational Sales",
    "wof:placetype":"venue"
},
  "geometry": {"coordinates":[-76.825439,39.4615],"type":"Point"}
}