{
  "type": "Feature",
  "properties": {
    "iso:country":"US",
    "sg:address":"12845 Harbor Rd",
    "sg:city":"Ocean City",
    "sg:classifiers":[
        {
            "category":"Retail",
            "subcategory":"Repair Shop",
            "type":"Services"
        }
    ],
    "sg:phone":"+1 410 213 8040",
    "sg:postcode":"21842",
    "sg:province":"MD",
    "sg:tags":[
        "bathtub",
        "sink",
        "refinishing"
    ],
    "wof:name":"Tub Tech",
    "wof:placetype":"venue"
},
  "geometry": {"coordinates":[-75.105448,38.326529],"type":"Point"}
}