{
  "type": "Feature",
  "properties": {
    "addr:full":"220 Park Ave Baltimore MD 21201",
    "addr:housenumber":"220",
    "addr:postcode":"21201",
    "addr:street":"Park Ave",
    "iso:country":"US",
    "sg:address":"220 Park Ave",
    "sg:city":"Baltimore",
    "sg:classifiers":[
        {
            "category":"Personal",
            "subcategory":"Beauty Salon",
            "type":"Services"
        }
    ],
    "sg:phone":"+1 410 837 3683",
    "sg:postcode":"21201",
    "sg:province":"MD",
    "wof:name":"Doves Dynasty",
    "wof:placetype":"venue"
},
  "geometry": {"coordinates":[-76.61805699999999,39.292301],"type":"Point"}
}