{
  "type": "Feature",
  "properties": {
    "iso:country":"US",
    "sg:address":"201 S 8th St",
    "sg:city":"Denton",
    "sg:classifiers":[
        {
            "category":"Building & Trades",
            "subcategory":"Construction",
            "type":"Services"
        }
    ],
    "sg:phone":"+1 410 479 5513",
    "sg:postcode":"21629",
    "sg:province":"MD",
    "sg:tags":[
        "hanging",
        "contractor"
    ],
    "wof:name":"Tuckahoe Painting",
    "wof:placetype":"venue"
},
  "geometry": {"coordinates":[-75.825614,38.880569],"type":"Point"}
}