{
  "type": "Feature",
  "properties": {
    "iso:country":"US",
    "sg:address":"211 Nichols Manor Dr",
    "sg:city":"Stevensville",
    "sg:classifiers":[
        {
            "category":"Building & Trades",
            "subcategory":"Construction",
            "type":"Services"
        }
    ],
    "sg:phone":"+1 410 827 7021",
    "sg:postcode":"21666",
    "sg:province":"MD",
    "sg:tags":[
        "altering",
        "remodeling",
        "contractor"
    ],
    "wof:name":"Paul W Alden & Co Inc",
    "wof:placetype":"venue"
},
  "geometry": {"coordinates":[-76.301198,39.002927],"type":"Point"}
}