{
  "type": "Feature",
  "properties": {
    "iso:country":"US",
    "sg:address":"6001 Executive Blvd",
    "sg:city":"Rockville",
    "sg:classifiers":[
        {
            "category":"Restaurant",
            "type":"Food & Drink"
        }
    ],
    "sg:phone":"+1 301 984 8665",
    "sg:postcode":"20852",
    "sg:province":"MD",
    "wof:name":"Nsc Cafetreia Llc",
    "wof:placetype":"venue"
},
  "geometry": {"coordinates":[-77.119698,39.048698],"type":"Point"}
}