{
  "type": "Feature",
  "properties": {
    "iso:country":"US",
    "sg:address":"11711 Dudley Chance Rd",
    "sg:city":"Galena",
    "sg:classifiers":[
        {
            "category":"Organizations",
            "subcategory":"Religious Organization",
            "type":"Services"
        }
    ],
    "sg:phone":"+1 410 348 2313",
    "sg:postcode":"21635",
    "sg:province":"MD",
    "sg:tags":[
        "church"
    ],
    "wof:name":"First United Pentecostal Ch",
    "wof:placetype":"venue"
},
  "geometry": {"coordinates":[-75.865549,39.298721],"type":"Point"}
}