{
  "type": "Feature",
  "properties": {
    "iso:country":"US",
    "sg:address":"8076 Windward Key Dr",
    "sg:city":"Chesapeake Beach",
    "sg:classifiers":[
        {
            "category":"Travel",
            "subcategory":"Travel Agent",
            "type":"Entertainment"
        }
    ],
    "sg:phone":"+1 410 286 8990",
    "sg:postcode":"20732",
    "sg:province":"MD",
    "sg:tags":[
        "tours",
        "promoter"
    ],
    "wof:name":"Bounty Hunter Charters",
    "wof:placetype":"venue"
},
  "geometry": {"coordinates":[-76.533674,38.69247],"type":"Point"}
}