{
  "type": "Feature",
  "properties": {
    "addr:full":"1300 Mercantile Ln Upper Marlboro MD 20774",
    "addr:housenumber":"1300",
    "addr:postcode":"20774",
    "addr:street":"Mercantile Ln",
    "iso:country":"US",
    "sg:address":"1300 Mercantile Ln",
    "sg:city":"Upper Marlboro",
    "sg:classifiers":[
        {
            "category":"Shopping",
            "subcategory":"Crafts & Fabrics",
            "type":"Retail Goods"
        }
    ],
    "sg:phone":"+1 301 386 3323",
    "sg:postcode":"20774",
    "sg:province":"MD",
    "sg:tags":[
        "yarn"
    ],
    "wof:name":"Yarn & Co Inc",
    "wof:placetype":"venue"
},
  "geometry": {"coordinates":[-76.837469,38.907095],"type":"Point"}
}