{
  "type": "Feature",
  "properties": {
    "iso:country":"US",
    "sg:address":"4601 Pall Mall Rd",
    "sg:city":"Baltimore",
    "sg:classifiers":[
        {
            "category":"Social Services",
            "subcategory":"Job Training",
            "type":"Services"
        }
    ],
    "sg:phone":"+1 410 664 5551",
    "sg:postcode":"21215",
    "sg:province":"MD",
    "sg:tags":[
        "nursing",
        "homes-skilled",
        "facility"
    ],
    "sg:website":"http://www.concordcarecenters.com",
    "wof:name":"Trans Healthcare Inc",
    "wof:placetype":"venue"
},
  "geometry": {"coordinates":[-76.66494,39.34222],"type":"Point"}
}