{
  "type": "Feature",
  "properties": {
    "iso:country":"US",
    "sg:address":"610 Tayman Dr",
    "sg:city":"Annapolis",
    "sg:classifiers":[
        {
            "category":"Professional",
            "subcategory":"Research",
            "type":"Services"
        }
    ],
    "sg:phone":"+1 410 268 4970",
    "sg:postcode":"21403",
    "sg:province":"MD",
    "sg:tags":[
        "consulting"
    ],
    "wof:name":"Stanley J Dapkunas",
    "wof:placetype":"venue"
},
  "geometry": {"coordinates":[-76.49809399999999,38.931623],"type":"Point"}
}