{
  "type": "Feature",
  "properties": {
    "iso:country":"US",
    "sg:address":"2226 Eagle St",
    "sg:city":"Baltimore",
    "sg:classifiers":[
        {
            "category":"Retail",
            "subcategory":"Auto Repair",
            "type":"Services"
        }
    ],
    "sg:phone":"+1 410 814 6800",
    "sg:postcode":"21223",
    "sg:province":"MD",
    "wof:name":"Tommy Meeks Mechanic Shop",
    "wof:placetype":"venue"
},
  "geometry": {"coordinates":[-76.650538,39.280025],"type":"Point"}
}