{
  "type": "Feature",
  "properties": {
    "iso:country":"US",
    "sg:address":"1409 N Central Ave",
    "sg:city":"Baltimore",
    "sg:classifiers":[
        {
            "category":"Autos & Motor Vehicles",
            "subcategory":"Auto Supplies",
            "type":"Retail Goods"
        }
    ],
    "sg:phone":"+1 443 844 5245",
    "sg:postcode":"21202",
    "sg:province":"MD",
    "sg:tags":[
        "automobile",
        "part"
    ],
    "wof:name":"O & P Product Conversion, Inc",
    "wof:placetype":"venue"
},
  "geometry": {"coordinates":[-76.600604,39.306209],"type":"Point"}
}