{
  "type": "Feature",
  "properties": {
    "addr:full":"1110 Professional Ct Hagerstown MD 21740",
    "addr:housenumber":"1110",
    "addr:postcode":"21740",
    "addr:street":"Professional Ct",
    "iso:country":"US",
    "sg:address":"1110 Professional Ct",
    "sg:city":"Hagerstown",
    "sg:classifiers":[
        {
            "category":"Health Services",
            "subcategory":"Doctor",
            "type":"Services"
        }
    ],
    "sg:phone":"+1 301 745 4219",
    "sg:postcode":"21740",
    "sg:province":"MD",
    "sg:tags":[
        "physician",
        "surgeon"
    ],
    "wof:name":"American Radiology Svc",
    "wof:placetype":"venue"
},
  "geometry": {"coordinates":[-77.69538,39.63725],"type":"Point"}
}