{
  "type": "Feature",
  "properties": {
    "iso:country":"US",
    "sg:address":"7133 Rutherford Rd Ste 412",
    "sg:city":"Windsor Mill",
    "sg:classifiers":[
        {
            "category":"Banks & Credit Unions",
            "subcategory":"Financial Services",
            "type":"Services"
        }
    ],
    "sg:phone":"+1 410 594 9200",
    "sg:postcode":"21244",
    "sg:province":"MD",
    "sg:tags":[
        "broker",
        "mortgage"
    ],
    "wof:name":"US Diversified Mortgage",
    "wof:placetype":"venue"
},
  "geometry": {"coordinates":[-76.747299,39.327702],"type":"Point"}
}