{
  "type": "Feature",
  "properties": {
    "iso:country":"US",
    "sg:address":"5320 Western Ave",
    "sg:city":"Chevy Chase",
    "sg:classifiers":[
        {
            "category":"Shopping",
            "subcategory":"Clothing, Apparel, & Fashions",
            "type":"Retail Goods"
        }
    ],
    "sg:phone":"+1 301 652 1163",
    "sg:postcode":"20815",
    "sg:province":"MD",
    "sg:tags":[
        "clothing",
        "women's"
    ],
    "sg:website":"www.talbots.com",
    "wof:name":"Talbots Misses Petites Women 20",
    "wof:placetype":"venue"
},
  "geometry": {"coordinates":[-77.087802,38.95935],"type":"Point"}
}