{
  "type": "Feature",
  "properties": {
    "addr:full":"8811 Stoneridge Cir Apt 301 Pikesville MD 21208",
    "addr:housenumber":"8811;301",
    "addr:postcode":"21208",
    "addr:street":"Stoneridge Cir Apt",
    "iso:country":"US",
    "sg:address":"8811 Stoneridge Cir Apt 301",
    "sg:city":"Pikesville",
    "sg:classifiers":[
        {
            "category":"Health Services",
            "subcategory":"Hospital",
            "type":"Services"
        }
    ],
    "sg:phone":"+1 410 833 4047",
    "sg:postcode":"21208",
    "sg:province":"MD",
    "sg:tags":[
        "sleep",
        "treatment",
        "disorders-information"
    ],
    "wof:name":"Northwest Enrichment Center",
    "wof:placetype":"venue"
},
  "geometry": {"coordinates":[-76.783294,39.389463],"type":"Point"}
}