{
  "type": "Feature",
  "properties": {
    "addr:full":"107 E Cecil Ave North East MD 21901",
    "addr:housenumber":"107",
    "addr:postcode":"21901",
    "addr:street":"E Cecil Ave North",
    "iso:country":"US",
    "sg:address":"107 E Cecil Ave",
    "sg:city":"North East",
    "sg:classifiers":[
        {
            "category":"Professional",
            "subcategory":"Accounting & Tax Preparation",
            "type":"Services"
        }
    ],
    "sg:phone":"+1 410 287 5771",
    "sg:postcode":"21901",
    "sg:province":"MD",
    "sg:tags":[
        "return",
        "filing"
    ],
    "wof:name":"Taylor Associates",
    "wof:placetype":"venue"
},
  "geometry": {"coordinates":[-75.94108799999999,39.601285],"type":"Point"}
}