{
  "type": "Feature",
  "properties": {
    "iso:country":"US",
    "sg:address":"4401 Ferrara Dr",
    "sg:city":"Silver Spring",
    "sg:classifiers":[
        {
            "category":"Professional",
            "type":"Services"
        }
    ],
    "sg:phone":"+1 301 933 1864",
    "sg:postcode":"20906",
    "sg:province":"MD",
    "wof:name":"Katherine Kahn Janus",
    "wof:placetype":"venue"
},
  "geometry": {"coordinates":[-77.086822,39.050762],"type":"Point"}
}