{
  "type": "Feature",
  "properties": {
    "iso:country":"US",
    "sg:address":"158 Dunlap Rd",
    "sg:city":"Pasadena",
    "sg:classifiers":[
        {
            "category":"Restaurant",
            "type":"Food & Drink"
        }
    ],
    "sg:phone":"+1 410 255 1692",
    "sg:postcode":"21122",
    "sg:province":"MD",
    "wof:name":"Barker Enterprises",
    "wof:placetype":"venue"
},
  "geometry": {"coordinates":[-76.505543,39.15801],"type":"Point"}
}