{
  "type": "Feature",
  "properties": {
    "addr:full":"2411 W Belvedere Ave Baltimore MD 21215",
    "addr:housenumber":"2411",
    "addr:postcode":"21215",
    "addr:street":"W Belvedere Ave",
    "iso:country":"US",
    "sg:address":"2411 W Belvedere Ave",
    "sg:city":"Baltimore",
    "sg:classifiers":[
        {
            "category":"Health Services",
            "subcategory":"Doctor",
            "type":"Services"
        }
    ],
    "sg:phone":"+1 410 601 9801",
    "sg:postcode":"21215",
    "sg:province":"MD",
    "wof:name":"Wheeless Clifford R MD",
    "wof:placetype":"venue"
},
  "geometry": {"coordinates":[-76.66349099999999,39.353668],"type":"Point"}
}