{
  "type": "Feature",
  "properties": {
    "iso:country":"US",
    "sg:address":"14513 Main St",
    "sg:city":"Upper Marlboro",
    "sg:classifiers":[
        {
            "category":"Professional",
            "subcategory":"Management & Consulting",
            "type":"Services"
        }
    ],
    "sg:phone":"+1 240 508 7247",
    "sg:postcode":"20772",
    "sg:province":"MD",
    "wof:name":"Marcia Nwosu",
    "wof:placetype":"venue"
},
  "geometry": {"coordinates":[-76.75379100000001,38.81559],"type":"Point"}
}