{
  "type": "Feature",
  "properties": {
    "iso:country":"US",
    "sg:address":"5447 Park Heights Ave",
    "sg:city":"Baltimore",
    "sg:classifiers":[
        {
            "category":"Sports & Exercise",
            "subcategory":"Bicycle Rental",
            "type":"Entertainment"
        }
    ],
    "sg:phone":"+1 410 542 6009",
    "sg:postcode":"21215",
    "sg:province":"MD",
    "sg:tags":[
        "wear"
    ],
    "wof:name":"The Sports Fan",
    "wof:placetype":"venue"
},
  "geometry": {"coordinates":[-76.68270099999999,39.351299],"type":"Point"}
}