{
  "type": "Feature",
  "properties": {
    "iso:country":"US",
    "sg:address":"15815 Kruhm Rd",
    "sg:city":"Burtonsville",
    "sg:classifiers":[
        {
            "category":"Retail",
            "subcategory":"Animal Services",
            "type":"Services"
        }
    ],
    "sg:phone":"+1 301 384 5547",
    "sg:postcode":"20866",
    "sg:province":"MD",
    "wof:name":"Shetland Sheepdogs Of Lingard",
    "wof:placetype":"venue"
},
  "geometry": {"coordinates":[-76.947585,39.117722],"type":"Point"}
}