{
  "type": "Feature",
  "properties": {
    "addr:full":"15815 Kruhm Rd Burtonsville MD 20866",
    "addr:housenumber":"15815",
    "addr:postcode":"20866",
    "addr:street":"Kruhm Rd",
    "iso:country":"US",
    "sg:address":"15815 Kruhm Rd",
    "sg:city":"Burtonsville",
    "sg:classifiers":[
        {
            "category":"Retail",
            "subcategory":"Animal Services",
            "type":"Services"
        }
    ],
    "sg:phone":"+1 301 384 5547",
    "sg:postcode":"20866",
    "sg:province":"MD",
    "wof:name":"Shetland Sheepdogs Of Lingard",
    "wof:placetype":"venue"
},
  "geometry": {"coordinates":[-76.947585,39.117722],"type":"Point"}
}