{
  "type": "Feature",
  "properties": {
    "iso:country":"US",
    "sg:address":"4411 Saint Barnabas Rd",
    "sg:city":"Temple Hills",
    "sg:classifiers":[
        {
            "category":"Food & Beverages",
            "subcategory":"Groceries & Convenience Stores",
            "type":"Retail Goods"
        }
    ],
    "sg:phone":"+1 301 316 3299",
    "sg:postcode":"20748",
    "sg:province":"MD",
    "wof:name":"Jj Food Mart Inc",
    "wof:placetype":"venue"
},
  "geometry": {"coordinates":[-76.943017,38.828925],"type":"Point"}
}