{
  "type": "Feature",
  "properties": {
    "addr:full":"7401 Osler Dr Towson MD 21204",
    "addr:housenumber":"7401",
    "addr:postcode":"21204",
    "addr:street":"Osler Dr",
    "iso:country":"US",
    "sg:address":"7401 Osler Dr",
    "sg:city":"Towson",
    "sg:classifiers":[
        {
            "category":"Health Services",
            "subcategory":"Doctor",
            "type":"Services"
        }
    ],
    "sg:phone":"+1 410 823 3885",
    "sg:postcode":"21204",
    "sg:province":"MD",
    "sg:tags":[
        "physician",
        "reconstructive",
        "surgeons",
        "cosmetic",
        "plastic",
        "surgery",
        "surgeon",
        "surgery-general"
    ],
    "sg:website":"http://drringelman.com",
    "wof:name":"Wilhelmsen & Associates PA",
    "wof:placetype":"venue"
},
  "geometry": {"coordinates":[-76.611099,39.383492],"type":"Point"}
}