{
  "type": "Feature",
  "properties": {
    "iso:country":"US",
    "sg:address":"326 Hill Top Rd",
    "sg:city":"Oakland",
    "sg:classifiers":[
        {
            "category":"Manufacturing",
            "subcategory":"Apparel",
            "type":"Manufacturing & Wholesale Goods"
        }
    ],
    "sg:phone":"+1 301 533 0750",
    "sg:postcode":"21550",
    "sg:province":"MD",
    "wof:name":"National Institute For Safety",
    "wof:placetype":"venue"
},
  "geometry": {"coordinates":[-79.480933,39.323325],"type":"Point"}
}