{
  "type": "Feature",
  "properties": {
    "addr:full":"209 Washington Blvd Laurel MD 20707",
    "addr:housenumber":"209",
    "addr:postcode":"20707",
    "addr:street":"Washington Blvd",
    "iso:country":"US",
    "sg:address":"209 Washington Blvd",
    "sg:city":"Laurel",
    "sg:classifiers":[
        {
            "category":"Organizations",
            "subcategory":"Professional Association",
            "type":"Services"
        }
    ],
    "sg:phone":"+1 301 725 4304",
    "sg:postcode":"20707",
    "sg:province":"MD",
    "wof:name":"Laurel Wreath Masonic Lodge",
    "wof:placetype":"venue"
},
  "geometry": {"coordinates":[-76.84571800000001,39.102146],"type":"Point"}
}