{
  "type": "Feature",
  "properties": {
    "iso:country":"US",
    "sg:address":"209 Washington Blvd",
    "sg:city":"Laurel",
    "sg:classifiers":[
        {
            "category":"Organizations",
            "subcategory":"Professional Association",
            "type":"Services"
        }
    ],
    "sg:phone":"+1 301 725 4304",
    "sg:postcode":"20707",
    "sg:province":"MD",
    "wof:name":"Laurel Wreath Masonic Lodge",
    "wof:placetype":"venue"
},
  "geometry": {"coordinates":[-76.845718,39.102146],"type":"Point"}
}