{
  "type": "Feature",
  "properties": {
    "iso:country":"US",
    "sg:address":"2435 W Belvedere Ave",
    "sg:city":"Baltimore",
    "sg:classifiers":[
        {
            "category":"Health Services",
            "subcategory":"Doctor",
            "type":"Services"
        }
    ],
    "sg:phone":"+1 410 601 8389",
    "sg:postcode":"21215",
    "sg:province":"MD",
    "sg:tags":[
        "physician",
        "surgeon"
    ],
    "wof:name":"John Meyerhoff MD",
    "wof:placetype":"venue"
},
  "geometry": {"coordinates":[-76.663302,39.353899],"type":"Point"}
}