{
  "type": "Feature",
  "properties": {
    "iso:country":"US",
    "sg:address":"23 E Patrick St",
    "sg:city":"Frederick",
    "sg:classifiers":[
        {
            "category":"Professional",
            "subcategory":"Lawyer & Legal Services",
            "type":"Services"
        }
    ],
    "sg:phone":"+1 301 695 7850",
    "sg:postcode":"21701",
    "sg:province":"MD",
    "sg:tags":[
        "attorney",
        "plan"
    ],
    "wof:name":"Lloyd Byron Hopkins PC",
    "wof:placetype":"venue"
},
  "geometry": {"coordinates":[-77.41054099999999,39.414141],"type":"Point"}
}