{
  "type": "Feature",
  "properties": {
    "iso:country":"US",
    "sg:address":"8523 Piney Branch Rd",
    "sg:city":"Silver Spring",
    "sg:classifiers":[
        {
            "category":"Restaurant",
            "type":"Food & Drink"
        }
    ],
    "sg:phone":"+1 301 650 5400",
    "sg:postcode":"20901",
    "sg:province":"MD",
    "wof:name":"Puerto El Trunfo",
    "wof:placetype":"venue"
},
  "geometry": {"coordinates":[-77.002539,38.998252],"type":"Point"}
}