{
  "type": "Feature",
  "properties": {
    "iso:country":"US",
    "sg:address":"1 E Lexington St",
    "sg:city":"Baltimore",
    "sg:classifiers":[
        {
            "category":"Professional",
            "subcategory":"Lawyer & Legal Services",
            "type":"Services"
        }
    ],
    "sg:phone":"+1 410 539 3480",
    "sg:postcode":"21202",
    "sg:province":"MD",
    "sg:tags":[
        "attorney"
    ],
    "wof:name":"Raysor Taylor Law Office",
    "wof:placetype":"venue"
},
  "geometry": {"coordinates":[-76.61397599999999,39.29117],"type":"Point"}
}