{
  "type": "Feature",
  "properties": {
    "addr:full":"8125 48th Ave College Park MD 20740",
    "addr:housenumber":"8125",
    "addr:postcode":"20740",
    "addr:street":"48Th Ave",
    "iso:country":"US",
    "sg:address":"8125 48th Ave",
    "sg:city":"College Park",
    "sg:classifiers":[
        {
            "category":"Real Estate",
            "subcategory":"Real Estate Operator",
            "type":"Services"
        }
    ],
    "sg:phone":"+1 301 474 0085",
    "sg:postcode":"20740",
    "sg:province":"MD",
    "sg:tags":[
        "apartment"
    ],
    "wof:name":"Berkley",
    "wof:placetype":"venue"
},
  "geometry": {"coordinates":[-76.932326,38.989449],"type":"Point"}
}