{
  "type": "Feature",
  "properties": {
    "iso:country":"US",
    "sg:address":"12029 Wetherfield Ln",
    "sg:city":"Potomac",
    "sg:classifiers":[
        {
            "category":"Professional",
            "subcategory":"Lawyer & Legal Services",
            "type":"Services"
        }
    ],
    "sg:phone":"+1 301 977 6481",
    "sg:postcode":"20854",
    "sg:province":"MD",
    "wof:name":"Wahl Barbara S Atty",
    "wof:placetype":"venue"
},
  "geometry": {"coordinates":[-77.259201,39.054298],"type":"Point"}
}