{
  "type": "Feature",
  "properties": {
    "addr:full":"30 25th St Baltimore MD 21201",
    "addr:housenumber":"30",
    "addr:postcode":"21201",
    "addr:street":"25Th St",
    "iso:country":"US",
    "sg:address":"30 25th St",
    "sg:city":"Baltimore",
    "sg:classifiers":[
        {
            "category":"Real Estate",
            "subcategory":"Architect",
            "type":"Services"
        }
    ],
    "sg:phone":"+1 410 662 5599",
    "sg:postcode":"21201",
    "sg:province":"MD",
    "wof:name":"Qodesh Professional Services Inc",
    "wof:placetype":"venue"
},
  "geometry": {"coordinates":[-76.616525,39.317962],"type":"Point"}
}