{
  "type": "Feature",
  "properties": {
    "iso:country":"US",
    "sg:address":"4203 Sanner Ave",
    "sg:city":"Baltimore",
    "sg:classifiers":[
        {
            "category":"Restaurant",
            "type":"Food & Drink"
        }
    ],
    "sg:phone":"+1 410 483 2722",
    "sg:postcode":"21206",
    "sg:province":"MD",
    "sg:tags":[
        "seafood"
    ],
    "wof:name":"Mackeys Crab House",
    "wof:placetype":"venue"
},
  "geometry": {"coordinates":[-76.562044,39.330689],"type":"Point"}
}