{
  "type": "Feature",
  "properties": {
    "iso:country":"US",
    "sg:address":"6150 Greenbelt Rd",
    "sg:city":"Greenbelt",
    "sg:classifiers":[
        {
            "category":"Restaurant",
            "type":"Food & Drink"
        }
    ],
    "sg:phone":"+1 301 345 0500",
    "sg:postcode":"20770",
    "sg:province":"MD",
    "wof:name":"Bun Cafe",
    "wof:placetype":"venue"
},
  "geometry": {"coordinates":[-76.90783500000001,38.997326],"type":"Point"}
}