{
  "type": "Feature",
  "properties": {
    "iso:country":"US",
    "sg:address":"4027 Emerald Ln Apt A",
    "sg:city":"Bowie",
    "sg:classifiers":[
        {
            "category":"Professional",
            "subcategory":"Detective & Security Services",
            "type":"Services"
        }
    ],
    "sg:phone":"+1 302 275 6668",
    "sg:postcode":"20716",
    "sg:province":"MD",
    "sg:tags":[
        "car",
        "armored",
        "private",
        "investigator"
    ],
    "wof:name":"Alexandra T Suttell",
    "wof:placetype":"venue"
},
  "geometry": {"coordinates":[-76.728184,38.944261],"type":"Point"}
}