{
  "type": "Feature",
  "properties": {
    "iso:country":"US",
    "sg:address":"7600 Osler Dr",
    "sg:city":"Towson",
    "sg:classifiers":[
        {
            "category":"Health Services",
            "subcategory":"Doctor",
            "type":"Services"
        }
    ],
    "sg:phone":"+1 410 821 6242",
    "sg:postcode":"21204",
    "sg:province":"MD",
    "sg:tags":[
        "dentist"
    ],
    "wof:name":"Thomas C Llewellyn DDS",
    "wof:placetype":"venue"
},
  "geometry": {"coordinates":[-76.614762,39.393384],"type":"Point"}
}