{
  "type": "Feature",
  "properties": {
    "iso:country":"US",
    "sg:address":"4905 del Ray Ave",
    "sg:city":"Bethesda",
    "sg:classifiers":[
        {
            "category":"Professional",
            "type":"Services"
        }
    ],
    "sg:phone":"+1 301 951 0763",
    "sg:postcode":"20814",
    "sg:province":"MD",
    "sg:tags":[
        "establishment"
    ],
    "sg:website":"www.theadvantagegroup.com",
    "wof:name":"Advantage Grp",
    "wof:placetype":"venue"
},
  "geometry": {"coordinates":[-77.100279,38.988485],"type":"Point"}
}