{
  "type": "Feature",
  "properties": {
    "addr:full":"1576 Merritt Blvd Baltimore MD 21222",
    "addr:housenumber":"1576",
    "addr:postcode":"21222",
    "addr:street":"Merritt Blvd",
    "iso:country":"US",
    "sg:address":"1576 Merritt Blvd",
    "sg:city":"Baltimore",
    "sg:classifiers":[
        {
            "category":"Health Services",
            "subcategory":"Doctor",
            "type":"Services"
        }
    ],
    "sg:phone":"+1 410 282 2992",
    "sg:postcode":"21222",
    "sg:province":"MD",
    "sg:tags":[
        "physician",
        "surgeon"
    ],
    "wof:name":"Mukesh Luhar MD",
    "wof:placetype":"venue"
},
  "geometry": {"coordinates":[-76.503112,39.27351],"type":"Point"}
}