{
  "type": "Feature",
  "properties": {
    "iso:country":"US",
    "sg:address":"805 Brightseat Rd",
    "sg:city":"Hyattsville",
    "sg:classifiers":[
        {
            "category":"Organizations",
            "subcategory":"Non-profit Organization",
            "type":"Services"
        }
    ],
    "sg:phone":"+1 301 909 7000",
    "sg:postcode":"20785",
    "sg:province":"MD",
    "sg:tags":[
        "social"
    ],
    "wof:name":"Prince Grg Cnty Dept Scl Svcs",
    "wof:placetype":"venue"
},
  "geometry": {"coordinates":[-76.853054,38.899531],"type":"Point"}
}