{
  "type": "Feature",
  "properties": {
    "addr:full":"2401 Stringtown Rd Sparks Glencoe MD 21152",
    "addr:housenumber":"2401",
    "addr:postcode":"21152",
    "addr:street":"Stringtown Rd",
    "iso:country":"US",
    "sg:address":"2401 Stringtown Rd",
    "sg:city":"Sparks Glencoe",
    "sg:classifiers":[
        {
            "category":"Building & Trades",
            "subcategory":"Construction",
            "type":"Services"
        }
    ],
    "sg:phone":"+1 410 771 4311",
    "sg:postcode":"21152",
    "sg:province":"MD",
    "sg:tags":[
        "paving",
        "contractor"
    ],
    "sg:website":"www.grayandson.com",
    "wof:name":"Gray & Sons",
    "wof:placetype":"venue"
},
  "geometry": {"coordinates":[-76.732857,39.543697],"type":"Point"}
}