{
  "type": "Feature",
  "properties": {
    "addr:full":"1301 W Patrick St Frederick MD 21702",
    "addr:housenumber":"1301",
    "addr:postcode":"21702",
    "addr:street":"W Patrick St",
    "iso:country":"US",
    "sg:address":"1301 W Patrick St",
    "sg:city":"Frederick",
    "sg:classifiers":[
        {
            "category":"Shopping",
            "subcategory":"Hobbies, Toys, & Games",
            "type":"Retail Goods"
        }
    ],
    "sg:phone":"+1 301 620 1750",
    "sg:postcode":"21702",
    "sg:province":"MD",
    "sg:tags":[
        "craft"
    ],
    "wof:name":"Everest Handicrafts",
    "wof:placetype":"venue"
},
  "geometry": {"coordinates":[-77.461175,39.419658],"type":"Point"}
}