{
  "type": "Feature",
  "properties": {
    "iso:country":"US",
    "sg:address":"3818 Bay Rd",
    "sg:city":"Street",
    "sg:classifiers":[
        {
            "category":"Professional",
            "type":"Services"
        }
    ],
    "sg:phone":"+1 410 452 5076",
    "sg:postcode":"21154",
    "sg:province":"MD",
    "sg:tags":[
        "establishment"
    ],
    "wof:name":"Ramlynx Corp",
    "wof:placetype":"venue"
},
  "geometry": {"coordinates":[-76.32853799999999,39.673578],"type":"Point"}
}