{
  "type": "Feature",
  "properties": {
    "addr:full":"7415 Pomfret Rd La Plata MD 20646",
    "addr:housenumber":"7415",
    "addr:postcode":"20646",
    "addr:street":"Pomfret Rd",
    "iso:country":"US",
    "sg:address":"7415 Pomfret Rd",
    "sg:city":"La Plata",
    "sg:classifiers":[
        {
            "category":"Personal",
            "subcategory":"Beauty Salon",
            "type":"Services"
        }
    ],
    "sg:phone":"+1 301 248 3933",
    "sg:postcode":"20646",
    "sg:province":"MD",
    "sg:tags":[
        "shop"
    ],
    "wof:name":"Hair Trends",
    "wof:placetype":"venue"
},
  "geometry": {"coordinates":[-77.05111599999999,38.590518],"type":"Point"}
}