{
  "type": "Feature",
  "properties": {
    "addr:full":"8401 Carlson Ln Windsor Mill MD 21244",
    "addr:housenumber":"8401",
    "addr:postcode":"21244",
    "addr:street":"Carlson Ln",
    "iso:country":"US",
    "sg:address":"8401 Carlson Ln",
    "sg:city":"Windsor Mill",
    "sg:classifiers":[
        {
            "category":"Social Services",
            "subcategory":"Child Care",
            "type":"Services"
        }
    ],
    "sg:phone":"+1 410 655 2244",
    "sg:postcode":"21244",
    "sg:province":"MD",
    "wof:name":"Kid's Place At Northwest Hosp",
    "wof:placetype":"venue"
},
  "geometry": {"coordinates":[-76.782033,39.356916],"type":"Point"}
}