{
  "type": "Feature",
  "properties": {
    "addr:full":"7645 Arundel Mills Blvd Hanover MD 21076",
    "addr:housenumber":"7645",
    "addr:postcode":"21076",
    "addr:street":"Arundel Mills Blvd",
    "iso:country":"US",
    "sg:address":"7645 Arundel Mills Blvd",
    "sg:city":"Hanover",
    "sg:classifiers":[
        {
            "category":"Manufacturing",
            "subcategory":"Buildings",
            "type":"Manufacturing & Wholesale Goods"
        },
        {
            "category":"Building & Trades",
            "subcategory":"Construction",
            "type":"Services"
        }
    ],
    "sg:phone":"+1 410 799 9130",
    "sg:postcode":"21076",
    "sg:province":"MD",
    "sg:tags":[
        "industrial",
        "system",
        "specialty",
        "builder",
        "heating",
        "contractor",
        "contractors-commercial",
        "home",
        "air conditioning"
    ],
    "wof:name":"Eden's Ridge E & A",
    "wof:placetype":"venue"
},
  "geometry": {"coordinates":[-76.73005999999999,39.152899],"type":"Point"}
}