{
  "type": "Feature",
  "properties": {
    "addr:full":"1 S Janney St Baltimore MD 21224",
    "addr:housenumber":"1",
    "addr:postcode":"21224",
    "addr:street":"S Janney St",
    "iso:country":"US",
    "sg:address":"1 S Janney St",
    "sg:city":"Baltimore",
    "sg:classifiers":[
        {
            "category":"Retail",
            "subcategory":"Auto Repair",
            "type":"Services"
        }
    ],
    "sg:phone":"+1 410 342 4396",
    "sg:postcode":"21224",
    "sg:province":"MD",
    "sg:tags":[
        "repairing",
        "tire"
    ],
    "wof:name":"E C Burkhardt Co",
    "wof:placetype":"venue"
},
  "geometry": {"coordinates":[-76.56086999999999,39.291668],"type":"Point"}
}