{
  "type": "Feature",
  "properties": {
    "addr:full":"8433 Woodward St Savage MD 20763",
    "addr:housenumber":"8433",
    "addr:postcode":"20763",
    "addr:street":"Woodward St",
    "iso:country":"US",
    "sg:address":"8433 Woodward St",
    "sg:city":"Savage",
    "sg:classifiers":[
        {
            "category":"Social Services",
            "type":"Services"
        }
    ],
    "sg:phone":"+1 301 497 1119",
    "sg:postcode":"20763",
    "sg:province":"MD",
    "sg:tags":[
        "physician",
        "surgeon",
        "instruction",
        "health",
        "care"
    ],
    "wof:name":"Surecare Healthcare",
    "wof:placetype":"venue"
},
  "geometry": {"coordinates":[-76.821929,39.139758],"type":"Point"}
}