{
  "type": "Feature",
  "properties": {
    "addr:full":"10902 Old Princess Anne Rd Westover MD 21871",
    "addr:housenumber":"10902",
    "addr:postcode":"21871",
    "addr:street":"Old Princess Anne Rd",
    "iso:country":"US",
    "sg:address":"10902 Old Princess Anne Rd",
    "sg:city":"Westover",
    "sg:classifiers":[
        {
            "category":"Education",
            "subcategory":"School",
            "type":"Public Place"
        }
    ],
    "sg:phone":"+1 410 651 3489",
    "sg:postcode":"21871",
    "sg:province":"MD",
    "sg:tags":[
        "k-",
        "private"
    ],
    "wof:name":"Somerset County Board Of Education",
    "wof:placetype":"venue"
},
  "geometry": {"coordinates":[-75.690994,38.125977],"type":"Point"}
}