{
  "type": "Feature",
  "properties": {
    "addr:full":"5817 Rolling Dr Derwood MD 20855",
    "addr:housenumber":"5817",
    "addr:postcode":"20855",
    "addr:street":"Rolling Dr",
    "iso:country":"US",
    "sg:address":"5817 Rolling Dr",
    "sg:city":"Derwood",
    "sg:classifiers":[
        {
            "category":"Structure",
            "subcategory":"Office Building",
            "type":"Public Place"
        }
    ],
    "sg:phone":"+1 301 977 7778",
    "sg:postcode":"20855",
    "sg:province":"MD",
    "sg:tags":[
        "park"
    ],
    "wof:name":"Kingsview Properties",
    "wof:placetype":"venue"
},
  "geometry": {"coordinates":[-77.11843399999999,39.172991],"type":"Point"}
}