{
  "type": "Feature",
  "properties": {
    "iso:country":"US",
    "sg:address":"755 Hungerford Dr",
    "sg:city":"Rockville",
    "sg:classifiers":[
        {
            "category":"Restaurant",
            "type":"Food & Drink"
        }
    ],
    "sg:phone":"+1 301 294 0808",
    "sg:postcode":"20850",
    "sg:province":"MD",
    "sg:tags":[
        "asian",
        "chinese",
        "pan"
    ],
    "wof:name":"Sushi Train",
    "wof:placetype":"venue"
},
  "geometry": {"coordinates":[-77.15333699999999,39.093239],"type":"Point"}
}