{
  "type": "Feature",
  "properties": {
    "iso:country":"US",
    "sg:address":"5310 Baltimore Ave",
    "sg:city":"Hyattsville",
    "sg:classifiers":[
        {
            "category":"Restaurant",
            "type":"Food & Drink"
        }
    ],
    "sg:phone":"+1 301 768 4137",
    "sg:postcode":"20781",
    "sg:province":"MD",
    "sg:website":"pikerotisserieandgrill.com",
    "wof:name":"Pike Rotisserie & Grill",
    "wof:placetype":"venue"
},
  "geometry": {"coordinates":[-76.94064299999999,38.954045],"type":"Point"}
}