{
  "type": "Feature",
  "properties": {
    "iso:country":"US",
    "sg:address":"2405 Chesterfield Ave",
    "sg:city":"Baltimore",
    "sg:classifiers":[
        {
            "category":"Professional",
            "subcategory":"Lawyer & Legal Services",
            "type":"Services"
        }
    ],
    "sg:phone":"+1 410 366 5316",
    "sg:postcode":"21213",
    "sg:province":"MD",
    "sg:tags":[
        "attorney",
        "business",
        "corporation",
        "partnership",
        "law"
    ],
    "wof:name":"Oi Partners Inc",
    "wof:placetype":"venue"
},
  "geometry": {"coordinates":[-76.577061,39.329798],"type":"Point"}
}