{
  "type": "Feature",
  "properties": {
    "addr:full":"4101 Crain Hwy Bowie MD 20716",
    "addr:housenumber":"4101",
    "addr:postcode":"20716",
    "addr:street":"Crain Hwy",
    "iso:country":"US",
    "sg:address":"4101 Crain Hwy",
    "sg:city":"Bowie",
    "sg:phone":"+1 301 464 4806",
    "sg:postcode":"20716",
    "sg:province":"MD",
    "wof:name":"Bowie Baysox Drive-In",
    "wof:placetype":"venue"
},
  "geometry": {"coordinates":[-76.71779600000001,38.945648],"type":"Point"}
}