{
  "type": "Feature",
  "properties": {
    "iso:country":"US",
    "sg:address":"10314 Floral Dr",
    "sg:city":"Adelphi",
    "sg:classifiers":[
        {
            "category":"Restaurant",
            "type":"Food & Drink"
        }
    ],
    "sg:phone":"+1 301 439 7435",
    "sg:postcode":"20783",
    "sg:province":"MD",
    "wof:name":"Clapp Delight",
    "wof:placetype":"venue"
},
  "geometry": {"coordinates":[-76.96113200000001,39.021853],"type":"Point"}
}