{
  "type": "Feature",
  "properties": {
    "iso:country":"US",
    "sg:address":"2315 Bel Air Rd",
    "sg:city":"Fallston",
    "sg:classifiers":[
        {
            "category":"Manufacturing",
            "subcategory":"Apparel",
            "type":"Manufacturing & Wholesale Goods"
        }
    ],
    "sg:phone":"+1 410 879 5202",
    "sg:postcode":"21047",
    "sg:province":"MD",
    "sg:tags":[
        "sewing",
        "contractor"
    ],
    "wof:name":"Apple Monograms",
    "wof:placetype":"venue"
},
  "geometry": {"coordinates":[-76.392786,39.492971],"type":"Point"}
}