{
  "type": "Feature",
  "properties": {
    "addr:full":"8238 14th Ave Apt 203 Hyattsville MD 20783",
    "addr:housenumber":"8238;203",
    "addr:postcode":"20783",
    "addr:street":"14Th Ave Apt",
    "iso:country":"US",
    "sg:address":"8238 14th Ave Apt 203",
    "sg:city":"Hyattsville",
    "sg:classifiers":[
        {
            "category":"Building & Trades",
            "subcategory":"Construction",
            "type":"Services"
        }
    ],
    "sg:phone":"+1 301 439 7429",
    "sg:postcode":"20783",
    "sg:province":"MD",
    "sg:tags":[
        "contractor"
    ],
    "wof:name":"Nolasco General Contractors",
    "wof:placetype":"venue"
},
  "geometry": {"coordinates":[-76.984296,38.992551],"type":"Point"}
}