{
  "type": "Feature",
  "properties": {
    "addr:full":"7916 Stansbury Rd Baltimore MD 21222",
    "addr:housenumber":"7916",
    "addr:postcode":"21222",
    "addr:street":"Stansbury Rd",
    "iso:country":"US",
    "sg:address":"7916 Stansbury Rd",
    "sg:city":"Baltimore",
    "sg:classifiers":[
        {
            "category":"Wholesale",
            "subcategory":"Metals & Minerals",
            "type":"Manufacturing & Wholesale Goods"
        }
    ],
    "sg:phone":"+1 410 285 5646",
    "sg:postcode":"21222",
    "sg:province":"MD",
    "sg:tags":[
        "product",
        "wire"
    ],
    "wof:name":"L E Jones Wire Cloth",
    "wof:placetype":"venue"
},
  "geometry": {"coordinates":[-76.500327,39.256374],"type":"Point"}
}