{
  "type": "Feature",
  "properties": {
    "addr:full":"4201 Cathedral Ave NW Washington MD 20016",
    "addr:housenumber":"4201",
    "addr:postcode":"20016",
    "addr:street":"Cathedral Ave Nw",
    "iso:country":"US",
    "sg:address":"4201 Cathedral Ave NW",
    "sg:city":"Washington",
    "sg:classifiers":[
        {
            "category":"Shopping",
            "subcategory":"Clothing, Apparel, & Fashions",
            "type":"Retail Goods"
        }
    ],
    "sg:phone":"+1 202 363 9099",
    "sg:postcode":"20016",
    "sg:province":"MD",
    "sg:tags":[
        "designer"
    ],
    "wof:name":"Haute Couture Inc",
    "wof:placetype":"venue"
},
  "geometry": {"coordinates":[-77.083995,38.930277],"type":"Point"}
}