{
  "type": "Feature",
  "properties": {
    "iso:country":"US",
    "sg:address":"208 E Baltimore St",
    "sg:city":"Baltimore",
    "sg:classifiers":[
        {
            "category":"Organizations",
            "subcategory":"Membership Organization",
            "type":"Services"
        },
        {
            "category":"Government",
            "subcategory":"Office",
            "type":"Public Place"
        }
    ],
    "sg:phone":"+1 410 347 2270",
    "sg:postcode":"21202",
    "sg:province":"MD",
    "wof:name":"Maryland You Are Beautiful",
    "wof:placetype":"venue"
},
  "geometry": {"coordinates":[-76.61111,39.289773],"type":"Point"}
}