{
  "type": "Feature",
  "properties": {
    "addr:full":"1616 Bolton St Baltimore MD 21217",
    "addr:housenumber":"1616",
    "addr:postcode":"21217",
    "addr:street":"Bolton St",
    "iso:country":"US",
    "sg:address":"1616 Bolton St",
    "sg:city":"Baltimore",
    "sg:classifiers":[
        {
            "category":"Health Services",
            "subcategory":"Doctor",
            "type":"Services"
        }
    ],
    "sg:phone":"+1 410 955 2883",
    "sg:postcode":"21217",
    "sg:province":"MD",
    "wof:name":"Stephens Joseph H MD",
    "wof:placetype":"venue"
},
  "geometry": {"coordinates":[-76.627724,39.307927],"type":"Point"}
}