{
  "type": "Feature",
  "properties": {
    "addr:full":"52 Stone Park Pl Nottingham MD 21236",
    "addr:housenumber":"52",
    "addr:postcode":"21236",
    "addr:street":"Stone Park Pl",
    "iso:country":"US",
    "sg:address":"52 Stone Park Pl",
    "sg:city":"Nottingham",
    "sg:classifiers":[
        {
            "category":"Retail",
            "subcategory":"Car Wash",
            "type":"Services"
        }
    ],
    "sg:phone":"+1 443 564 3375",
    "sg:postcode":"21236",
    "sg:province":"MD",
    "wof:name":"Fergie's Angel's Mobile Detailing & Pressure Washing",
    "wof:placetype":"venue"
},
  "geometry": {"coordinates":[-76.486125,39.414126],"type":"Point"}
}