{
  "type": "Feature",
  "properties": {
    "iso:country":"US",
    "sg:address":"2415 Musgrove Rd Ste 105",
    "sg:city":"Silver Spring",
    "sg:classifiers":[
        {
            "category":"Health Services",
            "subcategory":"Doctor",
            "type":"Services"
        }
    ],
    "sg:phone":"+1 301 989 0193",
    "sg:postcode":"20904",
    "sg:province":"MD",
    "sg:tags":[
        "practice",
        "family"
    ],
    "wof:name":"Montgomery Family Medicine Associates Inc",
    "wof:placetype":"venue"
},
  "geometry": {"coordinates":[-76.96060799999999,39.067821],"type":"Point"}
}