{
  "type": "Feature",
  "properties": {
    "addr:full":"13705 Heatherstone Dr Bowie MD 20720",
    "addr:housenumber":"13705",
    "addr:postcode":"20720",
    "addr:street":"Heatherstone Dr",
    "iso:country":"US",
    "sg:address":"13705 Heatherstone Dr",
    "sg:city":"Bowie",
    "sg:classifiers":[
        {
            "category":"Building & Trades",
            "subcategory":"Cleaning & Sanitation",
            "type":"Services"
        }
    ],
    "sg:phone":"+1 301 464 3526",
    "sg:postcode":"20720",
    "sg:province":"MD",
    "sg:tags":[
        "window"
    ],
    "wof:name":"J&D Window Washer & Cleaning",
    "wof:placetype":"venue"
},
  "geometry": {"coordinates":[-76.763448,38.962394],"type":"Point"}
}