{
  "type": "Feature",
  "properties": {
    "iso:country":"US",
    "sg:address":"1100 N Eutaw St",
    "sg:city":"Baltimore",
    "sg:classifiers":[
        {
            "category":"Professional",
            "subcategory":"Employment Agencies",
            "type":"Services"
        }
    ],
    "sg:phone":"+1 410 767 2133",
    "sg:postcode":"21201",
    "sg:province":"MD",
    "sg:tags":[
        "opportunity"
    ],
    "wof:name":"Baltimore Works Career Center",
    "wof:placetype":"venue"
},
  "geometry": {"coordinates":[-76.62449599999999,39.302601],"type":"Point"}
}