{
  "type": "Feature",
  "properties": {
    "iso:country":"US",
    "sg:address":"6320 Greenspring Ave",
    "sg:city":"Baltimore",
    "sg:classifiers":[
        {
            "category":"Professional",
            "subcategory":"Business Services",
            "type":"Services"
        }
    ],
    "sg:phone":"+1 410 358 5912",
    "sg:postcode":"21209",
    "sg:province":"MD",
    "sg:tags":[
        "patent",
        "searcher"
    ],
    "sg:website":"www.patentspending.com",
    "wof:name":"Patents Pending",
    "wof:placetype":"venue"
},
  "geometry": {"coordinates":[-76.682388,39.371949],"type":"Point"}
}