{
  "type": "Feature",
  "properties": {
    "iso:country":"US",
    "sg:address":"500 E Lexington St",
    "sg:city":"Baltimore",
    "sg:classifiers":[
        {
            "category":"Professional",
            "subcategory":"Lawyer & Legal Services",
            "type":"Services"
        }
    ],
    "sg:phone":"+1 410 951 7620",
    "sg:postcode":"21202",
    "sg:province":"MD",
    "wof:name":"Legal Aid of MD",
    "wof:placetype":"venue"
},
  "geometry": {"coordinates":[-76.60900100000001,39.291199],"type":"Point"}
}