{
  "type": "Feature",
  "properties": {
    "iso:country":"US",
    "sg:address":"1822 Greenleese Dr",
    "sg:city":"Frederick",
    "sg:classifiers":[
        {
            "category":"Recreation",
            "type":"Entertainment"
        }
    ],
    "sg:phone":"+1 301 668 5100",
    "sg:postcode":"21701",
    "sg:province":"MD",
    "sg:tags":[
        "historical"
    ],
    "wof:name":"Frederick County Landmark Fndt",
    "wof:placetype":"venue"
},
  "geometry": {"coordinates":[-77.372255,39.449413],"type":"Point"}
}