{
  "type": "Feature",
  "properties": {
    "iso:country":"US",
    "sg:address":"8004 Jumpers Hole Rd",
    "sg:city":"Pasadena",
    "sg:classifiers":[
        {
            "category":"Shopping",
            "subcategory":"Bicycles & Sporting Goods",
            "type":"Retail Goods"
        },
        {
            "category":"Building & Trades",
            "subcategory":"Equipment Rental",
            "type":"Services"
        },
        {
            "category":"Shopping",
            "subcategory":"Party Supplies",
            "type":"Retail Goods"
        }
    ],
    "sg:phone":"+1 410 787 8333",
    "sg:postcode":"21122",
    "sg:province":"MD",
    "sg:tags":[
        "contractors'",
        "yard",
        "tents-rental",
        "store",
        "tent"
    ],
    "sg:website":"http://www.rentalworksofmd.com",
    "wof:name":"Rental Works Pasadena & Eastern Shore",
    "wof:placetype":"venue"
},
  "geometry": {"coordinates":[-76.584351,39.13369],"type":"Point"}
}