{
  "type": "Feature",
  "properties": {
    "addr:full":"379 Deep Shore Rd Denton MD 21629",
    "addr:housenumber":"379",
    "addr:postcode":"21629",
    "addr:street":"Deep Shore Rd",
    "iso:country":"US",
    "sg:address":"379 Deep Shore Rd",
    "sg:city":"Denton",
    "sg:classifiers":[
        {
            "category":"Banks & Credit Unions",
            "subcategory":"Bank",
            "type":"Services"
        }
    ],
    "sg:phone":"+1 410 479 2323",
    "sg:postcode":"21629",
    "sg:province":"MD",
    "sg:tags":[
        "financing"
    ],
    "sg:website":"www.midatlanticfarmcredit.com",
    "wof:name":"Midatlantic Farm Credit",
    "wof:placetype":"venue"
},
  "geometry": {"coordinates":[-75.82492499999999,38.866438],"type":"Point"}
}