{
  "type": "Feature",
  "properties": {
    "addr:full":"2930 Washington Blvd Baltimore MD 21230",
    "addr:housenumber":"2930",
    "addr:postcode":"21230",
    "addr:street":"Washington Blvd",
    "iso:country":"US",
    "sg:address":"2930 Washington Blvd",
    "sg:city":"Baltimore",
    "sg:classifiers":[
        {
            "category":"Freight",
            "type":"Transportation"
        }
    ],
    "sg:phone":"+1 301 252 1220",
    "sg:postcode":"21230",
    "sg:province":"MD",
    "sg:tags":[
        "shipping"
    ],
    "sg:website":"www.runnersinc.com",
    "wof:name":"Runners Inc",
    "wof:placetype":"venue"
},
  "geometry": {"coordinates":[-76.65891499999999,39.261197],"type":"Point"}
}