{
  "type": "Feature",
  "properties": {
    "iso:country":"US",
    "sg:address":"45 Westminster Rd",
    "sg:city":"Reisterstown",
    "sg:classifiers":[
        {
            "category":"Health Services",
            "subcategory":"Health Practitioner",
            "type":"Services"
        }
    ],
    "sg:phone":"+1 410 526 3030",
    "sg:postcode":"21136",
    "sg:province":"MD",
    "sg:tags":[
        "therapist",
        "physical"
    ],
    "wof:name":"Brian Virostek Pt",
    "wof:placetype":"venue"
},
  "geometry": {"coordinates":[-76.830998,39.47029],"type":"Point"}
}