{
  "type": "Feature",
  "properties": {
    "iso:country":"US",
    "sg:address":"2611 Chestnut Hill Rd",
    "sg:city":"Forest Hill",
    "sg:classifiers":[
        {
            "category":"Professional",
            "type":"Services"
        }
    ],
    "sg:phone":"+1 410 803 7148",
    "sg:postcode":"21050",
    "sg:province":"MD",
    "wof:name":"Chesapeake Office Services",
    "wof:placetype":"venue"
},
  "geometry": {"coordinates":[-76.348447,39.60539],"type":"Point"}
}