{
  "type": "Feature",
  "properties": {
    "addr:full":"2611 Chestnut Hill Rd Forest Hill MD 21050",
    "addr:housenumber":"2611",
    "addr:postcode":"21050",
    "addr:street":"Chestnut Hill Rd",
    "iso:country":"US",
    "sg:address":"2611 Chestnut Hill Rd",
    "sg:city":"Forest Hill",
    "sg:classifiers":[
        {
            "category":"Professional",
            "type":"Services"
        }
    ],
    "sg:phone":"+1 410 803 7148",
    "sg:postcode":"21050",
    "sg:province":"MD",
    "wof:name":"Chesapeake Office Services",
    "wof:placetype":"venue"
},
  "geometry": {"coordinates":[-76.34844699999999,39.60539],"type":"Point"}
}