{
  "type": "Feature",
  "properties": {
    "iso:country":"US",
    "sg:address":"8900 Edgeworth Dr Ste N",
    "sg:city":"Capitol Heights",
    "sg:classifiers":[
        {
            "category":"Professional",
            "type":"Services"
        }
    ],
    "sg:phone":"+1 301 324 1933",
    "sg:postcode":"20743",
    "sg:province":"MD",
    "sg:tags":[
        "caterer"
    ],
    "wof:name":"C & C Catering Inc",
    "wof:placetype":"venue"
},
  "geometry": {"coordinates":[-76.85279800000001,38.881401],"type":"Point"}
}