{
  "type": "Feature",
  "properties": {
    "addr:full":"7905 Muncaster Mill Rd Gaithersburg MD 20877",
    "addr:housenumber":"7905",
    "addr:postcode":"20877",
    "addr:street":"Muncaster Mill Rd",
    "iso:country":"US",
    "sg:address":"7905 Muncaster Mill Rd",
    "sg:city":"Gaithersburg",
    "sg:classifiers":[
        {
            "category":"Retail",
            "subcategory":"Auto Repair",
            "type":"Services"
        }
    ],
    "sg:phone":"+1 301 948 7997",
    "sg:postcode":"20877",
    "sg:province":"MD",
    "sg:tags":[
        "wrecker"
    ],
    "wof:name":"Airpark Towing",
    "wof:placetype":"venue"
},
  "geometry": {"coordinates":[-77.160276,39.159057],"type":"Point"}
}