{
  "type": "Feature",
  "properties": {
    "iso:country":"US",
    "sg:address":"16835 Skunk Hollow Rd",
    "sg:city":"Sabillasville",
    "sg:classifiers":[
        {
            "category":"Shopping",
            "subcategory":"Gifts & Souvenirs",
            "type":"Retail Goods"
        }
    ],
    "sg:phone":"+1 301 241 3762",
    "sg:postcode":"21780",
    "sg:province":"MD",
    "wof:name":"Js Kreations",
    "wof:placetype":"venue"
},
  "geometry": {"coordinates":[-77.46761600000001,39.70468],"type":"Point"}
}