{
  "type": "Feature",
  "properties": {
    "iso:country":"US",
    "sg:address":"14440 Cherry Lane Ct",
    "sg:city":"Laurel",
    "sg:classifiers":[
        {
            "category":"Health Services",
            "subcategory":"Chiropractor",
            "type":"Services"
        }
    ],
    "sg:phone":"+1 301 490 7785",
    "sg:postcode":"20707",
    "sg:province":"MD",
    "sg:website":"www.hirshchiropractic.com",
    "wof:name":"Hirsh Donald W DC",
    "wof:placetype":"venue"
},
  "geometry": {"coordinates":[-76.85489699999999,39.088501],"type":"Point"}
}