{
  "type": "Feature",
  "properties": {
    "iso:country":"US",
    "sg:address":"5508 Belair Rd Ste 2",
    "sg:city":"Baltimore",
    "sg:classifiers":[
        {
            "category":"Real Estate",
            "subcategory":"Real Estate Services",
            "type":"Services"
        },
        {
            "category":"Building & Trades",
            "subcategory":"Construction",
            "type":"Services"
        }
    ],
    "sg:phone":"+1 410 485 2446",
    "sg:postcode":"21206",
    "sg:province":"MD",
    "sg:tags":[
        "management",
        "contractor"
    ],
    "wof:name":"Wiesand William J Inc",
    "wof:placetype":"venue"
},
  "geometry": {"coordinates":[-76.54879800000001,39.340099],"type":"Point"}
}