{
  "type": "Feature",
  "properties": {
    "iso:country":"US",
    "sg:address":"6400 Homestake Dr S",
    "sg:city":"Bowie",
    "sg:classifiers":[
        {
            "category":"Professional",
            "subcategory":"Computer Services",
            "type":"Services"
        }
    ],
    "sg:phone":"+1 301 352 9177",
    "sg:postcode":"20720",
    "sg:province":"MD",
    "sg:tags":[
        "related"
    ],
    "wof:name":"Quantum Consultants",
    "wof:placetype":"venue"
},
  "geometry": {"coordinates":[-76.782898,38.977863],"type":"Point"}
}