{
  "type": "Feature",
  "properties": {
    "addr:full":"7935 Baltimore Annapolis Blvd Glen Burnie MD 21060",
    "addr:housenumber":"7935",
    "addr:postcode":"21060",
    "addr:street":"Baltimore Annapolis Blvd",
    "iso:country":"US",
    "sg:address":"7935 Baltimore Annapolis Blvd",
    "sg:city":"Glen Burnie",
    "sg:classifiers":[
        {
            "category":"Restaurant",
            "type":"Food & Drink"
        }
    ],
    "sg:phone":"+1 410 863 0350",
    "sg:postcode":"21060",
    "sg:province":"MD",
    "sg:tags":[
        "eating"
    ],
    "wof:name":"Daikim Express",
    "wof:placetype":"venue"
},
  "geometry": {"coordinates":[-76.585668,39.136249],"type":"Point"}
}