{
  "type": "Feature",
  "properties": {
    "iso:country":"US",
    "sg:address":"8941 N Westland Dr ",
    "sg:city":"Gaithersburg",
    "sg:classifiers":[
        {
            "category":"Restaurant",
            "type":"Food & Drink"
        }
    ],
    "sg:menulink":"http://www.allmenus.com/md/gaithersburg/292722-il-forno-pizzeria-/menu/",
    "sg:phone":"+1 301 977 5900",
    "sg:postcode":"20877",
    "sg:province":"MD",
    "sg:tags":[
        "pizza"
    ],
    "wof:name":"Il Forno Pizzeria ",
    "wof:placetype":"venue"
},
  "geometry": {"coordinates":[-77.18421600000001,39.12864],"type":"Point"}
}