{
  "type": "Feature",
  "properties": {
    "addr:full":"6415 Harford Rd Baltimore MD 21214",
    "addr:housenumber":"6415",
    "addr:postcode":"21214",
    "addr:street":"Harford Rd",
    "iso:country":"US",
    "sg:address":"6415 Harford Rd",
    "sg:city":"Baltimore",
    "sg:classifiers":[
        {
            "category":"Home & Garden",
            "subcategory":"Furniture",
            "type":"Retail Goods"
        }
    ],
    "sg:phone":"+1 410 254 6021",
    "sg:postcode":"21214",
    "sg:province":"MD",
    "sg:tags":[
        "maker",
        "cabinet"
    ],
    "sg:website":"http://www.northfieldkitchens.com",
    "wof:name":"Northfield Sales Co Inc",
    "wof:placetype":"venue"
},
  "geometry": {"coordinates":[-76.55386,39.361055],"type":"Point"}
}