{
  "type": "Feature",
  "properties": {
    "addr:full":"2703 N Salisbury Blvd Salisbury MD 21801",
    "addr:housenumber":"2703",
    "addr:postcode":"21801",
    "addr:street":"N Salisbury Blvd",
    "iso:country":"US",
    "sg:address":"2703 N Salisbury Blvd",
    "sg:city":"Salisbury",
    "sg:classifiers":[
        {
            "category":"Restaurant",
            "type":"Food & Drink"
        }
    ],
    "sg:phone":"+1 410 546 0997",
    "sg:postcode":"21801",
    "sg:province":"MD",
    "sg:tags":[
        "grill",
        "style",
        "bar",
        "american",
        "family"
    ],
    "sg:website":"http://www.applebees.com",
    "wof:name":"Applebee's",
    "wof:placetype":"venue"
},
  "geometry": {"coordinates":[-75.571674,38.397989],"type":"Point"}
}