{
  "type": "Feature",
  "properties": {
    "addr:full":"1706 Sullivan Rd Westminster MD 21157",
    "addr:housenumber":"1706",
    "addr:postcode":"21157",
    "addr:street":"Sullivan Rd",
    "iso:country":"US",
    "sg:address":"1706 Sullivan Rd",
    "sg:city":"Westminster",
    "sg:classifiers":[
        {
            "category":"Real Estate",
            "subcategory":"Real Estate Operator",
            "type":"Services"
        }
    ],
    "sg:phone":"+1 410 848 3982",
    "sg:postcode":"21157",
    "sg:province":"MD",
    "sg:tags":[
        "property",
        "lessor"
    ],
    "wof:name":"Edward Beard",
    "wof:placetype":"venue"
},
  "geometry": {"coordinates":[-76.934163,39.628282],"type":"Point"}
}