{
  "type": "Feature",
  "properties": {
    "addr:full":"10214 Royal Rd Silver Spring MD 20903",
    "addr:housenumber":"10214",
    "addr:postcode":"20903",
    "addr:street":"Royal Rd",
    "iso:country":"US",
    "sg:address":"10214 Royal Rd",
    "sg:city":"Silver Spring",
    "sg:classifiers":[
        {
            "category":"Health Services",
            "subcategory":"Nursing And Care Facility",
            "type":"Services"
        }
    ],
    "sg:phone":"+1 301 431 0800",
    "sg:postcode":"20903",
    "sg:province":"MD",
    "sg:tags":[
        "adult"
    ],
    "wof:name":"Family United Assisted Living",
    "wof:placetype":"venue"
},
  "geometry": {"coordinates":[-76.985783,39.022497],"type":"Point"}
}