{
  "type": "Feature",
  "properties": {
    "addr:full":"6624 22nd Pl Hyattsville MD 20782",
    "addr:housenumber":"6624",
    "addr:postcode":"20782",
    "addr:street":"22Nd Pl",
    "iso:country":"US",
    "sg:address":"6624 22nd Pl",
    "sg:city":"Hyattsville",
    "sg:classifiers":[
        {
            "category":"Professional",
            "type":"Services"
        }
    ],
    "sg:phone":"+1 301 422 1001",
    "sg:postcode":"20782",
    "sg:province":"MD",
    "wof:name":"Cartel Duciel Ltd",
    "wof:placetype":"venue"
},
  "geometry": {"coordinates":[-76.97364899999999,38.971206],"type":"Point"}
}