{
  "type": "Feature",
  "properties": {
    "iso:country":"US",
    "sg:address":"222 Walnut St",
    "sg:city":"Church Hill",
    "sg:classifiers":[
        {
            "category":"Health Services",
            "subcategory":"Nursing And Care Facility",
            "type":"Services"
        }
    ],
    "sg:phone":"+1 410 556 6600",
    "sg:postcode":"21623",
    "sg:province":"MD",
    "sg:tags":[
        "home",
        "convalescent"
    ],
    "wof:name":"Schuyler House",
    "wof:placetype":"venue"
},
  "geometry": {"coordinates":[-75.981575,39.139576],"type":"Point"}
}