{
  "type": "Feature",
  "properties": {
    "iso:country":"US",
    "sg:address":"7602 Belair Rd",
    "sg:city":"Nottingham",
    "sg:classifiers":[
        {
            "category":"Health Services",
            "subcategory":"Doctor",
            "type":"Services"
        }
    ],
    "sg:phone":"+1 410 663 8100",
    "sg:postcode":"21236",
    "sg:province":"MD",
    "wof:name":"Zang Michael MD",
    "wof:placetype":"venue"
},
  "geometry": {"coordinates":[-76.51870099999999,39.365564],"type":"Point"}
}