{
  "type": "Feature",
  "properties": {
    "addr:full":"32 Market Pl Baltimore MD 21202",
    "addr:housenumber":"32",
    "addr:postcode":"21202",
    "addr:street":"Market Pl",
    "iso:country":"US",
    "sg:address":"32 Market Pl",
    "sg:city":"Baltimore",
    "sg:classifiers":[
        {
            "category":"Personal",
            "type":"Services"
        },
        {
            "category":"Restaurant",
            "type":"Food & Drink"
        },
        {
            "category":"Retail",
            "subcategory":"Event Space",
            "type":"Services"
        },
        {
            "category":"Organizations",
            "subcategory":"Community Association",
            "type":"Services"
        }
    ],
    "sg:phone":"+1 410 234 9898",
    "sg:postcode":"21202",
    "sg:province":"MD",
    "sg:tags":[
        "grill",
        "bar",
        "facility",
        "club",
        "hall",
        "planning",
        "reception",
        "party",
        "meeting",
        "banquet"
    ],
    "sg:website":"http://www.babalugrill.com",
    "wof:name":"Babalu Grill",
    "wof:placetype":"venue"
},
  "geometry": {"coordinates":[-76.60697999999999,39.28855],"type":"Point"}
}