{
  "type": "Feature",
  "properties": {
    "iso:country":"US",
    "sg:address":"3617 Telmar Rd",
    "sg:city":"Baltimore",
    "sg:classifiers":[
        {
            "category":"Professional",
            "subcategory":"Research",
            "type":"Services"
        }
    ],
    "sg:phone":"+1 410 298 7040",
    "sg:postcode":"21207",
    "sg:province":"MD",
    "sg:tags":[
        "review",
        "grant"
    ],
    "wof:name":"Cynthia C Robertson",
    "wof:placetype":"venue"
},
  "geometry": {"coordinates":[-76.715827,39.338457],"type":"Point"}
}