{
  "type": "Feature",
  "properties": {
    "addr:full":"17 Hawthorne Ave Pikesville MD 21208",
    "addr:housenumber":"17",
    "addr:postcode":"21208",
    "addr:street":"Hawthorne Ave",
    "iso:country":"US",
    "sg:address":"17 Hawthorne Ave",
    "sg:city":"Pikesville",
    "sg:classifiers":[
        {
            "category":"Building & Trades",
            "subcategory":"Construction",
            "type":"Services"
        }
    ],
    "sg:phone":"+1 410 484 7093",
    "sg:postcode":"21208",
    "sg:province":"MD",
    "sg:tags":[
        "hanging",
        "contractor"
    ],
    "wof:name":"P&S Painting Contractors",
    "wof:placetype":"venue"
},
  "geometry": {"coordinates":[-76.722644,39.371174],"type":"Point"}
}