{
  "type": "Feature",
  "properties": {
    "addr:full":"8511 Landover Rd Landover MD 20785",
    "addr:housenumber":"8511",
    "addr:postcode":"20785",
    "addr:street":"Landover Rd",
    "iso:country":"US",
    "sg:address":"8511 Landover Rd",
    "sg:city":"Landover",
    "sg:classifiers":[
        {
            "category":"Shopping",
            "subcategory":"Department Store",
            "type":"Retail Goods"
        }
    ],
    "sg:phone":"+1 301 386 5577",
    "sg:postcode":"20785",
    "sg:province":"MD",
    "wof:name":"Sam's Club",
    "wof:placetype":"venue"
},
  "geometry": {"coordinates":[-76.856008,38.917068],"type":"Point"}
}