{
  "type": "Feature",
  "properties": {
    "iso:country":"US",
    "sg:address":"9410 Northgate Rd",
    "sg:city":"Laurel",
    "sg:classifiers":[
        {
            "category":"Professional",
            "subcategory":"Research",
            "type":"Services"
        }
    ],
    "sg:phone":"+1 301 725 0139",
    "sg:postcode":"20723",
    "sg:province":"MD",
    "sg:tags":[
        "nonphysical",
        "commercial"
    ],
    "wof:name":"Biazaran-Farbod Zinoosh",
    "wof:placetype":"venue"
},
  "geometry": {"coordinates":[-76.833461,39.121346],"type":"Point"}
}