{
  "type": "Feature",
  "properties": {
    "iso:country":"US",
    "sg:address":"5818 Martin Luther King Jr Hwy",
    "sg:city":"Capitol Heights",
    "sg:classifiers":[
        {
            "category":"Autos & Motor Vehicles",
            "subcategory":"Fuel & Gas Station",
            "type":"Retail Goods"
        }
    ],
    "sg:phone":"+1 301 925 4751",
    "sg:postcode":"20743",
    "sg:province":"MD",
    "wof:name":"Seat Pleasant Bp",
    "wof:placetype":"venue"
},
  "geometry": {"coordinates":[-76.907791,38.895952],"type":"Point"}
}