{
  "type": "Feature",
  "properties": {
    "addr:full":"3106 Superior Ln Bowie MD 20715",
    "addr:housenumber":"3106",
    "addr:postcode":"20715",
    "addr:street":"Superior Ln",
    "iso:country":"US",
    "sg:address":"3106 Superior Ln",
    "sg:city":"Bowie",
    "sg:classifiers":[
        {
            "category":"Utilities",
            "subcategory":"Telephone",
            "type":"Services"
        }
    ],
    "sg:phone":"+1 301 464 1588",
    "sg:postcode":"20715",
    "sg:province":"MD",
    "sg:tags":[
        "communications"
    ],
    "wof:name":"Pacificeastonline",
    "wof:placetype":"venue"
},
  "geometry": {"coordinates":[-76.733986,38.974734],"type":"Point"}
}