{
  "type": "Feature",
  "properties": {
    "addr:full":"6713 44th Ave University PA MD 20782",
    "addr:housenumber":"6713",
    "addr:postcode":"20782",
    "addr:street":"44Th Ave",
    "iso:country":"US",
    "sg:address":"6713 44th Ave",
    "sg:city":"University PA",
    "sg:classifiers":[
        {
            "category":"Health Services",
            "subcategory":"Clinic",
            "type":"Services"
        }
    ],
    "sg:phone":"+1 301 220 0707",
    "sg:postcode":"20782",
    "sg:province":"MD",
    "sg:tags":[
        "counseling",
        "mental"
    ],
    "wof:name":"The Oberg Group PA",
    "wof:placetype":"venue"
},
  "geometry": {"coordinates":[-76.939499,38.971901],"type":"Point"}
}