{
  "type": "Feature",
  "properties": {
    "iso:country":"US",
    "sg:address":"244 S Highland Ave",
    "sg:city":"Baltimore",
    "sg:classifiers":[
        {
            "category":"Home & Garden",
            "subcategory":"Building Materials",
            "type":"Retail Goods"
        },
        {
            "category":"Manufacturing",
            "subcategory":"Paper Products",
            "type":"Manufacturing & Wholesale Goods"
        }
    ],
    "sg:phone":"+1 410 675 6329",
    "sg:postcode":"21224",
    "sg:province":"MD",
    "sg:tags":[
        "manufacturer",
        "wallpaper",
        "wallcoverings-wholesale",
        "wallcoverings"
    ],
    "sg:website":"http://www.highlandtown.com",
    "wof:name":"Etherarts Inc",
    "wof:placetype":"venue"
},
  "geometry": {"coordinates":[-76.569193,39.289297],"type":"Point"}
}