{
  "type": "Feature",
  "properties": {
    "addr:full":"10611 Iron Bridge Rd Jessup MD 20794",
    "addr:housenumber":"10611",
    "addr:postcode":"20794",
    "addr:street":"Iron Bridge Rd",
    "iso:country":"US",
    "sg:address":"10611 Iron Bridge Rd",
    "sg:city":"Jessup",
    "sg:classifiers":[
        {
            "category":"Wholesale",
            "subcategory":"Machinery & Supplies",
            "type":"Manufacturing & Wholesale Goods"
        }
    ],
    "sg:phone":"+1 301 490 0281",
    "sg:postcode":"20794",
    "sg:province":"MD",
    "sg:tags":[
        "ladder"
    ],
    "wof:name":"Industrial Ladder & Supply Co",
    "wof:placetype":"venue"
},
  "geometry": {"coordinates":[-76.80262999999999,39.13485],"type":"Point"}
}