{
  "type": "Feature",
  "properties": {
    "iso:country":"US",
    "sg:address":"5901 Tuxedo Rd",
    "sg:city":"Hyattsville",
    "sg:classifiers":[
        {
            "category":"Retail",
            "subcategory":"Repair Shop",
            "type":"Services"
        }
    ],
    "sg:phone":"+1 301 773 1801",
    "sg:postcode":"20781",
    "sg:province":"MD",
    "sg:tags":[
        "sharpening"
    ],
    "wof:name":"Superior Saw Svc",
    "wof:placetype":"venue"
},
  "geometry": {"coordinates":[-76.92137200000001,38.917376],"type":"Point"}
}