{
  "type": "Feature",
  "properties": {
    "addr:full":"2100 Wayside Dr Frederick MD 21702",
    "addr:housenumber":"2100",
    "addr:postcode":"21702",
    "addr:street":"Wayside Dr",
    "iso:country":"US",
    "sg:address":"2100 Wayside Dr",
    "sg:city":"Frederick",
    "sg:classifiers":[
        {
            "category":"Communications",
            "subcategory":"Radio Station",
            "type":"Services"
        }
    ],
    "sg:phone":"+1 301 695 3320",
    "sg:postcode":"21702",
    "sg:province":"MD",
    "sg:tags":[
        "broadcast"
    ],
    "wof:name":"All Quartets Radio",
    "wof:placetype":"venue"
},
  "geometry": {"coordinates":[-77.448779,39.448887],"type":"Point"}
}