{
  "type": "Feature",
  "properties": {
    "iso:country":"US",
    "sg:address":"9644 Sea Shadow",
    "sg:city":"Columbia",
    "sg:classifiers":[
        {
            "category":"Shopping",
            "type":"Retail Goods"
        }
    ],
    "sg:phone":"+1 240 568 9539",
    "sg:postcode":"21046",
    "sg:province":"MD",
    "sg:tags":[
        "merchandise"
    ],
    "wof:name":"Resale Shop Network Inc",
    "wof:placetype":"venue"
},
  "geometry": {"coordinates":[-76.841904,39.162566],"type":"Point"}
}