{
  "type": "Feature",
  "properties": {
    "addr:full":"11703 Roby Ave Beltsville MD 20705",
    "addr:housenumber":"11703",
    "addr:postcode":"20705",
    "addr:street":"Roby Ave",
    "iso:country":"US",
    "sg:address":"11703 Roby Ave",
    "sg:city":"Beltsville",
    "sg:classifiers":[
        {
            "category":"Personal",
            "subcategory":"Barber",
            "type":"Services"
        }
    ],
    "sg:phone":"+1 301 595 8955",
    "sg:postcode":"20705",
    "sg:province":"MD",
    "wof:name":"Dao Hair Salon",
    "wof:placetype":"venue"
},
  "geometry": {"coordinates":[-76.917457,39.048363],"type":"Point"}
}