{
  "type": "Feature",
  "properties": {
    "addr:full":"5601 Massachusetts Ave Bethesda MD 20816",
    "addr:housenumber":"5601",
    "addr:postcode":"20816",
    "addr:street":"Massachusetts Ave",
    "iso:country":"US",
    "sg:address":"5601 Massachusetts Ave",
    "sg:city":"Bethesda",
    "sg:classifiers":[
        {
            "category":"Education",
            "subcategory":"School",
            "type":"Public Place"
        }
    ],
    "sg:phone":"+1 301 320 5233",
    "sg:postcode":"20816",
    "sg:province":"MD",
    "sg:tags":[
        "high",
        "middle",
        "elementary"
    ],
    "wof:name":"Little Flower School-Ccd Office",
    "wof:placetype":"venue"
},
  "geometry": {"coordinates":[-77.112099,38.959202],"type":"Point"}
}