{
  "type": "Feature",
  "properties": {
    "addr:full":"600 Warren Rd Cockysvl Hnt Vly MD 21030",
    "addr:housenumber":"600",
    "addr:postcode":"21030",
    "addr:street":"Warren Rd;Hnt Vly",
    "iso:country":"US",
    "sg:address":"600 Warren Rd",
    "sg:city":"Cockysvl Hnt Vly",
    "sg:classifiers":[
        {
            "category":"Shopping",
            "subcategory":"Used Merchandise",
            "type":"Retail Goods"
        }
    ],
    "sg:phone":"+1 410 666 1150",
    "sg:postcode":"21030",
    "sg:province":"MD",
    "sg:tags":[
        "shop",
        "thrift"
    ],
    "wof:name":"Penny Thrifty Shoppe",
    "wof:placetype":"venue"
},
  "geometry": {"coordinates":[-76.61727399999999,39.475587],"type":"Point"}
}