{
  "type": "Feature",
  "properties": {
    "addr:full":"3789 Queen Anne Bridge Rd Davidsonville MD 21035",
    "addr:housenumber":"3789",
    "addr:postcode":"21035",
    "addr:street":"Queen Anne Bridge Rd",
    "iso:country":"US",
    "sg:address":"3789 Queen Anne Bridge Rd",
    "sg:city":"Davidsonville",
    "sg:classifiers":[
        {
            "category":"Social Services",
            "type":"Services"
        }
    ],
    "sg:phone":"+1 410 798 8949",
    "sg:postcode":"21035",
    "sg:province":"MD",
    "sg:tags":[
        "youth",
        "organization",
        "center"
    ],
    "wof:name":"Boy Scout Pack 454",
    "wof:placetype":"venue"
},
  "geometry": {"coordinates":[-76.64966099999999,38.907576],"type":"Point"}
}