{
  "type": "Feature",
  "properties": {
    "iso:country":"US",
    "sg:address":"5808 Johnson Ave",
    "sg:city":"Bethesda",
    "sg:classifiers":[
        {
            "category":"Professional",
            "type":"Services"
        }
    ],
    "sg:phone":"+1 301 564 0802",
    "sg:postcode":"20817",
    "sg:province":"MD",
    "sg:tags":[
        "educational"
    ],
    "wof:name":"Deborah Norris",
    "wof:placetype":"venue"
},
  "geometry": {"coordinates":[-77.11801699999999,39.005516],"type":"Point"}
}