{
  "type": "Feature",
  "properties": {
    "addr:full":"322 Park Ave Frederick MD 21701",
    "addr:housenumber":"322",
    "addr:postcode":"21701",
    "addr:street":"Park Ave",
    "iso:country":"US",
    "sg:address":"322 Park Ave",
    "sg:city":"Frederick",
    "sg:classifiers":[
        {
            "category":"Social Services",
            "type":"Services"
        }
    ],
    "sg:phone":"+1 301 662 0633",
    "sg:postcode":"21701",
    "sg:province":"MD",
    "sg:tags":[
        "referral"
    ],
    "wof:name":"Cocaine & Alcohol Referral Svc",
    "wof:placetype":"venue"
},
  "geometry": {"coordinates":[-77.416005,39.421614],"type":"Point"}
}