{
  "type": "Feature",
  "properties": {
    "addr:full":"7379 Sunshine Ave Kingsville MD 21087",
    "addr:housenumber":"7379",
    "addr:postcode":"21087",
    "addr:street":"Sunshine Ave",
    "iso:country":"US",
    "sg:address":"7379 Sunshine Ave",
    "sg:city":"Kingsville",
    "sg:classifiers":[
        {
            "category":"Health Services",
            "subcategory":"Doctor",
            "type":"Services"
        }
    ],
    "sg:phone":"+1 410 592 7741",
    "sg:postcode":"21087",
    "sg:province":"MD",
    "sg:tags":[
        "dentist"
    ],
    "wof:name":"W D Chester DDS",
    "wof:placetype":"venue"
},
  "geometry": {"coordinates":[-76.417704,39.452789],"type":"Point"}
}