{
  "type": "Feature",
  "properties": {
    "addr:full":"629 Reisterstown Rd Pikesville MD 21208",
    "addr:housenumber":"629",
    "addr:postcode":"21208",
    "addr:street":"Reisterstown Rd",
    "iso:country":"US",
    "sg:address":"629 Reisterstown Rd",
    "sg:city":"Pikesville",
    "sg:classifiers":[
        {
            "category":"Building & Trades",
            "subcategory":"Construction",
            "type":"Services"
        }
    ],
    "sg:phone":"+1 410 358 3378",
    "sg:postcode":"21208",
    "sg:province":"MD",
    "sg:tags":[
        "plating"
    ],
    "wof:name":"Tarnish",
    "wof:placetype":"venue"
},
  "geometry": {"coordinates":[-76.718436,39.369644],"type":"Point"}
}