{
  "type": "Feature",
  "properties": {
    "iso:country":"US",
    "sg:address":"4108 Ulster Rd",
    "sg:city":"Beltsville",
    "sg:classifiers":[
        {
            "category":"Professional",
            "subcategory":"Management & Consulting",
            "type":"Services"
        }
    ],
    "sg:phone":"+1 301 937 0449",
    "sg:postcode":"20705",
    "sg:province":"MD",
    "sg:tags":[
        "consultant"
    ],
    "sg:website":"http://www.mymultipro.com",
    "wof:name":"Multipro",
    "wof:placetype":"venue"
},
  "geometry": {"coordinates":[-76.935924,39.036465],"type":"Point"}
}