{
  "type": "Feature",
  "properties": {
    "iso:country":"US",
    "sg:address":"1430 Joh Ave Ste M",
    "sg:city":"Halethorpe",
    "sg:classifiers":[
        {
            "category":"Manufacturing",
            "subcategory":"Tools & Machinery",
            "type":"Manufacturing & Wholesale Goods"
        },
        {
            "category":"Wholesale",
            "subcategory":"Machinery & Supplies",
            "type":"Manufacturing & Wholesale Goods"
        }
    ],
    "sg:phone":"+1 410 247 2345",
    "sg:postcode":"21227",
    "sg:province":"MD",
    "sg:tags":[
        "handling",
        "equipment-wholesale",
        "material",
        "equipment",
        "manufacturer"
    ],
    "sg:website":"http://www.ptcintl.com",
    "wof:name":"Ptc International, Inc.",
    "wof:placetype":"venue"
},
  "geometry": {"coordinates":[-76.669265,39.260168],"type":"Point"}
}