{
  "type": "Feature",
  "properties": {
    "addr:full":"830 Bowman Ave Hagerstown MD 21740",
    "addr:housenumber":"830",
    "addr:postcode":"21740",
    "addr:street":"Bowman Ave",
    "iso:country":"US",
    "sg:address":"830 Bowman Ave",
    "sg:city":"Hagerstown",
    "sg:classifiers":[
        {
            "category":"Building & Trades",
            "subcategory":"Construction",
            "type":"Services"
        }
    ],
    "sg:phone":"+1 301 733 9474",
    "sg:postcode":"21740",
    "sg:province":"MD",
    "sg:tags":[
        "maker",
        "cabinet"
    ],
    "wof:name":"J P Wood Designs",
    "wof:placetype":"venue"
},
  "geometry": {"coordinates":[-77.709766,39.624316],"type":"Point"}
}