{
  "type": "Feature",
  "properties": {
    "addr:full":"746 N Patterson Park Ave Baltimore MD 21205",
    "addr:housenumber":"746",
    "addr:postcode":"21205",
    "addr:street":"N Patterson Park Ave",
    "iso:country":"US",
    "sg:address":"746 N Patterson Park Ave",
    "sg:city":"Baltimore",
    "sg:classifiers":[
        {
            "category":"Food & Beverages",
            "subcategory":"Groceries & Convenience Stores",
            "type":"Retail Goods"
        }
    ],
    "sg:phone":"+1 410 276 3774",
    "sg:postcode":"21205",
    "sg:province":"MD",
    "sg:tags":[
        "grocer"
    ],
    "wof:name":"Lucia Food Market",
    "wof:placetype":"venue"
},
  "geometry": {"coordinates":[-76.584999,39.299198],"type":"Point"}
}