{
  "type": "Feature",
  "properties": {
    "iso:country":"US",
    "sg:address":"2 S Bond St",
    "sg:city":"Bel Air",
    "sg:classifiers":[
        {
            "category":"Government",
            "subcategory":"Office",
            "type":"Public Place"
        }
    ],
    "sg:phone":"+1 410 836 4600",
    "sg:postcode":"21014",
    "sg:province":"MD",
    "sg:tags":[
        "state",
        "resource"
    ],
    "wof:name":"Unemployment Insurance",
    "wof:placetype":"venue"
},
  "geometry": {"coordinates":[-76.34982,39.535341],"type":"Point"}
}