{
  "type": "Feature",
  "properties": {
    "addr:full":"722 Generals Hwy Millersville MD 21108",
    "addr:housenumber":"722",
    "addr:postcode":"21108",
    "addr:street":"Generals Hwy",
    "iso:country":"US",
    "sg:address":"722 Generals Hwy",
    "sg:city":"Millersville",
    "sg:classifiers":[
        {
            "category":"Restaurant",
            "type":"Food & Drink"
        }
    ],
    "sg:phone":"+1 410 923 8226",
    "sg:postcode":"21108",
    "sg:province":"MD",
    "wof:name":"Gina's Cantina",
    "wof:placetype":"venue"
},
  "geometry": {"coordinates":[-76.630471,39.072667],"type":"Point"}
}