{
  "type": "Feature",
  "properties": {
    "iso:country":"US",
    "sg:address":"126 N Liberty St",
    "sg:city":"Baltimore",
    "sg:classifiers":[
        {
            "category":"Personal",
            "subcategory":"Hair Removal",
            "type":"Services"
        }
    ],
    "sg:phone":"+1 410 347 1580",
    "sg:postcode":"21201",
    "sg:province":"MD",
    "sg:tags":[
        "real estate"
    ],
    "wof:name":"Asset Management LLC",
    "wof:placetype":"venue"
},
  "geometry": {"coordinates":[-76.617288,39.291388],"type":"Point"}
}