{
  "type": "Feature",
  "properties": {
    "addr:full":"13337 Clopper Rd Hagerstown MD 21742",
    "addr:housenumber":"13337",
    "addr:postcode":"21742",
    "addr:street":"Clopper Rd",
    "iso:country":"US",
    "sg:address":"13337 Clopper Rd",
    "sg:city":"Hagerstown",
    "sg:classifiers":[
        {
            "category":"Manufacturing",
            "subcategory":"Wood Products",
            "type":"Manufacturing & Wholesale Goods"
        }
    ],
    "sg:phone":"+1 301 733 5329",
    "sg:postcode":"21742",
    "sg:province":"MD",
    "sg:tags":[
        "mfg"
    ],
    "wof:name":"Mark A Hostetter",
    "wof:placetype":"venue"
},
  "geometry": {"coordinates":[-77.64408400000001,39.680151],"type":"Point"}
}