{
  "type": "Feature",
  "properties": {
    "iso:country":"US",
    "sg:address":"28 N Dundalk Ave",
    "sg:city":"Dundalk",
    "sg:classifiers":[
        {
            "category":"Shopping",
            "subcategory":"Florist",
            "type":"Retail Goods"
        }
    ],
    "sg:phone":"+1 410 284 4800",
    "sg:postcode":"21222",
    "sg:province":"MD",
    "wof:name":"Bouquets By Bell Florist",
    "wof:placetype":"venue"
},
  "geometry": {"coordinates":[-76.52433499999999,39.258029],"type":"Point"}
}