{
  "type": "Feature",
  "properties": {
    "addr:full":"3308 Churchville Rd Aberdeen MD 21001",
    "addr:housenumber":"3308",
    "addr:postcode":"21001",
    "addr:street":"Churchville Rd",
    "iso:country":"US",
    "sg:address":"3308 Churchville Rd",
    "sg:city":"Aberdeen",
    "sg:classifiers":[
        {
            "category":"Home & Garden",
            "subcategory":"Garden Supply",
            "type":"Retail Goods"
        }
    ],
    "sg:phone":"+1 410 838 3510",
    "sg:postcode":"21001",
    "sg:province":"MD",
    "sg:tags":[
        "nurseryman"
    ],
    "wof:name":"Kroh Nursery Inc",
    "wof:placetype":"venue"
},
  "geometry": {"coordinates":[-76.22890700000001,39.541494],"type":"Point"}
}