{
  "type": "Feature",
  "properties": {
    "addr:full":"19 S Charles St Baltimore MD 21230",
    "addr:housenumber":"19",
    "addr:postcode":"21230",
    "addr:street":"S Charles St",
    "iso:country":"US",
    "sg:address":"19 S Charles St",
    "sg:city":"Baltimore",
    "sg:classifiers":[
        {
            "category":"Shopping",
            "subcategory":"Gifts & Souvenirs",
            "type":"Retail Goods"
        }
    ],
    "sg:phone":"+1 410 837 4284",
    "sg:postcode":"21230",
    "sg:province":"MD",
    "sg:tags":[
        "cards",
        "greeting"
    ],
    "wof:name":"Manasa's Cards Gifts & Flowers",
    "wof:placetype":"venue"
},
  "geometry": {"coordinates":[-76.61480899999999,39.288217],"type":"Point"}
}