{
  "type": "Feature",
  "properties": {
    "iso:country":"US",
    "sg:address":"3500 Boston Street",
    "sg:city":"Baltimore",
    "sg:classifiers":[
        {
            "category":"Real Estate",
            "subcategory":"Real Estate Services",
            "type":"Services"
        },
        {
            "category":"Real Estate",
            "subcategory":"Real Estate Agent",
            "type":"Services"
        },
        {
            "category":"Professional",
            "type":"Services"
        }
    ],
    "sg:phone":"+1 443 765 5422",
    "sg:postcode":"21224",
    "sg:province":"MD",
    "sg:tags":[
        "information",
        "consultant",
        "relocation",
        "broker",
        "buyer",
        "referral"
    ],
    "sg:website":"http://www.ngrealtygroup.com",
    "wof:name":"Remax Sails",
    "wof:placetype":"venue"
},
  "geometry": {"coordinates":[-76.567459,39.277088],"type":"Point"}
}