{
  "type": "Feature",
  "properties": {
    "addr:full":"29 E Patrick St Frederick MD 21701",
    "addr:housenumber":"29",
    "addr:postcode":"21701",
    "addr:street":"E Patrick St",
    "iso:country":"US",
    "sg:address":"29 E Patrick St",
    "sg:city":"Frederick",
    "sg:classifiers":[
        {
            "category":"Professional",
            "subcategory":"Business Services",
            "type":"Services"
        }
    ],
    "sg:phone":"+1 301 620 9334",
    "sg:postcode":"21701",
    "sg:province":"MD",
    "sg:tags":[
        "interior",
        "consultant",
        "design",
        "decorator"
    ],
    "wof:name":"Jones & Eberhardt",
    "wof:placetype":"venue"
},
  "geometry": {"coordinates":[-77.410483,39.414231],"type":"Point"}
}