{
  "type": "Feature",
  "properties": {
    "iso:country":"US",
    "sg:address":"434 E Biddle St",
    "sg:city":"Baltimore",
    "sg:classifiers":[
        {
            "category":"Organizations",
            "subcategory":"Non-profit Organization",
            "type":"Services"
        }
    ],
    "sg:phone":"+1 410 347 3949",
    "sg:postcode":"21202",
    "sg:province":"MD",
    "sg:tags":[
        "info",
        "addiction",
        "abuse",
        "treatment",
        "drug"
    ],
    "wof:name":"Recovery King 2",
    "wof:placetype":"venue"
},
  "geometry": {"coordinates":[-76.609301,39.303801],"type":"Point"}
}