{
  "type": "Feature",
  "properties": {
    "addr:full":"12011 Marvel Ln Bowie MD 20715",
    "addr:housenumber":"12011",
    "addr:postcode":"20715",
    "addr:street":"Marvel Ln",
    "iso:country":"US",
    "sg:address":"12011 Marvel Ln",
    "sg:city":"Bowie",
    "sg:classifiers":[
        {
            "category":"Manufacturing",
            "subcategory":"Chemicals & Compounds",
            "type":"Manufacturing & Wholesale Goods"
        }
    ],
    "sg:phone":"+1 301 352 3935",
    "sg:postcode":"20715",
    "sg:province":"MD",
    "sg:tags":[
        "merchandise"
    ],
    "wof:name":"Dade Behring Inc",
    "wof:placetype":"venue"
},
  "geometry": {"coordinates":[-76.752988,38.976178],"type":"Point"}
}