{
  "type": "Feature",
  "properties": {
    "addr:full":"6060 Sargent Rd Hyattsville MD 20782",
    "addr:housenumber":"6060",
    "addr:postcode":"20782",
    "addr:street":"Sargent Rd",
    "iso:country":"US",
    "sg:address":"6060 Sargent Rd",
    "sg:city":"Hyattsville",
    "sg:classifiers":[
        {
            "category":"Real Estate",
            "subcategory":"Real Estate Operator",
            "type":"Services"
        }
    ],
    "sg:phone":"+1 301 559 2225",
    "sg:postcode":"20782",
    "sg:province":"MD",
    "sg:tags":[
        "apartment"
    ],
    "wof:name":"Rollingcrest Commons",
    "wof:placetype":"venue"
},
  "geometry": {"coordinates":[-76.984497,38.9632],"type":"Point"}
}