{
  "type": "Feature",
  "properties": {
    "addr:full":"211 Forest Spring Ln Baltimore MD 21228",
    "addr:housenumber":"211",
    "addr:postcode":"21228",
    "addr:street":"Forest Spring Ln",
    "iso:country":"US",
    "sg:address":"211 Forest Spring Ln",
    "sg:city":"Baltimore",
    "sg:classifiers":[
        {
            "category":"Real Estate",
            "subcategory":"Real Estate Operator",
            "type":"Services"
        }
    ],
    "sg:phone":"+1 410 371 1838",
    "sg:postcode":"21228",
    "sg:province":"MD",
    "sg:tags":[
        "property",
        "lessor"
    ],
    "wof:name":"JP Meek Properties LLC",
    "wof:placetype":"venue"
},
  "geometry": {"coordinates":[-76.736887,39.264385],"type":"Point"}
}