{
  "type": "Feature",
  "properties": {
    "iso:country":"US",
    "sg:address":"2901 Druid Park Dr",
    "sg:city":"Baltimore",
    "sg:classifiers":[
        {
            "category":"Social Services",
            "subcategory":"Adult Care",
            "type":"Services"
        }
    ],
    "sg:phone":"+1 410 225 7001",
    "sg:postcode":"21215",
    "sg:province":"MD",
    "sg:tags":[
        "foster"
    ],
    "wof:name":"Tuttie's Place",
    "wof:placetype":"venue"
},
  "geometry": {"coordinates":[-76.660352,39.323933],"type":"Point"}
}