{
  "type": "Feature",
  "properties": {
    "addr:full":"2801 Sisson St Baltimore MD 21211",
    "addr:housenumber":"2801",
    "addr:postcode":"21211",
    "addr:street":"Sisson St",
    "iso:country":"US",
    "sg:address":"2801 Sisson St",
    "sg:city":"Baltimore",
    "sg:classifiers":[
        {
            "category":"Building & Trades",
            "subcategory":"Construction",
            "type":"Services"
        }
    ],
    "sg:phone":"+1 410 338 1122",
    "sg:postcode":"21211",
    "sg:province":"MD",
    "sg:tags":[
        "altering",
        "consultant",
        "remodeling",
        "contractor"
    ],
    "wof:name":"Swirno Building Syst Mgmt",
    "wof:placetype":"venue"
},
  "geometry": {"coordinates":[-76.62531300000001,39.31945],"type":"Point"}
}