{
  "type": "Feature",
  "properties": {
    "addr:full":"310 E Green St Westminster MD 21157",
    "addr:housenumber":"310",
    "addr:postcode":"21157",
    "addr:street":"E Green St",
    "iso:country":"US",
    "sg:address":"310 E Green St",
    "sg:city":"Westminster",
    "sg:classifiers":[
        {
            "category":"Restaurant",
            "type":"Food & Drink"
        }
    ],
    "sg:phone":"+1 410 848 1441",
    "sg:postcode":"21157",
    "sg:province":"MD",
    "sg:website":"www.maggieswestminster.com",
    "wof:name":"Maggies Restaurant",
    "wof:placetype":"venue"
},
  "geometry": {"coordinates":[-76.988185,39.565557],"type":"Point"}
}