{
  "type": "Feature",
  "properties": {
    "iso:country":"US",
    "sg:address":"8850 Gander Ln",
    "sg:city":"Berlin",
    "sg:classifiers":[
        {
            "category":"Manufacturing",
            "subcategory":"Apparel",
            "type":"Manufacturing & Wholesale Goods"
        }
    ],
    "sg:phone":"+1 443 497 4206",
    "sg:postcode":"21811",
    "sg:province":"MD",
    "sg:tags":[
        "apparel-wholesale",
        "manufacturer",
        "women's"
    ],
    "wof:name":"Bolt Headbands",
    "wof:placetype":"venue"
},
  "geometry": {"coordinates":[-75.195678,38.301168],"type":"Point"}
}