{
  "type": "Feature",
  "properties": {
    "addr:full":"7313 Grove Rd Frederick MD 21704",
    "addr:housenumber":"7313",
    "addr:postcode":"21704",
    "addr:street":"Grove Rd",
    "iso:country":"US",
    "sg:address":"7313 Grove Rd",
    "sg:city":"Frederick",
    "sg:classifiers":[
        {
            "category":"Real Estate",
            "subcategory":"Surveying",
            "type":"Services"
        }
    ],
    "sg:phone":"+1 301 663 6630",
    "sg:postcode":"21704",
    "sg:province":"MD",
    "sg:tags":[
        "surveyor"
    ],
    "wof:name":"Seismic Surveys Inc",
    "wof:placetype":"venue"
},
  "geometry": {"coordinates":[-77.412757,39.389956],"type":"Point"}
}