{
  "type": "Feature",
  "properties": {
    "addr:full":"300 Decatur St NW Washington MD 20011",
    "addr:housenumber":"300",
    "addr:postcode":"20011",
    "addr:street":"Decatur St Nw",
    "iso:country":"US",
    "sg:address":"300 Decatur St NW",
    "sg:city":"Washington",
    "sg:classifiers":[
        {
            "category":"Professional",
            "subcategory":"Lawyer & Legal Services",
            "type":"Services"
        }
    ],
    "sg:phone":"+1 202 723 6624",
    "sg:postcode":"20011",
    "sg:province":"MD",
    "sg:tags":[
        "attorney"
    ],
    "wof:name":"Stephanie Y Bradley",
    "wof:placetype":"venue"
},
  "geometry": {"coordinates":[-77.015216,38.948558],"type":"Point"}
}