{
  "type": "Feature",
  "properties": {
    "iso:country":"US",
    "sg:address":"506 Brookletts Ave",
    "sg:city":"Easton",
    "sg:classifiers":[
        {
            "category":"Communications",
            "subcategory":"Film & Video Production",
            "type":"Services"
        }
    ],
    "sg:phone":"+1 410 819 0067",
    "sg:postcode":"21601",
    "sg:province":"MD",
    "sg:tags":[
        "taping"
    ],
    "wof:name":"New Horizon Video Svc",
    "wof:placetype":"venue"
},
  "geometry": {"coordinates":[-76.067055,38.770645],"type":"Point"}
}