{
  "type": "Feature",
  "properties": {
    "iso:country":"US",
    "sg:address":"103 E Mount Royal Ave",
    "sg:city":"Baltimore",
    "sg:classifiers":[
        {
            "category":"Organizations",
            "subcategory":"Membership Organization",
            "type":"Services"
        }
    ],
    "sg:phone":"+1 410 659 4108",
    "sg:postcode":"21202",
    "sg:province":"MD",
    "wof:name":"Health & Child Survival Prgrms",
    "wof:placetype":"venue"
},
  "geometry": {"coordinates":[-76.61428,39.30545],"type":"Point"}
}