{
  "type": "Feature",
  "properties": {
    "iso:country":"US",
    "sg:address":"1132 S Hanover St",
    "sg:city":"Baltimore",
    "sg:classifiers":[
        {
            "category":"Winery",
            "type":"Food & Drink"
        },
        {
            "category":"Bars & Pubs",
            "type":"Food & Drink"
        },
        {
            "category":"Food & Beverages",
            "subcategory":"Liquor & Beverages",
            "type":"Retail Goods"
        },
        {
            "category":"Wholesale",
            "subcategory":"Wine & Distilled Alcoholic Beverages",
            "type":"Manufacturing & Wholesale Goods"
        }
    ],
    "sg:phone":"+1 410 547 7415",
    "sg:postcode":"21230",
    "sg:province":"MD",
    "sg:tags":[
        "brew",
        "liquors-wholesale",
        "store"
    ],
    "wof:name":"Mums",
    "wof:placetype":"venue"
},
  "geometry": {"coordinates":[-76.615492,39.276347],"type":"Point"}
}