{
  "type": "Feature",
  "properties": {
    "addr:full":"80 Annapolis St Annapolis MD 21401",
    "addr:housenumber":"80",
    "addr:postcode":"21401",
    "addr:street":"Annapolis St",
    "iso:country":"US",
    "sg:address":"80 Annapolis St",
    "sg:city":"Annapolis",
    "sg:classifiers":[
        {
            "category":"Food & Beverages",
            "subcategory":"Bakery",
            "type":"Retail Goods"
        }
    ],
    "sg:phone":"+1 410 573 5144",
    "sg:postcode":"21401",
    "sg:province":"MD",
    "sg:tags":[
        "cookie",
        "cracker"
    ],
    "wof:name":"Great American Cookie Co",
    "wof:placetype":"venue"
},
  "geometry": {"coordinates":[-76.50094,38.989247],"type":"Point"}
}