{
  "type": "Feature",
  "properties": {
    "iso:country":"US",
    "sg:address":"31 E Lee St",
    "sg:city":"Bel Air",
    "sg:classifiers":[
        {
            "category":"Professional",
            "subcategory":"Management & Consulting",
            "type":"Services"
        }
    ],
    "sg:phone":"+1 410 879 6818",
    "sg:postcode":"21014",
    "sg:province":"MD",
    "sg:tags":[
        "consultant",
        "business"
    ],
    "wof:name":"Intercontinental Consulting",
    "wof:placetype":"venue"
},
  "geometry": {"coordinates":[-76.34993900000001,39.538174],"type":"Point"}
}