{
  "type": "Feature",
  "properties": {
    "iso:country":"US",
    "sg:address":"613 Ridge Rd",
    "sg:city":"Salisbury",
    "sg:classifiers":[
        {
            "category":"Home & Garden",
            "subcategory":"Building Materials",
            "type":"Retail Goods"
        }
    ],
    "sg:phone":"+1 410 742 1257",
    "sg:postcode":"21801",
    "sg:province":"MD",
    "wof:name":"R E Beauchamp Construction",
    "wof:placetype":"venue"
},
  "geometry": {"coordinates":[-75.612801,38.357019],"type":"Point"}
}