{
  "type": "Feature",
  "properties": {
    "addr:full":"3207 Dublin Rd Street MD 21154",
    "addr:housenumber":"3207",
    "addr:postcode":"21154",
    "addr:street":"Dublin Rd Street",
    "iso:country":"US",
    "sg:address":"3207 Dublin Rd",
    "sg:city":"Street",
    "sg:classifiers":[
        {
            "category":"Manufacturing",
            "subcategory":"Signs",
            "type":"Manufacturing & Wholesale Goods"
        }
    ],
    "sg:phone":"+1 410 879 6240",
    "sg:postcode":"21154",
    "sg:province":"MD",
    "wof:name":"Roberts Signs & Svc",
    "wof:placetype":"venue"
},
  "geometry": {"coordinates":[-76.27577100000001,39.648107],"type":"Point"}
}