{
  "type": "Feature",
  "properties": {
    "addr:full":"2507 Evergreen Ave Baltimore MD 21214",
    "addr:housenumber":"2507",
    "addr:postcode":"21214",
    "addr:street":"Evergreen Ave",
    "iso:country":"US",
    "sg:address":"2507 Evergreen Ave",
    "sg:city":"Baltimore",
    "sg:classifiers":[
        {
            "category":"Building & Trades",
            "subcategory":"Construction",
            "type":"Services"
        }
    ],
    "sg:phone":"+1 410 254 3675",
    "sg:postcode":"21214",
    "sg:province":"MD",
    "sg:tags":[
        "tile",
        "dealer"
    ],
    "wof:name":"Pete Profili & Co",
    "wof:placetype":"venue"
},
  "geometry": {"coordinates":[-76.5659,39.357186],"type":"Point"}
}