{
  "type": "Feature",
  "properties": {
    "iso:country":"US",
    "sg:address":"4771 Hollins Ferry Rd",
    "sg:city":"Halethorpe",
    "sg:classifiers":[
        {
            "category":"Autos & Motor Vehicles",
            "subcategory":"Auto Supplies",
            "type":"Retail Goods"
        }
    ],
    "sg:phone":"+1 410 247 4464",
    "sg:postcode":"21227",
    "sg:province":"MD",
    "sg:tags":[
        "tire"
    ],
    "wof:name":"Tci Tire Sales",
    "wof:placetype":"venue"
},
  "geometry": {"coordinates":[-76.684799,39.228699],"type":"Point"}
}