{
  "type": "Feature",
  "properties": {
    "addr:full":"3307 Liberty Pkwy Baltimore MD 21222",
    "addr:housenumber":"3307",
    "addr:postcode":"21222",
    "addr:street":"Liberty Pkwy",
    "iso:country":"US",
    "sg:address":"3307 Liberty Pkwy",
    "sg:city":"Baltimore",
    "sg:classifiers":[
        {
            "category":"Professional",
            "subcategory":"Management & Consulting",
            "type":"Services"
        }
    ],
    "sg:phone":"+1 410 664 7405",
    "sg:postcode":"21222",
    "sg:province":"MD",
    "wof:name":"Real Estate Brokers Baltimore",
    "wof:placetype":"venue"
},
  "geometry": {"coordinates":[-76.514126,39.25114],"type":"Point"}
}