{
  "type": "Feature",
  "properties": {
    "iso:country":"US",
    "sg:address":"3324 Sumter Ave",
    "sg:city":"Baltimore",
    "sg:classifiers":[
        {
            "category":"Travel",
            "subcategory":"Travel Agent",
            "type":"Entertainment"
        }
    ],
    "sg:phone":"+1 443 758 8697",
    "sg:postcode":"21215",
    "sg:province":"MD",
    "sg:tags":[
        "agency",
        "services-commercial"
    ],
    "wof:name":"1st Class Travel, Inc.",
    "wof:placetype":"venue"
},
  "geometry": {"coordinates":[-76.669353,39.341128],"type":"Point"}
}