{
  "type": "Feature",
  "properties": {
    "addr:full":"301 Londontown Rd Edgewater MD 21037",
    "addr:housenumber":"301",
    "addr:postcode":"21037",
    "addr:street":"Londontown Rd",
    "iso:country":"US",
    "sg:address":"301 Londontown Rd",
    "sg:city":"Edgewater",
    "sg:classifiers":[
        {
            "category":"Food & Beverages",
            "subcategory":"Groceries & Convenience Stores",
            "type":"Retail Goods"
        }
    ],
    "sg:phone":"+1 410 974 8156",
    "sg:postcode":"21037",
    "sg:province":"MD",
    "wof:name":"Royal Farms",
    "wof:placetype":"venue"
},
  "geometry": {"coordinates":[-76.55478599999999,38.931216],"type":"Point"}
}