{
  "type": "Feature",
  "properties": {
    "addr:full":"7545 Greenbelt Rd Greenbelt MD 20770",
    "addr:housenumber":"7545",
    "addr:postcode":"20770",
    "addr:street":"Greenbelt Rd",
    "iso:country":"US",
    "sg:address":"7545 Greenbelt Rd",
    "sg:city":"Greenbelt",
    "sg:classifiers":[
        {
            "category":"Personal",
            "subcategory":"Barber",
            "type":"Services"
        }
    ],
    "sg:phone":"+1 301 345 9767",
    "sg:postcode":"20770",
    "sg:province":"MD",
    "sg:website":"www.haircuttery.com",
    "wof:name":"Hair Cuttery",
    "wof:placetype":"venue"
},
  "geometry": {"coordinates":[-76.87567199999999,38.994046],"type":"Point"}
}