{
  "type": "Feature",
  "properties": {
    "iso:country":"US",
    "sg:address":"721 Monarch Ridge Rd",
    "sg:city":"Frederick",
    "sg:classifiers":[
        {
            "category":"Recreation",
            "type":"Entertainment"
        }
    ],
    "sg:phone":"+1 301 694 0808",
    "sg:postcode":"21703",
    "sg:province":"MD",
    "wof:name":"ABN Products",
    "wof:placetype":"venue"
},
  "geometry": {"coordinates":[-77.470275,39.409366],"type":"Point"}
}