{
  "type": "Feature",
  "properties": {
    "iso:country":"US",
    "sg:address":"14902 Sequoia Hill Ln",
    "sg:city":"Silver Spring",
    "sg:classifiers":[
        {
            "category":"Real Estate",
            "subcategory":"Real Estate Agent",
            "type":"Services"
        }
    ],
    "sg:phone":"+1 301 598 3807",
    "sg:postcode":"20906",
    "sg:province":"MD",
    "sg:tags":[
        "manager"
    ],
    "wof:name":"Jane Colin Realtor",
    "wof:placetype":"venue"
},
  "geometry": {"coordinates":[-77.044729,39.102265],"type":"Point"}
}