{
  "type": "Feature",
  "properties": {
    "iso:country":"US",
    "sg:address":"6808 N Point Rd",
    "sg:city":"Baltimore",
    "sg:classifiers":[
        {
            "category":"Shopping",
            "subcategory":"Bicycles & Sporting Goods",
            "type":"Retail Goods"
        }
    ],
    "sg:phone":"+1 410 477 0717",
    "sg:postcode":"21219",
    "sg:province":"MD",
    "sg:tags":[
        "apparel",
        "bowling",
        "accessory"
    ],
    "wof:name":"Edgemere Bowl",
    "wof:placetype":"venue"
},
  "geometry": {"coordinates":[-76.44945800000001,39.242537],"type":"Point"}
}