{
  "type": "Feature",
  "properties": {
    "addr:full":"3336 Gold Mine Rd Brookeville MD 20833",
    "addr:housenumber":"3336",
    "addr:postcode":"20833",
    "addr:street":"Gold Mine Rd",
    "iso:country":"US",
    "sg:address":"3336 Gold Mine Rd",
    "sg:city":"Brookeville",
    "sg:classifiers":[
        {
            "category":"Social Services",
            "subcategory":"Child Care",
            "type":"Services"
        }
    ],
    "sg:phone":"+1 301 774 2590",
    "sg:postcode":"20833",
    "sg:province":"MD",
    "wof:name":"Greenwood Extended-Day Ctr",
    "wof:placetype":"venue"
},
  "geometry": {"coordinates":[-77.06728099999999,39.166648],"type":"Point"}
}