{
  "type": "Feature",
  "properties": {
    "addr:full":"3400 Greencastle Rd Burtonsville MD 20866",
    "addr:postcode":"3400;20866",
    "addr:street":"Greencastle Rd",
    "iso:country":"US",
    "sg:address":"3400 Greencastle Rd",
    "sg:city":"Burtonsville",
    "sg:classifiers":[
        {
            "category":"Professional",
            "subcategory":"Business Services",
            "type":"Services"
        }
    ],
    "sg:phone":"+1 301 384 3123",
    "sg:postcode":"20866",
    "sg:province":"MD",
    "wof:name":"Natalie C Davis",
    "wof:placetype":"venue"
},
  "geometry": {"coordinates":[-76.93800299999999,39.095607],"type":"Point"}
}