{
  "type": "Feature",
  "properties": {
    "iso:country":"US",
    "sg:address":"15 E Main St",
    "sg:city":"Westminster",
    "sg:classifiers":[
        {
            "category":"Professional",
            "subcategory":"Engineering",
            "type":"Services"
        }
    ],
    "sg:phone":"+1 410 840 4499",
    "sg:postcode":"21157",
    "sg:province":"MD",
    "sg:tags":[
        "engineer"
    ],
    "wof:name":"Demario Design Consultants",
    "wof:placetype":"venue"
},
  "geometry": {"coordinates":[-76.995098,39.574438],"type":"Point"}
}