{
  "type": "Feature",
  "properties": {
    "addr:full":"17415 Batchellors Forest Rd Olney MD 20832",
    "addr:housenumber":"17415",
    "addr:postcode":"20832",
    "addr:street":"Batchellors Forest Rd",
    "iso:country":"US",
    "sg:address":"17415 Batchellors Forest Rd",
    "sg:city":"Olney",
    "sg:classifiers":[
        {
            "category":"Professional",
            "subcategory":"Engineering",
            "type":"Services"
        }
    ],
    "sg:phone":"+1 301 774 6296",
    "sg:postcode":"20832",
    "sg:province":"MD",
    "wof:name":"James K Rice Chartered",
    "wof:placetype":"venue"
},
  "geometry": {"coordinates":[-77.05068199999999,39.129932],"type":"Point"}
}