{
  "type": "Feature",
  "properties": {
    "addr:full":"12190 Crain Hwy Newburg MD 20664",
    "addr:housenumber":"12190",
    "addr:postcode":"20664",
    "addr:street":"Crain Hwy",
    "iso:country":"US",
    "sg:address":"12190 Crain Hwy",
    "sg:city":"Newburg",
    "sg:classifiers":[
        {
            "category":"Restaurant",
            "type":"Food & Drink"
        }
    ],
    "sg:phone":"+1 301 659 0300",
    "sg:postcode":"20664",
    "sg:province":"MD",
    "wof:name":"Norm's Big Bite",
    "wof:placetype":"venue"
},
  "geometry": {"coordinates":[-76.9571,38.378139],"type":"Point"}
}