{
  "type": "Feature",
  "properties": {
    "iso:country":"US",
    "sg:address":"19231 Montgomery Village Ave",
    "sg:city":"Gaithersburg",
    "sg:classifiers":[
        {
            "category":"Health Services",
            "subcategory":"Doctor",
            "type":"Services"
        }
    ],
    "sg:phone":"+1 301 258 9855",
    "sg:postcode":"20886",
    "sg:province":"MD",
    "sg:tags":[
        "dentist"
    ],
    "wof:name":"Steven W Goozh DDS",
    "wof:placetype":"venue"
},
  "geometry": {"coordinates":[-77.204026,39.170907],"type":"Point"}
}