{
  "type": "Feature",
  "properties": {
    "addr:full":"7719 Hollow Rd Middletown MD 21769",
    "addr:housenumber":"7719",
    "addr:postcode":"21769",
    "addr:street":"Hollow Rd",
    "iso:country":"US",
    "sg:address":"7719 Hollow Rd",
    "sg:city":"Middletown",
    "sg:classifiers":[
        {
            "category":"Professional",
            "subcategory":"Business Services",
            "type":"Services"
        }
    ],
    "sg:phone":"+1 301 748 1934",
    "sg:postcode":"21769",
    "sg:province":"MD",
    "wof:name":"Rfk Express LLC",
    "wof:placetype":"venue"
},
  "geometry": {"coordinates":[-77.51443500000001,39.444102],"type":"Point"}
}