{
  "type": "Feature",
  "properties": {
    "iso:country":"US",
    "sg:address":"3078 Tudor Hall Rd",
    "sg:city":"Riva",
    "sg:classifiers":[
        {
            "category":"Professional",
            "subcategory":"Management & Consulting",
            "type":"Services"
        }
    ],
    "sg:phone":"+1 410 956 9480",
    "sg:postcode":"21140",
    "sg:province":"MD",
    "sg:tags":[
        "statistics",
        "economic"
    ],
    "wof:name":"Gerald Donahoe",
    "wof:placetype":"venue"
},
  "geometry": {"coordinates":[-76.57828499999999,38.951695],"type":"Point"}
}