{
  "type": "Feature",
  "properties": {
    "addr:full":"303 Pintail Dr Havre De Grace MD 21078",
    "addr:housenumber":"303",
    "addr:postcode":"21078",
    "addr:street":"Pintail Dr",
    "iso:country":"US",
    "sg:address":"303 Pintail Dr",
    "sg:city":"Havre De Grace",
    "sg:classifiers":[
        {
            "category":"Real Estate",
            "subcategory":"Real Estate Agent",
            "type":"Services"
        }
    ],
    "sg:phone":"+1 410 939 7125",
    "sg:postcode":"21078",
    "sg:province":"MD",
    "wof:name":"Diane L Alegre",
    "wof:placetype":"venue"
},
  "geometry": {"coordinates":[-76.114886,39.556935],"type":"Point"}
}