{
  "type": "Feature",
  "properties": {
    "iso:country":"US",
    "sg:address":"7307 Baltimore Ave",
    "sg:city":"Takoma Park",
    "sg:classifiers":[
        {
            "category":"Health Services",
            "subcategory":"Health Practitioner",
            "type":"Services"
        }
    ],
    "sg:phone":"+1 301 585 6248",
    "sg:postcode":"20912",
    "sg:province":"MD",
    "sg:tags":[
        "psychologist"
    ],
    "wof:name":"Catherine Bernard PHD",
    "wof:placetype":"venue"
},
  "geometry": {"coordinates":[-77.018745,38.97972],"type":"Point"}
}