{
  "type": "Feature",
  "properties": {
    "addr:full":"29795 Three Notch Rd Charlotte Hall MD 20622",
    "addr:housenumber":"29795",
    "addr:postcode":"20622",
    "addr:street":"Three Notch Rd",
    "iso:country":"US",
    "sg:address":"29795 Three Notch Rd",
    "sg:city":"Charlotte Hall",
    "sg:classifiers":[
        {
            "category":"Health Services",
            "subcategory":"Doctor",
            "type":"Services"
        }
    ],
    "sg:phone":"+1 301 884 7330",
    "sg:postcode":"20622",
    "sg:province":"MD",
    "sg:tags":[
        "physician",
        "surgeon"
    ],
    "wof:name":"Thomas Wilkinson MD",
    "wof:placetype":"venue"
},
  "geometry": {"coordinates":[-76.775266,38.490618],"type":"Point"}
}