{
  "type": "Feature",
  "properties": {
    "addr:full":"11501 Alma St Silver Spring MD 20902",
    "addr:housenumber":"11501",
    "addr:postcode":"20902",
    "addr:street":"Alma St",
    "iso:country":"US",
    "sg:address":"11501 Alma St",
    "sg:city":"Silver Spring",
    "sg:classifiers":[
        {
            "category":"Professional",
            "subcategory":"Employment Agencies",
            "type":"Services"
        }
    ],
    "sg:phone":"+1 301 649 7492",
    "sg:postcode":"20902",
    "sg:province":"MD",
    "wof:name":"McDermott Assoc",
    "wof:placetype":"venue"
},
  "geometry": {"coordinates":[-77.04064099999999,39.045218],"type":"Point"}
}