{
  "type": "Feature",
  "properties": {
    "iso:country":"US",
    "sg:address":"5243 Fairlawn Ave",
    "sg:city":"Baltimore",
    "sg:classifiers":[
        {
            "category":"Building & Trades",
            "subcategory":"Construction",
            "type":"Services"
        }
    ],
    "sg:phone":"+1 410 542 8216",
    "sg:postcode":"21215",
    "sg:province":"MD",
    "sg:tags":[
        "maker",
        "cabinet"
    ],
    "wof:name":"Creative Cabinetry",
    "wof:placetype":"venue"
},
  "geometry": {"coordinates":[-76.68579699999999,39.343094],"type":"Point"}
}