{
  "type": "Feature",
  "properties": {
    "addr:full":"12 W Aylesbury Rd Lutherville MD 21093",
    "addr:housenumber":"12",
    "addr:postcode":"21093",
    "addr:street":"W Aylesbury Rd",
    "iso:country":"US",
    "sg:address":"12 W Aylesbury Rd",
    "sg:city":"Lutherville",
    "sg:classifiers":[
        {
            "category":"Social Services",
            "type":"Services"
        }
    ],
    "sg:phone":"+1 410 252 6770",
    "sg:postcode":"21093",
    "sg:province":"MD",
    "sg:tags":[
        "worker"
    ],
    "wof:name":"Ramberg Seska",
    "wof:placetype":"venue"
},
  "geometry": {"coordinates":[-76.626332,39.434552],"type":"Point"}
}