{
  "type": "Feature",
  "properties": {
    "addr:full":"21102 Camomile Ct Germantown MD 20876",
    "addr:postcode":"21102;20876",
    "addr:street":"Camomile Ct",
    "iso:country":"US",
    "sg:address":"21102 Camomile Ct",
    "sg:city":"Germantown",
    "sg:classifiers":[
        {
            "category":"Professional",
            "subcategory":"Detective & Security Services",
            "type":"Services"
        }
    ],
    "sg:phone":"+1 301 515 8300",
    "sg:postcode":"20876",
    "sg:province":"MD",
    "wof:name":"Apollo Consulting Group",
    "wof:placetype":"venue"
},
  "geometry": {"coordinates":[-77.26574599999999,39.203379],"type":"Point"}
}