{
  "type": "Feature",
  "properties": {
    "addr:full":"2117 W Pratt St Baltimore MD 21223",
    "addr:housenumber":"2117",
    "addr:postcode":"21223",
    "addr:street":"W Pratt St",
    "iso:country":"US",
    "sg:address":"2117 W Pratt St",
    "sg:city":"Baltimore",
    "sg:classifiers":[
        {
            "category":"Home & Garden",
            "subcategory":"Household Appliances",
            "type":"Retail Goods"
        }
    ],
    "sg:phone":"+1 410 233 7674",
    "sg:postcode":"21223",
    "sg:province":"MD",
    "sg:tags":[
        "refrigerator",
        "freezer"
    ],
    "wof:name":"City Wide Appliance & Refrig",
    "wof:placetype":"venue"
},
  "geometry": {"coordinates":[-76.650181,39.284911],"type":"Point"}
}