{
  "type": "Feature",
  "properties": {
    "iso:country":"US",
    "sg:address":"4858 Cordell Ave",
    "sg:city":"Bethesda",
    "sg:classifiers":[
        {
            "category":"Restaurant",
            "type":"Food & Drink"
        }
    ],
    "sg:phone":"+1 301 657 8388",
    "sg:postcode":"20814",
    "sg:province":"MD",
    "sg:tags":[
        "chinese"
    ],
    "sg:website":"asiancafebethesda.com",
    "wof:name":"Asian Cafe",
    "wof:placetype":"venue"
},
  "geometry": {"coordinates":[-77.097618,38.989913],"type":"Point"}
}