{
  "type": "Feature",
  "properties": {
    "iso:country":"US",
    "sg:address":"6901 Security Blvd Ste 3044",
    "sg:city":"Windsor Mill",
    "sg:classifiers":[
        {
            "category":"Professional",
            "type":"Services"
        }
    ],
    "sg:phone":"+1 410 944 2124",
    "sg:postcode":"21244",
    "sg:province":"MD",
    "sg:tags":[
        "caterer"
    ],
    "wof:name":"Honey Biscuits Inc",
    "wof:placetype":"venue"
},
  "geometry": {"coordinates":[-76.749494,39.312701],"type":"Point"}
}