{
  "type": "Feature",
  "properties": {
    "iso:country":"US",
    "sg:address":"8030 Georgia Ave",
    "sg:city":"Silver Spring",
    "sg:classifiers":[
        {
            "category":"Cafe",
            "type":"Food & Drink"
        },
        {
            "category":"Ice Cream",
            "type":"Food & Drink"
        }
    ],
    "sg:menulink":"http://www.allmenus.com/md/silver-spring/274477-moorenkos-ice-cream-cafe/menu/",
    "sg:phone":"+1 301 588 5656",
    "sg:postcode":"20910",
    "sg:province":"MD",
    "sg:tags":[
        "american"
    ],
    "wof:name":"Moorenko's Ice Cream Cafe",
    "wof:placetype":"venue"
},
  "geometry": {"coordinates":[-77.026736,38.987772],"type":"Point"}
}