{
  "type": "Feature",
  "properties": {
    "addr:full":"3301 New Mexico Ave NW Washington MD 20016",
    "addr:housenumber":"3301",
    "addr:postcode":"20016",
    "addr:street":"New Mexico Ave Nw",
    "iso:country":"US",
    "sg:address":"3301 New Mexico Ave NW",
    "sg:city":"Washington",
    "sg:classifiers":[
        {
            "category":"Health Services",
            "subcategory":"Doctor",
            "type":"Services"
        }
    ],
    "sg:phone":"+1 202 686 7077",
    "sg:postcode":"20016",
    "sg:province":"MD",
    "sg:tags":[
        "physician",
        "surgeon"
    ],
    "wof:name":"Francis W Iacobellis MD",
    "wof:placetype":"venue"
},
  "geometry": {"coordinates":[-77.086198,38.933985],"type":"Point"}
}