{
  "type": "Feature",
  "properties": {
    "iso:country":"US",
    "sg:address":"517 Main St",
    "sg:city":"Reisterstown",
    "sg:classifiers":[
        {
            "category":"Health Services",
            "subcategory":"Chiropractor",
            "type":"Services"
        }
    ],
    "sg:phone":"+1 410 833 3038",
    "sg:postcode":"21136",
    "sg:province":"MD",
    "wof:name":"Main Street Chiropractic",
    "wof:placetype":"venue"
},
  "geometry": {"coordinates":[-76.825968,39.456643],"type":"Point"}
}