{
  "type": "Feature",
  "properties": {
    "iso:country":"US",
    "sg:address":"4900 Philadelphia Way",
    "sg:city":"Lanham",
    "sg:classifiers":[
        {
            "category":"Building & Trades",
            "subcategory":"Construction",
            "type":"Services"
        }
    ],
    "sg:phone":"+1 301 306 3850",
    "sg:postcode":"20706",
    "sg:province":"MD",
    "sg:tags":[
        "contractor"
    ],
    "wof:name":"Adc Builders Inc",
    "wof:placetype":"venue"
},
  "geometry": {"coordinates":[-76.83832200000001,38.959944],"type":"Point"}
}