{
  "type": "Feature",
  "properties": {
    "addr:full":"6824 Industrial Dr Beltsville MD 20705",
    "addr:housenumber":"6824",
    "addr:postcode":"20705",
    "addr:street":"Industrial Dr",
    "iso:country":"US",
    "sg:address":"6824 Industrial Dr",
    "sg:city":"Beltsville",
    "sg:classifiers":[
        {
            "category":"Building & Trades",
            "subcategory":"Landscaping Services",
            "type":"Services"
        }
    ],
    "sg:phone":"+1 301 931 1122",
    "sg:postcode":"20705",
    "sg:province":"MD",
    "sg:tags":[
        "landscape",
        "contractor"
    ],
    "wof:name":"Metro Technologies Inc",
    "wof:placetype":"venue"
},
  "geometry": {"coordinates":[-76.88938899999999,39.052692],"type":"Point"}
}