{
  "type": "Feature",
  "properties": {
    "iso:country":"US",
    "sg:address":"17831 Georgia Ave",
    "sg:city":"Olney",
    "sg:classifiers":[
        {
            "category":"Banks & Credit Unions",
            "subcategory":"Bank",
            "type":"Services"
        }
    ],
    "sg:phone":"+1 301 924 3460",
    "sg:postcode":"20832",
    "sg:province":"MD",
    "sg:tags":[
        "saving",
        "commercial"
    ],
    "sg:website":"http://www.chevychasebank.com",
    "wof:name":"Chevy Chase Bank, F.S.B.",
    "wof:placetype":"venue"
},
  "geometry": {"coordinates":[-77.066788,39.148546],"type":"Point"}
}