{
  "type": "Feature",
  "properties": {
    "addr:full":"8708 Sharpsburg Pike Fairplay MD 21733",
    "addr:postcode":"8708;21733",
    "addr:street":"Sharpsburg Pike",
    "iso:country":"US",
    "sg:address":"8708 Sharpsburg Pike",
    "sg:city":"Fairplay",
    "sg:classifiers":[
        {
            "category":"Autos & Motor Vehicles",
            "subcategory":"Fuel & Gas Station",
            "type":"Retail Goods"
        }
    ],
    "sg:phone":"+1 301 582 0610",
    "sg:postcode":"21733",
    "sg:province":"MD",
    "sg:tags":[
        "oil"
    ],
    "wof:name":"May's Service Station",
    "wof:placetype":"venue"
},
  "geometry": {"coordinates":[-77.735384,39.556379],"type":"Point"}
}