{
  "type": "Feature",
  "properties": {
    "iso:country":"US",
    "sg:address":"2301 Distribution Cir",
    "sg:city":"Silver Spring",
    "sg:classifiers":[
        {
            "category":"Manufacturing",
            "subcategory":"Food",
            "type":"Manufacturing & Wholesale Goods"
        }
    ],
    "sg:phone":"+1 301 608 8996",
    "sg:postcode":"20910",
    "sg:province":"MD",
    "sg:tags":[
        "frozen",
        "dessert",
        "ice",
        "cream"
    ],
    "wof:name":"Great Falls Ice Cream",
    "wof:placetype":"venue"
},
  "geometry": {"coordinates":[-77.05039499999999,39.006801],"type":"Point"}
}