{
  "type": "Feature",
  "properties": {
    "addr:full":"1251 Light St Baltimore MD 21230",
    "addr:housenumber":"1251",
    "addr:postcode":"21230",
    "addr:street":"Light St",
    "iso:country":"US",
    "sg:address":"1251 Light St",
    "sg:city":"Baltimore",
    "sg:classifiers":[
        {
            "category":"Education",
            "subcategory":"Library",
            "type":"Public Place"
        }
    ],
    "sg:phone":"+1 410 396 1096",
    "sg:postcode":"21230",
    "sg:province":"MD",
    "sg:website":"http://prattlibrary.org",
    "wof:name":"Enoch Pratt Free Library - Light Street Branch",
    "wof:placetype":"venue"
},
  "geometry": {"coordinates":[-76.612109,39.275409],"type":"Point"}
}