{
  "type": "Feature",
  "properties": {
    "addr:full":"6625 Grove Ave Baltimore MD 21244",
    "addr:housenumber":"6625",
    "addr:postcode":"21244",
    "addr:street":"Grove Ave",
    "iso:country":"US",
    "sg:address":"6625 Grove Ave",
    "sg:city":"Baltimore",
    "sg:classifiers":[
        {
            "category":"Retail",
            "subcategory":"Car Wash",
            "type":"Services"
        }
    ],
    "sg:phone":"+1 410 298 9522",
    "sg:postcode":"21244",
    "sg:province":"MD",
    "sg:tags":[
        "polishing",
        "washing"
    ],
    "wof:name":"Mighty Wash",
    "wof:placetype":"venue"
},
  "geometry": {"coordinates":[-76.750919,39.315897],"type":"Point"}
}