{
  "type": "Feature",
  "properties": {
    "iso:country":"US",
    "sg:address":"1009 Bay Ridge Ave",
    "sg:city":"Annapolis",
    "sg:classifiers":[
        {
            "category":"Freight",
            "type":"Transportation"
        }
    ],
    "sg:phone":"+1 410 263 7919",
    "sg:postcode":"21403",
    "sg:province":"MD",
    "sg:tags":[
        "good",
        "for",
        "shipping",
        "packaging",
        "agent",
        "mailing"
    ],
    "wof:name":"Postal Express Inc",
    "wof:placetype":"venue"
},
  "geometry": {"coordinates":[-76.48957299999999,38.963973],"type":"Point"}
}