{
  "type": "Feature",
  "properties": {
    "addr:full":"11775 Holly Auto Center Ln Waldorf MD 20601",
    "addr:housenumber":"11775",
    "addr:postcode":"20601",
    "addr:street":"Holly Auto Center Ln",
    "iso:country":"US",
    "sg:address":"11775 Holly Auto Center Ln",
    "sg:city":"Waldorf",
    "sg:classifiers":[
        {
            "category":"Banks & Credit Unions",
            "subcategory":"Investment Brokerage",
            "type":"Services"
        },
        {
            "category":"Banks & Credit Unions",
            "subcategory":"Financial Services",
            "type":"Services"
        }
    ],
    "sg:phone":"+1 301 645 0029",
    "sg:postcode":"20601",
    "sg:province":"MD",
    "sg:tags":[
        "advisory",
        "management"
    ],
    "wof:name":"Upshaw Enterprises Investments",
    "wof:placetype":"venue"
},
  "geometry": {"coordinates":[-76.90151299999999,38.631939],"type":"Point"}
}