{
  "type": "Feature",
  "properties": {
    "addr:full":"2710 Hampstead Mexico Rd Hampstead MD 21074",
    "addr:housenumber":"2710",
    "addr:postcode":"21074",
    "addr:street":"Hampstead Mexico Rd",
    "iso:country":"US",
    "sg:address":"2710 Hampstead Mexico Rd",
    "sg:city":"Hampstead",
    "sg:classifiers":[
        {
            "category":"Recreation",
            "type":"Entertainment"
        }
    ],
    "sg:phone":"+1 410 374 8655",
    "sg:postcode":"21074",
    "sg:province":"MD",
    "sg:tags":[
        "instruction",
        "gymnastic"
    ],
    "wof:name":"Carroll Gymnastics Ctr",
    "wof:placetype":"venue"
},
  "geometry": {"coordinates":[-76.901545,39.609494],"type":"Point"}
}