{
  "type": "Feature",
  "properties": {
    "addr:full":"24 Nutwell Rd Lothian MD 20711",
    "addr:housenumber":"24",
    "addr:postcode":"20711",
    "addr:street":"Nutwell Rd",
    "iso:country":"US",
    "sg:address":"24 Nutwell Rd",
    "sg:city":"Lothian",
    "sg:classifiers":[
        {
            "category":"Building & Trades",
            "subcategory":"Landscaping Services",
            "type":"Services"
        }
    ],
    "sg:phone":"+1 410 956 1344",
    "sg:postcode":"20711",
    "sg:province":"MD",
    "sg:tags":[
        "landscape",
        "contractor"
    ],
    "sg:website":"www.exteriorimage.com",
    "wof:name":"Exterior Image & Woodscape Inc",
    "wof:placetype":"venue"
},
  "geometry": {"coordinates":[-76.593897,38.803524],"type":"Point"}
}