{
  "type": "Feature",
  "properties": {
    "iso:country":"US",
    "sg:address":"9517 Seminole St",
    "sg:city":"Silver Spring",
    "sg:classifiers":[
        {
            "category":"Education",
            "subcategory":"Special Training",
            "type":"Public Place"
        }
    ],
    "sg:phone":"+1 301 587 7976",
    "sg:postcode":"20901",
    "sg:province":"MD",
    "wof:name":"Vocal Quality Enhancement",
    "wof:placetype":"venue"
},
  "geometry": {"coordinates":[-77.006485,39.012282],"type":"Point"}
}