{
  "type": "Feature",
  "properties": {
    "addr:full":"13804 Bauer Dr Rockville MD 20853",
    "addr:housenumber":"13804",
    "addr:postcode":"20853",
    "addr:street":"Bauer Dr",
    "iso:country":"US",
    "sg:address":"13804 Bauer Dr",
    "sg:city":"Rockville",
    "sg:classifiers":[
        {
            "category":"Shopping",
            "subcategory":"Catalog Store",
            "type":"Retail Goods"
        }
    ],
    "sg:phone":"+1 301 460 4844",
    "sg:postcode":"20853",
    "sg:province":"MD",
    "sg:tags":[
        "mail",
        "order"
    ],
    "sg:website":"www.atlantissilver.com",
    "wof:name":"Atlantis Silver Co",
    "wof:placetype":"venue"
},
  "geometry": {"coordinates":[-77.08813600000001,39.083497],"type":"Point"}
}