{
  "type": "Feature",
  "properties": {
    "addr:full":"5700 Phillips St Brooklyn MD 21225",
    "addr:housenumber":"5700",
    "addr:postcode":"21225",
    "addr:street":"Phillips St",
    "iso:country":"US",
    "sg:address":"5700 Phillips St",
    "sg:city":"Brooklyn",
    "sg:classifiers":[
        {
            "category":"Utilities",
            "subcategory":"Natural Gas",
            "type":"Services"
        }
    ],
    "sg:phone":"+1 410 789 7214",
    "sg:postcode":"21225",
    "sg:province":"MD",
    "sg:tags":[
        "distribution"
    ],
    "wof:name":"Salutaris International S",
    "wof:placetype":"venue"
},
  "geometry": {"coordinates":[-76.609589,39.21833],"type":"Point"}
}