{
  "type": "Feature",
  "properties": {
    "iso:country":"US",
    "sg:address":"2015 William Franklin Dr",
    "sg:city":"Frederick",
    "sg:classifiers":[
        {
            "category":"Shopping",
            "subcategory":"Gifts & Souvenirs",
            "type":"Retail Goods"
        }
    ],
    "sg:phone":"+1 301 662 8029",
    "sg:postcode":"21702",
    "sg:province":"MD",
    "sg:tags":[
        "shop"
    ],
    "wof:name":"Exotic Treasures",
    "wof:placetype":"venue"
},
  "geometry": {"coordinates":[-77.412216,39.469761],"type":"Point"}
}