{
  "type": "Feature",
  "properties": {
    "iso:country":"US",
    "sg:address":"2900 Byrdtown Rd",
    "sg:city":"Crisfield",
    "sg:classifiers":[
        {
            "category":"Retail",
            "subcategory":"Repair Shop",
            "type":"Services"
        }
    ],
    "sg:phone":"+1 410 968 2174",
    "sg:postcode":"21817",
    "sg:province":"MD",
    "sg:tags":[
        "lock",
        "locksmith"
    ],
    "wof:name":"A W Buell Locksmiths",
    "wof:placetype":"venue"
},
  "geometry": {"coordinates":[-75.83327300000001,37.961817],"type":"Point"}
}