{
  "type": "Feature",
  "properties": {
    "iso:country":"US",
    "sg:address":"2 S Hays St",
    "sg:city":"Bel Air",
    "sg:classifiers":[
        {
            "category":"Building & Trades",
            "subcategory":"Construction",
            "type":"Services"
        }
    ],
    "sg:phone":"+1 410 838 7280",
    "sg:postcode":"21014",
    "sg:province":"MD",
    "sg:tags":[
        "home",
        "builder"
    ],
    "wof:name":"Stockdale Building Co",
    "wof:placetype":"venue"
},
  "geometry": {"coordinates":[-76.352231,39.535322],"type":"Point"}
}