{
  "type": "Feature",
  "properties": {
    "iso:country":"US",
    "sg:address":"100 N Holliday St",
    "sg:city":"Baltimore",
    "sg:classifiers":[
        {
            "category":"Education",
            "subcategory":"School",
            "type":"Public Place"
        }
    ],
    "sg:phone":"+1 410 545 1746",
    "sg:postcode":"21202",
    "sg:province":"MD",
    "wof:name":"Reginald F Lewis School",
    "wof:placetype":"venue"
},
  "geometry": {"coordinates":[-76.610303,39.291272],"type":"Point"}
}