{
  "type": "Feature",
  "properties": {
    "addr:full":"1699 Baltimore Annapolis Blvd Arnold MD 21012",
    "addr:housenumber":"1699",
    "addr:postcode":"21012",
    "addr:street":"Baltimore Annapolis Blvd",
    "iso:country":"US",
    "sg:address":"1699 Baltimore Annapolis Blvd",
    "sg:city":"Arnold",
    "sg:classifiers":[
        {
            "category":"Freight",
            "type":"Transportation"
        }
    ],
    "sg:phone":"+1 410 757 9300",
    "sg:postcode":"21012",
    "sg:province":"MD",
    "sg:tags":[
        "commercial",
        "storage"
    ],
    "wof:name":"Storage USA",
    "wof:placetype":"venue"
},
  "geometry": {"coordinates":[-76.491817,39.017016],"type":"Point"}
}