{
  "type": "Feature",
  "properties": {
    "addr:full":"1713 Rosemont Ave Frederick MD 21702",
    "addr:housenumber":"1713",
    "addr:postcode":"21702",
    "addr:street":"Rosemont Ave",
    "iso:country":"US",
    "sg:address":"1713 Rosemont Ave",
    "sg:city":"Frederick",
    "sg:classifiers":[
        {
            "category":"Restaurant",
            "type":"Food & Drink"
        }
    ],
    "sg:menulink":"http://www.allmenus.com/md/frederick/146825-subway/menu/",
    "sg:phone":"+1 301 682 6421",
    "sg:postcode":"21702",
    "sg:province":"MD",
    "sg:tags":[
        "american",
        "sandwich"
    ],
    "wof:name":"Subway",
    "wof:placetype":"venue"
},
  "geometry": {"coordinates":[-77.43200400000001,39.428276],"type":"Point"}
}