{
  "type": "Feature",
  "properties": {
    "addr:full":"6210 Fulmer Rd Frederick MD 21703",
    "addr:postcode":"6210;21703",
    "addr:street":"Fulmer Rd",
    "iso:country":"US",
    "sg:address":"6210 Fulmer Rd",
    "sg:city":"Frederick",
    "sg:classifiers":[
        {
            "category":"Building & Trades",
            "subcategory":"Construction",
            "type":"Services"
        }
    ],
    "sg:phone":"+1 301 473 8334",
    "sg:postcode":"21703",
    "sg:province":"MD",
    "sg:tags":[
        "tile",
        "dealer"
    ],
    "wof:name":"Tri State Tile Inc",
    "wof:placetype":"venue"
},
  "geometry": {"coordinates":[-77.49895100000001,39.406517],"type":"Point"}
}