{
  "type": "Feature",
  "properties": {
    "addr:full":"110 Hospital Rd Prince Frederick MD 20678",
    "addr:housenumber":"110",
    "addr:postcode":"20678",
    "addr:street":"Hospital Rd",
    "iso:country":"US",
    "sg:address":"110 Hospital Rd",
    "sg:city":"Prince Frederick",
    "sg:classifiers":[
        {
            "category":"Health Services",
            "subcategory":"Doctor",
            "type":"Services"
        }
    ],
    "sg:phone":"+1 410 535 9555",
    "sg:postcode":"20678",
    "sg:province":"MD",
    "sg:tags":[
        "physician",
        "surgeon"
    ],
    "wof:name":"Calvert Ear Nose & Throat",
    "wof:placetype":"venue"
},
  "geometry": {"coordinates":[-76.595539,38.560077],"type":"Point"}
}