{
  "type": "Feature",
  "properties": {
    "iso:country":"US",
    "sg:address":"446 Gaither St",
    "sg:city":"Gaithersburg",
    "sg:classifiers":[
        {
            "category":"Professional",
            "subcategory":"Computer Services",
            "type":"Services"
        }
    ],
    "sg:phone":"+1 301 926 1520",
    "sg:postcode":"20877",
    "sg:province":"MD",
    "sg:tags":[
        "related"
    ],
    "wof:name":"Jessy K Technology Corp",
    "wof:placetype":"venue"
},
  "geometry": {"coordinates":[-77.187873,39.134441],"type":"Point"}
}