{
  "type": "Feature",
  "properties": {
    "iso:country":"US",
    "sg:address":"4714 Miller Ave",
    "sg:city":"Bethesda",
    "sg:classifiers":[
        {
            "category":"Retail",
            "subcategory":"Auto Rental",
            "type":"Services"
        },
        {
            "category":"Retail",
            "subcategory":"Storage",
            "type":"Services"
        }
    ],
    "sg:phone":"+1 301 657 2326",
    "sg:postcode":"20814",
    "sg:province":"MD",
    "sg:tags":[
        "moving-self",
        "truck"
    ],
    "wof:name":"Bp Truck Rental",
    "wof:placetype":"venue"
},
  "geometry": {"coordinates":[-77.093586,38.980511],"type":"Point"}
}