{
  "type": "Feature",
  "properties": {
    "addr:full":"17502 Da Wrong Ln Hagerstown MD 21740",
    "addr:housenumber":"17502",
    "addr:postcode":"21740",
    "addr:street":"Da Wrong Ln",
    "iso:country":"US",
    "sg:address":"17502 Da Wrong Ln",
    "sg:city":"Hagerstown",
    "sg:classifiers":[
        {
            "category":"Manufacturing",
            "subcategory":"Printing",
            "type":"Manufacturing & Wholesale Goods"
        }
    ],
    "sg:phone":"+1 301 791 4970",
    "sg:postcode":"21740",
    "sg:province":"MD",
    "sg:tags":[
        "printer"
    ],
    "wof:name":"Penguin Graphics",
    "wof:placetype":"venue"
},
  "geometry": {"coordinates":[-77.76858300000001,39.586698],"type":"Point"}
}