{
  "type": "Feature",
  "properties": {
    "addr:full":"702 Baltimore Pike Bel Air MD 21014",
    "addr:housenumber":"702",
    "addr:postcode":"21014",
    "addr:street":"Baltimore Pike",
    "iso:country":"US",
    "sg:address":"702 Baltimore Pike",
    "sg:city":"Bel Air",
    "sg:classifiers":[
        {
            "category":"Personal",
            "subcategory":"Barber",
            "type":"Services"
        }
    ],
    "sg:phone":"+1 410 893 7089",
    "sg:postcode":"21014",
    "sg:province":"MD",
    "wof:name":"Off The Top",
    "wof:placetype":"venue"
},
  "geometry": {"coordinates":[-76.35781799999999,39.523029],"type":"Point"}
}