{
  "type": "Feature",
  "properties": {
    "addr:full":"3981 Clay St Point Of Rocks MD 21777",
    "addr:housenumber":"3981",
    "addr:postcode":"21777",
    "addr:street":"Clay St",
    "iso:country":"US",
    "sg:address":"3981 Clay St",
    "sg:city":"Point Of Rocks",
    "sg:classifiers":[
        {
            "category":"Freight",
            "type":"Transportation"
        }
    ],
    "sg:phone":"+1 301 874 3327",
    "sg:postcode":"21777",
    "sg:province":"MD",
    "wof:name":"Csx Transportation",
    "wof:placetype":"venue"
},
  "geometry": {"coordinates":[-77.531813,39.274045],"type":"Point"}
}