{
  "type": "Feature",
  "properties": {
    "addr:full":"2809 Liberty Rd Sykesville MD 21784",
    "addr:housenumber":"2809",
    "addr:postcode":"21784",
    "addr:street":"Liberty Rd",
    "iso:country":"US",
    "sg:address":"2809 Liberty Rd",
    "sg:city":"Sykesville",
    "sg:classifiers":[
        {
            "category":"Building & Trades",
            "subcategory":"Plumbing",
            "type":"Services"
        },
        {
            "category":"Shopping",
            "subcategory":"Party Supplies",
            "type":"Retail Goods"
        },
        {
            "category":"Building & Trades",
            "subcategory":"Construction",
            "type":"Services"
        },
        {
            "category":"Utilities",
            "subcategory":"Sewage",
            "type":"Services"
        }
    ],
    "sg:phone":"+1 410 795 2947",
    "sg:postcode":"21784",
    "sg:province":"MD",
    "sg:tags":[
        "systems-cleaning",
        "tank",
        "toilets-portable",
        "septic",
        "excavation",
        "system",
        "contractor"
    ],
    "sg:website":"http://www.poophappens.com",
    "wof:name":"Freedom Septic Service Inc - Serving Your",
    "wof:placetype":"venue"
},
  "geometry": {"coordinates":[-76.89577300000001,39.397161],"type":"Point"}
}