{
  "type": "Feature",
  "properties": {
    "iso:country":"US",
    "sg:address":"18642 Poffenberger Rd",
    "sg:city":"Hagerstown",
    "sg:classifiers":[
        {
            "category":"Food & Beverages",
            "subcategory":"Specialty",
            "type":"Retail Goods"
        }
    ],
    "sg:phone":"+1 301 739 2825",
    "sg:postcode":"21740",
    "sg:province":"MD",
    "sg:tags":[
        "water",
        "bulk",
        "company"
    ],
    "wof:name":"K & M Water Svc",
    "wof:placetype":"venue"
},
  "geometry": {"coordinates":[-77.72354,39.594441],"type":"Point"}
}