{
  "type": "Feature",
  "properties": {
    "iso:country":"US",
    "sg:address":"2316 E Gate Dr",
    "sg:city":"Silver Spring",
    "sg:classifiers":[
        {
            "category":"Building & Trades",
            "subcategory":"Construction",
            "type":"Services"
        }
    ],
    "sg:phone":"+1 301 460 3038",
    "sg:postcode":"20906",
    "sg:province":"MD",
    "sg:tags":[
        "builder",
        "operative"
    ],
    "wof:name":"J J & E Contractors",
    "wof:placetype":"venue"
},
  "geometry": {"coordinates":[-77.051649,39.085412],"type":"Point"}
}