{
  "type": "Feature",
  "properties": {
    "iso:country":"US",
    "sg:address":"3310 Wood Valley Dr",
    "sg:city":"Pikesville",
    "sg:classifiers":[
        {
            "category":"Social Services",
            "subcategory":"Child Care",
            "type":"Services"
        }
    ],
    "sg:phone":"+1 410 484 2728",
    "sg:postcode":"21208",
    "sg:province":"MD",
    "wof:name":"Play Keepers Inc",
    "wof:placetype":"venue"
},
  "geometry": {"coordinates":[-76.703524,39.399916],"type":"Point"}
}