{
  "type": "Feature",
  "properties": {
    "addr:full":"8200 Perry Hall Blvd Nottingham MD 21236",
    "addr:housenumber":"8200",
    "addr:postcode":"21236",
    "addr:street":"Perry Hall Blvd",
    "iso:country":"US",
    "sg:address":"8200 Perry Hall Blvd",
    "sg:city":"Nottingham",
    "sg:classifiers":[
        {
            "category":"Shopping",
            "subcategory":"Clothing, Apparel, & Fashions",
            "type":"Retail Goods"
        }
    ],
    "sg:phone":"+1 410 933 9601",
    "sg:postcode":"21236",
    "sg:province":"MD",
    "sg:tags":[
        "men's",
        "accessory",
        "apparel",
        "girls'",
        "women's",
        "clothing",
        "boys'",
        "store"
    ],
    "sg:website":"http://www.rue21.com",
    "wof:name":"Rue21",
    "wof:placetype":"venue"
},
  "geometry": {"coordinates":[-76.472458,39.375381],"type":"Point"}
}