{
  "type": "Feature",
  "properties": {
    "iso:country":"US",
    "sg:address":"7301 Brookside Dr",
    "sg:city":"Frederick",
    "sg:classifiers":[
        {
            "category":"Wholesale",
            "subcategory":"Machinery & Supplies",
            "type":"Manufacturing & Wholesale Goods"
        }
    ],
    "sg:phone":"+1 301 473 9300",
    "sg:postcode":"21702",
    "sg:province":"MD",
    "sg:tags":[
        "equipment",
        "safety",
        "clothing"
    ],
    "wof:name":"Airbag Safety Co",
    "wof:placetype":"venue"
},
  "geometry": {"coordinates":[-77.472572,39.436997],"type":"Point"}
}