{
  "type": "Feature",
  "properties": {
    "addr:full":"201 E Baltimore St Baltimore MD 21202",
    "addr:housenumber":"201",
    "addr:postcode":"21202",
    "addr:street":"E Baltimore St",
    "iso:country":"US",
    "sg:address":"201 E Baltimore St",
    "sg:city":"Baltimore",
    "sg:classifiers":[
        {
            "category":"Health Services",
            "subcategory":"Hospital",
            "type":"Services"
        }
    ],
    "sg:phone":"+1 410 837 2647",
    "sg:postcode":"21202",
    "sg:province":"MD",
    "sg:tags":[
        "mental"
    ],
    "sg:website":"www.bhca.org",
    "wof:name":"Baltimore Mental Health Systs",
    "wof:placetype":"venue"
},
  "geometry": {"coordinates":[-76.611048,39.289701],"type":"Point"}
}