{
  "type": "Feature",
  "properties": {
    "iso:country":"US",
    "sg:address":"3442 Mayfield Ave",
    "sg:city":"Baltimore",
    "sg:classifiers":[
        {
            "category":"Professional",
            "subcategory":"Business Services",
            "type":"Services"
        }
    ],
    "sg:phone":"+1 410 978 5233",
    "sg:postcode":"21213",
    "sg:province":"MD",
    "wof:name":"Hl Jones Enterprises",
    "wof:placetype":"venue"
},
  "geometry": {"coordinates":[-76.569479,39.31967],"type":"Point"}
}