{
  "type": "Feature",
  "properties": {
    "addr:full":"1100 Wayne Ave Silver Spring MD 20910",
    "addr:housenumber":"1100",
    "addr:postcode":"20910",
    "addr:street":"Wayne Ave",
    "iso:country":"US",
    "sg:address":"1100 Wayne Ave",
    "sg:city":"Silver Spring",
    "sg:classifiers":[
        {
            "category":"Shopping",
            "subcategory":"Computers & Home Electronics",
            "type":"Retail Goods"
        }
    ],
    "sg:phone":"+1 301 891 1890",
    "sg:postcode":"20910",
    "sg:province":"MD",
    "sg:tags":[
        "software"
    ],
    "wof:name":"Ondemand Software Inc",
    "wof:placetype":"venue"
},
  "geometry": {"coordinates":[-77.029197,38.99451],"type":"Point"}
}