{
  "type": "Feature",
  "properties": {
    "iso:country":"US",
    "sg:address":"29 S Main St",
    "sg:city":"Bel Air",
    "sg:classifiers":[
        {
            "category":"Restaurant",
            "type":"Food & Drink"
        }
    ],
    "sg:phone":"+1 410 838 8007",
    "sg:postcode":"21014",
    "sg:province":"MD",
    "sg:tags":[
        "eating"
    ],
    "sg:website":"www.tower-belair.com",
    "wof:name":"Main Street Tower Restaurant",
    "wof:placetype":"venue"
},
  "geometry": {"coordinates":[-76.349336,39.536573],"type":"Point"}
}