{
  "type": "Feature",
  "properties": {
    "addr:full":"9 W Saratoga St Baltimore MD 21201",
    "addr:housenumber":"9",
    "addr:postcode":"21201",
    "addr:street":"W Saratoga St",
    "iso:country":"US",
    "sg:address":"9 W Saratoga St",
    "sg:city":"Baltimore",
    "sg:classifiers":[
        {
            "category":"Food & Beverages",
            "subcategory":"Groceries & Convenience Stores",
            "type":"Retail Goods"
        }
    ],
    "sg:phone":"+1 410 727 4570",
    "sg:postcode":"21201",
    "sg:province":"MD",
    "wof:name":"Charles Towers Convenient Store",
    "wof:placetype":"venue"
},
  "geometry": {"coordinates":[-76.615303,39.292198],"type":"Point"}
}