{
  "type": "Feature",
  "properties": {
    "iso:country":"US",
    "sg:address":"2625 Riva Rd",
    "sg:city":"Annapolis",
    "sg:classifiers":[
        {
            "category":"Restaurant",
            "type":"Food & Drink"
        }
    ],
    "sg:menulink":"http://www.allmenus.com/md/annapolis/25382-squisito/menu/",
    "sg:phone":"+1 410 266 1474",
    "sg:postcode":"21401",
    "sg:province":"MD",
    "sg:tags":[
        "american",
        "pizza"
    ],
    "wof:name":"Squisito",
    "wof:placetype":"venue"
},
  "geometry": {"coordinates":[-76.557102,38.975791],"type":"Point"}
}