{
  "type": "Feature",
  "properties": {
    "addr:full":"5400 Queens Chapel Rd Hyattsville MD 20782",
    "addr:housenumber":"5400",
    "addr:postcode":"20782",
    "addr:street":"Queens Chapel Rd",
    "iso:country":"US",
    "sg:address":"5400 Queens Chapel Rd",
    "sg:city":"Hyattsville",
    "sg:classifiers":[
        {
            "category":"Communications",
            "type":"Services"
        }
    ],
    "sg:phone":"+1 301 559 9425",
    "sg:postcode":"20782",
    "sg:province":"MD",
    "wof:name":"First Choice Communications",
    "wof:placetype":"venue"
},
  "geometry": {"coordinates":[-76.961224,38.956482],"type":"Point"}
}