{
  "type": "Feature",
  "properties": {
    "iso:country":"US",
    "sg:address":"18248 Contour Rd",
    "sg:city":"Montgomery Vlg",
    "sg:classifiers":[
        {
            "category":"Home & Garden",
            "subcategory":"Furniture",
            "type":"Retail Goods"
        }
    ],
    "sg:phone":"+1 301 990 1333",
    "sg:postcode":"20877",
    "sg:province":"MD",
    "wof:name":"Zeyna Furniture Gallery Inc",
    "wof:placetype":"venue"
},
  "geometry": {"coordinates":[-77.1978,39.155429],"type":"Point"}
}