{
  "type": "Feature",
  "properties": {
    "iso:country":"US",
    "sg:address":"2400 Boston St",
    "sg:city":"Baltimore",
    "sg:classifiers":[
        {
            "category":"Professional",
            "subcategory":"Computer Services",
            "type":"Services"
        }
    ],
    "sg:phone":"+1 410 369 0050",
    "sg:postcode":"21224",
    "sg:province":"MD",
    "sg:tags":[
        "internet"
    ],
    "wof:name":"E Magination",
    "wof:placetype":"venue"
},
  "geometry": {"coordinates":[-76.581436,39.281243],"type":"Point"}
}