{
  "type": "Feature",
  "properties": {
    "iso:country":"US",
    "sg:address":"5917 Silver Hill Rd",
    "sg:city":"District Heights",
    "sg:classifiers":[
        {
            "category":"Retail",
            "subcategory":"Auto Repair",
            "type":"Services"
        }
    ],
    "sg:phone":"+1 301 736 5823",
    "sg:postcode":"20747",
    "sg:province":"MD",
    "sg:website":"www.jiffylube.com",
    "wof:name":"Jiffy Lube",
    "wof:placetype":"venue"
},
  "geometry": {"coordinates":[-76.901703,38.8615],"type":"Point"}
}