{
  "type": "Feature",
  "properties": {
    "iso:country":"US",
    "sg:address":"9710 Martin Luther King Jr Hwy",
    "sg:city":"Lanham",
    "sg:classifiers":[
        {
            "category":"Food & Beverages",
            "subcategory":"Liquor & Beverages",
            "type":"Retail Goods"
        }
    ],
    "sg:phone":"+1 301 773 2522",
    "sg:postcode":"20706",
    "sg:province":"MD",
    "wof:name":"A-1 Liquor & Restaurant",
    "wof:placetype":"venue"
},
  "geometry": {"coordinates":[-76.839701,38.949637],"type":"Point"}
}