{
  "type": "Feature",
  "properties": {
    "iso:country":"US",
    "sg:address":"7102 2nd Ave",
    "sg:city":"Queenstown",
    "sg:classifiers":[
        {
            "category":"Personal",
            "type":"Services"
        }
    ],
    "sg:phone":"+1 410 643 4567",
    "sg:postcode":"21658",
    "sg:province":"MD",
    "sg:tags":[
        "wear",
        "formal"
    ],
    "wof:name":"C R Bottems Inc",
    "wof:placetype":"venue"
},
  "geometry": {"coordinates":[-76.15893699999999,38.991984],"type":"Point"}
}