{
  "type": "Feature",
  "properties": {
    "addr:full":"23282 Three Notch Rd California MD 20619",
    "addr:housenumber":"23282",
    "addr:postcode":"20619",
    "addr:street":"Three Notch Rd",
    "iso:country":"US",
    "sg:address":"23282 Three Notch Rd",
    "sg:city":"California",
    "sg:classifiers":[
        {
            "category":"Organizations",
            "subcategory":"Community Association",
            "type":"Services"
        }
    ],
    "sg:phone":"+1 301 862 3247",
    "sg:postcode":"20619",
    "sg:province":"MD",
    "sg:tags":[
        "military"
    ],
    "wof:name":"V F W Post 2632",
    "wof:placetype":"venue"
},
  "geometry": {"coordinates":[-76.527159,38.306818],"type":"Point"}
}