{
  "type": "Feature",
  "properties": {
    "addr:full":"Philip J Bean Medica Hollywood MD 20636",
    "addr:postcode":"20636",
    "iso:country":"US",
    "sg:address":"Philip J Bean Medica",
    "sg:city":"Hollywood",
    "sg:classifiers":[
        {
            "category":"Health Services",
            "subcategory":"Doctor",
            "type":"Services"
        }
    ],
    "sg:phone":"+1 301 373 7900",
    "sg:postcode":"20636",
    "sg:province":"MD",
    "sg:tags":[
        "practice",
        "cardiologist",
        "family"
    ],
    "wof:name":"Shah Associates MD PA",
    "wof:placetype":"venue"
},
  "geometry": {"coordinates":[-76.562302,38.3405],"type":"Point"}
}