{
  "type": "Feature",
  "properties": {
    "addr:full":"311 Chalk Hill Dr Baltimore MD 21208",
    "addr:housenumber":"311",
    "addr:postcode":"21208",
    "addr:street":"Chalk Hill Dr",
    "iso:country":"US",
    "sg:address":"311 Chalk Hill Dr",
    "sg:city":"Baltimore",
    "sg:classifiers":[
        {
            "category":"Shopping",
            "subcategory":"Computers & Home Electronics",
            "type":"Retail Goods"
        }
    ],
    "sg:phone":"+1 410 653 9540",
    "sg:postcode":"21208",
    "sg:province":"MD",
    "sg:tags":[
        "software"
    ],
    "wof:name":"New Concept Inc",
    "wof:placetype":"venue"
},
  "geometry": {"coordinates":[-76.748175,39.391327],"type":"Point"}
}