{
  "type": "Feature",
  "properties": {
    "addr:full":"919 East St Frederick MD 21701",
    "addr:housenumber":"919",
    "addr:postcode":"21701",
    "addr:street":"East St",
    "iso:country":"US",
    "sg:address":"919 East St",
    "sg:city":"Frederick",
    "sg:classifiers":[
        {
            "category":"Organizations",
            "subcategory":"Religious Organization",
            "type":"Services"
        }
    ],
    "sg:phone":"+1 301 698 0930",
    "sg:postcode":"21701",
    "sg:province":"MD",
    "sg:tags":[
        "clergy"
    ],
    "wof:name":"Alexander Hardy",
    "wof:placetype":"venue"
},
  "geometry": {"coordinates":[-77.403544,39.426957],"type":"Point"}
}