{
  "type": "Feature",
  "properties": {
    "addr:full":"14244 Cuba Rd Cockeysville MD 21030",
    "addr:housenumber":"14244",
    "addr:postcode":"21030",
    "addr:street":"Cuba Rd",
    "iso:country":"US",
    "sg:address":"14244 Cuba Rd",
    "sg:city":"Cockeysville",
    "sg:classifiers":[
        {
            "category":"Food & Beverages",
            "subcategory":"Liquor & Beverages",
            "type":"Retail Goods"
        }
    ],
    "sg:phone":"+1 410 785 9881",
    "sg:postcode":"21030",
    "sg:province":"MD",
    "sg:tags":[
        "store"
    ],
    "wof:name":"Boulevard Spirits Inc",
    "wof:placetype":"venue"
},
  "geometry": {"coordinates":[-76.708039,39.515309],"type":"Point"}
}