{
  "type": "Feature",
  "properties": {
    "addr:full":"217 Grove Cove Rd Centreville MD 21617",
    "addr:housenumber":"217",
    "addr:postcode":"21617",
    "addr:street":"Grove Cove Rd",
    "iso:country":"US",
    "sg:address":"217 Grove Cove Rd",
    "sg:city":"Centreville",
    "sg:classifiers":[
        {
            "category":"Professional",
            "subcategory":"Business Services",
            "type":"Services"
        }
    ],
    "sg:phone":"+1 410 758 0122",
    "sg:postcode":"21617",
    "sg:province":"MD",
    "sg:tags":[
        "interior",
        "design"
    ],
    "wof:name":"Chesapeake Contract Furn",
    "wof:placetype":"venue"
},
  "geometry": {"coordinates":[-76.133593,39.058833],"type":"Point"}
}