{
  "type": "Feature",
  "properties": {
    "addr:full":"9924 Conestoga Way Potomac MD 20854",
    "addr:housenumber":"9924",
    "addr:postcode":"20854",
    "addr:street":"Conestoga Way",
    "iso:country":"US",
    "sg:address":"9924 Conestoga Way",
    "sg:city":"Potomac",
    "sg:classifiers":[
        {
            "category":"Health Services",
            "subcategory":"Doctor",
            "type":"Services"
        }
    ],
    "sg:phone":"+1 301 983 1143",
    "sg:postcode":"20854",
    "sg:province":"MD",
    "sg:tags":[
        "surgeon",
        "oral"
    ],
    "wof:name":"Decker Robert DDS",
    "wof:placetype":"venue"
},
  "geometry": {"coordinates":[-77.200401,39.019199],"type":"Point"}
}