{
  "type": "Feature",
  "properties": {
    "iso:country":"US",
    "sg:address":"10708 Kings Riding Way",
    "sg:city":"North Bethesda",
    "sg:classifiers":[
        {
            "category":"Retail",
            "subcategory":"Auto Repair",
            "type":"Services"
        }
    ],
    "sg:phone":"+1 301 938 9045",
    "sg:postcode":"20852",
    "sg:province":"MD",
    "sg:tags":[
        "limousine"
    ],
    "wof:name":"Mak Airport Sedans & Limos",
    "wof:placetype":"venue"
},
  "geometry": {"coordinates":[-77.112956,39.030433],"type":"Point"}
}