{
  "type": "Feature",
  "properties": {
    "addr:full":"702 Iona Ter Capitol Heights MD 20743",
    "addr:housenumber":"702",
    "addr:postcode":"20743",
    "addr:street":"Iona Ter",
    "iso:country":"US",
    "sg:address":"702 Iona Ter",
    "sg:city":"Capitol Heights",
    "sg:classifiers":[
        {
            "category":"Social Services",
            "subcategory":"Child Care",
            "type":"Services"
        }
    ],
    "sg:phone":"+1 301 350 6971",
    "sg:postcode":"20743",
    "sg:province":"MD",
    "wof:name":"Abdullah Family Child Home CA",
    "wof:placetype":"venue"
},
  "geometry": {"coordinates":[-76.887378,38.878539],"type":"Point"}
}