{
  "type": "Feature",
  "properties": {
    "iso:country":"US",
    "sg:address":"550 Crain Hwy N",
    "sg:city":"Glen Burnie",
    "sg:classifiers":[
        {
            "category":"Wholesale",
            "subcategory":"Vending Machines",
            "type":"Manufacturing & Wholesale Goods"
        }
    ],
    "sg:phone":"+1 410 553 9663",
    "sg:postcode":"21061",
    "sg:province":"MD",
    "wof:name":"M & M Concessions Inc",
    "wof:placetype":"venue"
},
  "geometry": {"coordinates":[-76.619062,39.174567],"type":"Point"}
}