{
  "type": "Feature",
  "properties": {
    "addr:full":"300 Market St Havre De Grace MD 21078",
    "addr:housenumber":"300",
    "addr:postcode":"21078",
    "addr:street":"Market St",
    "iso:country":"US",
    "sg:address":"300 Market St",
    "sg:city":"Havre De Grace",
    "sg:classifiers":[
        {
            "category":"Personal",
            "subcategory":"Beauty Salon",
            "type":"Services"
        }
    ],
    "sg:phone":"+1 410 378 2725",
    "sg:postcode":"21078",
    "sg:province":"MD",
    "sg:tags":[
        "shop"
    ],
    "wof:name":"Hawaiian Dreams Hair Design",
    "wof:placetype":"venue"
},
  "geometry": {"coordinates":[-76.08792699999999,39.544601],"type":"Point"}
}