{
  "type": "Feature",
  "properties": {
    "iso:country":"US",
    "sg:address":"100 Francis St",
    "sg:city":"Havre De Grace",
    "sg:classifiers":[
        {
            "category":"Building & Trades",
            "subcategory":"Electrical",
            "type":"Services"
        }
    ],
    "sg:phone":"+1 410 939 3818",
    "sg:postcode":"21078",
    "sg:province":"MD",
    "sg:tags":[
        "electric",
        "contractor"
    ],
    "wof:name":"Ferguson Electric Inc",
    "wof:placetype":"venue"
},
  "geometry": {"coordinates":[-76.10646699999999,39.557756],"type":"Point"}
}