{
  "type": "Feature",
  "properties": {
    "iso:country":"US",
    "sg:address":"983 Clopper Rd",
    "sg:city":"Gaithersburg",
    "sg:classifiers":[
        {
            "category":"Social Services",
            "type":"Services"
        }
    ],
    "sg:phone":"+1 301 948 5777",
    "sg:postcode":"20878",
    "sg:province":"MD",
    "sg:tags":[
        "organization",
        "welfare"
    ],
    "wof:name":"Joy To The World",
    "wof:placetype":"venue"
},
  "geometry": {"coordinates":[-77.22675099999999,39.145142],"type":"Point"}
}