{
  "type": "Feature",
  "properties": {
    "addr:full":"375 Amberwood Dr Annapolis MD 21409",
    "addr:housenumber":"375",
    "addr:postcode":"21409",
    "addr:street":"Amberwood Dr",
    "iso:country":"US",
    "sg:address":"375 Amberwood Dr",
    "sg:city":"Annapolis",
    "sg:classifiers":[
        {
            "category":"Building & Trades",
            "subcategory":"Electrical",
            "type":"Services"
        }
    ],
    "sg:phone":"+1 410 757 5678",
    "sg:postcode":"21409",
    "sg:province":"MD",
    "sg:tags":[
        "electrical",
        "contractor"
    ],
    "wof:name":"Garrett Contracting Inc",
    "wof:placetype":"venue"
},
  "geometry": {"coordinates":[-76.475009,39.029053],"type":"Point"}
}