{
  "type": "Feature",
  "properties": {
    "addr:full":"6701 Belfast Pl Fort Washington MD 20744",
    "addr:housenumber":"6701",
    "addr:postcode":"20744",
    "addr:street":"Belfast Pl",
    "iso:country":"US",
    "sg:address":"6701 Belfast Pl",
    "sg:city":"Fort Washington",
    "sg:classifiers":[
        {
            "category":"Wholesale",
            "subcategory":"Apparel",
            "type":"Manufacturing & Wholesale Goods"
        }
    ],
    "sg:phone":"+1 301 567 3207",
    "sg:postcode":"20744",
    "sg:province":"MD",
    "sg:tags":[
        "marketing",
        "design",
        "footwear"
    ],
    "wof:name":"Christian Footwear Inc",
    "wof:placetype":"venue"
},
  "geometry": {"coordinates":[-76.972048,38.79868],"type":"Point"}
}