{
  "type": "Feature",
  "properties": {
    "addr:full":"23780 Thawley Rd Denton MD 21629",
    "addr:postcode":"23780;21629",
    "addr:street":"Thawley Rd",
    "iso:country":"US",
    "sg:address":"23780 Thawley Rd",
    "sg:city":"Denton",
    "sg:classifiers":[
        {
            "category":"Wholesale",
            "subcategory":"Auto Parts",
            "type":"Manufacturing & Wholesale Goods"
        }
    ],
    "sg:phone":"+1 410 364 9800",
    "sg:postcode":"21629",
    "sg:province":"MD",
    "sg:tags":[
        "equipment",
        "truck"
    ],
    "wof:name":"Truck Pro",
    "wof:placetype":"venue"
},
  "geometry": {"coordinates":[-75.88678899999999,38.894329],"type":"Point"}
}