{
  "type": "Feature",
  "properties": {
    "addr:full":"21689 Great Mills Rd Lexington Park MD 20653",
    "addr:housenumber":"21689",
    "addr:postcode":"20653",
    "addr:street":"Great Mills Rd",
    "iso:country":"US",
    "sg:address":"21689 Great Mills Rd",
    "sg:city":"Lexington Park",
    "sg:classifiers":[
        {
            "category":"Professional",
            "subcategory":"Lawyer & Legal Services",
            "type":"Services"
        }
    ],
    "sg:phone":"+1 301 863 9434",
    "sg:postcode":"20653",
    "sg:province":"MD",
    "sg:tags":[
        "personal",
        "injury"
    ],
    "sg:website":"www.sawyerandmyerberg.com",
    "wof:name":"McNeill Susan P",
    "wof:placetype":"venue"
},
  "geometry": {"coordinates":[-76.45876,38.263351],"type":"Point"}
}