{
  "type": "Feature",
  "properties": {
    "addr:full":"7375 Executive Pl Lanham MD 20706",
    "addr:housenumber":"7375",
    "addr:postcode":"20706",
    "addr:street":"Executive Pl",
    "iso:country":"US",
    "sg:address":"7375 Executive Pl",
    "sg:city":"Lanham",
    "sg:classifiers":[
        {
            "category":"Manufacturing",
            "subcategory":"Tools & Machinery",
            "type":"Manufacturing & Wholesale Goods"
        }
    ],
    "sg:phone":"+1 301 464 6800",
    "sg:postcode":"20706",
    "sg:province":"MD",
    "sg:tags":[
        "industry",
        "aerospace"
    ],
    "sg:website":"www.oao.com",
    "wof:name":"Lockheed Martin Info & Tech",
    "wof:placetype":"venue"
},
  "geometry": {"coordinates":[-76.828552,38.991535],"type":"Point"}
}