{
  "type": "Feature",
  "properties": {
    "addr:full":"17800 Bowie Mill Rd Derwood MD 20855",
    "addr:housenumber":"17800",
    "addr:postcode":"20855",
    "addr:street":"Bowie Mill Rd",
    "iso:country":"US",
    "sg:address":"17800 Bowie Mill Rd",
    "sg:city":"Derwood",
    "sg:classifiers":[
        {
            "category":"Farming",
            "subcategory":"Livestock Farm",
            "type":"Manufacturing & Wholesale Goods"
        }
    ],
    "sg:phone":"+1 301 963 0021",
    "sg:postcode":"20855",
    "sg:province":"MD",
    "sg:tags":[
        "ranch"
    ],
    "wof:name":"Flint Hill Farm",
    "wof:placetype":"venue"
},
  "geometry": {"coordinates":[-77.114169,39.148909],"type":"Point"}
}