{
  "type": "Feature",
  "properties": {
    "addr:full":"5508 Belair Rd Baltimore MD 21206",
    "addr:housenumber":"5508",
    "addr:postcode":"21206",
    "addr:street":"Belair Rd",
    "iso:country":"US",
    "sg:address":"5508 Belair Rd",
    "sg:city":"Baltimore",
    "sg:classifiers":[
        {
            "category":"Health Services",
            "subcategory":"Podiatrist",
            "type":"Services"
        }
    ],
    "sg:phone":"+1 410 483 4245",
    "sg:postcode":"21206",
    "sg:province":"MD",
    "wof:name":"Reconstructive Foot Ctr",
    "wof:placetype":"venue"
},
  "geometry": {"coordinates":[-76.549424,39.33968],"type":"Point"}
}