{
  "type": "Feature",
  "properties": {
    "iso:country":"US",
    "sg:address":"9110 Wellington Pl",
    "sg:city":"Lanham",
    "sg:classifiers":[
        {
            "category":"Real Estate",
            "subcategory":"Real Estate Agent",
            "type":"Services"
        }
    ],
    "sg:phone":"+1 301 577 7898",
    "sg:postcode":"20706",
    "sg:province":"MD",
    "wof:name":"Best Property 2",
    "wof:placetype":"venue"
},
  "geometry": {"coordinates":[-76.854906,38.975152],"type":"Point"}
}