{
  "type": "Feature",
  "properties": {
    "addr:full":"9495 Old Annapolis Rd Ellicott City MD 21042",
    "addr:housenumber":"9495",
    "addr:postcode":"21042",
    "addr:street":"Old Annapolis Rd",
    "iso:country":"US",
    "sg:address":"9495 Old Annapolis Rd",
    "sg:city":"Ellicott City",
    "sg:classifiers":[
        {
            "category":"Food & Beverages",
            "subcategory":"Liquor & Beverages",
            "type":"Retail Goods"
        }
    ],
    "sg:phone":"+1 410 992 4444",
    "sg:postcode":"21042",
    "sg:province":"MD",
    "wof:name":"Allview Liquors",
    "wof:placetype":"venue"
},
  "geometry": {"coordinates":[-76.84100599999999,39.241279],"type":"Point"}
}