{
  "type": "Feature",
  "properties": {
    "addr:full":"7805 Assateague Dr Jessup MD 20794",
    "addr:housenumber":"7805",
    "addr:postcode":"20794",
    "addr:street":"Assateague Dr",
    "iso:country":"US",
    "sg:address":"7805 Assateague Dr",
    "sg:city":"Jessup",
    "sg:classifiers":[
        {
            "category":"Food & Beverages",
            "subcategory":"Groceries & Convenience Stores",
            "type":"Retail Goods"
        }
    ],
    "sg:phone":"+1 410 799 6733",
    "sg:postcode":"20794",
    "sg:province":"MD",
    "sg:tags":[
        "gourmet",
        "including",
        "supermarket",
        "drug"
    ],
    "wof:name":"Giant of Maryland Inc",
    "wof:placetype":"venue"
},
  "geometry": {"coordinates":[-76.78301,39.164585],"type":"Point"}
}