{
  "type": "Feature",
  "properties": {
    "addr:full":"8217 Georgia Ave Silver Spring MD 20910",
    "addr:housenumber":"8217",
    "addr:postcode":"20910",
    "addr:street":"Georgia Ave",
    "iso:country":"US",
    "sg:address":"8217 Georgia Ave",
    "sg:city":"Silver Spring",
    "sg:classifiers":[
        {
            "category":"Personal",
            "subcategory":"Barber",
            "type":"Services"
        }
    ],
    "sg:phone":"+1 301 562 6911",
    "sg:postcode":"20910",
    "sg:province":"MD",
    "wof:name":"Afrikutz",
    "wof:placetype":"venue"
},
  "geometry": {"coordinates":[-77.026539,38.992301],"type":"Point"}
}