{
  "type": "Feature",
  "properties": {
    "addr:full":"12070 Old Line Center Waldorf MD 20602",
    "addr:housenumber":"12070",
    "addr:postcode":"20602",
    "addr:street":"Old Line",
    "iso:country":"US",
    "sg:address":"12070 Old Line Center",
    "sg:city":"Waldorf",
    "sg:classifiers":[
        {
            "category":"Health Services",
            "subcategory":"Doctor",
            "type":"Services"
        }
    ],
    "sg:phone":"+1 301 870 7816",
    "sg:postcode":"20602",
    "sg:province":"MD",
    "sg:tags":[
        "physician",
        "surgeon"
    ],
    "sg:website":"www.mhca.com",
    "wof:name":"Maryland Health Care Assoc",
    "wof:placetype":"venue"
},
  "geometry": {"coordinates":[-76.888952,38.616563],"type":"Point"}
}