{
  "type": "Feature",
  "properties": {
    "addr:full":"137 N Washington St Havre De Grace MD 21078",
    "addr:housenumber":"137",
    "addr:postcode":"21078",
    "addr:street":"N Washington St",
    "iso:country":"US",
    "sg:address":"137 N Washington St",
    "sg:city":"Havre De Grace",
    "sg:classifiers":[
        {
            "category":"Professional",
            "type":"Services"
        }
    ],
    "sg:phone":"+1 410 939 8002",
    "sg:postcode":"21078",
    "sg:province":"MD",
    "sg:tags":[
        "establishment"
    ],
    "wof:name":"Cork & Barrel",
    "wof:placetype":"venue"
},
  "geometry": {"coordinates":[-76.08968900000001,39.54816],"type":"Point"}
}