{
  "type": "Feature",
  "properties": {
    "addr:full":"110 Broadway Centreville MD 21617",
    "addr:housenumber":"110",
    "addr:postcode":"21617",
    "addr:street":"Broadway",
    "iso:country":"US",
    "sg:address":"110 Broadway",
    "sg:city":"Centreville",
    "sg:classifiers":[
        {
            "category":"Building & Trades",
            "subcategory":"Construction",
            "type":"Services"
        }
    ],
    "sg:phone":"+1 410 758 4785",
    "sg:postcode":"21617",
    "sg:province":"MD",
    "sg:tags":[
        "contractor"
    ],
    "wof:name":"Builders Choice Construction",
    "wof:placetype":"venue"
},
  "geometry": {"coordinates":[-76.06567699999999,39.045606],"type":"Point"}
}