{
  "type": "Feature",
  "properties": {
    "iso:country":"US",
    "sg:address":"2507 Washington Blvd",
    "sg:city":"Baltimore",
    "sg:classifiers":[
        {
            "category":"Retail",
            "subcategory":"Laundry & Dry Cleaning",
            "type":"Services"
        }
    ],
    "sg:phone":"+1 410 644 7910",
    "sg:postcode":"21230",
    "sg:province":"MD",
    "sg:tags":[
        "cleaner",
        "plant",
        "drycleaning"
    ],
    "wof:name":"Bessie's Cleaners",
    "wof:placetype":"venue"
},
  "geometry": {"coordinates":[-76.652199,39.266701],"type":"Point"}
}