{
  "type": "Feature",
  "properties": {
    "iso:country":"US",
    "sg:address":"11322 Ridgeway Ave S",
    "sg:city":"Lutherville Timonium",
    "sg:classifiers":[
        {
            "category":"Real Estate",
            "subcategory":"Real Estate Agent",
            "type":"Services"
        }
    ],
    "sg:phone":"+1 410 252 0089",
    "sg:postcode":"21093",
    "sg:province":"MD",
    "wof:name":"Dan Eckert",
    "wof:placetype":"venue"
},
  "geometry": {"coordinates":[-76.71232999999999,39.433235],"type":"Point"}
}