{
  "type": "Feature",
  "properties": {
    "iso:country":"US",
    "sg:address":"6505 Sewells Orchard Dr",
    "sg:city":"Columbia",
    "sg:classifiers":[
        {
            "category":"Health Services",
            "subcategory":"Doctor",
            "type":"Services"
        }
    ],
    "sg:phone":"+1 410 381 3232",
    "sg:postcode":"21045",
    "sg:province":"MD",
    "sg:tags":[
        "dentist"
    ],
    "wof:name":"Ronald J Hollander DDS",
    "wof:placetype":"venue"
},
  "geometry": {"coordinates":[-76.832852,39.200456],"type":"Point"}
}