{
  "type": "Feature",
  "properties": {
    "addr:full":"3242 Foster Ave Baltimore MD 21224",
    "addr:housenumber":"3242",
    "addr:postcode":"21224",
    "addr:street":"Foster Ave",
    "iso:country":"US",
    "sg:address":"3242 Foster Ave",
    "sg:city":"Baltimore",
    "sg:classifiers":[
        {
            "category":"Retail",
            "subcategory":"Repair Shop",
            "type":"Services"
        }
    ],
    "sg:phone":"+1 410 342 0784",
    "sg:postcode":"21224",
    "sg:province":"MD",
    "sg:tags":[
        "dental",
        "refinishing",
        "equipment-repairing"
    ],
    "wof:name":"Paul Gillespie",
    "wof:placetype":"venue"
},
  "geometry": {"coordinates":[-76.570407,39.284438],"type":"Point"}
}