{
  "type": "Feature",
  "properties": {
    "iso:country":"US",
    "sg:address":"10220 River Rd",
    "sg:city":"Potomac",
    "sg:classifiers":[
        {
            "category":"Professional",
            "type":"Services"
        }
    ],
    "sg:phone":"+1 301 299 7571",
    "sg:postcode":"20854",
    "sg:province":"MD",
    "sg:tags":[
        "establishment"
    ],
    "wof:name":"Mfm Renter Monitor",
    "wof:placetype":"venue"
},
  "geometry": {"coordinates":[-77.211018,39.019232],"type":"Point"}
}