{
  "type": "Feature",
  "properties": {
    "iso:country":"US",
    "sg:address":"2133 Blue Knob Ter",
    "sg:city":"Silver Spring",
    "sg:classifiers":[
        {
            "category":"Arts & Performance",
            "subcategory":"Theater",
            "type":"Entertainment"
        }
    ],
    "sg:phone":"+1 301 598 2037",
    "sg:postcode":"20906",
    "sg:province":"MD",
    "sg:tags":[
        "bureau"
    ],
    "wof:name":"Red Line Entertainment",
    "wof:placetype":"venue"
},
  "geometry": {"coordinates":[-77.049976,39.106419],"type":"Point"}
}