{
  "type": "Feature",
  "properties": {
    "addr:full":"3829 Penn Belt Pl District Heights MD 20747",
    "addr:housenumber":"3829",
    "addr:postcode":"20747",
    "addr:street":"Penn Belt Pl",
    "iso:country":"US",
    "sg:address":"3829 Penn Belt Pl",
    "sg:city":"District Heights",
    "sg:classifiers":[
        {
            "category":"Building & Trades",
            "subcategory":"Electrical",
            "type":"Services"
        }
    ],
    "sg:phone":"+1 301 568 2788",
    "sg:postcode":"20747",
    "sg:province":"MD",
    "sg:tags":[
        "electric",
        "contractor"
    ],
    "wof:name":"Williams Electric",
    "wof:placetype":"venue"
},
  "geometry": {"coordinates":[-76.872747,38.836799],"type":"Point"}
}