{
  "type": "Feature",
  "properties": {
    "iso:country":"US",
    "sg:address":"6 Saint Paul St",
    "sg:city":"Baltimore",
    "sg:classifiers":[
        {
            "category":"Local Transit",
            "type":"Transportation"
        }
    ],
    "sg:phone":"+1 410 539 5000",
    "sg:postcode":"21202",
    "sg:province":"MD",
    "sg:tags":[
        "public"
    ],
    "sg:website":"www.mtamaryland.com",
    "wof:name":"Education MD State Dept",
    "wof:placetype":"venue"
},
  "geometry": {"coordinates":[-76.61406700000001,39.289991],"type":"Point"}
}