{
  "type": "Feature",
  "properties": {
    "addr:full":"8310 Annapolis Rd Ste A New Carrollton MD 20784",
    "addr:housenumber":"8310",
    "addr:postcode":"20784",
    "addr:street":"Annapolis Rd Ste A",
    "iso:country":"US",
    "sg:address":"8310 Annapolis Rd Ste A",
    "sg:city":"New Carrollton",
    "sg:classifiers":[
        {
            "category":"Shopping",
            "subcategory":"Mobile Phones",
            "type":"Retail Goods"
        }
    ],
    "sg:phone":"+1 301 577 5864",
    "sg:postcode":"20784",
    "sg:province":"MD",
    "sg:website":"sprint.com",
    "wof:name":"Sprint",
    "wof:placetype":"venue"
},
  "geometry": {"coordinates":[-76.87187400000001,38.956603],"type":"Point"}
}