{
  "type": "Feature",
  "properties": {
    "iso:country":"US",
    "sg:address":"7315 Wisconsin Ave",
    "sg:city":"Bethesda",
    "sg:classifiers":[
        {
            "category":"Professional",
            "subcategory":"Lawyer & Legal Services",
            "type":"Services"
        }
    ],
    "sg:phone":"+1 301 469 3666",
    "sg:postcode":"20814",
    "sg:province":"MD",
    "wof:name":"Richardson Christopher Atty",
    "wof:placetype":"venue"
},
  "geometry": {"coordinates":[-77.0933,38.982601],"type":"Point"}
}