{
  "type": "Feature",
  "properties": {
    "addr:full":"4646 York Rd Baltimore MD 21212",
    "addr:housenumber":"4646",
    "addr:postcode":"21212",
    "addr:street":"York Rd",
    "iso:country":"US",
    "sg:address":"4646 York Rd",
    "sg:city":"Baltimore",
    "sg:classifiers":[
        {
            "category":"Personal",
            "subcategory":"Massage",
            "type":"Services"
        },
        {
            "category":"Personal",
            "subcategory":"Nail Salon",
            "type":"Services"
        }
    ],
    "sg:phone":"+1 410 433 4118",
    "sg:postcode":"21212",
    "sg:province":"MD",
    "wof:name":"Nappee by Nature",
    "wof:placetype":"venue"
},
  "geometry": {"coordinates":[-76.609398,39.345699],"type":"Point"}
}