{
  "type": "Feature",
  "properties": {
    "addr:full":"11332 Nevets Pl Monrovia MD 21770",
    "addr:housenumber":"11332",
    "addr:postcode":"21770",
    "addr:street":"Nevets Pl",
    "iso:country":"US",
    "sg:address":"11332 Nevets Pl",
    "sg:city":"Monrovia",
    "sg:classifiers":[
        {
            "category":"Professional",
            "subcategory":"Computer Services",
            "type":"Services"
        }
    ],
    "sg:phone":"+1 301 865 1758",
    "sg:postcode":"21770",
    "sg:province":"MD",
    "sg:tags":[
        "on",
        "technology",
        "consultant"
    ],
    "wof:name":"Arthur Graphics Inc",
    "wof:placetype":"venue"
},
  "geometry": {"coordinates":[-77.269075,39.351261],"type":"Point"}
}