{
  "type": "Feature",
  "properties": {
    "addr:full":"9175 Guilford Rd Columbia MD 21046",
    "addr:housenumber":"9175",
    "addr:postcode":"21046",
    "addr:street":"Guilford Rd",
    "iso:country":"US",
    "sg:address":"9175 Guilford Rd",
    "sg:city":"Columbia",
    "sg:classifiers":[
        {
            "category":"Health Services",
            "subcategory":"Nursing And Care Facility",
            "type":"Services"
        }
    ],
    "sg:phone":"+1 301 317 7100",
    "sg:postcode":"21046",
    "sg:province":"MD",
    "sg:tags":[
        "skilled"
    ],
    "wof:name":"Genesis",
    "wof:placetype":"venue"
},
  "geometry": {"coordinates":[-76.848713,39.169984],"type":"Point"}
}