{
  "type": "Feature",
  "properties": {
    "iso:country":"US",
    "sg:address":"132 Main St",
    "sg:city":"Prince Frederick",
    "sg:classifiers":[
        {
            "category":"Professional",
            "subcategory":"Lawyer & Legal Services",
            "type":"Services"
        }
    ],
    "sg:phone":"+1 410 535 1780",
    "sg:postcode":"20678",
    "sg:province":"MD",
    "sg:tags":[
        "attorney"
    ],
    "wof:name":"Davis Upton & Palumbo",
    "wof:placetype":"venue"
},
  "geometry": {"coordinates":[-76.584366,38.539995],"type":"Point"}
}