{
  "type": "Feature",
  "properties": {
    "addr:full":"10363 Southern Maryland Blvd Dunkirk MD 20754",
    "addr:housenumber":"10363",
    "addr:postcode":"20754",
    "addr:street":"Southern Maryland Blvd",
    "iso:country":"US",
    "sg:address":"10363 Southern Maryland Blvd",
    "sg:city":"Dunkirk",
    "sg:classifiers":[
        {
            "category":"Social Services",
            "type":"Services"
        }
    ],
    "sg:phone":"+1 410 286 5586",
    "sg:postcode":"20754",
    "sg:province":"MD",
    "sg:tags":[
        "agency",
        "adoption"
    ],
    "wof:name":"First Steps Intl Adoption",
    "wof:placetype":"venue"
},
  "geometry": {"coordinates":[-76.66043999999999,38.721888],"type":"Point"}
}