{
  "type": "Feature",
  "properties": {
    "iso:country":"US",
    "sg:address":"3455 Wilkens Ave Ste 104",
    "sg:city":"Baltimore",
    "sg:classifiers":[
        {
            "category":"Health Services",
            "subcategory":"Doctor",
            "type":"Services"
        }
    ],
    "sg:phone":"+1 410 525 0508",
    "sg:postcode":"21229",
    "sg:province":"MD",
    "wof:name":"Miller Michael S M D",
    "wof:placetype":"venue"
},
  "geometry": {"coordinates":[-76.67559799999999,39.2724],"type":"Point"}
}