{
  "type": "Feature",
  "properties": {
    "addr:full":"19008 Legion Rd Barton MD 21521",
    "addr:housenumber":"19008",
    "addr:postcode":"21521",
    "addr:street":"Legion Rd",
    "iso:country":"US",
    "sg:address":"19008 Legion Rd",
    "sg:city":"Barton",
    "sg:classifiers":[
        {
            "category":"Organizations",
            "subcategory":"Community Association",
            "type":"Services"
        }
    ],
    "sg:phone":"+1 301 463 6248",
    "sg:postcode":"21521",
    "sg:province":"MD",
    "sg:tags":[
        "military"
    ],
    "wof:name":"American Legion",
    "wof:placetype":"venue"
},
  "geometry": {"coordinates":[-79.017617,39.53086],"type":"Point"}
}