{
  "type": "Feature",
  "properties": {
    "iso:country":"US",
    "sg:address":"5915 Belair Rd",
    "sg:city":"Baltimore",
    "sg:classifiers":[
        {
            "category":"Retail",
            "subcategory":"Animal Services",
            "type":"Services"
        }
    ],
    "sg:phone":"+1 410 483 5162",
    "sg:postcode":"21206",
    "sg:province":"MD",
    "sg:tags":[
        "washing",
        "pet",
        "hospital",
        "veterinary",
        "clinic",
        "veterinarian",
        "grooming"
    ],
    "wof:name":"Academy Animal Hospital",
    "wof:placetype":"venue"
},
  "geometry": {"coordinates":[-76.541,39.345798],"type":"Point"}
}