{
  "type": "Feature",
  "properties": {
    "iso:country":"US",
    "sg:address":"5506 Cherrywood Ln",
    "sg:city":"Greenbelt",
    "sg:classifiers":[
        {
            "category":"Restaurant",
            "type":"Food & Drink"
        }
    ],
    "sg:menulink":"http://www.allmenus.com/md/berwyn/221866-chipotle/menu/",
    "sg:phone":"+1 301 982 6722",
    "sg:postcode":"20770",
    "sg:province":"MD",
    "sg:tags":[
        "mexican"
    ],
    "wof:name":"Chipotle",
    "wof:placetype":"venue"
},
  "geometry": {"coordinates":[-76.912035,38.998112],"type":"Point"}
}