{
  "type": "Feature",
  "properties": {
    "iso:country":"US",
    "sg:address":"364 Marlboro Rd",
    "sg:city":"Lothian",
    "sg:classifiers":[
        {
            "category":"Professional",
            "type":"Services"
        }
    ],
    "sg:phone":"+1 410 867 8180",
    "sg:postcode":"20711",
    "sg:province":"MD",
    "sg:tags":[
        "establishment"
    ],
    "wof:name":"Wescam Inc",
    "wof:placetype":"venue"
},
  "geometry": {"coordinates":[-76.630638,38.815791],"type":"Point"}
}