{
  "type": "Feature",
  "properties": {
    "addr:full":"8714 Ritchboro Rd District Heights MD 20747",
    "addr:housenumber":"8714",
    "addr:postcode":"20747",
    "addr:street":"Ritchboro Rd",
    "iso:country":"US",
    "sg:address":"8714 Ritchboro Rd",
    "sg:city":"District Heights",
    "sg:classifiers":[
        {
            "category":"Wholesale",
            "subcategory":"Durable Goods & Equipment",
            "type":"Manufacturing & Wholesale Goods"
        }
    ],
    "sg:phone":"+1 301 499 1589",
    "sg:postcode":"20747",
    "sg:province":"MD",
    "sg:tags":[
        "importer"
    ],
    "wof:name":"Febco International",
    "wof:placetype":"venue"
},
  "geometry": {"coordinates":[-76.85377,38.864536],"type":"Point"}
}