{
  "type": "Feature",
  "properties": {
    "addr:full":"625 Harberts Ct Annapolis MD 21401",
    "addr:housenumber":"625",
    "addr:postcode":"21401",
    "addr:street":"Harberts Ct",
    "iso:country":"US",
    "sg:address":"625 Harberts Ct",
    "sg:city":"Annapolis",
    "sg:classifiers":[
        {
            "category":"Professional",
            "subcategory":"Management & Consulting",
            "type":"Services"
        }
    ],
    "sg:phone":"+1 410 571 1995",
    "sg:postcode":"21401",
    "sg:province":"MD",
    "sg:tags":[
        "consultant",
        "business"
    ],
    "wof:name":"Norpa Consulting",
    "wof:placetype":"venue"
},
  "geometry": {"coordinates":[-76.564716,38.997175],"type":"Point"}
}