{
  "type": "Feature",
  "properties": {
    "iso:country":"US",
    "sg:address":"3430 Bayside Forest Ct",
    "sg:city":"Huntingtown",
    "sg:classifiers":[
        {
            "category":"Professional",
            "type":"Services"
        }
    ],
    "sg:phone":"+1 410 257 0839",
    "sg:postcode":"20639",
    "sg:province":"MD",
    "wof:name":"James Skyrm",
    "wof:placetype":"venue"
},
  "geometry": {"coordinates":[-76.547449,38.566356],"type":"Point"}
}