{
  "type": "Feature",
  "properties": {
    "iso:country":"US",
    "sg:address":"833 N Howard St",
    "sg:city":"Baltimore",
    "sg:classifiers":[
        {
            "category":"Shopping",
            "subcategory":"Used Merchandise",
            "type":"Retail Goods"
        }
    ],
    "sg:phone":"+1 410 523 0550",
    "sg:postcode":"21201",
    "sg:province":"MD",
    "sg:tags":[
        "antique"
    ],
    "wof:name":"Angela R Thrasher Antiques",
    "wof:placetype":"venue"
},
  "geometry": {"coordinates":[-76.62020099999999,39.299198],"type":"Point"}
}