{
  "type": "Feature",
  "properties": {
    "iso:country":"US",
    "sg:address":"3913 Fleetwood Ave",
    "sg:city":"Baltimore",
    "sg:classifiers":[
        {
            "category":"Building & Trades",
            "subcategory":"Cleaning & Sanitation",
            "type":"Services"
        }
    ],
    "sg:phone":"+1 410 426 1147",
    "sg:postcode":"21206",
    "sg:province":"MD",
    "sg:tags":[
        "construction",
        "site-clean-up"
    ],
    "wof:name":"K T T Drywall Scrapping Services",
    "wof:placetype":"venue"
},
  "geometry": {"coordinates":[-76.53403400000001,39.356654],"type":"Point"}
}