{
  "type": "Feature",
  "properties": {
    "addr:full":"1202 Maryland Ave Baltimore MD 21201",
    "addr:housenumber":"1202",
    "addr:postcode":"21201",
    "addr:street":"Maryland Ave",
    "iso:country":"US",
    "sg:address":"1202 Maryland Ave",
    "sg:city":"Baltimore",
    "sg:classifiers":[
        {
            "category":"Education",
            "subcategory":"Special Training",
            "type":"Public Place"
        }
    ],
    "sg:phone":"+1 410 962 5580",
    "sg:postcode":"21201",
    "sg:province":"MD",
    "sg:tags":[
        "career",
        "vocational",
        "counseling"
    ],
    "wof:name":"Physician Health Program",
    "wof:placetype":"venue"
},
  "geometry": {"coordinates":[-76.61741000000001,39.30342],"type":"Point"}
}