{
  "type": "Feature",
  "properties": {
    "addr:full":"7839 Eastpoint Mall Baltimore MD 21224",
    "addr:housenumber":"7839",
    "addr:postcode":"21224",
    "addr:street":"Eastpoint Mall",
    "iso:country":"US",
    "sg:address":"7839 Eastpoint Mall",
    "sg:city":"Baltimore",
    "sg:classifiers":[
        {
            "category":"Restaurant",
            "type":"Food & Drink"
        }
    ],
    "sg:phone":"+1 410 282 3872",
    "sg:postcode":"21224",
    "sg:province":"MD",
    "wof:name":"Salad Gourmet",
    "wof:placetype":"venue"
},
  "geometry": {"coordinates":[-76.509697,39.291901],"type":"Point"}
}