{
  "type": "Feature",
  "properties": {
    "iso:country":"US",
    "sg:address":"13200 Executive Park Ter",
    "sg:city":"Germantown",
    "sg:classifiers":[
        {
            "category":"Professional",
            "subcategory":"Business Services",
            "type":"Services"
        }
    ],
    "sg:phone":"+1 301 972 3600",
    "sg:postcode":"20874",
    "sg:province":"MD",
    "sg:tags":[
        "lecture",
        "bureau",
        "seminar"
    ],
    "sg:website":"www.taxreductioninstitute.com",
    "wof:name":"TRI Seminars",
    "wof:placetype":"venue"
},
  "geometry": {"coordinates":[-77.275268,39.181461],"type":"Point"}
}