{
  "type": "Feature",
  "properties": {
    "addr:full":"4000 Mitchellville Rd Bowie MD 20716",
    "addr:housenumber":"4000",
    "addr:postcode":"20716",
    "addr:street":"Mitchellville Rd",
    "iso:country":"US",
    "sg:address":"4000 Mitchellville Rd",
    "sg:city":"Bowie",
    "sg:classifiers":[
        {
            "category":"Professional",
            "type":"Services"
        }
    ],
    "sg:phone":"+1 301 352 8500",
    "sg:postcode":"20716",
    "sg:province":"MD",
    "wof:name":"Facilities Service Inc",
    "wof:placetype":"venue"
},
  "geometry": {"coordinates":[-76.722955,38.945105],"type":"Point"}
}