{
  "type": "Feature",
  "properties": {
    "addr:full":"3592 Whiskey Bottom Rd Laurel MD 20724",
    "addr:housenumber":"3592",
    "addr:postcode":"20724",
    "addr:street":"Whiskey Bottom Rd",
    "iso:country":"US",
    "sg:address":"3592 Whiskey Bottom Rd",
    "sg:city":"Laurel",
    "sg:classifiers":[
        {
            "category":"Organizations",
            "subcategory":"Religious Organization",
            "type":"Services"
        }
    ],
    "sg:phone":"+1 301 490 3707",
    "sg:postcode":"20724",
    "sg:province":"MD",
    "wof:name":"Mount Zion Untd Methdst Church",
    "wof:placetype":"venue"
},
  "geometry": {"coordinates":[-76.816714,39.106535],"type":"Point"}
}