{
  "type": "Feature",
  "properties": {
    "addr:full":"305 Moonlight Ct Baltimore MD 21225",
    "addr:housenumber":"305",
    "addr:postcode":"21225",
    "addr:street":"Moonlight Ct",
    "iso:country":"US",
    "sg:address":"305 Moonlight Ct",
    "sg:city":"Baltimore",
    "sg:classifiers":[
        {
            "category":"Professional",
            "subcategory":"Management & Consulting",
            "type":"Services"
        }
    ],
    "sg:phone":"+1 410 789 7934",
    "sg:postcode":"21225",
    "sg:province":"MD",
    "wof:name":"Parish Management Services",
    "wof:placetype":"venue"
},
  "geometry": {"coordinates":[-76.62244099999999,39.22013],"type":"Point"}
}