{
  "type": "Feature",
  "properties": {
    "iso:country":"US",
    "sg:address":"305 Moonlight Ct",
    "sg:city":"Baltimore",
    "sg:classifiers":[
        {
            "category":"Professional",
            "subcategory":"Management & Consulting",
            "type":"Services"
        }
    ],
    "sg:phone":"+1 410 789 7934",
    "sg:postcode":"21225",
    "sg:province":"MD",
    "wof:name":"Parish Management Services",
    "wof:placetype":"venue"
},
  "geometry": {"coordinates":[-76.622441,39.22013],"type":"Point"}
}