{
  "type": "Feature",
  "properties": {
    "addr:full":"6327 Patuxent Quarter Rd Hanover MD 21076",
    "addr:housenumber":"6327",
    "addr:postcode":"21076",
    "addr:street":"Patuxent Quarter Rd",
    "iso:country":"US",
    "sg:address":"6327 Patuxent Quarter Rd",
    "sg:city":"Hanover",
    "sg:classifiers":[
        {
            "category":"Professional",
            "type":"Services"
        }
    ],
    "sg:phone":"+1 410 579 8311",
    "sg:postcode":"21076",
    "sg:province":"MD",
    "wof:name":"Advance Hosting Services Inc",
    "wof:placetype":"venue"
},
  "geometry": {"coordinates":[-76.716973,39.198213],"type":"Point"}
}