{
  "type": "Feature",
  "properties": {
    "iso:country":"US",
    "sg:address":"2405 Loch Raven Rd",
    "sg:city":"Baltimore",
    "sg:classifiers":[
        {
            "category":"Food & Beverages",
            "subcategory":"Groceries & Convenience Stores",
            "type":"Retail Goods"
        }
    ],
    "sg:phone":"+1 410 467 4228",
    "sg:postcode":"21218",
    "sg:province":"MD",
    "sg:tags":[
        "product"
    ],
    "wof:name":"Donald Bentley's Food Pantry",
    "wof:placetype":"venue"
},
  "geometry": {"coordinates":[-76.607421,39.31774],"type":"Point"}
}