{
  "type": "Feature",
  "properties": {
    "addr:full":"304 Montgomery St Laurel MD 20707",
    "addr:housenumber":"304",
    "addr:postcode":"20707",
    "addr:street":"Montgomery St",
    "iso:country":"US",
    "sg:address":"304 Montgomery St",
    "sg:city":"Laurel",
    "sg:classifiers":[
        {
            "category":"Personal",
            "subcategory":"Beauty Salon",
            "type":"Services"
        }
    ],
    "sg:phone":"+1 301 776 6605",
    "sg:postcode":"20707",
    "sg:province":"MD",
    "wof:name":"Prosperity Hair Salon",
    "wof:placetype":"venue"
},
  "geometry": {"coordinates":[-76.84648300000001,39.102455],"type":"Point"}
}