{
  "type": "Feature",
  "properties": {
    "addr:full":"226 Harry S Truman Dr Upper Marlboro MD 20774",
    "addr:housenumber":"226",
    "addr:postcode":"20774",
    "addr:street":"Harry S Truman Dr",
    "iso:country":"US",
    "sg:address":"226 Harry S Truman Dr",
    "sg:city":"Upper Marlboro",
    "sg:classifiers":[
        {
            "category":"Building & Trades",
            "subcategory":"Construction",
            "type":"Services"
        }
    ],
    "sg:phone":"+1 301 499 1067",
    "sg:postcode":"20774",
    "sg:province":"MD",
    "sg:tags":[
        "residential"
    ],
    "wof:name":"Rolle Cassius Construction LLC",
    "wof:placetype":"venue"
},
  "geometry": {"coordinates":[-76.832632,38.883999],"type":"Point"}
}