{
  "type": "Feature",
  "properties": {
    "addr:full":"3141 Oakford Ave Baltimore MD 21215",
    "addr:housenumber":"3141",
    "addr:postcode":"21215",
    "addr:street":"Oakford Ave",
    "iso:country":"US",
    "sg:address":"3141 Oakford Ave",
    "sg:city":"Baltimore",
    "sg:classifiers":[
        {
            "category":"Autos & Motor Vehicles",
            "subcategory":"Automobile Sales",
            "type":"Retail Goods"
        }
    ],
    "sg:phone":"+1 443 854 6145",
    "sg:postcode":"21215",
    "sg:province":"MD",
    "sg:tags":[
        "new",
        "car"
    ],
    "wof:name":"Favmer Motors",
    "wof:placetype":"venue"
},
  "geometry": {"coordinates":[-76.666183,39.340711],"type":"Point"}
}