{
  "type": "Feature",
  "properties": {
    "addr:full":"1012 Crain Hwy S Glen Burnie MD 21061",
    "addr:housenumber":"1012",
    "addr:postcode":"21061",
    "addr:street":"Crain Hwy S",
    "iso:country":"US",
    "sg:address":"1012 Crain Hwy S",
    "sg:city":"Glen Burnie",
    "sg:classifiers":[
        {
            "category":"Organizations",
            "subcategory":"Religious Organization",
            "type":"Services"
        }
    ],
    "sg:phone":"+1 410 551 8500",
    "sg:postcode":"21061",
    "sg:province":"MD",
    "sg:tags":[
        "church"
    ],
    "wof:name":"Heritage Community Church",
    "wof:placetype":"venue"
},
  "geometry": {"coordinates":[-76.630994,39.154312],"type":"Point"}
}