{
  "type": "Feature",
  "properties": {
    "iso:country":"US",
    "sg:address":"5105 Baltimore Ave",
    "sg:city":"Hyattsville",
    "sg:classifiers":[
        {
            "category":"Personal",
            "subcategory":"Beauty Salon",
            "type":"Services"
        }
    ],
    "sg:phone":"+1 301 277 5455",
    "sg:postcode":"20781",
    "sg:province":"MD",
    "wof:name":"Rose Hair Braid & Salon",
    "wof:placetype":"venue"
},
  "geometry": {"coordinates":[-76.940715,38.951538],"type":"Point"}
}