{
  "type": "Feature",
  "properties": {
    "iso:country":"US",
    "sg:address":"21 N Hanson St",
    "sg:city":"Easton",
    "sg:classifiers":[
        {
            "category":"Real Estate",
            "subcategory":"Real Estate Services",
            "type":"Services"
        },
        {
            "category":"Professional",
            "subcategory":"Research",
            "type":"Services"
        },
        {
            "category":"Insurance",
            "subcategory":"Title Insurance",
            "type":"Services"
        }
    ],
    "sg:phone":"+1 410 770 5200",
    "sg:postcode":"21601",
    "sg:province":"MD",
    "sg:tags":[
        "abstracter",
        "mortgage"
    ],
    "sg:website":"http://www.venturetitle.com",
    "wof:name":"Venture Title Company",
    "wof:placetype":"venue"
},
  "geometry": {"coordinates":[-76.0731,38.775075],"type":"Point"}
}