{
  "type": "Feature",
  "properties": {
    "iso:country":"US",
    "sg:address":"8901 Hawbottom Rd",
    "sg:city":"Middletown",
    "sg:classifiers":[
        {
            "category":"Communications",
            "subcategory":"Film & Video Production",
            "type":"Services"
        }
    ],
    "sg:phone":"+1 301 293 0210",
    "sg:postcode":"21769",
    "sg:province":"MD",
    "sg:tags":[
        "motion"
    ],
    "wof:name":"Ivd Tech LLC",
    "wof:placetype":"venue"
},
  "geometry": {"coordinates":[-77.507274,39.475312],"type":"Point"}
}