{
  "type": "Feature",
  "properties": {
    "addr:full":"4606 Panacea Rd Pikesville MD 21208",
    "addr:housenumber":"4606",
    "addr:postcode":"21208",
    "addr:street":"Panacea Rd",
    "iso:country":"US",
    "sg:address":"4606 Panacea Rd",
    "sg:city":"Pikesville",
    "sg:classifiers":[
        {
            "category":"Professional",
            "subcategory":"Computer Services",
            "type":"Services"
        }
    ],
    "sg:phone":"+1 410 922 5045",
    "sg:postcode":"21208",
    "sg:province":"MD",
    "sg:tags":[
        "consulting"
    ],
    "wof:name":"Experience Navigation and Comm",
    "wof:placetype":"venue"
},
  "geometry": {"coordinates":[-76.757785,39.368198],"type":"Point"}
}