{
  "type": "Feature",
  "properties": {
    "addr:full":"20 Crossroads Dr Owings Mills MD 21117",
    "addr:housenumber":"20",
    "addr:postcode":"21117",
    "addr:street":"Crossroads Dr",
    "iso:country":"US",
    "sg:address":"20 Crossroads Dr",
    "sg:city":"Owings Mills",
    "sg:classifiers":[
        {
            "category":"Health Services",
            "subcategory":"Doctor",
            "type":"Services"
        }
    ],
    "sg:phone":"+1 410 363 2500",
    "sg:postcode":"21117",
    "sg:province":"MD",
    "sg:tags":[
        "dentist"
    ],
    "wof:name":"Mc Donogh Dental Assoc",
    "wof:placetype":"venue"
},
  "geometry": {"coordinates":[-76.75185399999999,39.397161],"type":"Point"}
}