{
  "type": "Feature",
  "properties": {
    "iso:country":"US",
    "sg:address":"8433 Georgia Ave",
    "sg:city":"Silver Spring",
    "sg:classifiers":[
        {
            "category":"Food & Beverages",
            "subcategory":"Groceries & Convenience Stores",
            "type":"Retail Goods"
        }
    ],
    "sg:phone":"+1 301 588 6087",
    "sg:postcode":"20910",
    "sg:province":"MD",
    "sg:tags":[
        "market"
    ],
    "wof:name":"LA Hispaniola Market",
    "wof:placetype":"venue"
},
  "geometry": {"coordinates":[-77.026623,38.993886],"type":"Point"}
}