{
  "type": "Feature",
  "properties": {
    "iso:country":"US",
    "sg:address":"8995 Yellow Brick Rd",
    "sg:city":"Baltimore",
    "sg:classifiers":[
        {
            "category":"Manufacturing",
            "subcategory":"Printing",
            "type":"Manufacturing & Wholesale Goods"
        }
    ],
    "sg:phone":"+1 410 682 3342",
    "sg:postcode":"21237",
    "sg:province":"MD",
    "sg:tags":[
        "printer"
    ],
    "wof:name":"ADP Printing & Distribution",
    "wof:placetype":"venue"
},
  "geometry": {"coordinates":[-76.476591,39.341594],"type":"Point"}
}