{
  "type": "Feature",
  "properties": {
    "addr:full":"1711 W Joppa Rd Baltimore MD 21204",
    "addr:housenumber":"1711",
    "addr:postcode":"21204",
    "addr:street":"W Joppa Rd",
    "iso:country":"US",
    "sg:address":"1711 W Joppa Rd",
    "sg:city":"Baltimore",
    "sg:classifiers":[
        {
            "category":"Retail",
            "subcategory":"Auto Repair",
            "type":"Services"
        }
    ],
    "sg:phone":"+1 410 823 9693",
    "sg:postcode":"21204",
    "sg:province":"MD",
    "sg:tags":[
        "repairing",
        "automobile"
    ],
    "wof:name":"Gill's Garage Inc",
    "wof:placetype":"venue"
},
  "geometry": {"coordinates":[-76.64961700000001,39.408993],"type":"Point"}
}