{
  "type": "Feature",
  "properties": {
    "addr:full":"5406 Indian Head Hwy Oxon Hill MD 20745",
    "addr:housenumber":"5406",
    "addr:postcode":"20745",
    "addr:street":"Indian Head Hwy",
    "iso:country":"US",
    "sg:address":"5406 Indian Head Hwy",
    "sg:city":"Oxon Hill",
    "sg:classifiers":[
        {
            "category":"Autos & Motor Vehicles",
            "subcategory":"Auto Supplies",
            "type":"Retail Goods"
        }
    ],
    "sg:phone":"+1 301 839 9100",
    "sg:postcode":"20745",
    "sg:province":"MD",
    "sg:tags":[
        "tire"
    ],
    "sg:website":"www.geminicarcare.com",
    "wof:name":"Goodyear Auto Service Centers",
    "wof:placetype":"venue"
},
  "geometry": {"coordinates":[-76.998802,38.816299],"type":"Point"}
}