{
  "type": "Feature",
  "properties": {
    "addr:full":"7 Wellington Pl Annapolis MD 21403",
    "addr:housenumber":"7",
    "addr:postcode":"21403",
    "addr:street":"Wellington Pl",
    "iso:country":"US",
    "sg:address":"7 Wellington Pl",
    "sg:city":"Annapolis",
    "sg:classifiers":[
        {
            "category":"Freight",
            "type":"Transportation"
        },
        {
            "category":"Retail",
            "subcategory":"Auto Rental",
            "type":"Services"
        }
    ],
    "sg:phone":"+1 410 267 7217",
    "sg:postcode":"21403",
    "sg:province":"MD",
    "sg:tags":[
        "operator",
        "renting",
        "leasing",
        "truck",
        "trucking"
    ],
    "wof:name":"Clydes Trucking Co",
    "wof:placetype":"venue"
},
  "geometry": {"coordinates":[-76.512045,38.964939],"type":"Point"}
}