{
  "type": "Feature",
  "properties": {
    "iso:country":"US",
    "sg:address":"2316 Dargan Rd",
    "sg:city":"Sharpsburg",
    "sg:classifiers":[
        {
            "category":"Professional",
            "subcategory":"Lawyer & Legal Services",
            "type":"Services"
        }
    ],
    "sg:phone":"+1 301 432 0048",
    "sg:postcode":"21782",
    "sg:province":"MD",
    "sg:tags":[
        "attorney",
        "practice"
    ],
    "wof:name":"Bailey & Bailey",
    "wof:placetype":"venue"
},
  "geometry": {"coordinates":[-77.733009,39.378394],"type":"Point"}
}