{
  "type": "Feature",
  "properties": {
    "addr:full":"12706 Keswick Ln Bowie MD 20715",
    "addr:housenumber":"12706",
    "addr:postcode":"20715",
    "addr:street":"Keswick Ln",
    "iso:country":"US",
    "sg:address":"12706 Keswick Ln",
    "sg:city":"Bowie",
    "sg:classifiers":[
        {
            "category":"Professional",
            "subcategory":"Accounting & Tax Preparation",
            "type":"Services"
        }
    ],
    "sg:phone":"+1 301 464 2912",
    "sg:postcode":"20715",
    "sg:province":"MD",
    "sg:tags":[
        "accountant"
    ],
    "wof:name":"Computer Accounting Svc",
    "wof:placetype":"venue"
},
  "geometry": {"coordinates":[-76.72881099999999,38.957586],"type":"Point"}
}