{
  "type": "Feature",
  "properties": {
    "addr:full":"3802 Plum Meadow Dr Ellicott City MD 21042",
    "addr:housenumber":"3802",
    "addr:postcode":"21042",
    "addr:street":"Plum Meadow Dr",
    "iso:country":"US",
    "sg:address":"3802 Plum Meadow Dr",
    "sg:city":"Ellicott City",
    "sg:classifiers":[
        {
            "category":"Building & Trades",
            "subcategory":"Construction",
            "type":"Services"
        }
    ],
    "sg:phone":"+1 410 465 9520",
    "sg:postcode":"21042",
    "sg:province":"MD",
    "sg:tags":[
        "handyman"
    ],
    "wof:name":"Home Fixin' Handyman Svc",
    "wof:placetype":"venue"
},
  "geometry": {"coordinates":[-76.839766,39.267067],"type":"Point"}
}