{
  "type": "Feature",
  "properties": {
    "addr:full":"26281 Tunis Mills Rd Easton MD 21601",
    "addr:postcode":"26281;21601",
    "addr:street":"Tunis Mills Rd",
    "iso:country":"US",
    "sg:address":"26281 Tunis Mills Rd",
    "sg:city":"Easton",
    "sg:classifiers":[
        {
            "category":"Organizations",
            "subcategory":"Religious Organization",
            "type":"Services"
        }
    ],
    "sg:phone":"+1 410 822 1464",
    "sg:postcode":"21601",
    "sg:province":"MD",
    "sg:tags":[
        "church"
    ],
    "wof:name":"All Faith Chapel",
    "wof:placetype":"venue"
},
  "geometry": {"coordinates":[-76.165088,38.820095],"type":"Point"}
}