{
  "type": "Feature",
  "properties": {
    "addr:full":"400 N Center St Westminster MD 21157",
    "addr:housenumber":"400",
    "addr:postcode":"21157",
    "addr:street":"N Center St",
    "iso:country":"US",
    "sg:address":"400 N Center St",
    "sg:city":"Westminster",
    "sg:classifiers":[
        {
            "category":"Shopping",
            "subcategory":"Clothing, Apparel, & Fashions",
            "type":"Retail Goods"
        }
    ],
    "sg:phone":"+1 410 871 9994",
    "sg:postcode":"21157",
    "sg:province":"MD",
    "sg:tags":[
        "sportswear"
    ],
    "sg:website":"www.pacsun.com",
    "wof:name":"Pacific Sunwear",
    "wof:placetype":"venue"
},
  "geometry": {"coordinates":[-76.983442,39.575374],"type":"Point"}
}