{
  "type": "Feature",
  "properties": {
    "iso:country":"US",
    "sg:address":"18022 Fence Post Ct",
    "sg:city":"Gaithersburg",
    "sg:classifiers":[
        {
            "category":"Professional",
            "subcategory":"Research",
            "type":"Services"
        }
    ],
    "sg:phone":"+1 301 330 2979",
    "sg:postcode":"20877",
    "sg:province":"MD",
    "sg:tags":[
        "economic",
        "analysis"
    ],
    "wof:name":"Benchmark Research Svc",
    "wof:placetype":"venue"
},
  "geometry": {"coordinates":[-77.171014,39.152143],"type":"Point"}
}