{
  "type": "Feature",
  "properties": {
    "addr:full":"2254 Old Washington Rd Waldorf MD 20601",
    "addr:housenumber":"2254",
    "addr:postcode":"20601",
    "addr:street":"Old Washington Rd",
    "iso:country":"US",
    "sg:address":"2254 Old Washington Rd",
    "sg:city":"Waldorf",
    "sg:classifiers":[
        {
            "category":"Building & Trades",
            "subcategory":"Construction",
            "type":"Services"
        }
    ],
    "sg:phone":"+1 301 843 2741",
    "sg:postcode":"20601",
    "sg:province":"MD",
    "sg:tags":[
        "tile",
        "dealer"
    ],
    "wof:name":"International Tile & Marble",
    "wof:placetype":"venue"
},
  "geometry": {"coordinates":[-76.88270799999999,38.649896],"type":"Point"}
}