{
  "type": "Feature",
  "properties": {
    "iso:country":"US",
    "sg:address":"6902 Holabird Ave",
    "sg:city":"Baltimore",
    "sg:classifiers":[
        {
            "category":"Shopping",
            "subcategory":"Mobile Phones",
            "type":"Retail Goods"
        }
    ],
    "sg:phone":"+1 443 376 5738",
    "sg:postcode":"21222",
    "sg:province":"MD",
    "wof:name":"Gotta Go Wireless",
    "wof:placetype":"venue"
},
  "geometry": {"coordinates":[-76.525847,39.272589],"type":"Point"}
}