{
  "type": "Feature",
  "properties": {
    "iso:country":"US",
    "sg:address":"6808 Algonquin Ave",
    "sg:city":"Bethesda",
    "sg:classifiers":[
        {
            "category":"Professional",
            "subcategory":"Business Services",
            "type":"Services"
        }
    ],
    "sg:phone":"+1 301 320 3960",
    "sg:postcode":"20817",
    "sg:province":"MD",
    "sg:tags":[
        "consulting",
        "management"
    ],
    "wof:name":"Strategic Business Consulting",
    "wof:placetype":"venue"
},
  "geometry": {"coordinates":[-77.138455,38.98642],"type":"Point"}
}