{
  "type": "Feature",
  "properties": {
    "addr:full":"6745 Cortina Dr Highland MD 20777",
    "addr:housenumber":"6745",
    "addr:postcode":"20777",
    "addr:street":"Cortina Dr",
    "iso:country":"US",
    "sg:address":"6745 Cortina Dr",
    "sg:city":"Highland",
    "sg:classifiers":[
        {
            "category":"Manufacturing",
            "subcategory":"Building Materials",
            "type":"Manufacturing & Wholesale Goods"
        }
    ],
    "sg:phone":"+1 301 854 1146",
    "sg:postcode":"20777",
    "sg:province":"MD",
    "sg:tags":[
        "mill",
        "paper",
        "mfg"
    ],
    "wof:name":"Georgia-Pacific",
    "wof:placetype":"venue"
},
  "geometry": {"coordinates":[-76.98884700000001,39.185558],"type":"Point"}
}