{
  "type": "Feature",
  "properties": {
    "iso:country":"US",
    "sg:address":"6745 Cortina Dr",
    "sg:city":"Highland",
    "sg:classifiers":[
        {
            "category":"Manufacturing",
            "subcategory":"Building Materials",
            "type":"Manufacturing & Wholesale Goods"
        }
    ],
    "sg:phone":"+1 301 854 1146",
    "sg:postcode":"20777",
    "sg:province":"MD",
    "sg:tags":[
        "mill",
        "paper",
        "mfg"
    ],
    "wof:name":"Georgia-Pacific",
    "wof:placetype":"venue"
},
  "geometry": {"coordinates":[-76.988847,39.185558],"type":"Point"}
}