{
  "type": "Feature",
  "properties": {
    "iso:country":"US",
    "sg:address":"7453 Broken Staff",
    "sg:city":"Columbia",
    "sg:classifiers":[
        {
            "category":"Wholesale",
            "subcategory":"Furniture",
            "type":"Manufacturing & Wholesale Goods"
        }
    ],
    "sg:phone":"+1 410 381 2649",
    "sg:postcode":"21045",
    "sg:province":"MD",
    "wof:name":"The Knoll Group",
    "wof:placetype":"venue"
},
  "geometry": {"coordinates":[-76.848251,39.184779],"type":"Point"}
}