{
  "type": "Feature",
  "properties": {
    "iso:country":"US",
    "sg:address":"22301 Georgia Ave",
    "sg:city":"Brookeville",
    "sg:classifiers":[
        {
            "category":"Shopping",
            "type":"Retail Goods"
        }
    ],
    "sg:phone":"+1 301 774 8114",
    "sg:postcode":"20833",
    "sg:province":"MD",
    "sg:tags":[
        "pet",
        "food",
        "supply"
    ],
    "wof:name":"Country Pet Stop",
    "wof:placetype":"venue"
},
  "geometry": {"coordinates":[-77.058593,39.225661],"type":"Point"}
}