{
  "type": "Feature",
  "properties": {
    "addr:full":"25220 Woodfield School Rd Gaithersburg MD 20882",
    "addr:housenumber":"25220",
    "addr:postcode":"20882",
    "addr:street":"Woodfield School Rd",
    "iso:country":"US",
    "sg:address":"25220 Woodfield School Rd",
    "sg:city":"Gaithersburg",
    "sg:classifiers":[
        {
            "category":"Home & Garden",
            "subcategory":"Building Materials",
            "type":"Retail Goods"
        }
    ],
    "sg:phone":"+1 301 253 1663",
    "sg:postcode":"20882",
    "sg:province":"MD",
    "sg:tags":[
        "windows"
    ],
    "wof:name":"Macklin Contracting",
    "wof:placetype":"venue"
},
  "geometry": {"coordinates":[-77.17652699999999,39.274871],"type":"Point"}
}