{
  "type": "Feature",
  "properties": {
    "addr:full":"14200 Seneca Rd Germantown MD 20874",
    "addr:housenumber":"14200",
    "addr:postcode":"20874",
    "addr:street":"Seneca Rd",
    "iso:country":"US",
    "sg:address":"14200 Seneca Rd",
    "sg:city":"Germantown",
    "sg:classifiers":[
        {
            "category":"Manufacturing",
            "subcategory":"Buildings",
            "type":"Manufacturing & Wholesale Goods"
        },
        {
            "category":"Building & Trades",
            "subcategory":"Construction",
            "type":"Services"
        }
    ],
    "sg:phone":"+1 301 947 8999",
    "sg:postcode":"20874",
    "sg:province":"MD",
    "sg:tags":[
        "industrial",
        "contractors-commercial",
        "builder",
        "system",
        "specialty",
        "heating",
        "contractor",
        "home",
        "air conditioning",
        "road",
        "paving"
    ],
    "wof:name":"K C C",
    "wof:placetype":"venue"
},
  "geometry": {"coordinates":[-77.293648,39.101219],"type":"Point"}
}