{
  "type": "Feature",
  "properties": {
    "addr:full":"3209 N Point Rd Dundalk MD 21222",
    "addr:housenumber":"3209",
    "addr:postcode":"21222",
    "addr:street":"N Point Rd",
    "iso:country":"US",
    "sg:address":"3209 N Point Rd",
    "sg:city":"Dundalk",
    "sg:classifiers":[
        {
            "category":"Fast Food",
            "type":"Food & Drink"
        },
        {
            "category":"Restaurant",
            "type":"Food & Drink"
        }
    ],
    "sg:phone":"+1 410 282 7237",
    "sg:postcode":"21222",
    "sg:province":"MD",
    "sg:tags":[
        "style",
        "take",
        "family"
    ],
    "wof:name":"Pennys Carryout",
    "wof:placetype":"venue"
},
  "geometry": {"coordinates":[-76.48498600000001,39.277896],"type":"Point"}
}