{
  "type": "Feature",
  "properties": {
    "addr:full":"4906 Decatur St Hyattsville MD 20781",
    "addr:housenumber":"4906",
    "addr:postcode":"20781",
    "addr:street":"Decatur St",
    "iso:country":"US",
    "sg:address":"4906 Decatur St",
    "sg:city":"Hyattsville",
    "sg:classifiers":[
        {
            "category":"Building & Trades",
            "subcategory":"Construction",
            "type":"Services"
        }
    ],
    "sg:phone":"+1 301 927 0400",
    "sg:postcode":"20781",
    "sg:province":"MD",
    "sg:tags":[
        "concrete",
        "contractor"
    ],
    "wof:name":"Santos Construction Co",
    "wof:placetype":"venue"
},
  "geometry": {"coordinates":[-76.936373,38.949905],"type":"Point"}
}