{
  "type": "Feature",
  "properties": {
    "iso:country":"US",
    "sg:address":"3920 Lumo Cir",
    "sg:city":"Randallstown",
    "sg:classifiers":[
        {
            "category":"Building & Trades",
            "subcategory":"Electrical",
            "type":"Services"
        }
    ],
    "sg:phone":"+1 410 655 8286",
    "sg:postcode":"21133",
    "sg:province":"MD",
    "sg:tags":[
        "electrical",
        "contractor"
    ],
    "wof:name":"Webster Electric",
    "wof:placetype":"venue"
},
  "geometry": {"coordinates":[-76.788181,39.375811],"type":"Point"}
}