{
  "type": "Feature",
  "properties": {
    "addr:full":"9653 Overton Dr Laurel MD 20723",
    "addr:housenumber":"9653",
    "addr:postcode":"20723",
    "addr:street":"Overton Dr",
    "iso:country":"US",
    "sg:address":"9653 Overton Dr",
    "sg:city":"Laurel",
    "sg:classifiers":[
        {
            "category":"Professional",
            "subcategory":"Computer Services",
            "type":"Services"
        }
    ],
    "sg:phone":"+1 301 651 7010",
    "sg:postcode":"20723",
    "sg:province":"MD",
    "sg:tags":[
        "related"
    ],
    "wof:name":"Technopro",
    "wof:placetype":"venue"
},
  "geometry": {"coordinates":[-76.841661,39.127319],"type":"Point"}
}