{
  "type": "Feature",
  "properties": {
    "addr:full":"102 S Morris St Oxford MD 21654",
    "addr:housenumber":"102",
    "addr:postcode":"21654",
    "addr:street":"S Morris St",
    "iso:country":"US",
    "sg:address":"102 S Morris St",
    "sg:city":"Oxford",
    "sg:classifiers":[
        {
            "category":"Autos & Motor Vehicles",
            "subcategory":"Boat Sales",
            "type":"Retail Goods"
        }
    ],
    "sg:phone":"+1 410 226 5000",
    "sg:postcode":"21654",
    "sg:province":"MD",
    "sg:tags":[
        "yacht",
        "broker"
    ],
    "wof:name":"Tred Avon Yacht Sales",
    "wof:placetype":"venue"
},
  "geometry": {"coordinates":[-76.172895,38.689043],"type":"Point"}
}