{
  "type": "Feature",
  "properties": {
    "iso:country":"US",
    "sg:address":"21921 Dickerson Rd",
    "sg:city":"Dickerson",
    "sg:classifiers":[
        {
            "category":"Building & Trades",
            "subcategory":"Construction",
            "type":"Services"
        }
    ],
    "sg:phone":"+1 301 972 7159",
    "sg:postcode":"20842",
    "sg:province":"MD",
    "sg:tags":[
        "industrial",
        "contractors-commercial",
        "road",
        "contractor"
    ],
    "wof:name":"Wm I Jordan General Constructor",
    "wof:placetype":"venue"
},
  "geometry": {"coordinates":[-77.428594,39.215993],"type":"Point"}
}