{
  "type": "Feature",
  "properties": {
    "iso:country":"US",
    "sg:address":"217 Glen View Ter",
    "sg:city":"Abingdon",
    "sg:classifiers":[
        {
            "category":"Professional",
            "subcategory":"Accounting & Tax Preparation",
            "type":"Services"
        }
    ],
    "sg:phone":"+1 410 515 8700",
    "sg:postcode":"21009",
    "sg:province":"MD",
    "sg:tags":[
        "accountant"
    ],
    "wof:name":"Stanley A Mengel & Assoc",
    "wof:placetype":"venue"
},
  "geometry": {"coordinates":[-76.321966,39.476003],"type":"Point"}
}