{
  "type": "Feature",
  "properties": {
    "addr:full":"8101 Odell Rd Beltsville MD 20705",
    "addr:housenumber":"8101",
    "addr:postcode":"20705",
    "addr:street":"Odell Rd",
    "iso:country":"US",
    "sg:address":"8101 Odell Rd",
    "sg:city":"Beltsville",
    "sg:classifiers":[
        {
            "category":"Government",
            "subcategory":"Office",
            "type":"Public Place"
        }
    ],
    "sg:phone":"+1 301 985 8004",
    "sg:postcode":"20705",
    "sg:province":"MD",
    "sg:tags":[
        "agency"
    ],
    "wof:name":"United States Dept of State",
    "wof:placetype":"venue"
},
  "geometry": {"coordinates":[-76.86600799999999,39.047729],"type":"Point"}
}