{
  "type": "Feature",
  "properties": {
    "iso:country":"US",
    "sg:address":"2301 Boston St",
    "sg:city":"Baltimore",
    "sg:classifiers":[
        {
            "category":"Professional",
            "type":"Services"
        }
    ],
    "sg:phone":"+1 410 327 4848",
    "sg:postcode":"21224",
    "sg:province":"MD",
    "sg:tags":[
        "establishment"
    ],
    "wof:name":"North Shore Canton Sales Ctr",
    "wof:placetype":"venue"
},
  "geometry": {"coordinates":[-76.583888,39.282768],"type":"Point"}
}