{
  "type": "Feature",
  "properties": {
    "addr:full":"2600 Liberty Heights Ave Baltimore MD 21215",
    "addr:housenumber":"2600",
    "addr:postcode":"21215",
    "addr:street":"Liberty Heights Ave",
    "iso:country":"US",
    "sg:address":"2600 Liberty Heights Ave",
    "sg:city":"Baltimore",
    "sg:classifiers":[
        {
            "category":"Health Services",
            "subcategory":"Hospital",
            "type":"Services"
        }
    ],
    "sg:phone":"+1 410 383 4263",
    "sg:postcode":"21215",
    "sg:province":"MD",
    "wof:name":"Bon Secours Rehabilitation and Wellness Center",
    "wof:placetype":"venue"
},
  "geometry": {"coordinates":[-76.6558,39.319401],"type":"Point"}
}