{
  "type": "Feature",
  "properties": {
    "iso:country":"US",
    "sg:address":"3700 Koppers St",
    "sg:city":"Baltimore",
    "sg:classifiers":[
        {
            "category":"Health Services",
            "subcategory":"Nursing And Care Facility",
            "type":"Services"
        },
        {
            "category":"Health Services",
            "subcategory":"Health Practitioner",
            "type":"Services"
        }
    ],
    "sg:phone":"+1 410 525 9300",
    "sg:postcode":"21227",
    "sg:province":"MD",
    "sg:tags":[
        "therapist",
        "skilled",
        "physical"
    ],
    "wof:name":"Home Health Connection Inc",
    "wof:placetype":"venue"
},
  "geometry": {"coordinates":[-76.67045899999999,39.261499],"type":"Point"}
}