{
  "type": "Feature",
  "properties": {
    "iso:country":"US",
    "sg:address":"12339 Carroll Ave",
    "sg:city":"Rockville",
    "sg:classifiers":[
        {
            "category":"Retail",
            "subcategory":"Auto Repair",
            "type":"Services"
        }
    ],
    "sg:phone":"+1 301 230 0099",
    "sg:postcode":"20852",
    "sg:province":"MD",
    "sg:tags":[
        "muffler",
        "exhaust",
        "system"
    ],
    "wof:name":"International Kitchen Exhaust",
    "wof:placetype":"venue"
},
  "geometry": {"coordinates":[-77.113961,39.060242],"type":"Point"}
}