{
  "type": "Feature",
  "properties": {
    "addr:full":"7814 Parston Dr District Heights MD 20747",
    "addr:housenumber":"7814",
    "addr:postcode":"20747",
    "addr:street":"Parston Dr",
    "iso:country":"US",
    "sg:address":"7814 Parston Dr",
    "sg:city":"District Heights",
    "sg:classifiers":[
        {
            "category":"Shopping",
            "subcategory":"Computers & Home Electronics",
            "type":"Retail Goods"
        }
    ],
    "sg:phone":"+1 301 516 2878",
    "sg:postcode":"20747",
    "sg:province":"MD",
    "sg:tags":[
        "audio"
    ],
    "wof:name":"Elite Audio Solutions",
    "wof:placetype":"venue"
},
  "geometry": {"coordinates":[-76.87095100000001,38.84686],"type":"Point"}
}