{
  "type": "Feature",
  "properties": {
    "addr:full":"21048 Frederick Rd Germantown MD 20876",
    "addr:housenumber":"21048",
    "addr:postcode":"20876",
    "addr:street":"Frederick Rd",
    "iso:country":"US",
    "sg:address":"21048 Frederick Rd",
    "sg:city":"Germantown",
    "sg:classifiers":[
        {
            "category":"Restaurant",
            "type":"Food & Drink"
        }
    ],
    "sg:menulink":"http://www.allmenus.com/md/clarksburg/24438-applebees/menu/",
    "sg:phone":"+1 301 972 1301",
    "sg:postcode":"20876",
    "sg:province":"MD",
    "sg:tags":[
        "burger",
        "american",
        "sandwich",
        "soup"
    ],
    "wof:name":"Applebee's",
    "wof:placetype":"venue"
},
  "geometry": {"coordinates":[-77.245554,39.201914],"type":"Point"}
}