{
  "type": "Feature",
  "properties": {
    "addr:full":"18916 Graystone Rd White Hall MD 21161",
    "addr:housenumber":"18916",
    "addr:postcode":"21161",
    "addr:street":"Graystone Rd",
    "iso:country":"US",
    "sg:address":"18916 Graystone Rd",
    "sg:city":"White Hall",
    "sg:classifiers":[
        {
            "category":"Professional",
            "subcategory":"Management & Consulting",
            "type":"Services"
        }
    ],
    "sg:phone":"+1 410 329 6841",
    "sg:postcode":"21161",
    "sg:province":"MD",
    "sg:tags":[
        "consultant",
        "educational"
    ],
    "wof:name":"Ed Events Inc",
    "wof:placetype":"venue"
},
  "geometry": {"coordinates":[-76.626234,39.642164],"type":"Point"}
}