{
  "type": "Feature",
  "properties": {
    "iso:country":"US",
    "sg:address":"18042 Mateny Rd",
    "sg:city":"Germantown",
    "sg:classifiers":[
        {
            "category":"Personal",
            "subcategory":"Barber",
            "type":"Services"
        }
    ],
    "sg:phone":"+1 301 916 6900",
    "sg:postcode":"20874",
    "sg:province":"MD",
    "sg:website":"http://www.barbershop.org/",
    "wof:name":"Barber Shop",
    "wof:placetype":"venue"
},
  "geometry": {"coordinates":[-77.272903,39.146905],"type":"Point"}
}