{
  "type": "Feature",
  "properties": {
    "iso:country":"US",
    "sg:address":"510 Idlewild Ave Ste 110",
    "sg:city":"Easton",
    "sg:classifiers":[
        {
            "category":"Health Services",
            "subcategory":"Doctor",
            "type":"Services"
        }
    ],
    "sg:phone":"+1 410 820 4470",
    "sg:postcode":"21601",
    "sg:province":"MD",
    "sg:tags":[
        "physician",
        "surgeon",
        "surgeons",
        "surgery-general"
    ],
    "wof:name":"Surgery Hlgs Surg Ctr Of",
    "wof:placetype":"venue"
},
  "geometry": {"coordinates":[-76.06662799999999,38.764408],"type":"Point"}
}