{
  "type": "Feature",
  "properties": {
    "iso:country":"US",
    "sg:address":"743 Frederick Rd",
    "sg:city":"Catonsville",
    "sg:classifiers":[
        {
            "category":"Retail",
            "subcategory":"Repair Shop",
            "type":"Services"
        }
    ],
    "sg:phone":"+1 410 747 1900",
    "sg:postcode":"21228",
    "sg:province":"MD",
    "sg:tags":[
        "instrument",
        "teacher",
        "musical"
    ],
    "sg:website":"http://www.billsmusic.com",
    "wof:name":"Bill's Music House",
    "wof:placetype":"venue"
},
  "geometry": {"coordinates":[-76.733492,39.271636],"type":"Point"}
}