{
  "type": "Feature",
  "properties": {
    "addr:full":"10632 Little Patuxent Pkwy Columbia MD 21044",
    "addr:housenumber":"10632",
    "addr:postcode":"21044",
    "addr:street":"Little Patuxent Pkwy",
    "iso:country":"US",
    "sg:address":"10632 Little Patuxent Pkwy",
    "sg:city":"Columbia",
    "sg:classifiers":[
        {
            "category":"Professional",
            "subcategory":"Computer Services",
            "type":"Services"
        }
    ],
    "sg:phone":"+1 410 997 6707",
    "sg:postcode":"21044",
    "sg:province":"MD",
    "sg:tags":[
        "design",
        "system",
        "network"
    ],
    "wof:name":"Cardinal Health 301",
    "wof:placetype":"venue"
},
  "geometry": {"coordinates":[-76.87110300000001,39.213999],"type":"Point"}
}