{
  "type": "Feature",
  "properties": {
    "addr:full":"3331 Pouska Rd Abingdon MD 21009",
    "addr:housenumber":"3331",
    "addr:postcode":"21009",
    "addr:street":"Pouska Rd",
    "iso:country":"US",
    "sg:address":"3331 Pouska Rd",
    "sg:city":"Abingdon",
    "sg:classifiers":[
        {
            "category":"Building & Trades",
            "subcategory":"Construction",
            "type":"Services"
        }
    ],
    "sg:phone":"+1 410 515 0551",
    "sg:postcode":"21009",
    "sg:province":"MD",
    "sg:tags":[
        "contractor"
    ],
    "wof:name":"Crumbakers Inc",
    "wof:placetype":"venue"
},
  "geometry": {"coordinates":[-76.27704799999999,39.473075],"type":"Point"}
}