{
  "type": "Feature",
  "properties": {
    "addr:full":"5852 Hubbard Dr Rockville MD 20852",
    "addr:housenumber":"5852",
    "addr:postcode":"20852",
    "addr:street":"Hubbard Dr",
    "iso:country":"US",
    "sg:address":"5852 Hubbard Dr",
    "sg:city":"Rockville",
    "sg:classifiers":[
        {
            "category":"Building & Trades",
            "subcategory":"Construction",
            "type":"Services"
        }
    ],
    "sg:phone":"+1 301 770 2582",
    "sg:postcode":"20852",
    "sg:province":"MD",
    "sg:tags":[
        "home",
        "builder"
    ],
    "sg:website":"www.belleterreconstruction.com",
    "wof:name":"Belle Terre Development",
    "wof:placetype":"venue"
},
  "geometry": {"coordinates":[-77.118678,39.054905],"type":"Point"}
}