{
  "type": "Feature",
  "properties": {
    "addr:full":"10408 Farmview Ct New Market MD 21774",
    "addr:housenumber":"10408",
    "addr:postcode":"21774",
    "addr:street":"Farmview Ct",
    "iso:country":"US",
    "sg:address":"10408 Farmview Ct",
    "sg:city":"New Market",
    "sg:classifiers":[
        {
            "category":"Social Services",
            "type":"Services"
        }
    ],
    "sg:phone":"+1 301 865 7141",
    "sg:postcode":"21774",
    "sg:province":"MD",
    "wof:name":"Jan Kennedy",
    "wof:placetype":"venue"
},
  "geometry": {"coordinates":[-77.305188,39.42477],"type":"Point"}
}