{
  "type": "Feature",
  "properties": {
    "addr:full":"8801 River Oaks Ter Frederick MD 21704",
    "addr:housenumber":"8801",
    "addr:postcode":"21704",
    "addr:street":"River Oaks Ter",
    "iso:country":"US",
    "sg:address":"8801 River Oaks Ter",
    "sg:city":"Frederick",
    "sg:classifiers":[
        {
            "category":"Wholesale",
            "subcategory":"Electrical",
            "type":"Manufacturing & Wholesale Goods"
        }
    ],
    "sg:phone":"+1 301 846 9204",
    "sg:postcode":"21704",
    "sg:province":"MD",
    "sg:website":"www.statec-vacuum.net",
    "wof:name":"Statec",
    "wof:placetype":"venue"
},
  "geometry": {"coordinates":[-77.36423499999999,39.393518],"type":"Point"}
}