{
  "type": "Feature",
  "properties": {
    "iso:country":"US",
    "sg:address":"8801 River Oaks Ter",
    "sg:city":"Frederick",
    "sg:classifiers":[
        {
            "category":"Wholesale",
            "subcategory":"Electrical",
            "type":"Manufacturing & Wholesale Goods"
        }
    ],
    "sg:phone":"+1 301 846 9204",
    "sg:postcode":"21704",
    "sg:province":"MD",
    "sg:website":"www.statec-vacuum.net",
    "wof:name":"Statec",
    "wof:placetype":"venue"
},
  "geometry": {"coordinates":[-77.364235,39.393518],"type":"Point"}
}