{
  "type": "Feature",
  "properties": {
    "iso:country":"US",
    "sg:address":"5005 Nassawango Rd",
    "sg:city":"Snow Hill",
    "sg:classifiers":[
        {
            "category":"Building & Trades",
            "subcategory":"Pest Control",
            "type":"Services"
        }
    ],
    "sg:phone":"+1 410 632 3869",
    "sg:postcode":"21863",
    "sg:province":"MD",
    "wof:name":"Omni Enterprises",
    "wof:placetype":"venue"
},
  "geometry": {"coordinates":[-75.43099100000001,38.170269],"type":"Point"}
}