{
  "type": "Feature",
  "properties": {
    "iso:country":"US",
    "sg:address":"621 Ridgely Ave",
    "sg:city":"Annapolis",
    "sg:classifiers":[
        {
            "category":"Health Services",
            "subcategory":"Doctor",
            "type":"Services"
        }
    ],
    "sg:phone":"+1 410 573 5053",
    "sg:postcode":"21401",
    "sg:province":"MD",
    "sg:tags":[
        "physician",
        "surgeon"
    ],
    "wof:name":"Ear Nose Throat & Asthma",
    "wof:placetype":"venue"
},
  "geometry": {"coordinates":[-76.51346599999999,38.995905],"type":"Point"}
}