{
  "type": "Feature",
  "properties": {
    "addr:full":"7 N Church St Middletown MD 21769",
    "addr:housenumber":"7",
    "addr:postcode":"21769",
    "addr:street":"N Church St",
    "iso:country":"US",
    "sg:address":"7 N Church St",
    "sg:city":"Middletown",
    "sg:classifiers":[
        {
            "category":"Autos & Motor Vehicles",
            "subcategory":"Automobile Sales",
            "type":"Retail Goods"
        }
    ],
    "sg:phone":"+1 301 371 6900",
    "sg:postcode":"21769",
    "sg:province":"MD",
    "sg:tags":[
        "car",
        "dealer"
    ],
    "sg:website":"www.mcpcars.com",
    "wof:name":"Middletown Chevrolet Pontiac",
    "wof:placetype":"venue"
},
  "geometry": {"coordinates":[-77.545615,39.442754],"type":"Point"}
}