{
  "type": "Feature",
  "properties": {
    "iso:country":"US",
    "sg:address":"209 12th St",
    "sg:city":"Pocomoke City",
    "sg:classifiers":[
        {
            "category":"Building & Trades",
            "subcategory":"Construction",
            "type":"Services"
        }
    ],
    "sg:phone":"+1 410 957 4260",
    "sg:postcode":"21851",
    "sg:province":"MD",
    "sg:tags":[
        "house"
    ],
    "wof:name":"Strauss Builders",
    "wof:placetype":"venue"
},
  "geometry": {"coordinates":[-75.556263,38.065967],"type":"Point"}
}