{
  "type": "Feature",
  "properties": {
    "iso:country":"US",
    "sg:address":"9600 Medical Center Dr",
    "sg:city":"Rockville",
    "sg:classifiers":[
        {
            "category":"Banks & Credit Unions",
            "subcategory":"Bank",
            "type":"Services"
        }
    ],
    "sg:phone":"+1 301 738 2367",
    "sg:postcode":"20850",
    "sg:province":"MD",
    "wof:name":"M & T Bank",
    "wof:placetype":"venue"
},
  "geometry": {"coordinates":[-77.195449,39.101436],"type":"Point"}
}