{
  "type": "Feature",
  "properties": {
    "iso:country":"US",
    "sg:address":"11259 Lockwood Dr",
    "sg:city":"Silver Spring",
    "sg:classifiers":[
        {
            "category":"Insurance",
            "subcategory":"Insurance Agent",
            "type":"Services"
        }
    ],
    "sg:phone":"+1 301 681 7550",
    "sg:postcode":"20901",
    "sg:province":"MD",
    "wof:name":"Gus Ioakim Insurance",
    "wof:placetype":"venue"
},
  "geometry": {"coordinates":[-76.993819,39.038048],"type":"Point"}
}