{
  "type": "Feature",
  "properties": {
    "iso:country":"US",
    "sg:address":"660 Americana Dr",
    "sg:city":"Annapolis",
    "sg:classifiers":[
        {
            "category":"Real Estate",
            "subcategory":"Real Estate Operator",
            "type":"Services"
        }
    ],
    "sg:phone":"+1 410 263 2361",
    "sg:postcode":"21403",
    "sg:province":"MD",
    "sg:tags":[
        "apartment"
    ],
    "sg:website":"www.bernsteinmgmt.com",
    "wof:name":"Watergate Village",
    "wof:placetype":"venue"
},
  "geometry": {"coordinates":[-76.48690999999999,38.96567],"type":"Point"}
}