{
  "type": "Feature",
  "properties": {
    "iso:country":"US",
    "sg:address":"3401 Edmondson Ave",
    "sg:city":"Baltimore",
    "sg:classifiers":[
        {
            "category":"Food & Beverages",
            "subcategory":"Liquor & Beverages",
            "type":"Retail Goods"
        }
    ],
    "sg:phone":"+1 410 947 7870",
    "sg:postcode":"21229",
    "sg:province":"MD",
    "sg:tags":[
        "beer",
        "spirit",
        "wine"
    ],
    "wof:name":"Jae Liquors Inc",
    "wof:placetype":"venue"
},
  "geometry": {"coordinates":[-76.67420199999999,39.2939],"type":"Point"}
}