{
  "type": "Feature",
  "properties": {
    "addr:full":"4908 Liberty Heights Ave Baltimore MD 21207",
    "addr:housenumber":"4908",
    "addr:postcode":"21207",
    "addr:street":"Liberty Heights Ave",
    "iso:country":"US",
    "sg:address":"4908 Liberty Heights Ave",
    "sg:city":"Baltimore",
    "sg:classifiers":[
        {
            "category":"Real Estate",
            "subcategory":"Real Estate Agent",
            "type":"Services"
        }
    ],
    "sg:phone":"+1 410 542 2025",
    "sg:postcode":"21207",
    "sg:province":"MD",
    "sg:tags":[
        "management"
    ],
    "wof:name":"Five Star Realty Co",
    "wof:placetype":"venue"
},
  "geometry": {"coordinates":[-76.699409,39.332662],"type":"Point"}
}