{
  "type": "Feature",
  "properties": {
    "addr:full":"9150 Parkland Rd Parkville MD 21234",
    "addr:housenumber":"9150",
    "addr:postcode":"21234",
    "addr:street":"Parkland Rd",
    "iso:country":"US",
    "sg:address":"9150 Parkland Rd",
    "sg:city":"Parkville",
    "sg:classifiers":[
        {
            "category":"Real Estate",
            "subcategory":"Real Estate Operator",
            "type":"Services"
        }
    ],
    "sg:phone":"+1 410 665 0066",
    "sg:postcode":"21234",
    "sg:province":"MD",
    "sg:tags":[
        "apartment"
    ],
    "sg:website":"www.homestore.com",
    "wof:name":"Town & Country Apt Carney",
    "wof:placetype":"venue"
},
  "geometry": {"coordinates":[-76.52443100000001,39.402237],"type":"Point"}
}