{
  "type": "Feature",
  "properties": {
    "addr:full":"2901 Watrvw Ave Baltimore MD 21201",
    "addr:housenumber":"2901",
    "addr:postcode":"21201",
    "addr:street":"Watrvw Ave",
    "iso:country":"US",
    "sg:address":"2901 Watrvw Ave",
    "sg:city":"Baltimore",
    "sg:classifiers":[
        {
            "category":"Building & Trades",
            "subcategory":"Construction",
            "type":"Services"
        }
    ],
    "sg:phone":"+1 410 385 0760",
    "sg:postcode":"21201",
    "sg:province":"MD",
    "sg:tags":[
        "contractor"
    ],
    "wof:name":"D & G Brice",
    "wof:placetype":"venue"
},
  "geometry": {"coordinates":[-76.622597,39.2957],"type":"Point"}
}