{
  "type": "Feature",
  "properties": {
    "iso:country":"US",
    "sg:address":"11914 Boyd Rd",
    "sg:city":"Clear Spring",
    "sg:classifiers":[
        {
            "category":"Professional",
            "subcategory":"Management & Consulting",
            "type":"Services"
        }
    ],
    "sg:phone":"+1 301 842 2960",
    "sg:postcode":"21722",
    "sg:province":"MD",
    "sg:tags":[
        "retail",
        "direct",
        "sales"
    ],
    "wof:name":"F Jean Snyder",
    "wof:placetype":"venue"
},
  "geometry": {"coordinates":[-77.954201,39.640923],"type":"Point"}
}