{
  "type": "Feature",
  "properties": {
    "addr:full":"213 Randolph Rd Silver Spring MD 20904",
    "addr:housenumber":"213",
    "addr:postcode":"20904",
    "addr:street":"Randolph Rd",
    "iso:country":"US",
    "sg:address":"213 Randolph Rd",
    "sg:city":"Silver Spring",
    "sg:classifiers":[
        {
            "category":"Social Services",
            "subcategory":"Child Care",
            "type":"Services"
        }
    ],
    "sg:phone":"+1 301 622 3365",
    "sg:postcode":"20904",
    "sg:province":"MD",
    "sg:tags":[
        "day"
    ],
    "wof:name":"Toddler House Inc",
    "wof:placetype":"venue"
},
  "geometry": {"coordinates":[-77.013603,39.069801],"type":"Point"}
}