{
  "type": "Feature",
  "properties": {
    "addr:full":"1513 N Main St Hampstead MD 21074",
    "addr:housenumber":"1513",
    "addr:postcode":"21074",
    "addr:street":"N Main St",
    "iso:country":"US",
    "sg:address":"1513 N Main St",
    "sg:city":"Hampstead",
    "sg:classifiers":[
        {
            "category":"Building & Trades",
            "subcategory":"Construction",
            "type":"Services"
        }
    ],
    "sg:phone":"+1 410 239 7721",
    "sg:postcode":"21074",
    "sg:province":"MD",
    "sg:tags":[
        "hanging",
        "contractor"
    ],
    "wof:name":"ASAP Painting",
    "wof:placetype":"venue"
},
  "geometry": {"coordinates":[-76.853386,39.613705],"type":"Point"}
}