{
  "type": "Feature",
  "properties": {
    "iso:country":"US",
    "sg:address":"109 Aspinwood Way",
    "sg:city":"Rosedale",
    "sg:classifiers":[
        {
            "category":"Real Estate",
            "subcategory":"Real Estate Operator",
            "type":"Services"
        }
    ],
    "sg:phone":"+1 410 661 1101",
    "sg:postcode":"21237",
    "sg:province":"MD",
    "sg:tags":[
        "apartment"
    ],
    "wof:name":"Ridge View Apartments",
    "wof:placetype":"venue"
},
  "geometry": {"coordinates":[-76.48389400000001,39.345456],"type":"Point"}
}