{
  "type": "Feature",
  "properties": {
    "addr:full":"722 Potomac Ave Hagerstown MD 21740",
    "addr:housenumber":"722",
    "addr:postcode":"21740",
    "addr:street":"Potomac Ave",
    "iso:country":"US",
    "sg:address":"722 Potomac Ave",
    "sg:city":"Hagerstown",
    "sg:classifiers":[
        {
            "category":"Retail",
            "subcategory":"Repair Shop",
            "type":"Services"
        }
    ],
    "sg:phone":"+1 301 733 7376",
    "sg:postcode":"21740",
    "sg:province":"MD",
    "sg:tags":[
        "clocks",
        "parts"
    ],
    "wof:name":"Northside Clock Shop",
    "wof:placetype":"venue"
},
  "geometry": {"coordinates":[-77.71187,39.650745],"type":"Point"}
}