{
  "type": "Feature",
  "properties": {
    "addr:full":"100 Chestnut Springs Rd Chesapeake City MD 21915",
    "addr:housenumber":"100",
    "addr:postcode":"21915",
    "addr:street":"Chestnut Springs Rd",
    "iso:country":"US",
    "sg:address":"100 Chestnut Springs Rd",
    "sg:city":"Chesapeake City",
    "sg:classifiers":[
        {
            "category":"Wholesale",
            "subcategory":"Toys & Hobbies",
            "type":"Manufacturing & Wholesale Goods"
        }
    ],
    "sg:phone":"+1 410 885 5051",
    "sg:postcode":"21915",
    "sg:province":"MD",
    "wof:name":"Integrity Toys Inc",
    "wof:placetype":"venue"
},
  "geometry": {"coordinates":[-75.84116,39.527655],"type":"Point"}
}