{
  "type": "Feature",
  "properties": {
    "iso:country":"US",
    "sg:address":"10121 Garden Valley Ct",
    "sg:city":"Cheltenham",
    "sg:classifiers":[
        {
            "category":"Restaurant",
            "type":"Food & Drink"
        }
    ],
    "sg:phone":"+1 301 372 1494",
    "sg:postcode":"20623",
    "sg:province":"MD",
    "sg:tags":[
        "caterer"
    ],
    "wof:name":"Tastes So Good",
    "wof:placetype":"venue"
},
  "geometry": {"coordinates":[-76.828781,38.749542],"type":"Point"}
}