{
  "type": "Feature",
  "properties": {
    "addr:full":"15877 Redland Rd Rockville MD 20855",
    "addr:housenumber":"15877",
    "addr:postcode":"20855",
    "addr:street":"Redland Rd",
    "iso:country":"US",
    "sg:address":"15877 Redland Rd",
    "sg:city":"Rockville",
    "sg:classifiers":[
        {
            "category":"Personal",
            "subcategory":"Tattoo Parlor",
            "type":"Services"
        }
    ],
    "sg:phone":"+1 301 977 0094",
    "sg:postcode":"20855",
    "sg:province":"MD",
    "sg:tags":[
        "tattooing"
    ],
    "wof:name":"Inkers Electric Tattooing",
    "wof:placetype":"venue"
},
  "geometry": {"coordinates":[-77.157292,39.12231],"type":"Point"}
}