{
  "type": "Feature",
  "properties": {
    "addr:full":"330 N Stonestreet Ave Ste A Rockville MD 20850",
    "addr:housenumber":"330",
    "addr:postcode":"20850",
    "addr:street":"N Stonestreet Ave Ste A",
    "iso:country":"US",
    "sg:address":"330 N Stonestreet Ave Ste A",
    "sg:city":"Rockville",
    "sg:classifiers":[
        {
            "category":"Retail",
            "subcategory":"Laundry & Dry Cleaning",
            "type":"Services"
        },
        {
            "category":"Retail",
            "subcategory":"Repair Shop",
            "type":"Services"
        },
        {
            "category":"Home & Garden",
            "subcategory":"Carpets & Floor Coverings",
            "type":"Retail Goods"
        }
    ],
    "sg:phone":"+1 301 762 0000",
    "sg:postcode":"20850",
    "sg:province":"MD",
    "sg:tags":[
        "cleaner",
        "rug"
    ],
    "wof:name":"Honar Oriental Rug Restoration",
    "wof:placetype":"venue"
},
  "geometry": {"coordinates":[-77.148021,39.087791],"type":"Point"}
}