{
  "type": "Feature",
  "properties": {
    "addr:full":"1385 Defense Hwy Gambrills MD 21054",
    "addr:housenumber":"1385",
    "addr:postcode":"21054",
    "addr:street":"Defense Hwy",
    "iso:country":"US",
    "sg:address":"1385 Defense Hwy",
    "sg:city":"Gambrills",
    "sg:classifiers":[
        {
            "category":"Building & Trades",
            "subcategory":"Construction",
            "type":"Services"
        }
    ],
    "sg:phone":"+1 301 249 8227",
    "sg:postcode":"21054",
    "sg:province":"MD",
    "sg:tags":[
        "paving",
        "contractor"
    ],
    "wof:name":"Driveways",
    "wof:placetype":"venue"
},
  "geometry": {"coordinates":[-76.671712,38.992495],"type":"Point"}
}