{
  "type": "Feature",
  "properties": {
    "addr:full":"520 River Bend Rd Fort Washington MD 20744",
    "addr:housenumber":"520",
    "addr:postcode":"20744",
    "addr:street":"River Bend Rd",
    "iso:country":"US",
    "sg:address":"520 River Bend Rd",
    "sg:city":"Fort Washington",
    "sg:classifiers":[
        {
            "category":"Professional",
            "subcategory":"Management & Consulting",
            "type":"Services"
        }
    ],
    "sg:phone":"+1 301 749 7282",
    "sg:postcode":"20744",
    "sg:province":"MD",
    "sg:tags":[
        "organizational"
    ],
    "wof:name":"Kuruvilla Associates LLC",
    "wof:placetype":"venue"
},
  "geometry": {"coordinates":[-77.02185900000001,38.777401],"type":"Point"}
}