{
  "type": "Feature",
  "properties": {
    "iso:country":"US",
    "sg:address":"35 Atherton Rd",
    "sg:city":"Lutherville",
    "sg:classifiers":[
        {
            "category":"Wholesale",
            "subcategory":"Durable Goods & Equipment",
            "type":"Manufacturing & Wholesale Goods"
        }
    ],
    "sg:phone":"+1 410 560 1845",
    "sg:postcode":"21093",
    "sg:province":"MD",
    "sg:tags":[
        "exporter"
    ],
    "wof:name":"International Products Direct",
    "wof:placetype":"venue"
},
  "geometry": {"coordinates":[-76.616121,39.429977],"type":"Point"}
}