{
  "type": "Feature",
  "properties": {
    "addr:full":"30 Main St Reisterstown MD 21136",
    "addr:housenumber":"30",
    "addr:postcode":"21136",
    "addr:street":"Main St",
    "iso:country":"US",
    "sg:address":"30 Main St",
    "sg:city":"Reisterstown",
    "sg:classifiers":[
        {
            "category":"Autos & Motor Vehicles",
            "subcategory":"Fuel & Gas Station",
            "type":"Retail Goods"
        }
    ],
    "sg:phone":"+1 410 833 4120",
    "sg:postcode":"21136",
    "sg:province":"MD",
    "sg:tags":[
        "car wash",
        "oil"
    ],
    "sg:website":"http://www.shell.com",
    "wof:name":"Main Street Shell",
    "wof:placetype":"venue"
},
  "geometry": {"coordinates":[-76.829697,39.4687],"type":"Point"}
}