{
  "type": "Feature",
  "properties": {
    "addr:full":"5006 Mathilda Ln Suitland MD 20746",
    "addr:postcode":"5006;20746",
    "addr:street":"Mathilda Ln",
    "iso:country":"US",
    "sg:address":"5006 Mathilda Ln",
    "sg:city":"Suitland",
    "sg:classifiers":[
        {
            "category":"Home & Garden",
            "subcategory":"Furniture",
            "type":"Retail Goods"
        }
    ],
    "sg:phone":"+1 301 735 5569",
    "sg:postcode":"20746",
    "sg:province":"MD",
    "sg:tags":[
        "equipment-household",
        "kitchen",
        "cabinet"
    ],
    "wof:name":"Custom Kitchen & Bath",
    "wof:placetype":"venue"
},
  "geometry": {"coordinates":[-76.920756,38.839918],"type":"Point"}
}