{
  "type": "Feature",
  "properties": {
    "addr:full":"114 N Main St Federalsburg MD 21632",
    "addr:housenumber":"114",
    "addr:postcode":"21632",
    "addr:street":"N Main St",
    "iso:country":"US",
    "sg:address":"114 N Main St",
    "sg:city":"Federalsburg",
    "sg:classifiers":[
        {
            "category":"Organizations",
            "subcategory":"Religious Organization",
            "type":"Services"
        }
    ],
    "sg:phone":"+1 410 754 9450",
    "sg:postcode":"21632",
    "sg:province":"MD",
    "sg:tags":[
        "church"
    ],
    "wof:name":"A New Destiny Outreach",
    "wof:placetype":"venue"
},
  "geometry": {"coordinates":[-75.77391,38.695175],"type":"Point"}
}