{
  "type": "Feature",
  "properties": {
    "iso:country":"US",
    "sg:address":"25520 Woodfield Rd",
    "sg:city":"Damascus",
    "sg:classifiers":[
        {
            "category":"Organizations",
            "subcategory":"Religious Organization",
            "type":"Services"
        }
    ],
    "sg:phone":"+1 301 253 6877",
    "sg:postcode":"20872",
    "sg:province":"MD",
    "sg:tags":[
        "church"
    ],
    "wof:name":"Iglesia Pentecostal Camino",
    "wof:placetype":"venue"
},
  "geometry": {"coordinates":[-77.204241,39.275348],"type":"Point"}
}