{
  "type": "Feature",
  "properties": {
    "addr:full":"1120 Crain Hwy N Glen Burnie MD 21061",
    "addr:housenumber":"1120",
    "addr:postcode":"21061",
    "addr:street":"Crain Hwy N",
    "iso:country":"US",
    "sg:address":"1120 Crain Hwy N",
    "sg:city":"Glen Burnie",
    "sg:classifiers":[
        {
            "category":"Autos & Motor Vehicles",
            "subcategory":"Automobile Sales",
            "type":"Retail Goods"
        }
    ],
    "sg:phone":"+1 410 766 8132",
    "sg:postcode":"21061",
    "sg:province":"MD",
    "sg:tags":[
        "truck"
    ],
    "wof:name":"Dovell & WILLIAMS Inc",
    "wof:placetype":"venue"
},
  "geometry": {"coordinates":[-76.61513600000001,39.181745],"type":"Point"}
}