{
  "type": "Feature",
  "properties": {
    "addr:full":"5800 Martin Luther King Jr Hwy Frnt Seat Pleasant MD 20743",
    "addr:housenumber":"5800",
    "addr:postcode":"20743",
    "addr:street":"Martin Luther King Jr Hwy Frnt",
    "iso:country":"US",
    "sg:address":"5800 Martin Luther King Jr Hwy Frnt",
    "sg:city":"Seat Pleasant",
    "sg:classifiers":[
        {
            "category":"Banks & Credit Unions",
            "subcategory":"Bank",
            "type":"Services"
        },
        {
            "category":"Banks & Credit Unions",
            "subcategory":"Financial Services",
            "type":"Services"
        }
    ],
    "sg:phone":"+1 301 454 8425",
    "sg:postcode":"20743",
    "sg:province":"MD",
    "sg:tags":[
        "broker",
        "mortgage"
    ],
    "sg:website":"www.bankofamerica.com",
    "wof:name":"Bank of America",
    "wof:placetype":"venue"
},
  "geometry": {"coordinates":[-76.90868399999999,38.895425],"type":"Point"}
}