{
  "type": "Feature",
  "properties": {
    "iso:country":"US",
    "sg:address":"2233 Bel Pre Rd",
    "sg:city":"Silver Spring",
    "sg:classifiers":[
        {
            "category":"Restaurant",
            "type":"Food & Drink"
        }
    ],
    "sg:phone":"+1 301 598 5783",
    "sg:postcode":"20906",
    "sg:province":"MD",
    "sg:tags":[
        "parlor",
        "ice",
        "cream"
    ],
    "wof:name":"Baskin-Robbins",
    "wof:placetype":"venue"
},
  "geometry": {"coordinates":[-77.046999,39.090601],"type":"Point"}
}