{
  "type": "Feature",
  "properties": {
    "addr:full":"804 Stratford Manor Ter Silver Spring MD 20905",
    "addr:housenumber":"804",
    "addr:postcode":"20905",
    "addr:street":"Stratford Manor Ter",
    "iso:country":"US",
    "sg:address":"804 Stratford Manor Ter",
    "sg:city":"Silver Spring",
    "sg:classifiers":[
        {
            "category":"Education",
            "subcategory":"Special Training",
            "type":"Public Place"
        }
    ],
    "sg:phone":"+1 301 989 0472",
    "sg:postcode":"20905",
    "sg:province":"MD",
    "sg:tags":[
        "instructor",
        "language"
    ],
    "wof:name":"University Professor",
    "wof:placetype":"venue"
},
  "geometry": {"coordinates":[-77.021253,39.09075],"type":"Point"}
}