{
  "type": "Feature",
  "properties": {
    "addr:full":"506 Pontiac Ave Brooklyn MD 21225",
    "addr:housenumber":"506",
    "addr:postcode":"21225",
    "addr:street":"Pontiac Ave",
    "iso:country":"US",
    "sg:address":"506 Pontiac Ave",
    "sg:city":"Brooklyn",
    "sg:classifiers":[
        {
            "category":"Manufacturing",
            "subcategory":"Building Materials",
            "type":"Manufacturing & Wholesale Goods"
        }
    ],
    "sg:phone":"+1 410 355 5439",
    "sg:postcode":"21225",
    "sg:province":"MD",
    "sg:tags":[
        "metal",
        "work",
        "sheet"
    ],
    "wof:name":"Harthausen Albert",
    "wof:placetype":"venue"
},
  "geometry": {"coordinates":[-76.604299,39.235693],"type":"Point"}
}