{
  "type": "Feature",
  "properties": {
    "addr:full":"45 Wilson Ct Prince Frederick MD 20678",
    "addr:housenumber":"45",
    "addr:postcode":"20678",
    "addr:street":"Wilson Ct",
    "iso:country":"US",
    "sg:address":"45 Wilson Ct",
    "sg:city":"Prince Frederick",
    "sg:classifiers":[
        {
            "category":"Shopping",
            "type":"Retail Goods"
        }
    ],
    "sg:phone":"+1 301 855 1199",
    "sg:postcode":"20678",
    "sg:province":"MD",
    "sg:tags":[
        "monument"
    ],
    "wof:name":"Bell Monuments",
    "wof:placetype":"venue"
},
  "geometry": {"coordinates":[-76.57916899999999,38.531545],"type":"Point"}
}