{
  "type": "Feature",
  "properties": {
    "iso:country":"US",
    "sg:address":"1920 Fleet St",
    "sg:city":"Baltimore",
    "sg:classifiers":[
        {
            "category":"Professional",
            "subcategory":"Computer Services",
            "type":"Services"
        }
    ],
    "sg:phone":"+1 443 996 8153",
    "sg:postcode":"21231",
    "sg:province":"MD",
    "sg:tags":[
        "design",
        "system",
        "network"
    ],
    "sg:website":"http://www.beeond.net",
    "wof:name":"Beeond, Inc",
    "wof:placetype":"venue"
},
  "geometry": {"coordinates":[-76.58931800000001,39.284722],"type":"Point"}
}