{
  "type": "Feature",
  "properties": {
    "addr:full":"603 Sandy Ridge Dr Glen Burnie MD 21061",
    "addr:housenumber":"603",
    "addr:postcode":"21061",
    "addr:street":"Sandy Ridge Dr",
    "iso:country":"US",
    "sg:address":"603 Sandy Ridge Dr",
    "sg:city":"Glen Burnie",
    "sg:classifiers":[
        {
            "category":"Building & Trades",
            "subcategory":"Construction",
            "type":"Services"
        }
    ],
    "sg:phone":"+1 410 760 9121",
    "sg:postcode":"21061",
    "sg:province":"MD",
    "sg:tags":[
        "house"
    ],
    "wof:name":"At Home Improvements",
    "wof:placetype":"venue"
},
  "geometry": {"coordinates":[-76.637314,39.192671],"type":"Point"}
}