{
  "type": "Feature",
  "properties": {
    "iso:country":"US",
    "sg:address":"1416 Gilbert Rd",
    "sg:city":"Arnold",
    "sg:classifiers":[
        {
            "category":"Professional",
            "subcategory":"Business Services",
            "type":"Services"
        }
    ],
    "sg:phone":"+1 410 974 4937",
    "sg:postcode":"21012",
    "sg:province":"MD",
    "wof:name":"National Assoc of Miniatu",
    "wof:placetype":"venue"
},
  "geometry": {"coordinates":[-76.497118,39.033792],"type":"Point"}
}