{
  "type": "Feature",
  "properties": {
    "addr:full":"7225 Parkway Dr Hanover MD 21076",
    "addr:housenumber":"7225",
    "addr:postcode":"21076",
    "addr:street":"Parkway Dr",
    "iso:country":"US",
    "sg:address":"7225 Parkway Dr",
    "sg:city":"Hanover",
    "sg:classifiers":[
        {
            "category":"Professional",
            "subcategory":"Business Services",
            "type":"Services"
        }
    ],
    "sg:phone":"+1 301 596 4800",
    "sg:postcode":"21076",
    "sg:province":"MD",
    "sg:tags":[
        "equipment",
        "microfilming"
    ],
    "sg:website":"www.medimicro.com",
    "wof:name":"Micrographic Equipment Design",
    "wof:placetype":"venue"
},
  "geometry": {"coordinates":[-76.730802,39.176391],"type":"Point"}
}