{
  "type": "Feature",
  "properties": {
    "addr:full":"277 Silverleaf Ct Arnold MD 21012",
    "addr:housenumber":"277",
    "addr:postcode":"21012",
    "addr:street":"Silverleaf Ct",
    "iso:country":"US",
    "sg:address":"277 Silverleaf Ct",
    "sg:city":"Arnold",
    "sg:classifiers":[
        {
            "category":"Manufacturing",
            "subcategory":"Retail Goods",
            "type":"Manufacturing & Wholesale Goods"
        }
    ],
    "sg:phone":"+1 410 544 5696",
    "sg:postcode":"21012",
    "sg:province":"MD",
    "sg:tags":[
        "manufacturer"
    ],
    "wof:name":"Harris Lange & Co Inc",
    "wof:placetype":"venue"
},
  "geometry": {"coordinates":[-76.49373199999999,39.049065],"type":"Point"}
}