{
  "type": "Feature",
  "properties": {
    "iso:country":"US",
    "sg:address":"7901 Comus Rd",
    "sg:city":"Dickerson",
    "sg:classifiers":[
        {
            "category":"Organizations",
            "subcategory":"Non-profit Organization",
            "type":"Services"
        }
    ],
    "sg:phone":"+1 301 874 2024",
    "sg:postcode":"20842",
    "sg:province":"MD",
    "wof:name":"Stronghold-Sugar Loaf Mt",
    "wof:placetype":"venue"
},
  "geometry": {"coordinates":[-77.393408,39.251511],"type":"Point"}
}