{
  "type": "Feature",
  "properties": {
    "addr:full":"123 Bowie Rd Laurel MD 20707",
    "addr:housenumber":"123",
    "addr:postcode":"20707",
    "addr:street":"Bowie Rd",
    "iso:country":"US",
    "sg:address":"123 Bowie Rd",
    "sg:city":"Laurel",
    "sg:classifiers":[
        {
            "category":"Shopping",
            "subcategory":"Crafts & Fabrics",
            "type":"Retail Goods"
        }
    ],
    "sg:phone":"+1 301 776 8656",
    "sg:postcode":"20707",
    "sg:province":"MD",
    "sg:tags":[
        "store"
    ],
    "sg:website":"www.hancockfabrics.com",
    "wof:name":"Hancock Fabrics Inc",
    "wof:placetype":"venue"
},
  "geometry": {"coordinates":[-76.84792,39.095679],"type":"Point"}
}