{
  "type": "Feature",
  "properties": {
    "iso:country":"US",
    "sg:address":"5813 Cherrywood Ln",
    "sg:city":"Greenbelt",
    "sg:classifiers":[
        {
            "category":"Professional",
            "subcategory":"Computer Services",
            "type":"Services"
        }
    ],
    "sg:phone":"+1 301 982 1120",
    "sg:postcode":"20770",
    "sg:province":"MD",
    "sg:tags":[
        "information",
        "technology"
    ],
    "wof:name":"Ejmt Inc",
    "wof:placetype":"venue"
},
  "geometry": {"coordinates":[-76.909106,39.002949],"type":"Point"}
}