{
  "type": "Feature",
  "properties": {
    "iso:country":"US",
    "sg:address":"705 Jennings Mill Dr",
    "sg:city":"Bowie",
    "sg:classifiers":[
        {
            "category":"Professional",
            "subcategory":"Management & Consulting",
            "type":"Services"
        }
    ],
    "sg:phone":"+1 301 249 0645",
    "sg:postcode":"20721",
    "sg:province":"MD",
    "wof:name":"Marion D Lenoir",
    "wof:placetype":"venue"
},
  "geometry": {"coordinates":[-76.743729,38.893164],"type":"Point"}
}