{
  "type": "Feature",
  "properties": {
    "addr:full":"8807 Annapolis Rd Lanham MD 20706",
    "addr:housenumber":"8807",
    "addr:postcode":"20706",
    "addr:street":"Annapolis Rd",
    "iso:country":"US",
    "sg:address":"8807 Annapolis Rd",
    "sg:city":"Lanham",
    "sg:classifiers":[
        {
            "category":"Autos & Motor Vehicles",
            "subcategory":"Boat Sales",
            "type":"Retail Goods"
        }
    ],
    "sg:phone":"+1 301 577 0660",
    "sg:postcode":"20706",
    "sg:province":"MD",
    "sg:tags":[
        "equipment",
        "marine",
        "supply"
    ],
    "sg:website":"www.westmarine.com",
    "wof:name":"West Marine",
    "wof:placetype":"venue"
},
  "geometry": {"coordinates":[-76.86291799999999,38.961299],"type":"Point"}
}