{
  "type": "Feature",
  "properties": {
    "addr:full":"3475 Leonardtown Rd Waldorf MD 20601",
    "addr:housenumber":"3475",
    "addr:postcode":"20601",
    "addr:street":"Leonardtown Rd",
    "iso:country":"US",
    "sg:address":"3475 Leonardtown Rd",
    "sg:city":"Waldorf",
    "sg:classifiers":[
        {
            "category":"Banks & Credit Unions",
            "subcategory":"Bank",
            "type":"Services"
        }
    ],
    "sg:phone":"+1 301 843 3515",
    "sg:postcode":"20601",
    "sg:province":"MD",
    "sg:tags":[
        "loan",
        "real estate"
    ],
    "wof:name":"Tri-County Mortgage",
    "wof:placetype":"venue"
},
  "geometry": {"coordinates":[-76.897795,38.619041],"type":"Point"}
}