{
  "type": "Feature",
  "properties": {
    "iso:country":"US",
    "sg:address":"1506 Harding Dr",
    "sg:city":"Salisbury",
    "sg:classifiers":[
        {
            "category":"Organizations",
            "subcategory":"Non-profit Organization",
            "type":"Services"
        }
    ],
    "sg:phone":"+1 410 219 9000",
    "sg:postcode":"21802",
    "sg:province":"MD",
    "sg:tags":[
        "info",
        "addiction",
        "abuse",
        "treatment",
        "drug"
    ],
    "sg:website":"www.hudsonhealth.org",
    "wof:name":"Hudson Health Svc In",
    "wof:placetype":"venue"
},
  "geometry": {"coordinates":[-75.59428,38.384744],"type":"Point"}
}