{
  "type": "Feature",
  "properties": {
    "addr:full":"918 Fairlawn Ave Laurel MD 20707",
    "addr:housenumber":"918",
    "addr:postcode":"20707",
    "addr:street":"Fairlawn Ave",
    "iso:country":"US",
    "sg:address":"918 Fairlawn Ave",
    "sg:city":"Laurel",
    "sg:classifiers":[
        {
            "category":"Health Services",
            "subcategory":"Dentist",
            "type":"Services"
        }
    ],
    "sg:phone":"+1 301 490 6922",
    "sg:postcode":"20707",
    "sg:province":"MD",
    "sg:tags":[
        "orthodontist"
    ],
    "wof:name":"Maryland-Virginia Orthodontic Specialists",
    "wof:placetype":"venue"
},
  "geometry": {"coordinates":[-76.85430100000001,39.097401],"type":"Point"}
}