{
  "type": "Feature",
  "properties": {
    "addr:full":"5166 Downwest Ride Columbia MD 21044",
    "addr:housenumber":"5166",
    "addr:postcode":"21044",
    "addr:street":"Downwest Ride",
    "iso:country":"US",
    "sg:address":"5166 Downwest Ride",
    "sg:city":"Columbia",
    "sg:classifiers":[
        {
            "category":"Shopping",
            "type":"Retail Goods"
        }
    ],
    "sg:phone":"+1 410 730 4392",
    "sg:postcode":"21044",
    "sg:province":"MD",
    "sg:tags":[
        "art",
        "gallery",
        "dealer"
    ],
    "wof:name":"Patagonia Art",
    "wof:placetype":"venue"
},
  "geometry": {"coordinates":[-76.858474,39.229268],"type":"Point"}
}