{
  "type": "Feature",
  "properties": {
    "iso:country":"US",
    "sg:address":"15207 Marlboro Pike",
    "sg:city":"Upper Marlboro",
    "sg:classifiers":[
        {
            "category":"Professional",
            "subcategory":"Accounting & Tax Preparation",
            "type":"Services"
        }
    ],
    "sg:phone":"+1 301 627 6567",
    "sg:postcode":"20772",
    "sg:province":"MD",
    "sg:tags":[
        "accountant"
    ],
    "wof:name":"Millard E Garbinsky",
    "wof:placetype":"venue"
},
  "geometry": {"coordinates":[-76.742203,38.822458],"type":"Point"}
}