{
  "type": "Feature",
  "properties": {
    "addr:full":"1925 Norfolk Dr Owings MD 20736",
    "addr:housenumber":"1925",
    "addr:postcode":"20736",
    "addr:street":"Norfolk Dr",
    "iso:country":"US",
    "sg:address":"1925 Norfolk Dr",
    "sg:city":"Owings",
    "sg:classifiers":[
        {
            "category":"Building & Trades",
            "subcategory":"Construction",
            "type":"Services"
        }
    ],
    "sg:phone":"+1 301 855 6512",
    "sg:postcode":"20736",
    "sg:province":"MD",
    "sg:tags":[
        "designer",
        "pool",
        "swimming"
    ],
    "sg:website":"http://www.stevensonpools.com",
    "wof:name":"Stevenson Pools",
    "wof:placetype":"venue"
},
  "geometry": {"coordinates":[-76.632671,38.682884],"type":"Point"}
}