{
  "type": "Feature",
  "properties": {
    "iso:country":"US",
    "sg:address":"2630 N Salisbury Blvd",
    "sg:city":"Salisbury",
    "sg:classifiers":[
        {
            "category":"Building & Trades",
            "subcategory":"Construction",
            "type":"Services"
        }
    ],
    "sg:phone":"+1 410 341 0099",
    "sg:postcode":"21801",
    "sg:province":"MD",
    "sg:tags":[
        "sun",
        "solarium",
        "rooms"
    ],
    "wof:name":"Country Sunrooms Of America",
    "wof:placetype":"venue"
},
  "geometry": {"coordinates":[-75.56773,38.411127],"type":"Point"}
}