{
  "type": "Feature",
  "properties": {
    "addr:full":"21 Homeland Rd Pasadena MD 21122",
    "addr:housenumber":"21",
    "addr:postcode":"21122",
    "addr:street":"Homeland Rd",
    "iso:country":"US",
    "sg:address":"21 Homeland Rd",
    "sg:city":"Pasadena",
    "sg:classifiers":[
        {
            "category":"Professional",
            "subcategory":"Management & Consulting",
            "type":"Services"
        },
        {
            "category":"Banks & Credit Unions",
            "subcategory":"Financial Services",
            "type":"Services"
        }
    ],
    "sg:phone":"+1 443 305 6039",
    "sg:postcode":"21122",
    "sg:province":"MD",
    "sg:tags":[
        "consultant",
        "financing",
        "planning",
        "card",
        "card-merchant"
    ],
    "sg:website":"http://www.americanexpress.com",
    "wof:name":"American Express Merchant Sales",
    "wof:placetype":"venue"
},
  "geometry": {"coordinates":[-76.52184099999999,39.160104],"type":"Point"}
}