{
  "type": "Feature",
  "properties": {
    "addr:full":"7005 Knighthood Ln Columbia MD 21045",
    "addr:housenumber":"7005",
    "addr:postcode":"21045",
    "addr:street":"Knighthood Ln",
    "iso:country":"US",
    "sg:address":"7005 Knighthood Ln",
    "sg:city":"Columbia",
    "sg:classifiers":[
        {
            "category":"Building & Trades",
            "subcategory":"Landscaping Services",
            "type":"Services"
        }
    ],
    "sg:phone":"+1 443 259 0421",
    "sg:postcode":"21045",
    "sg:province":"MD",
    "sg:tags":[
        "lawn"
    ],
    "wof:name":"Navill Landscaping",
    "wof:placetype":"venue"
},
  "geometry": {"coordinates":[-76.839251,39.192485],"type":"Point"}
}