{
  "type": "Feature",
  "properties": {
    "addr:full":"6535 N Charles St Towson MD 21204",
    "addr:housenumber":"6535",
    "addr:postcode":"21204",
    "addr:street":"N Charles St",
    "iso:country":"US",
    "sg:address":"6535 N Charles St",
    "sg:city":"Towson",
    "sg:classifiers":[
        {
            "category":"Health Services",
            "subcategory":"Doctor",
            "type":"Services"
        }
    ],
    "sg:phone":"+1 410 828 7417",
    "sg:postcode":"21204",
    "sg:province":"MD",
    "sg:tags":[
        "physician",
        "endocrinology",
        "surgeons",
        "surgeon",
        "metabolism",
        "diabetes"
    ],
    "wof:name":"Bay West Endocrinology Associates",
    "wof:placetype":"venue"
},
  "geometry": {"coordinates":[-76.624758,39.388323],"type":"Point"}
}