{
  "type": "Feature",
  "properties": {
    "addr:full":"301 Railroad Ave Mardela Springs MD 21837",
    "addr:housenumber":"301",
    "addr:postcode":"21837",
    "addr:street":"Railroad Ave",
    "iso:country":"US",
    "sg:address":"301 Railroad Ave",
    "sg:city":"Mardela Springs",
    "sg:classifiers":[
        {
            "category":"Government",
            "subcategory":"Post Office",
            "type":"Public Place"
        }
    ],
    "sg:phone":"+1 410 546 9050",
    "sg:postcode":"21837",
    "sg:province":"MD",
    "wof:name":"US Post Office",
    "wof:placetype":"venue"
},
  "geometry": {"coordinates":[-75.756298,38.461974],"type":"Point"}
}