{
  "type": "Feature",
  "properties": {
    "addr:full":"1100 Dual Hwy Hagerstown MD 21740",
    "addr:housenumber":"1100",
    "addr:postcode":"21740",
    "addr:street":"Dual Hwy",
    "iso:country":"US",
    "sg:address":"1100 Dual Hwy",
    "sg:city":"Hagerstown",
    "sg:classifiers":[
        {
            "category":"Real Estate",
            "subcategory":"Real Estate Services",
            "type":"Services"
        }
    ],
    "sg:phone":"+1 240 420 8301",
    "sg:postcode":"21740",
    "sg:province":"MD",
    "sg:tags":[
        "company",
        "title"
    ],
    "wof:name":"Fountainhead Title Group Inc",
    "wof:placetype":"venue"
},
  "geometry": {"coordinates":[-77.701329,39.63123],"type":"Point"}
}