{
  "type": "Feature",
  "properties": {
    "addr:full":"415 Crain Hwy S Glen Burnie MD 21061",
    "addr:housenumber":"415",
    "addr:postcode":"21061",
    "addr:street":"Crain Hwy S",
    "iso:country":"US",
    "sg:address":"415 Crain Hwy S",
    "sg:city":"Glen Burnie",
    "sg:classifiers":[
        {
            "category":"Health Services",
            "subcategory":"Doctor",
            "type":"Services"
        }
    ],
    "sg:phone":"+1 410 766 5056",
    "sg:postcode":"21061",
    "sg:province":"MD",
    "sg:tags":[
        "medical",
        "specialized",
        "cardiology"
    ],
    "wof:name":"Krishan K Singal MD Cardiology",
    "wof:placetype":"venue"
},
  "geometry": {"coordinates":[-76.629006,39.157646],"type":"Point"}
}