{
  "type": "Feature",
  "properties": {
    "iso:country":"US",
    "sg:address":"1203 Baltimore Blvd",
    "sg:city":"Westminster",
    "sg:classifiers":[
        {
            "category":"Autos & Motor Vehicles",
            "subcategory":"Auto Supplies",
            "type":"Retail Goods"
        }
    ],
    "sg:phone":"+1 410 871 0407",
    "sg:postcode":"21157",
    "sg:province":"MD",
    "sg:tags":[
        "equipment",
        "racing",
        "car",
        "automobile"
    ],
    "wof:name":"European Import Performance",
    "wof:placetype":"venue"
},
  "geometry": {"coordinates":[-76.956766,39.553639],"type":"Point"}
}