{
  "type": "Feature",
  "properties": {
    "iso:country":"US",
    "sg:address":"2205 Maryland Ave",
    "sg:city":"Baltimore",
    "sg:classifiers":[
        {
            "category":"Professional",
            "subcategory":"Secretarial Services",
            "type":"Services"
        }
    ],
    "sg:phone":"+1 410 889 3004",
    "sg:postcode":"21218",
    "sg:province":"MD",
    "sg:tags":[
        "convention",
        "court",
        "reporter"
    ],
    "wof:name":"County Court",
    "wof:placetype":"venue"
},
  "geometry": {"coordinates":[-76.61812,39.315164],"type":"Point"}
}