{
  "type": "Feature",
  "properties": {
    "addr:full":"15701 Columbia Pike Burtonsville MD 20866",
    "addr:housenumber":"15701",
    "addr:postcode":"20866",
    "addr:street":"Columbia Pike",
    "iso:country":"US",
    "sg:address":"15701 Columbia Pike",
    "sg:city":"Burtonsville",
    "sg:classifiers":[
        {
            "category":"Fast Food",
            "type":"Food & Drink"
        },
        {
            "category":"Restaurant",
            "type":"Food & Drink"
        }
    ],
    "sg:phone":"+1 301 421 4161",
    "sg:postcode":"20866",
    "sg:province":"MD",
    "sg:tags":[
        "chicken"
    ],
    "sg:website":"http://www.kfc.com",
    "wof:name":"Kfc",
    "wof:placetype":"venue"
},
  "geometry": {"coordinates":[-76.923401,39.12624],"type":"Point"}
}