{
  "type": "Feature",
  "properties": {
    "addr:full":"6200 Green Meadow Pkwy Baltimore MD 21209",
    "addr:housenumber":"6200",
    "addr:postcode":"21209",
    "addr:street":"Green Meadow Pkwy",
    "iso:country":"US",
    "sg:address":"6200 Green Meadow Pkwy",
    "sg:city":"Baltimore",
    "sg:classifiers":[
        {
            "category":"Professional",
            "type":"Services"
        }
    ],
    "sg:phone":"+1 410 358 8927",
    "sg:postcode":"21209",
    "sg:province":"MD",
    "sg:tags":[
        "establishment"
    ],
    "wof:name":"Multi-Ventures",
    "wof:placetype":"venue"
},
  "geometry": {"coordinates":[-76.67689,39.370476],"type":"Point"}
}