{
  "type": "Feature",
  "properties": {
    "iso:country":"US",
    "sg:address":"7 Church Ln",
    "sg:city":"Pikesville",
    "sg:classifiers":[
        {
            "category":"Communications",
            "type":"Services"
        }
    ],
    "sg:phone":"+1 410 602 9987",
    "sg:postcode":"21208",
    "sg:province":"MD",
    "wof:name":"Star Communications",
    "wof:placetype":"venue"
},
  "geometry": {"coordinates":[-76.724452,39.374899],"type":"Point"}
}