{
  "type": "Feature",
  "properties": {
    "addr:full":"6126 Ebenezer Rd Baltimore MD 21220",
    "addr:housenumber":"6126",
    "addr:postcode":"21220",
    "addr:street":"Ebenezer Rd",
    "iso:country":"US",
    "sg:address":"6126 Ebenezer Rd",
    "sg:city":"Baltimore",
    "sg:classifiers":[
        {
            "category":"Building & Trades",
            "subcategory":"Landscaping Services",
            "type":"Services"
        }
    ],
    "sg:phone":"+1 410 335 5905",
    "sg:postcode":"21220",
    "sg:province":"MD",
    "sg:tags":[
        "landscape"
    ],
    "wof:name":"S Wright Country Lawn Car",
    "wof:placetype":"venue"
},
  "geometry": {"coordinates":[-76.409966,39.371016],"type":"Point"}
}