{
  "type": "Feature",
  "properties": {
    "addr:full":"350 Carriage Ln Huntingtown MD 20639",
    "addr:housenumber":"350",
    "addr:postcode":"20639",
    "addr:street":"Carriage Ln",
    "iso:country":"US",
    "sg:address":"350 Carriage Ln",
    "sg:city":"Huntingtown",
    "sg:classifiers":[
        {
            "category":"Health Services",
            "subcategory":"Clinic",
            "type":"Services"
        }
    ],
    "sg:phone":"+1 301 855 9071",
    "sg:postcode":"20639",
    "sg:province":"MD",
    "wof:name":"Bowling Enterprises",
    "wof:placetype":"venue"
},
  "geometry": {"coordinates":[-76.614824,38.635262],"type":"Point"}
}