{
  "type": "Feature",
  "properties": {
    "iso:country":"US",
    "sg:address":"9554 Livingston Rd",
    "sg:city":"Fort Washington",
    "sg:classifiers":[
        {
            "category":"Shopping",
            "subcategory":"Department Store",
            "type":"Retail Goods"
        }
    ],
    "sg:phone":"+1 301 248 7792",
    "sg:postcode":"20744",
    "sg:province":"MD",
    "sg:tags":[
        "shop"
    ],
    "wof:name":"Dollar Tree",
    "wof:placetype":"venue"
},
  "geometry": {"coordinates":[-76.99537599999999,38.759361],"type":"Point"}
}