{
  "type": "Feature",
  "properties": {
    "iso:country":"US",
    "sg:address":"3440 Ellicott Center Dr",
    "sg:city":"Ellicott City",
    "sg:classifiers":[
        {
            "category":"Insurance",
            "subcategory":"Insurance Agent",
            "type":"Services"
        }
    ],
    "sg:phone":"+1 410 461 4896",
    "sg:postcode":"21043",
    "sg:province":"MD",
    "wof:name":"Donald L Meyer",
    "wof:placetype":"venue"
},
  "geometry": {"coordinates":[-76.814715,39.276828],"type":"Point"}
}