{
  "type": "Feature",
  "properties": {
    "addr:full":"8324 Woodyard Rd Clinton MD 20735",
    "addr:housenumber":"8324",
    "addr:postcode":"20735",
    "addr:street":"Woodyard Rd",
    "iso:country":"US",
    "sg:address":"8324 Woodyard Rd",
    "sg:city":"Clinton",
    "sg:classifiers":[
        {
            "category":"Organizations",
            "subcategory":"Religious Organization",
            "type":"Services"
        }
    ],
    "sg:phone":"+1 301 599 8351",
    "sg:postcode":"20735",
    "sg:province":"MD",
    "sg:tags":[
        "church"
    ],
    "wof:name":"New Horizon Baptist Church",
    "wof:placetype":"venue"
},
  "geometry": {"coordinates":[-76.869148,38.775572],"type":"Point"}
}