{
  "type": "Feature",
  "properties": {
    "iso:country":"US",
    "sg:address":"100 Lakeforest Blvd Ste 620",
    "sg:city":"Gaithersburg",
    "sg:classifiers":[
        {
            "category":"Health Services",
            "subcategory":"Dentist",
            "type":"Services"
        }
    ],
    "sg:phone":"+1 301 990 7778",
    "sg:postcode":"20877",
    "sg:province":"MD",
    "sg:website":"http://DSCreationBobMauri.intuitwebsites.com",
    "wof:name":"Lakeside Dental",
    "wof:placetype":"venue"
},
  "geometry": {"coordinates":[-77.208977,39.150188],"type":"Point"}
}