{
  "type": "Feature",
  "properties": {
    "addr:full":"4600 Millers Station Rd Hampstead MD 21074",
    "addr:housenumber":"4600",
    "addr:postcode":"21074",
    "addr:street":"Millers Station Rd",
    "iso:country":"US",
    "sg:address":"4600 Millers Station Rd",
    "sg:city":"Hampstead",
    "sg:classifiers":[
        {
            "category":"Home & Garden",
            "subcategory":"Garden Supply",
            "type":"Retail Goods"
        }
    ],
    "sg:phone":"+1 410 239 8525",
    "sg:postcode":"21074",
    "sg:province":"MD",
    "sg:tags":[
        "nurseryman"
    ],
    "wof:name":"King's Tree Farm",
    "wof:placetype":"venue"
},
  "geometry": {"coordinates":[-76.83025600000001,39.66284],"type":"Point"}
}