{
  "type": "Feature",
  "properties": {
    "iso:country":"US",
    "sg:address":"8215 Grey Eagle Dr",
    "sg:city":"Upper Marlboro",
    "sg:classifiers":[
        {
            "category":"Government",
            "subcategory":"Office",
            "type":"Public Place"
        },
        {
            "category":"Utilities",
            "subcategory":"Refuse",
            "type":"Services"
        }
    ],
    "sg:phone":"+1 301 669 1825",
    "sg:postcode":"20772",
    "sg:province":"MD",
    "sg:tags":[
        "management",
        "garbage",
        "collection"
    ],
    "wof:name":"Metro Waste Inc",
    "wof:placetype":"venue"
},
  "geometry": {"coordinates":[-76.864446,38.83422],"type":"Point"}
}