{
  "type": "Feature",
  "properties": {
    "iso:country":"US",
    "sg:address":"99A Hillside Rd",
    "sg:city":"Catonsville",
    "sg:classifiers":[
        {
            "category":"Banks & Credit Unions",
            "subcategory":"Financial Services",
            "type":"Services"
        }
    ],
    "sg:phone":"+1 410 744 2578",
    "sg:postcode":"21228",
    "sg:province":"MD",
    "sg:tags":[
        "information",
        "consumer"
    ],
    "wof:name":"Rlms Business Consultants",
    "wof:placetype":"venue"
},
  "geometry": {"coordinates":[-76.767105,39.264638],"type":"Point"}
}