{
  "type": "Feature",
  "properties": {
    "addr:full":"496 Ixworth Ct Severna Park MD 21146",
    "addr:housenumber":"496",
    "addr:postcode":"21146",
    "addr:street":"Ixworth Ct",
    "iso:country":"US",
    "sg:address":"496 Ixworth Ct",
    "sg:city":"Severna Park",
    "sg:classifiers":[
        {
            "category":"Retail",
            "subcategory":"Animal Services",
            "type":"Services"
        }
    ],
    "sg:phone":"+1 410 729 7333",
    "sg:postcode":"21146",
    "sg:province":"MD",
    "sg:tags":[
        "pet",
        "boarding",
        "sitting"
    ],
    "wof:name":"Pampered Pet Sitting",
    "wof:placetype":"venue"
},
  "geometry": {"coordinates":[-76.576072,39.088045],"type":"Point"}
}