{
  "type": "Feature",
  "properties": {
    "iso:country":"US",
    "sg:address":"6004 Greentree Rd",
    "sg:city":"Bethesda",
    "sg:classifiers":[
        {
            "category":"Professional",
            "subcategory":"Computer Services",
            "type":"Services"
        }
    ],
    "sg:phone":"+1 301 493 9606",
    "sg:postcode":"20817",
    "sg:province":"MD",
    "sg:tags":[
        "related"
    ],
    "wof:name":"Biagi Enterprises Inc",
    "wof:placetype":"venue"
},
  "geometry": {"coordinates":[-77.123146,39.001122],"type":"Point"}
}