{
  "type": "Feature",
  "properties": {
    "addr:full":"101 N Charles St Baltimore MD 21201",
    "addr:housenumber":"101",
    "addr:postcode":"21201",
    "addr:street":"N Charles St",
    "iso:country":"US",
    "sg:address":"101 N Charles St",
    "sg:city":"Baltimore",
    "sg:classifiers":[
        {
            "category":"Travel",
            "subcategory":"Hotels & Motels",
            "type":"Entertainment"
        }
    ],
    "sg:phone":"+1 410 400 8980",
    "sg:postcode":"21201",
    "sg:province":"MD",
    "sg:website":"www.staybridgesuites.com",
    "wof:name":"Staybridge Suites",
    "wof:placetype":"venue"
},
  "geometry": {"coordinates":[-76.615054,39.290392],"type":"Point"}
}