{
  "type": "Feature",
  "properties": {
    "addr:full":"6109 Tilden Ln North Bethesda MD 20852",
    "addr:housenumber":"6109",
    "addr:postcode":"20852",
    "addr:street":"Tilden Ln",
    "iso:country":"US",
    "sg:address":"6109 Tilden Ln",
    "sg:city":"North Bethesda",
    "sg:classifiers":[
        {
            "category":"Building & Trades",
            "subcategory":"Construction",
            "type":"Services"
        }
    ],
    "sg:phone":"+1 301 468 7366",
    "sg:postcode":"20852",
    "sg:province":"MD",
    "sg:tags":[
        "general",
        "contractor"
    ],
    "wof:name":"Ams Home Improvement",
    "wof:placetype":"venue"
},
  "geometry": {"coordinates":[-77.125345,39.044411],"type":"Point"}
}