{
  "type": "Feature",
  "properties": {
    "addr:full":"7600 Harford Rd Parkville MD 21234",
    "addr:housenumber":"7600",
    "addr:postcode":"21234",
    "addr:street":"Harford Rd",
    "iso:country":"US",
    "sg:address":"7600 Harford Rd",
    "sg:city":"Parkville",
    "sg:classifiers":[
        {
            "category":"Retail",
            "subcategory":"Auto Repair",
            "type":"Services"
        }
    ],
    "sg:phone":"+1 410 665 2072",
    "sg:postcode":"21234",
    "sg:province":"MD",
    "sg:tags":[
        "repairing",
        "automobile"
    ],
    "wof:name":"Bob Parks Carney Svc Ctr",
    "wof:placetype":"venue"
},
  "geometry": {"coordinates":[-76.544003,39.372468],"type":"Point"}
}