{
  "type": "Feature",
  "properties": {
    "addr:full":"9001 River Rd Potomac MD 20854",
    "addr:housenumber":"9001",
    "addr:postcode":"20854",
    "addr:street":"River Rd",
    "iso:country":"US",
    "sg:address":"9001 River Rd",
    "sg:city":"Potomac",
    "sg:classifiers":[
        {
            "category":"Health Services",
            "subcategory":"Doctor",
            "type":"Services"
        }
    ],
    "sg:phone":"+1 301 469 6543",
    "sg:postcode":"20854",
    "sg:province":"MD",
    "sg:tags":[
        "surgeon",
        "oral"
    ],
    "wof:name":"Heffelfinger Thomas B Jr DDS",
    "wof:placetype":"venue"
},
  "geometry": {"coordinates":[-77.181,39.001999],"type":"Point"}
}