{
  "type": "Feature",
  "properties": {
    "addr:full":"39 Broadway Hagerstown MD 21740",
    "addr:housenumber":"39",
    "addr:postcode":"21740",
    "addr:street":"Broadway",
    "iso:country":"US",
    "sg:address":"39 Broadway",
    "sg:city":"Hagerstown",
    "sg:classifiers":[
        {
            "category":"Building & Trades",
            "subcategory":"Cleaning & Sanitation",
            "type":"Services"
        }
    ],
    "sg:phone":"+1 301 293 1552",
    "sg:postcode":"21740",
    "sg:province":"MD",
    "sg:tags":[
        "house"
    ],
    "wof:name":"A-1 Quality Carpet Cleaning",
    "wof:placetype":"venue"
},
  "geometry": {"coordinates":[-77.713232,39.647232],"type":"Point"}
}