{
  "type": "Feature",
  "properties": {
    "addr:full":"4120 Norbeck Rd Rockville MD 20853",
    "addr:housenumber":"4120",
    "addr:postcode":"20853",
    "addr:street":"Norbeck Rd",
    "iso:country":"US",
    "sg:address":"4120 Norbeck Rd",
    "sg:city":"Rockville",
    "sg:classifiers":[
        {
            "category":"Professional",
            "subcategory":"Lawyer & Legal Services",
            "type":"Services"
        }
    ],
    "sg:phone":"+1 301 929 9124",
    "sg:postcode":"20853",
    "sg:province":"MD",
    "sg:tags":[
        "attorney"
    ],
    "wof:name":"Bernetich Group",
    "wof:placetype":"venue"
},
  "geometry": {"coordinates":[-77.08413,39.106696],"type":"Point"}
}