{
  "type": "Feature",
  "properties": {
    "addr:full":"10132 Fontaine Dr Baltimore MD 21234",
    "addr:housenumber":"10132",
    "addr:postcode":"21234",
    "addr:street":"Fontaine Dr",
    "iso:country":"US",
    "sg:address":"10132 Fontaine Dr",
    "sg:city":"Baltimore",
    "sg:classifiers":[
        {
            "category":"Building & Trades",
            "subcategory":"Electrical",
            "type":"Services"
        }
    ],
    "sg:phone":"+1 410 529 9321",
    "sg:postcode":"21234",
    "sg:province":"MD",
    "sg:tags":[
        "electrical",
        "contractor"
    ],
    "wof:name":"Jra",
    "wof:placetype":"venue"
},
  "geometry": {"coordinates":[-76.495771,39.409928],"type":"Point"}
}