{
  "type": "Feature",
  "properties": {
    "addr:full":"7940 Edgewood Farm Rd Frederick MD 21702",
    "addr:housenumber":"7940",
    "addr:postcode":"21702",
    "addr:street":"Edgewood Farm Rd",
    "iso:country":"US",
    "sg:address":"7940 Edgewood Farm Rd",
    "sg:city":"Frederick",
    "sg:classifiers":[
        {
            "category":"Professional",
            "subcategory":"Business Services",
            "type":"Services"
        }
    ],
    "sg:phone":"+1 301 694 8347",
    "sg:postcode":"21702",
    "sg:province":"MD",
    "wof:name":"R & S Associates Inc",
    "wof:placetype":"venue"
},
  "geometry": {"coordinates":[-77.425214,39.45195],"type":"Point"}
}