{
  "type": "Feature",
  "properties": {
    "iso:country":"US",
    "sg:address":"3207 Corporate Ct",
    "sg:city":"Ellicott City",
    "sg:classifiers":[
        {
            "category":"Shopping",
            "subcategory":"Stationery & Office Supplies",
            "type":"Retail Goods"
        }
    ],
    "sg:phone":"+1 410 750 7041",
    "sg:postcode":"21042",
    "sg:province":"MD",
    "wof:name":"Alex-Doherty Marketing Assoc",
    "wof:placetype":"venue"
},
  "geometry": {"coordinates":[-76.862239,39.281999],"type":"Point"}
}