{
  "type": "Feature",
  "properties": {
    "iso:country":"US",
    "sg:address":"13544 Travilah Rd",
    "sg:city":"North Potomac",
    "sg:classifiers":[
        {
            "category":"Building & Trades",
            "subcategory":"Construction",
            "type":"Services"
        }
    ],
    "sg:phone":"+1 301 869 0477",
    "sg:postcode":"20878",
    "sg:province":"MD",
    "sg:tags":[
        "roofing",
        "contractor"
    ],
    "wof:name":"Bateman Exteriors",
    "wof:placetype":"venue"
},
  "geometry": {"coordinates":[-77.251057,39.080725],"type":"Point"}
}