{
  "type": "Feature",
  "properties": {
    "addr:full":"1400 Hull St Baltimore MD 21230",
    "addr:housenumber":"1400",
    "addr:postcode":"21230",
    "addr:street":"Hull St",
    "iso:country":"US",
    "sg:address":"1400 Hull St",
    "sg:city":"Baltimore",
    "sg:classifiers":[
        {
            "category":"Bars & Pubs",
            "type":"Food & Drink"
        }
    ],
    "sg:phone":"+1 410 752 5471",
    "sg:postcode":"21230",
    "sg:province":"MD",
    "wof:name":"Oakes Brothers",
    "wof:placetype":"venue"
},
  "geometry": {"coordinates":[-76.593755,39.269024],"type":"Point"}
}