{
  "type": "Feature",
  "properties": {
    "addr:full":"612 Suffield Dr Gaithersburg MD 20878",
    "addr:housenumber":"612",
    "addr:postcode":"20878",
    "addr:street":"Suffield Dr",
    "iso:country":"US",
    "sg:address":"612 Suffield Dr",
    "sg:city":"Gaithersburg",
    "sg:classifiers":[
        {
            "category":"Wholesale",
            "subcategory":"Farm Supplies",
            "type":"Manufacturing & Wholesale Goods"
        }
    ],
    "sg:phone":"+1 301 770 0841",
    "sg:postcode":"20878",
    "sg:province":"MD",
    "sg:tags":[
        "leather",
        "oil"
    ],
    "wof:name":"Behive Overseas Ltd",
    "wof:placetype":"venue"
},
  "geometry": {"coordinates":[-77.219247,39.114279],"type":"Point"}
}