{
  "type": "Feature",
  "properties": {
    "addr:full":"7811 Ruark Ln Westover MD 21871",
    "addr:housenumber":"7811",
    "addr:postcode":"21871",
    "addr:street":"Ruark Ln",
    "iso:country":"US",
    "sg:address":"7811 Ruark Ln",
    "sg:city":"Westover",
    "sg:classifiers":[
        {
            "category":"Banks & Credit Unions",
            "subcategory":"Investment Brokerage",
            "type":"Services"
        }
    ],
    "sg:phone":"+1 410 651 1832",
    "sg:postcode":"21871",
    "sg:province":"MD",
    "sg:tags":[
        "advisory"
    ],
    "wof:name":"Heritage Investments",
    "wof:placetype":"venue"
},
  "geometry": {"coordinates":[-75.70218199999999,38.096463],"type":"Point"}
}