{
  "type": "Feature",
  "properties": {
    "iso:country":"US",
    "sg:address":"23164 Thawley Rd",
    "sg:city":"Denton",
    "sg:phone":"+1 410 479 0872",
    "sg:postcode":"21629",
    "sg:province":"MD",
    "sg:tags":[
        "farm",
        "wheat"
    ],
    "wof:name":"Oliver Smith",
    "wof:placetype":"venue"
},
  "geometry": {"coordinates":[-75.89564,38.885235],"type":"Point"}
}