{
  "type": "Feature",
  "properties": {
    "addr:full":"3372 N Chatham Rd Ellicott City MD 21042",
    "addr:housenumber":"3372",
    "addr:postcode":"21042",
    "addr:street":"N Chatham Rd",
    "iso:country":"US",
    "sg:address":"3372 N Chatham Rd",
    "sg:city":"Ellicott City",
    "sg:classifiers":[
        {
            "category":"Professional",
            "subcategory":"Management & Consulting",
            "type":"Services"
        },
        {
            "category":"Building & Trades",
            "subcategory":"Plumbing",
            "type":"Services"
        }
    ],
    "sg:phone":"+1 410 461 2420",
    "sg:postcode":"21042",
    "sg:province":"MD",
    "sg:tags":[
        "product",
        "energy",
        "system",
        "design",
        "maintenance",
        "commissioning"
    ],
    "wof:name":"Premier Energy Services LLC",
    "wof:placetype":"venue"
},
  "geometry": {"coordinates":[-76.832157,39.278699],"type":"Point"}
}