{
  "type": "Feature",
  "properties": {
    "addr:full":"2913 McGee Way Olney MD 20832",
    "addr:housenumber":"2913",
    "addr:postcode":"20832",
    "addr:street":"Mcgee Way",
    "iso:country":"US",
    "sg:address":"2913 McGee Way",
    "sg:city":"Olney",
    "sg:classifiers":[
        {
            "category":"Professional",
            "subcategory":"Management & Consulting",
            "type":"Services"
        }
    ],
    "sg:phone":"+1 301 570 0613",
    "sg:postcode":"20832",
    "sg:province":"MD",
    "sg:tags":[
        "retail",
        "direct",
        "sales"
    ],
    "wof:name":"Dawn E Mmon Avon Rpresentative",
    "wof:placetype":"venue"
},
  "geometry": {"coordinates":[-77.05995799999999,39.152314],"type":"Point"}
}