{
  "type": "Feature",
  "properties": {
    "iso:country":"US",
    "sg:address":"7605 Honeywell Ln",
    "sg:city":"Bethesda",
    "sg:classifiers":[
        {
            "category":"Real Estate",
            "subcategory":"Real Estate Agent",
            "type":"Services"
        }
    ],
    "sg:phone":"+1 301 961 5715",
    "sg:postcode":"20814",
    "sg:province":"MD",
    "wof:name":"Potomac Homes Realty Co",
    "wof:placetype":"venue"
},
  "geometry": {"coordinates":[-77.11212,38.986858],"type":"Point"}
}