{
  "type": "Feature",
  "properties": {
    "iso:country":"US",
    "sg:address":"8 Tyler Falls Ct",
    "sg:city":"Baltimore",
    "sg:classifiers":[
        {
            "category":"Professional",
            "subcategory":"Management & Consulting",
            "type":"Services"
        }
    ],
    "sg:phone":"+1 410 252 6404",
    "sg:postcode":"21209",
    "sg:province":"MD",
    "sg:tags":[
        "consultant"
    ],
    "wof:name":"Llewellyn F Helper",
    "wof:placetype":"venue"
},
  "geometry": {"coordinates":[-76.670441,39.381185],"type":"Point"}
}