{
  "type": "Feature",
  "properties": {
    "addr:full":"302 S Seton Ave Emmitsburg MD 21727",
    "addr:housenumber":"302",
    "addr:postcode":"21727",
    "addr:street":"S Seton Ave",
    "iso:country":"US",
    "sg:address":"302 S Seton Ave",
    "sg:city":"Emmitsburg",
    "sg:classifiers":[
        {
            "category":"Manufacturing",
            "subcategory":"Buildings",
            "type":"Manufacturing & Wholesale Goods"
        },
        {
            "category":"Building & Trades",
            "subcategory":"Construction",
            "type":"Services"
        }
    ],
    "sg:phone":"+1 301 447 1922",
    "sg:postcode":"21727",
    "sg:province":"MD",
    "sg:tags":[
        "home",
        "builder",
        "contractor"
    ],
    "wof:name":"Apple Tree Homes Inc Southgate",
    "wof:placetype":"venue"
},
  "geometry": {"coordinates":[-77.328346,39.70105],"type":"Point"}
}