{
  "type": "Feature",
  "properties": {
    "addr:full":"12811 Doe Ln Gaithersburg MD 20878",
    "addr:housenumber":"12811",
    "addr:postcode":"20878",
    "addr:street":"Doe Ln",
    "iso:country":"US",
    "sg:address":"12811 Doe Ln",
    "sg:city":"Gaithersburg",
    "sg:classifiers":[
        {
            "category":"Shopping",
            "subcategory":"Computers & Home Electronics",
            "type":"Retail Goods"
        }
    ],
    "sg:phone":"+1 301 990 9797",
    "sg:postcode":"20878",
    "sg:province":"MD",
    "sg:tags":[
        "software"
    ],
    "wof:name":"LCC",
    "wof:placetype":"venue"
},
  "geometry": {"coordinates":[-77.271338,39.099677],"type":"Point"}
}