{
  "type": "Feature",
  "properties": {
    "addr:full":"1501 Court Plaza Ln # 27 Salisbury MD 21801",
    "addr:housenumber":"1501;27",
    "addr:postcode":"21801",
    "addr:street":"Court Plaza Ln #",
    "iso:country":"US",
    "sg:address":"1501 Court Plaza Ln # 27",
    "sg:city":"Salisbury",
    "sg:classifiers":[
        {
            "category":"Professional",
            "subcategory":"Engineering",
            "type":"Services"
        },
        {
            "category":"Internet Cafe",
            "subcategory":"None",
            "type":"Food & Drink"
        },
        {
            "category":"Professional",
            "subcategory":"Computer Services",
            "type":"Services"
        }
    ],
    "sg:phone":"+1 410 548 3901",
    "sg:postcode":"21801",
    "sg:province":"MD",
    "sg:tags":[
        "product",
        "designer",
        "consultant",
        "system",
        "integration",
        "software",
        "engineer"
    ],
    "sg:website":"http://www.ideas-net.com",
    "wof:name":"I.D.E.A.S.",
    "wof:placetype":"venue"
},
  "geometry": {"coordinates":[-75.608994,38.33934],"type":"Point"}
}