{
  "type": "Feature",
  "properties": {
    "iso:country":"US",
    "sg:address":"118 S Main St",
    "sg:city":"Bel Air",
    "sg:classifiers":[
        {
            "category":"Shopping",
            "subcategory":"Books",
            "type":"Retail Goods"
        }
    ],
    "sg:phone":"+1 410 836 0206",
    "sg:postcode":"21014",
    "sg:province":"MD",
    "sg:tags":[
        "dealer"
    ],
    "wof:name":"Christian Outlet",
    "wof:placetype":"venue"
},
  "geometry": {"coordinates":[-76.34772,39.534899],"type":"Point"}
}