{
  "type": "Feature",
  "properties": {
    "addr:full":"2840 Old Washington Rd Waldorf MD 20601",
    "addr:housenumber":"2840",
    "addr:postcode":"20601",
    "addr:street":"Old Washington Rd",
    "iso:country":"US",
    "sg:address":"2840 Old Washington Rd",
    "sg:city":"Waldorf",
    "sg:classifiers":[
        {
            "category":"Wholesale",
            "subcategory":"Beer",
            "type":"Manufacturing & Wholesale Goods"
        }
    ],
    "sg:phone":"+1 301 645 5513",
    "sg:postcode":"20601",
    "sg:province":"MD",
    "sg:tags":[
        "ale"
    ],
    "wof:name":"Bozick Distributors Inc",
    "wof:placetype":"venue"
},
  "geometry": {"coordinates":[-76.90175499999999,38.631167],"type":"Point"}
}