{
  "type": "Feature",
  "properties": {
    "addr:full":"1144 Smallwood Dr W Waldorf MD 20603",
    "addr:housenumber":"1144",
    "addr:postcode":"20603",
    "addr:street":"Smallwood Dr W",
    "iso:country":"US",
    "sg:address":"1144 Smallwood Dr W",
    "sg:city":"Waldorf",
    "sg:classifiers":[
        {
            "category":"Shopping",
            "subcategory":"Pharmacy",
            "type":"Retail Goods"
        }
    ],
    "sg:phone":"+1 301 645 8234",
    "sg:postcode":"20603",
    "sg:province":"MD",
    "sg:website":"www.cvs.com",
    "wof:name":"CVS Pharmacy",
    "wof:placetype":"venue"
},
  "geometry": {"coordinates":[-76.925967,38.611998],"type":"Point"}
}