{
  "type": "Feature",
  "properties": {
    "addr:full":"14746 Main St Upper Marlboro MD 20772",
    "addr:housenumber":"14746",
    "addr:postcode":"20772",
    "addr:street":"Main St",
    "iso:country":"US",
    "sg:address":"14746 Main St",
    "sg:city":"Upper Marlboro",
    "sg:classifiers":[
        {
            "category":"Real Estate",
            "subcategory":"Real Estate Agent",
            "type":"Services"
        }
    ],
    "sg:phone":"+1 301 627 0405",
    "sg:postcode":"20772",
    "sg:province":"MD",
    "sg:tags":[
        "consultant"
    ],
    "wof:name":"Swetnam Real Estate Svc",
    "wof:placetype":"venue"
},
  "geometry": {"coordinates":[-76.75135899999999,38.816469],"type":"Point"}
}