{
  "type": "Feature",
  "properties": {
    "addr:full":"9337 Baltimore National Pike Baltimore MD 21201",
    "addr:housenumber":"9337",
    "addr:postcode":"21201",
    "addr:street":"Baltimore National Pike",
    "iso:country":"US",
    "sg:address":"9337 Baltimore National Pike",
    "sg:city":"Baltimore",
    "sg:classifiers":[
        {
            "category":"Banks & Credit Unions",
            "subcategory":"Bank",
            "type":"Services"
        }
    ],
    "sg:phone":"+1 410 281 7037",
    "sg:postcode":"21201",
    "sg:province":"MD",
    "wof:name":"Provident Bank",
    "wof:placetype":"venue"
},
  "geometry": {"coordinates":[-76.833457,39.277399],"type":"Point"}
}