{
  "type": "Feature",
  "properties": {
    "iso:country":"US",
    "sg:address":"15 Boone Trl",
    "sg:city":"Severna Park",
    "sg:classifiers":[
        {
            "category":"Farming",
            "subcategory":"Farm & Veterinary Services",
            "type":"Manufacturing & Wholesale Goods"
        }
    ],
    "sg:phone":"+1 410 647 5453",
    "sg:postcode":"21146",
    "sg:province":"MD",
    "sg:tags":[
        "livestock"
    ],
    "wof:name":"Flexible Flyers Aviary",
    "wof:placetype":"venue"
},
  "geometry": {"coordinates":[-76.55410999999999,39.064645],"type":"Point"}
}