{
  "type": "Feature",
  "properties": {
    "iso:country":"US",
    "sg:address":"1014 W 36th St",
    "sg:city":"Baltimore",
    "sg:classifiers":[
        {
            "category":"Professional",
            "subcategory":"Advertising",
            "type":"Services"
        }
    ],
    "sg:phone":"+1 410 889 0990",
    "sg:postcode":"21211",
    "sg:province":"MD",
    "sg:tags":[
        "counselor"
    ],
    "sg:website":"www.gilden.com",
    "wof:name":"Gilden Advertising",
    "wof:placetype":"venue"
},
  "geometry": {"coordinates":[-76.63369,39.331151],"type":"Point"}
}