{
  "type": "Feature",
  "properties": {
    "addr:full":"4505 Great Oak Rd Rockville MD 20853",
    "addr:housenumber":"4505",
    "addr:postcode":"20853",
    "addr:street":"Great Oak Rd",
    "iso:country":"US",
    "sg:address":"4505 Great Oak Rd",
    "sg:city":"Rockville",
    "sg:classifiers":[
        {
            "category":"Wholesale",
            "subcategory":"Computers",
            "type":"Manufacturing & Wholesale Goods"
        }
    ],
    "sg:phone":"+1 301 871 6808",
    "sg:postcode":"20853",
    "sg:province":"MD",
    "wof:name":"Osa",
    "wof:placetype":"venue"
},
  "geometry": {"coordinates":[-77.088825,39.10196],"type":"Point"}
}