{
  "type": "Feature",
  "properties": {
    "iso:country":"US",
    "sg:address":"228 Reisterstown Rd",
    "sg:city":"Pikesville",
    "sg:classifiers":[
        {
            "category":"Personal",
            "subcategory":"Beauty Salon",
            "type":"Services"
        },
        {
            "category":"Personal",
            "subcategory":"Day Spa",
            "type":"Services"
        }
    ],
    "sg:phone":"+1 410 484 8560",
    "sg:postcode":"21208",
    "sg:province":"MD",
    "sg:website":"www.saloncouture.org",
    "wof:name":"Salon Couture",
    "wof:placetype":"venue"
},
  "geometry": {"coordinates":[-76.7148,39.365669],"type":"Point"}
}