{
  "type": "Feature",
  "properties": {
    "addr:full":"2007 Tidewater Colony Way Annapolis MD 21401",
    "addr:housenumber":"2007",
    "addr:postcode":"21401",
    "addr:street":"Tidewater Colony Way",
    "iso:country":"US",
    "sg:address":"2007 Tidewater Colony Way",
    "sg:city":"Annapolis",
    "sg:classifiers":[
        {
            "category":"Professional",
            "subcategory":"Accounting & Tax Preparation",
            "type":"Services"
        }
    ],
    "sg:phone":"+1 410 224 3257",
    "sg:postcode":"21401",
    "sg:province":"MD",
    "sg:tags":[
        "accountant"
    ],
    "wof:name":"Robert D Hauck LLC",
    "wof:placetype":"venue"
},
  "geometry": {"coordinates":[-76.521435,38.996686],"type":"Point"}
}