{
  "type": "Feature",
  "properties": {
    "iso:country":"US",
    "sg:address":"8718 Leonard Dr",
    "sg:city":"Silver Spring",
    "sg:classifiers":[
        {
            "category":"Manufacturing",
            "subcategory":"Food",
            "type":"Manufacturing & Wholesale Goods"
        }
    ],
    "sg:phone":"+1 301 565 2005",
    "sg:postcode":"20910",
    "sg:province":"MD",
    "sg:tags":[
        "product",
        "mfg"
    ],
    "wof:name":"Mfg Associates",
    "wof:placetype":"venue"
},
  "geometry": {"coordinates":[-77.043694,38.999294],"type":"Point"}
}