{
  "type": "Feature",
  "properties": {
    "addr:full":"3 Church Cir Annapolis MD 21401",
    "addr:housenumber":"3",
    "addr:postcode":"21401",
    "addr:street":"Church Cir",
    "iso:country":"US",
    "sg:address":"3 Church Cir",
    "sg:city":"Annapolis",
    "sg:classifiers":[
        {
            "category":"Professional",
            "subcategory":"Business Services",
            "type":"Services"
        }
    ],
    "sg:phone":"+1 410 268 0584",
    "sg:postcode":"21401",
    "sg:province":"MD",
    "sg:tags":[
        "engineering",
        "drafting",
        "graphics"
    ],
    "wof:name":"Freelance Drafting Service",
    "wof:placetype":"venue"
},
  "geometry": {"coordinates":[-76.493274,38.978722],"type":"Point"}
}