{
  "type": "Feature",
  "properties": {
    "addr:full":"9812 Falls Rd Ste 201 Potomac MD 20854",
    "addr:housenumber":"9812",
    "addr:postcode":"20854",
    "addr:street":"Falls Rd Ste 201",
    "iso:country":"US",
    "sg:address":"9812 Falls Rd Ste 201",
    "sg:city":"Potomac",
    "sg:classifiers":[
        {
            "category":"Real Estate",
            "subcategory":"Real Estate Services",
            "type":"Services"
        },
        {
            "category":"Shopping Center",
            "type":"Public Place"
        }
    ],
    "sg:phone":"+1 301 983 9800",
    "sg:postcode":"20854",
    "sg:province":"MD",
    "sg:tags":[
        "mall",
        "management"
    ],
    "sg:website":"http://www.potomacpromenade.com",
    "wof:name":"Potomac Promenade Inc",
    "wof:placetype":"venue"
},
  "geometry": {"coordinates":[-77.211302,39.016417],"type":"Point"}
}