{
  "type": "Feature",
  "properties": {
    "addr:full":"1307 S Potomac St Hagerstown MD 21740",
    "addr:housenumber":"1307",
    "addr:postcode":"21740",
    "addr:street":"S Potomac St",
    "iso:country":"US",
    "sg:address":"1307 S Potomac St",
    "sg:city":"Hagerstown",
    "sg:classifiers":[
        {
            "category":"Building & Trades",
            "subcategory":"Construction",
            "type":"Services"
        }
    ],
    "sg:phone":"+1 240 313 2700",
    "sg:postcode":"21740",
    "sg:province":"MD",
    "sg:tags":[
        "grading",
        "contractor"
    ],
    "wof:name":"Washington County Public Works",
    "wof:placetype":"venue"
},
  "geometry": {"coordinates":[-77.730818,39.614451],"type":"Point"}
}