{
  "type": "Feature",
  "properties": {
    "iso:country":"US",
    "sg:address":"11130 Rockville Pike",
    "sg:city":"Rockville",
    "sg:classifiers":[
        {
            "category":"Retail",
            "subcategory":"Laundry & Dry Cleaning",
            "type":"Services"
        }
    ],
    "sg:phone":"+1 301 881 7411",
    "sg:postcode":"20852",
    "sg:province":"MD",
    "sg:tags":[
        "cleaner"
    ],
    "sg:website":"www.drycleanexpo.com",
    "wof:name":"Dry Clean Expo",
    "wof:placetype":"venue"
},
  "geometry": {"coordinates":[-77.10917600000001,39.039313],"type":"Point"}
}