{
  "type": "Feature",
  "properties": {
    "iso:country":"US",
    "sg:address":"8633 Cherry Ln",
    "sg:city":"Laurel",
    "sg:classifiers":[
        {
            "category":"Banks & Credit Unions",
            "subcategory":"Bank",
            "type":"Services"
        }
    ],
    "sg:phone":"+1 301 317 1250",
    "sg:postcode":"20707",
    "sg:province":"MD",
    "sg:tags":[
        "loan",
        "real estate"
    ],
    "wof:name":"Southern Star Mortgage Corp",
    "wof:placetype":"venue"
},
  "geometry": {"coordinates":[-76.856151,39.090907],"type":"Point"}
}