{
  "type": "Feature",
  "properties": {
    "iso:country":"US",
    "sg:address":"2713 N Point Rd",
    "sg:city":"Baltimore",
    "sg:classifiers":[
        {
            "category":"Restaurant",
            "type":"Food & Drink"
        }
    ],
    "sg:phone":"+1 410 284 9770",
    "sg:postcode":"21222",
    "sg:province":"MD",
    "wof:name":"Papa Leone's Spaghetti House",
    "wof:placetype":"venue"
},
  "geometry": {"coordinates":[-76.489956,39.279389],"type":"Point"}
}