{
  "type": "Feature",
  "properties": {
    "iso:country":"US",
    "sg:address":"18930 Bonanza Way",
    "sg:city":"Gaithersburg",
    "sg:classifiers":[
        {
            "category":"Home & Garden",
            "subcategory":"Furniture",
            "type":"Retail Goods"
        }
    ],
    "sg:phone":"+1 301 208 0401",
    "sg:postcode":"20879",
    "sg:province":"MD",
    "wof:name":"Fishermans Furniture",
    "wof:placetype":"venue"
},
  "geometry": {"coordinates":[-77.170861,39.166528],"type":"Point"}
}