{
  "type": "Feature",
  "properties": {
    "iso:country":"US",
    "sg:address":"9070 Maier Rd",
    "sg:city":"Laurel",
    "sg:classifiers":[
        {
            "category":"Wholesale",
            "subcategory":"Auto Parts",
            "type":"Manufacturing & Wholesale Goods"
        }
    ],
    "sg:phone":"+1 301 776 4110",
    "sg:postcode":"20723",
    "sg:province":"MD",
    "sg:tags":[
        "automobile",
        "supply"
    ],
    "wof:name":"Mighty Auto Parts",
    "wof:placetype":"venue"
},
  "geometry": {"coordinates":[-76.824355,39.119839],"type":"Point"}
}