{
  "type": "Feature",
  "properties": {
    "iso:country":"US",
    "sg:address":"5 Choke Cherry Rd",
    "sg:city":"Rockville",
    "sg:classifiers":[
        {
            "category":"Banks & Credit Unions",
            "subcategory":"Bank",
            "type":"Services"
        }
    ],
    "sg:phone":"+1 301 258 8802",
    "sg:postcode":"20850",
    "sg:province":"MD",
    "sg:tags":[
        "broker",
        "mortgage"
    ],
    "wof:name":"Excel Mortgage & Inv Svcs",
    "wof:placetype":"venue"
},
  "geometry": {"coordinates":[-77.185704,39.114476],"type":"Point"}
}