{
  "type": "Feature",
  "properties": {
    "addr:full":"9509 Livingston Rd Fort Washington MD 20744",
    "addr:housenumber":"9509",
    "addr:postcode":"20744",
    "addr:street":"Livingston Rd",
    "iso:country":"US",
    "sg:address":"9509 Livingston Rd",
    "sg:city":"Fort Washington",
    "sg:classifiers":[
        {
            "category":"Restaurant",
            "type":"Food & Drink"
        }
    ],
    "sg:menulink":"http://www.allmenus.com/md/piscataway/67379-dominos-pizza/menu/",
    "sg:phone":"+1 301 248 3030",
    "sg:postcode":"20744",
    "sg:province":"MD",
    "sg:tags":[
        "american",
        "wing",
        "pizza"
    ],
    "wof:name":"Domino's Pizza",
    "wof:placetype":"venue"
},
  "geometry": {"coordinates":[-76.995701,38.758726],"type":"Point"}
}