{
  "type": "Feature",
  "properties": {
    "addr:full":"14201 Laurel Park Dr # 107 Laurel MD 20707",
    "addr:housenumber":"14201;107",
    "addr:postcode":"20707",
    "addr:street":"Laurel Park Dr #",
    "iso:country":"US",
    "sg:address":"14201 Laurel Park Dr # 107",
    "sg:city":"Laurel",
    "sg:classifiers":[
        {
            "category":"Health Services",
            "subcategory":"Medical Lab",
            "type":"Services"
        }
    ],
    "sg:phone":"+1 301 490 9444",
    "sg:postcode":"20707",
    "sg:province":"MD",
    "sg:tags":[
        "laboratories-pathological",
        "laboratory"
    ],
    "sg:website":"http://www.questdiagnostics.com",
    "wof:name":"Quest Diagnostics",
    "wof:placetype":"venue"
},
  "geometry": {"coordinates":[-76.878693,39.084438],"type":"Point"}
}