{
  "type": "Feature",
  "properties": {
    "addr:full":"3715 Eastern Ave Baltimore MD 21224",
    "addr:housenumber":"3715",
    "addr:postcode":"21224",
    "addr:street":"Eastern Ave",
    "iso:country":"US",
    "sg:address":"3715 Eastern Ave",
    "sg:city":"Baltimore",
    "sg:classifiers":[
        {
            "category":"Health Services",
            "subcategory":"Dentist",
            "type":"Services"
        }
    ],
    "sg:phone":"+1 410 327 5488",
    "sg:postcode":"21224",
    "sg:province":"MD",
    "sg:website":"gen.dentistry",
    "wof:name":"An Eastern Family Dental Center",
    "wof:placetype":"venue"
},
  "geometry": {"coordinates":[-76.56590300000001,39.2868],"type":"Point"}
}