{
  "type": "Feature",
  "properties": {
    "iso:country":"US",
    "sg:address":"12835 Salem Ave",
    "sg:city":"Hagerstown",
    "sg:classifiers":[
        {
            "category":"Autos & Motor Vehicles",
            "subcategory":"Automobile Sales",
            "type":"Retail Goods"
        }
    ],
    "sg:phone":"+1 301 790 2200",
    "sg:postcode":"21740",
    "sg:province":"MD",
    "sg:tags":[
        "truck"
    ],
    "sg:website":"www.grimestruckcenter.com",
    "wof:name":"Grimes Truck Ctr",
    "wof:placetype":"venue"
},
  "geometry": {"coordinates":[-77.742349,39.665747],"type":"Point"}
}