{
  "type": "Feature",
  "properties": {
    "addr:full":"10610 Hunting Ln Columbia MD 21044",
    "addr:housenumber":"10610",
    "addr:postcode":"21044",
    "addr:street":"Hunting Ln",
    "iso:country":"US",
    "sg:address":"10610 Hunting Ln",
    "sg:city":"Columbia",
    "sg:classifiers":[
        {
            "category":"Real Estate",
            "subcategory":"Real Estate Services",
            "type":"Services"
        },
        {
            "category":"Real Estate",
            "subcategory":"Real Estate Agent",
            "type":"Services"
        }
    ],
    "sg:phone":"+1 410 531 5915",
    "sg:postcode":"21044",
    "sg:province":"MD",
    "sg:tags":[
        "buyer",
        "broker"
    ],
    "wof:name":"Carreno Real Estate Group, Inc.",
    "wof:placetype":"venue"
},
  "geometry": {"coordinates":[-76.87895,39.177926],"type":"Point"}
}