{
  "type": "Feature",
  "properties": {
    "addr:full":"5000 Freter Rd Sykesville MD 21784",
    "addr:housenumber":"5000",
    "addr:postcode":"21784",
    "addr:street":"Freter Rd",
    "iso:country":"US",
    "sg:address":"5000 Freter Rd",
    "sg:city":"Sykesville",
    "sg:classifiers":[
        {
            "category":"Building & Trades",
            "subcategory":"Construction",
            "type":"Services"
        }
    ],
    "sg:phone":"+1 410 549 1169",
    "sg:postcode":"21784",
    "sg:province":"MD",
    "sg:tags":[
        "contractor"
    ],
    "wof:name":"Wendell Bly Contractor",
    "wof:placetype":"venue"
},
  "geometry": {"coordinates":[-77.02893,39.433286],"type":"Point"}
}