{
  "type": "Feature",
  "properties": {
    "addr:full":"9510 Piscataway Rd Clinton MD 20735",
    "addr:postcode":"9510;20735",
    "addr:street":"Piscataway Rd",
    "iso:country":"US",
    "sg:address":"9510 Piscataway Rd",
    "sg:city":"Clinton",
    "sg:classifiers":[
        {
            "category":"Organizations",
            "subcategory":"Religious Organization",
            "type":"Services"
        }
    ],
    "sg:phone":"+1 301 856 8806",
    "sg:postcode":"20735",
    "sg:province":"MD",
    "sg:tags":[
        "church"
    ],
    "wof:name":"Greater Refuge Ministries Inc",
    "wof:placetype":"venue"
},
  "geometry": {"coordinates":[-76.916262,38.760715],"type":"Point"}
}