{
  "type": "Feature",
  "properties": {
    "iso:country":"US",
    "sg:address":"525 Michille Rd",
    "sg:city":"Odenton",
    "sg:classifiers":[
        {
            "category":"Building & Trades",
            "subcategory":"Construction",
            "type":"Services"
        }
    ],
    "sg:phone":"+1 410 674 1393",
    "sg:postcode":"21113",
    "sg:province":"MD",
    "sg:tags":[
        "contractor"
    ],
    "wof:name":"Pcr Window Installs",
    "wof:placetype":"venue"
},
  "geometry": {"coordinates":[-76.705241,39.076941],"type":"Point"}
}