{
  "type": "Feature",
  "properties": {
    "iso:country":"US",
    "sg:address":"1916 Alabaster Dr",
    "sg:city":"Silver Spring",
    "sg:classifiers":[
        {
            "category":"Professional",
            "subcategory":"Lawyer & Legal Services",
            "type":"Services"
        }
    ],
    "sg:phone":"+1 301 989 2202",
    "sg:postcode":"20904",
    "sg:province":"MD",
    "wof:name":"Kahan Allan R Atty",
    "wof:placetype":"venue"
},
  "geometry": {"coordinates":[-76.97199999999999,39.073399],"type":"Point"}
}