{
  "type": "Feature",
  "properties": {
    "addr:full":"2301 Rutledge Rd Fallston MD 21047",
    "addr:housenumber":"2301",
    "addr:postcode":"21047",
    "addr:street":"Rutledge Rd",
    "iso:country":"US",
    "sg:address":"2301 Rutledge Rd",
    "sg:city":"Fallston",
    "sg:classifiers":[
        {
            "category":"Shopping",
            "subcategory":"Bicycles & Sporting Goods",
            "type":"Retail Goods"
        }
    ],
    "sg:phone":"+1 410 557 6021",
    "sg:postcode":"21047",
    "sg:province":"MD",
    "sg:tags":[
        "horse",
        "furnishing"
    ],
    "wof:name":"Huntfend Farm Rutledge Ridge",
    "wof:placetype":"venue"
},
  "geometry": {"coordinates":[-76.48483899999999,39.559263],"type":"Point"}
}