{
  "type": "Feature",
  "properties": {
    "addr:full":"522 Rock Spring Rd Bel Air MD 21014",
    "addr:housenumber":"522",
    "addr:postcode":"21014",
    "addr:street":"Rock Spring Rd",
    "iso:country":"US",
    "sg:address":"522 Rock Spring Rd",
    "sg:city":"Bel Air",
    "sg:classifiers":[
        {
            "category":"Health Services",
            "subcategory":"Doctor",
            "type":"Services"
        }
    ],
    "sg:phone":"+1 410 838 6700",
    "sg:postcode":"21014",
    "sg:province":"MD",
    "sg:tags":[
        "dentist"
    ],
    "wof:name":"James W Taneyhill DDS",
    "wof:placetype":"venue"
},
  "geometry": {"coordinates":[-76.35759899999999,39.541078],"type":"Point"}
}