{
  "type": "Feature",
  "properties": {
    "iso:country":"US",
    "sg:address":"1833 Forest Dr",
    "sg:city":"Annapolis",
    "sg:classifiers":[
        {
            "category":"Health Services",
            "subcategory":"Doctor",
            "type":"Services"
        }
    ],
    "sg:phone":"+1 410 263 7338",
    "sg:postcode":"21401",
    "sg:province":"MD",
    "sg:tags":[
        "dentist"
    ],
    "wof:name":"Derek Siemon DDS",
    "wof:placetype":"venue"
},
  "geometry": {"coordinates":[-76.52486500000001,38.973078],"type":"Point"}
}