{
  "type": "Feature",
  "properties": {
    "addr:full":"1821 Portal St Ste B Baltimore MD 21224",
    "addr:housenumber":"1821",
    "addr:postcode":"21224",
    "addr:street":"Portal St Ste B",
    "iso:country":"US",
    "sg:address":"1821 Portal St Ste B",
    "sg:city":"Baltimore",
    "sg:classifiers":[
        {
            "category":"Health Services",
            "subcategory":"Clinic",
            "type":"Services"
        }
    ],
    "sg:phone":"+1 410 284 5006",
    "sg:postcode":"21224",
    "sg:province":"MD",
    "sg:tags":[
        "information",
        "mental"
    ],
    "wof:name":"Southeast Baltimore Mental Hea",
    "wof:placetype":"venue"
},
  "geometry": {"coordinates":[-76.53312699999999,39.270988],"type":"Point"}
}