{
  "type": "Feature",
  "properties": {
    "iso:country":"US",
    "sg:address":"17 Dockside Ct",
    "sg:city":"Berlin",
    "sg:classifiers":[
        {
            "category":"Professional",
            "subcategory":"Business Services",
            "type":"Services"
        }
    ],
    "sg:phone":"+1 410 641 8899",
    "sg:postcode":"21811",
    "sg:province":"MD",
    "sg:tags":[
        "interior",
        "consultant",
        "design",
        "decorator"
    ],
    "wof:name":"Interiors By Victoria",
    "wof:placetype":"venue"
},
  "geometry": {"coordinates":[-75.153763,38.389225],"type":"Point"}
}