{
  "type": "Feature",
  "properties": {
    "addr:full":"2822 Creswell Rd Bel Air MD 21015",
    "addr:postcode":"2822;21015",
    "addr:street":"Creswell Rd",
    "iso:country":"US",
    "sg:address":"2822 Creswell Rd",
    "sg:city":"Bel Air",
    "sg:classifiers":[
        {
            "category":"Shopping",
            "subcategory":"Gifts & Souvenirs",
            "type":"Retail Goods"
        }
    ],
    "sg:phone":"+1 410 734 7131",
    "sg:postcode":"21015",
    "sg:province":"MD",
    "wof:name":"Old German Gift Shop",
    "wof:placetype":"venue"
},
  "geometry": {"coordinates":[-76.250477,39.490557],"type":"Point"}
}