{
  "type": "Feature",
  "properties": {
    "iso:country":"US",
    "sg:address":"14832 Mockingbird Dr",
    "sg:city":"Germantown",
    "sg:classifiers":[
        {
            "category":"Health Services",
            "subcategory":"Doctor",
            "type":"Services"
        }
    ],
    "sg:phone":"+1 301 977 3368",
    "sg:postcode":"20874",
    "sg:province":"MD",
    "sg:tags":[
        "physician",
        "surgeon"
    ],
    "wof:name":"Ellen C Klosson Dr",
    "wof:placetype":"venue"
},
  "geometry": {"coordinates":[-77.291782,39.098516],"type":"Point"}
}