{
  "type": "Feature",
  "properties": {
    "addr:full":"9713 Greenel Rd Damascus MD 20872",
    "addr:housenumber":"9713",
    "addr:postcode":"20872",
    "addr:street":"Greenel Rd",
    "iso:country":"US",
    "sg:address":"9713 Greenel Rd",
    "sg:city":"Damascus",
    "sg:classifiers":[
        {
            "category":"Manufacturing",
            "subcategory":"Textiles",
            "type":"Manufacturing & Wholesale Goods"
        }
    ],
    "sg:phone":"+1 301 253 6839",
    "sg:postcode":"20872",
    "sg:province":"MD",
    "sg:tags":[
        "curtain"
    ],
    "wof:name":"Brandi's Inc",
    "wof:placetype":"venue"
},
  "geometry": {"coordinates":[-77.198564,39.262824],"type":"Point"}
}