{
  "type": "Feature",
  "properties": {
    "addr:full":"13001 Brandywine Rd Brandywine MD 20613",
    "addr:housenumber":"13001",
    "addr:postcode":"20613",
    "addr:street":"Brandywine Rd",
    "iso:country":"US",
    "sg:address":"13001 Brandywine Rd",
    "sg:city":"Brandywine",
    "sg:classifiers":[
        {
            "category":"Professional",
            "subcategory":"Engineering",
            "type":"Services"
        }
    ],
    "sg:phone":"+1 301 372 6644",
    "sg:postcode":"20613",
    "sg:province":"MD",
    "sg:tags":[
        "engineer"
    ],
    "wof:name":"Bradley Hutt Consultants Partn",
    "wof:placetype":"venue"
},
  "geometry": {"coordinates":[-76.886278,38.7144],"type":"Point"}
}