{
  "type": "Feature",
  "properties": {
    "addr:full":"8013 Carey Branch Pl Fort Washington MD 20744",
    "addr:housenumber":"8013",
    "addr:postcode":"20744",
    "addr:street":"Carey Branch Pl",
    "iso:country":"US",
    "sg:address":"8013 Carey Branch Pl",
    "sg:city":"Fort Washington",
    "sg:classifiers":[
        {
            "category":"Building & Trades",
            "subcategory":"Cleaning & Sanitation",
            "type":"Services"
        }
    ],
    "sg:phone":"+1 301 749 5895",
    "sg:postcode":"20744",
    "sg:province":"MD",
    "sg:tags":[
        "janitorial"
    ],
    "wof:name":"Jodar Cleaning Center",
    "wof:placetype":"venue"
},
  "geometry": {"coordinates":[-76.99513,38.778718],"type":"Point"}
}