{
  "type": "Feature",
  "properties": {
    "iso:country":"US",
    "sg:address":"931 National Hwy",
    "sg:city":"Cumberland",
    "sg:classifiers":[
        {
            "category":"Food & Beverages",
            "subcategory":"Bakery",
            "type":"Retail Goods"
        }
    ],
    "sg:phone":"+1 301 729 9379",
    "sg:postcode":"21502",
    "sg:province":"MD",
    "sg:tags":[
        "baker"
    ],
    "wof:name":"Dolly Madison Bakery Outlet",
    "wof:placetype":"venue"
},
  "geometry": {"coordinates":[-78.82163,39.645208],"type":"Point"}
}