{
  "type": "Feature",
  "properties": {
    "addr:full":"504 Poplar St Cambridge MD 21613",
    "addr:housenumber":"504",
    "addr:postcode":"21613",
    "addr:street":"Poplar St",
    "iso:country":"US",
    "sg:address":"504 Poplar St",
    "sg:city":"Cambridge",
    "sg:classifiers":[
        {
            "category":"Recreation",
            "type":"Entertainment"
        }
    ],
    "sg:phone":"+1 410 228 8300",
    "sg:postcode":"21613",
    "sg:province":"MD",
    "sg:tags":[
        "center"
    ],
    "wof:name":"Cambridge Recreation Ctr",
    "wof:placetype":"venue"
},
  "geometry": {"coordinates":[-76.07754199999999,38.570719],"type":"Point"}
}