{
  "type": "Feature",
  "properties": {
    "iso:country":"US",
    "sg:address":"70 John St",
    "sg:city":"Westminster",
    "sg:classifiers":[
        {
            "category":"Home & Garden",
            "subcategory":"Building Materials",
            "type":"Retail Goods"
        }
    ],
    "sg:phone":"+1 410 848 9030",
    "sg:postcode":"21157",
    "sg:province":"MD",
    "sg:tags":[
        "mixed",
        "concrete"
    ],
    "wof:name":"Thomas Bennett & Hunter Inc",
    "wof:placetype":"venue"
},
  "geometry": {"coordinates":[-76.993372,39.579371],"type":"Point"}
}