{
  "type": "Feature",
  "properties": {
    "iso:country":"US",
    "sg:address":"2026 Whiteford Rd",
    "sg:city":"Whiteford",
    "sg:classifiers":[
        {
            "category":"Building & Trades",
            "subcategory":"Construction",
            "type":"Services"
        }
    ],
    "sg:phone":"+1 410 838 2327",
    "sg:postcode":"21160",
    "sg:province":"MD",
    "sg:tags":[
        "bathroom",
        "remodeling"
    ],
    "wof:name":"Plumbing & Heating Svc Co",
    "wof:placetype":"venue"
},
  "geometry": {"coordinates":[-76.309361,39.693058],"type":"Point"}
}