{
  "type": "Feature",
  "properties": {
    "addr:full":"11236 Robinwood Dr Hagerstown MD 21742",
    "addr:housenumber":"11236",
    "addr:postcode":"21742",
    "addr:street":"Robinwood Dr",
    "iso:country":"US",
    "sg:address":"11236 Robinwood Dr",
    "sg:city":"Hagerstown",
    "sg:classifiers":[
        {
            "category":"Health Services",
            "subcategory":"Clinic",
            "type":"Services"
        }
    ],
    "sg:phone":"+1 240 313 4242",
    "sg:postcode":"21742",
    "sg:province":"MD",
    "sg:tags":[
        "welfare"
    ],
    "wof:name":"Our Urgent Care Center",
    "wof:placetype":"venue"
},
  "geometry": {"coordinates":[-77.67245699999999,39.624102],"type":"Point"}
}