{
  "type": "Feature",
  "properties": {
    "addr:full":"5539 Cedonia Ave Baltimore MD 21206",
    "addr:housenumber":"5539",
    "addr:postcode":"21206",
    "addr:street":"Cedonia Ave",
    "iso:country":"US",
    "sg:address":"5539 Cedonia Ave",
    "sg:city":"Baltimore",
    "sg:classifiers":[
        {
            "category":"Organizations",
            "subcategory":"Community Association",
            "type":"Services"
        }
    ],
    "sg:phone":"+1 410 325 2071",
    "sg:postcode":"21206",
    "sg:province":"MD",
    "sg:tags":[
        "club"
    ],
    "wof:name":"Super Club Resorts",
    "wof:placetype":"venue"
},
  "geometry": {"coordinates":[-76.533168,39.334797],"type":"Point"}
}