{
  "type": "Feature",
  "properties": {
    "addr:full":"240 N East Rd North East MD 21901",
    "addr:housenumber":"240",
    "addr:postcode":"21901",
    "addr:street":"N East Rd",
    "iso:country":"US",
    "sg:address":"240 N East Rd",
    "sg:city":"North East",
    "sg:classifiers":[
        {
            "category":"Building & Trades",
            "subcategory":"Equipment Rental",
            "type":"Services"
        }
    ],
    "sg:phone":"+1 410 287 3570",
    "sg:postcode":"21901",
    "sg:province":"MD",
    "sg:tags":[
        "yard"
    ],
    "wof:name":"Rent-A-Center",
    "wof:placetype":"venue"
},
  "geometry": {"coordinates":[-75.948094,39.615224],"type":"Point"}
}