{
  "type": "Feature",
  "properties": {
    "addr:full":"8005 Maple Ave Takoma Park MD 20912",
    "addr:housenumber":"8005",
    "addr:postcode":"20912",
    "addr:street":"Maple Ave",
    "iso:country":"US",
    "sg:address":"8005 Maple Ave",
    "sg:city":"Takoma Park",
    "sg:classifiers":[
        {
            "category":"Communications",
            "subcategory":"Film & Video Production",
            "type":"Services"
        }
    ],
    "sg:phone":"+1 301 589 3025",
    "sg:postcode":"20912",
    "sg:province":"MD",
    "sg:tags":[
        "motion",
        "picture",
        "consulting",
        "research"
    ],
    "wof:name":"Polly J Pettit",
    "wof:placetype":"venue"
},
  "geometry": {"coordinates":[-77.00341400000001,38.987264],"type":"Point"}
}