{
  "type": "Feature",
  "properties": {
    "iso:country":"US",
    "sg:address":"9601 Hale Dr",
    "sg:city":"Clinton",
    "sg:classifiers":[
        {
            "category":"Communications",
            "type":"Services"
        }
    ],
    "sg:phone":"+1 301 868 2942",
    "sg:postcode":"20735",
    "sg:province":"MD",
    "sg:tags":[
        "consultant",
        "engineer"
    ],
    "wof:name":"Thompson, Linda",
    "wof:placetype":"venue"
},
  "geometry": {"coordinates":[-76.889168,38.757591],"type":"Point"}
}