{
  "type": "Feature",
  "properties": {
    "iso:country":"US",
    "sg:address":"77 West St",
    "sg:city":"Annapolis",
    "sg:classifiers":[
        {
            "category":"Professional",
            "subcategory":"Lawyer & Legal Services",
            "type":"Services"
        }
    ],
    "sg:phone":"+1 443 482 9155",
    "sg:postcode":"21401",
    "sg:province":"MD",
    "sg:tags":[
        "attorney"
    ],
    "wof:name":"Stephen M Trattner",
    "wof:placetype":"venue"
},
  "geometry": {"coordinates":[-76.49609,38.978158],"type":"Point"}
}