{
  "type": "Feature",
  "properties": {
    "iso:country":"US",
    "sg:address":"8729 Church Ln",
    "sg:city":"Randallstown",
    "sg:classifiers":[
        {
            "category":"Organizations",
            "subcategory":"Religious Organization",
            "type":"Services"
        }
    ],
    "sg:phone":"+1 410 496 4400",
    "sg:postcode":"21133",
    "sg:province":"MD",
    "sg:tags":[
        "church"
    ],
    "wof:name":"Emmanuel Church",
    "wof:placetype":"venue"
},
  "geometry": {"coordinates":[-76.78506899999999,39.366737],"type":"Point"}
}