{
  "type": "Feature",
  "properties": {
    "addr:full":"17417 York Rd Parkton MD 21120",
    "addr:housenumber":"17417",
    "addr:postcode":"21120",
    "addr:street":"York Rd",
    "iso:country":"US",
    "sg:address":"17417 York Rd",
    "sg:city":"Parkton",
    "sg:classifiers":[
        {
            "category":"Restaurant",
            "type":"Food & Drink"
        }
    ],
    "sg:phone":"+1 410 357 9251",
    "sg:postcode":"21120",
    "sg:province":"MD",
    "sg:tags":[
        "lunch",
        "brunch",
        "breakfast"
    ],
    "wof:name":"Doughboys Inc",
    "wof:placetype":"venue"
},
  "geometry": {"coordinates":[-76.65928599999999,39.60259],"type":"Point"}
}