{
  "type": "Feature",
  "properties": {
    "addr:full":"8640 Pulaski Hwy Rosedale MD 21237",
    "addr:housenumber":"8640",
    "addr:postcode":"21237",
    "addr:street":"Pulaski Hwy",
    "iso:country":"US",
    "sg:address":"8640 Pulaski Hwy",
    "sg:city":"Rosedale",
    "sg:classifiers":[
        {
            "category":"Shopping",
            "subcategory":"Gifts & Souvenirs",
            "type":"Retail Goods"
        }
    ],
    "sg:phone":"+1 410 687 9040",
    "sg:postcode":"21237",
    "sg:province":"MD",
    "sg:tags":[
        "party",
        "supply"
    ],
    "wof:name":"Factory Card Outlet",
    "wof:placetype":"venue"
},
  "geometry": {"coordinates":[-76.487656,39.332678],"type":"Point"}
}