{
  "type": "Feature",
  "properties": {
    "iso:country":"US",
    "sg:address":"2400 Lakeside Dr",
    "sg:city":"Frederick",
    "sg:classifiers":[
        {
            "category":"Building & Trades",
            "subcategory":"Construction",
            "type":"Services"
        }
    ],
    "sg:phone":"+1 301 694 7727",
    "sg:postcode":"21702",
    "sg:province":"MD",
    "sg:tags":[
        "general",
        "contractor"
    ],
    "wof:name":"Greber Corp",
    "wof:placetype":"venue"
},
  "geometry": {"coordinates":[-77.450789,39.457485],"type":"Point"}
}