{
  "type": "Feature",
  "properties": {
    "iso:country":"US",
    "sg:address":"8 Old Club Ct",
    "sg:city":"Rockville",
    "sg:classifiers":[
        {
            "category":"Education",
            "subcategory":"School",
            "type":"Public Place"
        }
    ],
    "sg:phone":"+1 301 816 6918",
    "sg:postcode":"20852",
    "sg:province":"MD",
    "wof:name":"Maurice Maus Collins Scho",
    "wof:placetype":"venue"
},
  "geometry": {"coordinates":[-77.144329,39.041816],"type":"Point"}
}