{
  "type": "Feature",
  "properties": {
    "addr:full":"406 Pamela Dr Salisbury MD 21804",
    "addr:housenumber":"406",
    "addr:postcode":"21804",
    "addr:street":"Pamela Dr",
    "iso:country":"US",
    "sg:address":"406 Pamela Dr",
    "sg:city":"Salisbury",
    "sg:classifiers":[
        {
            "category":"Building & Trades",
            "subcategory":"Construction",
            "type":"Services"
        }
    ],
    "sg:phone":"+1 410 742 7775",
    "sg:postcode":"21804",
    "sg:province":"MD",
    "sg:tags":[
        "painter"
    ],
    "wof:name":"John H Peek Painting",
    "wof:placetype":"venue"
},
  "geometry": {"coordinates":[-75.55548899999999,38.383484],"type":"Point"}
}