{
  "type": "Feature",
  "properties": {
    "addr:full":"10612 Ashford Way Woodstock MD 21163",
    "addr:housenumber":"10612",
    "addr:postcode":"21163",
    "addr:street":"Ashford Way",
    "iso:country":"US",
    "sg:address":"10612 Ashford Way",
    "sg:city":"Woodstock",
    "sg:classifiers":[
        {
            "category":"Structure",
            "subcategory":"Office Building",
            "type":"Public Place"
        }
    ],
    "sg:phone":"+1 410 465 2514",
    "sg:postcode":"21163",
    "sg:province":"MD",
    "sg:tags":[
        "park"
    ],
    "wof:name":"Jdlee Properties",
    "wof:placetype":"venue"
},
  "geometry": {"coordinates":[-76.879797,39.309313],"type":"Point"}
}