{
  "type": "Feature",
  "properties": {
    "iso:country":"US",
    "sg:address":"7333 New Hampshire Ave",
    "sg:city":"Takoma Park",
    "sg:classifiers":[
        {
            "category":"Professional",
            "subcategory":"Business Services",
            "type":"Services"
        }
    ],
    "sg:phone":"+1 301 445 3333",
    "sg:postcode":"20912",
    "sg:province":"MD",
    "sg:tags":[
        "notary"
    ],
    "wof:name":"Winlu Inc",
    "wof:placetype":"venue"
},
  "geometry": {"coordinates":[-76.98842,38.982752],"type":"Point"}
}