{
  "type": "Feature",
  "properties": {
    "iso:country":"US",
    "sg:address":"8865 Stanford Blvd",
    "sg:city":"Columbia",
    "sg:classifiers":[
        {
            "category":"Professional",
            "subcategory":"Computer Services",
            "type":"Services"
        }
    ],
    "sg:phone":"+1 410 309 4800",
    "sg:postcode":"21045",
    "sg:province":"MD",
    "sg:website":"www.cisco.com",
    "wof:name":"Cisco Systems Inc",
    "wof:placetype":"venue"
},
  "geometry": {"coordinates":[-76.817597,39.188625],"type":"Point"}
}