{
  "type": "Feature",
  "properties": {
    "addr:full":"8865 Stanford Blvd Columbia MD 21045",
    "addr:housenumber":"8865",
    "addr:postcode":"21045",
    "addr:street":"Stanford Blvd",
    "iso:country":"US",
    "sg:address":"8865 Stanford Blvd",
    "sg:city":"Columbia",
    "sg:classifiers":[
        {
            "category":"Professional",
            "subcategory":"Computer Services",
            "type":"Services"
        }
    ],
    "sg:phone":"+1 410 309 4800",
    "sg:postcode":"21045",
    "sg:province":"MD",
    "sg:website":"www.cisco.com",
    "wof:name":"Cisco Systems Inc",
    "wof:placetype":"venue"
},
  "geometry": {"coordinates":[-76.81759700000001,39.188625],"type":"Point"}
}