{
  "type": "Feature",
  "properties": {
    "addr:full":"423 14th St Ocean City MD 21842",
    "addr:housenumber":"423",
    "addr:postcode":"21842",
    "addr:street":"14Th St",
    "iso:country":"US",
    "sg:address":"423 14th St",
    "sg:city":"Ocean City",
    "sg:classifiers":[
        {
            "category":"Travel",
            "subcategory":"Hotels & Motels",
            "type":"Entertainment"
        }
    ],
    "sg:phone":"+1 410 289 4408",
    "sg:postcode":"21842",
    "sg:province":"MD",
    "wof:name":"Bill Nielander",
    "wof:placetype":"venue"
},
  "geometry": {"coordinates":[-75.0836,38.345478],"type":"Point"}
}