{
  "type": "Feature",
  "properties": {
    "iso:country":"US",
    "sg:address":"9332 Annapolis Rd",
    "sg:city":"Lanham",
    "sg:classifiers":[
        {
            "category":"Professional",
            "subcategory":"Art Services",
            "type":"Services"
        }
    ],
    "sg:phone":"+1 240 296 3200",
    "sg:postcode":"20706",
    "sg:province":"MD",
    "sg:tags":[
        "graphic",
        "designer"
    ],
    "wof:name":"Just Great Graphics",
    "wof:placetype":"venue"
},
  "geometry": {"coordinates":[-76.848079,38.965051],"type":"Point"}
}