{
  "type": "Feature",
  "properties": {
    "iso:country":"US",
    "sg:address":"7347 Wisconsin Ave",
    "sg:city":"Bethesda",
    "sg:classifiers":[
        {
            "category":"Organizations",
            "subcategory":"Professional Association",
            "type":"Services"
        }
    ],
    "sg:phone":"+1 301 951 8058",
    "sg:postcode":"20814",
    "sg:province":"MD",
    "wof:name":"Golfe",
    "wof:placetype":"venue"
},
  "geometry": {"coordinates":[-77.093598,38.983268],"type":"Point"}
}