{
  "type": "Feature",
  "properties": {
    "iso:country":"US",
    "sg:address":"13906 Amberly Ct",
    "sg:city":"Bowie",
    "sg:classifiers":[
        {
            "category":"Professional",
            "subcategory":"Business Services",
            "type":"Services"
        }
    ],
    "sg:phone":"+1 301 352 0202",
    "sg:postcode":"20720",
    "sg:province":"MD",
    "wof:name":"JV Enterprises",
    "wof:placetype":"venue"
},
  "geometry": {"coordinates":[-76.764456,38.955389],"type":"Point"}
}