{
  "type": "Feature",
  "properties": {
    "iso:country":"US",
    "sg:address":"215 Najoles Rd",
    "sg:city":"Millersville",
    "sg:classifiers":[
        {
            "category":"Retail",
            "subcategory":"Auto Repair",
            "type":"Services"
        }
    ],
    "sg:phone":"+1 410 987 0130",
    "sg:postcode":"21108",
    "sg:province":"MD",
    "sg:tags":[
        "repairing",
        "automobile"
    ],
    "wof:name":"Autohaus Inc",
    "wof:placetype":"venue"
},
  "geometry": {"coordinates":[-76.631626,39.09507],"type":"Point"}
}