{
  "type": "Feature",
  "properties": {
    "iso:country":"US",
    "sg:address":"3516 Fort Meade Rd",
    "sg:city":"Laurel",
    "sg:classifiers":[
        {
            "category":"Autos & Motor Vehicles",
            "subcategory":"Automobile Sales",
            "type":"Retail Goods"
        }
    ],
    "sg:phone":"+1 301 617 4963",
    "sg:postcode":"20724",
    "sg:province":"MD",
    "sg:tags":[
        "car",
        "dealer"
    ],
    "wof:name":"Canby Motors",
    "wof:placetype":"venue"
},
  "geometry": {"coordinates":[-76.82592,39.100748],"type":"Point"}
}