{
  "type": "Feature",
  "properties": {
    "iso:country":"US",
    "sg:address":"5151 River Rd",
    "sg:city":"Bethesda",
    "sg:classifiers":[
        {
            "category":"Autos & Motor Vehicles",
            "subcategory":"Fuel & Gas Station",
            "type":"Retail Goods"
        },
        {
            "category":"Autos & Motor Vehicles",
            "subcategory":"Auto Supplies",
            "type":"Retail Goods"
        },
        {
            "category":"Personal",
            "type":"Services"
        },
        {
            "category":"Retail",
            "subcategory":"Auto Repair",
            "type":"Services"
        }
    ],
    "sg:phone":"+1 301 986 1221",
    "sg:postcode":"20816",
    "sg:province":"MD",
    "sg:tags":[
        "towing",
        "tire"
    ],
    "wof:name":"River Road Auto Service",
    "wof:placetype":"venue"
},
  "geometry": {"coordinates":[-77.103302,38.964298],"type":"Point"}
}