{
  "type": "Feature",
  "properties": {
    "iso:country":"US",
    "sg:address":"10266 Lake Arbor Way",
    "sg:city":"Mitchellville",
    "sg:classifiers":[
        {
            "category":"Personal",
            "type":"Services"
        }
    ],
    "sg:phone":"+1 301 499 0468",
    "sg:postcode":"20721",
    "sg:province":"MD",
    "sg:tags":[
        "control",
        "weight"
    ],
    "wof:name":"L A Weight Loss Ctr",
    "wof:placetype":"venue"
},
  "geometry": {"coordinates":[-76.828255,38.905959],"type":"Point"}
}