{
  "type": "Feature",
  "properties": {
    "addr:full":"2 Railroad Ave Glyndon MD 21071",
    "addr:housenumber":"2",
    "addr:postcode":"21071",
    "addr:street":"Railroad Ave",
    "iso:country":"US",
    "sg:address":"2 Railroad Ave",
    "sg:city":"Glyndon",
    "sg:classifiers":[
        {
            "category":"Personal",
            "subcategory":"Beauty Salon",
            "type":"Services"
        }
    ],
    "sg:phone":"+1 410 833 9999",
    "sg:postcode":"21071",
    "sg:province":"MD",
    "wof:name":"Glyndon Hair Station",
    "wof:placetype":"venue"
},
  "geometry": {"coordinates":[-76.819588,39.475479],"type":"Point"}
}