{
  "type": "Feature",
  "properties": {
    "iso:country":"US",
    "sg:address":"6104 Kenilworth Ave",
    "sg:city":"Riverdale",
    "sg:classifiers":[
        {
            "category":"Retail",
            "subcategory":"Auto Repair",
            "type":"Services"
        }
    ],
    "sg:phone":"+1 301 864 5680",
    "sg:postcode":"20737",
    "sg:province":"MD",
    "sg:tags":[
        "body",
        "shop"
    ],
    "wof:name":"Posada's Auto Body",
    "wof:placetype":"venue"
},
  "geometry": {"coordinates":[-76.919701,38.960999],"type":"Point"}
}