{
  "type": "Feature",
  "properties": {
    "addr:full":"38 W Main St Crisfield MD 21817",
    "addr:housenumber":"38",
    "addr:postcode":"21817",
    "addr:street":"W Main St",
    "iso:country":"US",
    "sg:address":"38 W Main St",
    "sg:city":"Crisfield",
    "sg:classifiers":[
        {
            "category":"Travel",
            "subcategory":"Hotels & Motels",
            "type":"Entertainment"
        }
    ],
    "sg:phone":"+1 410 968 0352",
    "sg:postcode":"21817",
    "sg:province":"MD",
    "sg:tags":[
        "breakfast",
        "accommodation",
        "bed"
    ],
    "wof:name":"My Fair Lady",
    "wof:placetype":"venue"
},
  "geometry": {"coordinates":[-75.847324,37.98183],"type":"Point"}
}