{
  "type": "Feature",
  "properties": {
    "addr:full":"2903 Kirtland Ave Forestville MD 20747",
    "addr:housenumber":"2903",
    "addr:postcode":"20747",
    "addr:street":"Kirtland Ave",
    "iso:country":"US",
    "sg:address":"2903 Kirtland Ave",
    "sg:city":"Forestville",
    "sg:classifiers":[
        {
            "category":"Building & Trades",
            "subcategory":"Construction",
            "type":"Services"
        }
    ],
    "sg:phone":"+1 301 420 0260",
    "sg:postcode":"20747",
    "sg:province":"MD",
    "sg:tags":[
        "general",
        "contractor"
    ],
    "wof:name":"Hill & Jack Construction Corp",
    "wof:placetype":"venue"
},
  "geometry": {"coordinates":[-76.879547,38.849842],"type":"Point"}
}