{
  "type": "Feature",
  "properties": {
    "addr:full":"10579 Middleport Ln White Plains MD 20695",
    "addr:housenumber":"10579",
    "addr:postcode":"20695",
    "addr:street":"Middleport Ln",
    "iso:country":"US",
    "sg:address":"10579 Middleport Ln",
    "sg:city":"White Plains",
    "sg:classifiers":[
        {
            "category":"Organizations",
            "subcategory":"Religious Organization",
            "type":"Services"
        }
    ],
    "sg:phone":"+1 301 885 2575",
    "sg:postcode":"20695",
    "sg:province":"MD",
    "sg:tags":[
        "church"
    ],
    "wof:name":"Choose Life Church Ministries",
    "wof:placetype":"venue"
},
  "geometry": {"coordinates":[-76.94247300000001,38.590596],"type":"Point"}
}