{
  "type": "Feature",
  "properties": {
    "addr:full":"11550 Philadelphia Rd White Marsh MD 21162",
    "addr:housenumber":"11550",
    "addr:postcode":"21162",
    "addr:street":"Philadelphia Rd",
    "iso:country":"US",
    "sg:address":"11550 Philadelphia Rd",
    "sg:city":"White Marsh",
    "sg:classifiers":[
        {
            "category":"Banks & Credit Unions",
            "subcategory":"Bank",
            "type":"Services"
        }
    ],
    "sg:phone":"+1 410 248 2555",
    "sg:postcode":"21162",
    "sg:province":"MD",
    "wof:name":"State Farm Bank",
    "wof:placetype":"venue"
},
  "geometry": {"coordinates":[-76.41390199999999,39.405701],"type":"Point"}
}