{
  "type": "Feature",
  "properties": {
    "iso:country":"US",
    "sg:address":"1362 Cape Saint Claire Rd",
    "sg:city":"Annapolis",
    "sg:classifiers":[
        {
            "category":"Personal",
            "type":"Services"
        }
    ],
    "sg:phone":"+1 410 757 6600",
    "sg:postcode":"21409",
    "sg:province":"MD",
    "sg:tags":[
        "control",
        "weight"
    ],
    "wof:name":"Watertogo Diet & Nutrition Ctr",
    "wof:placetype":"venue"
},
  "geometry": {"coordinates":[-76.437735,39.040811],"type":"Point"}
}