{
  "type": "Feature",
  "properties": {
    "iso:country":"US",
    "sg:address":"4225 N Woods Trl",
    "sg:city":"Hampstead",
    "sg:classifiers":[
        {
            "category":"Banks & Credit Unions",
            "subcategory":"Investment Brokerage",
            "type":"Services"
        }
    ],
    "sg:phone":"+1 866 733 2693",
    "sg:postcode":"21074",
    "sg:province":"MD",
    "sg:tags":[
        "tape",
        "video",
        "sale",
        "dvds-rental"
    ],
    "wof:name":"Redbox",
    "wof:placetype":"venue"
},
  "geometry": {"coordinates":[-76.845581,39.596062],"type":"Point"}
}