{
  "type": "Feature",
  "properties": {
    "addr:full":"935 Mount Hermon Rd Salisbury MD 21804",
    "addr:housenumber":"935",
    "addr:postcode":"21804",
    "addr:street":"Mount Hermon Rd",
    "iso:country":"US",
    "sg:address":"935 Mount Hermon Rd",
    "sg:city":"Salisbury",
    "sg:classifiers":[
        {
            "category":"Banks & Credit Unions",
            "subcategory":"Investment Brokerage",
            "type":"Services"
        }
    ],
    "sg:phone":"+1 410 860 1137",
    "sg:postcode":"21804",
    "sg:province":"MD",
    "sg:tags":[
        "security"
    ],
    "wof:name":"Rendine Financial Group",
    "wof:placetype":"venue"
},
  "geometry": {"coordinates":[-75.57814500000001,38.368032],"type":"Point"}
}