{
  "type": "Feature",
  "properties": {
    "iso:country":"US",
    "sg:address":"24221 Laytonsville Rd",
    "sg:city":"Gaithersburg",
    "sg:classifiers":[
        {
            "category":"Building & Trades",
            "subcategory":"Electrical",
            "type":"Services"
        }
    ],
    "sg:phone":"+1 301 414 0087",
    "sg:postcode":"20882",
    "sg:province":"MD",
    "sg:tags":[
        "electric",
        "contractor"
    ],
    "wof:name":"Maris Electric",
    "wof:placetype":"venue"
},
  "geometry": {"coordinates":[-77.143619,39.253115],"type":"Point"}
}