{
  "type": "Feature",
  "properties": {
    "iso:country":"US",
    "sg:address":"205 S Summit Ave",
    "sg:city":"Gaithersburg",
    "sg:classifiers":[
        {
            "category":"Organizations",
            "subcategory":"Religious Organization",
            "type":"Services"
        }
    ],
    "sg:phone":"+1 301 948 0122",
    "sg:postcode":"20877",
    "sg:province":"MD",
    "sg:tags":[
        "church"
    ],
    "sg:website":"www.ascensionmd.org",
    "wof:name":"Church Of The Ascension",
    "wof:placetype":"venue"
},
  "geometry": {"coordinates":[-77.19479200000001,39.136267],"type":"Point"}
}