{
  "type": "Feature",
  "properties": {
    "addr:full":"4118 Kathland Ave Gwynn Oak MD 21207",
    "addr:housenumber":"4118",
    "addr:postcode":"21207",
    "addr:street":"Kathland Ave",
    "iso:country":"US",
    "sg:address":"4118 Kathland Ave",
    "sg:city":"Gwynn Oak",
    "sg:classifiers":[
        {
            "category":"Organizations",
            "subcategory":"Religious Organization",
            "type":"Services"
        }
    ],
    "sg:phone":"+1 410 448 0638",
    "sg:postcode":"21207",
    "sg:province":"MD",
    "wof:name":"Coleman Abraham Rev",
    "wof:placetype":"venue"
},
  "geometry": {"coordinates":[-76.689499,39.3256],"type":"Point"}
}