{
  "type": "Feature",
  "properties": {
    "iso:country":"US",
    "sg:address":"3025 Pulaski Hwy",
    "sg:city":"Baltimore",
    "sg:classifiers":[
        {
            "category":"Retail",
            "subcategory":"Auto Repair",
            "type":"Services"
        }
    ],
    "sg:phone":"+1 410 563 9456",
    "sg:postcode":"21224",
    "sg:province":"MD",
    "wof:name":"Las Maravillas Auto Repair",
    "wof:placetype":"venue"
},
  "geometry": {"coordinates":[-76.57467,39.295309],"type":"Point"}
}