{
  "type": "Feature",
  "properties": {
    "iso:country":"US",
    "sg:address":"12 Catonridge Ct",
    "sg:city":"Baltimore",
    "sg:classifiers":[
        {
            "category":"Building & Trades",
            "subcategory":"Construction",
            "type":"Services"
        }
    ],
    "sg:phone":"+1 410 788 3615",
    "sg:postcode":"21228",
    "sg:province":"MD",
    "sg:tags":[
        "contractor"
    ],
    "wof:name":"Custom Tile Design",
    "wof:placetype":"venue"
},
  "geometry": {"coordinates":[-76.763732,39.281325],"type":"Point"}
}