{
  "type": "Feature",
  "properties": {
    "iso:country":"US",
    "sg:address":"8805 Centre Park Dr",
    "sg:city":"Columbia",
    "sg:classifiers":[
        {
            "category":"Communications",
            "subcategory":"Film & Video Production",
            "type":"Services"
        }
    ],
    "sg:phone":"+1 410 715 3528",
    "sg:postcode":"21045",
    "sg:province":"MD",
    "sg:tags":[
        "equipment",
        "leasing",
        "supplies-renting"
    ],
    "wof:name":"Video Mining Corp",
    "wof:placetype":"venue"
},
  "geometry": {"coordinates":[-76.814547,39.227379],"type":"Point"}
}