{
  "type": "Feature",
  "properties": {
    "iso:country":"US",
    "sg:address":"16550 Tammany Ln",
    "sg:city":"Williamsport",
    "sg:classifiers":[
        {
            "category":"Professional",
            "subcategory":"Management & Consulting",
            "type":"Services"
        }
    ],
    "sg:phone":"+1 301 582 3394",
    "sg:postcode":"21795",
    "sg:province":"MD",
    "sg:tags":[
        "selling",
        "establishment",
        "direct"
    ],
    "wof:name":"Shaklee Distributor",
    "wof:placetype":"venue"
},
  "geometry": {"coordinates":[-77.79602,39.610431],"type":"Point"}
}