{
  "type": "Feature",
  "properties": {
    "addr:full":"14617 McMullen Hwy SW Cumberland MD 21502",
    "addr:housenumber":"14617",
    "addr:postcode":"21502",
    "addr:street":"Mcmullen Hwy Sw",
    "iso:country":"US",
    "sg:address":"14617 McMullen Hwy SW",
    "sg:city":"Cumberland",
    "sg:classifiers":[
        {
            "category":"Building & Trades",
            "subcategory":"Construction",
            "type":"Services"
        }
    ],
    "sg:phone":"+1 301 729 0711",
    "sg:postcode":"21502",
    "sg:province":"MD",
    "sg:tags":[
        "contractor"
    ],
    "wof:name":"Danny Price Contractor",
    "wof:placetype":"venue"
},
  "geometry": {"coordinates":[-78.831051,39.594626],"type":"Point"}
}