{
  "type": "Feature",
  "properties": {
    "addr:full":"7129 Harford Rd Parkville MD 21234",
    "addr:housenumber":"7129",
    "addr:postcode":"21234",
    "addr:street":"Harford Rd",
    "iso:country":"US",
    "sg:address":"7129 Harford Rd",
    "sg:city":"Parkville",
    "sg:classifiers":[
        {
            "category":"Shopping",
            "subcategory":"Florist",
            "type":"Retail Goods"
        }
    ],
    "sg:phone":"+1 410 319 8500",
    "sg:postcode":"21234",
    "sg:province":"MD",
    "sg:tags":[
        "agent",
        "real estate"
    ],
    "wof:name":"Unique Expressions & More",
    "wof:placetype":"venue"
},
  "geometry": {"coordinates":[-76.54827400000001,39.367561],"type":"Point"}
}