{
  "type": "Feature",
  "properties": {
    "addr:full":"4020 Hunting Creek Rd Huntingtown MD 20639",
    "addr:housenumber":"4020",
    "addr:postcode":"20639",
    "addr:street":"Hunting Creek Rd",
    "iso:country":"US",
    "sg:address":"4020 Hunting Creek Rd",
    "sg:city":"Huntingtown",
    "sg:classifiers":[
        {
            "category":"Organizations",
            "subcategory":"Religious Organization",
            "type":"Services"
        }
    ],
    "sg:phone":"+1 410 257 3020",
    "sg:postcode":"20639",
    "sg:province":"MD",
    "sg:tags":[
        "church"
    ],
    "wof:name":"Huntingtown United Methodist",
    "wof:placetype":"venue"
},
  "geometry": {"coordinates":[-76.62230599999999,38.616724],"type":"Point"}
}