{
  "type": "Feature",
  "properties": {
    "addr:full":"1550 Old Westminster Pike Westminster MD 21157",
    "addr:housenumber":"1550",
    "addr:postcode":"21157",
    "addr:street":"Old Westminster Pike",
    "iso:country":"US",
    "sg:address":"1550 Old Westminster Pike",
    "sg:city":"Westminster",
    "sg:classifiers":[
        {
            "category":"Social Services",
            "subcategory":"Child Care",
            "type":"Services"
        }
    ],
    "sg:phone":"+1 410 876 4464",
    "sg:postcode":"21157",
    "sg:province":"MD",
    "wof:name":"Playtime Inc",
    "wof:placetype":"venue"
},
  "geometry": {"coordinates":[-76.94116200000001,39.545923],"type":"Point"}
}