{
  "type": "Feature",
  "properties": {
    "addr:full":"17223 Troyer Rd Monkton MD 21111",
    "addr:housenumber":"17223",
    "addr:postcode":"21111",
    "addr:street":"Troyer Rd",
    "iso:country":"US",
    "sg:address":"17223 Troyer Rd",
    "sg:city":"Monkton",
    "sg:classifiers":[
        {
            "category":"Organizations",
            "subcategory":"Religious Organization",
            "type":"Services"
        }
    ],
    "sg:phone":"+1 410 472 2077",
    "sg:postcode":"21111",
    "sg:province":"MD",
    "wof:name":"Mount Joy AME Church",
    "wof:placetype":"venue"
},
  "geometry": {"coordinates":[-76.573319,39.598507],"type":"Point"}
}