{
  "type": "Feature",
  "properties": {
    "addr:full":"10801 Lockwood Dr Ste 390 Silver Spring MD 20901",
    "addr:housenumber":"10801",
    "addr:postcode":"20901",
    "addr:street":"Lockwood Dr Ste 390",
    "iso:country":"US",
    "sg:address":"10801 Lockwood Dr Ste 390",
    "sg:city":"Silver Spring",
    "sg:classifiers":[
        {
            "category":"Health Services",
            "subcategory":"Doctor",
            "type":"Services"
        }
    ],
    "sg:phone":"+1 301 585 7766",
    "sg:postcode":"20901",
    "sg:province":"MD",
    "sg:tags":[
        "surgeon",
        "oral"
    ],
    "wof:name":"Kan Glen A DDS",
    "wof:placetype":"venue"
},
  "geometry": {"coordinates":[-77.00160200000001,39.033501],"type":"Point"}
}