{
  "type": "Feature",
  "properties": {
    "addr:full":"1513 Edgemore Ave Salisbury MD 21801",
    "addr:housenumber":"1513",
    "addr:postcode":"21801",
    "addr:street":"Edgemore Ave",
    "iso:country":"US",
    "sg:address":"1513 Edgemore Ave",
    "sg:city":"Salisbury",
    "sg:classifiers":[
        {
            "category":"Wholesale",
            "subcategory":"Durable Goods & Equipment",
            "type":"Manufacturing & Wholesale Goods"
        }
    ],
    "sg:phone":"+1 410 546 3898",
    "sg:postcode":"21801",
    "sg:province":"MD",
    "sg:tags":[
        "importer"
    ],
    "wof:name":"Icey Tek USA",
    "wof:placetype":"venue"
},
  "geometry": {"coordinates":[-75.585549,38.383722],"type":"Point"}
}