{
  "type": "Feature",
  "properties": {
    "iso:country":"US",
    "sg:address":"7501 Landover Rd",
    "sg:city":"Hyattsville",
    "sg:classifiers":[
        {
            "category":"Food & Beverages",
            "subcategory":"Groceries & Convenience Stores",
            "type":"Retail Goods"
        }
    ],
    "sg:phone":"+1 301 386 9701",
    "sg:postcode":"20785",
    "sg:province":"MD",
    "wof:name":"Stadium Mart",
    "wof:placetype":"venue"
},
  "geometry": {"coordinates":[-76.886703,38.926601],"type":"Point"}
}