{
  "type": "Feature",
  "properties": {
    "addr:full":"29 Lincoln Woods Way Perry Hall MD 21128",
    "addr:housenumber":"29",
    "addr:postcode":"21128",
    "addr:street":"Lincoln Woods Way",
    "iso:country":"US",
    "sg:address":"29 Lincoln Woods Way",
    "sg:city":"Perry Hall",
    "sg:classifiers":[
        {
            "category":"Professional",
            "subcategory":"Research",
            "type":"Services"
        }
    ],
    "sg:phone":"+1 410 933 1059",
    "sg:postcode":"21128",
    "sg:province":"MD",
    "sg:tags":[
        "commercial",
        "physical"
    ],
    "wof:name":"Ydm",
    "wof:placetype":"venue"
},
  "geometry": {"coordinates":[-76.45954,39.381338],"type":"Point"}
}