{
  "type": "Feature",
  "properties": {
    "iso:country":"US",
    "sg:address":"5406 Roosevelt St",
    "sg:city":"Bethesda",
    "sg:classifiers":[
        {
            "category":"Professional",
            "subcategory":"Computer Services",
            "type":"Services"
        }
    ],
    "sg:phone":"+1 301 897 2785",
    "sg:postcode":"20817",
    "sg:province":"MD",
    "sg:tags":[
        "datum",
        "programing",
        "custom"
    ],
    "wof:name":"Ravindra Kulkarni",
    "wof:placetype":"venue"
},
  "geometry": {"coordinates":[-77.111415,38.995414],"type":"Point"}
}