{
  "type": "Feature",
  "properties": {
    "addr:full":"1021 Fridinger Mill Rd Westminster MD 21157",
    "addr:housenumber":"1021",
    "addr:postcode":"21157",
    "addr:street":"Fridinger Mill Rd",
    "iso:country":"US",
    "sg:address":"1021 Fridinger Mill Rd",
    "sg:city":"Westminster",
    "sg:classifiers":[
        {
            "category":"Building & Trades",
            "subcategory":"Construction",
            "type":"Services"
        }
    ],
    "sg:phone":"+1 410 876 6511",
    "sg:postcode":"21157",
    "sg:province":"MD",
    "sg:tags":[
        "home",
        "improvement"
    ],
    "wof:name":"House Masters",
    "wof:placetype":"venue"
},
  "geometry": {"coordinates":[-76.958758,39.631801],"type":"Point"}
}