{
  "type": "Feature",
  "properties": {
    "iso:country":"US",
    "sg:address":"530 Swann Ave",
    "sg:city":"Baltimore",
    "sg:classifiers":[
        {
            "category":"Food & Beverages",
            "subcategory":"Groceries & Convenience Stores",
            "type":"Retail Goods"
        }
    ],
    "sg:phone":"+1 410 566 2448",
    "sg:postcode":"21229",
    "sg:province":"MD",
    "wof:name":"7-Eleven",
    "wof:placetype":"venue"
},
  "geometry": {"coordinates":[-76.69391299999999,39.293293],"type":"Point"}
}