{
  "type": "Feature",
  "properties": {
    "addr:full":"2269 Lewisdale Dr Hyattsville MD 20783",
    "addr:housenumber":"2269",
    "addr:postcode":"20783",
    "addr:street":"Lewisdale Dr",
    "iso:country":"US",
    "sg:address":"2269 Lewisdale Dr",
    "sg:city":"Hyattsville",
    "sg:classifiers":[
        {
            "category":"Building & Trades",
            "subcategory":"Cleaning & Sanitation",
            "type":"Services"
        }
    ],
    "sg:phone":"+1 301 587 2013",
    "sg:postcode":"20783",
    "sg:province":"MD",
    "sg:tags":[
        "maintenance"
    ],
    "wof:name":"G&C Cleaning Svc Inc",
    "wof:placetype":"venue"
},
  "geometry": {"coordinates":[-76.97306500000001,38.982396],"type":"Point"}
}