{
  "type": "Feature",
  "properties": {
    "addr:full":"5200 River Rd Bethesda MD 20816",
    "addr:housenumber":"5200",
    "addr:postcode":"20816",
    "addr:street":"River Rd",
    "iso:country":"US",
    "sg:address":"5200 River Rd",
    "sg:city":"Bethesda",
    "sg:classifiers":[
        {
            "category":"Building & Trades",
            "subcategory":"Cleaning & Sanitation",
            "type":"Services"
        }
    ],
    "sg:phone":"+1 240 497 0100",
    "sg:postcode":"20816",
    "sg:province":"MD",
    "sg:tags":[
        "snow",
        "removal"
    ],
    "wof:name":"Rasevic Snow Svc Inc",
    "wof:placetype":"venue"
},
  "geometry": {"coordinates":[-77.10363,38.964717],"type":"Point"}
}