{
  "type": "Feature",
  "properties": {
    "iso:country":"US",
    "sg:address":"5 August Ave",
    "sg:city":"Catonsville",
    "sg:classifiers":[
        {
            "category":"Building & Trades",
            "subcategory":"Electrical",
            "type":"Services"
        }
    ],
    "sg:phone":"+1 410 869 3532",
    "sg:postcode":"21228",
    "sg:province":"MD",
    "sg:tags":[
        "electric",
        "contractor"
    ],
    "wof:name":"Dominic Electrical Svc",
    "wof:placetype":"venue"
},
  "geometry": {"coordinates":[-76.735962,39.276783],"type":"Point"}
}