{
  "type": "Feature",
  "properties": {
    "addr:full":"735 Monroe St Rockville MD 20850",
    "addr:housenumber":"735",
    "addr:postcode":"20850",
    "addr:street":"Monroe St",
    "iso:country":"US",
    "sg:address":"735 Monroe St",
    "sg:city":"Rockville",
    "sg:classifiers":[
        {
            "category":"Real Estate",
            "subcategory":"Real Estate Operator",
            "type":"Services"
        }
    ],
    "sg:phone":"+1 301 279 7741",
    "sg:postcode":"20850",
    "sg:province":"MD",
    "sg:tags":[
        "apartment"
    ],
    "wof:name":"Fireside Park Apartments",
    "wof:placetype":"venue"
},
  "geometry": {"coordinates":[-77.153817,39.075307],"type":"Point"}
}