{
  "type": "Feature",
  "properties": {
    "iso:country":"US",
    "sg:address":"303 West Ln",
    "sg:city":"Churchville",
    "sg:classifiers":[
        {
            "category":"Manufacturing",
            "subcategory":"Toys & Sporting Goods",
            "type":"Manufacturing & Wholesale Goods"
        }
    ],
    "sg:phone":"+1 410 734 6238",
    "sg:postcode":"21028",
    "sg:province":"MD",
    "sg:tags":[
        "goods-wholesale",
        "manufacturer"
    ],
    "sg:website":"http://www.vincentidecoys.com",
    "wof:name":"Vincenti Decoys",
    "wof:placetype":"venue"
},
  "geometry": {"coordinates":[-76.22928,39.555855],"type":"Point"}
}