{
  "type": "Feature",
  "properties": {
    "iso:country":"US",
    "sg:address":"2341 Forest Dr",
    "sg:city":"Annapolis",
    "sg:classifiers":[
        {
            "category":"Shopping",
            "subcategory":"Baby Store",
            "type":"Retail Goods"
        }
    ],
    "sg:phone":"+1 410 396 8485",
    "sg:postcode":"21401",
    "sg:province":"MD",
    "sg:tags":[
        "children's",
        "infant",
        "wear"
    ],
    "sg:website":"http://www.gabbikids.com/",
    "wof:name":"Gabbi Authenic Outfitters",
    "wof:placetype":"venue"
},
  "geometry": {"coordinates":[-76.543379,38.980535],"type":"Point"}
}