{
  "type": "Feature",
  "properties": {
    "addr:full":"7525 Belair Rd Nottingham MD 21236",
    "addr:housenumber":"7525",
    "addr:postcode":"21236",
    "addr:street":"Belair Rd",
    "iso:country":"US",
    "sg:address":"7525 Belair Rd",
    "sg:city":"Nottingham",
    "sg:classifiers":[
        {
            "category":"Professional",
            "subcategory":"Business Services",
            "type":"Services"
        }
    ],
    "sg:phone":"+1 410 661 4192",
    "sg:postcode":"21236",
    "sg:province":"MD",
    "sg:tags":[
        "recording",
        "rehearsal",
        "studio"
    ],
    "wof:name":"Hot Tracks",
    "wof:placetype":"venue"
},
  "geometry": {"coordinates":[-76.5205,39.363998],"type":"Point"}
}