{
  "type": "Feature",
  "properties": {
    "iso:country":"US",
    "sg:address":"9705 Carmel Ct",
    "sg:city":"Bethesda",
    "sg:classifiers":[
        {
            "category":"Banks & Credit Unions",
            "subcategory":"Investment Brokerage",
            "type":"Services"
        }
    ],
    "sg:phone":"+1 301 530 9201",
    "sg:postcode":"20817",
    "sg:province":"MD",
    "sg:tags":[
        "investing"
    ],
    "wof:name":"Oak Forest Investment Management",
    "wof:placetype":"venue"
},
  "geometry": {"coordinates":[-77.15647199999999,39.014908],"type":"Point"}
}