{
  "type": "Feature",
  "properties": {
    "iso:country":"US",
    "sg:address":"7611 S Osborne Rd",
    "sg:city":"Upper Marlboro",
    "sg:classifiers":[
        {
            "category":"Organizations",
            "subcategory":"Religious Organization",
            "type":"Services"
        }
    ],
    "sg:phone":"+1 301 780 3021",
    "sg:postcode":"20772",
    "sg:province":"MD",
    "sg:tags":[
        "church"
    ],
    "wof:name":"Greater Grace Family Ministry",
    "wof:placetype":"venue"
},
  "geometry": {"coordinates":[-76.79724299999999,38.784982],"type":"Point"}
}