{
  "type": "Feature",
  "properties": {
    "iso:country":"US",
    "sg:address":"921 Pennsylvania Ave",
    "sg:city":"Hagerstown",
    "sg:classifiers":[
        {
            "category":"Shopping",
            "subcategory":"Department Store",
            "type":"Retail Goods"
        }
    ],
    "sg:phone":"+1 301 393 9425",
    "sg:postcode":"21742",
    "sg:province":"MD",
    "sg:tags":[
        "shop"
    ],
    "wof:name":"Family Dollar Store",
    "wof:placetype":"venue"
},
  "geometry": {"coordinates":[-77.718301,39.657777],"type":"Point"}
}