{
  "type": "Feature",
  "properties": {
    "addr:full":"18931 Premiere Ct Gaithersburg MD 20879",
    "addr:postcode":"18931;20879",
    "addr:street":"Premiere Ct",
    "iso:country":"US",
    "sg:address":"18931 Premiere Ct",
    "sg:city":"Gaithersburg",
    "sg:classifiers":[
        {
            "category":"Building & Trades",
            "subcategory":"Cleaning & Sanitation",
            "type":"Services"
        }
    ],
    "sg:phone":"+1 301 977 1144",
    "sg:postcode":"20879",
    "sg:province":"MD",
    "wof:name":"Carefree Cleaning Svc",
    "wof:placetype":"venue"
},
  "geometry": {"coordinates":[-77.166714,39.16685],"type":"Point"}
}