{
  "type": "Feature",
  "properties": {
    "iso:country":"US",
    "sg:address":"1020 N Linwood Ave",
    "sg:city":"Baltimore",
    "sg:classifiers":[
        {
            "category":"Professional",
            "subcategory":"Business Services",
            "type":"Services"
        }
    ],
    "sg:phone":"+1 410 563 1660",
    "sg:postcode":"21205",
    "sg:province":"MD",
    "wof:name":"Lester J Bernadine Bussa",
    "wof:placetype":"venue"
},
  "geometry": {"coordinates":[-76.57683900000001,39.302054],"type":"Point"}
}