{
  "type": "Feature",
  "properties": {
    "iso:country":"US",
    "sg:address":"6101 Moser Rd",
    "sg:city":"Boonsboro",
    "sg:classifiers":[
        {
            "category":"Shopping",
            "subcategory":"Crafts & Fabrics",
            "type":"Retail Goods"
        }
    ],
    "sg:phone":"+1 301 416 2596",
    "sg:postcode":"21713",
    "sg:province":"MD",
    "sg:tags":[
        "sewing"
    ],
    "wof:name":"Bear Acres Stitchery",
    "wof:placetype":"venue"
},
  "geometry": {"coordinates":[-77.62569499999999,39.47379],"type":"Point"}
}