{
  "type": "Feature",
  "properties": {
    "addr:full":"7311 Hanover Pkwy Greenbelt MD 20770",
    "addr:housenumber":"7311",
    "addr:postcode":"20770",
    "addr:street":"Hanover Pkwy",
    "iso:country":"US",
    "sg:address":"7311 Hanover Pkwy",
    "sg:city":"Greenbelt",
    "sg:classifiers":[
        {
            "category":"Local Transit",
            "type":"Transportation"
        }
    ],
    "sg:phone":"+1 301 982 6100",
    "sg:postcode":"20770",
    "sg:province":"MD",
    "sg:tags":[
        "limousine"
    ],
    "wof:name":"Capital City Limousine Co",
    "wof:placetype":"venue"
},
  "geometry": {"coordinates":[-76.877595,38.990554],"type":"Point"}
}