{
  "type": "Feature",
  "properties": {
    "addr:full":"518 Montana Ln Mountain Lake Pk MD 21550",
    "addr:housenumber":"518",
    "addr:postcode":"21550",
    "addr:street":"Montana Ln",
    "iso:country":"US",
    "sg:address":"518 Montana Ln",
    "sg:city":"Mountain Lake Pk",
    "sg:classifiers":[
        {
            "category":"Personal",
            "subcategory":"Beauty Salon",
            "type":"Services"
        }
    ],
    "sg:phone":"+1 301 334 4366",
    "sg:postcode":"21550",
    "sg:province":"MD",
    "wof:name":"Personal Touch",
    "wof:placetype":"venue"
},
  "geometry": {"coordinates":[-79.372829,39.47339],"type":"Point"}
}