{
  "type": "Feature",
  "properties": {
    "iso:country":"US",
    "sg:address":"6703 Whiteley Rd",
    "sg:city":"Hurlock",
    "sg:classifiers":[
        {
            "category":"Restaurant",
            "type":"Food & Drink"
        }
    ],
    "sg:phone":"+1 410 943 3432",
    "sg:postcode":"21643",
    "sg:province":"MD",
    "sg:tags":[
        "style",
        "american",
        "family"
    ],
    "sg:website":"http://www.countrykitchenrestaurants.com",
    "wof:name":"Country Kitchen",
    "wof:placetype":"venue"
},
  "geometry": {"coordinates":[-75.829233,38.659151],"type":"Point"}
}