{
  "type": "Feature",
  "properties": {
    "iso:country":"US",
    "sg:address":"13 W Main St",
    "sg:city":"Middletown",
    "sg:classifiers":[
        {
            "category":"Shopping",
            "subcategory":"Florist",
            "type":"Retail Goods"
        }
    ],
    "sg:phone":"+1 301 371 7996",
    "sg:postcode":"21769",
    "sg:province":"MD",
    "wof:name":"Ann's Florist Inc",
    "wof:placetype":"venue"
},
  "geometry": {"coordinates":[-77.545934,39.443883],"type":"Point"}
}