{
  "type": "Feature",
  "properties": {
    "addr:full":"233 E Redwood St Baltimore MD 21202",
    "addr:housenumber":"233",
    "addr:postcode":"21202",
    "addr:street":"E Redwood St",
    "iso:country":"US",
    "sg:address":"233 E Redwood St",
    "sg:city":"Baltimore",
    "sg:classifiers":[
        {
            "category":"Professional",
            "subcategory":"Lawyer & Legal Services",
            "type":"Services"
        }
    ],
    "sg:phone":"+1 410 576 4040",
    "sg:postcode":"21202",
    "sg:province":"MD",
    "wof:name":"Dean Jennifer L Atty",
    "wof:placetype":"venue"
},
  "geometry": {"coordinates":[-76.61170199999999,39.288898],"type":"Point"}
}