{
  "type": "Feature",
  "properties": {
    "iso:country":"US",
    "sg:address":"5410 Connecticut Ave NW",
    "sg:city":"Washington",
    "sg:classifiers":[
        {
            "category":"Health Services",
            "subcategory":"Doctor",
            "type":"Services"
        }
    ],
    "sg:phone":"+1 202 362 8625",
    "sg:postcode":"20015",
    "sg:province":"MD",
    "sg:tags":[
        "physician",
        "surgeon"
    ],
    "wof:name":"Barry J Landau MD",
    "wof:placetype":"venue"
},
  "geometry": {"coordinates":[-77.073527,38.961012],"type":"Point"}
}