{
  "type": "Feature",
  "properties": {
    "addr:full":"509 Drury Ln Baltimore MD 21229",
    "addr:housenumber":"509",
    "addr:postcode":"21229",
    "addr:street":"Drury Ln",
    "iso:country":"US",
    "sg:address":"509 Drury Ln",
    "sg:city":"Baltimore",
    "sg:classifiers":[
        {
            "category":"Professional",
            "subcategory":"Computer Services",
            "type":"Services"
        }
    ],
    "sg:phone":"+1 410 455 5300",
    "sg:postcode":"21229",
    "sg:province":"MD",
    "sg:tags":[
        "repair"
    ],
    "sg:website":"www.smartneighbor.com",
    "wof:name":"Smart Neighbor",
    "wof:placetype":"venue"
},
  "geometry": {"coordinates":[-76.705153,39.290863],"type":"Point"}
}