{
  "type": "Feature",
  "properties": {
    "addr:full":"1623 Postal Rd Chester MD 21619",
    "addr:housenumber":"1623",
    "addr:postcode":"21619",
    "addr:street":"Postal Rd",
    "iso:country":"US",
    "sg:address":"1623 Postal Rd",
    "sg:city":"Chester",
    "sg:classifiers":[
        {
            "category":"Personal",
            "type":"Services"
        },
        {
            "category":"Professional",
            "subcategory":"Detective & Security Services",
            "type":"Services"
        },
        {
            "category":"Manufacturing",
            "subcategory":"Electronics",
            "type":"Manufacturing & Wholesale Goods"
        },
        {
            "category":"Shopping",
            "subcategory":"Computers & Home Electronics",
            "type":"Retail Goods"
        },
        {
            "category":"Building & Trades",
            "subcategory":"Electrical",
            "type":"Services"
        }
    ],
    "sg:phone":"+1 410 758 1915",
    "sg:postcode":"21619",
    "sg:province":"MD",
    "sg:tags":[
        "control",
        "monitoring",
        "equipment-wholesale",
        "medical",
        "system",
        "surveillance",
        "equipment",
        "smoke",
        "detector",
        "alarm",
        "manufacturer"
    ],
    "sg:website":"http://www.astechsecurity.com",
    "wof:name":"Astech Security",
    "wof:placetype":"venue"
},
  "geometry": {"coordinates":[-76.284902,38.974645],"type":"Point"}
}