{
  "type": "Feature",
  "properties": {
    "iso:country":"US",
    "sg:address":"106 Wayside Ave",
    "sg:city":"Hagerstown",
    "sg:classifiers":[
        {
            "category":"Building & Trades",
            "subcategory":"Construction",
            "type":"Services"
        }
    ],
    "sg:phone":"+1 301 739 5120",
    "sg:postcode":"21740",
    "sg:province":"MD",
    "sg:tags":[
        "house"
    ],
    "wof:name":"WA Construction Inc",
    "wof:placetype":"venue"
},
  "geometry": {"coordinates":[-77.710832,39.648051],"type":"Point"}
}