{
  "type": "Feature",
  "properties": {
    "iso:country":"US",
    "sg:address":"4900 Liberty Heights Ave",
    "sg:city":"Gwynn Oak",
    "sg:classifiers":[
        {
            "category":"Food & Beverages",
            "subcategory":"Groceries & Convenience Stores",
            "type":"Retail Goods"
        }
    ],
    "sg:phone":"+1 410 367 1421",
    "sg:postcode":"21207",
    "sg:province":"MD",
    "wof:name":"Food Stop",
    "wof:placetype":"venue"
},
  "geometry": {"coordinates":[-76.698402,39.332401],"type":"Point"}
}