{
  "type": "Feature",
  "properties": {
    "iso:country":"US",
    "sg:address":"531 Jermor Ln",
    "sg:city":"Westminster",
    "sg:classifiers":[
        {
            "category":"Shopping",
            "type":"Retail Goods"
        }
    ],
    "sg:phone":"+1 410 876 6906",
    "sg:postcode":"21157",
    "sg:province":"MD",
    "sg:tags":[
        "cards",
        "sport",
        "baseball",
        "memorabilia"
    ],
    "wof:name":"Great Moments",
    "wof:placetype":"venue"
},
  "geometry": {"coordinates":[-76.976848,39.565113],"type":"Point"}
}