{
  "type": "Feature",
  "properties": {
    "iso:country":"US",
    "sg:address":"3135 Leonardtown Rd",
    "sg:city":"Waldorf",
    "sg:classifiers":[
        {
            "category":"Banks & Credit Unions",
            "subcategory":"Bank",
            "type":"Services"
        }
    ],
    "sg:phone":"+1 301 932 7509",
    "sg:postcode":"20601",
    "sg:province":"MD",
    "sg:website":"www.mdbank.com",
    "wof:name":"Maryland Bank & Trust Co",
    "wof:placetype":"venue"
},
  "geometry": {"coordinates":[-76.908192,38.624264],"type":"Point"}
}