{
  "type": "Feature",
  "properties": {
    "iso:country":"US",
    "sg:address":"7 Vintage Ct",
    "sg:city":"Cockysvl Hnt Vly",
    "sg:classifiers":[
        {
            "category":"Banks & Credit Unions",
            "subcategory":"Bank",
            "type":"Services"
        }
    ],
    "sg:phone":"+1 410 666 1311",
    "sg:postcode":"21030",
    "sg:province":"MD",
    "sg:tags":[
        "machine",
        "teller",
        "automated"
    ],
    "wof:name":"Capital Atm",
    "wof:placetype":"venue"
},
  "geometry": {"coordinates":[-76.62585,39.470695],"type":"Point"}
}