{
  "type": "Feature",
  "properties": {
    "addr:full":"19951 Aircraft Dr Germantown MD 20874",
    "addr:housenumber":"19951",
    "addr:postcode":"20874",
    "addr:street":"Aircraft Dr",
    "iso:country":"US",
    "sg:address":"19951 Aircraft Dr",
    "sg:city":"Germantown",
    "sg:classifiers":[
        {
            "category":"Retail",
            "subcategory":"Auto Repair",
            "type":"Services"
        }
    ],
    "sg:phone":"+1 301 428 0033",
    "sg:postcode":"20874",
    "sg:province":"MD",
    "sg:tags":[
        "body",
        "automobile",
        "painting"
    ],
    "wof:name":"Phase III Auto Body",
    "wof:placetype":"venue"
},
  "geometry": {"coordinates":[-77.26081600000001,39.183042],"type":"Point"}
}