{
  "type": "Feature",
  "properties": {
    "iso:country":"US",
    "sg:address":"843 Quince Orchard Blvd",
    "sg:city":"Gaithersburg",
    "sg:classifiers":[
        {
            "category":"Organizations",
            "subcategory":"Non-profit Organization",
            "type":"Services"
        }
    ],
    "sg:phone":"+1 301 340 2030",
    "sg:postcode":"20878",
    "sg:province":"MD",
    "sg:tags":[
        "charitable",
        "institution"
    ],
    "wof:name":"Labyrinth Inc",
    "wof:placetype":"venue"
},
  "geometry": {"coordinates":[-77.230755,39.136344],"type":"Point"}
}