{
  "type": "Feature",
  "properties": {
    "addr:full":"1428 Rockville Pike Rockville MD 20852",
    "addr:housenumber":"1428",
    "addr:postcode":"20852",
    "addr:street":"Rockville Pike",
    "iso:country":"US",
    "sg:address":"1428 Rockville Pike",
    "sg:city":"Rockville",
    "sg:classifiers":[
        {
            "category":"Home & Garden",
            "subcategory":"Furniture",
            "type":"Retail Goods"
        },
        {
            "category":"Home & Garden",
            "subcategory":"Home Furnishings",
            "type":"Retail Goods"
        },
        {
            "category":"Home & Garden",
            "subcategory":"Carpets & Floor Coverings",
            "type":"Retail Goods"
        }
    ],
    "sg:phone":"+1 301 230 2310",
    "sg:postcode":"20852",
    "sg:province":"MD",
    "sg:tags":[
        "set",
        "house",
        "bed",
        "mattress",
        "bedroom",
        "store"
    ],
    "sg:website":"http://clickserve.us2.dartsearch.net/link/click?lid=43000000124318664",
    "wof:name":"Havertys Furniture",
    "wof:placetype":"venue"
},
  "geometry": {"coordinates":[-77.12753600000001,39.066266],"type":"Point"}
}