{
  "type": "Feature",
  "properties": {
    "addr:full":"8651 Fort Smallwood Rd Pasadena MD 21122",
    "addr:housenumber":"8651",
    "addr:postcode":"21122",
    "addr:street":"Fort Smallwood Rd",
    "iso:country":"US",
    "sg:address":"8651 Fort Smallwood Rd",
    "sg:city":"Pasadena",
    "sg:classifiers":[
        {
            "category":"Health Services",
            "subcategory":"Doctor",
            "type":"Services"
        }
    ],
    "sg:phone":"+1 410 437 3773",
    "sg:postcode":"21122",
    "sg:province":"MD",
    "sg:tags":[
        "dentist"
    ],
    "wof:name":"Jeffrey Greenstein DDS",
    "wof:placetype":"venue"
},
  "geometry": {"coordinates":[-76.522088,39.149851],"type":"Point"}
}