{
  "type": "Feature",
  "properties": {
    "addr:full":"5913 Greenlawn Drive Bethesda MD 20814",
    "addr:housenumber":"5913",
    "addr:postcode":"20814",
    "addr:street":"Greenlawn Drive",
    "iso:country":"US",
    "sg:address":"5913 Greenlawn Drive",
    "sg:city":"Bethesda",
    "sg:classifiers":[
        {
            "category":"Personal",
            "type":"Services"
        }
    ],
    "sg:phone":"+1 301 980 5804",
    "sg:postcode":"20814",
    "sg:province":"MD",
    "sg:tags":[
        "chef"
    ],
    "sg:website":"www.theservingspoon.com",
    "wof:name":"The Serving Spoon",
    "wof:placetype":"venue"
},
  "geometry": {"coordinates":[-77.118746,39.020957],"type":"Point"}
}