{
  "type": "Feature",
  "properties": {
    "iso:country":"US",
    "sg:address":"400 W Lexington St",
    "sg:city":"Baltimore",
    "sg:classifiers":[
        {
            "category":"Restaurant",
            "type":"Food & Drink"
        }
    ],
    "sg:phone":"+1 410 727 6388",
    "sg:postcode":"21201",
    "sg:province":"MD",
    "sg:tags":[
        "out"
    ],
    "wof:name":"Auntie Anne's Hand Rolled Soft",
    "wof:placetype":"venue"
},
  "geometry": {"coordinates":[-76.62242500000001,39.291229],"type":"Point"}
}