{
  "type": "Feature",
  "properties": {
    "addr:full":"2754 Conway Rd Odenton MD 21113",
    "addr:housenumber":"2754",
    "addr:postcode":"21113",
    "addr:street":"Conway Rd",
    "iso:country":"US",
    "sg:address":"2754 Conway Rd",
    "sg:city":"Odenton",
    "sg:classifiers":[
        {
            "category":"Manufacturing",
            "subcategory":"Buildings",
            "type":"Manufacturing & Wholesale Goods"
        },
        {
            "category":"Utilities",
            "subcategory":"Water",
            "type":"Services"
        },
        {
            "category":"Building & Trades",
            "subcategory":"Construction",
            "type":"Services"
        },
        {
            "category":"Utilities",
            "type":"Services"
        }
    ],
    "sg:phone":"+1 301 261 3580",
    "sg:postcode":"21113",
    "sg:province":"MD",
    "sg:tags":[
        "company-utility",
        "builder",
        "contractor",
        "home"
    ],
    "wof:name":"Frs Construction Co Inc",
    "wof:placetype":"venue"
},
  "geometry": {"coordinates":[-76.722658,39.02874],"type":"Point"}
}