{
  "type": "Feature",
  "properties": {
    "addr:full":"7900 Ritchie Hwy Glen Burnie MD 21061",
    "addr:housenumber":"7900",
    "addr:postcode":"21061",
    "addr:street":"Ritchie Hwy",
    "iso:country":"US",
    "sg:address":"7900 Ritchie Hwy",
    "sg:city":"Glen Burnie",
    "sg:classifiers":[
        {
            "category":"Bakery",
            "type":"Food & Drink"
        }
    ],
    "sg:menulink":"http://www.allmenus.com/md/lake-shore/219961-auntie-annes-pretzels/menu/",
    "sg:phone":"+1 410 761 4622",
    "sg:postcode":"21061",
    "sg:province":"MD",
    "sg:tags":[
        "american",
        "pastry"
    ],
    "wof:name":"Auntie Anne's Pretzels",
    "wof:placetype":"venue"
},
  "geometry": {"coordinates":[-76.602881,39.140553],"type":"Point"}
}