{
  "type": "Feature",
  "properties": {
    "iso:country":"US",
    "sg:address":"4100 Pennington Ave",
    "sg:city":"Curtis Bay",
    "sg:classifiers":[
        {
            "category":"Farming",
            "subcategory":"Farm",
            "type":"Manufacturing & Wholesale Goods"
        }
    ],
    "sg:phone":"+1 410 355 6223",
    "sg:postcode":"21226",
    "sg:province":"MD",
    "wof:name":"Bell Farm Estates",
    "wof:placetype":"venue"
},
  "geometry": {"coordinates":[-76.58869,39.227608],"type":"Point"}
}