{
  "type": "Feature",
  "properties": {
    "addr:full":"16904 Hughes Rd Poolesville MD 20837",
    "addr:housenumber":"16904",
    "addr:postcode":"20837",
    "addr:street":"Hughes Rd",
    "iso:country":"US",
    "sg:address":"16904 Hughes Rd",
    "sg:city":"Poolesville",
    "sg:classifiers":[
        {
            "category":"Social Services",
            "type":"Services"
        }
    ],
    "sg:phone":"+1 301 353 0230",
    "sg:postcode":"20837",
    "sg:province":"MD",
    "sg:tags":[
        "organization",
        "welfare"
    ],
    "wof:name":"Catholic Relief Svc",
    "wof:placetype":"venue"
},
  "geometry": {"coordinates":[-77.40642,39.128796],"type":"Point"}
}