{
  "type": "Feature",
  "properties": {
    "addr:full":"5820 Gwynn Oak Ave Gwynn Oak MD 21207",
    "addr:housenumber":"5820",
    "addr:postcode":"21207",
    "addr:street":"Gwynn Oak Ave",
    "iso:country":"US",
    "sg:address":"5820 Gwynn Oak Ave",
    "sg:city":"Gwynn Oak",
    "sg:classifiers":[
        {
            "category":"Organizations",
            "subcategory":"Religious Organization",
            "type":"Services"
        }
    ],
    "sg:phone":"+1 410 281 9888",
    "sg:postcode":"21207",
    "sg:province":"MD",
    "sg:tags":[
        "church"
    ],
    "wof:name":"New Life Mt Calvary Holy Ch",
    "wof:placetype":"venue"
},
  "geometry": {"coordinates":[-76.712183,39.325865],"type":"Point"}
}