{
  "type": "Feature",
  "properties": {
    "addr:full":"6211 8th St NW Washington MD 20011",
    "addr:housenumber":"6211",
    "addr:postcode":"20011",
    "addr:street":"8Th St Nw",
    "iso:country":"US",
    "sg:address":"6211 8th St NW",
    "sg:city":"Washington",
    "sg:classifiers":[
        {
            "category":"Banks & Credit Unions",
            "subcategory":"Investment Brokerage",
            "type":"Services"
        }
    ],
    "sg:phone":"+1 202 722 1440",
    "sg:postcode":"20011",
    "sg:province":"MD",
    "sg:tags":[
        "advisory",
        "financial"
    ],
    "wof:name":"Option 1 Financial",
    "wof:placetype":"venue"
},
  "geometry": {"coordinates":[-77.02420499999999,38.964953],"type":"Point"}
}