{
  "type": "Feature",
  "properties": {
    "iso:country":"US",
    "sg:address":"7823 Riverdale Rd",
    "sg:city":"New Carrolltn",
    "sg:classifiers":[
        {
            "category":"Social Services",
            "subcategory":"Child Care",
            "type":"Services"
        }
    ],
    "sg:phone":"+1 301 577 1868",
    "sg:postcode":"20784",
    "sg:province":"MD",
    "sg:tags":[
        "day"
    ],
    "wof:name":"New Carrollton Early Learning Center",
    "wof:placetype":"venue"
},
  "geometry": {"coordinates":[-76.87490099999999,38.9585],"type":"Point"}
}