{
  "type": "Feature",
  "properties": {
    "iso:country":"US",
    "sg:address":"12 Emala Ave",
    "sg:city":"Middle River",
    "sg:classifiers":[
        {
            "category":"Manufacturing",
            "subcategory":"Tools & Machinery",
            "type":"Manufacturing & Wholesale Goods"
        }
    ],
    "sg:phone":"+1 410 780 7022",
    "sg:postcode":"21220",
    "sg:province":"MD",
    "sg:tags":[
        "machine",
        "shop"
    ],
    "wof:name":"Edge Machine",
    "wof:placetype":"venue"
},
  "geometry": {"coordinates":[-76.414017,39.334986],"type":"Point"}
}