{
  "type": "Feature",
  "properties": {
    "iso:country":"US",
    "sg:address":"7501 Greenway Center Dr # 720",
    "sg:city":"Greenbelt",
    "sg:classifiers":[
        {
            "category":"Shopping",
            "subcategory":"Clothing, Apparel, & Fashions",
            "type":"Retail Goods"
        }
    ],
    "sg:phone":"+1 301 474 8700",
    "sg:postcode":"20770",
    "sg:province":"MD",
    "sg:tags":[
        "work",
        "uniform",
        "clothes"
    ],
    "wof:name":"Uniform Intermodal Interchange Agreement",
    "wof:placetype":"venue"
},
  "geometry": {"coordinates":[-76.878776,38.991718],"type":"Point"}
}