{
  "type": "Feature",
  "properties": {
    "iso:country":"US",
    "sg:address":"5619 Monroe St",
    "sg:city":"Hyattsville",
    "sg:classifiers":[
        {
            "category":"Building & Trades",
            "subcategory":"Cleaning & Sanitation",
            "type":"Services"
        }
    ],
    "sg:phone":"+1 301 277 6734",
    "sg:postcode":"20784",
    "sg:province":"MD",
    "wof:name":"Strazae Cleaning Service",
    "wof:placetype":"venue"
},
  "geometry": {"coordinates":[-76.92178199999999,38.933678],"type":"Point"}
}