{
  "type": "Feature",
  "properties": {
    "addr:full":"4522 Saint Barnabas Rd Temple Hills MD 20748",
    "addr:housenumber":"4522",
    "addr:postcode":"20748",
    "addr:street":"Saint Barnabas Rd",
    "iso:country":"US",
    "sg:address":"4522 Saint Barnabas Rd",
    "sg:city":"Temple Hills",
    "sg:classifiers":[
        {
            "category":"Personal",
            "subcategory":"Nail Salon",
            "type":"Services"
        }
    ],
    "sg:phone":"+1 301 702 0377",
    "sg:postcode":"20748",
    "sg:province":"MD",
    "wof:name":"Pretty Nails",
    "wof:placetype":"venue"
},
  "geometry": {"coordinates":[-76.944603,38.827099],"type":"Point"}
}