{
  "type": "Feature",
  "properties": {
    "iso:country":"US",
    "sg:address":"14605 Baltimore Ave",
    "sg:city":"Laurel",
    "sg:classifiers":[
        {
            "category":"Restaurant",
            "type":"Food & Drink"
        }
    ],
    "sg:phone":"+1 301 490 9949",
    "sg:postcode":"20707",
    "sg:province":"MD",
    "sg:tags":[
        "pakistani",
        "indian"
    ],
    "wof:name":"India Gate Indian Cuisine",
    "wof:placetype":"venue"
},
  "geometry": {"coordinates":[-76.858704,39.090199],"type":"Point"}
}