{
  "type": "Feature",
  "properties": {
    "iso:country":"US",
    "sg:address":"849 International Dr",
    "sg:city":"Linthicum Hts",
    "sg:classifiers":[
        {
            "category":"Professional",
            "subcategory":"Management & Consulting",
            "type":"Services"
        }
    ],
    "sg:phone":"+1 410 694 0240",
    "sg:postcode":"21090",
    "sg:province":"MD",
    "sg:tags":[
        "consultant",
        "business"
    ],
    "sg:website":"www.exceptionalsoftware.com",
    "wof:name":"Exceptional Software Strtgs",
    "wof:placetype":"venue"
},
  "geometry": {"coordinates":[-76.674485,39.206326],"type":"Point"}
}