{
  "type": "Feature",
  "properties": {
    "iso:country":"US",
    "sg:address":"22590 Bay Shore Rd",
    "sg:city":"Chestertown",
    "sg:classifiers":[
        {
            "category":"Building & Trades",
            "subcategory":"Cleaning & Sanitation",
            "type":"Services"
        }
    ],
    "sg:phone":"+1 410 778 2584",
    "sg:postcode":"21620",
    "sg:province":"MD",
    "sg:tags":[
        "janitor"
    ],
    "wof:name":"Busy Beetle Window Cleaning",
    "wof:placetype":"venue"
},
  "geometry": {"coordinates":[-76.19452,39.229967],"type":"Point"}
}