{
  "type": "Feature",
  "properties": {
    "addr:full":"7523 Sharpsburg Pike Boonsboro MD 21713",
    "addr:housenumber":"7523",
    "addr:postcode":"21713",
    "addr:street":"Sharpsburg Pike",
    "iso:country":"US",
    "sg:address":"7523 Sharpsburg Pike",
    "sg:city":"Boonsboro",
    "sg:classifiers":[
        {
            "category":"Building & Trades",
            "subcategory":"Construction",
            "type":"Services"
        }
    ],
    "sg:phone":"+1 301 432 5872",
    "sg:postcode":"21713",
    "sg:province":"MD",
    "sg:tags":[
        "masonry",
        "contractor"
    ],
    "wof:name":"Smith Masonry",
    "wof:placetype":"venue"
},
  "geometry": {"coordinates":[-77.74392400000001,39.519992],"type":"Point"}
}