{
  "type": "Feature",
  "properties": {
    "iso:country":"US",
    "sg:address":"211 N Frederick Ave Ste C",
    "sg:city":"Gaithersburg",
    "sg:phone":"+1 301 963 6400",
    "sg:postcode":"20877",
    "sg:province":"MD",
    "sg:website":"http://www.starvinmarvinspizza.com",
    "wof:name":"Starvin Marvin Pizza & Subs",
    "wof:placetype":"venue"
},
  "geometry": {"coordinates":[-77.201618,39.143962],"type":"Point"}
}