{
  "type": "Feature",
  "properties": {
    "addr:full":"4814 Silver Hill Rd Suitland MD 20746",
    "addr:housenumber":"4814",
    "addr:postcode":"20746",
    "addr:street":"Silver Hill Rd",
    "iso:country":"US",
    "sg:address":"4814 Silver Hill Rd",
    "sg:city":"Suitland",
    "sg:classifiers":[
        {
            "category":"Health Services",
            "subcategory":"Doctor",
            "type":"Services"
        }
    ],
    "sg:phone":"+1 301 568 8991",
    "sg:postcode":"20746",
    "sg:province":"MD",
    "sg:tags":[
        "dentist"
    ],
    "wof:name":"Suitland Dental Ctr",
    "wof:placetype":"venue"
},
  "geometry": {"coordinates":[-76.922318,38.851109],"type":"Point"}
}