{
  "type": "Feature",
  "properties": {
    "addr:full":"1625 N Wolfe St Baltimore MD 21213",
    "addr:housenumber":"1625",
    "addr:postcode":"21213",
    "addr:street":"N Wolfe St",
    "iso:country":"US",
    "sg:address":"1625 N Wolfe St",
    "sg:city":"Baltimore",
    "sg:classifiers":[
        {
            "category":"Real Estate",
            "subcategory":"Real Estate Agent",
            "type":"Services"
        }
    ],
    "sg:phone":"+1 410 276 3143",
    "sg:postcode":"21213",
    "sg:province":"MD",
    "wof:name":"Warrington Smith Properties",
    "wof:placetype":"venue"
},
  "geometry": {"coordinates":[-76.59151199999999,39.309485],"type":"Point"}
}