{
  "type": "Feature",
  "properties": {
    "iso:country":"US",
    "sg:address":"10807 Falls Rd",
    "sg:city":"Timonium",
    "sg:classifiers":[
        {
            "category":"Health Services",
            "subcategory":"Doctor",
            "type":"Services"
        }
    ],
    "sg:phone":"+1 410 821 8800",
    "sg:postcode":"21093",
    "sg:province":"MD",
    "sg:tags":[
        "dentist"
    ],
    "wof:name":"Feldman Sachs & Fitzgerald",
    "wof:placetype":"venue"
},
  "geometry": {"coordinates":[-76.669985,39.420328],"type":"Point"}
}