{
  "type": "Feature",
  "properties": {
    "addr:full":"231 Skipjack Rd Prince Frederick MD 20678",
    "addr:housenumber":"231",
    "addr:postcode":"20678",
    "addr:street":"Skipjack Rd",
    "iso:country":"US",
    "sg:address":"231 Skipjack Rd",
    "sg:city":"Prince Frederick",
    "sg:classifiers":[
        {
            "category":"Professional",
            "subcategory":"Advertising",
            "type":"Services"
        }
    ],
    "sg:phone":"+1 301 855 1700",
    "sg:postcode":"20678",
    "sg:province":"MD",
    "sg:tags":[
        "mail"
    ],
    "sg:website":"www.dmgroup.com",
    "wof:name":"Direct Mail Lithographers Inc",
    "wof:placetype":"venue"
},
  "geometry": {"coordinates":[-76.641031,38.511642],"type":"Point"}
}