{
  "type": "Feature",
  "properties": {
    "iso:country":"US",
    "sg:address":"6828 Race Track Rd",
    "sg:city":"Bowie",
    "sg:classifiers":[
        {
            "category":"Shopping",
            "subcategory":"Books",
            "type":"Retail Goods"
        }
    ],
    "sg:phone":"+1 301 352 0446",
    "sg:postcode":"20715",
    "sg:province":"MD",
    "sg:tags":[
        "dealer"
    ],
    "wof:name":"Crown Books",
    "wof:placetype":"venue"
},
  "geometry": {"coordinates":[-76.72973,38.984303],"type":"Point"}
}