{
  "type": "Feature",
  "properties": {
    "iso:country":"US",
    "sg:address":"3830 Clarks Point Rd",
    "sg:city":"Baltimore",
    "sg:classifiers":[
        {
            "category":"Sports & Exercise",
            "subcategory":"Bowling",
            "type":"Entertainment"
        }
    ],
    "sg:phone":"+1 410 344 0833",
    "sg:postcode":"21220",
    "sg:province":"MD",
    "sg:tags":[
        "equipment",
        "lane",
        "related"
    ],
    "wof:name":"Cicchini Bowling Services",
    "wof:placetype":"venue"
},
  "geometry": {"coordinates":[-76.38521,39.322155],"type":"Point"}
}