{
  "type": "Feature",
  "properties": {
    "iso:country":"US",
    "sg:address":"1504 Quarry Dr",
    "sg:city":"Edgewood",
    "sg:classifiers":[
        {
            "category":"Manufacturing",
            "subcategory":"Printing",
            "type":"Manufacturing & Wholesale Goods"
        }
    ],
    "sg:phone":"+1 410 676 9258",
    "sg:postcode":"21040",
    "sg:province":"MD",
    "sg:tags":[
        "printer"
    ],
    "sg:website":"www.harland.net",
    "wof:name":"John H Harland Co",
    "wof:placetype":"venue"
},
  "geometry": {"coordinates":[-76.314268,39.447405],"type":"Point"}
}