{
  "type": "Feature",
  "properties": {
    "iso:country":"US",
    "sg:address":"5100 Brookwood Rd",
    "sg:city":"Brooklyn",
    "sg:classifiers":[
        {
            "category":"Building & Trades",
            "subcategory":"Electrical",
            "type":"Services"
        }
    ],
    "sg:phone":"+1 443 919 1085",
    "sg:postcode":"21225",
    "sg:province":"MD",
    "sg:tags":[
        "electrician"
    ],
    "wof:name":"L L C Darsec",
    "wof:placetype":"venue"
},
  "geometry": {"coordinates":[-76.609596,39.223598],"type":"Point"}
}