{
  "type": "Feature",
  "properties": {
    "addr:full":"2056 Mayflower Dr Silver Spring MD 20905",
    "addr:housenumber":"2056",
    "addr:postcode":"20905",
    "addr:street":"Mayflower Dr",
    "iso:country":"US",
    "sg:address":"2056 Mayflower Dr",
    "sg:city":"Silver Spring",
    "sg:classifiers":[
        {
            "category":"Professional",
            "subcategory":"Engineering",
            "type":"Services"
        }
    ],
    "sg:phone":"+1 301 219 2797",
    "sg:postcode":"20905",
    "sg:province":"MD",
    "wof:name":"AMA & Associates Inc",
    "wof:placetype":"venue"
},
  "geometry": {"coordinates":[-76.96830799999999,39.099491],"type":"Point"}
}