{
  "type": "Feature",
  "properties": {
    "iso:country":"US",
    "sg:address":"8329 Liberty Rd",
    "sg:city":"Baltimore",
    "sg:classifiers":[
        {
            "category":"Organizations",
            "subcategory":"Religious Organization",
            "type":"Services"
        }
    ],
    "sg:phone":"+1 410 922 8863",
    "sg:postcode":"21244",
    "sg:province":"MD",
    "sg:tags":[
        "clergy"
    ],
    "wof:name":"Pierce Keyser",
    "wof:placetype":"venue"
},
  "geometry": {"coordinates":[-76.770725,39.358276],"type":"Point"}
}