{
  "type": "Feature",
  "properties": {
    "addr:full":"45155 First Colony Way California MD 20619",
    "addr:housenumber":"45155",
    "addr:postcode":"20619",
    "addr:street":"First Colony Way",
    "iso:country":"US",
    "sg:address":"45155 First Colony Way",
    "sg:city":"California",
    "sg:classifiers":[
        {
            "category":"Shopping",
            "subcategory":"Optical Goods",
            "type":"Retail Goods"
        }
    ],
    "sg:phone":"+1 301 862 4718",
    "sg:postcode":"20619",
    "sg:province":"MD",
    "wof:name":"Target Optical",
    "wof:placetype":"venue"
},
  "geometry": {"coordinates":[-76.51596499999999,38.298207],"type":"Point"}
}