{
  "type": "Feature",
  "properties": {
    "addr:full":"5004 Honeygo Center Dr Perry Hall MD 21128",
    "addr:housenumber":"5004",
    "addr:postcode":"21128",
    "addr:street":"Honeygo Center Dr",
    "iso:country":"US",
    "sg:address":"5004 Honeygo Center Dr",
    "sg:city":"Perry Hall",
    "sg:classifiers":[
        {
            "category":"Food & Beverages",
            "subcategory":"Liquor & Beverages",
            "type":"Retail Goods"
        }
    ],
    "sg:phone":"+1 410 529 5500",
    "sg:postcode":"21128",
    "sg:province":"MD",
    "sg:tags":[
        "beer",
        "spirit",
        "wine"
    ],
    "sg:website":"www.honeygowines.com/",
    "wof:name":"Honeygo Wine and Spirits",
    "wof:placetype":"venue"
},
  "geometry": {"coordinates":[-76.44456099999999,39.405119],"type":"Point"}
}