{
  "type": "Feature",
  "properties": {
    "addr:full":"22911 Jefferson Blvd Smithsburg MD 21783",
    "addr:housenumber":"22911",
    "addr:postcode":"21783",
    "addr:street":"Jefferson Blvd",
    "iso:country":"US",
    "sg:address":"22911 Jefferson Blvd",
    "sg:city":"Smithsburg",
    "sg:classifiers":[
        {
            "category":"Health Services",
            "subcategory":"Doctor",
            "type":"Services"
        }
    ],
    "sg:phone":"+1 301 824 3343",
    "sg:postcode":"21783",
    "sg:province":"MD",
    "sg:tags":[
        "medicine",
        "practice",
        "internal",
        "family"
    ],
    "wof:name":"Holtsclaw John D",
    "wof:placetype":"venue"
},
  "geometry": {"coordinates":[-77.570702,39.646198],"type":"Point"}
}