{
  "type": "Feature",
  "properties": {
    "addr:full":"12020 Greenspring Ave Owings Mills MD 21117",
    "addr:housenumber":"12020",
    "addr:postcode":"21117",
    "addr:street":"Greenspring Ave",
    "iso:country":"US",
    "sg:address":"12020 Greenspring Ave",
    "sg:city":"Owings Mills",
    "sg:classifiers":[
        {
            "category":"Government",
            "subcategory":"Fire Station",
            "type":"Public Place"
        }
    ],
    "sg:phone":"+1 410 252 9734",
    "sg:postcode":"21117",
    "sg:province":"MD",
    "sg:tags":[
        "protection",
        "association"
    ],
    "wof:name":"Chestnut Ridge Vlntr Fire Dept",
    "wof:placetype":"venue"
},
  "geometry": {"coordinates":[-76.72800599999999,39.45581],"type":"Point"}
}