{
  "type": "Feature",
  "properties": {
    "iso:country":"US",
    "sg:address":"7501 Assateague Dr",
    "sg:city":"Jessup",
    "sg:classifiers":[
        {
            "category":"Freight",
            "type":"Transportation"
        }
    ],
    "sg:phone":"+1 410 799 9093",
    "sg:postcode":"20794",
    "sg:province":"MD",
    "wof:name":"Arnold Transportation Inc",
    "wof:placetype":"venue"
},
  "geometry": {"coordinates":[-76.78363400000001,39.166272],"type":"Point"}
}