{
  "type": "Feature",
  "properties": {
    "addr:full":"118 East St Frederick MD 21701",
    "addr:housenumber":"118",
    "addr:postcode":"21701",
    "addr:street":"East St",
    "iso:country":"US",
    "sg:address":"118 East St",
    "sg:city":"Frederick",
    "sg:classifiers":[
        {
            "category":"Shopping",
            "type":"Retail Goods"
        }
    ],
    "sg:phone":"+1 301 668 2787",
    "sg:postcode":"21701",
    "sg:province":"MD",
    "sg:tags":[
        "art",
        "gallery",
        "dealer"
    ],
    "wof:name":"Lavendar Hollow Gallery",
    "wof:placetype":"venue"
},
  "geometry": {"coordinates":[-77.40502600000001,39.416001],"type":"Point"}
}