{
  "type": "Feature",
  "properties": {
    "addr:full":"130 Holiday Ct Annapolis MD 21401",
    "addr:housenumber":"130",
    "addr:postcode":"21401",
    "addr:street":"Holiday Ct",
    "iso:country":"US",
    "sg:address":"130 Holiday Ct",
    "sg:city":"Annapolis",
    "sg:classifiers":[
        {
            "category":"Organizations",
            "subcategory":"Professional Association",
            "type":"Services"
        }
    ],
    "sg:phone":"+1 410 266 3766",
    "sg:postcode":"21401",
    "sg:province":"MD",
    "sg:website":"www.cesb.org",
    "wof:name":"Council Of Engineering",
    "wof:placetype":"venue"
},
  "geometry": {"coordinates":[-76.5463,38.982118],"type":"Point"}
}