{
  "type": "Feature",
  "properties": {
    "addr:full":"12615 Marlton Center Dr Upper Marlboro MD 20772",
    "addr:housenumber":"12615",
    "addr:postcode":"20772",
    "addr:street":"Marlton Center Dr",
    "iso:country":"US",
    "sg:address":"12615 Marlton Center Dr",
    "sg:city":"Upper Marlboro",
    "sg:classifiers":[
        {
            "category":"Shopping",
            "subcategory":"Gifts & Souvenirs",
            "type":"Retail Goods"
        }
    ],
    "sg:phone":"+1 301 780 3662",
    "sg:postcode":"20772",
    "sg:province":"MD",
    "wof:name":"Basketful 0f Blessng",
    "wof:placetype":"venue"
},
  "geometry": {"coordinates":[-76.783608,38.769795],"type":"Point"}
}