{
  "type": "Feature",
  "properties": {
    "iso:country":"US",
    "sg:address":"959 Gorsuch Ave",
    "sg:city":"Baltimore",
    "sg:classifiers":[
        {
            "category":"Restaurant",
            "type":"Food & Drink"
        }
    ],
    "sg:phone":"+1 410 243 4510",
    "sg:postcode":"21218",
    "sg:province":"MD",
    "sg:tags":[
        "grocery",
        "eating"
    ],
    "wof:name":"K & C",
    "wof:placetype":"venue"
},
  "geometry": {"coordinates":[-76.603359,39.32603],"type":"Point"}
}