{
  "type": "Feature",
  "properties": {
    "iso:country":"US",
    "sg:address":"11410 Old Georgetown Rd",
    "sg:city":"Rockville",
    "sg:classifiers":[
        {
            "category":"Communications",
            "subcategory":"Film & Video Production",
            "type":"Services"
        }
    ],
    "sg:phone":"+1 301 984 2330",
    "sg:postcode":"20852",
    "sg:province":"MD",
    "sg:tags":[
        "taping"
    ],
    "wof:name":"NFW Videographic Svc Inc",
    "wof:placetype":"venue"
},
  "geometry": {"coordinates":[-77.120585,39.044735],"type":"Point"}
}