{
  "type": "Feature",
  "properties": {
    "addr:full":"6731 Columbia Gateway Dr Ste 300A Columbia MD 21046",
    "addr:housenumber":"6731",
    "addr:postcode":"21046",
    "addr:street":"Columbia Gateway Dr Ste 300A",
    "iso:country":"US",
    "sg:address":"6731 Columbia Gateway Dr Ste 300A",
    "sg:city":"Columbia",
    "sg:classifiers":[
        {
            "category":"Professional",
            "subcategory":"Research",
            "type":"Services"
        }
    ],
    "sg:phone":"+1 443 285 0753",
    "sg:postcode":"21046",
    "sg:province":"MD",
    "sg:tags":[
        "development",
        "technology-research"
    ],
    "wof:name":"Bridge Technology Corp",
    "wof:placetype":"venue"
},
  "geometry": {"coordinates":[-76.80427,39.183944],"type":"Point"}
}