{
  "type": "Feature",
  "properties": {
    "iso:country":"US",
    "sg:address":"7703 Belair Rd",
    "sg:city":"Baltimore",
    "sg:classifiers":[
        {
            "category":"Restaurant",
            "type":"Food & Drink"
        }
    ],
    "sg:phone":"+1 410 668 5053",
    "sg:postcode":"21236",
    "sg:province":"MD",
    "wof:name":"Schooners Restaurant & Lounge",
    "wof:placetype":"venue"
},
  "geometry": {"coordinates":[-76.517124,39.36674],"type":"Point"}
}