{
  "type": "Feature",
  "properties": {
    "iso:country":"US",
    "sg:address":"5401 Loch Raven Blvd",
    "sg:city":"Baltimore",
    "sg:classifiers":[
        {
            "category":"Social Services",
            "type":"Services"
        }
    ],
    "sg:phone":"+1 410 323 8564",
    "sg:postcode":"21239",
    "sg:province":"MD",
    "sg:tags":[
        "organization",
        "welfare"
    ],
    "wof:name":"Immigration Outreach Svc Ctr",
    "wof:placetype":"venue"
},
  "geometry": {"coordinates":[-76.58928899999999,39.358095],"type":"Point"}
}