{
  "type": "Feature",
  "properties": {
    "addr:full":"21030 Frederick Rd Germantown MD 20876",
    "addr:housenumber":"21030",
    "addr:postcode":"20876",
    "addr:street":"Frederick Rd",
    "iso:country":"US",
    "sg:address":"21030 Frederick Rd",
    "sg:city":"Germantown",
    "sg:classifiers":[
        {
            "category":"Personal",
            "subcategory":"Beauty Salon",
            "type":"Services"
        }
    ],
    "sg:phone":"+1 301 972 6500",
    "sg:postcode":"20876",
    "sg:province":"MD",
    "wof:name":"A 1 Nail Salon",
    "wof:placetype":"venue"
},
  "geometry": {"coordinates":[-77.245897,39.203461],"type":"Point"}
}