{
  "type": "Feature",
  "properties": {
    "addr:full":"16900 Vine Ct Olney MD 20832",
    "addr:housenumber":"16900",
    "addr:postcode":"20832",
    "addr:street":"Vine Ct",
    "iso:country":"US",
    "sg:address":"16900 Vine Ct",
    "sg:city":"Olney",
    "sg:classifiers":[
        {
            "category":"Professional",
            "subcategory":"Lawyer & Legal Services",
            "type":"Services"
        }
    ],
    "sg:phone":"+1 301 774 9544",
    "sg:postcode":"20832",
    "sg:province":"MD",
    "sg:tags":[
        "attorney"
    ],
    "wof:name":"Philip Beram",
    "wof:placetype":"venue"
},
  "geometry": {"coordinates":[-77.083084,39.135871],"type":"Point"}
}