{
  "type": "Feature",
  "properties": {
    "addr:full":"9713 Fox Run Dr Clinton MD 20735",
    "addr:housenumber":"9713",
    "addr:postcode":"20735",
    "addr:street":"Fox Run Dr",
    "iso:country":"US",
    "sg:address":"9713 Fox Run Dr",
    "sg:city":"Clinton",
    "sg:classifiers":[
        {
            "category":"Health Services",
            "subcategory":"Clinic",
            "type":"Services"
        }
    ],
    "sg:phone":"+1 301 856 4361",
    "sg:postcode":"20735",
    "sg:province":"MD",
    "sg:tags":[
        "home"
    ],
    "wof:name":"Complete Respiratory Care Inc",
    "wof:placetype":"venue"
},
  "geometry": {"coordinates":[-76.87395100000001,38.756121],"type":"Point"}
}