{
  "type": "Feature",
  "properties": {
    "iso:country":"US",
    "sg:address":"8728 Piney Branch Rd",
    "sg:city":"Silver Spring",
    "sg:classifiers":[
        {
            "category":"Personal",
            "subcategory":"Beauty Salon",
            "type":"Services"
        }
    ],
    "sg:phone":"+1 301 445 5569",
    "sg:postcode":"20901",
    "sg:province":"MD",
    "wof:name":"Estela's Hair Salon",
    "wof:placetype":"venue"
},
  "geometry": {"coordinates":[-76.995384,38.999626],"type":"Point"}
}