{
  "type": "Feature",
  "properties": {
    "addr:full":"4658 Suitland Rd Suitland MD 20746",
    "addr:housenumber":"4658",
    "addr:postcode":"20746",
    "addr:street":"Suitland Rd",
    "iso:country":"US",
    "sg:address":"4658 Suitland Rd",
    "sg:city":"Suitland",
    "sg:classifiers":[
        {
            "category":"Shopping",
            "subcategory":"Jewelry",
            "type":"Retail Goods"
        }
    ],
    "sg:phone":"+1 301 420 3518",
    "sg:postcode":"20746",
    "sg:province":"MD",
    "wof:name":"Suitland Pawnbrokers",
    "wof:placetype":"venue"
},
  "geometry": {"coordinates":[-76.926697,38.849602],"type":"Point"}
}