{
  "type": "Feature",
  "properties": {
    "iso:country":"US",
    "sg:address":"944 Bishop Walsh Rd",
    "sg:city":"Cumberland",
    "sg:classifiers":[
        {
            "category":"Health Services",
            "subcategory":"Medical Lab",
            "type":"Services"
        }
    ],
    "sg:phone":"+1 301 777 2536",
    "sg:postcode":"21502",
    "sg:province":"MD",
    "sg:tags":[
        "laboratory"
    ],
    "wof:name":"Laboratory Corporation America",
    "wof:placetype":"venue"
},
  "geometry": {"coordinates":[-78.797512,39.651933],"type":"Point"}
}