{
  "type": "Feature",
  "properties": {
    "addr:full":"2525 Farringdon Rd Baltimore MD 21209",
    "addr:housenumber":"2525",
    "addr:postcode":"21209",
    "addr:street":"Farringdon Rd",
    "iso:country":"US",
    "sg:address":"2525 Farringdon Rd",
    "sg:city":"Baltimore",
    "sg:classifiers":[
        {
            "category":"Professional",
            "subcategory":"Management & Consulting",
            "type":"Services"
        }
    ],
    "sg:phone":"+1 410 484 6851",
    "sg:postcode":"21209",
    "sg:province":"MD",
    "sg:tags":[
        "business"
    ],
    "wof:name":"Freedman Consulting",
    "wof:placetype":"venue"
},
  "geometry": {"coordinates":[-76.685479,39.372026],"type":"Point"}
}