{
  "type": "Feature",
  "properties": {
    "addr:full":"102 Reisterstown Rd Pikesville MD 21208",
    "addr:housenumber":"102",
    "addr:postcode":"21208",
    "addr:street":"Reisterstown Rd",
    "iso:country":"US",
    "sg:address":"102 Reisterstown Rd",
    "sg:city":"Pikesville",
    "sg:classifiers":[
        {
            "category":"Restaurant",
            "type":"Food & Drink"
        }
    ],
    "sg:phone":"+1 410 580 9477",
    "sg:postcode":"21208",
    "sg:province":"MD",
    "wof:name":"Sabra Grille",
    "wof:placetype":"venue"
},
  "geometry": {"coordinates":[-76.712502,39.363998],"type":"Point"}
}