{
  "type": "Feature",
  "properties": {
    "addr:full":"948 Washington Ave Chestertown MD 21620",
    "addr:housenumber":"948",
    "addr:postcode":"21620",
    "addr:street":"Washington Ave",
    "iso:country":"US",
    "sg:address":"948 Washington Ave",
    "sg:city":"Chestertown",
    "sg:classifiers":[
        {
            "category":"Insurance",
            "subcategory":"Insurance Agent",
            "type":"Services"
        }
    ],
    "sg:phone":"+1 410 778 0647",
    "sg:postcode":"21620",
    "sg:province":"MD",
    "wof:name":"State Farm Insurance",
    "wof:placetype":"venue"
},
  "geometry": {"coordinates":[-76.068667,39.236796],"type":"Point"}
}