{
  "type": "Feature",
  "properties": {
    "addr:full":"3341 Cheverly Ct Abingdon MD 21009",
    "addr:housenumber":"3341",
    "addr:postcode":"21009",
    "addr:street":"Cheverly Ct",
    "iso:country":"US",
    "sg:address":"3341 Cheverly Ct",
    "sg:city":"Abingdon",
    "sg:classifiers":[
        {
            "category":"Personal",
            "type":"Services"
        }
    ],
    "sg:phone":"+1 410 569 7500",
    "sg:postcode":"21009",
    "sg:province":"MD",
    "sg:tags":[
        "consultant",
        "wedding"
    ],
    "wof:name":"2 Have & 2 Hold",
    "wof:placetype":"venue"
},
  "geometry": {"coordinates":[-76.317437,39.471252],"type":"Point"}
}