{
  "type": "Feature",
  "properties": {
    "addr:full":"12051 Rockville Pike Rockville MD 20852",
    "addr:housenumber":"12051",
    "addr:postcode":"20852",
    "addr:street":"Rockville Pike",
    "iso:country":"US",
    "sg:address":"12051 Rockville Pike",
    "sg:city":"Rockville",
    "sg:classifiers":[
        {
            "category":"Banks & Credit Unions",
            "subcategory":"Bank",
            "type":"Services"
        }
    ],
    "sg:phone":"+1 301 984 1281",
    "sg:postcode":"20852",
    "sg:province":"MD",
    "wof:name":"Chevy Chase Bank",
    "wof:placetype":"venue"
},
  "geometry": {"coordinates":[-77.11765699999999,39.054739],"type":"Point"}
}