{
  "type": "Feature",
  "properties": {
    "addr:full":"400 Overhill Rd Baltimore MD 21210",
    "addr:housenumber":"400",
    "addr:postcode":"21210",
    "addr:street":"Overhill Rd",
    "iso:country":"US",
    "sg:address":"400 Overhill Rd",
    "sg:city":"Baltimore",
    "sg:classifiers":[
        {
            "category":"Organizations",
            "subcategory":"Community Association",
            "type":"Services"
        }
    ],
    "sg:phone":"+1 410 889 1418",
    "sg:postcode":"21210",
    "sg:province":"MD",
    "sg:tags":[
        "opera"
    ],
    "wof:name":"Singing Opera Bears",
    "wof:placetype":"venue"
},
  "geometry": {"coordinates":[-76.62979900000001,39.34087],"type":"Point"}
}