{
  "type": "Feature",
  "properties": {
    "iso:country":"US",
    "sg:address":"11129 Arroyo Dr",
    "sg:city":"Rockville",
    "sg:classifiers":[
        {
            "category":"Professional",
            "subcategory":"Art Services",
            "type":"Services"
        }
    ],
    "sg:phone":"+1 301 530 7800",
    "sg:postcode":"20852",
    "sg:province":"MD",
    "sg:tags":[
        "graphic",
        "designer"
    ],
    "wof:name":"Lazarus Design",
    "wof:placetype":"venue"
},
  "geometry": {"coordinates":[-77.134272,39.038852],"type":"Point"}
}