{
  "type": "Feature",
  "properties": {
    "addr:full":"702 Sturgis Pl Pikesville MD 21208",
    "addr:housenumber":"702",
    "addr:postcode":"21208",
    "addr:street":"Sturgis Pl",
    "iso:country":"US",
    "sg:address":"702 Sturgis Pl",
    "sg:city":"Pikesville",
    "sg:classifiers":[
        {
            "category":"Retail",
            "subcategory":"Repair Shop",
            "type":"Services"
        }
    ],
    "sg:phone":"+1 410 484 1838",
    "sg:postcode":"21208",
    "sg:province":"MD",
    "sg:tags":[
        "electrical"
    ],
    "wof:name":"S&B Quick Appliance LLC",
    "wof:placetype":"venue"
},
  "geometry": {"coordinates":[-76.73360099999999,39.360556],"type":"Point"}
}