{
  "type": "Feature",
  "properties": {
    "addr:full":"271 Kentlands Blvd Gaithersburg MD 20878",
    "addr:housenumber":"271",
    "addr:postcode":"20878",
    "addr:street":"Kentlands Blvd",
    "iso:country":"US",
    "sg:address":"271 Kentlands Blvd",
    "sg:city":"Gaithersburg",
    "sg:classifiers":[
        {
            "category":"Health Services",
            "subcategory":"Optometrist",
            "type":"Services"
        }
    ],
    "sg:phone":"+1 301 590 9191",
    "sg:postcode":"20878",
    "sg:province":"MD",
    "wof:name":"Hour Eyes",
    "wof:placetype":"venue"
},
  "geometry": {"coordinates":[-77.240979,39.124478],"type":"Point"}
}