{
  "type": "Feature",
  "properties": {
    "iso:country":"US",
    "sg:address":"5410 Lynview Ave",
    "sg:city":"Baltimore",
    "sg:classifiers":[
        {
            "category":"Retail",
            "subcategory":"Car Wash",
            "type":"Services"
        }
    ],
    "sg:phone":"+1 410 764 1051",
    "sg:postcode":"21215",
    "sg:province":"MD",
    "wof:name":"Tony Auto Detailing",
    "wof:placetype":"venue"
},
  "geometry": {"coordinates":[-76.689874,39.344804],"type":"Point"}
}