{
  "type": "Feature",
  "properties": {
    "addr:full":"2550 Edmondson Ave Baltimore MD 21223",
    "addr:housenumber":"2550",
    "addr:postcode":"21223",
    "addr:street":"Edmondson Ave",
    "iso:country":"US",
    "sg:address":"2550 Edmondson Ave",
    "sg:city":"Baltimore",
    "sg:classifiers":[
        {
            "category":"Food & Beverages",
            "subcategory":"Liquor & Beverages",
            "type":"Retail Goods"
        }
    ],
    "sg:phone":"+1 410 362 8292",
    "sg:postcode":"21223",
    "sg:province":"MD",
    "sg:tags":[
        "beer",
        "spirit",
        "wine"
    ],
    "wof:name":"The One Liquor",
    "wof:placetype":"venue"
},
  "geometry": {"coordinates":[-76.657999,39.294791],"type":"Point"}
}