{
  "type": "Feature",
  "properties": {
    "addr:full":"195 Gittings Ave Baltimore MD 21212",
    "addr:housenumber":"195",
    "addr:postcode":"21212",
    "addr:street":"Gittings Ave",
    "iso:country":"US",
    "sg:address":"195 Gittings Ave",
    "sg:city":"Baltimore",
    "sg:classifiers":[
        {
            "category":"Travel",
            "subcategory":"Travel Agent",
            "type":"Entertainment"
        }
    ],
    "sg:phone":"+1 410 433 9297",
    "sg:postcode":"21212",
    "sg:province":"MD",
    "sg:tags":[
        "agency",
        "services-commercial"
    ],
    "wof:name":"Bbnt Travel",
    "wof:placetype":"venue"
},
  "geometry": {"coordinates":[-76.618978,39.371452],"type":"Point"}
}