{
  "type": "Feature",
  "properties": {
    "iso:country":"US",
    "sg:address":"5951 Arbor St",
    "sg:city":"Hyattsville",
    "sg:classifiers":[
        {
            "category":"Building & Trades",
            "subcategory":"Electrical",
            "type":"Services"
        }
    ],
    "sg:phone":"+1 301 322 3900",
    "sg:postcode":"20781",
    "sg:province":"MD",
    "sg:tags":[
        "electrician"
    ],
    "wof:name":"Welbourne Electrical Services",
    "wof:placetype":"venue"
},
  "geometry": {"coordinates":[-76.91680100000001,38.918598],"type":"Point"}
}