{
  "type": "Feature",
  "properties": {
    "addr:full":"13 W Biddle St Baltimore MD 21201",
    "addr:housenumber":"13",
    "addr:postcode":"21201",
    "addr:street":"W Biddle St",
    "iso:country":"US",
    "sg:address":"13 W Biddle St",
    "sg:city":"Baltimore",
    "sg:classifiers":[
        {
            "category":"Organizations",
            "subcategory":"Religious Organization",
            "type":"Services"
        }
    ],
    "sg:phone":"+1 410 837 0333",
    "sg:postcode":"21201",
    "sg:province":"MD",
    "wof:name":"Eastern United Methdst Church",
    "wof:placetype":"venue"
},
  "geometry": {"coordinates":[-76.617074,39.303347],"type":"Point"}
}