{
  "type": "Feature",
  "properties": {
    "addr:full":"4618 Saint Barnabas Rd Temple Hills MD 20748",
    "addr:housenumber":"4618",
    "addr:postcode":"20748",
    "addr:street":"Saint Barnabas Rd",
    "iso:country":"US",
    "sg:address":"4618 Saint Barnabas Rd",
    "sg:city":"Temple Hills",
    "sg:classifiers":[
        {
            "category":"Home & Garden",
            "subcategory":"Furniture",
            "type":"Retail Goods"
        }
    ],
    "sg:phone":"+1 301 316 0020",
    "sg:postcode":"20748",
    "sg:province":"MD",
    "sg:tags":[
        "store"
    ],
    "wof:name":"Lamonarca Furniture Inc",
    "wof:placetype":"venue"
},
  "geometry": {"coordinates":[-76.945318,38.826082],"type":"Point"}
}