{
  "type": "Feature",
  "properties": {
    "addr:full":"115 Central Ave W Edgewater MD 21037",
    "addr:housenumber":"115",
    "addr:postcode":"21037",
    "addr:street":"Central Ave W",
    "iso:country":"US",
    "sg:address":"115 Central Ave W",
    "sg:city":"Edgewater",
    "sg:classifiers":[
        {
            "category":"Retail",
            "subcategory":"Auto Repair",
            "type":"Services"
        }
    ],
    "sg:phone":"+1 410 956 7688",
    "sg:postcode":"21037",
    "sg:province":"MD",
    "sg:tags":[
        "repairing",
        "automobile"
    ],
    "wof:name":"Patriot Auto Svc",
    "wof:placetype":"venue"
},
  "geometry": {"coordinates":[-76.582645,38.927336],"type":"Point"}
}