{
  "type": "Feature",
  "properties": {
    "addr:full":"814 Crystal Ct Gaithersburg MD 20878",
    "addr:housenumber":"814",
    "addr:postcode":"20878",
    "addr:street":"Crystal Ct",
    "iso:country":"US",
    "sg:address":"814 Crystal Ct",
    "sg:city":"Gaithersburg",
    "sg:classifiers":[
        {
            "category":"Social Services",
            "subcategory":"Retirement Home",
            "type":"Services"
        }
    ],
    "sg:phone":"+1 301 921 0834",
    "sg:postcode":"20878",
    "sg:province":"MD",
    "sg:tags":[
        "convalescent",
        "nursing"
    ],
    "wof:name":"Mont Hospice",
    "wof:placetype":"venue"
},
  "geometry": {"coordinates":[-77.237022,39.137478],"type":"Point"}
}