{
  "type": "Feature",
  "properties": {
    "addr:full":"22530 Gateway Center Dr Clarksburg MD 20871",
    "addr:housenumber":"22530",
    "addr:postcode":"20871",
    "addr:street":"Gateway Center Dr",
    "iso:country":"US",
    "sg:address":"22530 Gateway Center Dr",
    "sg:city":"Clarksburg",
    "sg:classifiers":[
        {
            "category":"Social Services",
            "type":"Services"
        },
        {
            "category":"Personal",
            "type":"Services"
        }
    ],
    "sg:phone":"+1 240 686 0572",
    "sg:postcode":"20871",
    "sg:province":"MD",
    "sg:tags":[
        "family",
        "counselors-licensed",
        "individual",
        "marriage",
        "child",
        "professional",
        "counselor"
    ],
    "wof:name":"The Family Services",
    "wof:placetype":"venue"
},
  "geometry": {"coordinates":[-77.277804,39.227095],"type":"Point"}
}