{
  "type": "Feature",
  "properties": {
    "addr:full":"8908 Scheurer St Upper Marlboro MD 20774",
    "addr:housenumber":"8908",
    "addr:postcode":"20774",
    "addr:street":"Scheurer St",
    "iso:country":"US",
    "sg:address":"8908 Scheurer St",
    "sg:city":"Upper Marlboro",
    "sg:classifiers":[
        {
            "category":"Manufacturing",
            "subcategory":"Printing",
            "type":"Manufacturing & Wholesale Goods"
        }
    ],
    "sg:phone":"+1 301 772 7229",
    "sg:postcode":"20774",
    "sg:province":"MD",
    "sg:tags":[
        "publishing"
    ],
    "wof:name":"V W Concepts",
    "wof:placetype":"venue"
},
  "geometry": {"coordinates":[-76.85316899999999,38.93486],"type":"Point"}
}