{
  "type": "Feature",
  "properties": {
    "addr:full":"6073 Flagstone Ct Frederick MD 21701",
    "addr:housenumber":"6073",
    "addr:postcode":"21701",
    "addr:street":"Flagstone Ct",
    "iso:country":"US",
    "sg:address":"6073 Flagstone Ct",
    "sg:city":"Frederick",
    "sg:classifiers":[
        {
            "category":"Manufacturing",
            "subcategory":"Electronics",
            "type":"Manufacturing & Wholesale Goods"
        }
    ],
    "sg:phone":"+1 301 620 9589",
    "sg:postcode":"21701",
    "sg:province":"MD",
    "sg:tags":[
        "equipment",
        "electronic",
        "telecommunication",
        "mfg"
    ],
    "wof:name":"Ameritec Corporation",
    "wof:placetype":"venue"
},
  "geometry": {"coordinates":[-77.347172,39.401237],"type":"Point"}
}