{
  "type": "Feature",
  "properties": {
    "iso:country":"US",
    "sg:address":"1028 Cosby Ave",
    "sg:city":"Cambridge",
    "sg:classifiers":[
        {
            "category":"Recreation",
            "type":"Entertainment"
        }
    ],
    "sg:phone":"+1 410 228 3947",
    "sg:postcode":"21613",
    "sg:province":"MD",
    "sg:tags":[
        "hall",
        "auditorium"
    ],
    "wof:name":"Cambridge Police Community Ctr",
    "wof:placetype":"venue"
},
  "geometry": {"coordinates":[-76.089147,38.570602],"type":"Point"}
}