{
  "type": "Feature",
  "properties": {
    "addr:full":"18991 Little Pond Ln Leonardtown MD 20650",
    "addr:housenumber":"18991",
    "addr:postcode":"20650",
    "addr:street":"Little Pond Ln",
    "iso:country":"US",
    "sg:address":"18991 Little Pond Ln",
    "sg:city":"Leonardtown",
    "sg:classifiers":[
        {
            "category":"Building & Trades",
            "subcategory":"Construction",
            "type":"Services"
        }
    ],
    "sg:phone":"+1 301 994 9101",
    "sg:postcode":"20650",
    "sg:province":"MD",
    "sg:tags":[
        "home",
        "improvement"
    ],
    "wof:name":"Homeworks Service Group",
    "wof:placetype":"venue"
},
  "geometry": {"coordinates":[-76.552845,38.188244],"type":"Point"}
}