{
  "type": "Feature",
  "properties": {
    "iso:country":"US",
    "sg:address":"4805 Berryhill Cir",
    "sg:city":"Perry Hall",
    "sg:classifiers":[
        {
            "category":"Real Estate",
            "subcategory":"Real Estate Operator",
            "type":"Services"
        }
    ],
    "sg:phone":"+1 410 931 2110",
    "sg:postcode":"21128",
    "sg:province":"MD",
    "sg:tags":[
        "apartment"
    ],
    "wof:name":"Quail Ridge Apartments",
    "wof:placetype":"venue"
},
  "geometry": {"coordinates":[-76.456655,39.38061],"type":"Point"}
}