{
  "type": "Feature",
  "properties": {
    "addr:full":"13600 King Charles Ter Fort Washington MD 20744",
    "addr:housenumber":"13600",
    "addr:postcode":"20744",
    "addr:street":"King Charles Ter",
    "iso:country":"US",
    "sg:address":"13600 King Charles Ter",
    "sg:city":"Fort Washington",
    "sg:classifiers":[
        {
            "category":"Restaurant",
            "type":"Food & Drink"
        }
    ],
    "sg:phone":"+1 301 292 5521",
    "sg:postcode":"20744",
    "sg:province":"MD",
    "wof:name":"Mary Proud Restaurant",
    "wof:placetype":"venue"
},
  "geometry": {"coordinates":[-77.02759399999999,38.703077],"type":"Point"}
}