{
  "type": "Feature",
  "properties": {
    "iso:country":"US",
    "sg:address":"13600 King Charles Ter",
    "sg:city":"Fort Washington",
    "sg:classifiers":[
        {
            "category":"Restaurant",
            "type":"Food & Drink"
        }
    ],
    "sg:phone":"+1 301 292 5521",
    "sg:postcode":"20744",
    "sg:province":"MD",
    "wof:name":"Mary Proud Restaurant",
    "wof:placetype":"venue"
},
  "geometry": {"coordinates":[-77.027594,38.703077],"type":"Point"}
}