{
  "type": "Feature",
  "properties": {
    "addr:full":"4601 N Park Ave Chevy Chase MD 20815",
    "addr:housenumber":"4601",
    "addr:postcode":"20815",
    "addr:street":"N Park Ave",
    "iso:country":"US",
    "sg:address":"4601 N Park Ave",
    "sg:city":"Chevy Chase",
    "sg:classifiers":[
        {
            "category":"Shopping",
            "subcategory":"Clothing, Apparel, & Fashions",
            "type":"Retail Goods"
        }
    ],
    "sg:phone":"+1 301 656 8515",
    "sg:postcode":"20815",
    "sg:province":"MD",
    "sg:tags":[
        "tailor"
    ],
    "wof:name":"J's Tailoring & Dressmaking",
    "wof:placetype":"venue"
},
  "geometry": {"coordinates":[-77.09099399999999,38.963485],"type":"Point"}
}