{
  "type": "Feature",
  "properties": {
    "iso:country":"US",
    "sg:address":"10010 Stedwick Rd",
    "sg:city":"Gaithersburg",
    "sg:classifiers":[
        {
            "category":"Shopping",
            "subcategory":"Used Merchandise",
            "type":"Retail Goods"
        }
    ],
    "sg:phone":"+1 301 869 1256",
    "sg:postcode":"20886",
    "sg:province":"MD",
    "sg:tags":[
        "book",
        "rare",
        "dealer"
    ],
    "wof:name":"Doris Frohnsdorff",
    "wof:placetype":"venue"
},
  "geometry": {"coordinates":[-77.205675,39.169854],"type":"Point"}
}