{
  "type": "Feature",
  "properties": {
    "addr:full":"3377 Donnell Dr Forestville MD 20747",
    "addr:housenumber":"3377",
    "addr:postcode":"20747",
    "addr:street":"Donnell Dr",
    "iso:country":"US",
    "sg:address":"3377 Donnell Dr",
    "sg:city":"Forestville",
    "sg:classifiers":[
        {
            "category":"Shopping",
            "subcategory":"Gifts & Souvenirs",
            "type":"Retail Goods"
        }
    ],
    "sg:phone":"+1 301 736 6299",
    "sg:postcode":"20747",
    "sg:province":"MD",
    "sg:tags":[
        "shop"
    ],
    "wof:name":"Cardamerica",
    "wof:placetype":"venue"
},
  "geometry": {"coordinates":[-76.885047,38.846382],"type":"Point"}
}