{
  "type": "Feature",
  "properties": {
    "iso:country":"US",
    "sg:address":"3774 Howard Ave",
    "sg:city":"Kensington",
    "sg:classifiers":[
        {
            "category":"Retail",
            "subcategory":"Repair Shop",
            "type":"Services"
        }
    ],
    "sg:phone":"+1 301 949 0490",
    "sg:postcode":"20895",
    "sg:province":"MD",
    "sg:tags":[
        "jewelry"
    ],
    "wof:name":"Raffie Jewelers",
    "wof:placetype":"venue"
},
  "geometry": {"coordinates":[-77.074203,39.028],"type":"Point"}
}