{
  "type": "Feature",
  "properties": {
    "iso:country":"US",
    "sg:address":"1901 Research Blvd",
    "sg:city":"Rockville",
    "sg:classifiers":[
        {
            "category":"Organizations",
            "subcategory":"Non-profit Organization",
            "type":"Services"
        }
    ],
    "sg:phone":"+1 301 309 3400",
    "sg:postcode":"20850",
    "sg:province":"MD",
    "wof:name":"TCAG",
    "wof:placetype":"venue"
},
  "geometry": {"coordinates":[-77.181369,39.0993],"type":"Point"}
}