{
  "type": "Feature",
  "properties": {
    "iso:country":"US",
    "sg:address":"517 Scott St",
    "sg:city":"Baltimore",
    "sg:classifiers":[
        {
            "category":"Health Services",
            "subcategory":"Doctor",
            "type":"Services"
        }
    ],
    "sg:phone":"+1 410 685 1982",
    "sg:postcode":"21230",
    "sg:province":"MD",
    "wof:name":"Kwunyeun Pricha",
    "wof:placetype":"venue"
},
  "geometry": {"coordinates":[-76.628601,39.2826],"type":"Point"}
}