{
  "type": "Feature",
  "properties": {
    "iso:country":"US",
    "sg:address":"335 S Conkling St",
    "sg:city":"Baltimore",
    "sg:classifiers":[
        {
            "category":"Professional",
            "subcategory":"Accounting & Tax Preparation",
            "type":"Services"
        }
    ],
    "sg:phone":"+1 410 276 1933",
    "sg:postcode":"21224",
    "sg:province":"MD",
    "sg:tags":[
        "return",
        "filing"
    ],
    "wof:name":"Jan Abrams Income Tax Svc",
    "wof:placetype":"venue"
},
  "geometry": {"coordinates":[-76.567176,39.287997],"type":"Point"}
}