{
  "type": "Feature",
  "properties": {
    "addr:full":"797 Wembly Dr Frederick MD 21701",
    "addr:housenumber":"797",
    "addr:postcode":"21701",
    "addr:street":"Wembly Dr",
    "iso:country":"US",
    "sg:address":"797 Wembly Dr",
    "sg:city":"Frederick",
    "sg:classifiers":[
        {
            "category":"Professional",
            "type":"Services"
        }
    ],
    "sg:phone":"+1 301 698 0365",
    "sg:postcode":"21701",
    "sg:province":"MD",
    "wof:name":"Norken Freelance Services",
    "wof:placetype":"venue"
},
  "geometry": {"coordinates":[-77.39280599999999,39.430935],"type":"Point"}
}