{
  "type": "Feature",
  "properties": {
    "addr:full":"685 Mosser Rd Mc Henry MD 21541",
    "addr:housenumber":"685",
    "addr:postcode":"21541",
    "addr:street":"Mosser Rd",
    "iso:country":"US",
    "sg:address":"685 Mosser Rd",
    "sg:city":"Mc Henry",
    "sg:classifiers":[
        {
            "category":"Manufacturing",
            "subcategory":"Printing",
            "type":"Manufacturing & Wholesale Goods"
        }
    ],
    "sg:phone":"+1 301 334 9172",
    "sg:postcode":"21541",
    "sg:province":"MD",
    "sg:tags":[
        "newspaper"
    ],
    "wof:name":"Garrett County Weekender",
    "wof:placetype":"venue"
},
  "geometry": {"coordinates":[-79.342512,39.560003],"type":"Point"}
}