{
  "type": "Feature",
  "properties": {
    "iso:country":"US",
    "sg:address":"10225 Old Georgetown Rd",
    "sg:city":"Bethesda",
    "sg:classifiers":[
        {
            "category":"Restaurant",
            "type":"Food & Drink"
        }
    ],
    "sg:phone":"+1 301 530 1881",
    "sg:postcode":"20814",
    "sg:province":"MD",
    "wof:name":"Fortune Taste Inc",
    "wof:placetype":"venue"
},
  "geometry": {"coordinates":[-77.124544,39.023976],"type":"Point"}
}