{
  "type": "Feature",
  "properties": {
    "iso:country":"US",
    "sg:address":"301 Grand Champion Dr",
    "sg:city":"Rockville",
    "sg:classifiers":[
        {
            "category":"Professional",
            "subcategory":"Business Services",
            "type":"Services"
        }
    ],
    "sg:phone":"+1 301 461 0249",
    "sg:postcode":"20850",
    "sg:province":"MD",
    "wof:name":"Muzzatti/Associates",
    "wof:placetype":"venue"
},
  "geometry": {"coordinates":[-77.164756,39.11098],"type":"Point"}
}