{
  "type": "Feature",
  "properties": {
    "iso:country":"US",
    "sg:address":"8012 Alcoa Dr",
    "sg:city":"Fort Washington",
    "sg:classifiers":[
        {
            "category":"Health Services",
            "subcategory":"Hospital",
            "type":"Services"
        }
    ],
    "sg:phone":"+1 301 839 9129",
    "sg:postcode":"20744",
    "sg:province":"MD",
    "sg:tags":[
        "specialty"
    ],
    "wof:name":"Tech-Management & Associates",
    "wof:placetype":"venue"
},
  "geometry": {"coordinates":[-76.991629,38.778564],"type":"Point"}
}