{
  "type": "Feature",
  "properties": {
    "addr:full":"850 Lindy Ln Huntingtown MD 20639",
    "addr:housenumber":"850",
    "addr:postcode":"20639",
    "addr:street":"Lindy Ln",
    "iso:country":"US",
    "sg:address":"850 Lindy Ln",
    "sg:city":"Huntingtown",
    "sg:classifiers":[
        {
            "category":"Shopping",
            "subcategory":"Jewelry",
            "type":"Retail Goods"
        }
    ],
    "sg:phone":"+1 410 257 4500",
    "sg:postcode":"20639",
    "sg:province":"MD",
    "sg:tags":[
        "jeweler"
    ],
    "wof:name":"Chesapeake Gem Appraising Lab",
    "wof:placetype":"venue"
},
  "geometry": {"coordinates":[-76.62441,38.616353],"type":"Point"}
}