{
  "type": "Feature",
  "properties": {
    "iso:country":"US",
    "sg:address":"2922 Old Liberty Rd",
    "sg:city":"New Windsor",
    "sg:classifiers":[
        {
            "category":"Retail",
            "subcategory":"Animal Services",
            "type":"Services"
        }
    ],
    "sg:phone":"+1 410 875 2045",
    "sg:postcode":"21776",
    "sg:province":"MD",
    "sg:tags":[
        "pet",
        "boarding",
        "sitting"
    ],
    "sg:website":"www.mistyridge.com",
    "wof:name":"Misty Ridge Animal Resort",
    "wof:placetype":"venue"
},
  "geometry": {"coordinates":[-77.102981,39.46044],"type":"Point"}
}