{
  "type": "Feature",
  "properties": {
    "iso:country":"US",
    "sg:address":"1108 N Point Rd",
    "sg:city":"Baltimore",
    "sg:classifiers":[
        {
            "category":"Bars & Pubs",
            "type":"Food & Drink"
        }
    ],
    "sg:phone":"+1 410 285 5717",
    "sg:postcode":"21222",
    "sg:province":"MD",
    "wof:name":"Gary J's Pub",
    "wof:placetype":"venue"
},
  "geometry": {"coordinates":[-76.504779,39.287828],"type":"Point"}
}