{
  "type": "Feature",
  "properties": {
    "addr:full":"516 Earls Rd Baltimore MD 21220",
    "addr:housenumber":"516",
    "addr:postcode":"21220",
    "addr:street":"Earls Rd",
    "iso:country":"US",
    "sg:address":"516 Earls Rd",
    "sg:city":"Baltimore",
    "sg:classifiers":[
        {
            "category":"Retail",
            "subcategory":"Auto Repair",
            "type":"Services"
        }
    ],
    "sg:phone":"+1 410 335 0040",
    "sg:postcode":"21220",
    "sg:province":"MD",
    "sg:tags":[
        "body"
    ],
    "wof:name":"George Heim",
    "wof:placetype":"venue"
},
  "geometry": {"coordinates":[-76.393264,39.35825],"type":"Point"}
}