{
  "type": "Feature",
  "properties": {
    "addr:full":"468 N Frederick Ave Gaithersburg MD 20877",
    "addr:housenumber":"468",
    "addr:postcode":"20877",
    "addr:street":"N Frederick Ave",
    "iso:country":"US",
    "sg:address":"468 N Frederick Ave",
    "sg:city":"Gaithersburg",
    "sg:classifiers":[
        {
            "category":"Professional",
            "type":"Services"
        }
    ],
    "sg:phone":"+1 301 948 8990",
    "sg:postcode":"20877",
    "sg:province":"MD",
    "sg:tags":[
        "establishment"
    ],
    "wof:name":"Bbb Auto Parts",
    "wof:placetype":"venue"
},
  "geometry": {"coordinates":[-77.208735,39.149672],"type":"Point"}
}