{
  "type": "Feature",
  "properties": {
    "addr:full":"211 Milford St Salisbury MD 21804",
    "addr:housenumber":"211",
    "addr:postcode":"21804",
    "addr:street":"Milford St",
    "iso:country":"US",
    "sg:address":"211 Milford St",
    "sg:city":"Salisbury",
    "sg:classifiers":[
        {
            "category":"Personal",
            "subcategory":"Beauty Salon",
            "type":"Services"
        }
    ],
    "sg:phone":"+1 410 749 7578",
    "sg:postcode":"21804",
    "sg:province":"MD",
    "wof:name":"Classic Hair Design",
    "wof:placetype":"venue"
},
  "geometry": {"coordinates":[-75.605234,38.339348],"type":"Point"}
}