{
  "type": "Feature",
  "properties": {
    "iso:country":"US",
    "sg:address":"6539 17th St",
    "sg:city":"Chesapeake Beach",
    "sg:classifiers":[
        {
            "category":"Shopping",
            "type":"Retail Goods"
        }
    ],
    "sg:phone":"+1 301 855 0866",
    "sg:postcode":"20732",
    "sg:province":"MD",
    "sg:tags":[
        "cards",
        "sport",
        "baseball",
        "memorabilia"
    ],
    "wof:name":"Sport Card Fantasies",
    "wof:placetype":"venue"
},
  "geometry": {"coordinates":[-76.543445,38.664583],"type":"Point"}
}