{
  "type": "Feature",
  "properties": {
    "iso:country":"US",
    "sg:address":"9 N Water St",
    "sg:city":"Frostburg",
    "sg:classifiers":[
        {
            "category":"Wholesale",
            "subcategory":"Vending Machines",
            "type":"Manufacturing & Wholesale Goods"
        }
    ],
    "sg:phone":"+1 301 689 6091",
    "sg:postcode":"21532",
    "sg:province":"MD",
    "wof:name":"H & D Novelty Co",
    "wof:placetype":"venue"
},
  "geometry": {"coordinates":[-78.926099,39.658592],"type":"Point"}
}