{
  "type": "Feature",
  "properties": {
    "iso:country":"US",
    "sg:address":"19 E Frederick St",
    "sg:city":"Walkersville",
    "sg:classifiers":[
        {
            "category":"Shopping",
            "subcategory":"Pharmacy",
            "type":"Retail Goods"
        }
    ],
    "sg:phone":"+1 301 845 4401",
    "sg:postcode":"21793",
    "sg:province":"MD",
    "wof:name":"Walkersville Pharmacy",
    "wof:placetype":"venue"
},
  "geometry": {"coordinates":[-77.348375,39.482878],"type":"Point"}
}