{
  "type": "Feature",
  "properties": {
    "iso:country":"US",
    "sg:address":"13002 Lutes Dr",
    "sg:city":"Silver Spring",
    "sg:classifiers":[
        {
            "category":"Building & Trades",
            "subcategory":"Construction",
            "type":"Services"
        }
    ],
    "sg:phone":"+1 301 589 6098",
    "sg:postcode":"20906",
    "sg:province":"MD",
    "sg:tags":[
        "painter"
    ],
    "wof:name":"Al's Painting",
    "wof:placetype":"venue"
},
  "geometry": {"coordinates":[-77.052187,39.074809],"type":"Point"}
}