{
  "type": "Feature",
  "properties": {
    "addr:full":"17805 Oak Ridge Dr Hagerstown MD 21740",
    "addr:housenumber":"17805",
    "addr:postcode":"21740",
    "addr:street":"Oak Ridge Dr",
    "iso:country":"US",
    "sg:address":"17805 Oak Ridge Dr",
    "sg:city":"Hagerstown",
    "sg:classifiers":[
        {
            "category":"Place Of Worship",
            "type":"Public Place"
        },
        {
            "category":"Social Services",
            "subcategory":"Child Care",
            "type":"Services"
        },
        {
            "category":"Education",
            "subcategory":"Preschool",
            "type":"Public Place"
        }
    ],
    "sg:phone":"+1 301 739 0702",
    "sg:postcode":"21740",
    "sg:province":"MD",
    "sg:tags":[
        "kindergarten",
        "nursery",
        "day",
        "church"
    ],
    "wof:name":"Church Nursery Inc",
    "wof:placetype":"venue"
},
  "geometry": {"coordinates":[-77.75369600000001,39.618101],"type":"Point"}
}