{
  "type": "Feature",
  "properties": {
    "iso:country":"US",
    "sg:address":"19901 Spr Hill Dr",
    "sg:city":"Montgomery Village",
    "sg:classifiers":[
        {
            "category":"Shopping",
            "subcategory":"Florist",
            "type":"Retail Goods"
        }
    ],
    "sg:phone":"+1 301 917 9184",
    "sg:postcode":"20886",
    "sg:province":"MD",
    "wof:name":"Carribean Flowers",
    "wof:placetype":"venue"
},
  "geometry": {"coordinates":[-77.192161,39.183994],"type":"Point"}
}