{
  "type": "Feature",
  "properties": {
    "iso:country":"US",
    "sg:address":"2438 Ennalls Ave",
    "sg:city":"Silver Spring",
    "sg:classifiers":[
        {
            "category":"Shopping",
            "subcategory":"Computers & Home Electronics",
            "type":"Retail Goods"
        }
    ],
    "sg:phone":"+1 301 933 3480",
    "sg:postcode":"20902",
    "sg:province":"MD",
    "sg:tags":[
        "equipment",
        "electronic",
        "supply"
    ],
    "wof:name":"Choice Electronics",
    "wof:placetype":"venue"
},
  "geometry": {"coordinates":[-77.052566,39.040171],"type":"Point"}
}