{
  "type": "Feature",
  "properties": {
    "addr:full":"708 S Bond St Baltimore MD 21231",
    "addr:housenumber":"708",
    "addr:postcode":"21231",
    "addr:street":"S Bond St",
    "iso:country":"US",
    "sg:address":"708 S Bond St",
    "sg:city":"Baltimore",
    "sg:classifiers":[
        {
            "category":"Bars & Pubs",
            "type":"Food & Drink"
        },
        {
            "category":"Restaurant",
            "type":"Food & Drink"
        }
    ],
    "sg:phone":"+1 410 327 0445",
    "sg:postcode":"21231",
    "sg:province":"MD",
    "sg:tags":[
        "tavern"
    ],
    "sg:website":"www.oneeyedmikes.com",
    "wof:name":"One-Eyed Mike's",
    "wof:placetype":"venue"
},
  "geometry": {"coordinates":[-76.595157,39.28327],"type":"Point"}
}