{
  "type": "Feature",
  "properties": {
    "addr:full":"Metro Shoppes 2970 Belcrest Center Dr, Ste 112 Hyattsville MD 20748",
    "addr:housenumber":"2970",
    "addr:postcode":"20748",
    "addr:street":"Belcrest Center Dr Ste 112",
    "iso:country":"US",
    "sg:address":"Metro Shoppes 2970 Belcrest Center Dr, Ste 112",
    "sg:city":"Hyattsville",
    "sg:classifiers":[
        {
            "category":"Restaurant",
            "type":"Food & Drink"
        },
        {
            "category":"Donuts",
            "subcategory":"None",
            "type":"Food & Drink"
        }
    ],
    "sg:phone":"+1 301 559 1763",
    "sg:postcode":"20748",
    "sg:province":"MD",
    "sg:tags":[
        "breakfast",
        "brunch"
    ],
    "sg:website":"www.dunkindonuts.com",
    "wof:name":"Dunkin' Donuts",
    "wof:placetype":"venue"
},
  "geometry": {"coordinates":[-76.957655,38.966511],"type":"Point"}
}