{
  "type": "Feature",
  "properties": {
    "iso:country":"US",
    "sg:address":"7825 Georgia Ave NW",
    "sg:city":"Washington",
    "sg:classifiers":[
        {
            "category":"Autos & Motor Vehicles",
            "subcategory":"Fuel & Gas Station",
            "type":"Retail Goods"
        }
    ],
    "sg:phone":"+1 202 291 4749",
    "sg:postcode":"20012",
    "sg:province":"MD",
    "sg:tags":[
        "oil"
    ],
    "wof:name":"District Line Auto Svc",
    "wof:placetype":"venue"
},
  "geometry": {"coordinates":[-77.026518,38.984346],"type":"Point"}
}