{
  "type": "Feature",
  "properties": {
    "iso:country":"US",
    "sg:address":"3609 Toddsbury Ln",
    "sg:city":"Olney",
    "sg:classifiers":[
        {
            "category":"Professional",
            "subcategory":"Printing & Photocopies",
            "type":"Services"
        }
    ],
    "sg:phone":"+1 301 774 7672",
    "sg:postcode":"20832",
    "sg:province":"MD",
    "sg:tags":[
        "lithographer"
    ],
    "wof:name":"Spider Press Printing",
    "wof:placetype":"venue"
},
  "geometry": {"coordinates":[-77.071957,39.159275],"type":"Point"}
}