{
  "type": "Feature",
  "properties": {
    "iso:country":"US",
    "sg:address":"18550 Clovercrest Cir",
    "sg:city":"Olney",
    "sg:classifiers":[
        {
            "category":"Wholesale",
            "subcategory":"Medical Equipment & Supplies",
            "type":"Manufacturing & Wholesale Goods"
        }
    ],
    "sg:phone":"+1 301 924 5714",
    "sg:postcode":"20832",
    "sg:province":"MD",
    "sg:tags":[
        "x",
        "apparatus"
    ],
    "wof:name":"American Imaging",
    "wof:placetype":"venue"
},
  "geometry": {"coordinates":[-77.05772899999999,39.15866],"type":"Point"}
}