{
  "type": "Feature",
  "properties": {
    "iso:country":"US",
    "sg:address":"11850 Park Waldorf Ln",
    "sg:city":"Waldorf",
    "sg:classifiers":[
        {
            "category":"Personal",
            "subcategory":"Barber",
            "type":"Services"
        }
    ],
    "sg:phone":"+1 301 645 9881",
    "sg:postcode":"20601",
    "sg:province":"MD",
    "wof:name":"Forrest & Roberts Barber Shop",
    "wof:placetype":"venue"
},
  "geometry": {"coordinates":[-76.900038,38.635117],"type":"Point"}
}