{
  "type": "Feature",
  "properties": {
    "iso:country":"US",
    "sg:address":"907 Hubbard St",
    "sg:city":"Cambridge",
    "sg:classifiers":[
        {
            "category":"Personal",
            "subcategory":"Beauty Salon",
            "type":"Services"
        }
    ],
    "sg:phone":"+1 410 901 8338",
    "sg:postcode":"21613",
    "sg:province":"MD",
    "wof:name":"Sissily Hair",
    "wof:placetype":"venue"
},
  "geometry": {"coordinates":[-76.08273199999999,38.56283],"type":"Point"}
}