{
  "type": "Feature",
  "properties": {
    "addr:full":"7500 Pulaski Hwy Rosedale MD 21237",
    "addr:housenumber":"7500",
    "addr:postcode":"21237",
    "addr:street":"Pulaski Hwy",
    "iso:country":"US",
    "sg:address":"7500 Pulaski Hwy",
    "sg:city":"Rosedale",
    "sg:classifiers":[
        {
            "category":"Autos & Motor Vehicles",
            "subcategory":"Fuel & Gas Station",
            "type":"Retail Goods"
        }
    ],
    "sg:phone":"+1 410 866 9007",
    "sg:postcode":"21237",
    "sg:province":"MD",
    "sg:tags":[
        "oil"
    ],
    "wof:name":"Route 7 Amoco",
    "wof:placetype":"venue"
},
  "geometry": {"coordinates":[-76.52469600000001,39.312801],"type":"Point"}
}