{
  "type": "Feature",
  "properties": {
    "addr:full":"1726 Reisterstown Rd Pikesville MD 21208",
    "addr:housenumber":"1726",
    "addr:postcode":"21208",
    "addr:street":"Reisterstown Rd",
    "iso:country":"US",
    "sg:address":"1726 Reisterstown Rd",
    "sg:city":"Pikesville",
    "sg:classifiers":[
        {
            "category":"Banks & Credit Unions",
            "subcategory":"Bank",
            "type":"Services"
        }
    ],
    "sg:phone":"+1 410 484 7400",
    "sg:postcode":"21208",
    "sg:province":"MD",
    "sg:tags":[
        "lender",
        "broker",
        "mortgage"
    ],
    "wof:name":"American Bancorp Inc",
    "wof:placetype":"venue"
},
  "geometry": {"coordinates":[-76.732157,39.382847],"type":"Point"}
}