{
  "type": "Feature",
  "properties": {
    "iso:country":"US",
    "sg:address":"12 Farragut Rd",
    "sg:city":"Annapolis",
    "sg:classifiers":[
        {
            "category":"Real Estate",
            "subcategory":"Real Estate Agent",
            "type":"Services"
        }
    ],
    "sg:phone":"+1 410 263 7750",
    "sg:postcode":"21403",
    "sg:province":"MD",
    "wof:name":"Phillips & Zorn",
    "wof:placetype":"venue"
},
  "geometry": {"coordinates":[-76.45776600000001,38.937658],"type":"Point"}
}