{
  "type": "Feature",
  "properties": {
    "iso:country":"US",
    "sg:address":"2022 Denison St",
    "sg:city":"Baltimore",
    "sg:classifiers":[
        {
            "category":"Shopping",
            "subcategory":"Used Merchandise",
            "type":"Retail Goods"
        }
    ],
    "sg:phone":"+1 410 362 8508",
    "sg:postcode":"21216",
    "sg:province":"MD",
    "sg:tags":[
        "shop",
        "pawnbroker",
        "pawn"
    ],
    "wof:name":"Gold Trading Center",
    "wof:placetype":"venue"
},
  "geometry": {"coordinates":[-76.674004,39.310799],"type":"Point"}
}