{
  "type": "Feature",
  "properties": {
    "addr:full":"4400 E West Hwy Ste A Bethesda MD 20814",
    "addr:housenumber":"4400 e",
    "addr:postcode":"20814",
    "addr:street":"West Hwy Ste A",
    "iso:country":"US",
    "sg:address":"4400 E West Hwy Ste A",
    "sg:city":"Bethesda",
    "sg:classifiers":[
        {
            "category":"Health Services",
            "subcategory":"Dentist",
            "type":"Services"
        }
    ],
    "sg:phone":"+1 301 652 5445",
    "sg:postcode":"20814",
    "sg:province":"MD",
    "wof:name":"Nichols R Scott",
    "wof:placetype":"venue"
},
  "geometry": {"coordinates":[-77.101997,39.008598],"type":"Point"}
}