{
  "type": "Feature",
  "properties": {
    "iso:country":"US",
    "sg:address":"15045 Burnt Store Rd",
    "sg:city":"Hughesville",
    "sg:classifiers":[
        {
            "category":"Real Estate",
            "subcategory":"Surveying",
            "type":"Services"
        }
    ],
    "sg:phone":"+1 301 870 2520",
    "sg:postcode":"20637",
    "sg:province":"MD",
    "sg:tags":[
        "planning",
        "land"
    ],
    "wof:name":"Car Pool Van Pool Information",
    "wof:placetype":"venue"
},
  "geometry": {"coordinates":[-76.787038,38.532476],"type":"Point"}
}