{
  "type": "Feature",
  "properties": {
    "iso:country":"US",
    "sg:address":"8700 Larkin Rd",
    "sg:city":"Savage",
    "sg:classifiers":[
        {
            "category":"Wholesale",
            "subcategory":"Electrical",
            "type":"Manufacturing & Wholesale Goods"
        }
    ],
    "sg:phone":"+1 410 724 2030",
    "sg:postcode":"20763",
    "sg:province":"MD",
    "wof:name":"Rheem Manufacturing Company",
    "wof:placetype":"venue"
},
  "geometry": {"coordinates":[-76.809609,39.133142],"type":"Point"}
}