{
  "type": "Feature",
  "properties": {
    "addr:full":"7177 Ridge Rd Hanover MD 21076",
    "addr:housenumber":"7177",
    "addr:postcode":"21076",
    "addr:street":"Ridge Rd",
    "iso:country":"US",
    "sg:address":"7177 Ridge Rd",
    "sg:city":"Hanover",
    "sg:classifiers":[
        {
            "category":"Manufacturing",
            "subcategory":"Tools & Machinery",
            "type":"Manufacturing & Wholesale Goods"
        }
    ],
    "sg:phone":"+1 410 859 5775",
    "sg:postcode":"21076",
    "sg:province":"MD",
    "sg:tags":[
        "machine",
        "shop"
    ],
    "wof:name":"Fleck Machine Co",
    "wof:placetype":"venue"
},
  "geometry": {"coordinates":[-76.70243600000001,39.196862],"type":"Point"}
}