{
  "type": "Feature",
  "properties": {
    "addr:full":"4251 Mason School Rd Oakland MD 21550",
    "addr:housenumber":"4251",
    "addr:postcode":"21550",
    "addr:street":"Mason School Rd",
    "iso:country":"US",
    "sg:address":"4251 Mason School Rd",
    "sg:city":"Oakland",
    "sg:phone":"+1 301 334 4061",
    "sg:postcode":"21550",
    "sg:province":"MD",
    "sg:tags":[
        "wheat",
        "farm",
        "corn",
        "crop",
        "field",
        "dairy"
    ],
    "wof:name":"David Swartzentrub",
    "wof:placetype":"venue"
},
  "geometry": {"coordinates":[-79.420843,39.34864],"type":"Point"}
}