{
  "type": "Feature",
  "properties": {
    "iso:country":"US",
    "sg:address":"10206 Sunway Ter",
    "sg:city":"Ellicott City",
    "sg:classifiers":[
        {
            "category":"Professional",
            "type":"Services"
        }
    ],
    "sg:phone":"+1 410 203 0441",
    "sg:postcode":"21042",
    "sg:province":"MD",
    "wof:name":"Bill Fidel Writer Producer",
    "wof:placetype":"venue"
},
  "geometry": {"coordinates":[-76.872513,39.261819],"type":"Point"}
}