{
  "type": "Feature",
  "properties": {
    "addr:full":"1314 Church Hill Dr Pikesville MD 21208",
    "addr:housenumber":"1314",
    "addr:postcode":"21208",
    "addr:street":"Church Hill Dr",
    "iso:country":"US",
    "sg:address":"1314 Church Hill Dr",
    "sg:city":"Pikesville",
    "sg:classifiers":[
        {
            "category":"Freight",
            "type":"Transportation"
        }
    ],
    "sg:phone":"+1 410 486 8936",
    "sg:postcode":"21208",
    "sg:province":"MD",
    "sg:tags":[
        "operator",
        "local",
        "trucking"
    ],
    "wof:name":"Abba Moving LLC",
    "wof:placetype":"venue"
},
  "geometry": {"coordinates":[-76.73414,39.372968],"type":"Point"}
}