{
  "type": "Feature",
  "properties": {
    "iso:country":"US",
    "sg:address":"27701 Ridge Rd",
    "sg:city":"Damascus",
    "sg:classifiers":[
        {
            "category":"Organizations",
            "subcategory":"Religious Organization",
            "type":"Services"
        }
    ],
    "sg:phone":"+1 301 253 3411",
    "sg:postcode":"20872",
    "sg:province":"MD",
    "sg:tags":[
        "place",
        "worship",
        "church"
    ],
    "wof:name":"Friendship United Methodist Church",
    "wof:placetype":"venue"
},
  "geometry": {"coordinates":[-77.197755,39.309712],"type":"Point"}
}