{
  "type": "Feature",
  "properties": {
    "iso:country":"US",
    "sg:address":"9910 Liberty Rd",
    "sg:city":"Randallstown",
    "sg:classifiers":[
        {
            "category":"Shopping",
            "subcategory":"Pharmacy",
            "type":"Retail Goods"
        }
    ],
    "sg:phone":"+1 410 496 3844",
    "sg:postcode":"21133",
    "sg:province":"MD",
    "wof:name":"Walgreens",
    "wof:placetype":"venue"
},
  "geometry": {"coordinates":[-76.8246,39.381937],"type":"Point"}
}