{
  "type": "Feature",
  "properties": {
    "iso:country":"US",
    "sg:address":"2404 Fairview Dr",
    "sg:city":"Forest Hill",
    "sg:classifiers":[
        {
            "category":"Health Services",
            "subcategory":"Medical Lab",
            "type":"Services"
        }
    ],
    "sg:phone":"+1 410 879 2686",
    "sg:postcode":"21050",
    "sg:province":"MD",
    "sg:tags":[
        "laboratory"
    ],
    "wof:name":"Donnelly Dental Laboratories",
    "wof:placetype":"venue"
},
  "geometry": {"coordinates":[-76.367283,39.580798],"type":"Point"}
}