{
  "type": "Feature",
  "properties": {
    "addr:full":"10204 Everley Ter Lanham MD 20706",
    "addr:housenumber":"10204",
    "addr:postcode":"20706",
    "addr:street":"Everley Ter",
    "iso:country":"US",
    "sg:address":"10204 Everley Ter",
    "sg:city":"Lanham",
    "sg:classifiers":[
        {
            "category":"Organizations",
            "subcategory":"Religious Organization",
            "type":"Services"
        }
    ],
    "sg:phone":"+1 301 262 3482",
    "sg:postcode":"20706",
    "sg:province":"MD",
    "sg:tags":[
        "church"
    ],
    "wof:name":"God's House Of Prayer",
    "wof:placetype":"venue"
},
  "geometry": {"coordinates":[-76.830185,38.978603],"type":"Point"}
}