{
  "type": "Feature",
  "properties": {
    "iso:country":"US",
    "sg:address":"602 Arlewood Rd",
    "sg:city":"Baltimore",
    "sg:classifiers":[
        {
            "category":"Organizations",
            "subcategory":"Community Association",
            "type":"Services"
        }
    ],
    "sg:phone":"+1 410 744 8532",
    "sg:postcode":"21228",
    "sg:province":"MD",
    "wof:name":"Travelers Protective Assn Amer",
    "wof:placetype":"venue"
},
  "geometry": {"coordinates":[-76.731435,39.27747],"type":"Point"}
}