{
  "type": "Feature",
  "properties": {
    "addr:full":"1210 Bluebird Ct W Bel Air MD 21015",
    "addr:housenumber":"1210",
    "addr:postcode":"21015",
    "addr:street":"Bluebird Ct W",
    "iso:country":"US",
    "sg:address":"1210 Bluebird Ct W",
    "sg:city":"Bel Air",
    "sg:classifiers":[
        {
            "category":"Professional",
            "type":"Services"
        }
    ],
    "sg:phone":"+1 410 879 0013",
    "sg:postcode":"21015",
    "sg:province":"MD",
    "sg:tags":[
        "establishment"
    ],
    "wof:name":"DJM Sales Assocs",
    "wof:placetype":"venue"
},
  "geometry": {"coordinates":[-76.307559,39.557238],"type":"Point"}
}