{
  "type": "Feature",
  "properties": {
    "iso:country":"US",
    "sg:address":"16 Cross Keys Rd",
    "sg:city":"Baltimore",
    "sg:classifiers":[
        {
            "category":"Professional",
            "subcategory":"Lawyer & Legal Services",
            "type":"Services"
        }
    ],
    "sg:phone":"+1 410 433 1638",
    "sg:postcode":"21210",
    "sg:province":"MD",
    "wof:name":"Katz Laura L Lwyr",
    "wof:placetype":"venue"
},
  "geometry": {"coordinates":[-76.644897,39.3559],"type":"Point"}
}