{
  "type": "Feature",
  "properties": {
    "addr:full":"12312 Detour Rd Keymar MD 21757",
    "addr:housenumber":"12312",
    "addr:postcode":"21757",
    "addr:street":"Detour Rd",
    "iso:country":"US",
    "sg:address":"12312 Detour Rd",
    "sg:city":"Keymar",
    "sg:classifiers":[
        {
            "category":"Museum",
            "subcategory":"Botanical Garden",
            "type":"Entertainment"
        }
    ],
    "sg:phone":"+1 301 898 8106",
    "sg:postcode":"21757",
    "sg:province":"MD",
    "sg:tags":[
        "zoo"
    ],
    "wof:name":"Deer Haven Mini Zoo",
    "wof:placetype":"venue"
},
  "geometry": {"coordinates":[-77.288337,39.568727],"type":"Point"}
}