{
  "type": "Feature",
  "properties": {
    "iso:country":"US",
    "sg:address":"9113 Baltimore Ave",
    "sg:city":"College Park",
    "sg:classifiers":[
        {
            "category":"Travel",
            "subcategory":"Hotels & Motels",
            "type":"Entertainment"
        }
    ],
    "sg:phone":"+1 301 513 0002",
    "sg:postcode":"20740",
    "sg:province":"MD",
    "wof:name":"Howard Johnson",
    "wof:placetype":"venue"
},
  "geometry": {"coordinates":[-76.93018600000001,39.004616],"type":"Point"}
}