{
  "type": "Feature",
  "properties": {
    "iso:country":"US",
    "sg:address":"1214 Goldmine Ct",
    "sg:city":"Hyattsville",
    "sg:classifiers":[
        {
            "category":"Organizations",
            "subcategory":"Religious Organization",
            "type":"Services"
        }
    ],
    "sg:phone":"+1 301 324 5284",
    "sg:postcode":"20785",
    "sg:province":"MD",
    "wof:name":"First Vietnamese Baptst Church",
    "wof:placetype":"venue"
},
  "geometry": {"coordinates":[-76.89041400000001,38.905885],"type":"Point"}
}