{
  "type": "Feature",
  "properties": {
    "iso:country":"US",
    "sg:address":"2763 Summers Ridge Dr",
    "sg:city":"Odenton",
    "sg:classifiers":[
        {
            "category":"Building & Trades",
            "subcategory":"Electrical",
            "type":"Services"
        }
    ],
    "sg:phone":"+1 410 519 3133",
    "sg:postcode":"21113",
    "sg:province":"MD",
    "sg:tags":[
        "electrician"
    ],
    "wof:name":"Wells Electric",
    "wof:placetype":"venue"
},
  "geometry": {"coordinates":[-76.715227,39.062226],"type":"Point"}
}