{
  "type": "Feature",
  "properties": {
    "iso:country":"US",
    "sg:address":"18058 Mateny Rd",
    "sg:city":"Germantown",
    "sg:classifiers":[
        {
            "category":"Restaurant",
            "type":"Food & Drink"
        }
    ],
    "sg:phone":"+1 301 916 1422",
    "sg:postcode":"20874",
    "sg:province":"MD",
    "sg:tags":[
        "out"
    ],
    "wof:name":"Varsity Scoops & Grille",
    "wof:placetype":"venue"
},
  "geometry": {"coordinates":[-77.270813,39.147753],"type":"Point"}
}