{
  "type": "Feature",
  "properties": {
    "addr:full":"621 Central Ave E Edgewater MD 21037",
    "addr:housenumber":"621",
    "addr:postcode":"21037",
    "addr:street":"Central Ave E",
    "iso:country":"US",
    "sg:address":"621 Central Ave E",
    "sg:city":"Edgewater",
    "sg:classifiers":[
        {
            "category":"Retail",
            "subcategory":"Auto Repair",
            "type":"Services"
        }
    ],
    "sg:phone":"+1 410 956 5334",
    "sg:postcode":"21037",
    "sg:province":"MD",
    "sg:tags":[
        "repairing",
        "automobile"
    ],
    "wof:name":"Slaters Well Drilling",
    "wof:placetype":"venue"
},
  "geometry": {"coordinates":[-76.536658,38.906965],"type":"Point"}
}