{
  "type": "Feature",
  "properties": {
    "addr:full":"714 N Fremont Ave Baltimore MD 21217",
    "addr:housenumber":"714",
    "addr:postcode":"21217",
    "addr:street":"N Fremont Ave",
    "iso:country":"US",
    "sg:address":"714 N Fremont Ave",
    "sg:city":"Baltimore",
    "sg:classifiers":[
        {
            "category":"Organizations",
            "subcategory":"Religious Organization",
            "type":"Services"
        }
    ],
    "sg:phone":"+1 443 872 6269",
    "sg:postcode":"21217",
    "sg:province":"MD",
    "sg:tags":[
        "church"
    ],
    "sg:website":"www.churchofgod.cc",
    "wof:name":"Titus Memorial Church of God",
    "wof:placetype":"venue"
},
  "geometry": {"coordinates":[-76.633459,39.296919],"type":"Point"}
}