{
  "type": "Feature",
  "properties": {
    "iso:country":"US",
    "sg:address":"20 Firstfield Rd",
    "sg:city":"Gaithersburg",
    "sg:classifiers":[
        {
            "category":"Wholesale",
            "subcategory":"Medical Equipment & Supplies",
            "type":"Manufacturing & Wholesale Goods"
        }
    ],
    "sg:phone":"+1 301 527 2000",
    "sg:postcode":"20878",
    "sg:province":"MD",
    "sg:tags":[
        "physician",
        "surgeon"
    ],
    "wof:name":"Surgi-Vision",
    "wof:placetype":"venue"
},
  "geometry": {"coordinates":[-77.225874,39.135292],"type":"Point"}
}