{
  "type": "Feature",
  "properties": {
    "addr:full":"6254 Kenwood Ave Rosedale MD 21237",
    "addr:housenumber":"6254",
    "addr:postcode":"21237",
    "addr:street":"Kenwood Ave",
    "iso:country":"US",
    "sg:address":"6254 Kenwood Ave",
    "sg:city":"Rosedale",
    "sg:classifiers":[
        {
            "category":"Professional",
            "type":"Services"
        }
    ],
    "sg:phone":"+1 410 866 5232",
    "sg:postcode":"21237",
    "sg:province":"MD",
    "sg:tags":[
        "establishment"
    ],
    "wof:name":"Uhc Of Baltimore",
    "wof:placetype":"venue"
},
  "geometry": {"coordinates":[-76.505066,39.341449],"type":"Point"}
}