{
  "type": "Feature",
  "properties": {
    "addr:full":"19704 Toms Rd Boonsboro MD 21713",
    "addr:housenumber":"19704",
    "addr:postcode":"21713",
    "addr:street":"Toms Rd",
    "iso:country":"US",
    "sg:address":"19704 Toms Rd",
    "sg:city":"Boonsboro",
    "sg:classifiers":[
        {
            "category":"Food & Beverages",
            "subcategory":"Meat & Fish",
            "type":"Retail Goods"
        },
        {
            "category":"Wholesale",
            "subcategory":"Meat",
            "type":"Manufacturing & Wholesale Goods"
        }
    ],
    "sg:phone":"+1 301 797 2476",
    "sg:postcode":"21713",
    "sg:province":"MD",
    "sg:tags":[
        "product"
    ],
    "wof:name":"Buffalo Billie's",
    "wof:placetype":"venue"
},
  "geometry": {"coordinates":[-77.68174999999999,39.559117],"type":"Point"}
}