{
  "type": "Feature",
  "properties": {
    "addr:full":"8830 Stanford Blvd Columbia MD 21045",
    "addr:housenumber":"8830",
    "addr:postcode":"21045",
    "addr:street":"Stanford Blvd",
    "iso:country":"US",
    "sg:address":"8830 Stanford Blvd",
    "sg:city":"Columbia",
    "sg:classifiers":[
        {
            "category":"Shopping",
            "subcategory":"Computers & Home Electronics",
            "type":"Retail Goods"
        }
    ],
    "sg:phone":"+1 410 715 9399",
    "sg:postcode":"21045",
    "sg:province":"MD",
    "sg:tags":[
        "software"
    ],
    "sg:website":"www.capitol.com",
    "wof:name":"RABA Technologies",
    "wof:placetype":"venue"
},
  "geometry": {"coordinates":[-76.818862,39.187006],"type":"Point"}
}