{
  "type": "Feature",
  "properties": {
    "addr:full":"4712 Dorsey Hall Dr Ellicott City MD 21042",
    "addr:housenumber":"4712",
    "addr:postcode":"21042",
    "addr:street":"Dorsey Hall Dr",
    "iso:country":"US",
    "sg:address":"4712 Dorsey Hall Dr",
    "sg:city":"Ellicott City",
    "sg:classifiers":[
        {
            "category":"Building & Trades",
            "subcategory":"Construction",
            "type":"Services"
        }
    ],
    "sg:phone":"+1 410 715 9069",
    "sg:postcode":"21042",
    "sg:province":"MD",
    "sg:tags":[
        "house"
    ],
    "wof:name":"Marc Volkmann Construction",
    "wof:placetype":"venue"
},
  "geometry": {"coordinates":[-76.842378,39.244447],"type":"Point"}
}