{
  "type": "Feature",
  "properties": {
    "iso:country":"US",
    "sg:address":"2111 E Churchville Rd",
    "sg:city":"Bel Air",
    "sg:classifiers":[
        {
            "category":"Restaurant",
            "type":"Food & Drink"
        }
    ],
    "sg:menulink":"http://www.allmenus.com/md/bel-air/215549-mcdonalds/menu/",
    "sg:postcode":"21015",
    "sg:province":"MD",
    "sg:tags":[
        "burger",
        "american"
    ],
    "wof:name":"McDonald's",
    "wof:placetype":"venue"
},
  "geometry": {"coordinates":[-76.287767,39.55467],"type":"Point"}
}