{
  "type": "Feature",
  "properties": {
    "iso:country":"US",
    "sg:address":"23 C St",
    "sg:city":"Laurel",
    "sg:classifiers":[
        {
            "category":"Wholesale",
            "subcategory":"Electrical",
            "type":"Manufacturing & Wholesale Goods"
        }
    ],
    "sg:phone":"+1 410 880 6929",
    "sg:postcode":"20707",
    "sg:province":"MD",
    "sg:tags":[
        "lighting",
        "fixture"
    ],
    "wof:name":"Light Source",
    "wof:placetype":"venue"
},
  "geometry": {"coordinates":[-76.845578,39.105854],"type":"Point"}
}