{
  "type": "Feature",
  "properties": {
    "addr:full":"2 E Midland Rd Baltimore MD 21220",
    "addr:housenumber":"2",
    "addr:postcode":"21220",
    "addr:street":"E Midland Rd",
    "iso:country":"US",
    "sg:address":"2 E Midland Rd",
    "sg:city":"Baltimore",
    "sg:classifiers":[
        {
            "category":"Retail",
            "subcategory":"Portrait Studio",
            "type":"Services"
        }
    ],
    "sg:phone":"+1 410 574 3076",
    "sg:postcode":"21220",
    "sg:province":"MD",
    "sg:tags":[
        "photographer"
    ],
    "wof:name":"Southern Shots Photography",
    "wof:placetype":"venue"
},
  "geometry": {"coordinates":[-76.44386900000001,39.343475],"type":"Point"}
}