{
  "type": "Feature",
  "properties": {
    "iso:country":"US",
    "sg:address":"8401 Ocean Gateway",
    "sg:city":"Easton",
    "sg:classifiers":[
        {
            "category":"Home & Garden",
            "subcategory":"Building Materials",
            "type":"Retail Goods"
        }
    ],
    "sg:phone":"+1 410 822 4880",
    "sg:postcode":"21601",
    "sg:province":"MD",
    "sg:website":"www.moores.com",
    "wof:name":"Moore's Lumber & Bldg Supl Inc",
    "wof:placetype":"venue"
},
  "geometry": {"coordinates":[-76.060067,38.778756],"type":"Point"}
}