{
  "type": "Feature",
  "properties": {
    "addr:full":"5457 Marsh Hawk Way Columbia MD 21045",
    "addr:housenumber":"5457",
    "addr:postcode":"21045",
    "addr:street":"Marsh Hawk Way",
    "iso:country":"US",
    "sg:address":"5457 Marsh Hawk Way",
    "sg:city":"Columbia",
    "sg:classifiers":[
        {
            "category":"Professional",
            "subcategory":"Research",
            "type":"Services"
        }
    ],
    "sg:phone":"+1 410 740 0849",
    "sg:postcode":"21045",
    "sg:province":"MD",
    "sg:tags":[
        "development",
        "science",
        "life"
    ],
    "wof:name":"Science Communication Studies",
    "wof:placetype":"venue"
},
  "geometry": {"coordinates":[-76.835103,39.224115],"type":"Point"}
}