{
  "type": "Feature",
  "properties": {
    "addr:full":"204 Chaucer Ln Bel Air MD 21014",
    "addr:housenumber":"204",
    "addr:postcode":"21014",
    "addr:street":"Chaucer Ln",
    "iso:country":"US",
    "sg:address":"204 Chaucer Ln",
    "sg:city":"Bel Air",
    "sg:classifiers":[
        {
            "category":"Building & Trades",
            "subcategory":"Landscaping Services",
            "type":"Services"
        }
    ],
    "sg:phone":"+1 410 803 1803",
    "sg:postcode":"21014",
    "sg:province":"MD",
    "sg:tags":[
        "landscape",
        "contractor"
    ],
    "wof:name":"Fred's Landscape & Nursery",
    "wof:placetype":"venue"
},
  "geometry": {"coordinates":[-76.36523200000001,39.526632],"type":"Point"}
}