{
  "type": "Feature",
  "properties": {
    "iso:country":"US",
    "sg:address":"16023 Elegant Ct",
    "sg:city":"Bowie",
    "sg:classifiers":[
        {
            "category":"Building & Trades",
            "subcategory":"Construction",
            "type":"Services"
        }
    ],
    "sg:phone":"+1 301 805 0629",
    "sg:postcode":"20716",
    "sg:province":"MD",
    "sg:tags":[
        "hanging",
        "contractor"
    ],
    "wof:name":"Steven L Nancy M Painter",
    "wof:placetype":"venue"
},
  "geometry": {"coordinates":[-76.726456,38.943307],"type":"Point"}
}