{
  "type": "Feature",
  "properties": {
    "addr:full":"4710 Auth Pl Suitland MD 20746",
    "addr:postcode":"4710;20746",
    "addr:street":"Auth Pl",
    "iso:country":"US",
    "sg:address":"4710 Auth Pl",
    "sg:city":"Suitland",
    "sg:classifiers":[
        {
            "category":"Government",
            "subcategory":"Office",
            "type":"Public Place"
        }
    ],
    "sg:phone":"+1 301 899 1020",
    "sg:postcode":"20746",
    "sg:province":"MD",
    "sg:tags":[
        "state",
        "program"
    ],
    "sg:website":"www.dors.state.md.us",
    "wof:name":"Vocational Rehabilitation Div",
    "wof:placetype":"venue"
},
  "geometry": {"coordinates":[-76.92020100000001,38.824801],"type":"Point"}
}