{
  "type": "Feature",
  "properties": {
    "addr:full":"1123 N Eutaw St Baltimore MD 21201",
    "addr:housenumber":"1123",
    "addr:postcode":"21201",
    "addr:street":"N Eutaw St",
    "iso:country":"US",
    "sg:address":"1123 N Eutaw St",
    "sg:city":"Baltimore",
    "sg:classifiers":[
        {
            "category":"Real Estate",
            "subcategory":"Real Estate Operator",
            "type":"Services"
        }
    ],
    "sg:phone":"+1 410 669 2800",
    "sg:postcode":"21201",
    "sg:province":"MD",
    "sg:tags":[
        "apartment"
    ],
    "wof:name":"The Cecil Apartments",
    "wof:placetype":"venue"
},
  "geometry": {"coordinates":[-76.624199,39.302502],"type":"Point"}
}