{
  "type": "Feature",
  "properties": {
    "addr:full":"153 N Market St Frederick MD 21701",
    "addr:housenumber":"153",
    "addr:postcode":"21701",
    "addr:street":"N Market St",
    "iso:country":"US",
    "sg:address":"153 N Market St",
    "sg:city":"Frederick",
    "sg:classifiers":[
        {
            "category":"Shopping",
            "subcategory":"Tobacco",
            "type":"Retail Goods"
        }
    ],
    "sg:phone":"+1 301 682 6666",
    "sg:postcode":"21701",
    "sg:province":"MD",
    "sg:tags":[
        "cigarette",
        "cigar",
        "dealer"
    ],
    "wof:name":"Classic Cigars British Goodies",
    "wof:placetype":"venue"
},
  "geometry": {"coordinates":[-77.410791,39.416413],"type":"Point"}
}