{
  "type": "Feature",
  "properties": {
    "iso:country":"US",
    "sg:address":"5131 Park Heights Ave",
    "sg:city":"Baltimore",
    "sg:classifiers":[
        {
            "category":"Restaurant",
            "type":"Food & Drink"
        }
    ],
    "sg:phone":"+1 410 664 6699",
    "sg:postcode":"21215",
    "sg:province":"MD",
    "sg:tags":[
        "style",
        "seafood",
        "family"
    ],
    "wof:name":"Yellow Bowl No 2",
    "wof:placetype":"venue"
},
  "geometry": {"coordinates":[-76.675301,39.348598],"type":"Point"}
}