{
  "type": "Feature",
  "properties": {
    "addr:full":"9431 7 Courts Dr Baltimore MD 21236",
    "addr:housenumber":"9431 7",
    "addr:postcode":"21236",
    "addr:street":"Courts Dr",
    "iso:country":"US",
    "sg:address":"9431 7 Courts Dr",
    "sg:city":"Baltimore",
    "sg:classifiers":[
        {
            "category":"Retail",
            "subcategory":"Portrait Studio",
            "type":"Services"
        }
    ],
    "sg:phone":"+1 410 256 2645",
    "sg:postcode":"21236",
    "sg:province":"MD",
    "sg:tags":[
        "photo"
    ],
    "wof:name":"Rich Riggins Photography",
    "wof:placetype":"venue"
},
  "geometry": {"coordinates":[-76.485308,39.407512],"type":"Point"}
}