{
  "type": "Feature",
  "properties": {
    "iso:country":"US",
    "sg:address":"14205 Platinum Dr",
    "sg:city":"North Potomac",
    "sg:classifiers":[
        {
            "category":"Professional",
            "subcategory":"Business Services",
            "type":"Services"
        }
    ],
    "sg:phone":"+1 301 738 0033",
    "sg:postcode":"20878",
    "sg:province":"MD",
    "wof:name":"Historic Restoration Inc",
    "wof:placetype":"venue"
},
  "geometry": {"coordinates":[-77.219371,39.091824],"type":"Point"}
}