{
  "type": "Feature",
  "properties": {
    "iso:country":"US",
    "sg:address":"7515 Annapolis Rd",
    "sg:city":"Hyattsville",
    "sg:classifiers":[
        {
            "category":"Freight",
            "type":"Transportation"
        }
    ],
    "sg:phone":"+1 301 577 3883",
    "sg:postcode":"20784",
    "sg:province":"MD",
    "wof:name":"Metro Bi Links Inc",
    "wof:placetype":"venue"
},
  "geometry": {"coordinates":[-76.885869,38.950776],"type":"Point"}
}