{
  "type": "Feature",
  "properties": {
    "addr:full":"116 Governors Way N Queenstown MD 21658",
    "addr:housenumber":"116",
    "addr:postcode":"21658",
    "addr:street":"Governors Way N",
    "iso:country":"US",
    "sg:address":"116 Governors Way N",
    "sg:city":"Queenstown",
    "sg:classifiers":[
        {
            "category":"Wholesale",
            "subcategory":"Machinery & Supplies",
            "type":"Manufacturing & Wholesale Goods"
        }
    ],
    "sg:phone":"+1 410 827 4322",
    "sg:postcode":"21658",
    "sg:province":"MD",
    "sg:tags":[
        "equipment",
        "establishment"
    ],
    "wof:name":"Maryland Custom Embroidery",
    "wof:placetype":"venue"
},
  "geometry": {"coordinates":[-76.16673900000001,38.957758],"type":"Point"}
}