{
  "type": "Feature",
  "properties": {
    "iso:country":"US",
    "sg:address":"535 Morgnec Rd",
    "sg:city":"Chestertown",
    "sg:classifiers":[
        {
            "category":"Retail",
            "subcategory":"Repair Shop",
            "type":"Services"
        }
    ],
    "sg:phone":"+1 410 778 3993",
    "sg:postcode":"21620",
    "sg:province":"MD",
    "sg:tags":[
        "refinishing",
        "furniture"
    ],
    "wof:name":"Frank B Rhodes Furniture Maker",
    "wof:placetype":"venue"
},
  "geometry": {"coordinates":[-76.06049899999999,39.22538],"type":"Point"}
}