{
  "type": "Feature",
  "properties": {
    "addr:full":"11510 Falls Rd Potomac MD 20854",
    "addr:housenumber":"11510",
    "addr:postcode":"20854",
    "addr:street":"Falls Rd",
    "iso:country":"US",
    "sg:address":"11510 Falls Rd",
    "sg:city":"Potomac",
    "sg:classifiers":[
        {
            "category":"Education",
            "subcategory":"School",
            "type":"Public Place"
        }
    ],
    "sg:phone":"+1 301 299 4602",
    "sg:postcode":"20854",
    "sg:province":"MD",
    "sg:tags":[
        "high",
        "middle",
        "elementary"
    ],
    "wof:name":"Diener School the",
    "wof:placetype":"venue"
},
  "geometry": {"coordinates":[-77.19297899999999,39.044085],"type":"Point"}
}