{
  "type": "Feature",
  "properties": {
    "iso:country":"US",
    "sg:address":"9605 Ironsides Rd",
    "sg:city":"Nanjemoy",
    "sg:classifiers":[
        {
            "category":"Building & Trades",
            "subcategory":"Electrical",
            "type":"Services"
        }
    ],
    "sg:phone":"+1 301 753 4545",
    "sg:postcode":"20662",
    "sg:province":"MD",
    "sg:tags":[
        "electrician"
    ],
    "wof:name":"Amptech Inc",
    "wof:placetype":"venue"
},
  "geometry": {"coordinates":[-77.19139800000001,38.448022],"type":"Point"}
}