{
  "type": "Feature",
  "properties": {
    "addr:full":"309 Kentlands Blvd Gaithersburg MD 20878",
    "addr:housenumber":"309",
    "addr:postcode":"20878",
    "addr:street":"Kentlands Blvd",
    "iso:country":"US",
    "sg:address":"309 Kentlands Blvd",
    "sg:city":"Gaithersburg",
    "sg:classifiers":[
        {
            "category":"Cinema",
            "subcategory":"Movie Rental",
            "type":"Entertainment"
        }
    ],
    "sg:phone":"+1 301 987 9319",
    "sg:postcode":"20878",
    "sg:province":"MD",
    "sg:tags":[
        "leasing",
        "video",
        "disc",
        "tape"
    ],
    "wof:name":"Blockbuster Video",
    "wof:placetype":"venue"
},
  "geometry": {"coordinates":[-77.239851,39.123822],"type":"Point"}
}