{
  "type": "Feature",
  "properties": {
    "addr:full":"412 Maravista Ct Silver Spring MD 20905",
    "addr:housenumber":"412",
    "addr:postcode":"20905",
    "addr:street":"Maravista Ct",
    "iso:country":"US",
    "sg:address":"412 Maravista Ct",
    "sg:city":"Silver Spring",
    "sg:classifiers":[
        {
            "category":"Home & Garden",
            "subcategory":"Hardware",
            "type":"Retail Goods"
        }
    ],
    "sg:phone":"+1 301 384 2994",
    "sg:postcode":"20905",
    "sg:province":"MD",
    "wof:name":"True Inc",
    "wof:placetype":"venue"
},
  "geometry": {"coordinates":[-77.01378800000001,39.09393],"type":"Point"}
}