{
  "type": "Feature",
  "properties": {
    "iso:country":"US",
    "sg:address":"916 Thayer Ave",
    "sg:city":"Silver Spring",
    "sg:classifiers":[
        {
            "category":"Real Estate",
            "subcategory":"Real Estate Agent",
            "type":"Services"
        }
    ],
    "sg:phone":"+1 301 608 0069",
    "sg:postcode":"20910",
    "sg:province":"MD",
    "wof:name":"Pure Energy Assoc",
    "wof:placetype":"venue"
},
  "geometry": {"coordinates":[-77.025612,38.992917],"type":"Point"}
}