{
  "type": "Feature",
  "properties": {
    "addr:full":"16715 McMullen Hwy SW Cumberland MD 21502",
    "addr:housenumber":"16715",
    "addr:postcode":"21502",
    "addr:street":"Mcmullen Hwy Sw",
    "iso:country":"US",
    "sg:address":"16715 McMullen Hwy SW",
    "sg:city":"Cumberland",
    "sg:classifiers":[
        {
            "category":"Autos & Motor Vehicles",
            "subcategory":"Automobile Sales",
            "type":"Retail Goods"
        }
    ],
    "sg:phone":"+1 301 729 6034",
    "sg:postcode":"21502",
    "sg:province":"MD",
    "sg:tags":[
        "car",
        "dealer"
    ],
    "wof:name":"220 Auto Sales",
    "wof:placetype":"venue"
},
  "geometry": {"coordinates":[-78.85406399999999,39.567713],"type":"Point"}
}