{
  "type": "Feature",
  "properties": {
    "addr:full":"401 Market St Aberdeen MD 21001",
    "addr:housenumber":"401",
    "addr:postcode":"21001",
    "addr:street":"Market St",
    "iso:country":"US",
    "sg:address":"401 Market St",
    "sg:city":"Aberdeen",
    "sg:classifiers":[
        {
            "category":"Government",
            "subcategory":"Office",
            "type":"Public Place"
        }
    ],
    "sg:phone":"+1 410 272 1414",
    "sg:postcode":"21001",
    "sg:province":"MD",
    "sg:tags":[
        "village"
    ],
    "wof:name":"Aberdeen Maintenance Shop",
    "wof:placetype":"venue"
},
  "geometry": {"coordinates":[-76.172106,39.509198],"type":"Point"}
}