{
  "type": "Feature",
  "properties": {
    "addr:full":"11696 Somerset Ave Princess Anne MD 21853",
    "addr:housenumber":"11696",
    "addr:postcode":"21853",
    "addr:street":"Somerset Ave",
    "iso:country":"US",
    "sg:address":"11696 Somerset Ave",
    "sg:city":"Princess Anne",
    "sg:classifiers":[
        {
            "category":"Local Transit",
            "type":"Transportation"
        }
    ],
    "sg:phone":"+1 410 651 2450",
    "sg:postcode":"21853",
    "sg:province":"MD",
    "sg:tags":[
        "operator",
        "bus",
        "line",
        "trucking"
    ],
    "wof:name":"Chevron",
    "wof:placetype":"venue"
},
  "geometry": {"coordinates":[-75.69264699999999,38.201826],"type":"Point"}
}