{
  "type": "Feature",
  "properties": {
    "addr:full":"8536 Piney Branch Rd Silver Spring MD 20901",
    "addr:housenumber":"8536",
    "addr:postcode":"20901",
    "addr:street":"Piney Branch Rd",
    "iso:country":"US",
    "sg:address":"8536 Piney Branch Rd",
    "sg:city":"Silver Spring",
    "sg:classifiers":[
        {
            "category":"Shopping",
            "subcategory":"Crafts & Fabrics",
            "type":"Retail Goods"
        }
    ],
    "sg:phone":"+1 301 565 0895",
    "sg:postcode":"20901",
    "sg:province":"MD",
    "sg:tags":[
        "shop",
        "sewing"
    ],
    "wof:name":"Freedom Jewelry & Fabrics Inc",
    "wof:placetype":"venue"
},
  "geometry": {"coordinates":[-77.003078,38.998365],"type":"Point"}
}