{
  "type": "Feature",
  "properties": {
    "iso:country":"US",
    "sg:address":"2200 Broening Hwy Ste 280",
    "sg:city":"Baltimore",
    "sg:classifiers":[
        {
            "category":"Education",
            "subcategory":"Special Training",
            "type":"Public Place"
        }
    ],
    "sg:phone":"+1 888 292 1818",
    "sg:postcode":"21224",
    "sg:province":"MD",
    "sg:tags":[
        "school",
        "specialty"
    ],
    "wof:name":"All-State Career Healthcare Division",
    "wof:placetype":"venue"
},
  "geometry": {"coordinates":[-76.543207,39.26478],"type":"Point"}
}