{
  "type": "Feature",
  "properties": {
    "iso:country":"US",
    "sg:address":"11 Lloyd St",
    "sg:city":"Baltimore",
    "sg:classifiers":[
        {
            "category":"Museum",
            "type":"Entertainment"
        }
    ],
    "sg:phone":"+1 410 342 7561",
    "sg:postcode":"21202",
    "sg:province":"MD",
    "wof:name":"Lloyd Street Synagogue",
    "wof:placetype":"venue"
},
  "geometry": {"coordinates":[-76.60140199999999,39.290279],"type":"Point"}
}