{
  "type": "Feature",
  "properties": {
    "iso:country":"US",
    "sg:address":"21081 Haven Rd",
    "sg:city":"Rock Hall",
    "sg:classifiers":[
        {
            "category":"Home & Garden",
            "subcategory":"Carpets & Floor Coverings",
            "type":"Retail Goods"
        }
    ],
    "sg:phone":"+1 410 639 2948",
    "sg:postcode":"21661",
    "sg:province":"MD",
    "wof:name":"Davis C Oriental Rug Service",
    "wof:placetype":"venue"
},
  "geometry": {"coordinates":[-76.240661,39.142],"type":"Point"}
}