{
  "type": "Feature",
  "properties": {
    "iso:country":"US",
    "sg:address":"5601 Loch Raven Blvd",
    "sg:city":"Baltimore",
    "sg:classifiers":[
        {
            "category":"Health Services",
            "subcategory":"Health Practitioner",
            "type":"Services"
        }
    ],
    "sg:phone":"+1 410 532 3834",
    "sg:postcode":"21239",
    "sg:province":"MD",
    "sg:tags":[
        "gambling",
        "addiction-information",
        "treatment"
    ],
    "sg:website":"http://www.son.jhmi.edu",
    "wof:name":"Jhu Rehab Medicine At Gsh",
    "wof:placetype":"venue"
},
  "geometry": {"coordinates":[-76.588887,39.358921],"type":"Point"}
}