{
  "type": "Feature",
  "properties": {
    "iso:country":"US",
    "sg:address":"6751 Columbia Gateway Dr",
    "sg:city":"Columbia",
    "sg:classifiers":[
        {
            "category":"Education",
            "subcategory":"Vocational School",
            "type":"Public Place"
        }
    ],
    "sg:phone":"+1 410 772 4282",
    "sg:postcode":"21046",
    "sg:province":"MD",
    "sg:tags":[
        "training",
        "computer"
    ],
    "wof:name":"Charles I Ecker Bus Training",
    "wof:placetype":"venue"
},
  "geometry": {"coordinates":[-76.801902,39.183503],"type":"Point"}
}