{
  "type": "Feature",
  "properties": {
    "addr:full":"6503 Park Heights Ave Baltimore MD 21215",
    "addr:housenumber":"6503",
    "addr:postcode":"21215",
    "addr:street":"Park Heights Ave",
    "iso:country":"US",
    "sg:address":"6503 Park Heights Ave",
    "sg:city":"Baltimore",
    "sg:classifiers":[
        {
            "category":"Health Services",
            "subcategory":"Doctor",
            "type":"Services"
        }
    ],
    "sg:phone":"+1 410 358 2397",
    "sg:postcode":"21215",
    "sg:province":"MD",
    "sg:tags":[
        "physician",
        "surgeon"
    ],
    "wof:name":"R Menachem Cooper MD",
    "wof:placetype":"venue"
},
  "geometry": {"coordinates":[-76.69729100000001,39.360522],"type":"Point"}
}