{
  "type": "Feature",
  "properties": {
    "iso:country":"US",
    "sg:address":"2024 Broad St",
    "sg:city":"Pocomoke City",
    "sg:classifiers":[
        {
            "category":"Wholesale",
            "subcategory":"Metals & Minerals",
            "type":"Manufacturing & Wholesale Goods"
        }
    ],
    "sg:phone":"+1 410 572 5740",
    "sg:postcode":"21851",
    "sg:province":"MD",
    "sg:tags":[
        "product",
        "wire"
    ],
    "wof:name":"P B Wire",
    "wof:placetype":"venue"
},
  "geometry": {"coordinates":[-75.560433,38.056847],"type":"Point"}
}