{
  "type": "Feature",
  "properties": {
    "addr:full":"8900 Colesville Rd Silver Spring MD 20910",
    "addr:housenumber":"8900",
    "addr:postcode":"20910",
    "addr:street":"Colesville Rd",
    "iso:country":"US",
    "sg:address":"8900 Colesville Rd",
    "sg:city":"Silver Spring",
    "sg:classifiers":[
        {
            "category":"Organizations",
            "subcategory":"Religious Organization",
            "type":"Services"
        }
    ],
    "sg:phone":"+1 301 589 5768",
    "sg:postcode":"20910",
    "sg:province":"MD",
    "sg:tags":[
        "church"
    ],
    "wof:name":"Seventh-Day Adventist Church",
    "wof:placetype":"venue"
},
  "geometry": {"coordinates":[-77.02544399999999,39.00091],"type":"Point"}
}