{
  "type": "Feature",
  "properties": {
    "addr:full":"1100 Light St Ste A Baltimore MD 21230",
    "addr:housenumber":"1100",
    "addr:postcode":"21230",
    "addr:street":"Light St Ste A",
    "iso:country":"US",
    "sg:address":"1100 Light St Ste A",
    "sg:city":"Baltimore",
    "sg:classifiers":[
        {
            "category":"Shopping",
            "subcategory":"Photographic Equipment",
            "type":"Retail Goods"
        }
    ],
    "sg:phone":"+1 410 685 7979",
    "sg:postcode":"21230",
    "sg:province":"MD",
    "sg:tags":[
        "supply"
    ],
    "wof:name":"Sign Solutions, Inc.",
    "wof:placetype":"venue"
},
  "geometry": {"coordinates":[-76.612297,39.27681],"type":"Point"}
}