{
  "type": "Feature",
  "properties": {
    "addr:full":"138 Main St Annapolis MD 21401",
    "addr:housenumber":"138",
    "addr:postcode":"21401",
    "addr:street":"Main St",
    "iso:country":"US",
    "sg:address":"138 Main St",
    "sg:city":"Annapolis",
    "sg:classifiers":[
        {
            "category":"Shopping",
            "subcategory":"Photographic Equipment",
            "type":"Retail Goods"
        }
    ],
    "sg:phone":"+1 301 261 1250",
    "sg:postcode":"21401",
    "sg:province":"MD",
    "sg:tags":[
        "supply"
    ],
    "wof:name":"Ritz Camera Ctr",
    "wof:placetype":"venue"
},
  "geometry": {"coordinates":[-76.488979,38.977685],"type":"Point"}
}