{
  "type": "Feature",
  "properties": {
    "iso:country":"US",
    "sg:address":"1285 Cinnamon Ridge Ct",
    "sg:city":"Sykesville",
    "sg:classifiers":[
        {
            "category":"Professional",
            "type":"Services"
        }
    ],
    "sg:phone":"+1 410 549 4532",
    "sg:postcode":"21784",
    "sg:province":"MD",
    "wof:name":"Thomas Czajkowski",
    "wof:placetype":"venue"
},
  "geometry": {"coordinates":[-76.94714,39.396418],"type":"Point"}
}