{
  "type": "Feature",
  "properties": {
    "addr:full":"2836 The Alameda Baltimore MD 21218",
    "addr:housenumber":"2836",
    "addr:postcode":"21218",
    "addr:street":"The Alameda",
    "iso:country":"US",
    "sg:address":"2836 The Alameda",
    "sg:city":"Baltimore",
    "sg:classifiers":[
        {
            "category":"Organizations",
            "subcategory":"Religious Organization",
            "type":"Services"
        }
    ],
    "sg:phone":"+1 410 243 2847",
    "sg:postcode":"21218",
    "sg:province":"MD",
    "sg:tags":[
        "clergy"
    ],
    "wof:name":"Wiley H Barnes",
    "wof:placetype":"venue"
},
  "geometry": {"coordinates":[-76.593703,39.324503],"type":"Point"}
}