{
  "type": "Feature",
  "properties": {
    "iso:country":"US",
    "sg:address":"7425 MacArthur Blvd",
    "sg:city":"Cabin John",
    "sg:classifiers":[
        {
            "category":"Social Services",
            "subcategory":"Child Care",
            "type":"Services"
        },
        {
            "category":"Education",
            "subcategory":"Preschool",
            "type":"Public Place"
        },
        {
            "category":"Education",
            "subcategory":"School",
            "type":"Public Place"
        }
    ],
    "sg:phone":"+1 301 320 4565",
    "sg:postcode":"20818",
    "sg:province":"MD",
    "sg:tags":[
        "elementary",
        "day"
    ],
    "wof:name":"Clara Barton Center For Children",
    "wof:placetype":"venue"
},
  "geometry": {"coordinates":[-77.149399,38.972698],"type":"Point"}
}