{
  "type": "Feature",
  "properties": {
    "iso:country":"US",
    "sg:address":"3408 Lancer Dr",
    "sg:city":"Hyattsville",
    "sg:classifiers":[
        {
            "category":"Building & Trades",
            "subcategory":"Construction",
            "type":"Services"
        }
    ],
    "sg:phone":"+1 301 277 5461",
    "sg:postcode":"20782",
    "sg:province":"MD",
    "sg:tags":[
        "carpentry",
        "contractor"
    ],
    "wof:name":"Manuel E Bedon",
    "wof:placetype":"venue"
},
  "geometry": {"coordinates":[-76.958781,38.957171],"type":"Point"}
}