{
  "type": "Feature",
  "properties": {
    "addr:full":"15030 Turkey Foot Rd Gaithersburg MD 20878",
    "addr:housenumber":"15030",
    "addr:postcode":"20878",
    "addr:street":"Turkey Foot Rd",
    "iso:country":"US",
    "sg:address":"15030 Turkey Foot Rd",
    "sg:city":"Gaithersburg",
    "sg:classifiers":[
        {
            "category":"Social Services",
            "type":"Services"
        }
    ],
    "sg:phone":"+1 301 519 0200",
    "sg:postcode":"20878",
    "sg:province":"MD",
    "sg:tags":[
        "care",
        "center",
        "day"
    ],
    "wof:name":"Kids Adventures At Darnestown",
    "wof:placetype":"venue"
},
  "geometry": {"coordinates":[-77.284069,39.100691],"type":"Point"}
}