{
  "type": "Feature",
  "properties": {
    "iso:country":"US",
    "sg:address":"401 N Washington St",
    "sg:city":"Rockville",
    "sg:classifiers":[
        {
            "category":"Banks & Credit Unions",
            "subcategory":"Bank",
            "type":"Services"
        }
    ],
    "sg:phone":"+1 301 762 3101",
    "sg:postcode":"20850",
    "sg:province":"MD",
    "wof:name":"Provident Bank",
    "wof:placetype":"venue"
},
  "geometry": {"coordinates":[-77.15364700000001,39.090807],"type":"Point"}
}