{
  "type": "Feature",
  "properties": {
    "addr:full":"7127 Rutherford Rd Windsor Mill MD 21244",
    "addr:housenumber":"7127",
    "addr:postcode":"21244",
    "addr:street":"Rutherford Rd",
    "iso:country":"US",
    "sg:address":"7127 Rutherford Rd",
    "sg:city":"Windsor Mill",
    "sg:classifiers":[
        {
            "category":"Social Services",
            "subcategory":"Child Care",
            "type":"Services"
        }
    ],
    "sg:phone":"+1 410 944 7001",
    "sg:postcode":"21244",
    "sg:province":"MD",
    "sg:tags":[
        "day"
    ],
    "wof:name":"Kinderspiel Child Care Center",
    "wof:placetype":"venue"
},
  "geometry": {"coordinates":[-76.747539,39.327367],"type":"Point"}
}