{
  "type": "Feature",
  "properties": {
    "addr:full":"2822 Odonnell St Baltimore MD 21224",
    "addr:housenumber":"2822",
    "addr:postcode":"21224",
    "addr:street":"Odonnell St",
    "iso:country":"US",
    "sg:address":"2822 Odonnell St",
    "sg:city":"Baltimore",
    "sg:classifiers":[
        {
            "category":"Wholesale",
            "subcategory":"Plants",
            "type":"Manufacturing & Wholesale Goods"
        },
        {
            "category":"Shopping",
            "subcategory":"Crafts & Fabrics",
            "type":"Retail Goods"
        }
    ],
    "sg:phone":"+1 410 878 0373",
    "sg:postcode":"21224",
    "sg:province":"MD",
    "sg:tags":[
        "supplies-wholesale",
        "manufacturer",
        "florists'",
        "florists-wholesale"
    ],
    "wof:name":"My Flower Box Production",
    "wof:placetype":"venue"
},
  "geometry": {"coordinates":[-76.576105,39.280302],"type":"Point"}
}