{
  "type": "Feature",
  "properties": {
    "iso:country":"US",
    "sg:address":"610 E Diamond Ave",
    "sg:city":"Gaithersburg",
    "sg:classifiers":[
        {
            "category":"Social Services",
            "type":"Services"
        }
    ],
    "sg:phone":"+1 301 330 0330",
    "sg:postcode":"20877",
    "sg:province":"MD",
    "sg:tags":[
        "organization",
        "welfare"
    ],
    "sg:website":"www.mentor-me.org",
    "wof:name":"Task Force On Mentoring",
    "wof:placetype":"venue"
},
  "geometry": {"coordinates":[-77.180493,39.139298],"type":"Point"}
}