{
  "type": "Feature",
  "properties": {
    "iso:country":"US",
    "sg:address":"13118 Hathaway Dr",
    "sg:city":"Silver Spring",
    "sg:classifiers":[
        {
            "category":"Retail",
            "subcategory":"Repair Shop",
            "type":"Services"
        }
    ],
    "sg:phone":"+1 301 949 3723",
    "sg:postcode":"20906",
    "sg:province":"MD",
    "sg:tags":[
        "electrical"
    ],
    "wof:name":"Electro Tech",
    "wof:placetype":"venue"
},
  "geometry": {"coordinates":[-77.056069,39.071399],"type":"Point"}
}