{
  "type": "Feature",
  "properties": {
    "addr:full":"5910 Frederick Crossing Ln Frederick MD 21704",
    "addr:housenumber":"5910",
    "addr:postcode":"21704",
    "addr:street":"Frederick Crossing Ln",
    "iso:country":"US",
    "sg:address":"5910 Frederick Crossing Ln",
    "sg:city":"Frederick",
    "sg:classifiers":[
        {
            "category":"Health Services",
            "subcategory":"Doctor",
            "type":"Services"
        }
    ],
    "sg:phone":"+1 301 662 4422",
    "sg:postcode":"21704",
    "sg:province":"MD",
    "sg:tags":[
        "dentist"
    ],
    "wof:name":"Omar K Mahmassani DDS",
    "wof:placetype":"venue"
},
  "geometry": {"coordinates":[-77.413096,39.395086],"type":"Point"}
}