{
  "type": "Feature",
  "properties": {
    "addr:full":"8501 Bates Dr Bowie MD 20720",
    "addr:housenumber":"8501",
    "addr:postcode":"20720",
    "addr:street":"Bates Dr",
    "iso:country":"US",
    "sg:address":"8501 Bates Dr",
    "sg:city":"Bowie",
    "sg:classifiers":[
        {
            "category":"Manufacturing",
            "subcategory":"Paper Products",
            "type":"Manufacturing & Wholesale Goods"
        }
    ],
    "sg:phone":"+1 301 805 8977",
    "sg:postcode":"20720",
    "sg:province":"MD",
    "sg:tags":[
        "bamboo"
    ],
    "wof:name":"Garden Of Joy Child Enrichment Center",
    "wof:placetype":"venue"
},
  "geometry": {"coordinates":[-76.79612,39.005589],"type":"Point"}
}