{
  "type": "Feature",
  "properties": {
    "addr:full":"3188 Crain Hwy Waldorf MD 20603",
    "addr:housenumber":"3188",
    "addr:postcode":"20603",
    "addr:street":"Crain Hwy",
    "iso:country":"US",
    "sg:address":"3188 Crain Hwy",
    "sg:city":"Waldorf",
    "sg:classifiers":[
        {
            "category":"Autos & Motor Vehicles",
            "subcategory":"Automobile Sales",
            "type":"Retail Goods"
        }
    ],
    "sg:phone":"+1 301 645 1711",
    "sg:postcode":"20603",
    "sg:province":"MD",
    "sg:tags":[
        "car",
        "dealer"
    ],
    "sg:website":"www.mmasow.com",
    "wof:name":"M & M Auto Repairs",
    "wof:placetype":"venue"
},
  "geometry": {"coordinates":[-76.91241100000001,38.624354],"type":"Point"}
}