{
  "type": "Feature",
  "properties": {
    "iso:country":"US",
    "sg:address":"4101 Harvard Pl",
    "sg:city":"Frederick",
    "sg:classifiers":[
        {
            "category":"Building & Trades",
            "subcategory":"Landscaping Services",
            "type":"Services"
        }
    ],
    "sg:phone":"+1 301 473 4370",
    "sg:postcode":"21703",
    "sg:province":"MD",
    "sg:tags":[
        "stump",
        "tree",
        "grinding",
        "removal",
        "arborist"
    ],
    "wof:name":"Alan Nichols-Appalachian Tree Service",
    "wof:placetype":"venue"
},
  "geometry": {"coordinates":[-77.498009,39.347801],"type":"Point"}
}