{
  "type": "Feature",
  "properties": {
    "addr:full":"8904 Mallard Ct Columbia MD 21045",
    "addr:housenumber":"8904",
    "addr:postcode":"21045",
    "addr:street":"Mallard Ct",
    "iso:country":"US",
    "sg:address":"8904 Mallard Ct",
    "sg:city":"Columbia",
    "sg:classifiers":[
        {
            "category":"Professional",
            "type":"Services"
        }
    ],
    "sg:phone":"+1 410 804 4108",
    "sg:postcode":"21045",
    "sg:province":"MD",
    "sg:tags":[
        "establishment"
    ],
    "wof:name":"Carey & Carey",
    "wof:placetype":"venue"
},
  "geometry": {"coordinates":[-76.816113,39.232096],"type":"Point"}
}