{
  "type": "Feature",
  "properties": {
    "iso:country":"US",
    "sg:address":"18630 Keedysville Rd",
    "sg:city":"Keedysville",
    "sg:classifiers":[
        {
            "category":"Home & Garden",
            "subcategory":"Furniture",
            "type":"Retail Goods"
        }
    ],
    "sg:phone":"+1 301 432 2050",
    "sg:postcode":"21756",
    "sg:province":"MD",
    "sg:tags":[
        "store"
    ],
    "wof:name":"Dn Finneyfrock Inc",
    "wof:placetype":"venue"
},
  "geometry": {"coordinates":[-77.718473,39.496636],"type":"Point"}
}