{
  "type": "Feature",
  "properties": {
    "addr:full":"15308 Brandywine Dr SW Cumberland MD 21502",
    "addr:housenumber":"15308",
    "addr:postcode":"21502",
    "addr:street":"Brandywine Dr Sw",
    "iso:country":"US",
    "sg:address":"15308 Brandywine Dr SW",
    "sg:city":"Cumberland",
    "sg:classifiers":[
        {
            "category":"Banks & Credit Unions",
            "subcategory":"Investment Brokerage",
            "type":"Services"
        }
    ],
    "sg:phone":"+1 301 729 3333",
    "sg:postcode":"21502",
    "sg:province":"MD",
    "sg:tags":[
        "consultant",
        "planning",
        "financial"
    ],
    "wof:name":"G W Financial",
    "wof:placetype":"venue"
},
  "geometry": {"coordinates":[-78.85916,39.58555],"type":"Point"}
}