{
  "type": "Feature",
  "properties": {
    "iso:country":"US",
    "sg:address":"5709 Granby Rd",
    "sg:city":"Rockville",
    "sg:classifiers":[
        {
            "category":"Professional",
            "subcategory":"Accounting & Tax Preparation",
            "type":"Services"
        }
    ],
    "sg:phone":"+1 301 840 0438",
    "sg:postcode":"20855",
    "sg:province":"MD",
    "sg:tags":[
        "accountant"
    ],
    "sg:website":"www.pmrltd.com",
    "wof:name":"PMR Assoc LTD",
    "wof:placetype":"venue"
},
  "geometry": {"coordinates":[-77.115351,39.164734],"type":"Point"}
}