{
  "type": "Feature",
  "properties": {
    "iso:country":"US",
    "sg:address":"533 Baltimore Pike ",
    "sg:city":"Bel Air",
    "sg:classifiers":[
        {
            "category":"Cafe",
            "type":"Food & Drink"
        }
    ],
    "sg:menulink":"http://www.allmenus.com/md/bel-air/285697-zen16-sushi-cafe/menu/",
    "sg:phone":"+1 410 836 5999",
    "sg:postcode":"21014",
    "sg:province":"MD",
    "sg:tags":[
        "sushi",
        "asian"
    ],
    "wof:name":"Zen16 Sushi Cafe",
    "wof:placetype":"venue"
},
  "geometry": {"coordinates":[-76.353212,39.527596],"type":"Point"}
}