{
  "type": "Feature",
  "properties": {
    "addr:full":"14320 Marlborough Ln Upper Marlboro MD 20772",
    "addr:housenumber":"14320",
    "addr:postcode":"20772",
    "addr:street":"Marlborough Ln",
    "iso:country":"US",
    "sg:address":"14320 Marlborough Ln",
    "sg:city":"Upper Marlboro",
    "sg:classifiers":[
        {
            "category":"Banks & Credit Unions",
            "subcategory":"Investment Brokerage",
            "type":"Services"
        }
    ],
    "sg:phone":"+1 301 780 8680",
    "sg:postcode":"20772",
    "sg:province":"MD",
    "sg:tags":[
        "consultant",
        "planning",
        "financial"
    ],
    "wof:name":"American Express Financial Adv",
    "wof:placetype":"venue"
},
  "geometry": {"coordinates":[-76.758095,38.819595],"type":"Point"}
}