{
  "type": "Feature",
  "properties": {
    "iso:country":"US",
    "sg:address":"4102 Pennington Ave",
    "sg:city":"Baltimore",
    "sg:classifiers":[
        {
            "category":"Autos & Motor Vehicles",
            "subcategory":"Automobile Sales",
            "type":"Retail Goods"
        }
    ],
    "sg:phone":"+1 410 354 0274",
    "sg:postcode":"21226",
    "sg:province":"MD",
    "sg:tags":[
        "car",
        "used",
        "dealer"
    ],
    "wof:name":"Sann's Auto Sales & Trucks",
    "wof:placetype":"venue"
},
  "geometry": {"coordinates":[-76.588766,39.227618],"type":"Point"}
}