{
  "type": "Feature",
  "properties": {
    "iso:country":"US",
    "sg:address":"4236 Isbell St",
    "sg:city":"Silver Spring",
    "sg:classifiers":[
        {
            "category":"Building & Trades",
            "subcategory":"Landscaping Services",
            "type":"Services"
        }
    ],
    "sg:phone":"+1 301 933 4185",
    "sg:postcode":"20906",
    "sg:province":"MD",
    "sg:tags":[
        "landscape"
    ],
    "wof:name":"T D Landscaping",
    "wof:placetype":"venue"
},
  "geometry": {"coordinates":[-77.084476,39.062873],"type":"Point"}
}