{
  "type": "Feature",
  "properties": {
    "iso:country":"US",
    "sg:address":"9534 Croom Rd",
    "sg:city":"Upper Marlboro",
    "sg:classifiers":[
        {
            "category":"Recreation",
            "type":"Entertainment"
        }
    ],
    "sg:phone":"+1 301 627 3918",
    "sg:postcode":"20772",
    "sg:province":"MD",
    "sg:tags":[
        "stable"
    ],
    "wof:name":"Flying Change Farm Inc",
    "wof:placetype":"venue"
},
  "geometry": {"coordinates":[-76.760605,38.758993],"type":"Point"}
}