{
  "type": "Feature",
  "properties": {
    "addr:full":"11304 Earlston Dr Mitchellville MD 20721",
    "addr:housenumber":"11304",
    "addr:postcode":"20721",
    "addr:street":"Earlston Dr",
    "iso:country":"US",
    "sg:address":"11304 Earlston Dr",
    "sg:city":"Mitchellville",
    "sg:classifiers":[
        {
            "category":"Insurance",
            "subcategory":"Insurance Agent",
            "type":"Services"
        }
    ],
    "sg:phone":"+1 301 262 3240",
    "sg:postcode":"20721",
    "sg:province":"MD",
    "wof:name":"Ralph V Daniels Assoc",
    "wof:placetype":"venue"
},
  "geometry": {"coordinates":[-76.809613,38.940382],"type":"Point"}
}