{
  "type": "Feature",
  "properties": {
    "iso:country":"US",
    "sg:address":"8525 Gavin Manor Ct",
    "sg:city":"Chevy Chase",
    "sg:classifiers":[
        {
            "category":"Building & Trades",
            "subcategory":"Construction",
            "type":"Services"
        },
        {
            "category":"Home & Garden",
            "subcategory":"Furniture",
            "type":"Retail Goods"
        }
    ],
    "sg:phone":"+1 301 656 0200",
    "sg:postcode":"20815",
    "sg:province":"MD",
    "sg:tags":[
        "interior",
        "design",
        "store"
    ],
    "wof:name":"Chase Furniture Inc",
    "wof:placetype":"venue"
},
  "geometry": {"coordinates":[-77.072502,38.997799],"type":"Point"}
}