{
  "type": "Feature",
  "properties": {
    "iso:country":"US",
    "sg:address":"429 Danbridge St",
    "sg:city":"Gaithersburg",
    "sg:classifiers":[
        {
            "category":"Professional",
            "subcategory":"Accounting & Tax Preparation",
            "type":"Services"
        }
    ],
    "sg:phone":"+1 301 948 6333",
    "sg:postcode":"20878",
    "sg:province":"MD",
    "sg:tags":[
        "return",
        "preparation-business",
        "accountants-certified",
        "payroll",
        "bookkeeping",
        "public"
    ],
    "sg:website":"http://www.grimmandassociates.com",
    "wof:name":"Bjg Business Accounting - Beverly J Grimm CPA",
    "wof:placetype":"venue"
},
  "geometry": {"coordinates":[-77.227666,39.116407],"type":"Point"}
}