{
  "type": "Feature",
  "properties": {
    "iso:country":"US",
    "sg:address":"941 Bonifant St",
    "sg:city":"Silver Spring",
    "sg:classifiers":[
        {
            "category":"Personal",
            "subcategory":"Barber",
            "type":"Services"
        }
    ],
    "sg:phone":"+1 301 588 3440",
    "sg:postcode":"20910",
    "sg:province":"MD",
    "wof:name":"Millennium Barber Salon",
    "wof:placetype":"venue"
},
  "geometry": {"coordinates":[-77.025829,38.993799],"type":"Point"}
}