{
  "type": "Feature",
  "properties": {
    "iso:country":"US",
    "sg:address":"888 Memorial Dr",
    "sg:city":"Oakland",
    "sg:classifiers":[
        {
            "category":"Health Services",
            "subcategory":"Optometrist",
            "type":"Services"
        }
    ],
    "sg:phone":"+1 301 334 1016",
    "sg:postcode":"21550",
    "sg:province":"MD",
    "wof:name":"Precision Optical Of Oakland",
    "wof:placetype":"venue"
},
  "geometry": {"coordinates":[-79.395677,39.413609],"type":"Point"}
}