{
  "type": "Feature",
  "properties": {
    "addr:full":"601 Eastern Ave Ste 103 Fairmount Heights MD 20743",
    "addr:housenumber":"601",
    "addr:postcode":"20743",
    "addr:street":"Eastern Ave Ste 103",
    "iso:country":"US",
    "sg:address":"601 Eastern Ave Ste 103",
    "sg:city":"Fairmount Heights",
    "sg:classifiers":[
        {
            "category":"Health Services",
            "subcategory":"Doctor",
            "type":"Services"
        }
    ],
    "sg:phone":"+1 301 925 4433",
    "sg:postcode":"20743",
    "sg:province":"MD",
    "wof:name":"Akpan Margaret Dr MD",
    "wof:placetype":"venue"
},
  "geometry": {"coordinates":[-76.899002,38.883202],"type":"Point"}
}