{
  "type": "Feature",
  "properties": {
    "iso:country":"US",
    "sg:address":"1431 Steuart St",
    "sg:city":"Baltimore",
    "sg:classifiers":[
        {
            "category":"Structure",
            "subcategory":"Office Building",
            "type":"Public Place"
        }
    ],
    "sg:phone":"+1 410 404 0633",
    "sg:postcode":"21230",
    "sg:province":"MD",
    "sg:tags":[
        "park"
    ],
    "wof:name":"Open Door Properties",
    "wof:placetype":"venue"
},
  "geometry": {"coordinates":[-76.58955,39.268105],"type":"Point"}
}