{
  "type": "Feature",
  "properties": {
    "addr:full":"522 Thomas Run Rd Bel Air MD 21015",
    "addr:housenumber":"522",
    "addr:postcode":"21015",
    "addr:street":"Thomas Run Rd",
    "iso:country":"US",
    "sg:address":"522 Thomas Run Rd",
    "sg:city":"Bel Air",
    "sg:classifiers":[
        {
            "category":"Health Services",
            "subcategory":"Nursing And Care Facility",
            "type":"Services"
        }
    ],
    "sg:phone":"+1 410 989 0363",
    "sg:postcode":"21015",
    "sg:province":"MD",
    "sg:tags":[
        "adult"
    ],
    "wof:name":"Jacob's Well Assisted Living",
    "wof:placetype":"venue"
},
  "geometry": {"coordinates":[-76.29032599999999,39.569307],"type":"Point"}
}