{
  "type": "Feature",
  "properties": {
    "addr:full":"9712 Medical Center Dr Rockville MD 20850",
    "addr:housenumber":"9712",
    "addr:postcode":"20850",
    "addr:street":"Medical Center Dr",
    "iso:country":"US",
    "sg:address":"9712 Medical Center Dr",
    "sg:city":"Rockville",
    "sg:classifiers":[
        {
            "category":"Organizations",
            "subcategory":"Non-profit Organization",
            "type":"Services"
        }
    ],
    "sg:phone":"+1 301 838 0200",
    "sg:postcode":"20850",
    "sg:province":"MD",
    "wof:name":"TIGR",
    "wof:placetype":"venue"
},
  "geometry": {"coordinates":[-77.19499500000001,39.100575],"type":"Point"}
}