{
  "type": "Feature",
  "properties": {
    "addr:full":"1535 Oak Hill Ave Hagerstown MD 21742",
    "addr:housenumber":"1535",
    "addr:postcode":"21742",
    "addr:street":"Oak Hill Ave",
    "iso:country":"US",
    "sg:address":"1535 Oak Hill Ave",
    "sg:city":"Hagerstown",
    "sg:classifiers":[
        {
            "category":"Education",
            "subcategory":"School",
            "type":"Public Place"
        }
    ],
    "sg:phone":"+1 301 739 4266",
    "sg:postcode":"21742",
    "sg:province":"MD",
    "sg:website":"www.goretti.org",
    "wof:name":"St Maria Goretti High School",
    "wof:placetype":"venue"
},
  "geometry": {"coordinates":[-77.7037,39.664239],"type":"Point"}
}