{
  "type": "Feature",
  "properties": {
    "iso:country":"US",
    "sg:address":"3460 Ellicott Center Dr Ste 202",
    "sg:city":"Ellicott City",
    "sg:classifiers":[
        {
            "category":"Professional",
            "subcategory":"Accounting & Tax Preparation",
            "type":"Services"
        }
    ],
    "sg:phone":"+1 410 461 3110",
    "sg:postcode":"21043",
    "sg:province":"MD",
    "sg:tags":[
        "accountant"
    ],
    "wof:name":"Benicewicz Walter F Jr CPA",
    "wof:placetype":"venue"
},
  "geometry": {"coordinates":[-76.814697,39.2766],"type":"Point"}
}