{
  "type": "Feature",
  "properties": {
    "iso:country":"US",
    "sg:address":"3407 Fort Meade Rd",
    "sg:city":"Laurel",
    "sg:classifiers":[
        {
            "category":"Sports & Exercise",
            "subcategory":"Gym",
            "type":"Entertainment"
        }
    ],
    "sg:phone":"+1 301 776 4200",
    "sg:postcode":"20724",
    "sg:province":"MD",
    "sg:tags":[
        "club",
        "health",
        "studio",
        "gymnasium"
    ],
    "wof:name":"Ladies Workout Express",
    "wof:placetype":"venue"
},
  "geometry": {"coordinates":[-76.811741,39.099259],"type":"Point"}
}