{
  "type": "Feature",
  "properties": {
    "iso:country":"US",
    "sg:address":"3155 Hawks Hill Ln",
    "sg:city":"Keedysville",
    "sg:classifiers":[
        {
            "category":"Building & Trades",
            "subcategory":"Construction",
            "type":"Services"
        }
    ],
    "sg:phone":"+1 301 432 0883",
    "sg:postcode":"21756",
    "sg:province":"MD",
    "sg:tags":[
        "contractor"
    ],
    "sg:website":"www.northernloghomes.net",
    "wof:name":"Hawks Hill Log Homes",
    "wof:placetype":"venue"
},
  "geometry": {"coordinates":[-77.714938,39.387552],"type":"Point"}
}