{
  "type": "Feature",
  "properties": {
    "iso:country":"US",
    "sg:address":"11161 Pulaski Hwy",
    "sg:city":"White Marsh",
    "sg:classifiers":[
        {
            "category":"Manufacturing",
            "subcategory":"Tools & Machinery",
            "type":"Manufacturing & Wholesale Goods"
        }
    ],
    "sg:phone":"+1 410 335 6905",
    "sg:postcode":"21162",
    "sg:province":"MD",
    "sg:tags":[
        "equipment",
        "calculating",
        "adding"
    ],
    "wof:name":"Cannon-Wren's Business Machines",
    "wof:placetype":"venue"
},
  "geometry": {"coordinates":[-76.416397,39.388699],"type":"Point"}
}