{
  "type": "Feature",
  "properties": {
    "iso:country":"US",
    "sg:address":"54 Hardwood Dr",
    "sg:city":"Baltimore",
    "sg:classifiers":[
        {
            "category":"Freight",
            "type":"Transportation"
        }
    ],
    "sg:phone":"+1 443 829 9518",
    "sg:postcode":"21237",
    "sg:province":"MD",
    "sg:tags":[
        "operator",
        "local",
        "trucking"
    ],
    "wof:name":"J D K Trucking Inc",
    "wof:placetype":"venue"
},
  "geometry": {"coordinates":[-76.493501,39.378839],"type":"Point"}
}