{
  "type": "Feature",
  "properties": {
    "addr:full":"54 Hardwood Dr Baltimore MD 21237",
    "addr:housenumber":"54",
    "addr:postcode":"21237",
    "addr:street":"Hardwood Dr",
    "iso:country":"US",
    "sg:address":"54 Hardwood Dr",
    "sg:city":"Baltimore",
    "sg:classifiers":[
        {
            "category":"Freight",
            "type":"Transportation"
        }
    ],
    "sg:phone":"+1 443 829 9518",
    "sg:postcode":"21237",
    "sg:province":"MD",
    "sg:tags":[
        "operator",
        "local",
        "trucking"
    ],
    "wof:name":"J D K Trucking Inc",
    "wof:placetype":"venue"
},
  "geometry": {"coordinates":[-76.49350099999999,39.378839],"type":"Point"}
}