{
  "type": "Feature",
  "properties": {
    "iso:country":"US",
    "sg:address":"19322 Montgomery Village Ave",
    "sg:city":"Gaithersburg",
    "sg:classifiers":[
        {
            "category":"Personal",
            "subcategory":"Beauty Salon",
            "type":"Services"
        }
    ],
    "sg:phone":"+1 301 330 4403",
    "sg:postcode":"20886",
    "sg:province":"MD",
    "wof:name":"Linda's Nails",
    "wof:placetype":"venue"
},
  "geometry": {"coordinates":[-77.20364600000001,39.174093],"type":"Point"}
}