{
  "type": "Feature",
  "properties": {
    "iso:country":"US",
    "sg:address":"201 E Pratt St",
    "sg:city":"Baltimore",
    "sg:classifiers":[
        {
            "category":"Shopping",
            "subcategory":"Clothing, Apparel, & Fashions",
            "type":"Retail Goods"
        }
    ],
    "sg:phone":"+1 410 244 0011",
    "sg:postcode":"21202",
    "sg:province":"MD",
    "sg:tags":[
        "garment",
        "center"
    ],
    "wof:name":"Iggy Apparel",
    "wof:placetype":"venue"
},
  "geometry": {"coordinates":[-76.611546,39.286463],"type":"Point"}
}