{
  "type": "Feature",
  "properties": {
    "addr:full":"14 Flameleaf Ct Gaithersburg MD 20878",
    "addr:housenumber":"14",
    "addr:postcode":"20878",
    "addr:street":"Flameleaf Ct",
    "iso:country":"US",
    "sg:address":"14 Flameleaf Ct",
    "sg:city":"Gaithersburg",
    "sg:classifiers":[
        {
            "category":"Professional",
            "subcategory":"Business Services",
            "type":"Services"
        }
    ],
    "sg:phone":"+1 301 455 7726",
    "sg:postcode":"20878",
    "sg:province":"MD",
    "sg:tags":[
        "support",
        "deliver",
        "training",
        "government"
    ],
    "wof:name":"Andrew Taylor Inc",
    "wof:placetype":"venue"
},
  "geometry": {"coordinates":[-77.22498899999999,39.110834],"type":"Point"}
}