{
  "type": "Feature",
  "properties": {
    "iso:country":"US",
    "sg:address":"13447 New Hampshire Ave",
    "sg:city":"Silver Spring",
    "sg:classifiers":[
        {
            "category":"Health Services",
            "subcategory":"Medical Lab",
            "type":"Services"
        }
    ],
    "sg:phone":"+1 301 989 9384",
    "sg:postcode":"20904",
    "sg:province":"MD",
    "sg:tags":[
        "laboratory"
    ],
    "wof:name":"Denture Lab",
    "wof:placetype":"venue"
},
  "geometry": {"coordinates":[-77.001623,39.07669],"type":"Point"}
}