{
  "type": "Feature",
  "properties": {
    "iso:country":"US",
    "sg:address":"800 N Woodington Rd",
    "sg:city":"Baltimore",
    "sg:classifiers":[
        {
            "category":"Organizations",
            "subcategory":"Religious Organization",
            "type":"Services"
        }
    ],
    "sg:phone":"+1 410 945 6443",
    "sg:postcode":"21229",
    "sg:province":"MD",
    "sg:tags":[
        "clergy"
    ],
    "wof:name":"Levi B Miller",
    "wof:placetype":"venue"
},
  "geometry": {"coordinates":[-76.68613999999999,39.296996],"type":"Point"}
}