{
  "type": "Feature",
  "properties": {
    "iso:country":"US",
    "sg:address":"4300 Bedford Rd",
    "sg:city":"Baltimore",
    "sg:classifiers":[
        {
            "category":"Education",
            "subcategory":"School",
            "type":"Public Place"
        }
    ],
    "sg:phone":"+1 410 887 6720",
    "sg:postcode":"21208",
    "sg:province":"MD",
    "sg:website":"www.bcps.org",
    "wof:name":"Sudbrook Magnet Middle School",
    "wof:placetype":"venue"
},
  "geometry": {"coordinates":[-76.728427,39.356573],"type":"Point"}
}