{
  "type": "Feature",
  "properties": {
    "addr:full":"6401 Arundel Cove Ave Baltimore MD 21226",
    "addr:housenumber":"6401",
    "addr:postcode":"21226",
    "addr:street":"Arundel Cove Ave",
    "iso:country":"US",
    "sg:address":"6401 Arundel Cove Ave",
    "sg:city":"Baltimore",
    "sg:classifiers":[
        {
            "category":"Freight",
            "type":"Transportation"
        }
    ],
    "sg:phone":"+1 410 354 7020",
    "sg:postcode":"21226",
    "sg:province":"MD",
    "sg:tags":[
        "transfer",
        "express"
    ],
    "wof:name":"Dennis Trucking Co",
    "wof:placetype":"venue"
},
  "geometry": {"coordinates":[-76.567381,39.201999],"type":"Point"}
}