{
  "type": "Feature",
  "properties": {
    "iso:country":"US",
    "sg:address":"2223 E Monument St",
    "sg:city":"Baltimore",
    "sg:classifiers":[
        {
            "category":"Shopping",
            "subcategory":"Discount & Variety Stores",
            "type":"Retail Goods"
        }
    ],
    "sg:phone":"+1 410 342 6616",
    "sg:postcode":"21205",
    "sg:province":"MD",
    "wof:name":"R & M Bargain Store",
    "wof:placetype":"venue"
},
  "geometry": {"coordinates":[-76.585203,39.298668],"type":"Point"}
}