{
  "type": "Feature",
  "properties": {
    "iso:country":"US",
    "sg:address":"7701 White Sands Way",
    "sg:city":"Beltsville",
    "sg:classifiers":[
        {
            "category":"Real Estate",
            "subcategory":"Architect",
            "type":"Services"
        }
    ],
    "sg:phone":"+1 301 210 6990",
    "sg:postcode":"20705",
    "sg:province":"MD",
    "sg:tags":[
        "estimate",
        "construction"
    ],
    "wof:name":"T F Falcone",
    "wof:placetype":"venue"
},
  "geometry": {"coordinates":[-76.87487900000001,39.065234],"type":"Point"}
}