{
  "type": "Feature",
  "properties": {
    "iso:country":"US",
    "sg:address":"928 Melvin Rd",
    "sg:city":"Annapolis",
    "sg:classifiers":[
        {
            "category":"Real Estate",
            "subcategory":"Real Estate Services",
            "type":"Services"
        },
        {
            "category":"Real Estate",
            "subcategory":"Real Estate Agent",
            "type":"Services"
        }
    ],
    "sg:phone":"+1 443 994 2720",
    "sg:postcode":"21403",
    "sg:province":"MD",
    "sg:tags":[
        "management"
    ],
    "wof:name":"Lease Advisory Group",
    "wof:placetype":"venue"
},
  "geometry": {"coordinates":[-76.525361,38.942403],"type":"Point"}
}