{
  "type": "Feature",
  "properties": {
    "addr:full":"13022 Well House Ct Germantown MD 20874",
    "addr:housenumber":"13022",
    "addr:postcode":"20874",
    "addr:street":"Well House Ct",
    "iso:country":"US",
    "sg:address":"13022 Well House Ct",
    "sg:city":"Germantown",
    "sg:classifiers":[
        {
            "category":"Freight",
            "type":"Transportation"
        }
    ],
    "sg:phone":"+1 301 528 2605",
    "sg:postcode":"20874",
    "sg:province":"MD",
    "sg:tags":[
        "waste",
        "hauling"
    ],
    "wof:name":"B R Powersweeping",
    "wof:placetype":"venue"
},
  "geometry": {"coordinates":[-77.26903,39.154505],"type":"Point"}
}