{
  "type": "Feature",
  "properties": {
    "iso:country":"US",
    "sg:address":"7733 Annapolis Rd",
    "sg:city":"Lanham",
    "sg:classifiers":[
        {
            "category":"Autos & Motor Vehicles",
            "subcategory":"Fuel & Gas Station",
            "type":"Retail Goods"
        }
    ],
    "sg:phone":"+1 301 459 0040",
    "sg:postcode":"20706",
    "sg:province":"MD",
    "wof:name":"Lanham Amoco Services Inc",
    "wof:placetype":"venue"
},
  "geometry": {"coordinates":[-76.87840300000001,38.9529],"type":"Point"}
}