{
  "type": "Feature",
  "properties": {
    "addr:full":"1504 S Salisbury Blvd Salisbury MD 21801",
    "addr:housenumber":"1504",
    "addr:postcode":"21801",
    "addr:street":"S Salisbury Blvd",
    "iso:country":"US",
    "sg:address":"1504 S Salisbury Blvd",
    "sg:city":"Salisbury",
    "sg:classifiers":[
        {
            "category":"Professional",
            "subcategory":"Computer Services",
            "type":"Services"
        }
    ],
    "sg:phone":"+1 410 341 6630",
    "sg:postcode":"21801",
    "sg:province":"MD",
    "sg:tags":[
        "repair"
    ],
    "wof:name":"Express Tech",
    "wof:placetype":"venue"
},
  "geometry": {"coordinates":[-75.60666399999999,38.339277],"type":"Point"}
}