{
  "type": "Feature",
  "properties": {
    "iso:country":"US",
    "sg:address":"1 Kittery Ct",
    "sg:city":"Bethesda",
    "sg:classifiers":[
        {
            "category":"Professional",
            "subcategory":"Lawyer & Legal Services",
            "type":"Services"
        }
    ],
    "sg:phone":"+1 301 469 7444",
    "sg:postcode":"20817",
    "sg:province":"MD",
    "wof:name":"Henry E Nichols PC",
    "wof:placetype":"venue"
},
  "geometry": {"coordinates":[-77.150733,39.006248],"type":"Point"}
}