{
  "type": "Feature",
  "properties": {
    "iso:country":"US",
    "sg:address":"1917 Eastern Ave",
    "sg:city":"Baltimore",
    "sg:classifiers":[
        {
            "category":"Insurance",
            "subcategory":"Insurance Agent",
            "type":"Services"
        }
    ],
    "sg:phone":"+1 410 732 2883",
    "sg:postcode":"21231",
    "sg:province":"MD",
    "wof:name":"General Agent Insurance LTD",
    "wof:placetype":"venue"
},
  "geometry": {"coordinates":[-76.589432,39.285782],"type":"Point"}
}