{
  "type": "Feature",
  "properties": {
    "addr:full":"16 W Seminary Ave Lutherville MD 21093",
    "addr:housenumber":"16",
    "addr:postcode":"21093",
    "addr:street":"W Seminary Ave",
    "iso:country":"US",
    "sg:address":"16 W Seminary Ave",
    "sg:city":"Lutherville",
    "sg:classifiers":[
        {
            "category":"Building & Trades",
            "subcategory":"Construction",
            "type":"Services"
        }
    ],
    "sg:phone":"+1 410 321 1132",
    "sg:postcode":"21093",
    "sg:province":"MD",
    "sg:tags":[
        "contractor"
    ],
    "wof:name":"Hurd Construction Co",
    "wof:placetype":"venue"
},
  "geometry": {"coordinates":[-76.61807899999999,39.420466],"type":"Point"}
}