{
  "type": "Feature",
  "properties": {
    "addr:full":"9841 Brokenland Pkwy Columbia MD 21046",
    "addr:housenumber":"9841",
    "addr:postcode":"21046",
    "addr:street":"Brokenland Pkwy",
    "iso:country":"US",
    "sg:address":"9841 Brokenland Pkwy",
    "sg:city":"Columbia",
    "sg:classifiers":[
        {
            "category":"Social Services",
            "type":"Services"
        }
    ],
    "sg:phone":"+1 410 381 2212",
    "sg:postcode":"21046",
    "sg:province":"MD",
    "sg:tags":[
        "counselor",
        "marriage",
        "family"
    ],
    "wof:name":"Lynn Lewis",
    "wof:placetype":"venue"
},
  "geometry": {"coordinates":[-76.849287,39.183194],"type":"Point"}
}