{
  "type": "Feature",
  "properties": {
    "iso:country":"US",
    "sg:address":"1940 W Baltimore St",
    "sg:city":"Baltimore",
    "sg:classifiers":[
        {
            "category":"Health Services",
            "subcategory":"Doctor",
            "type":"Services"
        }
    ],
    "sg:phone":"+1 410 362 3079",
    "sg:postcode":"21223",
    "sg:province":"MD",
    "sg:tags":[
        "hospital",
        "clinic"
    ],
    "wof:name":"Bon Secours Family Care Center",
    "wof:placetype":"venue"
},
  "geometry": {"coordinates":[-76.64859800000001,39.2882],"type":"Point"}
}