{
  "type": "Feature",
  "properties": {
    "addr:full":"233 Tippin Dr Thurmont MD 21788",
    "addr:housenumber":"233",
    "addr:postcode":"21788",
    "addr:street":"Tippin Dr",
    "iso:country":"US",
    "sg:address":"233 Tippin Dr",
    "sg:city":"Thurmont",
    "sg:classifiers":[
        {
            "category":"Food & Beverages",
            "subcategory":"Groceries & Convenience Stores",
            "type":"Retail Goods"
        }
    ],
    "sg:phone":"+1 301 271 9949",
    "sg:postcode":"21788",
    "sg:province":"MD",
    "sg:tags":[
        "grocer"
    ],
    "wof:name":"Food Lion",
    "wof:placetype":"venue"
},
  "geometry": {"coordinates":[-77.421368,39.61661],"type":"Point"}
}