{
  "type": "Feature",
  "properties": {
    "addr:full":"3011 Courtside Rd Bowie MD 20721",
    "addr:housenumber":"3011",
    "addr:postcode":"20721",
    "addr:street":"Courtside Rd",
    "iso:country":"US",
    "sg:address":"3011 Courtside Rd",
    "sg:city":"Bowie",
    "sg:classifiers":[
        {
            "category":"Professional",
            "subcategory":"Computer Services",
            "type":"Services"
        }
    ],
    "sg:phone":"+1 301 218 2821",
    "sg:postcode":"20721",
    "sg:province":"MD",
    "sg:tags":[
        "information",
        "survey"
    ],
    "wof:name":"Isit LLC",
    "wof:placetype":"venue"
},
  "geometry": {"coordinates":[-76.791161,38.930897],"type":"Point"}
}