{
  "type": "Feature",
  "properties": {
    "addr:full":"14709 Baltimore Ave Laurel MD 20707",
    "addr:housenumber":"14709",
    "addr:postcode":"20707",
    "addr:street":"Baltimore Ave",
    "iso:country":"US",
    "sg:address":"14709 Baltimore Ave",
    "sg:city":"Laurel",
    "sg:classifiers":[
        {
            "category":"Retail",
            "subcategory":"Repair Shop",
            "type":"Services"
        }
    ],
    "sg:phone":"+1 301 317 4000",
    "sg:postcode":"20707",
    "sg:province":"MD",
    "sg:tags":[
        "recycling",
        "cartridge",
        "toner"
    ],
    "wof:name":"Precision Toner Systems",
    "wof:placetype":"venue"
},
  "geometry": {"coordinates":[-76.856905,39.091745],"type":"Point"}
}