{
  "type": "Feature",
  "properties": {
    "iso:country":"US",
    "sg:address":"2108 Merritt Blvd",
    "sg:city":"Dundalk",
    "sg:classifiers":[
        {
            "category":"Manufacturing",
            "subcategory":"Metals",
            "type":"Manufacturing & Wholesale Goods"
        }
    ],
    "sg:phone":"+1 410 282 1278",
    "sg:postcode":"21222",
    "sg:province":"MD",
    "sg:tags":[
        "steel",
        "distributor",
        "mill",
        "warehouse"
    ],
    "wof:name":"Coastal Steel Co J Donhauser",
    "wof:placetype":"venue"
},
  "geometry": {"coordinates":[-76.51152500000001,39.257376],"type":"Point"}
}