{
  "type": "Feature",
  "properties": {
    "iso:country":"US",
    "sg:address":"2027 Chadwick Ter",
    "sg:city":"Temple Hills",
    "sg:classifiers":[
        {
            "category":"Professional",
            "subcategory":"Business Services",
            "type":"Services"
        }
    ],
    "sg:phone":"+1 301 630 4338",
    "sg:postcode":"20748",
    "sg:province":"MD",
    "wof:name":"K Mac Enterprises Inc",
    "wof:placetype":"venue"
},
  "geometry": {"coordinates":[-76.9665,38.838683],"type":"Point"}
}