{
  "type": "Feature",
  "properties": {
    "addr:full":"6328 Baltimore National Pike Catonsville MD 21228",
    "addr:housenumber":"6328",
    "addr:postcode":"21228",
    "addr:street":"Baltimore National Pike",
    "iso:country":"US",
    "sg:address":"6328 Baltimore National Pike",
    "sg:city":"Catonsville",
    "sg:classifiers":[
        {
            "category":"Professional",
            "subcategory":"Lawyer & Legal Services",
            "type":"Services"
        }
    ],
    "sg:phone":"+1 410 747 4529",
    "sg:postcode":"21228",
    "sg:province":"MD",
    "wof:name":"The Law Offices of Ali Kalarestaghi",
    "wof:placetype":"venue"
},
  "geometry": {"coordinates":[-76.755318,39.284178],"type":"Point"}
}