{
  "type": "Feature",
  "properties": {
    "addr:full":"3701 Koppers St Baltimore MD 21227",
    "addr:housenumber":"3701",
    "addr:postcode":"21227",
    "addr:street":"Koppers St",
    "iso:country":"US",
    "sg:address":"3701 Koppers St",
    "sg:city":"Baltimore",
    "sg:classifiers":[
        {
            "category":"Wholesale",
            "subcategory":"Computers",
            "type":"Manufacturing & Wholesale Goods"
        }
    ],
    "sg:phone":"+1 877 424 4536",
    "sg:postcode":"21227",
    "sg:province":"MD",
    "wof:name":"Agilent Technologies",
    "wof:placetype":"venue"
},
  "geometry": {"coordinates":[-76.669995,39.261831],"type":"Point"}
}