{
  "type": "Feature",
  "properties": {
    "iso:country":"US",
    "sg:address":"5400 Grosvenor Ln",
    "sg:city":"Bethesda",
    "sg:classifiers":[
        {
            "category":"Organizations",
            "subcategory":"Professional Association",
            "type":"Services"
        }
    ],
    "sg:phone":"+1 301 897 8720",
    "sg:postcode":"20814",
    "sg:province":"MD",
    "sg:tags":[
        "business",
        "trade"
    ],
    "sg:website":"http://www.istf-bethesda.org",
    "wof:name":"Society Of American Foresters",
    "wof:placetype":"venue"
},
  "geometry": {"coordinates":[-77.10498,39.022572],"type":"Point"}
}