{
  "type": "Feature",
  "properties": {
    "iso:country":"US",
    "sg:address":"2541 Bert Fowler Rd",
    "sg:city":"Hampstead",
    "sg:classifiers":[
        {
            "category":"Personal",
            "type":"Services"
        },
        {
            "category":"Recreation",
            "subcategory":"Picnic Area",
            "type":"Entertainment"
        },
        {
            "category":"Recreation",
            "type":"Entertainment"
        }
    ],
    "sg:phone":"+1 410 374 9053",
    "sg:postcode":"21074",
    "sg:province":"MD",
    "sg:tags":[
        "arcade",
        "business",
        "planning",
        "place",
        "party",
        "entertainers-family",
        "event",
        "amusement"
    ],
    "wof:name":"Snowballs By Snow Stoppers",
    "wof:placetype":"venue"
},
  "geometry": {"coordinates":[-76.900721,39.643973],"type":"Point"}
}