{
  "type": "Feature",
  "properties": {
    "addr:full":"40646 Loretta Ln Mechanicsville MD 20659",
    "addr:postcode":"40646;20659",
    "addr:street":"Loretta Ln",
    "iso:country":"US",
    "sg:address":"40646 Loretta Ln",
    "sg:city":"Mechanicsville",
    "sg:classifiers":[
        {
            "category":"Real Estate",
            "subcategory":"Real Estate Agent",
            "type":"Services"
        }
    ],
    "sg:phone":"+1 301 290 1000",
    "sg:postcode":"20659",
    "sg:province":"MD",
    "sg:tags":[
        "appraiser"
    ],
    "wof:name":"Appraisel One",
    "wof:placetype":"venue"
},
  "geometry": {"coordinates":[-76.669721,38.413408],"type":"Point"}
}