{
  "type": "Feature",
  "properties": {
    "addr:full":"12504 Valley Pines Dr Reisterstown MD 21136",
    "addr:housenumber":"12504",
    "addr:postcode":"21136",
    "addr:street":"Valley Pines Dr",
    "iso:country":"US",
    "sg:address":"12504 Valley Pines Dr",
    "sg:city":"Reisterstown",
    "sg:classifiers":[
        {
            "category":"Building & Trades",
            "subcategory":"Construction",
            "type":"Services"
        }
    ],
    "sg:phone":"+1 410 581 1192",
    "sg:postcode":"21136",
    "sg:province":"MD",
    "sg:tags":[
        "home",
        "builder"
    ],
    "wof:name":"Chirgott Homes",
    "wof:placetype":"venue"
},
  "geometry": {"coordinates":[-76.74358599999999,39.465911],"type":"Point"}
}