{
  "type": "Feature",
  "properties": {
    "iso:country":"US",
    "sg:address":"7234 Windsor Mill Rd",
    "sg:city":"Windsor Mill",
    "sg:classifiers":[
        {
            "category":"Retail",
            "subcategory":"Auto Repair",
            "type":"Services"
        }
    ],
    "sg:phone":"+1 410 265 7153",
    "sg:postcode":"21244",
    "sg:province":"MD",
    "wof:name":"Windsor Mill Getty",
    "wof:placetype":"venue"
},
  "geometry": {"coordinates":[-76.753197,39.337399],"type":"Point"}
}