{
  "type": "Feature",
  "properties": {
    "addr:full":"301 N Charles St Baltimore MD 21201",
    "addr:housenumber":"301",
    "addr:postcode":"21201",
    "addr:street":"N Charles St",
    "iso:country":"US",
    "sg:address":"301 N Charles St",
    "sg:city":"Baltimore",
    "sg:classifiers":[
        {
            "category":"Professional",
            "subcategory":"Lawyer & Legal Services",
            "type":"Services"
        }
    ],
    "sg:phone":"+1 410 377 7466",
    "sg:postcode":"21201",
    "sg:province":"MD",
    "sg:tags":[
        "attorney",
        "practice"
    ],
    "wof:name":"Skeen Robert G Lwyr If No Answ",
    "wof:placetype":"venue"
},
  "geometry": {"coordinates":[-76.615334,39.292309],"type":"Point"}
}