{
  "type": "Feature",
  "properties": {
    "iso:country":"US",
    "sg:address":"15772 Livingston Rd",
    "sg:city":"Accokeek",
    "sg:classifiers":[
        {
            "category":"Autos & Motor Vehicles",
            "subcategory":"Automobile Sales",
            "type":"Retail Goods"
        }
    ],
    "sg:phone":"+1 301 292 7884",
    "sg:postcode":"20607",
    "sg:province":"MD",
    "sg:tags":[
        "car",
        "dealer"
    ],
    "wof:name":"Khalsa Car Sales",
    "wof:placetype":"venue"
},
  "geometry": {"coordinates":[-77.007194,38.669563],"type":"Point"}
}