{
  "type": "Feature",
  "properties": {
    "addr:full":"9729 Country Meadows Ln Laurel MD 20723",
    "addr:housenumber":"9729",
    "addr:postcode":"20723",
    "addr:street":"Country Meadows Ln",
    "iso:country":"US",
    "sg:address":"9729 Country Meadows Ln",
    "sg:city":"Laurel",
    "sg:classifiers":[
        {
            "category":"Building & Trades",
            "subcategory":"Construction",
            "type":"Services"
        }
    ],
    "sg:phone":"+1 301 498 5544",
    "sg:postcode":"20723",
    "sg:province":"MD",
    "sg:tags":[
        "wallcoverings-installation",
        "wallpaper",
        "painting",
        "contractor"
    ],
    "wof:name":"G&J Professional Painting",
    "wof:placetype":"venue"
},
  "geometry": {"coordinates":[-76.830431,39.120279],"type":"Point"}
}