{
  "type": "Feature",
  "properties": {
    "addr:full":"1640 Dual Hwy Hagerstown MD 21740",
    "addr:housenumber":"1640",
    "addr:postcode":"21740",
    "addr:street":"Dual Hwy",
    "iso:country":"US",
    "sg:address":"1640 Dual Hwy",
    "sg:city":"Hagerstown",
    "sg:classifiers":[
        {
            "category":"Utilities",
            "subcategory":"Mobile Phone",
            "type":"Services"
        }
    ],
    "sg:phone":"+1 301 745 4980",
    "sg:postcode":"21740",
    "sg:province":"MD",
    "sg:tags":[
        "telephone",
        "cellular"
    ],
    "wof:name":"Cellular One",
    "wof:placetype":"venue"
},
  "geometry": {"coordinates":[-77.69295,39.617638],"type":"Point"}
}