{
  "type": "Feature",
  "properties": {
    "iso:country":"US",
    "sg:address":"7642 Hennesey Ct",
    "sg:city":"Glen Burnie",
    "sg:classifiers":[
        {
            "category":"Building & Trades",
            "subcategory":"Construction",
            "type":"Services"
        }
    ],
    "sg:phone":"+1 410 787 1391",
    "sg:postcode":"21061",
    "sg:province":"MD",
    "sg:tags":[
        "residential"
    ],
    "wof:name":"Quinn Construction",
    "wof:placetype":"venue"
},
  "geometry": {"coordinates":[-76.640365,39.149235],"type":"Point"}
}