{
  "type": "Feature",
  "properties": {
    "addr:full":"15901 New Hampshire Ave Silver Spring MD 20905",
    "addr:housenumber":"15901",
    "addr:postcode":"20905",
    "addr:street":"New Hampshire Ave",
    "iso:country":"US",
    "sg:address":"15901 New Hampshire Ave",
    "sg:city":"Silver Spring",
    "sg:classifiers":[
        {
            "category":"Education",
            "subcategory":"Special Training",
            "type":"Public Place"
        },
        {
            "category":"Education",
            "subcategory":"Preschool",
            "type":"Public Place"
        }
    ],
    "sg:phone":"+1 301 421 0101",
    "sg:postcode":"20905",
    "sg:province":"MD",
    "sg:tags":[
        "educational"
    ],
    "wof:name":"International Children's Center",
    "wof:placetype":"venue"
},
  "geometry": {"coordinates":[-76.98889200000001,39.1173],"type":"Point"}
}