{
  "type": "Feature",
  "properties": {
    "iso:country":"US",
    "sg:address":"421 Marshall Minor Dr",
    "sg:city":"Silver Spring",
    "sg:classifiers":[
        {
            "category":"Professional",
            "subcategory":"Accounting & Tax Preparation",
            "type":"Services"
        }
    ],
    "sg:phone":"+1 301 989 8330",
    "sg:postcode":"20905",
    "sg:province":"MD",
    "sg:tags":[
        "accountant"
    ],
    "wof:name":"James A Bryant CPA",
    "wof:placetype":"venue"
},
  "geometry": {"coordinates":[-77.00069000000001,39.100554],"type":"Point"}
}