{
  "type": "Feature",
  "properties": {
    "addr:full":"19139 Garrett Hwy Oakland MD 21550",
    "addr:housenumber":"19139",
    "addr:postcode":"21550",
    "addr:street":"Garrett Hwy",
    "iso:country":"US",
    "sg:address":"19139 Garrett Hwy",
    "sg:city":"Oakland",
    "sg:classifiers":[
        {
            "category":"Shopping",
            "type":"Retail Goods"
        }
    ],
    "sg:phone":"+1 301 387 5614",
    "sg:postcode":"21550",
    "sg:province":"MD",
    "sg:tags":[
        "spa",
        "tub",
        "hot",
        "merchandise",
        "miscellaneous"
    ],
    "wof:name":"Hot Spring Spas of Alleghenies",
    "wof:placetype":"venue"
},
  "geometry": {"coordinates":[-79.331137,39.499688],"type":"Point"}
}