{
  "type": "Feature",
  "properties": {
    "addr:full":"5950 Hubbard Dr Rockville MD 20852",
    "addr:housenumber":"5950",
    "addr:postcode":"20852",
    "addr:street":"Hubbard Dr",
    "iso:country":"US",
    "sg:address":"5950 Hubbard Dr",
    "sg:city":"Rockville",
    "sg:classifiers":[
        {
            "category":"Health Services",
            "subcategory":"Dentist",
            "type":"Services"
        }
    ],
    "sg:phone":"+1 301 881 8351",
    "sg:postcode":"20852",
    "sg:province":"MD",
    "sg:tags":[
        "pediatric"
    ],
    "wof:name":"Douglas Pincock DMD",
    "wof:placetype":"venue"
},
  "geometry": {"coordinates":[-77.11983600000001,39.053978],"type":"Point"}
}