{
  "type": "Feature",
  "properties": {
    "iso:country":"US",
    "sg:address":"11073 Cathell Rd",
    "sg:city":"Berlin",
    "sg:classifiers":[
        {
            "category":"Banks & Credit Unions",
            "subcategory":"Investment Brokerage",
            "type":"Services"
        }
    ],
    "sg:phone":"+1 410 641 5665",
    "sg:postcode":"21811",
    "sg:province":"MD",
    "sg:tags":[
        "advisory",
        "financial"
    ],
    "wof:name":"Allstate Financial Svc",
    "wof:placetype":"venue"
},
  "geometry": {"coordinates":[-75.166928,38.377966],"type":"Point"}
}