{
  "type": "Feature",
  "properties": {
    "addr:full":"4938 Hampden Ln Bethesda MD 20814",
    "addr:housenumber":"4938",
    "addr:postcode":"20814",
    "addr:street":"Hampden Ln",
    "iso:country":"US",
    "sg:address":"4938 Hampden Ln",
    "sg:city":"Bethesda",
    "sg:classifiers":[
        {
            "category":"Professional",
            "subcategory":"Engineering",
            "type":"Services"
        }
    ],
    "sg:phone":"+1 301 320 4900",
    "sg:postcode":"20814",
    "sg:province":"MD",
    "sg:tags":[
        "consulting",
        "engineer"
    ],
    "wof:name":"Morris & Ward",
    "wof:placetype":"venue"
},
  "geometry": {"coordinates":[-77.09759099999999,38.982592],"type":"Point"}
}