{
  "type": "Feature",
  "properties": {
    "addr:full":"1654 Nalin Farm Pond Rd Frederick MD 21702",
    "addr:housenumber":"1654",
    "addr:postcode":"21702",
    "addr:street":"Nalin Farm Pond Rd",
    "iso:country":"US",
    "sg:address":"1654 Nalin Farm Pond Rd",
    "sg:city":"Frederick",
    "sg:classifiers":[
        {
            "category":"Professional",
            "subcategory":"Management & Consulting",
            "type":"Services"
        }
    ],
    "sg:phone":"+1 301 620 2229",
    "sg:postcode":"21702",
    "sg:province":"MD",
    "sg:tags":[
        "construction"
    ],
    "wof:name":"Centex Construction Co",
    "wof:placetype":"venue"
},
  "geometry": {"coordinates":[-77.411732,39.445183],"type":"Point"}
}