{
  "type": "Feature",
  "properties": {
    "addr:full":"220 Stonegate Dr Silver Spring MD 20905",
    "addr:housenumber":"220",
    "addr:postcode":"20905",
    "addr:street":"Stonegate Dr",
    "iso:country":"US",
    "sg:address":"220 Stonegate Dr",
    "sg:city":"Silver Spring",
    "sg:classifiers":[
        {
            "category":"Organizations",
            "subcategory":"Community Association",
            "type":"Services"
        }
    ],
    "sg:phone":"+1 301 384 4401",
    "sg:postcode":"20905",
    "sg:province":"MD",
    "sg:tags":[
        "club"
    ],
    "wof:name":"Stonegate Swim Club",
    "wof:placetype":"venue"
},
  "geometry": {"coordinates":[-77.01186,39.100656],"type":"Point"}
}