{
  "type": "Feature",
  "properties": {
    "iso:country":"US",
    "sg:address":"13507 Sherwood Forest Dr",
    "sg:city":"Silver Spring",
    "sg:classifiers":[
        {
            "category":"Shopping",
            "subcategory":"Computers & Home Electronics",
            "type":"Retail Goods"
        }
    ],
    "sg:phone":"+1 301 236 9666",
    "sg:postcode":"20904",
    "sg:province":"MD",
    "sg:tags":[
        "equipment",
        "dealer"
    ],
    "wof:name":"Maryland Computer Systems",
    "wof:placetype":"venue"
},
  "geometry": {"coordinates":[-77.010299,39.078197],"type":"Point"}
}