{
  "type": "Feature",
  "properties": {
    "addr:full":"1010 Hull St Ste 210 Baltimore MD 21230",
    "addr:housenumber":"1010",
    "addr:postcode":"21230",
    "addr:street":"Hull St Ste 210",
    "iso:country":"US",
    "sg:address":"1010 Hull St Ste 210",
    "sg:city":"Baltimore",
    "sg:classifiers":[
        {
            "category":"Professional",
            "subcategory":"Engineering",
            "type":"Services"
        }
    ],
    "sg:phone":"+1 410 528 5705",
    "sg:postcode":"21230",
    "sg:province":"MD",
    "sg:tags":[
        "energy",
        "management",
        "engineer"
    ],
    "sg:website":"http://www.energysg.com",
    "wof:name":"Energy Systems Group",
    "wof:placetype":"venue"
},
  "geometry": {"coordinates":[-76.590132,39.275228],"type":"Point"}
}