{
  "type": "Feature",
  "properties": {
    "iso:country":"US",
    "sg:address":"1013 Kingsbury Rd",
    "sg:city":"Reisterstown",
    "sg:classifiers":[
        {
            "category":"Farming",
            "subcategory":"Farm & Veterinary Services",
            "type":"Manufacturing & Wholesale Goods"
        }
    ],
    "sg:phone":"+1 410 526 5106",
    "sg:postcode":"21136",
    "sg:province":"MD",
    "sg:tags":[
        "preparation",
        "crop",
        "for",
        "market"
    ],
    "wof:name":"Chesapeake Delights Inc",
    "wof:placetype":"venue"
},
  "geometry": {"coordinates":[-76.799787,39.452068],"type":"Point"}
}