{
  "type": "Feature",
  "properties": {
    "addr:full":"3413 Terrapin Rd Pikesville MD 21208",
    "addr:housenumber":"3413",
    "addr:postcode":"21208",
    "addr:street":"Terrapin Rd",
    "iso:country":"US",
    "sg:address":"3413 Terrapin Rd",
    "sg:city":"Pikesville",
    "sg:classifiers":[
        {
            "category":"Health Services",
            "subcategory":"Health Practitioner",
            "type":"Services"
        }
    ],
    "sg:phone":"+1 410 486 4162",
    "sg:postcode":"21208",
    "sg:province":"MD",
    "sg:tags":[
        "hypnotherapy",
        "hypnotist"
    ],
    "wof:name":"Gumnit Stanley S",
    "wof:placetype":"venue"
},
  "geometry": {"coordinates":[-76.711679,39.382246],"type":"Point"}
}