{
  "type": "Feature",
  "properties": {
    "iso:country":"US",
    "sg:address":"12005 Quartette Ln",
    "sg:city":"Bowie",
    "sg:classifiers":[
        {
            "category":"Professional",
            "subcategory":"Business Services",
            "type":"Services"
        }
    ],
    "sg:phone":"+1 301 809 1360",
    "sg:postcode":"20720",
    "sg:province":"MD",
    "sg:tags":[
        "interior",
        "consultant",
        "design",
        "decorator"
    ],
    "wof:name":"Metro Interior Concepts",
    "wof:placetype":"venue"
},
  "geometry": {"coordinates":[-76.796133,38.993025],"type":"Point"}
}