{
  "type": "Feature",
  "properties": {
    "iso:country":"US",
    "sg:address":"5001 Walther Ave",
    "sg:city":"Baltimore",
    "sg:classifiers":[
        {
            "category":"Retail",
            "subcategory":"Repair Shop",
            "type":"Services"
        }
    ],
    "sg:phone":"+1 410 426 6981",
    "sg:postcode":"21214",
    "sg:province":"MD",
    "wof:name":"Cowie Cleaning",
    "wof:placetype":"venue"
},
  "geometry": {"coordinates":[-76.55996500000001,39.343891],"type":"Point"}
}