{
  "type": "Feature",
  "properties": {
    "iso:country":"US",
    "sg:address":"7880 Twin Ridge Dr",
    "sg:city":"Glen Burnie",
    "sg:classifiers":[
        {
            "category":"Social Services",
            "subcategory":"Child Care",
            "type":"Services"
        }
    ],
    "sg:phone":"+1 410 768 1756",
    "sg:postcode":"21061",
    "sg:province":"MD",
    "sg:tags":[
        "day"
    ],
    "wof:name":"Family Daycare",
    "wof:placetype":"venue"
},
  "geometry": {"coordinates":[-76.612784,39.142592],"type":"Point"}
}