{
  "type": "Feature",
  "properties": {
    "addr:full":"3664 Emory Church Rd Street MD 21154",
    "addr:housenumber":"3664",
    "addr:postcode":"21154",
    "addr:street":"Emory Church Rd Street",
    "iso:country":"US",
    "sg:address":"3664 Emory Church Rd",
    "sg:city":"Street",
    "sg:classifiers":[
        {
            "category":"Building & Trades",
            "subcategory":"Electrical",
            "type":"Services"
        }
    ],
    "sg:phone":"+1 410 893 7218",
    "sg:postcode":"21154",
    "sg:province":"MD",
    "sg:tags":[
        "electrician"
    ],
    "wof:name":"Dsr Electric",
    "wof:placetype":"venue"
},
  "geometry": {"coordinates":[-76.356837,39.657728],"type":"Point"}
}