{
  "type": "Feature",
  "properties": {
    "addr:full":"102 Hawthorne Rd Baltimore MD 21210",
    "addr:housenumber":"102",
    "addr:postcode":"21210",
    "addr:street":"Hawthorne Rd",
    "iso:country":"US",
    "sg:address":"102 Hawthorne Rd",
    "sg:city":"Baltimore",
    "sg:classifiers":[
        {
            "category":"Arts & Performance",
            "subcategory":"Theater",
            "type":"Entertainment"
        }
    ],
    "sg:phone":"+1 410 235 5546",
    "sg:postcode":"21210",
    "sg:province":"MD",
    "sg:tags":[
        "television",
        "program",
        "producer"
    ],
    "sg:website":"www.gardnerfilms.com",
    "wof:name":"Gardner Films Inc",
    "wof:placetype":"venue"
},
  "geometry": {"coordinates":[-76.63270900000001,39.346122],"type":"Point"}
}