{
  "type": "Feature",
  "properties": {
    "iso:country":"US",
    "sg:address":"6 Snyder Ave",
    "sg:city":"Hagerstown",
    "sg:classifiers":[
        {
            "category":"Building & Trades",
            "subcategory":"Construction",
            "type":"Services"
        }
    ],
    "sg:phone":"+1 301 797 9791",
    "sg:postcode":"21740",
    "sg:province":"MD",
    "sg:tags":[
        "contractor",
        "fence-sales"
    ],
    "wof:name":"Green Perimeters",
    "wof:placetype":"venue"
},
  "geometry": {"coordinates":[-77.738437,39.627191],"type":"Point"}
}