{
  "type": "Feature",
  "properties": {
    "addr:full":"309 W College Ave Salisbury MD 21801",
    "addr:housenumber":"309",
    "addr:postcode":"21801",
    "addr:street":"W College Ave",
    "iso:country":"US",
    "sg:address":"309 W College Ave",
    "sg:city":"Salisbury",
    "sg:classifiers":[
        {
            "category":"Organizations",
            "subcategory":"Religious Organization",
            "type":"Services"
        }
    ],
    "sg:phone":"+1 410 749 1820",
    "sg:postcode":"21801",
    "sg:province":"MD",
    "sg:tags":[
        "church"
    ],
    "sg:website":"www.easternbaptist.org",
    "wof:name":"Eastern Baptist Assn",
    "wof:placetype":"venue"
},
  "geometry": {"coordinates":[-75.60749800000001,38.349318],"type":"Point"}
}