{
  "type": "Feature",
  "properties": {
    "iso:country":"US",
    "sg:address":"309 W College Ave",
    "sg:city":"Salisbury",
    "sg:classifiers":[
        {
            "category":"Organizations",
            "subcategory":"Religious Organization",
            "type":"Services"
        }
    ],
    "sg:phone":"+1 410 749 1820",
    "sg:postcode":"21801",
    "sg:province":"MD",
    "sg:tags":[
        "church"
    ],
    "sg:website":"www.easternbaptist.org",
    "wof:name":"Eastern Baptist Assn",
    "wof:placetype":"venue"
},
  "geometry": {"coordinates":[-75.607498,38.349318],"type":"Point"}
}