{
  "type": "Feature",
  "properties": {
    "addr:full":"12423 Middlebrook Rd Germantown MD 20874",
    "addr:housenumber":"12423",
    "addr:postcode":"20874",
    "addr:street":"Middlebrook Rd",
    "iso:country":"US",
    "sg:address":"12423 Middlebrook Rd",
    "sg:city":"Germantown",
    "sg:classifiers":[
        {
            "category":"Retail",
            "subcategory":"Auto Rental",
            "type":"Services"
        },
        {
            "category":"Building & Trades",
            "subcategory":"Equipment Rental",
            "type":"Services"
        },
        {
            "category":"Retail",
            "subcategory":"Storage",
            "type":"Services"
        }
    ],
    "sg:phone":"+1 301 916 9016",
    "sg:postcode":"20874",
    "sg:province":"MD",
    "sg:tags":[
        "renting",
        "moving-self",
        "leasing",
        "truck",
        "van",
        "moving",
        "trailer"
    ],
    "sg:website":"http://www.budgettruck.com",
    "wof:name":"Budget Truck Rental",
    "wof:placetype":"venue"
},
  "geometry": {"coordinates":[-77.255403,39.17557],"type":"Point"}
}