{
  "type": "Feature",
  "properties": {
    "iso:country":"US",
    "sg:address":"17740 Garland Groh Blvd",
    "sg:city":"Hagerstown",
    "sg:classifiers":[
        {
            "category":"Shopping",
            "type":"Retail Goods"
        }
    ],
    "sg:phone":"+1 301 665 2820",
    "sg:postcode":"21740",
    "sg:province":"MD",
    "sg:tags":[
        "pet",
        "shop"
    ],
    "sg:website":"www.petsmart.com",
    "wof:name":"Petsmart",
    "wof:placetype":"venue"
},
  "geometry": {"coordinates":[-77.751057,39.654868],"type":"Point"}
}