{
  "type": "Feature",
  "properties": {
    "addr:full":"5208 Gwynn Oak Ave Baltimore MD 21207",
    "addr:housenumber":"5208",
    "addr:postcode":"21207",
    "addr:street":"Gwynn Oak Ave",
    "iso:country":"US",
    "sg:address":"5208 Gwynn Oak Ave",
    "sg:city":"Baltimore",
    "sg:classifiers":[
        {
            "category":"Professional",
            "type":"Services"
        }
    ],
    "sg:phone":"+1 410 448 0767",
    "sg:postcode":"21207",
    "sg:province":"MD",
    "sg:tags":[
        "a",
        "be",
        "applying",
        "for",
        "federal",
        "to",
        "individual",
        "reader"
    ],
    "wof:name":"Carol J McKinnon",
    "wof:placetype":"venue"
},
  "geometry": {"coordinates":[-76.70256000000001,39.330322],"type":"Point"}
}