{
  "type": "Feature",
  "properties": {
    "addr:full":"124 Cedar St Cambridge MD 21613",
    "addr:housenumber":"124",
    "addr:postcode":"21613",
    "addr:street":"Cedar St",
    "iso:country":"US",
    "sg:address":"124 Cedar St",
    "sg:city":"Cambridge",
    "sg:classifiers":[
        {
            "category":"Restaurant",
            "type":"Food & Drink"
        }
    ],
    "sg:menulink":"http://www.allmenus.com/md/cambridge/67356-dominos-pizza/menu/",
    "sg:phone":"+1 410 228 0100",
    "sg:postcode":"21613",
    "sg:province":"MD",
    "sg:tags":[
        "american",
        "wing",
        "pizza"
    ],
    "wof:name":"Domino's Pizza",
    "wof:placetype":"venue"
},
  "geometry": {"coordinates":[-76.068561,38.564463],"type":"Point"}
}