{
  "type": "Feature",
  "properties": {
    "addr:full":"11667 Browningsville Rd Ijamsville MD 21754",
    "addr:housenumber":"11667",
    "addr:postcode":"21754",
    "addr:street":"Browningsville Rd",
    "iso:country":"US",
    "sg:address":"11667 Browningsville Rd",
    "sg:city":"Ijamsville",
    "sg:classifiers":[
        {
            "category":"Organizations",
            "subcategory":"Religious Organization",
            "type":"Services"
        }
    ],
    "sg:phone":"+1 301 607 6466",
    "sg:postcode":"21754",
    "sg:province":"MD",
    "sg:tags":[
        "church"
    ],
    "wof:name":"Shining Light Baptist Church",
    "wof:placetype":"venue"
},
  "geometry": {"coordinates":[-77.26110300000001,39.322556],"type":"Point"}
}