{
  "type": "Feature",
  "properties": {
    "addr:full":"7272 Park Circle Dr Hanover MD 21076",
    "addr:housenumber":"7272",
    "addr:postcode":"21076",
    "addr:street":"Park Circle Dr",
    "iso:country":"US",
    "sg:address":"7272 Park Circle Dr",
    "sg:city":"Hanover",
    "sg:classifiers":[
        {
            "category":"Wholesale",
            "subcategory":"Electrical",
            "type":"Manufacturing & Wholesale Goods"
        }
    ],
    "sg:phone":"+1 410 712 0031",
    "sg:postcode":"21076",
    "sg:province":"MD",
    "sg:tags":[
        "equipment",
        "electronic",
        "supply"
    ],
    "wof:name":"Newark Electronics",
    "wof:placetype":"venue"
},
  "geometry": {"coordinates":[-76.733929,39.180887],"type":"Point"}
}