{
  "type": "Feature",
  "properties": {
    "addr:full":"1731 Ballenger Creek Pike Point Of Rocks MD 21777",
    "addr:housenumber":"1731",
    "addr:postcode":"21777",
    "addr:street":"Ballenger Creek Pike",
    "iso:country":"US",
    "sg:address":"1731 Ballenger Creek Pike",
    "sg:city":"Point Of Rocks",
    "sg:classifiers":[
        {
            "category":"Recreation",
            "type":"Entertainment"
        }
    ],
    "sg:phone":"+1 301 788 0354",
    "sg:postcode":"21777",
    "sg:province":"MD",
    "wof:name":"Nirvana Climbing Guides",
    "wof:placetype":"venue"
},
  "geometry": {"coordinates":[-77.53595,39.280595],"type":"Point"}
}