{
  "type": "Feature",
  "properties": {
    "addr:full":"7012 Heathcoate Dr Kingsville MD 21087",
    "addr:housenumber":"7012",
    "addr:postcode":"21087",
    "addr:street":"Heathcoate Dr",
    "iso:country":"US",
    "sg:address":"7012 Heathcoate Dr",
    "sg:city":"Kingsville",
    "sg:classifiers":[
        {
            "category":"Shopping",
            "subcategory":"Jewelry",
            "type":"Retail Goods"
        },
        {
            "category":"Manufacturing",
            "subcategory":"Jewelry",
            "type":"Manufacturing & Wholesale Goods"
        }
    ],
    "sg:phone":"+1 410 592 9048",
    "sg:postcode":"21087",
    "sg:province":"MD",
    "sg:tags":[
        "stone",
        "jewelers-wholesale",
        "jeweler",
        "precious",
        "semi-precious",
        "manufacturer"
    ],
    "wof:name":"Intercoastal Enterprises",
    "wof:placetype":"venue"
},
  "geometry": {"coordinates":[-76.43306699999999,39.429932],"type":"Point"}
}