{
  "type": "Feature",
  "properties": {
    "addr:full":"505 Fox Den Ln Millersville MD 21108",
    "addr:housenumber":"505",
    "addr:postcode":"21108",
    "addr:street":"Fox Den Ln",
    "iso:country":"US",
    "sg:address":"505 Fox Den Ln",
    "sg:city":"Millersville",
    "sg:classifiers":[
        {
            "category":"Communications",
            "type":"Services"
        }
    ],
    "sg:phone":"+1 410 987 0169",
    "sg:postcode":"21108",
    "sg:province":"MD",
    "wof:name":"Rnd Communications",
    "wof:placetype":"venue"
},
  "geometry": {"coordinates":[-76.61448300000001,39.104668],"type":"Point"}
}