{
  "type": "Feature",
  "properties": {
    "iso:country":"US",
    "sg:address":"120 Roesler Rd",
    "sg:city":"Glen Burnie",
    "sg:classifiers":[
        {
            "category":"Manufacturing",
            "subcategory":"Electronics",
            "type":"Manufacturing & Wholesale Goods"
        }
    ],
    "sg:phone":"+1 410 768 3333",
    "sg:postcode":"21060",
    "sg:province":"MD",
    "sg:tags":[
        "communication",
        "equipment"
    ],
    "wof:name":"Comm-Tronics Inc",
    "wof:placetype":"venue"
},
  "geometry": {"coordinates":[-76.615974,39.177541],"type":"Point"}
}