{
  "type": "Feature",
  "properties": {
    "iso:country":"US",
    "sg:address":"5813 Falls Rd",
    "sg:city":"Baltimore",
    "sg:classifiers":[
        {
            "category":"Shopping",
            "subcategory":"Bicycles & Sporting Goods",
            "type":"Retail Goods"
        }
    ],
    "sg:phone":"+1 410 323 2788",
    "sg:postcode":"21209",
    "sg:province":"MD",
    "sg:tags":[
        "bike"
    ],
    "sg:website":"www.mtwashingtonbikes.com",
    "wof:name":"Mount Washington Bike Shop",
    "wof:placetype":"venue"
},
  "geometry": {"coordinates":[-76.648163,39.367322],"type":"Point"}
}