{
  "type": "Feature",
  "properties": {
    "iso:country":"US",
    "sg:address":"7821 Mineral Springs Dr",
    "sg:city":"Gaithersburg",
    "sg:classifiers":[
        {
            "category":"Education",
            "subcategory":"Dance Studio",
            "type":"Public Place"
        }
    ],
    "sg:phone":"+1 301 963 4517",
    "sg:postcode":"20877",
    "sg:province":"MD",
    "wof:name":"Steps of Grace",
    "wof:placetype":"venue"
},
  "geometry": {"coordinates":[-77.161942,39.154002],"type":"Point"}
}