{
  "type": "Feature",
  "properties": {
    "iso:country":"US",
    "sg:address":"4407 Chalfont Pl",
    "sg:city":"Bethesda",
    "sg:classifiers":[
        {
            "category":"Professional",
            "subcategory":"Lawyer & Legal Services",
            "type":"Services"
        }
    ],
    "sg:phone":"+1 301 320 9757",
    "sg:postcode":"20816",
    "sg:province":"MD",
    "wof:name":"Vieth G Duane Atty",
    "wof:placetype":"venue"
},
  "geometry": {"coordinates":[-77.111198,38.945702],"type":"Point"}
}