{
  "type": "Feature",
  "properties": {
    "iso:country":"US",
    "sg:address":"929 Lewis Ave",
    "sg:city":"Rockville",
    "sg:classifiers":[
        {
            "category":"Manufacturing",
            "subcategory":"Signs",
            "type":"Manufacturing & Wholesale Goods"
        }
    ],
    "sg:phone":"+1 301 279 0415",
    "sg:postcode":"20851",
    "sg:province":"MD",
    "wof:name":"Capitol Signatures",
    "wof:placetype":"venue"
},
  "geometry": {"coordinates":[-77.135502,39.075996],"type":"Point"}
}