{
  "type": "Feature",
  "properties": {
    "addr:full":"2922 E Fayette St Baltimore MD 21224",
    "addr:housenumber":"2922",
    "addr:postcode":"21224",
    "addr:street":"E Fayette St",
    "iso:country":"US",
    "sg:address":"2922 E Fayette St",
    "sg:city":"Baltimore",
    "sg:classifiers":[
        {
            "category":"Social Services",
            "type":"Services"
        }
    ],
    "sg:phone":"+1 410 327 5463",
    "sg:postcode":"21224",
    "sg:province":"MD",
    "sg:tags":[
        "info",
        "program",
        "referral"
    ],
    "wof:name":"Choice Program",
    "wof:placetype":"venue"
},
  "geometry": {"coordinates":[-76.574967,39.294689],"type":"Point"}
}