{
  "type": "Feature",
  "properties": {
    "iso:country":"US",
    "sg:address":"6916 Westmoreland Ave",
    "sg:city":"Takoma Park",
    "sg:classifiers":[
        {
            "category":"Organizations",
            "subcategory":"Non-profit Organization",
            "type":"Services"
        }
    ],
    "sg:phone":"+1 301 270 4239",
    "sg:postcode":"20912",
    "sg:province":"MD",
    "sg:tags":[
        "social"
    ],
    "wof:name":"Westmoreland Area Cmmnty Orgnz",
    "wof:placetype":"venue"
},
  "geometry": {"coordinates":[-77.011518,38.974703],"type":"Point"}
}