{
  "type": "Feature",
  "properties": {
    "iso:country":"US",
    "sg:address":"2 N Main St",
    "sg:city":"Berlin",
    "sg:classifiers":[
        {
            "category":"Travel",
            "subcategory":"Hotels & Motels",
            "type":"Entertainment"
        }
    ],
    "sg:phone":"+1 410 641 3589",
    "sg:postcode":"21811",
    "sg:province":"MD",
    "sg:tags":[
        "lodging"
    ],
    "sg:website":"http://www.atlantichotel.com",
    "wof:name":"Atlantic Hotel",
    "wof:placetype":"venue"
},
  "geometry": {"coordinates":[-75.219009,38.324692],"type":"Point"}
}