{
  "type": "Feature",
  "properties": {
    "iso:country":"US",
    "sg:address":"5600 Wisconsin Ave",
    "sg:city":"Chevy Chase",
    "sg:classifiers":[
        {
            "category":"Real Estate",
            "subcategory":"Real Estate Agent",
            "type":"Services"
        }
    ],
    "sg:phone":"+1 301 215 4141",
    "sg:postcode":"20815",
    "sg:province":"MD",
    "wof:name":"Somerset House Realty Inc",
    "wof:placetype":"venue"
},
  "geometry": {"coordinates":[-77.088491,38.966366],"type":"Point"}
}