{
  "type": "Feature",
  "properties": {
    "addr:full":"10111 Martin Luther King Jr Hwy Ste 110 Lanham MD 20720",
    "addr:housenumber":"10111",
    "addr:postcode":"20720",
    "addr:street":"Martin Luther King Jr Hwy Ste 110",
    "iso:country":"US",
    "sg:address":"10111 Martin Luther King Jr Hwy Ste 110",
    "sg:city":"Lanham",
    "sg:classifiers":[
        {
            "category":"Professional",
            "subcategory":"Accounting & Tax Preparation",
            "type":"Services"
        }
    ],
    "sg:phone":"+1 301 459 3644",
    "sg:postcode":"20720",
    "sg:province":"MD",
    "sg:tags":[
        "accountant"
    ],
    "wof:name":"On Time Accounting",
    "wof:placetype":"venue"
},
  "geometry": {"coordinates":[-76.831621,38.953888],"type":"Point"}
}