{
  "type": "Feature",
  "properties": {
    "addr:full":"10820 Rhode Island Ave Beltsville MD 20705",
    "addr:housenumber":"10820",
    "addr:postcode":"20705",
    "addr:street":"Rhode Island Ave",
    "iso:country":"US",
    "sg:address":"10820 Rhode Island Ave",
    "sg:city":"Beltsville",
    "sg:classifiers":[
        {
            "category":"Restaurant",
            "type":"Food & Drink"
        }
    ],
    "sg:phone":"+1 301 595 5955",
    "sg:postcode":"20705",
    "sg:province":"MD",
    "sg:tags":[
        "american",
        "latin"
    ],
    "wof:name":"Pueblo Viejo",
    "wof:placetype":"venue"
},
  "geometry": {"coordinates":[-76.913704,39.034173],"type":"Point"}
}