{
  "type": "Feature",
  "properties": {
    "addr:full":"5514 Hoover St Bethesda MD 20817",
    "addr:housenumber":"5514",
    "addr:postcode":"20817",
    "addr:street":"Hoover St",
    "iso:country":"US",
    "sg:address":"5514 Hoover St",
    "sg:city":"Bethesda",
    "sg:classifiers":[
        {
            "category":"Professional",
            "subcategory":"Business Services",
            "type":"Services"
        }
    ],
    "sg:phone":"+1 301 530 0699",
    "sg:postcode":"20817",
    "sg:province":"MD",
    "wof:name":"Speight Decorating",
    "wof:placetype":"venue"
},
  "geometry": {"coordinates":[-77.114116,38.996766],"type":"Point"}
}