{
  "type": "Feature",
  "properties": {
    "iso:country":"US",
    "sg:address":"11411 Gas House Pike",
    "sg:city":"New Market",
    "sg:classifiers":[
        {
            "category":"Professional",
            "type":"Services"
        }
    ],
    "sg:phone":"+1 301 865 9829",
    "sg:postcode":"21774",
    "sg:province":"MD",
    "sg:tags":[
        "establishment"
    ],
    "wof:name":"Westwinds Pool",
    "wof:placetype":"venue"
},
  "geometry": {"coordinates":[-77.268146,39.425345],"type":"Point"}
}