{
  "type": "Feature",
  "properties": {
    "addr:full":"436 Race St Cambridge MD 21613",
    "addr:housenumber":"436",
    "addr:postcode":"21613",
    "addr:street":"Race St",
    "iso:country":"US",
    "sg:address":"436 Race St",
    "sg:city":"Cambridge",
    "sg:classifiers":[
        {
            "category":"Insurance",
            "subcategory":"Insurance Agent",
            "type":"Services"
        }
    ],
    "sg:phone":"+1 410 228 1656",
    "sg:postcode":"21613",
    "sg:province":"MD",
    "wof:name":"William T Hunt Insurance",
    "wof:placetype":"venue"
},
  "geometry": {"coordinates":[-76.077282,38.569333],"type":"Point"}
}