{
  "type": "Feature",
  "properties": {
    "iso:country":"US",
    "sg:address":"8652 Old Ardmore Rd",
    "sg:city":"Hyattsville",
    "sg:classifiers":[
        {
            "category":"Home & Garden",
            "subcategory":"Carpets & Floor Coverings",
            "type":"Retail Goods"
        }
    ],
    "sg:phone":"+1 301 773 1334",
    "sg:postcode":"20785",
    "sg:province":"MD",
    "sg:tags":[
        "carpeting"
    ],
    "wof:name":"Carpet Binding Services",
    "wof:placetype":"venue"
},
  "geometry": {"coordinates":[-76.859703,38.938999],"type":"Point"}
}