{
  "type": "Feature",
  "properties": {
    "addr:full":"127 Back River Neck Rd Essex MD 21221",
    "addr:housenumber":"127",
    "addr:postcode":"21221",
    "addr:street":"Back River Neck Rd",
    "iso:country":"US",
    "sg:address":"127 Back River Neck Rd",
    "sg:city":"Essex",
    "sg:classifiers":[
        {
            "category":"Retail",
            "subcategory":"Auto Repair",
            "type":"Services"
        }
    ],
    "sg:phone":"+1 410 686 0943",
    "sg:postcode":"21221",
    "sg:province":"MD",
    "sg:tags":[
        "body",
        "shop"
    ],
    "wof:name":"H & H Body Shop",
    "wof:placetype":"venue"
},
  "geometry": {"coordinates":[-76.44760100000001,39.311901],"type":"Point"}
}