{
  "type": "Feature",
  "properties": {
    "iso:country":"US",
    "sg:address":"306 Marine Academy Dr",
    "sg:city":"Stevensville",
    "sg:classifiers":[
        {
            "category":"Government",
            "subcategory":"Office",
            "type":"Public Place"
        }
    ],
    "sg:phone":"+1 410 643 5771",
    "sg:postcode":"21666",
    "sg:province":"MD",
    "sg:tags":[
        "state"
    ],
    "wof:name":"Technical Svc Div",
    "wof:placetype":"venue"
},
  "geometry": {"coordinates":[-76.353408,38.953986],"type":"Point"}
}