{
  "type": "Feature",
  "properties": {
    "addr:full":"1308 Cranesbill Ct Belcamp MD 21017",
    "addr:housenumber":"1308",
    "addr:postcode":"21017",
    "addr:street":"Cranesbill Ct",
    "iso:country":"US",
    "sg:address":"1308 Cranesbill Ct",
    "sg:city":"Belcamp",
    "sg:classifiers":[
        {
            "category":"Building & Trades",
            "subcategory":"Construction",
            "type":"Services"
        }
    ],
    "sg:phone":"+1 410 272 1130",
    "sg:postcode":"21017",
    "sg:province":"MD",
    "sg:tags":[
        "contractor"
    ],
    "wof:name":"Questar Builders Inc",
    "wof:placetype":"venue"
},
  "geometry": {"coordinates":[-76.248744,39.472546],"type":"Point"}
}