{
  "type": "Feature",
  "properties": {
    "iso:country":"US",
    "sg:address":"2420 N Salisbury Blvd",
    "sg:city":"Salisbury",
    "sg:classifiers":[
        {
            "category":"Home & Garden",
            "subcategory":"Furniture",
            "type":"Retail Goods"
        }
    ],
    "sg:phone":"+1 410 543 2280",
    "sg:postcode":"21801",
    "sg:province":"MD",
    "wof:name":"Mattress & Futon Store",
    "wof:placetype":"venue"
},
  "geometry": {"coordinates":[-75.569524,38.402711],"type":"Point"}
}