{
  "type": "Feature",
  "properties": {
    "addr:full":"4636 Coastal Blvd White Plains MD 20695",
    "addr:housenumber":"4636",
    "addr:postcode":"20695",
    "addr:street":"Coastal Blvd",
    "iso:country":"US",
    "sg:address":"4636 Coastal Blvd",
    "sg:city":"White Plains",
    "sg:classifiers":[
        {
            "category":"Building & Trades",
            "subcategory":"Construction",
            "type":"Services"
        }
    ],
    "sg:phone":"+1 301 870 3931",
    "sg:postcode":"20695",
    "sg:province":"MD",
    "sg:tags":[
        "painter"
    ],
    "wof:name":"Kimble Services Pressure Wash",
    "wof:placetype":"venue"
},
  "geometry": {"coordinates":[-76.9609,38.583065],"type":"Point"}
}