{
  "type": "Feature",
  "properties": {
    "iso:country":"US",
    "sg:address":"70 Pennsylvania Ave",
    "sg:city":"Earleville",
    "sg:classifiers":[
        {
            "category":"Bars & Pubs",
            "type":"Food & Drink"
        }
    ],
    "sg:phone":"+1 410 275 2591",
    "sg:postcode":"21919",
    "sg:province":"MD",
    "wof:name":"Fireside Tavern",
    "wof:placetype":"venue"
},
  "geometry": {"coordinates":[-75.977551,39.440709],"type":"Point"}
}