{
  "type": "Feature",
  "properties": {
    "addr:full":"419 Main St Laurel MD 20707",
    "addr:housenumber":"419",
    "addr:postcode":"20707",
    "addr:street":"Main St",
    "iso:country":"US",
    "sg:address":"419 Main St",
    "sg:city":"Laurel",
    "sg:classifiers":[
        {
            "category":"Social Services",
            "subcategory":"Job Training",
            "type":"Services"
        }
    ],
    "sg:phone":"+1 410 792 4080",
    "sg:postcode":"20707",
    "sg:province":"MD",
    "sg:tags":[
        "rehabilitation"
    ],
    "wof:name":"Reality",
    "wof:placetype":"venue"
},
  "geometry": {"coordinates":[-76.849288,39.106549],"type":"Point"}
}