{
  "type": "Feature",
  "properties": {
    "iso:country":"US",
    "sg:address":"2213 E Monument St",
    "sg:city":"Baltimore",
    "sg:classifiers":[
        {
            "category":"Shopping",
            "subcategory":"Clothing, Apparel, & Fashions",
            "type":"Retail Goods"
        }
    ],
    "sg:phone":"+1 410 276 6948",
    "sg:postcode":"21205",
    "sg:province":"MD",
    "sg:tags":[
        "apparel",
        "accessory",
        "clothing",
        "women's"
    ],
    "sg:website":"www.rainbowshops.com",
    "wof:name":"Rainbow Apparel Company",
    "wof:placetype":"venue"
},
  "geometry": {"coordinates":[-76.586304,39.298801],"type":"Point"}
}