{
  "type": "Feature",
  "properties": {
    "iso:country":"US",
    "sg:address":"8560 2nd Ave",
    "sg:city":"Silver Spring",
    "sg:classifiers":[
        {
            "category":"Organizations",
            "subcategory":"Non-profit Organization",
            "type":"Services"
        }
    ],
    "sg:phone":"+1 301 608 3977",
    "sg:postcode":"20910",
    "sg:province":"MD",
    "sg:tags":[
        "social"
    ],
    "wof:name":"Coffe Inc",
    "wof:placetype":"venue"
},
  "geometry": {"coordinates":[-77.032696,38.99667],"type":"Point"}
}