{
  "type": "Feature",
  "properties": {
    "addr:full":"4004 Greenway Baltimore MD 21218",
    "addr:housenumber":"4004",
    "addr:postcode":"21218",
    "addr:street":"Greenway",
    "iso:country":"US",
    "sg:address":"4004 Greenway",
    "sg:city":"Baltimore",
    "sg:classifiers":[
        {
            "category":"Professional",
            "type":"Services"
        }
    ],
    "sg:phone":"+1 410 366 4004",
    "sg:postcode":"21218",
    "sg:province":"MD",
    "sg:tags":[
        "establishment"
    ],
    "wof:name":"Twining Corp",
    "wof:placetype":"venue"
},
  "geometry": {"coordinates":[-76.61466,39.33954],"type":"Point"}
}