{
  "type": "Feature",
  "properties": {
    "iso:country":"US",
    "sg:address":"9811 Mallard Dr",
    "sg:city":"Laurel",
    "sg:classifiers":[
        {
            "category":"Health Services",
            "subcategory":"Doctor",
            "type":"Services"
        }
    ],
    "sg:phone":"+1 410 792 0081",
    "sg:postcode":"20708",
    "sg:province":"MD",
    "wof:name":"Haye Oswald MD",
    "wof:placetype":"venue"
},
  "geometry": {"coordinates":[-76.835178,39.055549],"type":"Point"}
}