{
  "type": "Feature",
  "properties": {
    "addr:full":"3614 Wabash Ave Baltimore MD 21215",
    "addr:housenumber":"3614",
    "addr:postcode":"21215",
    "addr:street":"Wabash Ave",
    "iso:country":"US",
    "sg:address":"3614 Wabash Ave",
    "sg:city":"Baltimore",
    "sg:classifiers":[
        {
            "category":"Social Services",
            "subcategory":"Child Care",
            "type":"Services"
        }
    ],
    "sg:phone":"+1 410 466 0200",
    "sg:postcode":"21215",
    "sg:province":"MD",
    "sg:tags":[
        "day"
    ],
    "wof:name":"Gentle Touch Licensed Daycare",
    "wof:placetype":"venue"
},
  "geometry": {"coordinates":[-76.66503400000001,39.326118],"type":"Point"}
}