{
  "type": "Feature",
  "properties": {
    "iso:country":"US",
    "sg:address":"11710 Reisterstown Rd",
    "sg:city":"Reisterstown",
    "sg:phone":"+1 410 833 8440",
    "sg:postcode":"21136",
    "sg:province":"MD",
    "wof:name":"Chiropractic Centers Of Maryland Inc",
    "wof:placetype":"venue"
},
  "geometry": {"coordinates":[-76.810783,39.444302],"type":"Point"}
}