{
  "type": "Feature",
  "properties": {
    "iso:country":"US",
    "sg:address":"3783 Pleasant Valley Rd",
    "sg:city":"Oakland",
    "sg:classifiers":[
        {
            "category":"Building & Trades",
            "subcategory":"Construction",
            "type":"Services"
        }
    ],
    "sg:phone":"+1 301 334 4208",
    "sg:postcode":"21550",
    "sg:province":"MD",
    "sg:tags":[
        "contractor"
    ],
    "wof:name":"Liller Construction",
    "wof:placetype":"venue"
},
  "geometry": {"coordinates":[-79.38088399999999,39.377957],"type":"Point"}
}