{
  "type": "Feature",
  "properties": {
    "addr:full":"6810 Lantern Hill Dr Gwynn Oak MD 21207",
    "addr:housenumber":"6810",
    "addr:postcode":"21207",
    "addr:street":"Lantern Hill Dr",
    "iso:country":"US",
    "sg:address":"6810 Lantern Hill Dr",
    "sg:city":"Gwynn Oak",
    "sg:classifiers":[
        {
            "category":"Real Estate",
            "subcategory":"Real Estate Operator",
            "type":"Services"
        }
    ],
    "sg:phone":"+1 410 944 0274",
    "sg:postcode":"21207",
    "sg:province":"MD",
    "sg:tags":[
        "apartment"
    ],
    "wof:name":"Lantern Hill Apts",
    "wof:placetype":"venue"
},
  "geometry": {"coordinates":[-76.730103,39.341499],"type":"Point"}
}