{
  "type": "Feature",
  "properties": {
    "iso:country":"US",
    "sg:address":"1607 Rockville Pike",
    "sg:city":"Rockville",
    "sg:classifiers":[
        {
            "category":"Restaurant",
            "type":"Food & Drink"
        }
    ],
    "sg:menulink":"http://www.allmenus.com/md/rockville/151917-baja-fresh-mexican-grill/menu/",
    "sg:phone":"+1 301 770 4339",
    "sg:postcode":"20852",
    "sg:province":"MD",
    "sg:tags":[
        "mexican"
    ],
    "wof:name":"Baja Fresh Mexican Grill",
    "wof:placetype":"venue"
},
  "geometry": {"coordinates":[-77.125972,39.064112],"type":"Point"}
}