{
  "type": "Feature",
  "properties": {
    "iso:country":"US",
    "sg:address":"4104 Greenspring Ave",
    "sg:city":"Baltimore",
    "sg:classifiers":[
        {
            "category":"Communications",
            "type":"Services"
        }
    ],
    "sg:phone":"+1 703 861 7758",
    "sg:postcode":"21209",
    "sg:province":"MD",
    "sg:tags":[
        "consultant",
        "telecommunication"
    ],
    "wof:name":"Jr Robert Bradshaw",
    "wof:placetype":"venue"
},
  "geometry": {"coordinates":[-76.65689399999999,39.338248],"type":"Point"}
}