{
  "type": "Feature",
  "properties": {
    "addr:full":"12648 Grey Eagle Ct Germantown MD 20874",
    "addr:housenumber":"12648",
    "addr:postcode":"20874",
    "addr:street":"Grey;Ct",
    "iso:country":"US",
    "sg:address":"12648 Grey Eagle Ct",
    "sg:city":"Germantown",
    "sg:classifiers":[
        {
            "category":"Social Services",
            "subcategory":"Child Care",
            "type":"Services"
        }
    ],
    "sg:phone":"+1 301 515 3204",
    "sg:postcode":"20874",
    "sg:province":"MD",
    "wof:name":"For Kids We Care Inc",
    "wof:placetype":"venue"
},
  "geometry": {"coordinates":[-77.26379300000001,39.169094],"type":"Point"}
}