{
  "type": "Feature",
  "properties": {
    "iso:country":"US",
    "sg:address":"8374 Kings Heights Rd",
    "sg:city":"Ellicott City",
    "sg:classifiers":[
        {
            "category":"Autos & Motor Vehicles",
            "subcategory":"Automobile Sales",
            "type":"Retail Goods"
        },
        {
            "category":"Retail",
            "subcategory":"Auto Repair",
            "type":"Services"
        }
    ],
    "sg:phone":"+1 410 203 9985",
    "sg:postcode":"21043",
    "sg:province":"MD",
    "sg:tags":[
        "limo"
    ],
    "wof:name":"David Webb Dba Krystal Coach",
    "wof:placetype":"venue"
},
  "geometry": {"coordinates":[-76.804186,39.253966],"type":"Point"}
}