{
  "type": "Feature",
  "properties": {
    "iso:country":"US",
    "sg:address":"8171 Maple Lawn Blvd",
    "sg:city":"Fulton",
    "sg:classifiers":[
        {
            "category":"Professional",
            "subcategory":"Lawyer & Legal Services",
            "type":"Services"
        }
    ],
    "sg:phone":"+1 301 575 0300",
    "sg:postcode":"20759",
    "sg:province":"MD",
    "sg:tags":[
        "attorney",
        "practice"
    ],
    "wof:name":"Offitkurman Law Firm",
    "wof:placetype":"venue"
},
  "geometry": {"coordinates":[-76.905896,39.14838],"type":"Point"}
}