{
  "type": "Feature",
  "properties": {
    "addr:full":"6140 Jerrys Dr Columbia MD 21044",
    "addr:housenumber":"6140",
    "addr:postcode":"21044",
    "addr:street":"Jerrys Dr",
    "iso:country":"US",
    "sg:address":"6140 Jerrys Dr",
    "sg:city":"Columbia",
    "sg:classifiers":[
        {
            "category":"Banks & Credit Unions",
            "subcategory":"Investment Brokerage",
            "type":"Services"
        }
    ],
    "sg:phone":"+1 410 772 1161",
    "sg:postcode":"21044",
    "sg:province":"MD",
    "sg:tags":[
        "consultant",
        "financing"
    ],
    "wof:name":"Wholesale Access",
    "wof:placetype":"venue"
},
  "geometry": {"coordinates":[-76.876229,39.201049],"type":"Point"}
}