{
  "type": "Feature",
  "properties": {
    "iso:country":"US",
    "sg:address":"3393 Donnell Dr",
    "sg:city":"District Heights",
    "sg:classifiers":[
        {
            "category":"Restaurant",
            "type":"Food & Drink"
        }
    ],
    "sg:phone":"+1 301 420 1009",
    "sg:postcode":"20747",
    "sg:province":"MD",
    "sg:tags":[
        "shop",
        "coffee"
    ],
    "wof:name":"Metropolitan Coffee",
    "wof:placetype":"venue"
},
  "geometry": {"coordinates":[-76.885091,38.846527],"type":"Point"}
}