{
  "type": "Feature",
  "properties": {
    "iso:country":"US",
    "sg:address":"3105 Hatton Rd",
    "sg:city":"Pikesville",
    "sg:classifiers":[
        {
            "category":"Health Services",
            "subcategory":"Doctor",
            "type":"Services"
        }
    ],
    "sg:phone":"+1 410 484 8421",
    "sg:postcode":"21208",
    "sg:province":"MD",
    "sg:tags":[
        "physician",
        "cardiology",
        "thoracic",
        "surgeons",
        "surgeon",
        "surgery",
        "cardiovascular"
    ],
    "wof:name":"Steven G Steinberg Md",
    "wof:placetype":"venue"
},
  "geometry": {"coordinates":[-76.69800600000001,39.374488],"type":"Point"}
}