{
  "type": "Feature",
  "properties": {
    "addr:full":"40955 Merchants Ln # 17 Leonardtown MD 20650",
    "addr:housenumber":"40955",
    "addr:postcode":"20650",
    "addr:street":"Merchants Ln # 17",
    "iso:country":"US",
    "sg:address":"40955 Merchants Ln # 17",
    "sg:city":"Leonardtown",
    "sg:classifiers":[
        {
            "category":"Personal",
            "subcategory":"Beauty Salon",
            "type":"Services"
        }
    ],
    "sg:phone":"+1 301 475 5272",
    "sg:postcode":"20650",
    "sg:province":"MD",
    "wof:name":"Haircutts",
    "wof:placetype":"venue"
},
  "geometry": {"coordinates":[-76.660821,38.305528],"type":"Point"}
}