{
  "type": "Feature",
  "properties": {
    "addr:full":"1715 Pulaski Hwy Havre De Grace MD 21078",
    "addr:housenumber":"1715",
    "addr:postcode":"21078",
    "addr:street":"Pulaski Hwy",
    "iso:country":"US",
    "sg:address":"1715 Pulaski Hwy",
    "sg:city":"Havre De Grace",
    "sg:classifiers":[
        {
            "category":"Retail",
            "subcategory":"Auto Repair",
            "type":"Services"
        }
    ],
    "sg:phone":"+1 410 939 5797",
    "sg:postcode":"21078",
    "sg:province":"MD",
    "sg:tags":[
        "repairing",
        "automobile"
    ],
    "wof:name":"Auto & Truck Headquarters",
    "wof:placetype":"venue"
},
  "geometry": {"coordinates":[-76.119602,39.533256],"type":"Point"}
}