{
  "type": "Feature",
  "properties": {
    "iso:country":"US",
    "sg:address":"1610 Gray Haven Ct",
    "sg:city":"Dundalk",
    "sg:classifiers":[
        {
            "category":"Building & Trades",
            "subcategory":"Equipment Rental",
            "type":"Services"
        }
    ],
    "sg:phone":"+1 410 284 1820",
    "sg:postcode":"21222",
    "sg:province":"MD",
    "sg:tags":[
        "machine",
        "vending"
    ],
    "wof:name":"Sneak A Snack",
    "wof:placetype":"venue"
},
  "geometry": {"coordinates":[-76.49279,39.270956],"type":"Point"}
}