{
  "type": "Feature",
  "properties": {
    "iso:country":"US",
    "sg:address":"400 W Lee St",
    "sg:city":"Baltimore",
    "sg:classifiers":[
        {
            "category":"Arts & Performance",
            "subcategory":"Art Gallery",
            "type":"Entertainment"
        }
    ],
    "sg:phone":"+1 410 547 6220",
    "sg:postcode":"21201",
    "sg:province":"MD",
    "wof:name":"Gallery E At Warehouse",
    "wof:placetype":"venue"
},
  "geometry": {"coordinates":[-76.62118100000001,39.282283],"type":"Point"}
}