{
  "type": "Feature",
  "properties": {
    "iso:country":"US",
    "sg:address":"300 N Gilmor St",
    "sg:city":"Baltimore",
    "sg:classifiers":[
        {
            "category":"Food & Beverages",
            "subcategory":"Liquor & Beverages",
            "type":"Retail Goods"
        }
    ],
    "sg:phone":"+1 410 566 1565",
    "sg:postcode":"21223",
    "sg:province":"MD",
    "sg:tags":[
        "beer",
        "spirit",
        "wine"
    ],
    "wof:name":"Pak & Pak Inc",
    "wof:placetype":"venue"
},
  "geometry": {"coordinates":[-76.642747,39.292057],"type":"Point"}
}