{
  "type": "Feature",
  "properties": {
    "addr:full":"7040 Morris Rd Pittsville MD 21850",
    "addr:housenumber":"7040",
    "addr:postcode":"21850",
    "addr:street":"Morris Rd",
    "iso:country":"US",
    "sg:address":"7040 Morris Rd",
    "sg:city":"Pittsville",
    "sg:classifiers":[
        {
            "category":"Home & Garden",
            "subcategory":"Building Materials",
            "type":"Retail Goods"
        }
    ],
    "sg:phone":"+1 410 835 0434",
    "sg:postcode":"21850",
    "sg:province":"MD",
    "sg:tags":[
        "plumbing",
        "fixture",
        "supply"
    ],
    "wof:name":"Kitchen & Bath Connections",
    "wof:placetype":"venue"
},
  "geometry": {"coordinates":[-75.408348,38.384034],"type":"Point"}
}