{
  "type": "Feature",
  "properties": {
    "iso:country":"US",
    "sg:address":"104 Railway Ln",
    "sg:city":"Hagerstown",
    "sg:classifiers":[
        {
            "category":"Restaurant",
            "type":"Food & Drink"
        }
    ],
    "sg:phone":"+1 301 791 2611",
    "sg:postcode":"21740",
    "sg:province":"MD",
    "wof:name":"Crazy Horse Steak House",
    "wof:placetype":"venue"
},
  "geometry": {"coordinates":[-77.765089,39.629298],"type":"Point"}
}