{
  "type": "Feature",
  "properties": {
    "iso:country":"US",
    "sg:address":"4800 Hampden Ln Ste 103",
    "sg:city":"Bethesda",
    "sg:classifiers":[
        {
            "category":"Restaurant",
            "type":"Food & Drink"
        }
    ],
    "sg:phone":"+1 301 986 4622",
    "sg:postcode":"20814",
    "sg:province":"MD",
    "wof:name":"Hampden Cafe",
    "wof:placetype":"venue"
},
  "geometry": {"coordinates":[-77.095001,38.9827],"type":"Point"}
}