{
  "type": "Feature",
  "properties": {
    "iso:country":"US",
    "sg:address":"15513 Hanover Pike",
    "sg:city":"Upperco",
    "sg:classifiers":[
        {
            "category":"Food & Beverages",
            "subcategory":"Fruits & Vegetables",
            "type":"Retail Goods"
        }
    ],
    "sg:phone":"+1 410 239 8505",
    "sg:postcode":"21155",
    "sg:province":"MD",
    "sg:tags":[
        "produce"
    ],
    "sg:website":"www.springmeadowfarms.com",
    "wof:name":"Spring Meadow Farms",
    "wof:placetype":"venue"
},
  "geometry": {"coordinates":[-76.839435,39.551211],"type":"Point"}
}