{
  "type": "Feature",
  "properties": {
    "addr:full":"835 N Howard St Baltimore MD 21201",
    "addr:housenumber":"835",
    "addr:postcode":"21201",
    "addr:street":"N Howard St",
    "iso:country":"US",
    "sg:address":"835 N Howard St",
    "sg:city":"Baltimore",
    "sg:classifiers":[
        {
            "category":"Shopping",
            "subcategory":"Jewelry",
            "type":"Retail Goods"
        }
    ],
    "sg:phone":"+1 410 523 5666",
    "sg:postcode":"21201",
    "sg:province":"MD",
    "sg:tags":[
        "jeweler"
    ],
    "wof:name":"Cromarate Mason Jewelers Inc",
    "wof:placetype":"venue"
},
  "geometry": {"coordinates":[-76.62003900000001,39.299683],"type":"Point"}
}