{
  "type": "Feature",
  "properties": {
    "iso:country":"US",
    "sg:address":"7 Hataswap Rd",
    "sg:city":"Cambridge",
    "sg:classifiers":[
        {
            "category":"Professional",
            "subcategory":"Research",
            "type":"Services"
        }
    ],
    "sg:phone":"+1 410 221 1493",
    "sg:postcode":"21613",
    "sg:province":"MD",
    "sg:tags":[
        "market",
        "analysis"
    ],
    "wof:name":"R K Assoc Inc",
    "wof:placetype":"venue"
},
  "geometry": {"coordinates":[-76.107154,38.583946],"type":"Point"}
}