{
  "type": "Feature",
  "properties": {
    "iso:country":"US",
    "sg:address":"9906 Sassafras Ln",
    "sg:city":"Bowie",
    "sg:classifiers":[
        {
            "category":"Building & Trades",
            "subcategory":"Construction",
            "type":"Services"
        }
    ],
    "sg:phone":"+1 301 925 9425",
    "sg:postcode":"20721",
    "sg:province":"MD",
    "sg:tags":[
        "home",
        "family"
    ],
    "wof:name":"Lfg Development Inc",
    "wof:placetype":"venue"
},
  "geometry": {"coordinates":[-76.834039,38.909839],"type":"Point"}
}