{
  "type": "Feature",
  "properties": {
    "addr:full":"13150 Old Marlboro Pike Upper Marlboro MD 20772",
    "addr:housenumber":"13150",
    "addr:postcode":"20772",
    "addr:street":"Old Marlboro Pike",
    "iso:country":"US",
    "sg:address":"13150 Old Marlboro Pike",
    "sg:city":"Upper Marlboro",
    "sg:classifiers":[
        {
            "category":"Utilities",
            "subcategory":"Mobile Phone",
            "type":"Services"
        }
    ],
    "sg:phone":"+1 301 574 1938",
    "sg:postcode":"20772",
    "sg:province":"MD",
    "sg:tags":[
        "telephone",
        "cellular"
    ],
    "wof:name":"Cellular One",
    "wof:placetype":"venue"
},
  "geometry": {"coordinates":[-76.77835,38.815664],"type":"Point"}
}