{
  "type": "Feature",
  "properties": {
    "addr:full":"11615 Nebel St Rockville MD 20852",
    "addr:housenumber":"11615",
    "addr:postcode":"20852",
    "addr:street":"Nebel St",
    "iso:country":"US",
    "sg:address":"11615 Nebel St",
    "sg:city":"Rockville",
    "sg:classifiers":[
        {
            "category":"Professional",
            "subcategory":"Accounting & Tax Preparation",
            "type":"Services"
        }
    ],
    "sg:phone":"+1 301 770 1525",
    "sg:postcode":"20852",
    "sg:province":"MD",
    "sg:tags":[
        "accountant"
    ],
    "wof:name":"Brockman Lawrence H CPA",
    "wof:placetype":"venue"
},
  "geometry": {"coordinates":[-77.1054,39.047501],"type":"Point"}
}