{
  "type": "Feature",
  "properties": {
    "iso:country":"US",
    "sg:address":"9014 Anna Dr",
    "sg:city":"Clinton",
    "sg:classifiers":[
        {
            "category":"Retail",
            "subcategory":"Repair Shop",
            "type":"Services"
        }
    ],
    "sg:phone":"+1 301 868 3374",
    "sg:postcode":"20735",
    "sg:province":"MD",
    "sg:tags":[
        "equipment",
        "electronic",
        "supply"
    ],
    "wof:name":"Orchid Standards Laboratories",
    "wof:placetype":"venue"
},
  "geometry": {"coordinates":[-76.91386300000001,38.764592],"type":"Point"}
}