{
  "type": "Feature",
  "properties": {
    "addr:full":"308 S Union Ave Havre De Grace MD 21078",
    "addr:housenumber":"308",
    "addr:postcode":"21078",
    "addr:street":"S Union Ave",
    "iso:country":"US",
    "sg:address":"308 S Union Ave",
    "sg:city":"Havre De Grace",
    "sg:classifiers":[
        {
            "category":"Health Services",
            "subcategory":"Health Practitioner",
            "type":"Services"
        }
    ],
    "sg:phone":"+1 443 643 4300",
    "sg:postcode":"21078",
    "sg:province":"MD",
    "sg:tags":[
        "midwife"
    ],
    "wof:name":"Susquehanna Ob-Gyn & Nurse",
    "wof:placetype":"venue"
},
  "geometry": {"coordinates":[-76.091618,39.544589],"type":"Point"}
}