{
  "type": "Feature",
  "properties": {
    "addr:full":"48 Tarn Ter Frostburg MD 21532",
    "addr:housenumber":"48",
    "addr:postcode":"21532",
    "addr:street":"Tarn Ter",
    "iso:country":"US",
    "sg:address":"48 Tarn Ter",
    "sg:city":"Frostburg",
    "sg:classifiers":[
        {
            "category":"Health Services",
            "subcategory":"Doctor",
            "type":"Services"
        }
    ],
    "sg:phone":"+1 301 689 1556",
    "sg:postcode":"21532",
    "sg:province":"MD",
    "sg:tags":[
        "medical"
    ],
    "wof:name":"Angel H Roque Dr",
    "wof:placetype":"venue"
},
  "geometry": {"coordinates":[-78.92790599999999,39.660447],"type":"Point"}
}