{
  "type": "Feature",
  "properties": {
    "iso:country":"US",
    "sg:address":"7411 Riggs Rd",
    "sg:city":"Hyattsville",
    "sg:classifiers":[
        {
            "category":"Professional",
            "subcategory":"Business Services",
            "type":"Services"
        }
    ],
    "sg:phone":"+1 301 445 1716",
    "sg:postcode":"20783",
    "sg:province":"MD",
    "wof:name":"Quality Tax Services",
    "wof:placetype":"venue"
},
  "geometry": {"coordinates":[-76.978922,38.981861],"type":"Point"}
}