{
  "type": "Feature",
  "properties": {
    "addr:full":"1317 Marquis Ct Fallston MD 21047",
    "addr:housenumber":"1317",
    "addr:postcode":"21047",
    "addr:street":"Marquis Ct",
    "iso:country":"US",
    "sg:address":"1317 Marquis Ct",
    "sg:city":"Fallston",
    "sg:classifiers":[
        {
            "category":"Professional",
            "subcategory":"Detective & Security Services",
            "type":"Services"
        }
    ],
    "sg:phone":"+1 410 803 0463",
    "sg:postcode":"21047",
    "sg:province":"MD",
    "sg:tags":[
        "guard",
        "patrol"
    ],
    "wof:name":"Son America Security Inc",
    "wof:placetype":"venue"
},
  "geometry": {"coordinates":[-76.42134299999999,39.521147],"type":"Point"}
}