{
  "type": "Feature",
  "properties": {
    "iso:country":"US",
    "sg:address":"7474 Weather Worn Way",
    "sg:city":"Columbia",
    "sg:classifiers":[
        {
            "category":"Building & Trades",
            "subcategory":"Construction",
            "type":"Services"
        }
    ],
    "sg:phone":"+1 410 381 5332",
    "sg:postcode":"21046",
    "sg:province":"MD",
    "sg:tags":[
        "painter"
    ],
    "wof:name":"Dackle Brothers Painting Co",
    "wof:placetype":"venue"
},
  "geometry": {"coordinates":[-76.869499,39.164799],"type":"Point"}
}