{
  "type": "Feature",
  "properties": {
    "addr:full":"5525 Belair Rd Baltimore MD 21206",
    "addr:housenumber":"5525",
    "addr:postcode":"21206",
    "addr:street":"Belair Rd",
    "iso:country":"US",
    "sg:address":"5525 Belair Rd",
    "sg:city":"Baltimore",
    "sg:classifiers":[
        {
            "category":"Shopping",
            "subcategory":"Books",
            "type":"Retail Goods"
        }
    ],
    "sg:phone":"+1 410 325 2225",
    "sg:postcode":"21206",
    "sg:province":"MD",
    "sg:tags":[
        "dealer"
    ],
    "wof:name":"Christ King Book Store & More",
    "wof:placetype":"venue"
},
  "geometry": {"coordinates":[-76.548051,39.340525],"type":"Point"}
}