{
  "type": "Feature",
  "properties": {
    "iso:country":"US",
    "sg:address":"1197 Baltimore Annapolis Blvd",
    "sg:city":"Arnold",
    "sg:classifiers":[
        {
            "category":"Building & Trades",
            "subcategory":"Electrical",
            "type":"Services"
        }
    ],
    "sg:phone":"+1 410 647 5107",
    "sg:postcode":"21012",
    "sg:province":"MD",
    "sg:tags":[
        "electric",
        "contractor"
    ],
    "wof:name":"B & L Electric Co Inc",
    "wof:placetype":"venue"
},
  "geometry": {"coordinates":[-76.519281,39.041481],"type":"Point"}
}