{
  "type": "Feature",
  "properties": {
    "iso:country":"US",
    "sg:address":"7440 Fort Smallwood Rd",
    "sg:city":"Baltimore",
    "sg:classifiers":[
        {
            "category":"Manufacturing",
            "subcategory":"Signs",
            "type":"Manufacturing & Wholesale Goods"
        }
    ],
    "sg:phone":"+1 410 255 6400",
    "sg:postcode":"21226",
    "sg:province":"MD",
    "sg:website":"www.gablesigns.com",
    "wof:name":"Gable Signs & Graphics Inc",
    "wof:placetype":"venue"
},
  "geometry": {"coordinates":[-76.54399600000001,39.178471],"type":"Point"}
}