{
  "type": "Feature",
  "properties": {
    "addr:full":"290 Owings Hill Ct Owings MD 20736",
    "addr:housenumber":"290",
    "addr:postcode":"20736",
    "addr:street":"Owings Hill Ct",
    "iso:country":"US",
    "sg:address":"290 Owings Hill Ct",
    "sg:city":"Owings",
    "sg:classifiers":[
        {
            "category":"Utilities",
            "subcategory":"Telephone",
            "type":"Services"
        },
        {
            "category":"Manufacturing",
            "subcategory":"Electronics",
            "type":"Manufacturing & Wholesale Goods"
        }
    ],
    "sg:phone":"+1 410 257 9265",
    "sg:postcode":"20736",
    "sg:province":"MD",
    "sg:tags":[
        "equipment",
        "telecommunications-equipment",
        "system",
        "supply"
    ],
    "sg:website":"http://www.motorola.com",
    "wof:name":"Motorola",
    "wof:placetype":"venue"
},
  "geometry": {"coordinates":[-76.60303,38.713882],"type":"Point"}
}