{
  "type": "Feature",
  "properties": {
    "iso:country":"US",
    "sg:address":"235 W Patrick St",
    "sg:city":"Frederick",
    "sg:classifiers":[
        {
            "category":"Health Services",
            "subcategory":"Health Practitioner",
            "type":"Services"
        }
    ],
    "sg:phone":"+1 301 662 4160",
    "sg:postcode":"21701",
    "sg:province":"MD",
    "wof:name":"Evergreen Psychology & Assoc",
    "wof:placetype":"venue"
},
  "geometry": {"coordinates":[-77.416263,39.41366],"type":"Point"}
}