{
  "type": "Feature",
  "properties": {
    "addr:full":"8801 Loch Raven Blvd Towson MD 21286",
    "addr:housenumber":"8801",
    "addr:postcode":"21286",
    "addr:street":"Loch Raven Blvd",
    "iso:country":"US",
    "sg:address":"8801 Loch Raven Blvd",
    "sg:city":"Towson",
    "sg:classifiers":[
        {
            "category":"Travel",
            "subcategory":"Hotels & Motels",
            "type":"Entertainment"
        }
    ],
    "sg:phone":"+1 800 424 6423",
    "sg:postcode":"21286",
    "sg:province":"MD",
    "sg:website":"http://www.comfortinn.com/hotel-towson-maryland-MD175?promo=yplocal",
    "wof:name":"Comfort Inn Towson",
    "wof:placetype":"venue"
},
  "geometry": {"coordinates":[-76.564097,39.398971],"type":"Point"}
}