{
  "type": "Feature",
  "properties": {
    "iso:country":"US",
    "sg:address":"10551 Faulkner Ridge Cir",
    "sg:city":"Columbia",
    "sg:classifiers":[
        {
            "category":"Shopping",
            "type":"Retail Goods"
        }
    ],
    "sg:phone":"+1 410 730 7982",
    "sg:postcode":"21044",
    "sg:province":"MD",
    "sg:tags":[
        "merchandise"
    ],
    "wof:name":"Hobbits Us Coin Mart",
    "wof:placetype":"venue"
},
  "geometry": {"coordinates":[-76.873988,39.222637],"type":"Point"}
}