{
  "type": "Feature",
  "properties": {
    "addr:full":"500 Light St Baltimore MD 21202",
    "addr:housenumber":"500",
    "addr:postcode":"21202",
    "addr:street":"Light St",
    "iso:country":"US",
    "sg:address":"500 Light St",
    "sg:city":"Baltimore",
    "sg:classifiers":[
        {
            "category":"Shopping",
            "subcategory":"Florist",
            "type":"Retail Goods"
        }
    ],
    "sg:phone":"+1 410 230 0908",
    "sg:postcode":"21202",
    "sg:province":"MD",
    "wof:name":"Dale J Klietz",
    "wof:placetype":"venue"
},
  "geometry": {"coordinates":[-76.613297,39.283001],"type":"Point"}
}