{
  "type": "Feature",
  "properties": {
    "iso:country":"US",
    "sg:address":"701 Russell Ave",
    "sg:city":"Gaithersburg",
    "sg:classifiers":[
        {
            "category":"Personal",
            "subcategory":"Beauty Salon",
            "type":"Services"
        }
    ],
    "sg:phone":"+1 301 948 7020",
    "sg:postcode":"20877",
    "sg:province":"MD",
    "sg:website":"www.cartoon-cuts.com",
    "wof:name":"Cartoon Cuts",
    "wof:placetype":"venue"
},
  "geometry": {"coordinates":[-77.20857100000001,39.152878],"type":"Point"}
}