{
  "type": "Feature",
  "properties": {
    "iso:country":"US",
    "sg:address":"500 S Boardwalk",
    "sg:city":"Ocean City",
    "sg:classifiers":[
        {
            "category":"Shopping",
            "subcategory":"Clothing, Apparel, & Fashions",
            "type":"Retail Goods"
        }
    ],
    "sg:phone":"+1 410 289 3858",
    "sg:postcode":"21842",
    "sg:province":"MD",
    "sg:tags":[
        "t"
    ],
    "wof:name":"T-Shirt Explosion",
    "wof:placetype":"venue"
},
  "geometry": {"coordinates":[-75.082,38.336813],"type":"Point"}
}