{
  "type": "Feature",
  "properties": {
    "iso:country":"US",
    "sg:address":"933 Taylor Ave",
    "sg:city":"Towson",
    "sg:classifiers":[
        {
            "category":"Retail",
            "subcategory":"Self-service Laundry",
            "type":"Services"
        }
    ],
    "sg:phone":"+1 410 828 1640",
    "sg:postcode":"21286",
    "sg:province":"MD",
    "wof:name":"J P Laundromat Inc",
    "wof:placetype":"venue"
},
  "geometry": {"coordinates":[-76.578591,39.386026],"type":"Point"}
}