{
  "type": "Feature",
  "properties": {
    "addr:full":"7208 Coastal Hwy Ocean City MD 21842",
    "addr:housenumber":"7208",
    "addr:postcode":"21842",
    "addr:street":"Coastal Hwy",
    "iso:country":"US",
    "sg:address":"7208 Coastal Hwy",
    "sg:city":"Ocean City",
    "sg:classifiers":[
        {
            "category":"Real Estate",
            "subcategory":"Real Estate Agent",
            "type":"Services"
        }
    ],
    "sg:phone":"+1 410 524 5781",
    "sg:postcode":"21842",
    "sg:province":"MD",
    "sg:tags":[
        "management"
    ],
    "sg:website":"www.oc-rem.com",
    "wof:name":"O C Real Estate Management",
    "wof:placetype":"venue"
},
  "geometry": {"coordinates":[-75.063371,38.393708],"type":"Point"}
}