{
  "type": "Feature",
  "properties": {
    "addr:full":"1313 Aldino Stepney Rd Aberdeen MD 21001",
    "addr:housenumber":"1313",
    "addr:postcode":"21001",
    "addr:street":"Stepney Rd",
    "iso:country":"US",
    "sg:address":"1313 Aldino Stepney Rd",
    "sg:city":"Aberdeen",
    "sg:classifiers":[
        {
            "category":"Retail",
            "subcategory":"Repair Shop",
            "type":"Services"
        }
    ],
    "sg:phone":"+1 410 575 6204",
    "sg:postcode":"21001",
    "sg:province":"MD",
    "sg:tags":[
        "electrical"
    ],
    "wof:name":"Aero Mist Inc",
    "wof:placetype":"venue"
},
  "geometry": {"coordinates":[-76.209101,39.520708],"type":"Point"}
}