{
  "type": "Feature",
  "properties": {
    "iso:country":"US",
    "sg:address":"210 S Centre St",
    "sg:city":"Cumberland",
    "sg:classifiers":[
        {
            "category":"Professional",
            "subcategory":"Business Services",
            "type":"Services"
        }
    ],
    "sg:phone":"+1 301 722 4800",
    "sg:postcode":"21502",
    "sg:province":"MD",
    "sg:tags":[
        "convention",
        "meeting",
        "facility"
    ],
    "wof:name":"Cumberland Armory Convention",
    "wof:placetype":"venue"
},
  "geometry": {"coordinates":[-78.760209,39.649854],"type":"Point"}
}