{
  "type": "Feature",
  "properties": {
    "addr:full":"1931 Searles Rd Dundalk MD 21222",
    "addr:housenumber":"1931",
    "addr:postcode":"21222",
    "addr:street":"Searles Rd",
    "iso:country":"US",
    "sg:address":"1931 Searles Rd",
    "sg:city":"Dundalk",
    "sg:classifiers":[
        {
            "category":"Retail",
            "subcategory":"Repair Shop",
            "type":"Services"
        }
    ],
    "sg:phone":"+1 888 851 6094",
    "sg:postcode":"21222",
    "sg:province":"MD",
    "sg:tags":[
        "small",
        "major",
        "appliance",
        "refinishing"
    ],
    "sg:website":"http://local.ingenio.com/Listings/Details.aspx?NUM=a%3a9829270%3a13%3a4859924%3a14%3a0%3a7",
    "wof:name":"Eleet Appliance Repair",
    "wof:placetype":"venue"
},
  "geometry": {"coordinates":[-76.50782,39.267891],"type":"Point"}
}