{
  "type": "Feature",
  "properties": {
    "iso:country":"US",
    "sg:address":"50 Maryland Ave",
    "sg:city":"Rockville",
    "sg:classifiers":[
        {
            "category":"Government",
            "subcategory":"Office",
            "type":"Public Place"
        }
    ],
    "sg:phone":"+1 240 777 9460",
    "sg:postcode":"20850",
    "sg:province":"MD",
    "wof:name":"Montgomery County License Dept",
    "wof:placetype":"venue"
},
  "geometry": {"coordinates":[-77.154978,39.079382],"type":"Point"}
}