{
  "type": "Feature",
  "properties": {
    "iso:country":"US",
    "sg:address":"4820 de Russey Pkwy",
    "sg:city":"Chevy Chase",
    "sg:classifiers":[
        {
            "category":"Education",
            "subcategory":"Special Training",
            "type":"Public Place"
        }
    ],
    "sg:phone":"+1 301 907 3293",
    "sg:postcode":"20815",
    "sg:province":"MD",
    "sg:tags":[
        "lesson",
        "music"
    ],
    "wof:name":"Stoop Cynthia Ann",
    "wof:placetype":"venue"
},
  "geometry": {"coordinates":[-77.097307,38.972135],"type":"Point"}
}