{
  "type": "Feature",
  "properties": {
    "addr:full":"20339 Notting Hill Way Germantown MD 20876",
    "addr:housenumber":"20339",
    "addr:postcode":"20876",
    "addr:street":"Notting Hill Way",
    "iso:country":"US",
    "sg:address":"20339 Notting Hill Way",
    "sg:city":"Germantown",
    "sg:classifiers":[
        {
            "category":"Professional",
            "subcategory":"Art Services",
            "type":"Services"
        }
    ],
    "sg:phone":"+1 240 463 7482",
    "sg:postcode":"20876",
    "sg:province":"MD",
    "sg:tags":[
        "graphic",
        "commercial",
        "designer",
        "artist"
    ],
    "wof:name":"Cecilia Pettit Hersh",
    "wof:placetype":"venue"
},
  "geometry": {"coordinates":[-77.242062,39.189172],"type":"Point"}
}