{
  "type": "Feature",
  "properties": {
    "addr:full":"9715 Bellevue Dr Bethesda MD 20814",
    "addr:housenumber":"9715",
    "addr:postcode":"20814",
    "addr:street":"Bellevue Dr",
    "iso:country":"US",
    "sg:address":"9715 Bellevue Dr",
    "sg:city":"Bethesda",
    "sg:classifiers":[
        {
            "category":"Education",
            "subcategory":"Special Training",
            "type":"Public Place"
        }
    ],
    "sg:phone":"+1 301 530 1708",
    "sg:postcode":"20814",
    "sg:province":"MD",
    "wof:name":"Mattson Gregory",
    "wof:placetype":"venue"
},
  "geometry": {"coordinates":[-77.09954399999999,39.01514],"type":"Point"}
}