{
  "type": "Feature",
  "properties": {
    "addr:full":"10275 Little Patuxent Pkwy Columbia MD 21044",
    "addr:housenumber":"10275",
    "addr:postcode":"21044",
    "addr:street":"Little Patuxent Pkwy",
    "iso:country":"US",
    "sg:address":"10275 Little Patuxent Pkwy",
    "sg:city":"Columbia",
    "sg:classifiers":[
        {
            "category":"Real Estate",
            "subcategory":"Real Estate Operator",
            "type":"Services"
        }
    ],
    "sg:phone":"+1 410 992 4377",
    "sg:postcode":"21044",
    "sg:province":"MD",
    "sg:tags":[
        "property",
        "management",
        "commercial"
    ],
    "wof:name":"Rouse Company The",
    "wof:placetype":"venue"
},
  "geometry": {"coordinates":[-76.857516,39.212894],"type":"Point"}
}