{
  "type": "Feature",
  "properties": {
    "iso:country":"US",
    "sg:address":"6640 Lake Park Drive, Suite 205",
    "sg:city":"Greenbelt",
    "sg:classifiers":[
        {
            "category":"Professional",
            "subcategory":"Computer Services",
            "type":"Services"
        }
    ],
    "sg:phone":"+1 651 317 3663",
    "sg:postcode":"20770",
    "sg:province":"MD",
    "sg:tags":[
        "online-wholesale-food-marketplace",
        "foodservice",
        "food-distribution",
        "food-distribution-industry",
        "foodservice-industry",
        "restaurants",
        "food-manufacturers",
        "wholesale-food-industry"
    ],
    "sg:website":"http://www.foodem.com",
    "wof:name":"Foodem",
    "wof:placetype":"venue"
},
  "geometry": {"coordinates":[-76.874065,38.987925],"type":"Point"}
}