{
  "type": "Feature",
  "properties": {
    "iso:country":"US",
    "sg:address":"12643 Council Oak Dr",
    "sg:city":"Waldorf",
    "sg:classifiers":[
        {
            "category":"Shopping",
            "subcategory":"Music",
            "type":"Retail Goods"
        }
    ],
    "sg:phone":"+1 301 792 6806",
    "sg:postcode":"20601",
    "sg:province":"MD",
    "sg:tags":[
        "store"
    ],
    "wof:name":"Blackson Records",
    "wof:placetype":"venue"
},
  "geometry": {"coordinates":[-76.875975,38.641075],"type":"Point"}
}