{
  "type": "Feature",
  "properties": {
    "addr:full":"8418 Coco Rd Rosedale MD 21237",
    "addr:housenumber":"8418",
    "addr:postcode":"21237",
    "addr:street":"Coco Rd",
    "iso:country":"US",
    "sg:address":"8418 Coco Rd",
    "sg:city":"Rosedale",
    "sg:classifiers":[
        {
            "category":"Shopping",
            "subcategory":"Computers & Home Electronics",
            "type":"Retail Goods"
        }
    ],
    "sg:phone":"+1 443 772 0995",
    "sg:postcode":"21237",
    "sg:province":"MD",
    "sg:tags":[
        "equipment",
        "satellite",
        "system"
    ],
    "wof:name":"Stellar Satellite",
    "wof:placetype":"venue"
},
  "geometry": {"coordinates":[-76.504921,39.333798],"type":"Point"}
}