{
  "type": "Feature",
  "properties": {
    "addr:full":"1070 Hardees Dr Aberdeen MD 21001",
    "addr:postcode":"1070;21001",
    "addr:street":"Hardees Dr",
    "iso:country":"US",
    "sg:address":"1070 Hardees Dr",
    "sg:city":"Aberdeen",
    "sg:classifiers":[
        {
            "category":"Manufacturing",
            "subcategory":"Tools & Machinery",
            "type":"Manufacturing & Wholesale Goods"
        }
    ],
    "sg:phone":"+1 410 272 9250",
    "sg:postcode":"21001",
    "sg:province":"MD",
    "sg:tags":[
        "machine",
        "shop"
    ],
    "wof:name":"Asi",
    "wof:placetype":"venue"
},
  "geometry": {"coordinates":[-76.19815699999999,39.490618],"type":"Point"}
}