{
  "type": "Feature",
  "properties": {
    "iso:country":"US",
    "sg:address":"25 N Harrison St",
    "sg:city":"Easton",
    "sg:classifiers":[
        {
            "category":"Shopping",
            "subcategory":"Gifts & Souvenirs",
            "type":"Retail Goods"
        }
    ],
    "sg:phone":"+1 410 822 4295",
    "sg:postcode":"21601",
    "sg:province":"MD",
    "sg:tags":[
        "shop"
    ],
    "wof:name":"Tidewater Foundry Gift Shop",
    "wof:placetype":"venue"
},
  "geometry": {"coordinates":[-76.074714,38.774488],"type":"Point"}
}