{
  "type": "Feature",
  "properties": {
    "addr:full":"10915 Adkins Rd Berlin MD 21811",
    "addr:housenumber":"10915",
    "addr:postcode":"21811",
    "addr:street":"Adkins Rd",
    "iso:country":"US",
    "sg:address":"10915 Adkins Rd",
    "sg:city":"Berlin",
    "sg:phone":"+1 410 641 1053",
    "sg:postcode":"21811",
    "sg:province":"MD",
    "wof:name":"Eastern Shore Tree Removal",
    "wof:placetype":"venue"
},
  "geometry": {"coordinates":[-75.179517,38.363728],"type":"Point"}
}