{
  "type": "Feature",
  "properties": {
    "iso:country":"US",
    "sg:address":"10300 Bunch Berry Ln",
    "sg:city":"Upper Marlboro",
    "sg:classifiers":[
        {
            "category":"Shopping",
            "subcategory":"Computers & Home Electronics",
            "type":"Retail Goods"
        }
    ],
    "sg:phone":"+1 301 599 6558",
    "sg:postcode":"20772",
    "sg:province":"MD",
    "sg:tags":[
        "software"
    ],
    "wof:name":"Crunchy Technologies",
    "wof:placetype":"venue"
},
  "geometry": {"coordinates":[-76.824008,38.794095],"type":"Point"}
}