{
  "type": "Feature",
  "properties": {
    "addr:full":"409 Fairmount Dr Edgewater MD 21037",
    "addr:housenumber":"409",
    "addr:postcode":"21037",
    "addr:street":"Fairmount Dr",
    "iso:country":"US",
    "sg:address":"409 Fairmount Dr",
    "sg:city":"Edgewater",
    "sg:classifiers":[
        {
            "category":"Retail",
            "subcategory":"Repair Shop",
            "type":"Services"
        }
    ],
    "sg:phone":"+1 410 956 3497",
    "sg:postcode":"21037",
    "sg:province":"MD",
    "wof:name":"Cleaning Houses",
    "wof:placetype":"venue"
},
  "geometry": {"coordinates":[-76.551343,38.927503],"type":"Point"}
}