{
  "type": "Feature",
  "properties": {
    "iso:country":"US",
    "sg:address":"200 Monroe St",
    "sg:city":"Rockville",
    "sg:classifiers":[
        {
            "category":"Real Estate",
            "subcategory":"Real Estate Agent",
            "type":"Services"
        }
    ],
    "sg:phone":"+1 301 251 2828",
    "sg:postcode":"20850",
    "sg:province":"MD",
    "sg:tags":[
        "appraiser"
    ],
    "wof:name":"Woodside Realty Co",
    "wof:placetype":"venue"
},
  "geometry": {"coordinates":[-77.14999299999999,39.080703],"type":"Point"}
}