{
  "type": "Feature",
  "properties": {
    "addr:full":"8614 Bramble Ln Randallstown MD 21133",
    "addr:housenumber":"8614",
    "addr:postcode":"21133",
    "addr:street":"Bramble Ln",
    "iso:country":"US",
    "sg:address":"8614 Bramble Ln",
    "sg:city":"Randallstown",
    "sg:classifiers":[
        {
            "category":"Building & Trades",
            "subcategory":"Landscaping Services",
            "type":"Services"
        }
    ],
    "sg:phone":"+1 410 982 2074",
    "sg:postcode":"21133",
    "sg:province":"MD",
    "sg:tags":[
        "lawn",
        "tree",
        "snow",
        "removal",
        "arborist"
    ],
    "wof:name":"Noqueras Lawn Service",
    "wof:placetype":"venue"
},
  "geometry": {"coordinates":[-76.78192,39.36139],"type":"Point"}
}