{
  "type": "Feature",
  "properties": {
    "iso:country":"US",
    "sg:address":"5741 Industry Ln",
    "sg:city":"Frederick",
    "sg:classifiers":[
        {
            "category":"Home & Garden",
            "subcategory":"Carpets & Floor Coverings",
            "type":"Retail Goods"
        }
    ],
    "sg:phone":"+1 301 698 4789",
    "sg:postcode":"21704",
    "sg:province":"MD",
    "sg:tags":[
        "dealer",
        "rug"
    ],
    "wof:name":"Petersen's Carpet & Flooring",
    "wof:placetype":"venue"
},
  "geometry": {"coordinates":[-77.41331,39.390101],"type":"Point"}
}