{
  "type": "Feature",
  "properties": {
    "addr:full":"732 Snowden Ln Glen Burnie MD 21061",
    "addr:housenumber":"732",
    "addr:postcode":"21061",
    "addr:street":"Snowden Ln",
    "iso:country":"US",
    "sg:address":"732 Snowden Ln",
    "sg:city":"Glen Burnie",
    "sg:classifiers":[
        {
            "category":"Personal",
            "type":"Services"
        }
    ],
    "sg:phone":"+1 410 969 1139",
    "sg:postcode":"21061",
    "sg:province":"MD",
    "wof:name":"Tom Fitez",
    "wof:placetype":"venue"
},
  "geometry": {"coordinates":[-76.651611,39.135058],"type":"Point"}
}