{
  "type": "Feature",
  "properties": {
    "iso:country":"US",
    "sg:address":"3414 Curtis Dr",
    "sg:city":"Suitland",
    "sg:classifiers":[
        {
            "category":"Personal",
            "subcategory":"Beauty Salon",
            "type":"Services"
        }
    ],
    "sg:phone":"+1 301 423 2268",
    "sg:postcode":"20746",
    "sg:province":"MD",
    "wof:name":"Rufus' Master Hair Studio",
    "wof:placetype":"venue"
},
  "geometry": {"coordinates":[-76.947097,38.848628],"type":"Point"}
}