{
  "type": "Feature",
  "properties": {
    "iso:country":"US",
    "sg:address":"8555 16th St",
    "sg:city":"Silver Spring",
    "sg:classifiers":[
        {
            "category":"Professional",
            "subcategory":"Management & Consulting",
            "type":"Services"
        }
    ],
    "sg:phone":"+1 301 588 6535",
    "sg:postcode":"20910",
    "sg:province":"MD",
    "sg:tags":[
        "consultant",
        "business"
    ],
    "wof:name":"EHS Technologies Inc",
    "wof:placetype":"venue"
},
  "geometry": {"coordinates":[-77.038517,38.998009],"type":"Point"}
}