{
  "type": "Feature",
  "properties": {
    "addr:full":"14650 Rothgeb Dr Rockville MD 20850",
    "addr:housenumber":"14650",
    "addr:postcode":"20850",
    "addr:street":"Rothgeb Dr",
    "iso:country":"US",
    "sg:address":"14650 Rothgeb Dr",
    "sg:city":"Rockville",
    "sg:classifiers":[
        {
            "category":"Shopping",
            "subcategory":"Computers & Home Electronics",
            "type":"Retail Goods"
        }
    ],
    "sg:phone":"+1 301 762 1991",
    "sg:postcode":"20850",
    "sg:province":"MD",
    "sg:tags":[
        "equipment",
        "dealer"
    ],
    "wof:name":"Byron Products",
    "wof:placetype":"venue"
},
  "geometry": {"coordinates":[-77.133425,39.099665],"type":"Point"}
}