{
  "type": "Feature",
  "properties": {
    "addr:full":"21764 S Coral Dr Lexington Park MD 20653",
    "addr:housenumber":"21764",
    "addr:postcode":"20653",
    "addr:street":"S Coral Dr",
    "iso:country":"US",
    "sg:address":"21764 S Coral Dr",
    "sg:city":"Lexington Park",
    "sg:classifiers":[
        {
            "category":"Social Services",
            "type":"Services"
        }
    ],
    "sg:phone":"+1 301 863 5700",
    "sg:postcode":"20653",
    "sg:province":"MD",
    "sg:tags":[
        "organization",
        "welfare"
    ],
    "wof:name":"St Mary's Caring Inc",
    "wof:placetype":"venue"
},
  "geometry": {"coordinates":[-76.452101,38.264268],"type":"Point"}
}