{
  "type": "Feature",
  "properties": {
    "iso:country":"US",
    "sg:address":"9320 Baltimore National Pike",
    "sg:city":"Ellicott City",
    "sg:classifiers":[
        {
            "category":"Food & Beverages",
            "subcategory":"Groceries & Convenience Stores",
            "type":"Retail Goods"
        }
    ],
    "sg:phone":"+1 410 313 9788",
    "sg:postcode":"21042",
    "sg:province":"MD",
    "sg:tags":[
        "station",
        "gasoline"
    ],
    "wof:name":"Fast Fare",
    "wof:placetype":"venue"
},
  "geometry": {"coordinates":[-76.832594,39.27755],"type":"Point"}
}