{
  "type": "Feature",
  "properties": {
    "iso:country":"US",
    "sg:address":"10 Light St",
    "sg:city":"Baltimore",
    "sg:classifiers":[
        {
            "category":"Professional",
            "subcategory":"Lawyer & Legal Services",
            "type":"Services"
        }
    ],
    "sg:phone":"+1 410 385 3608",
    "sg:postcode":"21202",
    "sg:province":"MD",
    "wof:name":"Kelberman Dale",
    "wof:placetype":"venue"
},
  "geometry": {"coordinates":[-76.613865,39.288979],"type":"Point"}
}