{
  "type": "Feature",
  "properties": {
    "iso:country":"US",
    "sg:address":"8010 Wisconsin Ave",
    "sg:city":"Bethesda",
    "sg:classifiers":[
        {
            "category":"Retail",
            "subcategory":"Laundry & Dry Cleaning",
            "type":"Services"
        }
    ],
    "sg:phone":"+1 301 656 8470",
    "sg:postcode":"20814",
    "sg:province":"MD",
    "wof:name":"Bethesda Shoe Repair",
    "wof:placetype":"venue"
},
  "geometry": {"coordinates":[-77.095596,38.990898],"type":"Point"}
}