{
  "type": "Feature",
  "properties": {
    "iso:country":"US",
    "sg:address":"84 Harkins Ln",
    "sg:city":"Chesapeake City",
    "sg:classifiers":[
        {
            "category":"Farming",
            "subcategory":"Livestock Farm",
            "type":"Manufacturing & Wholesale Goods"
        }
    ],
    "sg:phone":"+1 410 885 2842",
    "sg:postcode":"21915",
    "sg:province":"MD",
    "sg:tags":[
        "animal",
        "general"
    ],
    "wof:name":"Ballyduff Farm Inc",
    "wof:placetype":"venue"
},
  "geometry": {"coordinates":[-75.843981,39.511267],"type":"Point"}
}