{
  "type": "Feature",
  "properties": {
    "iso:country":"US",
    "sg:address":"4930 del Ray Ave",
    "sg:city":"Bethesda",
    "sg:classifiers":[
        {
            "category":"Health Services",
            "subcategory":"Doctor",
            "type":"Services"
        }
    ],
    "sg:phone":"+1 301 897 5656",
    "sg:postcode":"20814",
    "sg:province":"MD",
    "sg:tags":[
        "physician",
        "surgeon"
    ],
    "wof:name":"Groover Christie & Merritt",
    "wof:placetype":"venue"
},
  "geometry": {"coordinates":[-77.099862,38.988784],"type":"Point"}
}