{
  "type": "Feature",
  "properties": {
    "addr:full":"3235 Holland Cliffs Rd Huntingtown MD 20639",
    "addr:housenumber":"3235",
    "addr:postcode":"20639",
    "addr:street":"Holland Cliffs Rd",
    "iso:country":"US",
    "sg:address":"3235 Holland Cliffs Rd",
    "sg:city":"Huntingtown",
    "sg:classifiers":[
        {
            "category":"Real Estate",
            "subcategory":"Real Estate Agent",
            "type":"Services"
        }
    ],
    "sg:phone":"+1 301 855 1865",
    "sg:postcode":"20639",
    "sg:province":"MD",
    "wof:name":"Hutchins Property Mgt PC",
    "wof:placetype":"venue"
},
  "geometry": {"coordinates":[-76.667451,38.606348],"type":"Point"}
}