{
  "type": "Feature",
  "properties": {
    "addr:full":"22 W Padonia Rd Ste B217 Lutherville Timonium MD 21093",
    "addr:housenumber":"22",
    "addr:postcode":"21093",
    "addr:street":"W Padonia Rd Ste B217",
    "iso:country":"US",
    "sg:address":"22 W Padonia Rd Ste B217",
    "sg:city":"Lutherville Timonium",
    "sg:classifiers":[
        {
            "category":"Retail",
            "subcategory":"Auto Repair",
            "type":"Services"
        }
    ],
    "sg:phone":"+1 410 560 7120",
    "sg:postcode":"21093",
    "sg:province":"MD",
    "wof:name":"Mo Lube",
    "wof:placetype":"venue"
},
  "geometry": {"coordinates":[-76.63419,39.456014],"type":"Point"}
}