{
  "type": "Feature",
  "properties": {
    "iso:country":"US",
    "sg:address":"843 Lanvale St",
    "sg:city":"Hagerstown",
    "sg:classifiers":[
        {
            "category":"Restaurant",
            "type":"Food & Drink"
        }
    ],
    "sg:phone":"+1 301 745 5560",
    "sg:postcode":"21740",
    "sg:province":"MD",
    "sg:tags":[
        "delicatessen"
    ],
    "wof:name":"Taylor's Landing",
    "wof:placetype":"venue"
},
  "geometry": {"coordinates":[-77.73659600000001,39.645263],"type":"Point"}
}