{
  "type": "Feature",
  "properties": {
    "addr:full":"35 S Linwood Ave Baltimore MD 21224",
    "addr:housenumber":"35",
    "addr:postcode":"21224",
    "addr:street":"S Linwood Ave",
    "iso:country":"US",
    "sg:address":"35 S Linwood Ave",
    "sg:city":"Baltimore",
    "sg:classifiers":[
        {
            "category":"Health Services",
            "subcategory":"Dentist",
            "type":"Services"
        }
    ],
    "sg:phone":"+1 410 732 8900",
    "sg:postcode":"21224",
    "sg:province":"MD",
    "wof:name":"Mallek Paul P",
    "wof:placetype":"venue"
},
  "geometry": {"coordinates":[-76.575996,39.291199],"type":"Point"}
}