{
  "type": "Feature",
  "properties": {
    "addr:full":"228 Grange Hall Dr Gaithersburg MD 20877",
    "addr:housenumber":"228",
    "addr:postcode":"20877",
    "addr:street":"Grange Hall Dr",
    "iso:country":"US",
    "sg:address":"228 Grange Hall Dr",
    "sg:city":"Gaithersburg",
    "sg:classifiers":[
        {
            "category":"Professional",
            "subcategory":"Management & Consulting",
            "type":"Services"
        }
    ],
    "sg:phone":"+1 301 670 5637",
    "sg:postcode":"20877",
    "sg:province":"MD",
    "wof:name":"Kdw International",
    "wof:placetype":"venue"
},
  "geometry": {"coordinates":[-77.17966800000001,39.152389],"type":"Point"}
}