{
  "type": "Feature",
  "properties": {
    "addr:full":"1915 Rohrersville Rd Knoxville MD 21758",
    "addr:housenumber":"1915",
    "addr:postcode":"21758",
    "addr:street":"Rohrersville Rd",
    "iso:country":"US",
    "sg:address":"1915 Rohrersville Rd",
    "sg:city":"Knoxville",
    "sg:classifiers":[
        {
            "category":"Organizations",
            "subcategory":"Religious Organization",
            "type":"Services"
        }
    ],
    "sg:phone":"+1 301 432 8354",
    "sg:postcode":"21758",
    "sg:province":"MD",
    "sg:tags":[
        "church"
    ],
    "wof:name":"Brownsville Church-Brethren",
    "wof:placetype":"venue"
},
  "geometry": {"coordinates":[-77.669157,39.371342],"type":"Point"}
}