{
  "type": "Feature",
  "properties": {
    "addr:full":"15000 Sugar Pine Way Burtonsville MD 20866",
    "addr:housenumber":"15000",
    "addr:postcode":"20866",
    "addr:street":"Sugar Pine Way",
    "iso:country":"US",
    "sg:address":"15000 Sugar Pine Way",
    "sg:city":"Burtonsville",
    "sg:classifiers":[
        {
            "category":"Building & Trades",
            "subcategory":"Construction",
            "type":"Services"
        }
    ],
    "sg:phone":"+1 301 776 1176",
    "sg:postcode":"20866",
    "sg:province":"MD",
    "sg:tags":[
        "house"
    ],
    "wof:name":"Riehls Carpentry Services",
    "wof:placetype":"venue"
},
  "geometry": {"coordinates":[-76.921289,39.102432],"type":"Point"}
}