{
  "type": "Feature",
  "properties": {
    "addr:full":"9594 Baltimore Ave College Park MD 20740",
    "addr:housenumber":"9594",
    "addr:postcode":"20740",
    "addr:street":"Baltimore Ave",
    "iso:country":"US",
    "sg:address":"9594 Baltimore Ave",
    "sg:city":"College Park",
    "sg:classifiers":[
        {
            "category":"Autos & Motor Vehicles",
            "subcategory":"Motorcycle Sales",
            "type":"Retail Goods"
        }
    ],
    "sg:phone":"+1 301 474 2228",
    "sg:postcode":"20740",
    "sg:province":"MD",
    "sg:tags":[
        "scooter"
    ],
    "wof:name":"Dirt Shop",
    "wof:placetype":"venue"
},
  "geometry": {"coordinates":[-76.929294,39.008989],"type":"Point"}
}