{
  "type": "Feature",
  "properties": {
    "addr:full":"11423 Sinepuxent Rd Berlin MD 21811",
    "addr:postcode":"11423;21811",
    "addr:street":"Sinepuxent Rd",
    "iso:country":"US",
    "sg:address":"11423 Sinepuxent Rd",
    "sg:city":"Berlin",
    "sg:classifiers":[
        {
            "category":"Retail",
            "subcategory":"Auto Repair",
            "type":"Services"
        }
    ],
    "sg:phone":"+1 410 641 3540",
    "sg:postcode":"21811",
    "sg:province":"MD",
    "sg:tags":[
        "body",
        "shop",
        "painting",
        "automobile",
        "automotive"
    ],
    "wof:name":"Sinepuxent Auto Repair",
    "wof:placetype":"venue"
},
  "geometry": {"coordinates":[-75.16717300000001,38.31461],"type":"Point"}
}