{
  "type": "Feature",
  "properties": {
    "iso:country":"US",
    "sg:address":"28037 Sunbury Ct",
    "sg:city":"Salisbury",
    "sg:classifiers":[
        {
            "category":"Building & Trades",
            "subcategory":"Landscaping Services",
            "type":"Services"
        }
    ],
    "sg:phone":"+1 443 260 4873",
    "sg:postcode":"21801",
    "sg:province":"MD",
    "wof:name":"Murphy S Lawn",
    "wof:placetype":"venue"
},
  "geometry": {"coordinates":[-75.642676,38.363797],"type":"Point"}
}