{
  "type": "Feature",
  "properties": {
    "addr:full":"405 Marvel Ct Easton MD 21601",
    "addr:housenumber":"405",
    "addr:postcode":"21601",
    "addr:street":"Marvel Ct",
    "iso:country":"US",
    "sg:address":"405 Marvel Ct",
    "sg:city":"Easton",
    "sg:classifiers":[
        {
            "category":"Health Services",
            "subcategory":"Doctor",
            "type":"Services"
        }
    ],
    "sg:phone":"+1 410 822 8440",
    "sg:postcode":"21601",
    "sg:province":"MD",
    "sg:tags":[
        "physician",
        "surgeon"
    ],
    "wof:name":"H William Friedel MD",
    "wof:placetype":"venue"
},
  "geometry": {"coordinates":[-76.06359,38.765324],"type":"Point"}
}