{
  "type": "Feature",
  "properties": {
    "iso:country":"US",
    "sg:address":"5702 40th Ave",
    "sg:city":"Hyattsville",
    "sg:classifiers":[
        {
            "category":"Utilities",
            "subcategory":"Refuse",
            "type":"Services"
        }
    ],
    "sg:phone":"+1 240 832 4562",
    "sg:postcode":"20781",
    "sg:province":"MD",
    "sg:tags":[
        "disposal",
        "equipment",
        "recycling",
        "system",
        "waste"
    ],
    "wof:name":"Julio B Gomez",
    "wof:placetype":"venue"
},
  "geometry": {"coordinates":[-76.950064,38.956824],"type":"Point"}
}