{
  "type": "Feature",
  "properties": {
    "addr:full":"825 Dulaney Valley Rd Towson MD 21204",
    "addr:housenumber":"825",
    "addr:postcode":"21204",
    "addr:street":"Dulaney Valley Rd",
    "iso:country":"US",
    "sg:address":"825 Dulaney Valley Rd",
    "sg:city":"Towson",
    "sg:classifiers":[
        {
            "category":"Utilities",
            "subcategory":"Mobile Phone",
            "type":"Services"
        }
    ],
    "sg:phone":"+1 410 825 3796",
    "sg:postcode":"21204",
    "sg:province":"MD",
    "sg:tags":[
        "telephone",
        "cellular"
    ],
    "wof:name":"Verizon Wireless",
    "wof:placetype":"venue"
},
  "geometry": {"coordinates":[-76.60154199999999,39.403782],"type":"Point"}
}