{
  "type": "Feature",
  "properties": {
    "iso:country":"US",
    "sg:address":"572 Baltimore Annapolis Blvd",
    "sg:city":"Severna Park",
    "sg:classifiers":[
        {
            "category":"Real Estate",
            "subcategory":"Real Estate Agent",
            "type":"Services"
        }
    ],
    "sg:phone":"+1 410 544 8500",
    "sg:postcode":"21146",
    "sg:province":"MD",
    "sg:website":"www.mrhelpusell.com",
    "wof:name":"Help-U-Sell Real Estate",
    "wof:placetype":"venue"
},
  "geometry": {"coordinates":[-76.54699599999999,39.072854],"type":"Point"}
}