{
  "type": "Feature",
  "properties": {
    "iso:country":"US",
    "sg:address":"6702 Lake Park Dr",
    "sg:city":"Greenbelt",
    "sg:classifiers":[
        {
            "category":"Real Estate",
            "subcategory":"Real Estate Operator",
            "type":"Services"
        }
    ],
    "sg:phone":"+1 301 552 1492",
    "sg:postcode":"20770",
    "sg:province":"MD",
    "sg:tags":[
        "condominium"
    ],
    "wof:name":"Greenbelt Lake Vlg Condominium",
    "wof:placetype":"venue"
},
  "geometry": {"coordinates":[-76.874348,38.981868],"type":"Point"}
}