{
  "type": "Feature",
  "properties": {
    "addr:full":"131 E North Ave Baltimore MD 21202",
    "addr:housenumber":"131",
    "addr:postcode":"21202",
    "addr:street":"E North Ave",
    "iso:country":"US",
    "sg:address":"131 E North Ave",
    "sg:city":"Baltimore",
    "sg:classifiers":[
        {
            "category":"Restaurant",
            "type":"Food & Drink"
        }
    ],
    "sg:phone":"+1 410 727 1918",
    "sg:postcode":"21202",
    "sg:province":"MD",
    "sg:tags":[
        "out"
    ],
    "wof:name":"Tyrone's Chicken Inc",
    "wof:placetype":"venue"
},
  "geometry": {"coordinates":[-76.614071,39.311152],"type":"Point"}
}