{
  "type": "Feature",
  "properties": {
    "addr:full":"13100 Chestnut Oak Dr Gaithersburg MD 20878",
    "addr:housenumber":"13100",
    "addr:postcode":"20878",
    "addr:street":"Chestnut Oak Dr",
    "iso:country":"US",
    "sg:address":"13100 Chestnut Oak Dr",
    "sg:city":"Gaithersburg",
    "sg:classifiers":[
        {
            "category":"Travel",
            "subcategory":"Travel Agent",
            "type":"Entertainment"
        }
    ],
    "sg:phone":"+1 301 258 1170",
    "sg:postcode":"20878",
    "sg:province":"MD",
    "sg:tags":[
        "agency"
    ],
    "wof:name":"Travel Bound Inc",
    "wof:placetype":"venue"
},
  "geometry": {"coordinates":[-77.27379999999999,39.110232],"type":"Point"}
}