{
  "type": "Feature",
  "properties": {
    "iso:country":"US",
    "sg:address":"14314 Dairydale Rd",
    "sg:city":"Baldwin",
    "sg:classifiers":[
        {
            "category":"Insurance",
            "subcategory":"Hazard Insurance",
            "type":"Services"
        }
    ],
    "sg:phone":"+1 410 592 2011",
    "sg:postcode":"21013",
    "sg:province":"MD",
    "sg:tags":[
        "commercial",
        "business"
    ],
    "wof:name":"Hudson James L Csp Ins",
    "wof:placetype":"venue"
},
  "geometry": {"coordinates":[-76.52538800000001,39.517488],"type":"Point"}
}