{
  "type": "Feature",
  "properties": {
    "addr:full":"8100 Annapolis Rd Lanham MD 20706",
    "addr:housenumber":"8100",
    "addr:postcode":"20706",
    "addr:street":"Annapolis Rd",
    "iso:country":"US",
    "sg:address":"8100 Annapolis Rd",
    "sg:city":"Lanham",
    "sg:classifiers":[
        {
            "category":"Autos & Motor Vehicles",
            "subcategory":"Automobile Sales",
            "type":"Retail Goods"
        }
    ],
    "sg:phone":"+1 301 577 6400",
    "sg:postcode":"20706",
    "sg:province":"MD",
    "wof:name":"Chrysler Plymouth Jeep",
    "wof:placetype":"venue"
},
  "geometry": {"coordinates":[-76.873904,38.955115],"type":"Point"}
}