{
  "type": "Feature",
  "properties": {
    "iso:country":"US",
    "sg:address":"3928 N Point Blvd",
    "sg:city":"Baltimore",
    "sg:classifiers":[
        {
            "category":"Retail",
            "subcategory":"Auto Rental",
            "type":"Services"
        }
    ],
    "sg:phone":"+1 410 477 3870",
    "sg:postcode":"21222",
    "sg:province":"MD",
    "sg:tags":[
        "renting",
        "automobile"
    ],
    "wof:name":"C & S Auto Rental",
    "wof:placetype":"venue"
},
  "geometry": {"coordinates":[-76.472587,39.273522],"type":"Point"}
}