{
  "type": "Feature",
  "properties": {
    "iso:country":"US",
    "sg:address":"8615 20th Ave",
    "sg:city":"Hyattsville",
    "sg:classifiers":[
        {
            "category":"Real Estate",
            "subcategory":"Real Estate Services",
            "type":"Services"
        },
        {
            "category":"Building & Trades",
            "subcategory":"Cleaning & Sanitation",
            "type":"Services"
        }
    ],
    "sg:phone":"+1 301 434 4384",
    "sg:postcode":"20783",
    "sg:province":"MD",
    "sg:tags":[
        "maintenance",
        "cleaners-interior"
    ],
    "wof:name":"Diligent Universal Maintenance",
    "wof:placetype":"venue"
},
  "geometry": {"coordinates":[-76.97408299999999,38.99815],"type":"Point"}
}