{
  "type": "Feature",
  "properties": {
    "addr:full":"3307 Greenvale Rd Pikesville MD 21208",
    "addr:housenumber":"3307",
    "addr:postcode":"21208",
    "addr:street":"Greenvale Rd",
    "iso:country":"US",
    "sg:address":"3307 Greenvale Rd",
    "sg:city":"Pikesville",
    "sg:classifiers":[
        {
            "category":"Professional",
            "subcategory":"Management & Consulting",
            "type":"Services"
        }
    ],
    "sg:phone":"+1 410 653 1415",
    "sg:postcode":"21208",
    "sg:province":"MD",
    "sg:tags":[
        "educational"
    ],
    "wof:name":"Dr Elana Rock Consulting",
    "wof:placetype":"venue"
},
  "geometry": {"coordinates":[-76.705845,39.373896],"type":"Point"}
}