{
  "type": "Feature",
  "properties": {
    "iso:country":"US",
    "sg:address":"10632 Little Patuxent Pkwy Ste 104",
    "sg:city":"Columbia",
    "sg:classifiers":[
        {
            "category":"Professional",
            "subcategory":"Lawyer & Legal Services",
            "type":"Services"
        }
    ],
    "sg:phone":"+1 410 730 4949",
    "sg:postcode":"21044",
    "sg:province":"MD",
    "sg:tags":[
        "attorney",
        "criminal",
        "law"
    ],
    "sg:website":"http://www.wiessnerlawfirm.com",
    "wof:name":"Wiessner Gary W",
    "wof:placetype":"venue"
},
  "geometry": {"coordinates":[-76.87110300000001,39.213999],"type":"Point"}
}