{
  "type": "Feature",
  "properties": {
    "addr:full":"37 Maple Ln Elkton MD 21921",
    "addr:housenumber":"37",
    "addr:postcode":"21921",
    "addr:street":"Maple Ln",
    "iso:country":"US",
    "sg:address":"37 Maple Ln",
    "sg:city":"Elkton",
    "sg:classifiers":[
        {
            "category":"Freight",
            "type":"Transportation"
        }
    ],
    "sg:phone":"+1 410 392 3622",
    "sg:postcode":"21921",
    "sg:province":"MD",
    "sg:tags":[
        "operator",
        "local",
        "trucking"
    ],
    "wof:name":"Orr Trucking Inc",
    "wof:placetype":"venue"
},
  "geometry": {"coordinates":[-75.870565,39.653368],"type":"Point"}
}