{
  "type": "Feature",
  "properties": {
    "addr:full":"9936 Reisterstown Rd Owings Mills MD 21117",
    "addr:housenumber":"9936",
    "addr:postcode":"21117",
    "addr:street":"Reisterstown Rd",
    "iso:country":"US",
    "sg:address":"9936 Reisterstown Rd",
    "sg:city":"Owings Mills",
    "sg:classifiers":[
        {
            "category":"Home & Garden",
            "subcategory":"Furniture",
            "type":"Retail Goods"
        }
    ],
    "sg:phone":"+1 410 902 9737",
    "sg:postcode":"21117",
    "sg:province":"MD",
    "sg:tags":[
        "mattress"
    ],
    "wof:name":"Jo Anne' Bed & Back Shop",
    "wof:placetype":"venue"
},
  "geometry": {"coordinates":[-76.768901,39.411225],"type":"Point"}
}