{
  "type": "Feature",
  "properties": {
    "iso:country":"US",
    "sg:address":"6717 Reisterstown Rd",
    "sg:city":"Baltimore",
    "sg:classifiers":[
        {
            "category":"Restaurant",
            "type":"Food & Drink"
        }
    ],
    "sg:menulink":"http://www.allmenus.com/md/baltimore/245362-china-star/menu/",
    "sg:phone":"+1 410 764 7819",
    "sg:postcode":"21215",
    "sg:province":"MD",
    "sg:tags":[
        "asian",
        "chinese"
    ],
    "wof:name":"China Star",
    "wof:placetype":"venue"
},
  "geometry": {"coordinates":[-76.705775,39.358792],"type":"Point"}
}