{
  "type": "Feature",
  "properties": {
    "addr:full":"582 Bellerive Rd Annapolis MD 21409",
    "addr:housenumber":"582",
    "addr:postcode":"21409",
    "addr:street":"Bellerive Rd",
    "iso:country":"US",
    "sg:address":"582 Bellerive Rd",
    "sg:city":"Annapolis",
    "sg:classifiers":[
        {
            "category":"Home & Garden",
            "subcategory":"Furniture",
            "type":"Retail Goods"
        }
    ],
    "sg:phone":"+1 410 757 0293",
    "sg:postcode":"21409",
    "sg:province":"MD",
    "sg:tags":[
        "equipment",
        "kitchen",
        "cabinet"
    ],
    "sg:website":"www.lanegroup.com",
    "wof:name":"Lane Marketing Group",
    "wof:placetype":"venue"
},
  "geometry": {"coordinates":[-76.46898899999999,39.040527],"type":"Point"}
}