{
  "type": "Feature",
  "properties": {
    "iso:country":"US",
    "sg:address":"75 Maryland Ave",
    "sg:city":"Annapolis",
    "sg:classifiers":[
        {
            "category":"Shopping",
            "subcategory":"Hobbies, Toys, & Games",
            "type":"Retail Goods"
        }
    ],
    "sg:phone":"+1 410 263 4601",
    "sg:postcode":"21401",
    "sg:province":"MD",
    "wof:name":"Merlin Trading Company",
    "wof:placetype":"venue"
},
  "geometry": {"coordinates":[-76.489786,38.979848],"type":"Point"}
}