{
  "type": "Feature",
  "properties": {
    "iso:country":"US",
    "sg:address":"206 Crabb Ave",
    "sg:city":"Rockville",
    "sg:classifiers":[
        {
            "category":"Utilities",
            "subcategory":"Telephone",
            "type":"Services"
        }
    ],
    "sg:phone":"+1 301 340 7599",
    "sg:postcode":"20850",
    "sg:province":"MD",
    "sg:tags":[
        "communications"
    ],
    "wof:name":"Domain Dlx",
    "wof:placetype":"venue"
},
  "geometry": {"coordinates":[-77.144931,39.088835],"type":"Point"}
}