{
  "type": "Feature",
  "properties": {
    "addr:full":"4131 Beachwood Rd Baltimore MD 21222",
    "addr:housenumber":"4131",
    "addr:postcode":"21222",
    "addr:street":"Beachwood Rd",
    "iso:country":"US",
    "sg:address":"4131 Beachwood Rd",
    "sg:city":"Baltimore",
    "sg:classifiers":[
        {
            "category":"Restaurant",
            "type":"Food & Drink"
        }
    ],
    "sg:phone":"+1 410 388 2240",
    "sg:postcode":"21222",
    "sg:province":"MD",
    "sg:tags":[
        "caterer"
    ],
    "wof:name":"Mr Omelette",
    "wof:placetype":"venue"
},
  "geometry": {"coordinates":[-76.454094,39.273158],"type":"Point"}
}