{
  "type": "Feature",
  "properties": {
    "iso:country":"US",
    "sg:address":"7100 Chesapeake Rd",
    "sg:city":"Hyattsville",
    "sg:classifiers":[
        {
            "category":"Personal",
            "subcategory":"Beauty Salon",
            "type":"Services"
        }
    ],
    "sg:phone":"+1 301 577 0699",
    "sg:postcode":"20784",
    "sg:province":"MD",
    "wof:name":"Heaven Hair Salon",
    "wof:placetype":"venue"
},
  "geometry": {"coordinates":[-76.88483,38.948761],"type":"Point"}
}