{
  "type": "Feature",
  "properties": {
    "addr:full":"45 Appleton Rd Elkton MD 21921",
    "addr:housenumber":"45",
    "addr:postcode":"21921",
    "addr:street":"Appleton Rd",
    "iso:country":"US",
    "sg:address":"45 Appleton Rd",
    "sg:city":"Elkton",
    "sg:classifiers":[
        {
            "category":"Building & Trades",
            "subcategory":"Construction",
            "type":"Services"
        }
    ],
    "sg:phone":"+1 410 398 0800",
    "sg:postcode":"21921",
    "sg:province":"MD",
    "sg:tags":[
        "general",
        "contractor"
    ],
    "wof:name":"Lawrence C Bathon Home Bldrs",
    "wof:placetype":"venue"
},
  "geometry": {"coordinates":[-75.826939,39.623222],"type":"Point"}
}