{
  "type": "Feature",
  "properties": {
    "iso:country":"US",
    "sg:address":"581 Stocketts Run Rd",
    "sg:city":"Davidsonville",
    "sg:classifiers":[
        {
            "category":"Building & Trades",
            "subcategory":"Construction",
            "type":"Services"
        }
    ],
    "sg:phone":"+1 410 798 1675",
    "sg:postcode":"21035",
    "sg:province":"MD",
    "sg:tags":[
        "house"
    ],
    "wof:name":"Hns Custom Homes",
    "wof:placetype":"venue"
},
  "geometry": {"coordinates":[-76.642747,38.891268],"type":"Point"}
}