{
  "type": "Feature",
  "properties": {
    "iso:country":"US",
    "sg:address":"14209 Baltimore Ave",
    "sg:city":"Laurel",
    "sg:classifiers":[
        {
            "category":"Shopping",
            "subcategory":"Music",
            "type":"Retail Goods"
        }
    ],
    "sg:phone":"+1 301 483 8145",
    "sg:postcode":"20707",
    "sg:province":"MD",
    "sg:tags":[
        "compact",
        "record",
        "game",
        "disc",
        "video",
        "tape",
        "rental"
    ],
    "wof:name":"C D Warehouse",
    "wof:placetype":"venue"
},
  "geometry": {"coordinates":[-76.861397,39.085899],"type":"Point"}
}