{
  "type": "Feature",
  "properties": {
    "addr:full":"8114 Sandpiper Cir Perry Hall MD 21128",
    "addr:housenumber":"8114",
    "addr:postcode":"21128",
    "addr:street":"Sandpiper Cir",
    "iso:country":"US",
    "sg:address":"8114 Sandpiper Cir",
    "sg:city":"Perry Hall",
    "sg:classifiers":[
        {
            "category":"Community Center",
            "type":"Public Place"
        }
    ],
    "sg:phone":"+1 410 931 6757",
    "sg:postcode":"21128",
    "sg:province":"MD",
    "sg:tags":[
        "medical"
    ],
    "sg:website":"www.questdiagnostics.com",
    "wof:name":"Quest Diagnostic Incorporated",
    "wof:placetype":"venue"
},
  "geometry": {"coordinates":[-76.44499999999999,39.4105],"type":"Point"}
}