{
  "type": "Feature",
  "properties": {
    "addr:full":"64 Acorn Cir Towson MD 21286",
    "addr:housenumber":"64",
    "addr:postcode":"21286",
    "addr:street":"Acorn Cir",
    "iso:country":"US",
    "sg:address":"64 Acorn Cir",
    "sg:city":"Towson",
    "sg:classifiers":[
        {
            "category":"Real Estate",
            "subcategory":"Real Estate Operator",
            "type":"Services"
        }
    ],
    "sg:phone":"+1 410 494 4442",
    "sg:postcode":"21286",
    "sg:province":"MD",
    "sg:tags":[
        "apartment"
    ],
    "wof:name":"Courthouse Square Apartments",
    "wof:placetype":"venue"
},
  "geometry": {"coordinates":[-76.58675100000001,39.39438],"type":"Point"}
}