{
  "type": "Feature",
  "properties": {
    "addr:full":"621 Hickory Overlook Dr Bel Air MD 21014",
    "addr:housenumber":"621",
    "addr:postcode":"21014",
    "addr:street":"Hickory Overlook Dr",
    "iso:country":"US",
    "sg:address":"621 Hickory Overlook Dr",
    "sg:city":"Bel Air",
    "sg:classifiers":[
        {
            "category":"Shopping",
            "subcategory":"Clothing, Apparel, & Fashions",
            "type":"Retail Goods"
        }
    ],
    "sg:phone":"+1 410 838 7153",
    "sg:postcode":"21014",
    "sg:province":"MD",
    "wof:name":"Brian K Murphy",
    "wof:placetype":"venue"
},
  "geometry": {"coordinates":[-76.348568,39.562845],"type":"Point"}
}