{
  "type": "Feature",
  "properties": {
    "addr:full":"285 Wilderness Rd Severna Park MD 21146",
    "addr:housenumber":"285",
    "addr:postcode":"21146",
    "addr:street":"Wilderness Rd",
    "iso:country":"US",
    "sg:address":"285 Wilderness Rd",
    "sg:city":"Severna Park",
    "sg:classifiers":[
        {
            "category":"Health Services",
            "subcategory":"Health Practitioner",
            "type":"Services"
        }
    ],
    "sg:phone":"+1 410 315 9797",
    "sg:postcode":"21146",
    "sg:province":"MD",
    "sg:tags":[
        "psychologist"
    ],
    "wof:name":"Ruth Stremberger",
    "wof:placetype":"venue"
},
  "geometry": {"coordinates":[-76.544426,39.093778],"type":"Point"}
}