{
  "type": "Feature",
  "properties": {
    "addr:full":"10412 Blackstone Ave Cheltenham MD 20623",
    "addr:housenumber":"10412",
    "addr:postcode":"20623",
    "addr:street":"Blackstone Ave",
    "iso:country":"US",
    "sg:address":"10412 Blackstone Ave",
    "sg:city":"Cheltenham",
    "sg:classifiers":[
        {
            "category":"Organizations",
            "subcategory":"Religious Organization",
            "type":"Services"
        }
    ],
    "sg:phone":"+1 301 372 0411",
    "sg:postcode":"20623",
    "sg:province":"MD",
    "wof:name":"Expressions of Faith",
    "wof:placetype":"venue"
},
  "geometry": {"coordinates":[-76.824237,38.745701],"type":"Point"}
}