{
  "type": "Feature",
  "properties": {
    "iso:country":"US",
    "sg:address":"3321 Toledo Ter Ste 101",
    "sg:city":"Hyattsville",
    "sg:classifiers":[
        {
            "category":"Professional",
            "subcategory":"Employment Agencies",
            "type":"Services"
        }
    ],
    "sg:phone":"+1 301 559 6070",
    "sg:postcode":"20782",
    "sg:province":"MD",
    "wof:name":"Phyllis Wheatley Staffing",
    "wof:placetype":"venue"
},
  "geometry": {"coordinates":[-76.961962,38.96804],"type":"Point"}
}