{
  "type": "Feature",
  "properties": {
    "iso:country":"US",
    "sg:address":"7610 Carroll Ave",
    "sg:city":"Takoma Park",
    "sg:classifiers":[
        {
            "category":"Health Services",
            "subcategory":"Doctor",
            "type":"Services"
        }
    ],
    "sg:phone":"+1 301 891 2303",
    "sg:postcode":"20912",
    "sg:province":"MD",
    "sg:tags":[
        "physician",
        "surgeon"
    ],
    "wof:name":"Kempanna Sudhakar MD",
    "wof:placetype":"venue"
},
  "geometry": {"coordinates":[-76.99875299999999,38.984666],"type":"Point"}
}