{
  "type": "Feature",
  "properties": {
    "addr:full":"8909 Old Branch Ave Clinton MD 20735",
    "addr:housenumber":"8909",
    "addr:postcode":"20735",
    "addr:street":"Old Branch Ave",
    "iso:country":"US",
    "sg:address":"8909 Old Branch Ave",
    "sg:city":"Clinton",
    "sg:classifiers":[
        {
            "category":"Wholesale",
            "subcategory":"Chemicals & Plastics",
            "type":"Manufacturing & Wholesale Goods"
        }
    ],
    "sg:phone":"+1 301 868 8079",
    "sg:postcode":"20735",
    "sg:province":"MD",
    "sg:tags":[
        "oxygen"
    ],
    "wof:name":"L & L Oxygen & Medical Equip",
    "wof:placetype":"venue"
},
  "geometry": {"coordinates":[-76.899095,38.767367],"type":"Point"}
}