{
  "type": "Feature",
  "properties": {
    "iso:country":"US",
    "sg:address":"3816 Gateway Ter",
    "sg:city":"Burtonsville",
    "sg:classifiers":[
        {
            "category":"Professional",
            "type":"Services"
        }
    ],
    "sg:phone":"+1 301 890 3968",
    "sg:postcode":"20866",
    "sg:province":"MD",
    "wof:name":"Betsy M Saunders",
    "wof:placetype":"venue"
},
  "geometry": {"coordinates":[-76.932139,39.085316],"type":"Point"}
}