{
  "type": "Feature",
  "properties": {
    "addr:full":"3816 Gateway Ter Burtonsville MD 20866",
    "addr:housenumber":"3816",
    "addr:postcode":"20866",
    "addr:street":"Gateway Ter",
    "iso:country":"US",
    "sg:address":"3816 Gateway Ter",
    "sg:city":"Burtonsville",
    "sg:classifiers":[
        {
            "category":"Professional",
            "type":"Services"
        }
    ],
    "sg:phone":"+1 301 890 3968",
    "sg:postcode":"20866",
    "sg:province":"MD",
    "wof:name":"Betsy M Saunders",
    "wof:placetype":"venue"
},
  "geometry": {"coordinates":[-76.93213900000001,39.085316],"type":"Point"}
}