{
  "type": "Feature",
  "properties": {
    "addr:full":"910 S Grundy St Baltimore MD 21224",
    "addr:housenumber":"910",
    "addr:postcode":"21224",
    "addr:street":"S Grundy St",
    "iso:country":"US",
    "sg:address":"910 S Grundy St",
    "sg:city":"Baltimore",
    "sg:classifiers":[
        {
            "category":"Manufacturing",
            "subcategory":"Retail Goods",
            "type":"Manufacturing & Wholesale Goods"
        }
    ],
    "sg:phone":"+1 410 327 6816",
    "sg:postcode":"21224",
    "sg:province":"MD",
    "sg:tags":[
        "manufacturer"
    ],
    "wof:name":"Adcor Industries",
    "wof:placetype":"venue"
},
  "geometry": {"coordinates":[-76.563115,39.281796],"type":"Point"}
}