{
  "type": "Feature",
  "properties": {
    "iso:country":"US",
    "sg:address":"20 S Mechanic St",
    "sg:city":"Cumberland",
    "sg:classifiers":[
        {
            "category":"Organizations",
            "subcategory":"Community Association",
            "type":"Services"
        }
    ],
    "sg:phone":"+1 301 724 4446",
    "sg:postcode":"21502",
    "sg:province":"MD",
    "sg:tags":[
        "club"
    ],
    "wof:name":"Ed's Canal Club",
    "wof:placetype":"venue"
},
  "geometry": {"coordinates":[-78.76269499999999,39.650687],"type":"Point"}
}