{
  "type": "Feature",
  "properties": {
    "iso:country":"US",
    "sg:address":"1002 Quebec Ter",
    "sg:city":"Silver Spring",
    "sg:classifiers":[
        {
            "category":"Real Estate",
            "subcategory":"Real Estate Operator",
            "type":"Services"
        }
    ],
    "sg:phone":"+1 301 431 4860",
    "sg:postcode":"20903",
    "sg:province":"MD",
    "sg:tags":[
        "apartment"
    ],
    "wof:name":"Carroll Apartments",
    "wof:placetype":"venue"
},
  "geometry": {"coordinates":[-76.98513699999999,39.000666],"type":"Point"}
}