{
  "type": "Feature",
  "properties": {
    "addr:full":"10255 Old Columbia Rd Columbia MD 21046",
    "addr:housenumber":"10255",
    "addr:postcode":"21046",
    "addr:street":"Old Columbia Rd",
    "iso:country":"US",
    "sg:address":"10255 Old Columbia Rd",
    "sg:city":"Columbia",
    "sg:classifiers":[
        {
            "category":"Organizations",
            "subcategory":"Religious Organization",
            "type":"Services"
        }
    ],
    "sg:phone":"+1 410 290 7156",
    "sg:postcode":"21046",
    "sg:province":"MD",
    "wof:name":"Mid Maryland Baptist Association",
    "wof:placetype":"venue"
},
  "geometry": {"coordinates":[-76.869317,39.177421],"type":"Point"}
}