{
  "type": "Feature",
  "properties": {
    "addr:full":"660 Marley Run Huntingtown MD 20639",
    "addr:housenumber":"660",
    "addr:postcode":"20639",
    "addr:street":"Marley Run",
    "iso:country":"US",
    "sg:address":"660 Marley Run",
    "sg:city":"Huntingtown",
    "sg:classifiers":[
        {
            "category":"Building & Trades",
            "subcategory":"Construction",
            "type":"Services"
        },
        {
            "category":"Manufacturing",
            "subcategory":"Building Materials",
            "type":"Manufacturing & Wholesale Goods"
        }
    ],
    "sg:phone":"+1 410 414 3299",
    "sg:postcode":"20639",
    "sg:province":"MD",
    "sg:tags":[
        "roofing",
        "sheet",
        "work",
        "metal",
        "contractor",
        "siding"
    ],
    "wof:name":"Ras Contracting",
    "wof:placetype":"venue"
},
  "geometry": {"coordinates":[-76.59488,38.608023],"type":"Point"}
}