{
  "type": "Feature",
  "properties": {
    "addr:full":"306 Glyndon Mews Ct Reisterstown MD 21136",
    "addr:housenumber":"306",
    "addr:postcode":"21136",
    "addr:street":"Glyndon Mews Ct",
    "iso:country":"US",
    "sg:address":"306 Glyndon Mews Ct",
    "sg:city":"Reisterstown",
    "sg:classifiers":[
        {
            "category":"Professional",
            "subcategory":"Art Services",
            "type":"Services"
        }
    ],
    "sg:phone":"+1 410 833 7869",
    "sg:postcode":"21136",
    "sg:province":"MD",
    "sg:tags":[
        "commercial",
        "design"
    ],
    "wof:name":"Pumpkin Feather Designs",
    "wof:placetype":"venue"
},
  "geometry": {"coordinates":[-76.810042,39.472608],"type":"Point"}
}