{
  "type": "Feature",
  "properties": {
    "iso:country":"US",
    "sg:address":"4300 Crest Heights Rd",
    "sg:city":"Baltimore",
    "sg:classifiers":[
        {
            "category":"Social Services",
            "subcategory":"Child Care",
            "type":"Services"
        }
    ],
    "sg:phone":"+1 410 653 7625",
    "sg:postcode":"21215",
    "sg:province":"MD",
    "sg:tags":[
        "day"
    ],
    "wof:name":"Reaching Our Community Kids Inc",
    "wof:placetype":"venue"
},
  "geometry": {"coordinates":[-76.71295000000001,39.359905],"type":"Point"}
}