{
  "type": "Feature",
  "properties": {
    "addr:full":"12301 Old Columbia Pike Ste 200 Silver Spring MD 20904",
    "addr:housenumber":"12301",
    "addr:postcode":"20904",
    "addr:street":"Old Columbia Pike Ste 200",
    "iso:country":"US",
    "sg:address":"12301 Old Columbia Pike Ste 200",
    "sg:city":"Silver Spring",
    "sg:classifiers":[
        {
            "category":"Banks & Credit Unions",
            "subcategory":"Financial Services",
            "type":"Services"
        }
    ],
    "sg:phone":"+1 240 482 1050",
    "sg:postcode":"20904",
    "sg:province":"MD",
    "sg:tags":[
        "broker",
        "mortgage"
    ],
    "wof:name":"Bogman Incorporated",
    "wof:placetype":"venue"
},
  "geometry": {"coordinates":[-76.968102,39.057598],"type":"Point"}
}