{
  "type": "Feature",
  "properties": {
    "iso:country":"US",
    "sg:address":"6217 Baltimore Natinl Pke",
    "sg:city":"Catonsville",
    "sg:classifiers":[
        {
            "category":"Sports & Exercise",
            "subcategory":"Bicycle Rental",
            "type":"Entertainment"
        }
    ],
    "sg:phone":"+1 410 744 9629",
    "sg:postcode":"21228",
    "sg:province":"MD",
    "sg:tags":[
        "wear"
    ],
    "wof:name":"Casual Male Big and Tall",
    "wof:placetype":"venue"
},
  "geometry": {"coordinates":[-76.750702,39.283401],"type":"Point"}
}