{
  "type": "Feature",
  "properties": {
    "iso:country":"US",
    "sg:address":"3301 Clarks Ln",
    "sg:city":"Baltimore",
    "sg:classifiers":[
        {
            "category":"Real Estate",
            "subcategory":"Real Estate Operator",
            "type":"Services"
        }
    ],
    "sg:phone":"+1 410 764 1117",
    "sg:postcode":"21215",
    "sg:province":"MD",
    "sg:tags":[
        "apartment"
    ],
    "wof:name":"Cross Country Manor Apartments",
    "wof:placetype":"venue"
},
  "geometry": {"coordinates":[-76.69528699999999,39.367275],"type":"Point"}
}