{
  "type": "Feature",
  "properties": {
    "addr:full":"2323 Orleans St Baltimore MD 21224",
    "addr:housenumber":"2323",
    "addr:postcode":"21224",
    "addr:street":"Orleans St",
    "iso:country":"US",
    "sg:address":"2323 Orleans St",
    "sg:city":"Baltimore",
    "sg:classifiers":[
        {
            "category":"Health Services",
            "subcategory":"Doctor",
            "type":"Services"
        }
    ],
    "sg:phone":"+1 410 558 4717",
    "sg:postcode":"21224",
    "sg:province":"MD",
    "sg:tags":[
        "physician",
        "surgeon"
    ],
    "wof:name":"Shanti Ramesh MD",
    "wof:placetype":"venue"
},
  "geometry": {"coordinates":[-76.583612,39.295499],"type":"Point"}
}