{
  "type": "Feature",
  "properties": {
    "addr:full":"121 Archer St Bel Air MD 21014",
    "addr:housenumber":"121",
    "addr:postcode":"21014",
    "addr:street":"Archer St",
    "iso:country":"US",
    "sg:address":"121 Archer St",
    "sg:city":"Bel Air",
    "sg:classifiers":[
        {
            "category":"Professional",
            "subcategory":"Lawyer & Legal Services",
            "type":"Services"
        }
    ],
    "sg:phone":"+1 410 893 9111",
    "sg:postcode":"21014",
    "sg:province":"MD",
    "sg:tags":[
        "attorney"
    ],
    "wof:name":"Wagner & Schaech Pa LAW",
    "wof:placetype":"venue"
},
  "geometry": {"coordinates":[-76.351111,39.532567],"type":"Point"}
}