{
  "type": "Feature",
  "properties": {
    "iso:country":"US",
    "sg:address":"6551 Woodgreen Cir",
    "sg:city":"Baltimore",
    "sg:classifiers":[
        {
            "category":"Manufacturing",
            "subcategory":"Food",
            "type":"Manufacturing & Wholesale Goods"
        }
    ],
    "sg:phone":"+1 410 265 8585",
    "sg:postcode":"21207",
    "sg:province":"MD",
    "sg:tags":[
        "bottler"
    ],
    "wof:name":"A & S Wholesalers",
    "wof:placetype":"venue"
},
  "geometry": {"coordinates":[-76.72734199999999,39.333053],"type":"Point"}
}