{
  "type": "Feature",
  "properties": {
    "addr:full":"5517 Spruce Tree Ave Bethesda MD 20814",
    "addr:housenumber":"5517",
    "addr:postcode":"20814",
    "addr:street":"Spruce Tree Ave",
    "iso:country":"US",
    "sg:address":"5517 Spruce Tree Ave",
    "sg:city":"Bethesda",
    "sg:classifiers":[
        {
            "category":"Professional",
            "subcategory":"Management & Consulting",
            "type":"Services"
        }
    ],
    "sg:phone":"+1 301 493 6778",
    "sg:postcode":"20814",
    "sg:province":"MD",
    "sg:tags":[
        "consultant",
        "educational"
    ],
    "wof:name":"Roxanne E Fischer",
    "wof:placetype":"venue"
},
  "geometry": {"coordinates":[-77.11313699999999,39.008896],"type":"Point"}
}