{
  "type": "Feature",
  "properties": {
    "iso:country":"US",
    "sg:address":"3103 Windsor Ave",
    "sg:city":"Baltimore",
    "sg:classifiers":[
        {
            "category":"Real Estate",
            "subcategory":"Real Estate Operator",
            "type":"Services"
        }
    ],
    "sg:phone":"+1 410 944 1300",
    "sg:postcode":"21216",
    "sg:province":"MD",
    "sg:tags":[
        "apartment"
    ],
    "wof:name":"Town & Country Management Company the",
    "wof:placetype":"venue"
},
  "geometry": {"coordinates":[-76.67004300000001,39.31199],"type":"Point"}
}