{
  "type": "Feature",
  "properties": {
    "iso:country":"US",
    "sg:address":"2019 E Pratt St",
    "sg:city":"Baltimore",
    "sg:classifiers":[
        {
            "category":"Real Estate",
            "subcategory":"Real Estate Services",
            "type":"Services"
        },
        {
            "category":"Real Estate",
            "subcategory":"Real Estate Agent",
            "type":"Services"
        }
    ],
    "sg:phone":"+1 410 563 4040",
    "sg:postcode":"21231",
    "sg:province":"MD",
    "sg:tags":[
        "buyer",
        "broker"
    ],
    "wof:name":"Platinum Realty Group",
    "wof:placetype":"venue"
},
  "geometry": {"coordinates":[-76.58805099999999,39.289478],"type":"Point"}
}