{
  "type": "Feature",
  "properties": {
    "iso:country":"US",
    "sg:address":"40255 Beach Dr",
    "sg:city":"Mechanicsville",
    "sg:classifiers":[
        {
            "category":"Retail",
            "subcategory":"Repair Shop",
            "type":"Services"
        }
    ],
    "sg:phone":"+1 301 884 8271",
    "sg:postcode":"20659",
    "sg:province":"MD",
    "sg:tags":[
        "caning",
        "supply"
    ],
    "wof:name":"Fw Schoenbauer Furniture Repair Inc",
    "wof:placetype":"venue"
},
  "geometry": {"coordinates":[-76.682925,38.483879],"type":"Point"}
}