{
  "type": "Feature",
  "properties": {
    "addr:full":"711 Eastern Ave Baltimore MD 21202",
    "addr:housenumber":"711",
    "addr:postcode":"21202",
    "addr:street":"Eastern Ave",
    "iso:country":"US",
    "sg:address":"711 Eastern Ave",
    "sg:city":"Baltimore",
    "sg:classifiers":[
        {
            "category":"Restaurant",
            "type":"Food & Drink"
        }
    ],
    "sg:phone":"+1 410 230 0033",
    "sg:postcode":"21202",
    "sg:province":"MD",
    "sg:tags":[
        "house",
        "dining",
        "american",
        "steakhouse",
        "steak",
        "fine"
    ],
    "sg:website":"www.ruthschris-pier5.com",
    "wof:name":"Ruth's Chris Steak House",
    "wof:placetype":"venue"
},
  "geometry": {"coordinates":[-76.605628,39.284772],"type":"Point"}
}