{
  "type": "Feature",
  "properties": {
    "addr:full":"2127 Boston St Baltimore MD 21231",
    "addr:housenumber":"2127",
    "addr:postcode":"21231",
    "addr:street":"Boston St",
    "iso:country":"US",
    "sg:address":"2127 Boston St",
    "sg:city":"Baltimore",
    "sg:classifiers":[
        {
            "category":"Restaurant",
            "type":"Food & Drink"
        }
    ],
    "sg:menulink":"http://www.allmenus.com/md/baltimore/245522-bayview/menu/",
    "sg:phone":"+1 410 327 2411",
    "sg:postcode":"21231",
    "sg:province":"MD",
    "sg:tags":[
        "italian",
        "seafood",
        "sandwich",
        "american",
        "pizza"
    ],
    "wof:name":"Bayview",
    "wof:placetype":"venue"
},
  "geometry": {"coordinates":[-76.58661499999999,39.284417],"type":"Point"}
}