{
  "type": "Feature",
  "properties": {
    "iso:country":"US",
    "sg:address":"205 Raccoon Run Ct",
    "sg:city":"Hanover",
    "sg:classifiers":[
        {
            "category":"Building & Trades",
            "subcategory":"Construction",
            "type":"Services"
        }
    ],
    "sg:phone":"+1 410 519 7877",
    "sg:postcode":"21076",
    "sg:province":"MD",
    "sg:tags":[
        "system",
        "contractor",
        "air conditioning"
    ],
    "wof:name":"Dino's Heating & Cooling",
    "wof:placetype":"venue"
},
  "geometry": {"coordinates":[-76.726805,39.143002],"type":"Point"}
}