{
  "type": "Feature",
  "properties": {
    "iso:country":"US",
    "sg:address":"120 E Oak Ridge Dr",
    "sg:city":"Hagerstown",
    "sg:classifiers":[
        {
            "category":"Insurance",
            "subcategory":"Insurance Agent",
            "type":"Services"
        }
    ],
    "sg:phone":"+1 301 733 0895",
    "sg:postcode":"21740",
    "sg:province":"MD",
    "wof:name":"Antietam Insurance Assoc",
    "wof:placetype":"venue"
},
  "geometry": {"coordinates":[-77.726294,39.61209],"type":"Point"}
}