{
  "type": "Feature",
  "properties": {
    "addr:full":"712 Murdock Rd Baltimore MD 21212",
    "addr:housenumber":"712",
    "addr:postcode":"21212",
    "addr:street":"Murdock Rd",
    "iso:country":"US",
    "sg:address":"712 Murdock Rd",
    "sg:city":"Baltimore",
    "sg:classifiers":[
        {
            "category":"Professional",
            "subcategory":"Advertising",
            "type":"Services"
        }
    ],
    "sg:phone":"+1 410 337 3555",
    "sg:postcode":"21212",
    "sg:province":"MD",
    "wof:name":"Cycling East",
    "wof:placetype":"venue"
},
  "geometry": {"coordinates":[-76.599193,39.376206],"type":"Point"}
}