{
  "type": "Feature",
  "properties": {
    "addr:full":"7840 Briardale Ter Rockville MD 20855",
    "addr:housenumber":"7840",
    "addr:postcode":"20855",
    "addr:street":"Briardale Ter",
    "iso:country":"US",
    "sg:address":"7840 Briardale Ter",
    "sg:city":"Rockville",
    "sg:classifiers":[
        {
            "category":"Banks & Credit Unions",
            "subcategory":"Investment Brokerage",
            "type":"Services"
        }
    ],
    "sg:phone":"+1 240 631 7920",
    "sg:postcode":"20855",
    "sg:province":"MD",
    "sg:tags":[
        "consultant",
        "planning",
        "financial"
    ],
    "wof:name":"American Express Financial Adv",
    "wof:placetype":"venue"
},
  "geometry": {"coordinates":[-77.160676,39.132591],"type":"Point"}
}