{
  "type": "Feature",
  "properties": {
    "iso:country":"US",
    "sg:address":"2710 Fox St",
    "sg:city":"Baltimore",
    "sg:classifiers":[
        {
            "category":"Building & Trades",
            "subcategory":"Construction",
            "type":"Services"
        }
    ],
    "sg:phone":"+1 410 337 8774",
    "sg:postcode":"21211",
    "sg:province":"MD",
    "sg:tags":[
        "wallcoverings-installation",
        "wallpaper",
        "painter"
    ],
    "sg:website":"http://www.rhfewsterpainting.com",
    "wof:name":"R H Fewster Painting",
    "wof:placetype":"venue"
},
  "geometry": {"coordinates":[-76.62145099999999,39.32017],"type":"Point"}
}