{
  "type": "Feature",
  "properties": {
    "iso:country":"US",
    "sg:address":"12627 Belair Rd",
    "sg:city":"Kingsville",
    "sg:classifiers":[
        {
            "category":"Bars & Pubs",
            "type":"Food & Drink"
        },
        {
            "category":"Restaurant",
            "type":"Food & Drink"
        },
        {
            "category":"Bars & Pubs",
            "subcategory":"Lounge",
            "type":"Food & Drink"
        }
    ],
    "sg:phone":"+1 410 510 7193",
    "sg:postcode":"21087",
    "sg:province":"MD",
    "sg:tags":[
        "cocktail"
    ],
    "wof:name":"Horse-U Pub",
    "wof:placetype":"venue"
},
  "geometry": {"coordinates":[-76.410252,39.468839],"type":"Point"}
}