{
  "type": "Feature",
  "properties": {
    "addr:full":"22004 Valley Estate Dr Lexington Park MD 20653",
    "addr:housenumber":"22004",
    "addr:postcode":"20653",
    "addr:street":"Valley Estate Dr",
    "iso:country":"US",
    "sg:address":"22004 Valley Estate Dr",
    "sg:city":"Lexington Park",
    "sg:classifiers":[
        {
            "category":"Shopping",
            "subcategory":"Computers & Home Electronics",
            "type":"Retail Goods"
        }
    ],
    "sg:phone":"+1 301 737 4318",
    "sg:postcode":"20653",
    "sg:province":"MD",
    "sg:tags":[
        "equipment",
        "electrical"
    ],
    "wof:name":"D K Enterprises",
    "wof:placetype":"venue"
},
  "geometry": {"coordinates":[-76.463173,38.272178],"type":"Point"}
}