{
  "type": "Feature",
  "properties": {
    "iso:country":"US",
    "sg:address":"651 Great Falls Rd",
    "sg:city":"Rockville",
    "sg:classifiers":[
        {
            "category":"Government",
            "subcategory":"Office",
            "type":"Public Place"
        }
    ],
    "sg:phone":"+1 301 279 3929",
    "sg:postcode":"20850",
    "sg:province":"MD",
    "sg:tags":[
        "county"
    ],
    "wof:name":"Montgomery County Public",
    "wof:placetype":"venue"
},
  "geometry": {"coordinates":[-77.162794,39.075795],"type":"Point"}
}