{
  "type": "Feature",
  "properties": {
    "addr:full":"6051 Belle Grove Rd Baltimore MD 21225",
    "addr:housenumber":"6051",
    "addr:postcode":"21225",
    "addr:street":"Belle Grove Rd",
    "iso:country":"US",
    "sg:address":"6051 Belle Grove Rd",
    "sg:city":"Baltimore",
    "sg:classifiers":[
        {
            "category":"Taxi",
            "type":"Transportation"
        },
        {
            "category":"Retail",
            "subcategory":"Auto Repair",
            "type":"Services"
        }
    ],
    "sg:phone":"+1 410 609 1200",
    "sg:postcode":"21225",
    "sg:province":"MD",
    "wof:name":"Yellow Cab of AA County",
    "wof:placetype":"venue"
},
  "geometry": {"coordinates":[-76.643111,39.216614],"type":"Point"}
}