{
  "type": "Feature",
  "properties": {
    "addr:full":"9811 Washingtonian Blvd Gaithersburg MD 20878",
    "addr:housenumber":"9811",
    "addr:postcode":"20878",
    "addr:street":"Washingtonian Blvd",
    "iso:country":"US",
    "sg:address":"9811 Washingtonian Blvd",
    "sg:city":"Gaithersburg",
    "sg:classifiers":[
        {
            "category":"Health Services",
            "subcategory":"Doctor",
            "type":"Services"
        }
    ],
    "sg:phone":"+1 301 657 9876",
    "sg:postcode":"20878",
    "sg:province":"MD",
    "sg:tags":[
        "physician",
        "surgeon"
    ],
    "wof:name":"Metro Orthopedics & Sports",
    "wof:placetype":"venue"
},
  "geometry": {"coordinates":[-77.201279,39.116898],"type":"Point"}
}