{
  "type": "Feature",
  "properties": {
    "addr:full":"1407 West Rd Salisbury MD 21801",
    "addr:housenumber":"1407",
    "addr:postcode":"21801",
    "addr:street":"West Rd",
    "iso:country":"US",
    "sg:address":"1407 West Rd",
    "sg:city":"Salisbury",
    "sg:classifiers":[
        {
            "category":"Place Of Worship",
            "type":"Public Place"
        }
    ],
    "sg:phone":"+1 443 813 8406",
    "sg:postcode":"21801",
    "sg:province":"MD",
    "sg:tags":[
        "church"
    ],
    "wof:name":"Jireh, Inc.",
    "wof:placetype":"venue"
},
  "geometry": {"coordinates":[-75.611284,38.390363],"type":"Point"}
}