{
  "type": "Feature",
  "properties": {
    "iso:country":"US",
    "sg:address":"9803 Lundy Ct",
    "sg:city":"Lanham",
    "sg:classifiers":[
        {
            "category":"Professional",
            "subcategory":"Business Services",
            "type":"Services"
        }
    ],
    "sg:phone":"+1 301 459 0655",
    "sg:postcode":"20706",
    "sg:province":"MD",
    "wof:name":"Mr Fizz Refreshment Centers",
    "wof:placetype":"venue"
},
  "geometry": {"coordinates":[-76.836562,38.971696],"type":"Point"}
}