{
  "type": "Feature",
  "properties": {
    "addr:full":"1900 Lansdowne Rd Halethorpe MD 21227",
    "addr:housenumber":"1900",
    "addr:postcode":"21227",
    "addr:street":"Lansdowne Rd",
    "iso:country":"US",
    "sg:address":"1900 Lansdowne Rd",
    "sg:city":"Halethorpe",
    "sg:classifiers":[
        {
            "category":"Wholesale",
            "subcategory":"Construction Materials",
            "type":"Manufacturing & Wholesale Goods"
        }
    ],
    "sg:phone":"+1 410 737 9020",
    "sg:postcode":"21227",
    "sg:province":"MD",
    "sg:tags":[
        "marble"
    ],
    "wof:name":"Milestone Granite & Marble LLC",
    "wof:placetype":"venue"
},
  "geometry": {"coordinates":[-76.667745,39.25313],"type":"Point"}
}