{
  "type": "Feature",
  "properties": {
    "addr:full":"24 S Centre St Cumberland MD 21502",
    "addr:housenumber":"24",
    "addr:postcode":"21502",
    "addr:street":"S Centre St",
    "iso:country":"US",
    "sg:address":"24 S Centre St",
    "sg:city":"Cumberland",
    "sg:classifiers":[
        {
            "category":"Health Services",
            "subcategory":"Doctor",
            "type":"Services"
        }
    ],
    "sg:phone":"+1 301 759 9953",
    "sg:postcode":"21502",
    "sg:province":"MD",
    "sg:tags":[
        "physician",
        "surgeon"
    ],
    "wof:name":"C&P Tel Co Of Md",
    "wof:placetype":"venue"
},
  "geometry": {"coordinates":[-78.76091700000001,39.651201],"type":"Point"}
}