{
  "type": "Feature",
  "properties": {
    "addr:full":"38 Rising Sun Town Center Rising Sun MD 21911",
    "addr:housenumber":"38",
    "addr:postcode":"21911",
    "addr:street":"Rising Sun",
    "iso:country":"US",
    "sg:address":"38 Rising Sun Town Center",
    "sg:city":"Rising Sun",
    "sg:classifiers":[
        {
            "category":"Restaurant",
            "type":"Food & Drink"
        }
    ],
    "sg:phone":"+1 410 658 8088",
    "sg:postcode":"21911",
    "sg:province":"MD",
    "wof:name":"Pizza Boy",
    "wof:placetype":"venue"
},
  "geometry": {"coordinates":[-76.057298,39.698118],"type":"Point"}
}