{
  "type": "Feature",
  "properties": {
    "addr:full":"4317 Buckeystown Pike Frederick MD 21704",
    "addr:housenumber":"4317",
    "addr:postcode":"21704",
    "addr:street":"Buckeystown Pike",
    "iso:country":"US",
    "sg:address":"4317 Buckeystown Pike",
    "sg:city":"Frederick",
    "sg:classifiers":[
        {
            "category":"Real Estate",
            "subcategory":"Real Estate Agent",
            "type":"Services"
        }
    ],
    "sg:phone":"+1 301 874 5300",
    "sg:postcode":"21704",
    "sg:province":"MD",
    "wof:name":"RBA Realty",
    "wof:placetype":"venue"
},
  "geometry": {"coordinates":[-77.423574,39.352624],"type":"Point"}
}