{
  "type": "Feature",
  "properties": {
    "addr:full":"8653 Zetts Ave Gaithersburg MD 20877",
    "addr:housenumber":"8653",
    "addr:postcode":"20877",
    "addr:street":"Zetts Ave",
    "iso:country":"US",
    "sg:address":"8653 Zetts Ave",
    "sg:city":"Gaithersburg",
    "sg:classifiers":[
        {
            "category":"Utilities",
            "subcategory":"Mobile Phone",
            "type":"Services"
        }
    ],
    "sg:phone":"+1 301 926 7920",
    "sg:postcode":"20877",
    "sg:province":"MD",
    "sg:tags":[
        "telephone",
        "cellular"
    ],
    "wof:name":"Unlimited Wireless Inc",
    "wof:placetype":"venue"
},
  "geometry": {"coordinates":[-77.178167,39.121127],"type":"Point"}
}