{
  "type": "Feature",
  "properties": {
    "addr:full":"14 Goodport Ln Gaithersburg MD 20878",
    "addr:housenumber":"14",
    "addr:postcode":"20878",
    "addr:street":"Goodport Ln",
    "iso:country":"US",
    "sg:address":"14 Goodport Ln",
    "sg:city":"Gaithersburg",
    "sg:classifiers":[
        {
            "category":"Professional",
            "subcategory":"Management & Consulting",
            "type":"Services"
        }
    ],
    "sg:phone":"+1 301 208 8568",
    "sg:postcode":"20878",
    "sg:province":"MD",
    "sg:tags":[
        "business"
    ],
    "wof:name":"Typecasting",
    "wof:placetype":"venue"
},
  "geometry": {"coordinates":[-77.236445,39.151961],"type":"Point"}
}