{
  "type": "Feature",
  "properties": {
    "iso:country":"US",
    "sg:address":"108 Diener Pl Apt 103",
    "sg:city":"Baltimore",
    "sg:classifiers":[
        {
            "category":"Real Estate",
            "subcategory":"Real Estate Operator",
            "type":"Services"
        }
    ],
    "sg:phone":"+1 410 644 8300",
    "sg:postcode":"21229",
    "sg:province":"MD",
    "sg:tags":[
        "apartment"
    ],
    "wof:name":"Woodington Garden Apartments",
    "wof:placetype":"venue"
},
  "geometry": {"coordinates":[-76.6875,39.282501],"type":"Point"}
}