{
  "type": "Feature",
  "properties": {
    "iso:country":"US",
    "sg:address":"3511 Alameda Cir",
    "sg:city":"Baltimore",
    "sg:classifiers":[
        {
            "category":"Travel",
            "subcategory":"Travel Agent",
            "type":"Entertainment"
        }
    ],
    "sg:phone":"+1 410 366 4764",
    "sg:postcode":"21218",
    "sg:province":"MD",
    "sg:tags":[
        "agency",
        "services-commercial"
    ],
    "wof:name":"Easter Travel",
    "wof:placetype":"venue"
},
  "geometry": {"coordinates":[-76.59277400000001,39.330935],"type":"Point"}
}