{
  "type": "Feature",
  "properties": {
    "iso:country":"US",
    "sg:address":"1450 W Montgomery Ave",
    "sg:city":"Rockville",
    "sg:classifiers":[
        {
            "category":"Organizations",
            "subcategory":"Religious Organization",
            "type":"Services"
        }
    ],
    "sg:phone":"+1 301 279 7977",
    "sg:postcode":"20850",
    "sg:province":"MD",
    "wof:name":"Rockville Church of Christ",
    "wof:placetype":"venue"
},
  "geometry": {"coordinates":[-77.182743,39.092336],"type":"Point"}
}