{
  "type": "Feature",
  "properties": {
    "iso:country":"US",
    "sg:address":"16 S Aurora St",
    "sg:city":"Easton",
    "sg:classifiers":[
        {
            "category":"Retail",
            "subcategory":"Self-service Laundry",
            "type":"Services"
        }
    ],
    "sg:phone":"+1 410 822 7490",
    "sg:postcode":"21601",
    "sg:province":"MD",
    "wof:name":"Colonial Laundry & Dry Cleaner",
    "wof:placetype":"venue"
},
  "geometry": {"coordinates":[-76.071377,38.773366],"type":"Point"}
}