{
  "type": "Feature",
  "properties": {
    "addr:full":"8515 River Park Rd Bowie MD 20715",
    "addr:housenumber":"8515",
    "addr:postcode":"20715",
    "addr:street":"River Park Rd",
    "iso:country":"US",
    "sg:address":"8515 River Park Rd",
    "sg:city":"Bowie",
    "sg:classifiers":[
        {
            "category":"Wholesale",
            "subcategory":"Home Furnishings",
            "type":"Manufacturing & Wholesale Goods"
        }
    ],
    "sg:phone":"+1 301 805 6555",
    "sg:postcode":"20715",
    "sg:province":"MD",
    "wof:name":"C and S Remodelyng",
    "wof:placetype":"venue"
},
  "geometry": {"coordinates":[-76.74972699999999,39.002585],"type":"Point"}
}