{
  "type": "Feature",
  "properties": {
    "iso:country":"US",
    "sg:address":"1116 W Joppa Rd",
    "sg:city":"Baltimore",
    "sg:classifiers":[
        {
            "category":"Professional",
            "subcategory":"Business Services",
            "type":"Services"
        }
    ],
    "sg:phone":"+1 410 321 0488",
    "sg:postcode":"21204",
    "sg:province":"MD",
    "wof:name":"S2 Solutions Inc",
    "wof:placetype":"venue"
},
  "geometry": {"coordinates":[-76.6277,39.411228],"type":"Point"}
}