{
  "type": "Feature",
  "properties": {
    "iso:country":"US",
    "sg:address":"5602 Baltimore National Pike",
    "sg:city":"Catonsville",
    "sg:classifiers":[
        {
            "category":"Shopping",
            "subcategory":"Pharmacy",
            "type":"Retail Goods"
        }
    ],
    "sg:phone":"+1 443 830 1982",
    "sg:postcode":"21228",
    "sg:province":"MD",
    "wof:name":"Medmerica Pharmacy",
    "wof:placetype":"venue"
},
  "geometry": {"coordinates":[-76.727074,39.289299],"type":"Point"}
}