{
  "type": "Feature",
  "properties": {
    "addr:full":"1704 Farmshire Ct Jarrettsville MD 21084",
    "addr:housenumber":"1704",
    "addr:postcode":"21084",
    "addr:street":"Farmshire Ct",
    "iso:country":"US",
    "sg:address":"1704 Farmshire Ct",
    "sg:city":"Jarrettsville",
    "sg:classifiers":[
        {
            "category":"Wholesale",
            "subcategory":"Electrical",
            "type":"Manufacturing & Wholesale Goods"
        }
    ],
    "sg:phone":"+1 410 557 4352",
    "sg:postcode":"21084",
    "sg:province":"MD",
    "sg:tags":[
        "battery"
    ],
    "wof:name":"Friemann & Wolf",
    "wof:placetype":"venue"
},
  "geometry": {"coordinates":[-76.466836,39.597053],"type":"Point"}
}