{
  "type": "Feature",
  "properties": {
    "iso:country":"US",
    "sg:address":"826 Mayo Rd",
    "sg:city":"Edgewater",
    "sg:classifiers":[
        {
            "category":"Shopping",
            "subcategory":"Bicycles & Sporting Goods",
            "type":"Retail Goods"
        }
    ],
    "sg:phone":"+1 410 798 5767",
    "sg:postcode":"21037",
    "sg:province":"MD",
    "sg:tags":[
        "bait",
        "fishing"
    ],
    "wof:name":"Peninsula Farms",
    "wof:placetype":"venue"
},
  "geometry": {"coordinates":[-76.527864,38.906075],"type":"Point"}
}