{
  "type": "Feature",
  "properties": {
    "iso:country":"US",
    "sg:address":"914 Valley Rd",
    "sg:city":"Knoxville",
    "sg:classifiers":[
        {
            "category":"Professional",
            "subcategory":"Lawyer & Legal Services",
            "type":"Services"
        }
    ],
    "sg:phone":"+1 301 834 9079",
    "sg:postcode":"21758",
    "sg:province":"MD",
    "wof:name":"Roger Wolf",
    "wof:placetype":"venue"
},
  "geometry": {"coordinates":[-77.697101,39.33964],"type":"Point"}
}