{
  "type": "Feature",
  "properties": {
    "iso:country":"US",
    "sg:address":"908 Commerce Rd",
    "sg:city":"Annapolis",
    "sg:classifiers":[
        {
            "category":"Real Estate",
            "subcategory":"Real Estate Agent",
            "type":"Services"
        }
    ],
    "sg:phone":"+1 301 970 2300",
    "sg:postcode":"21401",
    "sg:province":"MD",
    "sg:tags":[
        "appraiser"
    ],
    "sg:website":"www.staplesappraisers.com",
    "wof:name":"Glenn B Staples & Assoc Inc",
    "wof:placetype":"venue"
},
  "geometry": {"coordinates":[-76.545632,38.994417],"type":"Point"}
}