{
  "type": "Feature",
  "properties": {
    "addr:full":"5728 Crain Hwy Upper Marlboro MD 20772",
    "addr:housenumber":"5728",
    "addr:postcode":"20772",
    "addr:street":"Crain Hwy",
    "iso:country":"US",
    "sg:address":"5728 Crain Hwy",
    "sg:city":"Upper Marlboro",
    "sg:classifiers":[
        {
            "category":"Restaurant",
            "type":"Food & Drink"
        }
    ],
    "sg:phone":"+1 301 574 3200",
    "sg:postcode":"20772",
    "sg:province":"MD",
    "wof:name":"Hong Kong Taste",
    "wof:placetype":"venue"
},
  "geometry": {"coordinates":[-76.740577,38.809211],"type":"Point"}
}