{
  "type": "Feature",
  "properties": {
    "addr:full":"202 Hodges Ln Takoma Park MD 20912",
    "addr:housenumber":"202",
    "addr:postcode":"20912",
    "addr:street":"Hodges Ln",
    "iso:country":"US",
    "sg:address":"202 Hodges Ln",
    "sg:city":"Takoma Park",
    "sg:classifiers":[
        {
            "category":"Shopping",
            "subcategory":"Computers & Home Electronics",
            "type":"Retail Goods"
        }
    ],
    "sg:phone":"+1 301 589 5574",
    "sg:postcode":"20912",
    "sg:province":"MD",
    "sg:tags":[
        "software"
    ],
    "wof:name":"Software Engineering Resources",
    "wof:placetype":"venue"
},
  "geometry": {"coordinates":[-77.01293200000001,38.983138],"type":"Point"}
}