{
  "type": "Feature",
  "properties": {
    "iso:country":"US",
    "sg:address":"19 W Pennsylvania Ave Ste 1",
    "sg:city":"Towson",
    "sg:classifiers":[
        {
            "category":"Banks & Credit Unions",
            "subcategory":"Bank",
            "type":"Services"
        },
        {
            "category":"Banks & Credit Unions",
            "subcategory":"Financial Services",
            "type":"Services"
        }
    ],
    "sg:phone":"+1 410 823 4800",
    "sg:postcode":"21204",
    "sg:province":"MD",
    "sg:tags":[
        "loan",
        "saving",
        "mortgage"
    ],
    "sg:website":"http://www.hamiltonfsb.com",
    "wof:name":"Hamilton Federal Bank",
    "wof:placetype":"venue"
},
  "geometry": {"coordinates":[-76.602937,39.400524],"type":"Point"}
}