{
  "type": "Feature",
  "properties": {
    "addr:full":"11907 Colin Rd Silver Spring MD 20906",
    "addr:housenumber":"11907",
    "addr:postcode":"20906",
    "addr:street":"Colin Rd",
    "iso:country":"US",
    "sg:address":"11907 Colin Rd",
    "sg:city":"Silver Spring",
    "sg:classifiers":[
        {
            "category":"Arts & Performance",
            "subcategory":"Theater",
            "type":"Entertainment"
        }
    ],
    "sg:phone":"+1 301 949 6842",
    "sg:postcode":"20906",
    "sg:province":"MD",
    "sg:tags":[
        "theatrical"
    ],
    "wof:name":"John K Gabbert",
    "wof:placetype":"venue"
},
  "geometry": {"coordinates":[-77.08712300000001,39.052192],"type":"Point"}
}