{
  "type": "Feature",
  "properties": {
    "iso:country":"US",
    "sg:address":"117 Jones Pl",
    "sg:city":"Chester",
    "sg:classifiers":[
        {
            "category":"Home & Garden",
            "subcategory":"Building Materials",
            "type":"Retail Goods"
        }
    ],
    "sg:phone":"+1 410 604 1100",
    "sg:postcode":"21619",
    "sg:province":"MD",
    "sg:tags":[
        "windows"
    ],
    "sg:website":"www.csdwindows.com",
    "wof:name":"Chesapeake Sash & Door LLC",
    "wof:placetype":"venue"
},
  "geometry": {"coordinates":[-76.28918,38.978132],"type":"Point"}
}