{
  "type": "Feature",
  "properties": {
    "iso:country":"US",
    "sg:address":"4733 Owl Hollow Ln",
    "sg:city":"Pocomoke City",
    "sg:classifiers":[
        {
            "category":"Building & Trades",
            "subcategory":"Construction",
            "type":"Services"
        }
    ],
    "sg:phone":"+1 410 632 4697",
    "sg:postcode":"21851",
    "sg:province":"MD",
    "sg:tags":[
        "house"
    ],
    "wof:name":"Davis Construction",
    "wof:placetype":"venue"
},
  "geometry": {"coordinates":[-75.440171,38.0833],"type":"Point"}
}