{
  "type": "Feature",
  "properties": {
    "addr:full":"101 S Main St Bel Air MD 21014",
    "addr:housenumber":"101",
    "addr:postcode":"21014",
    "addr:street":"S Main St",
    "iso:country":"US",
    "sg:address":"101 S Main St",
    "sg:city":"Bel Air",
    "sg:classifiers":[
        {
            "category":"Government",
            "subcategory":"Office",
            "type":"Public Place"
        }
    ],
    "sg:phone":"+1 410 638 3300",
    "sg:postcode":"21014",
    "sg:province":"MD",
    "sg:tags":[
        "management"
    ],
    "wof:name":"Hartford County Government",
    "wof:placetype":"venue"
},
  "geometry": {"coordinates":[-76.347532,39.534787],"type":"Point"}
}