{
  "type": "Feature",
  "properties": {
    "addr:full":"12250 Rockville Pike Rockville MD 20852",
    "addr:housenumber":"12250",
    "addr:postcode":"20852",
    "addr:street":"Rockville Pike",
    "iso:country":"US",
    "sg:address":"12250 Rockville Pike",
    "sg:city":"Rockville",
    "sg:classifiers":[
        {
            "category":"Real Estate",
            "subcategory":"Real Estate Agent",
            "type":"Services"
        }
    ],
    "sg:phone":"+1 301 770 0300",
    "sg:postcode":"20852",
    "sg:province":"MD",
    "sg:tags":[
        "management"
    ],
    "wof:name":"Multi-Family Management Inc",
    "wof:placetype":"venue"
},
  "geometry": {"coordinates":[-77.120463,39.057573],"type":"Point"}
}