{
  "type": "Feature",
  "properties": {
    "addr:full":"503 Greenway Rd SE Glen Burnie MD 21061",
    "addr:housenumber":"503",
    "addr:postcode":"21061",
    "addr:street":"Greenway Rd Se",
    "iso:country":"US",
    "sg:address":"503 Greenway Rd SE",
    "sg:city":"Glen Burnie",
    "sg:classifiers":[
        {
            "category":"Food & Beverages",
            "subcategory":"Bakery",
            "type":"Retail Goods"
        }
    ],
    "sg:phone":"+1 410 768 3532",
    "sg:postcode":"21061",
    "sg:province":"MD",
    "sg:tags":[
        "doughnut"
    ],
    "wof:name":"Carlson's Donuts & Deli",
    "wof:placetype":"venue"
},
  "geometry": {"coordinates":[-76.619534,39.155916],"type":"Point"}
}