{
  "type": "Feature",
  "properties": {
    "iso:country":"US",
    "sg:address":"8815 Centre Park Dr",
    "sg:city":"Columbia",
    "sg:classifiers":[
        {
            "category":"Professional",
            "subcategory":"Management & Consulting",
            "type":"Services"
        }
    ],
    "sg:phone":"+1 410 715 0427",
    "sg:postcode":"21045",
    "sg:province":"MD",
    "sg:tags":[
        "consultant",
        "business"
    ],
    "wof:name":"Qits USA",
    "wof:placetype":"venue"
},
  "geometry": {"coordinates":[-76.813239,39.228511],"type":"Point"}
}