{
  "type": "Feature",
  "properties": {
    "addr:full":"1808 Woodlawn Dr Gwynn Oak MD 21207",
    "addr:housenumber":"1808",
    "addr:postcode":"21207",
    "addr:street":"Woodlawn Dr",
    "iso:country":"US",
    "sg:address":"1808 Woodlawn Dr",
    "sg:city":"Gwynn Oak",
    "sg:classifiers":[
        {
            "category":"Organizations",
            "subcategory":"Religious Organization",
            "type":"Services"
        }
    ],
    "sg:phone":"+1 410 944 4056",
    "sg:postcode":"21207",
    "sg:province":"MD",
    "sg:tags":[
        "church"
    ],
    "wof:name":"New Vision Bible Fellowship",
    "wof:placetype":"venue"
},
  "geometry": {"coordinates":[-76.73700100000001,39.31614],"type":"Point"}
}