{
  "type": "Feature",
  "properties": {
    "iso:country":"US",
    "sg:address":"6378 Coventry Way",
    "sg:city":"Clinton",
    "sg:classifiers":[
        {
            "category":"Personal",
            "subcategory":"Barber",
            "type":"Services"
        }
    ],
    "sg:phone":"+1 301 868 8743",
    "sg:postcode":"20735",
    "sg:province":"MD",
    "sg:tags":[
        "salon",
        "beauty"
    ],
    "wof:name":"Clinton One Barber & Beauty Sp",
    "wof:placetype":"venue"
},
  "geometry": {"coordinates":[-76.896607,38.782199],"type":"Point"}
}