{
  "type": "Feature",
  "properties": {
    "addr:full":"4041 Conowingo Rd Darlington MD 21034",
    "addr:housenumber":"4041",
    "addr:postcode":"21034",
    "addr:street":"Conowingo Rd",
    "iso:country":"US",
    "sg:address":"4041 Conowingo Rd",
    "sg:city":"Darlington",
    "sg:classifiers":[
        {
            "category":"Education",
            "subcategory":"Special Training",
            "type":"Public Place"
        }
    ],
    "sg:phone":"+1 410 399 2380",
    "sg:postcode":"21034",
    "sg:province":"MD",
    "sg:tags":[
        "educational",
        "medical",
        "outreach"
    ],
    "wof:name":"Angel Network Outreach",
    "wof:placetype":"venue"
},
  "geometry": {"coordinates":[-76.24656400000001,39.647545],"type":"Point"}
}