{
  "type": "Feature",
  "properties": {
    "addr:full":"3800 W Belvedere Ave Baltimore MD 21215",
    "addr:housenumber":"3800",
    "addr:postcode":"21215",
    "addr:street":"W Belvedere Ave",
    "iso:country":"US",
    "sg:address":"3800 W Belvedere Ave",
    "sg:city":"Baltimore",
    "sg:classifiers":[
        {
            "category":"Real Estate",
            "subcategory":"Real Estate Services",
            "type":"Services"
        }
    ],
    "sg:phone":"+1 410 578 8630",
    "sg:postcode":"21215",
    "sg:province":"MD",
    "sg:tags":[
        "consultant",
        "housing",
        "referral"
    ],
    "wof:name":"Baltimore City",
    "wof:placetype":"venue"
},
  "geometry": {"coordinates":[-76.681358,39.345268],"type":"Point"}
}