{
  "type": "Feature",
  "properties": {
    "addr:full":"7519 Fire Tower Rd Hebron MD 21830",
    "addr:housenumber":"7519",
    "addr:postcode":"21830",
    "addr:street":"Fire Tower Rd",
    "iso:country":"US",
    "sg:address":"7519 Fire Tower Rd",
    "sg:city":"Hebron",
    "sg:classifiers":[
        {
            "category":"Professional",
            "subcategory":"Research",
            "type":"Services"
        }
    ],
    "sg:phone":"+1 410 742 0253",
    "sg:postcode":"21830",
    "sg:province":"MD",
    "sg:tags":[
        "environmental",
        "ecological"
    ],
    "wof:name":"Hall Inspections",
    "wof:placetype":"venue"
},
  "geometry": {"coordinates":[-75.700047,38.400447],"type":"Point"}
}