{
  "type": "Feature",
  "properties": {
    "iso:country":"US",
    "sg:address":"210 Castle Marina Rd",
    "sg:city":"Chester",
    "sg:classifiers":[
        {
            "category":"Insurance",
            "subcategory":"Insurance Agent",
            "type":"Services"
        }
    ],
    "sg:phone":"+1 410 643 5508",
    "sg:postcode":"21619",
    "sg:province":"MD",
    "wof:name":"Steve Hoofnagle Insurance Inc",
    "wof:placetype":"venue"
},
  "geometry": {"coordinates":[-76.289421,38.978046],"type":"Point"}
}