{
  "type": "Feature",
  "properties": {
    "iso:country":"US",
    "sg:address":"1708 Harford Rd",
    "sg:city":"Fallston",
    "sg:classifiers":[
        {
            "category":"Retail",
            "subcategory":"Auto Repair",
            "type":"Services"
        }
    ],
    "sg:phone":"+1 410 877 8797",
    "sg:postcode":"21047",
    "sg:province":"MD",
    "sg:tags":[
        "wheel",
        "automobile",
        "body",
        "dent",
        "servicing-automotive",
        "axle",
        "alignment-frame",
        "removal",
        "painting",
        "repairing"
    ],
    "wof:name":"Unique Auto Body Inc",
    "wof:placetype":"venue"
},
  "geometry": {"coordinates":[-76.382499,39.507488],"type":"Point"}
}