{
  "type": "Feature",
  "properties": {
    "iso:country":"US",
    "sg:address":"11 S Washington St",
    "sg:city":"Easton",
    "sg:classifiers":[
        {
            "category":"Professional",
            "subcategory":"Lawyer & Legal Services",
            "type":"Services"
        }
    ],
    "sg:phone":"+1 410 819 8747",
    "sg:postcode":"21601",
    "sg:province":"MD",
    "sg:tags":[
        "attorney"
    ],
    "wof:name":"Karen R Ketterman Atty At Law",
    "wof:placetype":"venue"
},
  "geometry": {"coordinates":[-76.07618100000001,38.774215],"type":"Point"}
}