{
  "type": "Feature",
  "properties": {
    "addr:full":"2095 Old Field Point Rd Elkton MD 21921",
    "addr:housenumber":"2095",
    "addr:postcode":"21921",
    "addr:street":"Old Field Point Rd",
    "iso:country":"US",
    "sg:address":"2095 Old Field Point Rd",
    "sg:city":"Elkton",
    "sg:classifiers":[
        {
            "category":"Health Services",
            "subcategory":"Clinic",
            "type":"Services"
        }
    ],
    "sg:phone":"+1 410 392 5639",
    "sg:postcode":"21921",
    "sg:province":"MD",
    "sg:tags":[
        "home"
    ],
    "wof:name":"Senior Quality Care",
    "wof:placetype":"venue"
},
  "geometry": {"coordinates":[-75.86045900000001,39.58438],"type":"Point"}
}