{
  "type": "Feature",
  "properties": {
    "addr:full":"8424 Old Harford Rd Parkville MD 21234",
    "addr:housenumber":"8424",
    "addr:postcode":"21234",
    "addr:street":"Old Harford Rd",
    "iso:country":"US",
    "sg:address":"8424 Old Harford Rd",
    "sg:city":"Parkville",
    "sg:classifiers":[
        {
            "category":"Professional",
            "subcategory":"Lawyer & Legal Services",
            "type":"Services"
        }
    ],
    "sg:phone":"+1 410 663 9800",
    "sg:postcode":"21234",
    "sg:province":"MD",
    "sg:tags":[
        "attorney"
    ],
    "wof:name":"Weston Park",
    "wof:placetype":"venue"
},
  "geometry": {"coordinates":[-76.544415,39.38622],"type":"Point"}
}