{
  "type": "Feature",
  "properties": {
    "addr:full":"15 E Salisbury St Williamsport MD 21795",
    "addr:housenumber":"15",
    "addr:postcode":"21795",
    "addr:street":"E Salisbury St",
    "iso:country":"US",
    "sg:address":"15 E Salisbury St",
    "sg:city":"Williamsport",
    "sg:classifiers":[
        {
            "category":"Personal",
            "subcategory":"Beauty Salon",
            "type":"Services"
        }
    ],
    "sg:phone":"+1 301 223 7667",
    "sg:postcode":"21795",
    "sg:province":"MD",
    "wof:name":"Cutting Lane",
    "wof:placetype":"venue"
},
  "geometry": {"coordinates":[-77.820213,39.599221],"type":"Point"}
}