{
  "type": "Feature",
  "properties": {
    "iso:country":"US",
    "sg:address":"2201 Southport Ave",
    "sg:city":"Baltimore",
    "sg:phone":"+1 410 355 6500",
    "sg:postcode":"21226",
    "sg:province":"MD",
    "sg:tags":[
        "product",
        "petroleum"
    ],
    "wof:name":"Citgo Petroleum Corp",
    "wof:placetype":"venue"
},
  "geometry": {"coordinates":[-76.568164,39.229653],"type":"Point"}
}