{
  "type": "Feature",
  "properties": {
    "addr:full":"3712 E Joppa Rd Nottingham MD 21236",
    "addr:housenumber":"3712 e",
    "addr:postcode":"21236",
    "addr:street":"Joppa Rd",
    "iso:country":"US",
    "sg:address":"3712 E Joppa Rd",
    "sg:city":"Nottingham",
    "sg:classifiers":[
        {
            "category":"Personal",
            "type":"Services"
        }
    ],
    "sg:phone":"+1 410 256 0082",
    "sg:postcode":"21236",
    "sg:province":"MD",
    "sg:tags":[
        "car",
        "loading",
        "unloading"
    ],
    "wof:name":"In & Out Movers",
    "wof:placetype":"venue"
},
  "geometry": {"coordinates":[-76.49735699999999,39.395201],"type":"Point"}
}