{
  "type": "Feature",
  "properties": {
    "iso:country":"US",
    "sg:address":"11431 Frederick Ave",
    "sg:city":"Beltsville",
    "sg:classifiers":[
        {
            "category":"Utilities",
            "subcategory":"Refuse",
            "type":"Services"
        }
    ],
    "sg:phone":"+1 301 937 8143",
    "sg:postcode":"20705",
    "sg:province":"MD",
    "sg:tags":[
        "garbage",
        "collection"
    ],
    "wof:name":"Don Dawes Refuse Co",
    "wof:placetype":"venue"
},
  "geometry": {"coordinates":[-76.90247,39.040533],"type":"Point"}
}