{
  "type": "Feature",
  "properties": {
    "iso:country":"US",
    "sg:address":"1702 Remington Dr",
    "sg:city":"Crofton",
    "sg:classifiers":[
        {
            "category":"Professional",
            "subcategory":"Computer Services",
            "type":"Services"
        }
    ],
    "sg:phone":"+1 410 721 2660",
    "sg:postcode":"21114",
    "sg:province":"MD",
    "sg:tags":[
        "datum"
    ],
    "wof:name":"Kevin Mc Grath",
    "wof:placetype":"venue"
},
  "geometry": {"coordinates":[-76.66585000000001,39.010667],"type":"Point"}
}