{
  "type": "Feature",
  "properties": {
    "addr:full":"10351 Southern Maryland Blvd Ste R101 Dunkirk MD 20754",
    "addr:housenumber":"10351",
    "addr:postcode":"20754",
    "addr:street":"Southern Maryland Blvd Ste R101",
    "iso:country":"US",
    "sg:address":"10351 Southern Maryland Blvd Ste R101",
    "sg:city":"Dunkirk",
    "sg:classifiers":[
        {
            "category":"Personal",
            "subcategory":"Barber",
            "type":"Services"
        }
    ],
    "sg:phone":"+1 301 812 0856",
    "sg:postcode":"20754",
    "sg:province":"MD",
    "wof:name":"J B & Friends",
    "wof:placetype":"venue"
},
  "geometry": {"coordinates":[-76.659536,38.727417],"type":"Point"}
}