{
  "type": "Feature",
  "properties": {
    "iso:country":"US",
    "sg:address":"8 Cross Keys Rd",
    "sg:city":"Baltimore",
    "sg:classifiers":[
        {
            "category":"Professional",
            "subcategory":"Art Services",
            "type":"Services"
        }
    ],
    "sg:phone":"+1 410 433 1107",
    "sg:postcode":"21210",
    "sg:province":"MD",
    "sg:tags":[
        "commercial",
        "artist"
    ],
    "wof:name":"Illustrations Unlimited",
    "wof:placetype":"venue"
},
  "geometry": {"coordinates":[-76.643919,39.352809],"type":"Point"}
}