{
  "type": "Feature",
  "properties": {
    "iso:country":"US",
    "sg:address":"5110 Ridgefield Rd",
    "sg:city":"Bethesda",
    "sg:classifiers":[
        {
            "category":"Social Services",
            "subcategory":"Child Care",
            "type":"Services"
        }
    ],
    "sg:phone":"+1 301 652 2229",
    "sg:postcode":"20816",
    "sg:province":"MD",
    "sg:tags":[
        "baby",
        "sitter"
    ],
    "sg:website":"http://www.achoicenanny.com",
    "wof:name":"A Choice Nanny",
    "wof:placetype":"venue"
},
  "geometry": {"coordinates":[-77.106099,38.966276],"type":"Point"}
}