{
  "type": "Feature",
  "properties": {
    "iso:country":"US",
    "sg:address":"3381 Plum Point Rd",
    "sg:city":"Huntingtown",
    "sg:classifiers":[
        {
            "category":"Retail",
            "subcategory":"Animal Services",
            "type":"Services"
        }
    ],
    "sg:phone":"+1 410 257 0706",
    "sg:postcode":"20639",
    "sg:province":"MD",
    "sg:tags":[
        "pet",
        "boarding",
        "sitting"
    ],
    "wof:name":"Canaan Farms Pet & Farm Care",
    "wof:placetype":"venue"
},
  "geometry": {"coordinates":[-76.54375,38.614667],"type":"Point"}
}