{
  "type": "Feature",
  "properties": {
    "addr:full":"1923 Old Eastern Ave Essex MD 21221",
    "addr:housenumber":"1923",
    "addr:postcode":"21221",
    "addr:street":"Old Eastern Ave",
    "iso:country":"US",
    "sg:address":"1923 Old Eastern Ave",
    "sg:city":"Essex",
    "sg:classifiers":[
        {
            "category":"Wholesale",
            "subcategory":"Auto Parts",
            "type":"Manufacturing & Wholesale Goods"
        }
    ],
    "sg:phone":"+1 410 574 6461",
    "sg:postcode":"21221",
    "sg:province":"MD",
    "sg:tags":[
        "body",
        "automobile",
        "shop"
    ],
    "wof:name":"My Body Shop",
    "wof:placetype":"venue"
},
  "geometry": {"coordinates":[-76.445195,39.324547],"type":"Point"}
}