{
  "type": "Feature",
  "properties": {
    "iso:country":"US",
    "sg:address":"550 Revolution St",
    "sg:city":"Havre De Grace",
    "sg:classifiers":[
        {
            "category":"Shopping",
            "subcategory":"Florist",
            "type":"Retail Goods"
        }
    ],
    "sg:phone":"+1 410 939 3900",
    "sg:postcode":"21078",
    "sg:province":"MD",
    "wof:name":"Dee's Flowers & Gifts Inc",
    "wof:placetype":"venue"
},
  "geometry": {"coordinates":[-76.09307099999999,39.543394],"type":"Point"}
}