{
  "type": "Feature",
  "properties": {
    "addr:full":"120 Penn St Baltimore MD 21201",
    "addr:housenumber":"120",
    "addr:postcode":"21201",
    "addr:street":"Penn St",
    "iso:country":"US",
    "sg:address":"120 Penn St",
    "sg:city":"Baltimore",
    "sg:classifiers":[
        {
            "category":"Health Services",
            "subcategory":"Doctor",
            "type":"Services"
        }
    ],
    "sg:phone":"+1 410 706 2500",
    "sg:postcode":"21201",
    "sg:province":"MD",
    "sg:tags":[
        "gynecology",
        "physician",
        "surgeon",
        "surgeons",
        "obstetrics"
    ],
    "wof:name":"Maternity Center West",
    "wof:placetype":"venue"
},
  "geometry": {"coordinates":[-76.625925,39.287234],"type":"Point"}
}