{
  "type": "Feature",
  "properties": {
    "addr:full":"1100 N Eutaw St Baltimore MD 21201",
    "addr:housenumber":"1100",
    "addr:postcode":"21201",
    "addr:street":"N Eutaw St",
    "iso:country":"US",
    "sg:address":"1100 N Eutaw St",
    "sg:city":"Baltimore",
    "sg:classifiers":[
        {
            "category":"Government",
            "subcategory":"Office",
            "type":"Public Place"
        }
    ],
    "sg:phone":"+1 410 767 2250",
    "sg:postcode":"21201",
    "sg:province":"MD",
    "sg:tags":[
        "state",
        "resource"
    ],
    "wof:name":"Labor Market & Statiatics",
    "wof:placetype":"venue"
},
  "geometry": {"coordinates":[-76.624196,39.302179],"type":"Point"}
}