{
  "type": "Feature",
  "properties": {
    "addr:full":"609 Overbrook Rd Baltimore MD 21212",
    "addr:housenumber":"609",
    "addr:postcode":"21212",
    "addr:street":"Overbrook Rd",
    "iso:country":"US",
    "sg:address":"609 Overbrook Rd",
    "sg:city":"Baltimore",
    "sg:classifiers":[
        {
            "category":"Building & Trades",
            "subcategory":"Construction",
            "type":"Services"
        }
    ],
    "sg:phone":"+1 410 377 3148",
    "sg:postcode":"21212",
    "sg:province":"MD",
    "sg:tags":[
        "house"
    ],
    "wof:name":"Renovations Black Rock",
    "wof:placetype":"venue"
},
  "geometry": {"coordinates":[-76.602271,39.374031],"type":"Point"}
}