{
  "type": "Feature",
  "properties": {
    "iso:country":"US",
    "sg:address":"6611 Mount Vista Rd",
    "sg:city":"Kingsville",
    "sg:classifiers":[
        {
            "category":"Building & Trades",
            "subcategory":"Construction",
            "type":"Services"
        }
    ],
    "sg:phone":"+1 410 592 9526",
    "sg:postcode":"21087",
    "sg:province":"MD",
    "sg:tags":[
        "home",
        "industrial",
        "contractors-commercial",
        "roofing",
        "improvement"
    ],
    "wof:name":"Kingsville Roofing And Siding",
    "wof:placetype":"venue"
},
  "geometry": {"coordinates":[-76.445638,39.455211],"type":"Point"}
}