{
  "type": "Feature",
  "properties": {
    "iso:country":"US",
    "sg:address":"2412 Blueridge Ave",
    "sg:city":"Wheaton",
    "sg:classifiers":[
        {
            "category":"Personal",
            "subcategory":"Beauty Salon",
            "type":"Services"
        }
    ],
    "sg:phone":"+1 301 946 2200",
    "sg:postcode":"20902",
    "sg:province":"MD",
    "wof:name":"Ultimate U Hair Gallery",
    "wof:placetype":"venue"
},
  "geometry": {"coordinates":[-77.05185400000001,39.042996],"type":"Point"}
}