{
  "type": "Feature",
  "properties": {
    "addr:full":"4307 Scotch Rose Ct Pikesville MD 21208",
    "addr:housenumber":"4307",
    "addr:postcode":"21208",
    "addr:street":"Scotch Rose Ct",
    "iso:country":"US",
    "sg:address":"4307 Scotch Rose Ct",
    "sg:city":"Pikesville",
    "sg:classifiers":[
        {
            "category":"Professional",
            "subcategory":"Testing Lab",
            "type":"Services"
        }
    ],
    "sg:phone":"+1 410 581 7858",
    "sg:postcode":"21208",
    "sg:province":"MD",
    "sg:tags":[
        "biological",
        "laboratory"
    ],
    "wof:name":"Lesley J Brown",
    "wof:placetype":"venue"
},
  "geometry": {"coordinates":[-76.760333,39.381331],"type":"Point"}
}