{
  "type": "Feature",
  "properties": {
    "iso:country":"US",
    "sg:address":"8483 Fort Smallwood Rd",
    "sg:city":"Pasadena",
    "sg:classifiers":[
        {
            "category":"Building & Trades",
            "subcategory":"Landscaping Services",
            "type":"Services"
        }
    ],
    "sg:phone":"+1 410 437 3721",
    "sg:postcode":"21122",
    "sg:province":"MD",
    "sg:tags":[
        "landscape",
        "contractor"
    ],
    "wof:name":"Sunshine Gardens",
    "wof:placetype":"venue"
},
  "geometry": {"coordinates":[-76.517419,39.158428],"type":"Point"}
}