{
  "type": "Feature",
  "properties": {
    "iso:country":"US",
    "sg:address":"5705 Old Silver Hill Rd",
    "sg:city":"District Heights",
    "sg:classifiers":[
        {
            "category":"Retail",
            "subcategory":"Auto Rental",
            "type":"Services"
        }
    ],
    "sg:phone":"+1 301 735 4361",
    "sg:postcode":"20747",
    "sg:province":"MD",
    "sg:tags":[
        "car"
    ],
    "wof:name":"Budget Rent A Car",
    "wof:placetype":"venue"
},
  "geometry": {"coordinates":[-76.908413,38.853139],"type":"Point"}
}