{
  "type": "Feature",
  "properties": {
    "iso:country":"US",
    "sg:address":"5507 Oregon Ave",
    "sg:city":"Halethorpe",
    "sg:classifiers":[
        {
            "category":"Restaurant",
            "type":"Food & Drink"
        }
    ],
    "sg:phone":"+1 410 247 5620",
    "sg:postcode":"21227",
    "sg:province":"MD",
    "wof:name":"Paul's Restaurant",
    "wof:placetype":"venue"
},
  "geometry": {"coordinates":[-76.69360399999999,39.247299],"type":"Point"}
}