{
  "type": "Feature",
  "properties": {
    "iso:country":"US",
    "sg:address":"1228 N Calvert St",
    "sg:city":"Baltimore",
    "sg:classifiers":[
        {
            "category":"Food & Beverages",
            "subcategory":"Liquor & Beverages",
            "type":"Retail Goods"
        }
    ],
    "sg:phone":"+1 410 539 5556",
    "sg:postcode":"21202",
    "sg:province":"MD",
    "wof:name":"Mac Gillivray's",
    "wof:placetype":"venue"
},
  "geometry": {"coordinates":[-76.613444,39.304323],"type":"Point"}
}