{
  "type": "Feature",
  "properties": {
    "addr:full":"32733 Cypress Rd Millington MD 21651",
    "addr:housenumber":"32733",
    "addr:postcode":"21651",
    "addr:street":"Cypress Rd",
    "iso:country":"US",
    "sg:address":"32733 Cypress Rd",
    "sg:city":"Millington",
    "sg:classifiers":[
        {
            "category":"Transit Center",
            "subcategory":"Freight",
            "type":"Transportation"
        },
        {
            "category":"Freight",
            "type":"Transportation"
        }
    ],
    "sg:phone":"+1 410 928 5268",
    "sg:postcode":"21651",
    "sg:province":"MD",
    "sg:tags":[
        "trucking-motor",
        "trucking"
    ],
    "wof:name":"B & B Truckin Express",
    "wof:placetype":"venue"
},
  "geometry": {"coordinates":[-75.831459,39.25718],"type":"Point"}
}