{
  "type": "Feature",
  "properties": {
    "iso:country":"US",
    "sg:address":"2905 Mitchellville Rd",
    "sg:city":"Bowie",
    "sg:classifiers":[
        {
            "category":"Health Services",
            "subcategory":"Health Practitioner",
            "type":"Services"
        }
    ],
    "sg:phone":"+1 240 929 0020",
    "sg:postcode":"20716",
    "sg:province":"MD",
    "sg:tags":[
        "therapist",
        "physical"
    ],
    "wof:name":"KPT Group",
    "wof:placetype":"venue"
},
  "geometry": {"coordinates":[-76.734094,38.931069],"type":"Point"}
}