{
  "type": "Feature",
  "properties": {
    "iso:country":"US",
    "sg:address":"534 Chalet Dr W",
    "sg:city":"Millersville",
    "sg:classifiers":[
        {
            "category":"Arts & Performance",
            "subcategory":"Theater",
            "type":"Entertainment"
        }
    ],
    "sg:phone":"+1 410 987 6322",
    "sg:postcode":"21108",
    "sg:province":"MD",
    "sg:tags":[
        "musician"
    ],
    "wof:name":"Roland Williams",
    "wof:placetype":"venue"
},
  "geometry": {"coordinates":[-76.624326,39.117083],"type":"Point"}
}