{
  "type": "Feature",
  "properties": {
    "addr:full":"8117 Harford Rd Parkville MD 21234",
    "addr:housenumber":"8117",
    "addr:postcode":"21234",
    "addr:street":"Harford Rd",
    "iso:country":"US",
    "sg:address":"8117 Harford Rd",
    "sg:city":"Parkville",
    "sg:classifiers":[
        {
            "category":"Real Estate",
            "subcategory":"Real Estate Agent",
            "type":"Services"
        }
    ],
    "sg:phone":"+1 410 882 4769",
    "sg:postcode":"21234",
    "sg:province":"MD",
    "wof:name":"Home Star Realty",
    "wof:placetype":"venue"
},
  "geometry": {"coordinates":[-76.539394,39.377849],"type":"Point"}
}