{
  "type": "Feature",
  "properties": {
    "iso:country":"US",
    "sg:address":"8304 Grey Eagle Dr",
    "sg:city":"Upper Marlboro",
    "sg:classifiers":[
        {
            "category":"Building & Trades",
            "subcategory":"Construction",
            "type":"Services"
        }
    ],
    "sg:phone":"+1 301 420 4900",
    "sg:postcode":"20772",
    "sg:province":"MD",
    "sg:tags":[
        "painter"
    ],
    "wof:name":"Grey Eagle Corporation",
    "wof:placetype":"venue"
},
  "geometry": {"coordinates":[-76.862396,38.834702],"type":"Point"}
}