{
  "type": "Feature",
  "properties": {
    "iso:country":"US",
    "sg:address":"7170 Kit Kat Rd",
    "sg:city":"Elkridge",
    "sg:classifiers":[
        {
            "category":"Utilities",
            "subcategory":"Refuse",
            "type":"Services"
        }
    ],
    "sg:phone":"+1 443 755 9497",
    "sg:postcode":"21075",
    "sg:province":"MD",
    "sg:tags":[
        "disposal",
        "waste"
    ],
    "wof:name":"Waste Management",
    "wof:placetype":"venue"
},
  "geometry": {"coordinates":[-76.767287,39.175718],"type":"Point"}
}