{
  "type": "Feature",
  "properties": {
    "addr:full":"9365 Beaver Dam Rd Nanjemoy MD 20662",
    "addr:housenumber":"9365",
    "addr:postcode":"20662",
    "addr:street":"Beaver Dam Rd",
    "iso:country":"US",
    "sg:address":"9365 Beaver Dam Rd",
    "sg:city":"Nanjemoy",
    "sg:classifiers":[
        {
            "category":"Government",
            "subcategory":"Post Office",
            "type":"Public Place"
        }
    ],
    "sg:phone":"+1 301 743 5029",
    "sg:postcode":"20662",
    "sg:province":"MD",
    "wof:name":"US Post Office",
    "wof:placetype":"venue"
},
  "geometry": {"coordinates":[-77.215502,38.452706],"type":"Point"}
}