{
  "type": "Feature",
  "properties": {
    "addr:full":"600 Washington Ave Baltimore MD 21204",
    "addr:housenumber":"600",
    "addr:postcode":"21204",
    "addr:street":"Washington Ave",
    "iso:country":"US",
    "sg:address":"600 Washington Ave",
    "sg:city":"Baltimore",
    "sg:classifiers":[
        {
            "category":"Professional",
            "subcategory":"Lawyer & Legal Services",
            "type":"Services"
        }
    ],
    "sg:phone":"+1 410 823 8110",
    "sg:postcode":"21204",
    "sg:province":"MD",
    "sg:tags":[
        "attorney"
    ],
    "wof:name":"Charles T Bowyer Law Office",
    "wof:placetype":"venue"
},
  "geometry": {"coordinates":[-76.604877,39.402543],"type":"Point"}
}