{
  "type": "Feature",
  "properties": {
    "addr:full":"4981 Ilchester Rd Ellicott City MD 21043",
    "addr:housenumber":"4981",
    "addr:postcode":"21043",
    "addr:street":"Ilchester Rd",
    "iso:country":"US",
    "sg:address":"4981 Ilchester Rd",
    "sg:city":"Ellicott City",
    "sg:classifiers":[
        {
            "category":"Education",
            "subcategory":"School",
            "type":"Public Place"
        }
    ],
    "sg:phone":"+1 410 313 2524",
    "sg:postcode":"21043",
    "sg:province":"MD",
    "wof:name":"Elementary Schools",
    "wof:placetype":"venue"
},
  "geometry": {"coordinates":[-76.77220199999999,39.234501],"type":"Point"}
}