{
  "type": "Feature",
  "properties": {
    "iso:country":"US",
    "sg:address":"15850 Crabbs Branch Way # 320",
    "sg:city":"Derwood",
    "sg:classifiers":[
        {
            "category":"Health Services",
            "subcategory":"Medical Lab",
            "type":"Services"
        }
    ],
    "sg:phone":"+1 301 948 9760",
    "sg:postcode":"20855",
    "sg:province":"MD",
    "wof:name":"American Association Of Colleg",
    "wof:placetype":"venue"
},
  "geometry": {"coordinates":[-77.15694999999999,39.116614],"type":"Point"}
}