{
  "type": "Feature",
  "properties": {
    "iso:country":"US",
    "sg:address":"831 University Blvd E",
    "sg:city":"Silver Spring",
    "sg:classifiers":[
        {
            "category":"Social Services",
            "subcategory":"Job Training",
            "type":"Services"
        }
    ],
    "sg:phone":"+1 301 445 3305",
    "sg:postcode":"20903",
    "sg:province":"MD",
    "sg:tags":[
        "rehabilitation"
    ],
    "wof:name":"Accucare Rehab & Therapy Ctr",
    "wof:placetype":"venue"
},
  "geometry": {"coordinates":[-76.992843,38.994796],"type":"Point"}
}