{
  "type": "Feature",
  "properties": {
    "iso:country":"US",
    "sg:address":"5892 Bonnie View Ln",
    "sg:city":"Elkridge",
    "sg:classifiers":[
        {
            "category":"Local Transit",
            "type":"Transportation"
        }
    ],
    "sg:phone":"+1 410 796 1838",
    "sg:postcode":"21075",
    "sg:province":"MD",
    "sg:tags":[
        "bus",
        "line"
    ],
    "wof:name":"Brown's Motor Tours Inc",
    "wof:placetype":"venue"
},
  "geometry": {"coordinates":[-76.72329000000001,39.212769],"type":"Point"}
}