{
  "type": "Feature",
  "properties": {
    "addr:full":"5485 Hardesty Rd Sunderland MD 20689",
    "addr:housenumber":"5485",
    "addr:postcode":"20689",
    "addr:street":"Hardesty Rd",
    "iso:country":"US",
    "sg:address":"5485 Hardesty Rd",
    "sg:city":"Sunderland",
    "sg:classifiers":[
        {
            "category":"Building & Trades",
            "subcategory":"Construction",
            "type":"Services"
        }
    ],
    "sg:phone":"+1 410 257 1679",
    "sg:postcode":"20689",
    "sg:province":"MD",
    "sg:tags":[
        "dry wall",
        "contractor"
    ],
    "wof:name":"J C Contractors",
    "wof:placetype":"venue"
},
  "geometry": {"coordinates":[-76.577203,38.64354],"type":"Point"}
}