{
  "type": "Feature",
  "properties": {
    "iso:country":"US",
    "sg:address":"11312 Kettering Ter",
    "sg:city":"Upper Marlboro",
    "sg:classifiers":[
        {
            "category":"Health Services",
            "subcategory":"Health Practitioner",
            "type":"Services"
        }
    ],
    "sg:phone":"+1 301 899 3200",
    "sg:postcode":"20774",
    "sg:province":"MD",
    "sg:tags":[
        "nurse",
        "registry"
    ],
    "wof:name":"Griswold Special Care",
    "wof:placetype":"venue"
},
  "geometry": {"coordinates":[-76.80774099999999,38.894582],"type":"Point"}
}