{
  "type": "Feature",
  "properties": {
    "iso:country":"US",
    "sg:address":"300 S Union Ave",
    "sg:city":"Havre De Grace",
    "sg:classifiers":[
        {
            "category":"Real Estate",
            "subcategory":"Real Estate Agent",
            "type":"Services"
        }
    ],
    "sg:phone":"+1 410 939 3633",
    "sg:postcode":"21078",
    "sg:province":"MD",
    "wof:name":"Prudential Ward & Hughes",
    "wof:placetype":"venue"
},
  "geometry": {"coordinates":[-76.09154100000001,39.544506],"type":"Point"}
}