{
  "type": "Feature",
  "properties": {
    "addr:full":"1471 Amberwood Dr N Annapolis MD 21409",
    "addr:housenumber":"1471",
    "addr:postcode":"21409",
    "addr:street":"Amberwood Dr N",
    "iso:country":"US",
    "sg:address":"1471 Amberwood Dr N",
    "sg:city":"Annapolis",
    "sg:classifiers":[
        {
            "category":"Wholesale",
            "subcategory":"Non-durable Goods",
            "type":"Manufacturing & Wholesale Goods"
        }
    ],
    "sg:phone":"+1 410 757 2736",
    "sg:postcode":"21409",
    "sg:province":"MD",
    "sg:tags":[
        "dry",
        "goods-wholesale"
    ],
    "wof:name":"Coalition For Fair Lumber Imports",
    "wof:placetype":"venue"
},
  "geometry": {"coordinates":[-76.475047,39.030109],"type":"Point"}
}