{
  "type": "Feature",
  "properties": {
    "addr:full":"22 Irongate Dr Waldorf MD 20602",
    "addr:housenumber":"22",
    "addr:postcode":"20602",
    "addr:street":"Irongate Dr",
    "iso:country":"US",
    "sg:address":"22 Irongate Dr",
    "sg:city":"Waldorf",
    "sg:classifiers":[
        {
            "category":"Home & Garden",
            "subcategory":"Building Materials",
            "type":"Retail Goods"
        }
    ],
    "sg:phone":"+1 301 638 5858",
    "sg:postcode":"20602",
    "sg:province":"MD",
    "sg:tags":[
        "door"
    ],
    "wof:name":"Fireside Hearth & Home",
    "wof:placetype":"venue"
},
  "geometry": {"coordinates":[-76.906621,38.61313],"type":"Point"}
}