{
  "type": "Feature",
  "properties": {
    "addr:full":"3535 Conowingo Rd Street MD 21154",
    "addr:housenumber":"3535",
    "addr:postcode":"21154",
    "addr:street":"Conowingo Rd Street",
    "iso:country":"US",
    "sg:address":"3535 Conowingo Rd",
    "sg:city":"Street",
    "sg:classifiers":[
        {
            "category":"Insurance",
            "subcategory":"Insurance Agent",
            "type":"Services"
        }
    ],
    "sg:phone":"+1 410 836 8780",
    "sg:postcode":"21154",
    "sg:province":"MD",
    "wof:name":"Northfield Insurance",
    "wof:placetype":"venue"
},
  "geometry": {"coordinates":[-76.26749100000001,39.6369],"type":"Point"}
}