{
  "type": "Feature",
  "properties": {
    "iso:country":"US",
    "sg:address":"6980 Laurel Bowie Rd",
    "sg:city":"Bowie",
    "sg:classifiers":[
        {
            "category":"Restaurant",
            "type":"Food & Drink"
        }
    ],
    "sg:menulink":"http://www.allmenus.com/md/bowie/197036-burger-king/menu/",
    "sg:phone":"+1 301 805 6759",
    "sg:postcode":"20715",
    "sg:province":"MD",
    "sg:tags":[
        "burger",
        "american"
    ],
    "wof:name":"Burger King",
    "wof:placetype":"venue"
},
  "geometry": {"coordinates":[-76.75748400000001,38.985973],"type":"Point"}
}