{
  "type": "Feature",
  "properties": {
    "iso:country":"US",
    "sg:address":"5830 Mount Briar Rd",
    "sg:city":"Keedysville",
    "sg:classifiers":[
        {
            "category":"Building & Trades",
            "subcategory":"Plumbing",
            "type":"Services"
        }
    ],
    "sg:phone":"+1 301 834 8892",
    "sg:postcode":"21756",
    "sg:province":"MD",
    "sg:tags":[
        "plumbing",
        "contractor"
    ],
    "wof:name":"Clydes Plumbing & Heating",
    "wof:placetype":"venue"
},
  "geometry": {"coordinates":[-77.69150399999999,39.473649],"type":"Point"}
}