{
  "type": "Feature",
  "properties": {
    "iso:country":"US",
    "sg:address":"5429 Stoney Ridge Rd",
    "sg:city":"Cambridge",
    "sg:classifiers":[
        {
            "category":"Shopping",
            "subcategory":"Used Merchandise",
            "type":"Retail Goods"
        }
    ],
    "sg:phone":"+1 410 228 8643",
    "sg:postcode":"21613",
    "sg:province":"MD",
    "wof:name":"Lexine D Lowe",
    "wof:placetype":"venue"
},
  "geometry": {"coordinates":[-76.1615,38.561552],"type":"Point"}
}