{
  "type": "Feature",
  "properties": {
    "iso:country":"US",
    "sg:address":"305 Crescendo Way",
    "sg:city":"Silver Spring",
    "sg:classifiers":[
        {
            "category":"Professional",
            "subcategory":"Business Services",
            "type":"Services"
        }
    ],
    "sg:phone":"+1 301 593 2072",
    "sg:postcode":"20901",
    "sg:province":"MD",
    "sg:tags":[
        "administrative",
        "solution",
        "social"
    ],
    "wof:name":"Emvi Services LLC",
    "wof:placetype":"venue"
},
  "geometry": {"coordinates":[-77.002565,39.04218],"type":"Point"}
}