{
  "type": "Feature",
  "properties": {
    "addr:full":"11410 Georgia Ave Silver Spring MD 20902",
    "addr:housenumber":"11410",
    "addr:postcode":"20902",
    "addr:street":"Georgia Ave",
    "iso:country":"US",
    "sg:address":"11410 Georgia Ave",
    "sg:city":"Silver Spring",
    "sg:classifiers":[
        {
            "category":"Personal",
            "subcategory":"Beauty Salon",
            "type":"Services"
        }
    ],
    "sg:phone":"+1 301 933 9380",
    "sg:postcode":"20902",
    "sg:province":"MD",
    "wof:name":"My Hair",
    "wof:placetype":"venue"
},
  "geometry": {"coordinates":[-77.051872,39.041772],"type":"Point"}
}