{
  "type": "Feature",
  "properties": {
    "addr:full":"7107 Portsmouth Rd Baltimore MD 21244",
    "addr:housenumber":"7107",
    "addr:postcode":"21244",
    "addr:street":"Portsmouth Rd",
    "iso:country":"US",
    "sg:address":"7107 Portsmouth Rd",
    "sg:city":"Baltimore",
    "sg:classifiers":[
        {
            "category":"Shopping",
            "subcategory":"Clothing, Apparel, & Fashions",
            "type":"Retail Goods"
        }
    ],
    "sg:phone":"+1 410 298 3944",
    "sg:postcode":"21244",
    "sg:province":"MD",
    "wof:name":"Zeni Enterprises",
    "wof:placetype":"venue"
},
  "geometry": {"coordinates":[-76.747905,39.337801],"type":"Point"}
}