{
  "type": "Feature",
  "properties": {
    "iso:country":"US",
    "sg:address":"5601 Loch Raven Blvd",
    "sg:city":"Baltimore",
    "sg:classifiers":[
        {
            "category":"Health Services",
            "subcategory":"Doctor",
            "type":"Services"
        },
        {
            "category":"Health Services",
            "subcategory":"Hospital",
            "type":"Services"
        }
    ],
    "sg:phone":"+1 410 532 4730",
    "sg:postcode":"21239",
    "sg:province":"MD",
    "sg:tags":[
        "orthopedist"
    ],
    "wof:name":"Johns Hopkins Orthodedics At Good Samaritan Hosptl",
    "wof:placetype":"venue"
},
  "geometry": {"coordinates":[-76.588402,39.359798],"type":"Point"}
}