{
  "type": "Feature",
  "properties": {
    "addr:full":"116 S Hickory Ave Bel Air MD 21014",
    "addr:housenumber":"116",
    "addr:postcode":"21014",
    "addr:street":"S Hickory Ave",
    "iso:country":"US",
    "sg:address":"116 S Hickory Ave",
    "sg:city":"Bel Air",
    "sg:classifiers":[
        {
            "category":"Food & Beverages",
            "subcategory":"Liquor & Beverages",
            "type":"Retail Goods"
        }
    ],
    "sg:phone":"+1 410 879 3855",
    "sg:postcode":"21014",
    "sg:province":"MD",
    "wof:name":"Bel Air Liquors",
    "wof:placetype":"venue"
},
  "geometry": {"coordinates":[-76.346467,39.535892],"type":"Point"}
}