{
  "type": "Feature",
  "properties": {
    "addr:full":"7603 Georgia Ave NW Washington MD 20012",
    "addr:housenumber":"7603",
    "addr:postcode":"20012",
    "addr:street":"Georgia Ave Nw",
    "iso:country":"US",
    "sg:address":"7603 Georgia Ave NW",
    "sg:city":"Washington",
    "sg:classifiers":[
        {
            "category":"Health Services",
            "subcategory":"Hospital",
            "type":"Services"
        }
    ],
    "sg:phone":"+1 202 545 1773",
    "sg:postcode":"20012",
    "sg:province":"MD",
    "sg:tags":[
        "mental"
    ],
    "wof:name":"Family Trauma Svc",
    "wof:placetype":"venue"
},
  "geometry": {"coordinates":[-77.026481,38.982711],"type":"Point"}
}