{
  "type": "Feature",
  "properties": {
    "iso:country":"US",
    "sg:address":"1266 Sunrise Beach Rd",
    "sg:city":"Crownsville",
    "sg:classifiers":[
        {
            "category":"Building & Trades",
            "subcategory":"Cleaning & Sanitation",
            "type":"Services"
        }
    ],
    "sg:phone":"+1 301 455 2971",
    "sg:postcode":"21032",
    "sg:province":"MD",
    "sg:tags":[
        "house"
    ],
    "sg:website":"http://www.chicasmaids.com",
    "wof:name":"Chicas Maids",
    "wof:placetype":"venue"
},
  "geometry": {"coordinates":[-76.614698,39.057416],"type":"Point"}
}