{
  "type": "Feature",
  "properties": {
    "iso:country":"US",
    "sg:address":"6301 Ivy Ln",
    "sg:city":"Greenbelt",
    "sg:classifiers":[
        {
            "category":"Professional",
            "type":"Services"
        }
    ],
    "sg:phone":"+1 301 220 1013",
    "sg:postcode":"20770",
    "sg:province":"MD",
    "sg:tags":[
        "scientist"
    ],
    "wof:name":"HTH Technical Agency Inc",
    "wof:placetype":"venue"
},
  "geometry": {"coordinates":[-76.897046,39.008328],"type":"Point"}
}