{
  "type": "Feature",
  "properties": {
    "addr:full":"401 Epping Way Annapolis MD 21401",
    "addr:housenumber":"401",
    "addr:postcode":"21401",
    "addr:street":"Epping Way",
    "iso:country":"US",
    "sg:address":"401 Epping Way",
    "sg:city":"Annapolis",
    "sg:classifiers":[
        {
            "category":"Manufacturing",
            "subcategory":"Chemicals & Compounds",
            "type":"Manufacturing & Wholesale Goods"
        }
    ],
    "sg:phone":"+1 410 266 7177",
    "sg:postcode":"21401",
    "sg:province":"MD",
    "sg:tags":[
        "product",
        "mfg"
    ],
    "wof:name":"Patrice Drago",
    "wof:placetype":"venue"
},
  "geometry": {"coordinates":[-76.53321699999999,39.013448],"type":"Point"}
}