{
  "type": "Feature",
  "properties": {
    "iso:country":"US",
    "sg:address":"1707 Aliceanna St",
    "sg:city":"Baltimore",
    "sg:classifiers":[
        {
            "category":"Shopping",
            "subcategory":"Clothing, Apparel, & Fashions",
            "type":"Retail Goods"
        }
    ],
    "sg:phone":"+1 410 276 2005",
    "sg:postcode":"21231",
    "sg:province":"MD",
    "sg:tags":[
        "handbag"
    ],
    "wof:name":"Pedx Baltimore",
    "wof:placetype":"venue"
},
  "geometry": {"coordinates":[-76.592883,39.283549],"type":"Point"}
}