{
  "type": "Feature",
  "properties": {
    "addr:full":"332 Derbyshire Ln Riva MD 21140",
    "addr:housenumber":"332",
    "addr:postcode":"21140",
    "addr:street":"Derbyshire Ln",
    "iso:country":"US",
    "sg:address":"332 Derbyshire Ln",
    "sg:city":"Riva",
    "sg:classifiers":[
        {
            "category":"Professional",
            "subcategory":"Computer Services",
            "type":"Services"
        }
    ],
    "sg:phone":"+1 410 956 8047",
    "sg:postcode":"21140",
    "sg:province":"MD",
    "sg:tags":[
        "home",
        "consulting",
        "page",
        "dev",
        "internet"
    ],
    "wof:name":"Unlimited Web Site Consulting",
    "wof:placetype":"venue"
},
  "geometry": {"coordinates":[-76.580556,38.941924],"type":"Point"}
}