{
  "type": "Feature",
  "properties": {
    "addr:full":"4202 58th Ave Ofc Bladensburg MD 20710",
    "addr:housenumber":"4202",
    "addr:postcode":"20710",
    "addr:street":"58Th Ave",
    "iso:country":"US",
    "sg:address":"4202 58th Ave Ofc",
    "sg:city":"Bladensburg",
    "sg:classifiers":[
        {
            "category":"Real Estate",
            "subcategory":"Real Estate Operator",
            "type":"Services"
        }
    ],
    "sg:phone":"+1 301 699 9785",
    "sg:postcode":"20710",
    "sg:province":"MD",
    "sg:tags":[
        "apartment"
    ],
    "wof:name":"Park View At Bladensburg",
    "wof:placetype":"venue"
},
  "geometry": {"coordinates":[-76.91709899999999,38.942299],"type":"Point"}
}