{
  "type": "Feature",
  "properties": {
    "addr:full":"White Marsh Mall Nottingham MD 21236",
    "addr:postcode":"21236",
    "iso:country":"US",
    "sg:address":"White Marsh Mall",
    "sg:city":"Nottingham",
    "sg:classifiers":[
        {
            "category":"Arts & Performance",
            "subcategory":"Art Gallery",
            "type":"Entertainment"
        }
    ],
    "sg:phone":"+1 410 931 5000",
    "sg:postcode":"21236",
    "sg:province":"MD",
    "wof:name":"Thomas Kinkade Gallery",
    "wof:placetype":"venue"
},
  "geometry": {"coordinates":[-76.466431,39.376284],"type":"Point"}
}