{
  "type": "Feature",
  "properties": {
    "addr:full":"3908 Sugarloaf Dr Monrovia MD 21770",
    "addr:housenumber":"3908",
    "addr:postcode":"21770",
    "addr:street":"Sugarloaf Dr",
    "iso:country":"US",
    "sg:address":"3908 Sugarloaf Dr",
    "sg:city":"Monrovia",
    "sg:classifiers":[
        {
            "category":"Building & Trades",
            "subcategory":"Cleaning & Sanitation",
            "type":"Services"
        }
    ],
    "sg:phone":"+1 301 831 3112",
    "sg:postcode":"21770",
    "sg:province":"MD",
    "sg:tags":[
        "fireplace",
        "chimney"
    ],
    "wof:name":"Dabbondanza Chimney Sweeps",
    "wof:placetype":"venue"
},
  "geometry": {"coordinates":[-77.239527,39.342892],"type":"Point"}
}