{
  "type": "Feature",
  "properties": {
    "iso:country":"US",
    "sg:address":"7000 Warfield Rd",
    "sg:city":"Laytonsville",
    "sg:classifiers":[
        {
            "category":"Building & Trades",
            "subcategory":"Plumbing",
            "type":"Services"
        }
    ],
    "sg:phone":"+1 301 926 5924",
    "sg:postcode":"20882",
    "sg:province":"MD",
    "sg:tags":[
        "tank",
        "septic"
    ],
    "wof:name":"Hy & Lowe",
    "wof:placetype":"venue"
},
  "geometry": {"coordinates":[-77.14226499999999,39.20014],"type":"Point"}
}