{
  "type": "Feature",
  "properties": {
    "iso:country":"US",
    "sg:address":"3901 Washington Blvd",
    "sg:city":"Halethorpe",
    "sg:classifiers":[
        {
            "category":"Organizations",
            "subcategory":"Non-profit Organization",
            "type":"Services"
        }
    ],
    "sg:phone":"+1 410 242 1444",
    "sg:postcode":"21227",
    "sg:province":"MD",
    "sg:tags":[
        "funeral",
        "cemetery"
    ],
    "wof:name":"United Hebrew Cemetery Inc",
    "wof:placetype":"venue"
},
  "geometry": {"coordinates":[-76.675003,39.243999],"type":"Point"}
}