{
  "type": "Feature",
  "properties": {
    "addr:full":"12035 Reisterstown Rd Reisterstown MD 21136",
    "addr:housenumber":"12035",
    "addr:postcode":"21136",
    "addr:street":"Reisterstown Rd",
    "iso:country":"US",
    "sg:address":"12035 Reisterstown Rd",
    "sg:city":"Reisterstown",
    "sg:classifiers":[
        {
            "category":"Organizations",
            "subcategory":"Non-profit Organization",
            "type":"Services"
        }
    ],
    "sg:phone":"+1 410 887 1143",
    "sg:postcode":"21136",
    "sg:province":"MD",
    "wof:name":"Reisterstown Senior Ctr",
    "wof:placetype":"venue"
},
  "geometry": {"coordinates":[-76.81404499999999,39.44708],"type":"Point"}
}