{
  "type": "Feature",
  "properties": {
    "iso:country":"US",
    "sg:address":"8678 Stonehouse Dr",
    "sg:city":"Ellicott City",
    "sg:classifiers":[
        {
            "category":"Building & Trades",
            "subcategory":"Construction",
            "type":"Services"
        }
    ],
    "sg:phone":"+1 410 750 8994",
    "sg:postcode":"21043",
    "sg:province":"MD",
    "sg:tags":[
        "house"
    ],
    "wof:name":"Grayson Hmes At Hollifield Stn",
    "wof:placetype":"venue"
},
  "geometry": {"coordinates":[-76.815404,39.301268],"type":"Point"}
}