{
  "type": "Feature",
  "properties": {
    "iso:country":"US",
    "sg:address":"1878 Autumn Frost Ln",
    "sg:city":"Baltimore",
    "sg:classifiers":[
        {
            "category":"Professional",
            "type":"Services"
        }
    ],
    "sg:phone":"+1 410 602 5012",
    "sg:postcode":"21209",
    "sg:province":"MD",
    "sg:tags":[
        "establishment"
    ],
    "wof:name":"Bernie Smith & Assoc Inc",
    "wof:placetype":"venue"
},
  "geometry": {"coordinates":[-76.668192,39.387788],"type":"Point"}
}