{
  "type": "Feature",
  "properties": {
    "iso:country":"US",
    "sg:address":"11942 Philadelphia Rd",
    "sg:city":"Kingsville",
    "sg:classifiers":[
        {
            "category":"Shopping",
            "subcategory":"Antiques",
            "type":"Retail Goods"
        }
    ],
    "sg:phone":"+1 410 679 9897",
    "sg:postcode":"21087",
    "sg:province":"MD",
    "wof:name":"Golden Oak Antiques",
    "wof:placetype":"venue"
},
  "geometry": {"coordinates":[-76.400127,39.41801],"type":"Point"}
}