{
  "type": "Feature",
  "properties": {
    "addr:full":"21528 Gibsontown Rd Tilghman MD 21671",
    "addr:postcode":"21528;21671",
    "addr:street":"Gibsontown Rd",
    "iso:country":"US",
    "sg:address":"21528 Gibsontown Rd",
    "sg:city":"Tilghman",
    "sg:classifiers":[
        {
            "category":"Marine",
            "type":"Transportation"
        }
    ],
    "sg:phone":"+1 410 886 2266",
    "sg:postcode":"21671",
    "sg:province":"MD",
    "sg:tags":[
        "cleaning",
        "boat"
    ],
    "wof:name":"Sparkle Yacht Detailing",
    "wof:placetype":"venue"
},
  "geometry": {"coordinates":[-76.33278,38.713457],"type":"Point"}
}