{
  "type": "Feature",
  "properties": {
    "iso:country":"US",
    "sg:address":"506 N Centre St",
    "sg:city":"Cumberland",
    "sg:classifiers":[
        {
            "category":"Health Services",
            "subcategory":"Optometrist",
            "type":"Services"
        }
    ],
    "sg:phone":"+1 301 722 6480",
    "sg:postcode":"21502",
    "sg:province":"MD",
    "wof:name":"Mitter Robert R",
    "wof:placetype":"venue"
},
  "geometry": {"coordinates":[-78.76961900000001,39.657579],"type":"Point"}
}