{
  "type": "Feature",
  "properties": {
    "addr:full":"1700 Rockville Pike Rockville MD 20852",
    "addr:housenumber":"1700",
    "addr:postcode":"20852",
    "addr:street":"Rockville Pike",
    "iso:country":"US",
    "sg:address":"1700 Rockville Pike",
    "sg:city":"Rockville",
    "sg:classifiers":[
        {
            "category":"Professional",
            "type":"Services"
        }
    ],
    "sg:phone":"+1 301 468 9596",
    "sg:postcode":"20852",
    "sg:province":"MD",
    "sg:tags":[
        "establishment"
    ],
    "wof:name":"JBG Twinbrook",
    "wof:placetype":"venue"
},
  "geometry": {"coordinates":[-77.122665,39.060283],"type":"Point"}
}