{
  "type": "Feature",
  "properties": {
    "addr:full":"25254 Garrett Hwy Mc Henry MD 21541",
    "addr:housenumber":"25254",
    "addr:postcode":"21541",
    "addr:street":"Garrett Hwy Mc Henry",
    "iso:country":"US",
    "sg:address":"25254 Garrett Hwy",
    "sg:city":"Mc Henry",
    "sg:classifiers":[
        {
            "category":"Real Estate",
            "subcategory":"Real Estate Agent",
            "type":"Services"
        }
    ],
    "sg:phone":"+1 301 387 8300",
    "sg:postcode":"21541",
    "sg:province":"MD",
    "wof:name":"Mountain Properties",
    "wof:placetype":"venue"
},
  "geometry": {"coordinates":[-79.37009,39.57089],"type":"Point"}
}