{
  "type": "Feature",
  "properties": {
    "addr:full":"109 W 2nd Ave Deer Park MD 21550",
    "addr:housenumber":"109",
    "addr:postcode":"21550",
    "addr:street":"W 2Nd Ave",
    "iso:country":"US",
    "sg:address":"109 W 2nd Ave",
    "sg:city":"Deer Park",
    "sg:classifiers":[
        {
            "category":"Retail",
            "subcategory":"Auto Repair",
            "type":"Services"
        }
    ],
    "sg:phone":"+1 301 334 2874",
    "sg:postcode":"21550",
    "sg:province":"MD",
    "sg:tags":[
        "wrecker"
    ],
    "wof:name":"Fitzwater Towing",
    "wof:placetype":"venue"
},
  "geometry": {"coordinates":[-79.37506399999999,39.393574],"type":"Point"}
}