{
  "type": "Feature",
  "properties": {
    "addr:full":"6770 Oak Hall Ln Columbia MD 21045",
    "addr:housenumber":"6770",
    "addr:postcode":"21045",
    "addr:street":"Oak Hall Ln",
    "iso:country":"US",
    "sg:address":"6770 Oak Hall Ln",
    "sg:city":"Columbia",
    "sg:classifiers":[
        {
            "category":"Professional",
            "type":"Services"
        }
    ],
    "sg:phone":"+1 410 309 9964",
    "sg:postcode":"21045",
    "sg:province":"MD",
    "sg:tags":[
        "establishment"
    ],
    "wof:name":"Pblshrs Crcltn Fulflmnt",
    "wof:placetype":"venue"
},
  "geometry": {"coordinates":[-76.822554,39.18488],"type":"Point"}
}