{
  "type": "Feature",
  "properties": {
    "addr:full":"8718 Blairwood Rd Baltimore MD 21236",
    "addr:housenumber":"8718",
    "addr:postcode":"21236",
    "addr:street":"Blairwood Rd",
    "iso:country":"US",
    "sg:address":"8718 Blairwood Rd",
    "sg:city":"Baltimore",
    "sg:classifiers":[
        {
            "category":"Professional",
            "type":"Services"
        }
    ],
    "sg:phone":"+1 410 529 6288",
    "sg:postcode":"21236",
    "sg:province":"MD",
    "wof:name":"Aaron Matthews",
    "wof:placetype":"venue"
},
  "geometry": {"coordinates":[-76.49211200000001,39.393651],"type":"Point"}
}