{
  "type": "Feature",
  "properties": {
    "addr:full":"12351 Wilkins Ave Rockville MD 20852",
    "addr:housenumber":"12351",
    "addr:postcode":"20852",
    "addr:street":"Wilkins Ave",
    "iso:country":"US",
    "sg:address":"12351 Wilkins Ave",
    "sg:city":"Rockville",
    "sg:classifiers":[
        {
            "category":"Retail",
            "subcategory":"Repair Shop",
            "type":"Services"
        }
    ],
    "sg:phone":"+1 301 231 8770",
    "sg:postcode":"20852",
    "sg:province":"MD",
    "sg:tags":[
        "upholsterer"
    ],
    "wof:name":"Trust Upholstery",
    "wof:placetype":"venue"
},
  "geometry": {"coordinates":[-77.11258599999999,39.059398],"type":"Point"}
}