{
  "type": "Feature",
  "properties": {
    "iso:country":"US",
    "sg:address":"2758 Sprague Dr",
    "sg:city":"Waldorf",
    "sg:classifiers":[
        {
            "category":"Professional",
            "subcategory":"Business Services",
            "type":"Services"
        }
    ],
    "sg:phone":"+1 301 870 0329",
    "sg:postcode":"20601",
    "sg:province":"MD",
    "sg:tags":[
        "organizing",
        "services-household"
    ],
    "wof:name":"Dhh Property Management Services",
    "wof:placetype":"venue"
},
  "geometry": {"coordinates":[-76.848546,38.650525],"type":"Point"}
}