{
  "type": "Feature",
  "properties": {
    "addr:full":"4 N 3rd St Oakland MD 21550",
    "addr:housenumber":"4",
    "addr:postcode":"21550",
    "addr:street":"N 3Rd St",
    "iso:country":"US",
    "sg:address":"4 N 3rd St",
    "sg:city":"Oakland",
    "sg:classifiers":[
        {
            "category":"Professional",
            "subcategory":"Accounting & Tax Preparation",
            "type":"Services"
        }
    ],
    "sg:phone":"+1 301 334 2359",
    "sg:postcode":"21550",
    "sg:province":"MD",
    "sg:tags":[
        "public",
        "accountants-certified"
    ],
    "wof:name":"Devine & Sheffield",
    "wof:placetype":"venue"
},
  "geometry": {"coordinates":[-79.405636,39.410391],"type":"Point"}
}