{
  "type": "Feature",
  "properties": {
    "iso:country":"US",
    "sg:address":"5732 Emory Rd",
    "sg:city":"Upperco",
    "sg:classifiers":[
        {
            "category":"Real Estate",
            "subcategory":"Developer",
            "type":"Services"
        }
    ],
    "sg:phone":"+1 410 429 5079",
    "sg:postcode":"21155",
    "sg:province":"MD",
    "wof:name":"C A Myers & Sons Inc",
    "wof:placetype":"venue"
},
  "geometry": {"coordinates":[-76.85143600000001,39.534876],"type":"Point"}
}