{
  "type": "Feature",
  "properties": {
    "iso:country":"US",
    "sg:address":"4800 Montgomery Ln",
    "sg:city":"Bethesda",
    "sg:classifiers":[
        {
            "category":"Banks & Credit Unions",
            "subcategory":"Bank",
            "type":"Services"
        }
    ],
    "sg:phone":"+1 240 497 0400",
    "sg:postcode":"20814",
    "sg:province":"MD",
    "wof:name":"Federally Insured Savings Network",
    "wof:placetype":"venue"
},
  "geometry": {"coordinates":[-77.095001,38.983398],"type":"Point"}
}