{
  "type": "Feature",
  "properties": {
    "addr:full":"14402 Bel Pre Dr Silver Spring MD 20906",
    "addr:housenumber":"14402",
    "addr:postcode":"20906",
    "addr:street":"Bel Pre Dr",
    "iso:country":"US",
    "sg:address":"14402 Bel Pre Dr",
    "sg:city":"Silver Spring",
    "sg:classifiers":[
        {
            "category":"Social Services",
            "subcategory":"Child Care",
            "type":"Services"
        }
    ],
    "sg:phone":"+1 301 871 4848",
    "sg:postcode":"20906",
    "sg:province":"MD",
    "sg:tags":[
        "day"
    ],
    "wof:name":"Vees Childcare",
    "wof:placetype":"venue"
},
  "geometry": {"coordinates":[-77.051739,39.091684],"type":"Point"}
}