{
  "type": "Feature",
  "properties": {
    "iso:country":"US",
    "sg:address":"4201 Rock Run Rd",
    "sg:city":"Havre De Grace",
    "sg:classifiers":[
        {
            "category":"Building & Trades",
            "subcategory":"Construction",
            "type":"Services"
        }
    ],
    "sg:phone":"+1 410 836 2657",
    "sg:postcode":"21078",
    "sg:province":"MD",
    "sg:tags":[
        "house"
    ],
    "wof:name":"Key Contractor Inc",
    "wof:placetype":"venue"
},
  "geometry": {"coordinates":[-76.153203,39.600148],"type":"Point"}
}