{
  "type": "Feature",
  "properties": {
    "addr:full":"12619 Wisteria Dr Germantown MD 20874",
    "addr:housenumber":"12619",
    "addr:postcode":"20874",
    "addr:street":"Wisteria Dr",
    "iso:country":"US",
    "sg:address":"12619 Wisteria Dr",
    "sg:city":"Germantown",
    "sg:classifiers":[
        {
            "category":"Personal",
            "subcategory":"Tanning Parlor",
            "type":"Services"
        }
    ],
    "sg:phone":"+1 301 972 2826",
    "sg:postcode":"20874",
    "sg:province":"MD",
    "sg:tags":[
        "salon"
    ],
    "wof:name":"Sunburst Tanning Salon",
    "wof:placetype":"venue"
},
  "geometry": {"coordinates":[-77.261965,39.17038],"type":"Point"}
}