{
  "type": "Feature",
  "properties": {
    "addr:full":"3412 Greenmount Ave Baltimore MD 21218",
    "addr:housenumber":"3412",
    "addr:postcode":"21218",
    "addr:street":"Greenmount Ave",
    "iso:country":"US",
    "sg:address":"3412 Greenmount Ave",
    "sg:city":"Baltimore",
    "sg:classifiers":[
        {
            "category":"Personal",
            "type":"Services"
        },
        {
            "category":"Retail",
            "subcategory":"Laundry & Dry Cleaning",
            "type":"Services"
        }
    ],
    "sg:phone":"+1 410 467 3766",
    "sg:postcode":"21218",
    "sg:province":"MD",
    "sg:tags":[
        "sewing",
        "alteration"
    ],
    "wof:name":"Neville's Tailoring Co",
    "wof:placetype":"venue"
},
  "geometry": {"coordinates":[-76.609486,39.330269],"type":"Point"}
}