{
  "type": "Feature",
  "properties": {
    "iso:country":"US",
    "sg:address":"1304 Redditch Ct",
    "sg:city":"Upper Marlboro",
    "sg:classifiers":[
        {
            "category":"Utilities",
            "subcategory":"Telephone",
            "type":"Services"
        }
    ],
    "sg:phone":"+1 301 499 4334",
    "sg:postcode":"20774",
    "sg:province":"MD",
    "sg:tags":[
        "communications"
    ],
    "wof:name":"Future Estates LLC",
    "wof:placetype":"venue"
},
  "geometry": {"coordinates":[-76.815924,38.870708],"type":"Point"}
}