{
  "type": "Feature",
  "properties": {
    "iso:country":"US",
    "sg:address":"3441 Fairfield Rd",
    "sg:city":"Baltimore",
    "sg:classifiers":[
        {
            "category":"Building & Trades",
            "subcategory":"Electrical",
            "type":"Services"
        }
    ],
    "sg:phone":"+1 410 355 0939",
    "sg:postcode":"21226",
    "sg:province":"MD",
    "sg:tags":[
        "electric",
        "contractor"
    ],
    "wof:name":"Mace Electric",
    "wof:placetype":"venue"
},
  "geometry": {"coordinates":[-76.57874200000001,39.236756],"type":"Point"}
}