{
  "type": "Feature",
  "properties": {
    "iso:country":"US",
    "sg:address":"6610 Rockledge Dr",
    "sg:city":"Bethesda",
    "sg:classifiers":[
        {
            "category":"Real Estate",
            "subcategory":"Real Estate Agent",
            "type":"Services"
        }
    ],
    "sg:phone":"+1 301 718 4111",
    "sg:postcode":"20817",
    "sg:province":"MD",
    "wof:name":"Weichert Real Estate School",
    "wof:placetype":"venue"
},
  "geometry": {"coordinates":[-77.134304,39.02985],"type":"Point"}
}