{
  "type": "Feature",
  "properties": {
    "addr:full":"9235 Bowline Rd Baltimore MD 21236",
    "addr:housenumber":"9235",
    "addr:postcode":"21236",
    "addr:street":"Bowline Rd",
    "iso:country":"US",
    "sg:address":"9235 Bowline Rd",
    "sg:city":"Baltimore",
    "sg:classifiers":[
        {
            "category":"Retail",
            "subcategory":"Auto Rental",
            "type":"Services"
        }
    ],
    "sg:phone":"+1 410 256 7684",
    "sg:postcode":"21236",
    "sg:province":"MD",
    "sg:tags":[
        "renting",
        "leasing",
        "trailer",
        "utility"
    ],
    "wof:name":"Tydings Enterprises LTD",
    "wof:placetype":"venue"
},
  "geometry": {"coordinates":[-76.454356,39.400099],"type":"Point"}
}