{
  "type": "Feature",
  "properties": {
    "iso:country":"US",
    "sg:address":"512 Crain Hwy N",
    "sg:city":"Glen Burnie",
    "sg:classifiers":[
        {
            "category":"Recreation",
            "subcategory":"Marina",
            "type":"Entertainment"
        }
    ],
    "sg:phone":"+1 410 766 7900",
    "sg:postcode":"21061",
    "sg:province":"MD",
    "sg:tags":[
        "repairing",
        "boat"
    ],
    "wof:name":"Skiworx Watercraft Performance",
    "wof:placetype":"venue"
},
  "geometry": {"coordinates":[-76.621043,39.1714],"type":"Point"}
}