{
  "type": "Feature",
  "properties": {
    "addr:full":"6315 Greenbelt Rd College Park MD 20740",
    "addr:housenumber":"6315",
    "addr:postcode":"20740",
    "addr:street":"Greenbelt Rd",
    "iso:country":"US",
    "sg:address":"6315 Greenbelt Rd",
    "sg:city":"College Park",
    "sg:classifiers":[
        {
            "category":"Professional",
            "type":"Services"
        }
    ],
    "sg:phone":"+1 301 614 0957",
    "sg:postcode":"20740",
    "sg:province":"MD",
    "wof:name":"S Krishnamrthy",
    "wof:placetype":"venue"
},
  "geometry": {"coordinates":[-76.904884,38.996632],"type":"Point"}
}