{
  "type": "Feature",
  "properties": {
    "addr:full":"1611 Parkridge Cir Crofton MD 21114",
    "addr:housenumber":"1611",
    "addr:postcode":"21114",
    "addr:street":"Parkridge Cir",
    "iso:country":"US",
    "sg:address":"1611 Parkridge Cir",
    "sg:city":"Crofton",
    "sg:classifiers":[
        {
            "category":"Professional",
            "subcategory":"Business Services",
            "type":"Services"
        }
    ],
    "sg:phone":"+1 410 721 6537",
    "sg:postcode":"21114",
    "sg:province":"MD",
    "wof:name":"J&L Enterprises",
    "wof:placetype":"venue"
},
  "geometry": {"coordinates":[-76.69301,39.014711],"type":"Point"}
}