{
  "type": "Feature",
  "properties": {
    "iso:country":"US",
    "sg:address":"1412 Post Ln",
    "sg:city":"Bowie",
    "sg:classifiers":[
        {
            "category":"Organizations",
            "subcategory":"Religious Organization",
            "type":"Services"
        }
    ],
    "sg:phone":"+1 301 249 1064",
    "sg:postcode":"20716",
    "sg:province":"MD",
    "wof:name":"Bowie New Life Assembly",
    "wof:placetype":"venue"
},
  "geometry": {"coordinates":[-76.73451799999999,38.90971],"type":"Point"}
}