{
  "type": "Feature",
  "properties": {
    "iso:country":"US",
    "sg:address":"421 Dover Rd",
    "sg:city":"Rockville",
    "sg:classifiers":[
        {
            "category":"Sports & Exercise",
            "subcategory":"Bowling",
            "type":"Entertainment"
        }
    ],
    "sg:phone":"+1 301 762 3977",
    "sg:postcode":"20850",
    "sg:province":"MD",
    "sg:tags":[
        "equipment",
        "accessory"
    ],
    "wof:name":"Glebe Bowling Pin Service, Inc",
    "wof:placetype":"venue"
},
  "geometry": {"coordinates":[-77.144475,39.095675],"type":"Point"}
}