{
  "type": "Feature",
  "properties": {
    "iso:country":"US",
    "sg:address":"1450 N Rolling Rd",
    "sg:city":"Catonsville",
    "sg:classifiers":[
        {
            "category":"Communications",
            "type":"Services"
        }
    ],
    "sg:phone":"+1 410 455 5680",
    "sg:postcode":"21228",
    "sg:province":"MD",
    "sg:tags":[
        "web",
        "design"
    ],
    "wof:name":"Cybergroup Inc",
    "wof:placetype":"venue"
},
  "geometry": {"coordinates":[-76.753789,39.300748],"type":"Point"}
}