{
  "type": "Feature",
  "properties": {
    "addr:full":"1239 Taylor Ave Arnold MD 21012",
    "addr:housenumber":"1239",
    "addr:postcode":"21012",
    "addr:street":"Taylor Ave",
    "iso:country":"US",
    "sg:address":"1239 Taylor Ave",
    "sg:city":"Arnold",
    "sg:classifiers":[
        {
            "category":"Professional",
            "subcategory":"Business Services",
            "type":"Services"
        }
    ],
    "sg:phone":"+1 410 544 1214",
    "sg:postcode":"21012",
    "sg:province":"MD",
    "sg:tags":[
        "translation"
    ],
    "wof:name":"Tmm & Associates",
    "wof:placetype":"venue"
},
  "geometry": {"coordinates":[-76.51329200000001,39.042258],"type":"Point"}
}