{
  "type": "Feature",
  "properties": {
    "addr:full":"9500 Michaels Ct Bethesda MD 20817",
    "addr:postcode":"9500;20817",
    "addr:street":"Michaels Ct",
    "iso:country":"US",
    "sg:address":"9500 Michaels Ct",
    "sg:city":"Bethesda",
    "sg:classifiers":[
        {
            "category":"Social Services",
            "type":"Services"
        }
    ],
    "sg:phone":"+1 301 469 5873",
    "sg:postcode":"20817",
    "sg:province":"MD",
    "sg:tags":[
        "counselor",
        "marriage",
        "family"
    ],
    "wof:name":"Marriage Savers Institute",
    "wof:placetype":"venue"
},
  "geometry": {"coordinates":[-77.135818,39.011108],"type":"Point"}
}