{
  "type": "Feature",
  "properties": {
    "iso:country":"US",
    "sg:address":"1033 Dundee Ct",
    "sg:city":"Chester",
    "sg:classifiers":[
        {
            "category":"Professional",
            "subcategory":"Detective & Security Services",
            "type":"Services"
        }
    ],
    "sg:phone":"+1 410 829 3939",
    "sg:postcode":"21619",
    "sg:province":"MD",
    "sg:tags":[
        "information",
        "bureau"
    ],
    "wof:name":"Donovans Safety Service",
    "wof:placetype":"venue"
},
  "geometry": {"coordinates":[-76.261872,38.96954],"type":"Point"}
}