{
  "type": "Feature",
  "properties": {
    "addr:full":"5225 Cooper Rd Eden MD 21801",
    "addr:housenumber":"5225",
    "addr:postcode":"21801",
    "addr:street":"Cooper Rd",
    "iso:country":"US",
    "sg:address":"5225 Cooper Rd",
    "sg:city":"Eden",
    "sg:classifiers":[
        {
            "category":"Health Services",
            "subcategory":"Clinic",
            "type":"Services"
        }
    ],
    "sg:phone":"+1 410 749 7205",
    "sg:postcode":"21801",
    "sg:province":"MD",
    "sg:tags":[
        "home",
        "care"
    ],
    "wof:name":"Eden House",
    "wof:placetype":"venue"
},
  "geometry": {"coordinates":[-75.708254,38.334386],"type":"Point"}
}