{
  "type": "Feature",
  "properties": {
    "iso:country":"US",
    "sg:address":"1300 Mercantile Ln Ste 140",
    "sg:city":"Uppr Marlboro",
    "sg:classifiers":[
        {
            "category":"Health Services",
            "subcategory":"Doctor",
            "type":"Services"
        }
    ],
    "sg:phone":"+1 301 773 2227",
    "sg:postcode":"20774",
    "sg:province":"MD",
    "wof:name":"Montanez Ciro MD",
    "wof:placetype":"venue"
},
  "geometry": {"coordinates":[-76.83729599999999,38.907175],"type":"Point"}
}