{
  "type": "Feature",
  "properties": {
    "addr:full":"825 Locust Dr West River MD 20778",
    "addr:housenumber":"825",
    "addr:postcode":"20778",
    "addr:street":"Locust Dr",
    "iso:country":"US",
    "sg:address":"825 Locust Dr",
    "sg:city":"West River",
    "sg:classifiers":[
        {
            "category":"Professional",
            "subcategory":"Management & Consulting",
            "type":"Services"
        }
    ],
    "sg:phone":"+1 301 261 5835",
    "sg:postcode":"20778",
    "sg:province":"MD",
    "sg:tags":[
        "business"
    ],
    "wof:name":"Bernice Hughes Consultant",
    "wof:placetype":"venue"
},
  "geometry": {"coordinates":[-76.55115000000001,38.829222],"type":"Point"}
}