{
  "type": "Feature",
  "properties": {
    "addr:full":"4325 Forbes Blvd Lanham MD 20706",
    "addr:housenumber":"4325",
    "addr:postcode":"20706",
    "addr:street":"Forbes Blvd",
    "iso:country":"US",
    "sg:address":"4325 Forbes Blvd",
    "sg:city":"Lanham",
    "sg:classifiers":[
        {
            "category":"Recreation",
            "type":"Entertainment"
        }
    ],
    "sg:phone":"+1 301 918 8111",
    "sg:postcode":"20706",
    "sg:province":"MD",
    "sg:tags":[
        "parks"
    ],
    "wof:name":"Maryland National Capital Park",
    "wof:placetype":"venue"
},
  "geometry": {"coordinates":[-76.828868,38.948694],"type":"Point"}
}