{
  "type": "Feature",
  "properties": {
    "addr:full":"400 E Pratt St Fl 8 Baltimore MD 21202",
    "addr:housenumber":"400;8",
    "addr:postcode":"21202",
    "addr:street":"E Pratt St",
    "iso:country":"US",
    "sg:address":"400 E Pratt St Fl 8",
    "sg:city":"Baltimore",
    "sg:classifiers":[
        {
            "category":"Professional",
            "subcategory":"Lawyer & Legal Services",
            "type":"Services"
        }
    ],
    "sg:phone":"+1 410 576 8570",
    "sg:postcode":"21202",
    "sg:province":"MD",
    "wof:name":"Zimmer David H Esquire",
    "wof:placetype":"venue"
},
  "geometry": {"coordinates":[-76.610001,39.286701],"type":"Point"}
}