{
  "type": "Feature",
  "properties": {
    "iso:country":"US",
    "sg:address":"1202 Annapolis Rd Ste E",
    "sg:city":"Odenton",
    "sg:classifiers":[
        {
            "category":"Personal",
            "subcategory":"Tanning Parlor",
            "type":"Services"
        }
    ],
    "sg:phone":"+1 410 674 6615",
    "sg:postcode":"21113",
    "sg:province":"MD",
    "sg:tags":[
        "salon"
    ],
    "wof:name":"Electric Beach Tanning Inc",
    "wof:placetype":"venue"
},
  "geometry": {"coordinates":[-76.69292299999999,39.083649],"type":"Point"}
}