{
  "type": "Feature",
  "properties": {
    "iso:country":"US",
    "sg:address":"3807 Salem Church Rd",
    "sg:city":"Jarrettsville",
    "sg:classifiers":[
        {
            "category":"Professional",
            "subcategory":"Management & Consulting",
            "type":"Services"
        }
    ],
    "sg:phone":"+1 410 692 9498",
    "sg:postcode":"21084",
    "sg:province":"MD",
    "sg:tags":[
        "consultant",
        "business"
    ],
    "wof:name":"Interactive Consulting Svc",
    "wof:placetype":"venue"
},
  "geometry": {"coordinates":[-76.493826,39.613849],"type":"Point"}
}