{
  "type": "Feature",
  "properties": {
    "addr:full":"715 E William St Salisbury MD 21804",
    "addr:housenumber":"715",
    "addr:postcode":"21804",
    "addr:street":"E William St",
    "iso:country":"US",
    "sg:address":"715 E William St",
    "sg:city":"Salisbury",
    "sg:classifiers":[
        {
            "category":"Social Services",
            "subcategory":"Adult Care",
            "type":"Services"
        }
    ],
    "sg:phone":"+1 410 341 0600",
    "sg:postcode":"21804",
    "sg:province":"MD",
    "sg:tags":[
        "organization",
        "senior",
        "citizen"
    ],
    "wof:name":"Senior Helpers",
    "wof:placetype":"venue"
},
  "geometry": {"coordinates":[-75.586422,38.367733],"type":"Point"}
}