{
  "type": "Feature",
  "properties": {
    "addr:full":"415 Headquarters Dr Millersville MD 21108",
    "addr:housenumber":"415",
    "addr:postcode":"21108",
    "addr:street":"Headquarters Dr",
    "iso:country":"US",
    "sg:address":"415 Headquarters Dr",
    "sg:city":"Millersville",
    "sg:classifiers":[
        {
            "category":"Shopping",
            "subcategory":"Clothing, Apparel, & Fashions",
            "type":"Retail Goods"
        }
    ],
    "sg:phone":"+1 410 987 2724",
    "sg:postcode":"21108",
    "sg:province":"MD",
    "sg:tags":[
        "dancing",
        "supply"
    ],
    "sg:website":"www.clingonsactivewear.com",
    "wof:name":"Clingons Activewear",
    "wof:placetype":"venue"
},
  "geometry": {"coordinates":[-76.623411,39.10061],"type":"Point"}
}