{
  "type": "Feature",
  "properties": {
    "iso:country":"US",
    "sg:address":"9680 Tilghman Island Rd",
    "sg:city":"Mcdaniel",
    "sg:classifiers":[
        {
            "category":"Building & Trades",
            "subcategory":"Electrical",
            "type":"Services"
        }
    ],
    "sg:phone":"+1 410 745 2292",
    "sg:postcode":"21647",
    "sg:province":"MD",
    "sg:tags":[
        "electric",
        "contractor"
    ],
    "wof:name":"New Millennium Electric",
    "wof:placetype":"venue"
},
  "geometry": {"coordinates":[-76.281753,38.817395],"type":"Point"}
}