{
  "type": "Feature",
  "properties": {
    "iso:country":"US",
    "sg:address":"1808 Madison Ave",
    "sg:city":"Baltimore",
    "sg:classifiers":[
        {
            "category":"Banks & Credit Unions",
            "subcategory":"Bank",
            "type":"Services"
        }
    ],
    "sg:phone":"+1 410 462 1595",
    "sg:postcode":"21217",
    "sg:province":"MD",
    "wof:name":"Data Bank Profissionals",
    "wof:placetype":"venue"
},
  "geometry": {"coordinates":[-76.632841,39.307767],"type":"Point"}
}