{
  "type": "Feature",
  "properties": {
    "iso:country":"US",
    "sg:address":"9751 Redamar Dr",
    "sg:city":"Hagerstown",
    "sg:classifiers":[
        {
            "category":"Professional",
            "type":"Services"
        }
    ],
    "sg:phone":"+1 301 790 2357",
    "sg:postcode":"21740",
    "sg:province":"MD",
    "sg:tags":[
        "establishment"
    ],
    "wof:name":"R Benjamin Jones & Co",
    "wof:placetype":"venue"
},
  "geometry": {"coordinates":[-77.67479,39.586527],"type":"Point"}
}