{
  "type": "Feature",
  "properties": {
    "iso:country":"US",
    "sg:address":"Loyola University Maryland 4501 N Charles St",
    "sg:city":"Baltimore",
    "sg:classifiers":[
        {
            "category":"Government",
            "subcategory":"Post Office",
            "type":"Public Place"
        }
    ],
    "sg:phone":"+1 410 617 2258",
    "sg:postcode":"21212",
    "sg:province":"MD",
    "sg:website":"www.usps.com",
    "wof:name":"US Postal Service",
    "wof:placetype":"venue"
},
  "geometry": {"coordinates":[-76.618244,39.346315],"type":"Point"}
}