{
  "type": "Feature",
  "properties": {
    "iso:country":"US",
    "sg:address":"2706 Price Rd",
    "sg:city":"Crofton",
    "sg:classifiers":[
        {
            "category":"Professional",
            "subcategory":"Advertising",
            "type":"Services"
        }
    ],
    "sg:phone":"+1 410 721 1973",
    "sg:postcode":"21114",
    "sg:province":"MD",
    "sg:tags":[
        "distributing",
        "sample",
        "service-circular"
    ],
    "wof:name":"Lasky Enterprises",
    "wof:placetype":"venue"
},
  "geometry": {"coordinates":[-76.680217,39.017545],"type":"Point"}
}