{
  "type": "Feature",
  "properties": {
    "addr:full":"10741 Pulaski Hwy Chase MD 21027",
    "addr:housenumber":"10741",
    "addr:postcode":"21027",
    "addr:street":"Pulaski Hwy",
    "iso:country":"US",
    "sg:address":"10741 Pulaski Hwy",
    "sg:city":"Chase",
    "sg:classifiers":[
        {
            "category":"Restaurant",
            "type":"Food & Drink"
        }
    ],
    "sg:phone":"+1 410 344 1020",
    "sg:postcode":"21027",
    "sg:province":"MD",
    "wof:name":"Double Tt Diner",
    "wof:placetype":"venue"
},
  "geometry": {"coordinates":[-76.428802,39.335201],"type":"Point"}
}