{
  "type": "Feature",
  "properties": {
    "iso:country":"US",
    "sg:address":"716 S Broadway",
    "sg:city":"Baltimore",
    "sg:classifiers":[
        {
            "category":"Professional",
            "subcategory":"Computer Services",
            "type":"Services"
        }
    ],
    "sg:phone":"+1 410 276 5888",
    "sg:postcode":"21231",
    "sg:province":"MD",
    "sg:tags":[
        "consultant",
        "designer"
    ],
    "sg:website":"www.fullburner.com",
    "wof:name":"Full Burner",
    "wof:placetype":"venue"
},
  "geometry": {"coordinates":[-76.593558,39.282708],"type":"Point"}
}