{
  "type": "Feature",
  "properties": {
    "iso:country":"US",
    "sg:address":"6202 State St",
    "sg:city":"Cheverly",
    "sg:classifiers":[
        {
            "category":"Transit Center",
            "subcategory":"Freight",
            "type":"Transportation"
        },
        {
            "category":"Freight",
            "type":"Transportation"
        }
    ],
    "sg:phone":"+1 301 499 6404",
    "sg:postcode":"20785",
    "sg:province":"MD",
    "sg:tags":[
        "local",
        "trucking-motor",
        "trucking"
    ],
    "wof:name":"Nash-Boyd Trucking Inc",
    "wof:placetype":"venue"
},
  "geometry": {"coordinates":[-76.911513,38.914005],"type":"Point"}
}