{
  "type": "Feature",
  "properties": {
    "addr:full":"9305 Steeple Ct Laurel MD 20723",
    "addr:housenumber":"9305",
    "addr:postcode":"20723",
    "addr:street":"Steeple Ct",
    "iso:country":"US",
    "sg:address":"9305 Steeple Ct",
    "sg:city":"Laurel",
    "sg:classifiers":[
        {
            "category":"Building & Trades",
            "subcategory":"Construction",
            "type":"Services"
        }
    ],
    "sg:phone":"+1 301 497 0493",
    "sg:postcode":"20723",
    "sg:province":"MD",
    "sg:tags":[
        "roofing",
        "contractor"
    ],
    "wof:name":"Angelo Family Contracting Inc",
    "wof:placetype":"venue"
},
  "geometry": {"coordinates":[-76.831885,39.130156],"type":"Point"}
}