{
  "type": "Feature",
  "properties": {
    "addr:full":"8767 Philadelphia Rd Baltimore MD 21237",
    "addr:housenumber":"8767",
    "addr:postcode":"21237",
    "addr:street":"Philadelphia Rd",
    "iso:country":"US",
    "sg:address":"8767 Philadelphia Rd",
    "sg:city":"Baltimore",
    "sg:classifiers":[
        {
            "category":"Retail",
            "subcategory":"Veterinary Services",
            "type":"Services"
        }
    ],
    "sg:phone":"+1 410 574 3738",
    "sg:postcode":"21237",
    "sg:province":"MD",
    "sg:tags":[
        "veterinarian"
    ],
    "wof:name":"Eastside Animal Hospital",
    "wof:placetype":"venue"
},
  "geometry": {"coordinates":[-76.48576300000001,39.339848],"type":"Point"}
}