{
  "type": "Feature",
  "properties": {
    "iso:country":"US",
    "sg:address":"1401 Bretton View Rd",
    "sg:city":"Annapolis",
    "sg:classifiers":[
        {
            "category":"Wholesale",
            "subcategory":"Machinery & Supplies",
            "type":"Manufacturing & Wholesale Goods"
        }
    ],
    "sg:phone":"+1 443 421 0832",
    "sg:postcode":"21409",
    "sg:province":"MD",
    "sg:tags":[
        "equipment",
        "material",
        "handling"
    ],
    "wof:name":"Peak Logix",
    "wof:placetype":"venue"
},
  "geometry": {"coordinates":[-76.472695,39.025052],"type":"Point"}
}