{
  "type": "Feature",
  "properties": {
    "iso:country":"US",
    "sg:address":"341 E 20th St",
    "sg:city":"Baltimore",
    "sg:classifiers":[
        {
            "category":"Real Estate",
            "subcategory":"Real Estate Operator",
            "type":"Services"
        }
    ],
    "sg:phone":"+1 410 243 3677",
    "sg:postcode":"21218",
    "sg:province":"MD",
    "sg:tags":[
        "apartment"
    ],
    "wof:name":"Barclay Townhouse Assocs",
    "wof:placetype":"venue"
},
  "geometry": {"coordinates":[-76.611228,39.312351],"type":"Point"}
}