{
  "type": "Feature",
  "properties": {
    "addr:full":"2417 Hannon Ct Ellicott City MD 21042",
    "addr:housenumber":"2417",
    "addr:postcode":"21042",
    "addr:street":"Hannon Ct",
    "iso:country":"US",
    "sg:address":"2417 Hannon Ct",
    "sg:city":"Ellicott City",
    "sg:classifiers":[
        {
            "category":"Manufacturing",
            "subcategory":"Printing",
            "type":"Manufacturing & Wholesale Goods"
        }
    ],
    "sg:phone":"+1 410 461 5103",
    "sg:postcode":"21042",
    "sg:province":"MD",
    "sg:tags":[
        "book"
    ],
    "wof:name":"One Heart Publishing Co",
    "wof:placetype":"venue"
},
  "geometry": {"coordinates":[-76.846976,39.304776],"type":"Point"}
}