{
  "type": "Feature",
  "properties": {
    "addr:full":"16200 Ellipse Ter Bowie MD 20716",
    "addr:housenumber":"16200",
    "addr:postcode":"20716",
    "addr:street":"Ellipse Ter",
    "iso:country":"US",
    "sg:address":"16200 Ellipse Ter",
    "sg:city":"Bowie",
    "sg:classifiers":[
        {
            "category":"Professional",
            "subcategory":"Management & Consulting",
            "type":"Services"
        }
    ],
    "sg:phone":"+1 301 805 2238",
    "sg:postcode":"20716",
    "sg:province":"MD",
    "sg:tags":[
        "consultant",
        "safety"
    ],
    "wof:name":"Fab Enterprises",
    "wof:placetype":"venue"
},
  "geometry": {"coordinates":[-76.724312,38.94278],"type":"Point"}
}