{
  "type": "Feature",
  "properties": {
    "iso:country":"US",
    "sg:address":"9 N Howard St",
    "sg:city":"Baltimore",
    "sg:classifiers":[
        {
            "category":"Wholesale",
            "subcategory":"Office Equipment",
            "type":"Manufacturing & Wholesale Goods"
        },
        {
            "category":"Professional",
            "subcategory":"Accounting & Tax Preparation",
            "type":"Services"
        }
    ],
    "sg:phone":"+1 410 244 1040",
    "sg:postcode":"21201",
    "sg:province":"MD",
    "sg:tags":[
        "machine",
        "bookkeeping",
        "return",
        "preparation-business",
        "supply"
    ],
    "sg:website":"http://www.instanttaxservice.com",
    "wof:name":"Instant Tax Svc",
    "wof:placetype":"venue"
},
  "geometry": {"coordinates":[-76.619439,39.28955],"type":"Point"}
}