{
  "type": "Feature",
  "properties": {
    "addr:full":"11720 Bad Dog Aly Waldorf MD 20601",
    "addr:postcode":"11720;20601",
    "iso:country":"US",
    "sg:address":"11720 Bad Dog Aly",
    "sg:city":"Waldorf",
    "sg:classifiers":[
        {
            "category":"Wholesale",
            "subcategory":"Auto Parts",
            "type":"Manufacturing & Wholesale Goods"
        }
    ],
    "sg:phone":"+1 301 870 9888",
    "sg:postcode":"20601",
    "sg:province":"MD",
    "sg:tags":[
        "automobile"
    ],
    "wof:name":"Automotive Service Ctr",
    "wof:placetype":"venue"
},
  "geometry": {"coordinates":[-76.904414,38.627339],"type":"Point"}
}