{
  "type": "Feature",
  "properties": {
    "iso:country":"US",
    "sg:address":"932 Copley Ave",
    "sg:city":"Waldorf",
    "sg:classifiers":[
        {
            "category":"Professional",
            "subcategory":"Management & Consulting",
            "type":"Services"
        }
    ],
    "sg:phone":"+1 301 843 8686",
    "sg:postcode":"20602",
    "sg:province":"MD",
    "sg:tags":[
        "business"
    ],
    "wof:name":"Richard L Holmes",
    "wof:placetype":"venue"
},
  "geometry": {"coordinates":[-76.917421,38.609458],"type":"Point"}
}