{
  "type": "Feature",
  "properties": {
    "iso:country":"US",
    "sg:address":"4 Rockingham Ct Apt B",
    "sg:city":"Parkville",
    "sg:classifiers":[
        {
            "category":"Wholesale",
            "subcategory":"Computers",
            "type":"Manufacturing & Wholesale Goods"
        },
        {
            "category":"Professional",
            "subcategory":"Computer Services",
            "type":"Services"
        }
    ],
    "sg:phone":"+1 410 665 0602",
    "sg:postcode":"21234",
    "sg:province":"MD",
    "sg:tags":[
        "repair",
        "software",
        "equipment-service",
        "equipment"
    ],
    "wof:name":"Swift Onsite Solutions",
    "wof:placetype":"venue"
},
  "geometry": {"coordinates":[-76.524261,39.400821],"type":"Point"}
}