{
  "type": "Feature",
  "properties": {
    "iso:country":"US",
    "sg:address":"2701 N Point Rd",
    "sg:city":"Baltimore",
    "sg:classifiers":[
        {
            "category":"Retail",
            "subcategory":"Repair Shop",
            "type":"Services"
        }
    ],
    "sg:phone":"+1 410 282 8686",
    "sg:postcode":"21222",
    "sg:province":"MD",
    "sg:tags":[
        "upholsterer"
    ],
    "wof:name":"Fran's Upholstery",
    "wof:placetype":"venue"
},
  "geometry": {"coordinates":[-76.489821,39.27941],"type":"Point"}
}