{
  "type": "Feature",
  "properties": {
    "addr:full":"7216 Gunpowder Rd Middle River MD 21220",
    "addr:housenumber":"7216",
    "addr:postcode":"21220",
    "addr:street":"Gunpowder Rd",
    "iso:country":"US",
    "sg:address":"7216 Gunpowder Rd",
    "sg:city":"Middle River",
    "sg:classifiers":[
        {
            "category":"Building & Trades",
            "subcategory":"Plumbing",
            "type":"Services"
        }
    ],
    "sg:phone":"+1 410 335 8836",
    "sg:postcode":"21220",
    "sg:province":"MD",
    "wof:name":"Tri-State Plumbing Llc",
    "wof:placetype":"venue"
},
  "geometry": {"coordinates":[-76.35007899999999,39.372046],"type":"Point"}
}