{
  "type": "Feature",
  "properties": {
    "addr:full":"1015 Pleasant Valley Dr Catonsville MD 21228",
    "addr:housenumber":"1015",
    "addr:postcode":"21228",
    "addr:street":"Pleasant Valley Dr",
    "iso:country":"US",
    "sg:address":"1015 Pleasant Valley Dr",
    "sg:city":"Catonsville",
    "sg:classifiers":[
        {
            "category":"Professional",
            "subcategory":"Business Services",
            "type":"Services"
        }
    ],
    "sg:phone":"+1 410 869 9215",
    "sg:postcode":"21228",
    "sg:province":"MD",
    "wof:name":"Golden Comfort",
    "wof:placetype":"venue"
},
  "geometry": {"coordinates":[-76.763623,39.292938],"type":"Point"}
}