{
  "type": "Feature",
  "properties": {
    "addr:full":"4534 Norrisville Rd White Hall MD 21161",
    "addr:housenumber":"4534",
    "addr:postcode":"21161",
    "addr:street":"Norrisville Rd",
    "iso:country":"US",
    "sg:address":"4534 Norrisville Rd",
    "sg:city":"White Hall",
    "sg:classifiers":[
        {
            "category":"Retail",
            "subcategory":"Veterinary Services",
            "type":"Services"
        }
    ],
    "sg:phone":"+1 410 329 6996",
    "sg:postcode":"21161",
    "sg:province":"MD",
    "sg:tags":[
        "hospital",
        "animal"
    ],
    "wof:name":"Shawsville Veterinary Hospital",
    "wof:placetype":"venue"
},
  "geometry": {"coordinates":[-76.553815,39.6412],"type":"Point"}
}