{
  "type": "Feature",
  "properties": {
    "iso:country":"US",
    "sg:address":"Congressional Plz",
    "sg:city":"Kensington",
    "sg:classifiers":[
        {
            "category":"Shopping",
            "subcategory":"Pets & Pet Supplies",
            "type":"Retail Goods"
        }
    ],
    "sg:phone":"+1 301 881 6182",
    "sg:postcode":"20895",
    "sg:province":"MD",
    "sg:tags":[
        "store"
    ],
    "wof:name":"Congressional Aquarium Inc",
    "wof:placetype":"venue"
},
  "geometry": {"coordinates":[-77.0783,39.027401],"type":"Point"}
}