{
  "type": "Feature",
  "properties": {
    "iso:country":"US",
    "sg:address":"9704 Medical Center Drive",
    "sg:city":"Rockville",
    "sg:classifiers":[
        {
            "category":"Professional",
            "subcategory":"Research",
            "type":"Services"
        }
    ],
    "sg:postcode":"20850",
    "sg:province":"MD",
    "sg:tags":[
        "sequencing",
        "genomics",
        "bioinformatics",
        "synthetic-biology",
        "bioenergy",
        "infectious-disease",
        "metagenomics",
        "not-for-profit"
    ],
    "sg:website":"http://www.jcvi.org",
    "wof:name":"J. Craig Venter Institute",
    "wof:placetype":"venue"
},
  "geometry": {"coordinates":[-77.19550700000001,39.098131],"type":"Point"}
}