{
  "type": "Feature",
  "properties": {
    "iso:country":"US",
    "sg:address":"13039 Glen Mill Rd",
    "sg:city":"Rockville",
    "sg:classifiers":[
        {
            "category":"Real Estate",
            "subcategory":"Developer",
            "type":"Services"
        }
    ],
    "sg:phone":"+1 301 294 7312",
    "sg:postcode":"20850",
    "sg:province":"MD",
    "wof:name":"Robert Connor LLC",
    "wof:placetype":"venue"
},
  "geometry": {"coordinates":[-77.209392,39.067383],"type":"Point"}
}