{
  "type": "Feature",
  "properties": {
    "iso:country":"US",
    "sg:address":"4421 Nicole Dr",
    "sg:city":"Lanham",
    "sg:classifiers":[
        {
            "category":"Professional",
            "subcategory":"Computer Services",
            "type":"Services"
        }
    ],
    "sg:phone":"+1 301 459 3522",
    "sg:postcode":"20706",
    "sg:province":"MD",
    "wof:name":"Mac Medics",
    "wof:placetype":"venue"
},
  "geometry": {"coordinates":[-76.829712,38.949457],"type":"Point"}
}