{
  "type": "Feature",
  "properties": {
    "addr:full":"8186 Lark Brown Rd Elkridge MD 21075",
    "addr:housenumber":"8186",
    "addr:postcode":"21075",
    "addr:street":"Lark Brown Rd",
    "iso:country":"US",
    "sg:address":"8186 Lark Brown Rd",
    "sg:city":"Elkridge",
    "sg:classifiers":[
        {
            "category":"Health Services",
            "subcategory":"Doctor",
            "type":"Services"
        }
    ],
    "sg:phone":"+1 410 799 8993",
    "sg:postcode":"21075",
    "sg:province":"MD",
    "sg:tags":[
        "clinic"
    ],
    "wof:name":"Crystal Medical LLC",
    "wof:placetype":"venue"
},
  "geometry": {"coordinates":[-76.796514,39.188715],"type":"Point"}
}