{
  "type": "Feature",
  "properties": {
    "iso:country":"US",
    "sg:address":"1107 West St",
    "sg:city":"Annapolis",
    "sg:classifiers":[
        {
            "category":"Autos & Motor Vehicles",
            "subcategory":"Automobile Sales",
            "type":"Retail Goods"
        }
    ],
    "sg:phone":"+1 410 268 6480",
    "sg:postcode":"21401",
    "sg:province":"MD",
    "sg:tags":[
        "car",
        "dealer"
    ],
    "wof:name":"Koons Toyota",
    "wof:placetype":"venue"
},
  "geometry": {"coordinates":[-76.511264,38.976858],"type":"Point"}
}