{
  "type": "Feature",
  "properties": {
    "addr:full":"9867 Good Luck Rd Lanham MD 20706",
    "addr:housenumber":"9867",
    "addr:postcode":"20706",
    "addr:street":"Good Luck Rd",
    "iso:country":"US",
    "sg:address":"9867 Good Luck Rd",
    "sg:city":"Lanham",
    "sg:classifiers":[
        {
            "category":"Building & Trades",
            "subcategory":"Cleaning & Sanitation",
            "type":"Services"
        }
    ],
    "sg:phone":"+1 301 794 7255",
    "sg:postcode":"20706",
    "sg:province":"MD",
    "sg:tags":[
        "maintenance"
    ],
    "wof:name":"Preston S Cleaning Services",
    "wof:placetype":"venue"
},
  "geometry": {"coordinates":[-76.836834,38.988113],"type":"Point"}
}