{
  "type": "Feature",
  "properties": {
    "iso:country":"US",
    "sg:address":"104 N Liberty St",
    "sg:city":"Baltimore",
    "sg:classifiers":[
        {
            "category":"Restaurant",
            "type":"Food & Drink"
        }
    ],
    "sg:phone":"+1 410 727 7778",
    "sg:postcode":"21201",
    "sg:province":"MD",
    "wof:name":"Eli's Carry Out",
    "wof:placetype":"venue"
},
  "geometry": {"coordinates":[-76.61717299999999,39.291652],"type":"Point"}
}