{
  "type": "Feature",
  "properties": {
    "addr:full":"9418 Spring House Ln B Laurel MD 20708",
    "addr:housenumber":"9418",
    "addr:postcode":"20708",
    "addr:street":"Spring House Ln B",
    "iso:country":"US",
    "sg:address":"9418 Spring House Ln B",
    "sg:city":"Laurel",
    "sg:classifiers":[
        {
            "category":"Food & Beverages",
            "subcategory":"Liquor & Beverages",
            "type":"Retail Goods"
        }
    ],
    "sg:phone":"+1 301 498 8486",
    "sg:postcode":"20708",
    "sg:province":"MD",
    "sg:website":"http://www.the-little-teapot.com",
    "wof:name":"The Little Teapot",
    "wof:placetype":"venue"
},
  "geometry": {"coordinates":[-76.841362,39.090881],"type":"Point"}
}