{
  "type": "Feature",
  "properties": {
    "iso:country":"US",
    "sg:address":"1205 Pemberton Dr",
    "sg:city":"Salisbury",
    "sg:classifiers":[
        {
            "category":"Health Services",
            "subcategory":"Doctor",
            "type":"Services"
        }
    ],
    "sg:phone":"+1 410 546 3125",
    "sg:postcode":"21801",
    "sg:province":"MD",
    "sg:tags":[
        "physician",
        "surgeon"
    ],
    "wof:name":"Joseph H Cutchin Jr MD",
    "wof:placetype":"venue"
},
  "geometry": {"coordinates":[-75.618132,38.367301],"type":"Point"}
}