{
  "type": "Feature",
  "properties": {
    "addr:full":"408 Lucabaugh Mill Rd Westminster MD 21157",
    "addr:housenumber":"408",
    "addr:postcode":"21157",
    "addr:street":"Lucabaugh Mill Rd",
    "iso:country":"US",
    "sg:address":"408 Lucabaugh Mill Rd",
    "sg:city":"Westminster",
    "sg:classifiers":[
        {
            "category":"Manufacturing",
            "subcategory":"Printing",
            "type":"Manufacturing & Wholesale Goods"
        }
    ],
    "sg:phone":"+1 410 876 4100",
    "sg:postcode":"21157",
    "sg:province":"MD",
    "sg:tags":[
        "printer",
        "form"
    ],
    "wof:name":"Advanced Office Solutions",
    "wof:placetype":"venue"
},
  "geometry": {"coordinates":[-76.97186000000001,39.585364],"type":"Point"}
}