{
  "type": "Feature",
  "properties": {
    "addr:full":"8190 Port Tobacco Rd Port Tobacco MD 20677",
    "addr:housenumber":"8190",
    "addr:postcode":"20677",
    "addr:street":"Port Tobacco Rd",
    "iso:country":"US",
    "sg:address":"8190 Port Tobacco Rd",
    "sg:city":"Port Tobacco",
    "sg:classifiers":[
        {
            "category":"Recreation",
            "type":"Entertainment"
        }
    ],
    "sg:phone":"+1 301 375 7875",
    "sg:postcode":"20677",
    "sg:province":"MD",
    "sg:tags":[
        "hall",
        "auditorium"
    ],
    "wof:name":"Matthews Henson Community Ctr",
    "wof:placetype":"venue"
},
  "geometry": {"coordinates":[-77.037339,38.5095],"type":"Point"}
}