{
  "type": "Feature",
  "properties": {
    "iso:country":"US",
    "sg:address":"39 Timber Rock Rd",
    "sg:city":"Gaithersburg",
    "sg:classifiers":[
        {
            "category":"Health Services",
            "subcategory":"Health Practitioner",
            "type":"Services"
        }
    ],
    "sg:phone":"+1 301 990 0868",
    "sg:postcode":"20878",
    "sg:province":"MD",
    "sg:tags":[
        "nurse",
        "registry"
    ],
    "wof:name":"Myologics",
    "wof:placetype":"venue"
},
  "geometry": {"coordinates":[-77.248689,39.120851],"type":"Point"}
}