{
  "type": "Feature",
  "properties": {
    "iso:country":"US",
    "sg:address":"733 S Glover St",
    "sg:city":"Baltimore",
    "sg:classifiers":[
        {
            "category":"Freight",
            "type":"Transportation"
        }
    ],
    "sg:phone":"+1 410 675 6007",
    "sg:postcode":"21224",
    "sg:province":"MD",
    "sg:tags":[
        "hauling",
        "trucking"
    ],
    "wof:name":"Gillum Joint Venture",
    "wof:placetype":"venue"
},
  "geometry": {"coordinates":[-76.579082,39.283449],"type":"Point"}
}