{
  "type": "Feature",
  "properties": {
    "addr:full":"4003 Paige View Rd Randallstown MD 21133",
    "addr:housenumber":"4003",
    "addr:postcode":"21133",
    "addr:street":"Paige View Rd",
    "iso:country":"US",
    "sg:address":"4003 Paige View Rd",
    "sg:city":"Randallstown",
    "sg:classifiers":[
        {
            "category":"Building & Trades",
            "subcategory":"Construction",
            "type":"Services"
        }
    ],
    "sg:phone":"+1 410 496 3500",
    "sg:postcode":"21133",
    "sg:province":"MD",
    "sg:tags":[
        "house"
    ],
    "sg:website":"www.birchwoodpark.com",
    "wof:name":"Woodbrook Subdivision",
    "wof:placetype":"venue"
},
  "geometry": {"coordinates":[-76.778547,39.38037],"type":"Point"}
}