{
  "type": "Feature",
  "properties": {
    "addr:full":"14 S Adams St Rockville MD 20850",
    "addr:housenumber":"14",
    "addr:postcode":"20850",
    "addr:street":"S Adams St",
    "iso:country":"US",
    "sg:address":"14 S Adams St",
    "sg:city":"Rockville",
    "sg:classifiers":[
        {
            "category":"Professional",
            "subcategory":"Management & Consulting",
            "type":"Services"
        }
    ],
    "sg:phone":"+1 301 340 6401",
    "sg:postcode":"20850",
    "sg:province":"MD",
    "sg:tags":[
        "personnel",
        "consultant"
    ],
    "wof:name":"MBL Assoc Staffing Agency",
    "wof:placetype":"venue"
},
  "geometry": {"coordinates":[-77.154706,39.083253],"type":"Point"}
}