{
  "type": "Feature",
  "properties": {
    "iso:country":"US",
    "sg:address":"11316 Fort Washington Rd",
    "sg:city":"Fort Washington",
    "sg:classifiers":[
        {
            "category":"Real Estate",
            "subcategory":"Real Estate Operator",
            "type":"Services"
        }
    ],
    "sg:phone":"+1 301 203 7726",
    "sg:postcode":"20744",
    "sg:province":"MD",
    "sg:tags":[
        "apartment"
    ],
    "wof:name":"Management Enterprise Dev Svc",
    "wof:placetype":"venue"
},
  "geometry": {"coordinates":[-77.00246,38.738026],"type":"Point"}
}