{
  "type": "Feature",
  "properties": {
    "addr:full":"8512 Allentown Rd Fort Washington MD 20744",
    "addr:housenumber":"8512",
    "addr:postcode":"20744",
    "addr:street":"Allentown Rd",
    "iso:country":"US",
    "sg:address":"8512 Allentown Rd",
    "sg:city":"Fort Washington",
    "sg:classifiers":[
        {
            "category":"Organizations",
            "subcategory":"Religious Organization",
            "type":"Services"
        }
    ],
    "sg:phone":"+1 301 248 0049",
    "sg:postcode":"20744",
    "sg:province":"MD",
    "wof:name":"New Life Family Fellowship",
    "wof:placetype":"venue"
},
  "geometry": {"coordinates":[-76.951055,38.772902],"type":"Point"}
}