{
  "type": "Feature",
  "properties": {
    "addr:full":"8920 Burdette Rd Bethesda MD 20817",
    "addr:housenumber":"8920",
    "addr:postcode":"20817",
    "addr:street":"Burdette Rd",
    "iso:country":"US",
    "sg:address":"8920 Burdette Rd",
    "sg:city":"Bethesda",
    "sg:classifiers":[
        {
            "category":"Professional",
            "subcategory":"Computer Services",
            "type":"Services"
        }
    ],
    "sg:phone":"+1 301 469 6116",
    "sg:postcode":"20817",
    "sg:province":"MD",
    "sg:tags":[
        "repair"
    ],
    "wof:name":"Electric-Tronics Inc",
    "wof:placetype":"venue"
},
  "geometry": {"coordinates":[-77.143354,39.002245],"type":"Point"}
}