{
  "type": "Feature",
  "properties": {
    "iso:country":"US",
    "sg:address":"8622 Hornets Nest Rd",
    "sg:city":"Emmitsburg",
    "sg:classifiers":[
        {
            "category":"Retail",
            "subcategory":"Auto Repair",
            "type":"Services"
        }
    ],
    "sg:phone":"+1 301 447 3225",
    "sg:postcode":"21727",
    "sg:province":"MD",
    "sg:tags":[
        "engine",
        "rebuilding"
    ],
    "wof:name":"Tim's Garage",
    "wof:placetype":"venue"
},
  "geometry": {"coordinates":[-77.36649199999999,39.7105],"type":"Point"}
}