{
  "type": "Feature",
  "properties": {
    "iso:country":"US",
    "sg:address":"14205 Park Center Dr Ste 202",
    "sg:city":"Laurel",
    "sg:classifiers":[
        {
            "category":"Health Services",
            "subcategory":"Doctor",
            "type":"Services"
        }
    ],
    "sg:phone":"+1 301 498 9494",
    "sg:postcode":"20707",
    "sg:province":"MD",
    "wof:name":"Pasmanik Elvira MD",
    "wof:placetype":"venue"
},
  "geometry": {"coordinates":[-76.87855999999999,39.084381],"type":"Point"}
}