{
  "type": "Feature",
  "properties": {
    "iso:country":"US",
    "sg:address":"1917 Ridgewood Rd",
    "sg:city":"Hanover",
    "sg:classifiers":[
        {
            "category":"Professional",
            "subcategory":"Management & Consulting",
            "type":"Services"
        }
    ],
    "sg:phone":"+1 410 551 6821",
    "sg:postcode":"21076",
    "sg:province":"MD",
    "sg:tags":[
        "promotion",
        "sales"
    ],
    "wof:name":"Premier Travel",
    "wof:placetype":"venue"
},
  "geometry": {"coordinates":[-76.732842,39.143657],"type":"Point"}
}