{
  "type": "Feature",
  "properties": {
    "iso:country":"US",
    "sg:address":"2700 Quarry Lake Dr # 290",
    "sg:city":"Baltimore",
    "sg:classifiers":[
        {
            "category":"Health Services",
            "subcategory":"Hospital",
            "type":"Services"
        }
    ],
    "sg:phone":"+1 410 484 8398",
    "sg:postcode":"21209",
    "sg:province":"MD",
    "sg:tags":[
        "sleep",
        "treatment",
        "disorders-information"
    ],
    "wof:name":"Malinow, Stanford",
    "wof:placetype":"venue"
},
  "geometry": {"coordinates":[-76.690781,39.384239],"type":"Point"}
}