{
  "type": "Feature",
  "properties": {
    "addr:full":"5339 Enterprise St Eldersburg MD 21784",
    "addr:housenumber":"5339",
    "addr:postcode":"21784",
    "addr:street":"Enterprise St",
    "iso:country":"US",
    "sg:address":"5339 Enterprise St",
    "sg:city":"Eldersburg",
    "sg:classifiers":[
        {
            "category":"Building & Trades",
            "subcategory":"Construction",
            "type":"Services"
        }
    ],
    "sg:phone":"+1 410 795 1621",
    "sg:postcode":"21784",
    "sg:province":"MD",
    "sg:tags":[
        "downspouts",
        "gutter"
    ],
    "wof:name":"Robosson Supply Inc",
    "wof:placetype":"venue"
},
  "geometry": {"coordinates":[-76.99698100000001,39.428128],"type":"Point"}
}