{
  "type": "Feature",
  "properties": {
    "addr:full":"8108 Roanoke Ave Takoma Park MD 20912",
    "addr:housenumber":"8108",
    "addr:postcode":"20912",
    "addr:street":"Roanoke Ave",
    "iso:country":"US",
    "sg:address":"8108 Roanoke Ave",
    "sg:city":"Takoma Park",
    "sg:classifiers":[
        {
            "category":"Professional",
            "subcategory":"Management & Consulting",
            "type":"Services"
        }
    ],
    "sg:phone":"+1 301 588 4667",
    "sg:postcode":"20912",
    "sg:province":"MD",
    "sg:tags":[
        "bus"
    ],
    "wof:name":"Neal Chalofsky Assoc",
    "wof:placetype":"venue"
},
  "geometry": {"coordinates":[-77.003446,38.990701],"type":"Point"}
}