{
  "type": "Feature",
  "properties": {
    "addr:full":"26520 Big Woods Rd Worton MD 21678",
    "addr:housenumber":"26520",
    "addr:postcode":"21678",
    "addr:street":"Big Woods Rd",
    "iso:country":"US",
    "sg:address":"26520 Big Woods Rd",
    "sg:city":"Worton",
    "sg:classifiers":[
        {
            "category":"Retail",
            "subcategory":"Auto Repair",
            "type":"Services"
        }
    ],
    "sg:phone":"+1 410 810 0092",
    "sg:postcode":"21678",
    "sg:province":"MD",
    "sg:tags":[
        "general"
    ],
    "wof:name":"S & S Shorters Automotive",
    "wof:placetype":"venue"
},
  "geometry": {"coordinates":[-76.05248899999999,39.28469],"type":"Point"}
}