{
  "type": "Feature",
  "properties": {
    "addr:full":"Laurel Center Mall Laurel MD 20707",
    "addr:postcode":"20707",
    "iso:country":"US",
    "sg:address":"Laurel Center Mall",
    "sg:city":"Laurel",
    "sg:classifiers":[
        {
            "category":"Home & Garden",
            "subcategory":"Furniture",
            "type":"Retail Goods"
        }
    ],
    "sg:phone":"+1 301 604 1779",
    "sg:postcode":"20707",
    "sg:province":"MD",
    "sg:tags":[
        "store"
    ],
    "wof:name":"Lamp & Furniture Outlet",
    "wof:placetype":"venue"
},
  "geometry": {"coordinates":[-76.869202,39.098301],"type":"Point"}
}