{
  "type": "Feature",
  "properties": {
    "addr:full":"9838 Mallard Dr Laurel MD 20708",
    "addr:housenumber":"9838",
    "addr:postcode":"20708",
    "addr:street":"Mallard Dr",
    "iso:country":"US",
    "sg:address":"9838 Mallard Dr",
    "sg:city":"Laurel",
    "sg:classifiers":[
        {
            "category":"Food & Beverages",
            "subcategory":"Groceries & Convenience Stores",
            "type":"Retail Goods"
        }
    ],
    "sg:phone":"+1 301 438 8400",
    "sg:postcode":"20708",
    "sg:province":"MD",
    "sg:tags":[
        "product"
    ],
    "wof:name":"International Food Oulet",
    "wof:placetype":"venue"
},
  "geometry": {"coordinates":[-76.83588399999999,39.055439],"type":"Point"}
}