{
  "type": "Feature",
  "properties": {
    "addr:full":"7006 Flagstaff St Hyattsville MD 20785",
    "addr:housenumber":"7006",
    "addr:postcode":"20785",
    "addr:street":"Flagstaff St",
    "iso:country":"US",
    "sg:address":"7006 Flagstaff St",
    "sg:city":"Hyattsville",
    "sg:classifiers":[
        {
            "category":"Organizations",
            "subcategory":"Religious Organization",
            "type":"Services"
        }
    ],
    "sg:phone":"+1 301 773 8299",
    "sg:postcode":"20785",
    "sg:province":"MD",
    "sg:tags":[
        "church"
    ],
    "wof:name":"Kent Baptist Church",
    "wof:placetype":"venue"
},
  "geometry": {"coordinates":[-76.884451,38.920608],"type":"Point"}
}