{
  "type": "Feature",
  "properties": {
    "addr:full":"1425 University Blvd E # 269 Hyattsville MD 20783",
    "addr:housenumber":"1425",
    "addr:postcode":"20783",
    "addr:street":"University Blvd E # 269",
    "iso:country":"US",
    "sg:address":"1425 University Blvd E # 269",
    "sg:city":"Hyattsville",
    "sg:classifiers":[
        {
            "category":"Personal",
            "subcategory":"Beauty Salon",
            "type":"Services"
        }
    ],
    "sg:phone":"+1 301 408 4004",
    "sg:postcode":"20783",
    "sg:province":"MD",
    "wof:name":"Lucely Hair & Spa, Inc.",
    "wof:placetype":"venue"
},
  "geometry": {"coordinates":[-76.98342100000001,38.986185],"type":"Point"}
}