{
  "type": "Feature",
  "properties": {
    "addr:full":"1386 Hanover Rd Hanover MD 21076",
    "addr:housenumber":"1386",
    "addr:postcode":"21076",
    "addr:street":"Hanover Rd",
    "iso:country":"US",
    "sg:address":"1386 Hanover Rd",
    "sg:city":"Hanover",
    "sg:classifiers":[
        {
            "category":"Communications",
            "type":"Services"
        }
    ],
    "sg:phone":"+1 410 379 3946",
    "sg:postcode":"21076",
    "sg:province":"MD",
    "wof:name":"S & N Communications Inc",
    "wof:placetype":"venue"
},
  "geometry": {"coordinates":[-76.717421,39.188603],"type":"Point"}
}