{
  "type": "Feature",
  "properties": {
    "iso:country":"US",
    "sg:address":"6900 Belair Rd",
    "sg:city":"Baltimore",
    "sg:classifiers":[
        {
            "category":"Bars & Pubs",
            "type":"Food & Drink"
        },
        {
            "category":"Restaurant",
            "type":"Food & Drink"
        }
    ],
    "sg:phone":"+1 410 661 3211",
    "sg:postcode":"21206",
    "sg:province":"MD",
    "sg:tags":[
        "traditional",
        "american"
    ],
    "wof:name":"Overlea Station",
    "wof:placetype":"venue"
},
  "geometry": {"coordinates":[-76.528083,39.35722],"type":"Point"}
}