{
  "type": "Feature",
  "properties": {
    "addr:full":"3390 Donnell Dr Forestville MD 20747",
    "addr:housenumber":"3390",
    "addr:postcode":"20747",
    "addr:street":"Donnell Dr",
    "iso:country":"US",
    "sg:address":"3390 Donnell Dr",
    "sg:city":"Forestville",
    "sg:classifiers":[
        {
            "category":"Professional",
            "subcategory":"Accounting & Tax Preparation",
            "type":"Services"
        }
    ],
    "sg:phone":"+1 301 735 0011",
    "sg:postcode":"20747",
    "sg:province":"MD",
    "sg:tags":[
        "return",
        "filing"
    ],
    "sg:website":"www.jacksonhewitt.com",
    "wof:name":"Jackson Hewitt Tax Svc",
    "wof:placetype":"venue"
},
  "geometry": {"coordinates":[-76.884764,38.846541],"type":"Point"}
}