{
  "type": "Feature",
  "properties": {
    "addr:full":"17842 Carter Ln Hagerstown MD 21740",
    "addr:housenumber":"17842",
    "addr:postcode":"21740",
    "addr:street":"Carter Ln",
    "iso:country":"US",
    "sg:address":"17842 Carter Ln",
    "sg:city":"Hagerstown",
    "sg:classifiers":[
        {
            "category":"Retail",
            "subcategory":"Animal Services",
            "type":"Services"
        }
    ],
    "sg:phone":"+1 301 797 5319",
    "sg:postcode":"21740",
    "sg:province":"MD",
    "wof:name":"Carleton H Faler",
    "wof:placetype":"venue"
},
  "geometry": {"coordinates":[-77.74691,39.584738],"type":"Point"}
}