{
  "type": "Feature",
  "properties": {
    "iso:country":"US",
    "sg:address":"7502 Flower Ave",
    "sg:city":"Takoma Park",
    "sg:classifiers":[
        {
            "category":"Education",
            "subcategory":"Dance Studio",
            "type":"Public Place"
        }
    ],
    "sg:phone":"+1 301 270 4409",
    "sg:postcode":"20912",
    "sg:province":"MD",
    "wof:name":"Dance Addition of Takoma Park",
    "wof:placetype":"venue"
},
  "geometry": {"coordinates":[-76.99861,38.984718],"type":"Point"}
}