{
  "type": "Feature",
  "properties": {
    "iso:country":"US",
    "sg:address":"907 Kenly Ave",
    "sg:city":"Hagerstown",
    "sg:classifiers":[
        {
            "category":"Professional",
            "subcategory":"Advertising",
            "type":"Services"
        },
        {
            "category":"Manufacturing",
            "subcategory":"Signs",
            "type":"Manufacturing & Wholesale Goods"
        }
    ],
    "sg:phone":"+1 301 745 3996",
    "sg:postcode":"21740",
    "sg:province":"MD",
    "sg:tags":[
        "specialty"
    ],
    "wof:name":"Carriagehouse Designs",
    "wof:placetype":"venue"
},
  "geometry": {"coordinates":[-77.71520200000001,39.622731],"type":"Point"}
}