{
  "type": "Feature",
  "properties": {
    "iso:country":"US",
    "sg:address":"577 Johnsville Rd",
    "sg:city":"Sykesville",
    "sg:classifiers":[
        {
            "category":"Restaurant",
            "type":"Food & Drink"
        }
    ],
    "sg:menulink":"http://www.allmenus.com/md/freedom/71373-ledo-pizza/menu/",
    "sg:phone":"+1 410 552 4000",
    "sg:postcode":"21784",
    "sg:province":"MD",
    "sg:tags":[
        "american",
        "pizza"
    ],
    "wof:name":"Ledo Pizza",
    "wof:placetype":"venue"
},
  "geometry": {"coordinates":[-76.965946,39.389591],"type":"Point"}
}