{
  "type": "Feature",
  "properties": {
    "iso:country":"US",
    "sg:address":"4308 Georgia Ave NW",
    "sg:city":"Washington",
    "sg:classifiers":[
        {
            "category":"Real Estate",
            "subcategory":"Real Estate Agent",
            "type":"Services"
        }
    ],
    "sg:phone":"+1 202 829 2299",
    "sg:postcode":"20011",
    "sg:province":"MD",
    "wof:name":"Floyd Bradford Development",
    "wof:placetype":"venue"
},
  "geometry": {"coordinates":[-77.026113,38.943894],"type":"Point"}
}