{
  "type": "Feature",
  "properties": {
    "iso:country":"US",
    "sg:address":"16924 Raven Rock Rd",
    "sg:city":"Cascade",
    "sg:classifiers":[
        {
            "category":"Organizations",
            "subcategory":"Religious Organization",
            "type":"Services"
        }
    ],
    "sg:phone":"+1 301 241 3050",
    "sg:postcode":"21780",
    "sg:province":"MD",
    "sg:tags":[
        "church"
    ],
    "wof:name":"Germantown Bethel Church-God",
    "wof:placetype":"venue"
},
  "geometry": {"coordinates":[-77.485349,39.698581],"type":"Point"}
}