{
  "type": "Feature",
  "properties": {
    "iso:country":"US",
    "sg:address":"1327 Baugher Rd",
    "sg:city":"Westminster",
    "sg:classifiers":[
        {
            "category":"Transit Center",
            "subcategory":"Freight",
            "type":"Transportation"
        },
        {
            "category":"Freight",
            "type":"Transportation"
        }
    ],
    "sg:phone":"+1 410 840 3222",
    "sg:postcode":"21158",
    "sg:province":"MD",
    "sg:tags":[
        "local",
        "trucking-motor",
        "trucking"
    ],
    "wof:name":"Specified Commodity Carriers Inc",
    "wof:placetype":"venue"
},
  "geometry": {"coordinates":[-77.043728,39.613817],"type":"Point"}
}