{
  "type": "Feature",
  "properties": {
    "addr:full":"5424 Riverdale Rd Riverdale MD 20737",
    "addr:housenumber":"5424",
    "addr:postcode":"20737",
    "addr:street":"Riverdale Rd",
    "iso:country":"US",
    "sg:address":"5424 Riverdale Rd",
    "sg:city":"Riverdale",
    "sg:classifiers":[
        {
            "category":"Arts & Performance",
            "subcategory":"Theater",
            "type":"Entertainment"
        }
    ],
    "sg:phone":"+1 301 779 0212",
    "sg:postcode":"20737",
    "sg:province":"MD",
    "sg:tags":[
        "entertainer"
    ],
    "wof:name":"Ms Franks Palm Reading",
    "wof:placetype":"venue"
},
  "geometry": {"coordinates":[-76.92127000000001,38.959165],"type":"Point"}
}