{
  "type": "Feature",
  "properties": {
    "iso:country":"US",
    "sg:address":"7910 Woodmont Ave",
    "sg:city":"Bethesda",
    "sg:classifiers":[
        {
            "category":"Real Estate",
            "subcategory":"Architect",
            "type":"Services"
        }
    ],
    "sg:phone":"+1 301 654 2454",
    "sg:postcode":"20814",
    "sg:province":"MD",
    "wof:name":"Mushinsky Associates-MR & A",
    "wof:placetype":"venue"
},
  "geometry": {"coordinates":[-77.096469,38.989745],"type":"Point"}
}