{
  "type": "Feature",
  "properties": {
    "addr:full":"7031 Liberty Rd Gwynn Oak MD 21207",
    "addr:housenumber":"7031",
    "addr:postcode":"21207",
    "addr:street":"Liberty Rd",
    "iso:country":"US",
    "sg:address":"7031 Liberty Rd",
    "sg:city":"Gwynn Oak",
    "sg:classifiers":[
        {
            "category":"Professional",
            "subcategory":"Accounting & Tax Preparation",
            "type":"Services"
        }
    ],
    "sg:phone":"+1 410 265 1975",
    "sg:postcode":"21207",
    "sg:province":"MD",
    "sg:tags":[
        "return",
        "filing"
    ],
    "wof:name":"Jackson Hewitt Tax Svc",
    "wof:placetype":"venue"
},
  "geometry": {"coordinates":[-76.732497,39.344443],"type":"Point"}
}