{
  "type": "Feature",
  "properties": {
    "addr:full":"1835 Robinson Mill Rd Darlington MD 21034",
    "addr:housenumber":"1835",
    "addr:postcode":"21034",
    "addr:street":"Robinson Mill Rd",
    "iso:country":"US",
    "sg:address":"1835 Robinson Mill Rd",
    "sg:city":"Darlington",
    "sg:classifiers":[
        {
            "category":"Wholesale",
            "subcategory":"Medical Equipment & Supplies",
            "type":"Manufacturing & Wholesale Goods"
        },
        {
            "category":"Shopping",
            "subcategory":"Pharmacy",
            "type":"Retail Goods"
        }
    ],
    "sg:phone":"+1 410 457 5547",
    "sg:postcode":"21034",
    "sg:province":"MD",
    "sg:tags":[
        "home",
        "health",
        "care"
    ],
    "wof:name":"Mwi Veteniary Supplies",
    "wof:placetype":"venue"
},
  "geometry": {"coordinates":[-76.260515,39.678394],"type":"Point"}
}