{
  "type": "Feature",
  "properties": {
    "addr:full":"9310 Kilbride Ct Perry Hall MD 21128",
    "addr:housenumber":"9310",
    "addr:postcode":"21128",
    "addr:street":"Kilbride Ct",
    "iso:country":"US",
    "sg:address":"9310 Kilbride Ct",
    "sg:city":"Perry Hall",
    "sg:classifiers":[
        {
            "category":"Professional",
            "subcategory":"Detective & Security Services",
            "type":"Services"
        }
    ],
    "sg:phone":"+1 410 375 9494",
    "sg:postcode":"21128",
    "sg:province":"MD",
    "sg:tags":[
        "guard"
    ],
    "wof:name":"Joseph Peach",
    "wof:placetype":"venue"
},
  "geometry": {"coordinates":[-76.45831200000001,39.4015],"type":"Point"}
}