{
  "type": "Feature",
  "properties": {
    "addr:full":"1200 Harkins Rd Pylesville MD 21132",
    "addr:housenumber":"1200",
    "addr:postcode":"21132",
    "addr:street":"Harkins Rd",
    "iso:country":"US",
    "sg:address":"1200 Harkins Rd",
    "sg:city":"Pylesville",
    "sg:classifiers":[
        {
            "category":"Building & Trades",
            "subcategory":"Plumbing",
            "type":"Services"
        }
    ],
    "sg:phone":"+1 410 692 5503",
    "sg:postcode":"21132",
    "sg:province":"MD",
    "sg:tags":[
        "system",
        "heating",
        "contractor",
        "air conditioning"
    ],
    "sg:website":"http://www.trane.com",
    "wof:name":"Foremost Heating & Ac",
    "wof:placetype":"venue"
},
  "geometry": {"coordinates":[-76.428467,39.69627],"type":"Point"}
}