{
  "type": "Feature",
  "properties": {
    "addr:full":"7250 Faraway Pl Hughesville MD 20637",
    "addr:housenumber":"7250",
    "addr:postcode":"20637",
    "addr:street":"Faraway Pl",
    "iso:country":"US",
    "sg:address":"7250 Faraway Pl",
    "sg:city":"Hughesville",
    "sg:classifiers":[
        {
            "category":"Restaurant",
            "type":"Food & Drink"
        }
    ],
    "sg:phone":"+1 301 274 9753",
    "sg:postcode":"20637",
    "sg:province":"MD",
    "sg:tags":[
        "eating"
    ],
    "wof:name":"Entertainment Inc",
    "wof:placetype":"venue"
},
  "geometry": {"coordinates":[-76.83624399999999,38.513441],"type":"Point"}
}