{
  "type": "Feature",
  "properties": {
    "addr:full":"6300 Kenilworth Ave Ste 2 Riverdale MD 20737",
    "addr:housenumber":"6300",
    "addr:postcode":"20737",
    "addr:street":"Kenilworth Ave Ste 2",
    "iso:country":"US",
    "sg:address":"6300 Kenilworth Ave Ste 2",
    "sg:city":"Riverdale",
    "sg:classifiers":[
        {
            "category":"Professional",
            "subcategory":"Accounting & Tax Preparation",
            "type":"Services"
        }
    ],
    "sg:phone":"+1 301 209 0887",
    "sg:postcode":"20737",
    "sg:province":"MD",
    "sg:tags":[
        "accountant"
    ],
    "wof:name":"Namcro Tax Services",
    "wof:placetype":"venue"
},
  "geometry": {"coordinates":[-76.91909800000001,38.963501],"type":"Point"}
}