{
  "type": "Feature",
  "properties": {
    "addr:full":"419 W Redwood St Ste 110 Baltimore MD 21201",
    "addr:housenumber":"419",
    "addr:postcode":"21201",
    "addr:street":"W Redwood St Ste 110",
    "iso:country":"US",
    "sg:address":"419 W Redwood St Ste 110",
    "sg:city":"Baltimore",
    "sg:classifiers":[
        {
            "category":"Health Services",
            "subcategory":"Medical Lab",
            "type":"Services"
        }
    ],
    "sg:phone":"+1 410 328 3225",
    "sg:postcode":"21201",
    "sg:province":"MD",
    "wof:name":"University Imaging Center",
    "wof:placetype":"venue"
},
  "geometry": {"coordinates":[-76.621134,39.288638],"type":"Point"}
}