{
  "type": "Feature",
  "properties": {
    "addr:full":"6545 Crain Hwy La Plata MD 20646",
    "addr:housenumber":"6545",
    "addr:postcode":"20646",
    "addr:street":"Crain Hwy",
    "iso:country":"US",
    "sg:address":"6545 Crain Hwy",
    "sg:city":"La Plata",
    "sg:classifiers":[
        {
            "category":"Health Services",
            "subcategory":"Doctor",
            "type":"Services"
        }
    ],
    "sg:phone":"+1 301 932 1105",
    "sg:postcode":"20646",
    "sg:province":"MD",
    "sg:tags":[
        "dentist"
    ],
    "wof:name":"Kenneth M Yip-Young DDS",
    "wof:placetype":"venue"
},
  "geometry": {"coordinates":[-76.98351,38.532929],"type":"Point"}
}