{
  "type": "Feature",
  "properties": {
    "addr:full":"200 Cardamon Dr Edgewater MD 21037",
    "addr:housenumber":"200",
    "addr:postcode":"21037",
    "addr:street":"Cardamon Dr",
    "iso:country":"US",
    "sg:address":"200 Cardamon Dr",
    "sg:city":"Edgewater",
    "sg:classifiers":[
        {
            "category":"Food & Beverages",
            "subcategory":"Specialty",
            "type":"Retail Goods"
        }
    ],
    "sg:phone":"+1 410 571 0460",
    "sg:postcode":"21037",
    "sg:province":"MD",
    "sg:tags":[
        "vitamin"
    ],
    "wof:name":"Shaklee Authorized Distr",
    "wof:placetype":"venue"
},
  "geometry": {"coordinates":[-76.553608,38.972747],"type":"Point"}
}