{
  "type": "Feature",
  "properties": {
    "iso:country":"US",
    "sg:address":"1241 Orleans St",
    "sg:city":"Baltimore",
    "sg:classifiers":[
        {
            "category":"Restaurant",
            "type":"Food & Drink"
        }
    ],
    "sg:menulink":"http://www.allmenus.com/md/baltimore/197095-burger-king/menu/",
    "sg:phone":"+1 410 563 7263",
    "sg:postcode":"21202",
    "sg:province":"MD",
    "sg:tags":[
        "burger",
        "american"
    ],
    "wof:name":"Burger King",
    "wof:placetype":"venue"
},
  "geometry": {"coordinates":[-76.600973,39.294885],"type":"Point"}
}