{
  "type": "Feature",
  "properties": {
    "addr:full":"1602 Eastern Ave Baltimore MD 21231",
    "addr:housenumber":"1602",
    "addr:postcode":"21231",
    "addr:street":"Eastern Ave",
    "iso:country":"US",
    "sg:address":"1602 Eastern Ave",
    "sg:city":"Baltimore",
    "sg:classifiers":[
        {
            "category":"Bakery",
            "type":"Food & Drink"
        },
        {
            "category":"Coffee & Tea",
            "type":"Food & Drink"
        },
        {
            "category":"Bagels",
            "type":"Food & Drink"
        },
        {
            "category":"Donuts",
            "type":"Food & Drink"
        }
    ],
    "sg:menulink":"http://www.allmenus.com/md/baltimore/148965-dunkin-donuts/menu/",
    "sg:phone":"+1 410 391 8557",
    "sg:postcode":"21231",
    "sg:province":"MD",
    "sg:tags":[
        "wrap",
        "american",
        "sandwich",
        "pastry"
    ],
    "wof:name":"Dunkin' Donuts",
    "wof:placetype":"venue"
},
  "geometry": {"coordinates":[-76.595234,39.285498],"type":"Point"}
}