{
  "type": "Feature",
  "properties": {
    "iso:country":"US",
    "sg:address":"6411 Belair Rd",
    "sg:city":"Baltimore",
    "sg:classifiers":[
        {
            "category":"Arts & Performance",
            "subcategory":"Theater",
            "type":"Entertainment"
        }
    ],
    "sg:phone":"+1 410 254 8670",
    "sg:postcode":"21206",
    "sg:province":"MD",
    "sg:tags":[
        "band",
        "orchestra"
    ],
    "wof:name":"Baltimore's Best Acoustic Msc",
    "wof:placetype":"venue"
},
  "geometry": {"coordinates":[-76.532777,39.352853],"type":"Point"}
}