{
  "type": "Feature",
  "properties": {
    "iso:country":"US",
    "sg:address":"408 Forest Bridge Ct",
    "sg:city":"Laurel",
    "sg:classifiers":[
        {
            "category":"Retail",
            "subcategory":"Auto Repair",
            "type":"Services"
        }
    ],
    "sg:phone":"+1 301 604 2869",
    "sg:postcode":"20724",
    "sg:province":"MD",
    "sg:tags":[
        "automotive"
    ],
    "wof:name":"Bernards Tuning",
    "wof:placetype":"venue"
},
  "geometry": {"coordinates":[-76.825887,39.083851],"type":"Point"}
}