{
  "type": "Feature",
  "properties": {
    "addr:full":"8205 Carroll Ave Takoma Park MD 20912",
    "addr:housenumber":"8205",
    "addr:postcode":"20912",
    "addr:street":"Carroll Ave",
    "iso:country":"US",
    "sg:address":"8205 Carroll Ave",
    "sg:city":"Takoma Park",
    "sg:classifiers":[
        {
            "category":"Personal",
            "subcategory":"Beauty Salon",
            "type":"Services"
        }
    ],
    "sg:phone":"+1 301 439 3393",
    "sg:postcode":"20912",
    "sg:province":"MD",
    "wof:name":"Unisex Beauty Salon-Ritz",
    "wof:placetype":"venue"
},
  "geometry": {"coordinates":[-76.99251599999999,38.994146],"type":"Point"}
}