{
  "type": "Feature",
  "properties": {
    "addr:full":"2109 Emmorton Park Dr Edgewood MD 21040",
    "addr:housenumber":"2109",
    "addr:postcode":"21040",
    "addr:street":"Emmorton Park Dr",
    "iso:country":"US",
    "sg:address":"2109 Emmorton Park Dr",
    "sg:city":"Edgewood",
    "sg:classifiers":[
        {
            "category":"Retail",
            "subcategory":"Auto Repair",
            "type":"Services"
        }
    ],
    "sg:phone":"+1 410 679 1311",
    "sg:postcode":"21040",
    "sg:province":"MD",
    "sg:tags":[
        "body",
        "automobile",
        "painting"
    ],
    "wof:name":"Bel Air Auto Body",
    "wof:placetype":"venue"
},
  "geometry": {"coordinates":[-76.308806,39.452185],"type":"Point"}
}