{
  "type": "Feature",
  "properties": {
    "addr:full":"2304 E Baltimore St Baltimore MD 21224",
    "addr:housenumber":"2304",
    "addr:postcode":"21224",
    "addr:street":"E Baltimore St",
    "iso:country":"US",
    "sg:address":"2304 E Baltimore St",
    "sg:city":"Baltimore",
    "sg:classifiers":[
        {
            "category":"Professional",
            "subcategory":"Art Services",
            "type":"Services"
        }
    ],
    "sg:phone":"+1 410 732 8379",
    "sg:postcode":"21224",
    "sg:province":"MD",
    "sg:tags":[
        "designer",
        "display",
        "producer"
    ],
    "wof:name":"Substance 151",
    "wof:placetype":"venue"
},
  "geometry": {"coordinates":[-76.58453799999999,39.291894],"type":"Point"}
}