{
  "type": "Feature",
  "properties": {
    "addr:full":"2 Shaftsbury Ct Reisterstown MD 21136",
    "addr:housenumber":"2",
    "addr:postcode":"21136",
    "addr:street":"Shaftsbury Ct",
    "iso:country":"US",
    "sg:address":"2 Shaftsbury Ct",
    "sg:city":"Reisterstown",
    "sg:classifiers":[
        {
            "category":"Professional",
            "type":"Services"
        }
    ],
    "sg:phone":"+1 410 833 0514",
    "sg:postcode":"21136",
    "sg:province":"MD",
    "sg:tags":[
        "engineer",
        "surveying"
    ],
    "wof:name":"Macks & Macks",
    "wof:placetype":"venue"
},
  "geometry": {"coordinates":[-76.799606,39.453651],"type":"Point"}
}