{
  "type": "Feature",
  "properties": {
    "addr:full":"4625 Falls Rd Baltimore MD 21209",
    "addr:housenumber":"4625",
    "addr:postcode":"21209",
    "addr:street":"Falls Rd",
    "iso:country":"US",
    "sg:address":"4625 Falls Rd",
    "sg:city":"Baltimore",
    "sg:classifiers":[
        {
            "category":"Wholesale",
            "subcategory":"Painting Supplies",
            "type":"Manufacturing & Wholesale Goods"
        }
    ],
    "sg:phone":"+1 410 243 7700",
    "sg:postcode":"21209",
    "sg:province":"MD",
    "sg:tags":[
        "paint",
        "contractor"
    ],
    "sg:website":"http://baltimore.citysearch.com/profile/external/4973948/baltimore_md/sherwin_williams.html?publisher=yellowpages&reference_id=1&placement=ypwebsitemip",
    "wof:name":"Sherwin-Williams",
    "wof:placetype":"venue"
},
  "geometry": {"coordinates":[-76.64102699999999,39.345753],"type":"Point"}
}