{
  "type": "Feature",
  "properties": {
    "addr:full":"2206 Old Frederick Rd Baltimore MD 21228",
    "addr:housenumber":"2206",
    "addr:postcode":"21228",
    "addr:street":"Old Frederick Rd",
    "iso:country":"US",
    "sg:address":"2206 Old Frederick Rd",
    "sg:city":"Baltimore",
    "sg:classifiers":[
        {
            "category":"Manufacturing",
            "subcategory":"Tools & Machinery",
            "type":"Manufacturing & Wholesale Goods"
        }
    ],
    "sg:phone":"+1 410 744 2144",
    "sg:postcode":"21228",
    "sg:province":"MD",
    "sg:tags":[
        "designed",
        "built"
    ],
    "wof:name":"Sweeny Automation",
    "wof:placetype":"venue"
},
  "geometry": {"coordinates":[-76.76612799999999,39.275285],"type":"Point"}
}