{
  "type": "Feature",
  "properties": {
    "iso:country":"US",
    "sg:address":"793 Oakdale Cir",
    "sg:city":"Millersville",
    "sg:classifiers":[
        {
            "category":"Professional",
            "subcategory":"Business Services",
            "type":"Services"
        }
    ],
    "sg:phone":"+1 410 987 4330",
    "sg:postcode":"21108",
    "sg:province":"MD",
    "wof:name":"Wheeler & Assoc Inc",
    "wof:placetype":"venue"
},
  "geometry": {"coordinates":[-76.639218,39.115966],"type":"Point"}
}