{
  "type": "Feature",
  "properties": {
    "iso:country":"US",
    "sg:address":"3810 Club Dr",
    "sg:city":"Chevy Chase",
    "sg:classifiers":[
        {
            "category":"Wholesale",
            "subcategory":"Furniture",
            "type":"Manufacturing & Wholesale Goods"
        }
    ],
    "sg:phone":"+1 301 913 9200",
    "sg:postcode":"20815",
    "sg:province":"MD",
    "wof:name":"Jeffrey C Fuge & Associates",
    "wof:placetype":"venue"
},
  "geometry": {"coordinates":[-77.076995,38.988925],"type":"Point"}
}