{
  "type": "Feature",
  "properties": {
    "addr:full":"3667 Saint Lukes Rd Salisbury MD 21804",
    "addr:housenumber":"3667",
    "addr:postcode":"21804",
    "addr:street":"Saint Lukes Rd",
    "iso:country":"US",
    "sg:address":"3667 Saint Lukes Rd",
    "sg:city":"Salisbury",
    "sg:classifiers":[
        {
            "category":"Building & Trades",
            "subcategory":"Landscaping Services",
            "type":"Services"
        }
    ],
    "sg:phone":"+1 410 546 8524",
    "sg:postcode":"21804",
    "sg:province":"MD",
    "sg:tags":[
        "topsoil"
    ],
    "wof:name":"Mulch Movers",
    "wof:placetype":"venue"
},
  "geometry": {"coordinates":[-75.59574499999999,38.294197],"type":"Point"}
}