{
  "type": "Feature",
  "properties": {
    "iso:country":"US",
    "sg:address":"30 E Padonia Rd",
    "sg:city":"Lutherville",
    "sg:classifiers":[
        {
            "category":"Organizations",
            "subcategory":"Professional Association",
            "type":"Services"
        }
    ],
    "sg:phone":"+1 410 252 2100",
    "sg:postcode":"21093",
    "sg:province":"MD",
    "sg:website":"www.mdhorsebreeders.com",
    "wof:name":"Maryland Horse Breeders Assn",
    "wof:placetype":"venue"
},
  "geometry": {"coordinates":[-76.629051,39.456386],"type":"Point"}
}