{
  "type": "Feature",
  "properties": {
    "iso:country":"US",
    "sg:address":"21300 Old York Rd",
    "sg:city":"Parkton",
    "sg:classifiers":[
        {
            "category":"Shopping",
            "subcategory":"Used Merchandise",
            "type":"Retail Goods"
        }
    ],
    "sg:phone":"+1 410 329 8047",
    "sg:postcode":"21120",
    "sg:province":"MD",
    "wof:name":"Line State Antiques",
    "wof:placetype":"venue"
},
  "geometry": {"coordinates":[-76.651461,39.711062],"type":"Point"}
}