{
  "type": "Feature",
  "properties": {
    "addr:full":"7901 Beechcraft Ave Ste N Gaithersburg MD 20879",
    "addr:housenumber":"7901",
    "addr:postcode":"20879",
    "addr:street":"Beechcraft Ave Ste N",
    "iso:country":"US",
    "sg:address":"7901 Beechcraft Ave Ste N",
    "sg:city":"Gaithersburg",
    "sg:classifiers":[
        {
            "category":"Manufacturing",
            "subcategory":"Electronics",
            "type":"Manufacturing & Wholesale Goods"
        }
    ],
    "sg:phone":"+1 301 924 6540",
    "sg:postcode":"20879",
    "sg:province":"MD",
    "sg:tags":[
        "equipment",
        "electronic",
        "supplies-wholesale",
        "manufacturer"
    ],
    "wof:name":"Electronic Systems Svc",
    "wof:placetype":"venue"
},
  "geometry": {"coordinates":[-77.160882,39.16253],"type":"Point"}
}