{
  "type": "Feature",
  "properties": {
    "addr:full":"531 York Rd Baltimore MD 21204",
    "addr:housenumber":"531",
    "addr:postcode":"21204",
    "addr:street":"York Rd",
    "iso:country":"US",
    "sg:address":"531 York Rd",
    "sg:city":"Baltimore",
    "sg:classifiers":[
        {
            "category":"Personal",
            "subcategory":"Tanning Parlor",
            "type":"Services"
        }
    ],
    "sg:phone":"+1 410 337 7299",
    "sg:postcode":"21204",
    "sg:province":"MD",
    "sg:tags":[
        "salon"
    ],
    "wof:name":"Tropical Tanning Ctr",
    "wof:placetype":"venue"
},
  "geometry": {"coordinates":[-76.60229699999999,39.401084],"type":"Point"}
}