{
  "type": "Feature",
  "properties": {
    "addr:full":"6685 Santa Barbara Rd A Elkridge MD 21075",
    "addr:housenumber":"6685",
    "addr:postcode":"21075",
    "addr:street":"Santa Barbara Rd",
    "iso:country":"US",
    "sg:address":"6685 Santa Barbara Rd A",
    "sg:city":"Elkridge",
    "sg:classifiers":[
        {
            "category":"Shopping",
            "subcategory":"Stationery & Office Supplies",
            "type":"Retail Goods"
        }
    ],
    "sg:phone":"+1 410 579 8533",
    "sg:postcode":"21075",
    "sg:province":"MD",
    "sg:tags":[
        "partition"
    ],
    "sg:website":"http://www.nellowall.com",
    "wof:name":"Nello Wall Systems, Inc.",
    "wof:placetype":"venue"
},
  "geometry": {"coordinates":[-76.747108,39.190041],"type":"Point"}
}