{
  "type": "Feature",
  "properties": {
    "addr:full":"23901 Mount Misery Rd St Michaels MD 21663",
    "addr:housenumber":"23901",
    "addr:postcode":"21663",
    "addr:street":"Mount Misery Rd St",
    "iso:country":"US",
    "sg:address":"23901 Mount Misery Rd",
    "sg:city":"St Michaels",
    "sg:classifiers":[
        {
            "category":"Real Estate",
            "subcategory":"Architect",
            "type":"Services"
        }
    ],
    "sg:phone":"+1 410 745 6166",
    "sg:postcode":"21663",
    "sg:province":"MD",
    "wof:name":"Pamela Heyne Aia",
    "wof:placetype":"venue"
},
  "geometry": {"coordinates":[-76.241342,38.782424],"type":"Point"}
}