{
  "type": "Feature",
  "properties": {
    "iso:country":"US",
    "sg:address":"27497 Westpoint Rd",
    "sg:city":"Easton",
    "sg:classifiers":[
        {
            "category":"Professional",
            "subcategory":"Lawyer & Legal Services",
            "type":"Services"
        }
    ],
    "sg:phone":"+1 410 819 0023",
    "sg:postcode":"21601",
    "sg:province":"MD",
    "sg:tags":[
        "attorney"
    ],
    "wof:name":"Bellinger & Assoc",
    "wof:placetype":"venue"
},
  "geometry": {"coordinates":[-76.124484,38.730942],"type":"Point"}
}