{
  "type": "Feature",
  "properties": {
    "addr:full":"12050 Parklawn Dr Rockville MD 20852",
    "addr:housenumber":"12050",
    "addr:postcode":"20852",
    "addr:street":"Parklawn Dr",
    "iso:country":"US",
    "sg:address":"12050 Parklawn Dr",
    "sg:city":"Rockville",
    "sg:classifiers":[
        {
            "category":"Wholesale",
            "subcategory":"Electrical",
            "type":"Manufacturing & Wholesale Goods"
        }
    ],
    "sg:phone":"+1 301 468 0800",
    "sg:postcode":"20852",
    "sg:province":"MD",
    "sg:tags":[
        "refrigerator",
        "freezer"
    ],
    "wof:name":"H M Sweenys Co",
    "wof:placetype":"venue"
},
  "geometry": {"coordinates":[-77.107917,39.056312],"type":"Point"}
}