{
  "type": "Feature",
  "properties": {
    "addr:full":"4418 Norwood Rd Baltimore MD 21218",
    "addr:housenumber":"4418",
    "addr:postcode":"21218",
    "addr:street":"Norwood Rd",
    "iso:country":"US",
    "sg:address":"4418 Norwood Rd",
    "sg:city":"Baltimore",
    "sg:classifiers":[
        {
            "category":"Organizations",
            "subcategory":"Community Association",
            "type":"Services"
        }
    ],
    "sg:phone":"+1 410 366 1284",
    "sg:postcode":"21218",
    "sg:province":"MD",
    "wof:name":"Guilford Assoc",
    "wof:placetype":"venue"
},
  "geometry": {"coordinates":[-76.612842,39.345029],"type":"Point"}
}