{
  "type": "Feature",
  "properties": {
    "addr:full":"7161 Baltimore Annapolis Blvd Glen Burnie MD 21061",
    "addr:housenumber":"7161",
    "addr:postcode":"21061",
    "addr:street":"Baltimore Annapolis Blvd",
    "iso:country":"US",
    "sg:address":"7161 Baltimore Annapolis Blvd",
    "sg:city":"Glen Burnie",
    "sg:classifiers":[
        {
            "category":"Organizations",
            "subcategory":"Professional Association",
            "type":"Services"
        }
    ],
    "sg:phone":"+1 410 760 1040",
    "sg:postcode":"21061",
    "sg:province":"MD",
    "sg:website":"www.mslba.org",
    "wof:name":"Maryland State Licensed Bvrg",
    "wof:placetype":"venue"
},
  "geometry": {"coordinates":[-76.642248,39.187909],"type":"Point"}
}