{
  "type": "Feature",
  "properties": {
    "addr:full":"7922 Cessna Ave Gaithersburg MD 20879",
    "addr:housenumber":"7922",
    "addr:postcode":"20879",
    "addr:street":"Cessna Ave",
    "iso:country":"US",
    "sg:address":"7922 Cessna Ave",
    "sg:city":"Gaithersburg",
    "sg:classifiers":[
        {
            "category":"Building & Trades",
            "subcategory":"Construction",
            "type":"Services"
        }
    ],
    "sg:phone":"+1 301 208 0989",
    "sg:postcode":"20879",
    "sg:province":"MD",
    "sg:tags":[
        "home",
        "improvement"
    ],
    "wof:name":"Steve Meyers Quality Home",
    "wof:placetype":"venue"
},
  "geometry": {"coordinates":[-77.160501,39.171285],"type":"Point"}
}