{
  "type": "Feature",
  "properties": {
    "addr:full":"200 N Marlyn Ave Essex MD 21221",
    "addr:housenumber":"200",
    "addr:postcode":"21221",
    "addr:street":"N Marlyn Ave",
    "iso:country":"US",
    "sg:address":"200 N Marlyn Ave",
    "sg:city":"Essex",
    "sg:classifiers":[
        {
            "category":"Place Of Worship",
            "subcategory":"Church",
            "type":"Public Place"
        },
        {
            "category":"Place Of Worship",
            "type":"Public Place"
        }
    ],
    "sg:phone":"+1 410 686 8226",
    "sg:postcode":"21221",
    "sg:province":"MD",
    "sg:tags":[
        "churches-pentecostal-independent",
        "churches-pentecostal"
    ],
    "wof:name":"Apostolic Life Center",
    "wof:placetype":"venue"
},
  "geometry": {"coordinates":[-76.466133,39.31498],"type":"Point"}
}