{
  "type": "Feature",
  "properties": {
    "iso:country":"US",
    "sg:address":"2 Hamill Rd Ste 332",
    "sg:city":"Baltimore",
    "sg:classifiers":[
        {
            "category":"Professional",
            "subcategory":"Lawyer & Legal Services",
            "type":"Services"
        }
    ],
    "sg:phone":"+1 410 464 0100",
    "sg:postcode":"21210",
    "sg:province":"MD",
    "wof:name":"Lapides Julian",
    "wof:placetype":"venue"
},
  "geometry": {"coordinates":[-76.64510300000001,39.351898],"type":"Point"}
}