{
  "type": "Feature",
  "properties": {
    "addr:full":"2900 Greenmount Ave Baltimore MD 21218",
    "addr:housenumber":"2900",
    "addr:postcode":"21218",
    "addr:street":"Greenmount Ave",
    "iso:country":"US",
    "sg:address":"2900 Greenmount Ave",
    "sg:city":"Baltimore",
    "sg:classifiers":[
        {
            "category":"Shopping",
            "subcategory":"Discount & Variety Stores",
            "type":"Retail Goods"
        }
    ],
    "sg:phone":"+1 410 235 6564",
    "sg:postcode":"21218",
    "sg:province":"MD",
    "wof:name":"Magic Discount Corp",
    "wof:placetype":"venue"
},
  "geometry": {"coordinates":[-76.609443,39.323772],"type":"Point"}
}