{
  "type": "Feature",
  "properties": {
    "iso:country":"US",
    "sg:address":"116 N Bohemia Ave",
    "sg:city":"Cecilton",
    "sg:classifiers":[
        {
            "category":"Real Estate",
            "subcategory":"Real Estate Agent",
            "type":"Services"
        }
    ],
    "sg:phone":"+1 410 275 2118",
    "sg:postcode":"21913",
    "sg:province":"MD",
    "wof:name":"Gunther Mc Clary Real Estate",
    "wof:placetype":"venue"
},
  "geometry": {"coordinates":[-75.866983,39.40557],"type":"Point"}
}