{
  "type": "Feature",
  "properties": {
    "iso:country":"US",
    "sg:address":"6067 Camelback Ln",
    "sg:city":"Columbia",
    "sg:classifiers":[
        {
            "category":"Retail",
            "subcategory":"Repair Shop",
            "type":"Services"
        }
    ],
    "sg:phone":"+1 410 997 0311",
    "sg:postcode":"21045",
    "sg:province":"MD",
    "sg:tags":[
        "door"
    ],
    "wof:name":"Door To Door Svc Co",
    "wof:placetype":"venue"
},
  "geometry": {"coordinates":[-76.852227,39.204915],"type":"Point"}
}