{
  "type": "Feature",
  "properties": {
    "iso:country":"US",
    "sg:address":"146 Leisters Church Rd",
    "sg:city":"Westminster",
    "sg:classifiers":[
        {
            "category":"Wholesale",
            "subcategory":"Non-durable Goods",
            "type":"Manufacturing & Wholesale Goods"
        },
        {
            "category":"Personal",
            "subcategory":"Barber",
            "type":"Services"
        }
    ],
    "sg:phone":"+1 410 751 2011",
    "sg:postcode":"21157",
    "sg:province":"MD",
    "sg:tags":[
        "beauty",
        "supply",
        "equipment",
        "salons-equipment",
        "supplies-wholesale",
        "manufacturer"
    ],
    "wof:name":"Syngenex",
    "wof:placetype":"venue"
},
  "geometry": {"coordinates":[-76.925209,39.580031],"type":"Point"}
}