{
  "type": "Feature",
  "properties": {
    "iso:country":"US",
    "sg:address":"19100 Annapolis Way",
    "sg:city":"Montgomery Village",
    "sg:classifiers":[
        {
            "category":"Professional",
            "subcategory":"Management & Consulting",
            "type":"Services"
        }
    ],
    "sg:phone":"+1 301 948 6121",
    "sg:postcode":"20886",
    "sg:province":"MD",
    "sg:tags":[
        "business"
    ],
    "wof:name":"Ralph W Notto & Associates",
    "wof:placetype":"venue"
},
  "geometry": {"coordinates":[-77.20249099999999,39.170421],"type":"Point"}
}