{
  "type": "Feature",
  "properties": {
    "addr:full":"36 Greene St Cumberland MD 21502",
    "addr:housenumber":"36",
    "addr:postcode":"21502",
    "addr:street":"Greene St",
    "iso:country":"US",
    "sg:address":"36 Greene St",
    "sg:city":"Cumberland",
    "sg:classifiers":[
        {
            "category":"Personal",
            "subcategory":"Massage",
            "type":"Services"
        },
        {
            "category":"Health Services",
            "subcategory":"Health Practitioner",
            "type":"Services"
        }
    ],
    "sg:phone":"+1 301 722 6010",
    "sg:postcode":"21502",
    "sg:province":"MD",
    "wof:name":"Allegheny Center For Massage",
    "wof:placetype":"venue"
},
  "geometry": {"coordinates":[-78.764535,39.6502],"type":"Point"}
}