{
  "type": "Feature",
  "properties": {
    "iso:country":"US",
    "sg:address":"1201 Dual Hwy",
    "sg:city":"Hagerstown",
    "sg:classifiers":[
        {
            "category":"Professional",
            "subcategory":"Computer Services",
            "type":"Services"
        }
    ],
    "sg:phone":"+1 443 744 0912",
    "sg:postcode":"21740",
    "sg:province":"MD",
    "sg:tags":[
        "website",
        "design"
    ],
    "wof:name":"Website Shapers",
    "wof:placetype":"venue"
},
  "geometry": {"coordinates":[-77.70083,39.63039],"type":"Point"}
}