{
  "type": "Feature",
  "properties": {
    "iso:country":"US",
    "sg:address":"9 Rambling Oaks Way",
    "sg:city":"Baltimore",
    "sg:classifiers":[
        {
            "category":"Real Estate",
            "subcategory":"Real Estate Operator",
            "type":"Services"
        }
    ],
    "sg:phone":"+1 410 747 0234",
    "sg:postcode":"21228",
    "sg:province":"MD",
    "sg:tags":[
        "building",
        "apartment"
    ],
    "wof:name":"Cedar Run White Oak Apartments",
    "wof:placetype":"venue"
},
  "geometry": {"coordinates":[-76.72312700000001,39.287544],"type":"Point"}
}