{
  "type": "Feature",
  "properties": {
    "addr:full":"2133 Defense Hwy Crofton MD 21114",
    "addr:postcode":"2133;21114",
    "addr:street":"Defense Hwy",
    "iso:country":"US",
    "sg:address":"2133 Defense Hwy",
    "sg:city":"Crofton",
    "sg:classifiers":[
        {
            "category":"Professional",
            "subcategory":"Lawyer & Legal Services",
            "type":"Services"
        }
    ],
    "sg:phone":"+1 410 721 3900",
    "sg:postcode":"21114",
    "sg:province":"MD",
    "sg:tags":[
        "attorney"
    ],
    "wof:name":"Callahan & Callahan",
    "wof:placetype":"venue"
},
  "geometry": {"coordinates":[-76.695318,38.992063],"type":"Point"}
}