{
  "type": "Feature",
  "properties": {
    "addr:full":"12788 Old Fort Rd Fort Washington MD 20744",
    "addr:housenumber":"12788",
    "addr:postcode":"20744",
    "addr:street":"Old Fort Rd",
    "iso:country":"US",
    "sg:address":"12788 Old Fort Rd",
    "sg:city":"Fort Washington",
    "sg:classifiers":[
        {
            "category":"Shopping",
            "type":"Retail Goods"
        }
    ],
    "sg:phone":"+1 301 203 4218",
    "sg:postcode":"20744",
    "sg:province":"MD",
    "sg:tags":[
        "cosmetic",
        "perfume"
    ],
    "wof:name":"Pink Beauty Supplies",
    "wof:placetype":"venue"
},
  "geometry": {"coordinates":[-76.987472,38.713173],"type":"Point"}
}