{
  "type": "Feature",
  "properties": {
    "iso:country":"US",
    "sg:address":"407 S. Camp Meade Rd",
    "sg:city":"Linthicum",
    "sg:classifiers":[
        {
            "category":"Fast Food",
            "type":"Food & Drink"
        },
        {
            "category":"Restaurant",
            "type":"Food & Drink"
        }
    ],
    "sg:phone":"+1 410 859 8181",
    "sg:postcode":"21090",
    "sg:province":"MD",
    "sg:tags":[
        "traditional",
        "american"
    ],
    "wof:name":"Bernie's Grille",
    "wof:placetype":"venue"
},
  "geometry": {"coordinates":[-76.655277,39.200727],"type":"Point"}
}