{
  "type": "Feature",
  "properties": {
    "iso:country":"US",
    "sg:address":"516 Sussex Rd",
    "sg:city":"Towson",
    "sg:classifiers":[
        {
            "category":"Professional",
            "subcategory":"Management & Consulting",
            "type":"Services"
        },
        {
            "category":"Professional",
            "subcategory":"Research",
            "type":"Services"
        }
    ],
    "sg:phone":"+1 410 825 7179",
    "sg:postcode":"21286",
    "sg:province":"MD",
    "sg:tags":[
        "marketing",
        "analysis",
        "economic",
        "consultant",
        "market"
    ],
    "wof:name":"Sussex Marketing Solutions",
    "wof:placetype":"venue"
},
  "geometry": {"coordinates":[-76.606756,39.384729],"type":"Point"}
}