{
  "type": "Feature",
  "properties": {
    "addr:full":"7 Perhall Ct Baltimore MD 21236",
    "addr:housenumber":"7",
    "addr:postcode":"21236",
    "addr:street":"Perhall Ct",
    "iso:country":"US",
    "sg:address":"7 Perhall Ct",
    "sg:city":"Baltimore",
    "sg:classifiers":[
        {
            "category":"Shopping",
            "subcategory":"Computers & Home Electronics",
            "type":"Retail Goods"
        }
    ],
    "sg:phone":"+1 410 529 9565",
    "sg:postcode":"21236",
    "sg:province":"MD",
    "sg:tags":[
        "software"
    ],
    "wof:name":"Premium Resources",
    "wof:placetype":"venue"
},
  "geometry": {"coordinates":[-76.47572099999999,39.410505],"type":"Point"}
}