{
  "type": "Feature",
  "properties": {
    "addr:full":"168 Carroll Island Rd Baltimore MD 21220",
    "addr:housenumber":"168",
    "addr:postcode":"21220",
    "addr:street":"Carroll Island Rd",
    "iso:country":"US",
    "sg:address":"168 Carroll Island Rd",
    "sg:city":"Baltimore",
    "sg:classifiers":[
        {
            "category":"Shopping",
            "subcategory":"Department Store",
            "type":"Retail Goods"
        }
    ],
    "sg:phone":"+1 410 335 3544",
    "sg:postcode":"21220",
    "sg:province":"MD",
    "sg:tags":[
        "shop"
    ],
    "wof:name":"Dollar General",
    "wof:placetype":"venue"
},
  "geometry": {"coordinates":[-76.39956599999999,39.337762],"type":"Point"}
}