{
  "type": "Feature",
  "properties": {
    "iso:country":"US",
    "sg:address":"610 9th Ave",
    "sg:city":"Brunswick",
    "sg:classifiers":[
        {
            "category":"Health Services",
            "subcategory":"Doctor",
            "type":"Services"
        }
    ],
    "sg:phone":"+1 301 834 6441",
    "sg:postcode":"21716",
    "sg:province":"MD",
    "sg:tags":[
        "surgeon",
        "oral"
    ],
    "wof:name":"Smith Kevin C DDS",
    "wof:placetype":"venue"
},
  "geometry": {"coordinates":[-77.61219800000001,39.316601],"type":"Point"}
}