{
  "type": "Feature",
  "properties": {
    "iso:country":"US",
    "sg:address":"3600 Crondall Ln",
    "sg:city":"Owings Mills",
    "sg:classifiers":[
        {
            "category":"Manufacturing",
            "subcategory":"Printing",
            "type":"Manufacturing & Wholesale Goods"
        }
    ],
    "sg:phone":"+1 410 581 5900",
    "sg:postcode":"21117",
    "sg:province":"MD",
    "sg:tags":[
        "publisher"
    ],
    "wof:name":"Arts & Kids",
    "wof:placetype":"venue"
},
  "geometry": {"coordinates":[-76.772519,39.435375],"type":"Point"}
}