{
  "type": "Feature",
  "properties": {
    "addr:full":"15104 Georgia Ave Rockville MD 20853",
    "addr:housenumber":"15104",
    "addr:postcode":"20853",
    "addr:street":"Georgia Ave",
    "iso:country":"US",
    "sg:address":"15104 Georgia Ave",
    "sg:city":"Rockville",
    "sg:classifiers":[
        {
            "category":"Conference Center",
            "type":"Public Place"
        }
    ],
    "sg:phone":"+1 301 474 7120",
    "sg:postcode":"20853",
    "sg:province":"MD",
    "sg:tags":[
        "lecture",
        "speakers",
        "seminar"
    ],
    "wof:name":"Patrick H Brown",
    "wof:placetype":"venue"
},
  "geometry": {"coordinates":[-77.077208,39.102683],"type":"Point"}
}