{
  "type": "Feature",
  "properties": {
    "iso:country":"US",
    "sg:address":"4810 Broom Dr",
    "sg:city":"Olney",
    "sg:classifiers":[
        {
            "category":"Wholesale",
            "subcategory":"Office Equipment",
            "type":"Manufacturing & Wholesale Goods"
        }
    ],
    "sg:phone":"+1 301 570 7767",
    "sg:postcode":"20832",
    "sg:province":"MD",
    "sg:tags":[
        "equipment-wholesale",
        "manufacturer",
        "furniture"
    ],
    "wof:name":"D & A Associates Inc",
    "wof:placetype":"venue"
},
  "geometry": {"coordinates":[-77.09675799999999,39.154206],"type":"Point"}
}