{
  "type": "Feature",
  "properties": {
    "addr:full":"14201 Sawmill Ct Phoenix MD 21131",
    "addr:housenumber":"14201",
    "addr:postcode":"21131",
    "addr:street":"Sawmill Ct",
    "iso:country":"US",
    "sg:address":"14201 Sawmill Ct",
    "sg:city":"Phoenix",
    "sg:classifiers":[
        {
            "category":"Travel",
            "subcategory":"Travel Agent",
            "type":"Entertainment"
        }
    ],
    "sg:phone":"+1 410 592 5066",
    "sg:postcode":"21131",
    "sg:province":"MD",
    "sg:tags":[
        "agency",
        "services-commercial"
    ],
    "wof:name":"Carefree Travel",
    "wof:placetype":"venue"
},
  "geometry": {"coordinates":[-76.547501,39.51363],"type":"Point"}
}