{
  "type": "Feature",
  "properties": {
    "iso:country":"US",
    "sg:address":"1610 New York Ave",
    "sg:city":"Knoxville",
    "sg:classifiers":[
        {
            "category":"Arts & Performance",
            "subcategory":"Art Gallery",
            "type":"Entertainment"
        }
    ],
    "sg:phone":"+1 301 834 5073",
    "sg:postcode":"21758",
    "sg:province":"MD",
    "sg:tags":[
        "fine",
        "artist"
    ],
    "wof:name":"Diane G Wright",
    "wof:placetype":"venue"
},
  "geometry": {"coordinates":[-77.614727,39.32981],"type":"Point"}
}