{
  "type": "Feature",
  "properties": {
    "iso:country":"US",
    "sg:address":"7425 Annapolis Rd",
    "sg:city":"Hyattsville",
    "sg:classifiers":[
        {
            "category":"Home & Garden",
            "subcategory":"Carpets & Floor Coverings",
            "type":"Retail Goods"
        }
    ],
    "sg:phone":"+1 301 577 1211",
    "sg:postcode":"20784",
    "sg:province":"MD",
    "sg:tags":[
        "carpeting"
    ],
    "wof:name":"Perge Company Inc",
    "wof:placetype":"venue"
},
  "geometry": {"coordinates":[-76.887497,38.9487],"type":"Point"}
}