{
  "type": "Feature",
  "properties": {
    "iso:country":"US",
    "sg:address":"23800 Grace Creek Rd",
    "sg:city":"Bozman",
    "sg:classifiers":[
        {
            "category":"Real Estate",
            "subcategory":"Developer",
            "type":"Services"
        }
    ],
    "sg:phone":"+1 410 745 3325",
    "sg:postcode":"21612",
    "sg:province":"MD",
    "wof:name":"Sachs Properties Inc",
    "wof:placetype":"venue"
},
  "geometry": {"coordinates":[-76.2519,38.751189],"type":"Point"}
}