{
  "type": "Feature",
  "properties": {
    "addr:full":"2833 Odonnell St Ste 201 Baltimore MD 21224",
    "addr:housenumber":"2833",
    "addr:postcode":"21224",
    "addr:street":"Odonnell St Ste 201",
    "iso:country":"US",
    "sg:address":"2833 Odonnell St Ste 201",
    "sg:city":"Baltimore",
    "sg:classifiers":[
        {
            "category":"Organizations",
            "subcategory":"Professional Association",
            "type":"Services"
        }
    ],
    "sg:phone":"+1 410 563 2800",
    "sg:postcode":"21224",
    "sg:province":"MD",
    "sg:tags":[
        "business",
        "trade"
    ],
    "wof:name":"Women's Business Center Limited Partnership",
    "wof:placetype":"venue"
},
  "geometry": {"coordinates":[-76.576008,39.280025],"type":"Point"}
}