{
  "type": "Feature",
  "properties": {
    "addr:full":"913 E Broadway Bel Air MD 21014",
    "addr:housenumber":"913",
    "addr:postcode":"21014",
    "addr:street":"E Broadway",
    "iso:country":"US",
    "sg:address":"913 E Broadway",
    "sg:city":"Bel Air",
    "sg:classifiers":[
        {
            "category":"Professional",
            "subcategory":"Management & Consulting",
            "type":"Services"
        }
    ],
    "sg:phone":"+1 410 420 0939",
    "sg:postcode":"21014",
    "sg:province":"MD",
    "sg:tags":[
        "consultant",
        "business"
    ],
    "wof:name":"Meritquest Legal Nurse Cnsltng",
    "wof:placetype":"venue"
},
  "geometry": {"coordinates":[-76.334391,39.547879],"type":"Point"}
}