{
  "type": "Feature",
  "properties": {
    "addr:full":"5401 Twin Knolls Rd Columbia MD 21045",
    "addr:housenumber":"5401",
    "addr:postcode":"21045",
    "addr:street":"Twin Knolls Rd",
    "iso:country":"US",
    "sg:address":"5401 Twin Knolls Rd",
    "sg:city":"Columbia",
    "sg:classifiers":[
        {
            "category":"Professional",
            "subcategory":"Lawyer & Legal Services",
            "type":"Services"
        }
    ],
    "sg:phone":"+1 301 596 4664",
    "sg:postcode":"21045",
    "sg:province":"MD",
    "wof:name":"Bonnie Wylie",
    "wof:placetype":"venue"
},
  "geometry": {"coordinates":[-76.842741,39.220695],"type":"Point"}
}