{
  "type": "Feature",
  "properties": {
    "iso:country":"US",
    "sg:address":"6480 Old Waterloo Rd",
    "sg:city":"Elkridge",
    "sg:classifiers":[
        {
            "category":"Retail",
            "subcategory":"Photofinishing",
            "type":"Services"
        },
        {
            "category":"Shopping",
            "subcategory":"Pharmacy",
            "type":"Retail Goods"
        }
    ],
    "sg:phone":"+1 410 799 0291",
    "sg:postcode":"21075",
    "sg:province":"MD",
    "sg:tags":[
        "photo",
        "finishing",
        "first",
        "aid",
        "supply"
    ],
    "sg:website":"http://www.cvs.com",
    "wof:name":"CVS/pharmacy",
    "wof:placetype":"venue"
},
  "geometry": {"coordinates":[-76.793633,39.19215],"type":"Point"}
}