{
  "type": "Feature",
  "properties": {
    "addr:full":"600 Chumleigh Rd Baltimore MD 21212",
    "addr:housenumber":"600",
    "addr:postcode":"21212",
    "addr:street":"Chumleigh Rd",
    "iso:country":"US",
    "sg:address":"600 Chumleigh Rd",
    "sg:city":"Baltimore",
    "sg:classifiers":[
        {
            "category":"Professional",
            "subcategory":"Management & Consulting",
            "type":"Services"
        }
    ],
    "sg:phone":"+1 410 321 8732",
    "sg:postcode":"21212",
    "sg:province":"MD",
    "sg:tags":[
        "consultant",
        "educational"
    ],
    "wof:name":"Antonio C Wolff",
    "wof:placetype":"venue"
},
  "geometry": {"coordinates":[-76.606667,39.38084],"type":"Point"}
}