{
  "type": "Feature",
  "properties": {
    "addr:full":"10 Quail Hollow Rd Lutherville MD 21093",
    "addr:housenumber":"10",
    "addr:postcode":"21093",
    "addr:street":"Quail Hollow Rd",
    "iso:country":"US",
    "sg:address":"10 Quail Hollow Rd",
    "sg:city":"Lutherville",
    "sg:classifiers":[
        {
            "category":"Professional",
            "subcategory":"Engineering",
            "type":"Services"
        }
    ],
    "sg:phone":"+1 410 823 0774",
    "sg:postcode":"21093",
    "sg:province":"MD",
    "sg:tags":[
        "engineer"
    ],
    "wof:name":"F Pierce Linaweaver & Assoc",
    "wof:placetype":"venue"
},
  "geometry": {"coordinates":[-76.665496,39.42413],"type":"Point"}
}