{
  "type": "Feature",
  "properties": {
    "iso:country":"US",
    "sg:address":"1214 Lake Falls Rd",
    "sg:city":"Baltimore",
    "sg:classifiers":[
        {
            "category":"Professional",
            "type":"Services"
        }
    ],
    "sg:phone":"+1 410 377 6946",
    "sg:postcode":"21210",
    "sg:province":"MD",
    "sg:tags":[
        "science",
        "consulting",
        "cardiology",
        "consultant",
        "academic"
    ],
    "wof:name":"Thomas Aversano",
    "wof:placetype":"venue"
},
  "geometry": {"coordinates":[-76.64703,39.374163],"type":"Point"}
}