{
  "type": "Feature",
  "properties": {
    "iso:country":"US",
    "sg:address":"12636 Sunset Ave",
    "sg:city":"Ocean City",
    "sg:classifiers":[
        {
            "category":"Food & Beverages",
            "subcategory":"Specialty",
            "type":"Retail Goods"
        }
    ],
    "sg:phone":"+1 410 213 0353",
    "sg:postcode":"21842",
    "sg:province":"MD",
    "sg:tags":[
        "gourmet",
        "shop"
    ],
    "wof:name":"Artemisia",
    "wof:placetype":"venue"
},
  "geometry": {"coordinates":[-75.114309,38.327878],"type":"Point"}
}