{
  "type": "Feature",
  "properties": {
    "iso:country":"US",
    "sg:address":"414 Main St",
    "sg:city":"Gaithersburg",
    "sg:classifiers":[
        {
            "category":"Health Services",
            "subcategory":"Doctor",
            "type":"Services"
        }
    ],
    "sg:phone":"+1 301 548 1001",
    "sg:postcode":"20878",
    "sg:province":"MD",
    "sg:tags":[
        "clinic"
    ],
    "wof:name":"Reliable Medical Svc",
    "wof:placetype":"venue"
},
  "geometry": {"coordinates":[-77.236062,39.121008],"type":"Point"}
}