{
  "type": "Feature",
  "properties": {
    "iso:country":"US",
    "sg:address":"2071 York Rd",
    "sg:city":"Timonium",
    "sg:classifiers":[
        {
            "category":"Retail",
            "subcategory":"Auto Repair",
            "type":"Services"
        }
    ],
    "sg:phone":"+1 410 561 8868",
    "sg:postcode":"21093",
    "sg:province":"MD",
    "sg:tags":[
        "automobile",
        "lubrication"
    ],
    "wof:name":"Jiffy Lube",
    "wof:placetype":"venue"
},
  "geometry": {"coordinates":[-76.625891,39.43991],"type":"Point"}
}