{
  "type": "Feature",
  "properties": {
    "addr:full":"11419 Eastern Ave Middle River MD 21220",
    "addr:housenumber":"11419",
    "addr:postcode":"21220",
    "addr:street":"Eastern Ave",
    "iso:country":"US",
    "sg:address":"11419 Eastern Ave",
    "sg:city":"Middle River",
    "sg:classifiers":[
        {
            "category":"Shopping",
            "subcategory":"Bicycles & Sporting Goods",
            "type":"Retail Goods"
        }
    ],
    "sg:phone":"+1 410 335 0770",
    "sg:postcode":"21220",
    "sg:province":"MD",
    "wof:name":"Sports World-Wedekind's",
    "wof:placetype":"venue"
},
  "geometry": {"coordinates":[-76.401703,39.3396],"type":"Point"}
}