{
  "type": "Feature",
  "properties": {
    "addr:full":"40 Harrys Ln North East MD 21901",
    "addr:housenumber":"40",
    "addr:postcode":"21901",
    "addr:street":"Harrys Ln North",
    "iso:country":"US",
    "sg:address":"40 Harrys Ln",
    "sg:city":"North East",
    "sg:classifiers":[
        {
            "category":"Professional",
            "type":"Services"
        }
    ],
    "sg:phone":"+1 410 287 7217",
    "sg:postcode":"21901",
    "sg:province":"MD",
    "sg:tags":[
        "establishment"
    ],
    "wof:name":"Lantern Queen",
    "wof:placetype":"venue"
},
  "geometry": {"coordinates":[-75.960162,39.486352],"type":"Point"}
}