{
  "type": "Feature",
  "properties": {
    "addr:full":"9113 Belair Rd Nottingham MD 21236",
    "addr:housenumber":"9113",
    "addr:postcode":"21236",
    "addr:street":"Belair Rd",
    "iso:country":"US",
    "sg:address":"9113 Belair Rd",
    "sg:city":"Nottingham",
    "sg:classifiers":[
        {
            "category":"Shopping",
            "subcategory":"Clothing, Apparel, & Fashions",
            "type":"Retail Goods"
        },
        {
            "category":"Banks & Credit Unions",
            "subcategory":"Bank",
            "type":"Services"
        }
    ],
    "sg:phone":"+1 410 256 8353",
    "sg:postcode":"21236",
    "sg:province":"MD",
    "sg:tags":[
        "second",
        "consignment",
        "hand"
    ],
    "wof:name":"Friends Consignment",
    "wof:placetype":"venue"
},
  "geometry": {"coordinates":[-76.477617,39.401026],"type":"Point"}
}