{
  "type": "Feature",
  "properties": {
    "addr:full":"506 S B Baltimore MD 21201",
    "addr:housenumber":"506",
    "addr:postcode":"21201",
    "addr:street":"S",
    "iso:country":"US",
    "sg:address":"506 S B",
    "sg:city":"Baltimore",
    "sg:classifiers":[
        {
            "category":"Shopping",
            "subcategory":"Clothing, Apparel, & Fashions",
            "type":"Retail Goods"
        }
    ],
    "sg:phone":"+1 410 276 5115",
    "sg:postcode":"21201",
    "sg:province":"MD",
    "sg:tags":[
        "lingerie"
    ],
    "wof:name":"Love Zone Lingerie",
    "wof:placetype":"venue"
},
  "geometry": {"coordinates":[-76.622597,39.2957],"type":"Point"}
}