{
  "type": "Feature",
  "properties": {
    "addr:full":"362 Cork Rd Glen Burnie MD 21060",
    "addr:housenumber":"362",
    "addr:postcode":"21060",
    "addr:street":"Cork Rd",
    "iso:country":"US",
    "sg:address":"362 Cork Rd",
    "sg:city":"Glen Burnie",
    "sg:classifiers":[
        {
            "category":"Arts & Performance",
            "subcategory":"Theater",
            "type":"Entertainment"
        }
    ],
    "sg:phone":"+1 410 255 1101",
    "sg:postcode":"21060",
    "sg:province":"MD",
    "sg:tags":[
        "live",
        "music"
    ],
    "wof:name":"Gray Fox DJ Svc",
    "wof:placetype":"venue"
},
  "geometry": {"coordinates":[-76.58224800000001,39.14956],"type":"Point"}
}