{
  "type": "Feature",
  "properties": {
    "iso:country":"US",
    "sg:address":"9701 Fields Rd",
    "sg:city":"Gaithersburg",
    "sg:classifiers":[
        {
            "category":"Professional",
            "subcategory":"Management & Consulting",
            "type":"Services"
        }
    ],
    "sg:phone":"+1 301 670 0967",
    "sg:postcode":"20878",
    "sg:province":"MD",
    "sg:tags":[
        "development",
        "marketing",
        "business"
    ],
    "wof:name":"John Redmond",
    "wof:placetype":"venue"
},
  "geometry": {"coordinates":[-77.195785,39.11236],"type":"Point"}
}