{
  "type": "Feature",
  "properties": {
    "addr:full":"7717 Suitt Dr Pasadena MD 21122",
    "addr:housenumber":"7717",
    "addr:postcode":"21122",
    "addr:street":"Suitt Dr",
    "iso:country":"US",
    "sg:address":"7717 Suitt Dr",
    "sg:city":"Pasadena",
    "sg:classifiers":[
        {
            "category":"Insurance",
            "subcategory":"Insurance Agent",
            "type":"Services"
        },
        {
            "category":"Insurance",
            "subcategory":"Hazard Insurance",
            "type":"Services"
        }
    ],
    "sg:phone":"+1 410 437 1120",
    "sg:postcode":"21122",
    "sg:province":"MD",
    "sg:tags":[
        "consultant",
        "analyst"
    ],
    "wof:name":"J F Wenger",
    "wof:placetype":"venue"
},
  "geometry": {"coordinates":[-76.49594,39.146318],"type":"Point"}
}