{
  "type": "Feature",
  "properties": {
    "iso:country":"US",
    "sg:address":"585 Main St Ste 143",
    "sg:city":"Laurel",
    "sg:classifiers":[
        {
            "category":"Community Center",
            "type":"Public Place"
        }
    ],
    "sg:phone":"+1 301 725 8855",
    "sg:postcode":"20707",
    "sg:province":"MD",
    "sg:tags":[
        "medical"
    ],
    "wof:name":"Clinicare Medical Centers of Laurel",
    "wof:placetype":"venue"
},
  "geometry": {"coordinates":[-76.852856,39.108136],"type":"Point"}
}