{
  "type": "Feature",
  "properties": {
    "addr:full":"7 S Main St Berlin MD 21811",
    "addr:housenumber":"7",
    "addr:postcode":"21811",
    "addr:street":"S Main St",
    "iso:country":"US",
    "sg:address":"7 S Main St",
    "sg:city":"Berlin",
    "sg:classifiers":[
        {
            "category":"Food & Beverages",
            "subcategory":"Specialty",
            "type":"Retail Goods"
        }
    ],
    "sg:phone":"+1 410 641 4000",
    "sg:postcode":"21811",
    "sg:province":"MD",
    "sg:tags":[
        "tea",
        "coffee"
    ],
    "wof:name":"Tea By The Sea",
    "wof:placetype":"venue"
},
  "geometry": {"coordinates":[-75.218763,38.324421],"type":"Point"}
}