{
  "type": "Feature",
  "properties": {
    "addr:full":"173 Teal Cir Berlin MD 21811",
    "addr:housenumber":"173",
    "addr:postcode":"21811",
    "addr:street":"Teal Cir",
    "iso:country":"US",
    "sg:address":"173 Teal Cir",
    "sg:city":"Berlin",
    "sg:classifiers":[
        {
            "category":"Retail",
            "subcategory":"Repair Shop",
            "type":"Services"
        }
    ],
    "sg:phone":"+1 410 208 6073",
    "sg:postcode":"21811",
    "sg:province":"MD",
    "sg:tags":[
        "equipment"
    ],
    "wof:name":"K B Assoc",
    "wof:placetype":"venue"
},
  "geometry": {"coordinates":[-75.138882,38.394936],"type":"Point"}
}