{
  "type": "Feature",
  "properties": {
    "iso:country":"US",
    "sg:address":"5706 Coley Ct",
    "sg:city":"Baltimore",
    "sg:classifiers":[
        {
            "category":"Building & Trades",
            "subcategory":"Construction",
            "type":"Services"
        }
    ],
    "sg:phone":"+1 410 433 7110",
    "sg:postcode":"21210",
    "sg:province":"MD",
    "sg:tags":[
        "system",
        "contractor",
        "air conditioning"
    ],
    "wof:name":"Marion J Ball Business Ac",
    "wof:placetype":"venue"
},
  "geometry": {"coordinates":[-76.635453,39.367206],"type":"Point"}
}