{
  "type": "Feature",
  "properties": {
    "addr:full":"255 Thompson Ave Glen Burnie MD 21060",
    "addr:housenumber":"255",
    "addr:postcode":"21060",
    "addr:street":"Thompson Ave",
    "iso:country":"US",
    "sg:address":"255 Thompson Ave",
    "sg:city":"Glen Burnie",
    "sg:classifiers":[
        {
            "category":"Building & Trades",
            "subcategory":"Construction",
            "type":"Services"
        }
    ],
    "sg:phone":"+1 410 768 1863",
    "sg:postcode":"21060",
    "sg:province":"MD",
    "sg:tags":[
        "house"
    ],
    "wof:name":"G & Tj Construction",
    "wof:placetype":"venue"
},
  "geometry": {"coordinates":[-76.609725,39.166636],"type":"Point"}
}