{
  "type": "Feature",
  "properties": {
    "addr:full":"8314 Harford Rd Parkville MD 21234",
    "addr:housenumber":"8314",
    "addr:postcode":"21234",
    "addr:street":"Harford Rd",
    "iso:country":"US",
    "sg:address":"8314 Harford Rd",
    "sg:city":"Parkville",
    "sg:classifiers":[
        {
            "category":"Home & Garden",
            "subcategory":"Household Appliances",
            "type":"Retail Goods"
        },
        {
            "category":"Building & Trades",
            "subcategory":"Construction",
            "type":"Services"
        },
        {
            "category":"Professional",
            "subcategory":"Engineering",
            "type":"Services"
        }
    ],
    "sg:phone":"+1 410 663 5900",
    "sg:postcode":"21234",
    "sg:province":"MD",
    "sg:tags":[
        "dishwashing",
        "system",
        "machine",
        "equipment",
        "contractor",
        "air conditioning"
    ],
    "sg:website":"http://www.enviroconassociates.com",
    "wof:name":"Envirocon Associate Inc",
    "wof:placetype":"venue"
},
  "geometry": {"coordinates":[-76.537758,39.379711],"type":"Point"}
}