{
  "type": "Feature",
  "properties": {
    "addr:full":"4300 Montgomery Ave Ste 102 Bethesda MD 20814",
    "addr:housenumber":"4300",
    "addr:postcode":"20814",
    "addr:street":"Montgomery Ave Ste 102",
    "iso:country":"US",
    "sg:address":"4300 Montgomery Ave Ste 102",
    "sg:city":"Bethesda",
    "sg:classifiers":[
        {
            "category":"Professional",
            "subcategory":"Lawyer & Legal Services",
            "type":"Services"
        }
    ],
    "sg:phone":"+1 301 652 6903",
    "sg:postcode":"20814",
    "sg:province":"MD",
    "wof:name":"Gruber Moia Tamber Esquire",
    "wof:placetype":"venue"
},
  "geometry": {"coordinates":[-77.086403,38.986],"type":"Point"}
}