{
  "type": "Feature",
  "properties": {
    "iso:country":"US",
    "sg:address":"4 E University Pkwy",
    "sg:city":"Baltimore",
    "sg:classifiers":[
        {
            "category":"Organizations",
            "subcategory":"Religious Organization",
            "type":"Services"
        }
    ],
    "sg:phone":"+1 410 467 3094",
    "sg:postcode":"21218",
    "sg:province":"MD",
    "wof:name":"Cathedral Church of the I",
    "wof:placetype":"venue"
},
  "geometry": {"coordinates":[-76.617659,39.332613],"type":"Point"}
}