{
  "type": "Feature",
  "properties": {
    "addr:full":"5 Wild Olive Ct Potomac MD 20854",
    "addr:housenumber":"5",
    "addr:postcode":"20854",
    "addr:street":"Wild Olive Ct",
    "iso:country":"US",
    "sg:address":"5 Wild Olive Ct",
    "sg:city":"Potomac",
    "sg:classifiers":[
        {
            "category":"Building & Trades",
            "subcategory":"Construction",
            "type":"Services"
        }
    ],
    "sg:phone":"+1 301 251 8895",
    "sg:postcode":"20854",
    "sg:province":"MD",
    "sg:tags":[
        "altering",
        "remodeling",
        "contractor"
    ],
    "wof:name":"Arken Enterprises, Inc.",
    "wof:placetype":"venue"
},
  "geometry": {"coordinates":[-77.173035,39.053836],"type":"Point"}
}