{
  "type": "Feature",
  "properties": {
    "addr:full":"1439 W Jarrettsville Rd Jarrettsville MD 21084",
    "addr:housenumber":"1439",
    "addr:postcode":"21084",
    "addr:street":"W Jarrettsville Rd",
    "iso:country":"US",
    "sg:address":"1439 W Jarrettsville Rd",
    "sg:city":"Jarrettsville",
    "sg:classifiers":[
        {
            "category":"Building & Trades",
            "subcategory":"Construction",
            "type":"Services"
        }
    ],
    "sg:phone":"+1 410 836 9666",
    "sg:postcode":"21084",
    "sg:province":"MD",
    "sg:tags":[
        "excavating",
        "contractor"
    ],
    "wof:name":"Jarrettsville Excavation",
    "wof:placetype":"venue"
},
  "geometry": {"coordinates":[-76.441028,39.598605],"type":"Point"}
}