{
  "type": "Feature",
  "properties": {
    "addr:full":"924 N Salisbury Blvd Salisbury MD 21801",
    "addr:housenumber":"924",
    "addr:postcode":"21801",
    "addr:street":"N Salisbury Blvd",
    "iso:country":"US",
    "sg:address":"924 N Salisbury Blvd",
    "sg:city":"Salisbury",
    "sg:classifiers":[
        {
            "category":"Autos & Motor Vehicles",
            "subcategory":"Automobile Sales",
            "type":"Retail Goods"
        }
    ],
    "sg:phone":"+1 410 546 8205",
    "sg:postcode":"21801",
    "sg:province":"MD",
    "sg:tags":[
        "car",
        "dealer"
    ],
    "wof:name":"Vic Gue Auto Sales",
    "wof:placetype":"venue"
},
  "geometry": {"coordinates":[-75.59283499999999,38.374269],"type":"Point"}
}