{
  "type": "Feature",
  "properties": {
    "iso:country":"US",
    "sg:address":"116 Derwood Cir",
    "sg:city":"Rockville",
    "sg:classifiers":[
        {
            "category":"Wholesale",
            "subcategory":"Auto Parts",
            "type":"Manufacturing & Wholesale Goods"
        }
    ],
    "sg:phone":"+1 301 294 9464",
    "sg:postcode":"20850",
    "sg:province":"MD",
    "sg:tags":[
        "body",
        "automobile",
        "shop"
    ],
    "wof:name":"Mattos Inc",
    "wof:placetype":"venue"
},
  "geometry": {"coordinates":[-77.152193,39.105684],"type":"Point"}
}