{
  "type": "Feature",
  "properties": {
    "iso:country":"US",
    "sg:address":"1301 York Rd",
    "sg:city":"Lutherville",
    "sg:classifiers":[
        {
            "category":"Professional",
            "subcategory":"Management & Consulting",
            "type":"Services"
        }
    ],
    "sg:phone":"+1 410 321 1792",
    "sg:postcode":"21093",
    "sg:province":"MD",
    "sg:tags":[
        "counselor",
        "public",
        "relations"
    ],
    "wof:name":"Columbia Financial Group",
    "wof:placetype":"venue"
},
  "geometry": {"coordinates":[-76.61655399999999,39.420487],"type":"Point"}
}