{
  "type": "Feature",
  "properties": {
    "addr:full":"6 Grice St Berlin MD 21811",
    "addr:housenumber":"6",
    "addr:postcode":"21811",
    "addr:street":"Grice St",
    "iso:country":"US",
    "sg:address":"6 Grice St",
    "sg:city":"Berlin",
    "sg:classifiers":[
        {
            "category":"Manufacturing",
            "subcategory":"Printing",
            "type":"Manufacturing & Wholesale Goods"
        }
    ],
    "sg:phone":"+1 410 641 4878",
    "sg:postcode":"21811",
    "sg:province":"MD",
    "sg:tags":[
        "screen"
    ],
    "wof:name":"Action Island Imprinters",
    "wof:placetype":"venue"
},
  "geometry": {"coordinates":[-75.215991,38.332315],"type":"Point"}
}