{
  "type": "Feature",
  "properties": {
    "addr:full":"100 Church Ln Baltimore MD 21208",
    "addr:housenumber":"100",
    "addr:postcode":"21208",
    "addr:street":"Church Ln",
    "iso:country":"US",
    "sg:address":"100 Church Ln",
    "sg:city":"Baltimore",
    "sg:classifiers":[
        {
            "category":"Professional",
            "subcategory":"Lawyer & Legal Services",
            "type":"Services"
        }
    ],
    "sg:phone":"+1 410 962 8580",
    "sg:postcode":"21208",
    "sg:province":"MD",
    "wof:name":"Cheslock Arthur S Atty",
    "wof:placetype":"venue"
},
  "geometry": {"coordinates":[-76.63445299999999,39.344292],"type":"Point"}
}