{
  "type": "Feature",
  "properties": {
    "iso:country":"US",
    "sg:address":"11710 Baltimore Ave",
    "sg:city":"Beltsville",
    "sg:classifiers":[
        {
            "category":"Professional",
            "type":"Services"
        }
    ],
    "sg:phone":"+1 301 210 3617",
    "sg:postcode":"20705",
    "sg:province":"MD",
    "sg:tags":[
        "establishment"
    ],
    "wof:name":"BCC",
    "wof:placetype":"venue"
},
  "geometry": {"coordinates":[-76.901826,39.045604],"type":"Point"}
}