{
  "type": "Feature",
  "properties": {
    "addr:full":"2633 Purnell Dr Gwynn Oak MD 21207",
    "addr:housenumber":"2633",
    "addr:postcode":"21207",
    "addr:street":"Purnell Dr",
    "iso:country":"US",
    "sg:address":"2633 Purnell Dr",
    "sg:city":"Gwynn Oak",
    "sg:classifiers":[
        {
            "category":"Social Services",
            "type":"Services"
        }
    ],
    "sg:phone":"+1 410 281 7737",
    "sg:postcode":"21207",
    "sg:province":"MD",
    "sg:tags":[
        "organization",
        "welfare"
    ],
    "wof:name":"Magic Unity House For Girls",
    "wof:placetype":"venue"
},
  "geometry": {"coordinates":[-76.71325,39.323549],"type":"Point"}
}