{
  "type": "Feature",
  "properties": {
    "iso:country":"US",
    "sg:address":"105 Eastern Ave",
    "sg:city":"Annapolis",
    "sg:classifiers":[
        {
            "category":"Professional",
            "subcategory":"Lawyer & Legal Services",
            "type":"Services"
        }
    ],
    "sg:phone":"+1 410 268 4150",
    "sg:postcode":"21403",
    "sg:province":"MD",
    "sg:tags":[
        "attorney"
    ],
    "wof:name":"Maxwell C Cohen Law Offices",
    "wof:placetype":"venue"
},
  "geometry": {"coordinates":[-76.47724,38.969669],"type":"Point"}
}