{
  "type": "Feature",
  "properties": {
    "iso:country":"US",
    "sg:address":"218 N Charles St",
    "sg:city":"Baltimore",
    "sg:classifiers":[
        {
            "category":"Professional",
            "type":"Services"
        }
    ],
    "sg:phone":"+1 410 230 6472",
    "sg:postcode":"21201",
    "sg:province":"MD",
    "wof:name":"Glen Burnie Lllp",
    "wof:placetype":"venue"
},
  "geometry": {"coordinates":[-76.615414,39.292327],"type":"Point"}
}