{
  "type": "Feature",
  "properties": {
    "iso:country":"US",
    "sg:address":"17300 Sandy Knoll Dr",
    "sg:city":"Olney",
    "sg:classifiers":[
        {
            "category":"Organizations",
            "subcategory":"Non-profit Organization",
            "type":"Services"
        }
    ],
    "sg:phone":"+1 301 570 3489",
    "sg:postcode":"20832",
    "sg:province":"MD",
    "sg:tags":[
        "human"
    ],
    "wof:name":"Health Development Intl Inc",
    "wof:placetype":"venue"
},
  "geometry": {"coordinates":[-77.090515,39.141372],"type":"Point"}
}