{
  "type": "Feature",
  "properties": {
    "iso:country":"US",
    "sg:address":"32260 Spearin Rd",
    "sg:city":"Salisbury",
    "sg:classifiers":[
        {
            "category":"Home & Garden",
            "subcategory":"Building Materials",
            "type":"Retail Goods"
        }
    ],
    "sg:phone":"+1 410 548 9292",
    "sg:postcode":"21804",
    "sg:province":"MD",
    "sg:tags":[
        "door"
    ],
    "wof:name":"Leonard Garage",
    "wof:placetype":"venue"
},
  "geometry": {"coordinates":[-75.495643,38.288768],"type":"Point"}
}