{
  "type": "Feature",
  "properties": {
    "iso:country":"US",
    "sg:address":"11820 Browningsville Rd",
    "sg:city":"Monrovia",
    "sg:classifiers":[
        {
            "category":"Professional",
            "subcategory":"Lawyer & Legal Services",
            "type":"Services"
        }
    ],
    "sg:phone":"+1 301 831 3689",
    "sg:postcode":"21770",
    "sg:province":"MD",
    "sg:tags":[
        "case"
    ],
    "wof:name":"Blade Wear",
    "wof:placetype":"venue"
},
  "geometry": {"coordinates":[-77.252228,39.316689],"type":"Point"}
}