{
  "type": "Feature",
  "properties": {
    "addr:full":"2037 E North Ave Baltimore MD 21213",
    "addr:housenumber":"2037",
    "addr:postcode":"21213",
    "addr:street":"E North Ave",
    "iso:country":"US",
    "sg:address":"2037 E North Ave",
    "sg:city":"Baltimore",
    "sg:classifiers":[
        {
            "category":"Organizations",
            "subcategory":"Religious Organization",
            "type":"Services"
        }
    ],
    "sg:phone":"+1 410 342 0700",
    "sg:postcode":"21213",
    "sg:province":"MD",
    "sg:tags":[
        "church"
    ],
    "wof:name":"Anointed House Of Prayer",
    "wof:placetype":"venue"
},
  "geometry": {"coordinates":[-76.589394,39.312374],"type":"Point"}
}