{
  "type": "Feature",
  "properties": {
    "iso:country":"US",
    "sg:address":"11110 Medical Campus Rd Ste 127 Ste 127",
    "sg:city":"Hagerstown",
    "sg:classifiers":[
        {
            "category":"Health Services",
            "subcategory":"Doctor",
            "type":"Services"
        }
    ],
    "sg:phone":"+1 301 714 4335",
    "sg:postcode":"21742",
    "sg:province":"MD",
    "sg:tags":[
        "physician",
        "family",
        "practice",
        "surgeons",
        "surgery-general",
        "surgeon",
        "vascular",
        "medicine",
        "surgery",
        "public"
    ],
    "wof:name":"Tri State Surgeons",
    "wof:placetype":"venue"
},
  "geometry": {"coordinates":[-77.679839,39.621314],"type":"Point"}
}