{
  "type": "Feature",
  "properties": {
    "iso:country":"US",
    "sg:address":"3001 Huron St",
    "sg:city":"Baltimore",
    "sg:classifiers":[
        {
            "category":"Autos & Motor Vehicles",
            "subcategory":"Auto Supplies",
            "type":"Retail Goods"
        },
        {
            "category":"Retail",
            "subcategory":"Auto Repair",
            "type":"Services"
        }
    ],
    "sg:phone":"+1 443 622 7497",
    "sg:postcode":"21230",
    "sg:province":"MD",
    "sg:tags":[
        "body",
        "transmission",
        "automobile",
        "dent",
        "brake",
        "removal",
        "painting",
        "repairing"
    ],
    "sg:website":"http://www.247mobileautocare.com",
    "wof:name":"24 7 Mobile Auto Care",
    "wof:placetype":"venue"
},
  "geometry": {"coordinates":[-76.65020800000001,39.25491],"type":"Point"}
}