{
  "type": "Feature",
  "properties": {
    "iso:country":"US",
    "sg:address":"8821 Walker Mill Rd",
    "sg:city":"Capitol Heights",
    "sg:classifiers":[
        {
            "category":"Building & Trades",
            "subcategory":"Pest Control",
            "type":"Services"
        }
    ],
    "sg:phone":"+1 301 336 4440",
    "sg:postcode":"20743",
    "sg:province":"MD",
    "sg:website":"www.lambrightpestcontrol.com",
    "wof:name":"Lambright Pest Control Services Inc",
    "wof:placetype":"venue"
},
  "geometry": {"coordinates":[-76.855278,38.871842],"type":"Point"}
}