{
  "type": "Feature",
  "properties": {
    "addr:full":"2750 Rogers Ave Ellicott City MD 21043",
    "addr:housenumber":"2750",
    "addr:postcode":"21043",
    "addr:street":"Rogers Ave",
    "iso:country":"US",
    "sg:address":"2750 Rogers Ave",
    "sg:city":"Ellicott City",
    "sg:classifiers":[
        {
            "category":"Organizations",
            "subcategory":"Religious Organization",
            "type":"Services"
        }
    ],
    "sg:phone":"+1 410 418 5147",
    "sg:postcode":"21043",
    "sg:province":"MD",
    "sg:tags":[
        "church"
    ],
    "wof:name":"Primera Igelsia Del Navareno",
    "wof:placetype":"venue"
},
  "geometry": {"coordinates":[-76.812241,39.297985],"type":"Point"}
}