{
  "type": "Feature",
  "properties": {
    "addr:full":"10901 Sir Paul Pl Clinton MD 20735",
    "addr:housenumber":"10901",
    "addr:postcode":"20735",
    "addr:street":"Sir Paul Pl",
    "iso:country":"US",
    "sg:address":"10901 Sir Paul Pl",
    "sg:city":"Clinton",
    "sg:classifiers":[
        {
            "category":"Real Estate",
            "subcategory":"Real Estate Services",
            "type":"Services"
        },
        {
            "category":"Real Estate",
            "subcategory":"Real Estate Agent",
            "type":"Services"
        }
    ],
    "sg:phone":"+1 301 234 0182",
    "sg:postcode":"20735",
    "sg:province":"MD",
    "sg:tags":[
        "buyer",
        "broker"
    ],
    "wof:name":"Nvr Inc",
    "wof:placetype":"venue"
},
  "geometry": {"coordinates":[-76.928741,38.741039],"type":"Point"}
}