{
  "type": "Feature",
  "properties": {
    "addr:full":"4003 Night Heron Ct Waldorf MD 20603",
    "addr:housenumber":"4003",
    "addr:postcode":"20603",
    "addr:street":"Night Heron Ct",
    "iso:country":"US",
    "sg:address":"4003 Night Heron Ct",
    "sg:city":"Waldorf",
    "sg:classifiers":[
        {
            "category":"Health Services",
            "subcategory":"Clinic",
            "type":"Services"
        }
    ],
    "sg:phone":"+1 301 374 2610",
    "sg:postcode":"20603",
    "sg:province":"MD",
    "sg:tags":[
        "home"
    ],
    "wof:name":"Health Force",
    "wof:placetype":"venue"
},
  "geometry": {"coordinates":[-76.937961,38.618612],"type":"Point"}
}