{
  "type": "Feature",
  "properties": {
    "iso:country":"US",
    "sg:address":"8610 Old Harford Rd",
    "sg:city":"Parkville",
    "sg:classifiers":[
        {
            "category":"Health Services",
            "subcategory":"Dentist",
            "type":"Services"
        }
    ],
    "sg:phone":"+1 410 661 1226",
    "sg:postcode":"21234",
    "sg:province":"MD",
    "sg:tags":[
        "clinic",
        "dental",
        "dentists-cosmetic",
        "dentists-pediatric",
        "dentistry"
    ],
    "sg:website":"http://www.sungchangdmd.com",
    "wof:name":"Sung Jin Chang",
    "wof:placetype":"venue"
},
  "geometry": {"coordinates":[-76.543404,39.39138],"type":"Point"}
}