{
  "type": "Feature",
  "properties": {
    "iso:country":"US",
    "sg:address":"3901 Rocks Rd",
    "sg:city":"Street",
    "sg:classifiers":[
        {
            "category":"Health Services",
            "subcategory":"Hospital",
            "type":"Services"
        }
    ],
    "sg:phone":"+1 410 879 4977",
    "sg:postcode":"21154",
    "sg:province":"MD",
    "sg:tags":[
        "sleep",
        "treatment",
        "disorders-information"
    ],
    "wof:name":"Md Vaccination Services",
    "wof:placetype":"venue"
},
  "geometry": {"coordinates":[-76.41223100000001,39.642319],"type":"Point"}
}