{
  "type": "Feature",
  "properties": {
    "iso:country":"US",
    "sg:address":"29 Shipping Pl",
    "sg:city":"Dundalk",
    "sg:classifiers":[
        {
            "category":"Retail",
            "subcategory":"Portrait Studio",
            "type":"Services"
        },
        {
            "category":"Shopping",
            "subcategory":"Pharmacy",
            "type":"Retail Goods"
        }
    ],
    "sg:phone":"+1 410 282 0020",
    "sg:postcode":"21222",
    "sg:province":"MD",
    "sg:tags":[
        "photography",
        "drugstore",
        "store"
    ],
    "wof:name":"Rite Aid",
    "wof:placetype":"venue"
},
  "geometry": {"coordinates":[-76.522797,39.257999],"type":"Point"}
}