{
  "type": "Feature",
  "properties": {
    "iso:country":"US",
    "sg:address":"1700 Braddock Dr",
    "sg:city":"Crofton",
    "sg:classifiers":[
        {
            "category":"Home & Garden",
            "subcategory":"Building Materials",
            "type":"Retail Goods"
        },
        {
            "category":"Building & Trades",
            "subcategory":"Construction",
            "type":"Services"
        }
    ],
    "sg:phone":"+1 410 793 0626",
    "sg:postcode":"21114",
    "sg:province":"MD",
    "sg:tags":[
        "concrete",
        "staining",
        "contractor"
    ],
    "wof:name":"E L Gardner Incorporated",
    "wof:placetype":"venue"
},
  "geometry": {"coordinates":[-76.6726,38.995838],"type":"Point"}
}