{
  "type": "Feature",
  "properties": {
    "addr:full":"1 N Park Dr Cockysvl Hnt Vly MD 21030",
    "addr:housenumber":"1",
    "addr:postcode":"21030",
    "addr:street":"N Park Dr;Hnt Vly",
    "iso:country":"US",
    "sg:address":"1 N Park Dr",
    "sg:city":"Cockysvl Hnt Vly",
    "sg:classifiers":[
        {
            "category":"Health Services",
            "subcategory":"Doctor",
            "type":"Services"
        }
    ],
    "sg:phone":"+1 410 527 5950",
    "sg:postcode":"21030",
    "sg:province":"MD",
    "sg:tags":[
        "physician",
        "surgeon"
    ],
    "wof:name":"Cyrus Hamidi MD",
    "wof:placetype":"venue"
},
  "geometry": {"coordinates":[-76.65047800000001,39.499004],"type":"Point"}
}