{
  "type": "Feature",
  "properties": {
    "addr:full":"2002 Cedar Dr Edgewood MD 21040",
    "addr:housenumber":"2002",
    "addr:postcode":"21040",
    "addr:street":"Cedar Dr",
    "iso:country":"US",
    "sg:address":"2002 Cedar Dr",
    "sg:city":"Edgewood",
    "sg:classifiers":[
        {
            "category":"Social Services",
            "type":"Services"
        }
    ],
    "sg:phone":"+1 410 676 1020",
    "sg:postcode":"21040",
    "sg:province":"MD",
    "sg:tags":[
        "youth",
        "organization",
        "center"
    ],
    "wof:name":"Harford County Boys & Girls",
    "wof:placetype":"venue"
},
  "geometry": {"coordinates":[-76.298416,39.42398],"type":"Point"}
}