{
  "type": "Feature",
  "properties": {
    "addr:full":"7836 Airpark Rd Gaithersburg MD 20879",
    "addr:housenumber":"7836",
    "addr:postcode":"20879",
    "addr:street":"Airpark Rd",
    "iso:country":"US",
    "sg:address":"7836 Airpark Rd",
    "sg:city":"Gaithersburg",
    "sg:classifiers":[
        {
            "category":"Building & Trades",
            "subcategory":"Plumbing",
            "type":"Services"
        }
    ],
    "sg:phone":"+1 301 258 0840",
    "sg:postcode":"20879",
    "sg:province":"MD",
    "sg:tags":[
        "sheet",
        "work",
        "metal",
        "contractor"
    ],
    "wof:name":"Davis Sheet Metal",
    "wof:placetype":"venue"
},
  "geometry": {"coordinates":[-77.160647,39.169911],"type":"Point"}
}