{
  "type": "Feature",
  "properties": {
    "addr:full":"1159 Liberty Grove Rd Conowingo MD 21918",
    "addr:housenumber":"1159",
    "addr:postcode":"21918",
    "addr:street":"Liberty Grove Rd",
    "iso:country":"US",
    "sg:address":"1159 Liberty Grove Rd",
    "sg:city":"Conowingo",
    "sg:classifiers":[
        {
            "category":"Retail",
            "subcategory":"Laundry & Dry Cleaning",
            "type":"Services"
        }
    ],
    "sg:phone":"+1 410 378 9145",
    "sg:postcode":"21918",
    "sg:province":"MD",
    "sg:tags":[
        "cleaners",
        "rug",
        "carpet"
    ],
    "wof:name":"Mike's Carpet Cleaning",
    "wof:placetype":"venue"
},
  "geometry": {"coordinates":[-76.120902,39.655338],"type":"Point"}
}