{
  "type": "Feature",
  "properties": {
    "addr:full":"726 2nd St Annapolis MD 21403",
    "addr:housenumber":"726",
    "addr:postcode":"21403",
    "addr:street":"2Nd St",
    "iso:country":"US",
    "sg:address":"726 2nd St",
    "sg:city":"Annapolis",
    "sg:classifiers":[
        {
            "category":"Banks & Credit Unions",
            "subcategory":"Bank",
            "type":"Services"
        }
    ],
    "sg:phone":"+1 410 263 7715",
    "sg:postcode":"21403",
    "sg:province":"MD",
    "sg:tags":[
        "financing"
    ],
    "wof:name":"First Commercial Corp",
    "wof:placetype":"venue"
},
  "geometry": {"coordinates":[-76.476381,38.968629],"type":"Point"}
}