{
  "type": "Feature",
  "properties": {
    "iso:country":"US",
    "sg:address":"910 Century St",
    "sg:city":"Hampstead",
    "sg:classifiers":[
        {
            "category":"Building & Trades",
            "subcategory":"Construction",
            "type":"Services"
        }
    ],
    "sg:phone":"+1 410 374 4909",
    "sg:postcode":"21074",
    "sg:province":"MD",
    "sg:tags":[
        "general",
        "contractor"
    ],
    "wof:name":"G J Crawford Inc Gen Contrs",
    "wof:placetype":"venue"
},
  "geometry": {"coordinates":[-76.844196,39.599354],"type":"Point"}
}