{
  "type": "Feature",
  "properties": {
    "addr:full":"11 E Chesapeake Ave Towson MD 21286",
    "addr:housenumber":"11",
    "addr:postcode":"21286",
    "addr:street":"E Chesapeake Ave",
    "iso:country":"US",
    "sg:address":"11 E Chesapeake Ave",
    "sg:city":"Towson",
    "sg:classifiers":[
        {
            "category":"Real Estate",
            "subcategory":"Real Estate Services",
            "type":"Services"
        }
    ],
    "sg:phone":"+1 410 337 6750",
    "sg:postcode":"21286",
    "sg:province":"MD",
    "sg:tags":[
        "company",
        "title"
    ],
    "wof:name":"Maple Leaf Title Co",
    "wof:placetype":"venue"
},
  "geometry": {"coordinates":[-76.601506,39.399341],"type":"Point"}
}