{
  "type": "Feature",
  "properties": {
    "iso:country":"US",
    "sg:address":"511 S Bond St Apt 205",
    "sg:city":"Baltimore",
    "sg:classifiers":[
        {
            "category":"Communications",
            "type":"Services"
        }
    ],
    "sg:phone":"+1 202 230 2414",
    "sg:postcode":"21231",
    "sg:province":"MD",
    "sg:tags":[
        "translator",
        "interpreter"
    ],
    "wof:name":"Freelance Interpreting",
    "wof:placetype":"venue"
},
  "geometry": {"coordinates":[-76.595343,39.285422],"type":"Point"}
}