{
  "type": "Feature",
  "properties": {
    "iso:country":"US",
    "sg:address":"3927 Branch Ave",
    "sg:city":"Temple Hills",
    "sg:classifiers":[
        {
            "category":"Shopping",
            "subcategory":"Shoes",
            "type":"Retail Goods"
        }
    ],
    "sg:phone":"+1 301 316 2010",
    "sg:postcode":"20748",
    "sg:province":"MD",
    "wof:name":"Bare Feet Children's Shoes",
    "wof:placetype":"venue"
},
  "geometry": {"coordinates":[-76.94367699999999,38.835444],"type":"Point"}
}