{
  "type": "Feature",
  "properties": {
    "iso:country":"US",
    "sg:address":"5503 Laurelton Ave",
    "sg:city":"Baltimore",
    "sg:classifiers":[
        {
            "category":"Bus Charters",
            "type":"Transportation"
        }
    ],
    "sg:phone":"+1 410 444 5567",
    "sg:postcode":"21214",
    "sg:province":"MD",
    "sg:tags":[
        "rental"
    ],
    "wof:name":"C & S Tours Inc",
    "wof:placetype":"venue"
},
  "geometry": {"coordinates":[-76.569108,39.357061],"type":"Point"}
}