{
  "type": "Feature",
  "properties": {
    "iso:country":"US",
    "sg:address":"302 Cedar Ln",
    "sg:city":"Annapolis",
    "sg:classifiers":[
        {
            "category":"Building & Trades",
            "subcategory":"Cleaning & Sanitation",
            "type":"Services"
        },
        {
            "category":"Personal",
            "type":"Services"
        }
    ],
    "sg:phone":"+1 410 269 7630",
    "sg:postcode":"21403",
    "sg:province":"MD",
    "sg:tags":[
        "maids'",
        "house",
        "butlers'",
        "janitorial",
        "cleaners-interior"
    ],
    "sg:website":"http://www.maidintheusaannapolis.com",
    "wof:name":"Maid In The USA",
    "wof:placetype":"venue"
},
  "geometry": {"coordinates":[-76.491794,38.942949],"type":"Point"}
}