{
  "type": "Feature",
  "properties": {
    "addr:full":"617 Stemmers Run Rd Essex MD 21221",
    "addr:housenumber":"617",
    "addr:postcode":"21221",
    "addr:street":"Stemmers Run Rd",
    "iso:country":"US",
    "sg:address":"617 Stemmers Run Rd",
    "sg:city":"Essex",
    "sg:classifiers":[
        {
            "category":"Insurance",
            "subcategory":"Hazard Insurance",
            "type":"Services"
        }
    ],
    "sg:phone":"+1 410 391 9700",
    "sg:postcode":"21221",
    "sg:province":"MD",
    "sg:tags":[
        "commercial",
        "business"
    ],
    "sg:website":"http://www.allstate.com",
    "wof:name":"Allstate Insurance Co Randy Maits",
    "wof:placetype":"venue"
},
  "geometry": {"coordinates":[-76.465998,39.32743],"type":"Point"}
}