{
  "type": "Feature",
  "properties": {
    "addr:full":"1755 Walnut Rd Port Republic MD 20676",
    "addr:housenumber":"1755",
    "addr:postcode":"20676",
    "addr:street":"Walnut Rd",
    "iso:country":"US",
    "sg:address":"1755 Walnut Rd",
    "sg:city":"Port Republic",
    "sg:classifiers":[
        {
            "category":"Building & Trades",
            "subcategory":"Construction",
            "type":"Services"
        }
    ],
    "sg:phone":"+1 301 855 1455",
    "sg:postcode":"20676",
    "sg:province":"MD",
    "sg:tags":[
        "home",
        "improvement"
    ],
    "wof:name":"C & B Contractors",
    "wof:placetype":"venue"
},
  "geometry": {"coordinates":[-76.50723000000001,38.49427],"type":"Point"}
}