{
  "type": "Feature",
  "properties": {
    "addr:full":"7806 Cryden Way District Heights MD 20747",
    "addr:housenumber":"7806",
    "addr:postcode":"20747",
    "addr:street":"Cryden Way",
    "iso:country":"US",
    "sg:address":"7806 Cryden Way",
    "sg:city":"District Heights",
    "sg:classifiers":[
        {
            "category":"Wholesale",
            "subcategory":"Medical Equipment & Supplies",
            "type":"Manufacturing & Wholesale Goods"
        }
    ],
    "sg:phone":"+1 301 736 7028",
    "sg:postcode":"20747",
    "sg:province":"MD",
    "sg:tags":[
        "hospital"
    ],
    "wof:name":"Affiliated Medical Equipment",
    "wof:placetype":"venue"
},
  "geometry": {"coordinates":[-76.87017299999999,38.847344],"type":"Point"}
}