{
  "type": "Feature",
  "properties": {
    "addr:full":"2412 Crofton Blvd Crofton MD 21114",
    "addr:housenumber":"2412",
    "addr:postcode":"21114",
    "addr:street":"Crofton Blvd",
    "iso:country":"US",
    "sg:address":"2412 Crofton Blvd",
    "sg:city":"Crofton",
    "sg:classifiers":[
        {
            "category":"Manufacturing",
            "subcategory":"Printing",
            "type":"Manufacturing & Wholesale Goods"
        }
    ],
    "sg:phone":"+1 410 721 8008",
    "sg:postcode":"21114",
    "sg:province":"MD",
    "sg:tags":[
        "printer"
    ],
    "wof:name":"Aalbar Book Bindery Inc",
    "wof:placetype":"venue"
},
  "geometry": {"coordinates":[-76.69785,39.01714],"type":"Point"}
}