{
  "type": "Feature",
  "properties": {
    "addr:full":"6630 Quad Ave Rosedale MD 21237",
    "addr:housenumber":"6630",
    "addr:postcode":"21237",
    "addr:street":"Quad Ave",
    "iso:country":"US",
    "sg:address":"6630 Quad Ave",
    "sg:city":"Rosedale",
    "sg:classifiers":[
        {
            "category":"Professional",
            "subcategory":"Engineering",
            "type":"Services"
        }
    ],
    "sg:phone":"+1 410 485 6801",
    "sg:postcode":"21237",
    "sg:province":"MD",
    "sg:tags":[
        "consulting",
        "engineer"
    ],
    "wof:name":"Haven Corp",
    "wof:placetype":"venue"
},
  "geometry": {"coordinates":[-76.534829,39.30114],"type":"Point"}
}