{
  "type": "Feature",
  "properties": {
    "iso:country":"US",
    "sg:address":"4319 Shell St",
    "sg:city":"Capitol Heights",
    "sg:classifiers":[
        {
            "category":"Building & Trades",
            "subcategory":"Construction",
            "type":"Services"
        }
    ],
    "sg:phone":"+1 301 568 6608",
    "sg:postcode":"20743",
    "sg:province":"MD",
    "sg:tags":[
        "house"
    ],
    "wof:name":"J H Heard Construction",
    "wof:placetype":"venue"
},
  "geometry": {"coordinates":[-76.933694,38.870315],"type":"Point"}
}