{
  "type": "Feature",
  "properties": {
    "addr:full":"927 West St Annapolis MD 21401",
    "addr:housenumber":"927",
    "addr:postcode":"21401",
    "addr:street":"West St",
    "iso:country":"US",
    "sg:address":"927 West St",
    "sg:city":"Annapolis",
    "sg:classifiers":[
        {
            "category":"Professional",
            "subcategory":"Engineering",
            "type":"Services"
        }
    ],
    "sg:phone":"+1 410 268 8930",
    "sg:postcode":"21401",
    "sg:province":"MD",
    "sg:tags":[
        "architect",
        "naval"
    ],
    "wof:name":"Herbert Engineering",
    "wof:placetype":"venue"
},
  "geometry": {"coordinates":[-76.50822700000001,38.976527],"type":"Point"}
}