{
  "type": "Feature",
  "properties": {
    "iso:country":"US",
    "sg:address":"305 Compton Ave",
    "sg:city":"Laurel",
    "sg:classifiers":[
        {
            "category":"Professional",
            "subcategory":"Employment Agencies",
            "type":"Services"
        },
        {
            "category":"Professional",
            "subcategory":"Lawyer & Legal Services",
            "type":"Services"
        }
    ],
    "sg:phone":"+1 301 776 0827",
    "sg:postcode":"20707",
    "sg:province":"MD",
    "sg:tags":[
        "employer"
    ],
    "wof:name":"Knight Manzi Brennan Shay & Ham PA",
    "wof:placetype":"venue"
},
  "geometry": {"coordinates":[-76.849503,39.098999],"type":"Point"}
}