{
  "type": "Feature",
  "properties": {
    "addr:full":"2901 Druid Park Dr Baltimore MD 21215",
    "addr:housenumber":"2901",
    "addr:postcode":"21215",
    "addr:street":"Druid Park Dr",
    "iso:country":"US",
    "sg:address":"2901 Druid Park Dr",
    "sg:city":"Baltimore",
    "sg:classifiers":[
        {
            "category":"Building & Trades",
            "subcategory":"Construction",
            "type":"Services"
        }
    ],
    "sg:phone":"+1 410 225 0486",
    "sg:postcode":"21215",
    "sg:province":"MD",
    "sg:tags":[
        "dry wall",
        "contractor"
    ],
    "wof:name":"Walker Drywall & Painting",
    "wof:placetype":"venue"
},
  "geometry": {"coordinates":[-76.660352,39.323933],"type":"Point"}
}