{
  "type": "Feature",
  "properties": {
    "iso:country":"US",
    "sg:address":"6819 Loch Raven Blvd",
    "sg:city":"Towson",
    "sg:classifiers":[
        {
            "category":"Autos & Motor Vehicles",
            "subcategory":"Fuel & Gas Station",
            "type":"Retail Goods"
        },
        {
            "category":"Food & Beverages",
            "subcategory":"Groceries & Convenience Stores",
            "type":"Retail Goods"
        }
    ],
    "sg:phone":"+1 410 821 6939",
    "sg:postcode":"21286",
    "sg:province":"MD",
    "wof:name":"Fast Fare",
    "wof:placetype":"venue"
},
  "geometry": {"coordinates":[-76.578819,39.382057],"type":"Point"}
}