{
  "type": "Feature",
  "properties": {
    "addr:full":"602 S Philadelphia Blvd Aberdeen MD 21001",
    "addr:housenumber":"602",
    "addr:postcode":"21001",
    "addr:street":"S Philadelphia Blvd",
    "iso:country":"US",
    "sg:address":"602 S Philadelphia Blvd",
    "sg:city":"Aberdeen",
    "sg:classifiers":[
        {
            "category":"Food & Beverages",
            "subcategory":"Groceries & Convenience Stores",
            "type":"Retail Goods"
        }
    ],
    "sg:phone":"+1 410 297 8135",
    "sg:postcode":"21001",
    "sg:province":"MD",
    "wof:name":"7-Eleven",
    "wof:placetype":"venue"
},
  "geometry": {"coordinates":[-76.16923800000001,39.500845],"type":"Point"}
}