{
  "type": "Feature",
  "properties": {
    "iso:country":"US",
    "sg:address":"24783 Deepwater Point Dr",
    "sg:city":"Saint Michaels",
    "sg:classifiers":[
        {
            "category":"Professional",
            "subcategory":"Management & Consulting",
            "type":"Services"
        }
    ],
    "sg:phone":"+1 410 745 2544",
    "sg:postcode":"21663",
    "sg:province":"MD",
    "sg:tags":[
        "business"
    ],
    "wof:name":"Alex Schuster Assoc",
    "wof:placetype":"venue"
},
  "geometry": {"coordinates":[-76.221164,38.805905],"type":"Point"}
}