{
  "type": "Feature",
  "properties": {
    "iso:country":"US",
    "sg:address":"1316 Whiteford Rd",
    "sg:city":"Street",
    "sg:classifiers":[
        {
            "category":"Retail",
            "subcategory":"Laundry & Dry Cleaning",
            "type":"Services"
        }
    ],
    "sg:phone":"+1 410 836 3573",
    "sg:postcode":"21154",
    "sg:province":"MD",
    "sg:tags":[
        "cleaner",
        "rug",
        "carpet"
    ],
    "wof:name":"K's Office Services",
    "wof:placetype":"venue"
},
  "geometry": {"coordinates":[-76.267539,39.637478],"type":"Point"}
}