{
  "type": "Feature",
  "properties": {
    "iso:country":"US",
    "sg:address":"17410 Valley Mall Rd",
    "sg:city":"Hagerstown",
    "sg:classifiers":[
        {
            "category":"Autos & Motor Vehicles",
            "subcategory":"Auto Supplies",
            "type":"Retail Goods"
        },
        {
            "category":"Retail",
            "subcategory":"Auto Repair",
            "type":"Services"
        }
    ],
    "sg:phone":"+1 301 582 3222",
    "sg:postcode":"21740",
    "sg:province":"MD",
    "sg:tags":[
        "brake",
        "tire"
    ],
    "wof:name":"Firestone Tire & Svc Ctr",
    "wof:placetype":"venue"
},
  "geometry": {"coordinates":[-77.770881,39.622915],"type":"Point"}
}