{
  "type": "Feature",
  "properties": {
    "iso:country":"US",
    "sg:address":"2421 Wellbridge Dr Ste A",
    "sg:city":"Parkville",
    "sg:classifiers":[
        {
            "category":"Real Estate",
            "subcategory":"Real Estate Operator",
            "type":"Services"
        },
        {
            "category":"Restaurant",
            "type":"Food & Drink"
        }
    ],
    "sg:phone":"+1 410 444 4411",
    "sg:postcode":"21234",
    "sg:province":"MD",
    "sg:tags":[
        "apartment"
    ],
    "wof:name":"Wellington Gate",
    "wof:placetype":"venue"
},
  "geometry": {"coordinates":[-76.563698,39.367699],"type":"Point"}
}