{
  "type": "Feature",
  "properties": {
    "iso:country":"US",
    "sg:address":"4809 Long Green Rd",
    "sg:city":"Long Green",
    "sg:classifiers":[
        {
            "category":"Home & Garden",
            "subcategory":"Garden Supply",
            "type":"Retail Goods"
        }
    ],
    "sg:phone":"+1 410 592 5030",
    "sg:postcode":"21057",
    "sg:province":"MD",
    "sg:tags":[
        "nurseryman"
    ],
    "wof:name":"Pinehurst Nursery",
    "wof:placetype":"venue"
},
  "geometry": {"coordinates":[-76.509286,39.47141],"type":"Point"}
}