{
  "type": "Feature",
  "properties": {
    "addr:full":"2728 Loch Raven Rd Baltimore MD 21218",
    "addr:housenumber":"2728",
    "addr:postcode":"21218",
    "addr:street":"Loch Raven Rd",
    "iso:country":"US",
    "sg:address":"2728 Loch Raven Rd",
    "sg:city":"Baltimore",
    "sg:classifiers":[
        {
            "category":"Retail",
            "subcategory":"Laundry & Dry Cleaning",
            "type":"Services"
        }
    ],
    "sg:phone":"+1 410 243 1875",
    "sg:postcode":"21218",
    "sg:province":"MD",
    "sg:website":"www.metrocleanersonline.com",
    "wof:name":"Metro Cleaners",
    "wof:placetype":"venue"
},
  "geometry": {"coordinates":[-76.60445799999999,39.320893],"type":"Point"}
}