{
  "type": "Feature",
  "properties": {
    "addr:full":"1105 Spring St Silver Spring MD 20910",
    "addr:housenumber":"1105",
    "addr:postcode":"20910",
    "addr:street":"Spring St",
    "iso:country":"US",
    "sg:address":"1105 Spring St",
    "sg:city":"Silver Spring",
    "sg:classifiers":[
        {
            "category":"Banks & Credit Unions",
            "subcategory":"Investment Brokerage",
            "type":"Services"
        }
    ],
    "sg:phone":"+1 301 588 7599",
    "sg:postcode":"20910",
    "sg:province":"MD",
    "sg:tags":[
        "consultant",
        "financing"
    ],
    "wof:name":"Steven I Bender",
    "wof:placetype":"venue"
},
  "geometry": {"coordinates":[-77.02906900000001,39.000231],"type":"Point"}
}