{
  "type": "Feature",
  "properties": {
    "iso:country":"US",
    "sg:address":"118 Rosewood Dr",
    "sg:city":"Greenbelt",
    "sg:classifiers":[
        {
            "category":"Professional",
            "subcategory":"Management & Consulting",
            "type":"Services"
        },
        {
            "category":"Professional",
            "subcategory":"Engineering",
            "type":"Services"
        }
    ],
    "sg:phone":"+1 301 345 4211",
    "sg:postcode":"20770",
    "sg:province":"MD",
    "sg:tags":[
        "environmental",
        "ecological",
        "engineer",
        "consultant"
    ],
    "wof:name":"American Lead Consultants, Inc",
    "wof:placetype":"venue"
},
  "geometry": {"coordinates":[-76.886757,39.006691],"type":"Point"}
}