{
  "type": "Feature",
  "properties": {
    "iso:country":"US",
    "sg:address":"2043 Edmondson Ave",
    "sg:city":"Baltimore",
    "sg:classifiers":[
        {
            "category":"Restaurant",
            "type":"Food & Drink"
        }
    ],
    "sg:phone":"+1 410 945 1119",
    "sg:postcode":"21223",
    "sg:province":"MD",
    "wof:name":"New York Fried Chicken",
    "wof:placetype":"venue"
},
  "geometry": {"coordinates":[-76.650333,39.295002],"type":"Point"}
}