{
  "type": "Feature",
  "properties": {
    "iso:country":"US",
    "sg:address":"145 W Patrick St",
    "sg:city":"Frederick",
    "sg:classifiers":[
        {
            "category":"Professional",
            "type":"Services"
        }
    ],
    "sg:phone":"+1 301 293 6188",
    "sg:postcode":"21701",
    "sg:province":"MD",
    "sg:tags":[
        "processing",
        "data"
    ],
    "wof:name":"Data Management Systems Inc",
    "wof:placetype":"venue"
},
  "geometry": {"coordinates":[-77.413608,39.414271],"type":"Point"}
}