{
  "type": "Feature",
  "properties": {
    "addr:full":"304 Lockhart Ct Havre De Grace MD 21078",
    "addr:housenumber":"304",
    "addr:postcode":"21078",
    "addr:street":"Lockhart Ct",
    "iso:country":"US",
    "sg:address":"304 Lockhart Ct",
    "sg:city":"Havre De Grace",
    "sg:classifiers":[
        {
            "category":"Professional",
            "type":"Services"
        }
    ],
    "sg:phone":"+1 410 942 0478",
    "sg:postcode":"21078",
    "sg:province":"MD",
    "sg:tags":[
        "establishment"
    ],
    "wof:name":"Broad Com Corp",
    "wof:placetype":"venue"
},
  "geometry": {"coordinates":[-76.117138,39.547932],"type":"Point"}
}