{
  "type": "Feature",
  "properties": {
    "addr:full":"57 E Broadway Bel Air MD 21014",
    "addr:housenumber":"57",
    "addr:postcode":"21014",
    "addr:street":"E Broadway",
    "iso:country":"US",
    "sg:address":"57 E Broadway",
    "sg:city":"Bel Air",
    "sg:classifiers":[
        {
            "category":"Health Services",
            "subcategory":"Doctor",
            "type":"Services"
        }
    ],
    "sg:phone":"+1 410 879 9593",
    "sg:postcode":"21014",
    "sg:province":"MD",
    "sg:tags":[
        "dentist"
    ],
    "wof:name":"Ralph N Cortezi DDS",
    "wof:placetype":"venue"
},
  "geometry": {"coordinates":[-76.353297,39.539972],"type":"Point"}
}