{
  "type": "Feature",
  "properties": {
    "iso:country":"US",
    "sg:address":"3905 Perry St",
    "sg:city":"Brentwood",
    "sg:classifiers":[
        {
            "category":"Manufacturing",
            "subcategory":"Buildings",
            "type":"Manufacturing & Wholesale Goods"
        },
        {
            "category":"Structure",
            "subcategory":"Warehouse",
            "type":"Public Place"
        },
        {
            "category":"Building & Trades",
            "subcategory":"Construction",
            "type":"Services"
        }
    ],
    "sg:phone":"+1 301 985 6080",
    "sg:postcode":"20722",
    "sg:province":"MD",
    "sg:tags":[
        "industrial",
        "warehouses-merchandise",
        "warehouses-public-commercial",
        "builder",
        "contractor",
        "contractors-commercial",
        "home",
        "estimate"
    ],
    "wof:name":"Radpark Construction Company",
    "wof:placetype":"venue"
},
  "geometry": {"coordinates":[-76.953502,38.938567],"type":"Point"}
}