{
  "type": "Feature",
  "properties": {
    "iso:country":"US",
    "sg:address":"3204 Tower Oaks Blvd # 100",
    "sg:city":"Rockville",
    "sg:classifiers":[
        {
            "category":"Real Estate",
            "subcategory":"Real Estate Services",
            "type":"Services"
        },
        {
            "category":"Real Estate",
            "subcategory":"Surveying",
            "type":"Services"
        }
    ],
    "sg:phone":"+1 202 466 4533",
    "sg:postcode":"20852",
    "sg:province":"MD",
    "sg:tags":[
        "industrial",
        "appraisers-commercial",
        "appraiser"
    ],
    "wof:name":"Millennium Real Estate Advisors, Inc.",
    "wof:placetype":"venue"
},
  "geometry": {"coordinates":[-77.150138,39.056705],"type":"Point"}
}