{
  "type": "Feature",
  "properties": {
    "iso:country":"US",
    "sg:address":"9905 Rhode Island Ave",
    "sg:city":"College Park",
    "sg:classifiers":[
        {
            "category":"Restaurant",
            "type":"Food & Drink"
        }
    ],
    "sg:menulink":"http://www.allmenus.com/md/berwyn/246011-shen-yang-chinese-restaurant/menu/",
    "sg:phone":"+1 301 441 2250",
    "sg:postcode":"20740",
    "sg:province":"MD",
    "sg:tags":[
        "asian",
        "chinese"
    ],
    "wof:name":"Shen Yang Chinese Restaurant",
    "wof:placetype":"venue"
},
  "geometry": {"coordinates":[-76.92062,39.016224],"type":"Point"}
}