{
  "type": "Feature",
  "properties": {
    "iso:country":"US",
    "sg:address":"350 Mountain Rd",
    "sg:city":"Pasadena",
    "sg:classifiers":[
        {
            "category":"Personal",
            "subcategory":"Beauty Salon",
            "type":"Services"
        }
    ],
    "sg:phone":"+1 410 360 4488",
    "sg:postcode":"21122",
    "sg:province":"MD",
    "sg:tags":[
        "manicuring"
    ],
    "wof:name":"Hollywood Nail 3",
    "wof:placetype":"venue"
},
  "geometry": {"coordinates":[-76.559,39.130597],"type":"Point"}
}