{
  "type": "Feature",
  "properties": {
    "iso:country":"US",
    "sg:address":"1428 Iris St NW",
    "sg:city":"Washington",
    "sg:classifiers":[
        {
            "category":"Health Services",
            "subcategory":"Doctor",
            "type":"Services"
        }
    ],
    "sg:phone":"+1 202 882 7451",
    "sg:postcode":"20012",
    "sg:province":"MD",
    "sg:tags":[
        "physician",
        "surgeon"
    ],
    "wof:name":"Marvin A Jackson MD",
    "wof:placetype":"venue"
},
  "geometry": {"coordinates":[-77.03598100000001,38.982206],"type":"Point"}
}