{
  "type": "Feature",
  "properties": {
    "iso:country":"US",
    "sg:address":"31516 Winterplace Pkwy",
    "sg:city":"Salisbury",
    "sg:classifiers":[
        {
            "category":"Real Estate",
            "subcategory":"Real Estate Services",
            "type":"Services"
        },
        {
            "category":"Real Estate",
            "subcategory":"Real Estate Agent",
            "type":"Services"
        }
    ],
    "sg:phone":"+1 410 742 1214",
    "sg:postcode":"21804",
    "sg:province":"MD",
    "sg:tags":[
        "buyer",
        "management",
        "broker"
    ],
    "wof:name":"Gm Real Estate",
    "wof:placetype":"venue"
},
  "geometry": {"coordinates":[-75.524385,38.37298],"type":"Point"}
}