{
  "type": "Feature",
  "properties": {
    "iso:country":"US",
    "sg:address":"10648 Columbia Pike",
    "sg:city":"Silver Spring",
    "sg:classifiers":[
        {
            "category":"Restaurant",
            "type":"Food & Drink"
        }
    ],
    "sg:menulink":"http://www.allmenus.com/md/silver-spring/24642-california-tortilla/menu/",
    "sg:phone":"+1 301 593 3955",
    "sg:postcode":"20901",
    "sg:province":"MD",
    "sg:tags":[
        "mexican"
    ],
    "wof:name":"California Tortilla",
    "wof:placetype":"venue"
},
  "geometry": {"coordinates":[-77.006733,39.029658],"type":"Point"}
}