{
  "type": "Feature",
  "properties": {
    "addr:full":"6934 Eylers Valley Flint Rd Sabillasville MD 21780",
    "addr:housenumber":"6934",
    "addr:postcode":"21780",
    "addr:street":"Eylers Valley Flint Rd",
    "iso:country":"US",
    "sg:address":"6934 Eylers Valley Flint Rd",
    "sg:city":"Sabillasville",
    "sg:classifiers":[
        {
            "category":"Building & Trades",
            "subcategory":"Construction",
            "type":"Services"
        }
    ],
    "sg:phone":"+1 301 620 0363",
    "sg:postcode":"21780",
    "sg:province":"MD",
    "sg:tags":[
        "builder",
        "operative"
    ],
    "wof:name":"J H Hymiller &",
    "wof:placetype":"venue"
},
  "geometry": {"coordinates":[-77.42601999999999,39.669708],"type":"Point"}
}