{
  "type": "Feature",
  "properties": {
    "iso:country":"US",
    "sg:address":"739 W Old Philadelphia Rd",
    "sg:city":"North East",
    "sg:classifiers":[
        {
            "category":"Personal",
            "subcategory":"Barber",
            "type":"Services"
        }
    ],
    "sg:phone":"+1 410 398 9728",
    "sg:postcode":"21901",
    "sg:province":"MD",
    "wof:name":"Elkton Barber Shop",
    "wof:placetype":"venue"
},
  "geometry": {"coordinates":[-75.966464,39.596458],"type":"Point"}
}