{
  "type": "Feature",
  "properties": {
    "addr:full":"7400 Baltimore Annapolis Blvd Glen Burnie MD 21061",
    "addr:housenumber":"7400",
    "addr:postcode":"21061",
    "addr:street":"Baltimore Annapolis Blvd",
    "iso:country":"US",
    "sg:address":"7400 Baltimore Annapolis Blvd",
    "sg:city":"Glen Burnie",
    "sg:phone":"+1 410 766 1200",
    "sg:postcode":"21061",
    "sg:province":"MD",
    "sg:tags":[
        "oil"
    ],
    "wof:name":"Hein Brothers Inc",
    "wof:placetype":"venue"
},
  "geometry": {"coordinates":[-76.631018,39.17055],"type":"Point"}
}