{
  "type": "Feature",
  "properties": {
    "addr:full":"120 N Harrison St Easton MD 21601",
    "addr:housenumber":"120",
    "addr:postcode":"21601",
    "addr:street":"N Harrison St",
    "iso:country":"US",
    "sg:address":"120 N Harrison St",
    "sg:city":"Easton",
    "sg:classifiers":[
        {
            "category":"Education",
            "subcategory":"Dance Studio",
            "type":"Public Place"
        }
    ],
    "sg:phone":"+1 410 819 0555",
    "sg:postcode":"21601",
    "sg:province":"MD",
    "sg:tags":[
        "instruction",
        "dancing"
    ],
    "wof:name":"Dancin To The Beat",
    "wof:placetype":"venue"
},
  "geometry": {"coordinates":[-76.07523500000001,38.776557],"type":"Point"}
}