{
  "type": "Feature",
  "properties": {
    "addr:full":"200 Penrod Ct Glen Burnie MD 21061",
    "addr:housenumber":"200",
    "addr:postcode":"21061",
    "addr:street":"Penrod Ct",
    "iso:country":"US",
    "sg:address":"200 Penrod Ct",
    "sg:city":"Glen Burnie",
    "sg:classifiers":[
        {
            "category":"Home & Garden",
            "subcategory":"Garden Supply",
            "type":"Retail Goods"
        }
    ],
    "sg:phone":"+1 410 590 2133",
    "sg:postcode":"21061",
    "sg:province":"MD",
    "sg:tags":[
        "landscaping",
        "equipment"
    ],
    "wof:name":"Davisson Golf Inc",
    "wof:placetype":"venue"
},
  "geometry": {"coordinates":[-76.627583,39.176914],"type":"Point"}
}