{
  "type": "Feature",
  "properties": {
    "addr:full":"1100 E Patapsco Ave Baltimore MD 21225",
    "addr:housenumber":"1100",
    "addr:postcode":"21225",
    "addr:street":"E Patapsco Ave",
    "iso:country":"US",
    "sg:address":"1100 E Patapsco Ave",
    "sg:city":"Baltimore",
    "sg:classifiers":[
        {
            "category":"Professional",
            "type":"Services"
        }
    ],
    "sg:phone":"+1 410 578 7117",
    "sg:postcode":"21225",
    "sg:province":"MD",
    "wof:name":"Atlas Fan Equipment Services",
    "wof:placetype":"venue"
},
  "geometry": {"coordinates":[-76.59317,39.233501],"type":"Point"}
}