{
  "type": "Feature",
  "properties": {
    "iso:country":"US",
    "sg:address":"105 W Saratoga St",
    "sg:city":"Baltimore",
    "sg:classifiers":[
        {
            "category":"Restaurant",
            "type":"Food & Drink"
        }
    ],
    "sg:phone":"+1 410 244 8677",
    "sg:postcode":"21201",
    "sg:province":"MD",
    "sg:tags":[
        "vietnamese"
    ],
    "wof:name":"Mekong Delta Cafe",
    "wof:placetype":"venue"
},
  "geometry": {"coordinates":[-76.61686899999999,39.292808],"type":"Point"}
}