{
  "type": "Feature",
  "properties": {
    "iso:country":"US",
    "sg:address":"9925 Lyons Mill Rd",
    "sg:city":"Owings Mills",
    "sg:classifiers":[
        {
            "category":"Home & Garden",
            "subcategory":"Building Materials",
            "type":"Retail Goods"
        }
    ],
    "sg:phone":"+1 410 496 1400",
    "sg:postcode":"21117",
    "sg:province":"MD",
    "sg:tags":[
        "door"
    ],
    "wof:name":"First Call Doors",
    "wof:placetype":"venue"
},
  "geometry": {"coordinates":[-76.829164,39.390828],"type":"Point"}
}