{
  "type": "Feature",
  "properties": {
    "addr:full":"118 Dogwood Dr Hurlock MD 21643",
    "addr:housenumber":"118",
    "addr:postcode":"21643",
    "addr:street":"Dogwood Dr",
    "iso:country":"US",
    "sg:address":"118 Dogwood Dr",
    "sg:city":"Hurlock",
    "sg:classifiers":[
        {
            "category":"Professional",
            "subcategory":"Detective & Security Services",
            "type":"Services"
        }
    ],
    "sg:phone":"+1 443 521 4104",
    "sg:postcode":"21643",
    "sg:province":"MD",
    "sg:tags":[
        "information",
        "bureau"
    ],
    "wof:name":"Rachel Woodward",
    "wof:placetype":"venue"
},
  "geometry": {"coordinates":[-75.86760200000001,38.631675],"type":"Point"}
}