{
  "type": "Feature",
  "properties": {
    "iso:country":"US",
    "sg:address":"7507 Burgess Ln",
    "sg:city":"Fort Washington",
    "sg:classifiers":[
        {
            "category":"Shopping",
            "subcategory":"Discount & Variety Stores",
            "type":"Retail Goods"
        }
    ],
    "sg:phone":"+1 301 248 5315",
    "sg:postcode":"20744",
    "sg:province":"MD",
    "sg:tags":[
        "merchandise",
        "general"
    ],
    "wof:name":"Delores A Tyler",
    "wof:placetype":"venue"
},
  "geometry": {"coordinates":[-76.941035,38.78584],"type":"Point"}
}