{
  "type": "Feature",
  "properties": {
    "addr:full":"10444 Carlyn Ridge Rd Damascus MD 20872",
    "addr:housenumber":"10444",
    "addr:postcode":"20872",
    "addr:street":"Carlyn Ridge Rd",
    "iso:country":"US",
    "sg:address":"10444 Carlyn Ridge Rd",
    "sg:city":"Damascus",
    "sg:classifiers":[
        {
            "category":"Building & Trades",
            "subcategory":"Construction",
            "type":"Services"
        }
    ],
    "sg:phone":"+1 301 926 9292",
    "sg:postcode":"20872",
    "sg:province":"MD",
    "sg:tags":[
        "siding",
        "contractor"
    ],
    "wof:name":"Contemporary Exteriors",
    "wof:placetype":"venue"
},
  "geometry": {"coordinates":[-77.21730700000001,39.261705],"type":"Point"}
}