{
  "type": "Feature",
  "properties": {
    "addr:full":"18 N Church St Thurmont MD 21788",
    "addr:housenumber":"18",
    "addr:postcode":"21788",
    "addr:street":"N Church St",
    "iso:country":"US",
    "sg:address":"18 N Church St",
    "sg:city":"Thurmont",
    "sg:classifiers":[
        {
            "category":"Health Services",
            "subcategory":"Hospital",
            "type":"Services"
        }
    ],
    "sg:phone":"+1 301 271 4870",
    "sg:postcode":"21788",
    "sg:province":"MD",
    "sg:tags":[
        "mental"
    ],
    "wof:name":"Catoctin Counseling Ctr",
    "wof:placetype":"venue"
},
  "geometry": {"coordinates":[-77.411439,39.623796],"type":"Point"}
}