{
  "type": "Feature",
  "properties": {
    "iso:country":"US",
    "sg:address":"215 Ellerslie Ct",
    "sg:city":"Abingdon",
    "sg:classifiers":[
        {
            "category":"Building & Trades",
            "subcategory":"Plumbing",
            "type":"Services"
        }
    ],
    "sg:phone":"+1 410 399 0011",
    "sg:postcode":"21009",
    "sg:province":"MD",
    "sg:tags":[
        "plumbing",
        "contractor"
    ],
    "wof:name":"Pioneer Plumbing",
    "wof:placetype":"venue"
},
  "geometry": {"coordinates":[-76.319791,39.474098],"type":"Point"}
}