{
  "type": "Feature",
  "properties": {
    "iso:country":"US",
    "sg:address":"5507 Selma Ave",
    "sg:city":"Halethorpe",
    "sg:classifiers":[
        {
            "category":"Bars & Pubs",
            "subcategory":"Nightclub",
            "type":"Food & Drink"
        }
    ],
    "sg:phone":"+1 410 242 1940",
    "sg:postcode":"21227",
    "sg:province":"MD",
    "sg:tags":[
        "nightlife"
    ],
    "wof:name":"Center Court Inc",
    "wof:placetype":"venue"
},
  "geometry": {"coordinates":[-76.692802,39.247299],"type":"Point"}
}