{
  "type": "Feature",
  "properties": {
    "iso:country":"US",
    "sg:address":"735 Ivy League Ln",
    "sg:city":"Rockville",
    "sg:classifiers":[
        {
            "category":"Professional",
            "type":"Services"
        }
    ],
    "sg:phone":"+1 301 279 0582",
    "sg:postcode":"20850",
    "sg:province":"MD",
    "wof:name":"Fan Ye",
    "wof:placetype":"venue"
},
  "geometry": {"coordinates":[-77.155282,39.094178],"type":"Point"}
}