{
  "type": "Feature",
  "properties": {
    "iso:country":"US",
    "sg:address":"7475 Wisconsin Ave",
    "sg:city":"Bethesda",
    "sg:classifiers":[
        {
            "category":"Personal",
            "subcategory":"Beauty Salon",
            "type":"Services"
        }
    ],
    "sg:phone":"+1 301 652 3918",
    "sg:postcode":"20814",
    "sg:province":"MD",
    "sg:website":"www.bubblessalons.com",
    "wof:name":"Bubbles Hair Salon",
    "wof:placetype":"venue"
},
  "geometry": {"coordinates":[-77.094081,38.984421],"type":"Point"}
}