{
  "type": "Feature",
  "properties": {
    "addr:full":"2324 Davidsonville Rd Gambrills MD 21054",
    "addr:postcode":"2324;21054",
    "addr:street":"Davidsonville Rd",
    "iso:country":"US",
    "sg:address":"2324 Davidsonville Rd",
    "sg:city":"Gambrills",
    "sg:classifiers":[
        {
            "category":"Health Services",
            "subcategory":"Doctor",
            "type":"Services"
        }
    ],
    "sg:phone":"+1 410 721 1410",
    "sg:postcode":"21054",
    "sg:province":"MD",
    "sg:tags":[
        "physician",
        "surgeon"
    ],
    "wof:name":"M J Rosenburg MD",
    "wof:placetype":"venue"
},
  "geometry": {"coordinates":[-76.669252,38.98605],"type":"Point"}
}