{
  "type": "Feature",
  "properties": {
    "addr:full":"818 York Rd Towson MD 21204",
    "addr:housenumber":"818",
    "addr:postcode":"21204",
    "addr:street":"York Rd",
    "iso:country":"US",
    "sg:address":"818 York Rd",
    "sg:city":"Towson",
    "sg:classifiers":[
        {
            "category":"Retail",
            "subcategory":"Auto Repair",
            "type":"Services"
        }
    ],
    "sg:phone":"+1 443 955 6366",
    "sg:postcode":"21204",
    "sg:province":"MD",
    "sg:tags":[
        "repairing",
        "automobile"
    ],
    "sg:website":"http://www.sarandosauto.net",
    "wof:name":"Sarandos Automotive Technology Inc",
    "wof:placetype":"venue"
},
  "geometry": {"coordinates":[-76.60679,39.406983],"type":"Point"}
}