{
  "type": "Feature",
  "properties": {
    "iso:country":"US",
    "sg:address":"11900 Oden Ct",
    "sg:city":"Rockville",
    "sg:classifiers":[
        {
            "category":"Professional",
            "subcategory":"Management & Consulting",
            "type":"Services"
        }
    ],
    "sg:phone":"+1 301 984 7444",
    "sg:postcode":"20852",
    "sg:province":"MD",
    "sg:tags":[
        "consultant",
        "business"
    ],
    "wof:name":"Harvey M Cohen",
    "wof:placetype":"venue"
},
  "geometry": {"coordinates":[-77.14082999999999,39.051956],"type":"Point"}
}