{
  "type": "Feature",
  "properties": {
    "iso:country":"US",
    "sg:address":"6700 Parkway Rd",
    "sg:city":"Baltimore",
    "sg:classifiers":[
        {
            "category":"Home & Garden",
            "subcategory":"Building Materials",
            "type":"Retail Goods"
        }
    ],
    "sg:phone":"+1 410 372 0200",
    "sg:postcode":"21239",
    "sg:province":"MD",
    "sg:tags":[
        "wallpaper"
    ],
    "wof:name":"Precision Wallpapering & Ptg",
    "wof:placetype":"venue"
},
  "geometry": {"coordinates":[-76.592109,39.377057],"type":"Point"}
}