{
  "type": "Feature",
  "properties": {
    "iso:country":"US",
    "sg:address":"4920 Niagara Rd",
    "sg:city":"College Park",
    "sg:classifiers":[
        {
            "category":"Health Services",
            "subcategory":"Health Practitioner",
            "type":"Services"
        }
    ],
    "sg:phone":"+1 301 313 0963",
    "sg:postcode":"20740",
    "sg:province":"MD",
    "sg:tags":[
        "nurse",
        "registry"
    ],
    "wof:name":"B T Healthcare Svc",
    "wof:placetype":"venue"
},
  "geometry": {"coordinates":[-76.92332,39.017521],"type":"Point"}
}