{
  "type": "Feature",
  "properties": {
    "addr:full":"706 Crain Hwy N Glen Burnie MD 21061",
    "addr:housenumber":"706",
    "addr:postcode":"21061",
    "addr:street":"Crain Hwy N",
    "iso:country":"US",
    "sg:address":"706 Crain Hwy N",
    "sg:city":"Glen Burnie",
    "sg:classifiers":[
        {
            "category":"Shopping",
            "subcategory":"Used Merchandise",
            "type":"Retail Goods"
        }
    ],
    "sg:phone":"+1 410 766 7357",
    "sg:postcode":"21061",
    "sg:province":"MD",
    "sg:tags":[
        "pawnbroker"
    ],
    "wof:name":"A & D Pawn Shop",
    "wof:placetype":"venue"
},
  "geometry": {"coordinates":[-76.617767,39.176883],"type":"Point"}
}