{
  "type": "Feature",
  "properties": {
    "iso:country":"US",
    "sg:address":"11266 Georgia Ave",
    "sg:city":"Silver Spring",
    "sg:classifiers":[
        {
            "category":"Food & Beverages",
            "subcategory":"Bakery",
            "type":"Retail Goods"
        }
    ],
    "sg:phone":"+1 301 949 2277",
    "sg:postcode":"20902",
    "sg:province":"MD",
    "sg:tags":[
        "baker"
    ],
    "wof:name":"Chicago Bakery Inc",
    "wof:placetype":"venue"
},
  "geometry": {"coordinates":[-77.051137,39.039109],"type":"Point"}
}