{
  "type": "Feature",
  "properties": {
    "addr:full":"123 E Main St Emmitsburg MD 21727",
    "addr:housenumber":"123",
    "addr:postcode":"21727",
    "addr:street":"E Main St",
    "iso:country":"US",
    "sg:address":"123 E Main St",
    "sg:city":"Emmitsburg",
    "sg:classifiers":[
        {
            "category":"Professional",
            "subcategory":"Business Services",
            "type":"Services"
        }
    ],
    "sg:phone":"+1 301 447 3033",
    "sg:postcode":"21727",
    "sg:province":"MD",
    "sg:tags":[
        "embroidery"
    ],
    "wof:name":"Grannies Attic Shurt Haus",
    "wof:placetype":"venue"
},
  "geometry": {"coordinates":[-77.32490900000001,39.704313],"type":"Point"}
}