{
  "type": "Feature",
  "properties": {
    "iso:country":"US",
    "sg:address":"7011 Highbridge Rd",
    "sg:city":"Bowie",
    "sg:classifiers":[
        {
            "category":"Education",
            "subcategory":"School",
            "type":"Public Place"
        }
    ],
    "sg:phone":"+1 301 805 2690",
    "sg:postcode":"20720",
    "sg:province":"MD",
    "wof:name":"High Bridge Elementary School",
    "wof:placetype":"venue"
},
  "geometry": {"coordinates":[-76.77322,38.987084],"type":"Point"}
}