{
  "type": "Feature",
  "properties": {
    "addr:full":"477 Old Mill Rd Millersville MD 21108",
    "addr:housenumber":"477",
    "addr:postcode":"21108",
    "addr:street":"Old Mill Rd",
    "iso:country":"US",
    "sg:address":"477 Old Mill Rd",
    "sg:city":"Millersville",
    "sg:classifiers":[
        {
            "category":"Food & Beverages",
            "subcategory":"Groceries & Convenience Stores",
            "type":"Retail Goods"
        }
    ],
    "sg:phone":"+1 410 987 5075",
    "sg:postcode":"21108",
    "sg:province":"MD",
    "wof:name":"7-Eleven",
    "wof:placetype":"venue"
},
  "geometry": {"coordinates":[-76.617795,39.118703],"type":"Point"}
}