{
  "type": "Feature",
  "properties": {
    "iso:country":"US",
    "sg:address":"7808 New Ascot Ln",
    "sg:city":"Clinton",
    "sg:classifiers":[
        {
            "category":"Professional",
            "subcategory":"Art Services",
            "type":"Services"
        }
    ],
    "sg:phone":"+1 301 856 1029",
    "sg:postcode":"20735",
    "sg:province":"MD",
    "sg:tags":[
        "commercial",
        "design"
    ],
    "wof:name":"Dvd Design & Graphics",
    "wof:placetype":"venue"
},
  "geometry": {"coordinates":[-76.870946,38.765099],"type":"Point"}
}