{
  "type": "Feature",
  "properties": {
    "iso:country":"US",
    "sg:address":"3 N Harrison St",
    "sg:city":"Easton",
    "sg:classifiers":[
        {
            "category":"Professional",
            "subcategory":"Lawyer & Legal Services",
            "type":"Services"
        }
    ],
    "sg:phone":"+1 410 763 4877",
    "sg:postcode":"21601",
    "sg:province":"MD",
    "sg:tags":[
        "attorney"
    ],
    "wof:name":"Elise Davis",
    "wof:placetype":"venue"
},
  "geometry": {"coordinates":[-76.074783,38.774987],"type":"Point"}
}