{
  "type": "Feature",
  "properties": {
    "addr:full":"334 N Tannery Rd Westminster MD 21157",
    "addr:housenumber":"334",
    "addr:postcode":"21157",
    "addr:street":"N Tannery Rd",
    "iso:country":"US",
    "sg:address":"334 N Tannery Rd",
    "sg:city":"Westminster",
    "sg:classifiers":[
        {
            "category":"Shopping",
            "subcategory":"Bicycles & Sporting Goods",
            "type":"Retail Goods"
        }
    ],
    "sg:phone":"+1 410 857 1213",
    "sg:postcode":"21157",
    "sg:province":"MD",
    "wof:name":"Hurlock Enterprises",
    "wof:placetype":"venue"
},
  "geometry": {"coordinates":[-76.958388,39.58474],"type":"Point"}
}