{
  "type": "Feature",
  "properties": {
    "addr:full":"3916 Vero Rd Halethorpe MD 21227",
    "addr:housenumber":"3916",
    "addr:postcode":"21227",
    "addr:street":"Vero Rd",
    "iso:country":"US",
    "sg:address":"3916 Vero Rd",
    "sg:city":"Halethorpe",
    "sg:classifiers":[
        {
            "category":"Freight",
            "type":"Transportation"
        }
    ],
    "sg:phone":"+1 443 524 3340",
    "sg:postcode":"21227",
    "sg:province":"MD",
    "sg:tags":[
        "consultant",
        "trucking"
    ],
    "wof:name":"Freight Management Group",
    "wof:placetype":"venue"
},
  "geometry": {"coordinates":[-76.676427,39.261087],"type":"Point"}
}