{
  "type": "Feature",
  "properties": {
    "addr:full":"1595 Opossumtown Pike Frederick MD 21702",
    "addr:housenumber":"1595",
    "addr:postcode":"21702",
    "addr:street":"Opossumtown Pike",
    "iso:country":"US",
    "sg:address":"1595 Opossumtown Pike",
    "sg:city":"Frederick",
    "sg:classifiers":[
        {
            "category":"Food & Beverages",
            "subcategory":"Bakery",
            "type":"Retail Goods"
        }
    ],
    "sg:phone":"+1 301 682 6914",
    "sg:postcode":"21702",
    "sg:province":"MD",
    "sg:tags":[
        "doughnut"
    ],
    "wof:name":"Dunkin Donuts",
    "wof:placetype":"venue"
},
  "geometry": {"coordinates":[-77.410554,39.439836],"type":"Point"}
}