{
  "type": "Feature",
  "properties": {
    "addr:full":"1220 E Joppa Rd Towson MD 21286",
    "addr:housenumber":"1220 e",
    "addr:postcode":"21286",
    "addr:street":"Joppa Rd",
    "iso:country":"US",
    "sg:address":"1220 E Joppa Rd",
    "sg:city":"Towson",
    "sg:classifiers":[
        {
            "category":"Health Services",
            "subcategory":"Optometrist",
            "type":"Services"
        }
    ],
    "sg:phone":"+1 410 828 5558",
    "sg:postcode":"21286",
    "sg:province":"MD",
    "wof:name":"McGinn Elizabeth",
    "wof:placetype":"venue"
},
  "geometry": {"coordinates":[-76.57804899999999,39.39637],"type":"Point"}
}