{
  "type": "Feature",
  "properties": {
    "iso:country":"US",
    "sg:address":"500 N Stuart St",
    "sg:city":"Baltimore",
    "sg:classifiers":[
        {
            "category":"Building & Trades",
            "subcategory":"Construction",
            "type":"Services"
        }
    ],
    "sg:phone":"+1 410 686 7896",
    "sg:postcode":"21221",
    "sg:province":"MD",
    "sg:tags":[
        "house"
    ],
    "wof:name":"J&E Construction Services",
    "wof:placetype":"venue"
},
  "geometry": {"coordinates":[-76.472994,39.313496],"type":"Point"}
}