{
  "type": "Feature",
  "properties": {
    "iso:country":"US",
    "sg:address":"24848 Meeting House Rd",
    "sg:city":"Denton",
    "sg:classifiers":[
        {
            "category":"Retail",
            "subcategory":"Auto Repair",
            "type":"Services"
        }
    ],
    "sg:phone":"+1 410 479 4360",
    "sg:postcode":"21629",
    "sg:province":"MD",
    "sg:tags":[
        "body",
        "automobile",
        "painting"
    ],
    "wof:name":"Hot Rod Garage Parts Depot Inc",
    "wof:placetype":"venue"
},
  "geometry": {"coordinates":[-75.841924,38.891013],"type":"Point"}
}