{
  "type": "Feature",
  "properties": {
    "iso:country":"US",
    "sg:address":"3500 Pelham Ave",
    "sg:city":"Baltimore",
    "sg:classifiers":[
        {
            "category":"Food & Beverages",
            "subcategory":"Groceries & Convenience Stores",
            "type":"Retail Goods"
        }
    ],
    "sg:phone":"+1 410 325 3033",
    "sg:postcode":"21213",
    "sg:province":"MD",
    "wof:name":"T & A Mart 2",
    "wof:placetype":"venue"
},
  "geometry": {"coordinates":[-76.565201,39.319901],"type":"Point"}
}