{
  "type": "Feature",
  "properties": {
    "iso:country":"US",
    "sg:address":"2258 Old Washington Rd",
    "sg:city":"Waldorf",
    "sg:classifiers":[
        {
            "category":"Restaurant",
            "type":"Food & Drink"
        }
    ],
    "sg:phone":"+1 301 893 8400",
    "sg:postcode":"20601",
    "sg:province":"MD",
    "sg:tags":[
        "out"
    ],
    "wof:name":"You-C-Carryout",
    "wof:placetype":"venue"
},
  "geometry": {"coordinates":[-76.883023,38.649384],"type":"Point"}
}