{
  "type": "Feature",
  "properties": {
    "addr:full":"1400 Haven Rd Apt B12 Hagerstown MD 21742",
    "addr:housenumber":"1400",
    "addr:postcode":"b12;21742",
    "addr:street":"Haven Rd",
    "iso:country":"US",
    "sg:address":"1400 Haven Rd Apt B12",
    "sg:city":"Hagerstown",
    "sg:classifiers":[
        {
            "category":"Communications",
            "type":"Services"
        }
    ],
    "sg:phone":"+1 301 302 2067",
    "sg:postcode":"21742",
    "sg:province":"MD",
    "wof:name":"Kgk Communications",
    "wof:placetype":"venue"
},
  "geometry": {"coordinates":[-77.72689800000001,39.669651],"type":"Point"}
}