{
  "type": "Feature",
  "properties": {
    "iso:country":"US",
    "sg:address":"5506 Park Heights Ave",
    "sg:city":"Baltimore",
    "sg:classifiers":[
        {
            "category":"Personal",
            "subcategory":"Beauty Salon",
            "type":"Services"
        },
        {
            "category":"Personal",
            "subcategory":"Barber",
            "type":"Services"
        },
        {
            "category":"Personal",
            "subcategory":"Nail Salon",
            "type":"Services"
        }
    ],
    "sg:phone":"+1 410 466 2442",
    "sg:postcode":"21215",
    "sg:province":"MD",
    "wof:name":"Shear Luck Beauty & Barber",
    "wof:placetype":"venue"
},
  "geometry": {"coordinates":[-76.683379,39.351792],"type":"Point"}
}