{
  "type": "Feature",
  "properties": {
    "addr:full":"4626 Leonardtown Rd Waldorf MD 20601",
    "addr:housenumber":"4626",
    "addr:postcode":"20601",
    "addr:street":"Leonardtown Rd",
    "iso:country":"US",
    "sg:address":"4626 Leonardtown Rd",
    "sg:city":"Waldorf",
    "sg:classifiers":[
        {
            "category":"Recreation",
            "type":"Entertainment"
        }
    ],
    "sg:phone":"+1 301 645 3038",
    "sg:postcode":"20601",
    "sg:province":"MD",
    "wof:name":"Blue Heron School Tae Kwon Do",
    "wof:placetype":"venue"
},
  "geometry": {"coordinates":[-76.87003199999999,38.595908],"type":"Point"}
}