{
  "type": "Feature",
  "properties": {
    "addr:full":"430 E Fort Ave Baltimore MD 21230",
    "addr:housenumber":"430",
    "addr:postcode":"21230",
    "addr:street":"E Fort Ave",
    "iso:country":"US",
    "sg:address":"430 E Fort Ave",
    "sg:city":"Baltimore",
    "sg:classifiers":[
        {
            "category":"Bars & Pubs",
            "type":"Food & Drink"
        }
    ],
    "sg:phone":"+1 410 547 9995",
    "sg:postcode":"21230",
    "sg:province":"MD",
    "sg:tags":[
        "tavern"
    ],
    "wof:name":"Southside Saloon",
    "wof:placetype":"venue"
},
  "geometry": {"coordinates":[-76.60749800000001,39.272881],"type":"Point"}
}