{
  "type": "Feature",
  "properties": {
    "iso:country":"US",
    "sg:address":"6345 Dobbin Rd",
    "sg:city":"Columbia",
    "sg:classifiers":[
        {
            "category":"Autos & Motor Vehicles",
            "subcategory":"Fuel & Gas Station",
            "type":"Retail Goods"
        }
    ],
    "sg:phone":"+1 410 740 5269",
    "sg:postcode":"21045",
    "sg:province":"MD",
    "sg:tags":[
        "oil"
    ],
    "wof:name":"Dobbin Center Mobil",
    "wof:placetype":"venue"
},
  "geometry": {"coordinates":[-76.819,39.198002],"type":"Point"}
}