{
  "type": "Feature",
  "properties": {
    "addr:full":"306 Virginia Rd Stevensville MD 21666",
    "addr:housenumber":"306",
    "addr:postcode":"21666",
    "addr:street":"Virginia Rd",
    "iso:country":"US",
    "sg:address":"306 Virginia Rd",
    "sg:city":"Stevensville",
    "sg:classifiers":[
        {
            "category":"Professional",
            "subcategory":"Engineering",
            "type":"Services"
        }
    ],
    "sg:phone":"+1 410 643 0466",
    "sg:postcode":"21666",
    "sg:province":"MD",
    "sg:tags":[
        "consultant",
        "drafting"
    ],
    "wof:name":"Shop Drawings Consultant",
    "wof:placetype":"venue"
},
  "geometry": {"coordinates":[-76.363749,38.888157],"type":"Point"}
}