{
  "type": "Feature",
  "properties": {
    "iso:country":"US",
    "sg:address":"701 S Charles St",
    "sg:city":"Baltimore",
    "sg:classifiers":[
        {
            "category":"Place Of Worship",
            "subcategory":"Church",
            "type":"Public Place"
        },
        {
            "category":"Place Of Worship",
            "type":"Public Place"
        }
    ],
    "sg:phone":"+1 410 752 7179",
    "sg:postcode":"21230",
    "sg:province":"MD",
    "sg:tags":[
        "churches-lutheran"
    ],
    "sg:website":"http://www.christinnerharbor.org",
    "wof:name":"Christ Lutheran Church",
    "wof:placetype":"venue"
},
  "geometry": {"coordinates":[-76.61463000000001,39.280746],"type":"Point"}
}