{
  "type": "Feature",
  "properties": {
    "iso:country":"US",
    "sg:address":"9241 Rumsey Rd",
    "sg:city":"Columbia",
    "sg:classifiers":[
        {
            "category":"Professional",
            "subcategory":"Research",
            "type":"Services"
        }
    ],
    "sg:phone":"+1 410 715 2111",
    "sg:postcode":"21045",
    "sg:province":"MD",
    "sg:tags":[
        "medical"
    ],
    "wof:name":"Ravgen",
    "wof:placetype":"venue"
},
  "geometry": {"coordinates":[-76.820268,39.232795],"type":"Point"}
}