{
  "type": "Feature",
  "properties": {
    "addr:full":"23171 Three Notch Rd California MD 20619",
    "addr:housenumber":"23171",
    "addr:postcode":"20619",
    "addr:street":"Three Notch Rd",
    "iso:country":"US",
    "sg:address":"23171 Three Notch Rd",
    "sg:city":"California",
    "sg:classifiers":[
        {
            "category":"Shopping",
            "type":"Retail Goods"
        }
    ],
    "sg:phone":"+1 301 737 2355",
    "sg:postcode":"20619",
    "sg:province":"MD",
    "sg:tags":[
        "telephone",
        "cellular"
    ],
    "wof:name":"Freedom Page Beepers Car Tlphs",
    "wof:placetype":"venue"
},
  "geometry": {"coordinates":[-76.520009,38.303649],"type":"Point"}
}