{
  "type": "Feature",
  "properties": {
    "iso:country":"US",
    "sg:address":"100 W Antietam St",
    "sg:city":"Hagerstown",
    "sg:classifiers":[
        {
            "category":"Insurance",
            "subcategory":"Insurance Agent",
            "type":"Services"
        }
    ],
    "sg:phone":"+1 301 714 1234",
    "sg:postcode":"21740",
    "sg:province":"MD",
    "wof:name":"All American Auto Insurance",
    "wof:placetype":"venue"
},
  "geometry": {"coordinates":[-77.72370100000001,39.64193],"type":"Point"}
}