{
  "type": "Feature",
  "properties": {
    "addr:full":"2314 Brightseat Rd Apt 3 Hyattsville MD 20785",
    "addr:housenumber":"2314;3",
    "addr:postcode":"20785",
    "addr:street":"Brightseat Rd Apt",
    "iso:country":"US",
    "sg:address":"2314 Brightseat Rd Apt 3",
    "sg:city":"Hyattsville",
    "sg:classifiers":[
        {
            "category":"Professional",
            "subcategory":"Business Services",
            "type":"Services"
        }
    ],
    "sg:phone":"+1 301 583 9146",
    "sg:postcode":"20785",
    "sg:province":"MD",
    "sg:tags":[
        "labeling"
    ],
    "wof:name":"Hoilday In A Bag",
    "wof:placetype":"venue"
},
  "geometry": {"coordinates":[-76.860184,38.92031],"type":"Point"}
}