{
  "type": "Feature",
  "properties": {
    "iso:country":"US",
    "sg:address":"9936 Stephen Decatur Hwy",
    "sg:city":"Ocean City",
    "sg:classifiers":[
        {
            "category":"Shopping",
            "subcategory":"Computers & Home Electronics",
            "type":"Retail Goods"
        }
    ],
    "sg:phone":"+1 410 213 1303",
    "sg:postcode":"21842",
    "sg:province":"MD",
    "sg:tags":[
        "equipment",
        "dealer"
    ],
    "wof:name":"Expresstech Computer Co",
    "wof:placetype":"venue"
},
  "geometry": {"coordinates":[-75.114412,38.333443],"type":"Point"}
}