{
  "type": "Feature",
  "properties": {
    "addr:full":"9577 White Pillar Ter Gaithersburg MD 20882",
    "addr:housenumber":"9577",
    "addr:postcode":"20882",
    "addr:street":"White Pillar Ter",
    "iso:country":"US",
    "sg:address":"9577 White Pillar Ter",
    "sg:city":"Gaithersburg",
    "sg:classifiers":[
        {
            "category":"Personal",
            "type":"Services"
        }
    ],
    "sg:phone":"+1 301 570 2087",
    "sg:postcode":"20882",
    "sg:province":"MD",
    "sg:tags":[
        "consultant",
        "program",
        "health",
        "fitness"
    ],
    "wof:name":"Perfect Parts",
    "wof:placetype":"venue"
},
  "geometry": {"coordinates":[-77.196136,39.248143],"type":"Point"}
}