{
  "type": "Feature",
  "properties": {
    "iso:country":"US",
    "sg:address":"2432 Holly Neck Rd",
    "sg:city":"Essex",
    "sg:classifiers":[
        {
            "category":"Manufacturing",
            "subcategory":"Textiles",
            "type":"Manufacturing & Wholesale Goods"
        }
    ],
    "sg:phone":"+1 410 686 9164",
    "sg:postcode":"21221",
    "sg:province":"MD",
    "sg:tags":[
        "textiles-manufacturers"
    ],
    "wof:name":"Wrights Canvas",
    "wof:placetype":"venue"
},
  "geometry": {"coordinates":[-76.398523,39.282823],"type":"Point"}
}