{
  "type": "Feature",
  "properties": {
    "iso:country":"US",
    "sg:address":"5507 Woodenhawk Cir",
    "sg:city":"Columbia",
    "sg:classifiers":[
        {
            "category":"Manufacturing",
            "subcategory":"Electronics",
            "type":"Manufacturing & Wholesale Goods"
        }
    ],
    "sg:phone":"+1 410 992 0048",
    "sg:postcode":"21044",
    "sg:province":"MD",
    "sg:tags":[
        "mfg",
        "boards",
        "circuit",
        "printed"
    ],
    "wof:name":"McDuff Engineering Services",
    "wof:placetype":"venue"
},
  "geometry": {"coordinates":[-76.885694,39.22098],"type":"Point"}
}