{
  "type": "Feature",
  "properties": {
    "addr:full":"14804 Village Gate Dr Silver Spring MD 20906",
    "addr:housenumber":"14804",
    "addr:postcode":"20906",
    "addr:street":"Village Gate Dr",
    "iso:country":"US",
    "sg:address":"14804 Village Gate Dr",
    "sg:city":"Silver Spring",
    "sg:classifiers":[
        {
            "category":"Professional",
            "subcategory":"Management & Consulting",
            "type":"Services"
        }
    ],
    "sg:phone":"+1 301 438 7240",
    "sg:postcode":"20906",
    "sg:province":"MD",
    "sg:tags":[
        "consultant",
        "business"
    ],
    "wof:name":"Glimmerglass Consulting",
    "wof:placetype":"venue"
},
  "geometry": {"coordinates":[-77.044849,39.097664],"type":"Point"}
}