{
  "type": "Feature",
  "properties": {
    "iso:country":"US",
    "sg:address":"12110 Otis Dr",
    "sg:city":"Rockville",
    "sg:classifiers":[
        {
            "category":"Manufacturing",
            "subcategory":"Tools & Machinery",
            "type":"Manufacturing & Wholesale Goods"
        },
        {
            "category":"Manufacturing",
            "subcategory":"Electronics",
            "type":"Manufacturing & Wholesale Goods"
        },
        {
            "category":"Shopping",
            "subcategory":"Computers & Home Electronics",
            "type":"Retail Goods"
        }
    ],
    "sg:phone":"+1 301 231 0638",
    "sg:postcode":"20852",
    "sg:province":"MD",
    "sg:tags":[
        "electric",
        "consumer",
        "equipment-testing",
        "equipment",
        "supplies-wholesale",
        "manufacturer"
    ],
    "wof:name":"Bernard T Doane & Sons Inc",
    "wof:placetype":"venue"
},
  "geometry": {"coordinates":[-77.099358,39.054531],"type":"Point"}
}