{
  "type": "Feature",
  "properties": {
    "iso:country":"US",
    "sg:address":"289 W Main St",
    "sg:city":"Westminster",
    "sg:classifiers":[
        {
            "category":"Food & Beverages",
            "subcategory":"Bakery",
            "type":"Retail Goods"
        },
        {
            "category":"Restaurant",
            "type":"Food & Drink"
        },
        {
            "category":"Bakery",
            "type":"Food & Drink"
        }
    ],
    "sg:phone":"+1 410 848 7413",
    "sg:postcode":"21158",
    "sg:province":"MD",
    "sg:tags":[
        "style",
        "american",
        "family",
        "pie"
    ],
    "sg:website":"http://www.baughers.com",
    "wof:name":"Baughers Country Restaurant",
    "wof:placetype":"venue"
},
  "geometry": {"coordinates":[-77.010502,39.584807],"type":"Point"}
}