{
  "type": "Feature",
  "properties": {
    "addr:full":"11259 Lockwood Dr Ste B Silver Spring MD 20901",
    "addr:housenumber":"11259",
    "addr:postcode":"20901",
    "addr:street":"Lockwood Dr Ste B",
    "iso:country":"US",
    "sg:address":"11259 Lockwood Dr Ste B",
    "sg:city":"Silver Spring",
    "sg:classifiers":[
        {
            "category":"Health Services",
            "subcategory":"Dentist",
            "type":"Services"
        }
    ],
    "sg:phone":"+1 301 681 4241",
    "sg:postcode":"20901",
    "sg:province":"MD",
    "wof:name":"Bugden Thos M",
    "wof:placetype":"venue"
},
  "geometry": {"coordinates":[-76.989799,39.0401],"type":"Point"}
}