{
  "type": "Feature",
  "properties": {
    "iso:country":"US",
    "sg:address":"6124 Macarthur Blvd",
    "sg:city":"Bethesda",
    "sg:classifiers":[
        {
            "category":"Shopping",
            "type":"Retail Goods"
        }
    ],
    "sg:phone":"+1 301 229 9585",
    "sg:postcode":"20816",
    "sg:province":"MD",
    "sg:tags":[
        "pet",
        "food",
        "supply"
    ],
    "wof:name":"Quack Quack Quack Enterprises",
    "wof:placetype":"venue"
},
  "geometry": {"coordinates":[-77.116619,38.943987],"type":"Point"}
}