{
  "type": "Feature",
  "properties": {
    "addr:full":"2901 Strickland St Baltimore MD 21223",
    "addr:housenumber":"2901",
    "addr:postcode":"21223",
    "addr:street":"Strickland St",
    "iso:country":"US",
    "sg:address":"2901 Strickland St",
    "sg:city":"Baltimore",
    "sg:classifiers":[
        {
            "category":"Organizations",
            "subcategory":"Non-profit Organization",
            "type":"Services"
        }
    ],
    "sg:phone":"+1 410 233 4568",
    "sg:postcode":"21223",
    "sg:province":"MD",
    "sg:website":"www.bism.com",
    "wof:name":"Blind Industries & Svc Of MD",
    "wof:placetype":"venue"
},
  "geometry": {"coordinates":[-76.665671,39.277522],"type":"Point"}
}