{
  "type": "Feature",
  "properties": {
    "addr:full":"12806 Ocean Gtwy Ocean City MD 21842",
    "addr:housenumber":"12806",
    "addr:postcode":"21842",
    "addr:street":"Ocean Gtwy",
    "iso:country":"US",
    "sg:address":"12806 Ocean Gtwy",
    "sg:city":"Ocean City",
    "sg:classifiers":[
        {
            "category":"Travel",
            "subcategory":"Hotels & Motels",
            "type":"Entertainment"
        }
    ],
    "sg:phone":"+1 410 213 0088",
    "sg:postcode":"21842",
    "sg:province":"MD",
    "sg:website":"www.fskmotel.com",
    "wof:name":"Francis Scott Key Motel",
    "wof:placetype":"venue"
},
  "geometry": {"coordinates":[-75.106123,38.336302],"type":"Point"}
}