{
  "type": "Feature",
  "properties": {
    "addr:full":"6801 Kenilworth Ave Riverdale MD 20737",
    "addr:housenumber":"6801",
    "addr:postcode":"20737",
    "addr:street":"Kenilworth Ave",
    "iso:country":"US",
    "sg:address":"6801 Kenilworth Ave",
    "sg:city":"Riverdale",
    "sg:classifiers":[
        {
            "category":"Professional",
            "subcategory":"Lawyer & Legal Services",
            "type":"Services"
        }
    ],
    "sg:phone":"+1 301 277 4727",
    "sg:postcode":"20737",
    "sg:province":"MD",
    "wof:name":"McPherson Kenneth E",
    "wof:placetype":"venue"
},
  "geometry": {"coordinates":[-76.916521,38.969705],"type":"Point"}
}