{
  "type": "Feature",
  "properties": {
    "addr:full":"227 W Patrick St Frederick MD 21701",
    "addr:housenumber":"227",
    "addr:postcode":"21701",
    "addr:street":"W Patrick St",
    "iso:country":"US",
    "sg:address":"227 W Patrick St",
    "sg:city":"Frederick",
    "sg:classifiers":[
        {
            "category":"Real Estate",
            "subcategory":"Real Estate Services",
            "type":"Services"
        }
    ],
    "sg:phone":"+1 240 379 7788",
    "sg:postcode":"21701",
    "sg:province":"MD",
    "sg:tags":[
        "company",
        "title"
    ],
    "wof:name":"Frederick Towne Title",
    "wof:placetype":"venue"
},
  "geometry": {"coordinates":[-77.41607999999999,39.413714],"type":"Point"}
}