{
  "type": "Feature",
  "properties": {
    "addr:full":"1701 Crimson Tree Way Edgewood MD 21040",
    "addr:housenumber":"1701",
    "addr:postcode":"21040",
    "addr:street":"Crimson Tree Way",
    "iso:country":"US",
    "sg:address":"1701 Crimson Tree Way",
    "sg:city":"Edgewood",
    "sg:classifiers":[
        {
            "category":"Organizations",
            "subcategory":"Religious Organization",
            "type":"Services"
        }
    ],
    "sg:phone":"+1 410 671 7232",
    "sg:postcode":"21040",
    "sg:province":"MD",
    "sg:tags":[
        "clergy"
    ],
    "wof:name":"Christian & Missionary Allinc",
    "wof:placetype":"venue"
},
  "geometry": {"coordinates":[-76.320813,39.432173],"type":"Point"}
}