{
  "type": "Feature",
  "properties": {
    "addr:full":"8755 Darcy Rd Forestville MD 20747",
    "addr:housenumber":"8755",
    "addr:postcode":"20747",
    "addr:street":"Darcy Rd",
    "iso:country":"US",
    "sg:address":"8755 Darcy Rd",
    "sg:city":"Forestville",
    "sg:classifiers":[
        {
            "category":"Freight",
            "type":"Transportation"
        }
    ],
    "sg:phone":"+1 301 350 3500",
    "sg:postcode":"20747",
    "sg:province":"MD",
    "sg:tags":[
        "mover"
    ],
    "wof:name":"United Van Lines",
    "wof:placetype":"venue"
},
  "geometry": {"coordinates":[-76.853718,38.857743],"type":"Point"}
}