{
  "type": "Feature",
  "properties": {
    "addr:full":"3728 Roland Ave Baltimore MD 21211",
    "addr:housenumber":"3728",
    "addr:postcode":"21211",
    "addr:street":"Roland Ave",
    "iso:country":"US",
    "sg:address":"3728 Roland Ave",
    "sg:city":"Baltimore",
    "sg:classifiers":[
        {
            "category":"Personal",
            "subcategory":"Beauty Salon",
            "type":"Services"
        }
    ],
    "sg:phone":"+1 410 366 7446",
    "sg:postcode":"21211",
    "sg:province":"MD",
    "wof:name":"Tangles Hair Design",
    "wof:placetype":"venue"
},
  "geometry": {"coordinates":[-76.632972,39.334201],"type":"Point"}
}