{
  "type": "Feature",
  "properties": {
    "iso:country":"US",
    "sg:address":"704 Quince Orchard Rd",
    "sg:city":"Gaithersburg",
    "sg:classifiers":[
        {
            "category":"Insurance",
            "subcategory":"Insurance Agent",
            "type":"Services"
        }
    ],
    "sg:phone":"+1 301 990 3500",
    "sg:postcode":"20878",
    "sg:province":"MD",
    "wof:name":"UCC Insurance Advisory Board",
    "wof:placetype":"venue"
},
  "geometry": {"coordinates":[-77.22325499999999,39.136173],"type":"Point"}
}