{
  "type": "Feature",
  "properties": {
    "iso:country":"US",
    "sg:address":"7159 Harlan Ln",
    "sg:city":"Sykesville",
    "sg:classifiers":[
        {
            "category":"Building & Trades",
            "subcategory":"Plumbing",
            "type":"Services"
        }
    ],
    "sg:phone":"+1 301 912 1415",
    "sg:postcode":"21784",
    "sg:province":"MD",
    "sg:tags":[
        "heating",
        "contractor"
    ],
    "wof:name":"Thomas D Stern Air Experts Inc",
    "wof:placetype":"venue"
},
  "geometry": {"coordinates":[-76.98324700000001,39.374805],"type":"Point"}
}