{
  "type": "Feature",
  "properties": {
    "iso:country":"US",
    "sg:address":"2600 Liberty Heights Ave",
    "sg:city":"Baltimore",
    "sg:classifiers":[
        {
            "category":"Shopping",
            "subcategory":"Clothing, Apparel, & Fashions",
            "type":"Retail Goods"
        },
        {
            "category":"Health Services",
            "subcategory":"Podiatrist",
            "type":"Services"
        }
    ],
    "sg:phone":"+1 410 879 2853",
    "sg:postcode":"21215",
    "sg:province":"MD",
    "sg:tags":[
        "physician",
        "surgeons",
        "shoes-orthopedic"
    ],
    "wof:name":"Marvin Leneau Dpm",
    "wof:placetype":"venue"
},
  "geometry": {"coordinates":[-76.656593,39.319672],"type":"Point"}
}