{
  "type": "Feature",
  "properties": {
    "iso:country":"US",
    "sg:address":"591 Primus Ct",
    "sg:city":"Frederick",
    "sg:classifiers":[
        {
            "category":"Shopping",
            "subcategory":"Computers & Home Electronics",
            "type":"Retail Goods"
        }
    ],
    "sg:phone":"+1 301 668 2076",
    "sg:postcode":"21703",
    "sg:province":"MD",
    "wof:name":"Lyncap Systems LLC",
    "wof:placetype":"venue"
},
  "geometry": {"coordinates":[-77.43717599999999,39.405558],"type":"Point"}
}