{
  "type": "Feature",
  "properties": {
    "iso:country":"US",
    "sg:address":"937 Gateway Dr",
    "sg:city":"Chestertown",
    "sg:classifiers":[
        {
            "category":"Health Services",
            "subcategory":"Hospital",
            "type":"Services"
        }
    ],
    "sg:phone":"+1 410 778 4566",
    "sg:postcode":"21620",
    "sg:province":"MD",
    "sg:tags":[
        "mental"
    ],
    "sg:website":"http://www.communitycrossroads.com",
    "wof:name":"Crossroads Community, Inc.",
    "wof:placetype":"venue"
},
  "geometry": {"coordinates":[-76.071067,39.234932],"type":"Point"}
}