{
  "type": "Feature",
  "properties": {
    "addr:full":"8322 Pulaski Hwy Rosedale MD 21237",
    "addr:housenumber":"8322",
    "addr:postcode":"21237",
    "addr:street":"Pulaski Hwy",
    "iso:country":"US",
    "sg:address":"8322 Pulaski Hwy",
    "sg:city":"Rosedale",
    "sg:classifiers":[
        {
            "category":"Manufacturing",
            "subcategory":"Tools & Machinery",
            "type":"Manufacturing & Wholesale Goods"
        }
    ],
    "sg:phone":"+1 410 686 1482",
    "sg:postcode":"21237",
    "sg:province":"MD",
    "sg:tags":[
        "building",
        "construction",
        "equipment"
    ],
    "wof:name":"United States Contracting Corporation",
    "wof:placetype":"venue"
},
  "geometry": {"coordinates":[-76.50081400000001,39.324235],"type":"Point"}
}