{
  "type": "Feature",
  "properties": {
    "addr:full":"6330 Gateway Blvd District Heights MD 20747",
    "addr:housenumber":"6330",
    "addr:postcode":"20747",
    "addr:street":"Gateway Blvd",
    "iso:country":"US",
    "sg:address":"6330 Gateway Blvd",
    "sg:city":"District Heights",
    "sg:classifiers":[
        {
            "category":"Organizations",
            "subcategory":"Religious Organization",
            "type":"Services"
        }
    ],
    "sg:phone":"+1 301 568 9127",
    "sg:postcode":"20747",
    "sg:province":"MD",
    "sg:tags":[
        "church"
    ],
    "wof:name":"Hemingway Memorial AME Chr",
    "wof:placetype":"venue"
},
  "geometry": {"coordinates":[-76.89649300000001,38.855578],"type":"Point"}
}