{
  "type": "Feature",
  "properties": {
    "addr:full":"8630-A Guilford Rd. Columbia MD 21046",
    "addr:housenumber":"8630-a",
    "addr:postcode":"21046",
    "addr:street":"Guilford Rd.",
    "iso:country":"US",
    "sg:address":"8630-A Guilford Rd.",
    "sg:city":"Columbia",
    "sg:classifiers":[
        {
            "category":"Retail",
            "subcategory":"Auto Repair",
            "type":"Services"
        }
    ],
    "sg:phone":"+1 410 929 3959",
    "sg:postcode":"21046",
    "sg:province":"MD",
    "sg:website":"www.lowpriceautoglass.info",
    "wof:name":"Low Price Auto Glass",
    "wof:placetype":"venue"
},
  "geometry": {"coordinates":[-76.864722,39.169874],"type":"Point"}
}