{
  "type": "Feature",
  "properties": {
    "iso:country":"US",
    "sg:address":"3745 Branch Ave Ste 2",
    "sg:city":"Temple Hills",
    "sg:classifiers":[
        {
            "category":"Restaurant",
            "type":"Food & Drink"
        }
    ],
    "sg:phone":"+1 301 899 8868",
    "sg:postcode":"20748",
    "sg:province":"MD",
    "sg:tags":[
        "seafood",
        "buffet"
    ],
    "wof:name":"Seafood Palace",
    "wof:placetype":"venue"
},
  "geometry": {"coordinates":[-76.94739300000001,38.837936],"type":"Point"}
}