{
  "type": "Feature",
  "properties": {
    "iso:country":"US",
    "sg:address":"322 Boeing Ct",
    "sg:city":"Abingdon",
    "sg:classifiers":[
        {
            "category":"Wholesale",
            "subcategory":"Construction Materials",
            "type":"Manufacturing & Wholesale Goods"
        }
    ],
    "sg:phone":"+1 410 515 3960",
    "sg:postcode":"21009",
    "sg:province":"MD",
    "wof:name":"Owens Corning",
    "wof:placetype":"venue"
},
  "geometry": {"coordinates":[-76.301772,39.487777],"type":"Point"}
}