{
  "type": "Feature",
  "properties": {
    "addr:full":"4301 Belmar Ave Baltimore MD 21206",
    "addr:housenumber":"4301",
    "addr:postcode":"21206",
    "addr:street":"Belmar Ave",
    "iso:country":"US",
    "sg:address":"4301 Belmar Ave",
    "sg:city":"Baltimore",
    "sg:classifiers":[
        {
            "category":"Personal",
            "type":"Services"
        }
    ],
    "sg:phone":"+1 410 866 5152",
    "sg:postcode":"21206",
    "sg:province":"MD",
    "wof:name":"T&L Enterprises",
    "wof:placetype":"venue"
},
  "geometry": {"coordinates":[-76.52714899999999,39.35154],"type":"Point"}
}