{
  "type": "Feature",
  "properties": {
    "addr:full":"21789 S Coral Dr Lexington Park MD 20653",
    "addr:housenumber":"21789",
    "addr:postcode":"20653",
    "addr:street":"S Coral Dr",
    "iso:country":"US",
    "sg:address":"21789 S Coral Dr",
    "sg:city":"Lexington Park",
    "sg:classifiers":[
        {
            "category":"Professional",
            "subcategory":"Management & Consulting",
            "type":"Services"
        }
    ],
    "sg:phone":"+1 301 866 1701",
    "sg:postcode":"20653",
    "sg:province":"MD",
    "sg:tags":[
        "defense",
        "contractor"
    ],
    "wof:name":"Holmes Tucker Intl Inc",
    "wof:placetype":"venue"
},
  "geometry": {"coordinates":[-76.452389,38.264604],"type":"Point"}
}