{
  "type": "Feature",
  "properties": {
    "iso:country":"US",
    "sg:address":"3881 Branch Ave",
    "sg:city":"Temple Hills",
    "sg:classifiers":[
        {
            "category":"Shopping",
            "subcategory":"Clothing, Apparel, & Fashions",
            "type":"Retail Goods"
        }
    ],
    "sg:phone":"+1 301 316 8560",
    "sg:postcode":"20748",
    "sg:province":"MD",
    "sg:tags":[
        "clothing",
        "women's"
    ],
    "wof:name":"Lexy Inc",
    "wof:placetype":"venue"
},
  "geometry": {"coordinates":[-76.945182,38.837276],"type":"Point"}
}