{
  "type": "Feature",
  "properties": {
    "iso:country":"US",
    "sg:address":"2525 Fleet St",
    "sg:city":"Baltimore",
    "sg:classifiers":[
        {
            "category":"Retail",
            "subcategory":"Funeral Services",
            "type":"Services"
        }
    ],
    "sg:phone":"+1 410 633 0000",
    "sg:postcode":"21224",
    "sg:province":"MD",
    "sg:tags":[
        "director"
    ],
    "wof:name":"Kaczorowski Funeral Home",
    "wof:placetype":"venue"
},
  "geometry": {"coordinates":[-76.579988,39.285115],"type":"Point"}
}