{
  "type": "Feature",
  "properties": {
    "addr:full":"2333 W Zion Rd Ocean City MD 21804",
    "addr:housenumber":"2333",
    "addr:postcode":"21804",
    "addr:street":"W Zion Rd",
    "iso:country":"US",
    "sg:address":"2333 W Zion Rd",
    "sg:city":"Ocean City",
    "sg:classifiers":[
        {
            "category":"Building & Trades",
            "subcategory":"Pest Control",
            "type":"Services"
        }
    ],
    "sg:phone":"+1 410 250 0314",
    "sg:postcode":"21804",
    "sg:province":"MD",
    "sg:tags":[
        "deodorizing",
        "disinfecting"
    ],
    "wof:name":"Staton Environmental Svc",
    "wof:placetype":"venue"
},
  "geometry": {"coordinates":[-75.57073,38.40467],"type":"Point"}
}