{
  "type": "Feature",
  "properties": {
    "addr:full":"602 S Atwood Rd Bel Air MD 21014",
    "addr:housenumber":"602",
    "addr:postcode":"21014",
    "addr:street":"S Atwood Rd",
    "iso:country":"US",
    "sg:address":"602 S Atwood Rd",
    "sg:city":"Bel Air",
    "sg:classifiers":[
        {
            "category":"Health Services",
            "subcategory":"Podiatrist",
            "type":"Services"
        }
    ],
    "sg:phone":"+1 410 356 0222",
    "sg:postcode":"21014",
    "sg:province":"MD",
    "wof:name":"Victor R Aybar DPM",
    "wof:placetype":"venue"
},
  "geometry": {"coordinates":[-76.346463,39.524954],"type":"Point"}
}