{
  "type": "Feature",
  "properties": {
    "addr:full":"317 Southwest Dr Silver Spring MD 20901",
    "addr:housenumber":"317",
    "addr:postcode":"20901",
    "addr:street":"Southwest Dr",
    "iso:country":"US",
    "sg:address":"317 Southwest Dr",
    "sg:city":"Silver Spring",
    "sg:classifiers":[
        {
            "category":"Autos & Motor Vehicles",
            "subcategory":"Auto Supplies",
            "type":"Retail Goods"
        }
    ],
    "sg:phone":"+1 410 730 8221",
    "sg:postcode":"20901",
    "sg:province":"MD",
    "sg:tags":[
        "automobile",
        "accessory"
    ],
    "wof:name":"Traction Tuning",
    "wof:placetype":"venue"
},
  "geometry": {"coordinates":[-77.003511,39.037867],"type":"Point"}
}