{
  "type": "Feature",
  "properties": {
    "iso:country":"US",
    "sg:address":"272 E Padonia Rd",
    "sg:city":"Lutherville",
    "sg:classifiers":[
        {
            "category":"Professional",
            "subcategory":"Management & Consulting",
            "type":"Services"
        }
    ],
    "sg:phone":"+1 410 252 0667",
    "sg:postcode":"21093",
    "sg:province":"MD",
    "sg:tags":[
        "consultant",
        "business"
    ],
    "wof:name":"Behavioral Dynamics",
    "wof:placetype":"venue"
},
  "geometry": {"coordinates":[-76.612652,39.462457],"type":"Point"}
}