{
  "type": "Feature",
  "properties": {
    "addr:full":"17600 Prince David Dr Olney MD 20832",
    "addr:housenumber":"17600",
    "addr:postcode":"20832",
    "addr:street":"Prince David Dr",
    "iso:country":"US",
    "sg:address":"17600 Prince David Dr",
    "sg:city":"Olney",
    "sg:classifiers":[
        {
            "category":"Building & Trades",
            "subcategory":"Landscaping Services",
            "type":"Services"
        }
    ],
    "sg:phone":"+1 301 260 8005",
    "sg:postcode":"20832",
    "sg:province":"MD",
    "sg:tags":[
        "landscape",
        "contractor"
    ],
    "wof:name":"Nave Landscape Svc",
    "wof:placetype":"venue"
},
  "geometry": {"coordinates":[-77.084716,39.146297],"type":"Point"}
}