{
  "type": "Feature",
  "properties": {
    "iso:country":"US",
    "sg:address":"12266 Rockville Pike",
    "sg:city":"Rockville",
    "sg:classifiers":[
        {
            "category":"Shopping",
            "subcategory":"Hobbies, Toys, & Games",
            "type":"Retail Goods"
        },
        {
            "category":"Shopping",
            "subcategory":"Computers & Home Electronics",
            "type":"Retail Goods"
        }
    ],
    "sg:phone":"+1 301 231 6691",
    "sg:postcode":"20852",
    "sg:province":"MD",
    "sg:tags":[
        "video"
    ],
    "wof:name":"Gamestop",
    "wof:placetype":"venue"
},
  "geometry": {"coordinates":[-77.12018,39.057097],"type":"Point"}
}