{
  "type": "Feature",
  "properties": {
    "addr:full":"8319 Liberty Rd Baltimore MD 21244",
    "addr:housenumber":"8319",
    "addr:postcode":"21244",
    "addr:street":"Liberty Rd",
    "iso:country":"US",
    "sg:address":"8319 Liberty Rd",
    "sg:city":"Baltimore",
    "sg:classifiers":[
        {
            "category":"Professional",
            "subcategory":"Management & Consulting",
            "type":"Services"
        }
    ],
    "sg:phone":"+1 410 922 6104",
    "sg:postcode":"21244",
    "sg:province":"MD",
    "sg:tags":[
        "party",
        "planning"
    ],
    "wof:name":"A Spiritual Psychic Advisor",
    "wof:placetype":"venue"
},
  "geometry": {"coordinates":[-76.767051,39.35686],"type":"Point"}
}