{
  "type": "Feature",
  "properties": {
    "iso:country":"US",
    "sg:address":"12009 Rustic Hill Dr",
    "sg:city":"Bowie",
    "sg:classifiers":[
        {
            "category":"Building & Trades",
            "subcategory":"Construction",
            "type":"Services"
        }
    ],
    "sg:phone":"+1 301 577 2217",
    "sg:postcode":"20715",
    "sg:province":"MD",
    "sg:tags":[
        "house"
    ],
    "wof:name":"Grace Renovations & General Co",
    "wof:placetype":"venue"
},
  "geometry": {"coordinates":[-76.756856,39.000903],"type":"Point"}
}