{
  "type": "Feature",
  "properties": {
    "iso:country":"US",
    "sg:address":"8709 Allentown Rd",
    "sg:city":"Fort Washington",
    "sg:classifiers":[
        {
            "category":"Recreation",
            "type":"Entertainment"
        }
    ],
    "sg:phone":"+1 301 248 4187",
    "sg:postcode":"20744",
    "sg:province":"MD",
    "sg:tags":[
        "bingo",
        "game"
    ],
    "wof:name":"Allentown Road Volunteer Fire",
    "wof:placetype":"venue"
},
  "geometry": {"coordinates":[-76.952455,38.769945],"type":"Point"}
}