{
  "type": "Feature",
  "properties": {
    "iso:country":"US",
    "sg:address":"10751 Falls Rd",
    "sg:city":"Timonium",
    "sg:classifiers":[
        {
            "category":"Banks & Credit Unions",
            "subcategory":"Investment Brokerage",
            "type":"Services"
        }
    ],
    "sg:phone":"+1 410 583 5222",
    "sg:postcode":"21093",
    "sg:province":"MD",
    "sg:tags":[
        "stock",
        "bond"
    ],
    "sg:website":"www.morganstanley.com",
    "wof:name":"Morgan Stanley",
    "wof:placetype":"venue"
},
  "geometry": {"coordinates":[-76.67022799999999,39.420753],"type":"Point"}
}