{
  "type": "Feature",
  "properties": {
    "iso:country":"US",
    "sg:address":"5335 Wisconsin Ave NW",
    "sg:city":"Washington",
    "sg:classifiers":[
        {
            "category":"Shopping",
            "subcategory":"Clothing, Apparel, & Fashions",
            "type":"Retail Goods"
        }
    ],
    "sg:phone":"+1 202 362 5600",
    "sg:postcode":"20015",
    "sg:province":"MD",
    "wof:name":"Koffi Agosu Inc",
    "wof:placetype":"venue"
},
  "geometry": {"coordinates":[-77.084846,38.959041],"type":"Point"}
}