{
  "type": "Feature",
  "properties": {
    "iso:country":"US",
    "sg:address":"2010 Keating St",
    "sg:city":"Temple Hills",
    "sg:classifiers":[
        {
            "category":"Real Estate",
            "subcategory":"Real Estate Services",
            "type":"Services"
        }
    ],
    "sg:phone":"+1 301 423 2121",
    "sg:postcode":"20748",
    "sg:province":"MD",
    "wof:name":"Young Real Estate",
    "wof:placetype":"venue"
},
  "geometry": {"coordinates":[-76.966003,38.8297],"type":"Point"}
}