{
  "type": "Feature",
  "properties": {
    "addr:full":"5774 Main St Rock Hall MD 21661",
    "addr:housenumber":"5774",
    "addr:postcode":"21661",
    "addr:street":"Main St",
    "iso:country":"US",
    "sg:address":"5774 Main St",
    "sg:city":"Rock Hall",
    "sg:classifiers":[
        {
            "category":"Shopping",
            "subcategory":"Clothing, Apparel, & Fashions",
            "type":"Retail Goods"
        }
    ],
    "sg:phone":"+1 410 639 7280",
    "sg:postcode":"21661",
    "sg:province":"MD",
    "wof:name":"Smilin Jake's",
    "wof:placetype":"venue"
},
  "geometry": {"coordinates":[-76.23494100000001,39.137982],"type":"Point"}
}