{
  "type": "Feature",
  "properties": {
    "addr:full":"4005 Ritchie Hwy Baltimore MD 21225",
    "addr:housenumber":"4005",
    "addr:postcode":"21225",
    "addr:street":"Ritchie Hwy",
    "iso:country":"US",
    "sg:address":"4005 Ritchie Hwy",
    "sg:city":"Baltimore",
    "sg:classifiers":[
        {
            "category":"Retail",
            "subcategory":"Veterinary Services",
            "type":"Services"
        }
    ],
    "sg:phone":"+1 410 355 3131",
    "sg:postcode":"21225",
    "sg:province":"MD",
    "sg:tags":[
        "veterinarian"
    ],
    "wof:name":"Goodman Robert DVM",
    "wof:placetype":"venue"
},
  "geometry": {"coordinates":[-76.612139,39.235207],"type":"Point"}
}