{
  "type": "Feature",
  "properties": {
    "iso:country":"US",
    "sg:address":"8649 Tower Bridge Way",
    "sg:city":"Lutherville",
    "sg:classifiers":[
        {
            "category":"Professional",
            "subcategory":"Credit Reporting & Collection",
            "type":"Services"
        }
    ],
    "sg:phone":"+1 410 337 2834",
    "sg:postcode":"21093",
    "sg:province":"MD",
    "sg:tags":[
        "agency"
    ],
    "wof:name":"Classic Collections",
    "wof:placetype":"venue"
},
  "geometry": {"coordinates":[-76.645346,39.428043],"type":"Point"}
}