{
  "type": "Feature",
  "properties": {
    "addr:full":"3010 W Patapsco Ave Baltimore MD 21230",
    "addr:housenumber":"3010",
    "addr:postcode":"21230",
    "addr:street":"W Patapsco Ave",
    "iso:country":"US",
    "sg:address":"3010 W Patapsco Ave",
    "sg:city":"Baltimore",
    "sg:classifiers":[
        {
            "category":"Autos & Motor Vehicles",
            "subcategory":"Auto Supplies",
            "type":"Retail Goods"
        },
        {
            "category":"Retail",
            "subcategory":"Auto Repair",
            "type":"Services"
        }
    ],
    "sg:phone":"+1 410 525 1602",
    "sg:postcode":"21230",
    "sg:province":"MD",
    "sg:tags":[
        "alignment-frame",
        "brake",
        "absorber",
        "tire",
        "automobile",
        "system",
        "lube",
        "equipment-service",
        "wheel",
        "exhaust",
        "oil",
        "strut",
        "servicing-automotive",
        "part",
        "balancing",
        "axle",
        "wheels-aligning",
        "muffler",
        "accessory",
        "air conditioning",
        "shock"
    ],
    "sg:website":"www.midas.com",
    "wof:name":"Midas Auto Service Experts",
    "wof:placetype":"venue"
},
  "geometry": {"coordinates":[-76.661102,39.256302],"type":"Point"}
}