{
  "type": "Feature",
  "properties": {
    "iso:country":"US",
    "sg:address":"7729 Notley Rd",
    "sg:city":"Pasadena",
    "sg:classifiers":[
        {
            "category":"Professional",
            "subcategory":"Business Services",
            "type":"Services"
        }
    ],
    "sg:phone":"+1 410 439 8933",
    "sg:postcode":"21122",
    "sg:province":"MD",
    "sg:tags":[
        "support"
    ],
    "wof:name":"Hsg & Associates",
    "wof:placetype":"venue"
},
  "geometry": {"coordinates":[-76.532265,39.146279],"type":"Point"}
}