{
  "type": "Feature",
  "properties": {
    "addr:full":"6215 Scaggs Rd Owings MD 20736",
    "addr:housenumber":"6215",
    "addr:postcode":"20736",
    "addr:street":"Scaggs Rd",
    "iso:country":"US",
    "sg:address":"6215 Scaggs Rd",
    "sg:city":"Owings",
    "sg:classifiers":[
        {
            "category":"Sports & Exercise",
            "subcategory":"Golf",
            "type":"Entertainment"
        }
    ],
    "sg:phone":"+1 410 286 8212",
    "sg:postcode":"20736",
    "sg:province":"MD",
    "sg:tags":[
        "course"
    ],
    "sg:website":"http://www.mellomar.com",
    "wof:name":"Mellomar Golf Park",
    "wof:placetype":"venue"
},
  "geometry": {"coordinates":[-76.677305,38.652567],"type":"Point"}
}