{
  "type": "Feature",
  "properties": {
    "addr:full":"1620 Whitehead Ct Gwynn Oak MD 21207",
    "addr:housenumber":"1620",
    "addr:postcode":"21207",
    "addr:street":"Whitehead Ct",
    "iso:country":"US",
    "sg:address":"1620 Whitehead Ct",
    "sg:city":"Gwynn Oak",
    "sg:classifiers":[
        {
            "category":"Food & Beverages",
            "subcategory":"Liquor & Beverages",
            "type":"Retail Goods"
        }
    ],
    "sg:phone":"+1 410 944 9400",
    "sg:postcode":"21207",
    "sg:province":"MD",
    "sg:tags":[
        "beer",
        "spirit",
        "wine"
    ],
    "wof:name":"Ellerin Charles",
    "wof:placetype":"venue"
},
  "geometry": {"coordinates":[-76.737602,39.310902],"type":"Point"}
}