{
  "type": "Feature",
  "properties": {
    "addr:full":"2118 Emmorton Park Dr Edgewood MD 21040",
    "addr:housenumber":"2118",
    "addr:postcode":"21040",
    "addr:street":"Emmorton Park Dr",
    "iso:country":"US",
    "sg:address":"2118 Emmorton Park Dr",
    "sg:city":"Edgewood",
    "sg:classifiers":[
        {
            "category":"Travel",
            "subcategory":"Hotels & Motels",
            "type":"Entertainment"
        }
    ],
    "sg:phone":"+1 410 612 1200",
    "sg:postcode":"21040",
    "sg:province":"MD",
    "sg:website":"www.6continentshotel.com",
    "wof:name":"Holiday Inn Express Edgewood",
    "wof:placetype":"venue"
},
  "geometry": {"coordinates":[-76.309708,39.452469],"type":"Point"}
}