{
  "type": "Feature",
  "properties": {
    "iso:country":"US",
    "sg:address":"245 High St",
    "sg:city":"Chestertown",
    "sg:classifiers":[
        {
            "category":"Banks & Credit Unions",
            "subcategory":"Bank",
            "type":"Services"
        },
        {
            "category":"Banks & Credit Unions",
            "subcategory":"Financial Services",
            "type":"Services"
        }
    ],
    "sg:phone":"+1 410 778 1600",
    "sg:postcode":"21620",
    "sg:province":"MD",
    "sg:tags":[
        "consultant",
        "financing",
        "planning",
        "mortgage"
    ],
    "sg:website":"http://www.chesapeaketrust.com",
    "wof:name":"Chesapeake Bank and Trust Company",
    "wof:placetype":"venue"
},
  "geometry": {"coordinates":[-76.065933,39.208713],"type":"Point"}
}