{
  "type": "Feature",
  "properties": {
    "addr:full":"15851 Commerce Ct Upper Marlboro MD 20774",
    "addr:housenumber":"15851",
    "addr:postcode":"20774",
    "addr:street":"Commerce Ct",
    "iso:country":"US",
    "sg:address":"15851 Commerce Ct",
    "sg:city":"Upper Marlboro",
    "sg:classifiers":[
        {
            "category":"Home & Garden",
            "subcategory":"Furniture",
            "type":"Retail Goods"
        }
    ],
    "sg:phone":"+1 301 430 0800",
    "sg:postcode":"20774",
    "sg:province":"MD",
    "sg:tags":[
        "equipment",
        "kitchen",
        "cabinet"
    ],
    "wof:name":"Blue Heron Kitchn & Bath Dsgn",
    "wof:placetype":"venue"
},
  "geometry": {"coordinates":[-76.730756,38.88501],"type":"Point"}
}