{
  "type": "Feature",
  "properties": {
    "addr:full":"3919 Hampden St Kensington MD 20895",
    "addr:housenumber":"3919",
    "addr:postcode":"20895",
    "addr:street":"Hampden St",
    "iso:country":"US",
    "sg:address":"3919 Hampden St",
    "sg:city":"Kensington",
    "sg:classifiers":[
        {
            "category":"Freight",
            "type":"Transportation"
        }
    ],
    "sg:phone":"+1 301 949 8631",
    "sg:postcode":"20895",
    "sg:province":"MD",
    "sg:tags":[
        "trucking"
    ],
    "wof:name":"Harrison Trucking Co",
    "wof:placetype":"venue"
},
  "geometry": {"coordinates":[-77.079424,39.031821],"type":"Point"}
}