{
  "type": "Feature",
  "properties": {
    "addr:full":"2301 Liberty Heights Ave Baltimore MD 21215",
    "addr:housenumber":"2301",
    "addr:postcode":"21215",
    "addr:street":"Liberty Heights Ave",
    "iso:country":"US",
    "sg:address":"2301 Liberty Heights Ave",
    "sg:city":"Baltimore",
    "sg:classifiers":[
        {
            "category":"Shopping",
            "subcategory":"Clothing, Apparel, & Fashions",
            "type":"Retail Goods"
        }
    ],
    "sg:phone":"+1 410 669 3244",
    "sg:postcode":"21215",
    "sg:province":"MD",
    "sg:tags":[
        "accessory"
    ],
    "wof:name":"Simply Fashions",
    "wof:placetype":"venue"
},
  "geometry": {"coordinates":[-76.65252,39.318436],"type":"Point"}
}