{
  "type": "Feature",
  "properties": {
    "iso:country":"US",
    "sg:address":"11023 Locust Dr",
    "sg:city":"Damascus",
    "sg:classifiers":[
        {
            "category":"Building & Trades",
            "subcategory":"Plumbing",
            "type":"Services"
        }
    ],
    "sg:phone":"+1 301 253 5895",
    "sg:postcode":"20872",
    "sg:province":"MD",
    "sg:tags":[
        "plumbing",
        "contractor"
    ],
    "wof:name":"Ed Fitterer Enterprises",
    "wof:placetype":"venue"
},
  "geometry": {"coordinates":[-77.208607,39.289288],"type":"Point"}
}