{
  "type": "Feature",
  "properties": {
    "addr:full":"101 8th St Pocomoke City MD 21851",
    "addr:housenumber":"101",
    "addr:postcode":"21851",
    "addr:street":"8Th St",
    "iso:country":"US",
    "sg:address":"101 8th St",
    "sg:city":"Pocomoke City",
    "sg:classifiers":[
        {
            "category":"Insurance",
            "subcategory":"Insurance Agent",
            "type":"Services"
        }
    ],
    "sg:phone":"+1 410 957 3298",
    "sg:postcode":"21851",
    "sg:province":"MD",
    "wof:name":"Marshall Insurance",
    "wof:placetype":"venue"
},
  "geometry": {"coordinates":[-75.558937,38.074273],"type":"Point"}
}