{
  "type": "Feature",
  "properties": {
    "addr:full":"706 Camden Avenue Salisbury MD 21801",
    "addr:housenumber":"706",
    "addr:postcode":"21801",
    "addr:street":"Camden Avenue",
    "iso:country":"US",
    "sg:address":"706 Camden Avenue",
    "sg:city":"Salisbury",
    "sg:classifiers":[
        {
            "category":"Personal",
            "subcategory":"Massage",
            "type":"Services"
        },
        {
            "category":"Health Services",
            "subcategory":"Health Practitioner",
            "type":"Services"
        },
        {
            "category":"Personal",
            "subcategory":"Skin Care",
            "type":"Services"
        }
    ],
    "sg:phone":"+1 443 880 3477",
    "sg:postcode":"21801",
    "sg:province":"MD",
    "sg:tags":[
        "medicine",
        "aromatherapy",
        "alternative",
        "therapist"
    ],
    "sg:website":"http://www.chesapeake-massage.com",
    "wof:name":"Chesapeake Massage & Bodywork",
    "wof:placetype":"venue"
},
  "geometry": {"coordinates":[-75.605334,38.357921],"type":"Point"}
}