{
  "type": "Feature",
  "properties": {
    "iso:country":"US",
    "sg:address":"10003 Derekwood Ln # 200",
    "sg:city":"Lanham",
    "sg:classifiers":[
        {
            "category":"Social Services",
            "type":"Services"
        },
        {
            "category":"Health Services",
            "subcategory":"Clinic",
            "type":"Services"
        }
    ],
    "sg:phone":"+1 301 429 2370",
    "sg:postcode":"20706",
    "sg:province":"MD",
    "sg:tags":[
        "welfare"
    ],
    "sg:website":"http://www.concern4kids.org",
    "wof:name":"Concern Professional Services For Children, Youth & Families",
    "wof:placetype":"venue"
},
  "geometry": {"coordinates":[-76.833265,38.948813],"type":"Point"}
}