{
  "type": "Feature",
  "properties": {
    "iso:country":"US",
    "sg:address":"300 Upper College Ter",
    "sg:city":"Frederick",
    "sg:classifiers":[
        {
            "category":"Health Services",
            "subcategory":"Doctor",
            "type":"Services"
        }
    ],
    "sg:phone":"+1 301 662 2862",
    "sg:postcode":"21701",
    "sg:province":"MD",
    "sg:tags":[
        "dentist"
    ],
    "wof:name":"Robert E Broadrup DDS",
    "wof:placetype":"venue"
},
  "geometry": {"coordinates":[-77.419823,39.420052],"type":"Point"}
}