{
  "type": "Feature",
  "properties": {
    "addr:full":"4001 Ritchie Hwy Brooklyn MD 21225",
    "addr:housenumber":"4001",
    "addr:postcode":"21225",
    "addr:street":"Ritchie Hwy",
    "iso:country":"US",
    "sg:address":"4001 Ritchie Hwy",
    "sg:city":"Brooklyn",
    "sg:classifiers":[
        {
            "category":"Retail",
            "subcategory":"Funeral Services",
            "type":"Services"
        }
    ],
    "sg:phone":"+1 410 789 1800",
    "sg:postcode":"21225",
    "sg:province":"MD",
    "sg:tags":[
        "cemetery"
    ],
    "wof:name":"Gonce Geo J Funeral Home PA",
    "wof:placetype":"venue"
},
  "geometry": {"coordinates":[-76.611801,39.234299],"type":"Point"}
}