{
  "type": "Feature",
  "properties": {
    "iso:country":"US",
    "sg:address":"120 Cockeysville Rd",
    "sg:city":"Cockysvl Hnt Vly",
    "sg:classifiers":[
        {
            "category":"Wholesale",
            "subcategory":"Machinery & Supplies",
            "type":"Manufacturing & Wholesale Goods"
        }
    ],
    "sg:phone":"+1 410 771 8800",
    "sg:postcode":"21030",
    "sg:province":"MD",
    "wof:name":"Empire Corrugated Machinery",
    "wof:placetype":"venue"
},
  "geometry": {"coordinates":[-76.64707,39.481795],"type":"Point"}
}