{
  "type": "Feature",
  "properties": {
    "addr:full":"21921 Three Notch Rd Lexington Park MD 20653",
    "addr:housenumber":"21921",
    "addr:postcode":"20653",
    "addr:street":"Three Notch Rd",
    "iso:country":"US",
    "sg:address":"21921 Three Notch Rd",
    "sg:city":"Lexington Park",
    "sg:classifiers":[
        {
            "category":"Health Services",
            "subcategory":"Doctor",
            "type":"Services"
        }
    ],
    "sg:phone":"+1 301 863 7067",
    "sg:postcode":"20653",
    "sg:province":"MD",
    "sg:tags":[
        "surgeon",
        "oral"
    ],
    "wof:name":"Wood Blair K DDS",
    "wof:placetype":"venue"
},
  "geometry": {"coordinates":[-76.459537,38.269658],"type":"Point"}
}