{
  "type": "Feature",
  "properties": {
    "addr:full":"3250 Superior Ln Bowie MD 20715",
    "addr:housenumber":"3250",
    "addr:postcode":"20715",
    "addr:street":"Superior Ln",
    "iso:country":"US",
    "sg:address":"3250 Superior Ln",
    "sg:city":"Bowie",
    "sg:classifiers":[
        {
            "category":"Wholesale",
            "subcategory":"Medical Equipment & Supplies",
            "type":"Manufacturing & Wholesale Goods"
        },
        {
            "category":"Shopping",
            "subcategory":"Beauty & Cosmetics",
            "type":"Retail Goods"
        },
        {
            "category":"Food & Beverages",
            "subcategory":"Specialty",
            "type":"Retail Goods"
        },
        {
            "category":"Shopping",
            "subcategory":"Gifts & Souvenirs",
            "type":"Retail Goods"
        },
        {
            "category":"Retail",
            "subcategory":"Photofinishing",
            "type":"Services"
        },
        {
            "category":"Shopping",
            "subcategory":"Pharmacy",
            "type":"Retail Goods"
        }
    ],
    "sg:phone":"+1 301 805 1866",
    "sg:postcode":"20715",
    "sg:province":"MD",
    "sg:tags":[
        "product",
        "photo",
        "vitamin",
        "perfume",
        "supplement",
        "health",
        "wellness",
        "aid",
        "finishing",
        "first",
        "card",
        "greeting"
    ],
    "sg:website":"http://www.riteaid.com",
    "wof:name":"Rite Aid",
    "wof:placetype":"venue"
},
  "geometry": {"coordinates":[-76.73264500000001,38.977706],"type":"Point"}
}