{
  "type": "Feature",
  "properties": {
    "addr:full":"1100 Batavia Farm Rd Baltimore MD 21237",
    "addr:housenumber":"1100",
    "addr:postcode":"21237",
    "addr:street":"Batavia Farm Rd",
    "iso:country":"US",
    "sg:address":"1100 Batavia Farm Rd",
    "sg:city":"Baltimore",
    "sg:classifiers":[
        {
            "category":"Building & Trades",
            "subcategory":"Construction",
            "type":"Services"
        }
    ],
    "sg:phone":"+1 410 682 5000",
    "sg:postcode":"21237",
    "sg:province":"MD",
    "sg:tags":[
        "roofing",
        "contractor"
    ],
    "wof:name":"MICHAEL J Bollinger Roofing Co",
    "wof:placetype":"venue"
},
  "geometry": {"coordinates":[-76.505517,39.320302],"type":"Point"}
}