{
  "type": "Feature",
  "properties": {
    "addr:full":"15 Charles St Walkersville MD 21793",
    "addr:housenumber":"15",
    "addr:postcode":"21793",
    "addr:street":"Charles St",
    "iso:country":"US",
    "sg:address":"15 Charles St",
    "sg:city":"Walkersville",
    "sg:classifiers":[
        {
            "category":"Building & Trades",
            "subcategory":"Landscaping Services",
            "type":"Services"
        }
    ],
    "sg:phone":"+1 301 845 0944",
    "sg:postcode":"21793",
    "sg:province":"MD",
    "sg:tags":[
        "designer",
        "landscape"
    ],
    "wof:name":"Jester Landscape Inc",
    "wof:placetype":"venue"
},
  "geometry": {"coordinates":[-77.34870600000001,39.487946],"type":"Point"}
}