{
  "type": "Feature",
  "properties": {
    "iso:country":"US",
    "sg:address":"8008 Custer Rd",
    "sg:city":"Bethesda",
    "sg:classifiers":[
        {
            "category":"Health Services",
            "subcategory":"Doctor",
            "type":"Services"
        }
    ],
    "sg:phone":"+1 301 372 1814",
    "sg:postcode":"20814",
    "sg:province":"MD",
    "sg:tags":[
        "physician",
        "surgeon"
    ],
    "wof:name":"Kathleen C Ackerman MD",
    "wof:placetype":"venue"
},
  "geometry": {"coordinates":[-77.107792,38.9909],"type":"Point"}
}