{
  "type": "Feature",
  "properties": {
    "addr:full":"8407 Main St Ellicott City MD 21043",
    "addr:housenumber":"8407",
    "addr:postcode":"21043",
    "addr:street":"Main St",
    "iso:country":"US",
    "sg:address":"8407 Main St",
    "sg:city":"Ellicott City",
    "sg:classifiers":[
        {
            "category":"Professional",
            "type":"Services"
        }
    ],
    "sg:phone":"+1 410 313 8215",
    "sg:postcode":"21043",
    "sg:province":"MD",
    "sg:tags":[
        "establishment"
    ],
    "wof:name":"Schlossberg M",
    "wof:placetype":"venue"
},
  "geometry": {"coordinates":[-76.80061600000001,39.268404],"type":"Point"}
}