{
  "type": "Feature",
  "properties": {
    "addr:full":"4610 Tournay Rd Bethesda MD 20816",
    "addr:postcode":"4610;20816",
    "addr:street":"Tournay Rd",
    "iso:country":"US",
    "sg:address":"4610 Tournay Rd",
    "sg:city":"Bethesda",
    "sg:classifiers":[
        {
            "category":"Education",
            "subcategory":"Special Training",
            "type":"Public Place"
        }
    ],
    "sg:phone":"+1 301 229 0777",
    "sg:postcode":"20816",
    "sg:province":"MD",
    "wof:name":"Mann Paller Foundation Inc",
    "wof:placetype":"venue"
},
  "geometry": {"coordinates":[-77.110765,38.950244],"type":"Point"}
}