{
  "type": "Feature",
  "properties": {
    "iso:country":"US",
    "sg:address":"6506 Baltimore Natinl Pke",
    "sg:city":"Catonsville",
    "sg:classifiers":[
        {
            "category":"Restaurant",
            "type":"Food & Drink"
        }
    ],
    "sg:phone":"+1 410 455 5140",
    "sg:postcode":"21228",
    "sg:province":"MD",
    "wof:name":"Old Country Buffet",
    "wof:placetype":"venue"
},
  "geometry": {"coordinates":[-76.7621,39.2859],"type":"Point"}
}