{
  "type": "Feature",
  "properties": {
    "iso:country":"US",
    "sg:address":"2427 Repton Ct",
    "sg:city":"Windsor Mill",
    "sg:classifiers":[
        {
            "category":"Professional",
            "subcategory":"Computer Services",
            "type":"Services"
        }
    ],
    "sg:phone":"+1 877 799 7117",
    "sg:postcode":"21244",
    "sg:province":"MD",
    "sg:tags":[
        "repair"
    ],
    "sg:website":"www.sdpsquared.com",
    "wof:name":"SDP Squared",
    "wof:placetype":"venue"
},
  "geometry": {"coordinates":[-76.76818,39.328152],"type":"Point"}
}