{
  "type": "Feature",
  "properties": {
    "addr:full":"10300 Mill Run Cir Owings Mills MD 21117",
    "addr:housenumber":"10300",
    "addr:postcode":"21117",
    "addr:street":"Mill Run Cir",
    "iso:country":"US",
    "sg:address":"10300 Mill Run Cir",
    "sg:city":"Owings Mills",
    "sg:classifiers":[
        {
            "category":"Personal",
            "subcategory":"Shoe Repair & Shine",
            "type":"Services"
        }
    ],
    "sg:phone":"+1 410 363 1666",
    "sg:postcode":"21117",
    "sg:province":"MD",
    "sg:tags":[
        "repairing",
        "boot"
    ],
    "wof:name":"Hakky Instant Shoe Repair",
    "wof:placetype":"venue"
},
  "geometry": {"coordinates":[-76.793564,39.407503],"type":"Point"}
}