{
  "type": "Feature",
  "properties": {
    "iso:country":"US",
    "sg:address":"7549 Montevideo Rd",
    "sg:city":"Jessup",
    "sg:classifiers":[
        {
            "category":"Building & Trades",
            "subcategory":"Landscaping Services",
            "type":"Services"
        }
    ],
    "sg:phone":"+1 410 799 3266",
    "sg:postcode":"20794",
    "sg:province":"MD",
    "sg:tags":[
        "tree"
    ],
    "wof:name":"Excel Tree Expert Co Inc",
    "wof:placetype":"venue"
},
  "geometry": {"coordinates":[-76.76739000000001,39.162597],"type":"Point"}
}