{
  "type": "Feature",
  "properties": {
    "iso:country":"US",
    "sg:address":"4111 Kahlston Rd",
    "sg:city":"Nottingham",
    "sg:classifiers":[
        {
            "category":"Professional",
            "subcategory":"Employment Agencies",
            "type":"Services"
        }
    ],
    "sg:phone":"+1 410 248 9212",
    "sg:postcode":"21236",
    "sg:province":"MD",
    "sg:tags":[
        "leasing"
    ],
    "wof:name":"Management Consultant Cnnctn",
    "wof:placetype":"venue"
},
  "geometry": {"coordinates":[-76.466396,39.419326],"type":"Point"}
}