{
  "type": "Feature",
  "properties": {
    "iso:country":"US",
    "sg:address":"3829 Eastern Ave",
    "sg:city":"Baltimore",
    "sg:classifiers":[
        {
            "category":"Home & Garden",
            "subcategory":"Furniture",
            "type":"Retail Goods"
        }
    ],
    "sg:phone":"+1 410 558 1045",
    "sg:postcode":"21224",
    "sg:province":"MD",
    "sg:tags":[
        "store"
    ],
    "wof:name":"Maxim Furniture",
    "wof:placetype":"venue"
},
  "geometry": {"coordinates":[-76.564995,39.28653],"type":"Point"}
}