{
  "type": "Feature",
  "properties": {
    "iso:country":"US",
    "sg:address":"3244 Conowingo Rd",
    "sg:city":"Street",
    "sg:classifiers":[
        {
            "category":"Wholesale",
            "subcategory":"Construction Materials",
            "type":"Manufacturing & Wholesale Goods"
        }
    ],
    "sg:phone":"+1 410 836 3552",
    "sg:postcode":"21154",
    "sg:province":"MD",
    "sg:tags":[
        "fence"
    ],
    "wof:name":"L & L Kennels & Fencing",
    "wof:placetype":"venue"
},
  "geometry": {"coordinates":[-76.281769,39.628421],"type":"Point"}
}