{
  "type": "Feature",
  "properties": {
    "addr:full":"921 Hoffmaster Rd Knoxville MD 21758",
    "addr:housenumber":"921",
    "addr:postcode":"21758",
    "addr:street":"Hoffmaster Rd",
    "iso:country":"US",
    "sg:address":"921 Hoffmaster Rd",
    "sg:city":"Knoxville",
    "sg:classifiers":[
        {
            "category":"Recreation",
            "type":"Entertainment"
        }
    ],
    "sg:phone":"+1 301 834 8882",
    "sg:postcode":"21758",
    "sg:province":"MD",
    "sg:tags":[
        "stable"
    ],
    "wof:name":"Elk Mountain Trails Inc",
    "wof:placetype":"venue"
},
  "geometry": {"coordinates":[-77.723913,39.350951],"type":"Point"}
}