{
  "type": "Feature",
  "properties": {
    "addr:full":"540 Dundalk Ave Baltimore MD 21224",
    "addr:housenumber":"540",
    "addr:postcode":"21224",
    "addr:street":"Dundalk Ave",
    "iso:country":"US",
    "sg:address":"540 Dundalk Ave",
    "sg:city":"Baltimore",
    "sg:classifiers":[
        {
            "category":"Organizations",
            "subcategory":"Labor Organization",
            "type":"Services"
        }
    ],
    "sg:phone":"+1 410 633 7400",
    "sg:postcode":"21224",
    "sg:province":"MD",
    "wof:name":"Steelworkers Hall",
    "wof:placetype":"venue"
},
  "geometry": {"coordinates":[-76.542393,39.286572],"type":"Point"}
}