{
  "type": "Feature",
  "properties": {
    "iso:country":"US",
    "sg:address":"19837 National Pike",
    "sg:city":"Hagerstown",
    "sg:classifiers":[
        {
            "category":"Communications",
            "type":"Services"
        }
    ],
    "sg:phone":"+1 301 733 9427",
    "sg:postcode":"21740",
    "sg:province":"MD",
    "wof:name":"Luvin Media Inc.",
    "wof:placetype":"venue"
},
  "geometry": {"coordinates":[-77.678467,39.593359],"type":"Point"}
}