{
  "type": "Feature",
  "properties": {
    "iso:country":"US",
    "sg:address":"6908 Kingston Dr",
    "sg:city":"Temple Hills",
    "sg:classifiers":[
        {
            "category":"Bus Charters",
            "type":"Transportation"
        }
    ],
    "sg:phone":"+1 301 449 0011",
    "sg:postcode":"20748",
    "sg:province":"MD",
    "sg:tags":[
        "rental"
    ],
    "wof:name":"Becton's Elite Getaway",
    "wof:placetype":"venue"
},
  "geometry": {"coordinates":[-76.916478,38.792415],"type":"Point"}
}