{
  "type": "Feature",
  "properties": {
    "addr:full":"3607 Lord Baltimore Way Monkton MD 21111",
    "addr:housenumber":"3607",
    "addr:postcode":"21111",
    "addr:street":"Lord Baltimore Way",
    "iso:country":"US",
    "sg:address":"3607 Lord Baltimore Way",
    "sg:city":"Monkton",
    "sg:classifiers":[
        {
            "category":"Social Services",
            "type":"Services"
        }
    ],
    "sg:phone":"+1 410 557 8168",
    "sg:postcode":"21111",
    "sg:province":"MD",
    "wof:name":"Full Cycle Parenting Inc",
    "wof:placetype":"venue"
},
  "geometry": {"coordinates":[-76.513479,39.588143],"type":"Point"}
}