{
  "type": "Feature",
  "properties": {
    "iso:country":"US",
    "sg:address":"8666 Old Ardmore Place",
    "sg:city":"Hyattsville",
    "sg:classifiers":[
        {
            "category":"Transit Center",
            "subcategory":"Freight",
            "type":"Transportation"
        },
        {
            "category":"Professional",
            "subcategory":"Business Services",
            "type":"Services"
        },
        {
            "category":"Taxi",
            "type":"Transportation"
        },
        {
            "category":"Government",
            "subcategory":"Post Office",
            "type":"Public Place"
        }
    ],
    "sg:phone":"+1 301 322 8100",
    "sg:postcode":"20785",
    "sg:province":"MD",
    "sg:tags":[
        "cargo",
        "courier",
        "package",
        "express",
        "air",
        "delivery",
        "messenger",
        "forwarding"
    ],
    "wof:name":"American Expediting Express Courier Delivery Service",
    "wof:placetype":"venue"
},
  "geometry": {"coordinates":[-76.85867500000001,38.938788],"type":"Point"}
}