{
  "type": "Feature",
  "properties": {
    "addr:full":"1111 N Rolling Rd Catonsville MD 21228",
    "addr:housenumber":"1111",
    "addr:postcode":"21228",
    "addr:street":"N Rolling Rd",
    "iso:country":"US",
    "sg:address":"1111 N Rolling Rd",
    "sg:city":"Catonsville",
    "sg:classifiers":[
        {
            "category":"Restaurant",
            "type":"Food & Drink"
        }
    ],
    "sg:phone":"+1 410 788 4777",
    "sg:postcode":"21228",
    "sg:province":"MD",
    "sg:tags":[
        "korean",
        "chinese"
    ],
    "wof:name":"Jang Won Restaurant",
    "wof:placetype":"venue"
},
  "geometry": {"coordinates":[-76.752712,39.285281],"type":"Point"}
}