{
  "type": "Feature",
  "properties": {
    "addr:full":"9 Wytchwood Ct Apt 201 Baltimore MD 21209",
    "addr:housenumber":"9;201",
    "addr:postcode":"21209",
    "addr:street":"Wytchwood Ct Apt",
    "iso:country":"US",
    "sg:address":"9 Wytchwood Ct Apt 201",
    "sg:city":"Baltimore",
    "sg:classifiers":[
        {
            "category":"Wholesale",
            "subcategory":"Books, Periodicals, & Newspapers",
            "type":"Manufacturing & Wholesale Goods"
        }
    ],
    "sg:phone":"+1 410 466 2814",
    "sg:postcode":"21209",
    "sg:province":"MD",
    "sg:tags":[
        "publisher",
        "book"
    ],
    "wof:name":"Mark V Stein",
    "wof:placetype":"venue"
},
  "geometry": {"coordinates":[-76.66167299999999,39.379893],"type":"Point"}
}