{
  "type": "Feature",
  "properties": {
    "iso:country":"US",
    "sg:address":"2640 Saint Paul St",
    "sg:city":"Baltimore",
    "sg:classifiers":[
        {
            "category":"Organizations",
            "subcategory":"Religious Organization",
            "type":"Services"
        }
    ],
    "sg:phone":"+1 410 366 7733",
    "sg:postcode":"21218",
    "sg:province":"MD",
    "sg:website":"www.umc.org",
    "wof:name":"St John's United Methodist Church",
    "wof:placetype":"venue"
},
  "geometry": {"coordinates":[-76.615709,39.319973],"type":"Point"}
}