{
  "type": "Feature",
  "properties": {
    "addr:full":"10720 Roberts Private Rd Cockysvl Hnt Vly MD 21030",
    "addr:housenumber":"10720",
    "addr:postcode":"21030",
    "addr:street":"Roberts Private Rd;Hnt Vly",
    "iso:country":"US",
    "sg:address":"10720 Roberts Private Rd",
    "sg:city":"Cockysvl Hnt Vly",
    "sg:classifiers":[
        {
            "category":"Home & Garden",
            "subcategory":"Building Materials",
            "type":"Retail Goods"
        }
    ],
    "sg:phone":"+1 410 666 1260",
    "sg:postcode":"21030",
    "sg:province":"MD",
    "sg:tags":[
        "glass",
        "window",
        "plate"
    ],
    "wof:name":"Valley Glass Co",
    "wof:placetype":"venue"
},
  "geometry": {"coordinates":[-76.645088,39.479576],"type":"Point"}
}