{
  "type": "Feature",
  "properties": {
    "addr:full":"3703 Spanish Bay Ct Elkton MD 21921",
    "addr:housenumber":"3703",
    "addr:postcode":"21921",
    "addr:street":"Spanish Bay Ct",
    "iso:country":"US",
    "sg:address":"3703 Spanish Bay Ct",
    "sg:city":"Elkton",
    "sg:classifiers":[
        {
            "category":"Professional",
            "subcategory":"Employment Agencies",
            "type":"Services"
        }
    ],
    "sg:phone":"+1 410 398 3205",
    "sg:postcode":"21921",
    "sg:province":"MD",
    "sg:tags":[
        "help",
        "supply"
    ],
    "wof:name":"Justin D Lacasse",
    "wof:placetype":"venue"
},
  "geometry": {"coordinates":[-75.788155,39.616055],"type":"Point"}
}