{
  "type": "Feature",
  "properties": {
    "iso:country":"US",
    "sg:address":"2532 Running Wolf Trl",
    "sg:city":"Odenton",
    "sg:classifiers":[
        {
            "category":"Professional",
            "subcategory":"Printing & Photocopies",
            "type":"Services"
        }
    ],
    "sg:phone":"+1 410 672 7563",
    "sg:postcode":"21113",
    "sg:province":"MD",
    "sg:tags":[
        "services-commercial"
    ],
    "wof:name":"Pip's Dock Street Dogs",
    "wof:placetype":"venue"
},
  "geometry": {"coordinates":[-76.71935999999999,39.057468],"type":"Point"}
}