{
  "type": "Feature",
  "properties": {
    "iso:country":"US",
    "sg:address":"3408 Westport Dr",
    "sg:city":"Jefferson",
    "sg:classifiers":[
        {
            "category":"Building & Trades",
            "subcategory":"Construction",
            "type":"Services"
        }
    ],
    "sg:phone":"+1 301 473 7322",
    "sg:postcode":"21755",
    "sg:province":"MD",
    "sg:tags":[
        "painter"
    ],
    "sg:website":"www.dunndecorating.com",
    "wof:name":"Dunn Decorating",
    "wof:placetype":"venue"
},
  "geometry": {"coordinates":[-77.55120100000001,39.361599],"type":"Point"}
}