{
  "type": "Feature",
  "properties": {
    "addr:full":"515 Brightfield Rd Lutherville MD 21093",
    "addr:housenumber":"515",
    "addr:postcode":"21093",
    "addr:street":"Brightfield Rd",
    "iso:country":"US",
    "sg:address":"515 Brightfield Rd",
    "sg:city":"Lutherville",
    "sg:classifiers":[
        {
            "category":"Health Services",
            "subcategory":"Nursing And Care Facility",
            "type":"Services"
        }
    ],
    "sg:phone":"+1 410 296 1990",
    "sg:postcode":"21093",
    "sg:province":"MD",
    "sg:tags":[
        "home",
        "convalescent"
    ],
    "sg:website":"www.ghv.com",
    "wof:name":"Brightwood Center",
    "wof:placetype":"venue"
},
  "geometry": {"coordinates":[-76.66592,39.40672],"type":"Point"}
}