{
  "type": "Feature",
  "properties": {
    "iso:country":"US",
    "sg:address":"1709 Crawford Dr",
    "sg:city":"Rockville",
    "sg:classifiers":[
        {
            "category":"Home & Garden",
            "subcategory":"Furniture",
            "type":"Retail Goods"
        }
    ],
    "sg:phone":"+1 301 738 3200",
    "sg:postcode":"20851",
    "sg:province":"MD",
    "wof:name":"Colonical Magi-Seal",
    "wof:placetype":"venue"
},
  "geometry": {"coordinates":[-77.124193,39.073467],"type":"Point"}
}