{
  "type": "Feature",
  "properties": {
    "addr:full":"8506 Hempstead Ave Bethesda MD 20817",
    "addr:housenumber":"8506",
    "addr:postcode":"20817",
    "addr:street":"Hempstead Ave",
    "iso:country":"US",
    "sg:address":"8506 Hempstead Ave",
    "sg:city":"Bethesda",
    "sg:classifiers":[
        {
            "category":"Professional",
            "subcategory":"Lawyer & Legal Services",
            "type":"Services"
        }
    ],
    "sg:phone":"+1 301 530 7274",
    "sg:postcode":"20817",
    "sg:province":"MD",
    "wof:name":"Goldberg James M Atty",
    "wof:placetype":"venue"
},
  "geometry": {"coordinates":[-77.117288,38.995277],"type":"Point"}
}