{
  "type": "Feature",
  "properties": {
    "addr:full":"1349 Generals Hwy Crownsville MD 21032",
    "addr:housenumber":"1349",
    "addr:postcode":"21032",
    "addr:street":"Generals Hwy",
    "iso:country":"US",
    "sg:address":"1349 Generals Hwy",
    "sg:city":"Crownsville",
    "sg:classifiers":[
        {
            "category":"Personal",
            "subcategory":"Beauty Salon",
            "type":"Services"
        }
    ],
    "sg:phone":"+1 410 923 9390",
    "sg:postcode":"21032",
    "sg:province":"MD",
    "sg:tags":[
        "manicuring"
    ],
    "wof:name":"Modern Nails",
    "wof:placetype":"venue"
},
  "geometry": {"coordinates":[-76.60357500000001,39.028685],"type":"Point"}
}