{
  "type": "Feature",
  "properties": {
    "addr:full":"17060 King James Way Gaithersburg MD 20877",
    "addr:housenumber":"17060",
    "addr:postcode":"20877",
    "addr:street":"King James Way",
    "iso:country":"US",
    "sg:address":"17060 King James Way",
    "sg:city":"Gaithersburg",
    "sg:classifiers":[
        {
            "category":"Professional",
            "subcategory":"Management & Consulting",
            "type":"Services"
        }
    ],
    "sg:phone":"+1 301 963 9045",
    "sg:postcode":"20877",
    "sg:province":"MD",
    "sg:tags":[
        "engineering"
    ],
    "wof:name":"Mongomery Financial Services",
    "wof:placetype":"venue"
},
  "geometry": {"coordinates":[-77.206495,39.136194],"type":"Point"}
}