{
  "type": "Feature",
  "properties": {
    "addr:full":"3531 Gough St Baltimore MD 21224",
    "addr:housenumber":"3531",
    "addr:postcode":"21224",
    "addr:street":"Gough St",
    "iso:country":"US",
    "sg:address":"3531 Gough St",
    "sg:city":"Baltimore",
    "sg:classifiers":[
        {
            "category":"Bars & Pubs",
            "type":"Food & Drink"
        },
        {
            "category":"Restaurant",
            "type":"Food & Drink"
        }
    ],
    "sg:phone":"+1 410 342 6544",
    "sg:postcode":"21224",
    "sg:province":"MD",
    "sg:website":"www.laughingpint.com",
    "wof:name":"The Laughing Pint",
    "wof:placetype":"venue"
},
  "geometry": {"coordinates":[-76.567401,39.288456],"type":"Point"}
}