{
  "type": "Feature",
  "properties": {
    "iso:country":"US",
    "sg:address":"21 Scottsdale Ct",
    "sg:city":"Lutherville",
    "sg:classifiers":[
        {
            "category":"Health Services",
            "subcategory":"Doctor",
            "type":"Services"
        }
    ],
    "sg:phone":"+1 410 296 0872",
    "sg:postcode":"21093",
    "sg:province":"MD",
    "sg:tags":[
        "physician",
        "surgeon"
    ],
    "wof:name":"Christopher Harvey MD",
    "wof:placetype":"venue"
},
  "geometry": {"coordinates":[-76.65452999999999,39.421297],"type":"Point"}
}