{
  "type": "Feature",
  "properties": {
    "iso:country":"US",
    "sg:address":"4407 Poplar Neck Rd",
    "sg:city":"Preston",
    "sg:classifiers":[
        {
            "category":"Farming",
            "subcategory":"Farm",
            "type":"Manufacturing & Wholesale Goods"
        }
    ],
    "sg:phone":"+1 410 673 2253",
    "sg:postcode":"21655",
    "sg:province":"MD",
    "sg:tags":[
        "crop",
        "general"
    ],
    "wof:name":"Poplar Acres Farm",
    "wof:placetype":"venue"
},
  "geometry": {"coordinates":[-75.932623,38.728216],"type":"Point"}
}