{
  "type": "Feature",
  "properties": {
    "addr:full":"735 E Oldtown Rd Cumberland MD 21502",
    "addr:housenumber":"735",
    "addr:postcode":"21502",
    "addr:street":"E Oldtown Rd",
    "iso:country":"US",
    "sg:address":"735 E Oldtown Rd",
    "sg:city":"Cumberland",
    "sg:classifiers":[
        {
            "category":"Health Services",
            "subcategory":"Doctor",
            "type":"Services"
        }
    ],
    "sg:phone":"+1 301 724 4411",
    "sg:postcode":"21502",
    "sg:province":"MD",
    "sg:tags":[
        "dentist"
    ],
    "wof:name":"John S Davis DDS",
    "wof:placetype":"venue"
},
  "geometry": {"coordinates":[-78.75066700000001,39.637879],"type":"Point"}
}