{
  "type": "Feature",
  "properties": {
    "addr:full":"1 Randall Ave Pikesville MD 21208",
    "addr:housenumber":"1",
    "addr:postcode":"21208",
    "addr:street":"Randall Ave",
    "iso:country":"US",
    "sg:address":"1 Randall Ave",
    "sg:city":"Pikesville",
    "sg:classifiers":[
        {
            "category":"Education",
            "subcategory":"Special Training",
            "type":"Public Place"
        }
    ],
    "sg:phone":"+1 410 653 7777",
    "sg:postcode":"21208",
    "sg:province":"MD",
    "sg:tags":[
        "school",
        "instruction",
        "driving"
    ],
    "sg:website":"www.prodrivedrivingschool.com",
    "wof:name":"Pro-Drive Driving School",
    "wof:placetype":"venue"
},
  "geometry": {"coordinates":[-76.7146,39.365799],"type":"Point"}
}