{
  "type": "Feature",
  "properties": {
    "addr:full":"2108 Geneva Pl Bel Air MD 21015",
    "addr:housenumber":"2108",
    "addr:postcode":"21015",
    "addr:street":"Geneva Pl",
    "iso:country":"US",
    "sg:address":"2108 Geneva Pl",
    "sg:city":"Bel Air",
    "sg:classifiers":[
        {
            "category":"Building & Trades",
            "subcategory":"Plumbing",
            "type":"Services"
        }
    ],
    "sg:phone":"+1 410 893 7971",
    "sg:postcode":"21015",
    "sg:province":"MD",
    "sg:tags":[
        "conditioning",
        "air",
        "system",
        "contractor"
    ],
    "wof:name":"Carrington Heating & Air Cond",
    "wof:placetype":"venue"
},
  "geometry": {"coordinates":[-76.304405,39.561297],"type":"Point"}
}