{
  "type": "Feature",
  "properties": {
    "iso:country":"US",
    "sg:address":"11700 Old Columbia Pike",
    "sg:city":"Silver Spring",
    "sg:classifiers":[
        {
            "category":"Real Estate",
            "subcategory":"Real Estate Agent",
            "type":"Services"
        }
    ],
    "sg:phone":"+1 301 625 0287",
    "sg:postcode":"20904",
    "sg:province":"MD",
    "sg:tags":[
        "appraiser"
    ],
    "wof:name":"Bert Herndon Consultant",
    "wof:placetype":"venue"
},
  "geometry": {"coordinates":[-76.986456,39.046383],"type":"Point"}
}