{
  "type": "Feature",
  "properties": {
    "iso:country":"US",
    "sg:address":"6816 Briarcliff Dr",
    "sg:city":"Clinton",
    "sg:classifiers":[
        {
            "category":"Manufacturing",
            "subcategory":"Printing",
            "type":"Manufacturing & Wholesale Goods"
        }
    ],
    "sg:phone":"+1 301 856 1977",
    "sg:postcode":"20735",
    "sg:province":"MD",
    "sg:tags":[
        "engraver",
        "wood"
    ],
    "wof:name":"New Level Engraving",
    "wof:placetype":"venue"
},
  "geometry": {"coordinates":[-76.89237,38.737878],"type":"Point"}
}