{
  "type": "Feature",
  "properties": {
    "addr:full":"865 W 36th St Ste 1 Baltimore MD 21211",
    "addr:housenumber":"865",
    "addr:postcode":"21211",
    "addr:street":"W 36Th St Ste 1",
    "iso:country":"US",
    "sg:address":"865 W 36th St Ste 1",
    "sg:city":"Baltimore",
    "sg:classifiers":[
        {
            "category":"Food & Beverages",
            "subcategory":"Liquor & Beverages",
            "type":"Retail Goods"
        },
        {
            "category":"Wholesale",
            "subcategory":"Wine & Distilled Alcoholic Beverages",
            "type":"Manufacturing & Wholesale Goods"
        }
    ],
    "sg:phone":"+1 410 338 0991",
    "sg:postcode":"21211",
    "sg:province":"MD",
    "sg:tags":[
        "beer",
        "ale",
        "broker",
        "store"
    ],
    "wof:name":"Keller's Liquor Store",
    "wof:placetype":"venue"
},
  "geometry": {"coordinates":[-76.630819,39.331168],"type":"Point"}
}