{
  "type": "Feature",
  "properties": {
    "addr:full":"9815 Allentown Rd Fort Washington MD 20744",
    "addr:housenumber":"9815",
    "addr:postcode":"20744",
    "addr:street":"Allentown Rd",
    "iso:country":"US",
    "sg:address":"9815 Allentown Rd",
    "sg:city":"Fort Washington",
    "sg:classifiers":[
        {
            "category":"Building & Trades",
            "subcategory":"Construction",
            "type":"Services"
        }
    ],
    "sg:phone":"+1 301 248 3565",
    "sg:postcode":"20744",
    "sg:province":"MD",
    "sg:tags":[
        "masonry",
        "contractor"
    ],
    "wof:name":"J W & Son Masonry",
    "wof:placetype":"venue"
},
  "geometry": {"coordinates":[-76.966916,38.756503],"type":"Point"}
}