{
  "type": "Feature",
  "properties": {
    "iso:country":"US",
    "sg:address":"13470 Baltimore Ave",
    "sg:city":"Laurel",
    "sg:classifiers":[
        {
            "category":"Retail",
            "subcategory":"Laundry & Dry Cleaning",
            "type":"Services"
        }
    ],
    "sg:phone":"+1 301 210 3244",
    "sg:postcode":"20707",
    "sg:province":"MD",
    "sg:tags":[
        "laundries-self",
        "operated",
        "washer",
        "dryer",
        "coin"
    ],
    "wof:name":"Mario Plaza Laundromat",
    "wof:placetype":"venue"
},
  "geometry": {"coordinates":[-76.87008400000001,39.074589],"type":"Point"}
}