{
  "type": "Feature",
  "properties": {
    "iso:country":"US",
    "sg:address":"10995 Owings Mills Blvd",
    "sg:city":"Owings Mills",
    "sg:classifiers":[
        {
            "category":"Restaurant",
            "type":"Food & Drink"
        }
    ],
    "sg:phone":"+1 410 363 3007",
    "sg:postcode":"21117",
    "sg:province":"MD",
    "wof:name":"Cheeburger Cheeburger",
    "wof:placetype":"venue"
},
  "geometry": {"coordinates":[-76.77986799999999,39.424528],"type":"Point"}
}