{
  "type": "Feature",
  "properties": {
    "addr:full":"8064 New Cut Rd Severn MD 21144",
    "addr:housenumber":"8064",
    "addr:postcode":"21144",
    "addr:street":"New Cut Rd",
    "iso:country":"US",
    "sg:address":"8064 New Cut Rd",
    "sg:city":"Severn",
    "sg:classifiers":[
        {
            "category":"Social Services",
            "type":"Services"
        }
    ],
    "sg:phone":"+1 410 969 5100",
    "sg:postcode":"21144",
    "sg:province":"MD",
    "sg:tags":[
        "faith",
        "based"
    ],
    "wof:name":"Calvary Chapel Endowment Fund",
    "wof:placetype":"venue"
},
  "geometry": {"coordinates":[-76.642275,39.12628],"type":"Point"}
}