{
  "type": "Feature",
  "properties": {
    "addr:full":"224 N Center St Westminster MD 21157",
    "addr:housenumber":"224",
    "addr:postcode":"21157",
    "addr:street":"N Center St",
    "iso:country":"US",
    "sg:address":"224 N Center St",
    "sg:city":"Westminster",
    "sg:classifiers":[
        {
            "category":"Government",
            "subcategory":"Office",
            "type":"Public Place"
        }
    ],
    "sg:phone":"+1 410 857 2983",
    "sg:postcode":"21157",
    "sg:province":"MD",
    "sg:tags":[
        "county",
        "program",
        "adm"
    ],
    "wof:name":"Carroll County Tourism Bureau",
    "wof:placetype":"venue"
},
  "geometry": {"coordinates":[-76.98702,39.573685],"type":"Point"}
}