{
  "type": "Feature",
  "properties": {
    "iso:country":"US",
    "sg:address":"149 Old Solomons Island Rd",
    "sg:city":"Annapolis",
    "sg:classifiers":[
        {
            "category":"Autos & Motor Vehicles",
            "subcategory":"Automobile Sales",
            "type":"Retail Goods"
        }
    ],
    "sg:phone":"+1 443 837 1400",
    "sg:postcode":"21401",
    "sg:province":"MD",
    "sg:tags":[
        "car",
        "dealer"
    ],
    "wof:name":"Annapolis Subaru",
    "wof:placetype":"venue"
},
  "geometry": {"coordinates":[-76.539603,38.976084],"type":"Point"}
}