{
  "type": "Feature",
  "properties": {
    "iso:country":"US",
    "sg:address":"11821 Parklawn Dr",
    "sg:city":"Rockville",
    "sg:classifiers":[
        {
            "category":"Real Estate",
            "subcategory":"Real Estate Services",
            "type":"Services"
        }
    ],
    "sg:phone":"+1 301 816 0604",
    "sg:postcode":"20852",
    "sg:province":"MD",
    "sg:tags":[
        "company",
        "title"
    ],
    "wof:name":"Heritage Title",
    "wof:placetype":"venue"
},
  "geometry": {"coordinates":[-77.103735,39.050532],"type":"Point"}
}