{
  "type": "Feature",
  "properties": {
    "iso:country":"US",
    "sg:address":"1 Cloister Ct",
    "sg:city":"Bethesda",
    "sg:classifiers":[
        {
            "category":"Organizations",
            "subcategory":"Non-profit Organization",
            "type":"Services"
        }
    ],
    "sg:phone":"+1 301 496 7975",
    "sg:postcode":"20814",
    "sg:province":"MD",
    "sg:website":"www.faes.org",
    "wof:name":"Faes For Adv Ed In The Sci",
    "wof:placetype":"venue"
},
  "geometry": {"coordinates":[-77.108863,39.002277],"type":"Point"}
}