{
  "type": "Feature",
  "properties": {
    "addr:full":"24230 Laytonsville Rd Gaithersburg MD 20882",
    "addr:housenumber":"24230",
    "addr:postcode":"20882",
    "addr:street":"Laytonsville Rd",
    "iso:country":"US",
    "sg:address":"24230 Laytonsville Rd",
    "sg:city":"Gaithersburg",
    "sg:classifiers":[
        {
            "category":"Autos & Motor Vehicles",
            "subcategory":"Motorcycle Sales",
            "type":"Retail Goods"
        }
    ],
    "sg:phone":"+1 301 368 3408",
    "sg:postcode":"20882",
    "sg:province":"MD",
    "sg:tags":[
        "scooter"
    ],
    "wof:name":"American Pro Street Cycle",
    "wof:placetype":"venue"
},
  "geometry": {"coordinates":[-77.14380199999999,39.252167],"type":"Point"}
}