{
  "type": "Feature",
  "properties": {
    "addr:full":"7613 Philadelphia Rd Rosedale MD 21237",
    "addr:housenumber":"7613",
    "addr:postcode":"21237",
    "addr:street":"Philadelphia Rd",
    "iso:country":"US",
    "sg:address":"7613 Philadelphia Rd",
    "sg:city":"Rosedale",
    "sg:classifiers":[
        {
            "category":"Food & Beverages",
            "subcategory":"Meat & Fish",
            "type":"Retail Goods"
        }
    ],
    "sg:phone":"+1 410 866 8100",
    "sg:postcode":"21237",
    "sg:province":"MD",
    "sg:tags":[
        "seafood",
        "market"
    ],
    "wof:name":"Dipaula S & Sons Seafood & Produce",
    "wof:placetype":"venue"
},
  "geometry": {"coordinates":[-76.523399,39.314899],"type":"Point"}
}