{
  "type": "Feature",
  "properties": {
    "iso:country":"US",
    "sg:address":"1402 Hanson Rd",
    "sg:city":"Edgewood",
    "sg:classifiers":[
        {
            "category":"Retail",
            "subcategory":"Laundry & Dry Cleaning",
            "type":"Services"
        }
    ],
    "sg:phone":"+1 410 676 8385",
    "sg:postcode":"21040",
    "sg:province":"MD",
    "wof:name":"Master Cleaners",
    "wof:placetype":"venue"
},
  "geometry": {"coordinates":[-76.321427,39.423133],"type":"Point"}
}