{
  "type": "Feature",
  "properties": {
    "iso:country":"US",
    "sg:address":"12780 Monticello Dr",
    "sg:city":"Lusby",
    "sg:classifiers":[
        {
            "category":"Education",
            "subcategory":"Special Training",
            "type":"Public Place"
        }
    ],
    "sg:phone":"+1 410 394 6240",
    "sg:postcode":"20657",
    "sg:province":"MD",
    "sg:tags":[
        "educational"
    ],
    "wof:name":"Straight A Academics",
    "wof:placetype":"venue"
},
  "geometry": {"coordinates":[-76.457836,38.354185],"type":"Point"}
}