{
  "type": "Feature",
  "properties": {
    "addr:full":"20215 Nanticoke Rd Nanticoke MD 21840",
    "addr:postcode":"20215;21840",
    "addr:street":"Nanticoke Rd",
    "iso:country":"US",
    "sg:address":"20215 Nanticoke Rd",
    "sg:city":"Nanticoke",
    "sg:classifiers":[
        {
            "category":"Manufacturing",
            "subcategory":"Buildings",
            "type":"Manufacturing & Wholesale Goods"
        },
        {
            "category":"Building & Trades",
            "subcategory":"Construction",
            "type":"Services"
        }
    ],
    "sg:phone":"+1 410 873 2916",
    "sg:postcode":"21840",
    "sg:province":"MD",
    "sg:tags":[
        "home",
        "builder",
        "contractor"
    ],
    "wof:name":"Darryl J Lewis Construction",
    "wof:placetype":"venue"
},
  "geometry": {"coordinates":[-75.903858,38.250449],"type":"Point"}
}