{
  "type": "Feature",
  "properties": {
    "addr:full":"300 E Lombard St Baltimore MD 21202",
    "addr:housenumber":"300",
    "addr:postcode":"21202",
    "addr:street":"E Lombard St",
    "iso:country":"US",
    "sg:address":"300 E Lombard St",
    "sg:city":"Baltimore",
    "sg:classifiers":[
        {
            "category":"Professional",
            "subcategory":"Lawyer & Legal Services",
            "type":"Services"
        }
    ],
    "sg:phone":"+1 410 528 5615",
    "sg:postcode":"21202",
    "sg:province":"MD",
    "wof:name":"Fisher Morton P Atty",
    "wof:placetype":"venue"
},
  "geometry": {"coordinates":[-76.61080200000001,39.287899],"type":"Point"}
}