{
  "type": "Feature",
  "properties": {
    "addr:full":"2031 Maryland Ave Baltimore MD 21218",
    "addr:housenumber":"2031",
    "addr:postcode":"21218",
    "addr:street":"Maryland Ave",
    "iso:country":"US",
    "sg:address":"2031 Maryland Ave",
    "sg:city":"Baltimore",
    "sg:classifiers":[
        {
            "category":"Place Of Worship",
            "type":"Public Place"
        }
    ],
    "sg:phone":"+1 410 332 1853",
    "sg:postcode":"21218",
    "sg:province":"MD",
    "sg:tags":[
        "church"
    ],
    "wof:name":"Word Alive Community Out Reach",
    "wof:placetype":"venue"
},
  "geometry": {"coordinates":[-76.61799000000001,39.312464],"type":"Point"}
}