{
  "type": "Feature",
  "properties": {
    "iso:country":"US",
    "sg:address":"105 Nob Hill Park Dr",
    "sg:city":"Reisterstown",
    "sg:classifiers":[
        {
            "category":"Retail",
            "subcategory":"Veterinary Services",
            "type":"Services"
        }
    ],
    "sg:phone":"+1 410 833 2543",
    "sg:postcode":"21136",
    "sg:province":"MD",
    "sg:tags":[
        "veterinarian",
        "specialty"
    ],
    "wof:name":"Rosenberger Wm R Dr Veterinarian Res",
    "wof:placetype":"venue"
},
  "geometry": {"coordinates":[-76.849007,39.482422],"type":"Point"}
}