{
  "type": "Feature",
  "properties": {
    "iso:country":"US",
    "sg:address":"10910 New England Dr",
    "sg:city":"Clinton",
    "sg:classifiers":[
        {
            "category":"Utilities",
            "subcategory":"Refuse",
            "type":"Services"
        }
    ],
    "sg:phone":"+1 301 297 7157",
    "sg:postcode":"20735",
    "sg:province":"MD",
    "sg:tags":[
        "garbage",
        "collection"
    ],
    "wof:name":"U S Refuse Removal Inc",
    "wof:placetype":"venue"
},
  "geometry": {"coordinates":[-76.923242,38.741946],"type":"Point"}
}