{
  "type": "Feature",
  "properties": {
    "iso:country":"US",
    "sg:address":"11121 Baltimore Ave",
    "sg:city":"Beltsville",
    "sg:classifiers":[
        {
            "category":"Restaurant",
            "type":"Food & Drink"
        }
    ],
    "sg:phone":"+1 301 595 3285",
    "sg:postcode":"20705",
    "sg:province":"MD",
    "sg:tags":[
        "peruvian",
        "american",
        "latin"
    ],
    "wof:name":"King Pollo",
    "wof:placetype":"venue"
},
  "geometry": {"coordinates":[-76.90722599999999,39.034937],"type":"Point"}
}