{
  "type": "Feature",
  "properties": {
    "addr:full":"10626 Liberty Rd Randallstown MD 21133",
    "addr:housenumber":"10626",
    "addr:postcode":"21133",
    "addr:street":"Liberty Rd",
    "iso:country":"US",
    "sg:address":"10626 Liberty Rd",
    "sg:city":"Randallstown",
    "sg:classifiers":[
        {
            "category":"Restaurant",
            "type":"Food & Drink"
        }
    ],
    "sg:phone":"+1 410 521 2960",
    "sg:postcode":"21133",
    "sg:province":"MD",
    "sg:tags":[
        "parlor",
        "ice",
        "cream"
    ],
    "wof:name":"Original Hawaiian Sno-Ball",
    "wof:placetype":"venue"
},
  "geometry": {"coordinates":[-76.845144,39.393197],"type":"Point"}
}