{
  "type": "Feature",
  "properties": {
    "addr:full":"9914 Richlyn Dr Perry Hall MD 21128",
    "addr:housenumber":"9914",
    "addr:postcode":"21128",
    "addr:street":"Richlyn Dr",
    "iso:country":"US",
    "sg:address":"9914 Richlyn Dr",
    "sg:city":"Perry Hall",
    "sg:classifiers":[
        {
            "category":"Building & Trades",
            "subcategory":"Construction",
            "type":"Services"
        }
    ],
    "sg:phone":"+1 410 256 5546",
    "sg:postcode":"21128",
    "sg:province":"MD",
    "sg:tags":[
        "contractor"
    ],
    "wof:name":"Reider John G",
    "wof:placetype":"venue"
},
  "geometry": {"coordinates":[-76.44333399999999,39.419626],"type":"Point"}
}