{
  "type": "Feature",
  "properties": {
    "iso:country":"US",
    "sg:address":"18425 Flower Hill Way",
    "sg:city":"Gaithersburg",
    "sg:classifiers":[
        {
            "category":"Education",
            "subcategory":"School",
            "type":"Public Place"
        }
    ],
    "sg:phone":"+1 301 840 7161",
    "sg:postcode":"20879",
    "sg:province":"MD",
    "wof:name":"Flower Hill Elementary",
    "wof:placetype":"venue"
},
  "geometry": {"coordinates":[-77.172026,39.158849],"type":"Point"}
}