{
  "type": "Feature",
  "properties": {
    "iso:country":"US",
    "sg:address":"574 Renee Dr",
    "sg:city":"Joppa",
    "sg:classifiers":[
        {
            "category":"Structure",
            "subcategory":"Office Building",
            "type":"Public Place"
        }
    ],
    "sg:phone":"+1 410 679 4313",
    "sg:postcode":"21085",
    "sg:province":"MD",
    "sg:tags":[
        "park"
    ],
    "wof:name":"Commercial Property Improvements Of Central Maryland Inc",
    "wof:placetype":"venue"
},
  "geometry": {"coordinates":[-76.353551,39.41051],"type":"Point"}
}