{
  "type": "Feature",
  "properties": {
    "addr:full":"13420 Overbrook Ln Bowie MD 20715",
    "addr:housenumber":"13420",
    "addr:postcode":"20715",
    "addr:street":"Overbrook Ln",
    "iso:country":"US",
    "sg:address":"13420 Overbrook Ln",
    "sg:city":"Bowie",
    "sg:classifiers":[
        {
            "category":"Building & Trades",
            "subcategory":"Construction",
            "type":"Services"
        }
    ],
    "sg:phone":"+1 301 352 5819",
    "sg:postcode":"20715",
    "sg:province":"MD",
    "sg:tags":[
        "roofing",
        "contractor"
    ],
    "wof:name":"Orion Contracting Svc Inc",
    "wof:placetype":"venue"
},
  "geometry": {"coordinates":[-76.732764,38.9982],"type":"Point"}
}