{
  "type": "Feature",
  "properties": {
    "addr:full":"332 N Grantley St Baltimore MD 21229",
    "addr:housenumber":"332",
    "addr:postcode":"21229",
    "addr:street":"N Grantley St",
    "iso:country":"US",
    "sg:address":"332 N Grantley St",
    "sg:city":"Baltimore",
    "sg:classifiers":[
        {
            "category":"Retail",
            "subcategory":"Auto Repair",
            "type":"Services"
        }
    ],
    "sg:phone":"+1 410 233 4964",
    "sg:postcode":"21229",
    "sg:province":"MD",
    "wof:name":"Moses Robert Car Repair",
    "wof:placetype":"venue"
},
  "geometry": {"coordinates":[-76.67681899999999,39.291218],"type":"Point"}
}