{
  "type": "Feature",
  "properties": {
    "iso:country":"US",
    "sg:address":"3225 Foster Ave",
    "sg:city":"Baltimore",
    "sg:classifiers":[
        {
            "category":"Food & Beverages",
            "subcategory":"Candy",
            "type":"Retail Goods"
        }
    ],
    "sg:phone":"+1 410 342 9484",
    "sg:postcode":"21224",
    "sg:province":"MD",
    "sg:tags":[
        "confectionery"
    ],
    "wof:name":"Dawn's Confectionery",
    "wof:placetype":"venue"
},
  "geometry": {"coordinates":[-76.569845,39.284476],"type":"Point"}
}