{
  "type": "Feature",
  "properties": {
    "addr:full":"100 Village Sq Baltimore MD 21210",
    "addr:housenumber":"100",
    "addr:postcode":"21210",
    "addr:street":"Village Sq",
    "iso:country":"US",
    "sg:address":"100 Village Sq",
    "sg:city":"Baltimore",
    "sg:classifiers":[
        {
            "category":"Restaurant",
            "type":"Food & Drink"
        }
    ],
    "sg:phone":"+1 410 435 0101",
    "sg:postcode":"21210",
    "sg:province":"MD",
    "sg:tags":[
        "american"
    ],
    "sg:website":"http://www.radisson.com/baltimoremd",
    "wof:name":"Crossroads at the Radisson Hotel Cross Keys",
    "wof:placetype":"venue"
},
  "geometry": {"coordinates":[-76.645591,39.3563],"type":"Point"}
}