{
  "type": "Feature",
  "properties": {
    "iso:country":"US",
    "sg:address":"300 W 29th St",
    "sg:city":"Baltimore",
    "sg:classifiers":[
        {
            "category":"Restaurant",
            "type":"Food & Drink"
        }
    ],
    "sg:menulink":"http://www.allmenus.com/md/baltimore/18393-pizza-bolis/menu/",
    "sg:phone":"+1 410 235 1000",
    "sg:postcode":"21211",
    "sg:province":"MD",
    "sg:tags":[
        "american",
        "pizza"
    ],
    "wof:name":"Pizza Boli's",
    "wof:placetype":"venue"
},
  "geometry": {"coordinates":[-76.622225,39.322017],"type":"Point"}
}