{
  "type": "Feature",
  "properties": {
    "addr:full":"7100 Ducketts Lane Elkridge MD 21075",
    "addr:housenumber":"7100",
    "addr:postcode":"21075",
    "addr:street":"Ducketts Lane",
    "iso:country":"US",
    "sg:address":"7100 Ducketts Lane",
    "sg:city":"Elkridge",
    "sg:classifiers":[
        {
            "category":"Building & Trades",
            "subcategory":"Cleaning & Sanitation",
            "type":"Services"
        }
    ],
    "sg:phone":"+1 410 877 6886",
    "sg:postcode":"21075",
    "sg:province":"MD",
    "sg:tags":[
        "carpet"
    ],
    "sg:website":"carpetcleaninginelkridge.info",
    "wof:name":"Rouse Inc Clean Care Carpet & Upholstery",
    "wof:placetype":"venue"
},
  "geometry": {"coordinates":[-76.742554,39.197163],"type":"Point"}
}