{
  "type": "Feature",
  "properties": {
    "iso:country":"US",
    "sg:address":"410 Outlet Center Dr",
    "sg:city":"Queenstown",
    "sg:classifiers":[
        {
            "category":"Home & Garden",
            "subcategory":"Home Furnishings",
            "type":"Retail Goods"
        }
    ],
    "sg:phone":"+1 410 827 7191",
    "sg:postcode":"21658",
    "sg:province":"MD",
    "sg:tags":[
        "glassware",
        "chinaware"
    ],
    "sg:website":"www.lenox.com",
    "wof:name":"Lenox Factory Outlet",
    "wof:placetype":"venue"
},
  "geometry": {"coordinates":[-76.160448,38.983448],"type":"Point"}
}