{
  "type": "Feature",
  "properties": {
    "addr:full":"521 Salem Ave Hagerstown MD 21740",
    "addr:housenumber":"521",
    "addr:postcode":"21740",
    "addr:street":"Salem Ave",
    "iso:country":"US",
    "sg:address":"521 Salem Ave",
    "sg:city":"Hagerstown",
    "sg:classifiers":[
        {
            "category":"Personal",
            "subcategory":"Beauty Salon",
            "type":"Services"
        }
    ],
    "sg:phone":"+1 301 739 8504",
    "sg:postcode":"21740",
    "sg:province":"MD",
    "sg:tags":[
        "shop"
    ],
    "wof:name":"House Of Glamour",
    "wof:placetype":"venue"
},
  "geometry": {"coordinates":[-77.726444,39.649375],"type":"Point"}
}