{
  "type": "Feature",
  "properties": {
    "iso:country":"US",
    "sg:address":"5030 Reisterstown Rd",
    "sg:city":"Baltimore",
    "sg:classifiers":[
        {
            "category":"Wholesale",
            "subcategory":"Stationery",
            "type":"Manufacturing & Wholesale Goods"
        }
    ],
    "sg:phone":"+1 410 466 8828",
    "sg:postcode":"21215",
    "sg:province":"MD",
    "sg:tags":[
        "product",
        "paper"
    ],
    "wof:name":"Office Paper Systems",
    "wof:placetype":"venue"
},
  "geometry": {"coordinates":[-76.681487,39.341736],"type":"Point"}
}