{
  "type": "Feature",
  "properties": {
    "addr:full":"4961 Jefferson Pike Frederick MD 21703",
    "addr:housenumber":"4961",
    "addr:postcode":"21703",
    "addr:street":"Jefferson Pike",
    "iso:country":"US",
    "sg:address":"4961 Jefferson Pike",
    "sg:city":"Frederick",
    "sg:classifiers":[
        {
            "category":"Professional",
            "subcategory":"Computer Services",
            "type":"Services"
        }
    ],
    "sg:phone":"+1 301 473 8725",
    "sg:postcode":"21703",
    "sg:province":"MD",
    "sg:tags":[
        "repair"
    ],
    "wof:name":"New Age Electronics",
    "wof:placetype":"venue"
},
  "geometry": {"coordinates":[-77.49731,39.371831],"type":"Point"}
}