{
  "type": "Feature",
  "properties": {
    "addr:full":"7401 Harford Rd Parkville MD 21234",
    "addr:housenumber":"7401",
    "addr:postcode":"21234",
    "addr:street":"Harford Rd",
    "iso:country":"US",
    "sg:address":"7401 Harford Rd",
    "sg:city":"Parkville",
    "sg:classifiers":[
        {
            "category":"Restaurant",
            "type":"Food & Drink"
        }
    ],
    "sg:phone":"+1 410 254 8128",
    "sg:postcode":"21234",
    "sg:province":"MD",
    "sg:tags":[
        "italian"
    ],
    "wof:name":"Giovanna's Italian Kitchen",
    "wof:placetype":"venue"
},
  "geometry": {"coordinates":[-76.545913,39.369734],"type":"Point"}
}