{
  "type": "Feature",
  "properties": {
    "addr:full":"221 Kennedy St NW Washington Twp MD 20011",
    "addr:housenumber":"221",
    "addr:postcode":"20011",
    "addr:street":"Kennedy St Nw",
    "iso:country":"US",
    "sg:address":"221 Kennedy St NW",
    "sg:city":"Washington Twp",
    "sg:classifiers":[
        {
            "category":"Insurance",
            "subcategory":"Insurance Agent",
            "type":"Services"
        }
    ],
    "sg:phone":"+1 201 228 3555",
    "sg:postcode":"20011",
    "sg:province":"MD",
    "wof:name":"Auto-Cycle Insurance Inc",
    "wof:placetype":"venue"
},
  "geometry": {"coordinates":[-77.01461,38.956634],"type":"Point"}
}