{
  "type": "Feature",
  "properties": {
    "addr:full":"113 Central Ave W Edgewater MD 21037",
    "addr:housenumber":"113",
    "addr:postcode":"21037",
    "addr:street":"Central Ave W",
    "iso:country":"US",
    "sg:address":"113 Central Ave W",
    "sg:city":"Edgewater",
    "sg:classifiers":[
        {
            "category":"Retail",
            "subcategory":"Auto Repair",
            "type":"Services"
        }
    ],
    "sg:phone":"+1 410 956 7000",
    "sg:postcode":"21037",
    "sg:province":"MD",
    "sg:tags":[
        "body",
        "automobile",
        "painting"
    ],
    "wof:name":"Classic Collision Ctr",
    "wof:placetype":"venue"
},
  "geometry": {"coordinates":[-76.58268200000001,38.927331],"type":"Point"}
}