{
  "type": "Feature",
  "properties": {
    "iso:country":"US",
    "sg:address":"2840 Dalton Bevard Rd",
    "sg:city":"Baldwin",
    "sg:classifiers":[
        {
            "category":"Professional",
            "type":"Services"
        }
    ],
    "sg:phone":"+1 410 557 0279",
    "sg:postcode":"21013",
    "sg:province":"MD",
    "sg:tags":[
        "establishment"
    ],
    "wof:name":"Planting With Joy",
    "wof:placetype":"venue"
},
  "geometry": {"coordinates":[-76.506104,39.534044],"type":"Point"}
}