{
  "type": "Feature",
  "properties": {
    "addr:full":"5830 Miriam Dr Sykesville MD 21784",
    "addr:housenumber":"5830",
    "addr:postcode":"21784",
    "addr:street":"Miriam Dr",
    "iso:country":"US",
    "sg:address":"5830 Miriam Dr",
    "sg:city":"Sykesville",
    "sg:classifiers":[
        {
            "category":"Building & Trades",
            "subcategory":"Equipment Rental",
            "type":"Services"
        }
    ],
    "sg:phone":"+1 410 781 4280",
    "sg:postcode":"21784",
    "sg:province":"MD",
    "sg:tags":[
        "heavy",
        "construction"
    ],
    "wof:name":"Triton Contracting Corporation",
    "wof:placetype":"venue"
},
  "geometry": {"coordinates":[-76.961204,39.413673],"type":"Point"}
}