{
  "type": "Feature",
  "properties": {
    "iso:country":"US",
    "sg:address":"9810 Patuxent Woods Dr",
    "sg:city":"Columbia",
    "sg:classifiers":[
        {
            "category":"Social Services",
            "type":"Services"
        }
    ],
    "sg:phone":"+1 301 596 2768",
    "sg:postcode":"21046",
    "sg:province":"MD",
    "sg:tags":[
        "organization",
        "welfare"
    ],
    "wof:name":"Star Center",
    "wof:placetype":"venue"
},
  "geometry": {"coordinates":[-76.85122699999999,39.178021],"type":"Point"}
}