{
  "type": "Feature",
  "properties": {
    "addr:full":"100 S Charles St Baltimore MD 21201",
    "addr:housenumber":"100",
    "addr:postcode":"21201",
    "addr:street":"S Charles St",
    "iso:country":"US",
    "sg:address":"100 S Charles St",
    "sg:city":"Baltimore",
    "sg:classifiers":[
        {
            "category":"Professional",
            "subcategory":"Lawyer & Legal Services",
            "type":"Services"
        }
    ],
    "sg:phone":"+1 410 332 8689",
    "sg:postcode":"21201",
    "sg:province":"MD",
    "sg:tags":[
        "attorney",
        "practice"
    ],
    "wof:name":"Michael P Smith",
    "wof:placetype":"venue"
},
  "geometry": {"coordinates":[-76.614998,39.287731],"type":"Point"}
}