{
  "type": "Feature",
  "properties": {
    "addr:full":"1120 River Bay Rd Annapolis MD 21409",
    "addr:housenumber":"1120",
    "addr:postcode":"21409",
    "addr:street":"River Bay Rd",
    "iso:country":"US",
    "sg:address":"1120 River Bay Rd",
    "sg:city":"Annapolis",
    "sg:classifiers":[
        {
            "category":"Retail",
            "subcategory":"Laundry & Dry Cleaning",
            "type":"Services"
        },
        {
            "category":"Building & Trades",
            "subcategory":"Cleaning & Sanitation",
            "type":"Services"
        }
    ],
    "sg:phone":"+1 410 787 1722",
    "sg:postcode":"21409",
    "sg:province":"MD",
    "sg:tags":[
        "cleaner",
        "upholstery",
        "house",
        "rug",
        "cleaners-interior",
        "janitorial",
        "carpet"
    ],
    "sg:website":"http://www.cathyscleaning.com",
    "wof:name":"Cathy's Cleaning Service",
    "wof:placetype":"venue"
},
  "geometry": {"coordinates":[-76.439763,39.052213],"type":"Point"}
}