{
  "type": "Feature",
  "properties": {
    "addr:full":"10660 Breezewood Dr Woodstock MD 21163",
    "addr:housenumber":"10660",
    "addr:postcode":"21163",
    "addr:street":"Breezewood Dr",
    "iso:country":"US",
    "sg:address":"10660 Breezewood Dr",
    "sg:city":"Woodstock",
    "sg:classifiers":[
        {
            "category":"Manufacturing",
            "subcategory":"Printing",
            "type":"Manufacturing & Wholesale Goods"
        }
    ],
    "sg:phone":"+1 410 461 9138",
    "sg:postcode":"21163",
    "sg:province":"MD",
    "sg:tags":[
        "printer"
    ],
    "wof:name":"Hatton Management Group",
    "wof:placetype":"venue"
},
  "geometry": {"coordinates":[-76.88167300000001,39.325177],"type":"Point"}
}