{
  "type": "Feature",
  "properties": {
    "iso:country":"US",
    "sg:address":"8910 Old Annapolis Rd",
    "sg:city":"Columbia",
    "sg:classifiers":[
        {
            "category":"Professional",
            "subcategory":"Management & Consulting",
            "type":"Services"
        }
    ],
    "sg:phone":"+1 410 884 4158",
    "sg:postcode":"21045",
    "sg:province":"MD",
    "sg:tags":[
        "consultant",
        "business"
    ],
    "wof:name":"APG Inc",
    "wof:placetype":"venue"
},
  "geometry": {"coordinates":[-76.821396,39.226968],"type":"Point"}
}