{
  "type": "Feature",
  "properties": {
    "iso:country":"US",
    "sg:address":"8105 Crabapple Ln",
    "sg:city":"Gaithersburg",
    "sg:classifiers":[
        {
            "category":"Building & Trades",
            "subcategory":"Construction",
            "type":"Services"
        }
    ],
    "sg:phone":"+1 301 869 2200",
    "sg:postcode":"20879",
    "sg:province":"MD",
    "sg:tags":[
        "pumping",
        "contractor"
    ],
    "wof:name":"Storm Water Mgmt Facilities",
    "wof:placetype":"venue"
},
  "geometry": {"coordinates":[-77.166791,39.159426],"type":"Point"}
}