{
  "type": "Feature",
  "properties": {
    "iso:country":"US",
    "sg:address":"7650 Sandy Farm Rd",
    "sg:city":"Severn",
    "sg:classifiers":[
        {
            "category":"Farming",
            "subcategory":"Livestock Farm",
            "type":"Manufacturing & Wholesale Goods"
        }
    ],
    "sg:phone":"+1 410 766 0879",
    "sg:postcode":"21144",
    "sg:province":"MD",
    "wof:name":"Basil Smith",
    "wof:placetype":"venue"
},
  "geometry": {"coordinates":[-76.68461499999999,39.14878],"type":"Point"}
}