{
  "type": "Feature",
  "properties": {
    "iso:country":"US",
    "sg:address":"7411 Lindbergh Dr",
    "sg:city":"Gaithersburg",
    "sg:classifiers":[
        {
            "category":"Manufacturing",
            "subcategory":"Metals",
            "type":"Manufacturing & Wholesale Goods"
        }
    ],
    "sg:phone":"+1 301 548 7400",
    "sg:postcode":"20879",
    "sg:province":"MD",
    "sg:tags":[
        "steel"
    ],
    "wof:name":"Rockville Steel & Mfg Co",
    "wof:placetype":"venue"
},
  "geometry": {"coordinates":[-77.15702,39.164079],"type":"Point"}
}