{
  "type": "Feature",
  "properties": {
    "addr:full":"14122 Silver Teal Way Upper Marlboro MD 20774",
    "addr:housenumber":"14122",
    "addr:postcode":"20774",
    "addr:street":"Silver Teal Way",
    "iso:country":"US",
    "sg:address":"14122 Silver Teal Way",
    "sg:city":"Upper Marlboro",
    "sg:classifiers":[
        {
            "category":"Arts & Performance",
            "subcategory":"Theater",
            "type":"Entertainment"
        }
    ],
    "sg:phone":"+1 301 218 1698",
    "sg:postcode":"20774",
    "sg:province":"MD",
    "sg:tags":[
        "bureau"
    ],
    "wof:name":"SDL Entertainment",
    "wof:placetype":"venue"
},
  "geometry": {"coordinates":[-76.77601199999999,38.868398],"type":"Point"}
}