{
  "type": "Feature",
  "properties": {
    "addr:full":"20610 Duck Pond Dr Germantown MD 20874",
    "addr:housenumber":"20610",
    "addr:postcode":"20874",
    "addr:street":"Duck Pond Dr",
    "iso:country":"US",
    "sg:address":"20610 Duck Pond Dr",
    "sg:city":"Germantown",
    "sg:classifiers":[
        {
            "category":"Professional",
            "subcategory":"Research",
            "type":"Services"
        }
    ],
    "sg:phone":"+1 301 515 8338",
    "sg:postcode":"20874",
    "sg:province":"MD",
    "sg:tags":[
        "scientific"
    ],
    "wof:name":"David A McKeown Dr",
    "wof:placetype":"venue"
},
  "geometry": {"coordinates":[-77.270552,39.195335],"type":"Point"}
}