{
  "type": "Feature",
  "properties": {
    "addr:full":"5225 Baltimore National Pike Baltimore MD 21229",
    "addr:housenumber":"5225",
    "addr:postcode":"21229",
    "addr:street":"Baltimore National Pike",
    "iso:country":"US",
    "sg:address":"5225 Baltimore National Pike",
    "sg:city":"Baltimore",
    "sg:classifiers":[
        {
            "category":"Insurance",
            "subcategory":"Insurance Agent",
            "type":"Services"
        }
    ],
    "sg:phone":"+1 410 455 9265",
    "sg:postcode":"21229",
    "sg:province":"MD",
    "wof:name":"Amalgamated Insurance Svc Inc",
    "wof:placetype":"venue"
},
  "geometry": {"coordinates":[-76.714218,39.291337],"type":"Point"}
}