{
  "type": "Feature",
  "properties": {
    "iso:country":"US",
    "sg:address":"5512 Whitfield Chapel Rd",
    "sg:city":"Lanham",
    "sg:classifiers":[
        {
            "category":"Organizations",
            "subcategory":"Religious Organization",
            "type":"Services"
        }
    ],
    "sg:phone":"+1 301 577 1500",
    "sg:postcode":"20706",
    "sg:province":"MD",
    "sg:tags":[
        "church"
    ],
    "wof:name":"Lanham United Methodist Church",
    "wof:placetype":"venue"
},
  "geometry": {"coordinates":[-76.85787,38.959134],"type":"Point"}
}