{
  "type": "Feature",
  "properties": {
    "addr:full":"3905 National Dr. Suite 110 Burtonsville MD 20866",
    "addr:housenumber":"3905",
    "addr:postcode":"20866",
    "addr:street":"National Dr. Suite 110",
    "iso:country":"US",
    "sg:address":"3905 National Dr. Suite 110",
    "sg:city":"Burtonsville",
    "sg:classifiers":[
        {
            "category":"Professional",
            "subcategory":"Research",
            "type":"Services"
        }
    ],
    "sg:postcode":"20866",
    "sg:province":"MD",
    "sg:tags":[
        "green-tech",
        "energy",
        "solar",
        "solar-cell",
        "motion",
        "kinetic-energy"
    ],
    "sg:website":"http://www.octillioncorp.com/index",
    "wof:name":"New Energy Technologies",
    "wof:placetype":"venue"
},
  "geometry": {"coordinates":[-76.930592,39.112891],"type":"Point"}
}