{
  "type": "Feature",
  "properties": {
    "addr:full":"512 Pulaski Hwy Joppa MD 21085",
    "addr:housenumber":"512",
    "addr:postcode":"21085",
    "addr:street":"Pulaski Hwy",
    "iso:country":"US",
    "sg:address":"512 Pulaski Hwy",
    "sg:city":"Joppa",
    "sg:classifiers":[
        {
            "category":"Building & Trades",
            "subcategory":"Plumbing",
            "type":"Services"
        }
    ],
    "sg:phone":"+1 410 679 6366",
    "sg:postcode":"21085",
    "sg:province":"MD",
    "sg:tags":[
        "conditioning",
        "air",
        "system",
        "contractor"
    ],
    "wof:name":"Carter Cooling & Heating Inc",
    "wof:placetype":"venue"
},
  "geometry": {"coordinates":[-76.363597,39.427848],"type":"Point"}
}