{
  "type": "Feature",
  "properties": {
    "addr:full":"10155 Clearspring Rd Damascus MD 20872",
    "addr:housenumber":"10155",
    "addr:postcode":"20872",
    "addr:street":"Clearspring Rd",
    "iso:country":"US",
    "sg:address":"10155 Clearspring Rd",
    "sg:city":"Damascus",
    "sg:classifiers":[
        {
            "category":"Wholesale",
            "subcategory":"Electrical",
            "type":"Manufacturing & Wholesale Goods"
        }
    ],
    "sg:phone":"+1 301 482 0354",
    "sg:postcode":"20872",
    "sg:province":"MD",
    "sg:tags":[
        "telecommunication"
    ],
    "wof:name":"Eastcoast Connection Cabling",
    "wof:placetype":"venue"
},
  "geometry": {"coordinates":[-77.205405,39.272501],"type":"Point"}
}