{
  "type": "Feature",
  "properties": {
    "iso:country":"US",
    "sg:address":"1002 Saint Albans Way",
    "sg:city":"Baltimore",
    "sg:classifiers":[
        {
            "category":"Retail",
            "subcategory":"Portrait Studio",
            "type":"Services"
        }
    ],
    "sg:phone":"+1 410 377 5619",
    "sg:postcode":"21212",
    "sg:province":"MD",
    "sg:tags":[
        "photo"
    ],
    "wof:name":"Steven C Fine",
    "wof:placetype":"venue"
},
  "geometry": {"coordinates":[-76.621151,39.354761],"type":"Point"}
}