{
  "type": "Feature",
  "properties": {
    "addr:full":"2091 West St Annapolis MD 21401",
    "addr:housenumber":"2091",
    "addr:postcode":"21401",
    "addr:street":"West St",
    "iso:country":"US",
    "sg:address":"2091 West St",
    "sg:city":"Annapolis",
    "sg:classifiers":[
        {
            "category":"Shopping",
            "subcategory":"Clothing, Apparel, & Fashions",
            "type":"Retail Goods"
        }
    ],
    "sg:phone":"+1 410 224 4190",
    "sg:postcode":"21401",
    "sg:province":"MD",
    "sg:tags":[
        "men's",
        "clothing",
        "sportswear"
    ],
    "sg:website":"http://www.casualmale.com",
    "wof:name":"Casual Male Xl",
    "wof:placetype":"venue"
},
  "geometry": {"coordinates":[-76.54322000000001,38.984321],"type":"Point"}
}