{
  "type": "Feature",
  "properties": {
    "addr:full":"450 Prime Outlets Blvd Hagerstown MD 21740",
    "addr:postcode":"21740",
    "addr:street":"Outlets Blvd",
    "iso:country":"US",
    "sg:address":"450 Prime Outlets Blvd",
    "sg:city":"Hagerstown",
    "sg:classifiers":[
        {
            "category":"Shopping",
            "subcategory":"Hobbies, Toys, & Games",
            "type":"Retail Goods"
        }
    ],
    "sg:phone":"+1 301 766 9077",
    "sg:postcode":"21740",
    "sg:province":"MD",
    "sg:website":"www.kbtoys.com",
    "wof:name":"K-B Toys",
    "wof:placetype":"venue"
},
  "geometry": {"coordinates":[-77.731118,39.609355],"type":"Point"}
}