{
  "type": "Feature",
  "properties": {
    "iso:country":"US",
    "sg:address":"9525 Berger Rd",
    "sg:city":"Columbia",
    "sg:classifiers":[
        {
            "category":"Retail",
            "subcategory":"Repair Shop",
            "type":"Services"
        }
    ],
    "sg:phone":"+1 301 621 3300",
    "sg:postcode":"21046",
    "sg:province":"MD",
    "wof:name":"Petes Big Tvs",
    "wof:placetype":"venue"
},
  "geometry": {"coordinates":[-76.840501,39.174805],"type":"Point"}
}