{
  "type": "Feature",
  "properties": {
    "addr:full":"125 N Prospect St Hagerstown MD 21740",
    "addr:housenumber":"125",
    "addr:postcode":"21740",
    "addr:street":"N Prospect St",
    "iso:country":"US",
    "sg:address":"125 N Prospect St",
    "sg:city":"Hagerstown",
    "sg:classifiers":[
        {
            "category":"Shopping",
            "subcategory":"Used Merchandise",
            "type":"Retail Goods"
        }
    ],
    "sg:phone":"+1 301 739 1165",
    "sg:postcode":"21740",
    "sg:province":"MD",
    "sg:tags":[
        "shop",
        "thrift"
    ],
    "wof:name":"Hagerstown Union Rescue Inc",
    "wof:placetype":"venue"
},
  "geometry": {"coordinates":[-77.72300199999999,39.645668],"type":"Point"}
}