{
  "type": "Feature",
  "properties": {
    "iso:country":"US",
    "sg:address":"29595 Dutchmans Ln",
    "sg:city":"Easton",
    "sg:classifiers":[
        {
            "category":"Building & Trades",
            "subcategory":"Construction",
            "type":"Services"
        }
    ],
    "sg:phone":"+1 410 822 1956",
    "sg:postcode":"21601",
    "sg:province":"MD",
    "sg:tags":[
        "house"
    ],
    "wof:name":"Doug Eskridge Constructio",
    "wof:placetype":"venue"
},
  "geometry": {"coordinates":[-76.048981,38.749988],"type":"Point"}
}