{
  "type": "Feature",
  "properties": {
    "iso:country":"US",
    "sg:address":"11614 Gilsan St",
    "sg:city":"Silver Spring",
    "sg:classifiers":[
        {
            "category":"Building & Trades",
            "subcategory":"Construction",
            "type":"Services"
        }
    ],
    "sg:phone":"+1 301 593 4603",
    "sg:postcode":"20902",
    "sg:province":"MD",
    "sg:tags":[
        "home",
        "improvement"
    ],
    "wof:name":"V & I Construction",
    "wof:placetype":"venue"
},
  "geometry": {"coordinates":[-77.013034,39.046769],"type":"Point"}
}