{
  "type": "Feature",
  "properties": {
    "addr:full":"101 S Caroline St Baltimore MD 21231",
    "addr:housenumber":"101",
    "addr:postcode":"21231",
    "addr:street":"S Caroline St",
    "iso:country":"US",
    "sg:address":"101 S Caroline St",
    "sg:city":"Baltimore",
    "sg:classifiers":[
        {
            "category":"Education",
            "subcategory":"School",
            "type":"Public Place"
        }
    ],
    "sg:phone":"+1 443 642 2150",
    "sg:postcode":"21231",
    "sg:province":"MD",
    "sg:tags":[
        "k-",
        "private"
    ],
    "wof:name":"The Baltimore Freedom Academy Foundation Inc",
    "wof:placetype":"venue"
},
  "geometry": {"coordinates":[-76.597092,39.290249],"type":"Point"}
}