{
  "type": "Feature",
  "properties": {
    "iso:country":"US",
    "sg:address":"4008 Marjeff Pl",
    "sg:city":"Baltimore",
    "sg:classifiers":[
        {
            "category":"Real Estate",
            "subcategory":"Real Estate Operator",
            "type":"Services"
        }
    ],
    "sg:phone":"+1 410 663 9819",
    "sg:postcode":"21236",
    "sg:province":"MD",
    "sg:tags":[
        "apartment"
    ],
    "wof:name":"Taylor Park Apartments",
    "wof:placetype":"venue"
},
  "geometry": {"coordinates":[-76.528298,39.363686],"type":"Point"}
}