{
  "type": "Feature",
  "properties": {
    "iso:country":"US",
    "sg:address":"8800 Emory Grove Rd",
    "sg:city":"Gaithersburg",
    "sg:classifiers":[
        {
            "category":"Building & Trades",
            "subcategory":"Landscaping Services",
            "type":"Services"
        }
    ],
    "sg:phone":"+1 301 330 1209",
    "sg:postcode":"20877",
    "sg:province":"MD",
    "sg:tags":[
        "tree"
    ],
    "wof:name":"Garcia Tree Expert Comp",
    "wof:placetype":"venue"
},
  "geometry": {"coordinates":[-77.183571,39.159002],"type":"Point"}
}