{
  "type": "Feature",
  "properties": {
    "addr:full":"5 Bloomsbury Ave Baltimore MD 21228",
    "addr:housenumber":"5",
    "addr:postcode":"21228",
    "addr:street":"Bloomsbury Ave",
    "iso:country":"US",
    "sg:address":"5 Bloomsbury Ave",
    "sg:city":"Baltimore",
    "sg:classifiers":[
        {
            "category":"Taxi",
            "type":"Transportation"
        }
    ],
    "sg:phone":"+1 410 788 8000",
    "sg:postcode":"21228",
    "sg:province":"MD",
    "sg:tags":[
        "taxicab"
    ],
    "wof:name":"Monarch Taxi Assoc Inc",
    "wof:placetype":"venue"
},
  "geometry": {"coordinates":[-76.730774,39.270234],"type":"Point"}
}