{
  "type": "Feature",
  "properties": {
    "iso:country":"US",
    "sg:address":"2175 Defense Hwy",
    "sg:city":"Crofton",
    "sg:classifiers":[
        {
            "category":"Shopping",
            "subcategory":"Gifts & Souvenirs",
            "type":"Retail Goods"
        }
    ],
    "sg:phone":"+1 410 451 7255",
    "sg:postcode":"21114",
    "sg:province":"MD",
    "sg:tags":[
        "shop"
    ],
    "sg:website":"http://www.mysticpiercing.com",
    "wof:name":"Get Real",
    "wof:placetype":"venue"
},
  "geometry": {"coordinates":[-76.70040899999999,38.991928],"type":"Point"}
}