{
  "type": "Feature",
  "properties": {
    "iso:country":"US",
    "sg:address":"29 Holmehurst Ave",
    "sg:city":"Baltimore",
    "sg:classifiers":[
        {
            "category":"Organizations",
            "subcategory":"Religious Organization",
            "type":"Services"
        }
    ],
    "sg:phone":"+1 410 747 3030",
    "sg:postcode":"21228",
    "sg:province":"MD",
    "sg:tags":[
        "church"
    ],
    "wof:name":"Grace Reformed Presbyterian Ch",
    "wof:placetype":"venue"
},
  "geometry": {"coordinates":[-76.724376,39.268059],"type":"Point"}
}