{
  "type": "Feature",
  "properties": {
    "iso:country":"US",
    "sg:address":"126 W High St",
    "sg:city":"Hancock",
    "sg:classifiers":[
        {
            "category":"Government",
            "subcategory":"Office",
            "type":"Public Place"
        }
    ],
    "sg:phone":"+1 301 678 5622",
    "sg:postcode":"21750",
    "sg:province":"MD",
    "sg:tags":[
        "town"
    ],
    "wof:name":"Hancock Historical Society",
    "wof:placetype":"venue"
},
  "geometry": {"coordinates":[-78.182638,39.700565],"type":"Point"}
}