{
  "type": "Feature",
  "properties": {
    "addr:full":"4013 Chelmont Ln Bowie MD 20715",
    "addr:housenumber":"4013",
    "addr:postcode":"20715",
    "addr:street":"Chelmont Ln",
    "iso:country":"US",
    "sg:address":"4013 Chelmont Ln",
    "sg:city":"Bowie",
    "sg:classifiers":[
        {
            "category":"Personal",
            "subcategory":"Beauty Salon",
            "type":"Services"
        }
    ],
    "sg:phone":"+1 301 464 2088",
    "sg:postcode":"20715",
    "sg:province":"MD",
    "sg:tags":[
        "shop"
    ],
    "wof:name":"Jans Place Inc",
    "wof:placetype":"venue"
},
  "geometry": {"coordinates":[-76.74159899999999,38.99161],"type":"Point"}
}