{
  "type": "Feature",
  "properties": {
    "iso:country":"US",
    "sg:address":"119 E Antietam St",
    "sg:city":"Hagerstown",
    "sg:classifiers":[
        {
            "category":"Health Services",
            "subcategory":"Doctor",
            "type":"Services"
        }
    ],
    "sg:phone":"+1 301 739 2560",
    "sg:postcode":"21740",
    "sg:province":"MD",
    "sg:tags":[
        "physician",
        "surgeon"
    ],
    "wof:name":"Gastroenterology Consultant",
    "wof:placetype":"venue"
},
  "geometry": {"coordinates":[-77.717569,39.638872],"type":"Point"}
}