{
  "type": "Feature",
  "properties": {
    "addr:full":"7019 Harford Rd Parkville MD 21234",
    "addr:housenumber":"7019",
    "addr:postcode":"21234",
    "addr:street":"Harford Rd",
    "iso:country":"US",
    "sg:address":"7019 Harford Rd",
    "sg:city":"Parkville",
    "sg:classifiers":[
        {
            "category":"Shopping",
            "subcategory":"Computers & Home Electronics",
            "type":"Retail Goods"
        }
    ],
    "sg:phone":"+1 410 426 0776",
    "sg:postcode":"21234",
    "sg:province":"MD",
    "wof:name":"A Award Winning Service",
    "wof:placetype":"venue"
},
  "geometry": {"coordinates":[-76.548698,39.367199],"type":"Point"}
}