{
  "type": "Feature",
  "properties": {
    "addr:full":"2050 Crain Hwy Waldorf MD 20601",
    "addr:housenumber":"2050",
    "addr:postcode":"20601",
    "addr:street":"Crain Hwy",
    "iso:country":"US",
    "sg:address":"2050 Crain Hwy",
    "sg:city":"Waldorf",
    "sg:classifiers":[
        {
            "category":"Autos & Motor Vehicles",
            "subcategory":"Fuel & Gas Station",
            "type":"Retail Goods"
        }
    ],
    "sg:phone":"+1 301 638 7705",
    "sg:postcode":"20601",
    "sg:province":"MD",
    "sg:tags":[
        "oil"
    ],
    "wof:name":"Mattawoman Amoco",
    "wof:placetype":"venue"
},
  "geometry": {"coordinates":[-76.874256,38.658034],"type":"Point"}
}