{
  "type": "Feature",
  "properties": {
    "addr:full":"508 S 5th Ave Denton MD 21629",
    "addr:housenumber":"508",
    "addr:postcode":"21629",
    "addr:street":"S 5Th Ave",
    "iso:country":"US",
    "sg:address":"508 S 5th Ave",
    "sg:city":"Denton",
    "sg:classifiers":[
        {
            "category":"Shopping",
            "subcategory":"Pharmacy",
            "type":"Retail Goods"
        }
    ],
    "sg:phone":"+1 410 479 1100",
    "sg:postcode":"21629",
    "sg:province":"MD",
    "wof:name":"Denton Pharmacy",
    "wof:placetype":"venue"
},
  "geometry": {"coordinates":[-75.82815600000001,38.879229],"type":"Point"}
}