{
  "type": "Feature",
  "properties": {
    "iso:country":"US",
    "sg:address":"256 Frock Ln",
    "sg:city":"Conowingo",
    "sg:classifiers":[
        {
            "category":"Building & Trades",
            "subcategory":"Landscaping Services",
            "type":"Services"
        }
    ],
    "sg:phone":"+1 410 378 3712",
    "sg:postcode":"21918",
    "sg:province":"MD",
    "sg:tags":[
        "tree"
    ],
    "wof:name":"Nitz Tree Svc",
    "wof:placetype":"venue"
},
  "geometry": {"coordinates":[-76.166116,39.684897],"type":"Point"}
}