{
  "type": "Feature",
  "properties": {
    "iso:country":"US",
    "sg:address":"105 Haverhill Rd",
    "sg:city":"Joppa",
    "sg:classifiers":[
        {
            "category":"Professional",
            "subcategory":"Engineering",
            "type":"Services"
        }
    ],
    "sg:phone":"+1 410 679 6419",
    "sg:postcode":"21085",
    "sg:province":"MD",
    "sg:tags":[
        "consulting",
        "engineer"
    ],
    "sg:website":"http://www.keh-ee.com",
    "wof:name":"Keh Energy Engineering",
    "wof:placetype":"venue"
},
  "geometry": {"coordinates":[-76.33772999999999,39.39798],"type":"Point"}
}