{
  "type": "Feature",
  "properties": {
    "iso:country":"US",
    "sg:address":"22 Longview Dr",
    "sg:city":"Elkton",
    "sg:classifiers":[
        {
            "category":"Shopping",
            "subcategory":"Catalog Store",
            "type":"Retail Goods"
        }
    ],
    "sg:phone":"+1 410 392 4177",
    "sg:postcode":"21921",
    "sg:province":"MD",
    "sg:tags":[
        "mail",
        "house"
    ],
    "wof:name":"Kortas Marketing",
    "wof:placetype":"venue"
},
  "geometry": {"coordinates":[-75.900177,39.533816],"type":"Point"}
}