{
  "type": "Feature",
  "properties": {
    "addr:full":"207 W Hilltop Rd Baltimore MD 21225",
    "addr:housenumber":"207",
    "addr:postcode":"21225",
    "addr:street":"W Hilltop Rd",
    "iso:country":"US",
    "sg:address":"207 W Hilltop Rd",
    "sg:city":"Baltimore",
    "sg:classifiers":[
        {
            "category":"Building & Trades",
            "subcategory":"Construction",
            "type":"Services"
        }
    ],
    "sg:phone":"+1 410 636 4124",
    "sg:postcode":"21225",
    "sg:province":"MD",
    "sg:tags":[
        "house"
    ],
    "wof:name":"Steve Hock",
    "wof:placetype":"venue"
},
  "geometry": {"coordinates":[-76.617779,39.234697],"type":"Point"}
}