{
  "type": "Feature",
  "properties": {
    "addr:full":"137 Baltimore St Cumberland MD 21502",
    "addr:housenumber":"137",
    "addr:postcode":"21502",
    "addr:street":"Baltimore St",
    "iso:country":"US",
    "sg:address":"137 Baltimore St",
    "sg:city":"Cumberland",
    "sg:classifiers":[
        {
            "category":"Shopping",
            "subcategory":"Clothing, Apparel, & Fashions",
            "type":"Retail Goods"
        }
    ],
    "sg:phone":"+1 301 759 9375",
    "sg:postcode":"21502",
    "sg:province":"MD",
    "sg:tags":[
        "we",
        "accessory",
        "wear",
        "bridal",
        "formal"
    ],
    "wof:name":"Elizabeth Anns Brdal Formal Wr",
    "wof:placetype":"venue"
},
  "geometry": {"coordinates":[-78.760542,39.65167],"type":"Point"}
}