{
  "type": "Feature",
  "properties": {
    "addr:full":"2100 Garfield Ct Frederick MD 21702",
    "addr:housenumber":"2100",
    "addr:postcode":"21702",
    "addr:street":"Garfield Ct",
    "iso:country":"US",
    "sg:address":"2100 Garfield Ct",
    "sg:city":"Frederick",
    "sg:classifiers":[
        {
            "category":"Utilities",
            "subcategory":"Cable",
            "type":"Services"
        }
    ],
    "sg:phone":"+1 301 846 4234",
    "sg:postcode":"21702",
    "sg:province":"MD",
    "sg:tags":[
        "television"
    ],
    "wof:name":"Puja Electronics",
    "wof:placetype":"venue"
},
  "geometry": {"coordinates":[-77.43984399999999,39.449591],"type":"Point"}
}