{
  "type": "Feature",
  "properties": {
    "addr:full":"5171 Duke Ct Frederick MD 21703",
    "addr:housenumber":"5171",
    "addr:postcode":"21703",
    "addr:street":"Duke Ct",
    "iso:country":"US",
    "sg:address":"5171 Duke Ct",
    "sg:city":"Frederick",
    "sg:classifiers":[
        {
            "category":"Building & Trades",
            "subcategory":"Cleaning & Sanitation",
            "type":"Services"
        }
    ],
    "sg:phone":"+1 301 668 2789",
    "sg:postcode":"21703",
    "sg:province":"MD",
    "sg:tags":[
        "maintenance"
    ],
    "wof:name":"Tommys Cleaning Service",
    "wof:placetype":"venue"
},
  "geometry": {"coordinates":[-77.42613,39.377648],"type":"Point"}
}