{
  "type": "Feature",
  "properties": {
    "iso:country":"US",
    "sg:address":"5000 Pennsylvania Ave",
    "sg:city":"Suitland",
    "sg:classifiers":[
        {
            "category":"Manufacturing",
            "subcategory":"Printing",
            "type":"Manufacturing & Wholesale Goods"
        }
    ],
    "sg:phone":"+1 301 669 6550",
    "sg:postcode":"20746",
    "sg:province":"MD",
    "sg:tags":[
        "publishing"
    ],
    "wof:name":"Sks Press",
    "wof:placetype":"venue"
},
  "geometry": {"coordinates":[-76.923636,38.864172],"type":"Point"}
}