{
  "type": "Feature",
  "properties": {
    "addr:full":"2012 Eliza Dorsey Ln Ellicott City MD 21042",
    "addr:housenumber":"2012",
    "addr:postcode":"21042",
    "addr:street":"Eliza Dorsey Ln",
    "iso:country":"US",
    "sg:address":"2012 Eliza Dorsey Ln",
    "sg:city":"Ellicott City",
    "sg:classifiers":[
        {
            "category":"Health Services",
            "subcategory":"Dentist",
            "type":"Services"
        }
    ],
    "sg:phone":"+1 410 203 9335",
    "sg:postcode":"21042",
    "sg:province":"MD",
    "wof:name":"Berne Alan M DDS",
    "wof:placetype":"venue"
},
  "geometry": {"coordinates":[-76.826843,39.306356],"type":"Point"}
}