{
  "type": "Feature",
  "properties": {
    "addr:full":"5901 Hillside Rd St Leonard MD 20685",
    "addr:housenumber":"5901",
    "addr:postcode":"20685",
    "addr:street":"Hillside Rd St",
    "iso:country":"US",
    "sg:address":"5901 Hillside Rd",
    "sg:city":"St Leonard",
    "sg:classifiers":[
        {
            "category":"Real Estate",
            "subcategory":"Real Estate Agent",
            "type":"Services"
        }
    ],
    "sg:phone":"+1 410 586 1963",
    "sg:postcode":"20685",
    "sg:province":"MD",
    "sg:tags":[
        "inspection"
    ],
    "wof:name":"American Property Consultants",
    "wof:placetype":"venue"
},
  "geometry": {"coordinates":[-76.482738,38.459755],"type":"Point"}
}