{
  "type": "Feature",
  "properties": {
    "iso:country":"US",
    "sg:address":"110 S Washington St",
    "sg:city":"Rockville",
    "sg:classifiers":[
        {
            "category":"Real Estate",
            "subcategory":"Real Estate Agent",
            "type":"Services"
        }
    ],
    "sg:phone":"+1 301 340 9400",
    "sg:postcode":"20850",
    "sg:province":"MD",
    "wof:name":"Clogg J Realty Group Inc",
    "wof:placetype":"venue"
},
  "geometry": {"coordinates":[-77.152773,39.082878],"type":"Point"}
}