{
  "type": "Feature",
  "properties": {
    "addr:full":"4515 Sandy Spring Rd Burtonsville MD 20866",
    "addr:housenumber":"4515",
    "addr:postcode":"20866",
    "addr:street":"Sandy Spring Rd",
    "iso:country":"US",
    "sg:address":"4515 Sandy Spring Rd",
    "sg:city":"Burtonsville",
    "sg:classifiers":[
        {
            "category":"Education",
            "subcategory":"School",
            "type":"Public Place"
        }
    ],
    "sg:phone":"+1 301 549 3725",
    "sg:postcode":"20866",
    "sg:province":"MD",
    "wof:name":"Providence Christian School",
    "wof:placetype":"venue"
},
  "geometry": {"coordinates":[-76.914817,39.106384],"type":"Point"}
}