{
  "type": "Feature",
  "properties": {
    "iso:country":"US",
    "sg:address":"7312 Piney Branch Rd",
    "sg:city":"Takoma Park",
    "sg:classifiers":[
        {
            "category":"Professional",
            "subcategory":"Art Services",
            "type":"Services"
        }
    ],
    "sg:phone":"+1 301 589 8263",
    "sg:postcode":"20912",
    "sg:province":"MD",
    "sg:tags":[
        "photography",
        "commercial"
    ],
    "wof:name":"Katanya Assoc",
    "wof:placetype":"venue"
},
  "geometry": {"coordinates":[-77.01727,38.979905],"type":"Point"}
}