{
  "type": "Feature",
  "properties": {
    "addr:full":"2 Wayside Ave Hagerstown MD 21740",
    "addr:housenumber":"2",
    "addr:postcode":"21740",
    "addr:street":"Wayside Ave",
    "iso:country":"US",
    "sg:address":"2 Wayside Ave",
    "sg:city":"Hagerstown",
    "sg:classifiers":[
        {
            "category":"Health Services",
            "subcategory":"Doctor",
            "type":"Services"
        }
    ],
    "sg:phone":"+1 301 733 9020",
    "sg:postcode":"21740",
    "sg:province":"MD",
    "sg:tags":[
        "dentist"
    ],
    "wof:name":"Jay M Blickenstaff DDS",
    "wof:placetype":"venue"
},
  "geometry": {"coordinates":[-77.71338299999999,39.649239],"type":"Point"}
}