{
  "type": "Feature",
  "properties": {
    "addr:full":"16290 Spielman Rd Williamsport MD 21795",
    "addr:postcode":"16290;21795",
    "addr:street":"Spielman Rd",
    "iso:country":"US",
    "sg:address":"16290 Spielman Rd",
    "sg:city":"Williamsport",
    "sg:classifiers":[
        {
            "category":"Building & Trades",
            "subcategory":"Electrical",
            "type":"Services"
        }
    ],
    "sg:phone":"+1 301 223 1152",
    "sg:postcode":"21795",
    "sg:province":"MD",
    "sg:tags":[
        "industrial",
        "electrician",
        "contractors-commercial",
        "electric"
    ],
    "wof:name":"Antietam Electrical Contractors Inc",
    "wof:placetype":"venue"
},
  "geometry": {"coordinates":[-77.808531,39.559427],"type":"Point"}
}