{
  "type": "Feature",
  "properties": {
    "addr:full":"10309 Pimlico Pl Laurel MD 20723",
    "addr:housenumber":"10309",
    "addr:postcode":"20723",
    "addr:street":"Pimlico Pl",
    "iso:country":"US",
    "sg:address":"10309 Pimlico Pl",
    "sg:city":"Laurel",
    "sg:classifiers":[
        {
            "category":"Building & Trades",
            "subcategory":"Construction",
            "type":"Services"
        }
    ],
    "sg:phone":"+1 410 519 9000",
    "sg:postcode":"20723",
    "sg:province":"MD",
    "sg:tags":[
        "general",
        "contractor"
    ],
    "wof:name":"Atlantic Home Recovery",
    "wof:placetype":"venue"
},
  "geometry": {"coordinates":[-76.866896,39.154274],"type":"Point"}
}