{
  "type": "Feature",
  "properties": {
    "iso:country":"US",
    "sg:address":"7811 Wise Ave",
    "sg:city":"Baltimore",
    "sg:classifiers":[
        {
            "category":"Health Services",
            "subcategory":"Doctor",
            "type":"Services"
        }
    ],
    "sg:phone":"+1 410 282 0500",
    "sg:postcode":"21222",
    "sg:province":"MD",
    "sg:tags":[
        "physician",
        "surgeon"
    ],
    "wof:name":"Arturo A Pidlaoan MD",
    "wof:placetype":"venue"
},
  "geometry": {"coordinates":[-76.49861300000001,39.268035],"type":"Point"}
}