{
  "type": "Feature",
  "properties": {
    "addr:full":"11134 Rum Springs Rd Myersville MD 21773",
    "addr:postcode":"11134;21773",
    "addr:street":"Springs Rd",
    "iso:country":"US",
    "sg:address":"11134 Rum Springs Rd",
    "sg:city":"Myersville",
    "sg:classifiers":[
        {
            "category":"Building & Trades",
            "subcategory":"Construction",
            "type":"Services"
        }
    ],
    "sg:phone":"+1 301 293 3213",
    "sg:postcode":"21773",
    "sg:province":"MD",
    "sg:tags":[
        "contractor"
    ],
    "wof:name":"Event Acoustics",
    "wof:placetype":"venue"
},
  "geometry": {"coordinates":[-77.509924,39.53384],"type":"Point"}
}