{
  "type": "Feature",
  "properties": {
    "addr:full":"4347 Ebenezer Rd Nottingham MD 21236",
    "addr:housenumber":"4347",
    "addr:postcode":"21236",
    "addr:street":"Ebenezer Rd",
    "iso:country":"US",
    "sg:address":"4347 Ebenezer Rd",
    "sg:city":"Nottingham",
    "sg:classifiers":[
        {
            "category":"Restaurant",
            "type":"Food & Drink"
        }
    ],
    "sg:phone":"+1 410 248 1088",
    "sg:postcode":"21236",
    "sg:province":"MD",
    "sg:tags":[
        "thai"
    ],
    "sg:website":"boualas.com/",
    "wof:name":"Bouala's Thai Restaurant",
    "wof:placetype":"venue"
},
  "geometry": {"coordinates":[-76.419279,39.375749],"type":"Point"}
}