{
  "type": "Feature",
  "properties": {
    "iso:country":"US",
    "sg:address":"7698 Belair Rd",
    "sg:city":"Baltimore",
    "sg:classifiers":[
        {
            "category":"Home & Garden",
            "subcategory":"Furniture",
            "type":"Retail Goods"
        }
    ],
    "sg:phone":"+1 410 668 6210",
    "sg:postcode":"21236",
    "sg:province":"MD",
    "sg:tags":[
        "mattress"
    ],
    "wof:name":"Mr Mattress",
    "wof:placetype":"venue"
},
  "geometry": {"coordinates":[-76.517974,39.366076],"type":"Point"}
}