{
  "type": "Feature",
  "properties": {
    "iso:country":"US",
    "sg:address":"10845 Town Center Blvd",
    "sg:city":"Dunkirk",
    "sg:classifiers":[
        {
            "category":"Health Services",
            "subcategory":"Doctor",
            "type":"Services"
        }
    ],
    "sg:phone":"+1 301 812 0435",
    "sg:postcode":"20754",
    "sg:province":"MD",
    "sg:tags":[
        "physician",
        "surgeon"
    ],
    "wof:name":"Calvert Medical Imaging Ctr",
    "wof:placetype":"venue"
},
  "geometry": {"coordinates":[-76.657191,38.725272],"type":"Point"}
}