{
  "type": "Feature",
  "properties": {
    "iso:country":"US",
    "sg:address":"2301 Twin Valley Ln",
    "sg:city":"Silver Spring",
    "sg:classifiers":[
        {
            "category":"Professional",
            "type":"Services"
        }
    ],
    "sg:phone":"+1 301 924 0970",
    "sg:postcode":"20906",
    "sg:province":"MD",
    "sg:tags":[
        "establishment"
    ],
    "sg:website":"www.babybrazil.com",
    "wof:name":"BABYBRAZIL.COM",
    "wof:placetype":"venue"
},
  "geometry": {"coordinates":[-77.050215,39.113758],"type":"Point"}
}