{
  "type": "Feature",
  "properties": {
    "addr:full":"6108 Old Silver Hill Rd Ste 209 District Heights MD 20747",
    "addr:housenumber":"6108",
    "addr:postcode":"20747",
    "addr:street":"Old Silver Hill Rd Ste 209",
    "iso:country":"US",
    "sg:address":"6108 Old Silver Hill Rd Ste 209",
    "sg:city":"District Heights",
    "sg:classifiers":[
        {
            "category":"Professional",
            "subcategory":"Lawyer & Legal Services",
            "type":"Services"
        }
    ],
    "sg:phone":"+1 301 420 5541",
    "sg:postcode":"20747",
    "sg:province":"MD",
    "wof:name":"Burton Aubrey Jr",
    "wof:placetype":"venue"
},
  "geometry": {"coordinates":[-76.90165,38.855329],"type":"Point"}
}