{
  "type": "Feature",
  "properties": {
    "iso:country":"US",
    "sg:address":"15825 Shady Grove Rd",
    "sg:city":"Rockville",
    "sg:classifiers":[
        {
            "category":"Government",
            "subcategory":"Fire Station",
            "type":"Public Place"
        }
    ],
    "sg:phone":"+1 240 777 2248",
    "sg:postcode":"20877",
    "sg:province":"MD",
    "sg:tags":[
        "protection"
    ],
    "wof:name":"Fire & Rescue",
    "wof:placetype":"venue"
},
  "geometry": {"coordinates":[-77.183835,39.116894],"type":"Point"}
}