{
  "type": "Feature",
  "properties": {
    "iso:country":"US",
    "sg:address":"5101 Branchville Rd",
    "sg:city":"College Park",
    "sg:classifiers":[
        {
            "category":"Building & Trades",
            "subcategory":"Construction",
            "type":"Services"
        }
    ],
    "sg:phone":"+1 301 474 7550",
    "sg:postcode":"20740",
    "sg:province":"MD",
    "sg:tags":[
        "elevator"
    ],
    "wof:name":"Advanced Elevator Corp",
    "wof:placetype":"venue"
},
  "geometry": {"coordinates":[-76.920709,38.998971],"type":"Point"}
}