{
  "type": "Feature",
  "properties": {
    "addr:full":"6526 Holabird Ave Baltimore MD 21224",
    "addr:housenumber":"6526",
    "addr:postcode":"21224",
    "addr:street":"Holabird Ave",
    "iso:country":"US",
    "sg:address":"6526 Holabird Ave",
    "sg:city":"Baltimore",
    "sg:classifiers":[
        {
            "category":"Restaurant",
            "type":"Food & Drink"
        }
    ],
    "sg:menulink":"http://www.allmenus.com/md/baltimore/268776-jimmys-famous-seafood/menu/",
    "sg:phone":"+1 410 633 4040",
    "sg:postcode":"21224",
    "sg:province":"MD",
    "sg:tags":[
        "seafood",
        "american"
    ],
    "wof:name":"Jimmy's Famous Seafood",
    "wof:placetype":"venue"
},
  "geometry": {"coordinates":[-76.53463499999999,39.272673],"type":"Point"}
}