{
  "type": "Feature",
  "properties": {
    "iso:country":"US",
    "sg:address":"3619 7th Ave",
    "sg:city":"Edgewater",
    "sg:classifiers":[
        {
            "category":"Building & Trades",
            "subcategory":"Construction",
            "type":"Services"
        }
    ],
    "sg:phone":"+1 410 798 5033",
    "sg:postcode":"21037",
    "sg:province":"MD",
    "sg:tags":[
        "house"
    ],
    "wof:name":"McCoy Home Improvement",
    "wof:placetype":"venue"
},
  "geometry": {"coordinates":[-76.523394,38.908213],"type":"Point"}
}