{
  "type": "Feature",
  "properties": {
    "addr:full":"6000 Greenbelt Rd Greenbelt MD 20770",
    "addr:housenumber":"6000",
    "addr:postcode":"20770",
    "addr:street":"Greenbelt Rd",
    "iso:country":"US",
    "sg:address":"6000 Greenbelt Rd",
    "sg:city":"Greenbelt",
    "sg:classifiers":[
        {
            "category":"Restaurant",
            "type":"Food & Drink"
        }
    ],
    "sg:menulink":"http://www.allmenus.com/md/berwyn/215561-mcdonalds/menu/",
    "sg:phone":"+1 301 614 3428",
    "sg:postcode":"20770",
    "sg:province":"MD",
    "sg:tags":[
        "burger",
        "american"
    ],
    "wof:name":"McDonald's",
    "wof:placetype":"venue"
},
  "geometry": {"coordinates":[-76.91203899999999,38.99802],"type":"Point"}
}