{
  "type": "Feature",
  "properties": {
    "iso:country":"US",
    "sg:address":"10400 Darnestown Rd",
    "sg:city":"Rockville",
    "sg:classifiers":[
        {
            "category":"Organizations",
            "subcategory":"Religious Organization",
            "type":"Services"
        }
    ],
    "sg:phone":"+1 301 251 3719",
    "sg:postcode":"20850",
    "sg:province":"MD",
    "sg:tags":[
        "church"
    ],
    "wof:name":"King--Nations Christian Fllwsp",
    "wof:placetype":"venue"
},
  "geometry": {"coordinates":[-77.21438499999999,39.100479],"type":"Point"}
}