{
  "type": "Feature",
  "properties": {
    "iso:country":"US",
    "sg:address":"9807 Sea Gull Ct",
    "sg:city":"Upper Marlboro",
    "sg:classifiers":[
        {
            "category":"Real Estate",
            "subcategory":"Real Estate Agent",
            "type":"Services"
        }
    ],
    "sg:phone":"+1 301 877 2687",
    "sg:postcode":"20772",
    "sg:province":"MD",
    "wof:name":"Acumen Real Properties",
    "wof:placetype":"venue"
},
  "geometry": {"coordinates":[-76.824552,38.75384],"type":"Point"}
}