{
  "type": "Feature",
  "properties": {
    "addr:full":"10 Creston Ln Solomons MD 20688",
    "addr:housenumber":"10",
    "addr:postcode":"20688",
    "addr:street":"Creston Ln",
    "iso:country":"US",
    "sg:address":"10 Creston Ln",
    "sg:city":"Solomons",
    "sg:classifiers":[
        {
            "category":"Recreation",
            "subcategory":"Boat Charter",
            "type":"Entertainment"
        }
    ],
    "sg:phone":"+1 410 326 4014",
    "sg:postcode":"20688",
    "sg:province":"MD",
    "sg:tags":[
        "boating"
    ],
    "wof:name":"Bristol Technology Inc",
    "wof:placetype":"venue"
},
  "geometry": {"coordinates":[-76.466103,38.344299],"type":"Point"}
}