{
  "type": "Feature",
  "properties": {
    "addr:full":"10560 Cross Fox Ln Columbia MD 21044",
    "addr:housenumber":"10560",
    "addr:postcode":"21044",
    "addr:street":"Cross Fox Ln",
    "iso:country":"US",
    "sg:address":"10560 Cross Fox Ln",
    "sg:city":"Columbia",
    "sg:classifiers":[
        {
            "category":"Building & Trades",
            "subcategory":"Construction",
            "type":"Services"
        }
    ],
    "sg:phone":"+1 410 730 4601",
    "sg:postcode":"21044",
    "sg:province":"MD",
    "sg:tags":[
        "roofing",
        "industrial",
        "contractors-commercial",
        "contractor"
    ],
    "wof:name":"A1 Roofing Svc.",
    "wof:placetype":"venue"
},
  "geometry": {"coordinates":[-76.877708,39.219646],"type":"Point"}
}