{
  "type": "Feature",
  "properties": {
    "addr:full":"6422 Baltimore Natinl Pke Catonsville MD 21228",
    "addr:housenumber":"6422",
    "addr:postcode":"21228",
    "addr:street":"Baltimore Natinl Pke",
    "iso:country":"US",
    "sg:address":"6422 Baltimore Natinl Pke",
    "sg:city":"Catonsville",
    "sg:classifiers":[
        {
            "category":"Travel",
            "subcategory":"Hotels & Motels",
            "type":"Entertainment"
        }
    ],
    "sg:phone":"+1 410 788 3900",
    "sg:postcode":"21228",
    "sg:province":"MD",
    "wof:name":"Ramada Limited",
    "wof:placetype":"venue"
},
  "geometry": {"coordinates":[-76.758202,39.284901],"type":"Point"}
}