{
  "type": "Feature",
  "properties": {
    "addr:full":"52 Triple Crown Ct Baltimore MD 21244",
    "addr:housenumber":"52",
    "addr:postcode":"21244",
    "addr:street":"Triple Crown Ct",
    "iso:country":"US",
    "sg:address":"52 Triple Crown Ct",
    "sg:city":"Baltimore",
    "sg:classifiers":[
        {
            "category":"Building & Trades",
            "subcategory":"Construction",
            "type":"Services"
        }
    ],
    "sg:phone":"+1 410 944 1164",
    "sg:postcode":"21244",
    "sg:province":"MD",
    "sg:tags":[
        "contractor"
    ],
    "wof:name":"Hines Joe Master Contractor",
    "wof:placetype":"venue"
},
  "geometry": {"coordinates":[-76.77774700000001,39.313127],"type":"Point"}
}