{
  "type": "Feature",
  "properties": {
    "addr:full":"7405 Liberty Rd Baltimore MD 21207",
    "addr:housenumber":"7405",
    "addr:postcode":"21207",
    "addr:street":"Liberty Rd",
    "iso:country":"US",
    "sg:address":"7405 Liberty Rd",
    "sg:city":"Baltimore",
    "sg:classifiers":[
        {
            "category":"Shopping",
            "type":"Retail Goods"
        }
    ],
    "sg:phone":"+1 410 265 1092",
    "sg:postcode":"21207",
    "sg:province":"MD",
    "sg:tags":[
        "cosmetic",
        "perfume"
    ],
    "wof:name":"Lee Beauty Supply",
    "wof:placetype":"venue"
},
  "geometry": {"coordinates":[-76.740621,39.34734],"type":"Point"}
}