{
  "type": "Feature",
  "properties": {
    "addr:full":"13300 Baltimore Ave Laurel MD 20707",
    "addr:housenumber":"13300",
    "addr:postcode":"20707",
    "addr:street":"Baltimore Ave",
    "iso:country":"US",
    "sg:address":"13300 Baltimore Ave",
    "sg:city":"Laurel",
    "sg:classifiers":[
        {
            "category":"Retail",
            "subcategory":"Funeral Services",
            "type":"Services"
        }
    ],
    "sg:phone":"+1 410 813 0099",
    "sg:postcode":"20707",
    "sg:province":"MD",
    "sg:tags":[
        "cemetery"
    ],
    "wof:name":"Memorial Estate Planning Institute Inc",
    "wof:placetype":"venue"
},
  "geometry": {"coordinates":[-76.87159699999999,39.0732],"type":"Point"}
}