{
  "type": "Feature",
  "properties": {
    "iso:country":"US",
    "sg:address":"12186 Clarksville Pike",
    "sg:city":"Clarksville",
    "sg:classifiers":[
        {
            "category":"Shopping",
            "subcategory":"Florist",
            "type":"Retail Goods"
        }
    ],
    "sg:phone":"+1 410 531 5648",
    "sg:postcode":"21029",
    "sg:province":"MD",
    "wof:name":"Clarksville Flower Station",
    "wof:placetype":"venue"
},
  "geometry": {"coordinates":[-76.93567400000001,39.213707],"type":"Point"}
}