{
  "type": "Feature",
  "properties": {
    "iso:country":"US",
    "sg:address":"6416 Old Landover Rd",
    "sg:city":"Hyattsville",
    "sg:classifiers":[
        {
            "category":"Social Services",
            "subcategory":"Child Care",
            "type":"Services"
        }
    ],
    "sg:phone":"+1 301 386 5979",
    "sg:postcode":"20785",
    "sg:province":"MD",
    "sg:tags":[
        "day"
    ],
    "wof:name":"Faith Child Care Services",
    "wof:placetype":"venue"
},
  "geometry": {"coordinates":[-76.905502,38.933601],"type":"Point"}
}