{
  "type": "Feature",
  "properties": {
    "iso:country":"US",
    "sg:address":"1212 E Joppa Rd",
    "sg:city":"Baltimore",
    "sg:classifiers":[
        {
            "category":"Health Services",
            "subcategory":"Doctor",
            "type":"Services"
        }
    ],
    "sg:phone":"+1 410 825 1771",
    "sg:postcode":"21286",
    "sg:province":"MD",
    "sg:tags":[
        "dentist"
    ],
    "wof:name":"Zenaida M Cofie DDS",
    "wof:placetype":"venue"
},
  "geometry": {"coordinates":[-76.578475,39.39667],"type":"Point"}
}