{
  "type": "Feature",
  "properties": {
    "addr:full":"2 N Charles St Ste 320 Baltimore MD 21201",
    "addr:housenumber":"2",
    "addr:postcode":"21201",
    "addr:street":"N Charles St Ste 320",
    "iso:country":"US",
    "sg:address":"2 N Charles St Ste 320",
    "sg:city":"Baltimore",
    "sg:classifiers":[
        {
            "category":"Professional",
            "subcategory":"Lawyer & Legal Services",
            "type":"Services"
        }
    ],
    "sg:phone":"+1 410 752 1220",
    "sg:postcode":"21201",
    "sg:province":"MD",
    "wof:name":"Kleeman Stephen J Atty",
    "wof:placetype":"venue"
},
  "geometry": {"coordinates":[-76.614998,39.289501],"type":"Point"}
}