{
  "type": "Feature",
  "properties": {
    "iso:country":"US",
    "sg:address":"3105 Emmorton Rd Ste 2C",
    "sg:city":"Abingdon",
    "sg:classifiers":[
        {
            "category":"Health Services",
            "subcategory":"Doctor",
            "type":"Services"
        },
        {
            "category":"Health Services",
            "subcategory":"Chiropractor",
            "type":"Services"
        }
    ],
    "sg:phone":"+1 410 838 6464",
    "sg:postcode":"21009",
    "sg:province":"MD",
    "sg:tags":[
        "physician",
        "surgeon",
        "chiropractic"
    ],
    "wof:name":"Linsey Robert S Dr Chiropractor",
    "wof:placetype":"venue"
},
  "geometry": {"coordinates":[-76.309256,39.474971],"type":"Point"}
}