{
  "type": "Feature",
  "properties": {
    "addr:full":"13182 Ripon Pl Upper Marlboro MD 20772",
    "addr:housenumber":"13182",
    "addr:postcode":"20772",
    "addr:street":"Ripon Pl",
    "iso:country":"US",
    "sg:address":"13182 Ripon Pl",
    "sg:city":"Upper Marlboro",
    "sg:classifiers":[
        {
            "category":"Professional",
            "subcategory":"Business Services",
            "type":"Services"
        }
    ],
    "sg:phone":"+1 301 627 2610",
    "sg:postcode":"20772",
    "sg:province":"MD",
    "sg:tags":[
        "police"
    ],
    "wof:name":"Landry Anthony John",
    "wof:placetype":"venue"
},
  "geometry": {"coordinates":[-76.777964,38.827192],"type":"Point"}
}