{
  "type": "Feature",
  "properties": {
    "addr:full":"5342 Snow Hill Rd Snow Hill MD 21863",
    "addr:housenumber":"5342",
    "addr:postcode":"21863",
    "addr:street":"Snow Hill Rd",
    "iso:country":"US",
    "sg:address":"5342 Snow Hill Rd",
    "sg:city":"Snow Hill",
    "sg:classifiers":[
        {
            "category":"Restaurant",
            "type":"Food & Drink"
        }
    ],
    "sg:phone":"+1 410 632 0564",
    "sg:postcode":"21863",
    "sg:province":"MD",
    "wof:name":"Down Under",
    "wof:placetype":"venue"
},
  "geometry": {"coordinates":[-75.395764,38.180587],"type":"Point"}
}