{
  "type": "Feature",
  "properties": {
    "addr:full":"8702 Granite Ln Laurel MD 20708",
    "addr:housenumber":"8702",
    "addr:postcode":"20708",
    "addr:street":"Granite Ln",
    "iso:country":"US",
    "sg:address":"8702 Granite Ln",
    "sg:city":"Laurel",
    "sg:classifiers":[
        {
            "category":"Professional",
            "subcategory":"Employment Agencies",
            "type":"Services"
        }
    ],
    "sg:phone":"+1 301 725 6930",
    "sg:postcode":"20708",
    "sg:province":"MD",
    "sg:tags":[
        "teachers'"
    ],
    "wof:name":"Greater Laurel Music Teacher Association",
    "wof:placetype":"venue"
},
  "geometry": {"coordinates":[-76.855864,39.060235],"type":"Point"}
}