{
  "type": "Feature",
  "properties": {
    "iso:country":"US",
    "sg:address":"30040 Saint James Way",
    "sg:city":"Princess Anne",
    "sg:classifiers":[
        {
            "category":"Wholesale",
            "subcategory":"Drugs",
            "type":"Manufacturing & Wholesale Goods"
        }
    ],
    "sg:phone":"+1 410 651 3258",
    "sg:postcode":"21853",
    "sg:province":"MD",
    "wof:name":"Kevin Scott Stuckey",
    "wof:placetype":"venue"
},
  "geometry": {"coordinates":[-75.710729,38.20855],"type":"Point"}
}