{
  "type": "Feature",
  "properties": {
    "addr:full":"3405 Epic Gate Bowie MD 20716",
    "addr:postcode":"3405;20716",
    "addr:street":"Epic Gate",
    "iso:country":"US",
    "sg:address":"3405 Epic Gate",
    "sg:city":"Bowie",
    "sg:classifiers":[
        {
            "category":"Professional",
            "subcategory":"Lawyer & Legal Services",
            "type":"Services"
        }
    ],
    "sg:phone":"+1 301 249 3002",
    "sg:postcode":"20716",
    "sg:province":"MD",
    "sg:tags":[
        "attorney"
    ],
    "wof:name":"Robert Cappell Law Offices",
    "wof:placetype":"venue"
},
  "geometry": {"coordinates":[-76.736508,38.93952],"type":"Point"}
}