{
  "type": "Feature",
  "properties": {
    "addr:full":"6039 Melbourne Ave Deale MD 20751",
    "addr:housenumber":"6039",
    "addr:postcode":"20751",
    "addr:street":"Melbourne Ave",
    "iso:country":"US",
    "sg:address":"6039 Melbourne Ave",
    "sg:city":"Deale",
    "sg:classifiers":[
        {
            "category":"Professional",
            "subcategory":"Lawyer & Legal Services",
            "type":"Services"
        }
    ],
    "sg:phone":"+1 301 261 5445",
    "sg:postcode":"20751",
    "sg:province":"MD",
    "sg:tags":[
        "attorney"
    ],
    "wof:name":"Christopher May",
    "wof:placetype":"venue"
},
  "geometry": {"coordinates":[-76.550325,38.773224],"type":"Point"}
}