{
  "type": "Feature",
  "properties": {
    "iso:country":"US",
    "sg:address":"26 Market Pl",
    "sg:city":"Baltimore",
    "sg:classifiers":[
        {
            "category":"Restaurant",
            "type":"Food & Drink"
        }
    ],
    "sg:phone":"+1 410 539 5353",
    "sg:postcode":"21202",
    "sg:province":"MD",
    "wof:name":"Lucille's",
    "wof:placetype":"venue"
},
  "geometry": {"coordinates":[-76.60715500000001,39.288762],"type":"Point"}
}