{
  "type": "Feature",
  "properties": {
    "iso:country":"US",
    "sg:address":"6 Renmark Ct",
    "sg:city":"Gaithersburg",
    "sg:classifiers":[
        {
            "category":"Professional",
            "subcategory":"Accounting & Tax Preparation",
            "type":"Services"
        }
    ],
    "sg:phone":"+1 301 977 9389",
    "sg:postcode":"20878",
    "sg:province":"MD",
    "sg:tags":[
        "bookkeeping"
    ],
    "sg:website":"http://proadvisor.intuit.com/quickbooks-help/jill-m-frillman",
    "wof:name":"Bookkeeping Etc Inc",
    "wof:placetype":"venue"
},
  "geometry": {"coordinates":[-77.243337,39.135619],"type":"Point"}
}