{
  "type": "Feature",
  "properties": {
    "addr:full":"10401 Old Georgetown Rd Bethesda MD 20814",
    "addr:housenumber":"10401",
    "addr:postcode":"20814",
    "addr:street":"Old Georgetown Rd",
    "iso:country":"US",
    "sg:address":"10401 Old Georgetown Rd",
    "sg:city":"Bethesda",
    "sg:classifiers":[
        {
            "category":"Health Services",
            "subcategory":"Doctor",
            "type":"Services"
        }
    ],
    "sg:phone":"+1 301 581 0412",
    "sg:postcode":"20814",
    "sg:province":"MD",
    "sg:tags":[
        "physician",
        "surgeon"
    ],
    "wof:name":"Community Hematology-Oncology",
    "wof:placetype":"venue"
},
  "geometry": {"coordinates":[-77.123587,39.022473],"type":"Point"}
}