{
  "type": "Feature",
  "properties": {
    "iso:country":"US",
    "sg:address":"1400 Front Ave",
    "sg:city":"Lutherville",
    "sg:classifiers":[
        {
            "category":"Professional",
            "subcategory":"Lawyer & Legal Services",
            "type":"Services"
        }
    ],
    "sg:phone":"+1 410 828 8500",
    "sg:postcode":"21093",
    "sg:province":"MD",
    "sg:tags":[
        "attorney"
    ],
    "wof:name":"WASE & WASE",
    "wof:placetype":"venue"
},
  "geometry": {"coordinates":[-76.63108699999999,39.422456],"type":"Point"}
}