{
  "type": "Feature",
  "properties": {
    "addr:full":"663 Main St Laurel MD 20707",
    "addr:housenumber":"663",
    "addr:postcode":"20707",
    "addr:street":"Main St",
    "iso:country":"US",
    "sg:address":"663 Main St",
    "sg:city":"Laurel",
    "sg:classifiers":[
        {
            "category":"Health Services",
            "subcategory":"Dentist",
            "type":"Services"
        }
    ],
    "sg:phone":"+1 301 953 1981",
    "sg:postcode":"20707",
    "sg:province":"MD",
    "wof:name":"Parlato Anthony V DDS PC",
    "wof:placetype":"venue"
},
  "geometry": {"coordinates":[-76.854698,39.108799],"type":"Point"}
}