{
  "type": "Feature",
  "properties": {
    "addr:full":"18006 Mateny Rd Germantown MD 20874",
    "addr:housenumber":"18006",
    "addr:postcode":"20874",
    "addr:street":"Mateny Rd",
    "iso:country":"US",
    "sg:address":"18006 Mateny Rd",
    "sg:city":"Germantown",
    "sg:classifiers":[
        {
            "category":"Banks & Credit Unions",
            "subcategory":"Bank",
            "type":"Services"
        }
    ],
    "sg:phone":"+1 301 353 8402",
    "sg:postcode":"20874",
    "sg:province":"MD",
    "sg:tags":[
        "federal",
        "savings",
        "institution"
    ],
    "wof:name":"Chevy Chase Bank",
    "wof:placetype":"venue"
},
  "geometry": {"coordinates":[-77.271011,39.147623],"type":"Point"}
}