{
  "type": "Feature",
  "properties": {
    "addr:full":"8231 Liberty Rd Windsor Mill MD 21244",
    "addr:housenumber":"8231",
    "addr:postcode":"21244",
    "addr:street":"Liberty Rd",
    "iso:country":"US",
    "sg:address":"8231 Liberty Rd",
    "sg:city":"Windsor Mill",
    "sg:classifiers":[
        {
            "category":"Restaurant",
            "type":"Food & Drink"
        }
    ],
    "sg:phone":"+1 410 655 9886",
    "sg:postcode":"21244",
    "sg:province":"MD",
    "wof:name":"Mc Donald's",
    "wof:placetype":"venue"
},
  "geometry": {"coordinates":[-76.764197,39.355694],"type":"Point"}
}