{
  "type": "Feature",
  "properties": {
    "iso:country":"US",
    "sg:address":"6801 Harford Rd",
    "sg:city":"Baltimore",
    "sg:classifiers":[
        {
            "category":"Wholesale",
            "subcategory":"Non-durable Goods",
            "type":"Manufacturing & Wholesale Goods"
        }
    ],
    "sg:phone":"+1 410 426 4300",
    "sg:postcode":"21234",
    "sg:province":"MD",
    "sg:tags":[
        "canvas"
    ],
    "wof:name":"J B Cutting Svc",
    "wof:placetype":"venue"
},
  "geometry": {"coordinates":[-76.55074999999999,39.364715],"type":"Point"}
}