{
  "type": "Feature",
  "properties": {
    "addr:full":"1119 Arcola Ave Wheaton MD 20902",
    "addr:housenumber":"1119",
    "addr:postcode":"20902",
    "addr:street":"Arcola Ave",
    "iso:country":"US",
    "sg:address":"1119 Arcola Ave",
    "sg:city":"Wheaton",
    "sg:classifiers":[
        {
            "category":"Health Services",
            "subcategory":"Doctor",
            "type":"Services"
        }
    ],
    "sg:phone":"+1 301 649 2201",
    "sg:postcode":"20902",
    "sg:province":"MD",
    "sg:tags":[
        "dentist"
    ],
    "wof:name":"Stephen H Lee DDS",
    "wof:placetype":"venue"
},
  "geometry": {"coordinates":[-77.027945,39.039543],"type":"Point"}
}