{
  "type": "Feature",
  "properties": {
    "iso:country":"US",
    "sg:address":"920 E West Hwy",
    "sg:city":"Takoma Park",
    "sg:classifiers":[
        {
            "category":"Autos & Motor Vehicles",
            "subcategory":"Fuel & Gas Station",
            "type":"Retail Goods"
        }
    ],
    "sg:phone":"+1 301 270 5309",
    "sg:postcode":"20912",
    "sg:province":"MD",
    "sg:tags":[
        "oil"
    ],
    "wof:name":"Takoma Park Amoco",
    "wof:placetype":"venue"
},
  "geometry": {"coordinates":[-76.992887,38.975429],"type":"Point"}
}