{
  "type": "Feature",
  "properties": {
    "addr:full":"9120 Ball Rd Ijamsville MD 21754",
    "addr:housenumber":"9120",
    "addr:postcode":"21754",
    "addr:street":"Ball Rd",
    "iso:country":"US",
    "sg:address":"9120 Ball Rd",
    "sg:city":"Ijamsville",
    "sg:classifiers":[
        {
            "category":"Farming",
            "subcategory":"Dairy Farm",
            "type":"Manufacturing & Wholesale Goods"
        }
    ],
    "sg:phone":"+1 301 695 3609",
    "sg:postcode":"21754",
    "sg:province":"MD",
    "wof:name":"Montgomery Farms",
    "wof:placetype":"venue"
},
  "geometry": {"coordinates":[-77.3377,39.353025],"type":"Point"}
}