{
  "type": "Feature",
  "properties": {
    "addr:full":"7391 Washington Blvd Ste 103 Elkridge MD 21075",
    "addr:housenumber":"7391",
    "addr:postcode":"21075",
    "addr:street":"Washington Blvd Ste 103",
    "iso:country":"US",
    "sg:address":"7391 Washington Blvd Ste 103",
    "sg:city":"Elkridge",
    "sg:classifiers":[
        {
            "category":"Professional",
            "type":"Services"
        },
        {
            "category":"Personal",
            "type":"Services"
        },
        {
            "category":"Retail",
            "subcategory":"Event Space",
            "type":"Services"
        }
    ],
    "sg:phone":"+1 410 579 8777",
    "sg:postcode":"21075",
    "sg:province":"MD",
    "sg:tags":[
        "facility",
        "hall",
        "planning",
        "reception",
        "caterer",
        "party",
        "banquet"
    ],
    "wof:name":"Absolutel Perfect Catering",
    "wof:placetype":"venue"
},
  "geometry": {"coordinates":[-76.766683,39.181963],"type":"Point"}
}