{
  "type": "Feature",
  "properties": {
    "addr:full":"12120 Pulaski Hwy Joppa MD 21085",
    "addr:housenumber":"12120",
    "addr:postcode":"21085",
    "addr:street":"Pulaski Hwy",
    "iso:country":"US",
    "sg:address":"12120 Pulaski Hwy",
    "sg:city":"Joppa",
    "sg:classifiers":[
        {
            "category":"Retail",
            "subcategory":"Auto Repair",
            "type":"Services"
        }
    ],
    "sg:phone":"+1 410 679 9900",
    "sg:postcode":"21085",
    "sg:province":"MD",
    "wof:name":"Ram's Auto",
    "wof:placetype":"venue"
},
  "geometry": {"coordinates":[-76.385498,39.4123],"type":"Point"}
}