{
  "type": "Feature",
  "properties": {
    "addr:full":"7568 Broadcloth Way Columbia MD 21046",
    "addr:housenumber":"7568",
    "addr:postcode":"21046",
    "addr:street":"Broadcloth Way",
    "iso:country":"US",
    "sg:address":"7568 Broadcloth Way",
    "sg:city":"Columbia",
    "sg:classifiers":[
        {
            "category":"Professional",
            "subcategory":"Business Services",
            "type":"Services"
        }
    ],
    "sg:phone":"+1 410 309 6564",
    "sg:postcode":"21046",
    "sg:province":"MD",
    "wof:name":"Trish Amish Interiors",
    "wof:placetype":"venue"
},
  "geometry": {"coordinates":[-76.870857,39.16368],"type":"Point"}
}