{
  "type": "Feature",
  "properties": {
    "addr:full":"1527 University Blvd E A Hyattsville MD 20783",
    "addr:housenumber":"1527",
    "addr:postcode":"20783",
    "addr:street":"University Blvd E A",
    "iso:country":"US",
    "sg:address":"1527 University Blvd E A",
    "sg:city":"Hyattsville",
    "sg:classifiers":[
        {
            "category":"Bakery",
            "type":"Food & Drink"
        }
    ],
    "sg:phone":"+1 301 434 5470",
    "sg:postcode":"20783",
    "sg:province":"MD",
    "wof:name":"Bale Bakery",
    "wof:placetype":"venue"
},
  "geometry": {"coordinates":[-76.981723,38.985186],"type":"Point"}
}