{
  "type": "Feature",
  "properties": {
    "iso:country":"US",
    "sg:address":"2000 Industrial Pkwy",
    "sg:city":"Salisbury",
    "sg:classifiers":[
        {
            "category":"Building & Trades",
            "subcategory":"Construction",
            "type":"Services"
        }
    ],
    "sg:phone":"+1 410 677 3530",
    "sg:postcode":"21801",
    "sg:province":"MD",
    "sg:tags":[
        "designer",
        "marine",
        "contractor"
    ],
    "wof:name":"Silverton Marine Corp",
    "wof:placetype":"venue"
},
  "geometry": {"coordinates":[-75.587497,38.40086],"type":"Point"}
}