{
  "type": "Feature",
  "properties": {
    "iso:country":"US",
    "sg:address":"10 Gerard Ave",
    "sg:city":"Timonium",
    "sg:classifiers":[
        {
            "category":"Professional",
            "subcategory":"Accounting & Tax Preparation",
            "type":"Services"
        }
    ],
    "sg:phone":"+1 410 252 0085",
    "sg:postcode":"21093",
    "sg:province":"MD",
    "sg:tags":[
        "accountant"
    ],
    "wof:name":"Michael A Arthur CPA",
    "wof:placetype":"venue"
},
  "geometry": {"coordinates":[-76.62483400000001,39.441972],"type":"Point"}
}