{
  "type": "Feature",
  "properties": {
    "iso:country":"US",
    "sg:address":"11630 Glen Arm Rd",
    "sg:city":"Glen Arm",
    "sg:classifiers":[
        {
            "category":"Organizations",
            "subcategory":"Religious Organization",
            "type":"Services"
        }
    ],
    "sg:phone":"+1 410 319 5222",
    "sg:postcode":"21057",
    "sg:province":"MD",
    "sg:tags":[
        "clergy"
    ],
    "wof:name":"Lorenz Grumm",
    "wof:placetype":"venue"
},
  "geometry": {"coordinates":[-76.51142,39.443654],"type":"Point"}
}