{
  "type": "Feature",
  "properties": {
    "iso:country":"US",
    "sg:address":"7423 Lindbergh Dr",
    "sg:city":"Gaithersburg",
    "sg:classifiers":[
        {
            "category":"Professional",
            "type":"Services"
        }
    ],
    "sg:phone":"+1 301 519 8870",
    "sg:postcode":"20879",
    "sg:province":"MD",
    "sg:tags":[
        "establishment"
    ],
    "wof:name":"Bethesda On-Line Organization",
    "wof:placetype":"venue"
},
  "geometry": {"coordinates":[-77.156626,39.163973],"type":"Point"}
}