{
  "type": "Feature",
  "properties": {
    "addr:full":"803 Sailboat Ct Edgewood MD 21040",
    "addr:housenumber":"803",
    "addr:postcode":"21040",
    "addr:street":"Sailboat Ct",
    "iso:country":"US",
    "sg:address":"803 Sailboat Ct",
    "sg:city":"Edgewood",
    "sg:classifiers":[
        {
            "category":"Professional",
            "subcategory":"Business Services",
            "type":"Services"
        }
    ],
    "sg:phone":"+1 410 679 0518",
    "sg:postcode":"21040",
    "sg:province":"MD",
    "wof:name":"Architectural Drafting Service",
    "wof:placetype":"venue"
},
  "geometry": {"coordinates":[-76.31371300000001,39.42948],"type":"Point"}
}