{
  "type": "Feature",
  "properties": {
    "iso:country":"US",
    "sg:address":"600 Jefferson Plz Ste M1",
    "sg:city":"Rockville",
    "sg:classifiers":[
        {
            "category":"Professional",
            "subcategory":"Business Services",
            "type":"Services"
        },
        {
            "category":"Government",
            "subcategory":"Post Office",
            "type":"Public Place"
        }
    ],
    "sg:phone":"+1 301 251 6623",
    "sg:postcode":"20852",
    "sg:province":"MD",
    "sg:tags":[
        "delivery",
        "messenger",
        "courier"
    ],
    "wof:name":"Royal Express",
    "wof:placetype":"venue"
},
  "geometry": {"coordinates":[-77.146271,39.080719],"type":"Point"}
}