{
  "type": "Feature",
  "properties": {
    "iso:country":"US",
    "sg:address":"3642 Roland Ave",
    "sg:city":"Baltimore",
    "sg:classifiers":[
        {
            "category":"Professional",
            "subcategory":"Business Services",
            "type":"Services"
        }
    ],
    "sg:phone":"+1 410 889 1561",
    "sg:postcode":"21211",
    "sg:province":"MD",
    "sg:tags":[
        "consultant",
        "coach"
    ],
    "wof:name":"Patchwork Consulting",
    "wof:placetype":"venue"
},
  "geometry": {"coordinates":[-76.632706,39.331792],"type":"Point"}
}