{
  "type": "Feature",
  "properties": {
    "addr:full":"2630 Hafer St Baltimore MD 21223",
    "addr:housenumber":"2630",
    "addr:postcode":"21223",
    "addr:street":"Hafer St",
    "iso:country":"US",
    "sg:address":"2630 Hafer St",
    "sg:city":"Baltimore",
    "sg:classifiers":[
        {
            "category":"Manufacturing",
            "subcategory":"Metals",
            "type":"Manufacturing & Wholesale Goods"
        }
    ],
    "sg:phone":"+1 410 566 3400",
    "sg:postcode":"21223",
    "sg:province":"MD",
    "sg:tags":[
        "steel",
        "window",
        "door",
        "storm"
    ],
    "wof:name":"Eckart George A Inc",
    "wof:placetype":"venue"
},
  "geometry": {"coordinates":[-76.658502,39.283063],"type":"Point"}
}