{
  "type": "Feature",
  "properties": {
    "addr:full":"4700 Stamp Rd Temple Hills MD 20748",
    "addr:postcode":"4700;20748",
    "addr:street":"Stamp Rd",
    "iso:country":"US",
    "sg:address":"4700 Stamp Rd",
    "sg:city":"Temple Hills",
    "sg:classifiers":[
        {
            "category":"Personal",
            "subcategory":"Barber",
            "type":"Services"
        }
    ],
    "sg:phone":"+1 301 316 1665",
    "sg:postcode":"20748",
    "sg:province":"MD",
    "wof:name":"Executive Barber Shop & Salon",
    "wof:placetype":"venue"
},
  "geometry": {"coordinates":[-76.942801,38.825436],"type":"Point"}
}