{
  "type": "Feature",
  "properties": {
    "addr:full":"322 Prospect Bay Dr W Grasonville MD 21638",
    "addr:housenumber":"322",
    "addr:postcode":"21638",
    "addr:street":"Prospect Bay Dr W",
    "iso:country":"US",
    "sg:address":"322 Prospect Bay Dr W",
    "sg:city":"Grasonville",
    "sg:classifiers":[
        {
            "category":"Home & Garden",
            "subcategory":"Home Furnishings",
            "type":"Retail Goods"
        },
        {
            "category":"Wholesale",
            "subcategory":"Home Furnishings",
            "type":"Manufacturing & Wholesale Goods"
        }
    ],
    "sg:phone":"+1 410 827 4388",
    "sg:postcode":"21638",
    "sg:province":"MD",
    "sg:tags":[
        "fixture",
        "lamp",
        "lighting",
        "shade"
    ],
    "wof:name":"Miltec Corporation",
    "wof:placetype":"venue"
},
  "geometry": {"coordinates":[-76.19453,38.914265],"type":"Point"}
}