{
  "type": "Feature",
  "properties": {
    "addr:full":"14905 Village Gate Dr Silver Spring MD 20906",
    "addr:housenumber":"14905",
    "addr:postcode":"20906",
    "addr:street":"Village Gate Dr",
    "iso:country":"US",
    "sg:address":"14905 Village Gate Dr",
    "sg:city":"Silver Spring",
    "sg:classifiers":[
        {
            "category":"Personal",
            "type":"Services"
        },
        {
            "category":"Food & Beverages",
            "subcategory":"Bakery",
            "type":"Retail Goods"
        }
    ],
    "sg:phone":"+1 301 598 3737",
    "sg:postcode":"20906",
    "sg:province":"MD",
    "sg:tags":[
        "baker"
    ],
    "sg:website":"www.matasconfections.com",
    "wof:name":"Mata's Confections",
    "wof:placetype":"venue"
},
  "geometry": {"coordinates":[-77.043807,39.098338],"type":"Point"}
}