{
  "type": "Feature",
  "properties": {
    "addr:full":"207 Amberfield Ln Gaithersburg MD 20878",
    "addr:housenumber":"207",
    "addr:postcode":"20878",
    "addr:street":"Amberfield Ln",
    "iso:country":"US",
    "sg:address":"207 Amberfield Ln",
    "sg:city":"Gaithersburg",
    "sg:classifiers":[
        {
            "category":"Manufacturing",
            "subcategory":"Printing",
            "type":"Manufacturing & Wholesale Goods"
        },
        {
            "category":"Shopping",
            "subcategory":"Musical Instruments",
            "type":"Retail Goods"
        }
    ],
    "sg:phone":"+1 301 330 3469",
    "sg:postcode":"20878",
    "sg:province":"MD",
    "sg:tags":[
        "publisher",
        "music"
    ],
    "wof:name":"Kerner Songs Music Group",
    "wof:placetype":"venue"
},
  "geometry": {"coordinates":[-77.21679899999999,39.112349],"type":"Point"}
}