{
  "type": "Feature",
  "properties": {
    "iso:country":"US",
    "sg:address":"2600 Insulator Dr",
    "sg:city":"Baltimore",
    "sg:classifiers":[
        {
            "category":"Autos & Motor Vehicles",
            "subcategory":"Boat Sales",
            "type":"Retail Goods"
        }
    ],
    "sg:phone":"+1 410 547 2550",
    "sg:postcode":"21230",
    "sg:province":"MD",
    "sg:tags":[
        "dealer",
        "sales"
    ],
    "wof:name":"Downtown Marine Scout Boats",
    "wof:placetype":"venue"
},
  "geometry": {"coordinates":[-76.613461,39.261943],"type":"Point"}
}