{
  "type": "Feature",
  "properties": {
    "addr:full":"4301 Garden City Dr Hyattsville MD 20785",
    "addr:housenumber":"4301",
    "addr:postcode":"20785",
    "addr:street":"Garden City Dr",
    "iso:country":"US",
    "sg:address":"4301 Garden City Dr",
    "sg:city":"Hyattsville",
    "sg:classifiers":[
        {
            "category":"Organizations",
            "subcategory":"Professional Association",
            "type":"Services"
        }
    ],
    "sg:phone":"+1 301 577 4888",
    "sg:postcode":"20785",
    "sg:province":"MD",
    "wof:name":"Joint Labor Management Cmmtt",
    "wof:placetype":"venue"
},
  "geometry": {"coordinates":[-76.86716,38.949491],"type":"Point"}
}