{
  "type": "Feature",
  "properties": {
    "iso:country":"US",
    "sg:address":"20409 Highland Hall Dr",
    "sg:city":"Montgomery Village",
    "sg:classifiers":[
        {
            "category":"Manufacturing",
            "subcategory":"Jewelry",
            "type":"Manufacturing & Wholesale Goods"
        }
    ],
    "sg:phone":"+1 301 948 8512",
    "sg:postcode":"20886",
    "sg:province":"MD",
    "sg:tags":[
        "antique",
        "costume",
        "mfg"
    ],
    "wof:name":"Designs By Irene Inc",
    "wof:placetype":"venue"
},
  "geometry": {"coordinates":[-77.18674,39.191737],"type":"Point"}
}