{
  "type": "Feature",
  "properties": {
    "iso:country":"US",
    "sg:address":"23118 Silverberry Way",
    "sg:city":"California",
    "sg:classifiers":[
        {
            "category":"Recreation",
            "type":"Entertainment"
        }
    ],
    "sg:phone":"+1 301 481 0022",
    "sg:postcode":"20619",
    "sg:province":"MD",
    "sg:tags":[
        "entertainers-family",
        "business"
    ],
    "wof:name":"Thats Rentertainment",
    "wof:placetype":"venue"
},
  "geometry": {"coordinates":[-76.55758,38.300162],"type":"Point"}
}