{
  "type": "Feature",
  "properties": {
    "iso:country":"US",
    "sg:address":"4424 Montgomery Ave",
    "sg:city":"Bethesda",
    "sg:classifiers":[
        {
            "category":"Professional",
            "subcategory":"Accounting & Tax Preparation",
            "type":"Services"
        }
    ],
    "sg:phone":"+1 301 652 6380",
    "sg:postcode":"20814",
    "sg:province":"MD",
    "sg:tags":[
        "accountant"
    ],
    "wof:name":"Fishman Barry S CPA",
    "wof:placetype":"venue"
},
  "geometry": {"coordinates":[-77.08869900000001,38.984299],"type":"Point"}
}