{
  "type": "Feature",
  "properties": {
    "iso:country":"US",
    "sg:address":"1233 W Mount Royal Ave",
    "sg:city":"Baltimore",
    "sg:classifiers":[
        {
            "category":"Real Estate",
            "subcategory":"Real Estate Operator",
            "type":"Services"
        },
        {
            "category":"Building & Trades",
            "subcategory":"Construction",
            "type":"Services"
        }
    ],
    "sg:phone":"+1 410 727 4586",
    "sg:postcode":"21217",
    "sg:province":"MD",
    "sg:tags":[
        "apartment",
        "contractor"
    ],
    "wof:name":"Mt Royal Building Co",
    "wof:placetype":"venue"
},
  "geometry": {"coordinates":[-76.620598,39.307301],"type":"Point"}
}