{
  "type": "Feature",
  "properties": {
    "addr:full":"10423 Armory Ave Kensington MD 20895",
    "addr:housenumber":"10423",
    "addr:postcode":"20895",
    "addr:street":"Armory Ave",
    "iso:country":"US",
    "sg:address":"10423 Armory Ave",
    "sg:city":"Kensington",
    "sg:classifiers":[
        {
            "category":"Personal",
            "type":"Services"
        }
    ],
    "sg:phone":"+1 301 933 8700",
    "sg:postcode":"20895",
    "sg:province":"MD",
    "sg:tags":[
        "therapist",
        "massage"
    ],
    "wof:name":"Core",
    "wof:placetype":"venue"
},
  "geometry": {"coordinates":[-77.07454,39.02796],"type":"Point"}
}