{
  "type": "Feature",
  "properties": {
    "addr:full":"10 Council Dr Woodsboro MD 21798",
    "addr:housenumber":"10",
    "addr:postcode":"21798",
    "addr:street":"Council Dr",
    "iso:country":"US",
    "sg:address":"10 Council Dr",
    "sg:city":"Woodsboro",
    "sg:classifiers":[
        {
            "category":"Freight",
            "type":"Transportation"
        }
    ],
    "sg:phone":"+1 301 898 9046",
    "sg:postcode":"21798",
    "sg:province":"MD",
    "sg:tags":[
        "commercial",
        "storage"
    ],
    "wof:name":"Advantage Self Storge",
    "wof:placetype":"venue"
},
  "geometry": {"coordinates":[-77.30592799999999,39.528943],"type":"Point"}
}