{
  "type": "Feature",
  "properties": {
    "addr:full":"9475 Lottsford Rd Upper Marlboro MD 20774",
    "addr:housenumber":"9475",
    "addr:postcode":"20774",
    "addr:street":"Lottsford Rd",
    "iso:country":"US",
    "sg:address":"9475 Lottsford Rd",
    "sg:city":"Upper Marlboro",
    "sg:classifiers":[
        {
            "category":"Banks & Credit Unions",
            "subcategory":"Bank",
            "type":"Services"
        }
    ],
    "sg:phone":"+1 301 636 6050",
    "sg:postcode":"20774",
    "sg:province":"MD",
    "sg:tags":[
        "loan",
        "real estate"
    ],
    "wof:name":"Residential Morgtage Broker",
    "wof:placetype":"venue"
},
  "geometry": {"coordinates":[-76.841399,38.905687],"type":"Point"}
}