{
  "type": "Feature",
  "properties": {
    "iso:country":"US",
    "sg:address":"1118 Resden Run",
    "sg:city":"Salisbury",
    "sg:classifiers":[
        {
            "category":"Shopping",
            "type":"Retail Goods"
        },
        {
            "category":"Shopping",
            "subcategory":"Gifts & Souvenirs",
            "type":"Retail Goods"
        }
    ],
    "sg:phone":"+1 410 749 8100",
    "sg:postcode":"21804",
    "sg:province":"MD",
    "sg:tags":[
        "trophy",
        "medal",
        "award"
    ],
    "wof:name":"Bubba's Place",
    "wof:placetype":"venue"
},
  "geometry": {"coordinates":[-75.55973899999999,38.338505],"type":"Point"}
}