{
  "type": "Feature",
  "properties": {
    "iso:country":"US",
    "sg:address":"2400 Boston St",
    "sg:city":"Baltimore",
    "sg:classifiers":[
        {
            "category":"Bars & Pubs",
            "type":"Food & Drink"
        },
        {
            "category":"Restaurant",
            "type":"Food & Drink"
        },
        {
            "category":"Bars & Pubs",
            "subcategory":"Lounge",
            "type":"Food & Drink"
        }
    ],
    "sg:phone":"+1 410 327 9889",
    "sg:postcode":"21224",
    "sg:province":"MD",
    "sg:tags":[
        "continental",
        "american",
        "cocktail",
        "new"
    ],
    "wof:name":"Kiss Cafe",
    "wof:placetype":"venue"
},
  "geometry": {"coordinates":[-76.582397,39.281898],"type":"Point"}
}