{
  "type": "Feature",
  "properties": {
    "addr:full":"1008 Leslie Ave. Catonsville MD 21228",
    "addr:housenumber":"1008",
    "addr:postcode":"21228",
    "addr:street":"Leslie Ave.",
    "iso:country":"US",
    "sg:address":"1008 Leslie Ave.",
    "sg:city":"Catonsville",
    "sg:classifiers":[
        {
            "category":"Personal",
            "type":"Services"
        }
    ],
    "sg:phone":"+1 410 690 5266",
    "sg:postcode":"21228",
    "sg:province":"MD",
    "sg:tags":[
        "towing"
    ],
    "sg:website":"romerotowingservices.com/",
    "wof:name":"Romero Towing LLC",
    "wof:placetype":"venue"
},
  "geometry": {"coordinates":[-76.751293,39.284831],"type":"Point"}
}