{
  "type": "Feature",
  "properties": {
    "iso:country":"US",
    "sg:address":"7 W Eager St",
    "sg:city":"Baltimore",
    "sg:classifiers":[
        {
            "category":"Food & Beverages",
            "subcategory":"Supermarket",
            "type":"Retail Goods"
        }
    ],
    "sg:phone":"+1 410 547 1565",
    "sg:postcode":"21201",
    "sg:province":"MD",
    "sg:tags":[
        "super",
        "store"
    ],
    "wof:name":"Super Market Billing Inc",
    "wof:placetype":"venue"
},
  "geometry": {"coordinates":[-76.61660000000001,39.30098],"type":"Point"}
}