{
  "type": "Feature",
  "properties": {
    "iso:country":"US",
    "sg:address":"5601 Sunnyside Ave",
    "sg:city":"Beltsville",
    "sg:classifiers":[
        {
            "category":"Government",
            "subcategory":"Office",
            "type":"Public Place"
        }
    ],
    "sg:phone":"+1 301 504 9605",
    "sg:postcode":"20705",
    "sg:province":"MD",
    "sg:tags":[
        "agency"
    ],
    "wof:name":"Food Safety Education",
    "wof:placetype":"venue"
},
  "geometry": {"coordinates":[-76.909761,39.023106],"type":"Point"}
}