{
  "type": "Feature",
  "properties": {
    "addr:full":"7901 Garland Ave Takoma Park MD 20912",
    "addr:housenumber":"7901",
    "addr:postcode":"20912",
    "addr:street":"Garland Ave",
    "iso:country":"US",
    "sg:address":"7901 Garland Ave",
    "sg:city":"Takoma Park",
    "sg:classifiers":[
        {
            "category":"Professional",
            "subcategory":"Lawyer & Legal Services",
            "type":"Services"
        }
    ],
    "sg:phone":"+1 301 589 5449",
    "sg:postcode":"20912",
    "sg:province":"MD",
    "sg:tags":[
        "attorney"
    ],
    "wof:name":"Buonanno Law Office",
    "wof:placetype":"venue"
},
  "geometry": {"coordinates":[-76.998634,38.989463],"type":"Point"}
}