{
  "type": "Feature",
  "properties": {
    "addr:full":"2501 Springhill Ave Baltimore MD 21215",
    "addr:housenumber":"2501",
    "addr:postcode":"21215",
    "addr:street":"Springhill Ave",
    "iso:country":"US",
    "sg:address":"2501 Springhill Ave",
    "sg:city":"Baltimore",
    "sg:classifiers":[
        {
            "category":"Social Services",
            "type":"Services"
        },
        {
            "category":"Personal",
            "type":"Services"
        }
    ],
    "sg:phone":"+1 410 664 7860",
    "sg:postcode":"21215",
    "sg:province":"MD",
    "sg:tags":[
        "family",
        "counselors-licensed",
        "individual",
        "marriage",
        "child",
        "professional",
        "counselor"
    ],
    "wof:name":"Delta Family Support Ctr",
    "wof:placetype":"venue"
},
  "geometry": {"coordinates":[-76.658238,39.333144],"type":"Point"}
}