{
  "type": "Feature",
  "properties": {
    "addr:full":"8009 Darcy Rd Forestville MD 20747",
    "addr:housenumber":"8009",
    "addr:postcode":"20747",
    "addr:street":"Darcy Rd",
    "iso:country":"US",
    "sg:address":"8009 Darcy Rd",
    "sg:city":"Forestville",
    "sg:classifiers":[
        {
            "category":"Building & Trades",
            "subcategory":"Construction",
            "type":"Services"
        }
    ],
    "sg:phone":"+1 301 499 7155",
    "sg:postcode":"20747",
    "sg:province":"MD",
    "sg:tags":[
        "wallpaper"
    ],
    "wof:name":"J J Pyles Wallcovering Inc",
    "wof:placetype":"venue"
},
  "geometry": {"coordinates":[-76.864272,38.858734],"type":"Point"}
}