{
  "type": "Feature",
  "properties": {
    "iso:country":"US",
    "sg:address":"1010 S Beechfield Ave",
    "sg:city":"Baltimore",
    "sg:classifiers":[
        {
            "category":"Manufacturing",
            "subcategory":"Metals",
            "type":"Manufacturing & Wholesale Goods"
        }
    ],
    "sg:phone":"+1 410 737 0421",
    "sg:postcode":"21229",
    "sg:province":"MD",
    "sg:tags":[
        "working",
        "custom"
    ],
    "wof:name":"Hu/Mer Custom Rails",
    "wof:placetype":"venue"
},
  "geometry": {"coordinates":[-76.68817900000001,39.264385],"type":"Point"}
}