{
  "type": "Feature",
  "properties": {
    "iso:country":"US",
    "sg:address":"8454 Athol Rd",
    "sg:city":"Mardela Springs",
    "sg:classifiers":[
        {
            "category":"Building & Trades",
            "subcategory":"Construction",
            "type":"Services"
        }
    ],
    "sg:phone":"+1 443 260 2988",
    "sg:postcode":"21837",
    "sg:province":"MD",
    "sg:tags":[
        "home",
        "improvement"
    ],
    "wof:name":"Home Improvements & More",
    "wof:placetype":"venue"
},
  "geometry": {"coordinates":[-75.789186,38.427408],"type":"Point"}
}