{
  "type": "Feature",
  "properties": {
    "addr:full":"11215 New Hampshire Ave Silver Spring MD 20904",
    "addr:housenumber":"11215",
    "addr:postcode":"20904",
    "addr:street":"New Hampshire Ave",
    "iso:country":"US",
    "sg:address":"11215 New Hampshire Ave",
    "sg:city":"Silver Spring",
    "sg:classifiers":[
        {
            "category":"Cinema",
            "subcategory":"Movie Rental",
            "type":"Entertainment"
        }
    ],
    "sg:phone":"+1 301 681 2853",
    "sg:postcode":"20904",
    "sg:province":"MD",
    "sg:tags":[
        "leasing",
        "video",
        "disc",
        "tape"
    ],
    "wof:name":"Blockbuster Video",
    "wof:placetype":"venue"
},
  "geometry": {"coordinates":[-76.991496,39.042129],"type":"Point"}
}