{
  "type": "Feature",
  "properties": {
    "iso:country":"US",
    "sg:address":"19600 Frederick Rd",
    "sg:city":"Germantown",
    "sg:classifiers":[
        {
            "category":"Wholesale",
            "subcategory":"Painting Supplies",
            "type":"Manufacturing & Wholesale Goods"
        },
        {
            "category":"Retail",
            "subcategory":"Repair Shop",
            "type":"Services"
        },
        {
            "category":"Home & Garden",
            "subcategory":"Hardware",
            "type":"Retail Goods"
        },
        {
            "category":"Home & Garden",
            "subcategory":"Building Materials",
            "type":"Retail Goods"
        },
        {
            "category":"Wholesale",
            "subcategory":"Hardware",
            "type":"Manufacturing & Wholesale Goods"
        },
        {
            "category":"Home & Garden",
            "subcategory":"Garden Supply",
            "type":"Retail Goods"
        }
    ],
    "sg:phone":"+1 301 428 3200",
    "sg:postcode":"20876",
    "sg:province":"MD",
    "sg:tags":[
        "renting",
        "lawn",
        "outdoor",
        "power",
        "equipment",
        "equipment-sales",
        "landscaping",
        "saw",
        "paint",
        "store"
    ],
    "sg:website":"http://www.stihlusa.com/",
    "wof:name":"N & S Rentals Inc.",
    "wof:placetype":"venue"
},
  "geometry": {"coordinates":[-77.23848700000001,39.17767],"type":"Point"}
}