{
  "type": "Feature",
  "properties": {
    "addr:full":"831 Middlesex Rd Essex MD 21221",
    "addr:housenumber":"831",
    "addr:postcode":"21221",
    "addr:street":"Middlesex Rd",
    "iso:country":"US",
    "sg:address":"831 Middlesex Rd",
    "sg:city":"Essex",
    "sg:classifiers":[
        {
            "category":"Building & Trades",
            "subcategory":"Plumbing",
            "type":"Services"
        }
    ],
    "sg:phone":"+1 410 682 9682",
    "sg:postcode":"21221",
    "sg:province":"MD",
    "sg:tags":[
        "plumbing",
        "contractor"
    ],
    "wof:name":"Hayes-Osborne Plumbing & Htg",
    "wof:placetype":"venue"
},
  "geometry": {"coordinates":[-76.456945,39.327425],"type":"Point"}
}