{
  "type": "Feature",
  "properties": {
    "addr:full":"9530 Philadelphia Rd Rosedale MD 21237",
    "addr:housenumber":"9530",
    "addr:postcode":"21237",
    "addr:street":"Philadelphia Rd",
    "iso:country":"US",
    "sg:address":"9530 Philadelphia Rd",
    "sg:city":"Rosedale",
    "sg:classifiers":[
        {
            "category":"Shopping",
            "type":"Retail Goods"
        }
    ],
    "sg:phone":"+1 410 866 2733",
    "sg:postcode":"21237",
    "sg:province":"MD",
    "sg:tags":[
        "pet",
        "shop"
    ],
    "wof:name":"Afishion Ados Inc",
    "wof:placetype":"venue"
},
  "geometry": {"coordinates":[-76.460759,39.355576],"type":"Point"}
}