{
  "type": "Feature",
  "properties": {
    "addr:full":"1700 Piney Creek Rd Chester MD 21619",
    "addr:housenumber":"1700",
    "addr:postcode":"21619",
    "addr:street":"Piney Creek Rd",
    "iso:country":"US",
    "sg:address":"1700 Piney Creek Rd",
    "sg:city":"Chester",
    "sg:classifiers":[
        {
            "category":"Building & Trades",
            "subcategory":"Construction",
            "type":"Services"
        }
    ],
    "sg:phone":"+1 410 643 5555",
    "sg:postcode":"21619",
    "sg:province":"MD",
    "sg:tags":[
        "excavating",
        "contractor"
    ],
    "wof:name":"R T Bell Excavation",
    "wof:placetype":"venue"
},
  "geometry": {"coordinates":[-76.28743299999999,38.978373],"type":"Point"}
}