{
  "type": "Feature",
  "properties": {
    "iso:country":"US",
    "sg:address":"8109 Harford Rd",
    "sg:city":"Baltimore",
    "sg:classifiers":[
        {
            "category":"Health Services",
            "subcategory":"Doctor",
            "type":"Services"
        }
    ],
    "sg:phone":"+1 410 668 2404",
    "sg:postcode":"21234",
    "sg:province":"MD",
    "sg:tags":[
        "physician",
        "surgeon"
    ],
    "wof:name":"PGL Family Care",
    "wof:placetype":"venue"
},
  "geometry": {"coordinates":[-76.53976299999999,39.37742],"type":"Point"}
}