{
  "type": "Feature",
  "properties": {
    "iso:country":"US",
    "sg:address":"5110 Ridgefield Rd",
    "sg:city":"Bethesda",
    "sg:classifiers":[
        {
            "category":"Retail",
            "subcategory":"Portrait Studio",
            "type":"Services"
        }
    ],
    "sg:phone":"+1 301 652 9577",
    "sg:postcode":"20816",
    "sg:province":"MD",
    "sg:tags":[
        "photographer"
    ],
    "sg:website":"www.glogau.com",
    "wof:name":"Glogau Studio",
    "wof:placetype":"venue"
},
  "geometry": {"coordinates":[-77.106091,38.966221],"type":"Point"}
}