{
  "type": "Feature",
  "properties": {
    "iso:country":"US",
    "sg:address":"9818 Liberty Rd",
    "sg:city":"Randallstown",
    "sg:classifiers":[
        {
            "category":"Professional",
            "subcategory":"Management & Consulting",
            "type":"Services"
        }
    ],
    "sg:phone":"+1 410 496 4318",
    "sg:postcode":"21133",
    "sg:province":"MD",
    "sg:tags":[
        "consultant",
        "educational"
    ],
    "sg:website":"www.simplychildren.com",
    "wof:name":"Simply Children Inc",
    "wof:placetype":"venue"
},
  "geometry": {"coordinates":[-76.82063599999999,39.379982],"type":"Point"}
}