{
  "type": "Feature",
  "properties": {
    "addr:full":"1462 Desoto Rd Baltimore MD 21230",
    "addr:housenumber":"1462",
    "addr:postcode":"21230",
    "addr:street":"Desoto Rd",
    "iso:country":"US",
    "sg:address":"1462 Desoto Rd",
    "sg:city":"Baltimore",
    "sg:classifiers":[
        {
            "category":"Wholesale",
            "subcategory":"Construction Materials",
            "type":"Manufacturing & Wholesale Goods"
        }
    ],
    "sg:phone":"+1 410 525 8300",
    "sg:postcode":"21230",
    "sg:province":"MD",
    "sg:tags":[
        "concrete",
        "form"
    ],
    "wof:name":"Durand Forms Inc",
    "wof:placetype":"venue"
},
  "geometry": {"coordinates":[-76.658928,39.267788],"type":"Point"}
}