{
  "type": "Feature",
  "properties": {
    "addr:full":"7114 Bowers Rd Frederick MD 21702",
    "addr:housenumber":"7114",
    "addr:postcode":"21702",
    "addr:street":"Bowers Rd",
    "iso:country":"US",
    "sg:address":"7114 Bowers Rd",
    "sg:city":"Frederick",
    "sg:classifiers":[
        {
            "category":"Building & Trades",
            "subcategory":"Cleaning & Sanitation",
            "type":"Services"
        }
    ],
    "sg:phone":"+1 301 473 7938",
    "sg:postcode":"21702",
    "sg:province":"MD",
    "sg:tags":[
        "maintenance"
    ],
    "wof:name":"Shirls Janitorial Service",
    "wof:placetype":"venue"
},
  "geometry": {"coordinates":[-77.47398099999999,39.429385],"type":"Point"}
}