{
  "type": "Feature",
  "properties": {
    "addr:full":"218 Highland Ave Rockville MD 20850",
    "addr:housenumber":"218",
    "addr:postcode":"20850",
    "addr:street":"Highland Ave",
    "iso:country":"US",
    "sg:address":"218 Highland Ave",
    "sg:city":"Rockville",
    "sg:classifiers":[
        {
            "category":"Real Estate",
            "subcategory":"Architect",
            "type":"Services"
        }
    ],
    "sg:phone":"+1 301 424 5934",
    "sg:postcode":"20850",
    "sg:province":"MD",
    "wof:name":"Thomas J Taltavull",
    "wof:placetype":"venue"
},
  "geometry": {"coordinates":[-77.14321,39.085033],"type":"Point"}
}