{
  "type": "Feature",
  "properties": {
    "iso:country":"US",
    "sg:address":"916 Morris Ave",
    "sg:city":"Lutherville",
    "sg:classifiers":[
        {
            "category":"Autos & Motor Vehicles",
            "subcategory":"Automobile Sales",
            "type":"Retail Goods"
        },
        {
            "category":"Manufacturing",
            "subcategory":"Metals",
            "type":"Manufacturing & Wholesale Goods"
        }
    ],
    "sg:phone":"+1 410 560 7428",
    "sg:postcode":"21093",
    "sg:province":"MD",
    "sg:tags":[
        "product",
        "wire",
        "mfg",
        "fabricated",
        "race",
        "performance",
        "dealer"
    ],
    "wof:name":"James Robinson Racing Inc",
    "wof:placetype":"venue"
},
  "geometry": {"coordinates":[-76.63359199999999,39.432604],"type":"Point"}
}