{
  "type": "Feature",
  "properties": {
    "addr:full":"3361 75th Ave Ste F Hyattsville MD 20785",
    "addr:housenumber":"3361",
    "addr:postcode":"20785",
    "addr:street":"75Th Ave Ste F",
    "iso:country":"US",
    "sg:address":"3361 75th Ave Ste F",
    "sg:city":"Hyattsville",
    "sg:classifiers":[
        {
            "category":"Professional",
            "subcategory":"Business Services",
            "type":"Services"
        },
        {
            "category":"Government",
            "subcategory":"Post Office",
            "type":"Public Place"
        }
    ],
    "sg:phone":"+1 301 772 0225",
    "sg:postcode":"20785",
    "sg:province":"MD",
    "sg:tags":[
        "delivery",
        "messenger",
        "courier"
    ],
    "wof:name":"Manila Consulting Group Inc",
    "wof:placetype":"venue"
},
  "geometry": {"coordinates":[-76.88217,38.933907],"type":"Point"}
}