{
  "type": "Feature",
  "properties": {
    "addr:full":"4611 Assembly Dr Lanham MD 20706",
    "addr:housenumber":"4611",
    "addr:postcode":"20706",
    "addr:street":"Assembly Dr",
    "iso:country":"US",
    "sg:address":"4611 Assembly Dr",
    "sg:city":"Lanham",
    "sg:classifiers":[
        {
            "category":"Health Services",
            "subcategory":"Chiropractor",
            "type":"Services"
        }
    ],
    "sg:phone":"+1 240 296 3147",
    "sg:postcode":"20706",
    "sg:province":"MD",
    "wof:name":"Business Park Chiropractic",
    "wof:placetype":"venue"
},
  "geometry": {"coordinates":[-76.83054300000001,38.952707],"type":"Point"}
}