{
  "type": "Feature",
  "properties": {
    "addr:full":"8813 Orchard Tree Ln Baltimore MD 21286",
    "addr:housenumber":"8813",
    "addr:postcode":"21286",
    "addr:street":"Orchard Tree Ln",
    "iso:country":"US",
    "sg:address":"8813 Orchard Tree Ln",
    "sg:city":"Baltimore",
    "sg:classifiers":[
        {
            "category":"Personal",
            "subcategory":"Tanning Parlor",
            "type":"Services"
        }
    ],
    "sg:phone":"+1 410 828 4710",
    "sg:postcode":"21286",
    "sg:province":"MD",
    "sg:tags":[
        "salon"
    ],
    "wof:name":"Sahara Tanning",
    "wof:placetype":"venue"
},
  "geometry": {"coordinates":[-76.56907699999999,39.398854],"type":"Point"}
}