{
  "type": "Feature",
  "properties": {
    "addr:full":"2720 Pulaski Hwy Baltimore MD 21224",
    "addr:housenumber":"2720",
    "addr:postcode":"21224",
    "addr:street":"Pulaski Hwy",
    "iso:country":"US",
    "sg:address":"2720 Pulaski Hwy",
    "sg:city":"Baltimore",
    "sg:classifiers":[
        {
            "category":"Sports & Exercise",
            "subcategory":"Sports Center",
            "type":"Entertainment"
        }
    ],
    "sg:phone":"+1 410 342 1900",
    "sg:postcode":"21224",
    "sg:province":"MD",
    "sg:tags":[
        "amateur",
        "team"
    ],
    "wof:name":"Lazarus Center",
    "wof:placetype":"venue"
},
  "geometry": {"coordinates":[-76.578003,39.2948],"type":"Point"}
}