{
  "type": "Feature",
  "properties": {
    "addr:full":"2208 Nodleigh Ter Jarrettsville MD 21084",
    "addr:housenumber":"2208",
    "addr:postcode":"21084",
    "addr:street":"Nodleigh Ter",
    "iso:country":"US",
    "sg:address":"2208 Nodleigh Ter",
    "sg:city":"Jarrettsville",
    "sg:classifiers":[
        {
            "category":"Wholesale",
            "subcategory":"Machinery & Supplies",
            "type":"Manufacturing & Wholesale Goods"
        }
    ],
    "sg:phone":"+1 410 692 0400",
    "sg:postcode":"21084",
    "sg:province":"MD",
    "sg:tags":[
        "baling",
        "equipment"
    ],
    "wof:name":"Envinonmetal Recycling Svc Inc",
    "wof:placetype":"venue"
},
  "geometry": {"coordinates":[-76.499239,39.631965],"type":"Point"}
}