{
  "type": "Feature",
  "properties": {
    "addr:full":"1106 Churchview Pl Rockville MD 20854",
    "addr:housenumber":"1106",
    "addr:postcode":"20854",
    "addr:street":"Churchview Pl",
    "iso:country":"US",
    "sg:address":"1106 Churchview Pl",
    "sg:city":"Rockville",
    "sg:classifiers":[
        {
            "category":"Professional",
            "subcategory":"Business Services",
            "type":"Services"
        }
    ],
    "sg:phone":"+1 301 299 5841",
    "sg:postcode":"20854",
    "sg:province":"MD",
    "sg:tags":[
        "interior",
        "consultant",
        "design",
        "decorator"
    ],
    "wof:name":"Justine Sancho Interior Design",
    "wof:placetype":"venue"
},
  "geometry": {"coordinates":[-77.167723,39.070286],"type":"Point"}
}