{
  "type": "Feature",
  "properties": {
    "addr:full":"8101 Runnymeade Dr Frederick MD 21702",
    "addr:housenumber":"8101",
    "addr:postcode":"21702",
    "addr:street":"Runnymeade Dr",
    "iso:country":"US",
    "sg:address":"8101 Runnymeade Dr",
    "sg:city":"Frederick",
    "sg:classifiers":[
        {
            "category":"Professional",
            "subcategory":"Management & Consulting",
            "type":"Services"
        }
    ],
    "sg:phone":"+1 301 620 4290",
    "sg:postcode":"21702",
    "sg:province":"MD",
    "sg:tags":[
        "consultant",
        "security",
        "system"
    ],
    "wof:name":"Key Visual Solutions",
    "wof:placetype":"venue"
},
  "geometry": {"coordinates":[-77.423503,39.455391],"type":"Point"}
}