{
  "type": "Feature",
  "properties": {
    "iso:country":"US",
    "sg:address":"5816 Baltimore National Pike",
    "sg:city":"Catonsville",
    "sg:classifiers":[
        {
            "category":"Shopping",
            "subcategory":"Clothing, Apparel, & Fashions",
            "type":"Retail Goods"
        }
    ],
    "sg:phone":"+1 410 788 5580",
    "sg:postcode":"21228",
    "sg:province":"MD",
    "wof:name":"Fashion Cents Of Maryland",
    "wof:placetype":"venue"
},
  "geometry": {"coordinates":[-76.735044,39.287402],"type":"Point"}
}