{
  "type": "Feature",
  "properties": {
    "addr:full":"1820 Portal St Baltimore MD 21224",
    "addr:housenumber":"1820",
    "addr:postcode":"21224",
    "addr:street":"Portal St",
    "iso:country":"US",
    "sg:address":"1820 Portal St",
    "sg:city":"Baltimore",
    "sg:classifiers":[
        {
            "category":"Manufacturing",
            "subcategory":"Paper Products",
            "type":"Manufacturing & Wholesale Goods"
        }
    ],
    "sg:phone":"+1 212 382 1100",
    "sg:postcode":"21224",
    "sg:province":"MD",
    "sg:tags":[
        "impact",
        "printer",
        "converter",
        "envelope",
        "high",
        "colo"
    ],
    "wof:name":"Mail-Well",
    "wof:placetype":"venue"
},
  "geometry": {"coordinates":[-76.535079,39.270891],"type":"Point"}
}