{
  "type": "Feature",
  "properties": {
    "addr:full":"2315 Bel Air Rd Fallston MD 21047",
    "addr:postcode":"2315;21047",
    "addr:street":"Bel Air Rd",
    "iso:country":"US",
    "sg:address":"2315 Bel Air Rd",
    "sg:city":"Fallston",
    "sg:classifiers":[
        {
            "category":"Shopping",
            "subcategory":"Pharmacy",
            "type":"Retail Goods"
        }
    ],
    "sg:phone":"+1 410 877 7550",
    "sg:postcode":"21047",
    "sg:province":"MD",
    "sg:website":"www.cvs.com",
    "wof:name":"CVS Pharmacy",
    "wof:placetype":"venue"
},
  "geometry": {"coordinates":[-76.392786,39.492971],"type":"Point"}
}