{
  "type": "Feature",
  "properties": {
    "iso:country":"US",
    "sg:address":"3300 N Ridge Rd",
    "sg:city":"Ellicott City",
    "sg:classifiers":[
        {
            "category":"Professional",
            "subcategory":"Lawyer & Legal Services",
            "type":"Services"
        }
    ],
    "sg:phone":"+1 410 465 1110",
    "sg:postcode":"21043",
    "sg:province":"MD",
    "wof:name":"Gay Gerald F Atty",
    "wof:placetype":"venue"
},
  "geometry": {"coordinates":[-76.81729900000001,39.280499],"type":"Point"}
}