{
  "type": "Feature",
  "properties": {
    "iso:country":"US",
    "sg:address":"1404 Marlow Ct",
    "sg:city":"Bel Air",
    "sg:classifiers":[
        {
            "category":"Professional",
            "subcategory":"Computer Services",
            "type":"Services"
        }
    ],
    "sg:phone":"+1 410 893 0432",
    "sg:postcode":"21014",
    "sg:province":"MD",
    "sg:tags":[
        "programing",
        "custom"
    ],
    "wof:name":"PC Upgrade",
    "wof:placetype":"venue"
},
  "geometry": {"coordinates":[-76.335502,39.513249],"type":"Point"}
}