{
  "type": "Feature",
  "properties": {
    "addr:full":"307 E Broadway St Union Bridge MD 21791",
    "addr:housenumber":"307",
    "addr:postcode":"21791",
    "addr:street":"E Broadway St",
    "iso:country":"US",
    "sg:address":"307 E Broadway St",
    "sg:city":"Union Bridge",
    "sg:classifiers":[
        {
            "category":"Building & Trades",
            "subcategory":"Construction",
            "type":"Services"
        }
    ],
    "sg:phone":"+1 410 775 7404",
    "sg:postcode":"21791",
    "sg:province":"MD",
    "sg:tags":[
        "house"
    ],
    "wof:name":"Multi Phase Construction",
    "wof:placetype":"venue"
},
  "geometry": {"coordinates":[-77.172974,39.56826],"type":"Point"}
}