{
  "type": "Feature",
  "properties": {
    "addr:full":"527 Spruce Ave Westminster MD 21157",
    "addr:housenumber":"527",
    "addr:postcode":"21157",
    "addr:street":"Spruce Ave",
    "iso:country":"US",
    "sg:address":"527 Spruce Ave",
    "sg:city":"Westminster",
    "sg:classifiers":[
        {
            "category":"Professional",
            "subcategory":"Printing & Photocopies",
            "type":"Services"
        }
    ],
    "sg:phone":"+1 410 596 0987",
    "sg:postcode":"21157",
    "sg:province":"MD",
    "sg:tags":[
        "photographers-commercial"
    ],
    "wof:name":"Stacy Lee Fraizier Photography",
    "wof:placetype":"venue"
},
  "geometry": {"coordinates":[-76.974013,39.560704],"type":"Point"}
}