{
  "type": "Feature",
  "properties": {
    "addr:full":"1200 E 33rd St Baltimore MD 21218",
    "addr:housenumber":"1200",
    "addr:postcode":"21218",
    "addr:street":"E 33Rd St",
    "iso:country":"US",
    "sg:address":"1200 E 33rd St",
    "sg:city":"Baltimore",
    "sg:classifiers":[
        {
            "category":"Home & Garden",
            "subcategory":"Building Materials",
            "type":"Retail Goods"
        }
    ],
    "sg:phone":"+1 410 235 4706",
    "sg:postcode":"21218",
    "sg:province":"MD",
    "sg:tags":[
        "screen",
        "window"
    ],
    "wof:name":"Well Screen",
    "wof:placetype":"venue"
},
  "geometry": {"coordinates":[-76.599282,39.328523],"type":"Point"}
}