{
  "type": "Feature",
  "properties": {
    "addr:full":"961 Cloverfields Dr Stevensville MD 21666",
    "addr:housenumber":"961",
    "addr:postcode":"21666",
    "addr:street":"Cloverfields Dr",
    "iso:country":"US",
    "sg:address":"961 Cloverfields Dr",
    "sg:city":"Stevensville",
    "sg:classifiers":[
        {
            "category":"Professional",
            "subcategory":"Business Services",
            "type":"Services"
        }
    ],
    "sg:phone":"+1 410 643 8412",
    "sg:postcode":"21666",
    "sg:province":"MD",
    "wof:name":"AJS Computer Sales & Cnslts",
    "wof:placetype":"venue"
},
  "geometry": {"coordinates":[-76.30722,39.008487],"type":"Point"}
}