{
  "type": "Feature",
  "properties": {
    "iso:country":"US",
    "sg:address":"12110 Central Ave",
    "sg:city":"Mitchellville",
    "sg:classifiers":[
        {
            "category":"Retail",
            "subcategory":"Laundry & Dry Cleaning",
            "type":"Services"
        }
    ],
    "sg:phone":"+1 301 249 4018",
    "sg:postcode":"20721",
    "sg:province":"MD",
    "sg:tags":[
        "cleaners"
    ],
    "wof:name":"Central Cleaners",
    "wof:placetype":"venue"
},
  "geometry": {"coordinates":[-76.796785,38.899362],"type":"Point"}
}