{
  "type": "Feature",
  "properties": {
    "addr:full":"10834 Allen Ave Hagerstown MD 21740",
    "addr:housenumber":"10834",
    "addr:postcode":"21740",
    "addr:street":"Allen Ave",
    "iso:country":"US",
    "sg:address":"10834 Allen Ave",
    "sg:city":"Hagerstown",
    "sg:classifiers":[
        {
            "category":"Building & Trades",
            "subcategory":"Construction",
            "type":"Services"
        }
    ],
    "sg:phone":"+1 301 416 3344",
    "sg:postcode":"21740",
    "sg:province":"MD",
    "sg:tags":[
        "contractor"
    ],
    "wof:name":"Absolute Best Fence & Deck Co",
    "wof:placetype":"venue"
},
  "geometry": {"coordinates":[-77.76903900000001,39.6123],"type":"Point"}
}