{
  "type": "Feature",
  "properties": {
    "addr:full":"9616 Belair Rd Nottingham MD 21236",
    "addr:housenumber":"9616",
    "addr:postcode":"21236",
    "addr:street":"Belair Rd",
    "iso:country":"US",
    "sg:address":"9616 Belair Rd",
    "sg:city":"Nottingham",
    "sg:classifiers":[
        {
            "category":"Real Estate",
            "subcategory":"Real Estate Services",
            "type":"Services"
        },
        {
            "category":"Banks & Credit Unions",
            "subcategory":"Bank",
            "type":"Services"
        },
        {
            "category":"Banks & Credit Unions",
            "subcategory":"Financial Services",
            "type":"Services"
        }
    ],
    "sg:phone":"+1 410 256 5200",
    "sg:postcode":"21236",
    "sg:province":"MD",
    "sg:tags":[
        "loan",
        "processing"
    ],
    "sg:website":"http://www.rosedalefederal.com",
    "wof:name":"Rosedale Federal Savings/Loan",
    "wof:placetype":"venue"
},
  "geometry": {"coordinates":[-76.463364,39.413239],"type":"Point"}
}