{
  "type": "Feature",
  "properties": {
    "addr:full":"6320 Golden Triangle Dr Greenbelt MD 20770",
    "addr:housenumber":"6320",
    "addr:postcode":"20770",
    "addr:street":"Golden Triangle Dr",
    "iso:country":"US",
    "sg:address":"6320 Golden Triangle Dr",
    "sg:city":"Greenbelt",
    "sg:classifiers":[
        {
            "category":"Travel",
            "subcategory":"Hotels & Motels",
            "type":"Entertainment"
        }
    ],
    "sg:phone":"+1 301 982 1600",
    "sg:postcode":"20770",
    "sg:province":"MD",
    "sg:tags":[
        "hotels-apartment",
        "corporate",
        "lodging"
    ],
    "sg:website":"http://marriott.com/WASGL",
    "wof:name":"Residence Inn Greenbelt",
    "wof:placetype":"venue"
},
  "geometry": {"coordinates":[-76.896103,38.997533],"type":"Point"}
}