{
  "type": "Feature",
  "properties": {
    "iso:country":"US",
    "sg:address":"2002 Annapolis Mall",
    "sg:city":"Annapolis",
    "sg:classifiers":[
        {
            "category":"Home & Garden",
            "subcategory":"Home Furnishings",
            "type":"Retail Goods"
        }
    ],
    "sg:phone":"+1 410 573 4938",
    "sg:postcode":"21401",
    "sg:province":"MD",
    "sg:tags":[
        "bedding"
    ],
    "wof:name":"Pillow Pets",
    "wof:placetype":"venue"
},
  "geometry": {"coordinates":[-76.544083,38.99228],"type":"Point"}
}