{
  "type": "Feature",
  "properties": {
    "iso:country":"US",
    "sg:address":"4740 Chevy Chase Dr",
    "sg:city":"Chevy Chase",
    "sg:classifiers":[
        {
            "category":"Professional",
            "subcategory":"Accounting & Tax Preparation",
            "type":"Services"
        }
    ],
    "sg:phone":"+1 301 654 8677",
    "sg:postcode":"20815",
    "sg:province":"MD",
    "sg:tags":[
        "billing"
    ],
    "sg:website":"www.efconline.com",
    "wof:name":"Educational Funding Co",
    "wof:placetype":"venue"
},
  "geometry": {"coordinates":[-77.093311,38.976764],"type":"Point"}
}