{
  "type": "Feature",
  "properties": {
    "addr:full":"6500 Baltimore National Pike Catonsville MD 21228",
    "addr:housenumber":"6500",
    "addr:postcode":"21228",
    "addr:street":"Baltimore National Pike",
    "iso:country":"US",
    "sg:address":"6500 Baltimore National Pike",
    "sg:city":"Catonsville",
    "sg:classifiers":[
        {
            "category":"Restaurant",
            "type":"Food & Drink"
        }
    ],
    "sg:phone":"+1 410 788 5236",
    "sg:postcode":"21228",
    "sg:province":"MD",
    "wof:name":"KFC",
    "wof:placetype":"venue"
},
  "geometry": {"coordinates":[-76.769998,39.289092],"type":"Point"}
}