{
  "type": "Feature",
  "properties": {
    "iso:country":"US",
    "sg:address":"6235 Crain Hwy",
    "sg:city":"Upper Marlboro",
    "sg:classifiers":[
        {
            "category":"Professional",
            "subcategory":"Accounting & Tax Preparation",
            "type":"Services"
        }
    ],
    "sg:phone":"+1 301 627 2600",
    "sg:postcode":"20772",
    "sg:province":"MD",
    "sg:tags":[
        "return"
    ],
    "wof:name":"Debbies Tax Service Inc",
    "wof:placetype":"venue"
},
  "geometry": {"coordinates":[-76.746084,38.80586],"type":"Point"}
}