{
  "type": "Feature",
  "properties": {
    "iso:country":"US",
    "sg:address":"6022 Onondaga Rd",
    "sg:city":"Bethesda",
    "sg:classifiers":[
        {
            "category":"Professional",
            "subcategory":"Management & Consulting",
            "type":"Services"
        }
    ],
    "sg:phone":"+1 301 229 3399",
    "sg:postcode":"20816",
    "sg:province":"MD",
    "wof:name":"Alvin Sacks Inc",
    "wof:placetype":"venue"
},
  "geometry": {"coordinates":[-77.12495699999999,38.964856],"type":"Point"}
}