{
  "type": "Feature",
  "properties": {
    "addr:full":"1029 E Patapsco Ave Brooklyn MD 21225",
    "addr:housenumber":"1029",
    "addr:postcode":"21225",
    "addr:street":"E Patapsco Ave",
    "iso:country":"US",
    "sg:address":"1029 E Patapsco Ave",
    "sg:city":"Brooklyn",
    "sg:classifiers":[
        {
            "category":"Building & Trades",
            "subcategory":"Plumbing",
            "type":"Services"
        }
    ],
    "sg:phone":"+1 410 355 2290",
    "sg:postcode":"21225",
    "sg:province":"MD",
    "sg:tags":[
        "system",
        "mechanical",
        "contractor",
        "air conditioning"
    ],
    "wof:name":"Carter Mechanical",
    "wof:placetype":"venue"
},
  "geometry": {"coordinates":[-76.594815,39.234018],"type":"Point"}
}