{
  "type": "Feature",
  "properties": {
    "iso:country":"US",
    "sg:address":"534 E 43rd St",
    "sg:city":"Baltimore",
    "sg:classifiers":[
        {
            "category":"Personal",
            "subcategory":"Beauty Salon",
            "type":"Services"
        }
    ],
    "sg:phone":"+1 410 323 3442",
    "sg:postcode":"21212",
    "sg:province":"MD",
    "sg:tags":[
        "shop"
    ],
    "wof:name":"Monayes Head 2 Toe Buty Palace",
    "wof:placetype":"venue"
},
  "geometry": {"coordinates":[-76.60943899999999,39.341051],"type":"Point"}
}