{
  "type": "Feature",
  "properties": {
    "iso:country":"US",
    "sg:address":"7240 Chicamuxen Rd",
    "sg:city":"Indian Head",
    "sg:classifiers":[
        {
            "category":"Building & Trades",
            "subcategory":"Plumbing",
            "type":"Services"
        }
    ],
    "sg:phone":"+1 301 743 3536",
    "sg:postcode":"20640",
    "sg:province":"MD",
    "sg:tags":[
        "plumbing",
        "contractor"
    ],
    "wof:name":"Plumb Crazy Plumbing & Heating",
    "wof:placetype":"venue"
},
  "geometry": {"coordinates":[-77.230507,38.512005],"type":"Point"}
}