{
  "type": "Feature",
  "properties": {
    "addr:full":"300 S Burhans Blvd E Hagerstown MD 21740",
    "addr:housenumber":"300",
    "addr:postcode":"21740",
    "addr:street":"S Burhans Blvd E",
    "iso:country":"US",
    "sg:address":"300 S Burhans Blvd E",
    "sg:city":"Hagerstown",
    "sg:classifiers":[
        {
            "category":"Freight",
            "type":"Transportation"
        }
    ],
    "sg:phone":"+1 301 223 9100",
    "sg:postcode":"21740",
    "sg:province":"MD",
    "sg:tags":[
        "commercial",
        "storage"
    ],
    "wof:name":"Valley Storage Co",
    "wof:placetype":"venue"
},
  "geometry": {"coordinates":[-77.73486,39.64119],"type":"Point"}
}