{
  "type": "Feature",
  "properties": {
    "addr:full":"9500 Reach Rd Potomac MD 20854",
    "addr:postcode":"9500;20854",
    "addr:street":"Reach Rd",
    "iso:country":"US",
    "sg:address":"9500 Reach Rd",
    "sg:city":"Potomac",
    "sg:classifiers":[
        {
            "category":"Health Services",
            "subcategory":"Doctor",
            "type":"Services"
        }
    ],
    "sg:phone":"+1 301 545 0214",
    "sg:postcode":"20854",
    "sg:province":"MD",
    "sg:tags":[
        "clinic",
        "medical"
    ],
    "wof:name":"Jean Geschwind",
    "wof:placetype":"venue"
},
  "geometry": {"coordinates":[-77.196983,39.05545],"type":"Point"}
}