{
  "type": "Feature",
  "properties": {
    "addr:full":"10155 York Rd Cockysvl Hnt Vly MD 21030",
    "addr:housenumber":"10155",
    "addr:postcode":"21030",
    "addr:street":"York Rd;Hnt Vly",
    "iso:country":"US",
    "sg:address":"10155 York Rd",
    "sg:city":"Cockysvl Hnt Vly",
    "sg:classifiers":[
        {
            "category":"Manufacturing",
            "subcategory":"Printing",
            "type":"Manufacturing & Wholesale Goods"
        }
    ],
    "sg:phone":"+1 410 584 1900",
    "sg:postcode":"21030",
    "sg:province":"MD",
    "sg:tags":[
        "publisher"
    ],
    "sg:website":"www.networkpub.com",
    "wof:name":"Network Publications Inc",
    "wof:placetype":"venue"
},
  "geometry": {"coordinates":[-76.63757099999999,39.466924],"type":"Point"}
}