{
  "type": "Feature",
  "properties": {
    "addr:full":"1701 Eastern Blvd Essex MD 21221",
    "addr:housenumber":"1701",
    "addr:postcode":"21221",
    "addr:street":"Eastern Blvd",
    "iso:country":"US",
    "sg:address":"1701 Eastern Blvd",
    "sg:city":"Essex",
    "sg:classifiers":[
        {
            "category":"Professional",
            "subcategory":"Lawyer & Legal Services",
            "type":"Services"
        }
    ],
    "sg:phone":"+1 410 686 5258",
    "sg:postcode":"21221",
    "sg:province":"MD",
    "sg:tags":[
        "notary"
    ],
    "wof:name":"Norman's Tag & Title Service",
    "wof:placetype":"venue"
},
  "geometry": {"coordinates":[-76.451897,39.3218],"type":"Point"}
}