{
  "type": "Feature",
  "properties": {
    "addr:full":"9010 Pickwick Village Ter Silver Spring MD 20901",
    "addr:housenumber":"9010",
    "addr:postcode":"20901",
    "addr:street":"Pickwick Village Ter",
    "iso:country":"US",
    "sg:address":"9010 Pickwick Village Ter",
    "sg:city":"Silver Spring",
    "sg:classifiers":[
        {
            "category":"Professional",
            "subcategory":"Management & Consulting",
            "type":"Services"
        }
    ],
    "sg:phone":"+1 301 408 1351",
    "sg:postcode":"20901",
    "sg:province":"MD",
    "wof:name":"Sarah Davidson",
    "wof:placetype":"venue"
},
  "geometry": {"coordinates":[-76.998401,39.002791],"type":"Point"}
}