{
  "type": "Feature",
  "properties": {
    "iso:country":"US",
    "sg:address":"11 Ridgely Ave",
    "sg:city":"Annapolis",
    "sg:classifiers":[
        {
            "category":"Restaurant",
            "type":"Food & Drink"
        }
    ],
    "sg:menulink":"http://www.allmenus.com/md/annapolis/259736-canton-restaurant/menu/",
    "sg:phone":"+1 410 280 8658",
    "sg:postcode":"21401",
    "sg:province":"MD",
    "sg:tags":[
        "asian",
        "chinese"
    ],
    "wof:name":"Canton Restaurant",
    "wof:placetype":"venue"
},
  "geometry": {"coordinates":[-76.501963,38.988316],"type":"Point"}
}