{
  "type": "Feature",
  "properties": {
    "addr:full":"18140 Barnesville Rd Barnesville MD 20838",
    "addr:postcode":"18140;20838",
    "addr:street":"Barnesville Rd",
    "iso:country":"US",
    "sg:address":"18140 Barnesville Rd",
    "sg:city":"Barnesville",
    "sg:classifiers":[
        {
            "category":"Manufacturing",
            "subcategory":"Wood Products",
            "type":"Manufacturing & Wholesale Goods"
        }
    ],
    "sg:phone":"+1 301 972 8732",
    "sg:postcode":"20838",
    "sg:province":"MD",
    "sg:tags":[
        "millwork-wholesale",
        "manufacturer"
    ],
    "wof:name":"Barnesville Woodworking, Inc.",
    "wof:placetype":"venue"
},
  "geometry": {"coordinates":[-77.378151,39.220852],"type":"Point"}
}