{
  "type": "Feature",
  "properties": {
    "iso:country":"US",
    "sg:address":"609 Dutchmans Ln",
    "sg:city":"Easton",
    "sg:classifiers":[
        {
            "category":"Health Services",
            "subcategory":"Chiropractor",
            "type":"Services"
        }
    ],
    "sg:phone":"+1 410 763 6700",
    "sg:postcode":"21601",
    "sg:province":"MD",
    "wof:name":"Century Spine Ctr PC",
    "wof:placetype":"venue"
},
  "geometry": {"coordinates":[-76.063226,38.75978],"type":"Point"}
}