{
  "type": "Feature",
  "properties": {
    "addr:full":"7401 Main St Queenstown MD 21658",
    "addr:housenumber":"7401",
    "addr:postcode":"21658",
    "addr:street":"Main St",
    "iso:country":"US",
    "sg:address":"7401 Main St",
    "sg:city":"Queenstown",
    "sg:classifiers":[
        {
            "category":"Organizations",
            "subcategory":"Religious Organization",
            "type":"Services"
        }
    ],
    "sg:phone":"+1 410 827 6500",
    "sg:postcode":"21658",
    "sg:province":"MD",
    "sg:tags":[
        "church"
    ],
    "wof:name":"Shore Christian Fellowship",
    "wof:placetype":"venue"
},
  "geometry": {"coordinates":[-76.154353,38.990993],"type":"Point"}
}