{
  "type": "Feature",
  "properties": {
    "addr:full":"1407 Rome Rd Halethorpe MD 21227",
    "addr:housenumber":"1407",
    "addr:postcode":"21227",
    "addr:street":"Rome Rd",
    "iso:country":"US",
    "sg:address":"1407 Rome Rd",
    "sg:city":"Halethorpe",
    "sg:classifiers":[
        {
            "category":"Organizations",
            "subcategory":"Labor Organization",
            "type":"Services"
        }
    ],
    "sg:phone":"+1 410 737 9674",
    "sg:postcode":"21227",
    "sg:province":"MD",
    "wof:name":"Carpenters Dist Cncl",
    "wof:placetype":"venue"
},
  "geometry": {"coordinates":[-76.681372,39.260198],"type":"Point"}
}