{
  "type": "Feature",
  "properties": {
    "addr:full":"5018 Sidney Rd Mount Airy MD 21771",
    "addr:housenumber":"5018",
    "addr:postcode":"21771",
    "addr:street":"Sidney Rd",
    "iso:country":"US",
    "sg:address":"5018 Sidney Rd",
    "sg:city":"Mount Airy",
    "sg:classifiers":[
        {
            "category":"Building & Trades",
            "subcategory":"Landscaping Services",
            "type":"Services"
        }
    ],
    "sg:phone":"+1 301 831 7618",
    "sg:postcode":"21771",
    "sg:province":"MD",
    "sg:tags":[
        "landscape"
    ],
    "wof:name":"Schneider Enterprises Inc",
    "wof:placetype":"venue"
},
  "geometry": {"coordinates":[-77.187028,39.376057],"type":"Point"}
}