{
  "type": "Feature",
  "properties": {
    "iso:country":"US",
    "sg:address":"1213 Liberty Rd",
    "sg:city":"Sykesville",
    "sg:phone":"+1 410 549 4200",
    "sg:postcode":"21784",
    "sg:province":"MD",
    "wof:name":"Liberty Lanes",
    "wof:placetype":"venue"
},
  "geometry": {"coordinates":[-76.952811,39.404698],"type":"Point"}
}