{
  "type": "Feature",
  "properties": {
    "addr:full":"29270 Three Notch Rd Mechanicsville MD 20659",
    "addr:housenumber":"29270",
    "addr:postcode":"20659",
    "addr:street":"Three Notch Rd",
    "iso:country":"US",
    "sg:address":"29270 Three Notch Rd",
    "sg:city":"Mechanicsville",
    "sg:classifiers":[
        {
            "category":"Wholesale",
            "subcategory":"Machinery & Supplies",
            "type":"Manufacturing & Wholesale Goods"
        }
    ],
    "sg:phone":"+1 301 884 5780",
    "sg:postcode":"20659",
    "sg:province":"MD",
    "sg:tags":[
        "equipment",
        "welding"
    ],
    "wof:name":"Three Mules Welding Supplies",
    "wof:placetype":"venue"
},
  "geometry": {"coordinates":[-76.77070000000001,38.466774],"type":"Point"}
}