{
  "type": "Feature",
  "properties": {
    "addr:full":"4872 Montgomery Rd Ellicott City MD 21043",
    "addr:housenumber":"4872",
    "addr:postcode":"21043",
    "addr:street":"Montgomery Rd",
    "iso:country":"US",
    "sg:address":"4872 Montgomery Rd",
    "sg:city":"Ellicott City",
    "sg:classifiers":[
        {
            "category":"Professional",
            "subcategory":"Credit Reporting & Collection",
            "type":"Services"
        }
    ],
    "sg:phone":"+1 410 750 1733",
    "sg:postcode":"21043",
    "sg:province":"MD",
    "sg:tags":[
        "agency"
    ],
    "wof:name":"Worthington Moore & Jacobs",
    "wof:placetype":"venue"
},
  "geometry": {"coordinates":[-76.79877500000001,39.237128],"type":"Point"}
}