{
  "type": "Feature",
  "properties": {
    "addr:full":"431 Twin Oaks Rd Linthicum Heights MD 21090",
    "addr:housenumber":"431",
    "addr:postcode":"21090",
    "addr:street":"Twin Oaks Rd",
    "iso:country":"US",
    "sg:address":"431 Twin Oaks Rd",
    "sg:city":"Linthicum Heights",
    "sg:classifiers":[
        {
            "category":"Retail",
            "subcategory":"Auto Repair",
            "type":"Services"
        }
    ],
    "sg:phone":"+1 410 789 6879",
    "sg:postcode":"21090",
    "sg:province":"MD",
    "sg:tags":[
        "general"
    ],
    "wof:name":"Accurate Automotive Inc",
    "wof:placetype":"venue"
},
  "geometry": {"coordinates":[-76.654349,39.209353],"type":"Point"}
}