{
  "type": "Feature",
  "properties": {
    "iso:country":"US",
    "sg:address":"63 Devonshire Rd",
    "sg:city":"Hagerstown",
    "sg:classifiers":[
        {
            "category":"Building & Trades",
            "subcategory":"Pest Control",
            "type":"Services"
        }
    ],
    "sg:phone":"+1 301 791 5888",
    "sg:postcode":"21740",
    "sg:province":"MD",
    "wof:name":"X-Terminator Termite",
    "wof:placetype":"venue"
},
  "geometry": {"coordinates":[-77.738234,39.648838],"type":"Point"}
}