{
  "type": "Feature",
  "properties": {
    "iso:country":"US",
    "sg:address":"1830 Windjammer Way",
    "sg:city":"Gaithersburg",
    "sg:classifiers":[
        {
            "category":"Wholesale",
            "subcategory":"Books, Periodicals, & Newspapers",
            "type":"Manufacturing & Wholesale Goods"
        }
    ],
    "sg:phone":"+1 301 947 2641",
    "sg:postcode":"20879",
    "sg:province":"MD",
    "sg:tags":[
        "publishers-periodical"
    ],
    "sg:website":"http://www.brazilwatch.com",
    "wof:name":"Brazil Watch Publications",
    "wof:placetype":"venue"
},
  "geometry": {"coordinates":[-77.213354,39.162858],"type":"Point"}
}