{
  "type": "Feature",
  "properties": {
    "addr:full":"13625 Georgia Ave Silver Spring MD 20906",
    "addr:housenumber":"13625",
    "addr:postcode":"20906",
    "addr:street":"Georgia Ave",
    "iso:country":"US",
    "sg:address":"13625 Georgia Ave",
    "sg:city":"Silver Spring",
    "sg:classifiers":[
        {
            "category":"Restaurant",
            "type":"Food & Drink"
        }
    ],
    "sg:phone":"+1 301 929 6350",
    "sg:postcode":"20906",
    "sg:province":"MD",
    "wof:name":"Jjarchang Restaurant",
    "wof:placetype":"venue"
},
  "geometry": {"coordinates":[-77.0732,39.079289],"type":"Point"}
}