{
  "type": "Feature",
  "properties": {
    "addr:full":"589 Brethren Church Rd Accident MD 21520",
    "addr:housenumber":"589",
    "addr:postcode":"21520",
    "addr:street":"Church Rd",
    "iso:country":"US",
    "sg:address":"589 Brethren Church Rd",
    "sg:city":"Accident",
    "sg:phone":"+1 301 746 8355",
    "sg:postcode":"21520",
    "sg:province":"MD",
    "sg:tags":[
        "farm",
        "field",
        "corn",
        "crop"
    ],
    "wof:name":"Eugene Georg",
    "wof:placetype":"venue"
},
  "geometry": {"coordinates":[-79.310738,39.619637],"type":"Point"}
}