{
  "type": "Feature",
  "properties": {
    "iso:country":"US",
    "sg:address":"12001 Brightwood Dr",
    "sg:city":"Brandywine",
    "sg:classifiers":[
        {
            "category":"Professional",
            "subcategory":"Business Services",
            "type":"Services"
        }
    ],
    "sg:phone":"+1 301 372 6797",
    "sg:postcode":"20613",
    "sg:province":"MD",
    "wof:name":"Ralph Carroll Constructio",
    "wof:placetype":"venue"
},
  "geometry": {"coordinates":[-76.872416,38.725513],"type":"Point"}
}