{
  "type": "Feature",
  "properties": {
    "iso:country":"US",
    "sg:address":"203 Romancoke Rd",
    "sg:city":"Stevensville",
    "sg:classifiers":[
        {
            "category":"Insurance",
            "subcategory":"Insurance Agent",
            "type":"Services"
        },
        {
            "category":"Insurance",
            "subcategory":"Hazard Insurance",
            "type":"Services"
        },
        {
            "category":"Insurance",
            "subcategory":"Title Insurance",
            "type":"Services"
        },
        {
            "category":"Insurance",
            "subcategory":"Life Insurance",
            "type":"Services"
        }
    ],
    "sg:phone":"+1 410 643 8181",
    "sg:postcode":"21666",
    "sg:province":"MD",
    "sg:tags":[
        "business",
        "auto",
        "commercial",
        "homeowner",
        "motorcycle",
        "renter"
    ],
    "wof:name":"Allstate Insurance Company - Brian Burnell",
    "wof:placetype":"venue"
},
  "geometry": {"coordinates":[-76.324702,38.974444],"type":"Point"}
}