{
  "type": "Feature",
  "properties": {
    "iso:country":"US",
    "sg:address":"6132 Nest Side",
    "sg:city":"Columbia",
    "sg:classifiers":[
        {
            "category":"Social Services",
            "type":"Services"
        }
    ],
    "sg:phone":"+1 410 964 8660",
    "sg:postcode":"21045",
    "sg:province":"MD",
    "sg:tags":[
        "organization",
        "welfare"
    ],
    "wof:name":"Fish Of Howard County",
    "wof:placetype":"venue"
},
  "geometry": {"coordinates":[-76.830366,39.202964],"type":"Point"}
}