{
  "type": "Feature",
  "properties": {
    "iso:country":"US",
    "sg:address":"9315 Largo Dr W",
    "sg:city":"Upper Marlboro",
    "sg:classifiers":[
        {
            "category":"Real Estate",
            "subcategory":"Real Estate Services",
            "type":"Services"
        }
    ],
    "sg:phone":"+1 301 324 3007",
    "sg:postcode":"20774",
    "sg:province":"MD",
    "sg:tags":[
        "company",
        "title"
    ],
    "wof:name":"Integrity Title & Escrow",
    "wof:placetype":"venue"
},
  "geometry": {"coordinates":[-76.846373,38.898172],"type":"Point"}
}