{
  "type": "Feature",
  "properties": {
    "iso:country":"US",
    "sg:address":"423 Railroad Ave",
    "sg:city":"Centreville",
    "sg:phone":"+1 410 758 1200",
    "sg:postcode":"21617",
    "sg:province":"MD",
    "sg:tags":[
        "gas"
    ],
    "wof:name":"Suburban Propane",
    "wof:placetype":"venue"
},
  "geometry": {"coordinates":[-76.06089900000001,39.042062],"type":"Point"}
}