{
  "type": "Feature",
  "properties": {
    "addr:full":"345 Main St Gaithersburg MD 20878",
    "addr:housenumber":"345",
    "addr:postcode":"20878",
    "addr:street":"Main St",
    "iso:country":"US",
    "sg:address":"345 Main St",
    "sg:city":"Gaithersburg",
    "sg:classifiers":[
        {
            "category":"Real Estate",
            "subcategory":"Real Estate Agent",
            "type":"Services"
        }
    ],
    "sg:phone":"+1 301 947 6500",
    "sg:postcode":"20878",
    "sg:province":"MD",
    "wof:name":"Re/Max Metropolitan Realty",
    "wof:placetype":"venue"
},
  "geometry": {"coordinates":[-77.23724300000001,39.120975],"type":"Point"}
}