{
  "type": "Feature",
  "properties": {
    "addr:full":"1630 Annapolis Rd Odenton MD 21113",
    "addr:housenumber":"1630",
    "addr:postcode":"21113",
    "addr:street":"Annapolis Rd",
    "iso:country":"US",
    "sg:address":"1630 Annapolis Rd",
    "sg:city":"Odenton",
    "sg:classifiers":[
        {
            "category":"Restaurant",
            "type":"Food & Drink"
        }
    ],
    "sg:phone":"+1 410 674 6475",
    "sg:postcode":"21113",
    "sg:province":"MD",
    "wof:name":"Hwang Kum Sung",
    "wof:placetype":"venue"
},
  "geometry": {"coordinates":[-76.720602,39.10003],"type":"Point"}
}