{
  "type": "Feature",
  "properties": {
    "addr:full":"522 Chesapeake Ave Annapolis MD 21403",
    "addr:housenumber":"522",
    "addr:postcode":"21403",
    "addr:street":"Chesapeake Ave",
    "iso:country":"US",
    "sg:address":"522 Chesapeake Ave",
    "sg:city":"Annapolis",
    "sg:classifiers":[
        {
            "category":"Banks & Credit Unions",
            "subcategory":"Investment Brokerage",
            "type":"Services"
        }
    ],
    "sg:phone":"+1 410 267 8811",
    "sg:postcode":"21403",
    "sg:province":"MD",
    "sg:tags":[
        "security"
    ],
    "sg:website":"http://www.wyeriver.net",
    "wof:name":"Wye River Group Incorporated",
    "wof:placetype":"venue"
},
  "geometry": {"coordinates":[-76.482597,38.969574],"type":"Point"}
}