{
  "type": "Feature",
  "properties": {
    "addr:full":"6080 Falls Rd Baltimore MD 21209",
    "addr:housenumber":"6080",
    "addr:postcode":"21209",
    "addr:street":"Falls Rd",
    "iso:country":"US",
    "sg:address":"6080 Falls Rd",
    "sg:city":"Baltimore",
    "sg:classifiers":[
        {
            "category":"Shopping",
            "subcategory":"Shoes",
            "type":"Retail Goods"
        }
    ],
    "sg:phone":"+1 410 377 4200",
    "sg:postcode":"21209",
    "sg:province":"MD",
    "wof:name":"Clarks England Shoe Store",
    "wof:placetype":"venue"
},
  "geometry": {"coordinates":[-76.650717,39.375104],"type":"Point"}
}