{
  "type": "Feature",
  "properties": {
    "addr:full":"28 Allegheny Ave Baltimore MD 21204",
    "addr:housenumber":"28",
    "addr:postcode":"21204",
    "addr:street":"Allegheny Ave",
    "iso:country":"US",
    "sg:address":"28 Allegheny Ave",
    "sg:city":"Baltimore",
    "sg:classifiers":[
        {
            "category":"Real Estate",
            "subcategory":"Real Estate Agent",
            "type":"Services"
        }
    ],
    "sg:phone":"+1 410 494 8900",
    "sg:postcode":"21204",
    "sg:province":"MD",
    "wof:name":"Chesapeak Capital Management",
    "wof:placetype":"venue"
},
  "geometry": {"coordinates":[-76.603043,39.401747],"type":"Point"}
}