{
  "type": "Feature",
  "properties": {
    "addr:full":"306 S Philadelphia Blvd Aberdeen MD 21001",
    "addr:housenumber":"306",
    "addr:postcode":"21001",
    "addr:street":"S Philadelphia Blvd",
    "iso:country":"US",
    "sg:address":"306 S Philadelphia Blvd",
    "sg:city":"Aberdeen",
    "sg:classifiers":[
        {
            "category":"Restaurant",
            "type":"Food & Drink"
        }
    ],
    "sg:menulink":"http://www.allmenus.com/md/halls-cross-roads/67335-dominos-pizza/menu/",
    "sg:phone":"+1 410 272 3033",
    "sg:postcode":"21001",
    "sg:province":"MD",
    "sg:tags":[
        "american",
        "wing",
        "pizza"
    ],
    "wof:name":"Domino's Pizza",
    "wof:placetype":"venue"
},
  "geometry": {"coordinates":[-76.16637799999999,39.505175],"type":"Point"}
}