{
  "type": "Feature",
  "properties": {
    "iso:country":"US",
    "sg:address":"2635 Housley Rd",
    "sg:city":"Annapolis",
    "sg:classifiers":[
        {
            "category":"Coffee & Tea",
            "type":"Food & Drink"
        }
    ],
    "sg:menulink":"http://www.allmenus.com/md/annapolis/118962-starbucks-coffee/menu/",
    "sg:phone":"+1 410 224 8890",
    "sg:postcode":"21401",
    "sg:province":"MD",
    "sg:tags":[
        "american"
    ],
    "wof:name":"Starbucks Coffee",
    "wof:placetype":"venue"
},
  "geometry": {"coordinates":[-76.553521,38.99046],"type":"Point"}
}