{
  "type": "Feature",
  "properties": {
    "iso:country":"US",
    "sg:address":"931 Mc Donogh St",
    "sg:city":"Baltimore",
    "sg:classifiers":[
        {
            "category":"Bars & Pubs",
            "type":"Food & Drink"
        }
    ],
    "sg:phone":"+1 410 675 0132",
    "sg:postcode":"21205",
    "sg:province":"MD",
    "wof:name":"Three W's Bar",
    "wof:placetype":"venue"
},
  "geometry": {"coordinates":[-76.59349899999999,39.301927],"type":"Point"}
}