{
  "type": "Feature",
  "properties": {
    "addr:full":"1800 Woodlawn Dr Gwynn Oak MD 21207",
    "addr:housenumber":"1800",
    "addr:postcode":"21207",
    "addr:street":"Woodlawn Dr",
    "iso:country":"US",
    "sg:address":"1800 Woodlawn Dr",
    "sg:city":"Gwynn Oak",
    "sg:classifiers":[
        {
            "category":"Shopping",
            "subcategory":"Shoes",
            "type":"Retail Goods"
        }
    ],
    "sg:phone":"+1 301 621 4239",
    "sg:postcode":"21207",
    "sg:province":"MD",
    "sg:tags":[
        "store"
    ],
    "wof:name":"Esco Ltd",
    "wof:placetype":"venue"
},
  "geometry": {"coordinates":[-76.73719800000001,39.3172],"type":"Point"}
}