{
  "type": "Feature",
  "properties": {
    "addr:full":"23655 Royal Oak Rd Quantico MD 21856",
    "addr:housenumber":"23655",
    "addr:postcode":"21856",
    "addr:street":"Royal Oak Rd",
    "iso:country":"US",
    "sg:address":"23655 Royal Oak Rd",
    "sg:city":"Quantico",
    "sg:classifiers":[
        {
            "category":"Professional",
            "subcategory":"Research",
            "type":"Services"
        }
    ],
    "sg:phone":"+1 410 677 6720",
    "sg:postcode":"21856",
    "sg:province":"MD",
    "sg:tags":[
        "environmental",
        "ecological"
    ],
    "wof:name":"TPH Industries",
    "wof:placetype":"venue"
},
  "geometry": {"coordinates":[-75.80951,38.354003],"type":"Point"}
}