{
  "type": "Feature",
  "properties": {
    "iso:country":"US",
    "sg:address":"214 Main St",
    "sg:city":"Preston",
    "sg:classifiers":[
        {
            "category":"Shopping",
            "subcategory":"Used Merchandise",
            "type":"Retail Goods"
        }
    ],
    "sg:phone":"+1 410 673 9899",
    "sg:postcode":"21655",
    "sg:province":"MD",
    "sg:tags":[
        "shop",
        "consignment"
    ],
    "wof:name":"A & M Childrens Consignment",
    "wof:placetype":"venue"
},
  "geometry": {"coordinates":[-75.907402,38.710954],"type":"Point"}
}