{
  "type": "Feature",
  "properties": {
    "addr:full":"608 Pigpen Point Rd Queenstown MD 21658",
    "addr:housenumber":"608",
    "addr:postcode":"21658",
    "addr:street":"Pigpen Point Rd",
    "iso:country":"US",
    "sg:address":"608 Pigpen Point Rd",
    "sg:city":"Queenstown",
    "sg:classifiers":[
        {
            "category":"Shopping",
            "type":"Retail Goods"
        }
    ],
    "sg:phone":"+1 410 827 0342",
    "sg:postcode":"21658",
    "sg:province":"MD",
    "sg:tags":[
        "merchandise"
    ],
    "wof:name":"Family Pools",
    "wof:placetype":"venue"
},
  "geometry": {"coordinates":[-76.178214,38.897695],"type":"Point"}
}