{
  "type": "Feature",
  "properties": {
    "iso:country":"US",
    "sg:address":"5429 Connecticut Ave NW",
    "sg:city":"Washington",
    "sg:classifiers":[
        {
            "category":"Insurance",
            "subcategory":"Insurance Agent",
            "type":"Services"
        }
    ],
    "sg:phone":"+1 202 237 2085",
    "sg:postcode":"20015",
    "sg:province":"MD",
    "wof:name":"International Fidelity Ins",
    "wof:placetype":"venue"
},
  "geometry": {"coordinates":[-77.07438399999999,38.962973],"type":"Point"}
}