{
  "type": "Feature",
  "properties": {
    "addr:full":"725 Paldao Ter Hyattsville MD 20785",
    "addr:housenumber":"725",
    "addr:postcode":"20785",
    "addr:street":"Paldao Ter",
    "iso:country":"US",
    "sg:address":"725 Paldao Ter",
    "sg:city":"Hyattsville",
    "sg:classifiers":[
        {
            "category":"Shopping",
            "subcategory":"Clothing, Apparel, & Fashions",
            "type":"Retail Goods"
        }
    ],
    "sg:phone":"+1 301 324 9486",
    "sg:postcode":"20785",
    "sg:province":"MD",
    "wof:name":"Head To Toe Fashions Inc",
    "wof:placetype":"venue"
},
  "geometry": {"coordinates":[-76.88286100000001,38.900152],"type":"Point"}
}