{
  "type": "Feature",
  "properties": {
    "addr:full":"12259 Lime Kiln Rd Fulton MD 20759",
    "addr:housenumber":"12259",
    "addr:postcode":"20759",
    "addr:street":"Lime Kiln Rd",
    "iso:country":"US",
    "sg:address":"12259 Lime Kiln Rd",
    "sg:city":"Fulton",
    "sg:classifiers":[
        {
            "category":"Wholesale",
            "subcategory":"Groceries",
            "type":"Manufacturing & Wholesale Goods"
        }
    ],
    "sg:phone":"+1 301 470 3530",
    "sg:postcode":"20759",
    "sg:province":"MD",
    "sg:tags":[
        "food",
        "broker"
    ],
    "wof:name":"Capitol Specialities Inc",
    "wof:placetype":"venue"
},
  "geometry": {"coordinates":[-76.939611,39.148184],"type":"Point"}
}