{
  "type": "Feature",
  "properties": {
    "addr:full":"11212 Westport Dr Bowie MD 20720",
    "addr:housenumber":"11212",
    "addr:postcode":"20720",
    "addr:street":"Westport Dr",
    "iso:country":"US",
    "sg:address":"11212 Westport Dr",
    "sg:city":"Bowie",
    "sg:classifiers":[
        {
            "category":"Insurance",
            "subcategory":"Insurance Agent",
            "type":"Services"
        },
        {
            "category":"Insurance",
            "subcategory":"Hazard Insurance",
            "type":"Services"
        }
    ],
    "sg:phone":"+1 301 574 2176",
    "sg:postcode":"20720",
    "sg:province":"MD",
    "sg:tags":[
        "insured",
        "property",
        "adjuster",
        "replacement"
    ],
    "wof:name":"Ralph Parker",
    "wof:placetype":"venue"
},
  "geometry": {"coordinates":[-76.811691,38.950779],"type":"Point"}
}