{
  "type": "Feature",
  "properties": {
    "addr:full":"1520 Winterberry Dr Arnold MD 21012",
    "addr:housenumber":"1520",
    "addr:postcode":"21012",
    "addr:street":"Winterberry Dr",
    "iso:country":"US",
    "sg:address":"1520 Winterberry Dr",
    "sg:city":"Arnold",
    "sg:classifiers":[
        {
            "category":"Shopping",
            "subcategory":"Gifts & Souvenirs",
            "type":"Retail Goods"
        }
    ],
    "sg:phone":"+1 410 757 6356",
    "sg:postcode":"21012",
    "sg:province":"MD",
    "wof:name":"Gemmas Collectibles",
    "wof:placetype":"venue"
},
  "geometry": {"coordinates":[-76.48066300000001,39.031964],"type":"Point"}
}