{
  "type": "Feature",
  "properties": {
    "iso:country":"US",
    "sg:address":"1520 Winterberry Dr",
    "sg:city":"Arnold",
    "sg:classifiers":[
        {
            "category":"Shopping",
            "subcategory":"Gifts & Souvenirs",
            "type":"Retail Goods"
        }
    ],
    "sg:phone":"+1 410 757 6356",
    "sg:postcode":"21012",
    "sg:province":"MD",
    "wof:name":"Gemmas Collectibles",
    "wof:placetype":"venue"
},
  "geometry": {"coordinates":[-76.480663,39.031964],"type":"Point"}
}