{
  "type": "Feature",
  "properties": {
    "iso:country":"US",
    "sg:address":"11 Lauriann Ct",
    "sg:city":"Parkton",
    "sg:classifiers":[
        {
            "category":"Health Services",
            "subcategory":"Doctor",
            "type":"Services"
        }
    ],
    "sg:phone":"+1 410 357 9880",
    "sg:postcode":"21120",
    "sg:province":"MD",
    "sg:tags":[
        "dentist"
    ],
    "wof:name":"Your Whiter Brighter Smile",
    "wof:placetype":"venue"
},
  "geometry": {"coordinates":[-76.663085,39.64211],"type":"Point"}
}