{
  "type": "Feature",
  "properties": {
    "iso:country":"US",
    "sg:address":"6 Purdue Ct",
    "sg:city":"Rockville",
    "sg:classifiers":[
        {
            "category":"Restaurant",
            "type":"Food & Drink"
        }
    ],
    "sg:phone":"+1 301 251 0940",
    "sg:postcode":"20850",
    "sg:province":"MD",
    "sg:tags":[
        "eating"
    ],
    "wof:name":"Moussa B Antoun",
    "wof:placetype":"venue"
},
  "geometry": {"coordinates":[-77.163799,39.101552],"type":"Point"}
}