{
  "type": "Feature",
  "properties": {
    "addr:full":"8900 Falls Rd Potomac MD 20854",
    "addr:housenumber":"8900",
    "addr:postcode":"20854",
    "addr:street":"Falls Rd",
    "iso:country":"US",
    "sg:address":"8900 Falls Rd",
    "sg:city":"Potomac",
    "sg:classifiers":[
        {
            "category":"Professional",
            "subcategory":"Computer Services",
            "type":"Services"
        }
    ],
    "sg:phone":"+1 301 299 3236",
    "sg:postcode":"20854",
    "sg:province":"MD",
    "sg:tags":[
        "related",
        "programing",
        "custom"
    ],
    "wof:name":"LKL Consultants",
    "wof:placetype":"venue"
},
  "geometry": {"coordinates":[-77.227256,39.000961],"type":"Point"}
}