{
  "type": "Feature",
  "properties": {
    "iso:country":"US",
    "sg:address":"7129 Helmsdale Rd",
    "sg:city":"Bethesda",
    "sg:classifiers":[
        {
            "category":"Health Services",
            "subcategory":"Doctor",
            "type":"Services"
        }
    ],
    "sg:phone":"+1 301 229 7172",
    "sg:postcode":"20817",
    "sg:province":"MD",
    "sg:tags":[
        "medical"
    ],
    "wof:name":"Ben Zeichner M D PA",
    "wof:placetype":"venue"
},
  "geometry": {"coordinates":[-77.152388,38.981316],"type":"Point"}
}