{
  "type": "Feature",
  "properties": {
    "iso:country":"US",
    "sg:address":"36 York St",
    "sg:city":"Taneytown",
    "sg:classifiers":[
        {
            "category":"Organizations",
            "subcategory":"Religious Organization",
            "type":"Services"
        }
    ],
    "sg:phone":"+1 410 756 2233",
    "sg:postcode":"21787",
    "sg:province":"MD",
    "sg:tags":[
        "place",
        "worship",
        "church"
    ],
    "wof:name":"Taneytown Presbyterian Church",
    "wof:placetype":"venue"
},
  "geometry": {"coordinates":[-77.17495700000001,39.660629],"type":"Point"}
}