{
  "type": "Feature",
  "properties": {
    "addr:full":"22707 Three Notch Rd California MD 20619",
    "addr:housenumber":"22707",
    "addr:postcode":"20619",
    "addr:street":"Three Notch Rd",
    "iso:country":"US",
    "sg:address":"22707 Three Notch Rd",
    "sg:city":"California",
    "sg:classifiers":[
        {
            "category":"Autos & Motor Vehicles",
            "subcategory":"Auto Supplies",
            "type":"Retail Goods"
        }
    ],
    "sg:phone":"+1 301 862 3250",
    "sg:postcode":"20619",
    "sg:province":"MD",
    "sg:tags":[
        "automobile",
        "parts"
    ],
    "wof:name":"Autozone",
    "wof:placetype":"venue"
},
  "geometry": {"coordinates":[-76.49347899999999,38.291321],"type":"Point"}
}