{
  "type": "Feature",
  "properties": {
    "addr:full":"8379 Piney Orchard Pkwy Odenton MD 21113",
    "addr:housenumber":"8379",
    "addr:postcode":"21113",
    "addr:street":"Piney Orchard Pkwy",
    "iso:country":"US",
    "sg:address":"8379 Piney Orchard Pkwy",
    "sg:city":"Odenton",
    "sg:phone":"+1 410 674 8440",
    "sg:postcode":"21113",
    "sg:province":"MD",
    "wof:name":"New Life Community Church",
    "wof:placetype":"venue"
},
  "geometry": {"coordinates":[-76.69978,39.085026],"type":"Point"}
}