{
  "type": "Feature",
  "properties": {
    "addr:full":"4600 Flower Valley Dr Rockville MD 20853",
    "addr:housenumber":"4600",
    "addr:postcode":"20853",
    "addr:street":"Flower Valley Dr",
    "iso:country":"US",
    "sg:address":"4600 Flower Valley Dr",
    "sg:city":"Rockville",
    "sg:classifiers":[
        {
            "category":"Professional",
            "subcategory":"Lawyer & Legal Services",
            "type":"Services"
        }
    ],
    "sg:phone":"+1 301 929 1252",
    "sg:postcode":"20853",
    "sg:province":"MD",
    "sg:tags":[
        "international",
        "attorney",
        "business"
    ],
    "wof:name":"Dennis A Foster",
    "wof:placetype":"venue"
},
  "geometry": {"coordinates":[-77.093666,39.103339],"type":"Point"}
}