{
  "type": "Feature",
  "properties": {
    "addr:full":"905 Blue Leaf Ct Frederick MD 21701",
    "addr:housenumber":"905",
    "addr:postcode":"21701",
    "addr:street":"Blue Leaf Ct",
    "iso:country":"US",
    "sg:address":"905 Blue Leaf Ct",
    "sg:city":"Frederick",
    "sg:classifiers":[
        {
            "category":"Personal",
            "type":"Services"
        }
    ],
    "sg:phone":"+1 301 620 8808",
    "sg:postcode":"21701",
    "sg:province":"MD",
    "wof:name":"Stable Hands Massage Ther",
    "wof:placetype":"venue"
},
  "geometry": {"coordinates":[-77.39126899999999,39.436854],"type":"Point"}
}