{
  "type": "Feature",
  "properties": {
    "addr:full":"14517 Duckett Rd Brandywine MD 20613",
    "addr:postcode":"14517;20613",
    "addr:street":"Duckett Rd",
    "iso:country":"US",
    "sg:address":"14517 Duckett Rd",
    "sg:city":"Brandywine",
    "sg:classifiers":[
        {
            "category":"Freight",
            "type":"Transportation"
        }
    ],
    "sg:phone":"+1 301 372 8010",
    "sg:postcode":"20613",
    "sg:province":"MD",
    "sg:tags":[
        "operator",
        "local",
        "trucking"
    ],
    "wof:name":"Booth Trucking",
    "wof:placetype":"venue"
},
  "geometry": {"coordinates":[-76.904731,38.69014],"type":"Point"}
}