{
  "type": "Feature",
  "properties": {
    "addr:full":"8524 Walter Martz Rd Frederick MD 21702",
    "addr:housenumber":"8524",
    "addr:postcode":"21702",
    "addr:street":"Walter Martz Rd",
    "iso:country":"US",
    "sg:address":"8524 Walter Martz Rd",
    "sg:city":"Frederick",
    "sg:classifiers":[
        {
            "category":"Building & Trades",
            "subcategory":"Construction",
            "type":"Services"
        }
    ],
    "sg:phone":"+1 301 694 0740",
    "sg:postcode":"21702",
    "sg:province":"MD",
    "sg:tags":[
        "painter"
    ],
    "wof:name":"W Nicholas Albaugh",
    "wof:placetype":"venue"
},
  "geometry": {"coordinates":[-77.443039,39.465018],"type":"Point"}
}