{
  "type": "Feature",
  "properties": {
    "iso:country":"US",
    "sg:address":"7012 Marlboro Pike",
    "sg:city":"Forestville",
    "sg:classifiers":[
        {
            "category":"Shopping",
            "subcategory":"Pharmacy",
            "type":"Retail Goods"
        }
    ],
    "sg:phone":"+1 301 736 8683",
    "sg:postcode":"20747",
    "sg:province":"MD",
    "sg:tags":[
        "drugstore"
    ],
    "sg:website":"www.cvs.com",
    "wof:name":"Cvs Pharmacy",
    "wof:placetype":"venue"
},
  "geometry": {"coordinates":[-76.886166,38.85003],"type":"Point"}
}