{
  "type": "Feature",
  "properties": {
    "iso:country":"US",
    "sg:address":"12504 Augustine Herman Hwy",
    "sg:city":"Kennedyville",
    "sg:classifiers":[
        {
            "category":"Travel",
            "subcategory":"Travel Agent",
            "type":"Entertainment"
        }
    ],
    "sg:phone":"+1 410 778 6412",
    "sg:postcode":"21645",
    "sg:province":"MD",
    "sg:tags":[
        "outfitted",
        "expedition"
    ],
    "wof:name":"Goose Valley Farming",
    "wof:placetype":"venue"
},
  "geometry": {"coordinates":[-75.96605,39.322739],"type":"Point"}
}