{
  "type": "Feature",
  "properties": {
    "iso:country":"US",
    "sg:address":"920 University Blvd E",
    "sg:city":"Silver Spring",
    "sg:classifiers":[
        {
            "category":"Banks & Credit Unions",
            "subcategory":"Bank",
            "type":"Services"
        }
    ],
    "sg:phone":"+1 301 445 4900",
    "sg:postcode":"20903",
    "sg:province":"MD",
    "sg:tags":[
        "loan",
        "real estate"
    ],
    "wof:name":"Home Owners Mortgage Corp",
    "wof:placetype":"venue"
},
  "geometry": {"coordinates":[-76.991485,38.992687],"type":"Point"}
}