{
  "type": "Feature",
  "properties": {
    "addr:full":"1701 Taylor Ave Baltimore MD 21234",
    "addr:housenumber":"1701",
    "addr:postcode":"21234",
    "addr:street":"Taylor Ave",
    "iso:country":"US",
    "sg:address":"1701 Taylor Ave",
    "sg:city":"Baltimore",
    "sg:classifiers":[
        {
            "category":"Autos & Motor Vehicles",
            "subcategory":"Auto Supplies",
            "type":"Retail Goods"
        }
    ],
    "sg:phone":"+1 410 668 9828",
    "sg:postcode":"21234",
    "sg:province":"MD",
    "sg:tags":[
        "tire"
    ],
    "wof:name":"Excel Car Care Ctr",
    "wof:placetype":"venue"
},
  "geometry": {"coordinates":[-76.56021699999999,39.38144],"type":"Point"}
}