{
  "type": "Feature",
  "properties": {
    "addr:full":"6840 New Hampshire Ave Takoma Park MD 20912",
    "addr:housenumber":"6840",
    "addr:postcode":"20912",
    "addr:street":"New Hampshire Ave",
    "iso:country":"US",
    "sg:address":"6840 New Hampshire Ave",
    "sg:city":"Takoma Park",
    "sg:classifiers":[
        {
            "category":"Shopping",
            "type":"Retail Goods"
        }
    ],
    "sg:phone":"+1 301 270 5802",
    "sg:postcode":"20912",
    "sg:province":"MD",
    "sg:tags":[
        "cosmetic",
        "perfume"
    ],
    "wof:name":"Mama's Beauty Supplies",
    "wof:placetype":"venue"
},
  "geometry": {"coordinates":[-76.995687,38.973936],"type":"Point"}
}