{
  "type": "Feature",
  "properties": {
    "addr:full":"312 W Main St Salisbury MD 21801",
    "addr:housenumber":"312",
    "addr:postcode":"21801",
    "addr:street":"W Main St",
    "iso:country":"US",
    "sg:address":"312 W Main St",
    "sg:city":"Salisbury",
    "sg:classifiers":[
        {
            "category":"Real Estate",
            "subcategory":"Architect",
            "type":"Services"
        }
    ],
    "sg:phone":"+1 410 546 9100",
    "sg:postcode":"21801",
    "sg:province":"MD",
    "sg:website":"www.beckermorgan.com",
    "wof:name":"Becker Morgan Group Inc",
    "wof:placetype":"venue"
},
  "geometry": {"coordinates":[-75.603072,38.365176],"type":"Point"}
}