{
  "type": "Feature",
  "properties": {
    "iso:country":"US",
    "sg:address":"10803 Falls Rd",
    "sg:city":"Lutherville",
    "sg:classifiers":[
        {
            "category":"Recreation",
            "type":"Entertainment"
        }
    ],
    "sg:phone":"+1 410 821 5683",
    "sg:postcode":"21093",
    "sg:province":"MD",
    "sg:tags":[
        "tennis",
        "court"
    ],
    "wof:name":"Greenspring Racquet Club",
    "wof:placetype":"venue"
},
  "geometry": {"coordinates":[-76.670615,39.421058],"type":"Point"}
}