{
  "type": "Feature",
  "properties": {
    "iso:country":"US",
    "sg:address":"8798 Doves Fly Way",
    "sg:city":"Laurel",
    "sg:classifiers":[
        {
            "category":"Health Services",
            "subcategory":"Clinic",
            "type":"Services"
        }
    ],
    "sg:phone":"+1 301 688 8912",
    "sg:postcode":"20723",
    "sg:province":"MD",
    "sg:tags":[
        "system",
        "officer"
    ],
    "wof:name":"Trace Inc",
    "wof:placetype":"venue"
},
  "geometry": {"coordinates":[-76.870429,39.126287],"type":"Point"}
}