{
  "type": "Feature",
  "properties": {
    "iso:country":"US",
    "sg:address":"12048 Cherry Hill Rd",
    "sg:city":"Silver Spring",
    "sg:classifiers":[
        {
            "category":"Building & Trades",
            "subcategory":"Locksmith",
            "type":"Services"
        }
    ],
    "sg:phone":"+1 240 560 2231",
    "sg:postcode":"20904",
    "sg:province":"MD",
    "sg:tags":[
        "key"
    ],
    "wof:name":"Emergency Locksmith Silver Spring",
    "wof:placetype":"venue"
},
  "geometry": {"coordinates":[-76.95564,39.058506],"type":"Point"}
}