{
  "type": "Feature",
  "properties": {
    "iso:country":"US",
    "sg:address":"107 Baltimore Ave",
    "sg:city":"Stevensville",
    "sg:classifiers":[
        {
            "category":"Wholesale",
            "subcategory":"Durable Goods & Equipment",
            "type":"Manufacturing & Wholesale Goods"
        }
    ],
    "sg:phone":"+1 410 643 4817",
    "sg:postcode":"21666",
    "sg:province":"MD",
    "wof:name":"White Rabbit",
    "wof:placetype":"venue"
},
  "geometry": {"coordinates":[-76.305132,39.038224],"type":"Point"}
}