{
  "type": "Feature",
  "properties": {
    "addr:full":"4607 Embassy Cir Owings Mills MD 21117",
    "addr:housenumber":"4607",
    "addr:postcode":"21117",
    "addr:street":"Embassy Cir",
    "iso:country":"US",
    "sg:address":"4607 Embassy Cir",
    "sg:city":"Owings Mills",
    "sg:classifiers":[
        {
            "category":"Professional",
            "subcategory":"Computer Services",
            "type":"Services"
        }
    ],
    "sg:phone":"+1 410 654 6789",
    "sg:postcode":"21117",
    "sg:province":"MD",
    "sg:tags":[
        "processing",
        "datum"
    ],
    "wof:name":"Serengeti Data Management",
    "wof:placetype":"venue"
},
  "geometry": {"coordinates":[-76.80082899999999,39.396128],"type":"Point"}
}