{
  "type": "Feature",
  "properties": {
    "addr:full":"17820 Caddy Dr Derwood MD 20855",
    "addr:housenumber":"17820",
    "addr:postcode":"20855",
    "addr:street":"Caddy Dr",
    "iso:country":"US",
    "sg:address":"17820 Caddy Dr",
    "sg:city":"Derwood",
    "sg:classifiers":[
        {
            "category":"Professional",
            "subcategory":"Management & Consulting",
            "type":"Services"
        }
    ],
    "sg:phone":"+1 301 977 7291",
    "sg:postcode":"20855",
    "sg:province":"MD",
    "sg:tags":[
        "analysis"
    ],
    "wof:name":"Thomas E Ingalls Consultant",
    "wof:placetype":"venue"
},
  "geometry": {"coordinates":[-77.157445,39.14854],"type":"Point"}
}