{
  "type": "Feature",
  "properties": {
    "addr:full":"701 Gold St Baltimore MD 21217",
    "addr:housenumber":"701",
    "addr:postcode":"21217",
    "addr:street":"Gold St",
    "iso:country":"US",
    "sg:address":"701 Gold St",
    "sg:city":"Baltimore",
    "sg:classifiers":[
        {
            "category":"Education",
            "subcategory":"Preschool",
            "type":"Public Place"
        },
        {
            "category":"Education",
            "subcategory":"School",
            "type":"Public Place"
        }
    ],
    "sg:phone":"+1 410 383 0288",
    "sg:postcode":"21217",
    "sg:province":"MD",
    "sg:tags":[
        "elementary"
    ],
    "wof:name":"Baltimore New Compact Schools",
    "wof:placetype":"venue"
},
  "geometry": {"coordinates":[-76.640297,39.306702],"type":"Point"}
}