{
  "type": "Feature",
  "properties": {
    "iso:country":"US",
    "sg:address":"6931 Arlington Rd",
    "sg:city":"Bethesda",
    "sg:classifiers":[
        {
            "category":"Professional",
            "subcategory":"Management & Consulting",
            "type":"Services"
        }
    ],
    "sg:phone":"+1 301 913 0315",
    "sg:postcode":"20814",
    "sg:province":"MD",
    "sg:tags":[
        "consultant",
        "business"
    ],
    "wof:name":"Overhead Management Consultant",
    "wof:placetype":"venue"
},
  "geometry": {"coordinates":[-77.098326,38.980408],"type":"Point"}
}