{
  "type": "Feature",
  "properties": {
    "iso:country":"US",
    "sg:address":"4518 Albemarle St NW",
    "sg:city":"Washington",
    "sg:classifiers":[
        {
            "category":"Professional",
            "subcategory":"Management & Consulting",
            "type":"Services"
        }
    ],
    "sg:phone":"+1 202 537 1135",
    "sg:postcode":"20016",
    "sg:province":"MD",
    "sg:tags":[
        "consultant",
        "business"
    ],
    "wof:name":"C T Magee",
    "wof:placetype":"venue"
},
  "geometry": {"coordinates":[-77.090328,38.947831],"type":"Point"}
}