{
  "type": "Feature",
  "properties": {
    "addr:full":"3825 Bark Hill Rd Union Bridge MD 21791",
    "addr:housenumber":"3825",
    "addr:postcode":"21791",
    "addr:street":"Bark Hill Rd",
    "iso:country":"US",
    "sg:address":"3825 Bark Hill Rd",
    "sg:city":"Union Bridge",
    "sg:classifiers":[
        {
            "category":"Education",
            "subcategory":"School",
            "type":"Public Place"
        }
    ],
    "sg:phone":"+1 410 751 3320",
    "sg:postcode":"21791",
    "sg:province":"MD",
    "sg:tags":[
        "executive"
    ],
    "wof:name":"Francis Scott Key High School",
    "wof:placetype":"venue"
},
  "geometry": {"coordinates":[-77.134265,39.592826],"type":"Point"}
}