{
  "type": "Feature",
  "properties": {
    "iso:country":"US",
    "sg:address":"1721 N Smallwood St",
    "sg:city":"Baltimore",
    "sg:classifiers":[
        {
            "category":"Retail",
            "subcategory":"Auto Repair",
            "type":"Services"
        }
    ],
    "sg:phone":"+1 410 225 9139",
    "sg:postcode":"21216",
    "sg:province":"MD",
    "sg:tags":[
        "repairing",
        "automobile"
    ],
    "wof:name":"Earl's Auto Repair",
    "wof:placetype":"venue"
},
  "geometry": {"coordinates":[-76.65270200000001,39.308201],"type":"Point"}
}