{
  "type": "Feature",
  "properties": {
    "addr:full":"23154 Wetstone Ln California MD 20619",
    "addr:postcode":"23154;20619",
    "addr:street":"Wetstone Ln",
    "iso:country":"US",
    "sg:address":"23154 Wetstone Ln",
    "sg:city":"California",
    "sg:classifiers":[
        {
            "category":"Restaurant",
            "type":"Food & Drink"
        }
    ],
    "sg:phone":"+1 301 863 3219",
    "sg:postcode":"20619",
    "sg:province":"MD",
    "wof:name":"Wildewood Village Caterers",
    "wof:placetype":"venue"
},
  "geometry": {"coordinates":[-76.54949999999999,38.3008],"type":"Point"}
}