{
  "type": "Feature",
  "properties": {
    "addr:full":"19600 Frederick Rd Germantown MD 20876",
    "addr:housenumber":"19600",
    "addr:postcode":"20876",
    "addr:street":"Frederick Rd",
    "iso:country":"US",
    "sg:address":"19600 Frederick Rd",
    "sg:city":"Germantown",
    "sg:phone":"+1 301 831 1101",
    "sg:postcode":"20876",
    "sg:province":"MD",
    "sg:website":"http://www.haul911.net",
    "wof:name":"Haul 911",
    "wof:placetype":"venue"
},
  "geometry": {"coordinates":[-77.23848700000001,39.17767],"type":"Point"}
}