{
  "type": "Feature",
  "properties": {
    "addr:full":"211 E. Lombard St. Baltimore MD 21202",
    "addr:housenumber":"211",
    "addr:postcode":"21202",
    "addr:street":"E. Lombard",
    "iso:country":"US",
    "sg:address":"211 E. Lombard St.",
    "sg:city":"Baltimore",
    "sg:classifiers":[
        {
            "category":"Shopping",
            "subcategory":"Clothing, Apparel, & Fashions",
            "type":"Retail Goods"
        }
    ],
    "sg:phone":"+1 877 345 8974",
    "sg:postcode":"21202",
    "sg:province":"MD",
    "sg:website":"www.collegegear.com",
    "wof:name":"College Apparel by College Gear I Maryland Terps",
    "wof:placetype":"venue"
},
  "geometry": {"coordinates":[-76.61118,39.287829],"type":"Point"}
}