{
  "type": "Feature",
  "properties": {
    "addr:full":"728 Grandin Ave Rockville MD 20850",
    "addr:housenumber":"728",
    "addr:postcode":"20850",
    "addr:street":"Grandin Ave",
    "iso:country":"US",
    "sg:address":"728 Grandin Ave",
    "sg:city":"Rockville",
    "sg:classifiers":[
        {
            "category":"Professional",
            "subcategory":"Research",
            "type":"Services"
        }
    ],
    "sg:phone":"+1 301 251 7732",
    "sg:postcode":"20850",
    "sg:province":"MD",
    "sg:tags":[
        "educational"
    ],
    "wof:name":"Sonny's Kids Foundation Inc",
    "wof:placetype":"venue"
},
  "geometry": {"coordinates":[-77.14089,39.082085],"type":"Point"}
}