{
  "type": "Feature",
  "properties": {
    "addr:full":"12124 Greenspring Ave Owings Mills MD 21117",
    "addr:housenumber":"12124",
    "addr:postcode":"21117",
    "addr:street":"Greenspring Ave",
    "iso:country":"US",
    "sg:address":"12124 Greenspring Ave",
    "sg:city":"Owings Mills",
    "sg:classifiers":[
        {
            "category":"Food & Beverages",
            "subcategory":"Groceries & Convenience Stores",
            "type":"Retail Goods"
        }
    ],
    "sg:phone":"+1 410 252 9100",
    "sg:postcode":"21117",
    "sg:province":"MD",
    "sg:tags":[
        "grocer"
    ],
    "wof:name":"Chestnut Ridge Farm Market",
    "wof:placetype":"venue"
},
  "geometry": {"coordinates":[-76.730158,39.458674],"type":"Point"}
}