{
  "type": "Feature",
  "properties": {
    "iso:country":"US",
    "sg:address":"31787 River Rd",
    "sg:city":"Millington",
    "sg:classifiers":[
        {
            "category":"Retail",
            "subcategory":"Auto Repair",
            "type":"Services"
        }
    ],
    "sg:phone":"+1 410 810 3000",
    "sg:postcode":"21651",
    "sg:province":"MD",
    "sg:tags":[
        "truck"
    ],
    "wof:name":"Greg's Truck Repair & Tire Svc",
    "wof:placetype":"venue"
},
  "geometry": {"coordinates":[-75.863743,39.26402],"type":"Point"}
}