{
  "type": "Feature",
  "properties": {
    "addr:full":"3937 Penn Belt Pl District Heights MD 20747",
    "addr:housenumber":"3937",
    "addr:postcode":"20747",
    "addr:street":"Penn Belt Pl",
    "iso:country":"US",
    "sg:address":"3937 Penn Belt Pl",
    "sg:city":"District Heights",
    "sg:classifiers":[
        {
            "category":"Building & Trades",
            "subcategory":"Construction",
            "type":"Services"
        }
    ],
    "sg:phone":"+1 301 735 5909",
    "sg:postcode":"20747",
    "sg:province":"MD",
    "sg:tags":[
        "contractor"
    ],
    "wof:name":"J L & S Building",
    "wof:placetype":"venue"
},
  "geometry": {"coordinates":[-76.873047,38.835667],"type":"Point"}
}