{
  "type": "Feature",
  "properties": {
    "addr:full":"804 Suburbian Rd Reisterstown MD 21136",
    "addr:housenumber":"804",
    "addr:postcode":"21136",
    "addr:street":"Suburbian Rd",
    "iso:country":"US",
    "sg:address":"804 Suburbian Rd",
    "sg:city":"Reisterstown",
    "sg:classifiers":[
        {
            "category":"Building & Trades",
            "subcategory":"Construction",
            "type":"Services"
        }
    ],
    "sg:phone":"+1 410 526 9321",
    "sg:postcode":"21136",
    "sg:province":"MD",
    "sg:tags":[
        "house"
    ],
    "wof:name":"William Skipper Remodeling",
    "wof:placetype":"venue"
},
  "geometry": {"coordinates":[-76.808081,39.454437],"type":"Point"}
}