{
  "type": "Feature",
  "properties": {
    "addr:full":"6770 Oak Hall Ln Columbia MD 21045",
    "addr:housenumber":"6770",
    "addr:postcode":"21045",
    "addr:street":"Oak Hall Ln",
    "iso:country":"US",
    "sg:address":"6770 Oak Hall Ln",
    "sg:city":"Columbia",
    "sg:classifiers":[
        {
            "category":"Home & Garden",
            "subcategory":"Carpets & Floor Coverings",
            "type":"Retail Goods"
        }
    ],
    "sg:phone":"+1 410 381 5900",
    "sg:postcode":"21045",
    "sg:province":"MD",
    "sg:tags":[
        "dealer",
        "rug"
    ],
    "sg:website":"www.cbflooring.com",
    "wof:name":"C B Flooring LLC",
    "wof:placetype":"venue"
},
  "geometry": {"coordinates":[-76.822554,39.18488],"type":"Point"}
}