{
  "type": "Feature",
  "properties": {
    "iso:country":"US",
    "sg:address":"601 Academy Ave",
    "sg:city":"Owings Mills",
    "sg:classifiers":[
        {
            "category":"Professional",
            "subcategory":"Management & Consulting",
            "type":"Services"
        }
    ],
    "sg:phone":"+1 410 902 0464",
    "sg:postcode":"21117",
    "sg:province":"MD",
    "sg:tags":[
        "food",
        "facility"
    ],
    "wof:name":"Neumeier Consulting",
    "wof:placetype":"venue"
},
  "geometry": {"coordinates":[-76.793788,39.445952],"type":"Point"}
}