{
  "type": "Feature",
  "properties": {
    "addr:full":"7389 Baltimore Annapolis Blvd Glen Burnie MD 21061",
    "addr:housenumber":"7389",
    "addr:postcode":"21061",
    "addr:street":"Baltimore Annapolis Blvd",
    "iso:country":"US",
    "sg:address":"7389 Baltimore Annapolis Blvd",
    "sg:city":"Glen Burnie",
    "sg:classifiers":[
        {
            "category":"Health Services",
            "subcategory":"Health Practitioner",
            "type":"Services"
        }
    ],
    "sg:phone":"+1 410 590 4944",
    "sg:postcode":"21061",
    "sg:province":"MD",
    "sg:tags":[
        "therapist",
        "physical"
    ],
    "wof:name":"Maryland Healthcare Clinics",
    "wof:placetype":"venue"
},
  "geometry": {"coordinates":[-76.631433,39.170908],"type":"Point"}
}