{
  "type": "Feature",
  "properties": {
    "addr:full":"7020 Debold Rd Sabillasville MD 21780",
    "addr:postcode":"7020;21780",
    "addr:street":"Debold Rd",
    "iso:country":"US",
    "sg:address":"7020 Debold Rd",
    "sg:city":"Sabillasville",
    "sg:classifiers":[
        {
            "category":"Building & Trades",
            "subcategory":"Construction",
            "type":"Services"
        }
    ],
    "sg:phone":"+1 301 271 4261",
    "sg:postcode":"21780",
    "sg:province":"MD",
    "sg:tags":[
        "contractor"
    ],
    "wof:name":"Hahn Brothers Construction",
    "wof:placetype":"venue"
},
  "geometry": {"coordinates":[-77.421509,39.673157],"type":"Point"}
}