{
  "type": "Feature",
  "properties": {
    "addr:full":"5808 Johnnycake Rd Gwynn Oak MD 21207",
    "addr:housenumber":"5808",
    "addr:postcode":"21207",
    "addr:street":"Johnnycake Rd",
    "iso:country":"US",
    "sg:address":"5808 Johnnycake Rd",
    "sg:city":"Gwynn Oak",
    "sg:classifiers":[
        {
            "category":"Retail",
            "subcategory":"Laundry & Dry Cleaning",
            "type":"Services"
        }
    ],
    "sg:phone":"+1 410 788 8666",
    "sg:postcode":"21207",
    "sg:province":"MD",
    "sg:tags":[
        "cleaners"
    ],
    "wof:name":"Issa Cleaners",
    "wof:placetype":"venue"
},
  "geometry": {"coordinates":[-76.73057,39.292185],"type":"Point"}
}