{
  "type": "Feature",
  "properties": {
    "iso:country":"US",
    "sg:address":"1758 Wilcox Ln",
    "sg:city":"Silver Spring",
    "sg:classifiers":[
        {
            "category":"Banks & Credit Unions",
            "subcategory":"Bank",
            "type":"Services"
        }
    ],
    "sg:phone":"+1 301 933 9747",
    "sg:postcode":"20906",
    "sg:province":"MD",
    "sg:tags":[
        "loan",
        "real estate"
    ],
    "wof:name":"Millenium Mortgage",
    "wof:placetype":"venue"
},
  "geometry": {"coordinates":[-77.036247,39.066895],"type":"Point"}
}