{
  "type": "Feature",
  "properties": {
    "addr:full":"8903 Pensacola Pl Upper Marlboro MD 20772",
    "addr:housenumber":"8903",
    "addr:postcode":"20772",
    "addr:street":"Pensacola Pl",
    "iso:country":"US",
    "sg:address":"8903 Pensacola Pl",
    "sg:city":"Upper Marlboro",
    "sg:classifiers":[
        {
            "category":"Personal",
            "type":"Services"
        }
    ],
    "sg:phone":"+1 301 780 3121",
    "sg:postcode":"20772",
    "sg:province":"MD",
    "wof:name":"Montage LLC",
    "wof:placetype":"venue"
},
  "geometry": {"coordinates":[-76.790914,38.766859],"type":"Point"}
}