{
  "type": "Feature",
  "properties": {
    "iso:country":"US",
    "sg:address":"5410 Edson Ln",
    "sg:city":"Rockville",
    "sg:classifiers":[
        {
            "category":"Wholesale",
            "subcategory":"Electrical",
            "type":"Manufacturing & Wholesale Goods"
        }
    ],
    "sg:phone":"+1 301 354 5500",
    "sg:postcode":"20852",
    "sg:province":"MD",
    "sg:tags":[
        "control",
        "security",
        "system"
    ],
    "wof:name":"Sensormatic",
    "wof:placetype":"venue"
},
  "geometry": {"coordinates":[-77.110841,39.040182],"type":"Point"}
}