{
  "type": "Feature",
  "properties": {
    "addr:full":"201 N Washington St Easton MD 21601",
    "addr:housenumber":"201",
    "addr:postcode":"21601",
    "addr:street":"N Washington St",
    "iso:country":"US",
    "sg:address":"201 N Washington St",
    "sg:city":"Easton",
    "sg:classifiers":[
        {
            "category":"Professional",
            "subcategory":"Computer Services",
            "type":"Services"
        }
    ],
    "sg:phone":"+1 410 763 9400",
    "sg:postcode":"21601",
    "sg:province":"MD",
    "sg:tags":[
        "internet"
    ],
    "wof:name":"Easton Online",
    "wof:placetype":"venue"
},
  "geometry": {"coordinates":[-76.07595499999999,38.778811],"type":"Point"}
}