{
  "type": "Feature",
  "properties": {
    "iso:country":"US",
    "sg:address":"5101 River Rd",
    "sg:city":"Bethesda",
    "sg:classifiers":[
        {
            "category":"Real Estate",
            "subcategory":"Real Estate Operator",
            "type":"Services"
        }
    ],
    "sg:phone":"+1 301 657 3626",
    "sg:postcode":"20816",
    "sg:province":"MD",
    "sg:tags":[
        "apartment"
    ],
    "wof:name":"The Kenwood",
    "wof:placetype":"venue"
},
  "geometry": {"coordinates":[-77.10171800000001,38.963454],"type":"Point"}
}