{
  "type": "Feature",
  "properties": {
    "addr:full":"9600 Pulaski Park Dr Middle River MD 21220",
    "addr:housenumber":"9600",
    "addr:postcode":"21220",
    "addr:street":"Pulaski Park Dr",
    "iso:country":"US",
    "sg:address":"9600 Pulaski Park Dr",
    "sg:city":"Middle River",
    "sg:classifiers":[
        {
            "category":"Health Services",
            "subcategory":"Doctor",
            "type":"Services"
        }
    ],
    "sg:phone":"+1 410 574 3000",
    "sg:postcode":"21220",
    "sg:province":"MD",
    "wof:name":"Medstar Physician Partners",
    "wof:placetype":"venue"
},
  "geometry": {"coordinates":[-76.452392,39.352166],"type":"Point"}
}