{
  "type": "Feature",
  "properties": {
    "iso:country":"US",
    "sg:address":"10806 Reisterstown Rd",
    "sg:city":"Owings Mills",
    "sg:classifiers":[
        {
            "category":"Professional",
            "subcategory":"Lawyer & Legal Services",
            "type":"Services"
        }
    ],
    "sg:phone":"+1 410 654 0305",
    "sg:postcode":"21117",
    "sg:province":"MD",
    "sg:tags":[
        "attorney"
    ],
    "wof:name":"Attorney Services Corp",
    "wof:placetype":"venue"
},
  "geometry": {"coordinates":[-76.790057,39.427359],"type":"Point"}
}