{
  "type": "Feature",
  "properties": {
    "iso:country":"US",
    "sg:address":"15536 Emerald Way",
    "sg:city":"Bowie",
    "sg:classifiers":[
        {
            "category":"Shopping",
            "subcategory":"Baby Store",
            "type":"Retail Goods"
        }
    ],
    "sg:phone":"+1 301 464 5003",
    "sg:postcode":"20716",
    "sg:province":"MD",
    "sg:tags":[
        "children's",
        "infant",
        "wear"
    ],
    "wof:name":"G & G Retail Inc",
    "wof:placetype":"venue"
},
  "geometry": {"coordinates":[-76.735237,38.943968],"type":"Point"}
}