{
  "type": "Feature",
  "properties": {
    "addr:full":"6805 York Rd Baltimore MD 21212",
    "addr:housenumber":"6805",
    "addr:postcode":"21212",
    "addr:street":"York Rd",
    "iso:country":"US",
    "sg:address":"6805 York Rd",
    "sg:city":"Baltimore",
    "sg:classifiers":[
        {
            "category":"Food & Beverages",
            "subcategory":"Bakery",
            "type":"Retail Goods"
        }
    ],
    "sg:phone":"+1 443 279 0649",
    "sg:postcode":"21212",
    "sg:province":"MD",
    "sg:tags":[
        "bagel"
    ],
    "wof:name":"Sams Bagles",
    "wof:placetype":"venue"
},
  "geometry": {"coordinates":[-76.60865800000001,39.377636],"type":"Point"}
}