{
  "type": "Feature",
  "properties": {
    "iso:country":"US",
    "sg:address":"300 W Lombard St Apt 1003",
    "sg:city":"Baltimore",
    "sg:classifiers":[
        {
            "category":"Organizations",
            "subcategory":"Community Association",
            "type":"Services"
        }
    ],
    "sg:phone":"+1 443 610 5889",
    "sg:postcode":"21201",
    "sg:province":"MD",
    "sg:tags":[
        "club"
    ],
    "wof:name":"Havre De Grace Maryland Chapter 577 Of Aarp, Inc.",
    "wof:placetype":"venue"
},
  "geometry": {"coordinates":[-76.619308,39.28759],"type":"Point"}
}