{
  "type": "Feature",
  "properties": {
    "iso:country":"US",
    "sg:address":"151 Ravine St",
    "sg:city":"Grantsville",
    "sg:classifiers":[
        {
            "category":"Autos & Motor Vehicles",
            "subcategory":"Auto Supplies",
            "type":"Retail Goods"
        },
        {
            "category":"Retail",
            "subcategory":"Auto Repair",
            "type":"Services"
        }
    ],
    "sg:phone":"+1 301 895 5126",
    "sg:postcode":"21536",
    "sg:province":"MD",
    "sg:tags":[
        "recap",
        "retread",
        "tire"
    ],
    "wof:name":"Guy's Tire Shop Inc",
    "wof:placetype":"venue"
},
  "geometry": {"coordinates":[-79.155418,39.697189],"type":"Point"}
}