{
  "type": "Feature",
  "properties": {
    "addr:full":"22 Village Square Cross Baltimore MD 21201",
    "addr:housenumber":"22",
    "addr:postcode":"21201",
    "addr:street":"Village Square",
    "iso:country":"US",
    "sg:address":"22 Village Square Cross",
    "sg:city":"Baltimore",
    "sg:classifiers":[
        {
            "category":"Shopping",
            "subcategory":"Clothing, Apparel, & Fashions",
            "type":"Retail Goods"
        }
    ],
    "sg:phone":"+1 410 532 6442",
    "sg:postcode":"21201",
    "sg:province":"MD",
    "sg:tags":[
        "accessory",
        "clothing",
        "women's"
    ],
    "wof:name":"Chezelle",
    "wof:placetype":"venue"
},
  "geometry": {"coordinates":[-76.622597,39.2957],"type":"Point"}
}