{
  "type": "Feature",
  "properties": {
    "addr:full":"7302 Eden Brook Dr Columbia MD 21046",
    "addr:housenumber":"7302",
    "addr:postcode":"21046",
    "addr:street":"Eden Brook Dr",
    "iso:country":"US",
    "sg:address":"7302 Eden Brook Dr",
    "sg:city":"Columbia",
    "sg:classifiers":[
        {
            "category":"Professional",
            "subcategory":"Management & Consulting",
            "type":"Services"
        }
    ],
    "sg:phone":"+1 301 538 0457",
    "sg:postcode":"21046",
    "sg:province":"MD",
    "sg:tags":[
        "business"
    ],
    "wof:name":"Charles Flagg LLC",
    "wof:placetype":"venue"
},
  "geometry": {"coordinates":[-76.868667,39.167829],"type":"Point"}
}