{
  "type": "Feature",
  "properties": {
    "iso:country":"US",
    "sg:address":"33 E Patrick St",
    "sg:city":"Frederick",
    "sg:classifiers":[
        {
            "category":"Professional",
            "subcategory":"Management & Consulting",
            "type":"Services"
        }
    ],
    "sg:phone":"+1 301 695 6865",
    "sg:postcode":"21701",
    "sg:province":"MD",
    "sg:tags":[
        "consultant",
        "business"
    ],
    "sg:website":"www.anthonyrobbinsdc.com",
    "wof:name":"Anthony Robbins & Assoc",
    "wof:placetype":"venue"
},
  "geometry": {"coordinates":[-77.410421,39.414226],"type":"Point"}
}