{
  "type": "Feature",
  "properties": {
    "addr:full":"111 E Water St Centreville MD 21617",
    "addr:housenumber":"111",
    "addr:postcode":"21617",
    "addr:street":"E Water St",
    "iso:country":"US",
    "sg:address":"111 E Water St",
    "sg:city":"Centreville",
    "sg:classifiers":[
        {
            "category":"Health Services",
            "subcategory":"Optometrist",
            "type":"Services"
        }
    ],
    "sg:phone":"+1 443 262 9415",
    "sg:postcode":"21617",
    "sg:province":"MD",
    "wof:name":"An Optical Galleria LLC",
    "wof:placetype":"venue"
},
  "geometry": {"coordinates":[-76.065206,39.044276],"type":"Point"}
}