{
  "type": "Feature",
  "properties": {
    "iso:country":"US",
    "sg:address":"121 N Union Ave",
    "sg:city":"Havre De Grace",
    "sg:classifiers":[
        {
            "category":"Recreation",
            "type":"Entertainment"
        }
    ],
    "sg:phone":"+1 410 939 4078",
    "sg:postcode":"21078",
    "sg:province":"MD",
    "sg:tags":[
        "charter",
        "boat"
    ],
    "wof:name":"Martha Lewi Skipjack",
    "wof:placetype":"venue"
},
  "geometry": {"coordinates":[-76.091624,39.547679],"type":"Point"}
}