{
  "type": "Feature",
  "properties": {
    "addr:full":"1416 Jefferson Pike Knoxville MD 21758",
    "addr:housenumber":"1416",
    "addr:postcode":"21758",
    "addr:street":"Jefferson Pike",
    "iso:country":"US",
    "sg:address":"1416 Jefferson Pike",
    "sg:city":"Knoxville",
    "sg:classifiers":[
        {
            "category":"Building & Trades",
            "subcategory":"Landscaping Services",
            "type":"Services"
        }
    ],
    "sg:phone":"+1 301 834 6866",
    "sg:postcode":"21758",
    "sg:province":"MD",
    "sg:tags":[
        "taker",
        "care"
    ],
    "wof:name":"Harold Daugherty",
    "wof:placetype":"venue"
},
  "geometry": {"coordinates":[-77.62106199999999,39.34531],"type":"Point"}
}