{
  "type": "Feature",
  "properties": {
    "addr:full":"2215 Reedie Dr Silver Spring MD 20902",
    "addr:housenumber":"2215",
    "addr:postcode":"20902",
    "addr:street":"Reedie Dr",
    "iso:country":"US",
    "sg:address":"2215 Reedie Dr",
    "sg:city":"Silver Spring",
    "sg:classifiers":[
        {
            "category":"Manufacturing",
            "subcategory":"Signs",
            "type":"Manufacturing & Wholesale Goods"
        }
    ],
    "sg:phone":"+1 301 933 4209",
    "sg:postcode":"20902",
    "sg:province":"MD",
    "sg:tags":[
        "specialty",
        "mfg"
    ],
    "wof:name":"L C Signs Inc",
    "wof:placetype":"venue"
},
  "geometry": {"coordinates":[-77.048621,39.039168],"type":"Point"}
}