{
  "type": "Feature",
  "properties": {
    "addr:full":"806 Dulaney Valley Rd Towson MD 21204",
    "addr:housenumber":"806",
    "addr:postcode":"21204",
    "addr:street":"Dulaney Valley Rd",
    "iso:country":"US",
    "sg:address":"806 Dulaney Valley Rd",
    "sg:city":"Towson",
    "sg:classifiers":[
        {
            "category":"Banks & Credit Unions",
            "subcategory":"Investment Brokerage",
            "type":"Services"
        },
        {
            "category":"Banks & Credit Unions",
            "subcategory":"Financial Services",
            "type":"Services"
        }
    ],
    "sg:phone":"+1 410 825 0972",
    "sg:postcode":"21204",
    "sg:province":"MD",
    "sg:tags":[
        "advisory",
        "planning",
        "consultant"
    ],
    "sg:website":"http://www.investfinancial.com",
    "wof:name":"Invest Financial",
    "wof:placetype":"venue"
},
  "geometry": {"coordinates":[-76.60173,39.404397],"type":"Point"}
}