{
  "type": "Feature",
  "properties": {
    "addr:full":"1 Investment Pl Baltimore MD 21204",
    "addr:housenumber":"1",
    "addr:postcode":"21204",
    "addr:street":"Investment Pl",
    "iso:country":"US",
    "sg:address":"1 Investment Pl",
    "sg:city":"Baltimore",
    "sg:classifiers":[
        {
            "category":"Shopping",
            "subcategory":"Gifts & Souvenirs",
            "type":"Retail Goods"
        }
    ],
    "sg:phone":"+1 410 296 8797",
    "sg:postcode":"21204",
    "sg:province":"MD",
    "sg:tags":[
        "shop"
    ],
    "wof:name":"Kard Korner",
    "wof:placetype":"venue"
},
  "geometry": {"coordinates":[-76.603066,39.402387],"type":"Point"}
}