{
  "type": "Feature",
  "properties": {
    "iso:country":"US",
    "sg:address":"7699 Quarterfield Rd",
    "sg:city":"Glen Burnie",
    "sg:classifiers":[
        {
            "category":"Food & Beverages",
            "subcategory":"Groceries & Convenience Stores",
            "type":"Retail Goods"
        }
    ],
    "sg:phone":"+1 410 760 9354",
    "sg:postcode":"21061",
    "sg:province":"MD",
    "wof:name":"Wawa Food Market",
    "wof:placetype":"venue"
},
  "geometry": {"coordinates":[-76.637136,39.149916],"type":"Point"}
}