{
  "type": "Feature",
  "properties": {
    "iso:country":"US",
    "sg:address":"9410 Kendale Rd",
    "sg:city":"Potomac",
    "sg:classifiers":[
        {
            "category":"Health Services",
            "subcategory":"Doctor",
            "type":"Services"
        }
    ],
    "sg:phone":"+1 301 365 1534",
    "sg:postcode":"20854",
    "sg:province":"MD",
    "wof:name":"Moran Robert E Jr MD",
    "wof:placetype":"venue"
},
  "geometry": {"coordinates":[-77.179604,39.010201],"type":"Point"}
}