{
  "type": "Feature",
  "properties": {
    "addr:full":"6004 Lenox Rd Bethesda MD 20817",
    "addr:housenumber":"6004",
    "addr:postcode":"20817",
    "addr:street":"Lenox Rd",
    "iso:country":"US",
    "sg:address":"6004 Lenox Rd",
    "sg:city":"Bethesda",
    "sg:classifiers":[
        {
            "category":"Professional",
            "subcategory":"Research",
            "type":"Services"
        }
    ],
    "sg:phone":"+1 301 263 1001",
    "sg:postcode":"20817",
    "sg:province":"MD",
    "sg:tags":[
        "foundation",
        "philanthropic"
    ],
    "wof:name":"Shelby Cullom Davis Foundation",
    "wof:placetype":"venue"
},
  "geometry": {"coordinates":[-77.122165,38.979923],"type":"Point"}
}