{
  "type": "Feature",
  "properties": {
    "addr:full":"6571 Kali Dr Sykesville MD 21784",
    "addr:housenumber":"6571",
    "addr:postcode":"21784",
    "addr:street":"Kali Dr",
    "iso:country":"US",
    "sg:address":"6571 Kali Dr",
    "sg:city":"Sykesville",
    "sg:classifiers":[
        {
            "category":"Building & Trades",
            "subcategory":"Plumbing",
            "type":"Services"
        }
    ],
    "sg:phone":"+1 410 781 4200",
    "sg:postcode":"21784",
    "sg:province":"MD",
    "sg:tags":[
        "conditioning",
        "air",
        "system",
        "contractor"
    ],
    "wof:name":"Bridgeport Heating & Cooling",
    "wof:placetype":"venue"
},
  "geometry": {"coordinates":[-76.930452,39.395889],"type":"Point"}
}