{
  "type": "Feature",
  "properties": {
    "addr:full":"9616 Reisterstown Rd Owings Mills MD 21117",
    "addr:housenumber":"9616",
    "addr:postcode":"21117",
    "addr:street":"Reisterstown Rd",
    "iso:country":"US",
    "sg:address":"9616 Reisterstown Rd",
    "sg:city":"Owings Mills",
    "sg:classifiers":[
        {
            "category":"Shopping",
            "subcategory":"Discount & Variety Stores",
            "type":"Retail Goods"
        }
    ],
    "sg:phone":"+1 443 394 3700",
    "sg:postcode":"21117",
    "sg:province":"MD",
    "wof:name":"Amazing Savings",
    "wof:placetype":"venue"
},
  "geometry": {"coordinates":[-76.758965,39.404591],"type":"Point"}
}