{
  "type": "Feature",
  "properties": {
    "addr:full":"6124 Swansea St Bethesda MD 20817",
    "addr:housenumber":"6124",
    "addr:postcode":"20817",
    "addr:street":"Swansea St",
    "iso:country":"US",
    "sg:address":"6124 Swansea St",
    "sg:city":"Bethesda",
    "sg:classifiers":[
        {
            "category":"Professional",
            "subcategory":"Accounting & Tax Preparation",
            "type":"Services"
        }
    ],
    "sg:phone":"+1 301 365 9660",
    "sg:postcode":"20817",
    "sg:province":"MD",
    "sg:tags":[
        "accountant"
    ],
    "wof:name":"Charles F Behrens Accounting & Business Service",
    "wof:placetype":"venue"
},
  "geometry": {"coordinates":[-77.126999,38.9986],"type":"Point"}
}