{
  "type": "Feature",
  "properties": {
    "iso:country":"US",
    "sg:address":"5870 Urbana Pike",
    "sg:city":"Frederick",
    "sg:classifiers":[
        {
            "category":"Retail",
            "subcategory":"Auto Repair",
            "type":"Services"
        }
    ],
    "sg:phone":"+1 301 696 2222",
    "sg:postcode":"21704",
    "sg:province":"MD",
    "sg:tags":[
        "transmission"
    ],
    "sg:website":"www.aamcotransmissions.com",
    "wof:name":"AAMCO Transmissions",
    "wof:placetype":"venue"
},
  "geometry": {"coordinates":[-77.405683,39.391833],"type":"Point"}
}