{
  "type": "Feature",
  "properties": {
    "addr:full":"111 Georgia Ave NE Glen Burnie MD 21060",
    "addr:housenumber":"111",
    "addr:postcode":"21060",
    "addr:street":"Georgia Ave Ne",
    "iso:country":"US",
    "sg:address":"111 Georgia Ave NE",
    "sg:city":"Glen Burnie",
    "sg:classifiers":[
        {
            "category":"Professional",
            "subcategory":"Lawyer & Legal Services",
            "type":"Services"
        }
    ],
    "sg:phone":"+1 410 766 8250",
    "sg:postcode":"21060",
    "sg:province":"MD",
    "sg:tags":[
        "attorney"
    ],
    "wof:name":"Harris & Harris",
    "wof:placetype":"venue"
},
  "geometry": {"coordinates":[-76.619624,39.166729],"type":"Point"}
}