{
  "type": "Feature",
  "properties": {
    "iso:country":"US",
    "sg:address":"6119 Oakleaf Ave",
    "sg:city":"Baltimore",
    "sg:classifiers":[
        {
            "category":"Wholesale",
            "subcategory":"Hardware",
            "type":"Manufacturing & Wholesale Goods"
        }
    ],
    "sg:phone":"+1 410 358 3130",
    "sg:postcode":"21215",
    "sg:province":"MD",
    "sg:tags":[
        "nut",
        "bolt",
        "store"
    ],
    "sg:website":"www.marylandmetrics.com",
    "wof:name":"Maryland Metrics",
    "wof:placetype":"venue"
},
  "geometry": {"coordinates":[-76.698898,39.349998],"type":"Point"}
}