{
  "type": "Feature",
  "properties": {
    "addr:full":"3103 Offutt Rd Randallstown MD 21133",
    "addr:housenumber":"3103",
    "addr:postcode":"21133",
    "addr:street":"Offutt Rd",
    "iso:country":"US",
    "sg:address":"3103 Offutt Rd",
    "sg:city":"Randallstown",
    "sg:classifiers":[
        {
            "category":"Retail",
            "subcategory":"Animal Services",
            "type":"Services"
        }
    ],
    "sg:phone":"+1 410 655 3812",
    "sg:postcode":"21133",
    "sg:province":"MD",
    "sg:tags":[
        "personal"
    ],
    "wof:name":"Capri Pet Sitting Service",
    "wof:placetype":"venue"
},
  "geometry": {"coordinates":[-76.808093,39.363246],"type":"Point"}
}