{
  "type": "Feature",
  "properties": {
    "iso:country":"US",
    "sg:address":"2434 Holly Neck Rd",
    "sg:city":"Baltimore",
    "sg:classifiers":[
        {
            "category":"Recreation",
            "subcategory":"Marina",
            "type":"Entertainment"
        }
    ],
    "sg:phone":"+1 410 574 8281",
    "sg:postcode":"21221",
    "sg:province":"MD",
    "sg:tags":[
        "repairing",
        "boat"
    ],
    "sg:website":"www.allstarmarineonline.com",
    "wof:name":"All Star Marine",
    "wof:placetype":"venue"
},
  "geometry": {"coordinates":[-76.39797299999999,39.28291],"type":"Point"}
}