{
  "type": "Feature",
  "properties": {
    "iso:country":"US",
    "sg:address":"3716 Falls Rd",
    "sg:city":"Baltimore",
    "sg:classifiers":[
        {
            "category":"Shopping",
            "subcategory":"Music",
            "type":"Retail Goods"
        }
    ],
    "sg:phone":"+1 410 243 6246",
    "sg:postcode":"21211",
    "sg:province":"MD",
    "sg:tags":[
        "video",
        "disc",
        "tape",
        "cassette"
    ],
    "wof:name":"Stagecoach Video",
    "wof:placetype":"venue"
},
  "geometry": {"coordinates":[-76.6356,39.332691],"type":"Point"}
}