{
  "type": "Feature",
  "properties": {
    "addr:full":"48309 Wynne Rd Ridge MD 20680",
    "addr:postcode":"48309;20680",
    "addr:street":"Wynne Rd",
    "iso:country":"US",
    "sg:address":"48309 Wynne Rd",
    "sg:city":"Ridge",
    "sg:classifiers":[
        {
            "category":"Recreation",
            "type":"Entertainment"
        }
    ],
    "sg:phone":"+1 301 872 5815",
    "sg:postcode":"20680",
    "sg:province":"MD",
    "sg:tags":[
        "party",
        "fishing"
    ],
    "wof:name":"Chesapeake Bay Fishing Parties",
    "wof:placetype":"venue"
},
  "geometry": {"coordinates":[-76.386301,38.115947],"type":"Point"}
}