{
  "type": "Feature",
  "properties": {
    "iso:country":"US",
    "sg:address":"202 Juneberry Way",
    "sg:city":"Glen Burnie",
    "sg:classifiers":[
        {
            "category":"Professional",
            "subcategory":"Management & Consulting",
            "type":"Services"
        }
    ],
    "sg:phone":"+1 410 544 4848",
    "sg:postcode":"21061",
    "sg:province":"MD",
    "sg:tags":[
        "business"
    ],
    "wof:name":"Jeremy & Kathleen A Welsh",
    "wof:placetype":"venue"
},
  "geometry": {"coordinates":[-76.619553,39.195619],"type":"Point"}
}