{
  "type": "Feature",
  "properties": {
    "addr:full":"207 George St Chesapeake City MD 21915",
    "addr:housenumber":"207",
    "addr:postcode":"21915",
    "addr:street":"George St",
    "iso:country":"US",
    "sg:address":"207 George St",
    "sg:city":"Chesapeake City",
    "sg:classifiers":[
        {
            "category":"Retail",
            "subcategory":"Veterinary Services",
            "type":"Services"
        }
    ],
    "sg:phone":"+1 410 885 3700",
    "sg:postcode":"21915",
    "sg:province":"MD",
    "sg:tags":[
        "veterinarian"
    ],
    "wof:name":"Paula J Benner DVM",
    "wof:placetype":"venue"
},
  "geometry": {"coordinates":[-75.81355000000001,39.526981],"type":"Point"}
}