{
  "type": "Feature",
  "properties": {
    "iso:country":"US",
    "sg:address":"4600 Thunder Ct",
    "sg:city":"Darlington",
    "sg:classifiers":[
        {
            "category":"Shopping",
            "subcategory":"Clothing, Apparel, & Fashions",
            "type":"Retail Goods"
        },
        {
            "category":"Retail",
            "subcategory":"Driving School",
            "type":"Services"
        },
        {
            "category":"Autos & Motor Vehicles",
            "subcategory":"Motorcycle Sales",
            "type":"Retail Goods"
        },
        {
            "category":"Retail",
            "subcategory":"Auto Repair",
            "type":"Services"
        }
    ],
    "sg:phone":"+1 410 457 4541",
    "sg:postcode":"21034",
    "sg:province":"MD",
    "sg:tags":[
        "motorcycles-customizing",
        "scooters-repairing",
        "instruction",
        "leather",
        "apparel"
    ],
    "sg:website":"http://www.chesapeakehd.com",
    "wof:name":"Chesapeake Harley-Davidson",
    "wof:placetype":"venue"
},
  "geometry": {"coordinates":[-76.20343,39.649101],"type":"Point"}
}