{
  "type": "Feature",
  "properties": {
    "iso:country":"US",
    "sg:address":"9917 Woodsboro Rd",
    "sg:city":"Woodsboro",
    "sg:classifiers":[
        {
            "category":"Building & Trades",
            "subcategory":"Construction",
            "type":"Services"
        }
    ],
    "sg:phone":"+1 301 845 0618",
    "sg:postcode":"21798",
    "sg:province":"MD",
    "sg:tags":[
        "home",
        "builder",
        "contractor"
    ],
    "sg:website":"http://www.richardstine.com",
    "wof:name":"Richard B Stine Inc",
    "wof:placetype":"venue"
},
  "geometry": {"coordinates":[-77.272499,39.505689],"type":"Point"}
}