{
  "type": "Feature",
  "properties": {
    "iso:country":"US",
    "sg:address":"14730 Sugarland Rd",
    "sg:city":"Poolesville",
    "sg:classifiers":[
        {
            "category":"Organizations",
            "subcategory":"Religious Organization",
            "type":"Services"
        }
    ],
    "sg:phone":"+1 301 942 6830",
    "sg:postcode":"20837",
    "sg:province":"MD",
    "sg:tags":[
        "church"
    ],
    "wof:name":"Will Of God Mission Church",
    "wof:placetype":"venue"
},
  "geometry": {"coordinates":[-77.395768,39.100267],"type":"Point"}
}