{
  "type": "Feature",
  "properties": {
    "iso:country":"US",
    "sg:address":"558 Baltimore Pike",
    "sg:city":"Bel Air",
    "sg:classifiers":[
        {
            "category":"Wholesale",
            "subcategory":"Durable Goods & Equipment",
            "type":"Manufacturing & Wholesale Goods"
        }
    ],
    "sg:phone":"+1 410 893 7881",
    "sg:postcode":"21014",
    "sg:province":"MD",
    "sg:tags":[
        "compact",
        "record",
        "disc",
        "tape"
    ],
    "wof:name":"Record & Tape Traders",
    "wof:placetype":"venue"
},
  "geometry": {"coordinates":[-76.355698,39.525376],"type":"Point"}
}