{
  "type": "Feature",
  "properties": {
    "addr:full":"824 Dual Hwy Hagerstown MD 21740",
    "addr:housenumber":"824",
    "addr:postcode":"21740",
    "addr:street":"Dual Hwy",
    "iso:country":"US",
    "sg:address":"824 Dual Hwy",
    "sg:city":"Hagerstown",
    "sg:classifiers":[
        {
            "category":"Restaurant",
            "type":"Food & Drink"
        },
        {
            "category":"Ice Cream",
            "type":"Food & Drink"
        }
    ],
    "sg:menulink":"http://www.allmenus.com/md/hagerstown/168453-dairy-queen/menu/",
    "sg:phone":"+1 301 733 8486",
    "sg:postcode":"21740",
    "sg:province":"MD",
    "sg:tags":[
        "burger",
        "american",
        "ice",
        "cream"
    ],
    "wof:name":"Dairy Queen",
    "wof:placetype":"venue"
},
  "geometry": {"coordinates":[-77.70441099999999,39.634776],"type":"Point"}
}