{
  "type": "Feature",
  "properties": {
    "iso:country":"US",
    "sg:address":"4600 Decatur St",
    "sg:city":"Hyattsville",
    "sg:classifiers":[
        {
            "category":"Manufacturing",
            "subcategory":"Pet Food",
            "type":"Manufacturing & Wholesale Goods"
        },
        {
            "category":"Ice Cream",
            "type":"Food & Drink"
        }
    ],
    "sg:phone":"+1 301 927 5044",
    "sg:postcode":"20781",
    "sg:province":"MD",
    "sg:tags":[
        "ice-wholesale",
        "manufacturer"
    ],
    "sg:website":"http://www.ring-ring.com",
    "wof:name":"Apollo Ice Co",
    "wof:placetype":"venue"
},
  "geometry": {"coordinates":[-76.93890399999999,38.950562],"type":"Point"}
}