{
  "type": "Feature",
  "properties": {
    "iso:country":"US",
    "sg:address":"4390 Parliament Pl",
    "sg:city":"Lanham",
    "sg:classifiers":[
        {
            "category":"Professional",
            "type":"Services"
        }
    ],
    "sg:phone":"+1 301 459 9020",
    "sg:postcode":"20706",
    "sg:province":"MD",
    "sg:tags":[
        "establishment"
    ],
    "wof:name":"ACI",
    "wof:placetype":"venue"
},
  "geometry": {"coordinates":[-76.836543,38.949524],"type":"Point"}
}