{
  "type": "Feature",
  "properties": {
    "iso:country":"US",
    "sg:address":"216 Main St",
    "sg:city":"Laurel",
    "sg:classifiers":[
        {
            "category":"Personal",
            "subcategory":"Barber",
            "type":"Services"
        }
    ],
    "sg:phone":"+1 301 725 2323",
    "sg:postcode":"20707",
    "sg:province":"MD",
    "wof:name":"Perfect Cuts",
    "wof:placetype":"venue"
},
  "geometry": {"coordinates":[-76.843856,39.104035],"type":"Point"}
}