{
  "type": "Feature",
  "properties": {
    "addr:full":"154 N Market St Frederick MD 21701",
    "addr:housenumber":"154",
    "addr:postcode":"21701",
    "addr:street":"N Market St",
    "iso:country":"US",
    "sg:address":"154 N Market St",
    "sg:city":"Frederick",
    "sg:classifiers":[
        {
            "category":"Professional",
            "subcategory":"Lawyer & Legal Services",
            "type":"Services"
        }
    ],
    "sg:phone":"+1 301 662 0482",
    "sg:postcode":"21701",
    "sg:province":"MD",
    "sg:tags":[
        "attorney"
    ],
    "wof:name":"Frey & Grove",
    "wof:placetype":"venue"
},
  "geometry": {"coordinates":[-77.410629,39.416532],"type":"Point"}
}