{
  "type": "Feature",
  "properties": {
    "iso:country":"US",
    "sg:address":"1249 Engleberth Rd",
    "sg:city":"Essex",
    "sg:classifiers":[
        {
            "category":"Professional",
            "subcategory":"Engineering",
            "type":"Services"
        }
    ],
    "sg:phone":"+1 410 391 2336",
    "sg:postcode":"21221",
    "sg:province":"MD",
    "sg:tags":[
        "consulting",
        "engineer"
    ],
    "wof:name":"Bafitis & Associates Inc",
    "wof:placetype":"venue"
},
  "geometry": {"coordinates":[-76.395627,39.276824],"type":"Point"}
}