{
  "type": "Feature",
  "properties": {
    "addr:full":"121 Pine Tree Rd Crumpton MD 21620",
    "addr:housenumber":"121",
    "addr:postcode":"21620",
    "addr:street":"Pine Tree Rd",
    "iso:country":"US",
    "sg:address":"121 Pine Tree Rd",
    "sg:city":"Crumpton",
    "sg:classifiers":[
        {
            "category":"Banks & Credit Unions",
            "subcategory":"Bank",
            "type":"Services"
        }
    ],
    "sg:phone":"+1 410 810 7000",
    "sg:postcode":"21620",
    "sg:province":"MD",
    "sg:tags":[
        "loan",
        "real estate"
    ],
    "wof:name":"Chase Manhattan Mortgage Corp",
    "wof:placetype":"venue"
},
  "geometry": {"coordinates":[-75.928612,39.225752],"type":"Point"}
}