{
  "type": "Feature",
  "properties": {
    "addr:full":"315 Cove Rd Riva MD 21140",
    "addr:housenumber":"315",
    "addr:postcode":"21140",
    "addr:street":"Cove Rd",
    "iso:country":"US",
    "sg:address":"315 Cove Rd",
    "sg:city":"Riva",
    "sg:classifiers":[
        {
            "category":"Shopping",
            "subcategory":"Computers & Home Electronics",
            "type":"Retail Goods"
        }
    ],
    "sg:phone":"+1 410 956 6119",
    "sg:postcode":"21140",
    "sg:province":"MD",
    "sg:tags":[
        "software"
    ],
    "wof:name":"Plumtree Software Inc",
    "wof:placetype":"venue"
},
  "geometry": {"coordinates":[-76.583164,38.956018],"type":"Point"}
}