{
  "type": "Feature",
  "properties": {
    "addr:full":"4022 Chatham Rd Ellicott City MD 21042",
    "addr:housenumber":"4022",
    "addr:postcode":"21042",
    "addr:street":"Chatham Rd",
    "iso:country":"US",
    "sg:address":"4022 Chatham Rd",
    "sg:city":"Ellicott City",
    "sg:classifiers":[
        {
            "category":"Insurance",
            "subcategory":"Insurance Agent",
            "type":"Services"
        }
    ],
    "sg:phone":"+1 410 461 1300",
    "sg:postcode":"21042",
    "sg:province":"MD",
    "sg:tags":[
        "adjuster"
    ],
    "wof:name":"United Adjusters & Appraisers",
    "wof:placetype":"venue"
},
  "geometry": {"coordinates":[-76.833358,39.259554],"type":"Point"}
}