{
  "type": "Feature",
  "properties": {
    "addr:full":"9500 Annapolis Rd Ste A303 Lanham MD 20706",
    "addr:housenumber":"9500",
    "addr:postcode":"20706",
    "addr:street":"Annapolis Rd Ste A303",
    "iso:country":"US",
    "sg:address":"9500 Annapolis Rd Ste A303",
    "sg:city":"Lanham",
    "sg:classifiers":[
        {
            "category":"Professional",
            "subcategory":"Accounting & Tax Preparation",
            "type":"Services"
        }
    ],
    "sg:phone":"+1 301 429 0500",
    "sg:postcode":"20706",
    "sg:province":"MD",
    "sg:tags":[
        "accountant"
    ],
    "wof:name":"Bullard & Associates PC",
    "wof:placetype":"venue"
},
  "geometry": {"coordinates":[-76.84020200000001,38.964901],"type":"Point"}
}