{
  "type": "Feature",
  "properties": {
    "iso:country":"US",
    "sg:address":"8700 Georgia Ave",
    "sg:city":"Silver Spring",
    "sg:classifiers":[
        {
            "category":"Health Services",
            "subcategory":"Doctor",
            "type":"Services"
        }
    ],
    "sg:phone":"+1 301 585 6049",
    "sg:postcode":"20910",
    "sg:province":"MD",
    "sg:tags":[
        "physician",
        "surgeon"
    ],
    "wof:name":"Cameron Group",
    "wof:placetype":"venue"
},
  "geometry": {"coordinates":[-77.030632,38.998283],"type":"Point"}
}