{
  "type": "Feature",
  "properties": {
    "addr:full":"5121 Indian Head Hwy Oxon Hill MD 20745",
    "addr:housenumber":"5121",
    "addr:postcode":"20745",
    "addr:street":"Indian Head Hwy",
    "iso:country":"US",
    "sg:address":"5121 Indian Head Hwy",
    "sg:city":"Oxon Hill",
    "sg:classifiers":[
        {
            "category":"Restaurant",
            "type":"Food & Drink"
        }
    ],
    "sg:phone":"+1 301 839 5858",
    "sg:postcode":"20745",
    "sg:province":"MD",
    "sg:tags":[
        "seafood"
    ],
    "wof:name":"Shim's Seafood & Grill",
    "wof:placetype":"venue"
},
  "geometry": {"coordinates":[-76.999802,38.819199],"type":"Point"}
}