{
  "type": "Feature",
  "properties": {
    "addr:full":"3408 Olandwood Ct Olney MD 20832",
    "addr:housenumber":"3408",
    "addr:postcode":"20832",
    "addr:street":"Olandwood Ct",
    "iso:country":"US",
    "sg:address":"3408 Olandwood Ct",
    "sg:city":"Olney",
    "sg:classifiers":[
        {
            "category":"Wholesale",
            "subcategory":"Furniture",
            "type":"Manufacturing & Wholesale Goods"
        }
    ],
    "sg:phone":"+1 301 260 2161",
    "sg:postcode":"20832",
    "sg:province":"MD",
    "wof:name":"De Young & Assoc",
    "wof:placetype":"venue"
},
  "geometry": {"coordinates":[-77.067311,39.155979],"type":"Point"}
}