{
  "type": "Feature",
  "properties": {
    "addr:full":"7475 Wisconsin Ave Bethesda MD 20814",
    "addr:housenumber":"7475",
    "addr:postcode":"20814",
    "addr:street":"Wisconsin Ave",
    "iso:country":"US",
    "sg:address":"7475 Wisconsin Ave",
    "sg:city":"Bethesda",
    "sg:classifiers":[
        {
            "category":"Professional",
            "subcategory":"Accounting & Tax Preparation",
            "type":"Services"
        }
    ],
    "sg:phone":"+1 301 652 0030",
    "sg:postcode":"20814",
    "sg:province":"MD",
    "sg:tags":[
        "accountant"
    ],
    "sg:website":"www.capronassociates.com",
    "wof:name":"Capron & Assoc",
    "wof:placetype":"venue"
},
  "geometry": {"coordinates":[-77.094081,38.984421],"type":"Point"}
}