{
  "type": "Feature",
  "properties": {
    "addr:full":"4500 Mitchellville Rd Bowie MD 20716",
    "addr:housenumber":"4500",
    "addr:postcode":"20716",
    "addr:street":"Mitchellville Rd",
    "iso:country":"US",
    "sg:address":"4500 Mitchellville Rd",
    "sg:city":"Bowie",
    "sg:classifiers":[
        {
            "category":"Retail",
            "subcategory":"Veterinary Services",
            "type":"Services"
        }
    ],
    "sg:phone":"+1 301 805 8955",
    "sg:postcode":"20716",
    "sg:province":"MD",
    "sg:tags":[
        "veterinarian"
    ],
    "wof:name":"Banfield The Pet Hospital",
    "wof:placetype":"venue"
},
  "geometry": {"coordinates":[-76.72053699999999,38.951013],"type":"Point"}
}