{
  "type": "Feature",
  "properties": {
    "addr:full":"18232 Piedmont Dr Cobb Island MD 20625",
    "addr:housenumber":"18232",
    "addr:postcode":"20625",
    "addr:street":"Piedmont Dr",
    "iso:country":"US",
    "sg:address":"18232 Piedmont Dr",
    "sg:city":"Cobb Island",
    "sg:classifiers":[
        {
            "category":"Building & Trades",
            "subcategory":"Construction",
            "type":"Services"
        }
    ],
    "sg:phone":"+1 301 259 2370",
    "sg:postcode":"20625",
    "sg:province":"MD",
    "sg:tags":[
        "painter"
    ],
    "wof:name":"D J's Painting & Power Washing",
    "wof:placetype":"venue"
},
  "geometry": {"coordinates":[-76.84288599999999,38.259129],"type":"Point"}
}