{
  "type": "Feature",
  "properties": {
    "addr:full":"6922 Spinning Seed Columbia MD 21045",
    "addr:postcode":"6922;21045",
    "addr:street":"Spinning Seed",
    "iso:country":"US",
    "sg:address":"6922 Spinning Seed",
    "sg:city":"Columbia",
    "sg:classifiers":[
        {
            "category":"Professional",
            "type":"Services"
        }
    ],
    "sg:phone":"+1 410 290 9097",
    "sg:postcode":"21045",
    "sg:province":"MD",
    "wof:name":"Phillip Isacco",
    "wof:placetype":"venue"
},
  "geometry": {"coordinates":[-76.82796500000001,39.181891],"type":"Point"}
}