{
  "type": "Feature",
  "properties": {
    "addr:full":"6033 Belle Grove Rd Brooklyn MD 21225",
    "addr:housenumber":"6033",
    "addr:postcode":"21225",
    "addr:street":"Belle Grove Rd",
    "iso:country":"US",
    "sg:address":"6033 Belle Grove Rd",
    "sg:city":"Brooklyn",
    "sg:classifiers":[
        {
            "category":"Retail",
            "subcategory":"Auto Repair",
            "type":"Services"
        }
    ],
    "sg:phone":"+1 410 789 9270",
    "sg:postcode":"21225",
    "sg:province":"MD",
    "sg:tags":[
        "body",
        "shop"
    ],
    "wof:name":"Lee's J S Body Shop",
    "wof:placetype":"venue"
},
  "geometry": {"coordinates":[-76.6418,39.2178],"type":"Point"}
}