{
  "type": "Feature",
  "properties": {
    "iso:country":"US",
    "sg:address":"11273 New Hampshire Ave",
    "sg:city":"Silver Spring",
    "sg:classifiers":[
        {
            "category":"Shopping",
            "subcategory":"Beauty & Cosmetics",
            "type":"Retail Goods"
        }
    ],
    "sg:phone":"+1 301 593 3441",
    "sg:postcode":"20904",
    "sg:province":"MD",
    "sg:tags":[
        "supply"
    ],
    "wof:name":"Beauty Center the",
    "wof:placetype":"venue"
},
  "geometry": {"coordinates":[-76.99099699999999,39.040401],"type":"Point"}
}