{
  "type": "Feature",
  "properties": {
    "iso:country":"US",
    "sg:address":"4023 Arters Mill Rd",
    "sg:city":"Westminster",
    "sg:classifiers":[
        {
            "category":"Arena",
            "subcategory":"Horse Racetrack",
            "type":"Entertainment"
        }
    ],
    "sg:phone":"+1 410 857 4294",
    "sg:postcode":"21158",
    "sg:province":"MD",
    "sg:tags":[
        "breeder"
    ],
    "wof:name":"Camelot Stables",
    "wof:placetype":"venue"
},
  "geometry": {"coordinates":[-77.072283,39.683796],"type":"Point"}
}