{
  "type": "Feature",
  "properties": {
    "iso:country":"US",
    "sg:address":"3601 Michelle Way",
    "sg:city":"Pikesville",
    "sg:classifiers":[
        {
            "category":"Professional",
            "type":"Services"
        }
    ],
    "sg:phone":"+1 410 602 3324",
    "sg:postcode":"21208",
    "sg:province":"MD",
    "wof:name":"Minda F Goldberg",
    "wof:placetype":"venue"
},
  "geometry": {"coordinates":[-76.72274,39.394695],"type":"Point"}
}