{
  "type": "Feature",
  "properties": {
    "iso:country":"US",
    "sg:address":"204 Laurel St",
    "sg:city":"Pocomoke City",
    "sg:classifiers":[
        {
            "category":"Shopping",
            "subcategory":"Clothing, Apparel, & Fashions",
            "type":"Retail Goods"
        }
    ],
    "sg:phone":"+1 410 957 6166",
    "sg:postcode":"21851",
    "sg:province":"MD",
    "wof:name":"Jean's",
    "wof:placetype":"venue"
},
  "geometry": {"coordinates":[-75.57013999999999,38.072212],"type":"Point"}
}