{
  "type": "Feature",
  "properties": {
    "iso:country":"US",
    "sg:address":"2313 E North Ave",
    "sg:city":"Baltimore",
    "sg:classifiers":[
        {
            "category":"Retail",
            "subcategory":"Auto Repair",
            "type":"Services"
        }
    ],
    "sg:phone":"+1 410 276 2253",
    "sg:postcode":"21213",
    "sg:province":"MD",
    "wof:name":"Adi Auto Dynamics Inc",
    "wof:placetype":"venue"
},
  "geometry": {"coordinates":[-76.58580600000001,39.312372],"type":"Point"}
}