{
  "type": "Feature",
  "properties": {
    "addr:full":"502 Corbin Pkwy Annapolis MD 21401",
    "addr:housenumber":"502",
    "addr:postcode":"21401",
    "addr:street":"Corbin Pkwy",
    "iso:country":"US",
    "sg:address":"502 Corbin Pkwy",
    "sg:city":"Annapolis",
    "sg:classifiers":[
        {
            "category":"Home & Garden",
            "subcategory":"Building Materials",
            "type":"Retail Goods"
        },
        {
            "category":"Building & Trades",
            "subcategory":"Construction",
            "type":"Services"
        }
    ],
    "sg:phone":"+1 410 533 8977",
    "sg:postcode":"21401",
    "sg:province":"MD",
    "sg:tags":[
        "repair",
        "bathroom",
        "altering",
        "contractor",
        "planning",
        "maintenance",
        "tile-contractors",
        "improvement",
        "remodeling",
        "kitchen"
    ],
    "sg:website":"http://www.hometownrenovations.net",
    "wof:name":"Hometown Renovations LLC",
    "wof:placetype":"venue"
},
  "geometry": {"coordinates":[-76.55989099999999,39.00602],"type":"Point"}
}