{
  "type": "Feature",
  "properties": {
    "iso:country":"US",
    "sg:address":"1515 Reisterstown Rd",
    "sg:city":"Pikesville",
    "sg:classifiers":[
        {
            "category":"Banks & Credit Unions",
            "subcategory":"Bank",
            "type":"Services"
        }
    ],
    "sg:phone":"+1 410 486 5629",
    "sg:postcode":"21208",
    "sg:province":"MD",
    "sg:tags":[
        "commercial",
        "saving"
    ],
    "sg:website":"https://www.wachovia.com/?DCMP=KNL-CPS-DS-Directory-0703&HBX_PK=Banks&HBX_OU=71",
    "wof:name":"Wachovia Bank",
    "wof:placetype":"venue"
},
  "geometry": {"coordinates":[-76.72622800000001,39.377927],"type":"Point"}
}