{
  "type": "Feature",
  "properties": {
    "addr:full":"320 E Ridgely Rd Lutherville MD 21093",
    "addr:housenumber":"320",
    "addr:postcode":"21093",
    "addr:street":"E Ridgely Rd",
    "iso:country":"US",
    "sg:address":"320 E Ridgely Rd",
    "sg:city":"Lutherville",
    "sg:classifiers":[
        {
            "category":"Wholesale",
            "subcategory":"Electrical",
            "type":"Manufacturing & Wholesale Goods"
        }
    ],
    "sg:phone":"+1 410 284 3535",
    "sg:postcode":"21093",
    "sg:province":"MD",
    "sg:tags":[
        "alarm",
        "burglar",
        "system"
    ],
    "wof:name":"Alarm Pro",
    "wof:placetype":"venue"
},
  "geometry": {"coordinates":[-76.598038,39.434265],"type":"Point"}
}