{
  "type": "Feature",
  "properties": {
    "addr:full":"843 E Fort Ave Baltimore MD 21230",
    "addr:housenumber":"843",
    "addr:postcode":"21230",
    "addr:street":"E Fort Ave",
    "iso:country":"US",
    "sg:address":"843 E Fort Ave",
    "sg:city":"Baltimore",
    "sg:classifiers":[
        {
            "category":"Retail",
            "subcategory":"Laundry & Dry Cleaning",
            "type":"Services"
        }
    ],
    "sg:phone":"+1 410 332 0000",
    "sg:postcode":"21230",
    "sg:province":"MD",
    "wof:name":"Transworld Cleaners Inc",
    "wof:placetype":"venue"
},
  "geometry": {"coordinates":[-76.602118,39.271767],"type":"Point"}
}