{
  "type": "Feature",
  "properties": {
    "addr:full":"12 Goodport Ln Gaithersburg MD 20878",
    "addr:housenumber":"12",
    "addr:postcode":"20878",
    "addr:street":"Goodport Ln",
    "iso:country":"US",
    "sg:address":"12 Goodport Ln",
    "sg:city":"Gaithersburg",
    "sg:classifiers":[
        {
            "category":"Organizations",
            "subcategory":"Religious Organization",
            "type":"Services"
        }
    ],
    "sg:phone":"+1 301 829 7610",
    "sg:postcode":"20878",
    "sg:province":"MD",
    "sg:tags":[
        "church"
    ],
    "wof:name":"Gaithersburg Community Church",
    "wof:placetype":"venue"
},
  "geometry": {"coordinates":[-77.236405,39.151968],"type":"Point"}
}