{
  "type": "Feature",
  "properties": {
    "iso:country":"US",
    "sg:address":"14756 Main St",
    "sg:city":"Upper Marlboro",
    "sg:classifiers":[
        {
            "category":"Professional",
            "subcategory":"Accounting & Tax Preparation",
            "type":"Services"
        }
    ],
    "sg:phone":"+1 301 952 1040",
    "sg:postcode":"20772",
    "sg:province":"MD",
    "sg:tags":[
        "return"
    ],
    "wof:name":"H & R Block",
    "wof:placetype":"venue"
},
  "geometry": {"coordinates":[-76.751445,38.816435],"type":"Point"}
}