{
  "type": "Feature",
  "properties": {
    "iso:country":"US",
    "sg:address":"7120 Harford Rd",
    "sg:city":"Baltimore",
    "sg:classifiers":[
        {
            "category":"Restaurant",
            "type":"Food & Drink"
        }
    ],
    "sg:phone":"+1 410 254 7757",
    "sg:postcode":"21234",
    "sg:province":"MD",
    "sg:tags":[
        "parlor",
        "ice",
        "cream"
    ],
    "wof:name":"Charlie's Ice Cream Heaven",
    "wof:placetype":"venue"
},
  "geometry": {"coordinates":[-76.54798,39.367972],"type":"Point"}
}