{
  "type": "Feature",
  "properties": {
    "iso:country":"US",
    "sg:address":"3212 Midfield Rd",
    "sg:city":"Pikesville",
    "sg:classifiers":[
        {
            "category":"Building & Trades",
            "subcategory":"Construction",
            "type":"Services"
        }
    ],
    "sg:phone":"+1 410 262 2223",
    "sg:postcode":"21208",
    "sg:province":"MD",
    "sg:tags":[
        "house"
    ],
    "wof:name":"Ehs Structure & Remodeling Co",
    "wof:placetype":"venue"
},
  "geometry": {"coordinates":[-76.70242500000001,39.381627],"type":"Point"}
}