{
  "type": "Feature",
  "properties": {
    "addr:full":"5450 Reisterstown Rd Baltimore MD 21215",
    "addr:housenumber":"5450",
    "addr:postcode":"21215",
    "addr:street":"Reisterstown Rd",
    "iso:country":"US",
    "sg:address":"5450 Reisterstown Rd",
    "sg:city":"Baltimore",
    "sg:classifiers":[
        {
            "category":"Building & Trades",
            "subcategory":"Construction",
            "type":"Services"
        }
    ],
    "sg:phone":"+1 410 764 1044",
    "sg:postcode":"21215",
    "sg:province":"MD",
    "sg:tags":[
        "contractor"
    ],
    "wof:name":"Afram Inc",
    "wof:placetype":"venue"
},
  "geometry": {"coordinates":[-76.68942199999999,39.346851],"type":"Point"}
}