{
  "type": "Feature",
  "properties": {
    "addr:full":"35 N Market St Frederick MD 21701",
    "addr:housenumber":"35",
    "addr:postcode":"21701",
    "addr:street":"N Market St",
    "iso:country":"US",
    "sg:address":"35 N Market St",
    "sg:city":"Frederick",
    "sg:classifiers":[
        {
            "category":"Shopping",
            "subcategory":"Jewelry",
            "type":"Retail Goods"
        }
    ],
    "sg:phone":"+1 301 695 4556",
    "sg:postcode":"21701",
    "sg:province":"MD",
    "sg:tags":[
        "jeweler"
    ],
    "wof:name":"Zaruba & Co",
    "wof:placetype":"venue"
},
  "geometry": {"coordinates":[-77.410821,39.41617],"type":"Point"}
}