{
  "type": "Feature",
  "properties": {
    "iso:country":"US",
    "sg:address":"11332 Brandy Hall Ln",
    "sg:city":"Gaithersburg",
    "sg:classifiers":[
        {
            "category":"Professional",
            "subcategory":"Computer Services",
            "type":"Services"
        }
    ],
    "sg:phone":"+1 301 762 5247",
    "sg:postcode":"20878",
    "sg:province":"MD",
    "sg:tags":[
        "management",
        "database"
    ],
    "wof:name":"Peter Zaudtke",
    "wof:placetype":"venue"
},
  "geometry": {"coordinates":[-77.234037,39.101167],"type":"Point"}
}