{
  "type": "Feature",
  "properties": {
    "addr:full":"10103 Windstream Dr Columbia MD 21044",
    "addr:housenumber":"10103",
    "addr:postcode":"21044",
    "addr:street":"Windstream Dr",
    "iso:country":"US",
    "sg:address":"10103 Windstream Dr",
    "sg:city":"Columbia",
    "sg:classifiers":[
        {
            "category":"Wholesale",
            "subcategory":"Electrical",
            "type":"Manufacturing & Wholesale Goods"
        }
    ],
    "sg:phone":"+1 410 995 1688",
    "sg:postcode":"21044",
    "sg:province":"MD",
    "sg:tags":[
        "telecommunication"
    ],
    "wof:name":"Regional Telecommunications",
    "wof:placetype":"venue"
},
  "geometry": {"coordinates":[-76.86126899999999,39.220461],"type":"Point"}
}