{
  "type": "Feature",
  "properties": {
    "addr:full":"1141 Deanwood Rd Parkville MD 21234",
    "addr:housenumber":"1141",
    "addr:postcode":"21234",
    "addr:street":"Deanwood Rd",
    "iso:country":"US",
    "sg:address":"1141 Deanwood Rd",
    "sg:city":"Parkville",
    "sg:classifiers":[
        {
            "category":"Health Services",
            "subcategory":"Nursing And Care Facility",
            "type":"Services"
        }
    ],
    "sg:phone":"+1 410 583 0292",
    "sg:postcode":"21234",
    "sg:province":"MD",
    "sg:tags":[
        "homes-intermediate"
    ],
    "wof:name":"Open Arms Assistant Living",
    "wof:placetype":"venue"
},
  "geometry": {"coordinates":[-76.57281,39.378489],"type":"Point"}
}