{
  "type": "Feature",
  "properties": {
    "addr:full":"14350 Solomons Island Rd S Solomons MD 20688",
    "addr:housenumber":"14350",
    "addr:postcode":"20688",
    "addr:street":"Solomons Island Rd",
    "iso:country":"US",
    "sg:address":"14350 Solomons Island Rd S",
    "sg:city":"Solomons",
    "sg:classifiers":[
        {
            "category":"Restaurant",
            "type":"Food & Drink"
        }
    ],
    "sg:phone":"+1 410 326 3877",
    "sg:postcode":"20688",
    "sg:province":"MD",
    "wof:name":"Cd Cafe the",
    "wof:placetype":"venue"
},
  "geometry": {"coordinates":[-76.466103,38.344299],"type":"Point"}
}