{
  "type": "Feature",
  "properties": {
    "iso:country":"US",
    "sg:address":"9855 Washington Blvd N",
    "sg:city":"Laurel",
    "sg:classifiers":[
        {
            "category":"Shopping",
            "subcategory":"Optical Goods",
            "type":"Retail Goods"
        },
        {
            "category":"Health Services",
            "subcategory":"Optometrist",
            "type":"Services"
        }
    ],
    "sg:phone":"+1 301 776 1515",
    "sg:postcode":"20723",
    "sg:province":"MD",
    "sg:tags":[
        "repair"
    ],
    "wof:name":"Quick Fix Eyeglass Repair",
    "wof:placetype":"venue"
},
  "geometry": {"coordinates":[-76.83253499999999,39.115197],"type":"Point"}
}