{
  "type": "Feature",
  "properties": {
    "addr:full":"12451 Garrett Hwy Oakland MD 21550",
    "addr:housenumber":"12451",
    "addr:postcode":"21550",
    "addr:street":"Garrett Hwy",
    "iso:country":"US",
    "sg:address":"12451 Garrett Hwy",
    "sg:city":"Oakland",
    "sg:classifiers":[
        {
            "category":"Utilities",
            "subcategory":"Mobile Phone",
            "type":"Services"
        },
        {
            "category":"Shopping",
            "subcategory":"Mobile Phones",
            "type":"Retail Goods"
        }
    ],
    "sg:postcode":"21550",
    "sg:province":"MD",
    "sg:tags":[
        "supply",
        "communication",
        "telephone",
        "wireless",
        "equipment",
        "cellular"
    ],
    "sg:website":"http://clickserve.dartsearch.net/link/click?lid=43000000329024651",
    "wof:name":"U.S. Cellular",
    "wof:placetype":"venue"
},
  "geometry": {"coordinates":[-79.399877,39.419532],"type":"Point"}
}