{
  "type": "Feature",
  "properties": {
    "addr:full":"6524 Radiant Gleam Way Clarksville MD 21029",
    "addr:housenumber":"6524",
    "addr:postcode":"21029",
    "addr:street":"Radiant Gleam Way",
    "iso:country":"US",
    "sg:address":"6524 Radiant Gleam Way",
    "sg:city":"Clarksville",
    "sg:classifiers":[
        {
            "category":"Professional",
            "subcategory":"Management & Consulting",
            "type":"Services"
        }
    ],
    "sg:phone":"+1 410 531 0452",
    "sg:postcode":"21029",
    "sg:province":"MD",
    "wof:name":"Kathryn Grad & Assoc Inc",
    "wof:placetype":"venue"
},
  "geometry": {"coordinates":[-76.931996,39.192753],"type":"Point"}
}