{
  "type": "Feature",
  "properties": {
    "addr:full":"3511 Bussard Rd Middletown MD 21769",
    "addr:postcode":"3511;21769",
    "addr:street":"Bussard Rd",
    "iso:country":"US",
    "sg:address":"3511 Bussard Rd",
    "sg:city":"Middletown",
    "sg:phone":"+1 301 371 6867",
    "sg:postcode":"21769",
    "sg:province":"MD",
    "sg:tags":[
        "farm",
        "corn",
        "soybean"
    ],
    "wof:name":"Hickoryvale Farms",
    "wof:placetype":"venue"
},
  "geometry": {"coordinates":[-77.547012,39.420623],"type":"Point"}
}