{
  "type": "Feature",
  "properties": {
    "addr:full":"1934 Cedar Ln Dundalk MD 21222",
    "addr:housenumber":"1934",
    "addr:postcode":"21222",
    "addr:street":"Cedar Ln",
    "iso:country":"US",
    "sg:address":"1934 Cedar Ln",
    "sg:city":"Dundalk",
    "sg:classifiers":[
        {
            "category":"Marine",
            "type":"Transportation"
        }
    ],
    "sg:phone":"+1 410 633 2103",
    "sg:postcode":"21222",
    "sg:province":"MD",
    "sg:tags":[
        "towing"
    ],
    "wof:name":"Marine Towing",
    "wof:placetype":"venue"
},
  "geometry": {"coordinates":[-76.522336,39.274009],"type":"Point"}
}