{
  "type": "Feature",
  "properties": {
    "addr:full":"4600 East West Hwy Ste 201 Bethesda MD 20814",
    "addr:housenumber":"4600",
    "addr:postcode":"20814",
    "addr:street":"East West Hwy Ste 201",
    "iso:country":"US",
    "sg:address":"4600 East West Hwy Ste 201",
    "sg:city":"Bethesda",
    "sg:classifiers":[
        {
            "category":"Professional",
            "subcategory":"Lawyer & Legal Services",
            "type":"Services"
        }
    ],
    "sg:phone":"+1 301 652 7332",
    "sg:postcode":"20814",
    "sg:province":"MD",
    "wof:name":"Montedonico Hamilton & Altman PC",
    "wof:placetype":"venue"
},
  "geometry": {"coordinates":[-77.092707,38.98487],"type":"Point"}
}