{
  "type": "Feature",
  "properties": {
    "iso:country":"US",
    "sg:address":"3416 Donnell Dr",
    "sg:city":"Forestville",
    "sg:classifiers":[
        {
            "category":"Shopping",
            "subcategory":"Pawn Shop",
            "type":"Retail Goods"
        }
    ],
    "sg:phone":"+1 301 736 7246",
    "sg:postcode":"20747",
    "sg:province":"MD",
    "wof:name":"A-1 Pawnbrokers 4",
    "wof:placetype":"venue"
},
  "geometry": {"coordinates":[-76.884613,38.844584],"type":"Point"}
}