{
  "type": "Feature",
  "properties": {
    "addr:full":"300 E Cromwell St Baltimore MD 21230",
    "addr:housenumber":"300",
    "addr:postcode":"21230",
    "addr:street":"E Cromwell St",
    "iso:country":"US",
    "sg:address":"300 E Cromwell St",
    "sg:city":"Baltimore",
    "sg:classifiers":[
        {
            "category":"Communications",
            "subcategory":"Newspaper",
            "type":"Services"
        }
    ],
    "sg:phone":"+1 410 347 0891",
    "sg:postcode":"21230",
    "sg:province":"MD",
    "sg:tags":[
        "print",
        "medium"
    ],
    "wof:name":"Baltimore Sunpapers",
    "wof:placetype":"venue"
},
  "geometry": {"coordinates":[-76.610585,39.262547],"type":"Point"}
}