{
  "type": "Feature",
  "properties": {
    "iso:country":"US",
    "sg:address":"3314 Hampton Point Dr Apt B",
    "sg:city":"Silver Spring",
    "sg:classifiers":[
        {
            "category":"Community Center",
            "type":"Public Place"
        }
    ],
    "sg:phone":"+1 301 497 6075",
    "sg:postcode":"20904",
    "sg:province":"MD",
    "sg:tags":[
        "medical"
    ],
    "wof:name":"Sunset Healthcare Inc",
    "wof:placetype":"venue"
},
  "geometry": {"coordinates":[-76.94064400000001,39.077403],"type":"Point"}
}