{
  "type": "Feature",
  "properties": {
    "iso:country":"US",
    "sg:address":"1 E North Ave",
    "sg:city":"Baltimore",
    "sg:classifiers":[
        {
            "category":"Building & Trades",
            "subcategory":"Locksmith",
            "type":"Services"
        }
    ],
    "sg:phone":"+1 443 378 3802",
    "sg:postcode":"21202",
    "sg:province":"MD",
    "sg:tags":[
        "key"
    ],
    "wof:name":"A 24 Hour Emergency Locksmith",
    "wof:placetype":"venue"
},
  "geometry": {"coordinates":[-76.616389,39.311153],"type":"Point"}
}