{
  "type": "Feature",
  "properties": {
    "iso:country":"US",
    "sg:address":"399 Laburnum Rd",
    "sg:city":"Edgewood",
    "sg:classifiers":[
        {
            "category":"Professional",
            "type":"Services"
        }
    ],
    "sg:phone":"+1 410 676 8462",
    "sg:postcode":"21040",
    "sg:province":"MD",
    "sg:tags":[
        "establishment"
    ],
    "wof:name":"Willoughgy Woods Homeowners",
    "wof:placetype":"venue"
},
  "geometry": {"coordinates":[-76.271624,39.431166],"type":"Point"}
}