{
  "type": "Feature",
  "properties": {
    "iso:country":"US",
    "sg:address":"7500 Queen Anne Dr",
    "sg:city":"Parkville",
    "sg:classifiers":[
        {
            "category":"Arena",
            "subcategory":"Sports Club",
            "type":"Entertainment"
        },
        {
            "category":"Sports & Exercise",
            "subcategory":"Sports Center",
            "type":"Entertainment"
        },
        {
            "category":"Sports & Exercise",
            "subcategory":"Swimming Pool",
            "type":"Entertainment"
        }
    ],
    "sg:phone":"+1 410 668 9240",
    "sg:postcode":"21234",
    "sg:province":"MD",
    "sg:tags":[
        "pools-private"
    ],
    "wof:name":"Hillcrest Swim Club",
    "wof:placetype":"venue"
},
  "geometry": {"coordinates":[-76.554733,39.376019],"type":"Point"}
}