{
  "type": "Feature",
  "properties": {
    "iso:country":"US",
    "sg:address":"111 River Rd",
    "sg:city":"Chesapeake City",
    "sg:classifiers":[
        {
            "category":"Recreation",
            "subcategory":"Marina",
            "type":"Entertainment"
        }
    ],
    "sg:phone":"+1 410 885 5656",
    "sg:postcode":"21915",
    "sg:province":"MD",
    "wof:name":"North Marina Harbour Inc",
    "wof:placetype":"venue"
},
  "geometry": {"coordinates":[-75.87549300000001,39.511982],"type":"Point"}
}