{
  "type": "Feature",
  "properties": {
    "iso:country":"US",
    "sg:address":"7908 Fernham Ln",
    "sg:city":"District Heights",
    "sg:classifiers":[
        {
            "category":"Food & Beverages",
            "subcategory":"Groceries & Convenience Stores",
            "type":"Retail Goods"
        }
    ],
    "sg:phone":"+1 301 420 1088",
    "sg:postcode":"20747",
    "sg:province":"MD",
    "sg:website":"www.hosindia.com",
    "wof:name":"House of Spices",
    "wof:placetype":"venue"
},
  "geometry": {"coordinates":[-76.868202,38.846699],"type":"Point"}
}