{
  "type": "Feature",
  "properties": {
    "addr:full":"8911 Skyrock Ct Columbia MD 21046",
    "addr:housenumber":"8911",
    "addr:postcode":"21046",
    "addr:street":"Skyrock Ct",
    "iso:country":"US",
    "sg:address":"8911 Skyrock Ct",
    "sg:city":"Columbia",
    "sg:classifiers":[
        {
            "category":"Building & Trades",
            "subcategory":"Locksmith",
            "type":"Services"
        }
    ],
    "sg:phone":"+1 301 596 7595",
    "sg:postcode":"21046",
    "sg:province":"MD",
    "sg:tags":[
        "key"
    ],
    "wof:name":"Haga R A",
    "wof:placetype":"venue"
},
  "geometry": {"coordinates":[-76.855107,39.165581],"type":"Point"}
}