{
  "type": "Feature",
  "properties": {
    "iso:country":"US",
    "sg:address":"3508 Round Hollow Rd",
    "sg:city":"Pikesville",
    "sg:classifiers":[
        {
            "category":"Professional",
            "subcategory":"Management & Consulting",
            "type":"Services"
        }
    ],
    "sg:phone":"+1 410 486 2170",
    "sg:postcode":"21208",
    "sg:province":"MD",
    "sg:tags":[
        "business"
    ],
    "wof:name":"Rona E Lewis",
    "wof:placetype":"venue"
},
  "geometry": {"coordinates":[-76.716795,39.389254],"type":"Point"}
}