{
  "type": "Feature",
  "properties": {
    "addr:full":"5720 Executive Dr Catonsville MD 21228",
    "addr:housenumber":"5720",
    "addr:postcode":"21228",
    "addr:street":"Executive Dr",
    "iso:country":"US",
    "sg:address":"5720 Executive Dr",
    "sg:city":"Catonsville",
    "sg:classifiers":[
        {
            "category":"Building & Trades",
            "subcategory":"Landscaping Services",
            "type":"Services"
        },
        {
            "category":"Health Services",
            "subcategory":"Nursing And Care Facility",
            "type":"Services"
        }
    ],
    "sg:phone":"+1 443 543 2152",
    "sg:postcode":"21228",
    "sg:province":"MD",
    "sg:tags":[
        "personal",
        "home",
        "aged",
        "homes-institutional"
    ],
    "sg:website":"http://www.ohiomentor.com",
    "wof:name":"Rem Maryland",
    "wof:placetype":"venue"
},
  "geometry": {"coordinates":[-76.73157399999999,39.28374],"type":"Point"}
}