{
  "type": "Feature",
  "properties": {
    "addr:full":"11156 Cedarwood Dr Rockville MD 20852",
    "addr:housenumber":"11156",
    "addr:postcode":"20852",
    "addr:street":"Cedarwood Dr",
    "iso:country":"US",
    "sg:address":"11156 Cedarwood Dr",
    "sg:city":"Rockville",
    "sg:classifiers":[
        {
            "category":"Professional",
            "subcategory":"Management & Consulting",
            "type":"Services"
        }
    ],
    "sg:phone":"+1 301 984 9775",
    "sg:postcode":"20852",
    "sg:province":"MD",
    "wof:name":"Insignio Consulting LLC",
    "wof:placetype":"venue"
},
  "geometry": {"coordinates":[-77.12196,39.036255],"type":"Point"}
}