{
  "type": "Feature",
  "properties": {
    "addr:full":"10104 River Rd Potomac MD 20854",
    "addr:housenumber":"10104",
    "addr:postcode":"20854",
    "addr:street":"River Rd",
    "iso:country":"US",
    "sg:address":"10104 River Rd",
    "sg:city":"Potomac",
    "sg:classifiers":[
        {
            "category":"Building & Trades",
            "subcategory":"Locksmith",
            "type":"Services"
        }
    ],
    "sg:phone":"+1 301 841 6316",
    "sg:postcode":"20854",
    "sg:province":"MD",
    "sg:tags":[
        "key"
    ],
    "wof:name":"Locksmith & Locks-24 7 Emergency",
    "wof:placetype":"venue"
},
  "geometry": {"coordinates":[-77.208186,39.01728],"type":"Point"}
}