{
  "type": "Feature",
  "properties": {
    "iso:country":"US",
    "sg:address":"3351 Montrose Rd",
    "sg:city":"Indian Head",
    "sg:classifiers":[
        {
            "category":"Shopping",
            "subcategory":"Computers & Home Electronics",
            "type":"Retail Goods"
        }
    ],
    "sg:phone":"+1 301 870 8164",
    "sg:postcode":"20640",
    "sg:province":"MD",
    "sg:tags":[
        "software"
    ],
    "sg:website":"www.grpa.com",
    "wof:name":"G R Patel & Assoc Inc",
    "wof:placetype":"venue"
},
  "geometry": {"coordinates":[-77.098851,38.619976],"type":"Point"}
}