{
  "type": "Feature",
  "properties": {
    "addr:full":"7101 Democracy Blvd Bethesda MD 20817",
    "addr:housenumber":"7101",
    "addr:postcode":"20817",
    "addr:street":"Democracy Blvd",
    "iso:country":"US",
    "sg:address":"7101 Democracy Blvd",
    "sg:city":"Bethesda",
    "sg:classifiers":[
        {
            "category":"Building & Trades",
            "subcategory":"Locksmith",
            "type":"Services"
        }
    ],
    "sg:phone":"+1 240 383 5023",
    "sg:postcode":"20817",
    "sg:province":"MD",
    "sg:tags":[
        "key"
    ],
    "wof:name":"Locksmith",
    "wof:placetype":"venue"
},
  "geometry": {"coordinates":[-77.14811400000001,39.022429],"type":"Point"}
}