{
  "type": "Feature",
  "properties": {
    "iso:country":"US",
    "sg:address":"4104 Evans Chapel Rd",
    "sg:city":"Baltimore",
    "sg:classifiers":[
        {
            "category":"Travel",
            "subcategory":"Travel Agent",
            "type":"Entertainment"
        }
    ],
    "sg:phone":"+1 410 889 6188",
    "sg:postcode":"21211",
    "sg:province":"MD",
    "sg:tags":[
        "agency",
        "services-commercial"
    ],
    "wof:name":"The Travel Agent",
    "wof:placetype":"venue"
},
  "geometry": {"coordinates":[-76.634109,39.337624],"type":"Point"}
}