{
  "type": "Feature",
  "properties": {
    "addr:full":"529 Londontown Rd Edgewater MD 21037",
    "addr:housenumber":"529",
    "addr:postcode":"21037",
    "addr:street":"Londontown Rd",
    "iso:country":"US",
    "sg:address":"529 Londontown Rd",
    "sg:city":"Edgewater",
    "sg:classifiers":[
        {
            "category":"Real Estate",
            "subcategory":"Real Estate Agent",
            "type":"Services"
        }
    ],
    "sg:phone":"+1 410 956 6262",
    "sg:postcode":"21037",
    "sg:province":"MD",
    "wof:name":"Londontowne Property Owners",
    "wof:placetype":"venue"
},
  "geometry": {"coordinates":[-76.547011,38.935272],"type":"Point"}
}