{
  "type": "Feature",
  "properties": {
    "addr:full":"3426 Tulane Dr Hyattsville MD 20783",
    "addr:housenumber":"3426",
    "addr:postcode":"20783",
    "addr:street":"Tulane Dr",
    "iso:country":"US",
    "sg:address":"3426 Tulane Dr",
    "sg:city":"Hyattsville",
    "sg:classifiers":[
        {
            "category":"Professional",
            "subcategory":"Management & Consulting",
            "type":"Services"
        }
    ],
    "sg:phone":"+1 301 422 0147",
    "sg:postcode":"20783",
    "sg:province":"MD",
    "sg:tags":[
        "fuel"
    ],
    "wof:name":"Southern Management Corp",
    "wof:placetype":"venue"
},
  "geometry": {"coordinates":[-76.956687,38.984902],"type":"Point"}
}