{
  "type": "Feature",
  "properties": {
    "addr:full":"23328 Red Oak Ct California MD 20619",
    "addr:housenumber":"23328",
    "addr:postcode":"20619",
    "addr:street":"Red Oak Ct",
    "iso:country":"US",
    "sg:address":"23328 Red Oak Ct",
    "sg:city":"California",
    "sg:classifiers":[
        {
            "category":"Professional",
            "type":"Services"
        }
    ],
    "sg:phone":"+1 301 862 2474",
    "sg:postcode":"20619",
    "sg:province":"MD",
    "wof:name":"Alexander Rivera",
    "wof:placetype":"venue"
},
  "geometry": {"coordinates":[-76.534266,38.306863],"type":"Point"}
}