{
  "type": "Feature",
  "properties": {
    "iso:country":"US",
    "sg:address":"5129 Roland Ave",
    "sg:city":"Baltimore",
    "sg:classifiers":[
        {
            "category":"Professional",
            "subcategory":"Art Services",
            "type":"Services"
        },
        {
            "category":"Communications",
            "type":"Services"
        }
    ],
    "sg:phone":"+1 877 509 0441",
    "sg:postcode":"21210",
    "sg:province":"MD",
    "sg:tags":[
        "web",
        "graphic",
        "design"
    ],
    "sg:website":"21petals.com/webdesignquote/balt...",
    "wof:name":"21Petals Web Design",
    "wof:placetype":"venue"
},
  "geometry": {"coordinates":[-76.634485,39.356321],"type":"Point"}
}