{
  "type": "Feature",
  "properties": {
    "iso:country":"US",
    "sg:address":"7731 Eastpoint Mall",
    "sg:city":"Baltimore",
    "sg:classifiers":[
        {
            "category":"Restaurant",
            "type":"Food & Drink"
        }
    ],
    "sg:phone":"+1 410 282 3455",
    "sg:postcode":"21224",
    "sg:province":"MD",
    "sg:website":"www.mcdonalds.com",
    "wof:name":"McDonald's",
    "wof:placetype":"venue"
},
  "geometry": {"coordinates":[-76.51149700000001,39.294601],"type":"Point"}
}