{
  "type": "Feature",
  "properties": {
    "addr:full":"13818 Missouri Ave Brandywine MD 20613",
    "addr:housenumber":"13818",
    "addr:postcode":"20613",
    "addr:street":"Missouri Ave",
    "iso:country":"US",
    "sg:address":"13818 Missouri Ave",
    "sg:city":"Brandywine",
    "sg:classifiers":[
        {
            "category":"Shopping",
            "subcategory":"Hobbies, Toys, & Games",
            "type":"Retail Goods"
        },
        {
            "category":"Shopping",
            "subcategory":"Crafts & Fabrics",
            "type":"Retail Goods"
        }
    ],
    "sg:phone":"+1 301 782 7346",
    "sg:postcode":"20613",
    "sg:province":"MD",
    "sg:tags":[
        "shop",
        "hobby",
        "model",
        "supplies-wholesale",
        "manufacturer"
    ],
    "wof:name":"Ml Crafts",
    "wof:placetype":"venue"
},
  "geometry": {"coordinates":[-76.852396,38.698582],"type":"Point"}
}