{
  "type": "Feature",
  "properties": {
    "addr:full":"1789 Olive St Capitol Heights MD 20743",
    "addr:housenumber":"1789",
    "addr:postcode":"20743",
    "addr:street":"Olive St",
    "iso:country":"US",
    "sg:address":"1789 Olive St",
    "sg:city":"Capitol Heights",
    "sg:classifiers":[
        {
            "category":"Manufacturing",
            "subcategory":"Printing",
            "type":"Manufacturing & Wholesale Goods"
        }
    ],
    "sg:phone":"+1 301 773 6340",
    "sg:postcode":"20743",
    "sg:province":"MD",
    "sg:tags":[
        "commercial"
    ],
    "sg:website":"www.cantrellcutter.com",
    "wof:name":"Cantrell-Cutter Printing Inc",
    "wof:placetype":"venue"
},
  "geometry": {"coordinates":[-76.930413,38.912664],"type":"Point"}
}