{
  "type": "Feature",
  "properties": {
    "iso:country":"US",
    "sg:address":"313 Rosslare Dr",
    "sg:city":"Arnold",
    "sg:classifiers":[
        {
            "category":"Real Estate",
            "subcategory":"Real Estate Services",
            "type":"Services"
        },
        {
            "category":"Real Estate",
            "subcategory":"Real Estate Agent",
            "type":"Services"
        }
    ],
    "sg:phone":"+1 410 544 5372",
    "sg:postcode":"21012",
    "sg:province":"MD",
    "sg:tags":[
        "buyer",
        "broker"
    ],
    "wof:name":"Creighton Realtors",
    "wof:placetype":"venue"
},
  "geometry": {"coordinates":[-76.497304,39.044171],"type":"Point"}
}