{
  "type": "Feature",
  "properties": {
    "iso:country":"US",
    "sg:address":"900 Olney Spring Rd",
    "sg:city":"Sandy Spring",
    "sg:classifiers":[
        {
            "category":"Wholesale",
            "subcategory":"Computers",
            "type":"Manufacturing & Wholesale Goods"
        },
        {
            "category":"Professional",
            "subcategory":"Computer Services",
            "type":"Services"
        }
    ],
    "sg:phone":"+1 301 570 8086",
    "sg:postcode":"20860",
    "sg:province":"MD",
    "sg:tags":[
        "repair"
    ],
    "sg:website":"www.PCsAndServers.com",
    "wof:name":"PCs And Servers",
    "wof:placetype":"venue"
},
  "geometry": {"coordinates":[-77.026059,39.149506],"type":"Point"}
}