{
  "type": "Feature",
  "properties": {
    "iso:country":"US",
    "sg:address":"15400 Calhoun Dr",
    "sg:city":"Derwood",
    "sg:classifiers":[
        {
            "category":"Real Estate",
            "subcategory":"Real Estate Services",
            "type":"Services"
        }
    ],
    "sg:phone":"+1 301 340 0901",
    "sg:postcode":"20855",
    "sg:province":"MD",
    "sg:tags":[
        "vacancy",
        "rental",
        "listing"
    ],
    "sg:website":"http://www.psbusinessparks.com",
    "wof:name":"Metro Park Iii",
    "wof:placetype":"venue"
},
  "geometry": {"coordinates":[-77.149162,39.106529],"type":"Point"}
}