{
  "type": "Feature",
  "properties": {
    "iso:country":"US",
    "sg:address":"5111 Pegasus Ct Ste H",
    "sg:city":"Frederick",
    "sg:classifiers":[
        {
            "category":"Wholesale",
            "subcategory":"Machinery & Supplies",
            "type":"Manufacturing & Wholesale Goods"
        }
    ],
    "sg:phone":"+1 301 662 6835",
    "sg:postcode":"21704",
    "sg:province":"MD",
    "sg:tags":[
        "instrument",
        "scientific",
        "apparatus"
    ],
    "wof:name":"Microbiology International",
    "wof:placetype":"venue"
},
  "geometry": {"coordinates":[-77.40922500000001,39.371304],"type":"Point"}
}