{
  "type": "Feature",
  "properties": {
    "addr:full":"11027 Lake Arbor Way Bowie MD 20721",
    "addr:housenumber":"11027",
    "addr:postcode":"20721",
    "addr:street":"Lake Arbor Way",
    "iso:country":"US",
    "sg:address":"11027 Lake Arbor Way",
    "sg:city":"Bowie",
    "sg:classifiers":[
        {
            "category":"Arts & Performance",
            "subcategory":"Theater",
            "type":"Entertainment"
        }
    ],
    "sg:phone":"+1 301 499 4891",
    "sg:postcode":"20721",
    "sg:province":"MD",
    "sg:tags":[
        "musician"
    ],
    "wof:name":"Carl Pink",
    "wof:placetype":"venue"
},
  "geometry": {"coordinates":[-76.810451,38.902122],"type":"Point"}
}