{
  "type": "Feature",
  "properties": {
    "iso:country":"US",
    "sg:address":"4405 East West Hwy Ste 209",
    "sg:city":"Bethesda",
    "sg:classifiers":[
        {
            "category":"Health Services",
            "subcategory":"Clinic",
            "type":"Services"
        }
    ],
    "sg:phone":"+1 301 907 0877",
    "sg:postcode":"20814",
    "sg:province":"MD",
    "sg:tags":[
        "counseling",
        "mental"
    ],
    "wof:name":"Carol Barnaby",
    "wof:placetype":"venue"
},
  "geometry": {"coordinates":[-77.089583,38.985276],"type":"Point"}
}