{
  "type": "Feature",
  "properties": {
    "iso:country":"US",
    "sg:address":"112 Alessandra Ct",
    "sg:city":"Frederick",
    "sg:classifiers":[
        {
            "category":"Professional",
            "subcategory":"Management & Consulting",
            "type":"Services"
        }
    ],
    "sg:phone":"+1 301 662 2100",
    "sg:postcode":"21702",
    "sg:province":"MD",
    "wof:name":"Omni Media Inc",
    "wof:placetype":"venue"
},
  "geometry": {"coordinates":[-77.43323100000001,39.420514],"type":"Point"}
}