{
  "type": "Feature",
  "properties": {
    "iso:country":"US",
    "sg:address":"209 Blue Ball Ave",
    "sg:city":"Elkton",
    "sg:classifiers":[
        {
            "category":"Building & Trades",
            "subcategory":"Construction",
            "type":"Services"
        }
    ],
    "sg:phone":"+1 410 392 6636",
    "sg:postcode":"21921",
    "sg:province":"MD",
    "sg:tags":[
        "marking",
        "maintenance",
        "parking"
    ],
    "sg:website":"www.townofelkton.org",
    "wof:name":"Elkton Public Works Dept",
    "wof:placetype":"venue"
},
  "geometry": {"coordinates":[-75.839674,39.607074],"type":"Point"}
}