{
  "type": "Feature",
  "properties": {
    "iso:country":"US",
    "sg:address":"18181 Bowles Rd",
    "sg:city":"Lexington Park",
    "sg:classifiers":[
        {
            "category":"Building & Trades",
            "subcategory":"Construction",
            "type":"Services"
        }
    ],
    "sg:phone":"+1 301 862 3115",
    "sg:postcode":"20653",
    "sg:province":"MD",
    "sg:tags":[
        "house"
    ],
    "wof:name":"Alexander Homes Inc",
    "wof:placetype":"venue"
},
  "geometry": {"coordinates":[-76.428884,38.166227],"type":"Point"}
}