{
  "type": "Feature",
  "properties": {
    "iso:country":"US",
    "sg:address":"31381 Retirement Rd",
    "sg:city":"Cordova",
    "sg:classifiers":[
        {
            "category":"Manufacturing",
            "subcategory":"Building Materials",
            "type":"Manufacturing & Wholesale Goods"
        }
    ],
    "sg:phone":"+1 410 364 5718",
    "sg:postcode":"21625",
    "sg:province":"MD",
    "sg:tags":[
        "pipe-wholesale",
        "manufacturer"
    ],
    "wof:name":"Nq Enterprises",
    "wof:placetype":"venue"
},
  "geometry": {"coordinates":[-75.986557,38.882937],"type":"Point"}
}