{
  "type": "Feature",
  "properties": {
    "iso:country":"US",
    "sg:address":"23211 Linden Vale Dr",
    "sg:city":"Clarksburg",
    "sg:classifiers":[
        {
            "category":"Banks & Credit Unions",
            "subcategory":"Financial Services",
            "type":"Services"
        }
    ],
    "sg:phone":"+1 301 972 5371",
    "sg:postcode":"20871",
    "sg:province":"MD",
    "sg:tags":[
        "financing"
    ],
    "wof:name":"Apl Funding",
    "wof:placetype":"venue"
},
  "geometry": {"coordinates":[-77.256208,39.241145],"type":"Point"}
}