{
  "type": "Feature",
  "properties": {
    "addr:full":"7401 Wisconsin Ave Bethesda MD 20814",
    "addr:housenumber":"7401",
    "addr:postcode":"20814",
    "addr:street":"Wisconsin Ave",
    "iso:country":"US",
    "sg:address":"7401 Wisconsin Ave",
    "sg:city":"Bethesda",
    "sg:classifiers":[
        {
            "category":"Real Estate",
            "subcategory":"Real Estate Agent",
            "type":"Services"
        }
    ],
    "sg:phone":"+1 301 656 7979",
    "sg:postcode":"20814",
    "sg:province":"MD",
    "wof:name":"Ziff Akman Real Estate Group",
    "wof:placetype":"venue"
},
  "geometry": {"coordinates":[-77.094054,38.984134],"type":"Point"}
}