{
  "type": "Feature",
  "properties": {
    "iso:country":"US",
    "sg:address":"1035 W 41st St",
    "sg:city":"Baltimore",
    "sg:classifiers":[
        {
            "category":"Retail",
            "subcategory":"Auto Repair",
            "type":"Services"
        }
    ],
    "sg:phone":"+1 410 889 6748",
    "sg:postcode":"21211",
    "sg:province":"MD",
    "sg:tags":[
        "repairing",
        "automobile"
    ],
    "sg:website":"www.brentwoodauto.com/default.as...",
    "wof:name":"Brentwood Foreign Auto Service",
    "wof:placetype":"venue"
},
  "geometry": {"coordinates":[-76.635803,39.3377],"type":"Point"}
}