{
  "type": "Feature",
  "properties": {
    "iso:country":"US",
    "sg:address":"213 W Main St",
    "sg:city":"Salisbury",
    "sg:classifiers":[
        {
            "category":"Restaurant",
            "type":"Food & Drink"
        }
    ],
    "sg:phone":"+1 410 341 0606",
    "sg:postcode":"21801",
    "sg:province":"MD",
    "wof:name":"City Bistro",
    "wof:placetype":"venue"
},
  "geometry": {"coordinates":[-75.602121,38.365382],"type":"Point"}
}