{
  "type": "Feature",
  "properties": {
    "iso:country":"US",
    "sg:address":"795 Aquahart Rd",
    "sg:city":"Glen Burnie",
    "sg:classifiers":[
        {
            "category":"Professional",
            "subcategory":"Computer Services",
            "type":"Services"
        }
    ],
    "sg:phone":"+1 410 766 3585",
    "sg:postcode":"21061",
    "sg:province":"MD",
    "sg:tags":[
        "consultant",
        "designer"
    ],
    "wof:name":"Spectrum Computer Svc Inc",
    "wof:placetype":"venue"
},
  "geometry": {"coordinates":[-76.620098,39.151017],"type":"Point"}
}