{
  "type": "Feature",
  "properties": {
    "addr:full":"807 Carter Rd Rockville MD 20852",
    "addr:housenumber":"807",
    "addr:postcode":"20852",
    "addr:street":"Carter Rd",
    "iso:country":"US",
    "sg:address":"807 Carter Rd",
    "sg:city":"Rockville",
    "sg:classifiers":[
        {
            "category":"Professional",
            "type":"Services"
        }
    ],
    "sg:phone":"+1 301 309 1741",
    "sg:postcode":"20852",
    "sg:province":"MD",
    "sg:tags":[
        "editor"
    ],
    "wof:name":"Kernan Chaisson Edit Co",
    "wof:placetype":"venue"
},
  "geometry": {"coordinates":[-77.148048,39.071506],"type":"Point"}
}