{
  "type": "Feature",
  "properties": {
    "addr:full":"241 N Franklintown Rd Baltimore MD 21223",
    "addr:housenumber":"241",
    "addr:postcode":"21223",
    "addr:street":"N Franklintown Rd",
    "iso:country":"US",
    "sg:address":"241 N Franklintown Rd",
    "sg:city":"Baltimore",
    "sg:classifiers":[
        {
            "category":"Wholesale",
            "subcategory":"Medical Equipment & Supplies",
            "type":"Manufacturing & Wholesale Goods"
        }
    ],
    "sg:phone":"+1 410 945 0375",
    "sg:postcode":"21223",
    "sg:province":"MD",
    "sg:tags":[
        "hospital",
        "supplies-wholesale",
        "manufacturer"
    ],
    "wof:name":"Promotion Service Co Inc",
    "wof:placetype":"venue"
},
  "geometry": {"coordinates":[-76.660332,39.289977],"type":"Point"}
}