{
  "type": "Feature",
  "properties": {
    "iso:country":"US",
    "sg:address":"300 E Lombard St",
    "sg:city":"Baltimore",
    "sg:classifiers":[
        {
            "category":"Insurance",
            "subcategory":"Insurance Agent",
            "type":"Services"
        }
    ],
    "sg:phone":"+1 410 685 5845",
    "sg:postcode":"21202",
    "sg:province":"MD",
    "wof:name":"Royal Insurance Underwriting",
    "wof:placetype":"venue"
},
  "geometry": {"coordinates":[-76.61011499999999,39.287849],"type":"Point"}
}