{
  "type": "Feature",
  "properties": {
    "iso:country":"US",
    "sg:address":"310 Cameo Dr",
    "sg:city":"Hagerstown",
    "sg:classifiers":[
        {
            "category":"Social Services",
            "subcategory":"Adult Care",
            "type":"Services"
        }
    ],
    "sg:phone":"+1 301 766 9202",
    "sg:postcode":"21740",
    "sg:province":"MD",
    "sg:tags":[
        "home",
        "residential"
    ],
    "wof:name":"Eden Pines Assisted Living",
    "wof:placetype":"venue"
},
  "geometry": {"coordinates":[-77.69373299999999,39.636869],"type":"Point"}
}