{
  "type": "Feature",
  "properties": {
    "addr:full":"13 Amiel Ct Baltimore MD 21286",
    "addr:housenumber":"13",
    "addr:postcode":"21286",
    "addr:street":"Amiel Ct",
    "iso:country":"US",
    "sg:address":"13 Amiel Ct",
    "sg:city":"Baltimore",
    "sg:classifiers":[
        {
            "category":"Professional",
            "subcategory":"Accounting & Tax Preparation",
            "type":"Services"
        }
    ],
    "sg:phone":"+1 410 494 7028",
    "sg:postcode":"21286",
    "sg:province":"MD",
    "sg:tags":[
        "accountant"
    ],
    "wof:name":"Chan Ho Park CPA",
    "wof:placetype":"venue"
},
  "geometry": {"coordinates":[-76.56007,39.422872],"type":"Point"}
}