{
  "type": "Feature",
  "properties": {
    "addr:full":"3913 Leland St Chevy Chase MD 20815",
    "addr:housenumber":"3913",
    "addr:postcode":"20815",
    "addr:street":"Leland St",
    "iso:country":"US",
    "sg:address":"3913 Leland St",
    "sg:city":"Chevy Chase",
    "sg:classifiers":[
        {
            "category":"Professional",
            "type":"Services"
        }
    ],
    "sg:phone":"+1 301 986 0661",
    "sg:postcode":"20815",
    "sg:province":"MD",
    "wof:name":"Earl P & Reade Steinberg",
    "wof:placetype":"venue"
},
  "geometry": {"coordinates":[-77.07897699999999,38.985503],"type":"Point"}
}