{
  "type": "Feature",
  "properties": {
    "addr:full":"214 Churchwardens Rd Baltimore MD 21212",
    "addr:housenumber":"214",
    "addr:postcode":"21212",
    "addr:street":"Churchwardens Rd",
    "iso:country":"US",
    "sg:address":"214 Churchwardens Rd",
    "sg:city":"Baltimore",
    "sg:classifiers":[
        {
            "category":"Health Services",
            "subcategory":"Doctor",
            "type":"Services"
        }
    ],
    "sg:phone":"+1 410 435 5534",
    "sg:postcode":"21212",
    "sg:province":"MD",
    "wof:name":"Litrenta Frances MD",
    "wof:placetype":"venue"
},
  "geometry": {"coordinates":[-76.619202,39.364601],"type":"Point"}
}