{
  "type": "Feature",
  "properties": {
    "iso:country":"US",
    "sg:address":"2474 Cambridge Beltway",
    "sg:city":"Cambridge",
    "sg:classifiers":[
        {
            "category":"Government",
            "subcategory":"Office",
            "type":"Public Place"
        }
    ],
    "sg:phone":"+1 410 228 8569",
    "sg:postcode":"21613",
    "sg:province":"MD",
    "sg:tags":[
        "county",
        "resource"
    ],
    "wof:name":"Dorchester Commission Of Aging",
    "wof:placetype":"venue"
},
  "geometry": {"coordinates":[-76.094848,38.545848],"type":"Point"}
}