{
  "type": "Feature",
  "properties": {
    "addr:full":"8629 Liberty Rd Randallstown MD 21133",
    "addr:housenumber":"8629",
    "addr:postcode":"21133",
    "addr:street":"Liberty Rd",
    "iso:country":"US",
    "sg:address":"8629 Liberty Rd",
    "sg:city":"Randallstown",
    "sg:classifiers":[
        {
            "category":"Organizations",
            "subcategory":"Religious Organization",
            "type":"Services"
        }
    ],
    "sg:phone":"+1 410 655 9716",
    "sg:postcode":"21133",
    "sg:province":"MD",
    "wof:name":"Former & Latter Glory Assembly",
    "wof:placetype":"venue"
},
  "geometry": {"coordinates":[-76.78265399999999,39.362791],"type":"Point"}
}