{
  "type": "Feature",
  "properties": {
    "iso:country":"US",
    "sg:address":"4909 Cordell Ave",
    "sg:city":"Bethesda",
    "sg:classifiers":[
        {
            "category":"Real Estate",
            "subcategory":"Real Estate Services",
            "type":"Services"
        },
        {
            "category":"Real Estate",
            "subcategory":"Developer",
            "type":"Services"
        },
        {
            "category":"Real Estate",
            "subcategory":"Real Estate Agent",
            "type":"Services"
        }
    ],
    "sg:phone":"+1 301 718 1804",
    "sg:postcode":"20814",
    "sg:province":"MD",
    "sg:tags":[
        "management"
    ],
    "wof:name":"Stanford Properties Lc",
    "wof:placetype":"venue"
},
  "geometry": {"coordinates":[-77.09820000000001,38.989271],"type":"Point"}
}