{
  "type": "Feature",
  "properties": {
    "iso:country":"US",
    "sg:address":"101 W Ridgely Rd",
    "sg:city":"Lutherville",
    "sg:classifiers":[
        {
            "category":"Insurance",
            "subcategory":"Insurance Agent",
            "type":"Services"
        }
    ],
    "sg:phone":"+1 410 453 9744",
    "sg:postcode":"21093",
    "sg:province":"MD",
    "wof:name":"Community Insurance Assoc Inc",
    "wof:placetype":"venue"
},
  "geometry": {"coordinates":[-76.62486699999999,39.428886],"type":"Point"}
}