{
  "type": "Feature",
  "properties": {
    "addr:full":"46 Thomas Johnson Dr Frederick MD 21702",
    "addr:housenumber":"46",
    "addr:postcode":"21702",
    "addr:street":"Thomas Johnson Dr",
    "iso:country":"US",
    "sg:address":"46 Thomas Johnson Dr",
    "sg:city":"Frederick",
    "sg:classifiers":[
        {
            "category":"Health Services",
            "subcategory":"Clinic",
            "type":"Services"
        },
        {
            "category":"Community Center",
            "type":"Public Place"
        },
        {
            "category":"Health Services",
            "subcategory":"Hospital",
            "type":"Services"
        }
    ],
    "sg:phone":"+1 301 695 6777",
    "sg:postcode":"21702",
    "sg:province":"MD",
    "sg:tags":[
        "medical",
        "treatment",
        "cancer"
    ],
    "wof:name":"Cancer Care Center of Frederick",
    "wof:placetype":"venue"
},
  "geometry": {"coordinates":[-77.401068,39.453774],"type":"Point"}
}