{
  "type": "Feature",
  "properties": {
    "addr:full":"4224 Harford Ter Baltimore MD 21214",
    "addr:housenumber":"4224",
    "addr:postcode":"21214",
    "addr:street":"Harford Ter",
    "iso:country":"US",
    "sg:address":"4224 Harford Ter",
    "sg:city":"Baltimore",
    "sg:classifiers":[
        {
            "category":"Building & Trades",
            "subcategory":"Construction",
            "type":"Services"
        }
    ],
    "sg:phone":"+1 410 444 7462",
    "sg:postcode":"21214",
    "sg:province":"MD",
    "sg:tags":[
        "industrial",
        "contractors-commercial"
    ],
    "wof:name":"Camiel Interiors",
    "wof:placetype":"venue"
},
  "geometry": {"coordinates":[-76.574564,39.337752],"type":"Point"}
}