{
  "type": "Feature",
  "properties": {
    "iso:country":"US",
    "sg:address":"2 N Charles St",
    "sg:city":"Baltimore",
    "sg:classifiers":[
        {
            "category":"Real Estate",
            "subcategory":"Real Estate Services",
            "type":"Services"
        }
    ],
    "sg:phone":"+1 410 752 2955",
    "sg:postcode":"21201",
    "sg:province":"MD",
    "sg:tags":[
        "company",
        "title"
    ],
    "wof:name":"Fidelity National Title",
    "wof:placetype":"venue"
},
  "geometry": {"coordinates":[-76.615329,39.289972],"type":"Point"}
}