{
  "type": "Feature",
  "properties": {
    "iso:country":"US",
    "sg:address":"16020 Industrial Dr",
    "sg:city":"Gaithersburg",
    "sg:classifiers":[
        {
            "category":"Manufacturing",
            "subcategory":"Tools & Machinery",
            "type":"Manufacturing & Wholesale Goods"
        }
    ],
    "sg:phone":"+1 301 869 9800",
    "sg:postcode":"20877",
    "sg:province":"MD",
    "sg:tags":[
        "analytical",
        "laboratory",
        "mfg",
        "instrument"
    ],
    "wof:name":"Bioveris Corporation",
    "wof:placetype":"venue"
},
  "geometry": {"coordinates":[-77.18951,39.119142],"type":"Point"}
}