{
  "type": "Feature",
  "properties": {
    "addr:full":"4011 Vine St Capitol Heights MD 20743",
    "addr:housenumber":"4011",
    "addr:postcode":"20743",
    "addr:street":"Vine St",
    "iso:country":"US",
    "sg:address":"4011 Vine St",
    "sg:city":"Capitol Heights",
    "sg:classifiers":[
        {
            "category":"Retail",
            "subcategory":"Laundry & Dry Cleaning",
            "type":"Services"
        }
    ],
    "sg:phone":"+1 301 420 6908",
    "sg:postcode":"20743",
    "sg:province":"MD",
    "wof:name":"Murphys Carpet",
    "wof:placetype":"venue"
},
  "geometry": {"coordinates":[-76.93675399999999,38.869841],"type":"Point"}
}