{
  "type": "Feature",
  "properties": {
    "addr:full":"6301 Belmar Rd Baltimore MD 21201",
    "addr:housenumber":"6301",
    "addr:postcode":"21201",
    "addr:street":"Belmar Rd",
    "iso:country":"US",
    "sg:address":"6301 Belmar Rd",
    "sg:city":"Baltimore",
    "sg:classifiers":[
        {
            "category":"Banks & Credit Unions",
            "subcategory":"Bank",
            "type":"Services"
        },
        {
            "category":"Banks & Credit Unions",
            "subcategory":"Financial Services",
            "type":"Services"
        }
    ],
    "sg:phone":"+1 410 426 3050",
    "sg:postcode":"21201",
    "sg:province":"MD",
    "sg:tags":[
        "broker",
        "mortgage"
    ],
    "wof:name":"Hamilton Federal Bank",
    "wof:placetype":"venue"
},
  "geometry": {"coordinates":[-76.622597,39.2957],"type":"Point"}
}