{
  "type": "Feature",
  "properties": {
    "iso:country":"US",
    "sg:address":"9700 Reisterstown Rd",
    "sg:city":"Owings Mills",
    "sg:classifiers":[
        {
            "category":"Autos & Motor Vehicles",
            "subcategory":"Automobile Sales",
            "type":"Retail Goods"
        }
    ],
    "sg:phone":"+1 410 363 8700",
    "sg:postcode":"21117",
    "sg:province":"MD",
    "sg:tags":[
        "car",
        "dealer"
    ],
    "wof:name":"Honda Of Northwest",
    "wof:placetype":"venue"
},
  "geometry": {"coordinates":[-76.76144499999999,39.406343],"type":"Point"}
}