{
  "type": "Feature",
  "properties": {
    "addr:full":"7701 Chestnut Ln Bowie MD 20715",
    "addr:housenumber":"7701",
    "addr:postcode":"20715",
    "addr:street":"Chestnut Ln",
    "iso:country":"US",
    "sg:address":"7701 Chestnut Ln",
    "sg:city":"Bowie",
    "sg:classifiers":[
        {
            "category":"Professional",
            "subcategory":"Management & Consulting",
            "type":"Services"
        }
    ],
    "sg:phone":"+1 301 805 9117",
    "sg:postcode":"20715",
    "sg:province":"MD",
    "sg:tags":[
        "consultant"
    ],
    "wof:name":"Arcane Software Consulting Inc",
    "wof:placetype":"venue"
},
  "geometry": {"coordinates":[-76.77261799999999,38.997688],"type":"Point"}
}