{
  "type": "Feature",
  "properties": {
    "iso:country":"US",
    "sg:address":"7701 Chestnut Ln",
    "sg:city":"Bowie",
    "sg:classifiers":[
        {
            "category":"Professional",
            "subcategory":"Management & Consulting",
            "type":"Services"
        }
    ],
    "sg:phone":"+1 301 805 9117",
    "sg:postcode":"20715",
    "sg:province":"MD",
    "sg:tags":[
        "consultant"
    ],
    "wof:name":"Arcane Software Consulting Inc",
    "wof:placetype":"venue"
},
  "geometry": {"coordinates":[-76.772618,38.997688],"type":"Point"}
}