{
  "type": "Feature",
  "properties": {
    "addr:full":"5406 Burkittsville Rd Jefferson MD 21755",
    "addr:housenumber":"5406",
    "addr:postcode":"21755",
    "addr:street":"Burkittsville Rd",
    "iso:country":"US",
    "sg:address":"5406 Burkittsville Rd",
    "sg:city":"Jefferson",
    "sg:classifiers":[
        {
            "category":"Building & Trades",
            "subcategory":"Construction",
            "type":"Services"
        }
    ],
    "sg:phone":"+1 301 834 6236",
    "sg:postcode":"21755",
    "sg:province":"MD",
    "sg:tags":[
        "restoration",
        "cleaning",
        "patio",
        "deck"
    ],
    "wof:name":"M D Painting & Maintenance",
    "wof:placetype":"venue"
},
  "geometry": {"coordinates":[-77.637411,39.386134],"type":"Point"}
}