{
  "type": "Feature",
  "properties": {
    "addr:full":"411 N Warwick Ave Baltimore MD 21223",
    "addr:housenumber":"411",
    "addr:postcode":"21223",
    "addr:street":"N Warwick Ave",
    "iso:country":"US",
    "sg:address":"411 N Warwick Ave",
    "sg:city":"Baltimore",
    "sg:classifiers":[
        {
            "category":"Autos & Motor Vehicles",
            "subcategory":"Auto Supplies",
            "type":"Retail Goods"
        },
        {
            "category":"Retail",
            "subcategory":"Auto Repair",
            "type":"Services"
        }
    ],
    "sg:phone":"+1 410 945 0778",
    "sg:postcode":"21223",
    "sg:province":"MD",
    "sg:tags":[
        "wheel",
        "recap",
        "retread",
        "tire"
    ],
    "wof:name":"Dana's New & Used Tires",
    "wof:placetype":"venue"
},
  "geometry": {"coordinates":[-76.65630299999999,39.292801],"type":"Point"}
}