{
  "type": "Feature",
  "properties": {
    "addr:full":"213 W Pulaski Hwy Elkton MD 21921",
    "addr:housenumber":"213",
    "addr:postcode":"21921",
    "addr:street":"W Pulaski Hwy",
    "iso:country":"US",
    "sg:address":"213 W Pulaski Hwy",
    "sg:city":"Elkton",
    "sg:classifiers":[
        {
            "category":"Retail",
            "subcategory":"Auto Repair",
            "type":"Services"
        }
    ],
    "sg:phone":"+1 410 398 4600",
    "sg:postcode":"21921",
    "sg:province":"MD",
    "sg:tags":[
        "truck"
    ],
    "wof:name":"Triumph Truck Repair",
    "wof:placetype":"venue"
},
  "geometry": {"coordinates":[-75.83644200000001,39.602923],"type":"Point"}
}