{
  "type": "Feature",
  "properties": {
    "iso:country":"US",
    "sg:address":"211 W Read St",
    "sg:city":"Baltimore",
    "sg:classifiers":[
        {
            "category":"Cinema",
            "subcategory":"Movie Rental",
            "type":"Entertainment"
        }
    ],
    "sg:phone":"+1 410 728 8273",
    "sg:postcode":"21201",
    "sg:province":"MD",
    "sg:tags":[
        "game",
        "video"
    ],
    "wof:name":"Read Street Video",
    "wof:placetype":"venue"
},
  "geometry": {"coordinates":[-76.618797,39.300301],"type":"Point"}
}