{
  "type": "Feature",
  "properties": {
    "addr:full":"961 Linwood Rd Hagerstown MD 21740",
    "addr:housenumber":"961",
    "addr:postcode":"21740",
    "addr:street":"Linwood Rd",
    "iso:country":"US",
    "sg:address":"961 Linwood Rd",
    "sg:city":"Hagerstown",
    "sg:classifiers":[
        {
            "category":"Building & Trades",
            "subcategory":"Construction",
            "type":"Services"
        }
    ],
    "sg:phone":"+1 301 665 9445",
    "sg:postcode":"21740",
    "sg:province":"MD",
    "sg:tags":[
        "house"
    ],
    "wof:name":"Brian Builders",
    "wof:placetype":"venue"
},
  "geometry": {"coordinates":[-77.750574,39.626122],"type":"Point"}
}