{
  "type": "Feature",
  "properties": {
    "iso:country":"US",
    "sg:address":"107 Industry Ln",
    "sg:city":"Cockeysville",
    "sg:classifiers":[
        {
            "category":"Autos & Motor Vehicles",
            "subcategory":"Automobile Sales",
            "type":"Retail Goods"
        }
    ],
    "sg:phone":"+1 410 666 5030",
    "sg:postcode":"21030",
    "sg:province":"MD",
    "sg:tags":[
        "car",
        "repair"
    ],
    "sg:website":"www.billkidds.com",
    "wof:name":"Bill Kidds Timonium Toyota",
    "wof:placetype":"venue"
},
  "geometry": {"coordinates":[-76.639702,39.466],"type":"Point"}
}