{
  "type": "Feature",
  "properties": {
    "addr:full":"5509 Urbana Pike Frederick MD 21704",
    "addr:housenumber":"5509",
    "addr:postcode":"21704",
    "addr:street":"Urbana Pike",
    "iso:country":"US",
    "sg:address":"5509 Urbana Pike",
    "sg:city":"Frederick",
    "sg:classifiers":[
        {
            "category":"Health Services",
            "subcategory":"Optometrist",
            "type":"Services"
        }
    ],
    "sg:phone":"+1 301 662 0660",
    "sg:postcode":"21704",
    "sg:province":"MD",
    "wof:name":"Hour Eyes",
    "wof:placetype":"venue"
},
  "geometry": {"coordinates":[-77.40008400000001,39.381475],"type":"Point"}
}