{
  "type": "Feature",
  "properties": {
    "addr:full":"3 Commercial Plz Elkton MD 21921",
    "addr:housenumber":"3",
    "addr:postcode":"21921",
    "addr:street":"Commercial Plz",
    "iso:country":"US",
    "sg:address":"3 Commercial Plz",
    "sg:city":"Elkton",
    "sg:classifiers":[
        {
            "category":"Real Estate",
            "subcategory":"Real Estate Services",
            "type":"Services"
        },
        {
            "category":"Real Estate",
            "subcategory":"Real Estate Agent",
            "type":"Services"
        }
    ],
    "sg:phone":"+1 410 620 4359",
    "sg:postcode":"21921",
    "sg:province":"MD",
    "sg:tags":[
        "buyer",
        "broker"
    ],
    "wof:name":"Real Estate Consultant",
    "wof:placetype":"venue"
},
  "geometry": {"coordinates":[-75.830637,39.604408],"type":"Point"}
}