{
  "type": "Feature",
  "properties": {
    "addr:full":"1272 Windmill Ln Silver Spring MD 20905",
    "addr:housenumber":"1272",
    "addr:postcode":"20905",
    "addr:street":"Windmill Ln",
    "iso:country":"US",
    "sg:address":"1272 Windmill Ln",
    "sg:city":"Silver Spring",
    "sg:classifiers":[
        {
            "category":"Building & Trades",
            "subcategory":"Cleaning & Sanitation",
            "type":"Services"
        }
    ],
    "sg:phone":"+1 301 404 5677",
    "sg:postcode":"20905",
    "sg:province":"MD",
    "sg:tags":[
        "carpet"
    ],
    "sg:website":"www.200degrees.net",
    "wof:name":"200 Degrees Carpet Cleaning",
    "wof:placetype":"venue"
},
  "geometry": {"coordinates":[-76.981357,39.095813],"type":"Point"}
}