{
  "type": "Feature",
  "properties": {
    "addr:full":"15646 Millbrook Lane Laurel MD 20707",
    "addr:housenumber":"15646",
    "addr:postcode":"20707",
    "addr:street":"Millbrook Lane",
    "iso:country":"US",
    "sg:address":"15646 Millbrook Lane",
    "sg:city":"Laurel",
    "sg:classifiers":[
        {
            "category":"Building & Trades",
            "subcategory":"Plumbing",
            "type":"Services"
        }
    ],
    "sg:phone":"+1 240 979 4127",
    "sg:postcode":"20707",
    "sg:province":"MD",
    "sg:website":"marylandplumberpros.com/",
    "wof:name":"Maryland Plumber Pros",
    "wof:placetype":"venue"
},
  "geometry": {"coordinates":[-76.874751,39.104324],"type":"Point"}
}