{
  "type": "Feature",
  "properties": {
    "addr:full":"3005 Stranden Rd Baltimore MD 21230",
    "addr:housenumber":"3005",
    "addr:postcode":"21230",
    "addr:street":"Stranden Rd",
    "iso:country":"US",
    "sg:address":"3005 Stranden Rd",
    "sg:city":"Baltimore",
    "sg:classifiers":[
        {
            "category":"Insurance",
            "subcategory":"Hazard Insurance",
            "type":"Services"
        }
    ],
    "sg:phone":"+1 410 525 2280",
    "sg:postcode":"21230",
    "sg:province":"MD",
    "wof:name":"Diana Ritenour",
    "wof:placetype":"venue"
},
  "geometry": {"coordinates":[-76.645709,39.252411],"type":"Point"}
}