{
  "type": "Feature",
  "properties": {
    "addr:full":"7 Burley St Berlin MD 21811",
    "addr:housenumber":"7",
    "addr:postcode":"21811",
    "addr:street":"Burley St",
    "iso:country":"US",
    "sg:address":"7 Burley St",
    "sg:city":"Berlin",
    "sg:classifiers":[
        {
            "category":"Building & Trades",
            "subcategory":"Construction",
            "type":"Services"
        }
    ],
    "sg:phone":"+1 410 641 2231",
    "sg:postcode":"21811",
    "sg:province":"MD",
    "sg:tags":[
        "home",
        "improvement"
    ],
    "wof:name":"Jones & Sons Inc",
    "wof:placetype":"venue"
},
  "geometry": {"coordinates":[-75.21884799999999,38.320879],"type":"Point"}
}