{
  "type": "Feature",
  "properties": {
    "addr:full":"8232 Philadelphia Rd Rosedale MD 21237",
    "addr:housenumber":"8232",
    "addr:postcode":"21237",
    "addr:street":"Philadelphia Rd",
    "iso:country":"US",
    "sg:address":"8232 Philadelphia Rd",
    "sg:city":"Rosedale",
    "sg:classifiers":[
        {
            "category":"Retail",
            "subcategory":"Portrait Studio",
            "type":"Services"
        }
    ],
    "sg:phone":"+1 410 687 1963",
    "sg:postcode":"21237",
    "sg:province":"MD",
    "sg:tags":[
        "photographer"
    ],
    "wof:name":"Lazzaro Studio Photography",
    "wof:placetype":"venue"
},
  "geometry": {"coordinates":[-76.505336,39.327155],"type":"Point"}
}