{
  "type": "Feature",
  "properties": {
    "addr:full":"106 Mellor Ave Catonsville MD 21228",
    "addr:housenumber":"106",
    "addr:postcode":"21228",
    "addr:street":"Mellor Ave",
    "iso:country":"US",
    "sg:address":"106 Mellor Ave",
    "sg:city":"Catonsville",
    "sg:classifiers":[
        {
            "category":"Building & Trades",
            "subcategory":"Construction",
            "type":"Services"
        }
    ],
    "sg:phone":"+1 410 747 6165",
    "sg:postcode":"21228",
    "sg:province":"MD",
    "sg:tags":[
        "sewer",
        "contractor"
    ],
    "wof:name":"Syko Sewer & Drain Cleaning",
    "wof:placetype":"venue"
},
  "geometry": {"coordinates":[-76.73258300000001,39.267824],"type":"Point"}
}