{
  "type": "Feature",
  "properties": {
    "addr:full":"22 Redding Ridge Dr Gaithersburg MD 20878",
    "addr:housenumber":"22",
    "addr:postcode":"20878",
    "addr:street":"Redding Ridge Dr",
    "iso:country":"US",
    "sg:address":"22 Redding Ridge Dr",
    "sg:city":"Gaithersburg",
    "sg:classifiers":[
        {
            "category":"Professional",
            "subcategory":"Management & Consulting",
            "type":"Services"
        }
    ],
    "sg:phone":"+1 301 762 7119",
    "sg:postcode":"20878",
    "sg:province":"MD",
    "sg:tags":[
        "consultant",
        "training"
    ],
    "wof:name":"Harlow MB & Associates Inc",
    "wof:placetype":"venue"
},
  "geometry": {"coordinates":[-77.22644,39.104652],"type":"Point"}
}