{
  "type": "Feature",
  "properties": {
    "addr:full":"1526 Cecilton Warwick Rd Warwick MD 21912",
    "addr:housenumber":"1526",
    "addr:postcode":"21912",
    "addr:street":"Cecilton Warwick Rd",
    "iso:country":"US",
    "sg:address":"1526 Cecilton Warwick Rd",
    "sg:city":"Warwick",
    "sg:classifiers":[
        {
            "category":"Wholesale",
            "subcategory":"Poultry",
            "type":"Manufacturing & Wholesale Goods"
        }
    ],
    "sg:phone":"+1 410 755 6773",
    "sg:postcode":"21912",
    "sg:province":"MD",
    "sg:tags":[
        "eggs"
    ],
    "wof:name":"Ise America",
    "wof:placetype":"venue"
},
  "geometry": {"coordinates":[-75.817527,39.41076],"type":"Point"}
}