{
  "type": "Feature",
  "properties": {
    "iso:country":"US",
    "sg:address":"2103 Badian Dr",
    "sg:city":"Silver Spring",
    "sg:classifiers":[
        {
            "category":"Travel",
            "subcategory":"Travel Agent",
            "type":"Entertainment"
        }
    ],
    "sg:phone":"+1 301 384 7205",
    "sg:postcode":"20904",
    "sg:province":"MD",
    "wof:name":"Sally Bird",
    "wof:placetype":"venue"
},
  "geometry": {"coordinates":[-76.970001,39.0788],"type":"Point"}
}