{
  "type": "Feature",
  "properties": {
    "iso:country":"US",
    "sg:address":"11701 Danville Dr",
    "sg:city":"Rockville",
    "sg:classifiers":[
        {
            "category":"Education",
            "subcategory":"Preschool",
            "type":"Public Place"
        },
        {
            "category":"Education",
            "subcategory":"School",
            "type":"Public Place"
        }
    ],
    "sg:phone":"+1 301 881 4100",
    "sg:postcode":"20852",
    "sg:province":"MD",
    "sg:tags":[
        "high",
        "middle",
        "elementary"
    ],
    "sg:website":"www.congressionalschools.org",
    "wof:name":"Green Acres School",
    "wof:placetype":"venue"
},
  "geometry": {"coordinates":[-77.133499,39.048199],"type":"Point"}
}