{
  "type": "Feature",
  "properties": {
    "iso:country":"US",
    "sg:address":"16641 Crabbs Branch Way",
    "sg:city":"Rockville",
    "sg:classifiers":[
        {
            "category":"Recreation",
            "type":"Entertainment"
        }
    ],
    "sg:phone":"+1 301 670 8100",
    "sg:postcode":"20855",
    "sg:province":"MD",
    "sg:tags":[
        "parks"
    ],
    "wof:name":"Parks Dept-Central Maintenance",
    "wof:placetype":"venue"
},
  "geometry": {"coordinates":[-77.16679600000001,39.127546],"type":"Point"}
}