{
  "type": "Feature",
  "properties": {
    "iso:country":"US",
    "sg:address":"920 Cathedral St",
    "sg:city":"Baltimore",
    "sg:classifiers":[
        {
            "category":"Shopping",
            "subcategory":"Used Merchandise",
            "type":"Retail Goods"
        }
    ],
    "sg:phone":"+1 410 528 1650",
    "sg:postcode":"21201",
    "sg:province":"MD",
    "sg:tags":[
        "antique"
    ],
    "wof:name":"Ron's Attic",
    "wof:placetype":"venue"
},
  "geometry": {"coordinates":[-76.617664,39.300887],"type":"Point"}
}