{
  "type": "Feature",
  "properties": {
    "addr:full":"440 N Luzerne Ave Baltimore MD 21224",
    "addr:housenumber":"440",
    "addr:postcode":"21224",
    "addr:street":"N Luzerne Ave",
    "iso:country":"US",
    "sg:address":"440 N Luzerne Ave",
    "sg:city":"Baltimore",
    "sg:classifiers":[
        {
            "category":"Social Services",
            "type":"Services"
        }
    ],
    "sg:phone":"+1 443 969 4520",
    "sg:postcode":"21224",
    "sg:province":"MD",
    "wof:name":"Recovery For Life, Inc.",
    "wof:placetype":"venue"
},
  "geometry": {"coordinates":[-76.580713,39.296107],"type":"Point"}
}