{
  "type": "Feature",
  "properties": {
    "iso:country":"US",
    "sg:address":"1119 Battery Ave",
    "sg:city":"Baltimore",
    "sg:classifiers":[
        {
            "category":"Manufacturing",
            "subcategory":"Tools & Machinery",
            "type":"Manufacturing & Wholesale Goods"
        }
    ],
    "sg:phone":"+1 410 456 3333",
    "sg:postcode":"21230",
    "sg:province":"MD",
    "sg:tags":[
        "industrial",
        "electric",
        "supply",
        "sale",
        "equipment",
        "electrical"
    ],
    "sg:website":"http://www.primeequipmentinc.com",
    "wof:name":"Prime Equipment, Inc",
    "wof:placetype":"venue"
},
  "geometry": {"coordinates":[-76.60980600000001,39.277099],"type":"Point"}
}