{
  "type": "Feature",
  "properties": {
    "iso:country":"US",
    "sg:address":"1263 E Fayette St",
    "sg:city":"Baltimore",
    "sg:classifiers":[
        {
            "category":"Bars & Pubs",
            "type":"Food & Drink"
        }
    ],
    "sg:phone":"+1 410 327 8367",
    "sg:postcode":"21231",
    "sg:province":"MD",
    "wof:name":"Glass Door Lounge",
    "wof:placetype":"venue"
},
  "geometry": {"coordinates":[-76.600604,39.292117],"type":"Point"}
}