{
  "type": "Feature",
  "properties": {
    "iso:country":"US",
    "sg:address":"10226 Governor Lane Blvd",
    "sg:city":"Williamsport",
    "sg:classifiers":[
        {
            "category":"Wholesale",
            "subcategory":"Electrical",
            "type":"Manufacturing & Wholesale Goods"
        }
    ],
    "sg:phone":"+1 301 223 4800",
    "sg:postcode":"21795",
    "sg:province":"MD",
    "sg:tags":[
        "alarm",
        "burglar",
        "system"
    ],
    "wof:name":"Alarm Detection System",
    "wof:placetype":"venue"
},
  "geometry": {"coordinates":[-77.803857,39.598156],"type":"Point"}
}