{
  "type": "Feature",
  "properties": {
    "iso:country":"US",
    "sg:address":"8249 Dickerson Ln",
    "sg:city":"Salisbury",
    "sg:classifiers":[
        {
            "category":"Banks & Credit Unions",
            "subcategory":"Investment Brokerage",
            "type":"Services"
        }
    ],
    "sg:phone":"+1 410 341 3253",
    "sg:postcode":"21804",
    "sg:province":"MD",
    "wof:name":"Commercial Investment Prtnrshp",
    "wof:placetype":"venue"
},
  "geometry": {"coordinates":[-75.563899,38.418698],"type":"Point"}
}