{
  "type": "Feature",
  "properties": {
    "addr:full":"10420 Little Patuxent Pkwy Columbia MD 21044",
    "addr:housenumber":"10420",
    "addr:postcode":"21044",
    "addr:street":"Little Patuxent Pkwy",
    "iso:country":"US",
    "sg:address":"10420 Little Patuxent Pkwy",
    "sg:city":"Columbia",
    "sg:classifiers":[
        {
            "category":"Professional",
            "subcategory":"Lawyer & Legal Services",
            "type":"Services"
        }
    ],
    "sg:phone":"+1 410 730 6536",
    "sg:postcode":"21044",
    "sg:province":"MD",
    "sg:tags":[
        "attorney"
    ],
    "sg:website":"www.drazinlaw.com",
    "wof:name":"Drazin & Drazin",
    "wof:placetype":"venue"
},
  "geometry": {"coordinates":[-76.858608,39.211823],"type":"Point"}
}