{
  "type": "Feature",
  "properties": {
    "addr:full":"9712 Groffs Mill Dr Owings Mills MD 21117",
    "addr:housenumber":"9712",
    "addr:postcode":"21117",
    "addr:street":"Groffs Mill Dr",
    "iso:country":"US",
    "sg:address":"9712 Groffs Mill Dr",
    "sg:city":"Owings Mills",
    "sg:classifiers":[
        {
            "category":"Restaurant",
            "type":"Food & Drink"
        }
    ],
    "sg:phone":"+1 410 356 3100",
    "sg:postcode":"21117",
    "sg:province":"MD",
    "wof:name":"Liberatore's Catering",
    "wof:placetype":"venue"
},
  "geometry": {"coordinates":[-76.804937,39.404052],"type":"Point"}
}