{
  "type": "Feature",
  "properties": {
    "iso:country":"US",
    "sg:address":"4803 Breezy Point Rd",
    "sg:city":"Chesapeake Beach",
    "sg:classifiers":[
        {
            "category":"Professional",
            "type":"Services"
        }
    ],
    "sg:phone":"+1 410 257 2171",
    "sg:postcode":"20732",
    "sg:province":"MD",
    "wof:name":"Sailor For Hire",
    "wof:placetype":"venue"
},
  "geometry": {"coordinates":[-76.52539,38.621335],"type":"Point"}
}