{
  "type": "Feature",
  "properties": {
    "iso:country":"US",
    "sg:address":"12 N Washington St",
    "sg:city":"Rockville",
    "sg:classifiers":[
        {
            "category":"Restaurant",
            "type":"Food & Drink"
        }
    ],
    "sg:phone":"+1 301 294 3540",
    "sg:postcode":"20850",
    "sg:province":"MD",
    "wof:name":"Apollo Restaurant",
    "wof:placetype":"venue"
},
  "geometry": {"coordinates":[-77.152978,39.084259],"type":"Point"}
}