{
  "type": "Feature",
  "properties": {
    "addr:full":"922 N. Rolling Road inside the Hanori Town Catonsville MD 21228",
    "addr:housenumber":"922",
    "addr:postcode":"21228",
    "addr:street":"N. Rolling Road Inside The Hanori",
    "iso:country":"US",
    "sg:address":"922 N. Rolling Road inside the Hanori Town",
    "sg:city":"Catonsville",
    "sg:classifiers":[
        {
            "category":"Restaurant",
            "type":"Food & Drink"
        }
    ],
    "sg:phone":"+1 410 505 5002",
    "sg:postcode":"21228",
    "sg:province":"MD",
    "sg:tags":[
        "korean"
    ],
    "wof:name":"Two Youngs",
    "wof:placetype":"venue"
},
  "geometry": {"coordinates":[-76.75353699999999,39.283338],"type":"Point"}
}