{
  "type": "Feature",
  "properties": {
    "iso:country":"US",
    "sg:address":"11 Locust Rd",
    "sg:city":"Aberdeen",
    "sg:classifiers":[
        {
            "category":"Professional",
            "type":"Services"
        }
    ],
    "sg:phone":"+1 410 272 0966",
    "sg:postcode":"21001",
    "sg:province":"MD",
    "sg:tags":[
        "establishment"
    ],
    "wof:name":"Positive Image",
    "wof:placetype":"venue"
},
  "geometry": {"coordinates":[-76.227985,39.455553],"type":"Point"}
}