{
  "type": "Feature",
  "properties": {
    "addr:full":"16924 York Rd Monkton MD 21111",
    "addr:housenumber":"16924",
    "addr:postcode":"21111",
    "addr:street":"York Rd",
    "iso:country":"US",
    "sg:address":"16924 York Rd",
    "sg:city":"Monkton",
    "sg:classifiers":[
        {
            "category":"Retail",
            "subcategory":"Funeral Services",
            "type":"Services"
        }
    ],
    "sg:phone":"+1 410 343 3000",
    "sg:postcode":"21111",
    "sg:province":"MD",
    "sg:tags":[
        "director"
    ],
    "sg:website":"www.henrywjenkins.com",
    "wof:name":"Henry W Jenkins & Sons Co",
    "wof:placetype":"venue"
},
  "geometry": {"coordinates":[-76.663111,39.588339],"type":"Point"}
}