{
  "type": "Feature",
  "properties": {
    "addr:full":"8417 Rocky Ridge Rd Rocky Ridge MD 21778",
    "addr:housenumber":"8417",
    "addr:postcode":"21778",
    "addr:street":"Rocky Ridge Rd",
    "iso:country":"US",
    "sg:address":"8417 Rocky Ridge Rd",
    "sg:city":"Rocky Ridge",
    "sg:classifiers":[
        {
            "category":"Building & Trades",
            "subcategory":"Construction",
            "type":"Services"
        }
    ],
    "sg:phone":"+1 301 694 5430",
    "sg:postcode":"21778",
    "sg:province":"MD",
    "sg:tags":[
        "paving",
        "contractor"
    ],
    "wof:name":"Fogles Bonded Asphalt Paving",
    "wof:placetype":"venue"
},
  "geometry": {"coordinates":[-77.375736,39.616483],"type":"Point"}
}