{
  "type": "Feature",
  "properties": {
    "addr:full":"10912 Kingstead Rd Damascus MD 20872",
    "addr:housenumber":"10912",
    "addr:postcode":"20872",
    "addr:street":"Kingstead Rd",
    "iso:country":"US",
    "sg:address":"10912 Kingstead Rd",
    "sg:city":"Damascus",
    "sg:classifiers":[
        {
            "category":"Professional",
            "subcategory":"Management & Consulting",
            "type":"Services"
        }
    ],
    "sg:phone":"+1 301 253 3832",
    "sg:postcode":"20872",
    "sg:province":"MD",
    "wof:name":"D & S Associates",
    "wof:placetype":"venue"
},
  "geometry": {"coordinates":[-77.225742,39.268262],"type":"Point"}
}