{
  "type": "Feature",
  "properties": {
    "iso:country":"US",
    "sg:address":"411 S High St",
    "sg:city":"Baltimore",
    "sg:classifiers":[
        {
            "category":"Food & Beverages",
            "subcategory":"Ethnic Foods",
            "type":"Retail Goods"
        }
    ],
    "sg:phone":"+1 410 385 4900",
    "sg:postcode":"21202",
    "sg:province":"MD",
    "wof:name":"Indian Rasoi",
    "wof:placetype":"venue"
},
  "geometry": {"coordinates":[-76.60122200000001,39.285341],"type":"Point"}
}