{
  "type": "Feature",
  "properties": {
    "iso:country":"US",
    "sg:address":"10420 Little Patuxent Pkwy",
    "sg:city":"Columbia",
    "sg:classifiers":[
        {
            "category":"Health Services",
            "subcategory":"Hospital",
            "type":"Services"
        },
        {
            "category":"Health Services",
            "subcategory":"Medical Lab",
            "type":"Services"
        }
    ],
    "sg:phone":"+1 410 740 2370",
    "sg:postcode":"21044",
    "sg:province":"MD",
    "sg:website":"http://www.impulsemonitoring.com",
    "wof:name":"Impulse Monitoring, Inc.",
    "wof:placetype":"venue"
},
  "geometry": {"coordinates":[-76.859283,39.212811],"type":"Point"}
}