{
  "type": "Feature",
  "properties": {
    "addr:full":"2401 Liberty Heights Avenue Baltimore MD 21217",
    "addr:housenumber":"2401",
    "addr:postcode":"21217",
    "addr:street":"Liberty Heights Avenue",
    "iso:country":"US",
    "sg:address":"2401 Liberty Heights Avenue",
    "sg:city":"Baltimore",
    "sg:classifiers":[
        {
            "category":"Utilities",
            "type":"Services"
        }
    ],
    "sg:phone":"+1 410 512 6420",
    "sg:postcode":"21217",
    "sg:province":"MD",
    "sg:tags":[
        "provider",
        "internet"
    ],
    "sg:website":"www.clear.com/landing/state/md",
    "wof:name":"Clear Internet Store - Clearwire",
    "wof:placetype":"venue"
},
  "geometry": {"coordinates":[-76.65530800000001,39.317495],"type":"Point"}
}