{
  "type": "Feature",
  "properties": {
    "addr:full":"244 E Susquehanna Ave Baltimore MD 21286",
    "addr:housenumber":"244",
    "addr:postcode":"21286",
    "addr:street":"E Susquehanna Ave",
    "iso:country":"US",
    "sg:address":"244 E Susquehanna Ave",
    "sg:city":"Baltimore",
    "sg:classifiers":[
        {
            "category":"Restaurant",
            "type":"Food & Drink"
        }
    ],
    "sg:phone":"+1 410 576 8557",
    "sg:postcode":"21286",
    "sg:province":"MD",
    "sg:tags":[
        "eating"
    ],
    "wof:name":"Magoos Daily Perk",
    "wof:placetype":"venue"
},
  "geometry": {"coordinates":[-76.59567,39.397367],"type":"Point"}
}