{
  "type": "Feature",
  "properties": {
    "addr:full":"9004 Honeybee Ln Bethesda MD 20817",
    "addr:housenumber":"9004",
    "addr:postcode":"20817",
    "addr:street":"Honeybee Ln",
    "iso:country":"US",
    "sg:address":"9004 Honeybee Ln",
    "sg:city":"Bethesda",
    "sg:classifiers":[
        {
            "category":"Arts & Performance",
            "subcategory":"Art Gallery",
            "type":"Entertainment"
        }
    ],
    "sg:phone":"+1 301 365 7400",
    "sg:postcode":"20817",
    "sg:province":"MD",
    "wof:name":"Jeppson Lawrence S",
    "wof:placetype":"venue"
},
  "geometry": {"coordinates":[-77.162102,39.0014],"type":"Point"}
}