{
  "type": "Feature",
  "properties": {
    "addr:full":"5236 Green Bridge Rd Dayton MD 21036",
    "addr:housenumber":"5236",
    "addr:postcode":"21036",
    "addr:street":"Green Bridge Rd",
    "iso:country":"US",
    "sg:address":"5236 Green Bridge Rd",
    "sg:city":"Dayton",
    "sg:classifiers":[
        {
            "category":"Building & Trades",
            "subcategory":"Construction",
            "type":"Services"
        }
    ],
    "sg:phone":"+1 301 854 1633",
    "sg:postcode":"21036",
    "sg:province":"MD",
    "sg:tags":[
        "carpentry",
        "contractor"
    ],
    "wof:name":"Greenbridge Construction Inc",
    "wof:placetype":"venue"
},
  "geometry": {"coordinates":[-76.995346,39.228514],"type":"Point"}
}