{
  "type": "Feature",
  "properties": {
    "addr:full":"10190 Three Doctors Rd Dunkirk MD 20754",
    "addr:housenumber":"10190",
    "addr:postcode":"20754",
    "addr:street":"Three Doctors Rd",
    "iso:country":"US",
    "sg:address":"10190 Three Doctors Rd",
    "sg:city":"Dunkirk",
    "sg:classifiers":[
        {
            "category":"Sports & Exercise",
            "subcategory":"Gym",
            "type":"Entertainment"
        }
    ],
    "sg:phone":"+1 410 257 0399",
    "sg:postcode":"20754",
    "sg:province":"MD",
    "sg:tags":[
        "club",
        "health",
        "studio",
        "gymnasium"
    ],
    "wof:name":"Carpenter's Fitness Ctr",
    "wof:placetype":"venue"
},
  "geometry": {"coordinates":[-76.68004999999999,38.720429],"type":"Point"}
}