{
  "type": "Feature",
  "properties": {
    "addr:full":"4384 Hollins Ferry Rd Halethorpe MD 21227",
    "addr:housenumber":"4384",
    "addr:postcode":"21227",
    "addr:street":"Hollins Ferry Rd",
    "iso:country":"US",
    "sg:address":"4384 Hollins Ferry Rd",
    "sg:city":"Halethorpe",
    "sg:classifiers":[
        {
            "category":"Food & Beverages",
            "subcategory":"Groceries & Convenience Stores",
            "type":"Retail Goods"
        }
    ],
    "sg:phone":"+1 410 247 2929",
    "sg:postcode":"21227",
    "sg:province":"MD",
    "sg:website":"www.royalfarms.com",
    "wof:name":"Royal Farm Stores",
    "wof:placetype":"venue"
},
  "geometry": {"coordinates":[-76.659103,39.2379],"type":"Point"}
}