{
  "type": "Feature",
  "properties": {
    "addr:full":"19705 Waters Rd Germantown MD 20874",
    "addr:housenumber":"19705",
    "addr:postcode":"20874",
    "addr:street":"Waters Rd",
    "iso:country":"US",
    "sg:address":"19705 Waters Rd",
    "sg:city":"Germantown",
    "sg:classifiers":[
        {
            "category":"Retail",
            "subcategory":"Auto Rental",
            "type":"Services"
        }
    ],
    "sg:phone":"+1 301 528 9305",
    "sg:postcode":"20874",
    "sg:province":"MD",
    "sg:tags":[
        "renting",
        "truck",
        "leasing"
    ],
    "wof:name":"U-Haul Co",
    "wof:placetype":"venue"
},
  "geometry": {"coordinates":[-77.273132,39.180215],"type":"Point"}
}