{
  "type": "Feature",
  "properties": {
    "iso:country":"US",
    "sg:address":"5012 Macon Rd",
    "sg:city":"Rockville",
    "sg:classifiers":[
        {
            "category":"Professional",
            "subcategory":"Engineering",
            "type":"Services"
        }
    ],
    "sg:phone":"+1 301 984 3375",
    "sg:postcode":"20852",
    "sg:province":"MD",
    "sg:tags":[
        "consulting",
        "engineer"
    ],
    "wof:name":"Richard J Peppin Pe",
    "wof:placetype":"venue"
},
  "geometry": {"coordinates":[-77.102794,39.052118],"type":"Point"}
}