{
  "type": "Feature",
  "properties": {
    "addr:full":"404 Brown St Washington Grove MD 20880",
    "addr:housenumber":"404",
    "addr:postcode":"20880",
    "addr:street":"Brown St",
    "iso:country":"US",
    "sg:address":"404 Brown St",
    "sg:city":"Washington Grove",
    "sg:classifiers":[
        {
            "category":"Shopping",
            "subcategory":"Musical Instruments",
            "type":"Retail Goods"
        }
    ],
    "sg:phone":"+1 301 613 1026",
    "sg:postcode":"20880",
    "sg:province":"MD",
    "sg:tags":[
        "violin"
    ],
    "wof:name":"Violin Bow Rehair & Repair",
    "wof:placetype":"venue"
},
  "geometry": {"coordinates":[-77.17640400000001,39.1366],"type":"Point"}
}