{
  "type": "Feature",
  "properties": {
    "addr:full":"16911 Gorsuch Mill Rd Upperco MD 21155",
    "addr:housenumber":"16911",
    "addr:postcode":"21155",
    "addr:street":"Gorsuch Mill Rd",
    "iso:country":"US",
    "sg:address":"16911 Gorsuch Mill Rd",
    "sg:city":"Upperco",
    "sg:classifiers":[
        {
            "category":"Building & Trades",
            "subcategory":"Construction",
            "type":"Services"
        }
    ],
    "sg:phone":"+1 410 239 8764",
    "sg:postcode":"21155",
    "sg:province":"MD",
    "sg:tags":[
        "repairing",
        "remodeling",
        "contractor"
    ],
    "wof:name":"Donley Builders Inc",
    "wof:placetype":"venue"
},
  "geometry": {"coordinates":[-76.757802,39.585165],"type":"Point"}
}