{
  "type": "Feature",
  "properties": {
    "iso:country":"US",
    "sg:address":"113 Main St",
    "sg:city":"Secretary",
    "sg:classifiers":[
        {
            "category":"Personal",
            "subcategory":"Beauty Salon",
            "type":"Services"
        }
    ],
    "sg:phone":"+1 410 943 1926",
    "sg:postcode":"21664",
    "sg:province":"MD",
    "sg:tags":[
        "shop"
    ],
    "wof:name":"Carmen M Ramos",
    "wof:placetype":"venue"
},
  "geometry": {"coordinates":[-75.951357,38.609977],"type":"Point"}
}