{
  "type": "Feature",
  "properties": {
    "addr:full":"104 Back River Neck Rd Essex MD 21221",
    "addr:housenumber":"104",
    "addr:postcode":"21221",
    "addr:street":"Back River Neck Rd",
    "iso:country":"US",
    "sg:address":"104 Back River Neck Rd",
    "sg:city":"Essex",
    "sg:classifiers":[
        {
            "category":"Health Services",
            "subcategory":"Clinic",
            "type":"Services"
        },
        {
            "category":"Wholesale",
            "subcategory":"Wine & Distilled Alcoholic Beverages",
            "type":"Manufacturing & Wholesale Goods"
        }
    ],
    "sg:phone":"+1 410 574 5050",
    "sg:postcode":"21221",
    "sg:province":"MD",
    "sg:tags":[
        "information",
        "treatment",
        "alcoholism",
        "liquors-wholesale"
    ],
    "wof:name":"104 Bar & Grill Liquors",
    "wof:placetype":"venue"
},
  "geometry": {"coordinates":[-76.44824199999999,39.312328],"type":"Point"}
}