{
  "type": "Feature",
  "properties": {
    "iso:country":"US",
    "sg:address":"1013 Cresthaven Dr",
    "sg:city":"Silver Spring",
    "sg:classifiers":[
        {
            "category":"Professional",
            "subcategory":"Employment Agencies",
            "type":"Services"
        }
    ],
    "sg:phone":"+1 301 445 0558",
    "sg:postcode":"20903",
    "sg:province":"MD",
    "wof:name":"Majestic Placement Services",
    "wof:placetype":"venue"
},
  "geometry": {"coordinates":[-76.988257,39.021214],"type":"Point"}
}