{
  "type": "Feature",
  "properties": {
    "addr:full":"9600 Martin Luther King Jr Hwy Lanham MD 20706",
    "addr:housenumber":"9600",
    "addr:postcode":"20706",
    "addr:street":"Martin Luther King Jr Hwy",
    "iso:country":"US",
    "sg:address":"9600 Martin Luther King Jr Hwy",
    "sg:city":"Lanham",
    "sg:classifiers":[
        {
            "category":"Organizations",
            "subcategory":"Non-profit Organization",
            "type":"Services"
        }
    ],
    "sg:phone":"+1 301 702 1010",
    "sg:postcode":"20706",
    "sg:province":"MD",
    "wof:name":"Elevator Constructors Union",
    "wof:placetype":"venue"
},
  "geometry": {"coordinates":[-76.83879399999999,38.950185],"type":"Point"}
}