{
  "type": "Feature",
  "properties": {
    "iso:country":"US",
    "sg:address":"2213 Old Emmorton Rd",
    "sg:city":"Bel Air",
    "sg:classifiers":[
        {
            "category":"Recreation",
            "type":"Entertainment"
        }
    ],
    "sg:phone":"+1 410 638 3977",
    "sg:postcode":"21015",
    "sg:province":"MD",
    "sg:tags":[
        "tennis",
        "court"
    ],
    "wof:name":"Harford County Tennis Ctr",
    "wof:placetype":"venue"
},
  "geometry": {"coordinates":[-76.322379,39.494534],"type":"Point"}
}