{
  "type": "Feature",
  "properties": {
    "iso:country":"US",
    "sg:address":"12 Aventura Ct 1",
    "sg:city":"Randallstown",
    "sg:classifiers":[
        {
            "category":"Manufacturing",
            "subcategory":"Printing",
            "type":"Manufacturing & Wholesale Goods"
        }
    ],
    "sg:phone":"+1 410 521 1158",
    "sg:postcode":"21133",
    "sg:province":"MD",
    "sg:tags":[
        "imaging",
        "digital"
    ],
    "wof:name":"Team Tiger Printing",
    "wof:placetype":"venue"
},
  "geometry": {"coordinates":[-76.77136,39.385469],"type":"Point"}
}