{
  "type": "Feature",
  "properties": {
    "addr:full":"7701 Crain Hwy Upper Marlboro MD 20772",
    "addr:housenumber":"7701",
    "addr:postcode":"20772",
    "addr:street":"Crain Hwy",
    "iso:country":"US",
    "sg:address":"7701 Crain Hwy",
    "sg:city":"Upper Marlboro",
    "sg:classifiers":[
        {
            "category":"Food & Beverages",
            "subcategory":"Liquor & Beverages",
            "type":"Retail Goods"
        }
    ],
    "sg:phone":"+1 301 627 6550",
    "sg:postcode":"20772",
    "sg:province":"MD",
    "wof:name":"Olde Fitzgerald's Liquors",
    "wof:placetype":"venue"
},
  "geometry": {"coordinates":[-76.794814,38.78411],"type":"Point"}
}