{
  "type": "Feature",
  "properties": {
    "iso:country":"US",
    "sg:address":"4907 Niagara Rd",
    "sg:city":"College Park",
    "sg:classifiers":[
        {
            "category":"Professional",
            "subcategory":"Lawyer & Legal Services",
            "type":"Services"
        }
    ],
    "sg:phone":"+1 301 474 2300",
    "sg:postcode":"20740",
    "sg:province":"MD",
    "sg:tags":[
        "attorney"
    ],
    "wof:name":"Hamburg & Schwartz",
    "wof:placetype":"venue"
},
  "geometry": {"coordinates":[-76.923177,39.017372],"type":"Point"}
}