{
  "type": "Feature",
  "properties": {
    "addr:full":"625P Baltimore Blvd Westminster MD 21157",
    "addr:housenumber":"625p",
    "addr:postcode":"21157",
    "addr:street":"Baltimore Blvd",
    "iso:country":"US",
    "sg:address":"625P Baltimore Blvd",
    "sg:city":"Westminster",
    "sg:classifiers":[
        {
            "category":"Real Estate",
            "subcategory":"Real Estate Services",
            "type":"Services"
        },
        {
            "category":"Real Estate",
            "subcategory":"Real Estate Agent",
            "type":"Services"
        }
    ],
    "sg:phone":"+1 410 876 7100",
    "sg:postcode":"21157",
    "sg:province":"MD",
    "sg:tags":[
        "management"
    ],
    "sg:website":"http://www.brendae.com",
    "wof:name":"The Long & Foster Companies Inc",
    "wof:placetype":"venue"
},
  "geometry": {"coordinates":[-76.972984,39.563611],"type":"Point"}
}