{
  "type": "Feature",
  "properties": {
    "addr:full":"9112 Canterbury Riding Laurel MD 20723",
    "addr:housenumber":"9112",
    "addr:postcode":"20723",
    "addr:street":"Riding",
    "iso:country":"US",
    "sg:address":"9112 Canterbury Riding",
    "sg:city":"Laurel",
    "sg:classifiers":[
        {
            "category":"Personal",
            "type":"Services"
        }
    ],
    "sg:phone":"+1 301 604 2666",
    "sg:postcode":"20723",
    "sg:province":"MD",
    "wof:name":"Full Moon Graphics",
    "wof:placetype":"venue"
},
  "geometry": {"coordinates":[-76.845169,39.124691],"type":"Point"}
}