{
  "type": "Feature",
  "properties": {
    "iso:country":"US",
    "sg:address":"1000 Roxleigh Rd",
    "sg:city":"Towson",
    "sg:classifiers":[
        {
            "category":"Professional",
            "subcategory":"Accounting & Tax Preparation",
            "type":"Services"
        }
    ],
    "sg:phone":"+1 410 828 7192",
    "sg:postcode":"21286",
    "sg:province":"MD",
    "sg:tags":[
        "return",
        "preparation-business"
    ],
    "wof:name":"Towson Tax Service",
    "wof:placetype":"venue"
},
  "geometry": {"coordinates":[-76.557503,39.43121],"type":"Point"}
}