{
  "type": "Feature",
  "properties": {
    "iso:country":"US",
    "sg:address":"18310 Timko Ln",
    "sg:city":"Germantown",
    "sg:classifiers":[
        {
            "category":"Professional",
            "subcategory":"Management & Consulting",
            "type":"Services"
        }
    ],
    "sg:phone":"+1 301 528 0028",
    "sg:postcode":"20874",
    "sg:province":"MD",
    "sg:tags":[
        "marketing",
        "consultant"
    ],
    "wof:name":"Y P Internet",
    "wof:placetype":"venue"
},
  "geometry": {"coordinates":[-77.272307,39.157003],"type":"Point"}
}