{
  "type": "Feature",
  "properties": {
    "addr:full":"3630 Main St Grasonville MD 21638",
    "addr:housenumber":"3630",
    "addr:postcode":"21638",
    "addr:street":"Main St",
    "iso:country":"US",
    "sg:address":"3630 Main St",
    "sg:city":"Grasonville",
    "sg:classifiers":[
        {
            "category":"Autos & Motor Vehicles",
            "subcategory":"Auto Supplies",
            "type":"Retail Goods"
        },
        {
            "category":"Personal",
            "type":"Services"
        },
        {
            "category":"Retail",
            "subcategory":"Auto Repair",
            "type":"Services"
        }
    ],
    "sg:phone":"+1 410 827 7766",
    "sg:postcode":"21638",
    "sg:province":"MD",
    "sg:tags":[
        "lube",
        "oil",
        "towing",
        "tire"
    ],
    "sg:website":"http://www.parksgoodyear.com",
    "wof:name":"Parks Tire & Auto Service Inc",
    "wof:placetype":"venue"
},
  "geometry": {"coordinates":[-76.22516,38.965136],"type":"Point"}
}