{
  "type": "Feature",
  "properties": {
    "iso:country":"US",
    "sg:address":"1249 Shore Dr",
    "sg:city":"Edgewater",
    "sg:classifiers":[
        {
            "category":"Building & Trades",
            "subcategory":"Plumbing",
            "type":"Services"
        }
    ],
    "sg:phone":"+1 410 956 6722",
    "sg:postcode":"21037",
    "sg:province":"MD",
    "sg:tags":[
        "plumbing",
        "contractor"
    ],
    "wof:name":"K Beard Inc",
    "wof:placetype":"venue"
},
  "geometry": {"coordinates":[-76.544865,38.931241],"type":"Point"}
}