{
  "type": "Feature",
  "properties": {
    "addr:full":"8620 Glenarden Pkwy Lanham MD 20706",
    "addr:postcode":"8620;20706",
    "addr:street":"Glenarden Pkwy",
    "iso:country":"US",
    "sg:address":"8620 Glenarden Pkwy",
    "sg:city":"Lanham",
    "sg:classifiers":[
        {
            "category":"Social Services",
            "type":"Services"
        }
    ],
    "sg:phone":"+1 301 516 7773",
    "sg:postcode":"20706",
    "sg:province":"MD",
    "sg:tags":[
        "shelter",
        "for",
        "homeless"
    ],
    "wof:name":"Treasures Forever Inc",
    "wof:placetype":"venue"
},
  "geometry": {"coordinates":[-76.861662,38.930887],"type":"Point"}
}