{
  "type": "Feature",
  "properties": {
    "addr:full":"3 E Patrick St Frederick MD 21701",
    "addr:housenumber":"3",
    "addr:postcode":"21701",
    "addr:street":"E Patrick St",
    "iso:country":"US",
    "sg:address":"3 E Patrick St",
    "sg:city":"Frederick",
    "sg:classifiers":[
        {
            "category":"Wholesale",
            "subcategory":"Furniture",
            "type":"Manufacturing & Wholesale Goods"
        }
    ],
    "sg:phone":"+1 301 682 5565",
    "sg:postcode":"21701",
    "sg:province":"MD",
    "wof:name":"Deja Vu Rug Co",
    "wof:placetype":"venue"
},
  "geometry": {"coordinates":[-77.410971,39.414266],"type":"Point"}
}