{
  "type": "Feature",
  "properties": {
    "addr:full":"3841 Farragut Ave Kensington MD 20895",
    "addr:housenumber":"3841",
    "addr:postcode":"20895",
    "addr:street":"Farragut Ave",
    "iso:country":"US",
    "sg:address":"3841 Farragut Ave",
    "sg:city":"Kensington",
    "sg:classifiers":[
        {
            "category":"Health Services",
            "subcategory":"Health Practitioner",
            "type":"Services"
        }
    ],
    "sg:phone":"+1 301 949 9726",
    "sg:postcode":"20895",
    "sg:province":"MD",
    "sg:tags":[
        "psychologist"
    ],
    "wof:name":"Potomac Ctr",
    "wof:placetype":"venue"
},
  "geometry": {"coordinates":[-77.075659,39.031953],"type":"Point"}
}