{
  "type": "Feature",
  "properties": {
    "addr:full":"9434 Northgate Rd Laurel MD 20723",
    "addr:housenumber":"9434",
    "addr:postcode":"20723",
    "addr:street":"Northgate Rd",
    "iso:country":"US",
    "sg:address":"9434 Northgate Rd",
    "sg:city":"Laurel",
    "sg:classifiers":[
        {
            "category":"Professional",
            "subcategory":"Business Services",
            "type":"Services"
        }
    ],
    "sg:phone":"+1 301 725 5694",
    "sg:postcode":"20723",
    "sg:province":"MD",
    "wof:name":"Shiv Enterprises Inc",
    "wof:placetype":"venue"
},
  "geometry": {"coordinates":[-76.833144,39.120662],"type":"Point"}
}