{
  "type": "Feature",
  "properties": {
    "iso:country":"US",
    "sg:address":"10 Budds Landing Rd",
    "sg:city":"Warwick",
    "sg:classifiers":[
        {
            "category":"Building & Trades",
            "subcategory":"Landscaping Services",
            "type":"Services"
        }
    ],
    "sg:phone":"+1 410 275 2699",
    "sg:postcode":"21912",
    "sg:province":"MD",
    "sg:tags":[
        "landscape",
        "contractor"
    ],
    "wof:name":"Top Notch Lawn Care",
    "wof:placetype":"venue"
},
  "geometry": {"coordinates":[-75.838701,39.377642],"type":"Point"}
}