{
  "type": "Feature",
  "properties": {
    "iso:country":"US",
    "sg:address":"9208 Alcona St",
    "sg:city":"Lanham",
    "sg:classifiers":[
        {
            "category":"Manufacturing",
            "subcategory":"Printing",
            "type":"Manufacturing & Wholesale Goods"
        }
    ],
    "sg:phone":"+1 301 731 5031",
    "sg:postcode":"20706",
    "sg:province":"MD",
    "sg:tags":[
        "screen"
    ],
    "wof:name":"Creative Distinctions",
    "wof:placetype":"venue"
},
  "geometry": {"coordinates":[-76.848922,38.957568],"type":"Point"}
}