{
  "type": "Feature",
  "properties": {
    "addr:full":"137 Big Elk Mall Elkton MD 21921",
    "addr:housenumber":"137",
    "addr:postcode":"21921",
    "addr:street":"Big Elk Mall",
    "iso:country":"US",
    "sg:address":"137 Big Elk Mall",
    "sg:city":"Elkton",
    "sg:classifiers":[
        {
            "category":"Food & Beverages",
            "subcategory":"Specialty",
            "type":"Retail Goods"
        }
    ],
    "sg:phone":"+1 410 620 2252",
    "sg:postcode":"21921",
    "sg:province":"MD",
    "sg:tags":[
        "health",
        "diet"
    ],
    "wof:name":"General Nutrition Ctr",
    "wof:placetype":"venue"
},
  "geometry": {"coordinates":[-75.824135,39.599536],"type":"Point"}
}