{
  "type": "Feature",
  "properties": {
    "iso:country":"US",
    "sg:address":"12217 Dancrest Dr",
    "sg:city":"Clarksburg",
    "sg:classifiers":[
        {
            "category":"Building & Trades",
            "subcategory":"Construction",
            "type":"Services"
        }
    ],
    "sg:phone":"+1 301 540 8411",
    "sg:postcode":"20871",
    "sg:province":"MD",
    "sg:tags":[
        "hanging",
        "contractor"
    ],
    "wof:name":"Killian Raymond & Vicki",
    "wof:placetype":"venue"
},
  "geometry": {"coordinates":[-77.256298,39.248104],"type":"Point"}
}