{
  "type": "Feature",
  "properties": {
    "addr:full":"3808 Eastern Ave Baltimore MD 21224",
    "addr:housenumber":"3808",
    "addr:postcode":"21224",
    "addr:street":"Eastern Ave",
    "iso:country":"US",
    "sg:address":"3808 Eastern Ave",
    "sg:city":"Baltimore",
    "sg:classifiers":[
        {
            "category":"Health Services",
            "subcategory":"Health Practitioner",
            "type":"Services"
        }
    ],
    "sg:phone":"+1 410 534 7373",
    "sg:postcode":"21224",
    "sg:province":"MD",
    "sg:tags":[
        "therapist",
        "physical"
    ],
    "wof:name":"Therafirst",
    "wof:placetype":"venue"
},
  "geometry": {"coordinates":[-76.563433,39.286846],"type":"Point"}
}