{
  "type": "Feature",
  "properties": {
    "addr:full":"105 Wood Duck Cir La Plata MD 20646",
    "addr:housenumber":"105",
    "addr:postcode":"20646",
    "addr:street":"Wood Duck Cir",
    "iso:country":"US",
    "sg:address":"105 Wood Duck Cir",
    "sg:city":"La Plata",
    "sg:classifiers":[
        {
            "category":"Building & Trades",
            "subcategory":"Construction",
            "type":"Services"
        }
    ],
    "sg:phone":"+1 301 392 0737",
    "sg:postcode":"20646",
    "sg:province":"MD",
    "sg:tags":[
        "house"
    ],
    "wof:name":"Hannah Construction",
    "wof:placetype":"venue"
},
  "geometry": {"coordinates":[-76.991128,38.534691],"type":"Point"}
}