{
  "type": "Feature",
  "properties": {
    "iso:country":"US",
    "sg:address":"7710 Wise Ave",
    "sg:city":"Dundalk",
    "sg:classifiers":[
        {
            "category":"Restaurant",
            "type":"Food & Drink"
        }
    ],
    "sg:menulink":"http://www.allmenus.com/md/dundalk/151668-aw-restaurant/menu/",
    "sg:phone":"+1 410 282 0366",
    "sg:postcode":"21222",
    "sg:province":"MD",
    "sg:tags":[
        "burger",
        "american",
        "dog",
        "pub",
        "hot"
    ],
    "wof:name":"A&W Restaurant",
    "wof:placetype":"venue"
},
  "geometry": {"coordinates":[-76.502377,39.269673],"type":"Point"}
}