{
  "type": "Feature",
  "properties": {
    "addr:full":"235 E Burke Ave Apt D Towson MD 21286",
    "addr:housenumber":"235",
    "addr:postcode":"21286",
    "addr:street":"E Burke Ave Apt D",
    "iso:country":"US",
    "sg:address":"235 E Burke Ave Apt D",
    "sg:city":"Towson",
    "sg:classifiers":[
        {
            "category":"Professional",
            "type":"Services"
        }
    ],
    "sg:phone":"+1 410 458 1169",
    "sg:postcode":"21286",
    "sg:province":"MD",
    "sg:tags":[
        "transportation"
    ],
    "wof:name":"Carter Transportation",
    "wof:placetype":"venue"
},
  "geometry": {"coordinates":[-76.594752,39.394595],"type":"Point"}
}