{
  "type": "Feature",
  "properties": {
    "addr:full":"1300 W Industrial Blvd Cumberland MD 21502",
    "addr:housenumber":"1300",
    "addr:postcode":"21502",
    "addr:street":"W Industrial Blvd",
    "iso:country":"US",
    "sg:address":"1300 W Industrial Blvd",
    "sg:city":"Cumberland",
    "sg:classifiers":[
        {
            "category":"Retail",
            "subcategory":"Car Wash",
            "type":"Services"
        }
    ],
    "sg:phone":"+1 301 722 1016",
    "sg:postcode":"21502",
    "sg:province":"MD",
    "sg:tags":[
        "polishing",
        "washing"
    ],
    "wof:name":"Diamond Shine Carwash Inc",
    "wof:placetype":"venue"
},
  "geometry": {"coordinates":[-78.746556,39.629971],"type":"Point"}
}