{
  "type": "Feature",
  "properties": {
    "iso:country":"US",
    "sg:address":"5629 Landover Rd",
    "sg:city":"Hyattsville",
    "sg:classifiers":[
        {
            "category":"Retail",
            "subcategory":"Auto Repair",
            "type":"Services"
        }
    ],
    "sg:phone":"+1 301 209 7034",
    "sg:postcode":"20784",
    "sg:province":"MD",
    "sg:tags":[
        "automotive",
        "tune"
    ],
    "wof:name":"Pg Auto Services",
    "wof:placetype":"venue"
},
  "geometry": {"coordinates":[-76.921027,38.936815],"type":"Point"}
}