{
  "type": "Feature",
  "properties": {
    "addr:full":"12406 Detour Rd Keymar MD 21757",
    "addr:postcode":"12406;21757",
    "addr:street":"Detour Rd",
    "iso:country":"US",
    "sg:address":"12406 Detour Rd",
    "sg:city":"Keymar",
    "sg:classifiers":[
        {
            "category":"Recreation",
            "type":"Entertainment"
        }
    ],
    "sg:phone":"+1 301 845 6272",
    "sg:postcode":"21757",
    "sg:province":"MD",
    "sg:tags":[
        "amusement"
    ],
    "wof:name":"TBW Motorsports",
    "wof:placetype":"venue"
},
  "geometry": {"coordinates":[-77.287702,39.576744],"type":"Point"}
}