{
  "type": "Feature",
  "properties": {
    "addr:full":"631 W Lexington St Baltimore MD 21201",
    "addr:housenumber":"631",
    "addr:postcode":"21201",
    "addr:street":"W Lexington St",
    "iso:country":"US",
    "sg:address":"631 W Lexington St",
    "sg:city":"Baltimore",
    "sg:classifiers":[
        {
            "category":"Restaurant",
            "type":"Food & Drink"
        },
        {
            "category":"Food & Beverages",
            "subcategory":"Bakery",
            "type":"Retail Goods"
        }
    ],
    "sg:phone":"+1 410 528 5102",
    "sg:postcode":"21201",
    "sg:province":"MD",
    "sg:tags":[
        "house",
        "steak",
        "sandwich"
    ],
    "wof:name":"Anns",
    "wof:placetype":"venue"
},
  "geometry": {"coordinates":[-76.625252,39.291203],"type":"Point"}
}