{
  "type": "Feature",
  "properties": {
    "iso:country":"US",
    "sg:address":"6241 Executive Blvd",
    "sg:city":"Rockville",
    "sg:classifiers":[
        {
            "category":"Professional",
            "subcategory":"Accounting & Tax Preparation",
            "type":"Services"
        }
    ],
    "sg:phone":"+1 301 770 5098",
    "sg:postcode":"20852",
    "sg:province":"MD",
    "sg:tags":[
        "accountant"
    ],
    "wof:name":"Seligson Bright & Associates P C",
    "wof:placetype":"venue"
},
  "geometry": {"coordinates":[-77.123042,39.048805],"type":"Point"}
}