{
  "type": "Feature",
  "properties": {
    "addr:full":"1339 Black Walnut Ct Annapolis MD 21403",
    "addr:housenumber":"1339",
    "addr:postcode":"21403",
    "addr:street":"Black Walnut Ct",
    "iso:country":"US",
    "sg:address":"1339 Black Walnut Ct",
    "sg:city":"Annapolis",
    "sg:classifiers":[
        {
            "category":"Professional",
            "type":"Services"
        }
    ],
    "sg:phone":"+1 410 990 0023",
    "sg:postcode":"21403",
    "sg:province":"MD",
    "sg:tags":[
        "writer",
        "contract"
    ],
    "wof:name":"Stuart Y Gordon",
    "wof:placetype":"venue"
},
  "geometry": {"coordinates":[-76.47948,38.93945],"type":"Point"}
}