{
  "type": "Feature",
  "properties": {
    "iso:country":"US",
    "sg:address":"3801 Erdman Ave",
    "sg:city":"Baltimore",
    "sg:classifiers":[
        {
            "category":"Education",
            "subcategory":"Library",
            "type":"Public Place"
        }
    ],
    "sg:phone":"+1 410 396 0996",
    "sg:postcode":"21213",
    "sg:province":"MD",
    "wof:name":"Enoch Pratt Free Library",
    "wof:placetype":"venue"
},
  "geometry": {"coordinates":[-76.568663,39.315093],"type":"Point"}
}