{
  "type": "Feature",
  "properties": {
    "iso:country":"US",
    "sg:address":"2216 Lakewood St",
    "sg:city":"Suitland",
    "sg:classifiers":[
        {
            "category":"Education",
            "subcategory":"Special Training",
            "type":"Public Place"
        }
    ],
    "sg:phone":"+1 301 449 1928",
    "sg:postcode":"20746",
    "sg:province":"MD",
    "sg:tags":[
        "educational"
    ],
    "wof:name":"Excel Education Services, Incorporated",
    "wof:placetype":"venue"
},
  "geometry": {"coordinates":[-76.927543,38.861169],"type":"Point"}
}