{
  "type": "Feature",
  "properties": {
    "iso:country":"US",
    "sg:address":"410 N Washington St",
    "sg:city":"Rockville",
    "sg:classifiers":[
        {
            "category":"Personal",
            "subcategory":"Beauty Salon",
            "type":"Services"
        }
    ],
    "sg:phone":"+1 301 340 1233",
    "sg:postcode":"20850",
    "sg:province":"MD",
    "wof:name":"Ping Beauty Salon",
    "wof:placetype":"venue"
},
  "geometry": {"coordinates":[-77.153677,39.090116],"type":"Point"}
}