{
  "type": "Feature",
  "properties": {
    "iso:country":"US",
    "sg:address":"765 Elkridge Landing Rd",
    "sg:city":"Linthicum Hts",
    "sg:classifiers":[
        {
            "category":"Professional",
            "type":"Services"
        }
    ],
    "sg:phone":"+1 410 993 1636",
    "sg:postcode":"21090",
    "sg:province":"MD",
    "sg:tags":[
        "establishment"
    ],
    "wof:name":"Quality Systems Inc",
    "wof:placetype":"venue"
},
  "geometry": {"coordinates":[-76.677299,39.191603],"type":"Point"}
}