{
  "type": "Feature",
  "properties": {
    "addr:full":"19911 Frederick Rd Germantown MD 20876",
    "addr:housenumber":"19911",
    "addr:postcode":"20876",
    "addr:street":"Frederick Rd",
    "iso:country":"US",
    "sg:address":"19911 Frederick Rd",
    "sg:city":"Germantown",
    "sg:classifiers":[
        {
            "category":"Restaurant",
            "type":"Food & Drink"
        }
    ],
    "sg:phone":"+1 301 353 0000",
    "sg:postcode":"20876",
    "sg:province":"MD",
    "wof:name":"Caspian Cafe",
    "wof:placetype":"venue"
},
  "geometry": {"coordinates":[-77.23838000000001,39.179968],"type":"Point"}
}