{
  "type": "Feature",
  "properties": {
    "addr:full":"816 Baltimore Rd Rockville MD 20851",
    "addr:housenumber":"816",
    "addr:postcode":"20851",
    "addr:street":"Baltimore Rd",
    "iso:country":"US",
    "sg:address":"816 Baltimore Rd",
    "sg:city":"Rockville",
    "sg:classifiers":[
        {
            "category":"Retail",
            "subcategory":"Self-service Laundry",
            "type":"Services"
        }
    ],
    "sg:phone":"+1 301 279 9090",
    "sg:postcode":"20851",
    "sg:province":"MD",
    "wof:name":"Burgundy Park Laundry & Dry",
    "wof:placetype":"venue"
},
  "geometry": {"coordinates":[-77.134748,39.084505],"type":"Point"}
}