{
  "type": "Feature",
  "properties": {
    "iso:country":"US",
    "sg:address":"7101 Main St",
    "sg:city":"Queenstown",
    "sg:classifiers":[
        {
            "category":"Banks & Credit Unions",
            "subcategory":"Financial Services",
            "type":"Services"
        }
    ],
    "sg:phone":"+1 410 827 8881",
    "sg:postcode":"21658",
    "sg:province":"MD",
    "sg:tags":[
        "company",
        "holding"
    ],
    "sg:website":"www.queenstown-bank.com",
    "wof:name":"Queenstown Bancorp",
    "wof:placetype":"venue"
},
  "geometry": {"coordinates":[-76.158581,38.989565],"type":"Point"}
}