{
  "type": "Feature",
  "properties": {
    "addr:full":"640 Lucabaugh Mill Rd Westminster MD 21157",
    "addr:housenumber":"640",
    "addr:postcode":"21157",
    "addr:street":"Lucabaugh Mill Rd",
    "iso:country":"US",
    "sg:address":"640 Lucabaugh Mill Rd",
    "sg:city":"Westminster",
    "sg:classifiers":[
        {
            "category":"Organizations",
            "subcategory":"Religious Organization",
            "type":"Services"
        }
    ],
    "sg:phone":"+1 410 848 5537",
    "sg:postcode":"21157",
    "sg:province":"MD",
    "sg:tags":[
        "church"
    ],
    "sg:website":"www.westcog.org",
    "wof:name":"Westminister Church Of God",
    "wof:placetype":"venue"
},
  "geometry": {"coordinates":[-76.968805,39.592219],"type":"Point"}
}