{
  "type": "Feature",
  "properties": {
    "iso:country":"US",
    "sg:address":"2129 Baldwin Ave",
    "sg:city":"Crofton",
    "sg:classifiers":[
        {
            "category":"Manufacturing",
            "subcategory":"Signs",
            "type":"Manufacturing & Wholesale Goods"
        }
    ],
    "sg:phone":"+1 301 858 0100",
    "sg:postcode":"21114",
    "sg:province":"MD",
    "wof:name":"Silk Screen Svc",
    "wof:placetype":"venue"
},
  "geometry": {"coordinates":[-76.694999,38.987764],"type":"Point"}
}