{
  "type": "Feature",
  "properties": {
    "addr:full":"25 Summit Ave Hagerstown MD 21740",
    "addr:housenumber":"25",
    "addr:postcode":"21740",
    "addr:street":"Summit Ave",
    "iso:country":"US",
    "sg:address":"25 Summit Ave",
    "sg:city":"Hagerstown",
    "sg:classifiers":[
        {
            "category":"Organizations",
            "subcategory":"Membership Organization",
            "type":"Services"
        }
    ],
    "sg:phone":"+1 301 791 5522",
    "sg:postcode":"21740",
    "sg:province":"MD",
    "wof:name":"Mount Hope Ctr",
    "wof:placetype":"venue"
},
  "geometry": {"coordinates":[-77.7227,39.64315],"type":"Point"}
}