{
  "type": "Feature",
  "properties": {
    "addr:full":"19452 Garretts Mill Rd Knoxville MD 21758",
    "addr:housenumber":"19452",
    "addr:postcode":"21758",
    "addr:street":"Garretts Mill Rd",
    "iso:country":"US",
    "sg:address":"19452 Garretts Mill Rd",
    "sg:city":"Knoxville",
    "sg:classifiers":[
        {
            "category":"Professional",
            "subcategory":"Business Services",
            "type":"Services"
        }
    ],
    "sg:phone":"+1 301 695 9632",
    "sg:postcode":"21758",
    "sg:province":"MD",
    "sg:tags":[
        "plant",
        "rental",
        "sales"
    ],
    "wof:name":"Tropical Plant Outfitters Inc",
    "wof:placetype":"venue"
},
  "geometry": {"coordinates":[-77.692041,39.353564],"type":"Point"}
}