{
  "type": "Feature",
  "properties": {
    "iso:country":"US",
    "sg:address":"10631 Gramercy Pl",
    "sg:city":"Columbia",
    "sg:classifiers":[
        {
            "category":"Building & Trades",
            "subcategory":"Construction",
            "type":"Services"
        }
    ],
    "sg:phone":"+1 410 772 0205",
    "sg:postcode":"21044",
    "sg:province":"MD",
    "sg:tags":[
        "general",
        "contractor"
    ],
    "wof:name":"Robert General Contractors LLC",
    "wof:placetype":"venue"
},
  "geometry": {"coordinates":[-76.86723000000001,39.213222],"type":"Point"}
}