{
  "type": "Feature",
  "properties": {
    "addr:full":"642 Oak Hill Ave Hagerstown MD 21740",
    "addr:housenumber":"642",
    "addr:postcode":"21740",
    "addr:street":"Oak Hill Ave",
    "iso:country":"US",
    "sg:address":"642 Oak Hill Ave",
    "sg:city":"Hagerstown",
    "sg:classifiers":[
        {
            "category":"Shopping",
            "subcategory":"Pharmacy",
            "type":"Retail Goods"
        }
    ],
    "sg:phone":"+1 301 739 2780",
    "sg:postcode":"21740",
    "sg:province":"MD",
    "wof:name":"Schindel's Pharmacy",
    "wof:placetype":"venue"
},
  "geometry": {"coordinates":[-77.713466,39.650482],"type":"Point"}
}