{
  "type": "Feature",
  "properties": {
    "addr:full":"3406 Woodridge Ct Bowie MD 20721",
    "addr:housenumber":"3406",
    "addr:postcode":"20721",
    "addr:street":"Woodridge Ct",
    "iso:country":"US",
    "sg:address":"3406 Woodridge Ct",
    "sg:city":"Bowie",
    "sg:classifiers":[
        {
            "category":"Professional",
            "type":"Services"
        }
    ],
    "sg:phone":"+1 301 459 5351",
    "sg:postcode":"20721",
    "sg:province":"MD",
    "wof:name":"Microsys Information Syst",
    "wof:placetype":"venue"
},
  "geometry": {"coordinates":[-76.825248,38.936497],"type":"Point"}
}