{
  "type": "Feature",
  "properties": {
    "addr:full":"245 N Pennsylvania Ave Hancock MD 21750",
    "addr:housenumber":"245",
    "addr:postcode":"21750",
    "addr:street":"N Pennsylvania Ave",
    "iso:country":"US",
    "sg:address":"245 N Pennsylvania Ave",
    "sg:city":"Hancock",
    "sg:classifiers":[
        {
            "category":"Building & Trades",
            "subcategory":"Construction",
            "type":"Services"
        }
    ],
    "sg:phone":"+1 301 678 5199",
    "sg:postcode":"21750",
    "sg:province":"MD",
    "sg:tags":[
        "hanging",
        "contractor"
    ],
    "wof:name":"Sextons Services",
    "wof:placetype":"venue"
},
  "geometry": {"coordinates":[-78.177705,39.71082],"type":"Point"}
}