{
  "type": "Feature",
  "properties": {
    "addr:full":"11011 Cherry Hill Rd Beltsville MD 20705",
    "addr:housenumber":"11011",
    "addr:postcode":"20705",
    "addr:street":"Cherry Hill Rd",
    "iso:country":"US",
    "sg:address":"11011 Cherry Hill Rd",
    "sg:city":"Beltsville",
    "sg:classifiers":[
        {
            "category":"Organizations",
            "subcategory":"Religious Organization",
            "type":"Services"
        }
    ],
    "sg:phone":"+1 410 956 0405",
    "sg:postcode":"20705",
    "sg:province":"MD",
    "sg:tags":[
        "church"
    ],
    "sg:website":"www.trinityrpc.org",
    "wof:name":"Trinity Reformed Presbyterian",
    "wof:placetype":"venue"
},
  "geometry": {"coordinates":[-76.94431899999999,39.034676],"type":"Point"}
}