{
  "type": "Feature",
  "properties": {
    "addr:full":"25122 Three Notch Rd Hollywood MD 20636",
    "addr:housenumber":"25122",
    "addr:postcode":"20636",
    "addr:street":"Three Notch Rd",
    "iso:country":"US",
    "sg:address":"25122 Three Notch Rd",
    "sg:city":"Hollywood",
    "sg:classifiers":[
        {
            "category":"Personal",
            "type":"Services"
        }
    ],
    "sg:phone":"+1 301 373 9732",
    "sg:postcode":"20636",
    "sg:province":"MD",
    "wof:name":"Heather Feathers",
    "wof:placetype":"venue"
},
  "geometry": {"coordinates":[-76.590282,38.365914],"type":"Point"}
}