{
  "type": "Feature",
  "properties": {
    "iso:country":"US",
    "sg:address":"1925 Lincoln Dr",
    "sg:city":"Annapolis",
    "sg:classifiers":[
        {
            "category":"Recreation",
            "type":"Entertainment"
        }
    ],
    "sg:phone":"+1 410 268 1508",
    "sg:postcode":"21401",
    "sg:province":"MD",
    "sg:tags":[
        "karate",
        "judo",
        "instr"
    ],
    "sg:website":"www.tommyleeconsulting.com",
    "wof:name":"East Coast Martial Arts",
    "wof:placetype":"venue"
},
  "geometry": {"coordinates":[-76.52252799999999,38.973953],"type":"Point"}
}