{
  "type": "Feature",
  "properties": {
    "iso:country":"US",
    "sg:address":"4417 Maple Ave",
    "sg:city":"Bethesda",
    "sg:classifiers":[
        {
            "category":"Professional",
            "type":"Services"
        }
    ],
    "sg:phone":"+1 301 580 6194",
    "sg:postcode":"20814",
    "sg:province":"MD",
    "sg:tags":[
        "technical",
        "consulting",
        "scientific"
    ],
    "wof:name":"Tech Micro Services",
    "wof:placetype":"venue"
},
  "geometry": {"coordinates":[-77.08929000000001,38.992225],"type":"Point"}
}