{
  "type": "Feature",
  "properties": {
    "addr:full":"216 Manor Ter Hyattsville MD 20785",
    "addr:housenumber":"216",
    "addr:postcode":"20785",
    "addr:street":"Manor Ter",
    "iso:country":"US",
    "sg:address":"216 Manor Ter",
    "sg:city":"Hyattsville",
    "sg:classifiers":[
        {
            "category":"Professional",
            "subcategory":"Computer Services",
            "type":"Services"
        }
    ],
    "sg:phone":"+1 301 336 9360",
    "sg:postcode":"20785",
    "sg:province":"MD",
    "sg:tags":[
        "repair",
        "equipment-service"
    ],
    "wof:name":"Good Computer Service Inc",
    "wof:placetype":"venue"
},
  "geometry": {"coordinates":[-76.85342900000001,38.892429],"type":"Point"}
}