{
  "type": "Feature",
  "properties": {
    "addr:full":"7760 Baltimore Annapolis Blvd Glen Burnie MD 21060",
    "addr:housenumber":"7760",
    "addr:postcode":"21060",
    "addr:street":"Baltimore Annapolis Blvd",
    "iso:country":"US",
    "sg:address":"7760 Baltimore Annapolis Blvd",
    "sg:city":"Glen Burnie",
    "sg:classifiers":[
        {
            "category":"Food & Beverages",
            "subcategory":"Groceries & Convenience Stores",
            "type":"Retail Goods"
        }
    ],
    "sg:phone":"+1 410 768 8012",
    "sg:postcode":"21060",
    "sg:province":"MD",
    "wof:name":"Extra Mart",
    "wof:placetype":"venue"
},
  "geometry": {"coordinates":[-76.592287,39.146992],"type":"Point"}
}