{
  "type": "Feature",
  "properties": {
    "addr:full":"212 S Bond St Bel Air MD 21014",
    "addr:housenumber":"212",
    "addr:postcode":"21014",
    "addr:street":"S Bond St",
    "iso:country":"US",
    "sg:address":"212 S Bond St",
    "sg:city":"Bel Air",
    "sg:classifiers":[
        {
            "category":"Professional",
            "subcategory":"Employment Agencies",
            "type":"Services"
        }
    ],
    "sg:phone":"+1 410 893 3707",
    "sg:postcode":"21014",
    "sg:province":"MD",
    "wof:name":"OConnell Associates",
    "wof:placetype":"venue"
},
  "geometry": {"coordinates":[-76.34795200000001,39.533542],"type":"Point"}
}