{
  "type": "Feature",
  "properties": {
    "iso:country":"US",
    "sg:address":"13761 Travilah Rd",
    "sg:city":"Rockville",
    "sg:classifiers":[
        {
            "category":"Home & Garden",
            "subcategory":"Garden Supply",
            "type":"Retail Goods"
        }
    ],
    "sg:phone":"+1 301 340 1818",
    "sg:postcode":"20850",
    "sg:province":"MD",
    "sg:tags":[
        "mulch"
    ],
    "wof:name":"Mulch & More",
    "wof:placetype":"venue"
},
  "geometry": {"coordinates":[-77.23926,39.080419],"type":"Point"}
}