{
  "type": "Feature",
  "properties": {
    "addr:full":"4500 N Park Ave Chevy Chase MD 20815",
    "addr:housenumber":"4500",
    "addr:postcode":"20815",
    "addr:street":"N Park Ave",
    "iso:country":"US",
    "sg:address":"4500 N Park Ave",
    "sg:city":"Chevy Chase",
    "sg:classifiers":[
        {
            "category":"Health Services",
            "subcategory":"Doctor",
            "type":"Services"
        }
    ],
    "sg:phone":"+1 301 656 6605",
    "sg:postcode":"20815",
    "sg:province":"MD",
    "sg:tags":[
        "psychiatrist"
    ],
    "wof:name":"Maynard Stuart PHD RN Cs",
    "wof:placetype":"venue"
},
  "geometry": {"coordinates":[-77.089401,38.9636],"type":"Point"}
}