{
  "type": "Feature",
  "properties": {
    "iso:country":"US",
    "sg:address":"1101 Corliss St",
    "sg:city":"Silver Spring",
    "sg:classifiers":[
        {
            "category":"Recreation",
            "type":"Entertainment"
        }
    ],
    "sg:phone":"+1 301 439 9889",
    "sg:postcode":"20903",
    "sg:province":"MD",
    "sg:tags":[
        "pool",
        "swimming"
    ],
    "wof:name":"Oakview Pool",
    "wof:placetype":"venue"
},
  "geometry": {"coordinates":[-76.988922,39.017036],"type":"Point"}
}