{
  "type": "Feature",
  "properties": {
    "addr:full":"2110 Priest Bridge Dr Crofton MD 21114",
    "addr:housenumber":"2110",
    "addr:postcode":"21114",
    "addr:street":"Priest Bridge Dr",
    "iso:country":"US",
    "sg:address":"2110 Priest Bridge Dr",
    "sg:city":"Crofton",
    "sg:classifiers":[
        {
            "category":"Organizations",
            "subcategory":"Religious Organization",
            "type":"Services"
        }
    ],
    "sg:phone":"+1 301 805 8236",
    "sg:postcode":"21114",
    "sg:province":"MD",
    "wof:name":"Covenant Life Church of God",
    "wof:placetype":"venue"
},
  "geometry": {"coordinates":[-76.69779200000001,38.989313],"type":"Point"}
}