{
  "type": "Feature",
  "properties": {
    "iso:country":"US",
    "sg:address":"9105 Rosemont Dr",
    "sg:city":"Gaithersburg",
    "sg:classifiers":[
        {
            "category":"Retail",
            "subcategory":"Auto Repair",
            "type":"Services"
        }
    ],
    "sg:phone":"+1 301 330 1170",
    "sg:postcode":"20877",
    "sg:province":"MD",
    "sg:tags":[
        "towing"
    ],
    "wof:name":"Morton's Towing & Recovery",
    "wof:placetype":"venue"
},
  "geometry": {"coordinates":[-77.18922999999999,39.127841],"type":"Point"}
}