{
  "type": "Feature",
  "properties": {
    "iso:country":"US",
    "sg:address":"400 S Pennsylvania Ave",
    "sg:city":"Delmar",
    "sg:classifiers":[
        {
            "category":"Government",
            "subcategory":"Police Station",
            "type":"Public Place"
        }
    ],
    "sg:phone":"+1 410 896 3132",
    "sg:postcode":"21875",
    "sg:province":"MD",
    "sg:tags":[
        "department"
    ],
    "sg:website":"http://www.delmarpolice.com",
    "wof:name":"Delmar Police Dept",
    "wof:placetype":"venue"
},
  "geometry": {"coordinates":[-75.57827,38.453281],"type":"Point"}
}