{
  "type": "Feature",
  "properties": {
    "addr:full":"6423 Appletown Rd Boonsboro MD 21713",
    "addr:housenumber":"6423",
    "addr:postcode":"21713",
    "addr:street":"Appletown Rd",
    "iso:country":"US",
    "sg:address":"6423 Appletown Rd",
    "sg:city":"Boonsboro",
    "sg:classifiers":[
        {
            "category":"Manufacturing",
            "subcategory":"Glass & Minerals",
            "type":"Manufacturing & Wholesale Goods"
        }
    ],
    "sg:phone":"+1 301 432 6948",
    "sg:postcode":"21713",
    "sg:province":"MD",
    "sg:tags":[
        "product",
        "nonmetallic",
        "mfg"
    ],
    "wof:name":"Earth Song Heirlooms",
    "wof:placetype":"venue"
},
  "geometry": {"coordinates":[-77.647808,39.488889],"type":"Point"}
}