{
  "type": "Feature",
  "properties": {
    "iso:country":"US",
    "sg:address":"1445 Rock Spring Rd",
    "sg:city":"Bel Air",
    "sg:classifiers":[
        {
            "category":"Shopping",
            "subcategory":"Used Merchandise",
            "type":"Retail Goods"
        }
    ],
    "sg:phone":"+1 410 803 0011",
    "sg:postcode":"21014",
    "sg:province":"MD",
    "sg:tags":[
        "antique"
    ],
    "wof:name":"Spenceola Antique Ctr",
    "wof:placetype":"venue"
},
  "geometry": {"coordinates":[-76.369549,39.557378],"type":"Point"}
}