{
  "type": "Feature",
  "properties": {
    "addr:full":"14104 Kydan Ct Brandywine MD 20613",
    "addr:housenumber":"14104",
    "addr:postcode":"20613",
    "addr:street":"Kydan Ct",
    "iso:country":"US",
    "sg:address":"14104 Kydan Ct",
    "sg:city":"Brandywine",
    "sg:classifiers":[
        {
            "category":"Building & Trades",
            "subcategory":"Plumbing",
            "type":"Services"
        }
    ],
    "sg:phone":"+1 301 372 3822",
    "sg:postcode":"20613",
    "sg:province":"MD",
    "sg:tags":[
        "plumbing",
        "contractor"
    ],
    "wof:name":"B J Harper Plumbing Inc",
    "wof:placetype":"venue"
},
  "geometry": {"coordinates":[-76.900454,38.69537],"type":"Point"}
}