{
  "type": "Feature",
  "properties": {
    "addr:full":"400 N 2nd St Oakland MD 21550",
    "addr:housenumber":"400",
    "addr:postcode":"21550",
    "addr:street":"N 2Nd St",
    "iso:country":"US",
    "sg:address":"400 N 2nd St",
    "sg:city":"Oakland",
    "sg:classifiers":[
        {
            "category":"Health Services",
            "subcategory":"Doctor",
            "type":"Services"
        }
    ],
    "sg:phone":"+1 301 334 2200",
    "sg:postcode":"21550",
    "sg:province":"MD",
    "sg:tags":[
        "medical"
    ],
    "wof:name":"Andrew E Mance MD",
    "wof:placetype":"venue"
},
  "geometry": {"coordinates":[-79.402248,39.41804],"type":"Point"}
}