{
  "type": "Feature",
  "properties": {
    "addr:full":"4902 Edmonston Rd Hyattsville MD 20781",
    "addr:housenumber":"4902",
    "addr:postcode":"20781",
    "addr:street":"Edmonston Rd",
    "iso:country":"US",
    "sg:address":"4902 Edmonston Rd",
    "sg:city":"Hyattsville",
    "sg:classifiers":[
        {
            "category":"Home & Garden",
            "subcategory":"Carpets & Floor Coverings",
            "type":"Retail Goods"
        }
    ],
    "sg:phone":"+1 301 277 3006",
    "sg:postcode":"20781",
    "sg:province":"MD",
    "sg:tags":[
        "installation",
        "rug"
    ],
    "wof:name":"Creative Carpet Art",
    "wof:placetype":"venue"
},
  "geometry": {"coordinates":[-76.927548,38.947562],"type":"Point"}
}