{
  "type": "Feature",
  "properties": {
    "iso:country":"US",
    "sg:address":"6200 Annapolis Rd",
    "sg:city":"Hyattsville",
    "sg:classifiers":[
        {
            "category":"Retail",
            "subcategory":"Repair Shop",
            "type":"Services"
        }
    ],
    "sg:phone":"+1 301 322 3981",
    "sg:postcode":"20784",
    "sg:province":"MD",
    "sg:tags":[
        "upholsterer"
    ],
    "wof:name":"P G Upholstery",
    "wof:placetype":"venue"
},
  "geometry": {"coordinates":[-76.908469,38.939091],"type":"Point"}
}