{
  "type": "Feature",
  "properties": {
    "addr:full":"7967 Quarterfield Rd Severn MD 21144",
    "addr:housenumber":"7967",
    "addr:postcode":"21144",
    "addr:street":"Quarterfield Rd",
    "iso:country":"US",
    "sg:address":"7967 Quarterfield Rd",
    "sg:city":"Severn",
    "sg:classifiers":[
        {
            "category":"Education",
            "subcategory":"School",
            "type":"Public Place"
        }
    ],
    "sg:phone":"+1 410 222 6430",
    "sg:postcode":"21144",
    "sg:province":"MD",
    "sg:tags":[
        "executive"
    ],
    "wof:name":"Quarterfield Elementary School",
    "wof:placetype":"venue"
},
  "geometry": {"coordinates":[-76.65682,39.134719],"type":"Point"}
}