{
  "type": "Feature",
  "properties": {
    "iso:country":"US",
    "sg:address":"7521 Connelley Dr",
    "sg:city":"Hanover",
    "sg:classifiers":[
        {
            "category":"Building & Trades",
            "subcategory":"Electrical",
            "type":"Services"
        }
    ],
    "sg:phone":"+1 410 768 1733",
    "sg:postcode":"21076",
    "sg:province":"MD",
    "sg:tags":[
        "electric",
        "contractor"
    ],
    "wof:name":"Meade Electric Co",
    "wof:placetype":"venue"
},
  "geometry": {"coordinates":[-76.68189,39.156175],"type":"Point"}
}