{
  "type": "Feature",
  "properties": {
    "iso:country":"US",
    "sg:address":"10264 Lake Arbor Way",
    "sg:city":"Bowie",
    "sg:classifiers":[
        {
            "category":"Health Services",
            "subcategory":"Dentist",
            "type":"Services"
        }
    ],
    "sg:phone":"+1 301 333 3900",
    "sg:postcode":"20721",
    "sg:province":"MD",
    "sg:website":"www.harmonorthodontics.com",
    "wof:name":"Harmon David E DDS MSD",
    "wof:placetype":"venue"
},
  "geometry": {"coordinates":[-76.829697,38.905201],"type":"Point"}
}