{
  "type": "Feature",
  "properties": {
    "addr:full":"5241 Red Hill Rd Keedysville MD 21756",
    "addr:housenumber":"5241",
    "addr:postcode":"21756",
    "addr:street":"Red Hill Rd",
    "iso:country":"US",
    "sg:address":"5241 Red Hill Rd",
    "sg:city":"Keedysville",
    "sg:classifiers":[
        {
            "category":"Organizations",
            "subcategory":"Community Association",
            "type":"Services"
        }
    ],
    "sg:phone":"+1 301 432 8857",
    "sg:postcode":"21756",
    "sg:province":"MD",
    "sg:tags":[
        "club"
    ],
    "wof:name":"Mc Clellan Gun Club",
    "wof:placetype":"venue"
},
  "geometry": {"coordinates":[-77.69966100000001,39.445533],"type":"Point"}
}