{
  "type": "Feature",
  "properties": {
    "addr:full":"8730 Georgia Ave Silver Spring MD 20910",
    "addr:housenumber":"8730",
    "addr:postcode":"20910",
    "addr:street":"Georgia Ave",
    "iso:country":"US",
    "sg:address":"8730 Georgia Ave",
    "sg:city":"Silver Spring",
    "sg:classifiers":[
        {
            "category":"Professional",
            "subcategory":"Management & Consulting",
            "type":"Services"
        }
    ],
    "sg:phone":"+1 301 589 0942",
    "sg:postcode":"20910",
    "sg:province":"MD",
    "sg:tags":[
        "consultant",
        "business"
    ],
    "wof:name":"Business Promotion",
    "wof:placetype":"venue"
},
  "geometry": {"coordinates":[-77.029769,38.997516],"type":"Point"}
}