{
  "type": "Feature",
  "properties": {
    "iso:country":"US",
    "sg:address":"305 W Chesapeake Ave # 500",
    "sg:city":"Towson",
    "sg:classifiers":[
        {
            "category":"Banks & Credit Unions",
            "subcategory":"Investment Brokerage",
            "type":"Services"
        },
        {
            "category":"Banks & Credit Unions",
            "subcategory":"Bank",
            "type":"Services"
        }
    ],
    "sg:phone":"+1 410 832 7860",
    "sg:postcode":"21204",
    "sg:province":"MD",
    "sg:tags":[
        "commercial",
        "trust",
        "saving"
    ],
    "sg:website":"http://www.mandtbank.com",
    "wof:name":"M&T",
    "wof:placetype":"venue"
},
  "geometry": {"coordinates":[-76.6092,39.400006],"type":"Point"}
}