{
  "type": "Feature",
  "properties": {
    "iso:country":"US",
    "sg:address":"1215 Leadenhall St",
    "sg:city":"Baltimore",
    "sg:phone":"+1 410 752 0325",
    "sg:postcode":"21230",
    "sg:province":"MD",
    "sg:website":"http://www.furstbros.com",
    "wof:name":"Furst Brothers Co",
    "wof:placetype":"venue"
},
  "geometry": {"coordinates":[-76.618394,39.275771],"type":"Point"}
}