{
  "type": "Feature",
  "properties": {
    "iso:country":"US",
    "sg:address":"18 Broad St",
    "sg:city":"Berlin",
    "sg:classifiers":[
        {
            "category":"Autos & Motor Vehicles",
            "subcategory":"Auto Supplies",
            "type":"Retail Goods"
        }
    ],
    "sg:phone":"+1 410 641 2000",
    "sg:postcode":"21811",
    "sg:province":"MD",
    "sg:tags":[
        "tire"
    ],
    "wof:name":"Wainwright's Tire Ctr",
    "wof:placetype":"venue"
},
  "geometry": {"coordinates":[-75.219238,38.324616],"type":"Point"}
}