{
  "type": "Feature",
  "properties": {
    "iso:country":"US",
    "sg:address":"43 S Market St",
    "sg:city":"Frederick",
    "sg:classifiers":[
        {
            "category":"Organizations",
            "subcategory":"Professional Association",
            "type":"Services"
        }
    ],
    "sg:phone":"+1 301 662 4164",
    "sg:postcode":"21701",
    "sg:province":"MD",
    "wof:name":"Frederick Chamber Of Commerce",
    "wof:placetype":"venue"
},
  "geometry": {"coordinates":[-77.411204,39.413168],"type":"Point"}
}