{
  "type": "Feature",
  "properties": {
    "addr:full":"27230 Fairmount Rd Westover MD 21871",
    "addr:housenumber":"27230",
    "addr:postcode":"21871",
    "addr:street":"Fairmount Rd",
    "iso:country":"US",
    "sg:address":"27230 Fairmount Rd",
    "sg:city":"Westover",
    "sg:classifiers":[
        {
            "category":"Building & Trades",
            "subcategory":"Construction",
            "type":"Services"
        }
    ],
    "sg:phone":"+1 410 651 5714",
    "sg:postcode":"21871",
    "sg:province":"MD",
    "sg:tags":[
        "excavating",
        "contractor"
    ],
    "wof:name":"Doug Vann Sand & Gravel",
    "wof:placetype":"venue"
},
  "geometry": {"coordinates":[-75.810451,38.096195],"type":"Point"}
}