{
  "type": "Feature",
  "properties": {
    "iso:country":"US",
    "sg:address":"1 Edith Ct",
    "sg:city":"Baltimore",
    "sg:classifiers":[
        {
            "category":"Professional",
            "subcategory":"Management & Consulting",
            "type":"Services"
        }
    ],
    "sg:phone":"+1 443 253 8991",
    "sg:postcode":"21244",
    "sg:province":"MD",
    "sg:tags":[
        "business"
    ],
    "wof:name":"Comnet Partners LLC",
    "wof:placetype":"venue"
},
  "geometry": {"coordinates":[-76.76962399999999,39.31003],"type":"Point"}
}