{
  "type": "Feature",
  "properties": {
    "addr:full":"410 Sandy Spring Rd Laurel MD 20707",
    "addr:housenumber":"410",
    "addr:postcode":"20707",
    "addr:street":"Sandy Spring Rd",
    "iso:country":"US",
    "sg:address":"410 Sandy Spring Rd",
    "sg:city":"Laurel",
    "sg:classifiers":[
        {
            "category":"Food & Beverages",
            "subcategory":"Groceries & Convenience Stores",
            "type":"Retail Goods"
        }
    ],
    "sg:phone":"+1 301 362 9581",
    "sg:postcode":"20707",
    "sg:province":"MD",
    "sg:tags":[
        "grocer"
    ],
    "wof:name":"Food Lion",
    "wof:placetype":"venue"
},
  "geometry": {"coordinates":[-76.863687,39.106042],"type":"Point"}
}