{
  "type": "Feature",
  "properties": {
    "addr:full":"17977 Dumfries Cir Olney MD 20832",
    "addr:housenumber":"17977",
    "addr:postcode":"20832",
    "addr:street":"Dumfries Cir",
    "iso:country":"US",
    "sg:address":"17977 Dumfries Cir",
    "sg:city":"Olney",
    "sg:classifiers":[
        {
            "category":"Insurance",
            "subcategory":"Hazard Insurance",
            "type":"Services"
        }
    ],
    "sg:phone":"+1 301 260 9002",
    "sg:postcode":"20832",
    "sg:province":"MD",
    "sg:tags":[
        "commercial",
        "business"
    ],
    "wof:name":"Campbell Financial Insurance",
    "wof:placetype":"venue"
},
  "geometry": {"coordinates":[-77.050436,39.15249],"type":"Point"}
}