{
  "type": "Feature",
  "properties": {
    "addr:full":"4110 1/2 Pine Hill Rd Perry Hall MD 21128",
    "addr:housenumber":"4110 1 / 2",
    "addr:postcode":"21128",
    "addr:street":"Pine Hill Rd",
    "iso:country":"US",
    "sg:address":"4110 1/2 Pine Hill Rd",
    "sg:city":"Perry Hall",
    "sg:classifiers":[
        {
            "category":"Retail",
            "subcategory":"Event Space",
            "type":"Services"
        }
    ],
    "sg:phone":"+1 410 529 1582",
    "sg:postcode":"21128",
    "sg:province":"MD",
    "sg:tags":[
        "venue"
    ],
    "wof:name":"Knights of Columbus",
    "wof:placetype":"venue"
},
  "geometry": {"coordinates":[-76.473759,39.405436],"type":"Point"}
}