{
  "type": "Feature",
  "properties": {
    "addr:full":"1221 Cherry Tree Ln Annapolis MD 21403",
    "addr:housenumber":"1221",
    "addr:postcode":"21403",
    "addr:street":"Cherry Tree Ln",
    "iso:country":"US",
    "sg:address":"1221 Cherry Tree Ln",
    "sg:city":"Annapolis",
    "sg:classifiers":[
        {
            "category":"Professional",
            "subcategory":"Business Services",
            "type":"Services"
        }
    ],
    "sg:phone":"+1 410 268 2720",
    "sg:postcode":"21403",
    "sg:province":"MD",
    "wof:name":"Cabbages & Kings Ltd",
    "wof:placetype":"venue"
},
  "geometry": {"coordinates":[-76.476829,38.928034],"type":"Point"}
}