{
  "type": "Feature",
  "properties": {
    "addr:full":"10400 Shaker Dr Ste 7 Columbia MD 21046",
    "addr:housenumber":"10400",
    "addr:postcode":"21046",
    "addr:street":"Shaker Dr Ste 7",
    "iso:country":"US",
    "sg:address":"10400 Shaker Dr Ste 7",
    "sg:city":"Columbia",
    "sg:classifiers":[
        {
            "category":"Manufacturing",
            "subcategory":"Apparel",
            "type":"Manufacturing & Wholesale Goods"
        }
    ],
    "sg:phone":"+1 410 964 1131",
    "sg:postcode":"21046",
    "sg:province":"MD",
    "sg:tags":[
        "clothing-men's-wholesale",
        "manufacturer"
    ],
    "sg:website":"http://www.bransons.us",
    "wof:name":"Branson's",
    "wof:placetype":"venue"
},
  "geometry": {"coordinates":[-76.87183400000001,39.184052],"type":"Point"}
}