{
  "type": "Feature",
  "properties": {
    "addr:full":"10210 Democracy Ln Rockville MD 20854",
    "addr:housenumber":"10210",
    "addr:postcode":"20854",
    "addr:street":"Democracy Ln",
    "iso:country":"US",
    "sg:address":"10210 Democracy Ln",
    "sg:city":"Rockville",
    "sg:classifiers":[
        {
            "category":"Building & Trades",
            "subcategory":"Construction",
            "type":"Services"
        }
    ],
    "sg:phone":"+1 301 767 1916",
    "sg:postcode":"20854",
    "sg:province":"MD",
    "sg:tags":[
        "general",
        "contractor"
    ],
    "wof:name":"Pollin Construction Co",
    "wof:placetype":"venue"
},
  "geometry": {"coordinates":[-77.16514599999999,39.024549],"type":"Point"}
}