{
  "type": "Feature",
  "properties": {
    "addr:full":"16302 Baden Westwood Rd Brandywine MD 20613",
    "addr:housenumber":"16302",
    "addr:postcode":"20613",
    "addr:street":"Westwood Rd",
    "iso:country":"US",
    "sg:address":"16302 Baden Westwood Rd",
    "sg:city":"Brandywine",
    "sg:classifiers":[
        {
            "category":"Freight",
            "type":"Transportation"
        }
    ],
    "sg:phone":"+1 240 882 7872",
    "sg:postcode":"20613",
    "sg:province":"MD",
    "sg:tags":[
        "operator",
        "truck",
        "local",
        "dump",
        "trucking"
    ],
    "wof:name":"Clifford S Sweeney",
    "wof:placetype":"venue"
},
  "geometry": {"coordinates":[-76.722114,38.649095],"type":"Point"}
}