{
  "type": "Feature",
  "properties": {
    "addr:full":"9400 New Rd Mcdaniel MD 21647",
    "addr:housenumber":"9400",
    "addr:postcode":"21647",
    "addr:street":"New Rd",
    "iso:country":"US",
    "sg:address":"9400 New Rd",
    "sg:city":"Mcdaniel",
    "sg:classifiers":[
        {
            "category":"Home & Garden",
            "subcategory":"Building Materials",
            "type":"Retail Goods"
        }
    ],
    "sg:phone":"+1 410 745 5037",
    "sg:postcode":"21647",
    "sg:province":"MD",
    "sg:tags":[
        "equipment",
        "builder",
        "greenhouse"
    ],
    "wof:name":"Bay Hundred Botanicals",
    "wof:placetype":"venue"
},
  "geometry": {"coordinates":[-76.29555499999999,38.815805],"type":"Point"}
}