{
  "type": "Feature",
  "properties": {
    "iso:country":"US",
    "sg:address":"9248 Downsville Pike",
    "sg:city":"Williamsport",
    "sg:classifiers":[
        {
            "category":"Farming",
            "subcategory":"Farm",
            "type":"Manufacturing & Wholesale Goods"
        }
    ],
    "sg:phone":"+1 301 223 7998",
    "sg:postcode":"21795",
    "sg:province":"MD",
    "sg:tags":[
        "crop",
        "general"
    ],
    "wof:name":"Countryside Produce",
    "wof:placetype":"venue"
},
  "geometry": {"coordinates":[-77.788639,39.567231],"type":"Point"}
}