{
  "type": "Feature",
  "properties": {
    "addr:full":"9580 Old Annapolis Rd Ellicott City MD 21042",
    "addr:housenumber":"9580",
    "addr:postcode":"21042",
    "addr:street":"Old Annapolis Rd",
    "iso:country":"US",
    "sg:address":"9580 Old Annapolis Rd",
    "sg:city":"Ellicott City",
    "sg:classifiers":[
        {
            "category":"Organizations",
            "subcategory":"Religious Organization",
            "type":"Services"
        }
    ],
    "sg:phone":"+1 410 465 0206",
    "sg:postcode":"21042",
    "sg:province":"MD",
    "sg:tags":[
        "church"
    ],
    "wof:name":"First Mennonite Ch Of Columbia",
    "wof:placetype":"venue"
},
  "geometry": {"coordinates":[-76.84563,39.244196],"type":"Point"}
}