{
  "type": "Feature",
  "properties": {
    "addr:full":"5650 Annapolis Rd Bladensburg MD 20710",
    "addr:housenumber":"5650",
    "addr:postcode":"20710",
    "addr:street":"Annapolis Rd",
    "iso:country":"US",
    "sg:address":"5650 Annapolis Rd",
    "sg:city":"Bladensburg",
    "sg:classifiers":[
        {
            "category":"Utilities",
            "subcategory":"Telephone",
            "type":"Services"
        },
        {
            "category":"Communications",
            "type":"Services"
        }
    ],
    "sg:phone":"+1 301 277 9711",
    "sg:postcode":"20710",
    "sg:province":"MD",
    "sg:tags":[
        "equipment-servicing",
        "systems-repair",
        "answering",
        "system",
        "equipment"
    ],
    "wof:name":"Sterling Payphone",
    "wof:placetype":"venue"
},
  "geometry": {"coordinates":[-76.920374,38.939261],"type":"Point"}
}