{
  "type": "Feature",
  "properties": {
    "addr:full":"2208 Deckman Ln Silver Spring MD 20906",
    "addr:postcode":"2208;20906",
    "addr:street":"Deckman Ln",
    "iso:country":"US",
    "sg:address":"2208 Deckman Ln",
    "sg:city":"Silver Spring",
    "sg:classifiers":[
        {
            "category":"Retail",
            "subcategory":"Auto Rental",
            "type":"Services"
        }
    ],
    "sg:phone":"+1 301 404 7757",
    "sg:postcode":"20906",
    "sg:province":"MD",
    "sg:tags":[
        "passenger",
        "car"
    ],
    "wof:name":"Pradit Akkarach",
    "wof:placetype":"venue"
},
  "geometry": {"coordinates":[-77.048365,39.079649],"type":"Point"}
}