{
  "type": "Feature",
  "properties": {
    "iso:country":"US",
    "sg:address":"3300 Hollins Ferry Rd",
    "sg:city":"Halethorpe",
    "sg:classifiers":[
        {
            "category":"Retail",
            "subcategory":"Auto Repair",
            "type":"Services"
        }
    ],
    "sg:phone":"+1 410 242 7422",
    "sg:postcode":"21227",
    "sg:province":"MD",
    "sg:tags":[
        "body",
        "painting",
        "repairing",
        "automobile"
    ],
    "wof:name":"I.Q. Body & Paint Shop",
    "wof:placetype":"venue"
},
  "geometry": {"coordinates":[-76.64724699999999,39.25],"type":"Point"}
}