{
  "type": "Feature",
  "properties": {
    "addr:full":"15825 Crabbs Branch Way Rockville MD 20855",
    "addr:housenumber":"15825",
    "addr:postcode":"20855",
    "addr:street":"Crabbs Branch Way",
    "iso:country":"US",
    "sg:address":"15825 Crabbs Branch Way",
    "sg:city":"Rockville",
    "sg:classifiers":[
        {
            "category":"Building & Trades",
            "subcategory":"Cleaning & Sanitation",
            "type":"Services"
        }
    ],
    "sg:phone":"+1 301 258 0015",
    "sg:postcode":"20855",
    "sg:province":"MD",
    "sg:tags":[
        "janitor"
    ],
    "wof:name":"Molly Maids",
    "wof:placetype":"venue"
},
  "geometry": {"coordinates":[-77.15660699999999,39.113062],"type":"Point"}
}