{
  "type": "Feature",
  "properties": {
    "iso:country":"US",
    "sg:address":"1012 Crain Hwy S",
    "sg:city":"Glen Burnie",
    "sg:classifiers":[
        {
            "category":"Retail",
            "subcategory":"Animal Services",
            "type":"Services"
        }
    ],
    "sg:phone":"+1 410 760 3666",
    "sg:postcode":"21061",
    "sg:province":"MD",
    "sg:tags":[
        "pet",
        "grooming",
        "washing"
    ],
    "wof:name":"It's A Dogs World",
    "wof:placetype":"venue"
},
  "geometry": {"coordinates":[-76.630994,39.154312],"type":"Point"}
}