{
  "type": "Feature",
  "properties": {
    "addr:full":"113 S Main St Greensboro MD 21639",
    "addr:housenumber":"113",
    "addr:postcode":"21639",
    "addr:street":"S Main St",
    "iso:country":"US",
    "sg:address":"113 S Main St",
    "sg:city":"Greensboro",
    "sg:classifiers":[
        {
            "category":"Real Estate",
            "subcategory":"Real Estate Agent",
            "type":"Services"
        }
    ],
    "sg:phone":"+1 410 482 7111",
    "sg:postcode":"21639",
    "sg:province":"MD",
    "sg:website":"www.championrealty.com",
    "wof:name":"Champion Peninsula Realty",
    "wof:placetype":"venue"
},
  "geometry": {"coordinates":[-75.805294,38.974147],"type":"Point"}
}