{
  "type": "Feature",
  "properties": {
    "iso:country":"US",
    "sg:address":"3804 Regency Pkwy",
    "sg:city":"Suitland",
    "sg:classifiers":[
        {
            "category":"Food & Beverages",
            "subcategory":"Specialty",
            "type":"Retail Goods"
        }
    ],
    "sg:phone":"+1 301 735 3986",
    "sg:postcode":"20746",
    "sg:province":"MD",
    "sg:tags":[
        "honey"
    ],
    "wof:name":"Honey And Company",
    "wof:placetype":"venue"
},
  "geometry": {"coordinates":[-76.91195999999999,38.83844],"type":"Point"}
}