{
  "type": "Feature",
  "properties": {
    "addr:full":"7510 Shadywood Rd Bethesda MD 20817",
    "addr:housenumber":"7510",
    "addr:postcode":"20817",
    "addr:street":"Shadywood Rd",
    "iso:country":"US",
    "sg:address":"7510 Shadywood Rd",
    "sg:city":"Bethesda",
    "sg:classifiers":[
        {
            "category":"Professional",
            "subcategory":"Accounting & Tax Preparation",
            "type":"Services"
        }
    ],
    "sg:phone":"+1 301 469 7773",
    "sg:postcode":"20817",
    "sg:province":"MD",
    "sg:tags":[
        "auditing"
    ],
    "wof:name":"Hugo E Souza CPA & Associates",
    "wof:placetype":"venue"
},
  "geometry": {"coordinates":[-77.15692300000001,39.008192],"type":"Point"}
}