{
  "type": "Feature",
  "properties": {
    "iso:country":"US",
    "sg:address":"13400 Triadelphia Rd",
    "sg:city":"Ellicott City",
    "sg:classifiers":[
        {
            "category":"Education",
            "subcategory":"School",
            "type":"Public Place"
        }
    ],
    "sg:phone":"+1 410 313 2560",
    "sg:postcode":"21042",
    "sg:province":"MD",
    "wof:name":"Triadelphia Ridge Elementary",
    "wof:placetype":"venue"
},
  "geometry": {"coordinates":[-76.977369,39.266163],"type":"Point"}
}