{
  "type": "Feature",
  "properties": {
    "addr:full":"515 E Joppa Rd Baltimore MD 21286",
    "addr:housenumber":"515",
    "addr:postcode":"21286",
    "addr:street":"E Joppa Rd",
    "iso:country":"US",
    "sg:address":"515 E Joppa Rd",
    "sg:city":"Baltimore",
    "sg:classifiers":[
        {
            "category":"Organizations",
            "subcategory":"Non-profit Organization",
            "type":"Services"
        }
    ],
    "sg:phone":"+1 410 828 4205",
    "sg:postcode":"21286",
    "sg:province":"MD",
    "wof:name":"Work Force Solutions",
    "wof:placetype":"venue"
},
  "geometry": {"coordinates":[-76.595016,39.401607],"type":"Point"}
}