{
  "type": "Feature",
  "properties": {
    "addr:full":"16 E Patrick St Frederick MD 21701",
    "addr:housenumber":"16",
    "addr:postcode":"21701",
    "addr:street":"E Patrick St",
    "iso:country":"US",
    "sg:address":"16 E Patrick St",
    "sg:city":"Frederick",
    "sg:classifiers":[
        {
            "category":"Professional",
            "subcategory":"Advertising",
            "type":"Services"
        }
    ],
    "sg:phone":"+1 301 703 9034",
    "sg:postcode":"21701",
    "sg:province":"MD",
    "sg:tags":[
        "counselor",
        "datum",
        "processing"
    ],
    "sg:website":"http://national.citysearch.com/profile/external/5025090/frederick_md/immersion_active.html?publisher=yellowpages&reference_id=7&placement=ypwebsitemip",
    "wof:name":"Immersion Active",
    "wof:placetype":"venue"
},
  "geometry": {"coordinates":[-77.410687,39.414148],"type":"Point"}
}