{
  "type": "Feature",
  "properties": {
    "addr:full":"8036 Jumpers Hole Rd Pasadena MD 21122",
    "addr:housenumber":"8036",
    "addr:postcode":"21122",
    "addr:street":"Jumpers Hole Rd",
    "iso:country":"US",
    "sg:address":"8036 Jumpers Hole Rd",
    "sg:city":"Pasadena",
    "sg:classifiers":[
        {
            "category":"Restaurant",
            "type":"Food & Drink"
        }
    ],
    "sg:menulink":"http://www.allmenus.com/md/lake-shore/87525-little-caesars-pizza/menu/",
    "sg:phone":"+1 410 761 3942",
    "sg:postcode":"21122",
    "sg:province":"MD",
    "sg:tags":[
        "american",
        "pizza"
    ],
    "wof:name":"Little Caesar's Pizza",
    "wof:placetype":"venue"
},
  "geometry": {"coordinates":[-76.587384,39.129767],"type":"Point"}
}