{
  "type": "Feature",
  "properties": {
    "iso:country":"US",
    "sg:address":"2300 W Lafayette Ave",
    "sg:city":"Baltimore",
    "sg:classifiers":[
        {
            "category":"Place Of Worship",
            "subcategory":"Church",
            "type":"Public Place"
        },
        {
            "category":"Place Of Worship",
            "type":"Public Place"
        },
        {
            "category":"Organizations",
            "subcategory":"Religious Organization",
            "type":"Services"
        }
    ],
    "sg:phone":"+1 410 945 0002",
    "sg:postcode":"21216",
    "sg:province":"MD",
    "sg:tags":[
        "churches-episcopal-anglican",
        "churches-episcopal"
    ],
    "wof:name":"Church Of The Holy Trinity",
    "wof:placetype":"venue"
},
  "geometry": {"coordinates":[-76.65342699999999,39.298531],"type":"Point"}
}