{
  "type": "Feature",
  "properties": {
    "iso:country":"US",
    "sg:address":"700 Cambridge Plz",
    "sg:city":"Cambridge",
    "sg:classifiers":[
        {
            "category":"Home & Garden",
            "subcategory":"Building Materials",
            "type":"Retail Goods"
        }
    ],
    "sg:phone":"+1 410 221 0880",
    "sg:postcode":"21613",
    "sg:province":"MD",
    "sg:tags":[
        "paint"
    ],
    "wof:name":"Sherwin-Williams Paints",
    "wof:placetype":"venue"
},
  "geometry": {"coordinates":[-76.064796,38.561251],"type":"Point"}
}