{
  "type": "Feature",
  "properties": {
    "addr:full":"3601 Powder Mill Rd Beltsville MD 20705",
    "addr:housenumber":"3601",
    "addr:postcode":"20705",
    "addr:street":"Powder Mill Rd",
    "iso:country":"US",
    "sg:address":"3601 Powder Mill Rd",
    "sg:city":"Beltsville",
    "sg:classifiers":[
        {
            "category":"Organizations",
            "subcategory":"Religious Organization",
            "type":"Services"
        }
    ],
    "sg:phone":"+1 301 931 0313",
    "sg:postcode":"20705",
    "sg:province":"MD",
    "sg:tags":[
        "church"
    ],
    "wof:name":"Hope Chrstian Church",
    "wof:placetype":"venue"
},
  "geometry": {"coordinates":[-76.943264,39.043683],"type":"Point"}
}