{
  "type": "Feature",
  "properties": {
    "iso:country":"US",
    "sg:address":"2022 N Charles St",
    "sg:city":"Baltimore",
    "sg:classifiers":[
        {
            "category":"Organizations",
            "subcategory":"Non-profit Organization",
            "type":"Services"
        }
    ],
    "sg:phone":"+1 410 752 9072",
    "sg:postcode":"21218",
    "sg:province":"MD",
    "sg:tags":[
        "lesbian",
        "gay"
    ],
    "sg:website":"www.brotherhelpthyself.org",
    "wof:name":"Brother Help Thy Self",
    "wof:placetype":"venue"
},
  "geometry": {"coordinates":[-76.616783,39.313],"type":"Point"}
}