{
  "type": "Feature",
  "properties": {
    "iso:country":"US",
    "sg:address":"116 W University Pkwy # 426",
    "sg:city":"Baltimore",
    "sg:classifiers":[
        {
            "category":"Professional",
            "subcategory":"Management & Consulting",
            "type":"Services"
        },
        {
            "category":"Professional",
            "subcategory":"Advertising",
            "type":"Services"
        }
    ],
    "sg:phone":"+1 410 235 6789",
    "sg:postcode":"21210",
    "sg:province":"MD",
    "sg:tags":[
        "marketing",
        "program",
        "consultant"
    ],
    "wof:name":"Go Marketing Group",
    "wof:placetype":"venue"
},
  "geometry": {"coordinates":[-76.620859,39.334565],"type":"Point"}
}