{
  "type": "Feature",
  "properties": {
    "addr:full":"11029 Race Track Rd Berlin MD 21811",
    "addr:housenumber":"11029",
    "addr:postcode":"21811",
    "addr:street":"Race Track Rd",
    "iso:country":"US",
    "sg:address":"11029 Race Track Rd",
    "sg:city":"Berlin",
    "sg:classifiers":[
        {
            "category":"Banks & Credit Unions",
            "subcategory":"Bank",
            "type":"Services"
        }
    ],
    "sg:phone":"+1 410 208 1668",
    "sg:postcode":"21811",
    "sg:province":"MD",
    "sg:tags":[
        "savings",
        "loan",
        "association"
    ],
    "wof:name":"First Shore Federal S & L Assn",
    "wof:placetype":"venue"
},
  "geometry": {"coordinates":[-75.16652499999999,38.378342],"type":"Point"}
}