{
  "type": "Feature",
  "properties": {
    "iso:country":"US",
    "sg:address":"18 West St",
    "sg:city":"Annapolis",
    "sg:classifiers":[
        {
            "category":"Professional",
            "subcategory":"Lawyer & Legal Services",
            "type":"Services"
        }
    ],
    "sg:phone":"+1 410 280 9311",
    "sg:postcode":"21401",
    "sg:province":"MD",
    "sg:tags":[
        "attorney",
        "plan"
    ],
    "wof:name":"Stone & Youngberg",
    "wof:placetype":"venue"
},
  "geometry": {"coordinates":[-76.49477400000001,38.978344],"type":"Point"}
}