{
  "type": "Feature",
  "properties": {
    "iso:country":"US",
    "sg:address":"4901 Woodbine Rd",
    "sg:city":"Sykesville",
    "sg:classifiers":[
        {
            "category":"Place Of Worship",
            "subcategory":"Church",
            "type":"Public Place"
        },
        {
            "category":"Place Of Worship",
            "type":"Public Place"
        }
    ],
    "sg:phone":"+1 410 795 6136",
    "sg:postcode":"21784",
    "sg:province":"MD",
    "sg:tags":[
        "churches-methodist"
    ],
    "wof:name":"Ebenezer United Methodist Church",
    "wof:placetype":"venue"
},
  "geometry": {"coordinates":[-77.05476299999999,39.439086],"type":"Point"}
}