{
  "type": "Feature",
  "properties": {
    "addr:full":"22599 MacArthur Blvd California MD 20619",
    "addr:housenumber":"22599",
    "addr:postcode":"20619",
    "addr:street":"Macarthur Blvd",
    "iso:country":"US",
    "sg:address":"22599 MacArthur Blvd",
    "sg:city":"California",
    "sg:classifiers":[
        {
            "category":"Shopping",
            "subcategory":"Beauty & Cosmetics",
            "type":"Retail Goods"
        }
    ],
    "sg:phone":"+1 301 862 0042",
    "sg:postcode":"20619",
    "sg:province":"MD",
    "sg:tags":[
        "supply"
    ],
    "wof:name":"Sally Beauty Co Inc",
    "wof:placetype":"venue"
},
  "geometry": {"coordinates":[-76.487099,38.283001],"type":"Point"}
}