{
  "type": "Feature",
  "properties": {
    "addr:full":"27 S Harrison St Easton MD 21601",
    "addr:housenumber":"27",
    "addr:postcode":"21601",
    "addr:street":"S Harrison St",
    "iso:country":"US",
    "sg:address":"27 S Harrison St",
    "sg:city":"Easton",
    "sg:classifiers":[
        {
            "category":"Shopping",
            "subcategory":"Used Merchandise",
            "type":"Retail Goods"
        }
    ],
    "sg:phone":"+1 410 763 8853",
    "sg:postcode":"21601",
    "sg:province":"MD",
    "sg:tags":[
        "antique"
    ],
    "wof:name":"Easton Maritime Antiques",
    "wof:placetype":"venue"
},
  "geometry": {"coordinates":[-76.074674,38.773157],"type":"Point"}
}