{
  "type": "Feature",
  "properties": {
    "addr:full":"800 Oldham St Baltimore MD 21224",
    "addr:housenumber":"800",
    "addr:postcode":"21224",
    "addr:street":"Oldham St",
    "iso:country":"US",
    "sg:address":"800 Oldham St",
    "sg:city":"Baltimore",
    "sg:classifiers":[
        {
            "category":"Place Of Worship",
            "subcategory":"Church",
            "type":"Public Place"
        },
        {
            "category":"Place Of Worship",
            "type":"Public Place"
        },
        {
            "category":"Organizations",
            "subcategory":"Religious Organization",
            "type":"Services"
        }
    ],
    "sg:phone":"+1 410 327 0177",
    "sg:postcode":"21224",
    "sg:province":"MD",
    "sg:tags":[
        "god",
        "churches-church",
        "churches-pentecostal"
    ],
    "sg:website":"www.churchofgod.cc",
    "wof:name":"East Baltimore Church of God",
    "wof:placetype":"venue"
},
  "geometry": {"coordinates":[-76.555702,39.283699],"type":"Point"}
}