{
  "type": "Feature",
  "properties": {
    "iso:country":"US",
    "sg:address":"1616 E 28th St",
    "sg:city":"Baltimore",
    "sg:classifiers":[
        {
            "category":"Arts & Performance",
            "subcategory":"Theater",
            "type":"Entertainment"
        }
    ],
    "sg:phone":"+1 410 625 1165",
    "sg:postcode":"21218",
    "sg:province":"MD",
    "sg:tags":[
        "entertainer"
    ],
    "wof:name":"Monique Watkins",
    "wof:placetype":"venue"
},
  "geometry": {"coordinates":[-76.592072,39.323977],"type":"Point"}
}