{
  "type": "Feature",
  "properties": {
    "addr:full":"49 N Potomac St Hagerstown MD 21740",
    "addr:housenumber":"49",
    "addr:postcode":"21740",
    "addr:street":"N Potomac St",
    "iso:country":"US",
    "sg:address":"49 N Potomac St",
    "sg:city":"Hagerstown",
    "sg:classifiers":[
        {
            "category":"Professional",
            "type":"Services"
        }
    ],
    "sg:phone":"+1 301 733 3839",
    "sg:postcode":"21740",
    "sg:province":"MD",
    "sg:tags":[
        "establishment"
    ],
    "wof:name":"47-51 Limited Partnership",
    "wof:placetype":"venue"
},
  "geometry": {"coordinates":[-77.719414,39.64324],"type":"Point"}
}