{
  "type": "Feature",
  "properties": {
    "iso:country":"US",
    "sg:address":"222 S Bridge St",
    "sg:city":"Elkton",
    "sg:classifiers":[
        {
            "category":"Insurance",
            "subcategory":"Insurance Agent",
            "type":"Services"
        }
    ],
    "sg:phone":"+1 443 245 7580",
    "sg:postcode":"21921",
    "sg:province":"MD",
    "wof:name":"Prudential Insurance Co",
    "wof:placetype":"venue"
},
  "geometry": {"coordinates":[-75.83021599999999,39.603982],"type":"Point"}
}