{
  "type": "Feature",
  "properties": {
    "addr:full":"8715 Green Pastures Dr Towson MD 21286",
    "addr:housenumber":"8715",
    "addr:postcode":"21286",
    "addr:street":"Green Pastures Dr",
    "iso:country":"US",
    "sg:address":"8715 Green Pastures Dr",
    "sg:city":"Towson",
    "sg:classifiers":[
        {
            "category":"Wholesale",
            "subcategory":"Durable Goods & Equipment",
            "type":"Manufacturing & Wholesale Goods"
        }
    ],
    "sg:phone":"+1 410 321 4427",
    "sg:postcode":"21286",
    "sg:province":"MD",
    "sg:tags":[
        "laboratory",
        "supply"
    ],
    "wof:name":"JJB Industries LTD",
    "wof:placetype":"venue"
},
  "geometry": {"coordinates":[-76.56743400000001,39.400017],"type":"Point"}
}