{
  "type": "Feature",
  "properties": {
    "iso:country":"US",
    "sg:address":"14 S Market St",
    "sg:city":"Frederick",
    "sg:classifiers":[
        {
            "category":"Shopping",
            "subcategory":"Gifts & Souvenirs",
            "type":"Retail Goods"
        }
    ],
    "sg:phone":"+1 301 662 0603",
    "sg:postcode":"21701",
    "sg:province":"MD",
    "sg:tags":[
        "announcement",
        "invitation"
    ],
    "wof:name":"Inkthis",
    "wof:placetype":"venue"
},
  "geometry": {"coordinates":[-77.41100299999999,39.413665],"type":"Point"}
}