{
  "type": "Feature",
  "properties": {
    "addr:full":"6001 Montrose Rd #1010 Rockville MD 20852",
    "addr:housenumber":"6001",
    "addr:postcode":"20852",
    "addr:street":"Montrose Rd # 1010",
    "iso:country":"US",
    "sg:address":"6001 Montrose Rd #1010",
    "sg:city":"Rockville",
    "sg:classifiers":[
        {
            "category":"Health Services",
            "subcategory":"Dentist",
            "type":"Services"
        }
    ],
    "sg:phone":"+1 301 468 6200",
    "sg:postcode":"20852",
    "sg:province":"MD",
    "sg:website":"www.successfulsmiles.net",
    "wof:name":"Gary Adams DDS",
    "wof:placetype":"venue"
},
  "geometry": {"coordinates":[-77.119613,39.053],"type":"Point"}
}