{
  "type": "Feature",
  "properties": {
    "addr:full":"4800 Indian Ln College Park MD 20740",
    "addr:housenumber":"4800",
    "addr:postcode":"20740",
    "addr:street":"Indian Ln",
    "iso:country":"US",
    "sg:address":"4800 Indian Ln",
    "sg:city":"College Park",
    "sg:classifiers":[
        {
            "category":"Professional",
            "subcategory":"Engineering",
            "type":"Services"
        }
    ],
    "sg:phone":"+1 301 345 8782",
    "sg:postcode":"20740",
    "sg:province":"MD",
    "sg:tags":[
        "engineer"
    ],
    "wof:name":"Anco Engineering",
    "wof:placetype":"venue"
},
  "geometry": {"coordinates":[-76.92639200000001,39.00852],"type":"Point"}
}