{
  "type": "Feature",
  "properties": {
    "addr:full":"405 High St New Windsor MD 21776",
    "addr:housenumber":"405",
    "addr:postcode":"21776",
    "addr:street":"High St",
    "iso:country":"US",
    "sg:address":"405 High St",
    "sg:city":"New Windsor",
    "sg:classifiers":[
        {
            "category":"Building & Trades",
            "subcategory":"Plumbing",
            "type":"Services"
        }
    ],
    "sg:phone":"+1 410 635 6500",
    "sg:postcode":"21776",
    "sg:province":"MD",
    "sg:tags":[
        "plumbing",
        "contractor"
    ],
    "wof:name":"D P Smelser & Sons Inc",
    "wof:placetype":"venue"
},
  "geometry": {"coordinates":[-77.10630399999999,39.540044],"type":"Point"}
}