{
  "type": "Feature",
  "properties": {
    "iso:country":"US",
    "sg:address":"8651 Cipriano Springs Ct",
    "sg:city":"Lanham",
    "sg:classifiers":[
        {
            "category":"Shopping",
            "subcategory":"Catalog Store",
            "type":"Retail Goods"
        }
    ],
    "sg:phone":"+1 301 552 9571",
    "sg:postcode":"20706",
    "sg:province":"MD",
    "sg:tags":[
        "mail",
        "order"
    ],
    "wof:name":"Girdlebound",
    "wof:placetype":"venue"
},
  "geometry": {"coordinates":[-76.856092,38.988772],"type":"Point"}
}