{
  "type": "Feature",
  "properties": {
    "iso:country":"US",
    "sg:address":"1512 Magnolia Dr",
    "sg:city":"Salisbury",
    "sg:classifiers":[
        {
            "category":"Manufacturing",
            "subcategory":"Buildings",
            "type":"Manufacturing & Wholesale Goods"
        },
        {
            "category":"Building & Trades",
            "subcategory":"Construction",
            "type":"Services"
        }
    ],
    "sg:phone":"+1 410 603 9982",
    "sg:postcode":"21804",
    "sg:province":"MD",
    "sg:tags":[
        "home",
        "builder",
        "contractor"
    ],
    "sg:website":"http://www.davidndean.com",
    "wof:name":"Great Improvements",
    "wof:placetype":"venue"
},
  "geometry": {"coordinates":[-75.586871,38.329318],"type":"Point"}
}