{
  "type": "Feature",
  "properties": {
    "addr:full":"1573 Tilco Dr Frederick MD 21704",
    "addr:housenumber":"1573",
    "addr:postcode":"21704",
    "addr:street":"Tilco Dr",
    "iso:country":"US",
    "sg:address":"1573 Tilco Dr",
    "sg:city":"Frederick",
    "sg:classifiers":[
        {
            "category":"Manufacturing",
            "subcategory":"Printing",
            "type":"Manufacturing & Wholesale Goods"
        }
    ],
    "sg:phone":"+1 301 695 7587",
    "sg:postcode":"21704",
    "sg:province":"MD",
    "sg:tags":[
        "printer"
    ],
    "wof:name":"Printing Plus",
    "wof:placetype":"venue"
},
  "geometry": {"coordinates":[-77.38554000000001,39.397625],"type":"Point"}
}