{
  "type": "Feature",
  "properties": {
    "addr:full":"117 Church St Fruitland MD 21826",
    "addr:housenumber":"117",
    "addr:postcode":"21826",
    "addr:street":"Church St",
    "iso:country":"US",
    "sg:address":"117 Church St",
    "sg:city":"Fruitland",
    "sg:classifiers":[
        {
            "category":"Restaurant",
            "type":"Food & Drink"
        }
    ],
    "sg:phone":"+1 410 860 1614",
    "sg:postcode":"21826",
    "sg:province":"MD",
    "sg:tags":[
        "caterer"
    ],
    "wof:name":"Wanda Jean's Catering Business",
    "wof:placetype":"venue"
},
  "geometry": {"coordinates":[-75.615443,38.319808],"type":"Point"}
}