{
  "type": "Feature",
  "properties": {
    "addr:full":"21200 Martinsburg Rd Dickerson MD 20842",
    "addr:postcode":"21200;20842",
    "addr:street":"Martinsburg Rd",
    "iso:country":"US",
    "sg:address":"21200 Martinsburg Rd",
    "sg:city":"Dickerson",
    "sg:classifiers":[
        {
            "category":"Building & Trades",
            "subcategory":"Construction",
            "type":"Services"
        }
    ],
    "sg:phone":"+1 301 349 4620",
    "sg:postcode":"20842",
    "sg:province":"MD",
    "sg:tags":[
        "general",
        "contractor"
    ],
    "wof:name":"Hardesty Construction",
    "wof:placetype":"venue"
},
  "geometry": {"coordinates":[-77.44148199999999,39.204906],"type":"Point"}
}