{
  "type": "Feature",
  "properties": {
    "addr:full":"9031 Bethel Rd Frederick MD 21702",
    "addr:housenumber":"9031",
    "addr:postcode":"21702",
    "addr:street":"Bethel Rd",
    "iso:country":"US",
    "sg:address":"9031 Bethel Rd",
    "sg:city":"Frederick",
    "sg:classifiers":[
        {
            "category":"Wholesale",
            "subcategory":"Hardware",
            "type":"Manufacturing & Wholesale Goods"
        }
    ],
    "sg:phone":"+1 301 663 0099",
    "sg:postcode":"21702",
    "sg:province":"MD",
    "sg:tags":[
        "plumbing",
        "water",
        "well",
        "drilling",
        "bu"
    ],
    "wof:name":"Keyser AR Pump & Drill Co",
    "wof:placetype":"venue"
},
  "geometry": {"coordinates":[-77.459534,39.480231],"type":"Point"}
}