{
  "type": "Feature",
  "properties": {
    "addr:full":"Calverton Shpg Ctr Beltsville MD 20705",
    "addr:postcode":"20705",
    "iso:country":"US",
    "sg:address":"Calverton Shpg Ctr",
    "sg:city":"Beltsville",
    "sg:classifiers":[
        {
            "category":"Shopping",
            "subcategory":"Florist",
            "type":"Retail Goods"
        },
        {
            "category":"Bakery",
            "type":"Food & Drink"
        },
        {
            "category":"Shopping",
            "subcategory":"Pharmacy",
            "type":"Retail Goods"
        },
        {
            "category":"Food & Beverages",
            "subcategory":"Groceries & Convenience Stores",
            "type":"Retail Goods"
        }
    ],
    "sg:phone":"+1 301 572 4657",
    "sg:postcode":"20705",
    "sg:province":"MD",
    "sg:tags":[
        "drugstore"
    ],
    "wof:name":"Giant Food Inc",
    "wof:placetype":"venue"
},
  "geometry": {"coordinates":[-76.917801,39.048302],"type":"Point"}
}