{
  "type": "Feature",
  "properties": {
    "addr:full":"217 Bishops Glen Dr Frederick MD 21702",
    "addr:housenumber":"217",
    "addr:postcode":"21702",
    "addr:street":"Bishops Glen Dr",
    "iso:country":"US",
    "sg:address":"217 Bishops Glen Dr",
    "sg:city":"Frederick",
    "sg:classifiers":[
        {
            "category":"Professional",
            "subcategory":"Business Services",
            "type":"Services"
        }
    ],
    "sg:phone":"+1 301 696 2084",
    "sg:postcode":"21702",
    "sg:province":"MD",
    "wof:name":"Blu Enterprises Inc",
    "wof:placetype":"venue"
},
  "geometry": {"coordinates":[-77.45345399999999,39.42599],"type":"Point"}
}