{
  "type": "Feature",
  "properties": {
    "addr:full":"7839 Eastern Ave Baltimore MD 21224",
    "addr:housenumber":"7839",
    "addr:postcode":"21224",
    "addr:street":"Eastern Ave",
    "iso:country":"US",
    "sg:address":"7839 Eastern Ave",
    "sg:city":"Baltimore",
    "sg:classifiers":[
        {
            "category":"Shopping",
            "subcategory":"Clothing, Apparel, & Fashions",
            "type":"Retail Goods"
        }
    ],
    "sg:phone":"+1 410 282 9002",
    "sg:postcode":"21224",
    "sg:province":"MD",
    "sg:tags":[
        "accessory",
        "clothing",
        "women's"
    ],
    "wof:name":"Honeycomb Hide-Out",
    "wof:placetype":"venue"
},
  "geometry": {"coordinates":[-76.510701,39.295005],"type":"Point"}
}