{
  "type": "Feature",
  "properties": {
    "addr:full":"9105 All Saints Rd # E Laurel MD 20723",
    "addr:housenumber":"9105",
    "addr:postcode":"20723",
    "addr:street":"All Saints Rd # E",
    "iso:country":"US",
    "sg:address":"9105 All Saints Rd # E",
    "sg:city":"Laurel",
    "sg:classifiers":[
        {
            "category":"Personal",
            "subcategory":"Nail Salon",
            "type":"Services"
        }
    ],
    "sg:phone":"+1 301 497 5744",
    "sg:postcode":"20723",
    "sg:province":"MD",
    "wof:name":"Nails Vision Spa",
    "wof:placetype":"venue"
},
  "geometry": {"coordinates":[-76.84277899999999,39.124496],"type":"Point"}
}