{
  "type": "Feature",
  "properties": {
    "addr:full":"27137 Scotland Pkwy Salisbury MD 21801",
    "addr:postcode":"27137;21801",
    "addr:street":"Pkwy",
    "iso:country":"US",
    "sg:address":"27137 Scotland Pkwy",
    "sg:city":"Salisbury",
    "sg:classifiers":[
        {
            "category":"Wholesale",
            "subcategory":"Groceries",
            "type":"Manufacturing & Wholesale Goods"
        }
    ],
    "sg:phone":"+1 410 742 9500",
    "sg:postcode":"21801",
    "sg:province":"MD",
    "sg:tags":[
        "product",
        "soybean"
    ],
    "wof:name":"Maryland Soybean Board",
    "wof:placetype":"venue"
},
  "geometry": {"coordinates":[-75.67285,38.346424],"type":"Point"}
}