{
  "type": "Feature",
  "properties": {
    "iso:country":"US",
    "sg:address":"6300 Coastal Hwy",
    "sg:city":"Ocean City",
    "sg:classifiers":[
        {
            "category":"Building & Trades",
            "subcategory":"Plumbing",
            "type":"Services"
        }
    ],
    "sg:phone":"+1 410 289 5335",
    "sg:postcode":"21842",
    "sg:province":"MD",
    "sg:tags":[
        "conditioning",
        "air",
        "system",
        "contractor"
    ],
    "wof:name":"Airmasters Air Conditioning",
    "wof:placetype":"venue"
},
  "geometry": {"coordinates":[-75.06577799999999,38.386603],"type":"Point"}
}