{
  "type": "Feature",
  "properties": {
    "addr:full":"1130 Jersey Rd Salisbury MD 21801",
    "addr:housenumber":"1130",
    "addr:postcode":"21801",
    "addr:street":"Jersey Rd",
    "iso:country":"US",
    "sg:address":"1130 Jersey Rd",
    "sg:city":"Salisbury",
    "sg:classifiers":[
        {
            "category":"Education",
            "subcategory":"School",
            "type":"Public Place"
        }
    ],
    "sg:phone":"+1 410 543 4204",
    "sg:postcode":"21801",
    "sg:province":"MD",
    "wof:name":"Alternative Learning Ctr",
    "wof:placetype":"venue"
},
  "geometry": {"coordinates":[-75.60274099999999,38.381586],"type":"Point"}
}