{
  "type": "Feature",
  "properties": {
    "addr:full":"918 Galesville Rd Galesville MD 20765",
    "addr:housenumber":"918",
    "addr:postcode":"20765",
    "addr:street":"Galesville Rd",
    "iso:country":"US",
    "sg:address":"918 Galesville Rd",
    "sg:city":"Galesville",
    "sg:classifiers":[
        {
            "category":"Organizations",
            "subcategory":"Membership Organization",
            "type":"Services"
        }
    ],
    "sg:phone":"+1 410 867 4242",
    "sg:postcode":"20765",
    "sg:province":"MD",
    "wof:name":"Ruritan National",
    "wof:placetype":"venue"
},
  "geometry": {"coordinates":[-76.54926399999999,38.846515],"type":"Point"}
}