{
  "type": "Feature",
  "properties": {
    "iso:country":"US",
    "sg:address":"196 Mayo Rd",
    "sg:city":"Edgewater",
    "sg:classifiers":[
        {
            "category":"Restaurant",
            "type":"Food & Drink"
        }
    ],
    "sg:menulink":"http://www.allmenus.com/md/edgewater/146839-subway/menu/",
    "sg:phone":"+1 410 956 4795",
    "sg:postcode":"21037",
    "sg:province":"MD",
    "sg:tags":[
        "american",
        "sandwich"
    ],
    "wof:name":"Subway",
    "wof:placetype":"venue"
},
  "geometry": {"coordinates":[-76.55628299999999,38.931276],"type":"Point"}
}