{
  "type": "Feature",
  "properties": {
    "iso:country":"US",
    "sg:address":"8578 Laureldale Dr",
    "sg:city":"Laurel",
    "sg:classifiers":[
        {
            "category":"Shopping",
            "subcategory":"Bicycles & Sporting Goods",
            "type":"Retail Goods"
        }
    ],
    "sg:phone":"+1 301 498 4848",
    "sg:postcode":"20724",
    "sg:province":"MD",
    "wof:name":"USA Team Sports",
    "wof:placetype":"venue"
},
  "geometry": {"coordinates":[-76.821608,39.101226],"type":"Point"}
}