{
  "type": "Feature",
  "properties": {
    "iso:country":"US",
    "sg:address":"4635 Baltimore Ave",
    "sg:city":"Hyattsville",
    "sg:classifiers":[
        {
            "category":"Retail",
            "subcategory":"Auto Repair",
            "type":"Services"
        }
    ],
    "sg:phone":"+1 301 779 1158",
    "sg:postcode":"20781",
    "sg:province":"MD",
    "wof:name":"General Auto Service Inc",
    "wof:placetype":"venue"
},
  "geometry": {"coordinates":[-76.94119999999999,38.9454],"type":"Point"}
}