{
  "type": "Feature",
  "properties": {
    "iso:country":"US",
    "sg:address":"12 E 5th St",
    "sg:city":"Frederick",
    "sg:classifiers":[
        {
            "category":"Building & Trades",
            "subcategory":"Plumbing",
            "type":"Services"
        },
        {
            "category":"Wholesale",
            "subcategory":"Electrical",
            "type":"Manufacturing & Wholesale Goods"
        }
    ],
    "sg:phone":"+1 301 694 8239",
    "sg:postcode":"21701",
    "sg:province":"MD",
    "sg:tags":[
        "industrial",
        "fire",
        "sprinklers-residential",
        "commercial",
        "contractor",
        "equipment",
        "protection",
        "automatic"
    ],
    "sg:website":"http://www.rwwarner.com",
    "wof:name":"Kennedy Fire Protection",
    "wof:placetype":"venue"
},
  "geometry": {"coordinates":[-77.409987,39.420326],"type":"Point"}
}