{
  "type": "Feature",
  "properties": {
    "addr:full":"12435 Mattawoman Dr Waldorf MD 20601",
    "addr:housenumber":"12435",
    "addr:postcode":"20601",
    "addr:street":"Mattawoman Dr",
    "iso:country":"US",
    "sg:address":"12435 Mattawoman Dr",
    "sg:city":"Waldorf",
    "sg:classifiers":[
        {
            "category":"Organizations",
            "subcategory":"Religious Organization",
            "type":"Services"
        }
    ],
    "sg:phone":"+1 301 843 0551",
    "sg:postcode":"20601",
    "sg:province":"MD",
    "sg:tags":[
        "church"
    ],
    "wof:name":"New Community Church Of God",
    "wof:placetype":"venue"
},
  "geometry": {"coordinates":[-76.87982,38.655336],"type":"Point"}
}