{
  "type": "Feature",
  "properties": {
    "iso:country":"US",
    "sg:address":"50 Appeal Ln",
    "sg:city":"Lusby",
    "sg:classifiers":[
        {
            "category":"Real Estate",
            "subcategory":"Real Estate Operator",
            "type":"Services"
        }
    ],
    "sg:phone":"+1 410 535 5040",
    "sg:postcode":"20657",
    "sg:province":"MD",
    "sg:tags":[
        "building",
        "apartment",
        "executive"
    ],
    "wof:name":"Calvery Pines Apartments",
    "wof:placetype":"venue"
},
  "geometry": {"coordinates":[-76.43526199999999,38.37544],"type":"Point"}
}