{
  "type": "Feature",
  "properties": {
    "iso:country":"US",
    "sg:address":"1727 Lynch Rd",
    "sg:city":"Baltimore",
    "sg:classifiers":[
        {
            "category":"Organizations",
            "subcategory":"Religious Organization",
            "type":"Services"
        }
    ],
    "sg:phone":"+1 410 282 3120",
    "sg:postcode":"21222",
    "sg:province":"MD",
    "wof:name":"Our Lady Of Hope Church Rlgs",
    "wof:placetype":"venue"
},
  "geometry": {"coordinates":[-76.494856,39.269504],"type":"Point"}
}