{
  "type": "Feature",
  "properties": {
    "addr:full":"14125 Gallop Ter Germantown MD 20874",
    "addr:housenumber":"14125",
    "addr:postcode":"20874",
    "addr:street":"Gallop Ter",
    "iso:country":"US",
    "sg:address":"14125 Gallop Ter",
    "sg:city":"Germantown",
    "sg:classifiers":[
        {
            "category":"Restaurant",
            "type":"Food & Drink"
        }
    ],
    "sg:phone":"+1 301 353 1838",
    "sg:postcode":"20874",
    "sg:province":"MD",
    "sg:tags":[
        "delivery"
    ],
    "sg:website":"www.dineonline.com",
    "wof:name":"Dine Online",
    "wof:placetype":"venue"
},
  "geometry": {"coordinates":[-77.29092900000001,39.174143],"type":"Point"}
}