{
  "type": "Feature",
  "properties": {
    "iso:country":"US",
    "sg:address":"2323 Eastern Blvd",
    "sg:city":"Baltimore",
    "sg:classifiers":[
        {
            "category":"Education",
            "subcategory":"Library",
            "type":"Public Place"
        }
    ],
    "sg:phone":"+1 410 682 1574",
    "sg:postcode":"21220",
    "sg:province":"MD",
    "wof:name":"Lockheed Martin",
    "wof:placetype":"venue"
},
  "geometry": {"coordinates":[-76.437211,39.331798],"type":"Point"}
}