{
  "type": "Feature",
  "properties": {
    "addr:full":"920 S Conkling St Baltimore MD 21224",
    "addr:housenumber":"920",
    "addr:postcode":"21224",
    "addr:street":"S Conkling St",
    "iso:country":"US",
    "sg:address":"920 S Conkling St",
    "sg:city":"Baltimore",
    "sg:classifiers":[
        {
            "category":"Real Estate",
            "subcategory":"Real Estate Agent",
            "type":"Services"
        }
    ],
    "sg:phone":"+1 410 675 2500",
    "sg:postcode":"21224",
    "sg:province":"MD",
    "sg:tags":[
        "agency"
    ],
    "wof:name":"Inner Harbor Realty Inc",
    "wof:placetype":"venue"
},
  "geometry": {"coordinates":[-76.56692,39.281752],"type":"Point"}
}