{
  "type": "Feature",
  "properties": {
    "iso:country":"US",
    "sg:address":"4420 Walsh St",
    "sg:city":"Chevy Chase",
    "sg:classifiers":[
        {
            "category":"Professional",
            "subcategory":"Lawyer & Legal Services",
            "type":"Services"
        }
    ],
    "sg:phone":"+1 301 652 1625",
    "sg:postcode":"20815",
    "sg:province":"MD",
    "sg:tags":[
        "plan"
    ],
    "wof:name":"Litigation Graphics",
    "wof:placetype":"venue"
},
  "geometry": {"coordinates":[-77.089482,38.979462],"type":"Point"}
}