{
  "type": "Feature",
  "properties": {
    "addr:full":"9832 Hastings Ln Ocean City MD 21842",
    "addr:housenumber":"9832",
    "addr:postcode":"21842",
    "addr:street":"Hastings Ln",
    "iso:country":"US",
    "sg:address":"9832 Hastings Ln",
    "sg:city":"Ocean City",
    "sg:classifiers":[
        {
            "category":"Farming",
            "subcategory":"Livestock Farm",
            "type":"Manufacturing & Wholesale Goods"
        }
    ],
    "sg:phone":"+1 410 213 2811",
    "sg:postcode":"21842",
    "sg:province":"MD",
    "sg:tags":[
        "specialty",
        "animal"
    ],
    "wof:name":"Cheep Housing",
    "wof:placetype":"venue"
},
  "geometry": {"coordinates":[-75.120283,38.334446],"type":"Point"}
}