{
  "type": "Feature",
  "properties": {
    "addr:full":"10 Light St Baltimore MD 21202",
    "addr:housenumber":"10",
    "addr:postcode":"21202",
    "addr:street":"Light St",
    "iso:country":"US",
    "sg:address":"10 Light St",
    "sg:city":"Baltimore",
    "sg:classifiers":[
        {
            "category":"Professional",
            "subcategory":"Lawyer & Legal Services",
            "type":"Services"
        }
    ],
    "sg:phone":"+1 410 385 3432",
    "sg:postcode":"21202",
    "sg:province":"MD",
    "sg:tags":[
        "plan"
    ],
    "wof:name":"Hill Katherine",
    "wof:placetype":"venue"
},
  "geometry": {"coordinates":[-76.613865,39.288979],"type":"Point"}
}