{
  "type": "Feature",
  "properties": {
    "addr:full":"25946 Timothy Ct Mechanicsville MD 20659",
    "addr:housenumber":"25946",
    "addr:postcode":"20659",
    "addr:street":"Timothy Ct",
    "iso:country":"US",
    "sg:address":"25946 Timothy Ct",
    "sg:city":"Mechanicsville",
    "sg:classifiers":[
        {
            "category":"Building & Trades",
            "subcategory":"Landscaping Services",
            "type":"Services"
        }
    ],
    "sg:phone":"+1 301 884 4039",
    "sg:postcode":"20659",
    "sg:province":"MD",
    "sg:tags":[
        "lawn",
        "maintenance",
        "grounds"
    ],
    "wof:name":"Bud's Service",
    "wof:placetype":"venue"
},
  "geometry": {"coordinates":[-76.743585,38.374569],"type":"Point"}
}