{
  "type": "Feature",
  "properties": {
    "addr:full":"10502 Pookey Way Upper Marlboro MD 20774",
    "addr:housenumber":"10502",
    "addr:postcode":"20774",
    "addr:street":"Pookey Way",
    "iso:country":"US",
    "sg:address":"10502 Pookey Way",
    "sg:city":"Upper Marlboro",
    "sg:classifiers":[
        {
            "category":"Freight",
            "type":"Transportation"
        }
    ],
    "sg:phone":"+1 301 333 5211",
    "sg:postcode":"20774",
    "sg:province":"MD",
    "sg:tags":[
        "trucking"
    ],
    "wof:name":"MDR Trucking",
    "wof:placetype":"venue"
},
  "geometry": {"coordinates":[-76.825829,38.871744],"type":"Point"}
}