{
  "type": "Feature",
  "properties": {
    "iso:country":"US",
    "sg:address":"16331 Shady Grove Rd",
    "sg:city":"Gaithersburg",
    "sg:classifiers":[
        {
            "category":"Professional",
            "subcategory":"Business Services",
            "type":"Services"
        }
    ],
    "sg:phone":"+1 301 947 8806",
    "sg:postcode":"20877",
    "sg:province":"MD",
    "wof:name":"Gramophone",
    "wof:placetype":"venue"
},
  "geometry": {"coordinates":[-77.171095,39.12782],"type":"Point"}
}