{
  "type": "Feature",
  "properties": {
    "iso:country":"US",
    "sg:address":"1031 Maryland Ave",
    "sg:city":"Hagerstown",
    "sg:classifiers":[
        {
            "category":"Personal",
            "subcategory":"Barber",
            "type":"Services"
        }
    ],
    "sg:phone":"+1 301 739 9457",
    "sg:postcode":"21740",
    "sg:province":"MD",
    "wof:name":"South End Barber Shop",
    "wof:placetype":"venue"
},
  "geometry": {"coordinates":[-77.732742,39.623336],"type":"Point"}
}