{
  "type": "Feature",
  "properties": {
    "iso:country":"US",
    "sg:address":"2980 Festival Way",
    "sg:city":"Waldorf",
    "sg:classifiers":[
        {
            "category":"Cinema",
            "subcategory":"Movie Rental",
            "type":"Entertainment"
        }
    ],
    "sg:phone":"+1 301 705 9900",
    "sg:postcode":"20601",
    "sg:province":"MD",
    "sg:tags":[
        "leasing",
        "video",
        "disc",
        "tape"
    ],
    "wof:name":"Blockbuster Video",
    "wof:placetype":"venue"
},
  "geometry": {"coordinates":[-76.910837,38.627716],"type":"Point"}
}