{
  "type": "Feature",
  "properties": {
    "iso:country":"US",
    "sg:address":"1320 Crain Hwy",
    "sg:city":"Bowie",
    "sg:classifiers":[
        {
            "category":"Communications",
            "type":"Services"
        }
    ],
    "sg:phone":"+1 301 249 0969",
    "sg:postcode":"20716",
    "sg:province":"MD",
    "wof:name":"AXS Communications LLC",
    "wof:placetype":"venue"
},
  "geometry": {"coordinates":[-76.718479,38.907125],"type":"Point"}
}