{
  "type": "Feature",
  "properties": {
    "iso:country":"US",
    "sg:address":"1151 Martin Dr",
    "sg:city":"Westminster",
    "sg:classifiers":[
        {
            "category":"Building & Trades",
            "subcategory":"Construction",
            "type":"Services"
        }
    ],
    "sg:phone":"+1 410 751 7700",
    "sg:postcode":"21157",
    "sg:province":"MD",
    "sg:tags":[
        "home",
        "improvement"
    ],
    "wof:name":"RAR Construction",
    "wof:placetype":"venue"
},
  "geometry": {"coordinates":[-76.95189999999999,39.600032],"type":"Point"}
}