{
  "type": "Feature",
  "properties": {
    "addr:full":"20 Pebble Dr Brooklyn MD 21225",
    "addr:housenumber":"20",
    "addr:postcode":"21225",
    "addr:street":"Pebble Dr",
    "iso:country":"US",
    "sg:address":"20 Pebble Dr",
    "sg:city":"Brooklyn",
    "sg:classifiers":[
        {
            "category":"Real Estate",
            "subcategory":"Real Estate Operator",
            "type":"Services"
        },
        {
            "category":"Home & Garden",
            "subcategory":"Mobile Homes",
            "type":"Retail Goods"
        }
    ],
    "sg:phone":"+1 410 789 2822",
    "sg:postcode":"21225",
    "sg:province":"MD",
    "sg:tags":[
        "manufactured",
        "housing-communities",
        "site"
    ],
    "wof:name":"Frank & Bill's Trailer Park",
    "wof:placetype":"venue"
},
  "geometry": {"coordinates":[-76.631027,39.219742],"type":"Point"}
}