{
  "type": "Feature",
  "properties": {
    "iso:country":"US",
    "sg:address":"3412 Toledo Ter Unit D",
    "sg:city":"Hyattsville",
    "sg:classifiers":[
        {
            "category":"Shopping",
            "subcategory":"Beauty & Cosmetics",
            "type":"Retail Goods"
        },
        {
            "category":"Personal",
            "subcategory":"Skin Care",
            "type":"Services"
        }
    ],
    "sg:phone":"+1 301 559 8225",
    "sg:postcode":"20782",
    "sg:province":"MD",
    "sg:tags":[
        "perfume"
    ],
    "sg:website":"http://shop.avon.com/shop/default.aspx?newdept=&s=AV_GGL_BR&c=iProspect&otc=avon&bnd=&ym_mid=&ym_rid=",
    "wof:name":"Mrs. Cook an Avon Independent Sales Rep.",
    "wof:placetype":"venue"
},
  "geometry": {"coordinates":[-76.95871,38.971088],"type":"Point"}
}