{
  "type": "Feature",
  "properties": {
    "iso:country":"US",
    "sg:address":"5932 Cheshire Dr",
    "sg:city":"Bethesda",
    "sg:classifiers":[
        {
            "category":"Professional",
            "subcategory":"Business Services",
            "type":"Services"
        }
    ],
    "sg:phone":"+1 301 530 0939",
    "sg:postcode":"20814",
    "sg:province":"MD",
    "sg:tags":[
        "translation"
    ],
    "wof:name":"Ruth A Healey",
    "wof:placetype":"venue"
},
  "geometry": {"coordinates":[-77.118852,39.025212],"type":"Point"}
}