{
  "type": "Feature",
  "properties": {
    "addr:full":"211 W Bel Air Ave Aberdeen MD 21001",
    "addr:housenumber":"211",
    "addr:postcode":"21001",
    "addr:street":"W Bel Air Ave",
    "iso:country":"US",
    "sg:address":"211 W Bel Air Ave",
    "sg:city":"Aberdeen",
    "sg:classifiers":[
        {
            "category":"Retail",
            "subcategory":"Repair Shop",
            "type":"Services"
        }
    ],
    "sg:phone":"+1 410 272 4999",
    "sg:postcode":"21001",
    "sg:province":"MD",
    "sg:tags":[
        "lock",
        "locksmith"
    ],
    "wof:name":"Anderson Lock & Key",
    "wof:placetype":"venue"
},
  "geometry": {"coordinates":[-76.167342,39.510736],"type":"Point"}
}