{
  "type": "Feature",
  "properties": {
    "addr:full":"143 Lakin Ave Boonsboro MD 21713",
    "addr:housenumber":"143",
    "addr:postcode":"21713",
    "addr:street":"Lakin Ave",
    "iso:country":"US",
    "sg:address":"143 Lakin Ave",
    "sg:city":"Boonsboro",
    "sg:classifiers":[
        {
            "category":"Autos & Motor Vehicles",
            "subcategory":"Automobile Sales",
            "type":"Retail Goods"
        }
    ],
    "sg:phone":"+1 301 791 5700",
    "sg:postcode":"21713",
    "sg:province":"MD",
    "sg:tags":[
        "used"
    ],
    "wof:name":"Franks Used Cars Inc",
    "wof:placetype":"venue"
},
  "geometry": {"coordinates":[-77.649659,39.508637],"type":"Point"}
}