{
  "type": "Feature",
  "properties": {
    "addr:full":"3212 Weeping Willow Ct Silver Spring MD 20906",
    "addr:housenumber":"3212",
    "addr:postcode":"20906",
    "addr:street":"Weeping Willow Ct",
    "iso:country":"US",
    "sg:address":"3212 Weeping Willow Ct",
    "sg:city":"Silver Spring",
    "sg:classifiers":[
        {
            "category":"Social Services",
            "type":"Services"
        }
    ],
    "sg:phone":"+1 301 871 9700",
    "sg:postcode":"20906",
    "sg:province":"MD",
    "sg:tags":[
        "organization",
        "welfare"
    ],
    "wof:name":"National Center For Children",
    "wof:placetype":"venue"
},
  "geometry": {"coordinates":[-77.06684799999999,39.089094],"type":"Point"}
}