{
  "type": "Feature",
  "properties": {
    "iso:country":"US",
    "sg:address":"8301 Dangerfield Pl",
    "sg:city":"Clinton",
    "sg:classifiers":[
        {
            "category":"Building & Trades",
            "subcategory":"Construction",
            "type":"Services"
        }
    ],
    "sg:phone":"+1 301 877 1477",
    "sg:postcode":"20735",
    "sg:province":"MD",
    "sg:tags":[
        "contractor"
    ],
    "wof:name":"Tribecka Contracting",
    "wof:placetype":"venue"
},
  "geometry": {"coordinates":[-76.86389200000001,38.767615],"type":"Point"}
}