{
  "type": "Feature",
  "properties": {
    "iso:country":"US",
    "sg:address":"1614 N Calvert St Apt 2",
    "sg:city":"Baltimore",
    "sg:classifiers":[
        {
            "category":"Retail",
            "subcategory":"Laundry & Dry Cleaning",
            "type":"Services"
        },
        {
            "category":"Building & Trades",
            "subcategory":"Cleaning & Sanitation",
            "type":"Services"
        }
    ],
    "sg:phone":"+1 410 727 5675",
    "sg:postcode":"21202",
    "sg:province":"MD",
    "sg:tags":[
        "house",
        "cleaner"
    ],
    "wof:name":"Er Cleaning Service",
    "wof:placetype":"venue"
},
  "geometry": {"coordinates":[-76.613567,39.307836],"type":"Point"}
}