{
  "type": "Feature",
  "properties": {
    "addr:full":"940 Red Toad Rd North East MD 21901",
    "addr:housenumber":"940",
    "addr:postcode":"21901",
    "addr:street":"Red Toad Rd",
    "iso:country":"US",
    "sg:address":"940 Red Toad Rd",
    "sg:city":"North East",
    "sg:classifiers":[
        {
            "category":"Wholesale",
            "subcategory":"Machinery & Supplies",
            "type":"Manufacturing & Wholesale Goods"
        }
    ],
    "sg:phone":"+1 410 287 5917",
    "sg:postcode":"21901",
    "sg:province":"MD",
    "sg:tags":[
        "repairing"
    ],
    "wof:name":"Tecasa USA Inc",
    "wof:placetype":"venue"
},
  "geometry": {"coordinates":[-76.020645,39.630355],"type":"Point"}
}