{
  "type": "Feature",
  "properties": {
    "addr:full":"6500 Riggs Rd Hyattsville MD 20783",
    "addr:housenumber":"6500",
    "addr:postcode":"20783",
    "addr:street":"Riggs Rd",
    "iso:country":"US",
    "sg:address":"6500 Riggs Rd",
    "sg:city":"Hyattsville",
    "sg:classifiers":[
        {
            "category":"Retail",
            "subcategory":"Portrait Studio",
            "type":"Services"
        },
        {
            "category":"Professional",
            "subcategory":"Art Services",
            "type":"Services"
        }
    ],
    "sg:phone":"+1 301 559 0077",
    "sg:postcode":"20783",
    "sg:province":"MD",
    "sg:tags":[
        "rental",
        "photographers-portrait",
        "photographic",
        "darkroom"
    ],
    "wof:name":"Hollywood Shot Inc",
    "wof:placetype":"venue"
},
  "geometry": {"coordinates":[-76.984533,38.969475],"type":"Point"}
}