{
  "type": "Feature",
  "properties": {
    "addr:full":"14842 Baltimore Ave Laurel MD 20707",
    "addr:housenumber":"14842",
    "addr:postcode":"20707",
    "addr:street":"Baltimore Ave",
    "iso:country":"US",
    "sg:address":"14842 Baltimore Ave",
    "sg:city":"Laurel",
    "sg:classifiers":[
        {
            "category":"Food & Beverages",
            "subcategory":"Groceries & Convenience Stores",
            "type":"Retail Goods"
        }
    ],
    "sg:phone":"+1 301 362 0606",
    "sg:postcode":"20707",
    "sg:province":"MD",
    "sg:tags":[
        "grocer"
    ],
    "wof:name":"Laurel Market Place",
    "wof:placetype":"venue"
},
  "geometry": {"coordinates":[-76.855039,39.093644],"type":"Point"}
}