{
  "type": "Feature",
  "properties": {
    "iso:country":"US",
    "sg:address":"4225 N Woods Trl",
    "sg:city":"Hampstead",
    "sg:classifiers":[
        {
            "category":"Restaurant",
            "type":"Food & Drink"
        }
    ],
    "sg:menulink":"http://www.allmenus.com/md/hampstead/215716-mcdonalds/menu/",
    "sg:postcode":"21074",
    "sg:province":"MD",
    "sg:tags":[
        "burger",
        "american"
    ],
    "wof:name":"McDonald's",
    "wof:placetype":"venue"
},
  "geometry": {"coordinates":[-76.84566700000001,39.596022],"type":"Point"}
}