{
  "type": "Feature",
  "properties": {
    "iso:country":"US",
    "sg:address":"3 Bethesda Metro Ctr",
    "sg:city":"Bethesda",
    "sg:classifiers":[
        {
            "category":"Professional",
            "subcategory":"Lawyer & Legal Services",
            "type":"Services"
        }
    ],
    "sg:phone":"+1 301 961 5770",
    "sg:postcode":"20814",
    "sg:province":"MD",
    "wof:name":"Wolpert Ira C Atty",
    "wof:placetype":"venue"
},
  "geometry": {"coordinates":[-77.096298,38.983398],"type":"Point"}
}