{
  "type": "Feature",
  "properties": {
    "iso:country":"US",
    "sg:address":"908 Orchard Way",
    "sg:city":"Silver Spring",
    "sg:classifiers":[
        {
            "category":"Retail",
            "subcategory":"Portrait Studio",
            "type":"Services"
        },
        {
            "category":"Professional",
            "subcategory":"Art Services",
            "type":"Services"
        }
    ],
    "sg:phone":"+1 301 879 8950",
    "sg:postcode":"20904",
    "sg:province":"MD",
    "sg:tags":[
        "photographer",
        "photography",
        "store"
    ],
    "wof:name":"Randolph Photography",
    "wof:placetype":"venue"
},
  "geometry": {"coordinates":[-76.992699,39.082901],"type":"Point"}
}