{
  "type": "Feature",
  "properties": {
    "addr:full":"401 Main St Laurel MD 20707",
    "addr:housenumber":"401",
    "addr:postcode":"20707",
    "addr:street":"Main St",
    "iso:country":"US",
    "sg:address":"401 Main St",
    "sg:city":"Laurel",
    "sg:classifiers":[
        {
            "category":"Retail",
            "subcategory":"Portrait Studio",
            "type":"Services"
        }
    ],
    "sg:phone":"+1 301 498 1466",
    "sg:postcode":"20707",
    "sg:province":"MD",
    "sg:tags":[
        "photographer"
    ],
    "wof:name":"Photography & Photographic Svc",
    "wof:placetype":"venue"
},
  "geometry": {"coordinates":[-76.84791199999999,39.105936],"type":"Point"}
}