{
  "type": "Feature",
  "properties": {
    "iso:country":"US",
    "sg:address":"240 N Howard St",
    "sg:city":"Baltimore",
    "sg:classifiers":[
        {
            "category":"Restaurant",
            "type":"Food & Drink"
        }
    ],
    "sg:phone":"+1 410 385 9999",
    "sg:postcode":"21201",
    "sg:province":"MD",
    "wof:name":"Studio Z 54",
    "wof:placetype":"venue"
},
  "geometry": {"coordinates":[-76.619783,39.292724],"type":"Point"}
}