{
  "type": "Feature",
  "properties": {
    "iso:country":"US",
    "sg:address":"4 Clarke Pl",
    "sg:city":"Frederick",
    "sg:classifiers":[
        {
            "category":"Travel",
            "subcategory":"Hotels & Motels",
            "type":"Entertainment"
        }
    ],
    "sg:phone":"+1 301 228 3630",
    "sg:postcode":"21701",
    "sg:province":"MD",
    "sg:tags":[
        "operation"
    ],
    "wof:name":"Hollerstown Hl Bed & Breakfast",
    "wof:placetype":"venue"
},
  "geometry": {"coordinates":[-77.410229,39.407775],"type":"Point"}
}