{
  "type": "Feature",
  "properties": {
    "iso:country":"US",
    "sg:address":"4434 Falls Rd",
    "sg:city":"Baltimore",
    "sg:classifiers":[
        {
            "category":"Autos & Motor Vehicles",
            "subcategory":"Fuel & Gas Station",
            "type":"Retail Goods"
        }
    ],
    "sg:phone":"+1 410 366 6828",
    "sg:postcode":"21211",
    "sg:province":"MD",
    "sg:website":"http://www.exxon.com",
    "wof:name":"Cross Keys Exxon",
    "wof:placetype":"venue"
},
  "geometry": {"coordinates":[-76.640533,39.34294],"type":"Point"}
}