{
  "type": "Feature",
  "properties": {
    "iso:country":"US",
    "sg:address":"479 Elk Mills Rd",
    "sg:city":"Elkton",
    "sg:classifiers":[
        {
            "category":"Building & Trades",
            "subcategory":"Electrical",
            "type":"Services"
        }
    ],
    "sg:phone":"+1 410 398 6595",
    "sg:postcode":"21921",
    "sg:province":"MD",
    "sg:tags":[
        "electric",
        "contractor"
    ],
    "wof:name":"Mr Electric",
    "wof:placetype":"venue"
},
  "geometry": {"coordinates":[-75.832798,39.662694],"type":"Point"}
}