{
  "type": "Feature",
  "properties": {
    "addr:full":"8000 Cherry Ln Laurel MD 20707",
    "addr:housenumber":"8000",
    "addr:postcode":"20707",
    "addr:street":"Cherry Ln",
    "iso:country":"US",
    "sg:address":"8000 Cherry Ln",
    "sg:city":"Laurel",
    "sg:classifiers":[
        {
            "category":"Education",
            "subcategory":"School",
            "type":"Public Place"
        }
    ],
    "sg:phone":"+1 301 497 2050",
    "sg:postcode":"20707",
    "sg:province":"MD",
    "sg:tags":[
        "high",
        "middle",
        "elementary"
    ],
    "wof:name":"Prince George's County Public Schools",
    "wof:placetype":"venue"
},
  "geometry": {"coordinates":[-76.868301,39.093399],"type":"Point"}
}