{
  "type": "Feature",
  "properties": {
    "addr:full":"14102 London Ln Rockville MD 20853",
    "addr:housenumber":"14102",
    "addr:postcode":"20853",
    "addr:street":"London Ln",
    "iso:country":"US",
    "sg:address":"14102 London Ln",
    "sg:city":"Rockville",
    "sg:classifiers":[
        {
            "category":"Building & Trades",
            "subcategory":"Construction",
            "type":"Services"
        }
    ],
    "sg:phone":"+1 301 460 6697",
    "sg:postcode":"20853",
    "sg:province":"MD",
    "sg:tags":[
        "painter"
    ],
    "wof:name":"Manhattan Brother Painting",
    "wof:placetype":"venue"
},
  "geometry": {"coordinates":[-77.08070499999999,39.088177],"type":"Point"}
}