{
  "type": "Feature",
  "properties": {
    "iso:country":"US",
    "sg:address":"1318 E 36th St",
    "sg:city":"Baltimore",
    "sg:classifiers":[
        {
            "category":"Travel",
            "subcategory":"Travel Agent",
            "type":"Entertainment"
        }
    ],
    "sg:phone":"+1 410 235 0110",
    "sg:postcode":"21218",
    "sg:province":"MD",
    "sg:tags":[
        "agency",
        "services-commercial"
    ],
    "wof:name":"Mtm Travel",
    "wof:placetype":"venue"
},
  "geometry": {"coordinates":[-76.59764800000001,39.33168],"type":"Point"}
}