{
  "type": "Feature",
  "properties": {
    "iso:country":"US",
    "sg:address":"5914 Somerset Rd",
    "sg:city":"Riverdale",
    "sg:classifiers":[
        {
            "category":"Professional",
            "subcategory":"Employment Agencies",
            "type":"Services"
        }
    ],
    "sg:phone":"+1 301 779 2752",
    "sg:postcode":"20737",
    "sg:province":"MD",
    "wof:name":"Horizon Placement Agency LLC",
    "wof:placetype":"venue"
},
  "geometry": {"coordinates":[-76.913905,38.966016],"type":"Point"}
}