{
  "type": "Feature",
  "properties": {
    "iso:country":"US",
    "sg:address":"1832 W North Ave",
    "sg:city":"Baltimore",
    "sg:classifiers":[
        {
            "category":"Personal",
            "subcategory":"Beauty Salon",
            "type":"Services"
        }
    ],
    "sg:phone":"+1 410 669 2597",
    "sg:postcode":"21217",
    "sg:province":"MD",
    "wof:name":"A Classic Touch",
    "wof:placetype":"venue"
},
  "geometry": {"coordinates":[-76.648115,39.309892],"type":"Point"}
}