{
  "type": "Feature",
  "properties": {
    "iso:country":"US",
    "sg:address":"1301 Loflin Rd",
    "sg:city":"Aberdeen",
    "sg:classifiers":[
        {
            "category":"Real Estate",
            "subcategory":"Real Estate Agent",
            "type":"Services"
        }
    ],
    "sg:phone":"+1 410 272 8899",
    "sg:postcode":"21001",
    "sg:province":"MD",
    "sg:tags":[
        "relocation"
    ],
    "wof:name":"Chesapeake Relocation Svc",
    "wof:placetype":"venue"
},
  "geometry": {"coordinates":[-76.20362900000001,39.488151],"type":"Point"}
}