{
  "type": "Feature",
  "properties": {
    "addr:full":"1074 Taft St Rockville MD 20850",
    "addr:housenumber":"1074",
    "addr:postcode":"20850",
    "addr:street":"Taft St",
    "iso:country":"US",
    "sg:address":"1074 Taft St",
    "sg:city":"Rockville",
    "sg:classifiers":[
        {
            "category":"Retail",
            "subcategory":"Auto Repair",
            "type":"Services"
        }
    ],
    "sg:phone":"+1 301 340 0393",
    "sg:postcode":"20850",
    "sg:province":"MD",
    "sg:tags":[
        "body",
        "automobile",
        "painting"
    ],
    "wof:name":"In & Out Auto Body",
    "wof:placetype":"venue"
},
  "geometry": {"coordinates":[-77.13705899999999,39.093971],"type":"Point"}
}