{
  "type": "Feature",
  "properties": {
    "iso:country":"US",
    "sg:address":"2 E Baltimore St",
    "sg:city":"Hagerstown",
    "sg:classifiers":[
        {
            "category":"Professional",
            "subcategory":"Business Services",
            "type":"Services"
        }
    ],
    "sg:phone":"+1 301 791 0807",
    "sg:postcode":"21740",
    "sg:province":"MD",
    "sg:tags":[
        "interior",
        "consultant",
        "design",
        "decorator"
    ],
    "wof:name":"Interiors Of Maryland LLC",
    "wof:placetype":"venue"
},
  "geometry": {"coordinates":[-77.721628,39.638801],"type":"Point"}
}