{
  "type": "Feature",
  "properties": {
    "iso:country":"US",
    "sg:address":"8500 Connecticut Ave",
    "sg:city":"Chevy Chase",
    "sg:classifiers":[
        {
            "category":"Autos & Motor Vehicles",
            "subcategory":"Fuel & Gas Station",
            "type":"Retail Goods"
        }
    ],
    "sg:phone":"+1 301 656 4526",
    "sg:postcode":"20815",
    "sg:province":"MD",
    "sg:website":"www.armanschevychasesunoco.com",
    "wof:name":"Armans Chevy Chase Service Center",
    "wof:placetype":"venue"
},
  "geometry": {"coordinates":[-77.07710299999999,38.994301],"type":"Point"}
}