{
  "type": "Feature",
  "properties": {
    "addr:full":"4510 Harling Ln Bethesda MD 20814",
    "addr:housenumber":"4510",
    "addr:postcode":"20814",
    "addr:street":"Harling Ln",
    "iso:country":"US",
    "sg:address":"4510 Harling Ln",
    "sg:city":"Bethesda",
    "sg:classifiers":[
        {
            "category":"Shopping",
            "type":"Retail Goods"
        }
    ],
    "sg:phone":"+1 301 986 5144",
    "sg:postcode":"20814",
    "sg:province":"MD",
    "sg:tags":[
        "merchandise"
    ],
    "wof:name":"World Spice Shoppe",
    "wof:placetype":"venue"
},
  "geometry": {"coordinates":[-77.09157999999999,38.989176],"type":"Point"}
}