{
  "type": "Feature",
  "properties": {
    "addr:full":"8978 Glebe Park Dr Easton MD 21601",
    "addr:housenumber":"8978",
    "addr:postcode":"21601",
    "addr:street":"Glebe Park Dr",
    "iso:country":"US",
    "sg:address":"8978 Glebe Park Dr",
    "sg:city":"Easton",
    "sg:classifiers":[
        {
            "category":"Manufacturing",
            "subcategory":"Food",
            "type":"Manufacturing & Wholesale Goods"
        }
    ],
    "sg:phone":"+1 410 820 7848",
    "sg:postcode":"21601",
    "sg:province":"MD",
    "sg:tags":[
        "packer",
        "seafood"
    ],
    "wof:name":"Sea Watch Intl LTD",
    "wof:placetype":"venue"
},
  "geometry": {"coordinates":[-76.070897,38.79283],"type":"Point"}
}