{
  "type": "Feature",
  "properties": {
    "iso:country":"US",
    "sg:address":"3211 Boone Rd",
    "sg:city":"Crisfield",
    "sg:classifiers":[
        {
            "category":"Shopping",
            "subcategory":"Crafts & Fabrics",
            "type":"Retail Goods"
        }
    ],
    "sg:phone":"+1 410 968 2744",
    "sg:postcode":"21817",
    "sg:province":"MD",
    "sg:tags":[
        "sewing"
    ],
    "wof:name":"Stitches N Stuff",
    "wof:placetype":"venue"
},
  "geometry": {"coordinates":[-75.83290599999999,37.97026],"type":"Point"}
}