{
  "type": "Feature",
  "properties": {
    "addr:full":"9200 Piney Branch Rd Silver Spring MD 20903",
    "addr:housenumber":"9200",
    "addr:postcode":"20903",
    "addr:street":"Piney Branch Rd",
    "iso:country":"US",
    "sg:address":"9200 Piney Branch Rd",
    "sg:city":"Silver Spring",
    "sg:classifiers":[
        {
            "category":"Shopping",
            "subcategory":"Gifts & Souvenirs",
            "type":"Retail Goods"
        }
    ],
    "sg:phone":"+1 301 434 0647",
    "sg:postcode":"20903",
    "sg:province":"MD",
    "wof:name":"Haqndyman Service",
    "wof:placetype":"venue"
},
  "geometry": {"coordinates":[-76.987301,39.001422],"type":"Point"}
}