{
  "type": "Feature",
  "properties": {
    "addr:full":"43990 Commerce Ave Hollywood MD 20636",
    "addr:housenumber":"43990",
    "addr:postcode":"20636",
    "addr:street":"Commerce Ave",
    "iso:country":"US",
    "sg:address":"43990 Commerce Ave",
    "sg:city":"Hollywood",
    "sg:classifiers":[
        {
            "category":"Government",
            "subcategory":"Office",
            "type":"Public Place"
        }
    ],
    "sg:phone":"+1 301 373 4733",
    "sg:postcode":"20636",
    "sg:province":"MD",
    "wof:name":"St Marys County Sewer Svc",
    "wof:placetype":"venue"
},
  "geometry": {"coordinates":[-76.557022,38.320684],"type":"Point"}
}