{
  "type": "Feature",
  "properties": {
    "iso:country":"US",
    "sg:address":"111 Embleton Rd",
    "sg:city":"Owings Mills",
    "sg:classifiers":[
        {
            "category":"Education",
            "subcategory":"Vocational School",
            "type":"Public Place"
        }
    ],
    "sg:phone":"+1 410 356 1048",
    "sg:postcode":"21117",
    "sg:province":"MD",
    "sg:tags":[
        "training",
        "en",
        "agency",
        "to",
        "teaching",
        "security",
        "law",
        "specialized"
    ],
    "wof:name":"Powells Detective Agency",
    "wof:placetype":"venue"
},
  "geometry": {"coordinates":[-76.797791,39.442924],"type":"Point"}
}