{
  "type": "Feature",
  "properties": {
    "iso:country":"US",
    "sg:address":"215 Parker Rd",
    "sg:city":"Salisbury",
    "sg:classifiers":[
        {
            "category":"Organizations",
            "subcategory":"Religious Organization",
            "type":"Services"
        }
    ],
    "sg:phone":"+1 410 749 1060",
    "sg:postcode":"21804",
    "sg:province":"MD",
    "sg:tags":[
        "church"
    ],
    "wof:name":"Jehovah's Witnesses",
    "wof:placetype":"venue"
},
  "geometry": {"coordinates":[-75.55439,38.377057],"type":"Point"}
}