{
  "type": "Feature",
  "properties": {
    "addr:full":"7423 Greenbelt Rd Greenbelt MD 20770",
    "addr:housenumber":"7423",
    "addr:postcode":"20770",
    "addr:street":"Greenbelt Rd",
    "iso:country":"US",
    "sg:address":"7423 Greenbelt Rd",
    "sg:city":"Greenbelt",
    "sg:classifiers":[
        {
            "category":"Bakery",
            "type":"Food & Drink"
        },
        {
            "category":"Bagels",
            "type":"Food & Drink"
        }
    ],
    "sg:menulink":"http://www.allmenus.com/md/berwyn/219051-chesapeake-bagel-bakery/menu/",
    "sg:phone":"+1 301 474 1114",
    "sg:postcode":"20770",
    "sg:province":"MD",
    "sg:tags":[
        "american",
        "pastry"
    ],
    "wof:name":"Chesapeake Bagel Bakery",
    "wof:placetype":"venue"
},
  "geometry": {"coordinates":[-76.876797,38.993996],"type":"Point"}
}