{
  "type": "Feature",
  "properties": {
    "iso:country":"US",
    "sg:address":"225 King James Rd",
    "sg:city":"Upper Marlboro",
    "sg:classifiers":[
        {
            "category":"Real Estate",
            "subcategory":"Real Estate Operator",
            "type":"Services"
        }
    ],
    "sg:phone":"+1 301 249 6763",
    "sg:postcode":"20774",
    "sg:province":"MD",
    "sg:tags":[
        "property",
        "lessor"
    ],
    "wof:name":"St Amant James W & Kim MA",
    "wof:placetype":"venue"
},
  "geometry": {"coordinates":[-76.709536,38.887211],"type":"Point"}
}