{
  "type": "Feature",
  "properties": {
    "iso:country":"US",
    "sg:address":"2878 Daisy Rd",
    "sg:city":"Woodbine",
    "sg:classifiers":[
        {
            "category":"Retail",
            "subcategory":"Auto Repair",
            "type":"Services"
        }
    ],
    "sg:phone":"+1 410 489 9005",
    "sg:postcode":"21797",
    "sg:province":"MD",
    "sg:tags":[
        "repairing",
        "automobile",
        "general"
    ],
    "wof:name":"Schaeffer Import Auto Care Inc",
    "wof:placetype":"venue"
},
  "geometry": {"coordinates":[-77.067914,39.297164],"type":"Point"}
}