{
  "type": "Feature",
  "properties": {
    "iso:country":"US",
    "sg:address":"2385 Boston St",
    "sg:city":"Baltimore",
    "sg:classifiers":[
        {
            "category":"Health Services",
            "subcategory":"Doctor",
            "type":"Services"
        }
    ],
    "sg:phone":"+1 410 563 0250",
    "sg:postcode":"21224",
    "sg:province":"MD",
    "sg:tags":[
        "physician",
        "surgeon"
    ],
    "wof:name":"Henry D Train Md",
    "wof:placetype":"venue"
},
  "geometry": {"coordinates":[-76.582866,39.282136],"type":"Point"}
}