{
  "type": "Feature",
  "properties": {
    "addr:full":"1 Church St Rockville MD 20850",
    "addr:housenumber":"1",
    "addr:postcode":"20850",
    "addr:street":"Church St",
    "iso:country":"US",
    "sg:address":"1 Church St",
    "sg:city":"Rockville",
    "sg:classifiers":[
        {
            "category":"Health Services",
            "subcategory":"Doctor",
            "type":"Services"
        }
    ],
    "sg:phone":"+1 301 314 0692",
    "sg:postcode":"20850",
    "sg:province":"MD",
    "sg:tags":[
        "physician",
        "surgeon"
    ],
    "wof:name":"Thomas M Mould MD",
    "wof:placetype":"venue"
},
  "geometry": {"coordinates":[-77.145004,39.082865],"type":"Point"}
}