{
  "type": "Feature",
  "properties": {
    "addr:full":"12611 Wisteria Dr Germantown MD 20874",
    "addr:housenumber":"12611",
    "addr:postcode":"20874",
    "addr:street":"Wisteria Dr",
    "iso:country":"US",
    "sg:address":"12611 Wisteria Dr",
    "sg:city":"Germantown",
    "sg:classifiers":[
        {
            "category":"Personal",
            "subcategory":"Barber",
            "type":"Services"
        }
    ],
    "sg:phone":"+1 301 515 8243",
    "sg:postcode":"20874",
    "sg:province":"MD",
    "wof:name":"Germantown Barbershop",
    "wof:placetype":"venue"
},
  "geometry": {"coordinates":[-77.26190699999999,39.170305],"type":"Point"}
}