{
  "type": "Feature",
  "properties": {
    "iso:country":"US",
    "sg:address":"2424 Whiteford Rd",
    "sg:city":"Whiteford",
    "sg:classifiers":[
        {
            "category":"Restaurant",
            "type":"Food & Drink"
        }
    ],
    "sg:phone":"+1 410 452 8191",
    "sg:postcode":"21160",
    "sg:province":"MD",
    "sg:tags":[
        "pizza"
    ],
    "wof:name":"Delta Pizza",
    "wof:placetype":"venue"
},
  "geometry": {"coordinates":[-76.349186,39.711504],"type":"Point"}
}