{
  "type": "Feature",
  "properties": {
    "addr:full":"213 Shaw Ave Silver Spring MD 20904",
    "addr:housenumber":"213",
    "addr:postcode":"20904",
    "addr:street":"Shaw Ave",
    "iso:country":"US",
    "sg:address":"213 Shaw Ave",
    "sg:city":"Silver Spring",
    "sg:classifiers":[
        {
            "category":"Organizations",
            "subcategory":"Religious Organization",
            "type":"Services"
        }
    ],
    "sg:phone":"+1 301 622 5375",
    "sg:postcode":"20904",
    "sg:province":"MD",
    "sg:tags":[
        "church"
    ],
    "sg:website":"www.kbcw.org",
    "wof:name":"Korean Baptist Church",
    "wof:placetype":"venue"
},
  "geometry": {"coordinates":[-77.014537,39.067171],"type":"Point"}
}