{
  "type": "Feature",
  "properties": {
    "iso:country":"US",
    "sg:address":"16050 Elegant Ct",
    "sg:city":"Bowie",
    "sg:classifiers":[
        {
            "category":"Education",
            "subcategory":"Special Training",
            "type":"Public Place"
        }
    ],
    "sg:phone":"+1 301 352 5404",
    "sg:postcode":"20716",
    "sg:province":"MD",
    "sg:tags":[
        "educational",
        "consulting"
    ],
    "wof:name":"Tillman Tasha",
    "wof:placetype":"venue"
},
  "geometry": {"coordinates":[-76.726769,38.943263],"type":"Point"}
}