{
  "type": "Feature",
  "properties": {
    "addr:full":"9608 Bellevue Dr Bethesda MD 20814",
    "addr:housenumber":"9608",
    "addr:postcode":"20814",
    "addr:street":"Bellevue Dr",
    "iso:country":"US",
    "sg:address":"9608 Bellevue Dr",
    "sg:city":"Bethesda",
    "sg:classifiers":[
        {
            "category":"Professional",
            "type":"Services"
        }
    ],
    "sg:phone":"+1 301 897 8372",
    "sg:postcode":"20814",
    "sg:province":"MD",
    "wof:name":"Velmac Educational Servic",
    "wof:placetype":"venue"
},
  "geometry": {"coordinates":[-77.09772599999999,39.014553],"type":"Point"}
}