{
  "type": "Feature",
  "properties": {
    "addr:full":"31 Robinson Rd Severna Park MD 21146",
    "addr:housenumber":"31",
    "addr:postcode":"21146",
    "addr:street":"Robinson Rd",
    "iso:country":"US",
    "sg:address":"31 Robinson Rd",
    "sg:city":"Severna Park",
    "sg:classifiers":[
        {
            "category":"Health Services",
            "subcategory":"Doctor",
            "type":"Services"
        }
    ],
    "sg:phone":"+1 410 544 5900",
    "sg:postcode":"21146",
    "sg:province":"MD",
    "sg:tags":[
        "physician",
        "surgeon"
    ],
    "wof:name":"Stephen Katz MD",
    "wof:placetype":"venue"
},
  "geometry": {"coordinates":[-76.553032,39.078928],"type":"Point"}
}