{
  "type": "Feature",
  "properties": {
    "addr:full":"8600 Lasalle Rd Baltimore MD 21286",
    "addr:housenumber":"8600",
    "addr:postcode":"21286",
    "addr:street":"Lasalle Rd",
    "iso:country":"US",
    "sg:address":"8600 Lasalle Rd",
    "sg:city":"Baltimore",
    "sg:classifiers":[
        {
            "category":"Insurance",
            "subcategory":"Insurance Agent",
            "type":"Services"
        }
    ],
    "sg:phone":"+1 410 828 5282",
    "sg:postcode":"21286",
    "sg:province":"MD",
    "sg:tags":[
        "consultant"
    ],
    "wof:name":"Gem Group",
    "wof:placetype":"venue"
},
  "geometry": {"coordinates":[-76.57597699999999,39.395913],"type":"Point"}
}