{
  "type": "Feature",
  "properties": {
    "addr:full":"1101 N Rolling Rd Catonsville MD 21228",
    "addr:housenumber":"1101",
    "addr:postcode":"21228",
    "addr:street":"N Rolling Rd",
    "iso:country":"US",
    "sg:address":"1101 N Rolling Rd",
    "sg:city":"Catonsville",
    "sg:classifiers":[
        {
            "category":"Restaurant",
            "type":"Food & Drink"
        }
    ],
    "sg:menulink":"http://www.allmenus.com/md/catonsville/146769-subway/menu/",
    "sg:phone":"+1 410 744 3063",
    "sg:postcode":"21228",
    "sg:province":"MD",
    "sg:tags":[
        "american",
        "sandwich"
    ],
    "wof:name":"Subway",
    "wof:placetype":"venue"
},
  "geometry": {"coordinates":[-76.752774,39.285047],"type":"Point"}
}