{
  "type": "Feature",
  "properties": {
    "addr:full":"1030 Hull St Baltimore MD 21230",
    "addr:housenumber":"1030",
    "addr:postcode":"21230",
    "addr:street":"Hull St",
    "iso:country":"US",
    "sg:address":"1030 Hull St",
    "sg:city":"Baltimore",
    "sg:classifiers":[
        {
            "category":"Professional",
            "subcategory":"Business Services",
            "type":"Services"
        }
    ],
    "sg:phone":"+1 410 332 0053",
    "sg:postcode":"21230",
    "sg:province":"MD",
    "sg:tags":[
        "inspection"
    ],
    "wof:name":"National Auto Inspection",
    "wof:placetype":"venue"
},
  "geometry": {"coordinates":[-76.590585,39.274935],"type":"Point"}
}