{
  "type": "Feature",
  "properties": {
    "iso:country":"US",
    "sg:address":"1639 N Washington St",
    "sg:city":"Baltimore",
    "sg:classifiers":[
        {
            "category":"Personal",
            "subcategory":"Beauty Salon",
            "type":"Services"
        }
    ],
    "sg:phone":"+1 410 327 2182",
    "sg:postcode":"21213",
    "sg:province":"MD",
    "wof:name":"Barbie's Beauty Salon",
    "wof:placetype":"venue"
},
  "geometry": {"coordinates":[-76.590204,39.309382],"type":"Point"}
}