{
  "type": "Feature",
  "properties": {
    "iso:country":"US",
    "sg:address":"3511 N Calvert St",
    "sg:city":"Baltimore",
    "sg:classifiers":[
        {
            "category":"Professional",
            "subcategory":"Engineering",
            "type":"Services"
        }
    ],
    "sg:phone":"+1 443 874 4630",
    "sg:postcode":"21218",
    "sg:province":"MD",
    "sg:tags":[
        "consulting",
        "structural",
        "engineer"
    ],
    "wof:name":"Blake Structual",
    "wof:placetype":"venue"
},
  "geometry": {"coordinates":[-76.614532,39.331692],"type":"Point"}
}