{
  "type": "Feature",
  "properties": {
    "iso:country":"US",
    "sg:address":"9510 Culver St",
    "sg:city":"Kensington",
    "sg:classifiers":[
        {
            "category":"Building & Trades",
            "subcategory":"Electrical",
            "type":"Services"
        }
    ],
    "sg:phone":"+1 301 962 9191",
    "sg:postcode":"20895",
    "sg:province":"MD",
    "sg:tags":[
        "electric",
        "contractor"
    ],
    "wof:name":"New Age Electric",
    "wof:placetype":"venue"
},
  "geometry": {"coordinates":[-77.082555,39.009438],"type":"Point"}
}