{
  "type": "Feature",
  "properties": {
    "addr:full":"13523 Georgia Ave Silver Spring MD 20906",
    "addr:housenumber":"13523",
    "addr:postcode":"20906",
    "addr:street":"Georgia Ave",
    "iso:country":"US",
    "sg:address":"13523 Georgia Ave",
    "sg:city":"Silver Spring",
    "sg:classifiers":[
        {
            "category":"Building & Trades",
            "subcategory":"Construction",
            "type":"Services"
        }
    ],
    "sg:phone":"+1 301 942 1464",
    "sg:postcode":"20906",
    "sg:province":"MD",
    "sg:tags":[
        "stone",
        "contractor"
    ],
    "wof:name":"Global Construction & Landscpg",
    "wof:placetype":"venue"
},
  "geometry": {"coordinates":[-77.071718,39.078246],"type":"Point"}
}