{
  "type": "Feature",
  "properties": {
    "iso:country":"US",
    "sg:address":"603 W Patrick St",
    "sg:city":"Frederick",
    "sg:classifiers":[
        {
            "category":"Professional",
            "subcategory":"Lawyer & Legal Services",
            "type":"Services"
        }
    ],
    "sg:phone":"+1 301 662 9122",
    "sg:postcode":"21701",
    "sg:province":"MD",
    "sg:tags":[
        "civil",
        "discrimination",
        "attorney",
        "right",
        "law"
    ],
    "sg:website":"http://www.gordonsimmons.com",
    "wof:name":"Gordon & Simmons",
    "wof:placetype":"venue"
},
  "geometry": {"coordinates":[-77.428308,39.414032],"type":"Point"}
}