{
  "type": "Feature",
  "properties": {
    "iso:country":"US",
    "sg:address":"4920 Niagara Rd",
    "sg:city":"College Park",
    "sg:classifiers":[
        {
            "category":"Organizations",
            "subcategory":"Non-profit Organization",
            "type":"Services"
        }
    ],
    "sg:phone":"+1 301 441 3570",
    "sg:postcode":"20740",
    "sg:province":"MD",
    "wof:name":"Scripture Research Assn",
    "wof:placetype":"venue"
},
  "geometry": {"coordinates":[-76.92332,39.017521],"type":"Point"}
}