{
  "type": "Feature",
  "properties": {
    "addr:full":"6000 Laurel Bowie Rd Bowie MD 20715",
    "addr:housenumber":"6000",
    "addr:postcode":"20715",
    "addr:street":"Laurel Bowie Rd",
    "iso:country":"US",
    "sg:address":"6000 Laurel Bowie Rd",
    "sg:city":"Bowie",
    "sg:classifiers":[
        {
            "category":"Banks & Credit Unions",
            "subcategory":"Bank",
            "type":"Services"
        }
    ],
    "sg:phone":"+1 301 352 0168",
    "sg:postcode":"20715",
    "sg:province":"MD",
    "sg:tags":[
        "loan",
        "real estate"
    ],
    "wof:name":"Remax Allegiance Tower Mtg",
    "wof:placetype":"venue"
},
  "geometry": {"coordinates":[-76.755696,38.971864],"type":"Point"}
}