{
  "type": "Feature",
  "properties": {
    "addr:full":"231 E Deer Park Dr Gaithersburg MD 20877",
    "addr:housenumber":"231",
    "addr:postcode":"20877",
    "addr:street":"E Deer Park Dr",
    "iso:country":"US",
    "sg:address":"231 E Deer Park Dr",
    "sg:city":"Gaithersburg",
    "sg:classifiers":[
        {
            "category":"Real Estate",
            "subcategory":"Real Estate Agent",
            "type":"Services"
        }
    ],
    "sg:phone":"+1 301 972 1947",
    "sg:postcode":"20877",
    "sg:province":"MD",
    "sg:tags":[
        "authorities",
        "housing"
    ],
    "wof:name":"Middlebrook Square",
    "wof:placetype":"venue"
},
  "geometry": {"coordinates":[-77.18129399999999,39.136661],"type":"Point"}
}