{
  "type": "Feature",
  "properties": {
    "addr:full":"3748 Stonesboro Rd Fort Washington MD 20744",
    "addr:housenumber":"3748",
    "addr:postcode":"20744",
    "addr:street":"Stonesboro Rd",
    "iso:country":"US",
    "sg:address":"3748 Stonesboro Rd",
    "sg:city":"Fort Washington",
    "sg:classifiers":[
        {
            "category":"Banks & Credit Unions",
            "subcategory":"Bank",
            "type":"Services"
        }
    ],
    "sg:phone":"+1 301 248 3080",
    "sg:postcode":"20744",
    "sg:province":"MD",
    "sg:tags":[
        "loan",
        "real estate"
    ],
    "wof:name":"Wells Fargo Mortgage",
    "wof:placetype":"venue"
},
  "geometry": {"coordinates":[-76.949079,38.767509],"type":"Point"}
}