{
  "type": "Feature",
  "properties": {
    "addr:full":"5025 Marlboro Pike Capitol Heights MD 20743",
    "addr:housenumber":"5025",
    "addr:postcode":"20743",
    "addr:street":"Marlboro Pike",
    "iso:country":"US",
    "sg:address":"5025 Marlboro Pike",
    "sg:city":"Capitol Heights",
    "sg:classifiers":[
        {
            "category":"Food & Beverages",
            "subcategory":"Meat & Fish",
            "type":"Retail Goods"
        }
    ],
    "sg:phone":"+1 301 568 6150",
    "sg:postcode":"20743",
    "sg:province":"MD",
    "sg:tags":[
        "seafood",
        "market"
    ],
    "wof:name":"Suburban Seafood",
    "wof:placetype":"venue"
},
  "geometry": {"coordinates":[-76.921997,38.870499],"type":"Point"}
}