{
  "type": "Feature",
  "properties": {
    "iso:country":"US",
    "sg:address":"4615 Hollins Ferry Rd #B",
    "sg:city":"Halethorpe",
    "sg:classifiers":[
        {
            "category":"Restaurant",
            "type":"Food & Drink"
        }
    ],
    "sg:phone":"+1 410 247 7822",
    "sg:postcode":"21227",
    "sg:province":"MD",
    "sg:tags":[
        "flavor",
        "local"
    ],
    "sg:website":"www.ccbeer.com",
    "wof:name":"Clipper City Brewing Company",
    "wof:placetype":"venue"
},
  "geometry": {"coordinates":[-76.676395,39.231881],"type":"Point"}
}