{
  "type": "Feature",
  "properties": {
    "addr:full":"26750 Anthony Mill Rd Denton MD 21629",
    "addr:housenumber":"26750",
    "addr:postcode":"21629",
    "addr:street":"Anthony Mill Rd",
    "iso:country":"US",
    "sg:address":"26750 Anthony Mill Rd",
    "sg:city":"Denton",
    "sg:classifiers":[
        {
            "category":"Transit Center",
            "subcategory":"Freight",
            "type":"Transportation"
        },
        {
            "category":"Freight",
            "type":"Transportation"
        }
    ],
    "sg:phone":"+1 410 479 0957",
    "sg:postcode":"21629",
    "sg:province":"MD",
    "sg:tags":[
        "local",
        "trucking-motor",
        "trucking"
    ],
    "wof:name":"Bruce Miller Trucking",
    "wof:placetype":"venue"
},
  "geometry": {"coordinates":[-75.77722900000001,38.879007],"type":"Point"}
}