{
  "type": "Feature",
  "properties": {
    "addr:full":"620 Pyle Rd Forest Hill MD 21050",
    "addr:housenumber":"620",
    "addr:postcode":"21050",
    "addr:street":"Pyle Rd",
    "iso:country":"US",
    "sg:address":"620 Pyle Rd",
    "sg:city":"Forest Hill",
    "sg:classifiers":[
        {
            "category":"Wholesale",
            "subcategory":"Plants",
            "type":"Manufacturing & Wholesale Goods"
        }
    ],
    "sg:phone":"+1 410 838 7950",
    "sg:postcode":"21050",
    "sg:province":"MD",
    "sg:tags":[
        "supply"
    ],
    "wof:name":"Atlantic Star Nursery",
    "wof:placetype":"venue"
},
  "geometry": {"coordinates":[-76.367178,39.610647],"type":"Point"}
}