{
  "type": "Feature",
  "properties": {
    "iso:country":"US",
    "sg:address":"4500 Lehigh Rd",
    "sg:city":"College Park",
    "sg:classifiers":[
        {
            "category":"Personal",
            "subcategory":"Beauty Salon",
            "type":"Services"
        }
    ],
    "sg:phone":"+1 301 927 2319",
    "sg:postcode":"20740",
    "sg:province":"MD",
    "wof:name":"Expressions",
    "wof:placetype":"venue"
},
  "geometry": {"coordinates":[-76.936506,38.98119],"type":"Point"}
}