{
  "type": "Feature",
  "properties": {
    "iso:country":"US",
    "sg:address":"120 E 25th St Ste 1",
    "sg:city":"Baltimore",
    "sg:classifiers":[
        {
            "category":"Personal",
            "type":"Services"
        }
    ],
    "sg:phone":"+1 410 566 8669",
    "sg:postcode":"21218",
    "sg:province":"MD",
    "sg:tags":[
        "towing"
    ],
    "wof:name":"McMurray Towing Service",
    "wof:placetype":"venue"
},
  "geometry": {"coordinates":[-76.6147,39.318001],"type":"Point"}
}