{
  "type": "Feature",
  "properties": {
    "iso:country":"US",
    "sg:address":"620 Rolling Hills Rd",
    "sg:city":"Dowell",
    "sg:classifiers":[
        {
            "category":"Manufacturing",
            "subcategory":"Watercraft",
            "type":"Manufacturing & Wholesale Goods"
        }
    ],
    "sg:phone":"+1 410 326 3480",
    "sg:postcode":"20629",
    "sg:province":"MD",
    "sg:tags":[
        "rebuilt",
        "part",
        "boat"
    ],
    "wof:name":"Riker's Custom Marine",
    "wof:placetype":"venue"
},
  "geometry": {"coordinates":[-76.450857,38.3376],"type":"Point"}
}