{
  "type": "Feature",
  "properties": {
    "addr:full":"7915 Parston Dr District Heights MD 20747",
    "addr:housenumber":"7915",
    "addr:postcode":"20747",
    "addr:street":"Parston Dr",
    "iso:country":"US",
    "sg:address":"7915 Parston Dr",
    "sg:city":"District Heights",
    "sg:classifiers":[
        {
            "category":"Retail",
            "subcategory":"Auto Repair",
            "type":"Services"
        }
    ],
    "sg:phone":"+1 301 420 1901",
    "sg:postcode":"20747",
    "sg:province":"MD",
    "sg:tags":[
        "glass",
        "coating",
        "tinting"
    ],
    "wof:name":"U V's",
    "wof:placetype":"venue"
},
  "geometry": {"coordinates":[-76.870212,38.846348],"type":"Point"}
}