{
  "type": "Feature",
  "properties": {
    "addr:full":"1270 Buckhorn Rd Sykesville MD 21784",
    "addr:housenumber":"1270",
    "addr:postcode":"21784",
    "addr:street":"Buckhorn Rd",
    "iso:country":"US",
    "sg:address":"1270 Buckhorn Rd",
    "sg:city":"Sykesville",
    "sg:classifiers":[
        {
            "category":"Building & Trades",
            "subcategory":"Plumbing",
            "type":"Services"
        }
    ],
    "sg:phone":"+1 410 236 1178",
    "sg:postcode":"21784",
    "sg:province":"MD",
    "sg:tags":[
        "contractor"
    ],
    "wof:name":"Whetstone Plumbing",
    "wof:placetype":"venue"
},
  "geometry": {"coordinates":[-77.040739,39.43133],"type":"Point"}
}