{
  "type": "Feature",
  "properties": {
    "addr:full":"26901 Clarksburg Rd Damascus MD 20872",
    "addr:housenumber":"26901",
    "addr:postcode":"20872",
    "addr:street":"Clarksburg Rd",
    "iso:country":"US",
    "sg:address":"26901 Clarksburg Rd",
    "sg:city":"Damascus",
    "sg:classifiers":[
        {
            "category":"Building & Trades",
            "subcategory":"Landscaping Services",
            "type":"Services"
        }
    ],
    "sg:phone":"+1 301 253 4234",
    "sg:postcode":"20872",
    "sg:province":"MD",
    "sg:tags":[
        "tree",
        "landscape",
        "contractor"
    ],
    "wof:name":"John R Hoffman Landscaping",
    "wof:placetype":"venue"
},
  "geometry": {"coordinates":[-77.259145,39.297141],"type":"Point"}
}