{
  "type": "Feature",
  "properties": {
    "addr:full":"2200 Defense Hwy Crofton MD 21114",
    "addr:housenumber":"2200",
    "addr:postcode":"21114",
    "addr:street":"Defense Hwy",
    "iso:country":"US",
    "sg:address":"2200 Defense Hwy",
    "sg:city":"Crofton",
    "sg:classifiers":[
        {
            "category":"Health Services",
            "subcategory":"Doctor",
            "type":"Services"
        }
    ],
    "sg:phone":"+1 410 721 0790",
    "sg:postcode":"21114",
    "sg:province":"MD",
    "wof:name":"Alan R Heller DDS",
    "wof:placetype":"venue"
},
  "geometry": {"coordinates":[-76.69777999999999,38.992006],"type":"Point"}
}