{
  "type": "Feature",
  "properties": {
    "iso:country":"US",
    "sg:address":"13406 Pennsylvania Ave",
    "sg:city":"Hagerstown",
    "sg:classifiers":[
        {
            "category":"Building & Trades",
            "subcategory":"Construction",
            "type":"Services"
        }
    ],
    "sg:phone":"+1 301 790 1718",
    "sg:postcode":"21742",
    "sg:province":"MD",
    "sg:tags":[
        "home",
        "builder"
    ],
    "wof:name":"Quality Homes",
    "wof:placetype":"venue"
},
  "geometry": {"coordinates":[-77.720282,39.679346],"type":"Point"}
}