{
  "type": "Feature",
  "properties": {
    "iso:country":"US",
    "sg:address":"3216 Ryerson Cir",
    "sg:city":"Halethorpe",
    "sg:classifiers":[
        {
            "category":"Health Services",
            "subcategory":"Nursing And Care Facility",
            "type":"Services"
        }
    ],
    "sg:phone":"+1 410 242 7841",
    "sg:postcode":"21227",
    "sg:province":"MD",
    "sg:tags":[
        "nurse",
        "practice-arnp",
        "nurses-advanced"
    ],
    "wof:name":"Susan Lynn",
    "wof:placetype":"venue"
},
  "geometry": {"coordinates":[-76.659271,39.234829],"type":"Point"}
}