{
  "type": "Feature",
  "properties": {
    "addr:full":"14137 Oakland Rd Ridgely MD 21660",
    "addr:housenumber":"14137",
    "addr:postcode":"21660",
    "addr:street":"Oakland Rd",
    "iso:country":"US",
    "sg:address":"14137 Oakland Rd",
    "sg:city":"Ridgely",
    "sg:classifiers":[
        {
            "category":"Farming",
            "subcategory":"Farm",
            "type":"Manufacturing & Wholesale Goods"
        }
    ],
    "sg:phone":"+1 410 634 1016",
    "sg:postcode":"21660",
    "sg:province":"MD",
    "wof:name":"Oakland View Farms LLC",
    "wof:placetype":"venue"
},
  "geometry": {"coordinates":[-75.876222,38.99498],"type":"Point"}
}