{
  "type": "Feature",
  "properties": {
    "iso:country":"US",
    "sg:address":"10 E Preston St",
    "sg:city":"Baltimore",
    "sg:classifiers":[
        {
            "category":"Retail",
            "subcategory":"Self-service Laundry",
            "type":"Services"
        }
    ],
    "sg:phone":"+1 410 625 2059",
    "sg:postcode":"21202",
    "sg:province":"MD",
    "wof:name":"Preston Street Laundromat",
    "wof:placetype":"venue"
},
  "geometry": {"coordinates":[-76.615655,39.304601],"type":"Point"}
}