{
  "type": "Feature",
  "properties": {
    "addr:full":"955 Essex Ave Essex MD 21221",
    "addr:housenumber":"955",
    "addr:postcode":"21221",
    "addr:street":"Essex Ave",
    "iso:country":"US",
    "sg:address":"955 Essex Ave",
    "sg:city":"Essex",
    "sg:classifiers":[
        {
            "category":"Taxi",
            "type":"Transportation"
        }
    ],
    "sg:phone":"+1 410 687 3232",
    "sg:postcode":"21221",
    "sg:province":"MD",
    "wof:name":"New Eastern Cab Inc",
    "wof:placetype":"venue"
},
  "geometry": {"coordinates":[-76.46000600000001,39.317119],"type":"Point"}
}