{
  "type": "Feature",
  "properties": {
    "iso:country":"US",
    "sg:address":"3938 White Rose Way",
    "sg:city":"Ellicott City",
    "sg:classifiers":[
        {
            "category":"Professional",
            "subcategory":"Management & Consulting",
            "type":"Services"
        }
    ],
    "sg:phone":"+1 410 461 4996",
    "sg:postcode":"21042",
    "sg:province":"MD",
    "sg:tags":[
        "consultant",
        "business"
    ],
    "wof:name":"Rochelle & Associates Inc",
    "wof:placetype":"venue"
},
  "geometry": {"coordinates":[-76.86575000000001,39.263218],"type":"Point"}
}