{
  "type": "Feature",
  "properties": {
    "iso:country":"US",
    "sg:address":"14806 Crain Hwy",
    "sg:city":"Brandywine",
    "sg:classifiers":[
        {
            "category":"Autos & Motor Vehicles",
            "subcategory":"Fuel & Gas Station",
            "type":"Retail Goods"
        }
    ],
    "sg:phone":"+1 301 782 7430",
    "sg:postcode":"20613",
    "sg:province":"MD",
    "sg:tags":[
        "oil"
    ],
    "wof:name":"Shell",
    "wof:placetype":"venue"
},
  "geometry": {"coordinates":[-76.87206999999999,38.686656],"type":"Point"}
}