{
  "type": "Feature",
  "properties": {
    "iso:country":"US",
    "sg:address":"1412 Stateside Dr",
    "sg:city":"Silver Spring",
    "sg:classifiers":[
        {
            "category":"Professional",
            "type":"Services"
        }
    ],
    "sg:phone":"+1 301 445 5454",
    "sg:postcode":"20903",
    "sg:province":"MD",
    "sg:tags":[
        "columnist",
        "author"
    ],
    "wof:name":"Leon F Howell",
    "wof:placetype":"venue"
},
  "geometry": {"coordinates":[-76.981292,39.011315],"type":"Point"}
}