{
  "type": "Feature",
  "properties": {
    "addr:full":"530 N Linwood Ave Baltimore MD 21205",
    "addr:housenumber":"530",
    "addr:postcode":"21205",
    "addr:street":"N Linwood Ave",
    "iso:country":"US",
    "sg:address":"530 N Linwood Ave",
    "sg:city":"Baltimore",
    "sg:classifiers":[
        {
            "category":"Professional",
            "type":"Services"
        }
    ],
    "sg:phone":"+1 410 400 0336",
    "sg:postcode":"21205",
    "sg:province":"MD",
    "sg:tags":[
        "novelty",
        "neon"
    ],
    "wof:name":"Neon Limelight",
    "wof:placetype":"venue"
},
  "geometry": {"coordinates":[-76.576521,39.297263],"type":"Point"}
}