{
  "type": "Feature",
  "properties": {
    "iso:country":"US",
    "sg:address":"2772 Crain Hwy",
    "sg:city":"Waldorf",
    "sg:classifiers":[
        {
            "category":"Organizations",
            "subcategory":"Religious Organization",
            "type":"Services"
        }
    ],
    "sg:phone":"+1 301 843 1773",
    "sg:postcode":"20601",
    "sg:province":"MD",
    "wof:name":"Heritage Church International, Inc.",
    "wof:placetype":"venue"
},
  "geometry": {"coordinates":[-76.901742,38.634926],"type":"Point"}
}