{
  "type": "Feature",
  "properties": {
    "iso:country":"US",
    "sg:address":"11002 Gateview Rd",
    "sg:city":"Cockeysville",
    "sg:classifiers":[
        {
            "category":"Shopping",
            "type":"Retail Goods"
        }
    ],
    "sg:phone":"+1 410 667 0860",
    "sg:postcode":"21030",
    "sg:province":"MD",
    "sg:tags":[
        "merchandise"
    ],
    "wof:name":"Bill Longs Brooklyn Shop",
    "wof:placetype":"venue"
},
  "geometry": {"coordinates":[-76.62600999999999,39.488101],"type":"Point"}
}