{
  "type": "Feature",
  "properties": {
    "addr:full":"8104 Quarterfield Rd Severn MD 21144",
    "addr:postcode":"8104;21144",
    "addr:street":"Quarterfield Rd",
    "iso:country":"US",
    "sg:address":"8104 Quarterfield Rd",
    "sg:city":"Severn",
    "sg:classifiers":[
        {
            "category":"Building & Trades",
            "subcategory":"Construction",
            "type":"Services"
        }
    ],
    "sg:phone":"+1 410 551 5111",
    "sg:postcode":"21144",
    "sg:province":"MD",
    "sg:tags":[
        "roofing",
        "contractor"
    ],
    "wof:name":"Roof Repair Experts",
    "wof:placetype":"venue"
},
  "geometry": {"coordinates":[-76.66725599999999,39.12551],"type":"Point"}
}