{
  "type": "Feature",
  "properties": {
    "addr:full":"485 Prime Outlets Blvd Hagerstown MD 21740",
    "addr:housenumber":"485",
    "addr:postcode":"21740",
    "addr:street":"Outlets Blvd",
    "iso:country":"US",
    "sg:address":"485 Prime Outlets Blvd",
    "sg:city":"Hagerstown",
    "sg:classifiers":[
        {
            "category":"Shopping",
            "subcategory":"Optical Goods",
            "type":"Retail Goods"
        }
    ],
    "sg:phone":"+1 301 745 5911",
    "sg:postcode":"21740",
    "sg:province":"MD",
    "sg:tags":[
        "sun",
        "goggles",
        "sunglasses"
    ],
    "wof:name":"Sunglass Outlet",
    "wof:placetype":"venue"
},
  "geometry": {"coordinates":[-77.730951,39.609583],"type":"Point"}
}