{
  "type": "Feature",
  "properties": {
    "iso:country":"US",
    "sg:address":"11255 New Hampshire Ave",
    "sg:city":"Silver Spring",
    "sg:classifiers":[
        {
            "category":"Home & Garden",
            "subcategory":"Garden Supply",
            "type":"Retail Goods"
        }
    ],
    "sg:phone":"+1 301 681 1812",
    "sg:postcode":"20904",
    "sg:province":"MD",
    "sg:tags":[
        "nursery",
        "gardening"
    ],
    "wof:name":"Meadows Farms Nurseries",
    "wof:placetype":"venue"
},
  "geometry": {"coordinates":[-76.99062000000001,39.040375],"type":"Point"}
}