{
  "type": "Feature",
  "properties": {
    "iso:country":"US",
    "sg:address":"16073 Frederick Rd",
    "sg:city":"Derwood",
    "sg:classifiers":[
        {
            "category":"Retail",
            "subcategory":"Auto Repair",
            "type":"Services"
        }
    ],
    "sg:phone":"+1 301 251 5589",
    "sg:postcode":"20855",
    "sg:province":"MD",
    "sg:tags":[
        "repairing",
        "automobile",
        "general"
    ],
    "wof:name":"M G A Auto Repair",
    "wof:placetype":"venue"
},
  "geometry": {"coordinates":[-77.16645,39.115756],"type":"Point"}
}