{
  "type": "Feature",
  "properties": {
    "iso:country":"US",
    "sg:address":"608 Pasture Brook Rd",
    "sg:city":"Severn",
    "sg:classifiers":[
        {
            "category":"Real Estate",
            "subcategory":"Real Estate Services",
            "type":"Services"
        },
        {
            "category":"Real Estate",
            "subcategory":"Real Estate Agent",
            "type":"Services"
        }
    ],
    "sg:phone":"+1 410 353 7808",
    "sg:postcode":"21144",
    "sg:province":"MD",
    "sg:tags":[
        "management"
    ],
    "wof:name":"Encompass Real Estate Advisors",
    "wof:placetype":"venue"
},
  "geometry": {"coordinates":[-76.664292,39.120864],"type":"Point"}
}