{
  "type": "Feature",
  "properties": {
    "addr:full":"13816 Mills Ave Silver Spring MD 20904",
    "addr:housenumber":"13816",
    "addr:postcode":"20904",
    "addr:street":"Mills Ave",
    "iso:country":"US",
    "sg:address":"13816 Mills Ave",
    "sg:city":"Silver Spring",
    "sg:classifiers":[
        {
            "category":"Professional",
            "subcategory":"Business Services",
            "type":"Services"
        }
    ],
    "sg:phone":"+1 301 384 4877",
    "sg:postcode":"20904",
    "sg:province":"MD",
    "wof:name":"Cosmic Venture",
    "wof:placetype":"venue"
},
  "geometry": {"coordinates":[-77.015355,39.083638],"type":"Point"}
}