{
  "type": "Feature",
  "properties": {
    "iso:country":"US",
    "sg:address":"10730 Normandie Farm Dr",
    "sg:city":"Potomac",
    "sg:classifiers":[
        {
            "category":"Wholesale",
            "subcategory":"Durable Goods & Equipment",
            "type":"Manufacturing & Wholesale Goods"
        }
    ],
    "sg:phone":"+1 301 299 3900",
    "sg:postcode":"20854",
    "sg:province":"MD",
    "sg:tags":[
        "importer"
    ],
    "wof:name":"Index Corp",
    "wof:placetype":"venue"
},
  "geometry": {"coordinates":[-77.205774,39.028143],"type":"Point"}
}