{
  "type": "Feature",
  "properties": {
    "iso:country":"US",
    "sg:address":"3690 Sellman Rd",
    "sg:city":"Beltsville",
    "sg:classifiers":[
        {
            "category":"Professional",
            "subcategory":"Business Services",
            "type":"Services"
        }
    ],
    "sg:phone":"+1 301 572 2004",
    "sg:postcode":"20705",
    "sg:province":"MD",
    "wof:name":"Ambient Recording",
    "wof:placetype":"venue"
},
  "geometry": {"coordinates":[-76.936397,39.034478],"type":"Point"}
}