{
  "type": "Feature",
  "properties": {
    "iso:country":"US",
    "sg:address":"2306 Price Ave",
    "sg:city":"Wheaton",
    "sg:classifiers":[
        {
            "category":"Personal",
            "subcategory":"Beauty Salon",
            "type":"Services"
        }
    ],
    "sg:phone":"+1 301 949 3336",
    "sg:postcode":"20902",
    "sg:province":"MD",
    "wof:name":"Nee Hair Salon",
    "wof:placetype":"venue"
},
  "geometry": {"coordinates":[-77.050411,39.040207],"type":"Point"}
}