{
  "type": "Feature",
  "properties": {
    "iso:country":"US",
    "sg:address":"31 Robinson Rd",
    "sg:city":"Severna Park",
    "sg:classifiers":[
        {
            "category":"Health Services",
            "subcategory":"Doctor",
            "type":"Services"
        }
    ],
    "sg:phone":"+1 410 647 4242",
    "sg:postcode":"21146",
    "sg:province":"MD",
    "sg:tags":[
        "physician",
        "surgeon"
    ],
    "wof:name":"Donald H Hislop & Assoc",
    "wof:placetype":"venue"
},
  "geometry": {"coordinates":[-76.553032,39.078928],"type":"Point"}
}