{
  "type": "Feature",
  "properties": {
    "addr:full":"12827 Ocean Gtwy Ocean City MD 21842",
    "addr:housenumber":"12827",
    "addr:postcode":"21842",
    "addr:street":"Ocean Gtwy",
    "iso:country":"US",
    "sg:address":"12827 Ocean Gtwy",
    "sg:city":"Ocean City",
    "sg:classifiers":[
        {
            "category":"Autos & Motor Vehicles",
            "subcategory":"Fuel & Gas Station",
            "type":"Retail Goods"
        }
    ],
    "sg:phone":"+1 410 213 2104",
    "sg:postcode":"21842",
    "sg:province":"MD",
    "sg:tags":[
        "oil"
    ],
    "wof:name":"Ocean Petroleum Co",
    "wof:placetype":"venue"
},
  "geometry": {"coordinates":[-75.104725,38.336176],"type":"Point"}
}