{
  "type": "Feature",
  "properties": {
    "iso:country":"US",
    "sg:address":"4900 Beaver Run",
    "sg:city":"Ellicott City",
    "sg:classifiers":[
        {
            "category":"Restaurant",
            "type":"Food & Drink"
        }
    ],
    "sg:phone":"+1 410 740 9857",
    "sg:postcode":"21043",
    "sg:province":"MD",
    "sg:website":"www.bobevans.com",
    "wof:name":"Bob Evans",
    "wof:placetype":"venue"
},
  "geometry": {"coordinates":[-76.815262,39.235384],"type":"Point"}
}