{
  "type": "Feature",
  "properties": {
    "iso:country":"US",
    "sg:address":"25361 Collins Wharf Rd",
    "sg:city":"Eden",
    "sg:classifiers":[
        {
            "category":"Building & Trades",
            "subcategory":"Landscaping Services",
            "type":"Services"
        }
    ],
    "sg:phone":"+1 410 334 6676",
    "sg:postcode":"21822",
    "sg:province":"MD",
    "sg:tags":[
        "sod",
        "sodding"
    ],
    "wof:name":"Collins Wharf Sod Farm",
    "wof:placetype":"venue"
},
  "geometry": {"coordinates":[-75.717764,38.29399],"type":"Point"}
}