{
  "type": "Feature",
  "properties": {
    "addr:full":"31B Apples Church Rd Thurmont MD 21788",
    "addr:housenumber":"31b",
    "addr:postcode":"21788",
    "addr:street":"Apples Church Rd",
    "iso:country":"US",
    "sg:address":"31B Apples Church Rd",
    "sg:city":"Thurmont",
    "sg:classifiers":[
        {
            "category":"Professional",
            "subcategory":"Art Services",
            "type":"Services"
        }
    ],
    "sg:phone":"+1 301 271 0007",
    "sg:postcode":"21788",
    "sg:province":"MD",
    "sg:tags":[
        "designer",
        "display",
        "producer"
    ],
    "wof:name":"Province Proofing",
    "wof:placetype":"venue"
},
  "geometry": {"coordinates":[-77.400525,39.621473],"type":"Point"}
}