{
  "type": "Feature",
  "properties": {
    "addr:full":"11301 Spur Wheel Ln Potomac MD 20854",
    "addr:housenumber":"11301",
    "addr:postcode":"20854",
    "addr:street":"Spur Wheel Ln",
    "iso:country":"US",
    "sg:address":"11301 Spur Wheel Ln",
    "sg:city":"Potomac",
    "sg:classifiers":[
        {
            "category":"Professional",
            "subcategory":"Accounting & Tax Preparation",
            "type":"Services"
        }
    ],
    "sg:phone":"+1 301 983 0330",
    "sg:postcode":"20854",
    "sg:province":"MD",
    "sg:tags":[
        "accountant"
    ],
    "wof:name":"R H Thomas",
    "wof:placetype":"venue"
},
  "geometry": {"coordinates":[-77.24490400000001,39.041401],"type":"Point"}
}