{
  "type": "Feature",
  "properties": {
    "iso:country":"US",
    "sg:address":"200 Warren Rd",
    "sg:city":"Cockysvl Hnt Vly",
    "sg:classifiers":[
        {
            "category":"Autos & Motor Vehicles",
            "subcategory":"Auto Supplies",
            "type":"Retail Goods"
        }
    ],
    "sg:phone":"+1 410 667 8468",
    "sg:postcode":"21030",
    "sg:province":"MD",
    "sg:tags":[
        "automobile",
        "accessory"
    ],
    "wof:name":"Midnight Car Audio",
    "wof:placetype":"venue"
},
  "geometry": {"coordinates":[-76.632522,39.474351],"type":"Point"}
}