{
  "type": "Feature",
  "properties": {
    "iso:country":"US",
    "sg:address":"159 Topeg Dr",
    "sg:city":"Severna Park",
    "sg:classifiers":[
        {
            "category":"Health Services",
            "subcategory":"Doctor",
            "type":"Services"
        }
    ],
    "sg:phone":"+1 410 647 4457",
    "sg:postcode":"21146",
    "sg:province":"MD",
    "sg:tags":[
        "physician",
        "surgeon"
    ],
    "wof:name":"Manuel G Fontanilla MD",
    "wof:placetype":"venue"
},
  "geometry": {"coordinates":[-76.542111,39.085862],"type":"Point"}
}