{
  "type": "Feature",
  "properties": {
    "iso:country":"US",
    "sg:address":"7310 Walston Switch Rd",
    "sg:city":"Parsonsburg",
    "sg:classifiers":[
        {
            "category":"Building & Trades",
            "subcategory":"Electrical",
            "type":"Services"
        }
    ],
    "sg:phone":"+1 410 742 0934",
    "sg:postcode":"21849",
    "sg:province":"MD",
    "sg:tags":[
        "electric",
        "contractor"
    ],
    "wof:name":"Mc Laughlin Electrical Svc",
    "wof:placetype":"venue"
},
  "geometry": {"coordinates":[-75.50538899999999,38.394076],"type":"Point"}
}