{
  "type": "Feature",
  "properties": {
    "iso:country":"US",
    "sg:address":"5636 Annapolis Rd",
    "sg:city":"Bladensburg",
    "sg:classifiers":[
        {
            "category":"Professional",
            "subcategory":"Lawyer & Legal Services",
            "type":"Services"
        }
    ],
    "sg:phone":"+1 301 779 9030",
    "sg:postcode":"20710",
    "sg:province":"MD",
    "wof:name":"Law Offices of Arman Ravery",
    "wof:placetype":"venue"
},
  "geometry": {"coordinates":[-76.919701,38.939201],"type":"Point"}
}