{
  "type": "Feature",
  "properties": {
    "addr:full":"5668 Baltimore National Pike Catonsville MD 21228",
    "addr:housenumber":"5668",
    "addr:postcode":"21228",
    "addr:street":"Baltimore National Pike",
    "iso:country":"US",
    "sg:address":"5668 Baltimore National Pike",
    "sg:city":"Catonsville",
    "sg:classifiers":[
        {
            "category":"Restaurant",
            "type":"Food & Drink"
        }
    ],
    "sg:phone":"+1 410 788 4063",
    "sg:postcode":"21228",
    "sg:province":"MD",
    "sg:tags":[
        "chicken",
        "wing"
    ],
    "sg:website":"www.chick-fil-a.com",
    "wof:name":"Chick-Fil-A",
    "wof:placetype":"venue"
},
  "geometry": {"coordinates":[-76.72938000000001,39.288834],"type":"Point"}
}