{
  "type": "Feature",
  "properties": {
    "addr:full":"1 Beaver Ct Cockeysville MD 21030",
    "addr:housenumber":"1",
    "addr:postcode":"21030",
    "addr:street":"Beaver Ct",
    "iso:country":"US",
    "sg:address":"1 Beaver Ct",
    "sg:city":"Cockeysville",
    "sg:classifiers":[
        {
            "category":"Retail",
            "subcategory":"Storage",
            "type":"Services"
        }
    ],
    "sg:phone":"+1 410 527 1318",
    "sg:postcode":"21030",
    "sg:province":"MD",
    "sg:tags":[
        "self"
    ],
    "sg:website":"www.extraspace.com",
    "wof:name":"Extra Space Storage",
    "wof:placetype":"venue"
},
  "geometry": {"coordinates":[-76.648831,39.47585],"type":"Point"}
}