{
  "type": "Feature",
  "properties": {
    "addr:full":"11851 Lime Plant Rd New Market MD 21774",
    "addr:housenumber":"11851",
    "addr:postcode":"21774",
    "addr:street":"Lime Plant Rd",
    "iso:country":"US",
    "sg:address":"11851 Lime Plant Rd",
    "sg:city":"New Market",
    "sg:classifiers":[
        {
            "category":"Organizations",
            "subcategory":"Religious Organization",
            "type":"Services"
        }
    ],
    "sg:phone":"+1 301 865 5680",
    "sg:postcode":"21774",
    "sg:province":"MD",
    "wof:name":"Dorsey Chpl Untd Mthdst Church",
    "wof:placetype":"venue"
},
  "geometry": {"coordinates":[-77.25174699999999,39.420998],"type":"Point"}
}