{
  "type": "Feature",
  "properties": {
    "addr:full":"1313 Orchard Way Frederick MD 21703",
    "addr:housenumber":"1313",
    "addr:postcode":"21703",
    "addr:street":"Orchard Way",
    "iso:country":"US",
    "sg:address":"1313 Orchard Way",
    "sg:city":"Frederick",
    "sg:classifiers":[
        {
            "category":"Building & Trades",
            "subcategory":"Construction",
            "type":"Services"
        }
    ],
    "sg:phone":"+1 301 663 3426",
    "sg:postcode":"21703",
    "sg:province":"MD",
    "sg:tags":[
        "painter"
    ],
    "wof:name":"Wareham Custom Drywall & Paint",
    "wof:placetype":"venue"
},
  "geometry": {"coordinates":[-77.45375199999999,39.415356],"type":"Point"}
}