{
  "type": "Feature",
  "properties": {
    "iso:country":"US",
    "sg:address":"3935 Hilton Rd",
    "sg:city":"Baltimore",
    "sg:classifiers":[
        {
            "category":"Education",
            "subcategory":"School",
            "type":"Public Place"
        }
    ],
    "sg:phone":"+1 410 396 0636",
    "sg:postcode":"21215",
    "sg:province":"MD",
    "sg:tags":[
        "high",
        "middle",
        "elementary"
    ],
    "sg:website":"www.ci.baltimore.md.us",
    "wof:name":"Baltimore City",
    "wof:placetype":"venue"
},
  "geometry": {"coordinates":[-76.66804500000001,39.330642],"type":"Point"}
}