{
  "type": "Feature",
  "properties": {
    "addr:full":"9524 Belair Rd Nottingham MD 21236",
    "addr:housenumber":"9524",
    "addr:postcode":"21236",
    "addr:street":"Belair Rd",
    "iso:country":"US",
    "sg:address":"9524 Belair Rd",
    "sg:city":"Nottingham",
    "sg:classifiers":[
        {
            "category":"Health Services",
            "subcategory":"Doctor",
            "type":"Services"
        }
    ],
    "sg:phone":"+1 410 529 9631",
    "sg:postcode":"21236",
    "sg:province":"MD",
    "sg:tags":[
        "physician",
        "surgeon"
    ],
    "wof:name":"Chapel View Family Care PC",
    "wof:placetype":"venue"
},
  "geometry": {"coordinates":[-76.467102,39.409901],"type":"Point"}
}