{
  "type": "Feature",
  "properties": {
    "addr:full":"905 Baltimore Rd Rockville MD 20851",
    "addr:housenumber":"905",
    "addr:postcode":"20851",
    "addr:street":"Baltimore Rd",
    "iso:country":"US",
    "sg:address":"905 Baltimore Rd",
    "sg:city":"Rockville",
    "sg:classifiers":[
        {
            "category":"Building & Trades",
            "subcategory":"Plumbing",
            "type":"Services"
        }
    ],
    "sg:phone":"+1 301 762 5120",
    "sg:postcode":"20851",
    "sg:province":"MD",
    "sg:tags":[
        "contractor"
    ],
    "wof:name":"Preferred Heating and AC",
    "wof:placetype":"venue"
},
  "geometry": {"coordinates":[-77.13343999999999,39.084116],"type":"Point"}
}