{
  "type": "Feature",
  "properties": {
    "iso:country":"US",
    "sg:address":"101 Lakeforest Blvd",
    "sg:city":"Gaithersburg",
    "sg:classifiers":[
        {
            "category":"Manufacturing",
            "subcategory":"Tools & Machinery",
            "type":"Manufacturing & Wholesale Goods"
        }
    ],
    "sg:phone":"+1 301 990 3586",
    "sg:postcode":"20877",
    "sg:province":"MD",
    "sg:tags":[
        "industry",
        "aerospace"
    ],
    "sg:website":"www.bsiproteomics.com",
    "wof:name":"BSI Proteomics Inc",
    "wof:placetype":"venue"
},
  "geometry": {"coordinates":[-77.207313,39.151496],"type":"Point"}
}