{
  "type": "Feature",
  "properties": {
    "iso:country":"US",
    "sg:address":"3001 Bel Pre Rd",
    "sg:city":"Silver Spring",
    "sg:classifiers":[
        {
            "category":"Organizations",
            "subcategory":"Religious Organization",
            "type":"Services"
        }
    ],
    "sg:phone":"+1 301 603 1772",
    "sg:postcode":"20906",
    "sg:province":"MD",
    "sg:tags":[
        "church"
    ],
    "wof:name":"Vedanta Center Of Greater",
    "wof:placetype":"venue"
},
  "geometry": {"coordinates":[-77.05969899999999,39.090797],"type":"Point"}
}