{
  "type": "Feature",
  "properties": {
    "iso:country":"US",
    "sg:address":"5761 Worcester Hwy",
    "sg:city":"Snow Hill",
    "sg:classifiers":[
        {
            "category":"Autos & Motor Vehicles",
            "subcategory":"Automobile Sales",
            "type":"Retail Goods"
        }
    ],
    "sg:phone":"+1 410 632 2220",
    "sg:postcode":"21863",
    "sg:province":"MD",
    "sg:tags":[
        "car",
        "dealer"
    ],
    "sg:website":"www.prestonchevrolet.com",
    "wof:name":"Preston Chevrolet",
    "wof:placetype":"venue"
},
  "geometry": {"coordinates":[-75.36750000000001,38.19764],"type":"Point"}
}