{
  "type": "Feature",
  "properties": {
    "addr:full":"4904 Aurora Dr Kensington MD 20895",
    "addr:housenumber":"4904",
    "addr:postcode":"20895",
    "addr:street":"Aurora Dr",
    "iso:country":"US",
    "sg:address":"4904 Aurora Dr",
    "sg:city":"Kensington",
    "sg:classifiers":[
        {
            "category":"Real Estate",
            "subcategory":"Architect",
            "type":"Services"
        }
    ],
    "sg:phone":"+1 301 933 1511",
    "sg:postcode":"20895",
    "sg:province":"MD",
    "wof:name":"Kjd Architects",
    "wof:placetype":"venue"
},
  "geometry": {"coordinates":[-77.096661,39.035555],"type":"Point"}
}