{
  "type": "Feature",
  "properties": {
    "iso:country":"US",
    "sg:address":"352 Main St Ste 100",
    "sg:city":"Gaithersburg",
    "sg:classifiers":[
        {
            "category":"Health Services",
            "subcategory":"Doctor",
            "type":"Services"
        }
    ],
    "sg:phone":"+1 301 330 7993",
    "sg:postcode":"20878",
    "sg:province":"MD",
    "sg:tags":[
        "physician",
        "immunology",
        "allergy",
        "surgeons",
        "treatment",
        "surgeon"
    ],
    "wof:name":"The Allergy Care Centers",
    "wof:placetype":"venue"
},
  "geometry": {"coordinates":[-77.237443,39.121168],"type":"Point"}
}