{
  "type": "Feature",
  "properties": {
    "iso:country":"US",
    "sg:address":"26100 Woodfield Rd",
    "sg:city":"Damascus",
    "sg:classifiers":[
        {
            "category":"Autos & Motor Vehicles",
            "subcategory":"Automobile Sales",
            "type":"Retail Goods"
        }
    ],
    "sg:phone":"+1 301 253 2151",
    "sg:postcode":"20872",
    "sg:province":"MD",
    "sg:tags":[
        "car",
        "dealer"
    ],
    "wof:name":"Damascus Chevrolet",
    "wof:placetype":"venue"
},
  "geometry": {"coordinates":[-77.201872,39.286376],"type":"Point"}
}