{
  "type": "Feature",
  "properties": {
    "addr:full":"8001 Catherine Ave Pasadena MD 21122",
    "addr:housenumber":"8001",
    "addr:postcode":"21122",
    "addr:street":"Catherine Ave",
    "iso:country":"US",
    "sg:address":"8001 Catherine Ave",
    "sg:city":"Pasadena",
    "sg:classifiers":[
        {
            "category":"Building & Trades",
            "subcategory":"Plumbing",
            "type":"Services"
        }
    ],
    "sg:phone":"+1 410 439 9462",
    "sg:postcode":"21122",
    "sg:province":"MD",
    "sg:tags":[
        "contractor"
    ],
    "wof:name":"Ray Pitt Plumbing & Htg",
    "wof:placetype":"venue"
},
  "geometry": {"coordinates":[-76.54597699999999,39.130432],"type":"Point"}
}