{
  "type": "Feature",
  "properties": {
    "iso:country":"US",
    "sg:address":"2730 University Blvd W",
    "sg:city":"Silver Spring",
    "sg:classifiers":[
        {
            "category":"Banks & Credit Unions",
            "subcategory":"Investment Brokerage",
            "type":"Services"
        }
    ],
    "sg:phone":"+1 301 942 2775",
    "sg:postcode":"20902",
    "sg:province":"MD",
    "wof:name":"Manfuso Brothers",
    "wof:placetype":"venue"
},
  "geometry": {"coordinates":[-77.056248,39.03954],"type":"Point"}
}