{
  "type": "Feature",
  "properties": {
    "addr:full":"5313 East Dr Baltimore MD 21227",
    "addr:housenumber":"5313",
    "addr:postcode":"21227",
    "addr:street":"East Dr",
    "iso:country":"US",
    "sg:address":"5313 East Dr",
    "sg:city":"Baltimore",
    "sg:classifiers":[
        {
            "category":"Health Services",
            "subcategory":"Medical Lab",
            "type":"Services"
        }
    ],
    "sg:phone":"+1 410 242 3204",
    "sg:postcode":"21227",
    "sg:province":"MD",
    "sg:tags":[
        "laboratory"
    ],
    "wof:name":"Modern Dental Laboratory",
    "wof:placetype":"venue"
},
  "geometry": {"coordinates":[-76.69348100000001,39.249538],"type":"Point"}
}