{
  "type": "Feature",
  "properties": {
    "iso:country":"US",
    "sg:address":"4701 Randolph Rd",
    "sg:city":"Rockville",
    "sg:classifiers":[
        {
            "category":"Personal",
            "type":"Services"
        }
    ],
    "sg:phone":"+1 301 231 4839",
    "sg:postcode":"20852",
    "sg:province":"MD",
    "sg:tags":[
        "assistant"
    ],
    "wof:name":"Comcast Tri-County",
    "wof:placetype":"venue"
},
  "geometry": {"coordinates":[-77.094177,39.05394],"type":"Point"}
}