{
  "type": "Feature",
  "properties": {
    "iso:country":"US",
    "sg:address":"2225 Evergreen St",
    "sg:city":"Baltimore",
    "sg:classifiers":[
        {
            "category":"Professional",
            "subcategory":"Research",
            "type":"Services"
        },
        {
            "category":"Professional",
            "subcategory":"Business Services",
            "type":"Services"
        }
    ],
    "sg:phone":"+1 410 225 9771",
    "sg:postcode":"21216",
    "sg:province":"MD",
    "sg:tags":[
        "environmental",
        "product",
        "ecological"
    ],
    "sg:website":"http://www.omo-set.com",
    "wof:name":"Omo Science, Energy And Technology, Inc.",
    "wof:placetype":"venue"
},
  "geometry": {"coordinates":[-76.660408,39.312553],"type":"Point"}
}