{
  "type": "Feature",
  "properties": {
    "addr:full":"260 Schilling Cir Cockysvl Hnt Vly MD 21031",
    "addr:housenumber":"260",
    "addr:postcode":"21031",
    "addr:street":"Schilling Cir Cockysvl Hnt Vly",
    "iso:country":"US",
    "sg:address":"260 Schilling Cir",
    "sg:city":"Cockysvl Hnt Vly",
    "sg:classifiers":[
        {
            "category":"Professional",
            "type":"Services"
        }
    ],
    "sg:phone":"+1 410 785 7900",
    "sg:postcode":"21031",
    "sg:province":"MD",
    "sg:tags":[
        "establishment"
    ],
    "wof:name":"Tricat Inc",
    "wof:placetype":"venue"
},
  "geometry": {"coordinates":[-76.660235,39.491942],"type":"Point"}
}