{
  "type": "Feature",
  "properties": {
    "addr:full":"7416 Royal Dominion Dr Bethesda MD 20817",
    "addr:housenumber":"7416",
    "addr:postcode":"20817",
    "addr:street":"Royal Dominion Dr",
    "iso:country":"US",
    "sg:address":"7416 Royal Dominion Dr",
    "sg:city":"Bethesda",
    "sg:classifiers":[
        {
            "category":"Professional",
            "subcategory":"Computer Services",
            "type":"Services"
        }
    ],
    "sg:phone":"+1 301 469 8170",
    "sg:postcode":"20817",
    "sg:province":"MD",
    "sg:tags":[
        "it"
    ],
    "wof:name":"Fedsolutions",
    "wof:placetype":"venue"
},
  "geometry": {"coordinates":[-77.154174,38.986854],"type":"Point"}
}