{
  "type": "Feature",
  "properties": {
    "iso:country":"US",
    "sg:address":"2339 E Monument St",
    "sg:city":"Baltimore",
    "sg:classifiers":[
        {
            "category":"Wholesale",
            "subcategory":"Non-durable Goods",
            "type":"Manufacturing & Wholesale Goods"
        }
    ],
    "sg:phone":"+1 410 522 2385",
    "sg:postcode":"21205",
    "sg:province":"MD",
    "sg:tags":[
        "dry",
        "goods-wholesale"
    ],
    "wof:name":"Nick-O-Mar Corporation-Baltimore Office Supply",
    "wof:placetype":"venue"
},
  "geometry": {"coordinates":[-76.58426799999999,39.298757],"type":"Point"}
}