{
  "type": "Feature",
  "properties": {
    "iso:country":"US",
    "sg:address":"8200 Bayside Rd",
    "sg:city":"Chesapeake Beach",
    "sg:classifiers":[
        {
            "category":"Government",
            "subcategory":"Office",
            "type":"Public Place"
        }
    ],
    "sg:phone":"+1 301 855 8398",
    "sg:postcode":"20732",
    "sg:province":"MD",
    "sg:tags":[
        "city"
    ],
    "wof:name":"Chesapeake Beach Town Hall",
    "wof:placetype":"venue"
},
  "geometry": {"coordinates":[-76.533596,38.694517],"type":"Point"}
}