{
  "type": "Feature",
  "properties": {
    "addr:full":"1713 Brightwell Ct Waldorf MD 20602",
    "addr:housenumber":"1713",
    "addr:postcode":"20602",
    "addr:street":"Brightwell Ct",
    "iso:country":"US",
    "sg:address":"1713 Brightwell Ct",
    "sg:city":"Waldorf",
    "sg:classifiers":[
        {
            "category":"Building & Trades",
            "subcategory":"Construction",
            "type":"Services"
        }
    ],
    "sg:phone":"+1 301 645 7256",
    "sg:postcode":"20602",
    "sg:province":"MD",
    "sg:tags":[
        "house"
    ],
    "wof:name":"Residential Maintenance Repair",
    "wof:placetype":"venue"
},
  "geometry": {"coordinates":[-76.905728,38.595994],"type":"Point"}
}