{
  "type": "Feature",
  "properties": {
    "addr:full":"9407 Livingston Rd Fort Washington MD 20744",
    "addr:housenumber":"9407",
    "addr:postcode":"20744",
    "addr:street":"Livingston Rd",
    "iso:country":"US",
    "sg:address":"9407 Livingston Rd",
    "sg:city":"Fort Washington",
    "sg:classifiers":[
        {
            "category":"Autos & Motor Vehicles",
            "subcategory":"Motorcycle Sales",
            "type":"Retail Goods"
        }
    ],
    "sg:phone":"+1 301 248 1200",
    "sg:postcode":"20744",
    "sg:province":"MD",
    "sg:tags":[
        "scooter"
    ],
    "sg:website":"www.hdwash.com",
    "wof:name":"Harley-Davidson Inc",
    "wof:placetype":"venue"
},
  "geometry": {"coordinates":[-76.995465,38.763889],"type":"Point"}
}