{
  "type": "Feature",
  "properties": {
    "iso:country":"US",
    "sg:address":"330 Aviation Way",
    "sg:city":"Frederick",
    "sg:classifiers":[
        {
            "category":"Autos & Motor Vehicles",
            "subcategory":"Automobile Sales",
            "type":"Retail Goods"
        }
    ],
    "sg:phone":"+1 301 662 8156",
    "sg:postcode":"21701",
    "sg:province":"MD",
    "sg:tags":[
        "aircraft"
    ],
    "sg:website":"www.frederickaviation.com",
    "wof:name":"Frederick Aviation Inc",
    "wof:placetype":"venue"
},
  "geometry": {"coordinates":[-77.379919,39.418202],"type":"Point"}
}