{
  "type": "Feature",
  "properties": {
    "iso:country":"US",
    "sg:address":"3012 Churchville Rd",
    "sg:city":"Churchville",
    "sg:classifiers":[
        {
            "category":"Building & Trades",
            "subcategory":"Electrical",
            "type":"Services"
        }
    ],
    "sg:phone":"+1 410 399 4748",
    "sg:postcode":"21028",
    "sg:province":"MD",
    "sg:tags":[
        "electric",
        "contractor"
    ],
    "wof:name":"Gracen Electric Inc",
    "wof:placetype":"venue"
},
  "geometry": {"coordinates":[-76.240997,39.556452],"type":"Point"}
}