{
  "type": "Feature",
  "properties": {
    "iso:country":"US",
    "sg:address":"7618 Leonardtown Rd",
    "sg:city":"Waldorf",
    "sg:classifiers":[
        {
            "category":"Building & Trades",
            "subcategory":"Construction",
            "type":"Services"
        }
    ],
    "sg:phone":"+1 301 632 6800",
    "sg:postcode":"20601",
    "sg:province":"MD",
    "sg:tags":[
        "home",
        "improvement"
    ],
    "wof:name":"E & B Enterprises Inc",
    "wof:placetype":"venue"
},
  "geometry": {"coordinates":[-76.805024,38.549974],"type":"Point"}
}