{
  "type": "Feature",
  "properties": {
    "addr:full":"10738 Old Annapolis Rd Frederick MD 21701",
    "addr:housenumber":"10738",
    "addr:postcode":"21701",
    "addr:street":"Old Annapolis Rd",
    "iso:country":"US",
    "sg:address":"10738 Old Annapolis Rd",
    "sg:city":"Frederick",
    "sg:classifiers":[
        {
            "category":"Building & Trades",
            "subcategory":"Construction",
            "type":"Services"
        }
    ],
    "sg:phone":"+1 301 898 3844",
    "sg:postcode":"21701",
    "sg:province":"MD",
    "sg:tags":[
        "general",
        "contractor"
    ],
    "wof:name":"J E Ledford & Sons Inc",
    "wof:placetype":"venue"
},
  "geometry": {"coordinates":[-77.289995,39.451204],"type":"Point"}
}