{
  "type": "Feature",
  "properties": {
    "addr:full":"424 E 25th St Baltimore MD 21218",
    "addr:housenumber":"424",
    "addr:postcode":"21218",
    "addr:street":"E 25Th St",
    "iso:country":"US",
    "sg:address":"424 E 25th St",
    "sg:city":"Baltimore",
    "sg:classifiers":[
        {
            "category":"Professional",
            "subcategory":"Employment Agencies",
            "type":"Services"
        }
    ],
    "sg:phone":"+1 410 235 8905",
    "sg:postcode":"21218",
    "sg:province":"MD",
    "sg:tags":[
        "help",
        "contractor"
    ],
    "wof:name":"Ready Staffing Inc",
    "wof:placetype":"venue"
},
  "geometry": {"coordinates":[-76.609503,39.318221],"type":"Point"}
}