{
  "type": "Feature",
  "properties": {
    "addr:full":"18800 Woodfield Rd Gaithersburg MD 20879",
    "addr:housenumber":"18800",
    "addr:postcode":"20879",
    "addr:street":"Woodfield Rd",
    "iso:country":"US",
    "sg:address":"18800 Woodfield Rd",
    "sg:city":"Gaithersburg",
    "sg:classifiers":[
        {
            "category":"Manufacturing",
            "subcategory":"Tools & Machinery",
            "type":"Manufacturing & Wholesale Goods"
        }
    ],
    "sg:phone":"+1 301 963 6044",
    "sg:postcode":"20879",
    "sg:province":"MD",
    "sg:tags":[
        "flight"
    ],
    "wof:name":"Delawre Park",
    "wof:placetype":"venue"
},
  "geometry": {"coordinates":[-77.157257,39.164196],"type":"Point"}
}