{
  "type": "Feature",
  "properties": {
    "iso:country":"US",
    "sg:address":"6242 Sykesville Rd",
    "sg:city":"Eldersburg",
    "sg:classifiers":[
        {
            "category":"Insurance",
            "subcategory":"Insurance Agent",
            "type":"Services"
        }
    ],
    "sg:phone":"+1 410 781 4747",
    "sg:postcode":"21784",
    "sg:province":"MD",
    "wof:name":"State Farm Insurance",
    "wof:placetype":"venue"
},
  "geometry": {"coordinates":[-76.951103,39.403398],"type":"Point"}
}