{
  "type": "Feature",
  "properties": {
    "addr:full":"7225 Parkway Dr Hanover MD 21076",
    "addr:housenumber":"7225",
    "addr:postcode":"21076",
    "addr:street":"Parkway Dr",
    "iso:country":"US",
    "sg:address":"7225 Parkway Dr",
    "sg:city":"Hanover",
    "sg:classifiers":[
        {
            "category":"Insurance",
            "subcategory":"Hazard Insurance",
            "type":"Services"
        }
    ],
    "sg:phone":"+1 410 712 0341",
    "sg:postcode":"21076",
    "sg:province":"MD",
    "sg:tags":[
        "commercial",
        "business"
    ],
    "wof:name":"Local Government Insurance Trust",
    "wof:placetype":"venue"
},
  "geometry": {"coordinates":[-76.729607,39.17783],"type":"Point"}
}