{
  "type": "Feature",
  "properties": {
    "iso:country":"US",
    "sg:address":"8113 Fenway Rd",
    "sg:city":"Bethesda",
    "sg:classifiers":[
        {
            "category":"Professional",
            "subcategory":"Computer Services",
            "type":"Services"
        }
    ],
    "sg:phone":"+1 301 365 5409",
    "sg:postcode":"20817",
    "sg:province":"MD",
    "sg:tags":[
        "graphics"
    ],
    "wof:name":"Carnemark Systems",
    "wof:placetype":"venue"
},
  "geometry": {"coordinates":[-77.170991,38.989353],"type":"Point"}
}