{
  "type": "Feature",
  "properties": {
    "iso:country":"US",
    "sg:address":"14404 Mount Oak Rd",
    "sg:city":"Bowie",
    "sg:classifiers":[
        {
            "category":"Retail",
            "subcategory":"Animal Services",
            "type":"Services"
        }
    ],
    "sg:phone":"+1 301 249 2965",
    "sg:postcode":"20721",
    "sg:province":"MD",
    "wof:name":"Jackie Macleod",
    "wof:placetype":"venue"
},
  "geometry": {"coordinates":[-76.74399200000001,38.925403],"type":"Point"}
}