{
  "type": "Feature",
  "properties": {
    "iso:country":"US",
    "sg:address":"8802 Oak Ln",
    "sg:city":"Fort Washington",
    "sg:classifiers":[
        {
            "category":"Shopping",
            "type":"Retail Goods"
        }
    ],
    "sg:phone":"+1 301 567 6040",
    "sg:postcode":"20744",
    "sg:province":"MD",
    "sg:tags":[
        "merchandise"
    ],
    "wof:name":"Wizdom Productions",
    "wof:placetype":"venue"
},
  "geometry": {"coordinates":[-77.009519,38.769133],"type":"Point"}
}