{
  "type": "Feature",
  "properties": {
    "addr:full":"10020 Chapel Rd Potomac MD 20854",
    "addr:housenumber":"10020",
    "addr:postcode":"20854",
    "addr:street":"Chapel Rd",
    "iso:country":"US",
    "sg:address":"10020 Chapel Rd",
    "sg:city":"Potomac",
    "sg:classifiers":[
        {
            "category":"Health Services",
            "subcategory":"Medical Lab",
            "type":"Services"
        }
    ],
    "sg:phone":"+1 301 983 8300",
    "sg:postcode":"20854",
    "sg:province":"MD",
    "wof:name":"James M Kawecki & Assoc",
    "wof:placetype":"venue"
},
  "geometry": {"coordinates":[-77.21539799999999,39.022821],"type":"Point"}
}