{
  "type": "Feature",
  "properties": {
    "addr:full":"1156 Sparrow Mill Way Bel Air MD 21015",
    "addr:housenumber":"1156",
    "addr:postcode":"21015",
    "addr:street":"Sparrow Mill Way",
    "iso:country":"US",
    "sg:address":"1156 Sparrow Mill Way",
    "sg:city":"Bel Air",
    "sg:classifiers":[
        {
            "category":"Shopping",
            "subcategory":"Gifts & Souvenirs",
            "type":"Retail Goods"
        }
    ],
    "sg:phone":"+1 410 420 3525",
    "sg:postcode":"21015",
    "sg:province":"MD",
    "wof:name":"Beachbound Collections",
    "wof:placetype":"venue"
},
  "geometry": {"coordinates":[-76.299531,39.525718],"type":"Point"}
}