{
  "type": "Feature",
  "properties": {
    "iso:country":"US",
    "sg:address":"2023 Thresam Ct",
    "sg:city":"Gambrills",
    "sg:classifiers":[
        {
            "category":"Professional",
            "subcategory":"Computer Services",
            "type":"Services"
        }
    ],
    "sg:phone":"+1 410 721 9259",
    "sg:postcode":"21054",
    "sg:province":"MD",
    "sg:tags":[
        "related"
    ],
    "wof:name":"Dale Conklin",
    "wof:placetype":"venue"
},
  "geometry": {"coordinates":[-76.644683,38.992454],"type":"Point"}
}