{
  "type": "Feature",
  "properties": {
    "addr:full":"11 Gwynns Mill Ct Owings Mills MD 21117",
    "addr:housenumber":"11",
    "addr:postcode":"21117",
    "addr:street":"Gwynns Mill Ct",
    "iso:country":"US",
    "sg:address":"11 Gwynns Mill Ct",
    "sg:city":"Owings Mills",
    "sg:classifiers":[
        {
            "category":"Professional",
            "type":"Services"
        }
    ],
    "sg:phone":"+1 410 363 0439",
    "sg:postcode":"21117",
    "sg:province":"MD",
    "sg:tags":[
        "establishment"
    ],
    "wof:name":"I G Generics",
    "wof:placetype":"venue"
},
  "geometry": {"coordinates":[-76.781677,39.413982],"type":"Point"}
}