{
  "type": "Feature",
  "properties": {
    "addr:full":"8950 Edmonston Rd Greenbelt MD 20740",
    "addr:postcode":"8950;20740",
    "addr:street":"Edmonston Rd",
    "iso:country":"US",
    "sg:address":"8950 Edmonston Rd",
    "sg:city":"Greenbelt",
    "sg:classifiers":[
        {
            "category":"Education",
            "subcategory":"School",
            "type":"Public Place"
        }
    ],
    "sg:phone":"+1 301 513 5040",
    "sg:postcode":"20740",
    "sg:province":"MD",
    "wof:name":"Greenbelt Middle School",
    "wof:placetype":"venue"
},
  "geometry": {"coordinates":[-76.90083,38.99834],"type":"Point"}
}