{
  "type": "Feature",
  "properties": {
    "addr:full":"7201 Bucher Rd Sparrows Point MD 21219",
    "addr:housenumber":"7201",
    "addr:postcode":"21219",
    "addr:street":"Bucher Rd",
    "iso:country":"US",
    "sg:address":"7201 Bucher Rd",
    "sg:city":"Sparrows Point",
    "sg:classifiers":[
        {
            "category":"Building & Trades",
            "subcategory":"Construction",
            "type":"Services"
        }
    ],
    "sg:phone":"+1 410 477 6831",
    "sg:postcode":"21219",
    "sg:province":"MD",
    "sg:tags":[
        "excavating",
        "contractor"
    ],
    "wof:name":"Rehak's Marine Construction",
    "wof:placetype":"venue"
},
  "geometry": {"coordinates":[-76.459681,39.224315],"type":"Point"}
}