{
  "type": "Feature",
  "properties": {
    "iso:country":"US",
    "sg:address":"1309 Kenton Rd",
    "sg:city":"Parkville",
    "sg:classifiers":[
        {
            "category":"Government",
            "subcategory":"Fire Station",
            "type":"Public Place"
        }
    ],
    "sg:phone":"+1 410 944 4230",
    "sg:postcode":"21234",
    "sg:province":"MD",
    "sg:tags":[
        "relief",
        "recovery",
        "disaster"
    ],
    "wof:name":"Temps 2000",
    "wof:placetype":"venue"
},
  "geometry": {"coordinates":[-76.56807000000001,39.378273],"type":"Point"}
}