{
  "type": "Feature",
  "properties": {
    "iso:country":"US",
    "sg:address":"8810 Postoak Rd",
    "sg:city":"Rockville",
    "sg:classifiers":[
        {
            "category":"Education",
            "subcategory":"School",
            "type":"Public Place"
        }
    ],
    "sg:phone":"+1 301 469 1010",
    "sg:postcode":"20854",
    "sg:province":"MD",
    "sg:tags":[
        "high",
        "middle",
        "elementary"
    ],
    "wof:name":"Montgomery County Public Schools",
    "wof:placetype":"venue"
},
  "geometry": {"coordinates":[-77.1784,39.04688],"type":"Point"}
}