{
  "type": "Feature",
  "properties": {
    "addr:full":"66 Oakway Rd Lutherville Timonium MD 21093",
    "addr:housenumber":"66",
    "addr:postcode":"21093",
    "addr:street":"Oakway Rd",
    "iso:country":"US",
    "sg:address":"66 Oakway Rd",
    "sg:city":"Lutherville Timonium",
    "sg:classifiers":[
        {
            "category":"Building & Trades",
            "subcategory":"Construction",
            "type":"Services"
        }
    ],
    "sg:phone":"+1 410 252 2600",
    "sg:postcode":"21093",
    "sg:province":"MD",
    "sg:tags":[
        "carpentry",
        "contractor"
    ],
    "wof:name":"Arthur E Funk",
    "wof:placetype":"venue"
},
  "geometry": {"coordinates":[-76.618002,39.439439],"type":"Point"}
}