{
  "type": "Feature",
  "properties": {
    "iso:country":"US",
    "sg:address":"15 E Padonia Rd",
    "sg:city":"Lutherville Timonium",
    "sg:classifiers":[
        {
            "category":"Food & Beverages",
            "subcategory":"Groceries & Convenience Stores",
            "type":"Retail Goods"
        }
    ],
    "sg:phone":"+1 410 252 1100",
    "sg:postcode":"21093",
    "sg:province":"MD",
    "wof:name":"Mars Super Markets Inc",
    "wof:placetype":"venue"
},
  "geometry": {"coordinates":[-76.631897,39.456402],"type":"Point"}
}