{
  "type": "Feature",
  "properties": {
    "iso:country":"US",
    "sg:address":"11051 Pulaski Hwy",
    "sg:city":"White Marsh",
    "sg:classifiers":[
        {
            "category":"Autos & Motor Vehicles",
            "subcategory":"Boat Sales",
            "type":"Retail Goods"
        }
    ],
    "sg:phone":"+1 410 335 1500",
    "sg:postcode":"21162",
    "sg:province":"MD",
    "sg:tags":[
        "dealer",
        "sales"
    ],
    "sg:website":"www.riversideboats.com",
    "wof:name":"Riverside Marine Sales",
    "wof:placetype":"venue"
},
  "geometry": {"coordinates":[-76.419177,39.386394],"type":"Point"}
}