{
  "type": "Feature",
  "properties": {
    "addr:full":"4113 Wholesale Club Dr Baltimore MD 21236",
    "addr:housenumber":"4113",
    "addr:postcode":"21236",
    "addr:street":"Wholesale Club Dr",
    "iso:country":"US",
    "sg:address":"4113 Wholesale Club Dr",
    "sg:city":"Baltimore",
    "sg:classifiers":[
        {
            "category":"Banks & Credit Unions",
            "subcategory":"Bank",
            "type":"Services"
        }
    ],
    "sg:phone":"+1 410 882 6700",
    "sg:postcode":"21236",
    "sg:province":"MD",
    "sg:tags":[
        "financing"
    ],
    "wof:name":"Household Finance",
    "wof:placetype":"venue"
},
  "geometry": {"coordinates":[-76.500433,39.382682],"type":"Point"}
}