{
  "type": "Feature",
  "properties": {
    "iso:country":"US",
    "sg:address":"3500 Boston St Ste 400",
    "sg:city":"Baltimore",
    "sg:classifiers":[
        {
            "category":"Professional",
            "subcategory":"Lawyer & Legal Services",
            "type":"Services"
        }
    ],
    "sg:phone":"+1 410 342 9800",
    "sg:postcode":"21224",
    "sg:province":"MD",
    "wof:name":"Hessey & Hessey",
    "wof:placetype":"venue"
},
  "geometry": {"coordinates":[-76.56746800000001,39.277307],"type":"Point"}
}