{
  "type": "Feature",
  "properties": {
    "iso:country":"US",
    "sg:address":"321 Dorchester Ave",
    "sg:city":"Cambridge",
    "sg:classifiers":[
        {
            "category":"Health Services",
            "subcategory":"Doctor",
            "type":"Services"
        }
    ],
    "sg:phone":"+1 410 228 1325",
    "sg:postcode":"21613",
    "sg:province":"MD",
    "sg:tags":[
        "medicine",
        "physician",
        "practice",
        "surgeons",
        "family"
    ],
    "wof:name":"Rose Hill Family Physicians",
    "wof:placetype":"venue"
},
  "geometry": {"coordinates":[-76.06724699999999,38.565475],"type":"Point"}
}