{
  "type": "Feature",
  "properties": {
    "addr:full":"17 War Admiral Ct Gaithersburg MD 20878",
    "addr:housenumber":"17",
    "addr:postcode":"20878",
    "addr:street":"War Admiral Ct",
    "iso:country":"US",
    "sg:address":"17 War Admiral Ct",
    "sg:city":"Gaithersburg",
    "sg:classifiers":[
        {
            "category":"Professional",
            "type":"Services"
        }
    ],
    "sg:phone":"+1 301 208 6796",
    "sg:postcode":"20878",
    "sg:province":"MD",
    "sg:tags":[
        "science",
        "lab"
    ],
    "wof:name":"Badie Shirin",
    "wof:placetype":"venue"
},
  "geometry": {"coordinates":[-77.264431,39.09836],"type":"Point"}
}