{
  "type": "Feature",
  "properties": {
    "addr:full":"329 High St Chestertown MD 21620",
    "addr:housenumber":"329",
    "addr:postcode":"21620",
    "addr:street":"High St",
    "iso:country":"US",
    "sg:address":"329 High St",
    "sg:city":"Chestertown",
    "sg:classifiers":[
        {
            "category":"Shopping",
            "subcategory":"Pharmacy",
            "type":"Retail Goods"
        }
    ],
    "sg:phone":"+1 410 778 2575",
    "sg:postcode":"21620",
    "sg:province":"MD",
    "wof:name":"Chestertown Pharmacy",
    "wof:placetype":"venue"
},
  "geometry": {"coordinates":[-76.067351,39.209514],"type":"Point"}
}