{
  "type": "Feature",
  "properties": {
    "addr:full":"800 Pleasant Dr Rockville MD 20850",
    "addr:housenumber":"800",
    "addr:postcode":"20850",
    "addr:street":"Pleasant Dr",
    "iso:country":"US",
    "sg:address":"800 Pleasant Dr",
    "sg:city":"Rockville",
    "sg:classifiers":[
        {
            "category":"Personal",
            "subcategory":"Tanning Parlor",
            "type":"Services"
        }
    ],
    "sg:phone":"+1 301 869 1285",
    "sg:postcode":"20850",
    "sg:province":"MD",
    "sg:tags":[
        "salon"
    ],
    "wof:name":"South Beach Tanning Salon",
    "wof:placetype":"venue"
},
  "geometry": {"coordinates":[-77.17057,39.113319],"type":"Point"}
}