{
  "type": "Feature",
  "properties": {
    "iso:country":"US",
    "sg:address":"110 W 39th St",
    "sg:city":"Baltimore",
    "sg:classifiers":[
        {
            "category":"Professional",
            "subcategory":"Lawyer & Legal Services",
            "type":"Services"
        }
    ],
    "sg:phone":"+1 410 366 6527",
    "sg:postcode":"21210",
    "sg:province":"MD",
    "wof:name":"Ellison S Ronald",
    "wof:placetype":"venue"
},
  "geometry": {"coordinates":[-76.622398,39.336601],"type":"Point"}
}