{
  "type": "Feature",
  "properties": {
    "iso:country":"US",
    "sg:address":"8804 Earl Ct",
    "sg:city":"Bethesda",
    "sg:classifiers":[
        {
            "category":"Professional",
            "type":"Services"
        }
    ],
    "sg:phone":"+1 301 469 4811",
    "sg:postcode":"20817",
    "sg:province":"MD",
    "wof:name":"Mary W Blitz",
    "wof:placetype":"venue"
},
  "geometry": {"coordinates":[-77.159124,39.000079],"type":"Point"}
}