{
  "type": "Feature",
  "properties": {
    "addr:full":"1136 Shore Hwy Denton MD 21629",
    "addr:housenumber":"1136",
    "addr:postcode":"21629",
    "addr:street":"Shore Hwy",
    "iso:country":"US",
    "sg:address":"1136 Shore Hwy",
    "sg:city":"Denton",
    "sg:classifiers":[
        {
            "category":"Insurance",
            "subcategory":"Insurance Agent",
            "type":"Services"
        }
    ],
    "sg:phone":"+1 410 479 2151",
    "sg:postcode":"21629",
    "sg:province":"MD",
    "wof:name":"Ashley Insurance",
    "wof:placetype":"venue"
},
  "geometry": {"coordinates":[-75.82415,38.866846],"type":"Point"}
}