{
  "type": "Feature",
  "properties": {
    "addr:full":"19709 Executive Park Cir Germantown MD 20874",
    "addr:housenumber":"19709",
    "addr:postcode":"20874",
    "addr:street":"Executive Park Cir",
    "iso:country":"US",
    "sg:address":"19709 Executive Park Cir",
    "sg:city":"Germantown",
    "sg:classifiers":[
        {
            "category":"Health Services",
            "subcategory":"Doctor",
            "type":"Services"
        }
    ],
    "sg:phone":"+1 301 916 6800",
    "sg:postcode":"20874",
    "sg:province":"MD",
    "sg:tags":[
        "dentist"
    ],
    "wof:name":"Orthodontic Centers",
    "wof:placetype":"venue"
},
  "geometry": {"coordinates":[-77.275318,39.181013],"type":"Point"}
}