{
  "type": "Feature",
  "properties": {
    "addr:full":"3637 Leonardtown Rd Waldorf MD 20601",
    "addr:housenumber":"3637",
    "addr:postcode":"20601",
    "addr:street":"Leonardtown Rd",
    "iso:country":"US",
    "sg:address":"3637 Leonardtown Rd",
    "sg:city":"Waldorf",
    "sg:classifiers":[
        {
            "category":"Personal",
            "subcategory":"Beauty Salon",
            "type":"Services"
        }
    ],
    "sg:phone":"+1 301 645 9255",
    "sg:postcode":"20601",
    "sg:province":"MD",
    "wof:name":"Hollywood Nails",
    "wof:placetype":"venue"
},
  "geometry": {"coordinates":[-76.89352100000001,38.617894],"type":"Point"}
}