{
  "type": "Feature",
  "properties": {
    "addr:full":"9749 Washington Blvd N Laurel MD 20723",
    "addr:housenumber":"9749",
    "addr:postcode":"20723",
    "addr:street":"Washington Blvd N",
    "iso:country":"US",
    "sg:address":"9749 Washington Blvd N",
    "sg:city":"Laurel",
    "sg:classifiers":[
        {
            "category":"Retail",
            "subcategory":"Repair Shop",
            "type":"Services"
        }
    ],
    "sg:phone":"+1 410 792 0960",
    "sg:postcode":"20723",
    "sg:province":"MD",
    "sg:tags":[
        "antique",
        "upholsterer"
    ],
    "wof:name":"Chem Clean Inc",
    "wof:placetype":"venue"
},
  "geometry": {"coordinates":[-76.82959700000001,39.118099],"type":"Point"}
}