{
  "type": "Feature",
  "properties": {
    "addr:full":"1305 Francis Ave Ste 1 & 2 Halethorpe MD 21227",
    "addr:housenumber":"1305",
    "addr:postcode":"21227",
    "addr:street":"Francis Ave Ste 1 & 2",
    "iso:country":"US",
    "sg:address":"1305 Francis Ave Ste 1 & 2",
    "sg:city":"Halethorpe",
    "sg:classifiers":[
        {
            "category":"Health Services",
            "subcategory":"Doctor",
            "type":"Services"
        },
        {
            "category":"Personal",
            "subcategory":"Beauty Salon",
            "type":"Services"
        }
    ],
    "sg:phone":"+1 443 575 6043",
    "sg:postcode":"21227",
    "sg:province":"MD",
    "sg:tags":[
        "hair",
        "replacement"
    ],
    "sg:website":"http://www.thehairsociety.com",
    "wof:name":"The Hair Society",
    "wof:placetype":"venue"
},
  "geometry": {"coordinates":[-76.695055,39.23835],"type":"Point"}
}