{
  "type": "Feature",
  "properties": {
    "iso:country":"US",
    "sg:address":"2603 Bradenbaugh Rd",
    "sg:city":"White Hall",
    "sg:classifiers":[
        {
            "category":"Banks & Credit Unions",
            "subcategory":"Investment Brokerage",
            "type":"Services"
        }
    ],
    "sg:phone":"+1 410 692 2313",
    "sg:postcode":"21161",
    "sg:province":"MD",
    "sg:tags":[
        "advisory",
        "financial"
    ],
    "wof:name":"Corestar Financial Group",
    "wof:placetype":"venue"
},
  "geometry": {"coordinates":[-76.51366400000001,39.659109],"type":"Point"}
}