{
  "type": "Feature",
  "properties": {
    "addr:full":"5010 Nicholson Lane Suite H 4 MD 20895",
    "addr:housenumber":"5010;4",
    "addr:postcode":"20895",
    "addr:street":"Nicholson Lane Suite H",
    "iso:country":"US",
    "sg:address":"5010 Nicholson Lane Suite H",
    "sg:city":"4",
    "sg:classifiers":[
        {
            "category":"Insurance",
            "subcategory":"Hazard Insurance",
            "type":"Services"
        }
    ],
    "sg:phone":"+1 301 231 0977",
    "sg:postcode":"20895",
    "sg:province":"MD",
    "sg:website":"www.bobglista.com",
    "wof:name":"Bob Glista State Farm Insurance",
    "wof:placetype":"venue"
},
  "geometry": {"coordinates":[-77.102886,39.046846],"type":"Point"}
}