{
  "type": "Feature",
  "properties": {
    "addr:full":"11109 Powers Ave Cockeysville MD 21030",
    "addr:housenumber":"11109",
    "addr:postcode":"21030",
    "addr:street":"Powers Ave",
    "iso:country":"US",
    "sg:address":"11109 Powers Ave",
    "sg:city":"Cockeysville",
    "sg:classifiers":[
        {
            "category":"Building & Trades",
            "subcategory":"Construction",
            "type":"Services"
        }
    ],
    "sg:phone":"+1 410 666 8825",
    "sg:postcode":"21030",
    "sg:province":"MD",
    "sg:tags":[
        "house"
    ],
    "wof:name":"Graystone Custom Builders",
    "wof:placetype":"venue"
},
  "geometry": {"coordinates":[-76.62677600000001,39.489034],"type":"Point"}
}