{
  "type": "Feature",
  "properties": {
    "addr:full":"833 Southern Ave Oxon Hill MD 20745",
    "addr:housenumber":"833",
    "addr:postcode":"20745",
    "addr:street":"Southern Ave",
    "iso:country":"US",
    "sg:address":"833 Southern Ave",
    "sg:city":"Oxon Hill",
    "sg:classifiers":[
        {
            "category":"Food & Beverages",
            "subcategory":"Liquor & Beverages",
            "type":"Retail Goods"
        }
    ],
    "sg:phone":"+1 301 894 6666",
    "sg:postcode":"20745",
    "sg:province":"MD",
    "sg:tags":[
        "beer",
        "spirit",
        "wine"
    ],
    "wof:name":"Earl's Super Liquor Store",
    "wof:placetype":"venue"
},
  "geometry": {"coordinates":[-76.99156499999999,38.828785],"type":"Point"}
}