{
  "type": "Feature",
  "properties": {
    "iso:country":"US",
    "sg:address":"4500 Forbes Blvd",
    "sg:city":"Lanham",
    "sg:classifiers":[
        {
            "category":"Social Services",
            "type":"Services"
        }
    ],
    "sg:phone":"+1 301 429 2370",
    "sg:postcode":"20706",
    "sg:province":"MD",
    "sg:tags":[
        "organization",
        "welfare"
    ],
    "sg:website":"www.concern4kids.org",
    "wof:name":"Concern",
    "wof:placetype":"venue"
},
  "geometry": {"coordinates":[-76.83333,38.950933],"type":"Point"}
}