{
  "type": "Feature",
  "properties": {
    "iso:country":"US",
    "sg:address":"42563 Woodbury Pl",
    "sg:city":"Leonardtown",
    "sg:classifiers":[
        {
            "category":"Building & Trades",
            "subcategory":"Cleaning & Sanitation",
            "type":"Services"
        }
    ],
    "sg:phone":"+1 301 997 1400",
    "sg:postcode":"20650",
    "sg:province":"MD",
    "sg:tags":[
        "janitor"
    ],
    "wof:name":"Deb's Commercial & Residential",
    "wof:placetype":"venue"
},
  "geometry": {"coordinates":[-76.604747,38.245444],"type":"Point"}
}