{
  "type": "Feature",
  "properties": {
    "addr:full":"9385 Washington Blvd N F Laurel MD 20723",
    "addr:housenumber":"9385",
    "addr:postcode":"20723",
    "addr:street":"Washington Blvd N F",
    "iso:country":"US",
    "sg:address":"9385 Washington Blvd N F",
    "sg:city":"Laurel",
    "sg:classifiers":[
        {
            "category":"Shopping",
            "subcategory":"Clothing, Apparel, & Fashions",
            "type":"Retail Goods"
        },
        {
            "category":"Manufacturing",
            "subcategory":"Textiles",
            "type":"Manufacturing & Wholesale Goods"
        },
        {
            "category":"Wholesale",
            "subcategory":"Apparel",
            "type":"Manufacturing & Wholesale Goods"
        },
        {
            "category":"Professional",
            "subcategory":"Printing & Photocopies",
            "type":"Services"
        }
    ],
    "sg:phone":"+1 301 497 1575",
    "sg:postcode":"20723",
    "sg:province":"MD",
    "sg:tags":[
        "clothing",
        "screen",
        "t-shirts-wholesale",
        "shirts-wholesale",
        "store",
        "manufacturer"
    ],
    "sg:website":"http://www.tastyshirt.com",
    "wof:name":"Tasty Shirt Company",
    "wof:placetype":"venue"
},
  "geometry": {"coordinates":[-76.822759,39.126256],"type":"Point"}
}