{
  "type": "Feature",
  "properties": {
    "iso:country":"US",
    "sg:address":"1019 Chromine Rd",
    "sg:city":"Reisterstown",
    "sg:classifiers":[
        {
            "category":"Building & Trades",
            "subcategory":"Construction",
            "type":"Services"
        }
    ],
    "sg:phone":"+1 410 833 3690",
    "sg:postcode":"21136",
    "sg:province":"MD",
    "sg:tags":[
        "specializing",
        "excavating",
        "paving",
        "contractor"
    ],
    "wof:name":"Lee Ensor Excavating & Paving",
    "wof:placetype":"venue"
},
  "geometry": {"coordinates":[-76.842268,39.438814],"type":"Point"}
}