{
  "type": "Feature",
  "properties": {
    "addr:full":"7761 Eastpoint Mall Baltimore MD 21224",
    "addr:housenumber":"7761",
    "addr:postcode":"21224",
    "addr:street":"Eastpoint Mall",
    "iso:country":"US",
    "sg:address":"7761 Eastpoint Mall",
    "sg:city":"Baltimore",
    "sg:classifiers":[
        {
            "category":"Shopping",
            "subcategory":"Jewelry",
            "type":"Retail Goods"
        },
        {
            "category":"Manufacturing",
            "subcategory":"Jewelry",
            "type":"Manufacturing & Wholesale Goods"
        }
    ],
    "sg:phone":"+1 410 288 5606",
    "sg:postcode":"21224",
    "sg:province":"MD",
    "sg:tags":[
        "stone",
        "designer",
        "semi-precious",
        "precious",
        "jeweler"
    ],
    "sg:website":"http://www.zales.com",
    "wof:name":"Zales Jewelers",
    "wof:placetype":"venue"
},
  "geometry": {"coordinates":[-76.51058399999999,39.293892],"type":"Point"}
}