{
  "type": "Feature",
  "properties": {
    "iso:country":"US",
    "sg:address":"2612 Monument Rd",
    "sg:city":"Myersville",
    "sg:classifiers":[
        {
            "category":"Building & Trades",
            "subcategory":"Construction",
            "type":"Services"
        }
    ],
    "sg:phone":"+1 301 293 2502",
    "sg:postcode":"21773",
    "sg:province":"MD",
    "sg:tags":[
        "general",
        "contractor"
    ],
    "wof:name":"Complete Home Svc",
    "wof:placetype":"venue"
},
  "geometry": {"coordinates":[-77.578311,39.508271],"type":"Point"}
}