{
  "type": "Feature",
  "properties": {
    "addr:full":"5000 Sunnyside Ave # 105 Beltsville MD 20705",
    "addr:housenumber":"5000",
    "addr:postcode":"20705",
    "addr:street":"Sunnyside Ave # 105",
    "iso:country":"US",
    "sg:address":"5000 Sunnyside Ave # 105",
    "sg:city":"Beltsville",
    "sg:classifiers":[
        {
            "category":"Professional",
            "subcategory":"Engineering",
            "type":"Services"
        },
        {
            "category":"Wholesale",
            "subcategory":"Computers",
            "type":"Manufacturing & Wholesale Goods"
        },
        {
            "category":"Professional",
            "subcategory":"Computer Services",
            "type":"Services"
        }
    ],
    "sg:phone":"+1 301 595 1895",
    "sg:postcode":"20705",
    "sg:province":"MD",
    "sg:tags":[
        "repair",
        "designer",
        "consultant",
        "integration",
        "system",
        "equipment",
        "equipment-service",
        "engineer"
    ],
    "sg:website":"http://www.confluent-it.com",
    "wof:name":"Kada Computer Corporation",
    "wof:placetype":"venue"
},
  "geometry": {"coordinates":[-76.91980700000001,39.026291],"type":"Point"}
}