{
  "type": "Feature",
  "properties": {
    "addr:full":"9719 Woodsboro Pike Walkersville MD 21793",
    "addr:housenumber":"9719",
    "addr:postcode":"21793",
    "addr:street":"Woodsboro Pike",
    "iso:country":"US",
    "sg:address":"9719 Woodsboro Pike",
    "sg:city":"Walkersville",
    "sg:classifiers":[
        {
            "category":"Retail",
            "subcategory":"Laundry & Dry Cleaning",
            "type":"Services"
        },
        {
            "category":"Building & Trades",
            "subcategory":"Cleaning & Sanitation",
            "type":"Services"
        }
    ],
    "sg:phone":"+1 301 898 5895",
    "sg:postcode":"21793",
    "sg:province":"MD",
    "sg:tags":[
        "cleaner",
        "window",
        "house"
    ],
    "wof:name":"Sparkle Clean Window Cleaning & Pressure Washing Service",
    "wof:placetype":"venue"
},
  "geometry": {"coordinates":[-77.327538,39.498751],"type":"Point"}
}