{
  "type": "Feature",
  "properties": {
    "addr:full":"1045 N Broadway Baltimore MD 21205",
    "addr:housenumber":"1045",
    "addr:postcode":"21205",
    "addr:street":"N Broadway",
    "iso:country":"US",
    "sg:address":"1045 N Broadway",
    "sg:city":"Baltimore",
    "sg:classifiers":[
        {
            "category":"Personal",
            "subcategory":"Beauty Salon",
            "type":"Services"
        }
    ],
    "sg:phone":"+1 443 956 2291",
    "sg:postcode":"21205",
    "sg:province":"MD",
    "sg:tags":[
        "hair",
        "stylist"
    ],
    "wof:name":"Hershey Blu Stylez",
    "wof:placetype":"venue"
},
  "geometry": {"coordinates":[-76.59437699999999,39.302135],"type":"Point"}
}