{
  "type": "Feature",
  "properties": {
    "addr:full":"321 E Cromwell St Baltimore MD 21230",
    "addr:housenumber":"321",
    "addr:postcode":"21230",
    "addr:street":"E Cromwell St",
    "iso:country":"US",
    "sg:address":"321 E Cromwell St",
    "sg:city":"Baltimore",
    "sg:classifiers":[
        {
            "category":"Autos & Motor Vehicles",
            "subcategory":"Fuel & Gas Station",
            "type":"Retail Goods"
        },
        {
            "category":"Recreation",
            "subcategory":"Marina",
            "type":"Entertainment"
        },
        {
            "category":"Autos & Motor Vehicles",
            "subcategory":"Boat Sales",
            "type":"Retail Goods"
        },
        {
            "category":"Transit Center",
            "subcategory":"Freight",
            "type":"Transportation"
        },
        {
            "category":"Marine",
            "type":"Transportation"
        }
    ],
    "sg:phone":"+1 410 625 4992",
    "sg:postcode":"21230",
    "sg:province":"MD",
    "sg:tags":[
        "repair",
        "builder",
        "fueling",
        "maintenance",
        "ship"
    ],
    "sg:website":"http://www.tysc.com",
    "wof:name":"Tidewater Yacht Service Center, Inc.",
    "wof:placetype":"venue"
},
  "geometry": {"coordinates":[-76.613136,39.262149],"type":"Point"}
}