{
  "type": "Feature",
  "properties": {
    "addr:full":"1274 Bay Dale Dr Arnold MD 21012",
    "addr:housenumber":"1274",
    "addr:postcode":"21012",
    "addr:street":"Bay Dale Dr",
    "iso:country":"US",
    "sg:address":"1274 Bay Dale Dr",
    "sg:city":"Arnold",
    "sg:classifiers":[
        {
            "category":"Restaurant",
            "type":"Food & Drink"
        }
    ],
    "sg:phone":"+1 410 757 3400",
    "sg:postcode":"21012",
    "sg:province":"MD",
    "sg:tags":[
        "pizza"
    ],
    "wof:name":"George's Restaurant & Carryout",
    "wof:placetype":"venue"
},
  "geometry": {"coordinates":[-76.47924999999999,39.03843],"type":"Point"}
}