{
  "type": "Feature",
  "properties": {
    "iso:country":"US",
    "sg:address":"10906 Old Frederick Rd",
    "sg:city":"Thurmont",
    "sg:classifiers":[
        {
            "category":"Building & Trades",
            "subcategory":"Construction",
            "type":"Services"
        }
    ],
    "sg:phone":"+1 301 898 1525",
    "sg:postcode":"21788",
    "sg:province":"MD",
    "sg:tags":[
        "masonry",
        "contractor"
    ],
    "wof:name":"James N Rhoten Masonry Contr",
    "wof:placetype":"venue"
},
  "geometry": {"coordinates":[-77.387725,39.533574],"type":"Point"}
}