{
  "type": "Feature",
  "properties": {
    "addr:full":"3541 9th St Baltimore MD 21225",
    "addr:housenumber":"3541",
    "addr:postcode":"21225",
    "addr:street":"9Th St",
    "iso:country":"US",
    "sg:address":"3541 9th St",
    "sg:city":"Baltimore",
    "sg:classifiers":[
        {
            "category":"Wholesale",
            "subcategory":"Machinery & Supplies",
            "type":"Manufacturing & Wholesale Goods"
        }
    ],
    "sg:phone":"+1 410 355 8270",
    "sg:postcode":"21225",
    "sg:province":"MD",
    "sg:tags":[
        "valve"
    ],
    "wof:name":"Atlantic Valve & Supply Co",
    "wof:placetype":"venue"
},
  "geometry": {"coordinates":[-76.59773199999999,39.234914],"type":"Point"}
}