{
  "type": "Feature",
  "properties": {
    "addr:full":"201 Benton Ave Ste 207 Linthicum Heights MD 21090",
    "addr:housenumber":"201",
    "addr:postcode":"21090",
    "addr:street":"Benton Ave Ste 207",
    "iso:country":"US",
    "sg:address":"201 Benton Ave Ste 207",
    "sg:city":"Linthicum Heights",
    "sg:classifiers":[
        {
            "category":"Communications",
            "type":"Services"
        }
    ],
    "sg:phone":"+1 410 694 3575",
    "sg:postcode":"21090",
    "sg:province":"MD",
    "sg:tags":[
        "web",
        "design"
    ],
    "sg:website":"www.hairydogdigital.com",
    "wof:name":"Hairy Dog Digital",
    "wof:placetype":"venue"
},
  "geometry": {"coordinates":[-76.64785000000001,39.201133],"type":"Point"}
}