{
  "type": "Feature",
  "properties": {
    "iso:country":"US",
    "sg:address":"309 Carroll Ave",
    "sg:city":"Laurel",
    "sg:classifiers":[
        {
            "category":"Professional",
            "type":"Services"
        }
    ],
    "sg:phone":"+1 410 985 6200",
    "sg:postcode":"20707",
    "sg:province":"MD",
    "sg:tags":[
        "establishment"
    ],
    "wof:name":"Skycache Inc",
    "wof:placetype":"venue"
},
  "geometry": {"coordinates":[-76.849549,39.101541],"type":"Point"}
}