{
  "type": "Feature",
  "properties": {
    "addr:full":"2121 Russell St Baltimore MD 21230",
    "addr:housenumber":"2121",
    "addr:postcode":"21230",
    "addr:street":"Russell St",
    "iso:country":"US",
    "sg:address":"2121 Russell St",
    "sg:city":"Baltimore",
    "sg:classifiers":[
        {
            "category":"Freight",
            "type":"Transportation"
        }
    ],
    "sg:phone":"+1 410 539 0535",
    "sg:postcode":"21230",
    "sg:province":"MD",
    "sg:tags":[
        "trucking"
    ],
    "wof:name":"Blackburn Trucking",
    "wof:placetype":"venue"
},
  "geometry": {"coordinates":[-76.63516199999999,39.265786],"type":"Point"}
}