{
  "type": "Feature",
  "properties": {
    "iso:country":"US",
    "sg:address":"9405 Livingston Rd",
    "sg:city":"Fort Washington",
    "sg:classifiers":[
        {
            "category":"Manufacturing",
            "subcategory":"Motor Vehicles & Parts",
            "type":"Manufacturing & Wholesale Goods"
        }
    ],
    "sg:phone":"+1 301 248 7100",
    "sg:postcode":"20744",
    "sg:province":"MD",
    "sg:tags":[
        "automobile",
        "supply"
    ],
    "wof:name":"Savemore Installations",
    "wof:placetype":"venue"
},
  "geometry": {"coordinates":[-76.995469,38.763872],"type":"Point"}
}