{
  "type": "Feature",
  "properties": {
    "addr:full":"3922 Five Friars Rd Salisbury MD 21804",
    "addr:housenumber":"3922",
    "addr:postcode":"21804",
    "addr:street":"Five Friars Rd",
    "iso:country":"US",
    "sg:address":"3922 Five Friars Rd",
    "sg:city":"Salisbury",
    "sg:classifiers":[
        {
            "category":"Professional",
            "subcategory":"Engineering",
            "type":"Services"
        },
        {
            "category":"Professional",
            "subcategory":"Business Services",
            "type":"Services"
        }
    ],
    "sg:phone":"+1 410 860 6680",
    "sg:postcode":"21804",
    "sg:province":"MD",
    "sg:tags":[
        "consultant",
        "consulting",
        "coach",
        "engineer"
    ],
    "wof:name":"Milt Jones & Assoc",
    "wof:placetype":"venue"
},
  "geometry": {"coordinates":[-75.57855600000001,38.300344],"type":"Point"}
}