{
  "type": "Feature",
  "properties": {
    "addr:full":"1701 Kingfisher Dr Frederick MD 21701",
    "addr:housenumber":"1701",
    "addr:postcode":"21701",
    "addr:street":"Kingfisher Dr",
    "iso:country":"US",
    "sg:address":"1701 Kingfisher Dr",
    "sg:city":"Frederick",
    "sg:classifiers":[
        {
            "category":"Banks & Credit Unions",
            "subcategory":"Bank",
            "type":"Services"
        }
    ],
    "sg:phone":"+1 301 663 1003",
    "sg:postcode":"21701",
    "sg:province":"MD",
    "sg:website":"http://www.chevychasebank.com",
    "wof:name":"Chevy Chase Bank, F.S.B.",
    "wof:placetype":"venue"
},
  "geometry": {"coordinates":[-77.383629,39.44932],"type":"Point"}
}