{
  "type": "Feature",
  "properties": {
    "addr:full":"11610 Baltimore Ave Beltsville MD 20705",
    "addr:housenumber":"11610",
    "addr:postcode":"20705",
    "addr:street":"Baltimore Ave",
    "iso:country":"US",
    "sg:address":"11610 Baltimore Ave",
    "sg:city":"Beltsville",
    "sg:classifiers":[
        {
            "category":"Building & Trades",
            "subcategory":"Plumbing",
            "type":"Services"
        }
    ],
    "sg:phone":"+1 301 725 9333",
    "sg:postcode":"20705",
    "sg:province":"MD",
    "sg:tags":[
        "conditioning",
        "air",
        "system",
        "contractor"
    ],
    "wof:name":"Beltsville Heating & AC INC",
    "wof:placetype":"venue"
},
  "geometry": {"coordinates":[-76.90232399999999,39.044816],"type":"Point"}
}