{
  "type": "Feature",
  "properties": {
    "iso:country":"US",
    "sg:address":"338 Foreland Garth",
    "sg:city":"Abingdon",
    "sg:classifiers":[
        {
            "category":"Arts & Performance",
            "subcategory":"Theater",
            "type":"Entertainment"
        }
    ],
    "sg:phone":"+1 410 569 8035",
    "sg:postcode":"21009",
    "sg:province":"MD",
    "sg:tags":[
        "live",
        "music"
    ],
    "wof:name":"Amplitude DJ",
    "wof:placetype":"venue"
},
  "geometry": {"coordinates":[-76.331632,39.466872],"type":"Point"}
}