{
  "type": "Feature",
  "properties": {
    "iso:country":"US",
    "sg:address":"101 W All Saints St",
    "sg:city":"Frederick",
    "sg:classifiers":[
        {
            "category":"Organizations",
            "subcategory":"Religious Organization",
            "type":"Services"
        }
    ],
    "sg:phone":"+1 301 663 9380",
    "sg:postcode":"21701",
    "sg:province":"MD",
    "sg:tags":[
        "church"
    ],
    "wof:name":"Asbury United Methodist Church",
    "wof:placetype":"venue"
},
  "geometry": {"coordinates":[-77.413241,39.411989],"type":"Point"}
}