{
  "type": "Feature",
  "properties": {
    "iso:country":"US",
    "sg:address":"11314 Evans Trl",
    "sg:city":"Beltsville",
    "sg:classifiers":[
        {
            "category":"Social Services",
            "subcategory":"Child Care",
            "type":"Services"
        }
    ],
    "sg:phone":"+1 301 937 4322",
    "sg:postcode":"20705",
    "sg:province":"MD",
    "sg:tags":[
        "day"
    ],
    "wof:name":"Powder Mill Early Learning Center",
    "wof:placetype":"venue"
},
  "geometry": {"coordinates":[-76.93890399999999,39.043499],"type":"Point"}
}