{
  "type": "Feature",
  "properties": {
    "iso:country":"US",
    "sg:address":"200 Saint Paul St",
    "sg:city":"Baltimore",
    "sg:classifiers":[
        {
            "category":"Government",
            "subcategory":"Court House",
            "type":"Public Place"
        },
        {
            "category":"Government",
            "subcategory":"Office",
            "type":"Public Place"
        }
    ],
    "sg:phone":"+1 410 514 7483",
    "sg:postcode":"21202",
    "sg:province":"MD",
    "sg:tags":[
        "government-state",
        "justice"
    ],
    "sg:website":"http://www.oag.state.md.us",
    "wof:name":"Maryland State Government Single Family Lending Weatherization",
    "wof:placetype":"venue"
},
  "geometry": {"coordinates":[-76.61393700000001,39.291111],"type":"Point"}
}