{
  "type": "Feature",
  "properties": {
    "iso:country":"US",
    "sg:address":"1809 E Joppa Rd",
    "sg:city":"Parkville",
    "sg:classifiers":[
        {
            "category":"Local Transit",
            "type":"Transportation"
        }
    ],
    "sg:phone":"+1 410 661 1800",
    "sg:postcode":"21234",
    "sg:province":"MD",
    "sg:tags":[
        "ambulance"
    ],
    "wof:name":"Procare Ambulance Svc",
    "wof:placetype":"venue"
},
  "geometry": {"coordinates":[-76.55392399999999,39.399367],"type":"Point"}
}