{
  "type": "Feature",
  "properties": {
    "addr:full":"711 Marion St Hagerstown MD 21740",
    "addr:housenumber":"711",
    "addr:postcode":"21740",
    "addr:street":"Marion St",
    "iso:country":"US",
    "sg:address":"711 Marion St",
    "sg:city":"Hagerstown",
    "sg:classifiers":[
        {
            "category":"Wholesale",
            "subcategory":"Stationery",
            "type":"Manufacturing & Wholesale Goods"
        }
    ],
    "sg:phone":"+1 301 416 7745",
    "sg:postcode":"21740",
    "sg:province":"MD",
    "sg:tags":[
        "business",
        "form",
        "system"
    ],
    "wof:name":"GBF",
    "wof:placetype":"venue"
},
  "geometry": {"coordinates":[-77.741983,39.624595],"type":"Point"}
}