{
  "type": "Feature",
  "properties": {
    "addr:full":"11013 Haislip Ct Potomac MD 20854",
    "addr:housenumber":"11013",
    "addr:postcode":"20854",
    "addr:street":"Haislip Ct",
    "iso:country":"US",
    "sg:address":"11013 Haislip Ct",
    "sg:city":"Potomac",
    "sg:classifiers":[
        {
            "category":"Banks & Credit Unions",
            "subcategory":"Financial Services",
            "type":"Services"
        }
    ],
    "sg:phone":"+1 301 765 6200",
    "sg:postcode":"20854",
    "sg:province":"MD",
    "sg:tags":[
        "broker",
        "mortgage"
    ],
    "wof:name":"Goldberg Joe",
    "wof:placetype":"venue"
},
  "geometry": {"coordinates":[-77.18609600000001,39.0364],"type":"Point"}
}