{
  "type": "Feature",
  "properties": {
    "addr:full":"8527 Woodfall Rd Baltimore MD 21236",
    "addr:housenumber":"8527",
    "addr:postcode":"21236",
    "addr:street":"Woodfall Rd",
    "iso:country":"US",
    "sg:address":"8527 Woodfall Rd",
    "sg:city":"Baltimore",
    "sg:classifiers":[
        {
            "category":"Professional",
            "subcategory":"Computer Services",
            "type":"Services"
        }
    ],
    "sg:phone":"+1 410 931 4822",
    "sg:postcode":"21236",
    "sg:province":"MD",
    "sg:tags":[
        "related"
    ],
    "wof:name":"Born Computing",
    "wof:placetype":"venue"
},
  "geometry": {"coordinates":[-76.465056,39.384199],"type":"Point"}
}