{
  "type": "Feature",
  "properties": {
    "addr:full":"7407 Harford Rd Baltimore MD 21234",
    "addr:housenumber":"7407",
    "addr:postcode":"21234",
    "addr:street":"Harford Rd",
    "iso:country":"US",
    "sg:address":"7407 Harford Rd",
    "sg:city":"Baltimore",
    "sg:classifiers":[
        {
            "category":"Shopping",
            "subcategory":"Computers & Home Electronics",
            "type":"Retail Goods"
        }
    ],
    "sg:phone":"+1 410 444 3730",
    "sg:postcode":"21234",
    "sg:province":"MD",
    "sg:tags":[
        "equipment",
        "dealer"
    ],
    "sg:website":"www.betterbyte.com",
    "wof:name":"Better Byte Computer Computer",
    "wof:placetype":"venue"
},
  "geometry": {"coordinates":[-76.546139,39.369878],"type":"Point"}
}