{
  "type": "Feature",
  "properties": {
    "iso:country":"US",
    "sg:address":"301 N Gilmor St",
    "sg:city":"Baltimore",
    "sg:classifiers":[
        {
            "category":"Organizations",
            "subcategory":"Religious Organization",
            "type":"Services"
        }
    ],
    "sg:phone":"+1 410 383 8591",
    "sg:postcode":"21223",
    "sg:province":"MD",
    "sg:tags":[
        "churches-pentecostal"
    ],
    "wof:name":"First Pentecostal Church - Fax Line",
    "wof:placetype":"venue"
},
  "geometry": {"coordinates":[-76.64257000000001,39.29211],"type":"Point"}
}