{
  "type": "Feature",
  "properties": {
    "addr:full":"25 Shadow Point Ct Edgewater MD 21037",
    "addr:housenumber":"25",
    "addr:postcode":"21037",
    "addr:street":"Shadow Point Ct",
    "iso:country":"US",
    "sg:address":"25 Shadow Point Ct",
    "sg:city":"Edgewater",
    "sg:classifiers":[
        {
            "category":"Professional",
            "subcategory":"Management & Consulting",
            "type":"Services"
        }
    ],
    "sg:phone":"+1 410 897 9215",
    "sg:postcode":"21037",
    "sg:province":"MD",
    "sg:tags":[
        "counselor",
        "public",
        "relations"
    ],
    "wof:name":"Hills Communications Inc",
    "wof:placetype":"venue"
},
  "geometry": {"coordinates":[-76.546052,38.955086],"type":"Point"}
}