{
  "type": "Feature",
  "properties": {
    "addr:full":"4535 Piney Church Rd Waldorf MD 20602",
    "addr:housenumber":"4535",
    "addr:postcode":"20602",
    "addr:street":"Piney Church Rd",
    "iso:country":"US",
    "sg:address":"4535 Piney Church Rd",
    "sg:city":"Waldorf",
    "sg:classifiers":[
        {
            "category":"Organizations",
            "subcategory":"Religious Organization",
            "type":"Services"
        }
    ],
    "sg:phone":"+1 301 645 5000",
    "sg:postcode":"20602",
    "sg:province":"MD",
    "sg:tags":[
        "church"
    ],
    "sg:website":"www.pineyparish.org",
    "wof:name":"St Paul's Episcopal Church",
    "wof:placetype":"venue"
},
  "geometry": {"coordinates":[-76.90002699999999,38.587792],"type":"Point"}
}