{
  "type": "Feature",
  "properties": {
    "iso:country":"US",
    "sg:address":"28 Centinal Ln",
    "sg:city":"Aberdeen",
    "sg:classifiers":[
        {
            "category":"Organizations",
            "subcategory":"Non-profit Organization",
            "type":"Services"
        }
    ],
    "sg:phone":"+1 410 272 4150",
    "sg:postcode":"21001",
    "sg:province":"MD",
    "sg:tags":[
        "social"
    ],
    "wof:name":"Aa",
    "wof:placetype":"venue"
},
  "geometry": {"coordinates":[-76.166194,39.51072],"type":"Point"}
}