{
  "type": "Feature",
  "properties": {
    "iso:country":"US",
    "sg:address":"1503 Post Oak Dr",
    "sg:city":"Bowie",
    "sg:classifiers":[
        {
            "category":"Professional",
            "subcategory":"Management & Consulting",
            "type":"Services"
        }
    ],
    "sg:phone":"+1 301 925 2468",
    "sg:postcode":"20721",
    "sg:province":"MD",
    "wof:name":"Atp Consulting",
    "wof:placetype":"venue"
},
  "geometry": {"coordinates":[-76.833321,38.910354],"type":"Point"}
}