{
  "type": "Feature",
  "properties": {
    "addr:full":"4004 Alberta Ave Pasadena MD 21122",
    "addr:housenumber":"4004",
    "addr:postcode":"21122",
    "addr:street":"Alberta Ave",
    "iso:country":"US",
    "sg:address":"4004 Alberta Ave",
    "sg:city":"Pasadena",
    "sg:classifiers":[
        {
            "category":"Building & Trades",
            "subcategory":"Plumbing",
            "type":"Services"
        }
    ],
    "sg:phone":"+1 410 255 6253",
    "sg:postcode":"21122",
    "sg:province":"MD",
    "sg:tags":[
        "septic"
    ],
    "wof:name":"Pasadena Septic Svc",
    "wof:placetype":"venue"
},
  "geometry": {"coordinates":[-76.517512,39.125253],"type":"Point"}
}