{
  "type": "Feature",
  "properties": {
    "addr:full":"1607 W North Ave Baltimore MD 21217",
    "addr:housenumber":"1607",
    "addr:postcode":"21217",
    "addr:street":"W North Ave",
    "iso:country":"US",
    "sg:address":"1607 W North Ave",
    "sg:city":"Baltimore",
    "sg:classifiers":[
        {
            "category":"Professional",
            "subcategory":"Accounting & Tax Preparation",
            "type":"Services"
        }
    ],
    "sg:phone":"+1 410 728 7314",
    "sg:postcode":"21217",
    "sg:province":"MD",
    "sg:tags":[
        "return",
        "filing"
    ],
    "wof:name":"Jackson Hewitt Tax Svc",
    "wof:placetype":"venue"
},
  "geometry": {"coordinates":[-76.64340300000001,39.309971],"type":"Point"}
}