{
  "type": "Feature",
  "properties": {
    "iso:country":"US",
    "sg:address":"720 Maiden Choice Ln",
    "sg:city":"Catonsville",
    "sg:classifiers":[
        {
            "category":"Health Services",
            "subcategory":"Doctor",
            "type":"Services"
        }
    ],
    "sg:phone":"+1 410 744 5900",
    "sg:postcode":"21228",
    "sg:province":"MD",
    "wof:name":"Seton Medical Group At Maiden Choice II",
    "wof:placetype":"venue"
},
  "geometry": {"coordinates":[-76.705101,39.2682],"type":"Point"}
}