{
  "type": "Feature",
  "properties": {
    "iso:country":"US",
    "sg:address":"2733 Waldor Dr",
    "sg:city":"Parkville",
    "sg:classifiers":[
        {
            "category":"Real Estate",
            "subcategory":"Real Estate Agent",
            "type":"Services"
        }
    ],
    "sg:phone":"+1 410 661 6962",
    "sg:postcode":"21234",
    "sg:province":"MD",
    "sg:tags":[
        "inspection"
    ],
    "wof:name":"Abode Home Inspections",
    "wof:placetype":"venue"
},
  "geometry": {"coordinates":[-76.52413,39.413542],"type":"Point"}
}