{
  "type": "Feature",
  "properties": {
    "addr:full":"10155 New Hampshire Ave Silver Spring MD 20903",
    "addr:housenumber":"10155",
    "addr:postcode":"20903",
    "addr:street":"New Hampshire Ave",
    "iso:country":"US",
    "sg:address":"10155 New Hampshire Ave",
    "sg:city":"Silver Spring",
    "sg:classifiers":[
        {
            "category":"Shopping",
            "subcategory":"Florist",
            "type":"Retail Goods"
        }
    ],
    "sg:phone":"+1 301 439 5200",
    "sg:postcode":"20903",
    "sg:province":"MD",
    "sg:website":"www.parkflorists.com",
    "wof:name":"Park Florist",
    "wof:placetype":"venue"
},
  "geometry": {"coordinates":[-76.977345,39.0222],"type":"Point"}
}