{
  "type": "Feature",
  "properties": {
    "iso:country":"US",
    "sg:address":"11753 Chesterville Rd",
    "sg:city":"Kennedyville",
    "sg:classifiers":[
        {
            "category":"Deli",
            "type":"Food & Drink"
        },
        {
            "category":"Restaurant",
            "type":"Food & Drink"
        },
        {
            "category":"Food & Beverages",
            "subcategory":"Groceries & Convenience Stores",
            "type":"Retail Goods"
        }
    ],
    "sg:phone":"+1 410 778 0507",
    "sg:postcode":"21645",
    "sg:province":"MD",
    "sg:tags":[
        "delicatessen"
    ],
    "wof:name":"Dutch Family Deli",
    "wof:placetype":"venue"
},
  "geometry": {"coordinates":[-75.90463099999999,39.294584],"type":"Point"}
}