{
  "type": "Feature",
  "properties": {
    "addr:full":"33594 Dublin Rd Princess Anne MD 21853",
    "addr:housenumber":"33594",
    "addr:postcode":"21853",
    "addr:street":"Dublin Rd",
    "iso:country":"US",
    "sg:address":"33594 Dublin Rd",
    "sg:city":"Princess Anne",
    "sg:classifiers":[
        {
            "category":"Restaurant",
            "type":"Food & Drink"
        }
    ],
    "sg:phone":"+1 410 957 6518",
    "sg:postcode":"21853",
    "sg:province":"MD",
    "wof:name":"Buck's",
    "wof:placetype":"venue"
},
  "geometry": {"coordinates":[-75.585781,38.150924],"type":"Point"}
}