{
  "type": "Feature",
  "properties": {
    "iso:country":"US",
    "sg:address":"38 W Wilson Blvd",
    "sg:city":"Hagerstown",
    "sg:classifiers":[
        {
            "category":"Retail",
            "subcategory":"Repair Shop",
            "type":"Services"
        }
    ],
    "sg:phone":"+1 301 739 7954",
    "sg:postcode":"21740",
    "sg:province":"MD",
    "sg:tags":[
        "repairing",
        "lawn",
        "mower"
    ],
    "wof:name":"G & P Engine Repair",
    "wof:placetype":"venue"
},
  "geometry": {"coordinates":[-77.729071,39.624616],"type":"Point"}
}