{
  "type": "Feature",
  "properties": {
    "iso:country":"US",
    "sg:address":"8820 Howard Forest Ln",
    "sg:city":"Baltimore",
    "sg:classifiers":[
        {
            "category":"Insurance",
            "subcategory":"Insurance Agent",
            "type":"Services"
        }
    ],
    "sg:phone":"+1 410 526 0004",
    "sg:postcode":"21208",
    "sg:province":"MD",
    "wof:name":"LTCI Consulting Group Inc",
    "wof:placetype":"venue"
},
  "geometry": {"coordinates":[-76.738178,39.39152],"type":"Point"}
}