{
  "type": "Feature",
  "properties": {
    "addr:full":"10332 Royal Woods Ct Montgomery Village MD 20886",
    "addr:housenumber":"10332",
    "addr:postcode":"20886",
    "addr:street":"Royal Woods Ct",
    "iso:country":"US",
    "sg:address":"10332 Royal Woods Ct",
    "sg:city":"Montgomery Village",
    "sg:classifiers":[
        {
            "category":"Communications",
            "subcategory":"Film & Video Production",
            "type":"Services"
        }
    ],
    "sg:phone":"+1 301 977 1915",
    "sg:postcode":"20886",
    "sg:province":"MD",
    "sg:tags":[
        "sound",
        "producer"
    ],
    "wof:name":"Fergei Moskjlev",
    "wof:placetype":"venue"
},
  "geometry": {"coordinates":[-77.214326,39.179271],"type":"Point"}
}