{
  "type": "Feature",
  "properties": {
    "addr:full":"4701 Sangamore Rd Ste N270 Bethesda MD 20816",
    "addr:housenumber":"4701",
    "addr:postcode":"20816",
    "addr:street":"Sangamore Rd Ste N270",
    "iso:country":"US",
    "sg:address":"4701 Sangamore Rd Ste N270",
    "sg:city":"Bethesda",
    "sg:classifiers":[
        {
            "category":"Communications",
            "subcategory":"Newspaper",
            "type":"Services"
        }
    ],
    "sg:phone":"+1 301 320 2321",
    "sg:postcode":"20816",
    "sg:province":"MD",
    "sg:tags":[
        "print",
        "medium"
    ],
    "sg:website":"www.washingtonparent.com",
    "wof:name":"Washington Parent",
    "wof:placetype":"venue"
},
  "geometry": {"coordinates":[-77.11509700000001,38.958401],"type":"Point"}
}