{
  "type": "Feature",
  "properties": {
    "addr:full":"513 Carlsbad Ct Halethorpe MD 21227",
    "addr:housenumber":"513",
    "addr:postcode":"21227",
    "addr:street":"Carlsbad Ct",
    "iso:country":"US",
    "sg:address":"513 Carlsbad Ct",
    "sg:city":"Halethorpe",
    "sg:classifiers":[
        {
            "category":"Retail",
            "subcategory":"Repair Shop",
            "type":"Services"
        }
    ],
    "sg:phone":"+1 410 737 4717",
    "sg:postcode":"21227",
    "sg:province":"MD",
    "sg:tags":[
        "repairing",
        "organs"
    ],
    "wof:name":"Maryland Organ Svc",
    "wof:placetype":"venue"
},
  "geometry": {"coordinates":[-76.652427,39.23632],"type":"Point"}
}