{
  "type": "Feature",
  "properties": {
    "addr:full":"1116 Ct Revere Odenton MD 21113",
    "addr:postcode":"1116 ct;21113",
    "iso:country":"US",
    "sg:address":"1116 Ct Revere",
    "sg:city":"Odenton",
    "sg:classifiers":[
        {
            "category":"Organizations",
            "subcategory":"Religious Organization",
            "type":"Services"
        }
    ],
    "sg:phone":"+1 410 672 3698",
    "sg:postcode":"21113",
    "sg:province":"MD",
    "sg:tags":[
        "clergy"
    ],
    "wof:name":"Edward Regensburg",
    "wof:placetype":"venue"
},
  "geometry": {"coordinates":[-76.684939,39.074521],"type":"Point"}
}