{
  "type": "Feature",
  "properties": {
    "addr:full":"5221 Monroe Pl Hyattsville MD 20781",
    "addr:housenumber":"5221",
    "addr:postcode":"20781",
    "addr:street":"Monroe Pl",
    "iso:country":"US",
    "sg:address":"5221 Monroe Pl",
    "sg:city":"Hyattsville",
    "sg:classifiers":[
        {
            "category":"Manufacturing",
            "subcategory":"Printing",
            "type":"Manufacturing & Wholesale Goods"
        }
    ],
    "sg:phone":"+1 301 277 8836",
    "sg:postcode":"20781",
    "sg:province":"MD",
    "sg:tags":[
        "printer"
    ],
    "wof:name":"Homart Press & Envelope Co",
    "wof:placetype":"venue"
},
  "geometry": {"coordinates":[-76.928387,38.933875],"type":"Point"}
}