{
  "type": "Feature",
  "properties": {
    "addr:full":"1504 Sherbrook Rd Lutherville MD 21093",
    "addr:housenumber":"1504",
    "addr:postcode":"21093",
    "addr:street":"Sherbrook Rd",
    "iso:country":"US",
    "sg:address":"1504 Sherbrook Rd",
    "sg:city":"Lutherville",
    "sg:classifiers":[
        {
            "category":"Real Estate",
            "subcategory":"Real Estate Agent",
            "type":"Services"
        }
    ],
    "sg:phone":"+1 410 825 9292",
    "sg:postcode":"21093",
    "sg:province":"MD",
    "wof:name":"Manley F Gately & Assoc",
    "wof:placetype":"venue"
},
  "geometry": {"coordinates":[-76.60153099999999,39.427054],"type":"Point"}
}