{
  "type": "Feature",
  "properties": {
    "iso:country":"US",
    "sg:address":"7910 Mrtn Lthr Kng Jr Hwy",
    "sg:city":"Lanham",
    "sg:classifiers":[
        {
            "category":"Food & Beverages",
            "subcategory":"Liquor & Beverages",
            "type":"Retail Goods"
        }
    ],
    "sg:phone":"+1 301 773 2522",
    "sg:postcode":"20706",
    "sg:province":"MD",
    "sg:tags":[
        "beer",
        "spirit",
        "wine"
    ],
    "wof:name":"A-1 Liquor and Restaurant",
    "wof:placetype":"venue"
},
  "geometry": {"coordinates":[-76.871002,38.930099],"type":"Point"}
}