{
  "type": "Feature",
  "properties": {
    "iso:country":"US",
    "sg:address":"801 E Pulaski Hwy",
    "sg:city":"Elkton",
    "sg:classifiers":[
        {
            "category":"Shopping",
            "subcategory":"Department Store",
            "type":"Retail Goods"
        }
    ],
    "sg:phone":"+1 410 398 5477",
    "sg:postcode":"21921",
    "sg:province":"MD",
    "sg:tags":[
        "shop"
    ],
    "wof:name":"Dollar General",
    "wof:placetype":"venue"
},
  "geometry": {"coordinates":[-75.79916799999999,39.602647],"type":"Point"}
}