{
  "type": "Feature",
  "properties": {
    "addr:full":"8767 Piney Orchard Pkwy Odenton MD 21113",
    "addr:housenumber":"8767",
    "addr:postcode":"21113",
    "addr:street":"Piney Orchard Pkwy",
    "iso:country":"US",
    "sg:address":"8767 Piney Orchard Pkwy",
    "sg:city":"Odenton",
    "sg:classifiers":[
        {
            "category":"Personal",
            "subcategory":"Nail Salon",
            "type":"Services"
        }
    ],
    "sg:phone":"+1 410 695 0810",
    "sg:postcode":"21113",
    "sg:province":"MD",
    "wof:name":"Top Nails",
    "wof:placetype":"venue"
},
  "geometry": {"coordinates":[-76.721842,39.065185],"type":"Point"}
}