{
  "type": "Feature",
  "properties": {
    "addr:full":"1610 Abbotston St Baltimore MD 21218",
    "addr:housenumber":"1610",
    "addr:postcode":"21218",
    "addr:street":"Abbotston St",
    "iso:country":"US",
    "sg:address":"1610 Abbotston St",
    "sg:city":"Baltimore",
    "sg:classifiers":[
        {
            "category":"Food & Beverages",
            "subcategory":"Groceries & Convenience Stores",
            "type":"Retail Goods"
        }
    ],
    "sg:phone":"+1 410 243 4246",
    "sg:postcode":"21218",
    "sg:province":"MD",
    "wof:name":"Yom Food Market",
    "wof:placetype":"venue"
},
  "geometry": {"coordinates":[-76.59410099999999,39.322601],"type":"Point"}
}