{
  "type": "Feature",
  "properties": {
    "addr:full":"9160 Red Branch Rd Columbia MD 21045",
    "addr:housenumber":"9160",
    "addr:postcode":"21045",
    "addr:street":"Red Branch Rd",
    "iso:country":"US",
    "sg:address":"9160 Red Branch Rd",
    "sg:city":"Columbia",
    "sg:classifiers":[
        {
            "category":"Sports & Exercise",
            "subcategory":"Gym",
            "type":"Entertainment"
        }
    ],
    "sg:phone":"+1 410 730 5930",
    "sg:postcode":"21045",
    "sg:province":"MD",
    "sg:tags":[
        "club",
        "health",
        "studio",
        "gymnasium"
    ],
    "wof:name":"Golds Gym",
    "wof:placetype":"venue"
},
  "geometry": {"coordinates":[-76.819394,39.23141],"type":"Point"}
}