{
  "type": "Feature",
  "properties": {
    "iso:country":"US",
    "sg:address":"10921 Falls Rd",
    "sg:city":"Lutherville",
    "sg:classifiers":[
        {
            "category":"Shopping",
            "subcategory":"Florist",
            "type":"Retail Goods"
        }
    ],
    "sg:phone":"+1 410 825 4900",
    "sg:postcode":"21093",
    "sg:province":"MD",
    "wof:name":"Marlow-Mc Crystle & Jones",
    "wof:placetype":"venue"
},
  "geometry": {"coordinates":[-76.66994099999999,39.420035],"type":"Point"}
}