{
  "type": "Feature",
  "properties": {
    "iso:country":"US",
    "sg:address":"10568 Cliff Rd",
    "sg:city":"Chestertown",
    "sg:classifiers":[
        {
            "category":"Travel",
            "subcategory":"Hotels & Motels",
            "type":"Entertainment"
        }
    ],
    "sg:phone":"+1 410 778 5943",
    "sg:postcode":"21620",
    "sg:province":"MD",
    "sg:tags":[
        "breakfast",
        "accommodation",
        "bed"
    ],
    "sg:website":"www.greatoak.com",
    "wof:name":"Great Oak Manor B & B",
    "wof:placetype":"venue"
},
  "geometry": {"coordinates":[-76.201315,39.271347],"type":"Point"}
}