{
  "type": "Feature",
  "properties": {
    "iso:country":"US",
    "sg:address":"19907 Lonaconing St",
    "sg:city":"Midland",
    "sg:classifiers":[
        {
            "category":"Building & Trades",
            "subcategory":"Construction",
            "type":"Services"
        }
    ],
    "sg:phone":"+1 301 463 3154",
    "sg:postcode":"21542",
    "sg:province":"MD",
    "sg:tags":[
        "painter"
    ],
    "wof:name":"Daniel Booth Painting",
    "wof:placetype":"venue"
},
  "geometry": {"coordinates":[-78.950576,39.589127],"type":"Point"}
}