{
  "type": "Feature",
  "properties": {
    "iso:country":"US",
    "sg:address":"32 Village Sq",
    "sg:city":"Baltimore",
    "sg:classifiers":[
        {
            "category":"Shopping",
            "subcategory":"Optician",
            "type":"Retail Goods"
        },
        {
            "category":"Health Services",
            "subcategory":"Optometrist",
            "type":"Services"
        }
    ],
    "sg:phone":"+1 410 532 9046",
    "sg:postcode":"21210",
    "sg:province":"MD",
    "sg:tags":[
        "optical"
    ],
    "sg:website":"http://www.bowersandsnyder.com",
    "wof:name":"Bowers & Snyder",
    "wof:placetype":"venue"
},
  "geometry": {"coordinates":[-76.645444,39.356242],"type":"Point"}
}