{
  "type": "Feature",
  "properties": {
    "iso:country":"US",
    "sg:address":"15850 Crabbs Branch Way",
    "sg:city":"Rockville",
    "sg:classifiers":[
        {
            "category":"Professional",
            "subcategory":"Lawyer & Legal Services",
            "type":"Services"
        }
    ],
    "sg:phone":"+1 301 948 1177",
    "sg:postcode":"20855",
    "sg:province":"MD",
    "sg:tags":[
        "attorney"
    ],
    "sg:website":"www.lawyers.com",
    "wof:name":"Gavett & Datt",
    "wof:placetype":"venue"
},
  "geometry": {"coordinates":[-77.156961,39.113621],"type":"Point"}
}