{
  "type": "Feature",
  "properties": {
    "addr:full":"113 E Patrick St Frederick MD 21701",
    "addr:housenumber":"113",
    "addr:postcode":"21701",
    "addr:street":"E Patrick St",
    "iso:country":"US",
    "sg:address":"113 E Patrick St",
    "sg:city":"Frederick",
    "sg:classifiers":[
        {
            "category":"Shopping",
            "subcategory":"Gifts & Souvenirs",
            "type":"Retail Goods"
        }
    ],
    "sg:phone":"+1 301 631 0096",
    "sg:postcode":"21701",
    "sg:province":"MD",
    "sg:tags":[
        "shop"
    ],
    "wof:name":"Rivers Edge",
    "wof:placetype":"venue"
},
  "geometry": {"coordinates":[-77.40892700000001,39.414126],"type":"Point"}
}