{
  "type": "Feature",
  "properties": {
    "iso:country":"US",
    "sg:address":"1275 W Patrick St",
    "sg:city":"Frederick",
    "sg:classifiers":[
        {
            "category":"Retail",
            "subcategory":"Animal Services",
            "type":"Services"
        }
    ],
    "sg:phone":"+1 301 631 9010",
    "sg:postcode":"21702",
    "sg:province":"MD",
    "sg:tags":[
        "pet",
        "grooming"
    ],
    "wof:name":"Superpetz",
    "wof:placetype":"venue"
},
  "geometry": {"coordinates":[-77.452791,39.418725],"type":"Point"}
}