{
  "type": "Feature",
  "properties": {
    "iso:country":"US",
    "sg:address":"7900 Wisconsin Ave",
    "sg:city":"Bethesda",
    "sg:classifiers":[
        {
            "category":"Professional",
            "subcategory":"Management & Consulting",
            "type":"Services"
        }
    ],
    "sg:phone":"+1 301 657 3065",
    "sg:postcode":"20814",
    "sg:province":"MD",
    "sg:tags":[
        "marketing",
        "consultant"
    ],
    "sg:website":"www.wacel.org",
    "wof:name":"Cohn Communications",
    "wof:placetype":"venue"
},
  "geometry": {"coordinates":[-77.09554199999999,38.99055],"type":"Point"}
}