{
  "type": "Feature",
  "properties": {
    "iso:country":"US",
    "sg:address":"10201 Martin Luther King Jr Hwy",
    "sg:city":"Bowie",
    "sg:classifiers":[
        {
            "category":"Building & Trades",
            "subcategory":"Locksmith",
            "type":"Services"
        }
    ],
    "sg:phone":"+1 301 955 0035",
    "sg:postcode":"20720",
    "sg:province":"MD",
    "sg:tags":[
        "key"
    ],
    "wof:name":"Locksmith 0 1 24 Hr Available A",
    "wof:placetype":"venue"
},
  "geometry": {"coordinates":[-76.82763,38.955823],"type":"Point"}
}