{
  "type": "Feature",
  "properties": {
    "iso:country":"US",
    "sg:address":"38446 Barbara Ct",
    "sg:city":"Mechanicsville",
    "sg:classifiers":[
        {
            "category":"Building & Trades",
            "subcategory":"Construction",
            "type":"Services"
        }
    ],
    "sg:phone":"+1 301 884 7143",
    "sg:postcode":"20659",
    "sg:province":"MD",
    "sg:tags":[
        "nonresidential"
    ],
    "wof:name":"Cg Contractors",
    "wof:placetype":"venue"
},
  "geometry": {"coordinates":[-76.747786,38.467848],"type":"Point"}
}