{
  "type": "Feature",
  "properties": {
    "iso:country":"US",
    "sg:address":"401 Prince Georges Blvd",
    "sg:city":"Upper Marlboro",
    "sg:classifiers":[
        {
            "category":"Organizations",
            "subcategory":"Religious Organization",
            "type":"Services"
        }
    ],
    "sg:phone":"+1 301 218 7521",
    "sg:postcode":"20774",
    "sg:province":"MD",
    "sg:tags":[
        "church"
    ],
    "wof:name":"Beyond The Veil Worship Ctr",
    "wof:placetype":"venue"
},
  "geometry": {"coordinates":[-76.725916,38.884451],"type":"Point"}
}