{
  "type": "Feature",
  "properties": {
    "addr:full":"2815 Atlanta Dr Silver Spring MD 20906",
    "addr:housenumber":"2815",
    "addr:postcode":"20906",
    "addr:street":"Atlanta Dr",
    "iso:country":"US",
    "sg:address":"2815 Atlanta Dr",
    "sg:city":"Silver Spring",
    "sg:classifiers":[
        {
            "category":"Retail",
            "subcategory":"Repair Shop",
            "type":"Services"
        }
    ],
    "sg:phone":"+1 301 933 0722",
    "sg:postcode":"20906",
    "sg:province":"MD",
    "sg:tags":[
        "lock",
        "locksmith"
    ],
    "wof:name":"Carlos Lock & Saafe",
    "wof:placetype":"venue"
},
  "geometry": {"coordinates":[-77.055734,39.066241],"type":"Point"}
}