{
  "type": "Feature",
  "properties": {
    "iso:country":"US",
    "sg:address":"223 E Patapsco Ave",
    "sg:city":"Brooklyn",
    "sg:classifiers":[
        {
            "category":"Professional",
            "subcategory":"Lawyer & Legal Services",
            "type":"Services"
        }
    ],
    "sg:phone":"+1 410 354 3120",
    "sg:postcode":"21225",
    "sg:province":"MD",
    "wof:name":"Miller Albert M",
    "wof:placetype":"venue"
},
  "geometry": {"coordinates":[-76.607399,39.237999],"type":"Point"}
}