{
  "type": "Feature",
  "properties": {
    "iso:country":"US",
    "sg:address":"2103 N. Charles St.",
    "sg:city":"Baltimore",
    "sg:classifiers":[
        {
            "category":"Shopping",
            "subcategory":"Beauty & Cosmetics",
            "type":"Retail Goods"
        },
        {
            "category":"Restaurant",
            "type":"Food & Drink"
        }
    ],
    "sg:phone":"+1 410 343 7020",
    "sg:postcode":"21218",
    "sg:province":"MD",
    "sg:tags":[
        "flavor",
        "local",
        "supply"
    ],
    "sg:website":"exittheapple.com/",
    "wof:name":"Exittheapple",
    "wof:placetype":"venue"
},
  "geometry": {"coordinates":[-76.61647499999999,39.31341],"type":"Point"}
}