{
  "type": "Feature",
  "properties": {
    "addr:full":"7833 Walker Dr Greenbelt MD 20770",
    "addr:housenumber":"7833",
    "addr:postcode":"20770",
    "addr:street":"Walker Dr",
    "iso:country":"US",
    "sg:address":"7833 Walker Dr",
    "sg:city":"Greenbelt",
    "sg:classifiers":[
        {
            "category":"Banks & Credit Unions",
            "subcategory":"Bank",
            "type":"Services"
        }
    ],
    "sg:phone":"+1 301 614 0820",
    "sg:postcode":"20770",
    "sg:province":"MD",
    "sg:tags":[
        "loan",
        "real estate"
    ],
    "wof:name":"Aames Home Loan",
    "wof:placetype":"venue"
},
  "geometry": {"coordinates":[-76.894997,38.997935],"type":"Point"}
}