{
  "type": "Feature",
  "properties": {
    "addr:full":"635 Erie St Havre De Grace MD 21078",
    "addr:housenumber":"635",
    "addr:postcode":"21078",
    "addr:street":"Erie St",
    "iso:country":"US",
    "sg:address":"635 Erie St",
    "sg:city":"Havre De Grace",
    "sg:classifiers":[
        {
            "category":"Retail",
            "subcategory":"Auto Repair",
            "type":"Services"
        }
    ],
    "sg:phone":"+1 410 939 0448",
    "sg:postcode":"21078",
    "sg:province":"MD",
    "sg:tags":[
        "repairing",
        "automobile"
    ],
    "wof:name":"Susquehanna Auto Clinic",
    "wof:placetype":"venue"
},
  "geometry": {"coordinates":[-76.09395000000001,39.555262],"type":"Point"}
}