{
  "type": "Feature",
  "properties": {
    "iso:country":"US",
    "sg:address":"188 Wicomico Dr",
    "sg:city":"New Market",
    "sg:classifiers":[
        {
            "category":"Shopping",
            "type":"Retail Goods"
        }
    ],
    "sg:phone":"+1 301 865 2711",
    "sg:postcode":"21774",
    "sg:province":"MD",
    "sg:tags":[
        "craft",
        "gallery",
        "dealer"
    ],
    "wof:name":"Craftiques Stencil Studio",
    "wof:placetype":"venue"
},
  "geometry": {"coordinates":[-77.283851,39.385857],"type":"Point"}
}