{
  "type": "Feature",
  "properties": {
    "iso:country":"US",
    "sg:address":"2425 Eutaw Pl",
    "sg:city":"Baltimore",
    "sg:classifiers":[
        {
            "category":"Health Services",
            "subcategory":"Doctor",
            "type":"Services"
        }
    ],
    "sg:phone":"+1 410 728 6900",
    "sg:postcode":"21217",
    "sg:province":"MD",
    "sg:tags":[
        "clinic"
    ],
    "wof:name":"Eutaw Medical Walkin Clinic",
    "wof:placetype":"venue"
},
  "geometry": {"coordinates":[-76.637552,39.31418],"type":"Point"}
}