{
  "type": "Feature",
  "properties": {
    "addr:full":"1850 Old New Windsor Pike New Windsor MD 21776",
    "addr:housenumber":"1850",
    "addr:postcode":"21776",
    "addr:street":"Old New Windsor Pike",
    "iso:country":"US",
    "sg:address":"1850 Old New Windsor Pike",
    "sg:city":"New Windsor",
    "sg:classifiers":[
        {
            "category":"Organizations",
            "subcategory":"Religious Organization",
            "type":"Services"
        }
    ],
    "sg:phone":"+1 410 635 2019",
    "sg:postcode":"21776",
    "sg:province":"MD",
    "sg:tags":[
        "clergy"
    ],
    "wof:name":"Fred P Eckhardt",
    "wof:placetype":"venue"
},
  "geometry": {"coordinates":[-77.058778,39.553065],"type":"Point"}
}