{
  "type": "Feature",
  "properties": {
    "iso:country":"US",
    "sg:address":"1002 Auckland Way",
    "sg:city":"Chester",
    "sg:classifiers":[
        {
            "category":"Professional",
            "subcategory":"Business Services",
            "type":"Services"
        }
    ],
    "sg:phone":"+1 410 640 0059",
    "sg:postcode":"21619",
    "sg:province":"MD",
    "sg:tags":[
        "organizing",
        "services-household"
    ],
    "wof:name":"H And W Mgmt Services",
    "wof:placetype":"venue"
},
  "geometry": {"coordinates":[-76.283794,38.988479],"type":"Point"}
}