{
  "type": "Feature",
  "properties": {
    "iso:country":"US",
    "sg:address":"1 South St Suite 2200",
    "sg:city":"Baltimore",
    "sg:classifiers":[
        {
            "category":"Professional",
            "subcategory":"Lawyer & Legal Services",
            "type":"Services"
        },
        {
            "category":"Banks & Credit Unions",
            "subcategory":"Financial Services",
            "type":"Services"
        }
    ],
    "sg:phone":"+1 410 752 5830",
    "sg:postcode":"21202",
    "sg:province":"MD",
    "sg:tags":[
        "attorney",
        "practice",
        "tax",
        "law",
        "bankruptcy"
    ],
    "wof:name":"Nord Michael D",
    "wof:placetype":"venue"
},
  "geometry": {"coordinates":[-76.61096999999999,39.289688],"type":"Point"}
}