{
  "type": "Feature",
  "properties": {
    "addr:full":"1631 Opossumtown Pike Frederick MD 21702",
    "addr:housenumber":"1631",
    "addr:postcode":"21702",
    "addr:street":"Opossumtown Pike",
    "iso:country":"US",
    "sg:address":"1631 Opossumtown Pike",
    "sg:city":"Frederick",
    "sg:classifiers":[
        {
            "category":"Organizations",
            "subcategory":"Religious Organization",
            "type":"Services"
        }
    ],
    "sg:phone":"+1 301 663 1199",
    "sg:postcode":"21702",
    "sg:province":"MD",
    "sg:tags":[
        "church"
    ],
    "wof:name":"Frederick Alliance Church",
    "wof:placetype":"venue"
},
  "geometry": {"coordinates":[-77.41085699999999,39.442015],"type":"Point"}
}