{
  "type": "Feature",
  "properties": {
    "iso:country":"US",
    "sg:address":"238 Watts Branch Pkwy",
    "sg:city":"Rockville",
    "sg:classifiers":[
        {
            "category":"Professional",
            "subcategory":"Art Services",
            "type":"Services"
        }
    ],
    "sg:phone":"+1 301 424 0652",
    "sg:postcode":"20850",
    "sg:province":"MD",
    "sg:tags":[
        "graphic",
        "designer"
    ],
    "wof:name":"Lan Dam Design Works",
    "wof:placetype":"venue"
},
  "geometry": {"coordinates":[-77.17356,39.083419],"type":"Point"}
}