{
  "type": "Feature",
  "properties": {
    "addr:full":"7280 Candleshine Ct Columbia MD 21045",
    "addr:housenumber":"7280",
    "addr:postcode":"21045",
    "addr:street":"Candleshine Ct",
    "iso:country":"US",
    "sg:address":"7280 Candleshine Ct",
    "sg:city":"Columbia",
    "sg:classifiers":[
        {
            "category":"Personal",
            "subcategory":"Beauty Salon",
            "type":"Services"
        }
    ],
    "sg:phone":"+1 410 381 8300",
    "sg:postcode":"21045",
    "sg:province":"MD",
    "sg:tags":[
        "aromatherapy"
    ],
    "wof:name":"Zobiana Aromatherapy",
    "wof:placetype":"venue"
},
  "geometry": {"coordinates":[-76.845518,39.180601],"type":"Point"}
}