{
  "type": "Feature",
  "properties": {
    "addr:full":"18556 Office Park Dr Gaithersburg MD 20886",
    "addr:housenumber":"18556",
    "addr:postcode":"20886",
    "addr:street":"Office Park Dr",
    "iso:country":"US",
    "sg:address":"18556 Office Park Dr",
    "sg:city":"Gaithersburg",
    "sg:classifiers":[
        {
            "category":"Professional",
            "type":"Services"
        }
    ],
    "sg:phone":"+1 301 330 6300",
    "sg:postcode":"20886",
    "sg:province":"MD",
    "sg:tags":[
        "establishment"
    ],
    "wof:name":"IFG Network Securites Inc",
    "wof:placetype":"venue"
},
  "geometry": {"coordinates":[-77.203452,39.161997],"type":"Point"}
}