{
  "type": "Feature",
  "properties": {
    "addr:full":"18734 Walkers Choice Rd Gaithersburg MD 20886",
    "addr:housenumber":"18734",
    "addr:postcode":"20886",
    "addr:street":"Walkers Choice Rd",
    "iso:country":"US",
    "sg:address":"18734 Walkers Choice Rd",
    "sg:city":"Gaithersburg",
    "sg:classifiers":[
        {
            "category":"Retail",
            "subcategory":"Laundry & Dry Cleaning",
            "type":"Services"
        }
    ],
    "sg:phone":"+1 301 890 7442",
    "sg:postcode":"20886",
    "sg:province":"MD",
    "sg:tags":[
        "cleaners",
        "rug",
        "carpet"
    ],
    "wof:name":"Express Superdry",
    "wof:placetype":"venue"
},
  "geometry": {"coordinates":[-77.20446699999999,39.163565],"type":"Point"}
}