{
  "type": "Feature",
  "properties": {
    "addr:full":"11101 Pulaski Hwy White Marsh MD 21162",
    "addr:housenumber":"11101",
    "addr:postcode":"21162",
    "addr:street":"Pulaski Hwy",
    "iso:country":"US",
    "sg:address":"11101 Pulaski Hwy",
    "sg:city":"White Marsh",
    "sg:classifiers":[
        {
            "category":"Building & Trades",
            "subcategory":"Construction",
            "type":"Services"
        }
    ],
    "sg:phone":"+1 410 335 4095",
    "sg:postcode":"21162",
    "sg:province":"MD",
    "sg:tags":[
        "contractor"
    ],
    "sg:website":"www.creativedeckdesigns.com",
    "wof:name":"Creative Deck Designs",
    "wof:placetype":"venue"
},
  "geometry": {"coordinates":[-76.420536,39.3852],"type":"Point"}
}