{
  "type": "Feature",
  "properties": {
    "addr:full":"1002 Smoke Tree Rd Pikesville MD 21208",
    "addr:housenumber":"1002",
    "addr:postcode":"21208",
    "addr:street":"Smoke Tree Rd",
    "iso:country":"US",
    "sg:address":"1002 Smoke Tree Rd",
    "sg:city":"Pikesville",
    "sg:classifiers":[
        {
            "category":"Organizations",
            "subcategory":"Religious Organization",
            "type":"Services"
        }
    ],
    "sg:phone":"+1 410 580 0257",
    "sg:postcode":"21208",
    "sg:province":"MD",
    "sg:tags":[
        "rabbi"
    ],
    "wof:name":"Zvi Teichman",
    "wof:placetype":"venue"
},
  "geometry": {"coordinates":[-76.74573100000001,39.367941],"type":"Point"}
}