{
  "type": "Feature",
  "properties": {
    "iso:country":"US",
    "sg:address":"1002 Smoke Tree Rd",
    "sg:city":"Pikesville",
    "sg:classifiers":[
        {
            "category":"Organizations",
            "subcategory":"Religious Organization",
            "type":"Services"
        }
    ],
    "sg:phone":"+1 410 580 0257",
    "sg:postcode":"21208",
    "sg:province":"MD",
    "sg:tags":[
        "rabbi"
    ],
    "wof:name":"Zvi Teichman",
    "wof:placetype":"venue"
},
  "geometry": {"coordinates":[-76.745731,39.367941],"type":"Point"}
}