{
  "type": "Feature",
  "properties": {
    "addr:full":"13153 Loretta Rd Princess Anne MD 21853",
    "addr:housenumber":"13153",
    "addr:postcode":"21853",
    "addr:street":"Loretta Rd",
    "iso:country":"US",
    "sg:address":"13153 Loretta Rd",
    "sg:city":"Princess Anne",
    "sg:classifiers":[
        {
            "category":"Organizations",
            "subcategory":"Religious Organization",
            "type":"Services"
        }
    ],
    "sg:phone":"+1 410 651 0042",
    "sg:postcode":"21853",
    "sg:province":"MD",
    "sg:tags":[
        "church"
    ],
    "wof:name":"Supreme Council-House Of Jacob",
    "wof:placetype":"venue"
},
  "geometry": {"coordinates":[-75.67456900000001,38.2429],"type":"Point"}
}