{
  "type": "Feature",
  "properties": {
    "addr:full":"6511 Solomons Island Rd N Sunderland MD 20689",
    "addr:housenumber":"6511",
    "addr:postcode":"20689",
    "addr:street":"Solomons Island Rd N",
    "iso:country":"US",
    "sg:address":"6511 Solomons Island Rd N",
    "sg:city":"Sunderland",
    "sg:classifiers":[
        {
            "category":"Retail",
            "subcategory":"Auto Repair",
            "type":"Services"
        }
    ],
    "sg:phone":"+1 301 855 7067",
    "sg:postcode":"20689",
    "sg:province":"MD",
    "sg:tags":[
        "repairing",
        "automobile"
    ],
    "wof:name":"J C Autobody",
    "wof:placetype":"venue"
},
  "geometry": {"coordinates":[-76.602255,38.666343],"type":"Point"}
}