{
  "type": "Feature",
  "properties": {
    "addr:full":"4157 Mountain Rd Ste 235 Pasadena MD 21122",
    "addr:housenumber":"4157",
    "addr:postcode":"21122",
    "addr:street":"Mountain Rd Ste 235",
    "iso:country":"US",
    "sg:address":"4157 Mountain Rd Ste 235",
    "sg:city":"Pasadena",
    "sg:classifiers":[
        {
            "category":"Shopping",
            "subcategory":"Computers & Home Electronics",
            "type":"Retail Goods"
        }
    ],
    "sg:phone":"+1 410 299 7842",
    "sg:postcode":"21122",
    "sg:province":"MD",
    "sg:tags":[
        "hardware",
        "supply"
    ],
    "wof:name":"Technology Alliance Group",
    "wof:placetype":"venue"
},
  "geometry": {"coordinates":[-76.515647,39.122544],"type":"Point"}
}