{
  "type": "Feature",
  "properties": {
    "addr:full":"3700 Commerce Dr Halethorpe MD 21227",
    "addr:housenumber":"3700",
    "addr:postcode":"21227",
    "addr:street":"Commerce Dr",
    "iso:country":"US",
    "sg:address":"3700 Commerce Dr",
    "sg:city":"Halethorpe",
    "sg:classifiers":[
        {
            "category":"Professional",
            "subcategory":"Testing Lab",
            "type":"Services"
        }
    ],
    "sg:phone":"+1 410 381 2200",
    "sg:postcode":"21227",
    "sg:province":"MD",
    "sg:tags":[
        "laboratory"
    ],
    "sg:website":"www.met-test.com",
    "wof:name":"MET Electrical Testing Co",
    "wof:placetype":"venue"
},
  "geometry": {"coordinates":[-76.674041,39.251066],"type":"Point"}
}