{
  "type": "Feature",
  "properties": {
    "addr:full":"2114 Bay Ridge Ave Annapolis MD 21403",
    "addr:housenumber":"2114",
    "addr:postcode":"21403",
    "addr:street":"Bay Ridge Ave",
    "iso:country":"US",
    "sg:address":"2114 Bay Ridge Ave",
    "sg:city":"Annapolis",
    "sg:classifiers":[
        {
            "category":"Organizations",
            "subcategory":"Religious Organization",
            "type":"Services"
        }
    ],
    "sg:phone":"+1 410 263 4125",
    "sg:postcode":"21403",
    "sg:province":"MD",
    "wof:name":"John Wesley United Methodist",
    "wof:placetype":"venue"
},
  "geometry": {"coordinates":[-76.493763,38.952826],"type":"Point"}
}