{
  "type": "Feature",
  "properties": {
    "iso:country":"US",
    "sg:address":"17534 Cedar Lawn Dr",
    "sg:city":"Hagerstown",
    "sg:classifiers":[
        {
            "category":"Professional",
            "subcategory":"Secretarial Services",
            "type":"Services"
        }
    ],
    "sg:phone":"+1 301 733 0748",
    "sg:postcode":"21740",
    "sg:province":"MD",
    "sg:tags":[
        "convention",
        "court",
        "reporter"
    ],
    "wof:name":"Adams Barclay Business Svc",
    "wof:placetype":"venue"
},
  "geometry": {"coordinates":[-77.761627,39.6507],"type":"Point"}
}