{
  "type": "Feature",
  "properties": {
    "iso:country":"US",
    "sg:address":"8954 Skyrock Ct",
    "sg:city":"Columbia",
    "sg:classifiers":[
        {
            "category":"Professional",
            "subcategory":"Computer Services",
            "type":"Services"
        }
    ],
    "sg:phone":"+1 410 340 1263",
    "sg:postcode":"21046",
    "sg:province":"MD",
    "sg:tags":[
        "consultant"
    ],
    "wof:name":"World Wide Store Fronts Inc",
    "wof:placetype":"venue"
},
  "geometry": {"coordinates":[-76.855183,39.166805],"type":"Point"}
}