{
  "type": "Feature",
  "properties": {
    "addr:full":"20611 Sampson Rd Parkton MD 21120",
    "addr:housenumber":"20611",
    "addr:postcode":"21120",
    "addr:street":"Sampson Rd",
    "iso:country":"US",
    "sg:address":"20611 Sampson Rd",
    "sg:city":"Parkton",
    "sg:classifiers":[
        {
            "category":"Building & Trades",
            "subcategory":"Construction",
            "type":"Services"
        }
    ],
    "sg:phone":"+1 410 329 8209",
    "sg:postcode":"21120",
    "sg:province":"MD",
    "sg:tags":[
        "paving",
        "contractor"
    ],
    "wof:name":"Herb Schafer's Quality Asphalt",
    "wof:placetype":"venue"
},
  "geometry": {"coordinates":[-76.636584,39.696813],"type":"Point"}
}