{
  "type": "Feature",
  "properties": {
    "iso:country":"US",
    "sg:address":"5627 Lafayette Pl",
    "sg:city":"Hyattsville",
    "sg:classifiers":[
        {
            "category":"Manufacturing",
            "subcategory":"Metals",
            "type":"Manufacturing & Wholesale Goods"
        },
        {
            "category":"Building & Trades",
            "subcategory":"Construction",
            "type":"Services"
        }
    ],
    "sg:phone":"+1 301 277 0508",
    "sg:postcode":"20781",
    "sg:province":"MD",
    "sg:tags":[
        "steel",
        "detailers",
        "erectors",
        "metal-wholesale",
        "manufacturer",
        "structural"
    ],
    "wof:name":"Thrifty Iron Works, Inc.",
    "wof:placetype":"venue"
},
  "geometry": {"coordinates":[-76.935368,38.95623],"type":"Point"}
}