{
  "type": "Feature",
  "properties": {
    "addr:full":"5035 Indian Head Hwy Ste A Oxon Hill MD 20745",
    "addr:housenumber":"5035",
    "addr:postcode":"20745",
    "addr:street":"Indian Head Hwy Ste A",
    "iso:country":"US",
    "sg:address":"5035 Indian Head Hwy Ste A",
    "sg:city":"Oxon Hill",
    "sg:classifiers":[
        {
            "category":"Personal",
            "subcategory":"Shoe Repair & Shine",
            "type":"Services"
        }
    ],
    "sg:phone":"+1 301 839 3840",
    "sg:postcode":"20745",
    "sg:province":"MD",
    "wof:name":"K & S Shoe Repair",
    "wof:placetype":"venue"
},
  "geometry": {"coordinates":[-77.00062699999999,38.820201],"type":"Point"}
}