{
  "type": "Feature",
  "properties": {
    "addr:full":"2316 Harris Mill Rd Parkton MD 21120",
    "addr:housenumber":"2316",
    "addr:postcode":"21120",
    "addr:street":"Harris Mill Rd",
    "iso:country":"US",
    "sg:address":"2316 Harris Mill Rd",
    "sg:city":"Parkton",
    "sg:classifiers":[
        {
            "category":"Professional",
            "subcategory":"Printing & Photocopies",
            "type":"Services"
        }
    ],
    "sg:phone":"+1 410 343 0258",
    "sg:postcode":"21120",
    "sg:province":"MD",
    "sg:tags":[
        "photographers-commercial"
    ],
    "wof:name":"Frame Of Mind",
    "wof:placetype":"venue"
},
  "geometry": {"coordinates":[-76.597268,39.715723],"type":"Point"}
}