{
  "type": "Feature",
  "properties": {
    "iso:country":"US",
    "sg:address":"7777 Maple Ave",
    "sg:city":"Takoma Park",
    "sg:classifiers":[
        {
            "category":"Recreation",
            "type":"Entertainment"
        }
    ],
    "sg:phone":"+1 301 891 6736",
    "sg:postcode":"20912",
    "sg:province":"MD",
    "sg:tags":[
        "instruction",
        "physical",
        "provides",
        "fitness"
    ],
    "wof:name":"Downtown Fitness Specialist",
    "wof:placetype":"venue"
},
  "geometry": {"coordinates":[-77.003846,38.984578],"type":"Point"}
}