{
  "type": "Feature",
  "properties": {
    "addr:full":"8005 Thornley Ct Bethesda MD 20817",
    "addr:housenumber":"8005",
    "addr:postcode":"20817",
    "addr:street":"Thornley Ct",
    "iso:country":"US",
    "sg:address":"8005 Thornley Ct",
    "sg:city":"Bethesda",
    "sg:classifiers":[
        {
            "category":"Communications",
            "subcategory":"Film & Video Production",
            "type":"Services"
        }
    ],
    "sg:phone":"+1 301 469 9700",
    "sg:postcode":"20817",
    "sg:province":"MD",
    "sg:tags":[
        "motion"
    ],
    "wof:name":"Woodward Productions",
    "wof:placetype":"venue"
},
  "geometry": {"coordinates":[-77.162167,38.984967],"type":"Point"}
}