{
  "type": "Feature",
  "properties": {
    "iso:country":"US",
    "sg:address":"11369 Liberty St",
    "sg:city":"Fulton",
    "sg:classifiers":[
        {
            "category":"Shopping",
            "subcategory":"Catalog Store",
            "type":"Retail Goods"
        }
    ],
    "sg:phone":"+1 301 725 2166",
    "sg:postcode":"20759",
    "sg:province":"MD",
    "sg:tags":[
        "mail",
        "order",
        "online"
    ],
    "wof:name":"Staging By Ke&Y Associates",
    "wof:placetype":"venue"
},
  "geometry": {"coordinates":[-76.907167,39.160693],"type":"Point"}
}