{
  "type": "Feature",
  "properties": {
    "iso:country":"US",
    "sg:address":"370 Deep Shore Rd",
    "sg:city":"Denton",
    "sg:classifiers":[
        {
            "category":"Personal",
            "subcategory":"Beauty Salon",
            "type":"Services"
        }
    ],
    "sg:phone":"+1 410 479 0735",
    "sg:postcode":"21629",
    "sg:province":"MD",
    "wof:name":"Magic Mirror",
    "wof:placetype":"venue"
},
  "geometry": {"coordinates":[-75.82438399999999,38.866468],"type":"Point"}
}