{
  "type": "Feature",
  "properties": {
    "addr:full":"410 Winterberry Dr Edgewood MD 21040",
    "addr:housenumber":"410",
    "addr:postcode":"21040",
    "addr:street":"Winterberry Dr",
    "iso:country":"US",
    "sg:address":"410 Winterberry Dr",
    "sg:city":"Edgewood",
    "sg:classifiers":[
        {
            "category":"Transit Center",
            "subcategory":"Freight",
            "type":"Transportation"
        },
        {
            "category":"Freight",
            "type":"Transportation"
        }
    ],
    "sg:phone":"+1 410 588 6631",
    "sg:postcode":"21040",
    "sg:province":"MD",
    "sg:tags":[
        "local",
        "trucking-motor",
        "trucking"
    ],
    "wof:name":"Ed S Mobile Auto Truck De",
    "wof:placetype":"venue"
},
  "geometry": {"coordinates":[-76.273117,39.43214],"type":"Point"}
}