{
  "type": "Feature",
  "properties": {
    "iso:country":"US",
    "sg:address":"2601 Housley Rd",
    "sg:city":"Annapolis",
    "sg:classifiers":[
        {
            "category":"Shopping",
            "subcategory":"Computers & Home Electronics",
            "type":"Retail Goods"
        }
    ],
    "sg:phone":"+1 410 571 0100",
    "sg:postcode":"21401",
    "sg:province":"MD",
    "sg:tags":[
        "television",
        "radio"
    ],
    "wof:name":"Big Screen Store",
    "wof:placetype":"venue"
},
  "geometry": {"coordinates":[-76.55209600000001,38.990541],"type":"Point"}
}