{
  "type": "Feature",
  "properties": {
    "iso:country":"US",
    "sg:address":"2600 Insulator Dr",
    "sg:city":"Baltimore",
    "sg:classifiers":[
        {
            "category":"Recreation",
            "subcategory":"Marina",
            "type":"Entertainment"
        }
    ],
    "sg:phone":"+1 410 539 8895",
    "sg:postcode":"21230",
    "sg:province":"MD",
    "sg:tags":[
        "storage",
        "boat"
    ],
    "wof:name":"Baltimore Yacht Basin Inc",
    "wof:placetype":"venue"
},
  "geometry": {"coordinates":[-76.613461,39.261943],"type":"Point"}
}