{
  "type": "Feature",
  "properties": {
    "addr:full":"542 Washington Rd Westminster MD 21157",
    "addr:housenumber":"542",
    "addr:postcode":"21157",
    "addr:street":"Washington Rd",
    "iso:country":"US",
    "sg:address":"542 Washington Rd",
    "sg:city":"Westminster",
    "sg:classifiers":[
        {
            "category":"Professional",
            "type":"Services"
        }
    ],
    "sg:phone":"+1 410 876 0370",
    "sg:postcode":"21157",
    "sg:province":"MD",
    "sg:tags":[
        "establishment"
    ],
    "wof:name":"Center For Total Eye Care",
    "wof:placetype":"venue"
},
  "geometry": {"coordinates":[-76.986852,39.559944],"type":"Point"}
}