{
  "type": "Feature",
  "properties": {
    "addr:full":"4533 Stanford St Chevy Chase MD 20815",
    "addr:housenumber":"4533",
    "addr:postcode":"20815",
    "addr:street":"Stanford St",
    "iso:country":"US",
    "sg:address":"4533 Stanford St",
    "sg:city":"Chevy Chase",
    "sg:classifiers":[
        {
            "category":"Restaurant",
            "type":"Food & Drink"
        },
        {
            "category":"Ice Cream",
            "type":"Food & Drink"
        }
    ],
    "sg:menulink":"http://www.allmenus.com/md/bethesda/243245-baskin-robbins/menu/",
    "sg:phone":"+1 301 652 3142",
    "sg:postcode":"20815",
    "sg:province":"MD",
    "sg:tags":[
        "american",
        "ice",
        "cream"
    ],
    "wof:name":"Baskin-Robbins",
    "wof:placetype":"venue"
},
  "geometry": {"coordinates":[-77.090295,38.978632],"type":"Point"}
}