{
  "type": "Feature",
  "properties": {
    "iso:country":"US",
    "sg:address":"1625 Thames St",
    "sg:city":"Baltimore",
    "sg:classifiers":[
        {
            "category":"Home & Garden",
            "subcategory":"Home Furnishings",
            "type":"Retail Goods"
        }
    ],
    "sg:phone":"+1 410 522 7010",
    "sg:postcode":"21231",
    "sg:province":"MD",
    "sg:tags":[
        "decor"
    ],
    "wof:name":"Su Casa",
    "wof:placetype":"venue"
},
  "geometry": {"coordinates":[-76.593903,39.2817],"type":"Point"}
}