{
  "type": "Feature",
  "properties": {
    "iso:country":"US",
    "sg:address":"6852 Tulip Hill Ter",
    "sg:city":"Bethesda",
    "sg:classifiers":[
        {
            "category":"Professional",
            "subcategory":"Management & Consulting",
            "type":"Services"
        },
        {
            "category":"Professional",
            "subcategory":"Advertising",
            "type":"Services"
        },
        {
            "category":"Wholesale",
            "subcategory":"Computers",
            "type":"Manufacturing & Wholesale Goods"
        },
        {
            "category":"Professional",
            "subcategory":"Computer Services",
            "type":"Services"
        },
        {
            "category":"Internet Cafe",
            "subcategory":"None",
            "type":"Food & Drink"
        }
    ],
    "sg:phone":"+1 301 263 0731",
    "sg:postcode":"20816",
    "sg:province":"MD",
    "sg:tags":[
        "product",
        "marketing",
        "equipment",
        "program",
        "consultant",
        "software"
    ],
    "sg:website":"http://www.dtsearch.com",
    "wof:name":"Dt Search Corp",
    "wof:placetype":"venue"
},
  "geometry": {"coordinates":[-77.134799,38.96871],"type":"Point"}
}