{
  "type": "Feature",
  "properties": {
    "addr:full":"2806 Rogers Ave Ellicott City MD 21043",
    "addr:housenumber":"2806",
    "addr:postcode":"21043",
    "addr:street":"Rogers Ave",
    "iso:country":"US",
    "sg:address":"2806 Rogers Ave",
    "sg:city":"Ellicott City",
    "sg:classifiers":[
        {
            "category":"Retail",
            "subcategory":"Laundry & Dry Cleaning",
            "type":"Services"
        }
    ],
    "sg:phone":"+1 410 313 9075",
    "sg:postcode":"21043",
    "sg:province":"MD",
    "sg:tags":[
        "cleaners",
        "rug",
        "carpet"
    ],
    "wof:name":"B & J Carpet",
    "wof:placetype":"venue"
},
  "geometry": {"coordinates":[-76.811583,39.295412],"type":"Point"}
}