{
  "type": "Feature",
  "properties": {
    "addr:full":"300 W Seminary Ave Lutherville MD 21093",
    "addr:housenumber":"300",
    "addr:postcode":"21093",
    "addr:street":"W Seminary Ave",
    "iso:country":"US",
    "sg:address":"300 W Seminary Ave",
    "sg:city":"Lutherville",
    "sg:classifiers":[
        {
            "category":"Health Services",
            "subcategory":"Nursing And Care Facility",
            "type":"Services"
        }
    ],
    "sg:phone":"+1 410 252 0440",
    "sg:postcode":"21093",
    "sg:province":"MD",
    "sg:tags":[
        "adult"
    ],
    "sg:website":"www.collegemanor.com",
    "wof:name":"College Manor",
    "wof:placetype":"venue"
},
  "geometry": {"coordinates":[-76.628996,39.421853],"type":"Point"}
}