{
  "type": "Feature",
  "properties": {
    "iso:country":"US",
    "sg:address":"12 Arbutus Ave",
    "sg:city":"Baltimore",
    "sg:classifiers":[
        {
            "category":"Professional",
            "subcategory":"Business Services",
            "type":"Services"
        }
    ],
    "sg:phone":"+1 410 744 8971",
    "sg:postcode":"21228",
    "sg:province":"MD",
    "wof:name":"Big Wheel Enterprises Inc",
    "wof:placetype":"venue"
},
  "geometry": {"coordinates":[-76.725981,39.274928],"type":"Point"}
}