{
  "type": "Feature",
  "properties": {
    "addr:full":"2562 Hidden Cove Rd Annapolis MD 21401",
    "addr:housenumber":"2562",
    "addr:postcode":"21401",
    "addr:street":"Hidden Cove Rd",
    "iso:country":"US",
    "sg:address":"2562 Hidden Cove Rd",
    "sg:city":"Annapolis",
    "sg:classifiers":[
        {
            "category":"Organizations",
            "subcategory":"Professional Association",
            "type":"Services"
        }
    ],
    "sg:phone":"+1 410 614 5810",
    "sg:postcode":"21401",
    "sg:province":"MD",
    "sg:tags":[
        "health"
    ],
    "wof:name":"Health Services International",
    "wof:placetype":"venue"
},
  "geometry": {"coordinates":[-76.590695,38.97767],"type":"Point"}
}