{
  "type": "Feature",
  "properties": {
    "iso:country":"US",
    "sg:address":"500 E Pratt St Ste 1100",
    "sg:city":"Baltimore",
    "sg:classifiers":[
        {
            "category":"Banks & Credit Unions",
            "subcategory":"Investment Brokerage",
            "type":"Services"
        },
        {
            "category":"Banks & Credit Unions",
            "subcategory":"Bank",
            "type":"Services"
        },
        {
            "category":"Banks & Credit Unions",
            "subcategory":"Financial Services",
            "type":"Services"
        }
    ],
    "sg:phone":"+1 410 576 3200",
    "sg:postcode":"21202",
    "sg:province":"MD",
    "sg:tags":[
        "saving",
        "transfer",
        "commercial",
        "broker",
        "agent",
        "bond",
        "stock"
    ],
    "sg:website":"http://www.painewebber.com",
    "wof:name":"Ubs",
    "wof:placetype":"venue"
},
  "geometry": {"coordinates":[-76.60871899999999,39.286671],"type":"Point"}
}