{
  "type": "Feature",
  "properties": {
    "addr:full":"4200 Pennington Ave Baltimore MD 21226",
    "addr:housenumber":"4200",
    "addr:postcode":"21226",
    "addr:street":"Pennington Ave",
    "iso:country":"US",
    "sg:address":"4200 Pennington Ave",
    "sg:city":"Baltimore",
    "sg:classifiers":[
        {
            "category":"Building & Trades",
            "subcategory":"Construction",
            "type":"Services"
        }
    ],
    "sg:phone":"+1 410 354 8883",
    "sg:postcode":"21226",
    "sg:province":"MD",
    "sg:tags":[
        "contractor"
    ],
    "wof:name":"Bmw Construction Spec Inc",
    "wof:placetype":"venue"
},
  "geometry": {"coordinates":[-76.588826,39.227548],"type":"Point"}
}