{
  "type": "Feature",
  "properties": {
    "iso:country":"US",
    "sg:address":"6231 Crain Hwy",
    "sg:city":"La Plata",
    "sg:phone":"+1 301 934 2234",
    "sg:postcode":"20646",
    "sg:province":"MD",
    "sg:tags":[
        "gas"
    ],
    "wof:name":"United Propane Inc",
    "wof:placetype":"venue"
},
  "geometry": {"coordinates":[-76.98480000000001,38.54241],"type":"Point"}
}