{
  "type": "Feature",
  "properties": {
    "addr:full":"710 Merritt Blvd Dundalk MD 21222",
    "addr:housenumber":"710",
    "addr:postcode":"21222",
    "addr:street":"Merritt Blvd",
    "iso:country":"US",
    "sg:address":"710 Merritt Blvd",
    "sg:city":"Dundalk",
    "sg:classifiers":[
        {
            "category":"Shopping",
            "subcategory":"Clothing, Apparel, & Fashions",
            "type":"Retail Goods"
        }
    ],
    "sg:phone":"+1 410 282 6688",
    "sg:postcode":"21222",
    "sg:province":"MD",
    "sg:tags":[
        "lingerie"
    ],
    "wof:name":"Lovecraft",
    "wof:placetype":"venue"
},
  "geometry": {"coordinates":[-76.50438699999999,39.289956],"type":"Point"}
}