{
  "type": "Feature",
  "properties": {
    "iso:country":"US",
    "sg:address":"530 Ashford Rd",
    "sg:city":"Silver Spring",
    "sg:classifiers":[
        {
            "category":"Manufacturing",
            "subcategory":"Printing",
            "type":"Manufacturing & Wholesale Goods"
        }
    ],
    "sg:phone":"+1 301 585 4381",
    "sg:postcode":"20910",
    "sg:province":"MD",
    "sg:tags":[
        "publishing"
    ],
    "wof:name":"Seneca Press",
    "wof:placetype":"venue"
},
  "geometry": {"coordinates":[-77.018175,39.001712],"type":"Point"}
}