{
  "type": "Feature",
  "properties": {
    "iso:country":"US",
    "sg:address":"4115 Mountain Rd",
    "sg:city":"Pasadena",
    "sg:phone":"+1 410 439 4560",
    "sg:postcode":"21122",
    "sg:province":"MD",
    "sg:website":"http://www.safeway.com",
    "wof:name":"Safeway Stores",
    "wof:placetype":"venue"
},
  "geometry": {"coordinates":[-76.516437,39.122735],"type":"Point"}
}