{
  "type": "Feature",
  "properties": {
    "iso:country":"US",
    "sg:address":"4100 Ulster Rd",
    "sg:city":"Beltsville",
    "sg:classifiers":[
        {
            "category":"Home & Garden",
            "subcategory":"Building Materials",
            "type":"Retail Goods"
        },
        {
            "category":"Building & Trades",
            "subcategory":"Construction",
            "type":"Services"
        }
    ],
    "sg:phone":"+1 301 937 3997",
    "sg:postcode":"20705",
    "sg:province":"MD",
    "sg:tags":[
        "concrete",
        "staining",
        "contractor"
    ],
    "wof:name":"Pathways Plus Resurfacing",
    "wof:placetype":"venue"
},
  "geometry": {"coordinates":[-76.93637099999999,39.037201],"type":"Point"}
}