{
  "type": "Feature",
  "properties": {
    "iso:country":"US",
    "sg:address":"610 Norhurst Way",
    "sg:city":"Baltimore",
    "sg:classifiers":[
        {
            "category":"Manufacturing",
            "subcategory":"Printing",
            "type":"Manufacturing & Wholesale Goods"
        }
    ],
    "sg:phone":"+1 410 719 1073",
    "sg:postcode":"21228",
    "sg:province":"MD",
    "sg:tags":[
        "publishing"
    ],
    "wof:name":"Papier Productions",
    "wof:placetype":"venue"
},
  "geometry": {"coordinates":[-76.766026,39.279461],"type":"Point"}
}