{
  "type": "Feature",
  "properties": {
    "iso:country":"US",
    "sg:address":"2100 Olney Sandy Spring Rd",
    "sg:city":"Olney",
    "sg:classifiers":[
        {
            "category":"Personal",
            "subcategory":"Beauty Salon",
            "type":"Services"
        }
    ],
    "sg:phone":"+1 301 260 7480",
    "sg:postcode":"20860",
    "sg:province":"MD",
    "wof:name":"New York Beauty Shop",
    "wof:placetype":"venue"
},
  "geometry": {"coordinates":[-77.04721,39.144767],"type":"Point"}
}