{
  "type": "Feature",
  "properties": {
    "iso:country":"US",
    "sg:address":"8643 Pulaski Hwy",
    "sg:city":"Rosedale",
    "sg:classifiers":[
        {
            "category":"Home & Garden",
            "subcategory":"Furniture",
            "type":"Retail Goods"
        }
    ],
    "sg:phone":"+1 410 686 4242",
    "sg:postcode":"21237",
    "sg:province":"MD",
    "wof:name":"High Point Furniture Outlet",
    "wof:placetype":"venue"
},
  "geometry": {"coordinates":[-76.485862,39.333787],"type":"Point"}
}