{
  "type": "Feature",
  "properties": {
    "addr:full":"7932 Old Branch Ave Clinton MD 20735",
    "addr:housenumber":"7932",
    "addr:postcode":"20735",
    "addr:street":"Old Branch Ave",
    "iso:country":"US",
    "sg:address":"7932 Old Branch Ave",
    "sg:city":"Clinton",
    "sg:classifiers":[
        {
            "category":"Shopping",
            "type":"Retail Goods"
        }
    ],
    "sg:phone":"+1 301 868 6320",
    "sg:postcode":"20735",
    "sg:province":"MD",
    "sg:tags":[
        "trophy",
        "medal",
        "award"
    ],
    "sg:website":"www.pgengraving.com",
    "wof:name":"Prince George's Engraving Co",
    "wof:placetype":"venue"
},
  "geometry": {"coordinates":[-76.89918299999999,38.780467],"type":"Point"}
}