{
  "type": "Feature",
  "properties": {
    "addr:full":"6805 E Clinton St Clinton MD 20735",
    "addr:housenumber":"6805",
    "addr:postcode":"20735",
    "addr:street":"E Clinton St",
    "iso:country":"US",
    "sg:address":"6805 E Clinton St",
    "sg:city":"Clinton",
    "sg:classifiers":[
        {
            "category":"Recreation",
            "type":"Entertainment"
        }
    ],
    "sg:phone":"+1 301 868 6454",
    "sg:postcode":"20735",
    "sg:province":"MD",
    "sg:tags":[
        "skating",
        "rink"
    ],
    "wof:name":"Clinton Skating Ctr",
    "wof:placetype":"venue"
},
  "geometry": {"coordinates":[-76.888232,38.779082],"type":"Point"}
}