{
  "type": "Feature",
  "properties": {
    "addr:full":"9958 Reisterstown Rd Owings Mills MD 21117",
    "addr:housenumber":"9958",
    "addr:postcode":"21117",
    "addr:street":"Reisterstown Rd",
    "iso:country":"US",
    "sg:address":"9958 Reisterstown Rd",
    "sg:city":"Owings Mills",
    "sg:classifiers":[
        {
            "category":"Restaurant",
            "type":"Food & Drink"
        }
    ],
    "sg:phone":"+1 410 363 8160",
    "sg:postcode":"21117",
    "sg:province":"MD",
    "wof:name":"China Best Restaurant",
    "wof:placetype":"venue"
},
  "geometry": {"coordinates":[-76.76979799999999,39.411944],"type":"Point"}
}