{
  "type": "Feature",
  "properties": {
    "iso:country":"US",
    "sg:address":"6423 District Heights Pkwy",
    "sg:city":"District Heights",
    "sg:classifiers":[
        {
            "category":"Personal",
            "subcategory":"Beauty Salon",
            "type":"Services"
        }
    ],
    "sg:phone":"+1 301 420 1002",
    "sg:postcode":"20747",
    "sg:province":"MD",
    "wof:name":"Beauty Braid's Hair Studio",
    "wof:placetype":"venue"
},
  "geometry": {"coordinates":[-76.894744,38.859091],"type":"Point"}
}