{
  "type": "Feature",
  "properties": {
    "iso:country":"US",
    "sg:address":"3999 Whispering Meadow Dr",
    "sg:city":"Randallstown",
    "sg:classifiers":[
        {
            "category":"Building & Trades",
            "subcategory":"Cleaning & Sanitation",
            "type":"Services"
        }
    ],
    "sg:phone":"+1 410 521 0457",
    "sg:postcode":"21133",
    "sg:province":"MD",
    "sg:tags":[
        "janitor"
    ],
    "wof:name":"Whittington Service Group",
    "wof:placetype":"venue"
},
  "geometry": {"coordinates":[-76.778786,39.383021],"type":"Point"}
}