{
  "type": "Feature",
  "properties": {
    "iso:country":"US",
    "sg:address":"117 S Cross St",
    "sg:city":"Chestertown",
    "sg:phone":"+1 410 778 0871",
    "sg:postcode":"21620",
    "sg:province":"MD",
    "sg:website":"http://crossfirecafe.net",
    "wof:name":"Crossfire Cafe",
    "wof:placetype":"venue"
},
  "geometry": {"coordinates":[-76.066688,39.208975],"type":"Point"}
}