{
  "type": "Feature",
  "properties": {
    "addr:full":"102 N Main St Woodsboro MD 21798",
    "addr:housenumber":"102",
    "addr:postcode":"21798",
    "addr:street":"N Main St",
    "iso:country":"US",
    "sg:address":"102 N Main St",
    "sg:city":"Woodsboro",
    "sg:classifiers":[
        {
            "category":"Real Estate",
            "subcategory":"Real Estate Agent",
            "type":"Services"
        }
    ],
    "sg:phone":"+1 301 845 1200",
    "sg:postcode":"21798",
    "sg:province":"MD",
    "wof:name":"Mc Laughlin Realty",
    "wof:placetype":"venue"
},
  "geometry": {"coordinates":[-77.314795,39.535905],"type":"Point"}
}