{
  "type": "Feature",
  "properties": {
    "iso:country":"US",
    "sg:address":"104 W Chestnut St",
    "sg:city":"Salisbury",
    "sg:classifiers":[
        {
            "category":"Organizations",
            "subcategory":"Non-profit Organization",
            "type":"Services"
        }
    ],
    "sg:phone":"+1 410 749 6422",
    "sg:postcode":"21801",
    "sg:province":"MD",
    "sg:tags":[
        "information",
        "alcoholism",
        "treatment"
    ],
    "wof:name":"White Flint Recovery",
    "wof:placetype":"venue"
},
  "geometry": {"coordinates":[-75.601226,38.368676],"type":"Point"}
}