{
  "type": "Feature",
  "properties": {
    "iso:country":"US",
    "sg:address":"6290 Montrose Rd",
    "sg:city":"Rockville",
    "sg:classifiers":[
        {
            "category":"Professional",
            "type":"Services"
        }
    ],
    "sg:phone":"+1 301 770 5377",
    "sg:postcode":"20852",
    "sg:province":"MD",
    "sg:tags":[
        "establishment"
    ],
    "wof:name":"PATH",
    "wof:placetype":"venue"
},
  "geometry": {"coordinates":[-77.127053,39.052626],"type":"Point"}
}