{
  "type": "Feature",
  "properties": {
    "iso:country":"US",
    "sg:address":"8601 Grovemont Cir",
    "sg:city":"Gaithersburg",
    "sg:classifiers":[
        {
            "category":"Manufacturing",
            "subcategory":"Printing",
            "type":"Manufacturing & Wholesale Goods"
        }
    ],
    "sg:phone":"+1 301 208 1654",
    "sg:postcode":"20877",
    "sg:province":"MD",
    "sg:tags":[
        "printer"
    ],
    "wof:name":"PIP Printing",
    "wof:placetype":"venue"
},
  "geometry": {"coordinates":[-77.17597000000001,39.128868],"type":"Point"}
}