{
  "type": "Feature",
  "properties": {
    "iso:country":"US",
    "sg:address":"17089 Briardale Rd",
    "sg:city":"Derwood",
    "sg:classifiers":[
        {
            "category":"Professional",
            "subcategory":"Management & Consulting",
            "type":"Services"
        }
    ],
    "sg:phone":"+1 301 926 8277",
    "sg:postcode":"20855",
    "sg:province":"MD",
    "sg:tags":[
        "business"
    ],
    "wof:name":"Richard Larue",
    "wof:placetype":"venue"
},
  "geometry": {"coordinates":[-77.162941,39.135778],"type":"Point"}
}