{
  "type": "Feature",
  "properties": {
    "addr:full":"502 Skipper Ct Chester MD 21619",
    "addr:housenumber":"502",
    "addr:postcode":"21619",
    "addr:street":"Skipper Ct",
    "iso:country":"US",
    "sg:address":"502 Skipper Ct",
    "sg:city":"Chester",
    "sg:classifiers":[
        {
            "category":"Building & Trades",
            "subcategory":"Construction",
            "type":"Services"
        }
    ],
    "sg:phone":"+1 410 643 4686",
    "sg:postcode":"21619",
    "sg:province":"MD",
    "sg:tags":[
        "roofing",
        "contractor"
    ],
    "wof:name":"Johns Roofing",
    "wof:placetype":"venue"
},
  "geometry": {"coordinates":[-76.284443,38.983362],"type":"Point"}
}