{
  "type": "Feature",
  "properties": {
    "addr:full":"6655 Dobbin Rd Columbia MD 21045",
    "addr:housenumber":"6655",
    "addr:postcode":"21045",
    "addr:street":"Dobbin Rd",
    "iso:country":"US",
    "sg:address":"6655 Dobbin Rd",
    "sg:city":"Columbia",
    "sg:classifiers":[
        {
            "category":"Wholesale",
            "subcategory":"Machinery & Supplies",
            "type":"Manufacturing & Wholesale Goods"
        }
    ],
    "sg:phone":"+1 410 997 9057",
    "sg:postcode":"21045",
    "sg:province":"MD",
    "sg:tags":[
        "sprinkler"
    ],
    "wof:name":"Maryland Sprinkler Co Inc",
    "wof:placetype":"venue"
},
  "geometry": {"coordinates":[-76.825945,39.185944],"type":"Point"}
}