{
  "type": "Feature",
  "properties": {
    "iso:country":"US",
    "sg:address":"13914 Edgemont Rd",
    "sg:city":"Smithsburg",
    "sg:classifiers":[
        {
            "category":"Building & Trades",
            "subcategory":"Plumbing",
            "type":"Services"
        }
    ],
    "sg:phone":"+1 301 416 0327",
    "sg:postcode":"21783",
    "sg:province":"MD",
    "sg:tags":[
        "plumbing",
        "heating",
        "contractor"
    ],
    "wof:name":"Stotelmyer Plumbing & Heating",
    "wof:placetype":"venue"
},
  "geometry": {"coordinates":[-77.534809,39.692011],"type":"Point"}
}