{
  "type": "Feature",
  "properties": {
    "addr:full":"1900 Norfolk Dr Owings MD 20736",
    "addr:housenumber":"1900",
    "addr:postcode":"20736",
    "addr:street":"Norfolk Dr",
    "iso:country":"US",
    "sg:address":"1900 Norfolk Dr",
    "sg:city":"Owings",
    "sg:classifiers":[
        {
            "category":"Building & Trades",
            "subcategory":"Plumbing",
            "type":"Services"
        },
        {
            "category":"Building & Trades",
            "subcategory":"Construction",
            "type":"Services"
        }
    ],
    "sg:phone":"+1 301 855 2414",
    "sg:postcode":"20736",
    "sg:province":"MD",
    "sg:tags":[
        "plumber",
        "industrial",
        "system",
        "specialty",
        "heating",
        "contractors-commercial",
        "contractor",
        "air conditioning"
    ],
    "wof:name":"Severn Plumbing & Heating, Inc.",
    "wof:placetype":"venue"
},
  "geometry": {"coordinates":[-76.632671,38.682884],"type":"Point"}
}