{
  "type": "Feature",
  "properties": {
    "addr:full":"104 Williamsport Cir Salisbury MD 21804",
    "addr:housenumber":"104",
    "addr:postcode":"21804",
    "addr:street":"Williamsport Cir",
    "iso:country":"US",
    "sg:address":"104 Williamsport Cir",
    "sg:city":"Salisbury",
    "sg:classifiers":[
        {
            "category":"Social Services",
            "type":"Services"
        }
    ],
    "sg:phone":"+1 410 543 0007",
    "sg:postcode":"21804",
    "sg:province":"MD",
    "sg:tags":[
        "organization",
        "welfare"
    ],
    "wof:name":"National Multiple Sclerosis",
    "wof:placetype":"venue"
},
  "geometry": {"coordinates":[-75.59918399999999,38.350246],"type":"Point"}
}