{
  "type": "Feature",
  "properties": {
    "addr:full":"1028 S Conkling St Baltimore MD 21224",
    "addr:housenumber":"1028",
    "addr:postcode":"21224",
    "addr:street":"S Conkling St",
    "iso:country":"US",
    "sg:address":"1028 S Conkling St",
    "sg:city":"Baltimore",
    "sg:classifiers":[
        {
            "category":"Bars & Pubs",
            "type":"Food & Drink"
        }
    ],
    "sg:phone":"+1 410 276 2590",
    "sg:postcode":"21224",
    "sg:province":"MD",
    "sg:tags":[
        "club",
        "night"
    ],
    "wof:name":"Glory Days",
    "wof:placetype":"venue"
},
  "geometry": {"coordinates":[-76.56685299999999,39.280813],"type":"Point"}
}