{
  "type": "Feature",
  "properties": {
    "addr:full":"4001 Littlestown Pike Westminster MD 21158",
    "addr:housenumber":"4001",
    "addr:postcode":"21158",
    "addr:street":"Littlestown Pike",
    "iso:country":"US",
    "sg:address":"4001 Littlestown Pike",
    "sg:city":"Westminster",
    "sg:classifiers":[
        {
            "category":"Manufacturing",
            "subcategory":"Tools & Machinery",
            "type":"Manufacturing & Wholesale Goods"
        }
    ],
    "sg:phone":"+1 410 857 3778",
    "sg:postcode":"21158",
    "sg:province":"MD",
    "sg:tags":[
        "machine",
        "shop"
    ],
    "wof:name":"Rockland Machine",
    "wof:placetype":"venue"
},
  "geometry": {"coordinates":[-77.046746,39.684583],"type":"Point"}
}