{
  "type": "Feature",
  "properties": {
    "addr:full":"2706 2nd Ave Baltimore MD 21234",
    "addr:housenumber":"2706",
    "addr:postcode":"21234",
    "addr:street":"2Nd Ave",
    "iso:country":"US",
    "sg:address":"2706 2nd Ave",
    "sg:city":"Baltimore",
    "sg:classifiers":[
        {
            "category":"Manufacturing",
            "subcategory":"Metals",
            "type":"Manufacturing & Wholesale Goods"
        }
    ],
    "sg:phone":"+1 410 661 8667",
    "sg:postcode":"21234",
    "sg:province":"MD",
    "sg:tags":[
        "steel",
        "fabrication"
    ],
    "wof:name":"Creative Metal Fabrication Sls",
    "wof:placetype":"venue"
},
  "geometry": {"coordinates":[-76.531153,39.394071],"type":"Point"}
}