{
  "type": "Feature",
  "properties": {
    "iso:country":"US",
    "sg:address":"114 N Washington St",
    "sg:city":"Easton",
    "sg:classifiers":[
        {
            "category":"Wholesale",
            "subcategory":"Machinery & Supplies",
            "type":"Manufacturing & Wholesale Goods"
        }
    ],
    "sg:phone":"+1 410 822 4400",
    "sg:postcode":"21601",
    "sg:province":"MD",
    "sg:tags":[
        "lithographer",
        "equipment"
    ],
    "wof:name":"Dynalith",
    "wof:placetype":"venue"
},
  "geometry": {"coordinates":[-76.07631,38.776353],"type":"Point"}
}