{
  "type": "Feature",
  "properties": {
    "addr:full":"11169 Oakenshield Cir Columbia MD 21044",
    "addr:housenumber":"11169",
    "addr:postcode":"21044",
    "addr:street":"Oakenshield Cir",
    "iso:country":"US",
    "sg:address":"11169 Oakenshield Cir",
    "sg:city":"Columbia",
    "sg:classifiers":[
        {
            "category":"Professional",
            "subcategory":"Advertising",
            "type":"Services"
        }
    ],
    "sg:phone":"+1 410 997 1649",
    "sg:postcode":"21044",
    "sg:province":"MD",
    "sg:tags":[
        "promotion",
        "sale"
    ],
    "wof:name":"Medreps Associates",
    "wof:placetype":"venue"
},
  "geometry": {"coordinates":[-76.89985799999999,39.220414],"type":"Point"}
}