{
  "type": "Feature",
  "properties": {
    "addr:full":"9004 Chesapeake Ave Baltimore MD 21219",
    "addr:housenumber":"9004",
    "addr:postcode":"21219",
    "addr:street":"Chesapeake Ave",
    "iso:country":"US",
    "sg:address":"9004 Chesapeake Ave",
    "sg:city":"Baltimore",
    "sg:classifiers":[
        {
            "category":"Freight",
            "type":"Transportation"
        }
    ],
    "sg:phone":"+1 410 477 4387",
    "sg:postcode":"21219",
    "sg:province":"MD",
    "sg:tags":[
        "operator",
        "local",
        "trucking"
    ],
    "wof:name":"Warren J Bossalina Trucking Co",
    "wof:placetype":"venue"
},
  "geometry": {"coordinates":[-76.40121600000001,39.228829],"type":"Point"}
}