{
  "type": "Feature",
  "properties": {
    "iso:country":"US",
    "sg:address":"1441 Light St",
    "sg:city":"Baltimore",
    "sg:classifiers":[
        {
            "category":"Real Estate",
            "subcategory":"Architect",
            "type":"Services"
        }
    ],
    "sg:phone":"+1 410 783 1574",
    "sg:postcode":"21230",
    "sg:province":"MD",
    "wof:name":"Allen & Assoc",
    "wof:placetype":"venue"
},
  "geometry": {"coordinates":[-76.611681,39.272728],"type":"Point"}
}