{
  "type": "Feature",
  "properties": {
    "iso:country":"US",
    "sg:address":"620 Taylor Ave",
    "sg:city":"Annapolis",
    "sg:classifiers":[
        {
            "category":"Government",
            "subcategory":"Office",
            "type":"Public Place"
        }
    ],
    "sg:phone":"+1 410 263 7978",
    "sg:postcode":"21401",
    "sg:province":"MD",
    "sg:tags":[
        "village"
    ],
    "wof:name":"Emergency Medical Svc",
    "wof:placetype":"venue"
},
  "geometry": {"coordinates":[-76.502815,38.987043],"type":"Point"}
}