{
  "type": "Feature",
  "properties": {
    "iso:country":"US",
    "sg:address":"2501 Gibson Rd",
    "sg:city":"White Hall",
    "sg:classifiers":[
        {
            "category":"Farming",
            "subcategory":"Farm",
            "type":"Manufacturing & Wholesale Goods"
        }
    ],
    "sg:phone":"+1 410 329 2140",
    "sg:postcode":"21161",
    "sg:province":"MD",
    "sg:tags":[
        "crop",
        "general"
    ],
    "wof:name":"Stoecker Farms",
    "wof:placetype":"venue"
},
  "geometry": {"coordinates":[-76.59533999999999,39.696826],"type":"Point"}
}