{
  "type": "Feature",
  "properties": {
    "addr:full":"9504 Amberleigh Ln Apt P Perry Hall MD 21128",
    "addr:housenumber":"9504",
    "addr:postcode":"21128",
    "addr:street":"Amberleigh Ln Apt P Perry",
    "iso:country":"US",
    "sg:address":"9504 Amberleigh Ln Apt P",
    "sg:city":"Perry Hall",
    "sg:classifiers":[
        {
            "category":"Professional",
            "subcategory":"Lawyer & Legal Services",
            "type":"Services"
        }
    ],
    "sg:phone":"+1 410 256 5379",
    "sg:postcode":"21128",
    "sg:province":"MD",
    "wof:name":"Villa D James Atty",
    "wof:placetype":"venue"
},
  "geometry": {"coordinates":[-76.446198,39.4081],"type":"Point"}
}