{
  "type": "Feature",
  "properties": {
    "addr:full":"9204 Appleford Cir Owings Mills MD 21117",
    "addr:housenumber":"9204",
    "addr:postcode":"21117",
    "addr:street":"Appleford Cir",
    "iso:country":"US",
    "sg:address":"9204 Appleford Cir",
    "sg:city":"Owings Mills",
    "sg:classifiers":[
        {
            "category":"Real Estate",
            "subcategory":"Real Estate Operator",
            "type":"Services"
        }
    ],
    "sg:phone":"+1 410 581 3817",
    "sg:postcode":"21117",
    "sg:province":"MD",
    "sg:tags":[
        "apartment"
    ],
    "sg:website":"www.bozzuto.com",
    "wof:name":"Briarwood Apartments",
    "wof:placetype":"venue"
},
  "geometry": {"coordinates":[-76.780247,39.40044],"type":"Point"}
}