{
  "type": "Feature",
  "properties": {
    "iso:country":"US",
    "sg:address":"7 W Chesapeake Ave",
    "sg:city":"Baltimore",
    "sg:classifiers":[
        {
            "category":"Shopping",
            "subcategory":"Bicycles & Sporting Goods",
            "type":"Retail Goods"
        }
    ],
    "sg:phone":"+1 410 825 8050",
    "sg:postcode":"21204",
    "sg:province":"MD",
    "sg:tags":[
        "equipment",
        "camping"
    ],
    "wof:name":"Sunny's Great Outdoors Inc",
    "wof:placetype":"venue"
},
  "geometry": {"coordinates":[-76.605299,39.399579],"type":"Point"}
}