{
  "type": "Feature",
  "properties": {
    "addr:full":"861 Washington Ave Chestertown MD 21620",
    "addr:housenumber":"861",
    "addr:postcode":"21620",
    "addr:street":"Washington Ave",
    "iso:country":"US",
    "sg:address":"861 Washington Ave",
    "sg:city":"Chestertown",
    "sg:classifiers":[
        {
            "category":"Professional",
            "subcategory":"Advertising",
            "type":"Services"
        }
    ],
    "sg:phone":"+1 410 778 9446",
    "sg:postcode":"21620",
    "sg:province":"MD",
    "sg:tags":[
        "mailing",
        "shipping"
    ],
    "wof:name":"UPS Store",
    "wof:placetype":"venue"
},
  "geometry": {"coordinates":[-76.07264000000001,39.229451],"type":"Point"}
}