{
  "type": "Feature",
  "properties": {
    "iso:country":"US",
    "sg:address":"77 S Washington St",
    "sg:city":"Rockville",
    "sg:classifiers":[
        {
            "category":"Banks & Credit Unions",
            "subcategory":"Bank",
            "type":"Services"
        }
    ],
    "sg:phone":"+1 301 610 0888",
    "sg:postcode":"20850",
    "sg:province":"MD",
    "sg:tags":[
        "loan"
    ],
    "wof:name":"Equity Abstracts Inc",
    "wof:placetype":"venue"
},
  "geometry": {"coordinates":[-77.15295999999999,39.083947],"type":"Point"}
}