{
  "type": "Feature",
  "properties": {
    "addr:full":"1700 Madison Ave Baltimore MD 21217",
    "addr:housenumber":"1700",
    "addr:postcode":"21217",
    "addr:street":"Madison Ave",
    "iso:country":"US",
    "sg:address":"1700 Madison Ave",
    "sg:city":"Baltimore",
    "sg:classifiers":[
        {
            "category":"Personal",
            "subcategory":"Beauty Salon",
            "type":"Services"
        }
    ],
    "sg:phone":"+1 410 669 1147",
    "sg:postcode":"21217",
    "sg:province":"MD",
    "wof:name":"Estelle D Houston",
    "wof:placetype":"venue"
},
  "geometry": {"coordinates":[-76.631874,39.3071],"type":"Point"}
}