{
  "type": "Feature",
  "properties": {
    "addr:full":"3129 Pennsy Dr Landover MD 20785",
    "addr:housenumber":"3129",
    "addr:postcode":"20785",
    "addr:street":"Pennsy Dr",
    "iso:country":"US",
    "sg:address":"3129 Pennsy Dr",
    "sg:city":"Landover",
    "sg:classifiers":[
        {
            "category":"Wholesale",
            "subcategory":"Dairy",
            "type":"Manufacturing & Wholesale Goods"
        }
    ],
    "sg:phone":"+1 301 583 8404",
    "sg:postcode":"20785",
    "sg:province":"MD",
    "sg:tags":[
        "product"
    ],
    "wof:name":"Instantwhip-Baltimore Inc",
    "wof:placetype":"venue"
},
  "geometry": {"coordinates":[-76.887951,38.932663],"type":"Point"}
}