{
  "type": "Feature",
  "properties": {
    "addr:full":"301 Fallsway Baltimore MD 21202",
    "addr:housenumber":"301",
    "addr:postcode":"21202",
    "addr:street":"Fallsway",
    "iso:country":"US",
    "sg:address":"301 Fallsway",
    "sg:city":"Baltimore",
    "sg:classifiers":[
        {
            "category":"Home & Garden",
            "subcategory":"Furniture",
            "type":"Retail Goods"
        }
    ],
    "sg:phone":"+1 410 685 4545",
    "sg:postcode":"21202",
    "sg:province":"MD",
    "sg:tags":[
        "store"
    ],
    "wof:name":"Furncraft Wholesale Furniture Co",
    "wof:placetype":"venue"
},
  "geometry": {"coordinates":[-76.607597,39.292198],"type":"Point"}
}