{
  "type": "Feature",
  "properties": {
    "addr:full":"9715 Medical Center Dr # 101 Rockville MD 20850",
    "addr:housenumber":"9715",
    "addr:postcode":"20850",
    "addr:street":"Medical Center Dr # 101",
    "iso:country":"US",
    "sg:address":"9715 Medical Center Dr # 101",
    "sg:city":"Rockville",
    "sg:classifiers":[
        {
            "category":"Professional",
            "type":"Services"
        },
        {
            "category":"Restaurant",
            "type":"Food & Drink"
        }
    ],
    "sg:phone":"+1 301 424 8108",
    "sg:postcode":"20850",
    "sg:province":"MD",
    "sg:tags":[
        "lunch",
        "brunch",
        "breakfast",
        "caterer"
    ],
    "wof:name":"Royal Lunch Box",
    "wof:placetype":"venue"
},
  "geometry": {"coordinates":[-77.195437,39.098461],"type":"Point"}
}