{
  "type": "Feature",
  "properties": {
    "iso:country":"US",
    "sg:address":"838 State Hwy 2",
    "sg:city":"Severna Park",
    "sg:classifiers":[
        {
            "category":"Insurance",
            "subcategory":"Insurance Agent",
            "type":"Services"
        }
    ],
    "sg:phone":"+1 410 315 8200",
    "sg:postcode":"21146",
    "sg:province":"MD",
    "sg:tags":[
        "adjuster"
    ],
    "sg:website":"www.nardonenet.com",
    "wof:name":"Nardone & Co",
    "wof:placetype":"venue"
},
  "geometry": {"coordinates":[-76.53201799999999,39.0624],"type":"Point"}
}