{
  "type": "Feature",
  "properties": {
    "addr:full":"4041 Conowingo Rd Darlington MD 21034",
    "addr:housenumber":"4041",
    "addr:postcode":"21034",
    "addr:street":"Conowingo Rd",
    "iso:country":"US",
    "sg:address":"4041 Conowingo Rd",
    "sg:city":"Darlington",
    "sg:classifiers":[
        {
            "category":"Building & Trades",
            "subcategory":"Landscaping Services",
            "type":"Services"
        }
    ],
    "sg:phone":"+1 410 652 8756",
    "sg:postcode":"21034",
    "sg:province":"MD",
    "sg:tags":[
        "landscape",
        "contractor"
    ],
    "wof:name":"Freedom Lawn & Landscape",
    "wof:placetype":"venue"
},
  "geometry": {"coordinates":[-76.24656400000001,39.647545],"type":"Point"}
}