{
  "type": "Feature",
  "properties": {
    "addr:full":"10919 Adkins Rd Berlin MD 21811",
    "addr:housenumber":"10919",
    "addr:postcode":"21811",
    "addr:street":"Adkins Rd",
    "iso:country":"US",
    "sg:address":"10919 Adkins Rd",
    "sg:city":"Berlin",
    "sg:classifiers":[
        {
            "category":"Social Services",
            "subcategory":"Child Care",
            "type":"Services"
        }
    ],
    "sg:phone":"+1 410 641 5748",
    "sg:postcode":"21811",
    "sg:province":"MD",
    "sg:tags":[
        "day"
    ],
    "wof:name":"Daniel Langworthy",
    "wof:placetype":"venue"
},
  "geometry": {"coordinates":[-75.181428,38.364499],"type":"Point"}
}