{
  "type": "Feature",
  "properties": {
    "iso:country":"US",
    "sg:address":"3056 Westminster St",
    "sg:city":"Manchester",
    "sg:classifiers":[
        {
            "category":"Building & Trades",
            "subcategory":"Electrical",
            "type":"Services"
        }
    ],
    "sg:phone":"+1 410 374 5641",
    "sg:postcode":"21102",
    "sg:province":"MD",
    "sg:tags":[
        "electric",
        "contractor"
    ],
    "wof:name":"Echo Electrical Enterprises",
    "wof:placetype":"venue"
},
  "geometry": {"coordinates":[-76.887512,39.660265],"type":"Point"}
}