{
  "type": "Feature",
  "properties": {
    "iso:country":"US",
    "sg:address":"1388 Defense Hwy",
    "sg:city":"Gambrills",
    "sg:classifiers":[
        {
            "category":"Insurance",
            "subcategory":"Hazard Insurance",
            "type":"Services"
        }
    ],
    "sg:phone":"+1 410 774 0867",
    "sg:postcode":"21054",
    "sg:province":"MD",
    "sg:website":"http://www.maderinsurance.net",
    "wof:name":"Mader Craig S Insurance Incorporated",
    "wof:placetype":"venue"
},
  "geometry": {"coordinates":[-76.67902100000001,38.992175],"type":"Point"}
}