{
  "type": "Feature",
  "properties": {
    "addr:full":"12416 Benson Branch Rd Ellicott City MD 21042",
    "addr:housenumber":"12416",
    "addr:postcode":"21042",
    "addr:street":"Benson Branch Rd",
    "iso:country":"US",
    "sg:address":"12416 Benson Branch Rd",
    "sg:city":"Ellicott City",
    "sg:classifiers":[
        {
            "category":"Building & Trades",
            "subcategory":"Plumbing",
            "type":"Services"
        }
    ],
    "sg:phone":"+1 443 535 9487",
    "sg:postcode":"21042",
    "sg:province":"MD",
    "sg:tags":[
        "mechanical",
        "contractor"
    ],
    "wof:name":"Caigeann Mechanical Co Inc",
    "wof:placetype":"venue"
},
  "geometry": {"coordinates":[-76.944914,39.275597],"type":"Point"}
}