{
  "type": "Feature",
  "properties": {
    "addr:full":"196 Pennsylvania Ave Westminster MD 21157",
    "addr:housenumber":"196",
    "addr:postcode":"21157",
    "addr:street":"Pennsylvania Ave",
    "iso:country":"US",
    "sg:address":"196 Pennsylvania Ave",
    "sg:city":"Westminster",
    "sg:classifiers":[
        {
            "category":"Building & Trades",
            "subcategory":"Plumbing",
            "type":"Services"
        }
    ],
    "sg:phone":"+1 410 848 1000",
    "sg:postcode":"21157",
    "sg:province":"MD",
    "sg:tags":[
        "mechanical",
        "contractor"
    ],
    "wof:name":"Maryland Mechanical Corp",
    "wof:placetype":"venue"
},
  "geometry": {"coordinates":[-76.99901800000001,39.587485],"type":"Point"}
}