{
  "type": "Feature",
  "properties": {
    "addr:full":"617 Baldwin Dr Joppa MD 21085",
    "addr:housenumber":"617",
    "addr:postcode":"21085",
    "addr:street":"Baldwin Dr",
    "iso:country":"US",
    "sg:address":"617 Baldwin Dr",
    "sg:city":"Joppa",
    "sg:classifiers":[
        {
            "category":"Autos & Motor Vehicles",
            "subcategory":"Automobile Sales",
            "type":"Retail Goods"
        }
    ],
    "sg:phone":"+1 410 679 0237",
    "sg:postcode":"21085",
    "sg:province":"MD",
    "sg:tags":[
        "car",
        "used"
    ],
    "wof:name":"Jay S Auto Sales",
    "wof:placetype":"venue"
},
  "geometry": {"coordinates":[-76.357387,39.420898],"type":"Point"}
}