{
  "type": "Feature",
  "properties": {
    "iso:country":"US",
    "sg:address":"822 E Baltimore St",
    "sg:city":"Baltimore",
    "sg:classifiers":[
        {
            "category":"Education",
            "subcategory":"Special Training",
            "type":"Public Place"
        }
    ],
    "sg:phone":"+1 410 685 3224",
    "sg:postcode":"21202",
    "sg:province":"MD",
    "sg:tags":[
        "tutoring"
    ],
    "wof:name":"Brook Cherith Financial",
    "wof:placetype":"venue"
},
  "geometry": {"coordinates":[-76.605317,39.290074],"type":"Point"}
}