{
  "type": "Feature",
  "properties": {
    "iso:country":"US",
    "sg:address":"2231 Eastern Ave",
    "sg:city":"Baltimore",
    "sg:classifiers":[
        {
            "category":"Retail",
            "subcategory":"Repair Shop",
            "type":"Services"
        }
    ],
    "sg:phone":"+1 410 675 7886",
    "sg:postcode":"21231",
    "sg:province":"MD",
    "sg:tags":[
        "taxidermist"
    ],
    "wof:name":"A1 Taxidermist Thomas",
    "wof:placetype":"venue"
},
  "geometry": {"coordinates":[-76.58501099999999,39.285913],"type":"Point"}
}