{
  "type": "Feature",
  "properties": {
    "addr:full":"8328 Veterans Hwy Ste G Millersville MD 21108",
    "addr:housenumber":"8328",
    "addr:postcode":"21108",
    "addr:street":"Veterans Hwy Ste G",
    "iso:country":"US",
    "sg:address":"8328 Veterans Hwy Ste G",
    "sg:city":"Millersville",
    "sg:classifiers":[
        {
            "category":"Home & Garden",
            "subcategory":"Furniture",
            "type":"Retail Goods"
        }
    ],
    "sg:phone":"+1 410 987 2272",
    "sg:postcode":"21108",
    "sg:province":"MD",
    "sg:tags":[
        "store"
    ],
    "wof:name":"Unique Furnishings & Design Ll",
    "wof:placetype":"venue"
},
  "geometry": {"coordinates":[-76.63018,39.109508],"type":"Point"}
}