{
  "type": "Feature",
  "properties": {
    "iso:country":"US",
    "sg:address":"4105 Alton St",
    "sg:city":"Capitol Heights",
    "sg:classifiers":[
        {
            "category":"Organizations",
            "subcategory":"Religious Organization",
            "type":"Services"
        }
    ],
    "sg:phone":"+1 301 420 2427",
    "sg:postcode":"20743",
    "sg:province":"MD",
    "sg:tags":[
        "church"
    ],
    "wof:name":"New Life Christian Ctr",
    "wof:placetype":"venue"
},
  "geometry": {"coordinates":[-76.935405,38.866898],"type":"Point"}
}