{
  "type": "Feature",
  "properties": {
    "addr:full":"9150 Baltimore National Pike Ellicott City MD 21042",
    "addr:housenumber":"9150",
    "addr:postcode":"21042",
    "addr:street":"Baltimore National Pike",
    "iso:country":"US",
    "sg:address":"9150 Baltimore National Pike",
    "sg:city":"Ellicott City",
    "sg:classifiers":[
        {
            "category":"Shopping",
            "subcategory":"Pharmacy",
            "type":"Retail Goods"
        }
    ],
    "sg:phone":"+1 410 465 4666",
    "sg:postcode":"21042",
    "sg:province":"MD",
    "sg:tags":[
        "photofinishing",
        "laboratory"
    ],
    "wof:name":"Rite Aid",
    "wof:placetype":"venue"
},
  "geometry": {"coordinates":[-76.827564,39.276929],"type":"Point"}
}