{
  "type": "Feature",
  "properties": {
    "iso:country":"US",
    "sg:address":"7969 Riggs Rd",
    "sg:city":"Hyattsville",
    "sg:classifiers":[
        {
            "category":"Professional",
            "type":"Services"
        }
    ],
    "sg:phone":"+1 301 439 6597",
    "sg:postcode":"20783",
    "sg:province":"MD",
    "wof:name":"PO Services",
    "wof:placetype":"venue"
},
  "geometry": {"coordinates":[-76.975627,38.986935],"type":"Point"}
}