{
  "type": "Feature",
  "properties": {
    "iso:country":"US",
    "sg:address":"10112 Quiet Water Way",
    "sg:city":"Jessup",
    "sg:classifiers":[
        {
            "category":"Place Of Worship",
            "subcategory":"Church",
            "type":"Public Place"
        },
        {
            "category":"Place Of Worship",
            "type":"Public Place"
        }
    ],
    "sg:phone":"+1 301 497 9684",
    "sg:postcode":"20794",
    "sg:province":"MD",
    "sg:tags":[
        "christ",
        "churches-community"
    ],
    "wof:name":"Total Restoration Community Church",
    "wof:placetype":"venue"
},
  "geometry": {"coordinates":[-76.81470400000001,39.146221],"type":"Point"}
}