{
  "type": "Feature",
  "properties": {
    "iso:country":"US",
    "sg:address":"1761 Charles Rd",
    "sg:city":"Millersville",
    "sg:classifiers":[
        {
            "category":"Health Services",
            "subcategory":"Dentist",
            "type":"Services"
        }
    ],
    "sg:phone":"+1 410 923 2319",
    "sg:postcode":"21108",
    "sg:province":"MD",
    "wof:name":"Rose Family Partners",
    "wof:placetype":"venue"
},
  "geometry": {"coordinates":[-76.649748,39.050538],"type":"Point"}
}