{
  "type": "Feature",
  "properties": {
    "iso:country":"US",
    "sg:address":"5955 Quinn Orchard Rd",
    "sg:city":"Frederick",
    "sg:classifiers":[
        {
            "category":"Health Services",
            "subcategory":"Clinic",
            "type":"Services"
        },
        {
            "category":"Health Services",
            "subcategory":"Health Practitioner",
            "type":"Services"
        }
    ],
    "sg:phone":"+1 301 228 2741",
    "sg:postcode":"21704",
    "sg:province":"MD",
    "sg:tags":[
        "information",
        "addiction-information",
        "treatment",
        "alcoholism",
        "gambling"
    ],
    "wof:name":"Towson Rehabilitation Cntr",
    "wof:placetype":"venue"
},
  "geometry": {"coordinates":[-77.38087,39.396946],"type":"Point"}
}