{
  "type": "Feature",
  "properties": {
    "addr:full":"689 Lofstrand Ln Rockville MD 20850",
    "addr:housenumber":"689",
    "addr:postcode":"20850",
    "addr:street":"Lofstrand Ln",
    "iso:country":"US",
    "sg:address":"689 Lofstrand Ln",
    "sg:city":"Rockville",
    "sg:classifiers":[
        {
            "category":"Retail",
            "subcategory":"Auto Repair",
            "type":"Services"
        }
    ],
    "sg:phone":"+1 301 251 0121",
    "sg:postcode":"20850",
    "sg:province":"MD",
    "sg:tags":[
        "truck"
    ],
    "wof:name":"Auto Truck & Rv",
    "wof:placetype":"venue"
},
  "geometry": {"coordinates":[-77.137716,39.096441],"type":"Point"}
}