{
  "type": "Feature",
  "properties": {
    "addr:full":"6204 Frankford Ave Baltimore MD 21206",
    "addr:housenumber":"6204",
    "addr:postcode":"21206",
    "addr:street":"Frankford Ave",
    "iso:country":"US",
    "sg:address":"6204 Frankford Ave",
    "sg:city":"Baltimore",
    "sg:classifiers":[
        {
            "category":"Manufacturing",
            "subcategory":"Metals",
            "type":"Manufacturing & Wholesale Goods"
        }
    ],
    "sg:phone":"+1 410 485 9302",
    "sg:postcode":"21206",
    "sg:province":"MD",
    "sg:tags":[
        "plate",
        "tin"
    ],
    "wof:name":"Tin Star Co",
    "wof:placetype":"venue"
},
  "geometry": {"coordinates":[-76.540081,39.318978],"type":"Point"}
}