{
  "type": "Feature",
  "properties": {
    "iso:country":"US",
    "sg:address":"405 Sanders St",
    "sg:city":"Baltimore",
    "sg:classifiers":[
        {
            "category":"Wholesale",
            "subcategory":"Non-durable Goods",
            "type":"Manufacturing & Wholesale Goods"
        }
    ],
    "sg:phone":"+1 410 230 0649",
    "sg:postcode":"21230",
    "sg:province":"MD",
    "sg:tags":[
        "product",
        "advertising-promotional",
        "specialty",
        "ad"
    ],
    "wof:name":"Gil Ball Graphic Design",
    "wof:placetype":"venue"
},
  "geometry": {"coordinates":[-76.60874800000001,39.275844],"type":"Point"}
}