{
  "type": "Feature",
  "properties": {
    "iso:country":"US",
    "sg:address":"1180 Great Oak Ct",
    "sg:city":"Crownsville",
    "sg:classifiers":[
        {
            "category":"Health Services",
            "subcategory":"Doctor",
            "type":"Services"
        }
    ],
    "sg:phone":"+1 410 987 8127",
    "sg:postcode":"21032",
    "sg:province":"MD",
    "sg:tags":[
        "pediatrician"
    ],
    "wof:name":"Archie S Golden MD",
    "wof:placetype":"venue"
},
  "geometry": {"coordinates":[-76.593394,39.043957],"type":"Point"}
}