{
  "type": "Feature",
  "properties": {
    "iso:country":"US",
    "sg:address":"5444 Belair Rd Ste A",
    "sg:city":"Baltimore",
    "sg:classifiers":[
        {
            "category":"Place Of Worship",
            "subcategory":"Church",
            "type":"Public Place"
        },
        {
            "category":"Place Of Worship",
            "type":"Public Place"
        },
        {
            "category":"Organizations",
            "subcategory":"Religious Organization",
            "type":"Services"
        }
    ],
    "sg:phone":"+1 410 488 4370",
    "sg:postcode":"21206",
    "sg:province":"MD",
    "sg:tags":[
        "churches-interdenominational",
        "churches-various",
        "denomination"
    ],
    "wof:name":"New Joy Church",
    "wof:placetype":"venue"
},
  "geometry": {"coordinates":[-76.55007000000001,39.339333],"type":"Point"}
}