{
  "type": "Feature",
  "properties": {
    "addr:full":"16701 Melford Blvd Ste. 120 Bowie MD 20715",
    "addr:postcode":"16701;20715",
    "addr:street":"Melford Blvd Ste. 120",
    "iso:country":"US",
    "sg:address":"16701 Melford Blvd Ste. 120",
    "sg:city":"Bowie",
    "sg:classifiers":[
        {
            "category":"Professional",
            "subcategory":"Employment Agencies",
            "type":"Services"
        }
    ],
    "sg:phone":"+1 877 237 4790",
    "sg:postcode":"20715",
    "sg:province":"MD",
    "sg:tags":[
        "opportunity",
        "consultant",
        "temporary",
        "contractor"
    ],
    "sg:website":"http://www-aerotek-com.netsolads.com/?LEC-6UM982376821&_nsag=33207",
    "wof:name":"Aerotek",
    "wof:placetype":"venue"
},
  "geometry": {"coordinates":[-76.712841,38.960161],"type":"Point"}
}