{
  "type": "Feature",
  "properties": {
    "addr:full":"9240 Bridle Path Ln Laurel MD 20723",
    "addr:housenumber":"9240",
    "addr:postcode":"20723",
    "addr:street":"Bridle Path Ln",
    "iso:country":"US",
    "sg:address":"9240 Bridle Path Ln",
    "sg:city":"Laurel",
    "sg:classifiers":[
        {
            "category":"Professional",
            "subcategory":"Management & Consulting",
            "type":"Services"
        }
    ],
    "sg:phone":"+1 301 497 0361",
    "sg:postcode":"20723",
    "sg:province":"MD",
    "sg:tags":[
        "business"
    ],
    "wof:name":"Vincent Fekete Consultant",
    "wof:placetype":"venue"
},
  "geometry": {"coordinates":[-76.845111,39.117808],"type":"Point"}
}