{
  "type": "Feature",
  "properties": {
    "iso:country":"US",
    "sg:address":"327 W 7th St",
    "sg:city":"Frederick",
    "sg:classifiers":[
        {
            "category":"Personal",
            "subcategory":"Nail Salon",
            "type":"Services"
        }
    ],
    "sg:phone":"+1 301 620 2261",
    "sg:postcode":"21701",
    "sg:province":"MD",
    "wof:name":"La Villa Nails",
    "wof:placetype":"venue"
},
  "geometry": {"coordinates":[-77.41341300000001,39.423532],"type":"Point"}
}