{
  "type": "Feature",
  "properties": {
    "iso:country":"US",
    "sg:address":"3401 Bladensburg Rd",
    "sg:city":"Brentwood",
    "sg:classifiers":[
        {
            "category":"Real Estate",
            "subcategory":"Developer",
            "type":"Services"
        }
    ],
    "sg:phone":"+1 301 864 5090",
    "sg:postcode":"20722",
    "sg:province":"MD",
    "sg:tags":[
        "cemetery"
    ],
    "wof:name":"Fort Lincoln Funeral Home",
    "wof:placetype":"venue"
},
  "geometry": {"coordinates":[-76.95733199999999,38.930935],"type":"Point"}
}