{
  "type": "Feature",
  "properties": {
    "addr:full":"101 Ridgely Ave Annapolis MD 21401",
    "addr:housenumber":"101",
    "addr:postcode":"21401",
    "addr:street":"Ridgely Ave",
    "iso:country":"US",
    "sg:address":"101 Ridgely Ave",
    "sg:city":"Annapolis",
    "sg:classifiers":[
        {
            "category":"Health Services",
            "subcategory":"Dentist",
            "type":"Services"
        }
    ],
    "sg:phone":"+1 410 267 0766",
    "sg:postcode":"21401",
    "sg:province":"MD",
    "sg:tags":[
        "dentists-cosmetic",
        "denture",
        "dental",
        "dentists-pediatric",
        "clinic",
        "dentistry",
        "dentists-prosthodontists"
    ],
    "sg:website":"http://www.annapolisdentistmd.com",
    "wof:name":"Annapolis Dental Care",
    "wof:placetype":"venue"
},
  "geometry": {"coordinates":[-76.503052,38.989262],"type":"Point"}
}