{
  "type": "Feature",
  "properties": {
    "addr:full":"1300 Poplar Grove St Baltimore MD 21216",
    "addr:housenumber":"1300",
    "addr:postcode":"21216",
    "addr:street":"Poplar Grove St",
    "iso:country":"US",
    "sg:address":"1300 Poplar Grove St",
    "sg:city":"Baltimore",
    "sg:classifiers":[
        {
            "category":"Restaurant",
            "type":"Food & Drink"
        }
    ],
    "sg:phone":"+1 410 945 6614",
    "sg:postcode":"21216",
    "sg:province":"MD",
    "sg:tags":[
        "eating",
        "out"
    ],
    "wof:name":"K & K Carry Out",
    "wof:placetype":"venue"
},
  "geometry": {"coordinates":[-76.665398,39.302443],"type":"Point"}
}