{
  "type": "Feature",
  "properties": {
    "addr:full":"6797 Bowmans Xing Frederick MD 21703",
    "addr:housenumber":"6797",
    "addr:postcode":"21703",
    "addr:street":"Bowmans Xing",
    "iso:country":"US",
    "sg:address":"6797 Bowmans Xing",
    "sg:city":"Frederick",
    "sg:classifiers":[
        {
            "category":"Manufacturing",
            "subcategory":"Printing",
            "type":"Manufacturing & Wholesale Goods"
        }
    ],
    "sg:phone":"+1 301 696 9629",
    "sg:postcode":"21703",
    "sg:province":"MD",
    "sg:tags":[
        "printer"
    ],
    "wof:name":"Pacemaker Press Inc",
    "wof:placetype":"venue"
},
  "geometry": {"coordinates":[-77.43148100000001,39.359764],"type":"Point"}
}