{
  "type": "Feature",
  "properties": {
    "addr:full":"8201 Coastal Hwy Ocean City MD 21842",
    "addr:housenumber":"8201",
    "addr:postcode":"21842",
    "addr:street":"Coastal Hwy",
    "iso:country":"US",
    "sg:address":"8201 Coastal Hwy",
    "sg:city":"Ocean City",
    "sg:classifiers":[
        {
            "category":"Shopping",
            "subcategory":"Jewelry",
            "type":"Retail Goods"
        }
    ],
    "sg:phone":"+1 410 524 4353",
    "sg:postcode":"21842",
    "sg:province":"MD",
    "sg:tags":[
        "jeweler"
    ],
    "wof:name":"Harry's Collection 82nd St",
    "wof:placetype":"venue"
},
  "geometry": {"coordinates":[-75.061019,38.401807],"type":"Point"}
}