{
  "type": "Feature",
  "properties": {
    "addr:full":"1005 Bishop Walsh Rd Cumberland MD 21502",
    "addr:housenumber":"1005",
    "addr:postcode":"21502",
    "addr:street":"Bishop Walsh Rd",
    "iso:country":"US",
    "sg:address":"1005 Bishop Walsh Rd",
    "sg:city":"Cumberland",
    "sg:classifiers":[
        {
            "category":"Organizations",
            "subcategory":"Religious Organization",
            "type":"Services"
        }
    ],
    "sg:phone":"+1 301 777 1670",
    "sg:postcode":"21502",
    "sg:province":"MD",
    "wof:name":"Grace Memorial Cmnty Church",
    "wof:placetype":"venue"
},
  "geometry": {"coordinates":[-78.79846999999999,39.650876],"type":"Point"}
}