{
  "type": "Feature",
  "properties": {
    "iso:country":"US",
    "sg:address":"151 Rock Springs Rd",
    "sg:city":"Conowingo",
    "sg:classifiers":[
        {
            "category":"Organizations",
            "subcategory":"Religious Organization",
            "type":"Services"
        }
    ],
    "sg:phone":"+1 410 658 3441",
    "sg:postcode":"21918",
    "sg:province":"MD",
    "sg:tags":[
        "church"
    ],
    "sg:website":"www.conowingo.org",
    "wof:name":"Conowingo Baptist Church",
    "wof:placetype":"venue"
},
  "geometry": {"coordinates":[-76.162148,39.681157],"type":"Point"}
}