{
  "type": "Feature",
  "properties": {
    "iso:country":"US",
    "sg:address":"7127 Fountain Rock Way",
    "sg:city":"Columbia",
    "sg:classifiers":[
        {
            "category":"Autos & Motor Vehicles",
            "subcategory":"Auto Supplies",
            "type":"Retail Goods"
        }
    ],
    "sg:phone":"+1 410 381 4660",
    "sg:postcode":"21046",
    "sg:province":"MD",
    "sg:tags":[
        "equipment",
        "racing",
        "car",
        "automobile"
    ],
    "wof:name":"Festiva Motor Sport",
    "wof:placetype":"venue"
},
  "geometry": {"coordinates":[-76.865195,39.173958],"type":"Point"}
}