{
  "type": "Feature",
  "properties": {
    "addr:full":"1114 Kevin Rd Baltimore MD 21229",
    "addr:housenumber":"1114",
    "addr:postcode":"21229",
    "addr:street":"Kevin Rd",
    "iso:country":"US",
    "sg:address":"1114 Kevin Rd",
    "sg:city":"Baltimore",
    "sg:classifiers":[
        {
            "category":"Communications",
            "type":"Services"
        }
    ],
    "sg:phone":"+1 443 790 2637",
    "sg:postcode":"21229",
    "sg:province":"MD",
    "sg:tags":[
        "consultant",
        "telecommunication"
    ],
    "wof:name":"Saw Group, The",
    "wof:placetype":"venue"
},
  "geometry": {"coordinates":[-76.69000699999999,39.298345],"type":"Point"}
}