{
  "type": "Feature",
  "properties": {
    "iso:country":"US",
    "sg:address":"1009 N Washington St",
    "sg:city":"Easton",
    "sg:classifiers":[
        {
            "category":"Organizations",
            "subcategory":"Religious Organization",
            "type":"Services"
        }
    ],
    "sg:phone":"+1 410 822 7496",
    "sg:postcode":"21601",
    "sg:province":"MD",
    "sg:tags":[
        "church"
    ],
    "sg:website":"www.eastoncog.org",
    "wof:name":"Easton Church Of God",
    "wof:placetype":"venue"
},
  "geometry": {"coordinates":[-76.06554300000001,38.793903],"type":"Point"}
}