{
  "type": "Feature",
  "properties": {
    "addr:full":"1907 Seminary Rd Silver Spring MD 20910",
    "addr:housenumber":"1907",
    "addr:postcode":"20910",
    "addr:street":"Seminary Rd",
    "iso:country":"US",
    "sg:address":"1907 Seminary Rd",
    "sg:city":"Silver Spring",
    "sg:classifiers":[
        {
            "category":"Personal",
            "subcategory":"Beauty Salon",
            "type":"Services"
        }
    ],
    "sg:phone":"+1 301 588 9742",
    "sg:postcode":"20910",
    "sg:province":"MD",
    "wof:name":"Hair Cuttery",
    "wof:placetype":"venue"
},
  "geometry": {"coordinates":[-77.041031,39.008714],"type":"Point"}
}