{
  "type": "Feature",
  "properties": {
    "iso:country":"US",
    "sg:address":"3085 Frost Way",
    "sg:city":"Hampstead",
    "sg:classifiers":[
        {
            "category":"Shopping",
            "subcategory":"Computers & Home Electronics",
            "type":"Retail Goods"
        }
    ],
    "sg:phone":"+1 410 239 2373",
    "sg:postcode":"21074",
    "sg:province":"MD",
    "sg:tags":[
        "software"
    ],
    "sg:website":"www.sparkgroup.net",
    "wof:name":"Spark Group Inc",
    "wof:placetype":"venue"
},
  "geometry": {"coordinates":[-76.88655799999999,39.571771],"type":"Point"}
}