{
  "type": "Feature",
  "properties": {
    "iso:country":"US",
    "sg:address":"44 Avondale St",
    "sg:city":"Laurel",
    "sg:classifiers":[
        {
            "category":"Retail",
            "subcategory":"Auto Repair",
            "type":"Services"
        }
    ],
    "sg:phone":"+1 301 725 3423",
    "sg:postcode":"20707",
    "sg:province":"MD",
    "wof:name":"Midway Garage",
    "wof:placetype":"venue"
},
  "geometry": {"coordinates":[-76.845901,39.105301],"type":"Point"}
}