{
  "type": "Feature",
  "properties": {
    "addr:full":"4923 Eastern Ave Baltimore MD 21224",
    "addr:housenumber":"4923",
    "addr:postcode":"21224",
    "addr:street":"Eastern Ave",
    "iso:country":"US",
    "sg:address":"4923 Eastern Ave",
    "sg:city":"Baltimore",
    "sg:classifiers":[
        {
            "category":"Restaurant",
            "type":"Food & Drink"
        }
    ],
    "sg:phone":"+1 410 633 0064",
    "sg:postcode":"21224",
    "sg:province":"MD",
    "wof:name":"Bruno's Pizza",
    "wof:placetype":"venue"
},
  "geometry": {"coordinates":[-76.55422,39.287063],"type":"Point"}
}