{
  "type": "Feature",
  "properties": {
    "iso:country":"US",
    "sg:address":"12604 Brunswick Ln",
    "sg:city":"Bowie",
    "sg:classifiers":[
        {
            "category":"Professional",
            "type":"Services"
        }
    ],
    "sg:phone":"+1 301 262 9426",
    "sg:postcode":"20715",
    "sg:province":"MD",
    "wof:name":"Margaret M Suddeth",
    "wof:placetype":"venue"
},
  "geometry": {"coordinates":[-76.732878,38.97281],"type":"Point"}
}