{
  "type": "Feature",
  "properties": {
    "iso:country":"US",
    "sg:address":"14 W Main St",
    "sg:city":"Thurmont",
    "sg:classifiers":[
        {
            "category":"Professional",
            "subcategory":"Computer Services",
            "type":"Services"
        }
    ],
    "sg:phone":"+1 301 271 3167",
    "sg:postcode":"21788",
    "sg:province":"MD",
    "sg:tags":[
        "related"
    ],
    "wof:name":"Brault Consulting",
    "wof:placetype":"venue"
},
  "geometry": {"coordinates":[-77.413303,39.623995],"type":"Point"}
}