{
  "type": "Feature",
  "properties": {
    "addr:full":"2601 Georgetown Rd Baltimore MD 21230",
    "addr:housenumber":"2601",
    "addr:postcode":"21230",
    "addr:street":"Georgetown Rd",
    "iso:country":"US",
    "sg:address":"2601 Georgetown Rd",
    "sg:city":"Baltimore",
    "sg:classifiers":[
        {
            "category":"Wholesale",
            "subcategory":"Machinery & Supplies",
            "type":"Manufacturing & Wholesale Goods"
        }
    ],
    "sg:phone":"+1 410 368 8333",
    "sg:postcode":"21230",
    "sg:province":"MD",
    "sg:tags":[
        "printing",
        "word",
        "processing"
    ],
    "wof:name":"A & S Graphic Supplies",
    "wof:placetype":"venue"
},
  "geometry": {"coordinates":[-76.657954,39.268334],"type":"Point"}
}