{
  "type": "Feature",
  "properties": {
    "iso:country":"US",
    "sg:address":"1319 Robin Rd",
    "sg:city":"Pikesville",
    "sg:classifiers":[
        {
            "category":"Banks & Credit Unions",
            "subcategory":"Investment Brokerage",
            "type":"Services"
        }
    ],
    "sg:phone":"+1 410 486 4049",
    "sg:postcode":"21208",
    "sg:province":"MD",
    "sg:tags":[
        "transfer",
        "agent",
        "security",
        "bond",
        "stock"
    ],
    "wof:name":"Bey Enterprises Inc",
    "wof:placetype":"venue"
},
  "geometry": {"coordinates":[-76.73702299999999,39.371253],"type":"Point"}
}