{
  "type": "Feature",
  "properties": {
    "iso:country":"US",
    "sg:address":"3424 Arcadia Dr",
    "sg:city":"Ellicott City",
    "sg:classifiers":[
        {
            "category":"Professional",
            "subcategory":"Detective & Security Services",
            "type":"Services"
        }
    ],
    "sg:phone":"+1 410 418 5915",
    "sg:postcode":"21042",
    "sg:province":"MD",
    "sg:tags":[
        "investigation",
        "background"
    ],
    "wof:name":"Dennis M Cadigan",
    "wof:placetype":"venue"
},
  "geometry": {"coordinates":[-76.839026,39.276672],"type":"Point"}
}