{
  "type": "Feature",
  "properties": {
    "iso:country":"US",
    "sg:address":"8601 Cunningham Dr",
    "sg:city":"College Park",
    "sg:classifiers":[
        {
            "category":"Building & Trades",
            "subcategory":"Construction",
            "type":"Services"
        }
    ],
    "sg:phone":"+1 301 345 2382",
    "sg:postcode":"20740",
    "sg:province":"MD",
    "sg:tags":[
        "floor",
        "laying",
        "contractor"
    ],
    "wof:name":"Masco",
    "wof:placetype":"venue"
},
  "geometry": {"coordinates":[-76.913134,38.992253],"type":"Point"}
}