{
  "type": "Feature",
  "properties": {
    "iso:country":"US",
    "sg:address":"3410 Epic Gate",
    "sg:city":"Bowie",
    "sg:classifiers":[
        {
            "category":"Building & Trades",
            "subcategory":"Equipment Rental",
            "type":"Services"
        },
        {
            "category":"Shopping",
            "subcategory":"Computers & Home Electronics",
            "type":"Retail Goods"
        }
    ],
    "sg:phone":"+1 301 390 3220",
    "sg:postcode":"20716",
    "sg:province":"MD",
    "sg:tags":[
        "sound",
        "audio-visual",
        "leasing",
        "system",
        "equipment-renting"
    ],
    "wof:name":"Dave Strebe",
    "wof:placetype":"venue"
},
  "geometry": {"coordinates":[-76.736182,38.938741],"type":"Point"}
}