{
  "type": "Feature",
  "properties": {
    "iso:country":"US",
    "sg:address":"2245 E Fayette St",
    "sg:city":"Baltimore",
    "sg:classifiers":[
        {
            "category":"Food & Beverages",
            "subcategory":"Groceries & Convenience Stores",
            "type":"Retail Goods"
        }
    ],
    "sg:phone":"+1 410 534 4400",
    "sg:postcode":"21231",
    "sg:province":"MD",
    "sg:tags":[
        "grocer"
    ],
    "wof:name":"Patterson Food Market",
    "wof:placetype":"venue"
},
  "geometry": {"coordinates":[-76.585018,39.294236],"type":"Point"}
}