{
  "type": "Feature",
  "properties": {
    "iso:country":"US",
    "sg:address":"5222 Monroe Pl",
    "sg:city":"Hyattsville",
    "sg:classifiers":[
        {
            "category":"Wholesale",
            "subcategory":"Poultry",
            "type":"Manufacturing & Wholesale Goods"
        }
    ],
    "sg:phone":"+1 301 864 8191",
    "sg:postcode":"20781",
    "sg:province":"MD",
    "wof:name":"Capital Poultry Distributors",
    "wof:placetype":"venue"
},
  "geometry": {"coordinates":[-76.92841900000001,38.934029],"type":"Point"}
}