{
  "type": "Feature",
  "properties": {
    "addr:full":"6606 Cross Country Blvd Baltimore MD 21215",
    "addr:housenumber":"6606",
    "addr:postcode":"21215",
    "addr:street":"Cross Country Blvd",
    "iso:country":"US",
    "sg:address":"6606 Cross Country Blvd",
    "sg:city":"Baltimore",
    "sg:classifiers":[
        {
            "category":"Health Services",
            "subcategory":"Dentist",
            "type":"Services"
        }
    ],
    "sg:phone":"+1 410 358 7646",
    "sg:postcode":"21215",
    "sg:province":"MD",
    "wof:name":"Langermann Solomon Dr & Rena Dr",
    "wof:placetype":"venue"
},
  "geometry": {"coordinates":[-76.69589999999999,39.364799],"type":"Point"}
}