{
  "type": "Feature",
  "properties": {
    "iso:country":"US",
    "sg:address":"129 Baltimore St",
    "sg:city":"Cumberland",
    "sg:classifiers":[
        {
            "category":"Professional",
            "type":"Services"
        }
    ],
    "sg:phone":"+1 301 777 7101",
    "sg:postcode":"21502",
    "sg:province":"MD",
    "sg:tags":[
        "caterer"
    ],
    "sg:website":"http://www.oxfordhouserestaurant.com",
    "wof:name":"Tivoli Food Service",
    "wof:placetype":"venue"
},
  "geometry": {"coordinates":[-78.760423,39.651858],"type":"Point"}
}