{
  "type": "Feature",
  "properties": {
    "addr:full":"201 E Heath St Baltimore MD 21230",
    "addr:housenumber":"201",
    "addr:postcode":"21230",
    "addr:street":"E Heath St",
    "iso:country":"US",
    "sg:address":"201 E Heath St",
    "sg:city":"Baltimore",
    "sg:classifiers":[
        {
            "category":"Shopping",
            "subcategory":"Department Store",
            "type":"Retail Goods"
        }
    ],
    "sg:phone":"+1 410 347 1286",
    "sg:postcode":"21230",
    "sg:province":"MD",
    "sg:tags":[
        "variety"
    ],
    "wof:name":"Mechados Mini Mart",
    "wof:placetype":"venue"
},
  "geometry": {"coordinates":[-76.61067199999999,39.270649],"type":"Point"}
}