{
  "type": "Feature",
  "properties": {
    "addr:full":"12613 Wisteria Dr Germantown MD 20874",
    "addr:housenumber":"12613",
    "addr:postcode":"20874",
    "addr:street":"Wisteria Dr",
    "iso:country":"US",
    "sg:address":"12613 Wisteria Dr",
    "sg:city":"Germantown",
    "sg:classifiers":[
        {
            "category":"Food & Beverages",
            "subcategory":"Candy",
            "type":"Retail Goods"
        },
        {
            "category":"Manufacturing",
            "subcategory":"Food",
            "type":"Manufacturing & Wholesale Goods"
        }
    ],
    "sg:phone":"+1 301 540 5533",
    "sg:postcode":"20874",
    "sg:province":"MD",
    "sg:tags":[
        "confectionery-wholesale",
        "confectionery",
        "manufacturer"
    ],
    "wof:name":"Lapp's Candy",
    "wof:placetype":"venue"
},
  "geometry": {"coordinates":[-77.261366,39.169635],"type":"Point"}
}