{
  "type": "Feature",
  "properties": {
    "iso:country":"US",
    "sg:address":"532 N Montford Ave",
    "sg:city":"Baltimore",
    "sg:classifiers":[
        {
            "category":"Bars & Pubs",
            "type":"Food & Drink"
        }
    ],
    "sg:phone":"+1 410 342 9779",
    "sg:postcode":"21205",
    "sg:province":"MD",
    "sg:tags":[
        "lounge",
        "cocktail"
    ],
    "wof:name":"New Montford Lounge",
    "wof:placetype":"venue"
},
  "geometry": {"coordinates":[-76.583737,39.297618],"type":"Point"}
}