{
  "type": "Feature",
  "properties": {
    "addr:full":"905 Gateway Dr Chestertown MD 21620",
    "addr:housenumber":"905",
    "addr:postcode":"21620",
    "addr:street":"Gateway Dr",
    "iso:country":"US",
    "sg:address":"905 Gateway Dr",
    "sg:city":"Chestertown",
    "sg:classifiers":[
        {
            "category":"Organizations",
            "subcategory":"Religious Organization",
            "type":"Services"
        }
    ],
    "sg:phone":"+1 410 778 6057",
    "sg:postcode":"21620",
    "sg:province":"MD",
    "sg:tags":[
        "church"
    ],
    "wof:name":"Presbyterian Church",
    "wof:placetype":"venue"
},
  "geometry": {"coordinates":[-76.072042,39.233007],"type":"Point"}
}