{
  "type": "Feature",
  "properties": {
    "addr:full":"7226 Lasting Light Way Columbia MD 21045",
    "addr:housenumber":"7226",
    "addr:postcode":"21045",
    "addr:street":"Lasting Light Way",
    "iso:country":"US",
    "sg:address":"7226 Lasting Light Way",
    "sg:city":"Columbia",
    "sg:classifiers":[
        {
            "category":"Building & Trades",
            "subcategory":"Locksmith",
            "type":"Services"
        }
    ],
    "sg:phone":"+1 301 596 4292",
    "sg:postcode":"21045",
    "sg:province":"MD",
    "sg:tags":[
        "key"
    ],
    "wof:name":"Columbia Lock & Window",
    "wof:placetype":"venue"
},
  "geometry": {"coordinates":[-76.838678,39.186226],"type":"Point"}
}