{
  "type": "Feature",
  "properties": {
    "addr:full":"5555 Wisconsin Ave Bethesda MD 20815",
    "addr:housenumber":"5555",
    "addr:postcode":"20815",
    "addr:street":"Wisconsin Ave",
    "iso:country":"US",
    "sg:address":"5555 Wisconsin Ave",
    "sg:city":"Bethesda",
    "sg:classifiers":[
        {
            "category":"Building & Trades",
            "subcategory":"Locksmith",
            "type":"Services"
        }
    ],
    "sg:phone":"+1 301 284 8734",
    "sg:postcode":"20815",
    "sg:province":"MD",
    "sg:tags":[
        "key"
    ],
    "wof:name":"Locksmith Available",
    "wof:placetype":"venue"
},
  "geometry": {"coordinates":[-77.087417,38.964837],"type":"Point"}
}