{
  "type": "Feature",
  "properties": {
    "iso:country":"US",
    "sg:address":"505 S Main St",
    "sg:city":"Berlin",
    "sg:classifiers":[
        {
            "category":"Personal",
            "subcategory":"Beauty Salon",
            "type":"Services"
        }
    ],
    "sg:phone":"+1 410 641 0620",
    "sg:postcode":"21811",
    "sg:province":"MD",
    "sg:tags":[
        "shop"
    ],
    "wof:name":"Special Touches",
    "wof:placetype":"venue"
},
  "geometry": {"coordinates":[-75.220326,38.315153],"type":"Point"}
}