{
  "type": "Feature",
  "properties": {
    "iso:country":"US",
    "sg:address":"12080 Old Line Center",
    "sg:city":"Waldorf",
    "sg:classifiers":[
        {
            "category":"Banks & Credit Unions",
            "subcategory":"Bank",
            "type":"Services"
        }
    ],
    "sg:phone":"+1 301 645 7600",
    "sg:postcode":"20602",
    "sg:province":"MD",
    "wof:name":"Old Line Bank",
    "wof:placetype":"venue"
},
  "geometry": {"coordinates":[-76.888948,38.61659],"type":"Point"}
}