{
  "type": "Feature",
  "properties": {
    "addr:full":"415 Washington Blvd Laurel MD 20707",
    "addr:housenumber":"415",
    "addr:postcode":"20707",
    "addr:street":"Washington Blvd",
    "iso:country":"US",
    "sg:address":"415 Washington Blvd",
    "sg:city":"Laurel",
    "sg:classifiers":[
        {
            "category":"Autos & Motor Vehicles",
            "subcategory":"Automobile Sales",
            "type":"Retail Goods"
        }
    ],
    "sg:phone":"+1 240 456 4640",
    "sg:postcode":"20707",
    "sg:province":"MD",
    "sg:tags":[
        "car",
        "dealer"
    ],
    "wof:name":"Fox Chevrolet",
    "wof:placetype":"venue"
},
  "geometry": {"coordinates":[-76.847112,39.100846],"type":"Point"}
}