{
  "type": "Feature",
  "properties": {
    "iso:country":"US",
    "sg:address":"8200 Perry Hall Blvd",
    "sg:city":"Nottingham",
    "sg:classifiers":[
        {
            "category":"Shopping",
            "subcategory":"Gifts & Souvenirs",
            "type":"Retail Goods"
        }
    ],
    "sg:phone":"+1 410 931 8899",
    "sg:postcode":"21236",
    "sg:province":"MD",
    "sg:tags":[
        "shop"
    ],
    "wof:name":"Photo Gifts",
    "wof:placetype":"venue"
},
  "geometry": {"coordinates":[-76.472458,39.375381],"type":"Point"}
}