{
  "type": "Feature",
  "properties": {
    "iso:country":"US",
    "sg:address":"7504 Damascus Rd",
    "sg:city":"Laytonsville",
    "sg:classifiers":[
        {
            "category":"Building & Trades",
            "subcategory":"Plumbing",
            "type":"Services"
        }
    ],
    "sg:phone":"+1 301 414 7447",
    "sg:postcode":"20882",
    "sg:province":"MD",
    "sg:tags":[
        "plumbing",
        "contractor"
    ],
    "wof:name":"BML Plumbing",
    "wof:placetype":"venue"
},
  "geometry": {"coordinates":[-77.152394,39.269153],"type":"Point"}
}