{
  "type": "Feature",
  "properties": {
    "iso:country":"US",
    "sg:address":"3535 Chevy Chase Lake Dr",
    "sg:city":"Chevy Chase",
    "sg:classifiers":[
        {
            "category":"Health Services",
            "subcategory":"Doctor",
            "type":"Services"
        }
    ],
    "sg:phone":"+1 301 951 3302",
    "sg:postcode":"20815",
    "sg:province":"MD",
    "wof:name":"Geber Antonia MD",
    "wof:placetype":"venue"
},
  "geometry": {"coordinates":[-77.071067,38.995285],"type":"Point"}
}