{
  "type": "Feature",
  "properties": {
    "iso:country":"US",
    "sg:address":"1001 Pine Heights Ave # 100",
    "sg:city":"Baltimore",
    "sg:classifiers":[
        {
            "category":"Health Services",
            "subcategory":"Doctor",
            "type":"Services"
        }
    ],
    "sg:phone":"+1 410 494 1402",
    "sg:postcode":"21229",
    "sg:province":"MD",
    "sg:tags":[
        "physician",
        "surgeons",
        "medicine",
        "surgeon",
        "rehabilitation",
        "physical"
    ],
    "wof:name":"Neurological Surgery Assoc",
    "wof:placetype":"venue"
},
  "geometry": {"coordinates":[-76.676498,39.271198],"type":"Point"}
}