{
  "type": "Feature",
  "properties": {
    "addr:full":"6707 Animal Shelter Rd Hughesville MD 20637",
    "addr:postcode":"20637",
    "addr:street":"Animal Shelter Rd",
    "iso:country":"US",
    "sg:address":"6707 Animal Shelter Rd",
    "sg:city":"Hughesville",
    "sg:classifiers":[
        {
            "category":"Government",
            "subcategory":"Office",
            "type":"Public Place"
        }
    ],
    "sg:phone":"+1 301 932 1713",
    "sg:postcode":"20637",
    "sg:province":"MD",
    "sg:website":"www.charlescounty.org/es/animalcontrol",
    "wof:name":"Charles County Animal Shelter",
    "wof:placetype":"venue"
},
  "geometry": {"coordinates":[-76.73274000000001,38.528992],"type":"Point"}
}