{
  "type": "Feature",
  "properties": {
    "iso:country":"US",
    "sg:address":"39510 Mount Wolf Rd",
    "sg:city":"Charlotte Hall",
    "sg:classifiers":[
        {
            "category":"Building & Trades",
            "subcategory":"Construction",
            "type":"Services"
        }
    ],
    "sg:phone":"+1 301 884 5838",
    "sg:postcode":"20622",
    "sg:province":"MD",
    "sg:tags":[
        "residential"
    ],
    "wof:name":"Infinity Construction Inc",
    "wof:placetype":"venue"
},
  "geometry": {"coordinates":[-76.763403,38.503584],"type":"Point"}
}