{
  "type": "Feature",
  "properties": {
    "iso:country":"US",
    "sg:address":"500 Wilson Rd",
    "sg:city":"Annapolis",
    "sg:classifiers":[
        {
            "category":"Travel",
            "subcategory":"Hotels & Motels",
            "type":"Entertainment"
        }
    ],
    "sg:phone":"+1 410 571 9511",
    "sg:postcode":"21401",
    "sg:province":"MD",
    "sg:tags":[
        "breakfast",
        "accommodation",
        "bed"
    ],
    "wof:name":"Barn On Howard's Cove B & B",
    "wof:placetype":"venue"
},
  "geometry": {"coordinates":[-76.51305499999999,39.004664],"type":"Point"}
}