{
  "type": "Feature",
  "properties": {
    "addr:full":"201 S Edgewood Dr Hagerstown MD 21740",
    "addr:housenumber":"201",
    "addr:postcode":"21740",
    "addr:street":"S Edgewood Dr",
    "iso:country":"US",
    "sg:address":"201 S Edgewood Dr",
    "sg:city":"Hagerstown",
    "sg:classifiers":[
        {
            "category":"Professional",
            "type":"Services"
        }
    ],
    "sg:phone":"+1 301 733 3599",
    "sg:postcode":"21740",
    "sg:province":"MD",
    "sg:tags":[
        "transportation"
    ],
    "sg:website":"https://www.avis.com/",
    "wof:name":"Avis",
    "wof:placetype":"venue"
},
  "geometry": {"coordinates":[-77.697732,39.614945],"type":"Point"}
}