{
  "type": "Feature",
  "properties": {
    "iso:country":"US",
    "sg:address":"7389 Baltimore Annapolis Blvd",
    "sg:city":"Glen Burnie",
    "sg:classifiers":[
        {
            "category":"Personal",
            "subcategory":"Beauty Salon",
            "type":"Services"
        }
    ],
    "sg:phone":"+1 410 768 9866",
    "sg:postcode":"21061",
    "sg:province":"MD",
    "wof:name":"Hair Cuttery",
    "wof:placetype":"venue"
},
  "geometry": {"coordinates":[-76.631433,39.170908],"type":"Point"}
}