{
  "type": "Feature",
  "properties": {
    "iso:country":"US",
    "sg:address":"4018 S Main St",
    "sg:city":"Trappe",
    "sg:classifiers":[
        {
            "category":"Retail",
            "subcategory":"Repair Shop",
            "type":"Services"
        }
    ],
    "sg:phone":"+1 410 822 8580",
    "sg:postcode":"21673",
    "sg:province":"MD",
    "sg:tags":[
        "upholsterer"
    ],
    "wof:name":"Classic Cushion Design",
    "wof:placetype":"venue"
},
  "geometry": {"coordinates":[-76.057122,38.654583],"type":"Point"}
}