{
  "type": "Feature",
  "properties": {
    "iso:country":"US",
    "sg:address":"7811 Malcolm Rd",
    "sg:city":"Clinton",
    "sg:classifiers":[
        {
            "category":"Retail",
            "subcategory":"Auto Repair",
            "type":"Services"
        }
    ],
    "sg:phone":"+1 301 868 3011",
    "sg:postcode":"20735",
    "sg:province":"MD",
    "sg:tags":[
        "transmission"
    ],
    "wof:name":"J Tech Transmissions",
    "wof:placetype":"venue"
},
  "geometry": {"coordinates":[-76.890366,38.783431],"type":"Point"}
}