{
  "type": "Feature",
  "properties": {
    "addr:full":"2905 Thornbrook Rd Ellicott City MD 21042",
    "addr:housenumber":"2905",
    "addr:postcode":"21042",
    "addr:street":"Thornbrook Rd",
    "iso:country":"US",
    "sg:address":"2905 Thornbrook Rd",
    "sg:city":"Ellicott City",
    "sg:classifiers":[
        {
            "category":"Restaurant",
            "type":"Food & Drink"
        }
    ],
    "sg:phone":"+1 410 590 0002",
    "sg:postcode":"21042",
    "sg:province":"MD",
    "wof:name":"Top This Pizza",
    "wof:placetype":"venue"
},
  "geometry": {"coordinates":[-76.84194100000001,39.307873],"type":"Point"}
}