{
  "type": "Feature",
  "properties": {
    "addr:full":"2003 W 41st St Baltimore MD 21211",
    "addr:housenumber":"2003",
    "addr:postcode":"21211",
    "addr:street":"W 41St St",
    "iso:country":"US",
    "sg:address":"2003 W 41st St",
    "sg:city":"Baltimore",
    "sg:classifiers":[
        {
            "category":"Retail",
            "subcategory":"Auto Repair",
            "type":"Services"
        }
    ],
    "sg:phone":"+1 410 243 5215",
    "sg:postcode":"21211",
    "sg:province":"MD",
    "sg:website":"www.briansautocare.com/",
    "wof:name":"Brian's Auto Care Inc",
    "wof:placetype":"venue"
},
  "geometry": {"coordinates":[-76.646742,39.333629],"type":"Point"}
}