{
  "type": "Feature",
  "properties": {
    "iso:country":"US",
    "sg:address":"2002 Annapolis Mall",
    "sg:city":"Annapolis",
    "sg:classifiers":[
        {
            "category":"Coffee & Tea",
            "type":"Food & Drink"
        }
    ],
    "sg:menulink":"http://www.allmenus.com/md/annapolis/118959-starbucks-coffee/menu/",
    "sg:phone":"+1 410 224 3197",
    "sg:postcode":"21401",
    "sg:province":"MD",
    "sg:tags":[
        "american"
    ],
    "wof:name":"Starbucks Coffee",
    "wof:placetype":"venue"
},
  "geometry": {"coordinates":[-76.54871,38.990658],"type":"Point"}
}