{
  "type": "Feature",
  "properties": {
    "iso:country":"US",
    "sg:address":"8100 Gibbs Way",
    "sg:city":"Hyattsville",
    "sg:classifiers":[
        {
            "category":"Real Estate",
            "subcategory":"Real Estate Services",
            "type":"Services"
        },
        {
            "category":"Real Estate",
            "subcategory":"Real Estate Operator",
            "type":"Services"
        }
    ],
    "sg:phone":"+1 301 350 8333",
    "sg:postcode":"20785",
    "sg:province":"MD",
    "sg:tags":[
        "apartment",
        "property",
        "management"
    ],
    "sg:website":"www.camdensummerfield.com",
    "wof:name":"Camden Summerfield",
    "wof:placetype":"venue"
},
  "geometry": {"coordinates":[-76.86606500000001,38.895848],"type":"Point"}
}