{
  "type": "Feature",
  "properties": {
    "addr:full":"716 N Bridge St Elkton MD 21921",
    "addr:housenumber":"716",
    "addr:postcode":"21921",
    "addr:street":"N Bridge St",
    "iso:country":"US",
    "sg:address":"716 N Bridge St",
    "sg:city":"Elkton",
    "sg:classifiers":[
        {
            "category":"Health Services",
            "subcategory":"Chiropractor",
            "type":"Services"
        }
    ],
    "sg:phone":"+1 410 392 3930",
    "sg:postcode":"21921",
    "sg:province":"MD",
    "wof:name":"Mc Donald's Chiropractic Ctr",
    "wof:placetype":"venue"
},
  "geometry": {"coordinates":[-75.83815,39.616865],"type":"Point"}
}