{
  "type": "Feature",
  "properties": {
    "addr:full":"12018 Auth Ln Silver Spring MD 20902",
    "addr:postcode":"12018;20902",
    "addr:street":"Auth Ln",
    "iso:country":"US",
    "sg:address":"12018 Auth Ln",
    "sg:city":"Silver Spring",
    "sg:classifiers":[
        {
            "category":"Professional",
            "subcategory":"Computer Services",
            "type":"Services"
        }
    ],
    "sg:phone":"+1 301 593 8989",
    "sg:postcode":"20902",
    "sg:province":"MD",
    "sg:tags":[
        "related"
    ],
    "wof:name":"David Goldschlig",
    "wof:placetype":"venue"
},
  "geometry": {"coordinates":[-77.022952,39.054121],"type":"Point"}
}