{
  "type": "Feature",
  "properties": {
    "iso:country":"US",
    "sg:address":"18513 McKernon Way",
    "sg:city":"Poolesville",
    "sg:classifiers":[
        {
            "category":"Building & Trades",
            "subcategory":"Construction",
            "type":"Services"
        }
    ],
    "sg:phone":"+1 301 349 2015",
    "sg:postcode":"20837",
    "sg:province":"MD",
    "sg:tags":[
        "general",
        "contractor"
    ],
    "wof:name":"Hart Construction Svc Inc",
    "wof:placetype":"venue"
},
  "geometry": {"coordinates":[-77.401886,39.155541],"type":"Point"}
}