{
  "type": "Feature",
  "properties": {
    "iso:country":"US",
    "sg:address":"4831 Bucktown Rd",
    "sg:city":"Cambridge",
    "sg:classifiers":[
        {
            "category":"Building & Trades",
            "subcategory":"Plumbing",
            "type":"Services"
        }
    ],
    "sg:phone":"+1 410 228 6525",
    "sg:postcode":"21613",
    "sg:province":"MD",
    "sg:tags":[
        "septic"
    ],
    "wof:name":"Elzey Septic Svc",
    "wof:placetype":"venue"
},
  "geometry": {"coordinates":[-76.016958,38.507771],"type":"Point"}
}