{
  "type": "Feature",
  "properties": {
    "iso:country":"US",
    "sg:address":"9201 Philadelphia Rd",
    "sg:city":"Baltimore",
    "sg:classifiers":[
        {
            "category":"Health Services",
            "subcategory":"Hospital",
            "type":"Services"
        }
    ],
    "sg:phone":"+1 410 574 7700",
    "sg:postcode":"21237",
    "sg:province":"MD",
    "sg:tags":[
        "mental"
    ],
    "wof:name":"Alliance Drop In Ctr",
    "wof:placetype":"venue"
},
  "geometry": {"coordinates":[-76.469781,39.349295],"type":"Point"}
}