{
  "type": "Feature",
  "properties": {
    "iso:country":"US",
    "sg:address":"7411 Riggs Rd",
    "sg:city":"Hyattsville",
    "sg:classifiers":[
        {
            "category":"Personal",
            "subcategory":"Beauty Salon",
            "type":"Services"
        }
    ],
    "sg:phone":"+1 301 434 4900",
    "sg:postcode":"20783",
    "sg:province":"MD",
    "wof:name":"D'Franco Family Hair Salon",
    "wof:placetype":"venue"
},
  "geometry": {"coordinates":[-76.978922,38.981861],"type":"Point"}
}