{
  "type": "Feature",
  "properties": {
    "iso:country":"US",
    "sg:address":"9400 Snowden River Pkwy",
    "sg:city":"Columbia",
    "sg:classifiers":[
        {
            "category":"Home & Garden",
            "subcategory":"Furniture",
            "type":"Retail Goods"
        }
    ],
    "sg:phone":"+1 410 309 9655",
    "sg:postcode":"21045",
    "sg:province":"MD",
    "sg:tags":[
        "mattress"
    ],
    "sg:website":"www.sleephappens.com",
    "wof:name":"Mattress Warehouse of Columbia",
    "wof:placetype":"venue"
},
  "geometry": {"coordinates":[-76.833702,39.176498],"type":"Point"}
}