{
  "type": "Feature",
  "properties": {
    "iso:country":"US",
    "sg:address":"7448 Holabird Ave",
    "sg:city":"Dundalk",
    "sg:classifiers":[
        {
            "category":"Building & Trades",
            "subcategory":"Construction",
            "type":"Services"
        }
    ],
    "sg:phone":"+1 410 284 2717",
    "sg:postcode":"21222",
    "sg:province":"MD",
    "sg:tags":[
        "system",
        "specialty",
        "heating",
        "contractor",
        "air conditioning"
    ],
    "wof:name":"Standard Heating & Air Conditioning Contractors Inc",
    "wof:placetype":"venue"
},
  "geometry": {"coordinates":[-76.50846799999999,39.271405],"type":"Point"}
}