{
  "type": "Feature",
  "properties": {
    "addr:full":"1592 Rockville Pike Rockville MD 20852",
    "addr:housenumber":"1592",
    "addr:postcode":"20852",
    "addr:street":"Rockville Pike",
    "iso:country":"US",
    "sg:address":"1592 Rockville Pike",
    "sg:city":"Rockville",
    "sg:classifiers":[
        {
            "category":"Restaurant",
            "type":"Food & Drink"
        }
    ],
    "sg:menulink":"http://www.allmenus.com/md/rockville/92854-fuddruckers/menu/",
    "sg:phone":"+1 301 468 3501",
    "sg:postcode":"20852",
    "sg:province":"MD",
    "sg:tags":[
        "burger",
        "american"
    ],
    "wof:name":"Fuddruckers",
    "wof:placetype":"venue"
},
  "geometry": {"coordinates":[-77.12546399999999,39.063941],"type":"Point"}
}