{
  "type": "Feature",
  "properties": {
    "iso:country":"US",
    "sg:address":"102 Washington St",
    "sg:city":"Cambridge",
    "sg:classifiers":[
        {
            "category":"Wholesale",
            "subcategory":"Electrical",
            "type":"Manufacturing & Wholesale Goods"
        }
    ],
    "sg:phone":"+1 410 228 4429",
    "sg:postcode":"21613",
    "sg:province":"MD",
    "sg:tags":[
        "fire",
        "equipment",
        "protection"
    ],
    "wof:name":"Tom's Fire Equipment",
    "wof:placetype":"venue"
},
  "geometry": {"coordinates":[-76.070558,38.561059],"type":"Point"}
}