{
  "type": "Feature",
  "properties": {
    "iso:country":"US",
    "sg:address":"31 Norman Allen St",
    "sg:city":"Elkton",
    "sg:classifiers":[
        {
            "category":"Shopping",
            "type":"Retail Goods"
        }
    ],
    "sg:phone":"+1 410 392 0090",
    "sg:postcode":"21921",
    "sg:province":"MD",
    "sg:tags":[
        "candle"
    ],
    "sg:website":"www.pureesscentscandles.com",
    "wof:name":"Esscents",
    "wof:placetype":"venue"
},
  "geometry": {"coordinates":[-75.824024,39.59479],"type":"Point"}
}