{
  "type": "Feature",
  "properties": {
    "addr:full":"6569 N Charles St Towson MD 21204",
    "addr:housenumber":"6569",
    "addr:postcode":"21204",
    "addr:street":"N Charles St",
    "iso:country":"US",
    "sg:address":"6569 N Charles St",
    "sg:city":"Towson",
    "sg:classifiers":[
        {
            "category":"Health Services",
            "subcategory":"Doctor",
            "type":"Services"
        },
        {
            "category":"Health Services",
            "subcategory":"Health Practitioner",
            "type":"Services"
        }
    ],
    "sg:phone":"+1 443 849 3051",
    "sg:postcode":"21204",
    "sg:province":"MD",
    "sg:tags":[
        "acupuncture",
        "physician",
        "alternative",
        "medicine",
        "surgeon"
    ],
    "wof:name":"Donegan Robert MD",
    "wof:placetype":"venue"
},
  "geometry": {"coordinates":[-76.62585199999999,39.388815],"type":"Point"}
}