{
  "type": "Feature",
  "properties": {
    "iso:country":"US",
    "sg:address":"1526 York Rd",
    "sg:city":"Lutherville",
    "sg:classifiers":[
        {
            "category":"Banks & Credit Unions",
            "subcategory":"Bank",
            "type":"Services"
        }
    ],
    "sg:phone":"+1 410 825 8840",
    "sg:postcode":"21093",
    "sg:province":"MD",
    "sg:tags":[
        "loan",
        "real estate"
    ],
    "wof:name":"Newport Shores Mtg Inc O'Shea",
    "wof:placetype":"venue"
},
  "geometry": {"coordinates":[-76.617901,39.42282],"type":"Point"}
}