{
  "type": "Feature",
  "properties": {
    "iso:country":"US",
    "sg:address":"12500 Baltimore Ave",
    "sg:city":"Beltsville",
    "sg:classifiers":[
        {
            "category":"Manufacturing",
            "subcategory":"Tools & Machinery",
            "type":"Manufacturing & Wholesale Goods"
        },
        {
            "category":"Manufacturing",
            "subcategory":"Electronics",
            "type":"Manufacturing & Wholesale Goods"
        },
        {
            "category":"Utilities",
            "subcategory":"Electric",
            "type":"Services"
        },
        {
            "category":"Wholesale",
            "subcategory":"Electrical",
            "type":"Manufacturing & Wholesale Goods"
        }
    ],
    "sg:phone":"+1 443 909 7200",
    "sg:postcode":"20705",
    "sg:province":"MD",
    "sg:tags":[
        "equipment",
        "manufacturer",
        "supplies-wholesale",
        "equipment-testing",
        "supply"
    ],
    "wof:name":"Sune Solar Viii",
    "wof:placetype":"venue"
},
  "geometry": {"coordinates":[-76.886909,39.060589],"type":"Point"}
}