{
  "type": "Feature",
  "properties": {
    "addr:full":"3476 Mannassas Ct Davidsonville MD 21035",
    "addr:housenumber":"3476",
    "addr:postcode":"21035",
    "addr:street":"Mannassas Ct",
    "iso:country":"US",
    "sg:address":"3476 Mannassas Ct",
    "sg:city":"Davidsonville",
    "sg:classifiers":[
        {
            "category":"Building & Trades",
            "subcategory":"Construction",
            "type":"Services"
        }
    ],
    "sg:phone":"+1 410 956 6249",
    "sg:postcode":"21035",
    "sg:province":"MD",
    "sg:tags":[
        "house"
    ],
    "wof:name":"McEntire General Construction",
    "wof:placetype":"venue"
},
  "geometry": {"coordinates":[-76.616457,38.930124],"type":"Point"}
}