{
  "type": "Feature",
  "properties": {
    "addr:full":"215 E Alder St Oakland MD 21550",
    "addr:housenumber":"215",
    "addr:postcode":"21550",
    "addr:street":"E Alder St",
    "iso:country":"US",
    "sg:address":"215 E Alder St",
    "sg:city":"Oakland",
    "sg:classifiers":[
        {
            "category":"Personal",
            "subcategory":"Shoe Repair & Shine",
            "type":"Services"
        }
    ],
    "sg:phone":"+1 301 334 4433",
    "sg:postcode":"21550",
    "sg:province":"MD",
    "sg:tags":[
        "repairing",
        "boot"
    ],
    "wof:name":"Gary's Shoe Repair & Leather",
    "wof:placetype":"venue"
},
  "geometry": {"coordinates":[-79.408207,39.408195],"type":"Point"}
}