{
  "type": "Feature",
  "properties": {
    "addr:full":"1406 Crain Hwy S Glen Burnie MD 21061",
    "addr:housenumber":"1406",
    "addr:postcode":"21061",
    "addr:street":"Crain Hwy S",
    "iso:country":"US",
    "sg:address":"1406 Crain Hwy S",
    "sg:city":"Glen Burnie",
    "sg:classifiers":[
        {
            "category":"Professional",
            "subcategory":"Lawyer & Legal Services",
            "type":"Services"
        }
    ],
    "sg:phone":"+1 410 787 7009",
    "sg:postcode":"21061",
    "sg:province":"MD",
    "sg:tags":[
        "attorney"
    ],
    "wof:name":"A Aamalpractice",
    "wof:placetype":"venue"
},
  "geometry": {"coordinates":[-76.63189800000001,39.148486],"type":"Point"}
}