{
  "type": "Feature",
  "properties": {
    "iso:country":"US",
    "sg:address":"5012 Frye Rd",
    "sg:city":"Upperco",
    "sg:classifiers":[
        {
            "category":"Organizations",
            "subcategory":"Religious Organization",
            "type":"Services"
        }
    ],
    "sg:phone":"+1 410 429 8993",
    "sg:postcode":"21155",
    "sg:province":"MD",
    "wof:name":"Dover United Methodist Church",
    "wof:placetype":"venue"
},
  "geometry": {"coordinates":[-76.825807,39.528758],"type":"Point"}
}