{
  "type": "Feature",
  "properties": {
    "iso:country":"US",
    "sg:address":"814 Thayer Ave",
    "sg:city":"Silver Spring",
    "sg:classifiers":[
        {
            "category":"Communications",
            "type":"Services"
        }
    ],
    "sg:phone":"+1 301 589 4756",
    "sg:postcode":"20910",
    "sg:province":"MD",
    "wof:name":"Star Access",
    "wof:placetype":"venue"
},
  "geometry": {"coordinates":[-77.023851,38.992976],"type":"Point"}
}