{
  "type": "Feature",
  "properties": {
    "addr:full":"25870 Ricky Dr Hollywood MD 20636",
    "addr:housenumber":"25870",
    "addr:postcode":"20636",
    "addr:street":"Ricky Dr",
    "iso:country":"US",
    "sg:address":"25870 Ricky Dr",
    "sg:city":"Hollywood",
    "sg:classifiers":[
        {
            "category":"Building & Trades",
            "subcategory":"Electrical",
            "type":"Services"
        }
    ],
    "sg:phone":"+1 301 373 3057",
    "sg:postcode":"20636",
    "sg:province":"MD",
    "sg:tags":[
        "electrical",
        "contractor"
    ],
    "wof:name":"Buck Electric",
    "wof:placetype":"venue"
},
  "geometry": {"coordinates":[-76.59584,38.377609],"type":"Point"}
}