{
  "type": "Feature",
  "properties": {
    "iso:country":"US",
    "sg:address":"31744 Tappers Corner Rd",
    "sg:city":"Cordova",
    "sg:phone":"+1 410 364 5318",
    "sg:postcode":"21625",
    "sg:province":"MD",
    "sg:tags":[
        "farm",
        "soybean"
    ],
    "wof:name":"Andrew Ellsworth",
    "wof:placetype":"venue"
},
  "geometry": {"coordinates":[-75.971947,38.885256],"type":"Point"}
}