{
  "type": "Feature",
  "properties": {
    "addr:full":"20201 Kellys Ln Hagerstown MD 21742",
    "addr:housenumber":"20201",
    "addr:postcode":"21742",
    "addr:street":"Kellys Ln",
    "iso:country":"US",
    "sg:address":"20201 Kellys Ln",
    "sg:city":"Hagerstown",
    "sg:classifiers":[
        {
            "category":"Retail",
            "subcategory":"Animal Services",
            "type":"Services"
        }
    ],
    "sg:phone":"+1 301 745 3160",
    "sg:postcode":"21742",
    "sg:province":"MD",
    "sg:tags":[
        "pet",
        "grooming",
        "washing"
    ],
    "wof:name":"Ramona's Corner Grooming Salon",
    "wof:placetype":"venue"
},
  "geometry": {"coordinates":[-77.669764,39.623726],"type":"Point"}
}