{
  "type": "Feature",
  "properties": {
    "iso:country":"US",
    "sg:address":"3783 Branch Ave",
    "sg:city":"Temple Hills",
    "sg:classifiers":[
        {
            "category":"Manufacturing",
            "subcategory":"Apparel",
            "type":"Manufacturing & Wholesale Goods"
        }
    ],
    "sg:phone":"+1 301 702 1600",
    "sg:postcode":"20748",
    "sg:province":"MD",
    "sg:tags":[
        "clothes",
        "accessory"
    ],
    "wof:name":"His & Hers",
    "wof:placetype":"venue"
},
  "geometry": {"coordinates":[-76.946006,38.838452],"type":"Point"}
}