{
  "type": "Feature",
  "properties": {
    "addr:full":"13 Silverwood Ct Baltimore MD 21236",
    "addr:housenumber":"13",
    "addr:postcode":"21236",
    "addr:street":"Silverwood Ct",
    "iso:country":"US",
    "sg:address":"13 Silverwood Ct",
    "sg:city":"Baltimore",
    "sg:classifiers":[
        {
            "category":"Government",
            "subcategory":"Office",
            "type":"Public Place"
        }
    ],
    "sg:phone":"+1 410 529 4258",
    "sg:postcode":"21236",
    "sg:province":"MD",
    "sg:tags":[
        "sector",
        "regulation",
        "commercial"
    ],
    "wof:name":"Beverage Control Systems",
    "wof:placetype":"venue"
},
  "geometry": {"coordinates":[-76.478279,39.40666],"type":"Point"}
}