{
  "type": "Feature",
  "properties": {
    "addr:full":"6125 Reisterstown Rd Baltimore MD 21215",
    "addr:housenumber":"6125",
    "addr:postcode":"21215",
    "addr:street":"Reisterstown Rd",
    "iso:country":"US",
    "sg:address":"6125 Reisterstown Rd",
    "sg:city":"Baltimore",
    "sg:classifiers":[
        {
            "category":"Retail",
            "subcategory":"Car Wash",
            "type":"Services"
        }
    ],
    "sg:phone":"+1 410 358 1227",
    "sg:postcode":"21215",
    "sg:province":"MD",
    "sg:website":"http://www.sparklecarwashmd.com",
    "wof:name":"Sparkle Car Wash",
    "wof:placetype":"venue"
},
  "geometry": {"coordinates":[-76.698776,39.353668],"type":"Point"}
}