{
  "type": "Feature",
  "properties": {
    "addr:full":"4231 Ebenezer Rd Nottingham MD 21236",
    "addr:housenumber":"4231",
    "addr:postcode":"21236",
    "addr:street":"Ebenezer Rd",
    "iso:country":"US",
    "sg:address":"4231 Ebenezer Rd",
    "sg:city":"Nottingham",
    "sg:classifiers":[
        {
            "category":"Wholesale",
            "subcategory":"Painting Supplies",
            "type":"Manufacturing & Wholesale Goods"
        },
        {
            "category":"Retail",
            "subcategory":"Repair Shop",
            "type":"Services"
        },
        {
            "category":"Home & Garden",
            "subcategory":"Hardware",
            "type":"Retail Goods"
        },
        {
            "category":"Home & Garden",
            "subcategory":"Building Materials",
            "type":"Retail Goods"
        },
        {
            "category":"Wholesale",
            "subcategory":"Hardware",
            "type":"Manufacturing & Wholesale Goods"
        },
        {
            "category":"Home & Garden",
            "subcategory":"Garden Supply",
            "type":"Retail Goods"
        }
    ],
    "sg:phone":"+1 410 256 1913",
    "sg:postcode":"21236",
    "sg:province":"MD",
    "sg:tags":[
        "renting",
        "lawn",
        "outdoor",
        "power",
        "equipment",
        "equipment-sales",
        "landscaping",
        "saw",
        "paint",
        "store"
    ],
    "sg:website":"http://www.stihlusa.com/",
    "wof:name":"Rommel's Ace Home Center",
    "wof:placetype":"venue"
},
  "geometry": {"coordinates":[-76.47933999999999,39.398499],"type":"Point"}
}