{
  "type": "Feature",
  "properties": {
    "addr:full":"214 Midhurst Rd Baltimore MD 21212",
    "addr:housenumber":"214",
    "addr:postcode":"21212",
    "addr:street":"Midhurst Rd",
    "iso:country":"US",
    "sg:address":"214 Midhurst Rd",
    "sg:city":"Baltimore",
    "sg:classifiers":[
        {
            "category":"Health Services",
            "subcategory":"Dentist",
            "type":"Services"
        }
    ],
    "sg:phone":"+1 410 377 0577",
    "sg:postcode":"21212",
    "sg:province":"MD",
    "sg:tags":[
        "dental",
        "clinic"
    ],
    "wof:name":"Howard L Levy",
    "wof:placetype":"venue"
},
  "geometry": {"coordinates":[-76.616761,39.373319],"type":"Point"}
}