{
  "type": "Feature",
  "properties": {
    "iso:country":"US",
    "sg:address":"5440 Old Tucker Row",
    "sg:city":"Columbia",
    "sg:classifiers":[
        {
            "category":"Real Estate",
            "subcategory":"Developer",
            "type":"Services"
        }
    ],
    "sg:phone":"+1 443 341 1880",
    "sg:postcode":"21044",
    "sg:province":"MD",
    "sg:tags":[
        "investing"
    ],
    "wof:name":"Grassfield Investment",
    "wof:placetype":"venue"
},
  "geometry": {"coordinates":[-76.88731300000001,39.222296],"type":"Point"}
}