{
  "type": "Feature",
  "properties": {
    "addr:full":"16279 Spielman Rd Williamsport MD 21795",
    "addr:housenumber":"16279",
    "addr:postcode":"21795",
    "addr:street":"Spielman Rd",
    "iso:country":"US",
    "sg:address":"16279 Spielman Rd",
    "sg:city":"Williamsport",
    "sg:phone":"+1 301 223 6364",
    "sg:postcode":"21795",
    "sg:province":"MD",
    "sg:tags":[
        "farm"
    ],
    "wof:name":"Willville Farms",
    "wof:placetype":"venue"
},
  "geometry": {"coordinates":[-77.81282899999999,39.564469],"type":"Point"}
}