{
  "type": "Feature",
  "properties": {
    "iso:country":"US",
    "sg:address":"104 Elm Ave",
    "sg:city":"Takoma Park",
    "sg:classifiers":[
        {
            "category":"Professional",
            "subcategory":"Business Services",
            "type":"Services"
        }
    ],
    "sg:phone":"+1 301 270 3803",
    "sg:postcode":"20912",
    "sg:province":"MD",
    "sg:tags":[
        "consulting"
    ],
    "wof:name":"Business-Community Synergies",
    "wof:placetype":"venue"
},
  "geometry": {"coordinates":[-77.008175,38.973515],"type":"Point"}
}