{
  "type": "Feature",
  "properties": {
    "addr:full":"6264 Central Ave Capitol Heights MD 20743",
    "addr:housenumber":"6264",
    "addr:postcode":"20743",
    "addr:street":"Central Ave",
    "iso:country":"US",
    "sg:address":"6264 Central Ave",
    "sg:city":"Capitol Heights",
    "sg:classifiers":[
        {
            "category":"Government",
            "subcategory":"Police Station",
            "type":"Public Place"
        }
    ],
    "sg:phone":"+1 301 499 8700",
    "sg:postcode":"20743",
    "sg:province":"MD",
    "sg:tags":[
        "department"
    ],
    "wof:name":"Seat Pleasant Police Dept",
    "wof:placetype":"venue"
},
  "geometry": {"coordinates":[-76.901099,38.886467],"type":"Point"}
}