{
  "type": "Feature",
  "properties": {
    "addr:full":"1521 Jutewood Ave Hyattsville MD 20785",
    "addr:housenumber":"1521",
    "addr:postcode":"20785",
    "addr:street":"Jutewood Ave",
    "iso:country":"US",
    "sg:address":"1521 Jutewood Ave",
    "sg:city":"Hyattsville",
    "sg:classifiers":[
        {
            "category":"Recreation",
            "subcategory":"Amusement Park",
            "type":"Entertainment"
        }
    ],
    "sg:phone":"+1 301 773 8072",
    "sg:postcode":"20785",
    "sg:province":"MD",
    "sg:tags":[
        "device"
    ],
    "wof:name":"Tnt Amusements",
    "wof:placetype":"venue"
},
  "geometry": {"coordinates":[-76.914485,38.910015],"type":"Point"}
}