{
  "type": "Feature",
  "properties": {
    "addr:full":"6424 Baltimore National Pike Catonsville MD 21228",
    "addr:housenumber":"6424",
    "addr:postcode":"21228",
    "addr:street":"Baltimore National Pike",
    "iso:country":"US",
    "sg:address":"6424 Baltimore National Pike",
    "sg:city":"Catonsville",
    "sg:classifiers":[
        {
            "category":"Fast Food",
            "type":"Food & Drink"
        }
    ],
    "sg:phone":"+1 410 788 8001",
    "sg:postcode":"21228",
    "sg:province":"MD",
    "sg:website":"www.arbys.com",
    "wof:name":"Arby's",
    "wof:placetype":"venue"
},
  "geometry": {"coordinates":[-76.758758,39.285026],"type":"Point"}
}