{
  "type": "Feature",
  "properties": {
    "addr:full":"901 Crain Hwy Mitchellville MD 20716",
    "addr:housenumber":"901",
    "addr:postcode":"20716",
    "addr:street":"Crain Hwy",
    "iso:country":"US",
    "sg:address":"901 Crain Hwy",
    "sg:city":"Mitchellville",
    "sg:classifiers":[
        {
            "category":"Building & Trades",
            "subcategory":"Landscaping Services",
            "type":"Services"
        }
    ],
    "sg:phone":"+1 301 390 9311",
    "sg:postcode":"20716",
    "sg:province":"MD",
    "sg:tags":[
        "landscape",
        "contractor"
    ],
    "wof:name":"Diamond Eagle Farms",
    "wof:placetype":"venue"
},
  "geometry": {"coordinates":[-76.71981100000001,38.902667],"type":"Point"}
}