{
  "type": "Feature",
  "properties": {
    "iso:country":"US",
    "sg:address":"101 School Ln",
    "sg:city":"Linthicum Heights",
    "sg:classifiers":[
        {
            "category":"Education",
            "subcategory":"School",
            "type":"Public Place"
        }
    ],
    "sg:phone":"+1 410 222 6935",
    "sg:postcode":"21090",
    "sg:province":"MD",
    "sg:tags":[
        "high",
        "middle",
        "elementary"
    ],
    "sg:website":"www.aacps.org",
    "wof:name":"Anne Arundel County Public Schools",
    "wof:placetype":"venue"
},
  "geometry": {"coordinates":[-76.653491,39.203387],"type":"Point"}
}