{
  "type": "Feature",
  "properties": {
    "iso:country":"US",
    "sg:address":"5509 Huntington Pkwy",
    "sg:city":"Bethesda",
    "sg:classifiers":[
        {
            "category":"Building & Trades",
            "subcategory":"Construction",
            "type":"Services"
        }
    ],
    "sg:phone":"+1 301 986 1076",
    "sg:postcode":"20814",
    "sg:province":"MD",
    "sg:tags":[
        "interior",
        "design"
    ],
    "wof:name":"Creative U Interior Designs",
    "wof:placetype":"venue"
},
  "geometry": {"coordinates":[-77.111603,38.991901],"type":"Point"}
}