{
  "type": "Feature",
  "properties": {
    "iso:country":"US",
    "sg:address":"803 Hedge Hopper Rd",
    "sg:city":"Gambrills",
    "sg:classifiers":[
        {
            "category":"Professional",
            "subcategory":"Computer Services",
            "type":"Services"
        }
    ],
    "sg:phone":"+1 410 218 4004",
    "sg:postcode":"21054",
    "sg:province":"MD",
    "sg:tags":[
        "development",
        "software"
    ],
    "wof:name":"PTL",
    "wof:placetype":"venue"
},
  "geometry": {"coordinates":[-76.669034,39.070004],"type":"Point"}
}