{
  "type": "Feature",
  "properties": {
    "addr:full":"8601 Georgia Ave Silver Spring MD 20910",
    "addr:housenumber":"8601",
    "addr:postcode":"20910",
    "addr:street":"Georgia Ave",
    "iso:country":"US",
    "sg:address":"8601 Georgia Ave",
    "sg:city":"Silver Spring",
    "sg:classifiers":[
        {
            "category":"Professional",
            "subcategory":"Management & Consulting",
            "type":"Services"
        }
    ],
    "sg:phone":"+1 301 589 0780",
    "sg:postcode":"20910",
    "sg:province":"MD",
    "sg:tags":[
        "consultant",
        "business"
    ],
    "sg:website":"www.mcfarlandwired.com",
    "wof:name":"Mc Farland & Assoc Inc",
    "wof:placetype":"venue"
},
  "geometry": {"coordinates":[-77.028747,38.996551],"type":"Point"}
}