{
  "type": "Feature",
  "properties": {
    "iso:country":"US",
    "sg:address":"9727 Mount Pisgah Rd",
    "sg:city":"Silver Spring",
    "sg:classifiers":[
        {
            "category":"Personal",
            "subcategory":"Beauty Salon",
            "type":"Services"
        }
    ],
    "sg:phone":"+1 301 439 6137",
    "sg:postcode":"20903",
    "sg:province":"MD",
    "sg:tags":[
        "shop"
    ],
    "wof:name":"Foxes Den Hair Salon Inc",
    "wof:placetype":"venue"
},
  "geometry": {"coordinates":[-76.97623400000001,39.016523],"type":"Point"}
}