{
  "type": "Feature",
  "properties": {
    "addr:full":"8611 Baltimore National Pike Middletown MD 21769",
    "addr:housenumber":"8611",
    "addr:postcode":"21769",
    "addr:street":"Baltimore National Pike",
    "iso:country":"US",
    "sg:address":"8611 Baltimore National Pike",
    "sg:city":"Middletown",
    "sg:classifiers":[
        {
            "category":"Building & Trades",
            "subcategory":"Landscaping Services",
            "type":"Services"
        }
    ],
    "sg:phone":"+1 301 371 5141",
    "sg:postcode":"21769",
    "sg:province":"MD",
    "sg:tags":[
        "landscape",
        "contractor"
    ],
    "wof:name":"Personal Touch Lawn & Garden",
    "wof:placetype":"venue"
},
  "geometry": {"coordinates":[-77.515545,39.472079],"type":"Point"}
}