{
  "type": "Feature",
  "properties": {
    "addr:full":"6250 Columbia Crossing Dr Columbia MD 21045",
    "addr:housenumber":"6250",
    "addr:postcode":"21045",
    "addr:street":"Columbia Crossing Dr",
    "iso:country":"US",
    "sg:address":"6250 Columbia Crossing Dr",
    "sg:city":"Columbia",
    "sg:classifiers":[
        {
            "category":"Health Services",
            "subcategory":"Optometrist",
            "type":"Services"
        },
        {
            "category":"Shopping",
            "subcategory":"Optician",
            "type":"Retail Goods"
        }
    ],
    "sg:phone":"+1 443 285 0100",
    "sg:postcode":"21045",
    "sg:province":"MD",
    "sg:tags":[
        "eyewear"
    ],
    "sg:website":"http://www.steinoptical.com",
    "wof:name":"Doctor's Visionworks",
    "wof:placetype":"venue"
},
  "geometry": {"coordinates":[-76.814499,39.198299],"type":"Point"}
}