{
  "type": "Feature",
  "properties": {
    "addr:full":"30165 Three Notch Rd Charlotte Hall MD 20622",
    "addr:housenumber":"30165",
    "addr:postcode":"20622",
    "addr:street":"Three Notch Rd",
    "iso:country":"US",
    "sg:address":"30165 Three Notch Rd",
    "sg:city":"Charlotte Hall",
    "sg:classifiers":[
        {
            "category":"Banks & Credit Unions",
            "subcategory":"Bank",
            "type":"Services"
        }
    ],
    "sg:phone":"+1 301 645 7509",
    "sg:postcode":"20622",
    "sg:province":"MD",
    "wof:name":"Community Bank Of Tri-County",
    "wof:placetype":"venue"
},
  "geometry": {"coordinates":[-76.77524,38.496879],"type":"Point"}
}