{
  "type": "Feature",
  "properties": {
    "addr:full":"8325 Guilford Rd Columbia MD 21046",
    "addr:housenumber":"8325",
    "addr:postcode":"21046",
    "addr:street":"Guilford Rd",
    "iso:country":"US",
    "sg:address":"8325 Guilford Rd",
    "sg:city":"Columbia",
    "sg:classifiers":[
        {
            "category":"Shopping",
            "subcategory":"Computers & Home Electronics",
            "type":"Retail Goods"
        }
    ],
    "sg:phone":"+1 410 381 2310",
    "sg:postcode":"21046",
    "sg:province":"MD",
    "sg:tags":[
        "software"
    ],
    "sg:website":"www.segamicorp.com",
    "wof:name":"Segami Corp",
    "wof:placetype":"venue"
},
  "geometry": {"coordinates":[-76.870062,39.176705],"type":"Point"}
}