{
  "type": "Feature",
  "properties": {
    "iso:country":"US",
    "sg:address":"37 N Market St",
    "sg:city":"Frederick",
    "sg:classifiers":[
        {
            "category":"Banks & Credit Unions",
            "subcategory":"Bank",
            "type":"Services"
        }
    ],
    "sg:phone":"+1 301 662 5086",
    "sg:postcode":"21701",
    "sg:province":"MD",
    "sg:tags":[
        "saving",
        "commercial"
    ],
    "sg:website":"http://www.graystonebank.com",
    "wof:name":"Graystone Bank",
    "wof:placetype":"venue"
},
  "geometry": {"coordinates":[-77.410904,39.414613],"type":"Point"}
}