{
  "type": "Feature",
  "properties": {
    "iso:country":"US",
    "sg:address":"31 S Calvert St",
    "sg:city":"Baltimore",
    "sg:classifiers":[
        {
            "category":"Banks & Credit Unions",
            "subcategory":"Investment Brokerage",
            "type":"Services"
        }
    ],
    "sg:phone":"+1 410 837 3377",
    "sg:postcode":"21202",
    "sg:province":"MD",
    "sg:tags":[
        "advisory",
        "financial"
    ],
    "wof:name":"T D Securities",
    "wof:placetype":"venue"
},
  "geometry": {"coordinates":[-76.612061,39.287841],"type":"Point"}
}