{
  "type": "Feature",
  "properties": {
    "iso:country":"US",
    "sg:address":"101 Monroe St",
    "sg:city":"Rockville",
    "sg:classifiers":[
        {
            "category":"Government",
            "subcategory":"Court House",
            "type":"Public Place"
        }
    ],
    "sg:phone":"+1 240 777 6700",
    "sg:postcode":"20850",
    "sg:province":"MD",
    "sg:tags":[
        "legal"
    ],
    "wof:name":"County Attorney",
    "wof:placetype":"venue"
},
  "geometry": {"coordinates":[-77.1492,39.081953],"type":"Point"}
}