{
  "type": "Feature",
  "properties": {
    "iso:country":"US",
    "sg:address":"7364 Baltimore Annapolis Blvd",
    "sg:city":"Glen Burnie",
    "sg:classifiers":[
        {
            "category":"Home & Garden",
            "subcategory":"Carpets & Floor Coverings",
            "type":"Retail Goods"
        }
    ],
    "sg:phone":"+1 410 787 8686",
    "sg:postcode":"21061",
    "sg:province":"MD",
    "sg:tags":[
        "material"
    ],
    "wof:name":"Interface Architectural Resour",
    "wof:placetype":"venue"
},
  "geometry": {"coordinates":[-76.63241600000001,39.171624],"type":"Point"}
}