{
  "type": "Feature",
  "properties": {
    "addr:full":"890 Rockville Pike Rockville MD 20852",
    "addr:housenumber":"890",
    "addr:postcode":"20852",
    "addr:street":"Rockville Pike",
    "iso:country":"US",
    "sg:address":"890 Rockville Pike",
    "sg:city":"Rockville",
    "sg:classifiers":[
        {
            "category":"Professional",
            "type":"Services"
        }
    ],
    "sg:phone":"+1 301 762 1660",
    "sg:postcode":"20852",
    "sg:province":"MD",
    "sg:tags":[
        "establishment"
    ],
    "wof:name":"Winter Green Texico",
    "wof:placetype":"venue"
},
  "geometry": {"coordinates":[-77.13893,39.076927],"type":"Point"}
}