{
  "type": "Feature",
  "properties": {
    "addr:full":"4611 Sangamore Rd Bethesda MD 20816",
    "addr:housenumber":"4611",
    "addr:postcode":"20816",
    "addr:street":"Sangamore Rd",
    "iso:country":"US",
    "sg:address":"4611 Sangamore Rd",
    "sg:city":"Bethesda",
    "sg:classifiers":[
        {
            "category":"Restaurant",
            "type":"Food & Drink"
        }
    ],
    "sg:menulink":"http://www.allmenus.com/md/bethesda/275168-praline-bakery--restaurant/menu/",
    "sg:phone":"+1 301 229 8180",
    "sg:postcode":"20816",
    "sg:province":"MD",
    "sg:tags":[
        "american"
    ],
    "wof:name":"Praline Bakery & Restaurant",
    "wof:placetype":"venue"
},
  "geometry": {"coordinates":[-77.12002,38.948873],"type":"Point"}
}