{
  "type": "Feature",
  "properties": {
    "addr:full":"1711 Edgewood Rd Parkville MD 21234",
    "addr:housenumber":"1711",
    "addr:postcode":"21234",
    "addr:street":"Edgewood Rd",
    "iso:country":"US",
    "sg:address":"1711 Edgewood Rd",
    "sg:city":"Parkville",
    "sg:classifiers":[
        {
            "category":"Real Estate",
            "subcategory":"Real Estate Operator",
            "type":"Services"
        }
    ],
    "sg:phone":"+1 410 661 6800",
    "sg:postcode":"21234",
    "sg:province":"MD",
    "sg:tags":[
        "apartment"
    ],
    "wof:name":"Loch Raven Village Apartments",
    "wof:placetype":"venue"
},
  "geometry": {"coordinates":[-76.565736,39.389742],"type":"Point"}
}