{
  "type": "Feature",
  "properties": {
    "iso:country":"US",
    "sg:address":"10400 Ridgland Rd",
    "sg:city":"Cockysvl Hnt Vly",
    "sg:classifiers":[
        {
            "category":"Personal",
            "type":"Services"
        }
    ],
    "sg:phone":"+1 410 666 5995",
    "sg:postcode":"21030",
    "sg:province":"MD",
    "sg:tags":[
        "control",
        "weight"
    ],
    "wof:name":"Family Accupunctcure Ctr",
    "wof:placetype":"venue"
},
  "geometry": {"coordinates":[-76.620238,39.472578],"type":"Point"}
}