{
  "type": "Feature",
  "properties": {
    "iso:country":"US",
    "sg:address":"222 Severn Ave",
    "sg:city":"Annapolis",
    "sg:classifiers":[
        {
            "category":"Shopping",
            "subcategory":"Computers & Home Electronics",
            "type":"Retail Goods"
        }
    ],
    "sg:phone":"+1 410 263 2626",
    "sg:postcode":"21403",
    "sg:province":"MD",
    "sg:tags":[
        "software"
    ],
    "wof:name":"Quantum 3D",
    "wof:placetype":"venue"
},
  "geometry": {"coordinates":[-76.48132699999999,38.972425],"type":"Point"}
}