{
  "type": "Feature",
  "properties": {
    "iso:country":"US",
    "sg:address":"2217 Defense Hwy",
    "sg:city":"Crofton",
    "sg:classifiers":[
        {
            "category":"Manufacturing",
            "subcategory":"Printing",
            "type":"Manufacturing & Wholesale Goods"
        }
    ],
    "sg:phone":"+1 410 451 5946",
    "sg:postcode":"21114",
    "sg:province":"MD",
    "sg:tags":[
        "printer"
    ],
    "wof:name":"Minuteman Press",
    "wof:placetype":"venue"
},
  "geometry": {"coordinates":[-76.69822499999999,38.992],"type":"Point"}
}