{
  "type": "Feature",
  "properties": {
    "addr:full":"1724 Woodlawn Dr Ste 27 Gwynn Oak MD 21207",
    "addr:housenumber":"1724",
    "addr:postcode":"21207",
    "addr:street":"Woodlawn Dr Ste 27",
    "iso:country":"US",
    "sg:address":"1724 Woodlawn Dr Ste 27",
    "sg:city":"Gwynn Oak",
    "sg:classifiers":[
        {
            "category":"Education",
            "subcategory":"Kindergarten",
            "type":"Public Place"
        }
    ],
    "sg:phone":"+1 410 298 6771",
    "sg:postcode":"21207",
    "sg:province":"MD",
    "sg:tags":[
        "school",
        "driving"
    ],
    "sg:website":"www.mydrivingschoolinc.com",
    "wof:name":"My Driving School Inc",
    "wof:placetype":"venue"
},
  "geometry": {"coordinates":[-76.735601,39.313919],"type":"Point"}
}