{
  "type": "Feature",
  "properties": {
    "addr:full":"6914 Emerson St Hyattsville MD 20784",
    "addr:housenumber":"6914",
    "addr:postcode":"20784",
    "addr:street":"Emerson St",
    "iso:country":"US",
    "sg:address":"6914 Emerson St",
    "sg:city":"Hyattsville",
    "sg:classifiers":[
        {
            "category":"Professional",
            "subcategory":"Business Services",
            "type":"Services"
        }
    ],
    "sg:phone":"+1 301 341 6404",
    "sg:postcode":"20784",
    "sg:province":"MD",
    "wof:name":"Trend Mart",
    "wof:placetype":"venue"
},
  "geometry": {"coordinates":[-76.89882,38.951662],"type":"Point"}
}