{
  "type": "Feature",
  "properties": {
    "iso:country":"US",
    "sg:address":"204 E Alder St",
    "sg:city":"Oakland",
    "sg:classifiers":[
        {
            "category":"Professional",
            "type":"Services"
        }
    ],
    "sg:phone":"+1 301 359 8000",
    "sg:postcode":"21550",
    "sg:province":"MD",
    "sg:tags":[
        "establishment"
    ],
    "wof:name":"Skidmore & Alderson Pa",
    "wof:placetype":"venue"
},
  "geometry": {"coordinates":[-79.408247,39.408377],"type":"Point"}
}