{
  "type": "Feature",
  "properties": {
    "iso:country":"US",
    "sg:address":"834 Bay Ridge Ave",
    "sg:city":"Annapolis",
    "sg:classifiers":[
        {
            "category":"Personal",
            "type":"Services"
        }
    ],
    "sg:phone":"+1 410 280 5660",
    "sg:postcode":"21403",
    "sg:province":"MD",
    "wof:name":"Bodies By Lili",
    "wof:placetype":"venue"
},
  "geometry": {"coordinates":[-76.488333,38.967623],"type":"Point"}
}