{
  "type": "Feature",
  "properties": {
    "addr:full":"3026 Liberty Heights Ave Baltimore MD 21215",
    "addr:housenumber":"3026",
    "addr:postcode":"21215",
    "addr:street":"Liberty Heights Ave",
    "iso:country":"US",
    "sg:address":"3026 Liberty Heights Ave",
    "sg:city":"Baltimore",
    "sg:classifiers":[
        {
            "category":"Shopping",
            "subcategory":"Clothing, Apparel, & Fashions",
            "type":"Retail Goods"
        }
    ],
    "sg:phone":"+1 410 383 2646",
    "sg:postcode":"21215",
    "sg:province":"MD",
    "wof:name":"Hendins",
    "wof:placetype":"venue"
},
  "geometry": {"coordinates":[-76.66735199999999,39.323039],"type":"Point"}
}