{
  "type": "Feature",
  "properties": {
    "addr:full":"10045 Red Run Blvd Owings Mills MD 21117",
    "addr:housenumber":"10045",
    "addr:postcode":"21117",
    "addr:street":"Red Run Blvd",
    "iso:country":"US",
    "sg:address":"10045 Red Run Blvd",
    "sg:city":"Owings Mills",
    "sg:classifiers":[
        {
            "category":"Insurance",
            "subcategory":"Insurance Agent",
            "type":"Services"
        }
    ],
    "sg:phone":"+1 410 581 9500",
    "sg:postcode":"21117",
    "sg:province":"MD",
    "wof:name":"Print Delete Gates Mc Donald",
    "wof:placetype":"venue"
},
  "geometry": {"coordinates":[-76.779145,39.400293],"type":"Point"}
}