{
  "type": "Feature",
  "properties": {
    "iso:country":"US",
    "sg:address":"3278 Springs Dr W",
    "sg:city":"Ellicott City",
    "sg:classifiers":[
        {
            "category":"Health Services",
            "subcategory":"Medical Lab",
            "type":"Services"
        }
    ],
    "sg:phone":"+1 410 480 1460",
    "sg:postcode":"21043",
    "sg:province":"MD",
    "sg:tags":[
        "support",
        "administrative"
    ],
    "wof:name":"Michelle Beth Kaminski",
    "wof:placetype":"venue"
},
  "geometry": {"coordinates":[-76.81569,39.284772],"type":"Point"}
}