{
  "type": "Feature",
  "properties": {
    "iso:country":"US",
    "sg:address":"16302 Alderwood Ln",
    "sg:city":"Bowie",
    "sg:classifiers":[
        {
            "category":"Professional",
            "subcategory":"Computer Services",
            "type":"Services"
        }
    ],
    "sg:phone":"+1 301 346 8698",
    "sg:postcode":"20716",
    "sg:province":"MD",
    "sg:tags":[
        "datum"
    ],
    "wof:name":"Websketch",
    "wof:placetype":"venue"
},
  "geometry": {"coordinates":[-76.720747,38.917469],"type":"Point"}
}