{
  "type": "Feature",
  "properties": {
    "iso:country":"US",
    "sg:address":"1301 Mount Hermon Rd",
    "sg:city":"Salisbury",
    "sg:classifiers":[
        {
            "category":"Health Services",
            "subcategory":"Doctor",
            "type":"Services"
        }
    ],
    "sg:phone":"+1 410 749 0320",
    "sg:postcode":"21804",
    "sg:province":"MD",
    "sg:tags":[
        "dentist"
    ],
    "wof:name":"Joseph M Heher DDS",
    "wof:placetype":"venue"
},
  "geometry": {"coordinates":[-75.568911,38.367113],"type":"Point"}
}