{
  "type": "Feature",
  "properties": {
    "iso:country":"US",
    "sg:address":"1686 Coventry Pl",
    "sg:city":"Annapolis",
    "sg:classifiers":[
        {
            "category":"Home & Garden",
            "subcategory":"Building Materials",
            "type":"Retail Goods"
        }
    ],
    "sg:phone":"+1 443 994 5725",
    "sg:postcode":"21401",
    "sg:province":"MD",
    "sg:tags":[
        "roofing"
    ],
    "wof:name":"Certainteed Commercial Roofing",
    "wof:placetype":"venue"
},
  "geometry": {"coordinates":[-76.547686,39.019504],"type":"Point"}
}