{
  "type": "Feature",
  "properties": {
    "iso:country":"US",
    "sg:address":"3220 Mountain Rd",
    "sg:city":"Pasadena",
    "sg:classifiers":[
        {
            "category":"Building & Trades",
            "subcategory":"Construction",
            "type":"Services"
        }
    ],
    "sg:phone":"+1 410 255 3700",
    "sg:postcode":"21122",
    "sg:province":"MD",
    "sg:tags":[
        "general",
        "contractor"
    ],
    "wof:name":"Adams Construction",
    "wof:placetype":"venue"
},
  "geometry": {"coordinates":[-76.53448,39.125972],"type":"Point"}
}