{
  "type": "Feature",
  "properties": {
    "iso:country":"US",
    "sg:address":"300 Hopkins Rd",
    "sg:city":"Baltimore",
    "sg:classifiers":[
        {
            "category":"Education",
            "subcategory":"Special Training",
            "type":"Public Place"
        }
    ],
    "sg:phone":"+1 410 377 9077",
    "sg:postcode":"21212",
    "sg:province":"MD",
    "sg:tags":[
        "school",
        "language"
    ],
    "wof:name":"Baltimore French Language School",
    "wof:placetype":"venue"
},
  "geometry": {"coordinates":[-76.612694,39.376579],"type":"Point"}
}