{
  "type": "Feature",
  "properties": {
    "iso:country":"US",
    "sg:address":"370 Cypress St",
    "sg:city":"Millington",
    "sg:classifiers":[
        {
            "category":"Retail",
            "subcategory":"Funeral Services",
            "type":"Services"
        }
    ],
    "sg:phone":"+1 410 928 5311",
    "sg:postcode":"21651",
    "sg:province":"MD",
    "sg:tags":[
        "director"
    ],
    "wof:name":"Fellows Helfenbein & Newnam",
    "wof:placetype":"venue"
},
  "geometry": {"coordinates":[-75.843052,39.259534],"type":"Point"}
}