{
  "type": "Feature",
  "properties": {
    "iso:country":"US",
    "sg:address":"217 E Redwood St Fl 22",
    "sg:city":"Baltimore",
    "sg:classifiers":[
        {
            "category":"Professional",
            "subcategory":"Accounting & Tax Preparation",
            "type":"Services"
        }
    ],
    "sg:phone":"+1 410 767 6351",
    "sg:postcode":"21202",
    "sg:province":"MD",
    "sg:tags":[
        "public",
        "accountants-certified"
    ],
    "wof:name":"Joseph C Okechukwu Mba Cpa",
    "wof:placetype":"venue"
},
  "geometry": {"coordinates":[-76.612013,39.288921],"type":"Point"}
}