{
  "type": "Feature",
  "properties": {
    "iso:country":"US",
    "sg:address":"3255 Breckenridge Way",
    "sg:city":"Riva",
    "sg:classifiers":[
        {
            "category":"Professional",
            "subcategory":"Art Services",
            "type":"Services"
        }
    ],
    "sg:phone":"+1 410 956 8481",
    "sg:postcode":"21140",
    "sg:province":"MD",
    "sg:tags":[
        "commercial",
        "design"
    ],
    "wof:name":"S J Design Inc",
    "wof:placetype":"venue"
},
  "geometry": {"coordinates":[-76.586401,38.941816],"type":"Point"}
}