{
  "type": "Feature",
  "properties": {
    "iso:country":"US",
    "sg:address":"10297 Globe Dr",
    "sg:city":"Ellicott City",
    "sg:classifiers":[
        {
            "category":"Home & Garden",
            "subcategory":"Home Furnishings",
            "type":"Retail Goods"
        }
    ],
    "sg:phone":"+1 410 480 7000",
    "sg:postcode":"21042",
    "sg:province":"MD",
    "sg:tags":[
        "window",
        "covering"
    ],
    "wof:name":"Window Scenes",
    "wof:placetype":"venue"
},
  "geometry": {"coordinates":[-76.867954,39.278441],"type":"Point"}
}