{
  "type": "Feature",
  "properties": {
    "iso:country":"US",
    "sg:address":"8004 Moss Bank Dr",
    "sg:city":"Laurel",
    "sg:classifiers":[
        {
            "category":"Professional",
            "subcategory":"Business Services",
            "type":"Services"
        }
    ],
    "sg:phone":"+1 301 498 3485",
    "sg:postcode":"20724",
    "sg:province":"MD",
    "sg:tags":[
        "contract",
        "background",
        "check"
    ],
    "wof:name":"Rdr Investigations",
    "wof:placetype":"venue"
},
  "geometry": {"coordinates":[-76.807208,39.116609],"type":"Point"}
}