{
  "type": "Feature",
  "properties": {
    "addr:full":"1725 Gwynn Oak Ave Gwynn Oak MD 21207",
    "addr:housenumber":"1725",
    "addr:postcode":"21207",
    "addr:street":"Gwynn Oak Ave",
    "iso:country":"US",
    "sg:address":"1725 Gwynn Oak Ave",
    "sg:city":"Gwynn Oak",
    "sg:classifiers":[
        {
            "category":"Retail",
            "subcategory":"Auto Repair",
            "type":"Services"
        }
    ],
    "sg:phone":"+1 410 265 6662",
    "sg:postcode":"21207",
    "sg:province":"MD",
    "wof:name":"Jordan Auto Services",
    "wof:placetype":"venue"
},
  "geometry": {"coordinates":[-76.729797,39.3125],"type":"Point"}
}