{
  "type": "Feature",
  "properties": {
    "addr:full":"231 Cardamon Dr Edgewater MD 21037",
    "addr:housenumber":"231",
    "addr:postcode":"21037",
    "addr:street":"Cardamon Dr",
    "iso:country":"US",
    "sg:address":"231 Cardamon Dr",
    "sg:city":"Edgewater",
    "sg:classifiers":[
        {
            "category":"Building & Trades",
            "subcategory":"Construction",
            "type":"Services"
        }
    ],
    "sg:phone":"+1 410 573 1863",
    "sg:postcode":"21037",
    "sg:province":"MD",
    "sg:tags":[
        "downspouts",
        "gutter"
    ],
    "wof:name":"Action Vacuum Gutter Cleaning",
    "wof:placetype":"venue"
},
  "geometry": {"coordinates":[-76.553462,38.972569],"type":"Point"}
}