{
  "type": "Feature",
  "properties": {
    "iso:country":"US",
    "sg:address":"1024 Shore Acres Rd",
    "sg:city":"Arnold",
    "sg:classifiers":[
        {
            "category":"Professional",
            "subcategory":"Management & Consulting",
            "type":"Services"
        }
    ],
    "sg:phone":"+1 410 757 7714",
    "sg:postcode":"21012",
    "sg:province":"MD",
    "sg:tags":[
        "business"
    ],
    "wof:name":"Degen Assoc Interpretive Svcs",
    "wof:placetype":"venue"
},
  "geometry": {"coordinates":[-76.457038,39.058466],"type":"Point"}
}