{
  "type": "Feature",
  "properties": {
    "iso:country":"US",
    "sg:address":"104 Water St Ste 300",
    "sg:city":"Baltimore",
    "sg:classifiers":[
        {
            "category":"Professional",
            "subcategory":"Art Services",
            "type":"Services"
        }
    ],
    "sg:phone":"+1 410 332 0041",
    "sg:postcode":"21202",
    "sg:province":"MD",
    "sg:tags":[
        "graphic",
        "designer"
    ],
    "sg:website":"http://www.noinc.com",
    "wof:name":"No.Inc",
    "wof:placetype":"venue"
},
  "geometry": {"coordinates":[-76.613302,39.288186],"type":"Point"}
}