{
  "type": "Feature",
  "properties": {
    "addr:full":"8502 Gradien Dr Nottingham MD 21236",
    "addr:housenumber":"8502",
    "addr:postcode":"21236",
    "addr:street":"Gradien Dr",
    "iso:country":"US",
    "sg:address":"8502 Gradien Dr",
    "sg:city":"Nottingham",
    "sg:classifiers":[
        {
            "category":"Transit Center",
            "subcategory":"Freight",
            "type":"Transportation"
        },
        {
            "category":"Freight",
            "type":"Transportation"
        }
    ],
    "sg:phone":"+1 410 933 0252",
    "sg:postcode":"21236",
    "sg:province":"MD",
    "sg:tags":[
        "trucking-motor",
        "trucking"
    ],
    "wof:name":"Time Travel Transport",
    "wof:placetype":"venue"
},
  "geometry": {"coordinates":[-76.50471899999999,39.387875],"type":"Point"}
}