{
  "type": "Feature",
  "properties": {
    "addr:full":"210 Marlboro Ave Easton MD 21601",
    "addr:housenumber":"210",
    "addr:postcode":"21601",
    "addr:street":"Marlboro Ave",
    "iso:country":"US",
    "sg:address":"210 Marlboro Ave",
    "sg:city":"Easton",
    "sg:classifiers":[
        {
            "category":"Shopping",
            "subcategory":"Jewelry",
            "type":"Retail Goods"
        }
    ],
    "sg:phone":"+1 410 822 5398",
    "sg:postcode":"21601",
    "sg:province":"MD",
    "sg:tags":[
        "jeweler"
    ],
    "wof:name":"Delmarva Jewelers",
    "wof:placetype":"venue"
},
  "geometry": {"coordinates":[-76.080522,38.780449],"type":"Point"}
}