{
  "type": "Feature",
  "properties": {
    "iso:country":"US",
    "sg:address":"6108 Oxon Hill Rd",
    "sg:city":"Oxon Hill",
    "sg:classifiers":[
        {
            "category":"Food & Beverages",
            "subcategory":"Liquor & Beverages",
            "type":"Retail Goods"
        }
    ],
    "sg:phone":"+1 301 567 4200",
    "sg:postcode":"20745",
    "sg:province":"MD",
    "sg:tags":[
        "beer",
        "spirit",
        "wine"
    ],
    "wof:name":"Esquire Liquors",
    "wof:placetype":"venue"
},
  "geometry": {"coordinates":[-76.975098,38.8055],"type":"Point"}
}