{
  "type": "Feature",
  "properties": {
    "iso:country":"US",
    "sg:address":"12904 Middlevale Ln",
    "sg:city":"Silver Spring",
    "sg:classifiers":[
        {
            "category":"Education",
            "subcategory":"Vocational School",
            "type":"Public Place"
        }
    ],
    "sg:phone":"+1 301 933 6707",
    "sg:postcode":"20906",
    "sg:province":"MD",
    "sg:tags":[
        "technical",
        "trade"
    ],
    "wof:name":"Bell & Howell Schools",
    "wof:placetype":"venue"
},
  "geometry": {"coordinates":[-77.040648,39.065993],"type":"Point"}
}