{
  "type": "Feature",
  "properties": {
    "iso:country":"US",
    "sg:address":"24 Locharron Dr",
    "sg:city":"Elkton",
    "sg:classifiers":[
        {
            "category":"Professional",
            "subcategory":"Computer Services",
            "type":"Services"
        }
    ],
    "sg:phone":"+1 410 398 0125",
    "sg:postcode":"21921",
    "sg:province":"MD",
    "sg:tags":[
        "design",
        "system"
    ],
    "wof:name":"Whitmyre Equipment Company",
    "wof:placetype":"venue"
},
  "geometry": {"coordinates":[-75.793224,39.688735],"type":"Point"}
}