{
  "type": "Feature",
  "properties": {
    "addr:full":"7186 Virginia Bowland Rd Westover MD 21871",
    "addr:housenumber":"7186",
    "addr:postcode":"21871",
    "addr:street":"Virginia Bowland Rd",
    "iso:country":"US",
    "sg:address":"7186 Virginia Bowland Rd",
    "sg:city":"Westover",
    "sg:classifiers":[
        {
            "category":"Farming",
            "subcategory":"Farm",
            "type":"Manufacturing & Wholesale Goods"
        }
    ],
    "sg:phone":"+1 410 623 8335",
    "sg:postcode":"21871",
    "sg:province":"MD",
    "sg:tags":[
        "crop",
        "general"
    ],
    "wof:name":"Andrew L Crockett",
    "wof:placetype":"venue"
},
  "geometry": {"coordinates":[-75.703374,38.074722],"type":"Point"}
}