{
  "type": "Feature",
  "properties": {
    "iso:country":"US",
    "sg:address":"20990 Point Lookout Rd",
    "sg:city":"Callaway",
    "sg:classifiers":[
        {
            "category":"Banks & Credit Unions",
            "subcategory":"Bank",
            "type":"Services"
        }
    ],
    "sg:phone":"+1 301 994 3405",
    "sg:postcode":"20620",
    "sg:province":"MD",
    "sg:website":"www.mdbank.com",
    "wof:name":"Maryland Bank & Trust Company Na",
    "wof:placetype":"venue"
},
  "geometry": {"coordinates":[-76.525114,38.238001],"type":"Point"}
}