{
  "type": "Feature",
  "properties": {
    "iso:country":"US",
    "sg:address":"1111 E Patrick St",
    "sg:city":"Frederick",
    "sg:classifiers":[
        {
            "category":"Food & Beverages",
            "subcategory":"Groceries & Convenience Stores",
            "type":"Retail Goods"
        }
    ],
    "sg:phone":"+1 301 228 3856",
    "sg:postcode":"21701",
    "sg:province":"MD",
    "wof:name":"Frederick Citgo",
    "wof:placetype":"venue"
},
  "geometry": {"coordinates":[-77.390112,39.408447],"type":"Point"}
}