{
  "type": "Feature",
  "properties": {
    "addr:full":"237 N College Ave Chestertown MD 21620",
    "addr:housenumber":"237",
    "addr:postcode":"21620",
    "addr:street":"N College Ave",
    "iso:country":"US",
    "sg:address":"237 N College Ave",
    "sg:city":"Chestertown",
    "sg:classifiers":[
        {
            "category":"Organizations",
            "subcategory":"Religious Organization",
            "type":"Services"
        }
    ],
    "sg:phone":"+1 410 778 2833",
    "sg:postcode":"21620",
    "sg:province":"MD",
    "sg:tags":[
        "church"
    ],
    "wof:name":"Bethel AME Church",
    "wof:placetype":"venue"
},
  "geometry": {"coordinates":[-76.070395,39.2136],"type":"Point"}
}