{
  "type": "Feature",
  "properties": {
    "iso:country":"US",
    "sg:address":"9801 Greenbelt Rd Ste 211",
    "sg:city":"Lanham",
    "sg:classifiers":[
        {
            "category":"Insurance",
            "subcategory":"Hazard Insurance",
            "type":"Services"
        }
    ],
    "sg:phone":"+1 301 794 8600",
    "sg:postcode":"20706",
    "sg:province":"MD",
    "sg:tags":[
        "commercial",
        "business"
    ],
    "sg:website":"http://www.statefarm.com",
    "wof:name":"Perry G Jones",
    "wof:placetype":"venue"
},
  "geometry": {"coordinates":[-76.834976,38.990799],"type":"Point"}
}