{
  "type": "Feature",
  "properties": {
    "iso:country":"US",
    "sg:address":"8265 Patuxent Range Rd",
    "sg:city":"Jessup",
    "sg:classifiers":[
        {
            "category":"Building & Trades",
            "subcategory":"Construction",
            "type":"Services"
        }
    ],
    "sg:phone":"+1 301 953 0001",
    "sg:postcode":"20794",
    "sg:province":"MD",
    "sg:tags":[
        "siding",
        "contractor"
    ],
    "wof:name":"Pagoda Siding Co",
    "wof:placetype":"venue"
},
  "geometry": {"coordinates":[-76.796594,39.147189],"type":"Point"}
}