{
  "type": "Feature",
  "properties": {
    "addr:full":"4738 Wakefield Rd Baltimore MD 21216",
    "addr:housenumber":"4738",
    "addr:postcode":"21216",
    "addr:street":"Wakefield Rd",
    "iso:country":"US",
    "sg:address":"4738 Wakefield Rd",
    "sg:city":"Baltimore",
    "sg:classifiers":[
        {
            "category":"Professional",
            "type":"Services"
        }
    ],
    "sg:phone":"+1 410 448 0697",
    "sg:postcode":"21216",
    "sg:province":"MD",
    "sg:tags":[
        "establishment"
    ],
    "wof:name":"Multi-Ventures",
    "wof:placetype":"venue"
},
  "geometry": {"coordinates":[-76.696478,39.319053],"type":"Point"}
}