{
  "type": "Feature",
  "properties": {
    "addr:full":"115 Franklin St Snow Hill MD 21863",
    "addr:housenumber":"115",
    "addr:postcode":"21863",
    "addr:street":"Franklin St",
    "iso:country":"US",
    "sg:address":"115 Franklin St",
    "sg:city":"Snow Hill",
    "sg:classifiers":[
        {
            "category":"Organizations",
            "subcategory":"Religious Organization",
            "type":"Services"
        }
    ],
    "sg:phone":"+1 410 632 1698",
    "sg:postcode":"21863",
    "sg:province":"MD",
    "sg:tags":[
        "church"
    ],
    "wof:name":"Makemie Memorial Presbyterian",
    "wof:placetype":"venue"
},
  "geometry": {"coordinates":[-75.39369600000001,38.176684],"type":"Point"}
}