{
  "type": "Feature",
  "properties": {
    "iso:country":"US",
    "sg:address":"907 Seton Dr",
    "sg:city":"Cumberland",
    "sg:classifiers":[
        {
            "category":"Social Services",
            "type":"Services"
        },
        {
            "category":"Personal",
            "type":"Services"
        }
    ],
    "sg:phone":"+1 301 777 0633",
    "sg:postcode":"21502",
    "sg:province":"MD",
    "sg:tags":[
        "family",
        "counselors-licensed",
        "individual",
        "marriage",
        "child",
        "professional",
        "counselor"
    ],
    "wof:name":"Covenant Counseling Ministries Inc",
    "wof:placetype":"venue"
},
  "geometry": {"coordinates":[-78.797597,39.654063],"type":"Point"}
}