{
  "type": "Feature",
  "properties": {
    "iso:country":"US",
    "sg:address":"7185 Columbia Gateway Dr",
    "sg:city":"Columbia",
    "sg:classifiers":[
        {
            "category":"Personal",
            "subcategory":"Tanning Parlor",
            "type":"Services"
        }
    ],
    "sg:phone":"+1 410 872 1300",
    "sg:postcode":"21046",
    "sg:province":"MD",
    "sg:tags":[
        "salon"
    ],
    "wof:name":"Caribbean Dreams",
    "wof:placetype":"venue"
},
  "geometry": {"coordinates":[-76.80489,39.181804],"type":"Point"}
}