{
  "type": "Feature",
  "properties": {
    "addr:full":"1813 Midsummer Ln Jarrettsville MD 21084",
    "addr:housenumber":"1813",
    "addr:postcode":"21084",
    "addr:street":"Midsummer Ln",
    "iso:country":"US",
    "sg:address":"1813 Midsummer Ln",
    "sg:city":"Jarrettsville",
    "sg:classifiers":[
        {
            "category":"Manufacturing",
            "subcategory":"Jewelry",
            "type":"Manufacturing & Wholesale Goods"
        }
    ],
    "sg:phone":"+1 410 692 2103",
    "sg:postcode":"21084",
    "sg:province":"MD",
    "sg:tags":[
        "rings",
        "mfg"
    ],
    "wof:name":"Jostens Inc",
    "wof:placetype":"venue"
},
  "geometry": {"coordinates":[-76.453531,39.648327],"type":"Point"}
}