{
  "type": "Feature",
  "properties": {
    "addr:full":"6619 Mount Vernon Ave Baltimore MD 21215",
    "addr:housenumber":"6619",
    "addr:postcode":"21215",
    "addr:street":"Mount Vernon Ave",
    "iso:country":"US",
    "sg:address":"6619 Mount Vernon Ave",
    "sg:city":"Baltimore",
    "sg:classifiers":[
        {
            "category":"Building & Trades",
            "subcategory":"Construction",
            "type":"Services"
        }
    ],
    "sg:phone":"+1 410 602 1006",
    "sg:postcode":"21215",
    "sg:province":"MD",
    "sg:tags":[
        "general",
        "contractor"
    ],
    "wof:name":"Gary Johnson Construction",
    "wof:placetype":"venue"
},
  "geometry": {"coordinates":[-76.714241,39.351367],"type":"Point"}
}