{
  "type": "Feature",
  "properties": {
    "iso:country":"US",
    "sg:address":"6822 Oak Hall Ln",
    "sg:city":"Columbia",
    "sg:classifiers":[
        {
            "category":"Wholesale",
            "subcategory":"Groceries",
            "type":"Manufacturing & Wholesale Goods"
        }
    ],
    "sg:phone":"+1 410 290 9800",
    "sg:postcode":"21045",
    "sg:province":"MD",
    "sg:tags":[
        "food",
        "broker",
        "general"
    ],
    "wof:name":"Acosta Sales & Marketing Co",
    "wof:placetype":"venue"
},
  "geometry": {"coordinates":[-76.823537,39.183482],"type":"Point"}
}