{
  "type": "Feature",
  "properties": {
    "iso:country":"US",
    "sg:address":"10776 Grays Corner Rd",
    "sg:city":"Berlin",
    "sg:classifiers":[
        {
            "category":"Sports & Exercise",
            "subcategory":"Gym",
            "type":"Entertainment"
        }
    ],
    "sg:phone":"+1 410 641 0509",
    "sg:postcode":"21811",
    "sg:province":"MD",
    "sg:tags":[
        "club",
        "health",
        "studio",
        "gymnasium"
    ],
    "wof:name":"Curves For Women",
    "wof:placetype":"venue"
},
  "geometry": {"coordinates":[-75.185952,38.345682],"type":"Point"}
}