{
  "type": "Feature",
  "properties": {
    "addr:full":"729 Mccabe Ave Baltimore MD 21212",
    "addr:housenumber":"729",
    "addr:postcode":"21212",
    "addr:street":"Mccabe Ave",
    "iso:country":"US",
    "sg:address":"729 Mccabe Ave",
    "sg:city":"Baltimore",
    "sg:classifiers":[
        {
            "category":"Cinema",
            "subcategory":"Movie Rental",
            "type":"Entertainment"
        }
    ],
    "sg:phone":"+1 443 834 0958",
    "sg:postcode":"21212",
    "sg:province":"MD",
    "sg:tags":[
        "picture",
        "exchange",
        "motion",
        "distributor",
        "film"
    ],
    "wof:name":"Tally Productions",
    "wof:placetype":"venue"
},
  "geometry": {"coordinates":[-76.60575900000001,39.352188],"type":"Point"}
}