{
  "type": "Feature",
  "properties": {
    "iso:country":"US",
    "sg:address":"2055 Carousel Dr",
    "sg:city":"Westminster",
    "sg:classifiers":[
        {
            "category":"Professional",
            "subcategory":"Business Services",
            "type":"Services"
        }
    ],
    "sg:phone":"+1 410 871 3044",
    "sg:postcode":"21157",
    "sg:province":"MD",
    "sg:tags":[
        "consultant",
        "coach"
    ],
    "wof:name":"Aaa Consulting",
    "wof:placetype":"venue"
},
  "geometry": {"coordinates":[-77.0136,39.520056],"type":"Point"}
}