{
  "type": "Feature",
  "properties": {
    "addr:full":"749 G St Pasadena MD 21122",
    "addr:housenumber":"749",
    "addr:postcode":"21122",
    "addr:street":"G St",
    "iso:country":"US",
    "sg:address":"749 G St",
    "sg:city":"Pasadena",
    "sg:classifiers":[
        {
            "category":"Communications",
            "subcategory":"Film & Video Production",
            "type":"Services"
        }
    ],
    "sg:phone":"+1 410 360 5042",
    "sg:postcode":"21122",
    "sg:province":"MD",
    "sg:tags":[
        "educational"
    ],
    "wof:name":"Write Angle Inc",
    "wof:placetype":"venue"
},
  "geometry": {"coordinates":[-76.52184699999999,39.110017],"type":"Point"}
}