{
  "type": "Feature",
  "properties": {
    "iso:country":"US",
    "sg:address":"7 Amtrak Way BWI Thurgood Marshall Airport",
    "sg:city":"Hanover",
    "sg:classifiers":[
        {
            "category":"Transit Center",
            "subcategory":"Passenger",
            "type":"Transportation"
        }
    ],
    "sg:postcode":"21076",
    "sg:province":"MD",
    "sg:website":"www.amtrak.com/servlet/ContentSe...",
    "wof:name":"Amtrak - BWI Rail Station",
    "wof:placetype":"venue"
},
  "geometry": {"coordinates":[-76.694149,39.192897],"type":"Point"}
}