{
  "type": "Feature",
  "properties": {
    "addr:full":"809 Irvington St Oxon Hill MD 20745",
    "addr:housenumber":"809",
    "addr:postcode":"20745",
    "addr:street":"Irvington St",
    "iso:country":"US",
    "sg:address":"809 Irvington St",
    "sg:city":"Oxon Hill",
    "sg:classifiers":[
        {
            "category":"Retail",
            "subcategory":"Repair Shop",
            "type":"Services"
        }
    ],
    "sg:phone":"+1 301 567 5320",
    "sg:postcode":"20745",
    "sg:province":"MD",
    "sg:tags":[
        "appliance"
    ],
    "wof:name":"Freelance Appliance Svc",
    "wof:placetype":"venue"
},
  "geometry": {"coordinates":[-76.99533,38.822291],"type":"Point"}
}