{
  "type": "Feature",
  "properties": {
    "addr:full":"309 N Washington St Snow Hill MD 21863",
    "addr:housenumber":"309",
    "addr:postcode":"21863",
    "addr:street":"N Washington St",
    "iso:country":"US",
    "sg:address":"309 N Washington St",
    "sg:city":"Snow Hill",
    "sg:classifiers":[
        {
            "category":"Banks & Credit Unions",
            "subcategory":"Bank",
            "type":"Services"
        }
    ],
    "sg:phone":"+1 410 632 3151",
    "sg:postcode":"21863",
    "sg:province":"MD",
    "wof:name":"Peninsula Bank",
    "wof:placetype":"venue"
},
  "geometry": {"coordinates":[-75.39406,38.178348],"type":"Point"}
}