{
  "type": "Feature",
  "properties": {
    "iso:country":"US",
    "sg:address":"1018 S Robinson St",
    "sg:city":"Baltimore",
    "sg:classifiers":[
        {
            "category":"Building & Trades",
            "subcategory":"Cleaning & Sanitation",
            "type":"Services"
        }
    ],
    "sg:phone":"+1 443 801 0008",
    "sg:postcode":"21224",
    "sg:province":"MD",
    "sg:tags":[
        "home"
    ],
    "sg:website":"www.greenapplecleaningmd.com",
    "wof:name":"Green Apple Cleaning",
    "wof:placetype":"venue"
},
  "geometry": {"coordinates":[-76.572064,39.280822],"type":"Point"}
}