{
  "type": "Feature",
  "properties": {
    "iso:country":"US",
    "sg:address":"16421 Lappans Rd",
    "sg:city":"Williamsport",
    "sg:classifiers":[
        {
            "category":"Organizations",
            "subcategory":"Religious Organization",
            "type":"Services"
        }
    ],
    "sg:phone":"+1 301 223 8125",
    "sg:postcode":"21795",
    "sg:province":"MD",
    "sg:tags":[
        "church"
    ],
    "wof:name":"Seventh Day Adventist Church",
    "wof:placetype":"venue"
},
  "geometry": {"coordinates":[-77.795112,39.581139],"type":"Point"}
}