{
  "type": "Feature",
  "properties": {
    "addr:full":"295 Muddy Branch Rd Gaithersburg MD 20878",
    "addr:housenumber":"295",
    "addr:postcode":"20878",
    "addr:street":"Muddy Branch Rd",
    "iso:country":"US",
    "sg:address":"295 Muddy Branch Rd",
    "sg:city":"Gaithersburg",
    "sg:classifiers":[
        {
            "category":"Retail",
            "subcategory":"Self-service Laundry",
            "type":"Services"
        }
    ],
    "sg:phone":"+1 301 670 9139",
    "sg:postcode":"20878",
    "sg:province":"MD",
    "sg:tags":[
        "coin"
    ],
    "wof:name":"Muddy Branch Laundry Mat",
    "wof:placetype":"venue"
},
  "geometry": {"coordinates":[-77.207221,39.130077],"type":"Point"}
}