{
  "type": "Feature",
  "properties": {
    "addr:full":"18746 Ginger Ct Germantown MD 20874",
    "addr:housenumber":"18746",
    "addr:postcode":"20874",
    "addr:street":"Ginger Ct",
    "iso:country":"US",
    "sg:address":"18746 Ginger Ct",
    "sg:city":"Germantown",
    "sg:classifiers":[
        {
            "category":"Building & Trades",
            "subcategory":"Construction",
            "type":"Services"
        }
    ],
    "sg:phone":"+1 301 540 8477",
    "sg:postcode":"20874",
    "sg:province":"MD",
    "wof:name":"Colors Unlimited 612",
    "wof:placetype":"venue"
},
  "geometry": {"coordinates":[-77.265259,39.162611],"type":"Point"}
}