{
  "type": "Feature",
  "properties": {
    "iso:country":"US",
    "sg:address":"5008 60th Ave",
    "sg:city":"Hyattsville",
    "sg:classifiers":[
        {
            "category":"Organizations",
            "subcategory":"Membership Organization",
            "type":"Services"
        }
    ],
    "sg:phone":"+1 301 927 2008",
    "sg:postcode":"20781",
    "sg:province":"MD",
    "sg:tags":[
        "sorority",
        "fraternity"
    ],
    "wof:name":"Knights Templar Of Us 2 C",
    "wof:placetype":"venue"
},
  "geometry": {"coordinates":[-76.91754899999999,38.948009],"type":"Point"}
}