{
  "type": "Feature",
  "properties": {
    "iso:country":"US",
    "sg:address":"6755 Dorsey Rd",
    "sg:city":"Elkridge",
    "sg:classifiers":[
        {
            "category":"Travel",
            "subcategory":"Hotels & Motels",
            "type":"Entertainment"
        }
    ],
    "sg:phone":"+1 877 574 2464",
    "sg:postcode":"21075",
    "sg:province":"MD",
    "sg:tags":[
        "lodging"
    ],
    "sg:website":"http://book.bestwestern.com/bestwestern/priceAvail.do?propertyCode=21028&cm_mmc=IYP-_-YP-_-property-_-21028",
    "wof:name":"Best Western Baltimore-Washington Airport",
    "wof:placetype":"venue"
},
  "geometry": {"coordinates":[-76.75639099999999,39.184778],"type":"Point"}
}