{
  "type": "Feature",
  "properties": {
    "iso:country":"US",
    "sg:address":"542 Cranbrook Rd",
    "sg:city":"Cockysvl Hnt Vly",
    "sg:classifiers":[
        {
            "category":"Shopping",
            "subcategory":"Discount & Variety Stores",
            "type":"Retail Goods"
        }
    ],
    "sg:phone":"+1 410 667 0880",
    "sg:postcode":"21030",
    "sg:province":"MD",
    "wof:name":"Dollarama",
    "wof:placetype":"venue"
},
  "geometry": {"coordinates":[-76.621969,39.471888],"type":"Point"}
}