{
  "type": "Feature",
  "properties": {
    "addr:full":"3480 Leonardtown Rd Waldorf MD 20601",
    "addr:housenumber":"3480",
    "addr:postcode":"20601",
    "addr:street":"Leonardtown Rd",
    "iso:country":"US",
    "sg:address":"3480 Leonardtown Rd",
    "sg:city":"Waldorf",
    "sg:classifiers":[
        {
            "category":"Coffee & Tea",
            "type":"Food & Drink"
        },
        {
            "category":"Bakery",
            "type":"Food & Drink"
        },
        {
            "category":"Donuts",
            "type":"Food & Drink"
        }
    ],
    "sg:menulink":"http://www.allmenus.com/md/waldorf/222436-donut-connection/menu/",
    "sg:phone":"+1 301 843 9447",
    "sg:postcode":"20601",
    "sg:province":"MD",
    "sg:tags":[
        "american",
        "pastry"
    ],
    "wof:name":"Donut Connection",
    "wof:placetype":"venue"
},
  "geometry": {"coordinates":[-76.896998,38.619075],"type":"Point"}
}