{
  "type": "Feature",
  "properties": {
    "addr:full":"7420 Westlake Ter Bethesda MD 20817",
    "addr:housenumber":"7420",
    "addr:postcode":"20817",
    "addr:street":"Westlake Ter",
    "iso:country":"US",
    "sg:address":"7420 Westlake Ter",
    "sg:city":"Bethesda",
    "sg:classifiers":[
        {
            "category":"Real Estate",
            "subcategory":"Real Estate Operator",
            "type":"Services"
        }
    ],
    "sg:phone":"+1 301 365 2511",
    "sg:postcode":"20817",
    "sg:province":"MD",
    "sg:tags":[
        "condominium"
    ],
    "wof:name":"Westlake Park Condominiums",
    "wof:placetype":"venue"
},
  "geometry": {"coordinates":[-77.15210399999999,39.026351],"type":"Point"}
}