{
  "type": "Feature",
  "properties": {
    "addr:full":"3355 Saint Johns Ln Ste F Ellicott City MD 21042",
    "addr:housenumber":"3355",
    "addr:postcode":"21042",
    "addr:street":"Saint Johns Ln Ste F",
    "iso:country":"US",
    "sg:address":"3355 Saint Johns Ln Ste F",
    "sg:city":"Ellicott City",
    "sg:classifiers":[
        {
            "category":"Health Services",
            "subcategory":"Doctor",
            "type":"Services"
        }
    ],
    "sg:phone":"+1 410 465 2056",
    "sg:postcode":"21042",
    "sg:province":"MD",
    "wof:name":"Soulen Jeffrey MD",
    "wof:placetype":"venue"
},
  "geometry": {"coordinates":[-76.825699,39.278599],"type":"Point"}
}