{
  "type": "Feature",
  "properties": {
    "iso:country":"US",
    "sg:address":"452 N Camp Meade Rd",
    "sg:city":"Linthicum Heights",
    "sg:classifiers":[
        {
            "category":"Building & Trades",
            "subcategory":"Locksmith",
            "type":"Services"
        }
    ],
    "sg:phone":"+1 443 378 3903",
    "sg:postcode":"21090",
    "sg:province":"MD",
    "sg:tags":[
        "key"
    ],
    "wof:name":"Locksmith AA",
    "wof:placetype":"venue"
},
  "geometry": {"coordinates":[-76.64445000000001,39.214124],"type":"Point"}
}