{
  "type": "Feature",
  "properties": {
    "iso:country":"US",
    "sg:address":"85 Dover Rd NE",
    "sg:city":"Glen Burnie",
    "sg:classifiers":[
        {
            "category":"Manufacturing",
            "subcategory":"Printing",
            "type":"Manufacturing & Wholesale Goods"
        }
    ],
    "sg:phone":"+1 410 760 0008",
    "sg:postcode":"21060",
    "sg:province":"MD",
    "sg:tags":[
        "bookbinder"
    ],
    "wof:name":"Advantage Book Binding Inc",
    "wof:placetype":"venue"
},
  "geometry": {"coordinates":[-76.612055,39.186886],"type":"Point"}
}