{
  "type": "Feature",
  "properties": {
    "addr:full":"6732 Oakridge Rd New Market MD 21774",
    "addr:housenumber":"6732",
    "addr:postcode":"21774",
    "addr:street":"Oakridge Rd",
    "iso:country":"US",
    "sg:address":"6732 Oakridge Rd",
    "sg:city":"New Market",
    "sg:classifiers":[
        {
            "category":"Professional",
            "type":"Services"
        }
    ],
    "sg:phone":"+1 301 798 0538",
    "sg:postcode":"21774",
    "sg:province":"MD",
    "wof:name":"Brushstrokes",
    "wof:placetype":"venue"
},
  "geometry": {"coordinates":[-77.29718,39.418551],"type":"Point"}
}