{
  "type": "Feature",
  "properties": {
    "iso:country":"US",
    "sg:address":"2426 Chillum Rd",
    "sg:city":"Hyattsville",
    "sg:classifiers":[
        {
            "category":"Health Services",
            "subcategory":"Doctor",
            "type":"Services"
        }
    ],
    "sg:phone":"+1 301 927 8808",
    "sg:postcode":"20782",
    "sg:province":"MD",
    "sg:tags":[
        "medicine",
        "internal"
    ],
    "wof:name":"Ultimate Renal Care",
    "wof:placetype":"venue"
},
  "geometry": {"coordinates":[-76.970299,38.9524],"type":"Point"}
}