{
  "type": "Feature",
  "properties": {
    "addr:full":"8338 Academy Rd Ellicott City MD 21043",
    "addr:housenumber":"8338",
    "addr:postcode":"21043",
    "addr:street":"Academy Rd",
    "iso:country":"US",
    "sg:address":"8338 Academy Rd",
    "sg:city":"Ellicott City",
    "sg:classifiers":[
        {
            "category":"Arena",
            "subcategory":"Sports Club",
            "type":"Entertainment"
        }
    ],
    "sg:phone":"+1 443 574 8999",
    "sg:postcode":"21043",
    "sg:province":"MD",
    "sg:tags":[
        "martial art"
    ],
    "wof:name":"Joseph Justin",
    "wof:placetype":"venue"
},
  "geometry": {"coordinates":[-76.790199,39.249033],"type":"Point"}
}