{
  "type": "Feature",
  "properties": {
    "addr:full":"15757 Crabbs Branch Way Rockville MD 20855",
    "addr:housenumber":"15757",
    "addr:postcode":"20855",
    "addr:street":"Crabbs Branch Way",
    "iso:country":"US",
    "sg:address":"15757 Crabbs Branch Way",
    "sg:city":"Rockville",
    "sg:classifiers":[
        {
            "category":"Travel",
            "subcategory":"Travel Agent",
            "type":"Entertainment"
        }
    ],
    "sg:phone":"+1 301 309 6601",
    "sg:postcode":"20855",
    "sg:province":"MD",
    "sg:tags":[
        "agency",
        "bureau"
    ],
    "sg:website":"www.childrensconcierge.com",
    "wof:name":"Childrens Concierge",
    "wof:placetype":"venue"
},
  "geometry": {"coordinates":[-77.15568399999999,39.111666],"type":"Point"}
}