{
  "type": "Feature",
  "properties": {
    "iso:country":"US",
    "sg:address":"1806 Old Eastern Ave",
    "sg:city":"Essex",
    "sg:classifiers":[
        {
            "category":"Manufacturing",
            "subcategory":"Food",
            "type":"Manufacturing & Wholesale Goods"
        }
    ],
    "sg:phone":"+1 410 686 8805",
    "sg:postcode":"21221",
    "sg:province":"MD",
    "sg:tags":[
        "consultant",
        "product",
        "facility",
        "manufacturer"
    ],
    "wof:name":"Home Fresh Food Co",
    "wof:placetype":"venue"
},
  "geometry": {"coordinates":[-76.44650300000001,39.32234],"type":"Point"}
}