{
  "type": "Feature",
  "properties": {
    "iso:country":"US",
    "sg:address":"521 S Camp Meade Rd",
    "sg:city":"Linthicum Hts",
    "sg:classifiers":[
        {
            "category":"Retail",
            "subcategory":"Auto Repair",
            "type":"Services"
        }
    ],
    "sg:phone":"+1 410 859 9701",
    "sg:postcode":"21090",
    "sg:province":"MD",
    "sg:tags":[
        "repairing",
        "automobile"
    ],
    "wof:name":"Wayson's Citgo",
    "wof:placetype":"venue"
},
  "geometry": {"coordinates":[-76.65601700000001,39.199356],"type":"Point"}
}