{
  "type": "Feature",
  "properties": {
    "addr:full":"423 S Washington St Easton MD 21601",
    "addr:housenumber":"423",
    "addr:postcode":"21601",
    "addr:street":"S Washington St",
    "iso:country":"US",
    "sg:address":"423 S Washington St",
    "sg:city":"Easton",
    "sg:classifiers":[
        {
            "category":"Retail",
            "subcategory":"Portrait Studio",
            "type":"Services"
        }
    ],
    "sg:phone":"+1 410 820 7417",
    "sg:postcode":"21601",
    "sg:province":"MD",
    "sg:tags":[
        "photographer"
    ],
    "wof:name":"Larry Waldron Photography",
    "wof:placetype":"venue"
},
  "geometry": {"coordinates":[-76.074139,38.764809],"type":"Point"}
}