{
  "type": "Feature",
  "properties": {
    "addr:full":"12918 Old Fletchertown Rd Bowie MD 20720",
    "addr:housenumber":"12918",
    "addr:postcode":"20720",
    "addr:street":"Old Fletchertown Rd",
    "iso:country":"US",
    "sg:address":"12918 Old Fletchertown Rd",
    "sg:city":"Bowie",
    "sg:classifiers":[
        {
            "category":"Professional",
            "subcategory":"Business Services",
            "type":"Services"
        }
    ],
    "sg:phone":"+1 301 352 9244",
    "sg:postcode":"20720",
    "sg:province":"MD",
    "wof:name":"Thomas Group",
    "wof:placetype":"venue"
},
  "geometry": {"coordinates":[-76.779427,38.99255],"type":"Point"}
}