{
  "type": "Feature",
  "properties": {
    "addr:full":"16954 York Rd Monkton MD 21111",
    "addr:housenumber":"16954",
    "addr:postcode":"21111",
    "addr:street":"York Rd",
    "iso:country":"US",
    "sg:address":"16954 York Rd",
    "sg:city":"Monkton",
    "sg:classifiers":[
        {
            "category":"Retail",
            "subcategory":"Laundry & Dry Cleaning",
            "type":"Services"
        }
    ],
    "sg:phone":"+1 410 357 4011",
    "sg:postcode":"21111",
    "sg:province":"MD",
    "wof:name":"Admiral Inc",
    "wof:placetype":"venue"
},
  "geometry": {"coordinates":[-76.663321,39.589605],"type":"Point"}
}