{
  "type": "Feature",
  "properties": {
    "addr:full":"42239 Ridge Rd Mechanicsville MD 20659",
    "addr:housenumber":"42239",
    "addr:postcode":"20659",
    "addr:street":"Ridge Rd",
    "iso:country":"US",
    "sg:address":"42239 Ridge Rd",
    "sg:city":"Mechanicsville",
    "sg:classifiers":[
        {
            "category":"Home & Garden",
            "subcategory":"Building Materials",
            "type":"Retail Goods"
        }
    ],
    "sg:phone":"+1 301 373 3464",
    "sg:postcode":"20659",
    "sg:province":"MD",
    "wof:name":"Studio 1735",
    "wof:placetype":"venue"
},
  "geometry": {"coordinates":[-76.614063,38.412611],"type":"Point"}
}