{
  "type": "Feature",
  "properties": {
    "addr:full":"17 Jefferson St Berlin MD 21811",
    "addr:housenumber":"17",
    "addr:postcode":"21811",
    "addr:street":"Jefferson St",
    "iso:country":"US",
    "sg:address":"17 Jefferson St",
    "sg:city":"Berlin",
    "sg:classifiers":[
        {
            "category":"Retail",
            "subcategory":"Portrait Studio",
            "type":"Services"
        }
    ],
    "sg:phone":"+1 410 352 3211",
    "sg:postcode":"21811",
    "sg:province":"MD",
    "sg:tags":[
        "photographer"
    ],
    "wof:name":"Best Side Photography",
    "wof:placetype":"venue"
},
  "geometry": {"coordinates":[-75.21908500000001,38.324437],"type":"Point"}
}