{
  "type": "Feature",
  "properties": {
    "addr:full":"4413 Mountain Rd Pasadena MD 21122",
    "addr:housenumber":"4413",
    "addr:postcode":"21122",
    "addr:street":"Mountain Rd",
    "iso:country":"US",
    "sg:address":"4413 Mountain Rd",
    "sg:city":"Pasadena",
    "sg:classifiers":[
        {
            "category":"Bus Charters",
            "type":"Transportation"
        }
    ],
    "sg:phone":"+1 410 255 1047",
    "sg:postcode":"21122",
    "sg:province":"MD",
    "sg:tags":[
        "rental"
    ],
    "wof:name":"Wilson's Bus Svc",
    "wof:placetype":"venue"
},
  "geometry": {"coordinates":[-76.502635,39.115337],"type":"Point"}
}