{
  "type": "Feature",
  "properties": {
    "addr:full":"7504 Terra Alta Ct Lanham MD 20706",
    "addr:housenumber":"7504",
    "addr:postcode":"20706",
    "addr:street":"Terra Alta Ct",
    "iso:country":"US",
    "sg:address":"7504 Terra Alta Ct",
    "sg:city":"Lanham",
    "sg:classifiers":[
        {
            "category":"Organizations",
            "subcategory":"Religious Organization",
            "type":"Services"
        }
    ],
    "sg:phone":"+1 202 409 3065",
    "sg:postcode":"20706",
    "sg:province":"MD",
    "sg:tags":[
        "church"
    ],
    "sg:website":"www.jesuschristgmission.org",
    "wof:name":"24 Hours Prayer & Intercessory",
    "wof:placetype":"venue"
},
  "geometry": {"coordinates":[-76.88025500000001,38.978186],"type":"Point"}
}