{
  "type": "Feature",
  "properties": {
    "addr:full":"373 Short Run Rd Kitzmiller MD 21538",
    "addr:housenumber":"373",
    "addr:postcode":"21538",
    "addr:street":"Short Run Rd",
    "iso:country":"US",
    "sg:address":"373 Short Run Rd",
    "sg:city":"Kitzmiller",
    "sg:classifiers":[
        {
            "category":"Building & Trades",
            "subcategory":"Landscaping Services",
            "type":"Services"
        }
    ],
    "sg:phone":"+1 301 453 3385",
    "sg:postcode":"21538",
    "sg:province":"MD",
    "sg:tags":[
        "landscape",
        "contractor"
    ],
    "wof:name":"Maple Lane Farm & Nursery",
    "wof:placetype":"venue"
},
  "geometry": {"coordinates":[-79.22630700000001,39.384203],"type":"Point"}
}