{
  "type": "Feature",
  "properties": {
    "iso:country":"US",
    "sg:address":"687 Lofstrand Ln",
    "sg:city":"Rockville",
    "sg:classifiers":[
        {
            "category":"Organizations",
            "subcategory":"Religious Organization",
            "type":"Services"
        }
    ],
    "sg:phone":"+1 301 610 5618",
    "sg:postcode":"20850",
    "sg:province":"MD",
    "sg:tags":[
        "synagogue"
    ],
    "wof:name":"Temple Allen Industries I",
    "wof:placetype":"venue"
},
  "geometry": {"coordinates":[-77.13773999999999,39.096475],"type":"Point"}
}