{
  "type": "Feature",
  "properties": {
    "iso:country":"US",
    "sg:address":"2109 Ravenswood St",
    "sg:city":"Hyattsville",
    "sg:classifiers":[
        {
            "category":"Building & Trades",
            "subcategory":"Cleaning & Sanitation",
            "type":"Services"
        }
    ],
    "sg:phone":"+1 301 853 3503",
    "sg:postcode":"20782",
    "sg:province":"MD",
    "sg:tags":[
        "maintenance"
    ],
    "wof:name":"International Window Cleaners",
    "wof:placetype":"venue"
},
  "geometry": {"coordinates":[-76.976017,38.96825],"type":"Point"}
}