{
  "type": "Feature",
  "properties": {
    "iso:country":"US",
    "sg:address":"1015 S Noyes Dr",
    "sg:city":"Silver Spring",
    "sg:classifiers":[
        {
            "category":"Manufacturing",
            "subcategory":"Printing",
            "type":"Manufacturing & Wholesale Goods"
        }
    ],
    "sg:phone":"+1 301 565 2054",
    "sg:postcode":"20910",
    "sg:province":"MD",
    "sg:tags":[
        "printer"
    ],
    "wof:name":"Accordion Repairs-Merv Conn",
    "wof:placetype":"venue"
},
  "geometry": {"coordinates":[-77.026765,39.000592],"type":"Point"}
}