{
  "type": "Feature",
  "properties": {
    "iso:country":"US",
    "sg:address":"11 Acorn Cir",
    "sg:city":"Towson",
    "sg:classifiers":[
        {
            "category":"Professional",
            "type":"Services"
        }
    ],
    "sg:phone":"+1 410 825 2128",
    "sg:postcode":"21286",
    "sg:province":"MD",
    "sg:tags":[
        "establishment"
    ],
    "wof:name":"Tony Mumpower",
    "wof:placetype":"venue"
},
  "geometry": {"coordinates":[-76.585284,39.395142],"type":"Point"}
}