{
  "type": "Feature",
  "properties": {
    "iso:country":"US",
    "sg:address":"1701 Madison Ave",
    "sg:city":"Baltimore",
    "sg:classifiers":[
        {
            "category":"Professional",
            "subcategory":"Lawyer & Legal Services",
            "type":"Services"
        }
    ],
    "sg:phone":"+1 410 462 5800",
    "sg:postcode":"21217",
    "sg:province":"MD",
    "wof:name":"Law Offices of Rickey Nelson Jones",
    "wof:placetype":"venue"
},
  "geometry": {"coordinates":[-76.630865,39.306333],"type":"Point"}
}