{
  "type": "Feature",
  "properties": {
    "addr:full":"12079 Broad Meadow Ln Clarksville MD 21029",
    "addr:housenumber":"12079",
    "addr:postcode":"21029",
    "addr:street":"Broad Meadow Ln",
    "iso:country":"US",
    "sg:address":"12079 Broad Meadow Ln",
    "sg:city":"Clarksville",
    "sg:classifiers":[
        {
            "category":"Professional",
            "subcategory":"Management & Consulting",
            "type":"Services"
        }
    ],
    "sg:phone":"+1 410 531 1554",
    "sg:postcode":"21029",
    "sg:province":"MD",
    "sg:tags":[
        "consultant"
    ],
    "wof:name":"Georgetown Consulting",
    "wof:placetype":"venue"
},
  "geometry": {"coordinates":[-76.93156399999999,39.225676],"type":"Point"}
}