{
  "type": "Feature",
  "properties": {
    "iso:country":"US",
    "sg:address":"11755 Business Park Dr",
    "sg:city":"Waldorf",
    "sg:classifiers":[
        {
            "category":"Autos & Motor Vehicles",
            "subcategory":"Automobile Sales",
            "type":"Retail Goods"
        },
        {
            "category":"Retail",
            "subcategory":"Auto Repair",
            "type":"Services"
        }
    ],
    "sg:phone":"+1 301 843 5200",
    "sg:postcode":"20601",
    "sg:province":"MD",
    "sg:tags":[
        "car",
        "new"
    ],
    "sg:website":"http://www.chrysler.com/",
    "wof:name":"Waldorf Chrysler Jeep",
    "wof:placetype":"venue"
},
  "geometry": {"coordinates":[-76.898972,38.638401],"type":"Point"}
}