{
  "type": "Feature",
  "properties": {
    "iso:country":"US",
    "sg:address":"7831 Woodmont Ave",
    "sg:city":"Bethesda",
    "sg:classifiers":[
        {
            "category":"Professional",
            "subcategory":"Research",
            "type":"Services"
        }
    ],
    "sg:phone":"+1 301 657 5955",
    "sg:postcode":"20814",
    "sg:province":"MD",
    "sg:tags":[
        "nonphysical",
        "commercial"
    ],
    "wof:name":"Helder Surveys",
    "wof:placetype":"venue"
},
  "geometry": {"coordinates":[-77.09609,38.988649],"type":"Point"}
}