{
  "type": "Feature",
  "properties": {
    "iso:country":"US",
    "sg:address":"1057 Maryland Ave",
    "sg:city":"Hagerstown",
    "sg:classifiers":[
        {
            "category":"Home & Garden",
            "subcategory":"Carpets & Floor Coverings",
            "type":"Retail Goods"
        }
    ],
    "sg:phone":"+1 301 739 3422",
    "sg:postcode":"21740",
    "sg:province":"MD",
    "sg:tags":[
        "dealer",
        "rug"
    ],
    "wof:name":"Carpet Gallery",
    "wof:placetype":"venue"
},
  "geometry": {"coordinates":[-77.732286,39.623907],"type":"Point"}
}