{
  "type": "Feature",
  "properties": {
    "addr:full":"3227 Erdman Ave Baltimore MD 21213",
    "addr:housenumber":"3227",
    "addr:postcode":"21213",
    "addr:street":"Erdman Ave",
    "iso:country":"US",
    "sg:address":"3227 Erdman Ave",
    "sg:city":"Baltimore",
    "sg:classifiers":[
        {
            "category":"Personal",
            "subcategory":"Barber",
            "type":"Services"
        }
    ],
    "sg:phone":"+1 410 558 1145",
    "sg:postcode":"21213",
    "sg:province":"MD",
    "wof:name":"Harlem Blues Inc",
    "wof:placetype":"venue"
},
  "geometry": {"coordinates":[-76.572271,39.320553],"type":"Point"}
}