{
  "type": "Feature",
  "properties": {
    "addr:full":"12160 Parklawn Dr Rockville MD 20852",
    "addr:housenumber":"12160",
    "addr:postcode":"20852",
    "addr:street":"Parklawn Dr",
    "iso:country":"US",
    "sg:address":"12160 Parklawn Dr",
    "sg:city":"Rockville",
    "sg:classifiers":[
        {
            "category":"Retail",
            "subcategory":"Repair Shop",
            "type":"Services"
        }
    ],
    "sg:phone":"+1 301 984 8841",
    "sg:postcode":"20852",
    "sg:province":"MD",
    "wof:name":"Pawlowski Restoration",
    "wof:placetype":"venue"
},
  "geometry": {"coordinates":[-77.111457,39.059838],"type":"Point"}
}