{
  "type": "Feature",
  "properties": {
    "iso:country":"US",
    "sg:address":"3345 Crain Hwy",
    "sg:city":"Waldorf",
    "sg:classifiers":[
        {
            "category":"Restaurant",
            "type":"Food & Drink"
        }
    ],
    "sg:menulink":"http://www.allmenus.com/md/waldorf/42210-bob-evans/menu/",
    "sg:phone":"+1 301 885 2144",
    "sg:postcode":"20603",
    "sg:province":"MD",
    "sg:tags":[
        "american"
    ],
    "wof:name":"Bob Evans",
    "wof:placetype":"venue"
},
  "geometry": {"coordinates":[-76.916842,38.620486],"type":"Point"}
}