{
  "type": "Feature",
  "properties": {
    "iso:country":"US",
    "sg:address":"10845 Town Center Blvd",
    "sg:city":"Dunkirk",
    "sg:classifiers":[
        {
            "category":"Health Services",
            "subcategory":"Doctor",
            "type":"Services"
        }
    ],
    "sg:phone":"+1 410 286 3865",
    "sg:postcode":"20754",
    "sg:province":"MD",
    "sg:tags":[
        "physician",
        "surgeon"
    ],
    "wof:name":"Brophy Owens Family Practice",
    "wof:placetype":"venue"
},
  "geometry": {"coordinates":[-76.657191,38.725272],"type":"Point"}
}