{
  "type": "Feature",
  "properties": {
    "iso:country":"US",
    "sg:address":"100 E Pratt St Ste 2520",
    "sg:city":"Baltimore",
    "sg:classifiers":[
        {
            "category":"Government",
            "subcategory":"City Hall",
            "type":"Public Place"
        },
        {
            "category":"Communications",
            "subcategory":"Newspaper",
            "type":"Services"
        }
    ],
    "sg:phone":"+1 410 244 6688",
    "sg:postcode":"21202",
    "sg:province":"MD",
    "sg:tags":[
        "print",
        "medium"
    ],
    "sg:website":"www.dwlr.com",
    "wof:name":"Daily Washington Law Reporter",
    "wof:placetype":"venue"
},
  "geometry": {"coordinates":[-76.613544,39.286687],"type":"Point"}
}