{
  "type": "Feature",
  "properties": {
    "iso:country":"US",
    "sg:address":"919 Bay Ridge Ave",
    "sg:city":"Annapolis",
    "sg:classifiers":[
        {
            "category":"Autos & Motor Vehicles",
            "subcategory":"Boat Sales",
            "type":"Retail Goods"
        }
    ],
    "sg:phone":"+1 410 267 9464",
    "sg:postcode":"21403",
    "sg:province":"MD",
    "sg:tags":[
        "repair",
        "maintenance"
    ],
    "wof:name":"Easport Spar & Rigging",
    "wof:placetype":"venue"
},
  "geometry": {"coordinates":[-76.48889200000001,38.966179],"type":"Point"}
}