{
  "type": "Feature",
  "properties": {
    "addr:full":"1618 West Rd Salisbury MD 21801",
    "addr:housenumber":"1618",
    "addr:postcode":"21801",
    "addr:street":"West Rd",
    "iso:country":"US",
    "sg:address":"1618 West Rd",
    "sg:city":"Salisbury",
    "sg:classifiers":[
        {
            "category":"Real Estate",
            "subcategory":"Developer",
            "type":"Services"
        }
    ],
    "sg:phone":"+1 410 341 6338",
    "sg:postcode":"21801",
    "sg:province":"MD",
    "sg:tags":[
        "cemetery"
    ],
    "wof:name":"Green Acres Memorial Park Inc",
    "wof:placetype":"venue"
},
  "geometry": {"coordinates":[-75.612476,38.397535],"type":"Point"}
}