{
  "type": "Feature",
  "properties": {
    "addr:full":"2708 Afton St Temple Hills MD 20748",
    "addr:housenumber":"2708",
    "addr:postcode":"20748",
    "addr:street":"Afton St",
    "iso:country":"US",
    "sg:address":"2708 Afton St",
    "sg:city":"Temple Hills",
    "sg:classifiers":[
        {
            "category":"Professional",
            "subcategory":"Business Services",
            "type":"Services"
        }
    ],
    "sg:phone":"+1 301 894 9527",
    "sg:postcode":"20748",
    "sg:province":"MD",
    "wof:name":"Dreher Gray & Assoc",
    "wof:placetype":"venue"
},
  "geometry": {"coordinates":[-76.958202,38.847639],"type":"Point"}
}