{
  "type": "Feature",
  "properties": {
    "addr:full":"76 Gwynns Mill Ct Owings Mills MD 21117",
    "addr:housenumber":"76",
    "addr:postcode":"21117",
    "addr:street":"Gwynns Mill Ct",
    "iso:country":"US",
    "sg:address":"76 Gwynns Mill Ct",
    "sg:city":"Owings Mills",
    "sg:classifiers":[
        {
            "category":"Building & Trades",
            "subcategory":"Construction",
            "type":"Services"
        }
    ],
    "sg:phone":"+1 410 902 4607",
    "sg:postcode":"21117",
    "sg:province":"MD",
    "sg:tags":[
        "general",
        "contractor"
    ],
    "wof:name":"Matthew Slater Inc",
    "wof:placetype":"venue"
},
  "geometry": {"coordinates":[-76.781437,39.416257],"type":"Point"}
}