{
  "type": "Feature",
  "properties": {
    "addr:full":"5431 Woodland Blvd Oxon Hill MD 20745",
    "addr:housenumber":"5431",
    "addr:postcode":"20745",
    "addr:street":"Woodland Blvd",
    "iso:country":"US",
    "sg:address":"5431 Woodland Blvd",
    "sg:city":"Oxon Hill",
    "sg:classifiers":[
        {
            "category":"Organizations",
            "subcategory":"Professional Association",
            "type":"Services"
        }
    ],
    "sg:phone":"+1 301 505 8805",
    "sg:postcode":"20745",
    "sg:province":"MD",
    "wof:name":"Team Megamite Assn",
    "wof:placetype":"venue"
},
  "geometry": {"coordinates":[-76.97327,38.81518],"type":"Point"}
}