{
  "type": "Feature",
  "properties": {
    "addr:full":"2435 Bailey Rd Forest Hill MD 21050",
    "addr:housenumber":"2435",
    "addr:postcode":"21050",
    "addr:street":"Bailey Rd",
    "iso:country":"US",
    "sg:address":"2435 Bailey Rd",
    "sg:city":"Forest Hill",
    "sg:classifiers":[
        {
            "category":"Organizations",
            "subcategory":"Religious Organization",
            "type":"Services"
        }
    ],
    "sg:phone":"+1 410 420 3722",
    "sg:postcode":"21050",
    "sg:province":"MD",
    "sg:tags":[
        "church"
    ],
    "wof:name":"Forest Ridge Baptist Church",
    "wof:placetype":"venue"
},
  "geometry": {"coordinates":[-76.402677,39.590014],"type":"Point"}
}