{
  "type": "Feature",
  "properties": {
    "addr:full":"23 W Susquehanna Ave Baltimore MD 21204",
    "addr:housenumber":"23",
    "addr:postcode":"21204",
    "addr:street":"W Susquehanna Ave",
    "iso:country":"US",
    "sg:address":"23 W Susquehanna Ave",
    "sg:city":"Baltimore",
    "sg:classifiers":[
        {
            "category":"Banks & Credit Unions",
            "subcategory":"Bank",
            "type":"Services"
        }
    ],
    "sg:phone":"+1 410 828 4730",
    "sg:postcode":"21204",
    "sg:province":"MD",
    "wof:name":"Baltimore County Employees Cu",
    "wof:placetype":"venue"
},
  "geometry": {"coordinates":[-76.60530199999999,39.398475],"type":"Point"}
}