{
  "type": "Feature",
  "properties": {
    "addr:full":"4204 1/2 Roland Ave Baltimore MD 21210",
    "addr:housenumber":"4204 1 / 2",
    "addr:postcode":"21210",
    "addr:street":"Roland Ave",
    "iso:country":"US",
    "sg:address":"4204 1/2 Roland Ave",
    "sg:city":"Baltimore",
    "sg:classifiers":[
        {
            "category":"Real Estate",
            "subcategory":"Real Estate Services",
            "type":"Services"
        },
        {
            "category":"Real Estate",
            "subcategory":"Surveying",
            "type":"Services"
        },
        {
            "category":"Real Estate",
            "subcategory":"Real Estate Agent",
            "type":"Services"
        }
    ],
    "sg:phone":"+1 410 243 5900",
    "sg:postcode":"21210",
    "sg:province":"MD",
    "sg:tags":[
        "consultant",
        "industrial",
        "appraisers-commercial",
        "appraiser"
    ],
    "wof:name":"Campanella & Co",
    "wof:placetype":"venue"
},
  "geometry": {"coordinates":[-76.634293,39.340711],"type":"Point"}
}