{
  "type": "Feature",
  "properties": {
    "addr:full":"530 Main St Prince Frederick MD 20678",
    "addr:housenumber":"530",
    "addr:postcode":"20678",
    "addr:street":"Main St",
    "iso:country":"US",
    "sg:address":"530 Main St",
    "sg:city":"Prince Frederick",
    "sg:classifiers":[
        {
            "category":"Social Services",
            "type":"Services"
        }
    ],
    "sg:phone":"+1 410 535 1115",
    "sg:postcode":"20678",
    "sg:province":"MD",
    "sg:tags":[
        "organization",
        "welfare"
    ],
    "wof:name":"Big Brothers & Big Sisters",
    "wof:placetype":"venue"
},
  "geometry": {"coordinates":[-76.57975999999999,38.536604],"type":"Point"}
}