{
  "type": "Feature",
  "properties": {
    "addr:full":"8308 Carrbridge Cir Baltimore MD 21204",
    "addr:housenumber":"8308",
    "addr:postcode":"21204",
    "addr:street":"Carrbridge Cir",
    "iso:country":"US",
    "sg:address":"8308 Carrbridge Cir",
    "sg:city":"Baltimore",
    "sg:classifiers":[
        {
            "category":"Professional",
            "subcategory":"Employment Agencies",
            "type":"Services"
        }
    ],
    "sg:phone":"+1 410 339 7312",
    "sg:postcode":"21204",
    "sg:province":"MD",
    "sg:tags":[
        "consultant",
        "medical"
    ],
    "wof:name":"Raymond H Flores",
    "wof:placetype":"venue"
},
  "geometry": {"coordinates":[-76.654465,39.417218],"type":"Point"}
}