{
  "type": "Feature",
  "properties": {
    "iso:country":"US",
    "sg:address":"15747 Ambiance Dr",
    "sg:city":"Gaithersburg",
    "sg:classifiers":[
        {
            "category":"Professional",
            "type":"Services"
        }
    ],
    "sg:phone":"+1 301 208 8638",
    "sg:postcode":"20878",
    "sg:province":"MD",
    "wof:name":"Quikimpact",
    "wof:placetype":"venue"
},
  "geometry": {"coordinates":[-77.242909,39.113543],"type":"Point"}
}