{
  "type": "Feature",
  "properties": {
    "iso:country":"US",
    "sg:address":"2 Pennsylvania Ave",
    "sg:city":"Westminster",
    "sg:classifiers":[
        {
            "category":"Personal",
            "type":"Services"
        },
        {
            "category":"Autos & Motor Vehicles",
            "subcategory":"Auto Supplies",
            "type":"Retail Goods"
        },
        {
            "category":"Retail",
            "subcategory":"Auto Repair",
            "type":"Services"
        }
    ],
    "sg:phone":"+1 410 848 3644",
    "sg:postcode":"21157",
    "sg:province":"MD",
    "sg:tags":[
        "engine",
        "shop",
        "rebuilding",
        "transmission",
        "automobile",
        "machine",
        "towing"
    ],
    "sg:website":"http://www.dougsgarage.net",
    "wof:name":"Doug's Garage",
    "wof:placetype":"venue"
},
  "geometry": {"coordinates":[-76.998772,39.577969],"type":"Point"}
}