{
  "type": "Feature",
  "properties": {
    "iso:country":"US",
    "sg:address":"5057 Garrett Ave",
    "sg:city":"Beltsville",
    "sg:classifiers":[
        {
            "category":"Retail",
            "subcategory":"Laundry & Dry Cleaning",
            "type":"Services"
        }
    ],
    "sg:phone":"+1 301 937 8861",
    "sg:postcode":"20705",
    "sg:province":"MD",
    "wof:name":"Star Cleaners",
    "wof:placetype":"venue"
},
  "geometry": {"coordinates":[-76.90450300000001,39.041302],"type":"Point"}
}