{
  "type": "Feature",
  "properties": {
    "addr:full":"213 Cockeysville Rd Cockysvl Hnt Vly MD 21030",
    "addr:housenumber":"213",
    "addr:postcode":"21030",
    "addr:street":"Cockeysville Rd;Hnt Vly",
    "iso:country":"US",
    "sg:address":"213 Cockeysville Rd",
    "sg:city":"Cockysvl Hnt Vly",
    "sg:classifiers":[
        {
            "category":"Wholesale",
            "subcategory":"Electrical",
            "type":"Manufacturing & Wholesale Goods"
        }
    ],
    "sg:phone":"+1 410 229 0022",
    "sg:postcode":"21030",
    "sg:province":"MD",
    "sg:tags":[
        "alarm",
        "burglar",
        "system"
    ],
    "wof:name":"Digital Electronic Security",
    "wof:placetype":"venue"
},
  "geometry": {"coordinates":[-76.651549,39.480009],"type":"Point"}
}