{
  "type": "Feature",
  "properties": {
    "addr:full":"3705 Rockdale Rd Manchester MD 21102",
    "addr:housenumber":"3705",
    "addr:postcode":"21102",
    "addr:street":"Rockdale Rd",
    "iso:country":"US",
    "sg:address":"3705 Rockdale Rd",
    "sg:city":"Manchester",
    "sg:classifiers":[
        {
            "category":"Freight",
            "type":"Transportation"
        }
    ],
    "sg:phone":"+1 410 239 0038",
    "sg:postcode":"21102",
    "sg:province":"MD",
    "sg:tags":[
        "operator",
        "local",
        "trucking"
    ],
    "wof:name":"Donald Panuska Trucking",
    "wof:placetype":"venue"
},
  "geometry": {"coordinates":[-76.77479599999999,39.668599],"type":"Point"}
}