{
  "type": "Feature",
  "properties": {
    "addr:full":"236 Falcon Dr Pasadena MD 21122",
    "addr:housenumber":"236",
    "addr:postcode":"21122",
    "addr:street":"Falcon Dr",
    "iso:country":"US",
    "sg:address":"236 Falcon Dr",
    "sg:city":"Pasadena",
    "sg:classifiers":[
        {
            "category":"Professional",
            "subcategory":"Business Services",
            "type":"Services"
        }
    ],
    "sg:phone":"+1 410 437 8126",
    "sg:postcode":"21122",
    "sg:province":"MD",
    "wof:name":"Nancy Henry Interiors",
    "wof:placetype":"venue"
},
  "geometry": {"coordinates":[-76.46394600000001,39.101311],"type":"Point"}
}