{
  "type": "Feature",
  "properties": {
    "iso:country":"US",
    "sg:address":"29959 Matthewstown Rd",
    "sg:city":"Easton",
    "sg:classifiers":[
        {
            "category":"Building & Trades",
            "subcategory":"Landscaping Services",
            "type":"Services"
        }
    ],
    "sg:phone":"+1 410 822 9255",
    "sg:postcode":"21601",
    "sg:province":"MD",
    "sg:tags":[
        "landscape",
        "contractor"
    ],
    "wof:name":"George's Green Thumb Garden",
    "wof:placetype":"venue"
},
  "geometry": {"coordinates":[-76.0372,38.790675],"type":"Point"}
}