{
  "type": "Feature",
  "properties": {
    "addr:full":"702 Mount Alban Dr Annapolis MD 21409",
    "addr:housenumber":"702",
    "addr:postcode":"21409",
    "addr:street":"Mount Alban Dr",
    "iso:country":"US",
    "sg:address":"702 Mount Alban Dr",
    "sg:city":"Annapolis",
    "sg:classifiers":[
        {
            "category":"Professional",
            "subcategory":"Management & Consulting",
            "type":"Services"
        }
    ],
    "sg:phone":"+1 410 757 8949",
    "sg:postcode":"21409",
    "sg:province":"MD",
    "wof:name":"Jan L Settele",
    "wof:placetype":"venue"
},
  "geometry": {"coordinates":[-76.459985,39.041791],"type":"Point"}
}