{
  "type": "Feature",
  "properties": {
    "iso:country":"US",
    "sg:address":"9926 Walker House Rd",
    "sg:city":"Gaithersburg",
    "sg:classifiers":[
        {
            "category":"Professional",
            "subcategory":"Engineering",
            "type":"Services"
        }
    ],
    "sg:phone":"+1 301 330 8549",
    "sg:postcode":"20886",
    "sg:province":"MD",
    "sg:tags":[
        "engineer"
    ],
    "wof:name":"Mgv Consult Structural Engr",
    "wof:placetype":"venue"
},
  "geometry": {"coordinates":[-77.20572900000001,39.16239],"type":"Point"}
}