{
  "type": "Feature",
  "properties": {
    "addr:full":"10412 Crossing Creek Rd Potomac MD 20854",
    "addr:housenumber":"10412",
    "addr:postcode":"20854",
    "addr:street":"Crossing Creek Rd",
    "iso:country":"US",
    "sg:address":"10412 Crossing Creek Rd",
    "sg:city":"Potomac",
    "sg:classifiers":[
        {
            "category":"Professional",
            "type":"Services"
        }
    ],
    "sg:phone":"+1 301 299 8969",
    "sg:postcode":"20854",
    "sg:province":"MD",
    "sg:tags":[
        "doctor"
    ],
    "sg:website":"www.collegeacceptance.com",
    "wof:name":"Brody Michael Dr",
    "wof:placetype":"venue"
},
  "geometry": {"coordinates":[-77.17910000000001,39.026299],"type":"Point"}
}