{
  "type": "Feature",
  "properties": {
    "addr:full":"4109 Forestville Rd Forestville MD 20747",
    "addr:housenumber":"4109",
    "addr:postcode":"20747",
    "addr:street":"Forestville Rd",
    "iso:country":"US",
    "sg:address":"4109 Forestville Rd",
    "sg:city":"Forestville",
    "sg:classifiers":[
        {
            "category":"Building & Trades",
            "subcategory":"Electrical",
            "type":"Services"
        }
    ],
    "sg:phone":"+1 301 736 9752",
    "sg:postcode":"20747",
    "sg:province":"MD",
    "sg:tags":[
        "electric",
        "contractor"
    ],
    "wof:name":"Latchman Electrical Inc",
    "wof:placetype":"venue"
},
  "geometry": {"coordinates":[-76.876133,38.834294],"type":"Point"}
}