{
  "type": "Feature",
  "properties": {
    "addr:full":"120 W Church St Frederick MD 21701",
    "addr:housenumber":"120",
    "addr:postcode":"21701",
    "addr:street":"W Church St",
    "iso:country":"US",
    "sg:address":"120 W Church St",
    "sg:city":"Frederick",
    "sg:classifiers":[
        {
            "category":"Professional",
            "subcategory":"Accounting & Tax Preparation",
            "type":"Services"
        }
    ],
    "sg:phone":"+1 301 620 4226",
    "sg:postcode":"21701",
    "sg:province":"MD",
    "sg:tags":[
        "accountant"
    ],
    "wof:name":"John Koelbl CPA",
    "wof:placetype":"venue"
},
  "geometry": {"coordinates":[-77.414455,39.415529],"type":"Point"}
}