{
  "type": "Feature",
  "properties": {
    "addr:full":"705 S Philadelphia Blvd Aberdeen MD 21001",
    "addr:housenumber":"705",
    "addr:postcode":"21001",
    "addr:street":"S Philadelphia Blvd",
    "iso:country":"US",
    "sg:address":"705 S Philadelphia Blvd",
    "sg:city":"Aberdeen",
    "sg:classifiers":[
        {
            "category":"Bars & Pubs",
            "type":"Food & Drink"
        }
    ],
    "sg:phone":"+1 410 272 4404",
    "sg:postcode":"21001",
    "sg:province":"MD",
    "wof:name":"Towne Pub & Restaurant",
    "wof:placetype":"venue"
},
  "geometry": {"coordinates":[-76.17218,39.498702],"type":"Point"}
}