{
  "type": "Feature",
  "properties": {
    "addr:full":"5201 Raynor Ave Linthicum Heights MD 21090",
    "addr:housenumber":"5201",
    "addr:postcode":"21090",
    "addr:street":"Raynor Ave",
    "iso:country":"US",
    "sg:address":"5201 Raynor Ave",
    "sg:city":"Linthicum Heights",
    "sg:classifiers":[
        {
            "category":"Building & Trades",
            "subcategory":"Pest Control",
            "type":"Services"
        }
    ],
    "sg:phone":"+1 410 636 2400",
    "sg:postcode":"21090",
    "sg:province":"MD",
    "wof:name":"York Distributors",
    "wof:placetype":"venue"
},
  "geometry": {"coordinates":[-76.65930400000001,39.22318],"type":"Point"}
}