{
  "type": "Feature",
  "properties": {
    "iso:country":"US",
    "sg:address":"11123 Veirs Mill Rd",
    "sg:city":"Silver Spring",
    "sg:classifiers":[
        {
            "category":"Bars & Pubs",
            "type":"Food & Drink"
        }
    ],
    "sg:phone":"+1 301 933 5887",
    "sg:postcode":"20902",
    "sg:province":"MD",
    "wof:name":"Bilio Billard Bar",
    "wof:placetype":"venue"
},
  "geometry": {"coordinates":[-77.053623,39.039027],"type":"Point"}
}