{
  "type": "Feature",
  "properties": {
    "addr:full":"2705 Pennsylvania Ave Baltimore MD 21217",
    "addr:housenumber":"2705",
    "addr:postcode":"21217",
    "addr:street":"Pennsylvania Ave",
    "iso:country":"US",
    "sg:address":"2705 Pennsylvania Ave",
    "sg:city":"Baltimore",
    "sg:classifiers":[
        {
            "category":"Food & Beverages",
            "subcategory":"Liquor & Beverages",
            "type":"Retail Goods"
        }
    ],
    "sg:phone":"+1 410 669 5605",
    "sg:postcode":"21217",
    "sg:province":"MD",
    "sg:tags":[
        "beer",
        "spirit",
        "wine"
    ],
    "wof:name":"Charlie's Gents and Ladies Too",
    "wof:placetype":"venue"
},
  "geometry": {"coordinates":[-76.645599,39.312599],"type":"Point"}
}