{
  "type": "Feature",
  "properties": {
    "iso:country":"US",
    "sg:address":"7663 Arundel Mills Blvd",
    "sg:city":"Hanover",
    "sg:classifiers":[
        {
            "category":"Retail",
            "subcategory":"Veterinary Services",
            "type":"Services"
        }
    ],
    "sg:phone":"+1 410 799 3732",
    "sg:postcode":"21076",
    "sg:province":"MD",
    "sg:tags":[
        "clinic",
        "hospital",
        "veterinarian",
        "specialty"
    ],
    "sg:website":"http://www.banfield.net/ypoffer/?source=yp",
    "wof:name":"Banfield the Pet Hospital",
    "wof:placetype":"venue"
},
  "geometry": {"coordinates":[-76.72909900000001,39.152702],"type":"Point"}
}