{
  "type": "Feature",
  "properties": {
    "iso:country":"US",
    "sg:address":"555 N Mechanic St",
    "sg:city":"Cumberland",
    "sg:classifiers":[
        {
            "category":"Retail",
            "subcategory":"Auto Repair",
            "type":"Services"
        }
    ],
    "sg:phone":"+1 301 724 1212",
    "sg:postcode":"21502",
    "sg:province":"MD",
    "sg:tags":[
        "muffler",
        "exhaust",
        "system"
    ],
    "wof:name":"Bill's Muffler Shop",
    "wof:placetype":"venue"
},
  "geometry": {"coordinates":[-78.771782,39.657517],"type":"Point"}
}