{
  "type": "Feature",
  "properties": {
    "iso:country":"US",
    "sg:address":"119 S Main St",
    "sg:city":"Federalsburg",
    "sg:classifiers":[
        {
            "category":"Restaurant",
            "type":"Food & Drink"
        }
    ],
    "sg:phone":"+1 410 754 8806",
    "sg:postcode":"21632",
    "sg:province":"MD",
    "wof:name":"Great Wall",
    "wof:placetype":"venue"
},
  "geometry": {"coordinates":[-75.773671,38.69407],"type":"Point"}
}