{
  "type": "Feature",
  "properties": {
    "addr:full":"822 W 36th St Baltimore MD 21211",
    "addr:housenumber":"822",
    "addr:postcode":"21211",
    "addr:street":"W 36Th St",
    "iso:country":"US",
    "sg:address":"822 W 36th St",
    "sg:city":"Baltimore",
    "sg:classifiers":[
        {
            "category":"Professional",
            "subcategory":"Art Services",
            "type":"Services"
        }
    ],
    "sg:phone":"+1 410 889 3353",
    "sg:postcode":"21211",
    "sg:province":"MD",
    "sg:tags":[
        "photographer"
    ],
    "sg:website":"www.dreyphoto.com",
    "wof:name":"Susan Drey Photographer",
    "wof:placetype":"venue"
},
  "geometry": {"coordinates":[-76.629683,39.331324],"type":"Point"}
}