{
  "type": "Feature",
  "properties": {
    "iso:country":"US",
    "sg:address":"8535 Bradshaw Rd",
    "sg:city":"Kingsville",
    "sg:classifiers":[
        {
            "category":"Professional",
            "type":"Services"
        }
    ],
    "sg:phone":"+1 410 679 8789",
    "sg:postcode":"21087",
    "sg:province":"MD",
    "wof:name":"Lindas Quality Restoration",
    "wof:placetype":"venue"
},
  "geometry": {"coordinates":[-76.378473,39.421016],"type":"Point"}
}