{
  "type": "Feature",
  "properties": {
    "addr:full":"31 Highfields Dr Catonsville MD 21228",
    "addr:housenumber":"31",
    "addr:postcode":"21228",
    "addr:street":"Highfields Dr",
    "iso:country":"US",
    "sg:address":"31 Highfields Dr",
    "sg:city":"Catonsville",
    "sg:classifiers":[
        {
            "category":"Retail",
            "subcategory":"Repair Shop",
            "type":"Services"
        }
    ],
    "sg:phone":"+1 410 644 2453",
    "sg:postcode":"21228",
    "sg:province":"MD",
    "sg:tags":[
        "bicycle"
    ],
    "wof:name":"Baltimore Bicycle Svc",
    "wof:placetype":"venue"
},
  "geometry": {"coordinates":[-76.71861,39.251673],"type":"Point"}
}