{
  "type": "Feature",
  "properties": {
    "addr:full":"3441 Clifton Ave Baltimore MD 21216",
    "addr:housenumber":"3441",
    "addr:postcode":"21216",
    "addr:street":"Clifton Ave",
    "iso:country":"US",
    "sg:address":"3441 Clifton Ave",
    "sg:city":"Baltimore",
    "sg:classifiers":[
        {
            "category":"Banks & Credit Unions",
            "subcategory":"Financial Services",
            "type":"Services"
        }
    ],
    "sg:phone":"+1 410 945 2243",
    "sg:postcode":"21216",
    "sg:province":"MD",
    "sg:tags":[
        "cashing",
        "loan",
        "payday",
        "alternative",
        "check"
    ],
    "sg:website":"http://www.acecashexpress.com",
    "wof:name":"ACE Cash Express",
    "wof:placetype":"venue"
},
  "geometry": {"coordinates":[-76.674561,39.31097],"type":"Point"}
}