{
  "type": "Feature",
  "properties": {
    "addr:full":"9709 York Rd Cockeysville MD 21030",
    "addr:housenumber":"9709",
    "addr:postcode":"21030",
    "addr:street":"York Rd",
    "iso:country":"US",
    "sg:address":"9709 York Rd",
    "sg:city":"Cockeysville",
    "sg:classifiers":[
        {
            "category":"Home & Garden",
            "subcategory":"Carpets & Floor Coverings",
            "type":"Retail Goods"
        }
    ],
    "sg:phone":"+1 410 666 5507",
    "sg:postcode":"21030",
    "sg:province":"MD",
    "sg:tags":[
        "mattress"
    ],
    "sg:website":"www.mattressdiscounters.com",
    "wof:name":"Mattress Discounters",
    "wof:placetype":"venue"
},
  "geometry": {"coordinates":[-76.633301,39.456799],"type":"Point"}
}