{
  "type": "Feature",
  "properties": {
    "iso:country":"US",
    "sg:address":"18305 Leaman Farm Rd",
    "sg:city":"Germantown",
    "sg:classifiers":[
        {
            "category":"Restaurant",
            "type":"Food & Drink"
        }
    ],
    "sg:phone":"+1 301 540 6500",
    "sg:postcode":"20874",
    "sg:province":"MD",
    "wof:name":"King China Buffet",
    "wof:placetype":"venue"
},
  "geometry": {"coordinates":[-77.27901199999999,39.158437],"type":"Point"}
}