{
  "type": "Feature",
  "properties": {
    "addr:full":"505 Springdale St Cumberland MD 21502",
    "addr:housenumber":"505",
    "addr:postcode":"21502",
    "addr:street":"Springdale St",
    "iso:country":"US",
    "sg:address":"505 Springdale St",
    "sg:city":"Cumberland",
    "sg:classifiers":[
        {
            "category":"Restaurant",
            "type":"Food & Drink"
        }
    ],
    "sg:phone":"+1 301 777 7773",
    "sg:postcode":"21502",
    "sg:province":"MD",
    "wof:name":"China Express",
    "wof:placetype":"venue"
},
  "geometry": {"coordinates":[-78.7653,39.634097],"type":"Point"}
}