{
  "type": "Feature",
  "properties": {
    "addr:full":"7500 Old Georgetown Rd Bethesda MD 20814",
    "addr:housenumber":"7500",
    "addr:postcode":"20814",
    "addr:street":"Old Georgetown Rd",
    "iso:country":"US",
    "sg:address":"7500 Old Georgetown Rd",
    "sg:city":"Bethesda",
    "sg:classifiers":[
        {
            "category":"Banks & Credit Unions",
            "subcategory":"Investment Brokerage",
            "type":"Services"
        }
    ],
    "sg:phone":"+1 301 961 1993",
    "sg:postcode":"20814",
    "sg:province":"MD",
    "sg:tags":[
        "advisory",
        "financial"
    ],
    "wof:name":"Scott Financial Inc Beth",
    "wof:placetype":"venue"
},
  "geometry": {"coordinates":[-77.095664,38.98561],"type":"Point"}
}