{
  "type": "Feature",
  "properties": {
    "addr:full":"9006 Yellow Brick Rd Baltimore MD 21237",
    "addr:housenumber":"9006",
    "addr:postcode":"21237",
    "addr:street":"Yellow Brick Rd",
    "iso:country":"US",
    "sg:address":"9006 Yellow Brick Rd",
    "sg:city":"Baltimore",
    "sg:classifiers":[
        {
            "category":"Health Services",
            "subcategory":"Clinic",
            "type":"Services"
        }
    ],
    "sg:phone":"+1 301 596 2700",
    "sg:postcode":"21237",
    "sg:province":"MD",
    "sg:tags":[
        "home",
        "care"
    ],
    "wof:name":"Severn Healthcare Inc",
    "wof:placetype":"venue"
},
  "geometry": {"coordinates":[-76.472881,39.344111],"type":"Point"}
}