{
  "type": "Feature",
  "properties": {
    "addr:full":"19200 Chennault Way Gaithersburg MD 20879",
    "addr:housenumber":"19200",
    "addr:postcode":"20879",
    "addr:street":"Chennault Way",
    "iso:country":"US",
    "sg:address":"19200 Chennault Way",
    "sg:city":"Gaithersburg",
    "sg:classifiers":[
        {
            "category":"Wholesale",
            "subcategory":"Hardware",
            "type":"Manufacturing & Wholesale Goods"
        }
    ],
    "sg:phone":"+1 301 417 9333",
    "sg:postcode":"20879",
    "sg:province":"MD",
    "sg:tags":[
        "water",
        "cooler",
        "fountain",
        "filter"
    ],
    "sg:website":"www.drinkmorewater.com",
    "wof:name":"Drink More Water Store",
    "wof:placetype":"venue"
},
  "geometry": {"coordinates":[-77.157096,39.171016],"type":"Point"}
}