{
  "type": "Feature",
  "properties": {
    "addr:full":"5 Railroad Ave East New Market MD 21631",
    "addr:housenumber":"5",
    "addr:postcode":"21631",
    "addr:street":"Railroad Ave East",
    "iso:country":"US",
    "sg:address":"5 Railroad Ave",
    "sg:city":"East New Market",
    "sg:classifiers":[
        {
            "category":"Retail",
            "subcategory":"Repair Shop",
            "type":"Services"
        }
    ],
    "sg:phone":"+1 410 943 3600",
    "sg:postcode":"21631",
    "sg:province":"MD",
    "sg:tags":[
        "taxidermist"
    ],
    "wof:name":"Bucks Unlimited Taxidermy",
    "wof:placetype":"venue"
},
  "geometry": {"coordinates":[-75.927026,38.599186],"type":"Point"}
}