{
  "type": "Feature",
  "properties": {
    "iso:country":"US",
    "sg:address":"25228 Ocean Gateway",
    "sg:city":"Mardela Springs",
    "sg:classifiers":[
        {
            "category":"Food & Beverages",
            "subcategory":"Fruits & Vegetables",
            "type":"Retail Goods"
        }
    ],
    "sg:phone":"+1 410 749 4486",
    "sg:postcode":"21837",
    "sg:province":"MD",
    "sg:tags":[
        "produce"
    ],
    "wof:name":"Hill Top Market",
    "wof:placetype":"venue"
},
  "geometry": {"coordinates":[-75.741744,38.460119],"type":"Point"}
}