{
  "type": "Feature",
  "properties": {
    "iso:country":"US",
    "sg:address":"7717 Philadelphia Rd",
    "sg:city":"Baltimore",
    "sg:classifiers":[
        {
            "category":"Professional",
            "subcategory":"Lawyer & Legal Services",
            "type":"Services"
        }
    ],
    "sg:phone":"+1 410 866 7111",
    "sg:postcode":"21237",
    "sg:province":"MD",
    "sg:tags":[
        "litigation",
        "injury",
        "family",
        "personal",
        "divorce",
        "law"
    ],
    "wof:name":"David B. Love Esq.",
    "wof:placetype":"venue"
},
  "geometry": {"coordinates":[-76.520428,39.316504],"type":"Point"}
}