{
  "type": "Feature",
  "properties": {
    "iso:country":"US",
    "sg:address":"6797 Dorsey Rd",
    "sg:city":"Elkridge",
    "sg:classifiers":[
        {
            "category":"Professional",
            "subcategory":"Management & Consulting",
            "type":"Services"
        }
    ],
    "sg:phone":"+1 410 379 2693",
    "sg:postcode":"21075",
    "sg:province":"MD",
    "sg:tags":[
        "consultant"
    ],
    "wof:name":"Beco Management",
    "wof:placetype":"venue"
},
  "geometry": {"coordinates":[-76.755375,39.184],"type":"Point"}
}