{
  "type": "Feature",
  "properties": {
    "addr:full":"14017 Briarwood Dr Laurel MD 20708",
    "addr:housenumber":"14017",
    "addr:postcode":"20708",
    "addr:street":"Briarwood Dr",
    "iso:country":"US",
    "sg:address":"14017 Briarwood Dr",
    "sg:city":"Laurel",
    "sg:classifiers":[
        {
            "category":"Real Estate",
            "subcategory":"Real Estate Services",
            "type":"Services"
        },
        {
            "category":"Real Estate",
            "subcategory":"Real Estate Agent",
            "type":"Services"
        }
    ],
    "sg:phone":"+1 301 776 3145",
    "sg:postcode":"20708",
    "sg:province":"MD",
    "sg:tags":[
        "buyer",
        "broker"
    ],
    "wof:name":"Mt Vernon Realty",
    "wof:placetype":"venue"
},
  "geometry": {"coordinates":[-76.846777,39.080231],"type":"Point"}
}