{
  "type": "Feature",
  "properties": {
    "iso:country":"US",
    "sg:address":"3605 Evergreen Ave",
    "sg:city":"Baltimore",
    "sg:classifiers":[
        {
            "category":"Education",
            "subcategory":"Kindergarten",
            "type":"Public Place"
        }
    ],
    "sg:phone":"+1 410 426 1836",
    "sg:postcode":"21206",
    "sg:province":"MD",
    "sg:tags":[
        "school",
        "driving"
    ],
    "wof:name":"A-3A Method Driving",
    "wof:placetype":"venue"
},
  "geometry": {"coordinates":[-76.55259700000001,39.348801],"type":"Point"}
}