{
  "type": "Feature",
  "properties": {
    "iso:country":"US",
    "sg:address":"3730 Commerce Dr",
    "sg:city":"Baltimore",
    "sg:classifiers":[
        {
            "category":"Manufacturing",
            "subcategory":"Printing",
            "type":"Manufacturing & Wholesale Goods"
        }
    ],
    "sg:phone":"+1 410 644 3081",
    "sg:postcode":"21227",
    "sg:province":"MD",
    "sg:tags":[
        "publisher"
    ],
    "wof:name":"Harmon Auto",
    "wof:placetype":"venue"
},
  "geometry": {"coordinates":[-76.672461,39.248842],"type":"Point"}
}