{
  "type": "Feature",
  "properties": {
    "addr:full":"5406 Queens Chapel Rd Hyattsville MD 20782",
    "addr:housenumber":"5406",
    "addr:postcode":"20782",
    "addr:street":"Queens Chapel Rd",
    "iso:country":"US",
    "sg:address":"5406 Queens Chapel Rd",
    "sg:city":"Hyattsville",
    "sg:classifiers":[
        {
            "category":"Professional",
            "subcategory":"Accounting & Tax Preparation",
            "type":"Services"
        }
    ],
    "sg:phone":"+1 301 559 0124",
    "sg:postcode":"20782",
    "sg:province":"MD",
    "sg:tags":[
        "return",
        "filing"
    ],
    "wof:name":"Ace Tax Svc",
    "wof:placetype":"venue"
},
  "geometry": {"coordinates":[-76.961456,38.956407],"type":"Point"}
}