{
  "type": "Feature",
  "properties": {
    "iso:country":"US",
    "sg:address":"1132 Gorsuch Ave",
    "sg:city":"Baltimore",
    "sg:classifiers":[
        {
            "category":"Shopping",
            "subcategory":"Bicycles & Sporting Goods",
            "type":"Retail Goods"
        }
    ],
    "sg:phone":"+1 410 467 7873",
    "sg:postcode":"21218",
    "sg:province":"MD",
    "wof:name":"Fitness Equipment Store/46427",
    "wof:placetype":"venue"
},
  "geometry": {"coordinates":[-76.601072,39.325275],"type":"Point"}
}