{
  "type": "Feature",
  "properties": {
    "iso:country":"US",
    "sg:address":"135 W Dares Beach Rd",
    "sg:city":"Prince Frederick",
    "sg:classifiers":[
        {
            "category":"Professional",
            "subcategory":"Lawyer & Legal Services",
            "type":"Services"
        }
    ],
    "sg:phone":"+1 410 535 9200",
    "sg:postcode":"20678",
    "sg:province":"MD",
    "sg:tags":[
        "attorney"
    ],
    "wof:name":"Richard D Lloyd",
    "wof:placetype":"venue"
},
  "geometry": {"coordinates":[-76.591842,38.54592],"type":"Point"}
}