{
  "type": "Feature",
  "properties": {
    "iso:country":"US",
    "sg:address":"914 Bay Ridge Ave",
    "sg:city":"Annapolis",
    "sg:classifiers":[
        {
            "category":"Government",
            "subcategory":"Fire Station",
            "type":"Public Place"
        }
    ],
    "sg:phone":"+1 410 263 6133",
    "sg:postcode":"21403",
    "sg:province":"MD",
    "sg:tags":[
        "department"
    ],
    "wof:name":"Eastport Volunteer Fire Dept",
    "wof:placetype":"venue"
},
  "geometry": {"coordinates":[-76.488828,38.966717],"type":"Point"}
}