{
  "type": "Feature",
  "properties": {
    "addr:full":"14690 Rothgeb Dr Rockville MD 20850",
    "addr:housenumber":"14690",
    "addr:postcode":"20850",
    "addr:street":"Rothgeb Dr",
    "iso:country":"US",
    "sg:address":"14690 Rothgeb Dr",
    "sg:city":"Rockville",
    "sg:classifiers":[
        {
            "category":"Autos & Motor Vehicles",
            "subcategory":"Motorcycle Sales",
            "type":"Retail Goods"
        }
    ],
    "sg:phone":"+1 301 980 6380",
    "sg:postcode":"20850",
    "sg:province":"MD",
    "wof:name":"Rkb Motorsports",
    "wof:placetype":"venue"
},
  "geometry": {"coordinates":[-77.13355199999999,39.097508],"type":"Point"}
}