{
  "type": "Feature",
  "properties": {
    "addr:full":"1675 Armistice Way Marriottsville MD 21104",
    "addr:housenumber":"1675",
    "addr:postcode":"21104",
    "addr:street":"Armistice Way",
    "iso:country":"US",
    "sg:address":"1675 Armistice Way",
    "sg:city":"Marriottsville",
    "sg:classifiers":[
        {
            "category":"Shopping",
            "subcategory":"Clothing, Apparel, & Fashions",
            "type":"Retail Goods"
        }
    ],
    "sg:phone":"+1 410 795 0297",
    "sg:postcode":"21104",
    "sg:province":"MD",
    "sg:tags":[
        "uniforms-accessories",
        "uniform"
    ],
    "wof:name":"Uniform A Team",
    "wof:placetype":"venue"
},
  "geometry": {"coordinates":[-76.935851,39.37472],"type":"Point"}
}