{
  "type": "Feature",
  "properties": {
    "iso:country":"US",
    "sg:address":"8504 Ardwick Ardmore Rd",
    "sg:city":"Landover",
    "sg:classifiers":[
        {
            "category":"Utilities",
            "subcategory":"Mobile Phone",
            "type":"Services"
        }
    ],
    "sg:phone":"+1 301 773 1617",
    "sg:postcode":"20785",
    "sg:province":"MD",
    "sg:tags":[
        "equipment",
        "paging",
        "signaling",
        "system"
    ],
    "wof:name":"Front Page Wireless",
    "wof:placetype":"venue"
},
  "geometry": {"coordinates":[-76.861378,38.939955],"type":"Point"}
}