{
  "type": "Feature",
  "properties": {
    "addr:full":"825 Dulaney Valley Rd Towson MD 21204",
    "addr:housenumber":"825",
    "addr:postcode":"21204",
    "addr:street":"Dulaney Valley Rd",
    "iso:country":"US",
    "sg:address":"825 Dulaney Valley Rd",
    "sg:city":"Towson",
    "sg:classifiers":[
        {
            "category":"Restaurant",
            "type":"Food & Drink"
        }
    ],
    "sg:phone":"+1 410 828 4556",
    "sg:postcode":"21204",
    "sg:province":"MD",
    "sg:website":"www.myfridays.com",
    "wof:name":"TGI Friday's",
    "wof:placetype":"venue"
},
  "geometry": {"coordinates":[-76.60154199999999,39.403782],"type":"Point"}
}