{
  "type": "Feature",
  "properties": {
    "addr:full":"8504 Ardwick Ardmore Rd Ste A Hyattsville MD 20785",
    "addr:housenumber":"8504",
    "addr:postcode":"20785",
    "addr:street":"Ardwick Ardmore Rd Ste A",
    "iso:country":"US",
    "sg:address":"8504 Ardwick Ardmore Rd Ste A",
    "sg:city":"Hyattsville",
    "sg:classifiers":[
        {
            "category":"Retail",
            "subcategory":"Auto Repair",
            "type":"Services"
        }
    ],
    "sg:phone":"+1 301 773 3533",
    "sg:postcode":"20785",
    "sg:province":"MD",
    "sg:website":"www.collisionautocrafters.com",
    "wof:name":"Collision Auto Crafters",
    "wof:placetype":"venue"
},
  "geometry": {"coordinates":[-76.861482,38.94006],"type":"Point"}
}