{
  "type": "Feature",
  "properties": {
    "iso:country":"US",
    "sg:address":"520 Guilford Ave",
    "sg:city":"Hagerstown",
    "sg:classifiers":[
        {
            "category":"Building & Trades",
            "subcategory":"Construction",
            "type":"Services"
        }
    ],
    "sg:phone":"+1 301 790 0433",
    "sg:postcode":"21740",
    "sg:province":"MD",
    "sg:tags":[
        "painter"
    ],
    "wof:name":"James G Winters Painting",
    "wof:placetype":"venue"
},
  "geometry": {"coordinates":[-77.727926,39.633972],"type":"Point"}
}