{
  "type": "Feature",
  "properties": {
    "addr:full":"2601 Housley Rd Annapolis MD 21401",
    "addr:housenumber":"2601",
    "addr:postcode":"21401",
    "addr:street":"Housley Rd",
    "iso:country":"US",
    "sg:address":"2601 Housley Rd",
    "sg:city":"Annapolis",
    "sg:classifiers":[
        {
            "category":"Retail",
            "subcategory":"Veterinary Services",
            "type":"Services"
        }
    ],
    "sg:phone":"+1 410 266 7170",
    "sg:postcode":"21401",
    "sg:province":"MD",
    "sg:tags":[
        "veterinarian"
    ],
    "wof:name":"Banfield The Pet Hospital",
    "wof:placetype":"venue"
},
  "geometry": {"coordinates":[-76.55209600000001,38.990541],"type":"Point"}
}