{
  "type": "Feature",
  "properties": {
    "iso:country":"US",
    "sg:address":"39820 Persimmon Creek Rd",
    "sg:city":"Mechanicsville",
    "sg:classifiers":[
        {
            "category":"Retail",
            "subcategory":"Repair Shop",
            "type":"Services"
        }
    ],
    "sg:phone":"+1 301 884 5208",
    "sg:postcode":"20659",
    "sg:province":"MD",
    "wof:name":"Durst Outdoors Taxidermy",
    "wof:placetype":"venue"
},
  "geometry": {"coordinates":[-76.70912800000001,38.441199],"type":"Point"}
}