{
  "type": "Feature",
  "properties": {
    "addr:full":"3993 Forest Valley Rd Baltimore MD 21234",
    "addr:housenumber":"3993",
    "addr:postcode":"21234",
    "addr:street":"Forest Valley Rd",
    "iso:country":"US",
    "sg:address":"3993 Forest Valley Rd",
    "sg:city":"Baltimore",
    "sg:classifiers":[
        {
            "category":"Shopping",
            "subcategory":"Hobbies, Toys, & Games",
            "type":"Retail Goods"
        }
    ],
    "sg:phone":"+1 410 668 1516",
    "sg:postcode":"21234",
    "sg:province":"MD",
    "wof:name":"Featherwings Unique Bird Toys",
    "wof:placetype":"venue"
},
  "geometry": {"coordinates":[-76.546329,39.407108],"type":"Point"}
}