{
  "type": "Feature",
  "properties": {
    "iso:country":"US",
    "sg:address":"5012 New Forge Rd",
    "sg:city":"Perry Hall",
    "sg:classifiers":[
        {
            "category":"Freight",
            "type":"Transportation"
        }
    ],
    "sg:phone":"+1 410 256 7568",
    "sg:postcode":"21128",
    "sg:province":"MD",
    "wof:name":"Way Truck & Auto Trnsprtn Co",
    "wof:placetype":"venue"
},
  "geometry": {"coordinates":[-76.42818,39.412558],"type":"Point"}
}