{
  "type": "Feature",
  "properties": {
    "iso:country":"US",
    "sg:address":"1730 Good Hope Dr",
    "sg:city":"Crofton",
    "sg:classifiers":[
        {
            "category":"Social Services",
            "subcategory":"Child Care",
            "type":"Services"
        }
    ],
    "sg:phone":"+1 301 858 1326",
    "sg:postcode":"21114",
    "sg:province":"MD",
    "sg:tags":[
        "day"
    ],
    "wof:name":"Custom Memorial Care",
    "wof:placetype":"venue"
},
  "geometry": {"coordinates":[-76.698623,38.994501],"type":"Point"}
}