{
  "type": "Feature",
  "properties": {
    "addr:full":"1634 Old Westminster Pike Westminster MD 21157",
    "addr:housenumber":"1634",
    "addr:postcode":"21157",
    "addr:street":"Old Westminster Pike",
    "iso:country":"US",
    "sg:address":"1634 Old Westminster Pike",
    "sg:city":"Westminster",
    "sg:classifiers":[
        {
            "category":"Building & Trades",
            "subcategory":"Construction",
            "type":"Services"
        }
    ],
    "sg:phone":"+1 410 751 7788",
    "sg:postcode":"21157",
    "sg:province":"MD",
    "sg:tags":[
        "caulking",
        "contractor"
    ],
    "wof:name":"Robey, Inc",
    "wof:placetype":"venue"
},
  "geometry": {"coordinates":[-76.936807,39.542518],"type":"Point"}
}