{
  "type": "Feature",
  "properties": {
    "iso:country":"US",
    "sg:address":"4305 Strauss Ave",
    "sg:city":"Indian Head",
    "sg:classifiers":[
        {
            "category":"Building & Trades",
            "subcategory":"Cleaning & Sanitation",
            "type":"Services"
        }
    ],
    "sg:phone":"+1 301 753 8311",
    "sg:postcode":"20640",
    "sg:province":"MD",
    "sg:tags":[
        "janitorial"
    ],
    "wof:name":"BJs & Jjs Prof Clg Svc",
    "wof:placetype":"venue"
},
  "geometry": {"coordinates":[-77.15824499999999,38.599664],"type":"Point"}
}