{
  "type": "Feature",
  "properties": {
    "iso:country":"US",
    "sg:address":"317 S North Point Rd",
    "sg:city":"Baltimore",
    "sg:classifiers":[
        {
            "category":"Wholesale",
            "subcategory":"Auto Parts",
            "type":"Manufacturing & Wholesale Goods"
        }
    ],
    "sg:phone":"+1 410 288 2288",
    "sg:postcode":"21224",
    "sg:province":"MD",
    "sg:tags":[
        "automobile",
        "wrecking"
    ],
    "wof:name":"City Line Truck & Auto Salvage",
    "wof:placetype":"venue"
},
  "geometry": {"coordinates":[-76.521579,39.293648],"type":"Point"}
}