{
  "type": "Feature",
  "properties": {
    "addr:full":"855 Deep Creek Dr Mc Henry MD 21541",
    "addr:housenumber":"855",
    "addr:postcode":"21541",
    "addr:street":"Deep Creek Dr",
    "iso:country":"US",
    "sg:address":"855 Deep Creek Dr",
    "sg:city":"Mc Henry",
    "sg:classifiers":[
        {
            "category":"Travel",
            "subcategory":"Hotels & Motels",
            "type":"Entertainment"
        }
    ],
    "sg:phone":"+1 301 387 5115",
    "sg:postcode":"21541",
    "sg:province":"MD",
    "wof:name":"Pine Oaks Lodge",
    "wof:placetype":"venue"
},
  "geometry": {"coordinates":[-79.35024,39.540757],"type":"Point"}
}