{
  "type": "Feature",
  "properties": {
    "addr:full":"1517 Reisterstown Rd Pikesville MD 21208",
    "addr:housenumber":"1517",
    "addr:postcode":"21208",
    "addr:street":"Reisterstown Rd",
    "iso:country":"US",
    "sg:address":"1517 Reisterstown Rd",
    "sg:city":"Pikesville",
    "sg:classifiers":[
        {
            "category":"Health Services",
            "subcategory":"Doctor",
            "type":"Services"
        }
    ],
    "sg:phone":"+1 410 653 1600",
    "sg:postcode":"21208",
    "sg:province":"MD",
    "sg:tags":[
        "physician",
        "surgeon"
    ],
    "wof:name":"Drs Brenner & Rubin",
    "wof:placetype":"venue"
},
  "geometry": {"coordinates":[-76.72618,39.377952],"type":"Point"}
}