{
  "type": "Feature",
  "properties": {
    "iso:country":"US",
    "sg:address":"400 W Lexington St",
    "sg:city":"Baltimore",
    "sg:classifiers":[
        {
            "category":"Fast Food",
            "type":"Food & Drink"
        },
        {
            "category":"Deli",
            "type":"Food & Drink"
        },
        {
            "category":"Restaurant",
            "type":"Food & Drink"
        }
    ],
    "sg:phone":"+1 410 752 1372",
    "sg:postcode":"21201",
    "sg:province":"MD",
    "sg:tags":[
        "delicatessen",
        "take"
    ],
    "wof:name":"Sheppards Deli",
    "wof:placetype":"venue"
},
  "geometry": {"coordinates":[-76.622383,39.291431],"type":"Point"}
}