{
  "type": "Feature",
  "properties": {
    "addr:full":"1924 Greenspring Dr Timonium MD 21093",
    "addr:housenumber":"1924",
    "addr:postcode":"21093",
    "addr:street":"Greenspring Dr",
    "iso:country":"US",
    "sg:address":"1924 Greenspring Dr",
    "sg:city":"Timonium",
    "sg:classifiers":[
        {
            "category":"Manufacturing",
            "subcategory":"Printing",
            "type":"Manufacturing & Wholesale Goods"
        }
    ],
    "sg:phone":"+1 410 252 7781",
    "sg:postcode":"21093",
    "sg:province":"MD",
    "sg:tags":[
        "commercial"
    ],
    "sg:website":"www.wilmerprinting.com",
    "wof:name":"Wilmer Printing Co",
    "wof:placetype":"venue"
},
  "geometry": {"coordinates":[-76.62938,39.431861],"type":"Point"}
}