{
  "type": "Feature",
  "properties": {
    "iso:country":"US",
    "sg:address":"7509 Mountain Approach Rd",
    "sg:city":"Adamstown",
    "sg:classifiers":[
        {
            "category":"Communications",
            "type":"Services"
        }
    ],
    "sg:phone":"+1 240 674 8511",
    "sg:postcode":"21710",
    "sg:province":"MD",
    "sg:tags":[
        "consultant",
        "engineer"
    ],
    "wof:name":"Machadocom",
    "wof:placetype":"venue"
},
  "geometry": {"coordinates":[-77.405208,39.302389],"type":"Point"}
}