{
  "type": "Feature",
  "properties": {
    "addr:full":"2033 E Joppa Rd Ste A Parkville MD 21234",
    "addr:housenumber":"2033 e",
    "addr:postcode":"21234",
    "addr:street":"Joppa Rd Ste A",
    "iso:country":"US",
    "sg:address":"2033 E Joppa Rd Ste A",
    "sg:city":"Parkville",
    "sg:phone":"+1 410 882 3155",
    "sg:postcode":"21234",
    "sg:province":"MD",
    "sg:website":"http://www.oldcountrybuffet.com",
    "wof:name":"Old Country Buffet",
    "wof:placetype":"venue"
},
  "geometry": {"coordinates":[-76.542468,39.398569],"type":"Point"}
}