{
  "type": "Feature",
  "properties": {
    "iso:country":"US",
    "sg:address":"9471 Black Velvet Ln",
    "sg:city":"Columbia",
    "sg:classifiers":[
        {
            "category":"Wholesale",
            "subcategory":"Groceries",
            "type":"Manufacturing & Wholesale Goods"
        }
    ],
    "sg:phone":"+1 410 312 7204",
    "sg:postcode":"21046",
    "sg:province":"MD",
    "sg:tags":[
        "food",
        "direct",
        "sales"
    ],
    "wof:name":"US Foodservice Inc",
    "wof:placetype":"venue"
},
  "geometry": {"coordinates":[-76.836431,39.158133],"type":"Point"}
}