{
  "type": "Feature",
  "properties": {
    "addr:full":"12205 Blaketon St Upper Marlboro MD 20774",
    "addr:postcode":"12205;20774",
    "addr:street":"Blaketon St",
    "iso:country":"US",
    "sg:address":"12205 Blaketon St",
    "sg:city":"Upper Marlboro",
    "sg:classifiers":[
        {
            "category":"Organizations",
            "subcategory":"Religious Organization",
            "type":"Services"
        }
    ],
    "sg:phone":"+1 301 249 7500",
    "sg:postcode":"20774",
    "sg:province":"MD",
    "sg:tags":[
        "church"
    ],
    "wof:name":"Hedges & Highways Holiness Chr",
    "wof:placetype":"venue"
},
  "geometry": {"coordinates":[-76.794066,38.895131],"type":"Point"}
}