{
  "type": "Feature",
  "properties": {
    "addr:full":"507 S Camp Meade Rd Linthicum Heights MD 21090",
    "addr:housenumber":"507",
    "addr:postcode":"21090",
    "addr:street":"S Camp Meade Rd",
    "iso:country":"US",
    "sg:address":"507 S Camp Meade Rd",
    "sg:city":"Linthicum Heights",
    "sg:classifiers":[
        {
            "category":"Shopping",
            "subcategory":"Bicycles & Sporting Goods",
            "type":"Retail Goods"
        }
    ],
    "sg:phone":"+1 410 691 2453",
    "sg:postcode":"21090",
    "sg:province":"MD",
    "sg:tags":[
        "bike"
    ],
    "wof:name":"Bike Doctor of Linthicum",
    "wof:placetype":"venue"
},
  "geometry": {"coordinates":[-76.655952,39.199554],"type":"Point"}
}