{
  "type": "Feature",
  "properties": {
    "iso:country":"US",
    "sg:address":"5304 Kenilworth Ave",
    "sg:city":"Riverdale",
    "sg:classifiers":[
        {
            "category":"Personal",
            "subcategory":"Beauty Salon",
            "type":"Services"
        }
    ],
    "sg:phone":"+1 301 209 7072",
    "sg:postcode":"20737",
    "sg:province":"MD",
    "wof:name":"Victoria's Unisex",
    "wof:placetype":"venue"
},
  "geometry": {"coordinates":[-76.923167,38.955278],"type":"Point"}
}