{
  "type": "Feature",
  "properties": {
    "iso:country":"US",
    "sg:address":"6360 S Hanover Rd Ste E",
    "sg:city":"Elkridge",
    "sg:classifiers":[
        {
            "category":"Building & Trades",
            "subcategory":"Construction",
            "type":"Services"
        }
    ],
    "sg:phone":"+1 410 796 7025",
    "sg:postcode":"21075",
    "sg:province":"MD",
    "sg:tags":[
        "contractor"
    ],
    "wof:name":"Icon Construction Services",
    "wof:placetype":"venue"
},
  "geometry": {"coordinates":[-76.731572,39.195899],"type":"Point"}
}