{
  "type": "Feature",
  "properties": {
    "iso:country":"US",
    "sg:address":"181 E Main St",
    "sg:city":"Westminster",
    "sg:classifiers":[
        {
            "category":"Professional",
            "subcategory":"Art Services",
            "type":"Services"
        }
    ],
    "sg:phone":"+1 410 840 3365",
    "sg:postcode":"21157",
    "sg:province":"MD",
    "sg:tags":[
        "commercial",
        "design"
    ],
    "wof:name":"Stanton Design",
    "wof:placetype":"venue"
},
  "geometry": {"coordinates":[-76.99115500000001,39.570641],"type":"Point"}
}