{
  "type": "Feature",
  "properties": {
    "addr:full":"13208 Executive Park Ter Germantown MD 20874",
    "addr:housenumber":"13208",
    "addr:postcode":"20874",
    "addr:street":"Executive Park Ter",
    "iso:country":"US",
    "sg:address":"13208 Executive Park Ter",
    "sg:city":"Germantown",
    "sg:classifiers":[
        {
            "category":"Insurance",
            "subcategory":"Insurance Agent",
            "type":"Services"
        },
        {
            "category":"Insurance",
            "subcategory":"Hazard Insurance",
            "type":"Services"
        }
    ],
    "sg:phone":"+1 301 428 0282",
    "sg:postcode":"20874",
    "sg:province":"MD",
    "sg:tags":[
        "auto",
        "recreational",
        "motorcycle",
        "vehicle",
        "marine",
        "boat"
    ],
    "sg:website":"http://www.schaeferinsurance.com",
    "wof:name":"Schaefer Insurance Services",
    "wof:placetype":"venue"
},
  "geometry": {"coordinates":[-77.27334399999999,39.179681],"type":"Point"}
}