{
  "type": "Feature",
  "properties": {
    "iso:country":"US",
    "sg:address":"4499 Leonardtown Rd",
    "sg:city":"Waldorf",
    "sg:classifiers":[
        {
            "category":"Professional",
            "type":"Services"
        }
    ],
    "sg:phone":"+1 301 843 6680",
    "sg:postcode":"20601",
    "sg:province":"MD",
    "sg:tags":[
        "establishment"
    ],
    "wof:name":"Happy Kids Day Care-Worship",
    "wof:placetype":"venue"
},
  "geometry": {"coordinates":[-76.87177,38.599353],"type":"Point"}
}