{
  "type": "Feature",
  "properties": {
    "addr:full":"10901 Indian Head Hwy Fort Washington MD 20744",
    "addr:housenumber":"10901",
    "addr:postcode":"20744",
    "addr:street":"Indian Head Hwy",
    "iso:country":"US",
    "sg:address":"10901 Indian Head Hwy",
    "sg:city":"Fort Washington",
    "sg:classifiers":[
        {
            "category":"Real Estate",
            "subcategory":"Real Estate Agent",
            "type":"Services"
        }
    ],
    "sg:phone":"+1 301 292 0700",
    "sg:postcode":"20744",
    "sg:province":"MD",
    "wof:name":"Long & Foster Realtors",
    "wof:placetype":"venue"
},
  "geometry": {"coordinates":[-76.991377,38.737519],"type":"Point"}
}