{
  "type": "Feature",
  "properties": {
    "addr:full":"PO Box 6422 Baltimore MD 21230",
    "addr:housenumber":"po",
    "addr:postcode":"21230",
    "addr:street":"Box 6422",
    "iso:country":"US",
    "sg:address":"PO Box 6422",
    "sg:city":"Baltimore",
    "sg:classifiers":[
        {
            "category":"Building & Trades",
            "subcategory":"Construction",
            "type":"Services"
        }
    ],
    "sg:phone":"+1 410 727 7472",
    "sg:postcode":"21230",
    "sg:province":"MD",
    "sg:tags":[
        "contractor"
    ],
    "wof:name":"Peregrine Construction Group Llc",
    "wof:placetype":"venue"
},
  "geometry": {"coordinates":[-76.61660000000001,39.2747],"type":"Point"}
}