{
  "type": "Feature",
  "properties": {
    "iso:country":"US",
    "sg:address":"2410 Carolyne Ave",
    "sg:city":"Baltimore",
    "sg:classifiers":[
        {
            "category":"Building & Trades",
            "subcategory":"Construction",
            "type":"Services"
        }
    ],
    "sg:phone":"+1 443 677 8738",
    "sg:postcode":"21219",
    "sg:province":"MD",
    "sg:tags":[
        "repair",
        "demolition",
        "welding"
    ],
    "wof:name":"Donna Tiemann",
    "wof:placetype":"venue"
},
  "geometry": {"coordinates":[-76.454715,39.230657],"type":"Point"}
}