{
  "type": "Feature",
  "properties": {
    "iso:country":"US",
    "sg:address":"19169 Brookegrove Ct",
    "sg:city":"Gaithersburg",
    "sg:classifiers":[
        {
            "category":"Personal",
            "subcategory":"Beauty Salon",
            "type":"Services"
        }
    ],
    "sg:phone":"+1 301 330 0114",
    "sg:postcode":"20886",
    "sg:province":"MD",
    "wof:name":"Fantasies Hair Salon",
    "wof:placetype":"venue"
},
  "geometry": {"coordinates":[-77.197295,39.169696],"type":"Point"}
}