{
  "type": "Feature",
  "properties": {
    "addr:full":"6204 Baltimore National Pike Catonsville MD 21228",
    "addr:housenumber":"6204",
    "addr:postcode":"21228",
    "addr:street":"Baltimore National Pike",
    "iso:country":"US",
    "sg:address":"6204 Baltimore National Pike",
    "sg:city":"Catonsville",
    "sg:classifiers":[
        {
            "category":"Retail",
            "subcategory":"Auto Repair",
            "type":"Services"
        }
    ],
    "sg:phone":"+1 410 788 7452",
    "sg:postcode":"21228",
    "sg:province":"MD",
    "sg:tags":[
        "repairing",
        "automobile"
    ],
    "wof:name":"Sams Auto Repair",
    "wof:placetype":"venue"
},
  "geometry": {"coordinates":[-76.75121300000001,39.283652],"type":"Point"}
}