{
  "type": "Feature",
  "properties": {
    "addr:full":"106 E Pennsylvania Ave Baltimore MD 21286",
    "addr:housenumber":"106",
    "addr:postcode":"21286",
    "addr:street":"E Pennsylvania Ave",
    "iso:country":"US",
    "sg:address":"106 E Pennsylvania Ave",
    "sg:city":"Baltimore",
    "sg:classifiers":[
        {
            "category":"Retail",
            "subcategory":"Auto Repair",
            "type":"Services"
        }
    ],
    "sg:phone":"+1 410 828 0215",
    "sg:postcode":"21286",
    "sg:province":"MD",
    "sg:tags":[
        "repairing",
        "automobile"
    ],
    "wof:name":"Towsontowne Garage",
    "wof:placetype":"venue"
},
  "geometry": {"coordinates":[-76.599971,39.400172],"type":"Point"}
}