{
  "type": "Feature",
  "properties": {
    "iso:country":"US",
    "sg:address":"3669 Kenyon Ave",
    "sg:city":"Baltimore",
    "sg:classifiers":[
        {
            "category":"Real Estate",
            "subcategory":"Architect",
            "type":"Services"
        }
    ],
    "sg:phone":"+1 410 485 0070",
    "sg:postcode":"21213",
    "sg:province":"MD",
    "sg:tags":[
        "architects'",
        "specification",
        "builders'",
        "construction",
        "architectural"
    ],
    "wof:name":"Hair Architects Baltimore",
    "wof:placetype":"venue"
},
  "geometry": {"coordinates":[-76.562622,39.319192],"type":"Point"}
}