{
  "type": "Feature",
  "properties": {
    "iso:country":"US",
    "sg:address":"21 Church St Ste 100",
    "sg:city":"Rockville",
    "sg:classifiers":[
        {
            "category":"Insurance",
            "subcategory":"Insurance Agent",
            "type":"Services"
        },
        {
            "category":"Banks & Credit Unions",
            "subcategory":"Investment Brokerage",
            "type":"Services"
        },
        {
            "category":"Insurance",
            "subcategory":"Hazard Insurance",
            "type":"Services"
        }
    ],
    "sg:phone":"+1 301 838 9400",
    "sg:postcode":"20850",
    "sg:province":"MD",
    "sg:tags":[
        "business",
        "resume",
        "commercial",
        "fidelity",
        "surety",
        "bond"
    ],
    "sg:website":"http://www.insassoc.com",
    "wof:name":"Insurance Associates Inc",
    "wof:placetype":"venue"
},
  "geometry": {"coordinates":[-77.145083,39.083114],"type":"Point"}
}