{
  "type": "Feature",
  "properties": {
    "iso:country":"US",
    "sg:address":"1620 Rappolla St",
    "sg:city":"Baltimore",
    "sg:classifiers":[
        {
            "category":"Professional",
            "type":"Services"
        }
    ],
    "sg:phone":"+1 410 396 9066",
    "sg:postcode":"21224",
    "sg:province":"MD",
    "sg:tags":[
        "transportation"
    ],
    "wof:name":"Bureau Transportation Ma",
    "wof:placetype":"venue"
},
  "geometry": {"coordinates":[-76.552063,39.273704],"type":"Point"}
}