{
  "type": "Feature",
  "properties": {
    "iso:country":"US",
    "sg:address":"728 Somerset Pl",
    "sg:city":"Hyattsville",
    "sg:classifiers":[
        {
            "category":"Building & Trades",
            "subcategory":"Construction",
            "type":"Services"
        }
    ],
    "sg:phone":"+1 301 559 1212",
    "sg:postcode":"20783",
    "sg:province":"MD",
    "sg:tags":[
        "repairing",
        "remodeling",
        "contractor"
    ],
    "wof:name":"Affordable Total Remodeling",
    "wof:placetype":"venue"
},
  "geometry": {"coordinates":[-76.995345,38.96612],"type":"Point"}
}