{
  "type": "Feature",
  "properties": {
    "addr:full":"3917 Chatham Rd Ellicott City MD 21042",
    "addr:housenumber":"3917",
    "addr:postcode":"21042",
    "addr:street":"Chatham Rd",
    "iso:country":"US",
    "sg:address":"3917 Chatham Rd",
    "sg:city":"Ellicott City",
    "sg:classifiers":[
        {
            "category":"Shopping",
            "subcategory":"Gifts & Souvenirs",
            "type":"Retail Goods"
        }
    ],
    "sg:phone":"+1 410 480 2600",
    "sg:postcode":"21042",
    "sg:province":"MD",
    "sg:tags":[
        "party",
        "supply"
    ],
    "wof:name":"Picture Confections",
    "wof:placetype":"venue"
},
  "geometry": {"coordinates":[-76.832646,39.261738],"type":"Point"}
}