{
  "type": "Feature",
  "properties": {
    "addr:full":"13242 Sylvan Ave Baltimore MD 21220",
    "addr:housenumber":"13242",
    "addr:postcode":"21220",
    "addr:street":"Sylvan Ave",
    "iso:country":"US",
    "sg:address":"13242 Sylvan Ave",
    "sg:city":"Baltimore",
    "sg:classifiers":[
        {
            "category":"Utilities",
            "type":"Services"
        }
    ],
    "sg:phone":"+1 410 335 2445",
    "sg:postcode":"21220",
    "sg:province":"MD",
    "sg:tags":[
        "sweeping"
    ],
    "wof:name":"Action Sweeping Svc",
    "wof:placetype":"venue"
},
  "geometry": {"coordinates":[-76.355131,39.378498],"type":"Point"}
}