{
  "type": "Feature",
  "properties": {
    "iso:country":"US",
    "sg:address":"9002 Harford Rd",
    "sg:city":"Parkville",
    "sg:classifiers":[
        {
            "category":"Personal",
            "subcategory":"Beauty Salon",
            "type":"Services"
        }
    ],
    "sg:phone":"+1 410 665 3632",
    "sg:postcode":"21234",
    "sg:province":"MD",
    "wof:name":"Mane Attraction Hair Salon",
    "wof:placetype":"venue"
},
  "geometry": {"coordinates":[-76.532021,39.386349],"type":"Point"}
}