{
  "type": "Feature",
  "properties": {
    "addr:full":"204 Coldbrook Rd Lutherville Timonium MD 21093",
    "addr:housenumber":"204",
    "addr:postcode":"21093",
    "addr:street":"Coldbrook Rd",
    "iso:country":"US",
    "sg:address":"204 Coldbrook Rd",
    "sg:city":"Lutherville Timonium",
    "sg:classifiers":[
        {
            "category":"Professional",
            "subcategory":"Management & Consulting",
            "type":"Services"
        }
    ],
    "sg:phone":"+1 410 308 4921",
    "sg:postcode":"21093",
    "sg:province":"MD",
    "sg:tags":[
        "consultant",
        "business"
    ],
    "wof:name":"Anthony Taresco",
    "wof:placetype":"venue"
},
  "geometry": {"coordinates":[-76.611435,39.441721],"type":"Point"}
}