{
  "type": "Feature",
  "properties": {
    "addr:full":"3205 Bayonne Ave Baltimore MD 21214",
    "addr:housenumber":"3205",
    "addr:postcode":"21214",
    "addr:street":"Bayonne Ave",
    "iso:country":"US",
    "sg:address":"3205 Bayonne Ave",
    "sg:city":"Baltimore",
    "sg:classifiers":[
        {
            "category":"Wholesale",
            "subcategory":"Electrical",
            "type":"Manufacturing & Wholesale Goods"
        }
    ],
    "sg:phone":"+1 703 691 4608",
    "sg:postcode":"21214",
    "sg:province":"MD",
    "sg:tags":[
        "control",
        "security",
        "system"
    ],
    "wof:name":"MDI Security Systems",
    "wof:placetype":"venue"
},
  "geometry": {"coordinates":[-76.55820799999999,39.353124],"type":"Point"}
}