{
  "type": "Feature",
  "properties": {
    "addr:full":"212 Cinder Rd Lutherville MD 21093",
    "addr:housenumber":"212",
    "addr:postcode":"21093",
    "addr:street":"Cinder Rd",
    "iso:country":"US",
    "sg:address":"212 Cinder Rd",
    "sg:city":"Lutherville",
    "sg:classifiers":[
        {
            "category":"Manufacturing",
            "subcategory":"Printing",
            "type":"Manufacturing & Wholesale Goods"
        }
    ],
    "sg:phone":"+1 410 561 1012",
    "sg:postcode":"21093",
    "sg:province":"MD",
    "sg:tags":[
        "newspaper"
    ],
    "wof:name":"J J Sun Paper Inc",
    "wof:placetype":"venue"
},
  "geometry": {"coordinates":[-76.610095,39.440777],"type":"Point"}
}