{
  "type": "Feature",
  "properties": {
    "iso:country":"US",
    "sg:address":"71 Gallatin St NW",
    "sg:city":"Washington",
    "sg:classifiers":[
        {
            "category":"Organizations",
            "subcategory":"Religious Organization",
            "type":"Services"
        }
    ],
    "sg:phone":"+1 202 723 7399",
    "sg:postcode":"20011",
    "sg:province":"MD",
    "sg:tags":[
        "clergy"
    ],
    "wof:name":"W Rudolph Bell",
    "wof:placetype":"venue"
},
  "geometry": {"coordinates":[-77.01100099999999,38.952429],"type":"Point"}
}