{
  "type": "Feature",
  "properties": {
    "iso:country":"US",
    "sg:address":"4937 Green Valley Rd",
    "sg:city":"Monrovia",
    "sg:classifiers":[
        {
            "category":"Building & Trades",
            "subcategory":"Electrical",
            "type":"Services"
        }
    ],
    "sg:phone":"+1 301 831 3121",
    "sg:postcode":"21770",
    "sg:province":"MD",
    "sg:tags":[
        "electric",
        "contractor"
    ],
    "wof:name":"Electrical Services Unltd Inc",
    "wof:placetype":"venue"
},
  "geometry": {"coordinates":[-77.271883,39.370342],"type":"Point"}
}