{
  "type": "Feature",
  "properties": {
    "iso:country":"US",
    "sg:address":"32 N Summit Ave",
    "sg:city":"Gaithersburg",
    "sg:classifiers":[
        {
            "category":"Food & Beverages",
            "subcategory":"Groceries & Convenience Stores",
            "type":"Retail Goods"
        }
    ],
    "sg:phone":"+1 301 869 0096",
    "sg:postcode":"20877",
    "sg:province":"MD",
    "sg:tags":[
        "grocer"
    ],
    "wof:name":"Morazan Grocery Store Inc",
    "wof:placetype":"venue"
},
  "geometry": {"coordinates":[-77.193033,39.143617],"type":"Point"}
}