{
  "type": "Feature",
  "properties": {
    "iso:country":"US",
    "sg:address":"20 Wisconsin Cir",
    "sg:city":"Chevy Chase",
    "sg:classifiers":[
        {
            "category":"Insurance",
            "subcategory":"Health Insurance",
            "type":"Services"
        }
    ],
    "sg:phone":"+1 301 907 6764",
    "sg:postcode":"20815",
    "sg:province":"MD",
    "sg:tags":[
        "market"
    ],
    "sg:website":"www.gnc.com",
    "wof:name":"General Nutrition Center",
    "wof:placetype":"venue"
},
  "geometry": {"coordinates":[-77.08470199999999,38.9618],"type":"Point"}
}