{
  "type": "Feature",
  "properties": {
    "addr:full":"5300 Balistan Rd Baltimore MD 21237",
    "addr:housenumber":"5300",
    "addr:postcode":"21237",
    "addr:street":"Balistan Rd",
    "iso:country":"US",
    "sg:address":"5300 Balistan Rd",
    "sg:city":"Baltimore",
    "sg:classifiers":[
        {
            "category":"Building & Trades",
            "subcategory":"Construction",
            "type":"Services"
        }
    ],
    "sg:phone":"+1 410 391 9170",
    "sg:postcode":"21237",
    "sg:province":"MD",
    "sg:tags":[
        "house"
    ],
    "wof:name":"Fs Builders / Maintenance",
    "wof:placetype":"venue"
},
  "geometry": {"coordinates":[-76.466442,39.355498],"type":"Point"}
}