{
  "type": "Feature",
  "properties": {
    "addr:full":"1331 Blue Mount Rd Monkton MD 21111",
    "addr:housenumber":"1331",
    "addr:postcode":"21111",
    "addr:street":"Blue Mount Rd",
    "iso:country":"US",
    "sg:address":"1331 Blue Mount Rd",
    "sg:city":"Monkton",
    "sg:classifiers":[
        {
            "category":"Professional",
            "subcategory":"Lawyer & Legal Services",
            "type":"Services"
        }
    ],
    "sg:phone":"+1 410 343 2610",
    "sg:postcode":"21111",
    "sg:province":"MD",
    "wof:name":"Goldman Herbert Atty & Harriet",
    "wof:placetype":"venue"
},
  "geometry": {"coordinates":[-76.629997,39.593899],"type":"Point"}
}