{
  "type": "Feature",
  "properties": {
    "addr:full":"772 N Prince Frederick Blvd Prince Frederick MD 20678",
    "addr:housenumber":"772",
    "addr:postcode":"20678",
    "addr:street":"N Prince Frederick Blvd",
    "iso:country":"US",
    "sg:address":"772 N Prince Frederick Blvd",
    "sg:city":"Prince Frederick",
    "sg:classifiers":[
        {
            "category":"Sports & Exercise",
            "subcategory":"Gym",
            "type":"Entertainment"
        }
    ],
    "sg:phone":"+1 410 414 7000",
    "sg:postcode":"20678",
    "sg:province":"MD",
    "sg:tags":[
        "club",
        "health",
        "studio",
        "gymnasium"
    ],
    "wof:name":"Curves For Women",
    "wof:placetype":"venue"
},
  "geometry": {"coordinates":[-76.596092,38.552953],"type":"Point"}
}