{
  "type": "Feature",
  "properties": {
    "iso:country":"US",
    "sg:address":"6 Camano Ct",
    "sg:city":"Randallstown",
    "sg:classifiers":[
        {
            "category":"Professional",
            "subcategory":"Employment Agencies",
            "type":"Services"
        },
        {
            "category":"Communications",
            "type":"Services"
        },
        {
            "category":"Professional",
            "subcategory":"Computer Services",
            "type":"Services"
        }
    ],
    "sg:phone":"+1 877 399 6824",
    "sg:postcode":"21133",
    "sg:province":"MD",
    "sg:tags":[
        "consultant",
        "opportunity",
        "telecommunication"
    ],
    "sg:website":"http://www.fdivoice.com/346659",
    "wof:name":"Financial Destination Inc.",
    "wof:placetype":"venue"
},
  "geometry": {"coordinates":[-76.818787,39.386092],"type":"Point"}
}