{
  "type": "Feature",
  "properties": {
    "addr:full":"5648 Southwestern Blvd Halethorpe MD 21227",
    "addr:housenumber":"5648",
    "addr:postcode":"21227",
    "addr:street":"Southwestern Blvd",
    "iso:country":"US",
    "sg:address":"5648 Southwestern Blvd",
    "sg:city":"Halethorpe",
    "sg:classifiers":[
        {
            "category":"Building & Trades",
            "subcategory":"Construction",
            "type":"Services"
        }
    ],
    "sg:phone":"+1 410 242 3325",
    "sg:postcode":"21227",
    "sg:province":"MD",
    "sg:tags":[
        "home",
        "improvement"
    ],
    "wof:name":"C & D Framing & Home Imprvmnt",
    "wof:placetype":"venue"
},
  "geometry": {"coordinates":[-76.691861,39.239258],"type":"Point"}
}