{
  "type": "Feature",
  "properties": {
    "addr:full":"14674 Southlawn Ln Rockville MD 20850",
    "addr:housenumber":"14674",
    "addr:postcode":"20850",
    "addr:street":"Southlawn Ln",
    "iso:country":"US",
    "sg:address":"14674 Southlawn Ln",
    "sg:city":"Rockville",
    "sg:classifiers":[
        {
            "category":"Manufacturing",
            "subcategory":"Chemicals & Compounds",
            "type":"Manufacturing & Wholesale Goods"
        }
    ],
    "sg:phone":"+1 301 279 2295",
    "sg:postcode":"20850",
    "sg:province":"MD",
    "sg:website":"www.transworldchem.com",
    "wof:name":"Trans World Chemicals Inc",
    "wof:placetype":"venue"
},
  "geometry": {"coordinates":[-77.138313,39.096447],"type":"Point"}
}