{
  "type": "Feature",
  "properties": {
    "iso:country":"US",
    "sg:address":"15708 White Rock Rd",
    "sg:city":"Gaithersburg",
    "sg:classifiers":[
        {
            "category":"Health Services",
            "subcategory":"Doctor",
            "type":"Services"
        }
    ],
    "sg:phone":"+1 301 963 6577",
    "sg:postcode":"20878",
    "sg:province":"MD",
    "sg:tags":[
        "dentist"
    ],
    "wof:name":"James C Campbell DDS",
    "wof:placetype":"venue"
},
  "geometry": {"coordinates":[-77.273787,39.114398],"type":"Point"}
}