{
  "type": "Feature",
  "properties": {
    "iso:country":"US",
    "sg:address":"1120 Benfield Blvd",
    "sg:city":"Millersville",
    "sg:classifiers":[
        {
            "category":"Shopping",
            "subcategory":"Discount & Variety Stores",
            "type":"Retail Goods"
        }
    ],
    "sg:phone":"+1 410 987 9111",
    "sg:postcode":"21108",
    "sg:province":"MD",
    "sg:tags":[
        "post",
        "trading"
    ],
    "wof:name":"Scoshi's Trading Co",
    "wof:placetype":"venue"
},
  "geometry": {"coordinates":[-76.632047,39.094465],"type":"Point"}
}