{
  "type": "Feature",
  "properties": {
    "iso:country":"US",
    "sg:address":"7812 Klovstad Dr",
    "sg:city":"Fort Washington",
    "sg:classifiers":[
        {
            "category":"Building & Trades",
            "subcategory":"Construction",
            "type":"Services"
        }
    ],
    "sg:phone":"+1 301 248 1122",
    "sg:postcode":"20744",
    "sg:province":"MD",
    "sg:tags":[
        "house"
    ],
    "wof:name":"Hyun Sang Won",
    "wof:placetype":"venue"
},
  "geometry": {"coordinates":[-76.947946,38.780982],"type":"Point"}
}