{
  "type": "Feature",
  "properties": {
    "iso:country":"US",
    "sg:address":"4905 Del Ray Ave Ste 212",
    "sg:city":"Bethesda",
    "sg:classifiers":[
        {
            "category":"Communications",
            "type":"Services"
        },
        {
            "category":"Professional",
            "subcategory":"Computer Services",
            "type":"Services"
        }
    ],
    "sg:phone":"+1 301 718 9390",
    "sg:postcode":"20814",
    "sg:province":"MD",
    "sg:tags":[
        "web",
        "isp",
        "design",
        "provider",
        "internet"
    ],
    "sg:website":"www.brookslittlefield.net",
    "wof:name":"Brooks Littlefield Associates Inc",
    "wof:placetype":"venue"
},
  "geometry": {"coordinates":[-77.0989,38.989799],"type":"Point"}
}