{
  "type": "Feature",
  "properties": {
    "iso:country":"US",
    "sg:address":"4787 Black Walnut Point Rd",
    "sg:city":"Tilghman",
    "sg:classifiers":[
        {
            "category":"Recreation",
            "type":"Entertainment"
        }
    ],
    "sg:phone":"+1 410 886 2545",
    "sg:postcode":"21671",
    "sg:province":"MD",
    "sg:tags":[
        "charter",
        "boat"
    ],
    "wof:name":"Deep Reef Small Craft Rental",
    "wof:placetype":"venue"
},
  "geometry": {"coordinates":[-76.343167,38.687049],"type":"Point"}
}