{
  "type": "Feature",
  "properties": {
    "addr:full":"3315 Crain Hwy Waldorf MD 20603",
    "addr:housenumber":"3315",
    "addr:postcode":"20603",
    "addr:street":"Crain Hwy",
    "iso:country":"US",
    "sg:address":"3315 Crain Hwy",
    "sg:city":"Waldorf",
    "sg:classifiers":[
        {
            "category":"Restaurant",
            "type":"Food & Drink"
        }
    ],
    "sg:menulink":"http://www.allmenus.com/md/waldorf/98609-longhorn-steakhouse/menu/",
    "sg:phone":"+1 301 632 6300",
    "sg:postcode":"20603",
    "sg:province":"MD",
    "sg:tags":[
        "american",
        "steakhouse"
    ],
    "wof:name":"LongHorn Steakhouse",
    "wof:placetype":"venue"
},
  "geometry": {"coordinates":[-76.9162,38.621168],"type":"Point"}
}