{
  "type": "Feature",
  "properties": {
    "addr:full":"108 W Timonium Rd Timonium MD 21093",
    "addr:housenumber":"108",
    "addr:postcode":"21093",
    "addr:street":"W Timonium Rd",
    "iso:country":"US",
    "sg:address":"108 W Timonium Rd",
    "sg:city":"Timonium",
    "sg:classifiers":[
        {
            "category":"Professional",
            "subcategory":"Accounting & Tax Preparation",
            "type":"Services"
        }
    ],
    "sg:phone":"+1 410 560 3535",
    "sg:postcode":"21093",
    "sg:province":"MD",
    "sg:tags":[
        "accountant"
    ],
    "wof:name":"Weinberg Griffith Tucker Jones",
    "wof:placetype":"venue"
},
  "geometry": {"coordinates":[-76.631271,39.439166],"type":"Point"}
}