{
  "type": "Feature",
  "properties": {
    "iso:country":"US",
    "sg:address":"1469 Tyler Ave",
    "sg:city":"Annapolis",
    "sg:classifiers":[
        {
            "category":"Recreation",
            "type":"Entertainment"
        }
    ],
    "sg:phone":"+1 410 267 8539",
    "sg:postcode":"21403",
    "sg:province":"MD",
    "sg:tags":[
        "center"
    ],
    "wof:name":"Robin Wood Recreation Ctr",
    "wof:placetype":"venue"
},
  "geometry": {"coordinates":[-76.50645,38.955305],"type":"Point"}
}