{
  "type": "Feature",
  "properties": {
    "addr:full":"23816 Old Stables Rd Rawlings MD 21557",
    "addr:housenumber":"23816",
    "addr:postcode":"21557",
    "addr:street":"Old Stables Rd",
    "iso:country":"US",
    "sg:address":"23816 Old Stables Rd",
    "sg:city":"Rawlings",
    "sg:classifiers":[
        {
            "category":"Retail",
            "subcategory":"Repair Shop",
            "type":"Services"
        }
    ],
    "sg:phone":"+1 301 786 4667",
    "sg:postcode":"21557",
    "sg:province":"MD",
    "sg:tags":[
        "welding"
    ],
    "wof:name":"D & B Welding & Fabrication",
    "wof:placetype":"venue"
},
  "geometry": {"coordinates":[-78.959743,39.466574],"type":"Point"}
}