{
  "type": "Feature",
  "properties": {
    "addr:full":"3086 Festival Way Waldorf MD 20601",
    "addr:housenumber":"3086",
    "addr:postcode":"20601",
    "addr:street":"Festival Way",
    "iso:country":"US",
    "sg:address":"3086 Festival Way",
    "sg:city":"Waldorf",
    "sg:classifiers":[
        {
            "category":"Restaurant",
            "type":"Food & Drink"
        }
    ],
    "sg:phone":"+1 301 632 9846",
    "sg:postcode":"20601",
    "sg:province":"MD",
    "wof:name":"Wings To Go",
    "wof:placetype":"venue"
},
  "geometry": {"coordinates":[-76.911283,38.627127],"type":"Point"}
}