{
  "type": "Feature",
  "properties": {
    "iso:country":"US",
    "sg:address":"824 Park Ave",
    "sg:city":"Baltimore",
    "sg:classifiers":[
        {
            "category":"Shopping",
            "type":"Retail Goods"
        }
    ],
    "sg:phone":"+1 410 225 9525",
    "sg:postcode":"21201",
    "sg:province":"MD",
    "sg:tags":[
        "art",
        "gallery",
        "dealer"
    ],
    "wof:name":"Third Eye Arts",
    "wof:placetype":"venue"
},
  "geometry": {"coordinates":[-76.618634,39.299587],"type":"Point"}
}