{
  "type": "Feature",
  "properties": {
    "addr:full":"1900 E Northern Pkwy Ste 100 Baltimore MD 21239",
    "addr:housenumber":"1900",
    "addr:postcode":"21239",
    "addr:street":"E Northern Pkwy Ste 100",
    "iso:country":"US",
    "sg:address":"1900 E Northern Pkwy Ste 100",
    "sg:city":"Baltimore",
    "sg:classifiers":[
        {
            "category":"Shopping",
            "subcategory":"Pharmacy",
            "type":"Retail Goods"
        }
    ],
    "sg:phone":"+1 410 433 8150",
    "sg:postcode":"21239",
    "sg:province":"MD",
    "sg:tags":[
        "drugstore"
    ],
    "wof:name":"Sunrise Pharmacy",
    "wof:placetype":"venue"
},
  "geometry": {"coordinates":[-76.5812,39.367281],"type":"Point"}
}