{
  "type": "Feature",
  "properties": {
    "addr:full":"1121 Saint Agnes Ln Gwynn Oak MD 21207",
    "addr:housenumber":"1121",
    "addr:postcode":"21207",
    "addr:street":"Saint Agnes Ln",
    "iso:country":"US",
    "sg:address":"1121 Saint Agnes Ln",
    "sg:city":"Gwynn Oak",
    "sg:classifiers":[
        {
            "category":"Real Estate",
            "subcategory":"Real Estate Operator",
            "type":"Services"
        }
    ],
    "sg:phone":"+1 410 869 9620",
    "sg:postcode":"21207",
    "sg:province":"MD",
    "sg:tags":[
        "apartment"
    ],
    "wof:name":"Fairspring Apartments",
    "wof:placetype":"venue"
},
  "geometry": {"coordinates":[-76.717697,39.294701],"type":"Point"}
}