{
  "type": "Feature",
  "properties": {
    "iso:country":"US",
    "sg:address":"7598 Commerce Ln",
    "sg:city":"Clinton",
    "sg:classifiers":[
        {
            "category":"Restaurant",
            "type":"Food & Drink"
        }
    ],
    "sg:phone":"+1 240 375 7711",
    "sg:postcode":"20735",
    "sg:province":"MD",
    "sg:tags":[
        "caterer"
    ],
    "wof:name":"Creative Touch By Rhonda",
    "wof:placetype":"venue"
},
  "geometry": {"coordinates":[-76.90594900000001,38.784831],"type":"Point"}
}