{
  "type": "Feature",
  "properties": {
    "addr:full":"4906 Edmonston Rd Hyattsville MD 20781",
    "addr:housenumber":"4906",
    "addr:postcode":"20781",
    "addr:street":"Edmonston Rd",
    "iso:country":"US",
    "sg:address":"4906 Edmonston Rd",
    "sg:city":"Hyattsville",
    "sg:classifiers":[
        {
            "category":"Travel",
            "subcategory":"Travel Agent",
            "type":"Entertainment"
        }
    ],
    "sg:phone":"+1 301 403 2990",
    "sg:postcode":"20781",
    "sg:province":"MD",
    "sg:tags":[
        "agency",
        "bureau"
    ],
    "wof:name":"York Dominican's Tambores Inc",
    "wof:placetype":"venue"
},
  "geometry": {"coordinates":[-76.926558,38.948893],"type":"Point"}
}