{
  "type": "Feature",
  "properties": {
    "iso:country":"US",
    "sg:address":"15037 Eardley Ct",
    "sg:city":"Silver Spring",
    "sg:classifiers":[
        {
            "category":"Manufacturing",
            "subcategory":"Printing",
            "type":"Manufacturing & Wholesale Goods"
        }
    ],
    "sg:phone":"+1 301 438 1900",
    "sg:postcode":"20906",
    "sg:province":"MD",
    "sg:tags":[
        "printer"
    ],
    "wof:name":"Walter Burroughs",
    "wof:placetype":"venue"
},
  "geometry": {"coordinates":[-77.059741,39.103086],"type":"Point"}
}