{
  "type": "Feature",
  "properties": {
    "addr:full":"26508 Aiken Dr Clarksburg MD 20871",
    "addr:housenumber":"26508",
    "addr:postcode":"20871",
    "addr:street":"Aiken Dr",
    "iso:country":"US",
    "sg:address":"26508 Aiken Dr",
    "sg:city":"Clarksburg",
    "sg:classifiers":[
        {
            "category":"Professional",
            "subcategory":"Detective & Security Services",
            "type":"Services"
        }
    ],
    "sg:phone":"+1 301 253 3625",
    "sg:postcode":"20871",
    "sg:province":"MD",
    "sg:tags":[
        "information",
        "bureau"
    ],
    "wof:name":"Corazza Services Inc",
    "wof:placetype":"venue"
},
  "geometry": {"coordinates":[-77.29003400000001,39.291229],"type":"Point"}
}