{
  "type": "Feature",
  "properties": {
    "addr:full":"5500 River Rd Bethesda MD 20816",
    "addr:housenumber":"5500",
    "addr:postcode":"20816",
    "addr:street":"River Rd",
    "iso:country":"US",
    "sg:address":"5500 River Rd",
    "sg:city":"Bethesda",
    "sg:classifiers":[
        {
            "category":"Place Of Worship",
            "subcategory":"Church",
            "type":"Public Place"
        },
        {
            "category":"Place Of Worship",
            "type":"Public Place"
        }
    ],
    "sg:phone":"+1 301 320 3600",
    "sg:postcode":"20816",
    "sg:province":"MD",
    "sg:tags":[
        "churches-presbyterian-arp",
        "churches-presbyterian"
    ],
    "sg:website":"http://www.4thpres.org",
    "wof:name":"Fourth Presbyterian Church",
    "wof:placetype":"venue"
},
  "geometry": {"coordinates":[-77.11013,38.968971],"type":"Point"}
}