{
  "type": "Feature",
  "properties": {
    "iso:country":"US",
    "sg:address":"10310 Oaklyn Dr",
    "sg:city":"Potomac",
    "sg:classifiers":[
        {
            "category":"Place Of Worship",
            "subcategory":"Synagogue",
            "type":"Public Place"
        },
        {
            "category":"Place Of Worship",
            "type":"Public Place"
        }
    ],
    "sg:phone":"+1 301 299 2100",
    "sg:postcode":"20854",
    "sg:province":"MD",
    "sg:tags":[
        "church"
    ],
    "wof:name":"International Society-Krishna",
    "wof:placetype":"venue"
},
  "geometry": {"coordinates":[-77.211071,39.001026],"type":"Point"}
}