{
  "type": "Feature",
  "properties": {
    "iso:country":"US",
    "sg:address":"8002 Darcy Rd",
    "sg:city":"District Heights",
    "sg:classifiers":[
        {
            "category":"Building & Trades",
            "subcategory":"Landscaping Services",
            "type":"Services"
        }
    ],
    "sg:phone":"+1 301 333 2548",
    "sg:postcode":"20747",
    "sg:province":"MD",
    "sg:tags":[
        "landscape"
    ],
    "wof:name":"Storkers Landscaping",
    "wof:placetype":"venue"
},
  "geometry": {"coordinates":[-76.863935,38.858797],"type":"Point"}
}