{
  "type": "Feature",
  "properties": {
    "addr:full":"2703 Foster Ave Baltimore MD 21224",
    "addr:housenumber":"2703",
    "addr:postcode":"21224",
    "addr:street":"Foster Ave",
    "iso:country":"US",
    "sg:address":"2703 Foster Ave",
    "sg:city":"Baltimore",
    "sg:classifiers":[
        {
            "category":"Banks & Credit Unions",
            "subcategory":"Bank",
            "type":"Services"
        }
    ],
    "sg:phone":"+1 410 276 0894",
    "sg:postcode":"21224",
    "sg:province":"MD",
    "sg:tags":[
        "commercial",
        "state",
        "saving"
    ],
    "wof:name":"St Casimirs Savings Bank",
    "wof:placetype":"venue"
},
  "geometry": {"coordinates":[-76.578102,39.284302],"type":"Point"}
}