{
  "type": "Feature",
  "properties": {
    "addr:full":"4815 Frankford Ave Baltimore MD 21206",
    "addr:housenumber":"4815",
    "addr:postcode":"21206",
    "addr:street":"Frankford Ave",
    "iso:country":"US",
    "sg:address":"4815 Frankford Ave",
    "sg:city":"Baltimore",
    "sg:classifiers":[
        {
            "category":"Social Services",
            "subcategory":"Child Care",
            "type":"Services"
        }
    ],
    "sg:phone":"+1 410 325 1743",
    "sg:postcode":"21206",
    "sg:province":"MD",
    "sg:tags":[
        "day"
    ],
    "wof:name":"Carter Walter P Day Care Center",
    "wof:placetype":"venue"
},
  "geometry": {"coordinates":[-76.544296,39.332001],"type":"Point"}
}