{
  "type": "Feature",
  "properties": {
    "addr:full":"7 W Courtland St Bel Air MD 21014",
    "addr:housenumber":"7",
    "addr:postcode":"21014",
    "addr:street":"W Courtland St",
    "iso:country":"US",
    "sg:address":"7 W Courtland St",
    "sg:city":"Bel Air",
    "sg:classifiers":[
        {
            "category":"Shopping",
            "type":"Retail Goods"
        }
    ],
    "sg:phone":"+1 410 420 7400",
    "sg:postcode":"21014",
    "sg:province":"MD",
    "sg:tags":[
        "equipment",
        "care",
        "health",
        "home"
    ],
    "wof:name":"A Courtyard Hm Medical Supply",
    "wof:placetype":"venue"
},
  "geometry": {"coordinates":[-76.34933700000001,39.534983],"type":"Point"}
}