{
  "type": "Feature",
  "properties": {
    "iso:country":"US",
    "sg:address":"8030 Woodmont Ave",
    "sg:city":"Bethesda",
    "sg:classifiers":[
        {
            "category":"Real Estate",
            "subcategory":"Architect",
            "type":"Services"
        }
    ],
    "sg:phone":"+1 301 656 2787",
    "sg:postcode":"20814",
    "sg:province":"MD",
    "sg:website":"www.bzaonline.com",
    "wof:name":"Brackett-Zimmermann & Associates",
    "wof:placetype":"venue"
},
  "geometry": {"coordinates":[-77.096298,38.989799],"type":"Point"}
}