{
  "type": "Feature",
  "properties": {
    "addr:full":"4700 Belle Grove Rd Ste 4 Baltimore MD 21225",
    "addr:housenumber":"4700",
    "addr:postcode":"21225",
    "addr:street":"Belle Grove Rd Ste 4",
    "iso:country":"US",
    "sg:address":"4700 Belle Grove Rd Ste 4",
    "sg:city":"Baltimore",
    "sg:classifiers":[
        {
            "category":"Shopping",
            "subcategory":"Hobbies, Toys, & Games",
            "type":"Retail Goods"
        }
    ],
    "sg:phone":"+1 410 789 1660",
    "sg:postcode":"21225",
    "sg:province":"MD",
    "sg:tags":[
        "shop",
        "hobby"
    ],
    "wof:name":"AA Games & Jukes Inc",
    "wof:placetype":"venue"
},
  "geometry": {"coordinates":[-76.62112999999999,39.228293],"type":"Point"}
}