{
  "type": "Feature",
  "properties": {
    "iso:country":"US",
    "sg:address":"7824 Brookstone Ct",
    "sg:city":"Ellicott City",
    "sg:classifiers":[
        {
            "category":"Real Estate",
            "subcategory":"Architect",
            "type":"Services"
        }
    ],
    "sg:phone":"+1 410 796 5752",
    "sg:postcode":"21043",
    "sg:province":"MD",
    "sg:tags":[
        "architectural"
    ],
    "wof:name":"Pointon Architecture",
    "wof:placetype":"venue"
},
  "geometry": {"coordinates":[-76.78604,39.21934],"type":"Point"}
}