{
  "type": "Feature",
  "properties": {
    "addr:full":"3325 Brendan Ave Baltimore MD 21213",
    "addr:housenumber":"3325",
    "addr:postcode":"21213",
    "addr:street":"Brendan Ave",
    "iso:country":"US",
    "sg:address":"3325 Brendan Ave",
    "sg:city":"Baltimore",
    "sg:classifiers":[
        {
            "category":"Health Services",
            "subcategory":"Clinic",
            "type":"Services"
        }
    ],
    "sg:phone":"+1 443 869 2663",
    "sg:postcode":"21213",
    "sg:province":"MD",
    "sg:tags":[
        "outpatient"
    ],
    "wof:name":"Jerry Williams Foundation",
    "wof:placetype":"venue"
},
  "geometry": {"coordinates":[-76.568011,39.320964],"type":"Point"}
}