{
  "type": "Feature",
  "properties": {
    "iso:country":"US",
    "sg:address":"51 Ritchie Rd",
    "sg:city":"Capitol Heights",
    "sg:classifiers":[
        {
            "category":"Manufacturing",
            "subcategory":"Metals",
            "type":"Manufacturing & Wholesale Goods"
        }
    ],
    "sg:phone":"+1 301 350 4200",
    "sg:postcode":"20743",
    "sg:province":"MD",
    "sg:tags":[
        "fabricator",
        "sheet"
    ],
    "wof:name":"United Sheet Metal Inc",
    "wof:placetype":"venue"
},
  "geometry": {"coordinates":[-76.862512,38.888956],"type":"Point"}
}