{
  "type": "Feature",
  "properties": {
    "iso:country":"US",
    "sg:address":"606 S Ann St",
    "sg:city":"Baltimore",
    "sg:classifiers":[
        {
            "category":"Education",
            "subcategory":"Library",
            "type":"Public Place"
        }
    ],
    "sg:phone":"+1 410 396 0992",
    "sg:postcode":"21231",
    "sg:province":"MD",
    "wof:name":"Fell's Point",
    "wof:placetype":"venue"
},
  "geometry": {"coordinates":[-76.59132700000001,39.284579],"type":"Point"}
}