{
  "type": "Feature",
  "properties": {
    "iso:country":"US",
    "sg:address":"125 Kerney St",
    "sg:city":"Federalsburg",
    "sg:classifiers":[
        {
            "category":"Government",
            "subcategory":"Office",
            "type":"Public Place"
        }
    ],
    "sg:phone":"+1 410 754 8649",
    "sg:postcode":"21632",
    "sg:province":"MD",
    "sg:tags":[
        "village"
    ],
    "wof:name":"Federalsburg Town Barn",
    "wof:placetype":"venue"
},
  "geometry": {"coordinates":[-75.76696699999999,38.691009],"type":"Point"}
}