{
  "type": "Feature",
  "properties": {
    "iso:country":"US",
    "sg:address":"14923 Winchester Rd SW",
    "sg:city":"Cumberland",
    "sg:classifiers":[
        {
            "category":"Social Services",
            "subcategory":"Child Care",
            "type":"Services"
        }
    ],
    "sg:phone":"+1 301 729 1101",
    "sg:postcode":"21502",
    "sg:province":"MD",
    "sg:tags":[
        "nursery",
        "day"
    ],
    "wof:name":"Melissa Shriver",
    "wof:placetype":"venue"
},
  "geometry": {"coordinates":[-78.832649,39.589901],"type":"Point"}
}