{
  "type": "Feature",
  "properties": {
    "iso:country":"US",
    "sg:address":"4419 S Meadow Ct",
    "sg:city":"Ellicott City",
    "sg:classifiers":[
        {
            "category":"Health Services",
            "subcategory":"Doctor",
            "type":"Services"
        }
    ],
    "sg:phone":"+1 410 350 3341",
    "sg:postcode":"21042",
    "sg:province":"MD",
    "sg:tags":[
        "physician",
        "surgeon"
    ],
    "wof:name":"Harborview Anesthesia",
    "wof:placetype":"venue"
},
  "geometry": {"coordinates":[-76.861363,39.247002],"type":"Point"}
}