{
  "type": "Feature",
  "properties": {
    "iso:country":"US",
    "sg:address":"1442 Martin Blvd",
    "sg:city":"Middle River",
    "sg:classifiers":[
        {
            "category":"Banks & Credit Unions",
            "subcategory":"Bank",
            "type":"Services"
        }
    ],
    "sg:phone":"+1 410 687 5678",
    "sg:postcode":"21220",
    "sg:province":"MD",
    "sg:website":"www.wachovia.com",
    "wof:name":"Wachovia",
    "wof:placetype":"venue"
},
  "geometry": {"coordinates":[-76.43620300000001,39.329201],"type":"Point"}
}