{
  "type": "Feature",
  "properties": {
    "addr:full":"10264 Southern Maryland Blvd Dunkirk MD 20754",
    "addr:housenumber":"10264",
    "addr:postcode":"20754",
    "addr:street":"Southern Maryland Blvd",
    "iso:country":"US",
    "sg:address":"10264 Southern Maryland Blvd",
    "sg:city":"Dunkirk",
    "sg:classifiers":[
        {
            "category":"Banks & Credit Unions",
            "subcategory":"Bank",
            "type":"Services"
        }
    ],
    "sg:phone":"+1 410 257 7396",
    "sg:postcode":"20754",
    "sg:province":"MD",
    "wof:name":"B B & T",
    "wof:placetype":"venue"
},
  "geometry": {"coordinates":[-76.660787,38.721392],"type":"Point"}
}