{
  "type": "Feature",
  "properties": {
    "addr:full":"320 Oak Manor Dr Glen Burnie MD 21061",
    "addr:housenumber":"320",
    "addr:postcode":"21061",
    "addr:street":"Oak Manor Dr",
    "iso:country":"US",
    "sg:address":"320 Oak Manor Dr",
    "sg:city":"Glen Burnie",
    "sg:classifiers":[
        {
            "category":"Social Services",
            "subcategory":"Child Care",
            "type":"Services"
        }
    ],
    "sg:phone":"+1 410 768 3047",
    "sg:postcode":"21061",
    "sg:province":"MD",
    "wof:name":"Tomorrow's Hope Child Care",
    "wof:placetype":"venue"
},
  "geometry": {"coordinates":[-76.626524,39.14159],"type":"Point"}
}