{
  "type": "Feature",
  "properties": {
    "addr:full":"12053 Tech Rd Silver Spring MD 20904",
    "addr:housenumber":"12053",
    "addr:postcode":"20904",
    "addr:street":"Tech Rd",
    "iso:country":"US",
    "sg:address":"12053 Tech Rd",
    "sg:city":"Silver Spring",
    "sg:classifiers":[
        {
            "category":"Banks & Credit Unions",
            "subcategory":"Bank",
            "type":"Services"
        }
    ],
    "sg:phone":"+1 301 680 7130",
    "sg:postcode":"20904",
    "sg:province":"MD",
    "sg:tags":[
        "loan",
        "real estate"
    ],
    "wof:name":"Atlantic Coast Mtg Group Inc",
    "wof:placetype":"venue"
},
  "geometry": {"coordinates":[-76.970176,39.051457],"type":"Point"}
}