{
  "type": "Feature",
  "properties": {
    "addr:full":"9889 Brewers Ct Laurel MD 20723",
    "addr:housenumber":"9889",
    "addr:postcode":"20723",
    "addr:street":"Brewers Ct",
    "iso:country":"US",
    "sg:address":"9889 Brewers Ct",
    "sg:city":"Laurel",
    "sg:classifiers":[
        {
            "category":"Building & Trades",
            "subcategory":"Locksmith",
            "type":"Services"
        }
    ],
    "sg:phone":"+1 301 591 2803",
    "sg:postcode":"20723",
    "sg:province":"MD",
    "sg:tags":[
        "lock",
        "industrial",
        "locksmiths-commercial"
    ],
    "wof:name":"0 7 7 Day Emergency A 24 Hour",
    "wof:placetype":"venue"
},
  "geometry": {"coordinates":[-76.83215199999999,39.113258],"type":"Point"}
}