{
  "type": "Feature",
  "properties": {
    "iso:country":"US",
    "sg:address":"1210 Presstman St",
    "sg:city":"Baltimore",
    "sg:classifiers":[
        {
            "category":"Professional",
            "type":"Services"
        }
    ],
    "sg:phone":"+1 410 728 1729",
    "sg:postcode":"21217",
    "sg:province":"MD",
    "sg:tags":[
        "caterer"
    ],
    "wof:name":"St Peter Clavers Hall",
    "wof:placetype":"venue"
},
  "geometry": {"coordinates":[-76.638397,39.305698],"type":"Point"}
}