{
  "type": "Feature",
  "properties": {
    "iso:country":"US",
    "sg:address":"10216 Parkwood Dr",
    "sg:city":"Kensington",
    "sg:classifiers":[
        {
            "category":"Professional",
            "subcategory":"Accounting & Tax Preparation",
            "type":"Services"
        }
    ],
    "sg:phone":"+1 301 896 0145",
    "sg:postcode":"20895",
    "sg:province":"MD",
    "wof:name":"Michael Poor",
    "wof:placetype":"venue"
},
  "geometry": {"coordinates":[-77.09398299999999,39.024026],"type":"Point"}
}