{
  "type": "Feature",
  "properties": {
    "addr:full":"11459 Cron Hill Dr Owings Mills MD 21117",
    "addr:housenumber":"11459",
    "addr:postcode":"21117",
    "addr:street":"Cron Hill Dr",
    "iso:country":"US",
    "sg:address":"11459 Cron Hill Dr",
    "sg:city":"Owings Mills",
    "sg:classifiers":[
        {
            "category":"Professional",
            "subcategory":"Management & Consulting",
            "type":"Services"
        }
    ],
    "sg:phone":"+1 410 998 9999",
    "sg:postcode":"21117",
    "sg:province":"MD",
    "sg:tags":[
        "party",
        "planning"
    ],
    "wof:name":"Zozzie & Heidi Innovative",
    "wof:placetype":"venue"
},
  "geometry": {"coordinates":[-76.772965,39.435755],"type":"Point"}
}