{
  "type": "Feature",
  "properties": {
    "addr:full":"9260 Billingsley Rd White Plains MD 20695",
    "addr:housenumber":"9260",
    "addr:postcode":"20695",
    "addr:street":"Billingsley Rd",
    "iso:country":"US",
    "sg:address":"9260 Billingsley Rd",
    "sg:city":"White Plains",
    "sg:classifiers":[
        {
            "category":"Wholesale",
            "subcategory":"Electrical",
            "type":"Manufacturing & Wholesale Goods"
        }
    ],
    "sg:phone":"+1 301 870 6888",
    "sg:postcode":"20695",
    "sg:province":"MD",
    "sg:tags":[
        "control",
        "security",
        "system"
    ],
    "wof:name":"ACSI Inc",
    "wof:placetype":"venue"
},
  "geometry": {"coordinates":[-76.991615,38.604532],"type":"Point"}
}