{
  "type": "Feature",
  "properties": {
    "addr:full":"2434 Cape Horn Rd Hampstead MD 21074",
    "addr:housenumber":"2434",
    "addr:postcode":"21074",
    "addr:street":"Cape Horn Rd",
    "iso:country":"US",
    "sg:address":"2434 Cape Horn Rd",
    "sg:city":"Hampstead",
    "sg:classifiers":[
        {
            "category":"Social Services",
            "subcategory":"Child Care",
            "type":"Services"
        }
    ],
    "sg:phone":"+1 410 374 4291",
    "sg:postcode":"21074",
    "sg:province":"MD",
    "sg:tags":[
        "kindergarten",
        "academic",
        "school"
    ],
    "wof:name":"St George's Christian Preschl",
    "wof:placetype":"venue"
},
  "geometry": {"coordinates":[-76.89160099999999,39.627534],"type":"Point"}
}