{
  "type": "Feature",
  "properties": {
    "addr:full":"1 Katurah Ln Owings Mills MD 21117",
    "addr:housenumber":"1",
    "addr:postcode":"21117",
    "addr:street":"Katurah Ln",
    "iso:country":"US",
    "sg:address":"1 Katurah Ln",
    "sg:city":"Owings Mills",
    "sg:classifiers":[
        {
            "category":"Professional",
            "subcategory":"Management & Consulting",
            "type":"Services"
        }
    ],
    "sg:phone":"+1 410 902 0801",
    "sg:postcode":"21117",
    "sg:province":"MD",
    "sg:tags":[
        "marketing",
        "consultant"
    ],
    "wof:name":"Brave New Markets",
    "wof:placetype":"venue"
},
  "geometry": {"coordinates":[-76.816242,39.414547],"type":"Point"}
}