{
  "type": "Feature",
  "properties": {
    "addr:full":"5027 Baffin Bay Ln Rockville MD 20853",
    "addr:housenumber":"5027",
    "addr:postcode":"20853",
    "addr:street":"Baffin Bay Ln",
    "iso:country":"US",
    "sg:address":"5027 Baffin Bay Ln",
    "sg:city":"Rockville",
    "sg:classifiers":[
        {
            "category":"Professional",
            "type":"Services"
        }
    ],
    "sg:phone":"+1 301 460 6525",
    "sg:postcode":"20853",
    "sg:province":"MD",
    "wof:name":"Bonnie Gail Scheinker",
    "wof:placetype":"venue"
},
  "geometry": {"coordinates":[-77.103165,39.097079],"type":"Point"}
}