{
  "type": "Feature",
  "properties": {
    "addr:full":"8888 Good Luck Rd Lanham MD 20706",
    "addr:housenumber":"8888",
    "addr:postcode":"20706",
    "addr:street":"Good Luck Rd",
    "iso:country":"US",
    "sg:address":"8888 Good Luck Rd",
    "sg:city":"Lanham",
    "sg:classifiers":[
        {
            "category":"Social Services",
            "subcategory":"Child Care",
            "type":"Services"
        }
    ],
    "sg:phone":"+1 301 552 0007",
    "sg:postcode":"20706",
    "sg:province":"MD",
    "sg:tags":[
        "nursery",
        "day"
    ],
    "wof:name":"Seabrook Adventist Early Learn",
    "wof:placetype":"venue"
},
  "geometry": {"coordinates":[-76.853774,38.978033],"type":"Point"}
}