{
  "type": "Feature",
  "properties": {
    "iso:country":"US",
    "sg:address":"794 Biggs Hwy",
    "sg:city":"Rising Sun",
    "sg:classifiers":[
        {
            "category":"Wholesale",
            "subcategory":"Non-durable Goods",
            "type":"Manufacturing & Wholesale Goods"
        }
    ],
    "sg:phone":"+1 410 658 6707",
    "sg:postcode":"21911",
    "sg:province":"MD",
    "sg:tags":[
        "pet",
        "supply"
    ],
    "sg:website":"www.jemarpet.com",
    "wof:name":"Jemar Pet Supplies",
    "wof:placetype":"venue"
},
  "geometry": {"coordinates":[-76.037355,39.682099],"type":"Point"}
}