{
  "type": "Feature",
  "properties": {
    "addr:full":"830 Bayard Rd Lothian MD 20711",
    "addr:housenumber":"830",
    "addr:postcode":"20711",
    "addr:street":"Bayard Rd",
    "iso:country":"US",
    "sg:address":"830 Bayard Rd",
    "sg:city":"Lothian",
    "sg:classifiers":[
        {
            "category":"Home & Garden",
            "subcategory":"Building Materials",
            "type":"Retail Goods"
        }
    ],
    "sg:phone":"+1 410 741 1547",
    "sg:postcode":"20711",
    "sg:province":"MD",
    "wof:name":"Bayard Sand & Gravel",
    "wof:placetype":"venue"
},
  "geometry": {"coordinates":[-76.664573,38.843758],"type":"Point"}
}