{
  "type": "Feature",
  "properties": {
    "addr:full":"301 Saint Paul St Baltimore MD 21202",
    "addr:housenumber":"301",
    "addr:postcode":"21202",
    "addr:street":"Saint Paul St",
    "iso:country":"US",
    "sg:address":"301 Saint Paul St",
    "sg:city":"Baltimore",
    "sg:classifiers":[
        {
            "category":"Health Services",
            "subcategory":"Doctor",
            "type":"Services"
        }
    ],
    "sg:phone":"+1 410 547 8651",
    "sg:postcode":"21202",
    "sg:province":"MD",
    "wof:name":"Agheb John R MD",
    "wof:placetype":"venue"
},
  "geometry": {"coordinates":[-76.613343,39.292369],"type":"Point"}
}