{
  "type": "Feature",
  "properties": {
    "addr:full":"14644 Wexhall Ter Burtonsville MD 20866",
    "addr:postcode":"14644;20866",
    "addr:street":"Wexhall Ter",
    "iso:country":"US",
    "sg:address":"14644 Wexhall Ter",
    "sg:city":"Burtonsville",
    "sg:classifiers":[
        {
            "category":"Professional",
            "subcategory":"Management & Consulting",
            "type":"Services"
        }
    ],
    "sg:phone":"+1 301 890 3025",
    "sg:postcode":"20866",
    "sg:province":"MD",
    "sg:tags":[
        "work",
        "radio",
        "journalist"
    ],
    "wof:name":"Redko Antonina",
    "wof:placetype":"venue"
},
  "geometry": {"coordinates":[-76.93440099999999,39.098051],"type":"Point"}
}