{
  "type": "Feature",
  "properties": {
    "iso:country":"US",
    "sg:address":"16 Francis St",
    "sg:city":"Annapolis",
    "sg:classifiers":[
        {
            "category":"Government",
            "subcategory":"Office",
            "type":"Public Place"
        }
    ],
    "sg:phone":"+1 410 974 2389",
    "sg:postcode":"21401",
    "sg:province":"MD",
    "sg:tags":[
        "security",
        "homeland"
    ],
    "wof:name":"Governors Office Homeland SEC",
    "wof:placetype":"venue"
},
  "geometry": {"coordinates":[-76.489988,38.978298],"type":"Point"}
}