{
  "type": "Feature",
  "properties": {
    "addr:full":"701 S Division St Salisbury MD 21804",
    "addr:housenumber":"701",
    "addr:postcode":"21804",
    "addr:street":"S Division St",
    "iso:country":"US",
    "sg:address":"701 S Division St",
    "sg:city":"Salisbury",
    "sg:classifiers":[
        {
            "category":"Food & Beverages",
            "subcategory":"Fruits & Vegetables",
            "type":"Retail Goods"
        }
    ],
    "sg:phone":"+1 410 749 5431",
    "sg:postcode":"21804",
    "sg:province":"MD",
    "sg:tags":[
        "produce"
    ],
    "wof:name":"Harris Market",
    "wof:placetype":"venue"
},
  "geometry": {"coordinates":[-75.596161,38.357853],"type":"Point"}
}