{
  "type": "Feature",
  "properties": {
    "addr:full":"727 Frederick Rd Catonsville MD 21228",
    "addr:housenumber":"727",
    "addr:postcode":"21228",
    "addr:street":"Frederick Rd",
    "iso:country":"US",
    "sg:address":"727 Frederick Rd",
    "sg:city":"Catonsville",
    "sg:classifiers":[
        {
            "category":"Shopping",
            "subcategory":"Optician",
            "type":"Retail Goods"
        }
    ],
    "sg:phone":"+1 410 744 1111",
    "sg:postcode":"21228",
    "sg:province":"MD",
    "sg:tags":[
        "eyewear"
    ],
    "wof:name":"Catonsville Optical",
    "wof:placetype":"venue"
},
  "geometry": {"coordinates":[-76.733002,39.271599],"type":"Point"}
}