{
  "type": "Feature",
  "properties": {
    "iso:country":"US",
    "sg:address":"10 Wyndmoor Pl",
    "sg:city":"Gwynn Oak",
    "sg:classifiers":[
        {
            "category":"Professional",
            "subcategory":"Research",
            "type":"Services"
        }
    ],
    "sg:phone":"+1 410 265 6213",
    "sg:postcode":"21207",
    "sg:province":"MD",
    "sg:tags":[
        "development",
        "marketing",
        "product"
    ],
    "wof:name":"J & D Distributors",
    "wof:placetype":"venue"
},
  "geometry": {"coordinates":[-76.729403,39.331656],"type":"Point"}
}