{
  "type": "Feature",
  "properties": {
    "iso:country":"US",
    "sg:address":"4629 Benson Ave",
    "sg:city":"Halethorpe",
    "sg:classifiers":[
        {
            "category":"Personal",
            "type":"Services"
        },
        {
            "category":"Arena",
            "subcategory":"Sports Club",
            "type":"Entertainment"
        }
    ],
    "sg:phone":"+1 410 536 7612",
    "sg:postcode":"21227",
    "sg:province":"MD",
    "sg:tags":[
        "trainer",
        "consultant",
        "health",
        "fitness",
        "physical"
    ],
    "wof:name":"Xpose Fitness Inc",
    "wof:placetype":"venue"
},
  "geometry": {"coordinates":[-76.684674,39.257397],"type":"Point"}
}