{
  "type": "Feature",
  "properties": {
    "addr:full":"5141 Bowers Rd Taneytown MD 21787",
    "addr:housenumber":"5141",
    "addr:postcode":"21787",
    "addr:street":"Bowers Rd",
    "iso:country":"US",
    "sg:address":"5141 Bowers Rd",
    "sg:city":"Taneytown",
    "sg:classifiers":[
        {
            "category":"Real Estate",
            "subcategory":"Real Estate Agent",
            "type":"Services"
        }
    ],
    "sg:phone":"+1 410 526 0277",
    "sg:postcode":"21787",
    "sg:province":"MD",
    "wof:name":"Property Investors",
    "wof:placetype":"venue"
},
  "geometry": {"coordinates":[-77.174532,39.702313],"type":"Point"}
}