{
  "type": "Feature",
  "properties": {
    "addr:full":"3420 Hampton Hollow Dr Silver Spring MD 20904",
    "addr:housenumber":"3420",
    "addr:postcode":"20904",
    "addr:street":"Hampton Hollow Dr",
    "iso:country":"US",
    "sg:address":"3420 Hampton Hollow Dr",
    "sg:city":"Silver Spring",
    "sg:classifiers":[
        {
            "category":"Utilities",
            "subcategory":"Telephone",
            "type":"Services"
        }
    ],
    "sg:phone":"+1 301 562 8209",
    "sg:postcode":"20904",
    "sg:province":"MD",
    "sg:tags":[
        "intelligence",
        "e"
    ],
    "wof:name":"Mahendra & Mahendra",
    "wof:placetype":"venue"
},
  "geometry": {"coordinates":[-76.940049,39.076051],"type":"Point"}
}