{
  "type": "Feature",
  "properties": {
    "iso:country":"US",
    "sg:address":"3855 Greenspring Ave",
    "sg:city":"Baltimore",
    "sg:classifiers":[
        {
            "category":"Social Services",
            "subcategory":"Adult Care",
            "type":"Services"
        }
    ],
    "sg:phone":"+1 410 225 9337",
    "sg:postcode":"21211",
    "sg:province":"MD",
    "sg:tags":[
        "home",
        "residential"
    ],
    "sg:website":"www.emeritus.com",
    "wof:name":"Emerald Estates",
    "wof:placetype":"venue"
},
  "geometry": {"coordinates":[-76.656167,39.335508],"type":"Point"}
}