{
  "type": "Feature",
  "properties": {
    "iso:country":"US",
    "sg:address":"5523 Silverbell Rd",
    "sg:city":"Baltimore",
    "sg:classifiers":[
        {
            "category":"Professional",
            "subcategory":"Detective & Security Services",
            "type":"Services"
        }
    ],
    "sg:phone":"+1 410 325 7484",
    "sg:postcode":"21206",
    "sg:province":"MD",
    "sg:tags":[
        "control",
        "monitoring",
        "system"
    ],
    "wof:name":"Taylor Rogers Enterprises",
    "wof:placetype":"venue"
},
  "geometry": {"coordinates":[-76.532049,39.334552],"type":"Point"}
}