{
  "type": "Feature",
  "properties": {
    "iso:country":"US",
    "sg:address":"1001 Rockville Pike",
    "sg:city":"Rockville",
    "sg:classifiers":[
        {
            "category":"Health Services",
            "subcategory":"Medical Lab",
            "type":"Services"
        }
    ],
    "sg:phone":"+1 301 610 6098",
    "sg:postcode":"20852",
    "sg:province":"MD",
    "sg:tags":[
        "laboratory"
    ],
    "wof:name":"Zhong Nianxin",
    "wof:placetype":"venue"
},
  "geometry": {"coordinates":[-77.132125,39.071022],"type":"Point"}
}