{
  "type": "Feature",
  "properties": {
    "addr:full":"863 Clover Leaf Ct Edgewood MD 21040",
    "addr:housenumber":"863",
    "addr:postcode":"21040",
    "addr:street":"Clover Leaf Ct",
    "iso:country":"US",
    "sg:address":"863 Clover Leaf Ct",
    "sg:city":"Edgewood",
    "sg:classifiers":[
        {
            "category":"Home & Garden",
            "subcategory":"Hardware",
            "type":"Retail Goods"
        }
    ],
    "sg:phone":"+1 410 299 4907",
    "sg:postcode":"21040",
    "sg:province":"MD",
    "wof:name":"Jt Tools",
    "wof:placetype":"venue"
},
  "geometry": {"coordinates":[-76.328334,39.427289],"type":"Point"}
}