{
  "type": "Feature",
  "properties": {
    "iso:country":"US",
    "sg:address":"517 Benfield Rd",
    "sg:city":"Severna Park",
    "sg:classifiers":[
        {
            "category":"Professional",
            "subcategory":"Accounting & Tax Preparation",
            "type":"Services"
        }
    ],
    "sg:phone":"+1 410 544 2988",
    "sg:postcode":"21146",
    "sg:province":"MD",
    "sg:tags":[
        "accountant"
    ],
    "wof:name":"Gordon & Assoc",
    "wof:placetype":"venue"
},
  "geometry": {"coordinates":[-76.577055,39.079388],"type":"Point"}
}