{
  "type": "Feature",
  "properties": {
    "addr:full":"356 Domer Ave Laurel MD 20707",
    "addr:housenumber":"356",
    "addr:postcode":"20707",
    "addr:street":"Domer Ave",
    "iso:country":"US",
    "sg:address":"356 Domer Ave",
    "sg:city":"Laurel",
    "sg:classifiers":[
        {
            "category":"Personal",
            "subcategory":"Barber",
            "type":"Services"
        }
    ],
    "sg:phone":"+1 301 317 9111",
    "sg:postcode":"20707",
    "sg:province":"MD",
    "wof:name":"Bart's Full Service Barber Shop",
    "wof:placetype":"venue"
},
  "geometry": {"coordinates":[-76.854401,39.095299],"type":"Point"}
}