{
  "type": "Feature",
  "properties": {
    "addr:full":"7715 Garrison Rd Hyattsville MD 20784",
    "addr:housenumber":"7715",
    "addr:postcode":"20784",
    "addr:street":"Garrison Rd",
    "iso:country":"US",
    "sg:address":"7715 Garrison Rd",
    "sg:city":"Hyattsville",
    "sg:classifiers":[
        {
            "category":"Building & Trades",
            "subcategory":"Construction",
            "type":"Services"
        }
    ],
    "sg:phone":"+1 301 459 7836",
    "sg:postcode":"20784",
    "sg:province":"MD",
    "sg:tags":[
        "house"
    ],
    "wof:name":"Cunninghams Home",
    "wof:placetype":"venue"
},
  "geometry": {"coordinates":[-76.87852100000001,38.950673],"type":"Point"}
}