{
  "type": "Feature",
  "properties": {
    "addr:full":"1113 Dorsey Rd Glen Burnie MD 21061",
    "addr:housenumber":"1113",
    "addr:postcode":"21061",
    "addr:street":"Dorsey Rd",
    "iso:country":"US",
    "sg:address":"1113 Dorsey Rd",
    "sg:city":"Glen Burnie",
    "sg:classifiers":[
        {
            "category":"Local Transit",
            "type":"Transportation"
        }
    ],
    "sg:phone":"+1 410 269 9000",
    "sg:postcode":"21061",
    "sg:province":"MD",
    "sg:tags":[
        "limousine"
    ],
    "sg:website":"www.bigcars.com",
    "wof:name":"NAN Extraordinare",
    "wof:placetype":"venue"
},
  "geometry": {"coordinates":[-76.654113,39.163812],"type":"Point"}
}