{
  "type": "Feature",
  "properties": {
    "addr:full":"10320 Inwood Ave Silver Spring MD 20902",
    "addr:housenumber":"10320",
    "addr:postcode":"20902",
    "addr:street":"Inwood Ave",
    "iso:country":"US",
    "sg:address":"10320 Inwood Ave",
    "sg:city":"Silver Spring",
    "sg:classifiers":[
        {
            "category":"Building & Trades",
            "subcategory":"Cleaning & Sanitation",
            "type":"Services"
        }
    ],
    "sg:phone":"+1 301 649 6500",
    "sg:postcode":"20902",
    "sg:province":"MD",
    "sg:tags":[
        "window"
    ],
    "wof:name":"Abel Cleaning Svc Inc",
    "wof:placetype":"venue"
},
  "geometry": {"coordinates":[-77.03548600000001,39.025704],"type":"Point"}
}