{
  "type": "Feature",
  "properties": {
    "addr:full":"2476 Solomons Island Rd Annapolis MD 21401",
    "addr:housenumber":"2476",
    "addr:postcode":"21401",
    "addr:street":"Solomons Island Rd",
    "iso:country":"US",
    "sg:address":"2476 Solomons Island Rd",
    "sg:city":"Annapolis",
    "sg:classifiers":[
        {
            "category":"Autos & Motor Vehicles",
            "subcategory":"Boat Sales",
            "type":"Retail Goods"
        }
    ],
    "sg:phone":"+1 410 266 7766",
    "sg:postcode":"21401",
    "sg:province":"MD",
    "sg:tags":[
        "equipment",
        "supply"
    ],
    "sg:website":"www.boatersworld.com",
    "wof:name":"Boater's World Marine Ctr",
    "wof:placetype":"venue"
},
  "geometry": {"coordinates":[-76.54262199999999,38.971976],"type":"Point"}
}