{
  "type": "Feature",
  "properties": {
    "iso:country":"US",
    "sg:address":"1111 Park Ave Ph",
    "sg:city":"Baltimore",
    "sg:classifiers":[
        {
            "category":"Professional",
            "subcategory":"Lawyer & Legal Services",
            "type":"Services"
        }
    ],
    "sg:phone":"+1 410 523 1115",
    "sg:postcode":"21201",
    "sg:province":"MD",
    "wof:name":"Edward T Pinder Llc",
    "wof:placetype":"venue"
},
  "geometry": {"coordinates":[-76.61990400000001,39.304199],"type":"Point"}
}