{
  "type": "Feature",
  "properties": {
    "iso:country":"US",
    "sg:address":"6201 Ford Rd",
    "sg:city":"Frederick",
    "sg:classifiers":[
        {
            "category":"Professional",
            "subcategory":"Lawyer & Legal Services",
            "type":"Services"
        },
        {
            "category":"Retail",
            "subcategory":"Animal Services",
            "type":"Services"
        }
    ],
    "sg:phone":"+1 301 663 0135",
    "sg:postcode":"21702",
    "sg:province":"MD",
    "sg:tags":[
        "attorney"
    ],
    "wof:name":"Stone Manor Kennels",
    "wof:placetype":"venue"
},
  "geometry": {"coordinates":[-77.450267,39.486439],"type":"Point"}
}