{
  "type": "Feature",
  "properties": {
    "addr:full":"5514 Harford Rd Baltimore MD 21214",
    "addr:housenumber":"5514",
    "addr:postcode":"21214",
    "addr:street":"Harford Rd",
    "iso:country":"US",
    "sg:address":"5514 Harford Rd",
    "sg:city":"Baltimore",
    "sg:classifiers":[
        {
            "category":"Personal",
            "subcategory":"Barber",
            "type":"Services"
        }
    ],
    "sg:phone":"+1 410 444 1600",
    "sg:postcode":"21214",
    "sg:province":"MD",
    "wof:name":"New Faces Unisex",
    "wof:placetype":"venue"
},
  "geometry": {"coordinates":[-76.560799,39.352901],"type":"Point"}
}