{
  "type": "Feature",
  "properties": {
    "addr:full":"400 E Pulaski Hwy Elkton MD 21921",
    "addr:housenumber":"400",
    "addr:postcode":"21921",
    "addr:street":"E Pulaski Hwy",
    "iso:country":"US",
    "sg:address":"400 E Pulaski Hwy",
    "sg:city":"Elkton",
    "sg:classifiers":[
        {
            "category":"Shopping",
            "subcategory":"Florist",
            "type":"Retail Goods"
        }
    ],
    "sg:phone":"+1 410 398 9088",
    "sg:postcode":"21921",
    "sg:province":"MD",
    "sg:website":"www.fairhillflorist.com",
    "wof:name":"Fair Hill Florist",
    "wof:placetype":"venue"
},
  "geometry": {"coordinates":[-75.815826,39.597994],"type":"Point"}
}