{
  "type": "Feature",
  "properties": {
    "addr:full":"313 Buschs Frontage Rd Annapolis MD 21409",
    "addr:housenumber":"313",
    "addr:postcode":"21409",
    "addr:street":"Buschs Frontage Rd",
    "iso:country":"US",
    "sg:address":"313 Buschs Frontage Rd",
    "sg:city":"Annapolis",
    "sg:classifiers":[
        {
            "category":"Autos & Motor Vehicles",
            "subcategory":"Automobile Sales",
            "type":"Retail Goods"
        }
    ],
    "sg:phone":"+1 410 757 4400",
    "sg:postcode":"21409",
    "sg:province":"MD",
    "sg:tags":[
        "car",
        "used",
        "dealer"
    ],
    "wof:name":"Annapolis Used Cars Inc",
    "wof:placetype":"venue"
},
  "geometry": {"coordinates":[-76.452682,39.026825],"type":"Point"}
}