{
  "type": "Feature",
  "properties": {
    "addr:full":"40 Greenknoll Blvd Hanover MD 21076",
    "addr:housenumber":"40",
    "addr:postcode":"21076",
    "addr:street":"Greenknoll Blvd",
    "iso:country":"US",
    "sg:address":"40 Greenknoll Blvd",
    "sg:city":"Hanover",
    "sg:classifiers":[
        {
            "category":"Professional",
            "subcategory":"Business Services",
            "type":"Services"
        }
    ],
    "sg:phone":"+1 410 761 0328",
    "sg:postcode":"21076",
    "sg:province":"MD",
    "wof:name":"Finkin Young",
    "wof:placetype":"venue"
},
  "geometry": {"coordinates":[-76.705455,39.153109],"type":"Point"}
}