{
  "type": "Feature",
  "properties": {
    "iso:country":"US",
    "sg:address":"4185 Knowles Ave",
    "sg:city":"Kensington",
    "sg:classifiers":[
        {
            "category":"Building & Trades",
            "subcategory":"Locksmith",
            "type":"Services"
        }
    ],
    "sg:phone":"+1 202 621 2341",
    "sg:postcode":"20895",
    "sg:province":"MD",
    "sg:tags":[
        "key"
    ],
    "wof:name":"Existing Locksmith",
    "wof:placetype":"venue"
},
  "geometry": {"coordinates":[-77.081233,39.028748],"type":"Point"}
}