{
  "type": "Feature",
  "properties": {
    "iso:country":"US",
    "sg:address":"5515 Jefferson Pike",
    "sg:city":"Frederick",
    "sg:classifiers":[
        {
            "category":"Building & Trades",
            "subcategory":"Electrical",
            "type":"Services"
        }
    ],
    "sg:phone":"+1 301 695 4400",
    "sg:postcode":"21703",
    "sg:province":"MD",
    "sg:tags":[
        "electric",
        "contractor"
    ],
    "wof:name":"Noah Electric",
    "wof:placetype":"venue"
},
  "geometry": {"coordinates":[-77.47533,39.385956],"type":"Point"}
}