{
  "type": "Feature",
  "properties": {
    "iso:country":"US",
    "sg:address":"9143 Red Branch Rd",
    "sg:city":"Columbia",
    "sg:classifiers":[
        {
            "category":"Shopping",
            "subcategory":"Florist",
            "type":"Retail Goods"
        }
    ],
    "sg:phone":"+1 410 730 0097",
    "sg:postcode":"21045",
    "sg:province":"MD",
    "wof:name":"Columbia Flower Mart",
    "wof:placetype":"venue"
},
  "geometry": {"coordinates":[-76.821643,39.230906],"type":"Point"}
}