{
  "type": "Feature",
  "properties": {
    "addr:full":"363 Hawick Ct Severna Park MD 21146",
    "addr:housenumber":"363",
    "addr:postcode":"21146",
    "addr:street":"Hawick Ct",
    "iso:country":"US",
    "sg:address":"363 Hawick Ct",
    "sg:city":"Severna Park",
    "sg:classifiers":[
        {
            "category":"Professional",
            "subcategory":"Engineering",
            "type":"Services"
        }
    ],
    "sg:phone":"+1 410 987 7835",
    "sg:postcode":"21146",
    "sg:province":"MD",
    "sg:tags":[
        "communication",
        "product",
        "design",
        "navigation"
    ],
    "wof:name":"Cns Systems Inc",
    "wof:placetype":"venue"
},
  "geometry": {"coordinates":[-76.604224,39.09118],"type":"Point"}
}