{
  "type": "Feature",
  "properties": {
    "iso:country":"US",
    "sg:address":"5032 Mangum Rd",
    "sg:city":"College Park",
    "sg:classifiers":[
        {
            "category":"Building & Trades",
            "subcategory":"Construction",
            "type":"Services"
        }
    ],
    "sg:phone":"+1 301 455 6026",
    "sg:postcode":"20740",
    "sg:province":"MD",
    "sg:tags":[
        "hanging",
        "contractor"
    ],
    "wof:name":"Tahlamburis Painting",
    "wof:placetype":"venue"
},
  "geometry": {"coordinates":[-76.917665,39.014747],"type":"Point"}
}