{
  "type": "Feature",
  "properties": {
    "addr:full":"432 Manor Rd Arnold MD 21012",
    "addr:housenumber":"432",
    "addr:postcode":"21012",
    "addr:street":"Manor Rd",
    "iso:country":"US",
    "sg:address":"432 Manor Rd",
    "sg:city":"Arnold",
    "sg:classifiers":[
        {
            "category":"Retail",
            "subcategory":"Repair Shop",
            "type":"Services"
        }
    ],
    "sg:phone":"+1 410 647 0068",
    "sg:postcode":"21012",
    "sg:province":"MD",
    "sg:tags":[
        "refrigerator",
        "freezer"
    ],
    "wof:name":"Chesapeake Refrigeration Inc",
    "wof:placetype":"venue"
},
  "geometry": {"coordinates":[-76.50199499999999,39.066261],"type":"Point"}
}