{
  "type": "Feature",
  "properties": {
    "iso:country":"US",
    "sg:address":"410 Park Ave",
    "sg:city":"Baltimore",
    "sg:classifiers":[
        {
            "category":"Manufacturing",
            "subcategory":"Retail Goods",
            "type":"Manufacturing & Wholesale Goods"
        }
    ],
    "sg:phone":"+1 410 625 2659",
    "sg:postcode":"21201",
    "sg:province":"MD",
    "sg:tags":[
        "giftware's-wholesale",
        "manufacturer"
    ],
    "wof:name":"Chin H Liu",
    "wof:placetype":"venue"
},
  "geometry": {"coordinates":[-76.618202,39.294498],"type":"Point"}
}