{
  "type": "Feature",
  "properties": {
    "iso:country":"US",
    "sg:address":"532 E Church St",
    "sg:city":"Frederick",
    "sg:classifiers":[
        {
            "category":"Building & Trades",
            "subcategory":"Plumbing",
            "type":"Services"
        }
    ],
    "sg:phone":"+1 301 663 4417",
    "sg:postcode":"21701",
    "sg:province":"MD",
    "sg:tags":[
        "plumbing",
        "contractor"
    ],
    "wof:name":"Glenn E Waltz Plumbing & Heat",
    "wof:placetype":"venue"
},
  "geometry": {"coordinates":[-77.400548,39.417339],"type":"Point"}
}