{
  "type": "Feature",
  "properties": {
    "addr:full":"11830 Bethesda Church Rd Damascus MD 20872",
    "addr:housenumber":"11830",
    "addr:postcode":"20872",
    "addr:street":"Bethesda Church Rd",
    "iso:country":"US",
    "sg:address":"11830 Bethesda Church Rd",
    "sg:city":"Damascus",
    "sg:classifiers":[
        {
            "category":"Personal",
            "type":"Services"
        }
    ],
    "sg:phone":"+1 301 428 7283",
    "sg:postcode":"20872",
    "sg:province":"MD",
    "sg:tags":[
        "miscellaneous"
    ],
    "wof:name":"Ronald Turner",
    "wof:placetype":"venue"
},
  "geometry": {"coordinates":[-77.245672,39.31121],"type":"Point"}
}