{
  "type": "Feature",
  "properties": {
    "iso:country":"US",
    "sg:address":"4111 Raymonn Ave",
    "sg:city":"Baltimore",
    "sg:classifiers":[
        {
            "category":"Professional",
            "subcategory":"Business Services",
            "type":"Services"
        }
    ],
    "sg:phone":"+1 202 293 3328",
    "sg:postcode":"21213",
    "sg:province":"MD",
    "wof:name":"E & S Management",
    "wof:placetype":"venue"
},
  "geometry": {"coordinates":[-76.557779,39.317026],"type":"Point"}
}