{
  "type": "Feature",
  "properties": {
    "iso:country":"US",
    "sg:address":"4147 Hayward Ave",
    "sg:city":"Baltimore",
    "sg:classifiers":[
        {
            "category":"Shopping",
            "subcategory":"Stationery & Office Supplies",
            "type":"Retail Goods"
        }
    ],
    "sg:phone":"+1 410 664 6226",
    "sg:postcode":"21215",
    "sg:province":"MD",
    "sg:tags":[
        "equipment"
    ],
    "wof:name":"Sue-Ann's Office Supply Inc",
    "wof:placetype":"venue"
},
  "geometry": {"coordinates":[-76.688599,39.343601],"type":"Point"}
}