{
  "type": "Feature",
  "properties": {
    "iso:country":"US",
    "sg:address":"307 Cross Green St",
    "sg:city":"Gaithersburg",
    "sg:classifiers":[
        {
            "category":"Professional",
            "subcategory":"Management & Consulting",
            "type":"Services"
        }
    ],
    "sg:phone":"+1 517 204 8905",
    "sg:postcode":"20878",
    "sg:province":"MD",
    "sg:tags":[
        "development",
        "creation",
        "system"
    ],
    "wof:name":"Kane and Kane Enterprises LLC",
    "wof:placetype":"venue"
},
  "geometry": {"coordinates":[-77.232816,39.120425],"type":"Point"}
}