{
  "type": "Feature",
  "properties": {
    "addr:full":"1122 Baldwin Mill Rd Jarrettsville MD 21084",
    "addr:housenumber":"1122",
    "addr:postcode":"21084",
    "addr:street":"Baldwin Mill Rd",
    "iso:country":"US",
    "sg:address":"1122 Baldwin Mill Rd",
    "sg:city":"Jarrettsville",
    "sg:classifiers":[
        {
            "category":"Building & Trades",
            "subcategory":"Construction",
            "type":"Services"
        }
    ],
    "sg:phone":"+1 410 557 6653",
    "sg:postcode":"21084",
    "sg:province":"MD",
    "sg:tags":[
        "home",
        "builder",
        "custom"
    ],
    "wof:name":"Woods Construction Co Inc",
    "wof:placetype":"venue"
},
  "geometry": {"coordinates":[-76.477729,39.601831],"type":"Point"}
}