{
  "type": "Feature",
  "properties": {
    "addr:full":"10319 Grandhaven Ave Upper Marlboro MD 20772",
    "addr:postcode":"10319;20772",
    "addr:street":"Grandhaven Ave",
    "iso:country":"US",
    "sg:address":"10319 Grandhaven Ave",
    "sg:city":"Upper Marlboro",
    "sg:classifiers":[
        {
            "category":"Restaurant",
            "type":"Food & Drink"
        }
    ],
    "sg:phone":"+1 301 627 6844",
    "sg:postcode":"20772",
    "sg:province":"MD",
    "sg:tags":[
        "caterer"
    ],
    "wof:name":"Ccs Delights Catering",
    "wof:placetype":"venue"
},
  "geometry": {"coordinates":[-76.78552500000001,38.748626],"type":"Point"}
}