{
  "type": "Feature",
  "properties": {
    "addr:full":"300 Huntersview Ln Centreville MD 21617",
    "addr:housenumber":"300",
    "addr:postcode":"21617",
    "addr:street":"Huntersview Ln",
    "iso:country":"US",
    "sg:address":"300 Huntersview Ln",
    "sg:city":"Centreville",
    "sg:classifiers":[
        {
            "category":"Building & Trades",
            "subcategory":"Electrical",
            "type":"Services"
        }
    ],
    "sg:phone":"+1 410 758 3781",
    "sg:postcode":"21617",
    "sg:province":"MD",
    "sg:tags":[
        "electrical",
        "contractor"
    ],
    "wof:name":"Cw Electric",
    "wof:placetype":"venue"
},
  "geometry": {"coordinates":[-76.11658199999999,39.049836],"type":"Point"}
}