{
  "type": "Feature",
  "properties": {
    "addr:full":"5309 East Dr Halethorpe MD 21227",
    "addr:housenumber":"5309",
    "addr:postcode":"21227",
    "addr:street":"East Dr",
    "iso:country":"US",
    "sg:address":"5309 East Dr",
    "sg:city":"Halethorpe",
    "sg:classifiers":[
        {
            "category":"Restaurant",
            "type":"Food & Drink"
        }
    ],
    "sg:phone":"+1 410 247 2274",
    "sg:postcode":"21227",
    "sg:province":"MD",
    "wof:name":"Leon's Triple L Restaurant",
    "wof:placetype":"venue"
},
  "geometry": {"coordinates":[-76.693398,39.249901],"type":"Point"}
}