{
  "type": "Feature",
  "properties": {
    "iso:country":"US",
    "sg:address":"4760 Clifton Rd",
    "sg:city":"Temple Hills",
    "sg:classifiers":[
        {
            "category":"Retail",
            "subcategory":"Auto Repair",
            "type":"Services"
        }
    ],
    "sg:phone":"+1 301 899 3131",
    "sg:postcode":"20748",
    "sg:province":"MD",
    "sg:tags":[
        "body",
        "shop"
    ],
    "wof:name":"Maaco Enterprises Inc",
    "wof:placetype":"venue"
},
  "geometry": {"coordinates":[-76.94380200000001,38.824799],"type":"Point"}
}