{
  "type": "Feature",
  "properties": {
    "iso:country":"US",
    "sg:address":"1107 Knopp Rd",
    "sg:city":"Jarrettsville",
    "sg:classifiers":[
        {
            "category":"Building & Trades",
            "subcategory":"Plumbing",
            "type":"Services"
        }
    ],
    "sg:phone":"+1 410 557 8033",
    "sg:postcode":"21084",
    "sg:province":"MD",
    "sg:tags":[
        "plumbing",
        "contractor"
    ],
    "wof:name":"Bill's Plumbing & Heating",
    "wof:placetype":"venue"
},
  "geometry": {"coordinates":[-76.420535,39.629305],"type":"Point"}
}