{
  "type": "Feature",
  "properties": {
    "addr:full":"5118 Meadow Creek Ter Ellicott City MD 21043",
    "addr:housenumber":"5118",
    "addr:postcode":"21043",
    "addr:street":"Meadow Creek Ter",
    "iso:country":"US",
    "sg:address":"5118 Meadow Creek Ter",
    "sg:city":"Ellicott City",
    "sg:classifiers":[
        {
            "category":"Professional",
            "subcategory":"Computer Services",
            "type":"Services"
        }
    ],
    "sg:phone":"+1 410 203 1613",
    "sg:postcode":"21043",
    "sg:province":"MD",
    "sg:tags":[
        "datum"
    ],
    "wof:name":"Patrick Gillespie",
    "wof:placetype":"venue"
},
  "geometry": {"coordinates":[-76.79771700000001,39.231346],"type":"Point"}
}