{
  "type": "Feature",
  "properties": {
    "addr:full":"501 Watkins Park Dr Upper Marlboro MD 20774",
    "addr:housenumber":"501",
    "addr:postcode":"20774",
    "addr:street":"Watkins Park Dr",
    "iso:country":"US",
    "sg:address":"501 Watkins Park Dr",
    "sg:city":"Upper Marlboro",
    "sg:classifiers":[
        {
            "category":"Education",
            "subcategory":"School",
            "type":"Public Place"
        }
    ],
    "sg:phone":"+1 301 218 3040",
    "sg:postcode":"20774",
    "sg:province":"MD",
    "sg:website":"www.pgcps.org",
    "wof:name":"Perrywood Elementary School",
    "wof:placetype":"venue"
},
  "geometry": {"coordinates":[-76.780612,38.881073],"type":"Point"}
}