{
  "type": "Feature",
  "properties": {
    "iso:country":"US",
    "sg:address":"2637 Brandermill Blvd",
    "sg:city":"Gambrills",
    "sg:classifiers":[
        {
            "category":"Banks & Credit Unions",
            "subcategory":"Bank",
            "type":"Services"
        }
    ],
    "sg:phone":"+1 410 451 0220",
    "sg:postcode":"21054",
    "sg:province":"MD",
    "wof:name":"M & T Bank",
    "wof:placetype":"venue"
},
  "geometry": {"coordinates":[-76.679068,39.037946],"type":"Point"}
}