{
  "type": "Feature",
  "properties": {
    "iso:country":"US",
    "sg:address":"4201 Northview Dr",
    "sg:city":"Bowie",
    "sg:classifiers":[
        {
            "category":"Professional",
            "subcategory":"Lawyer & Legal Services",
            "type":"Services"
        }
    ],
    "sg:phone":"+1 301 262 7422",
    "sg:postcode":"20716",
    "sg:province":"MD",
    "sg:tags":[
        "attorney"
    ],
    "wof:name":"Costello & Mc Carthy",
    "wof:placetype":"venue"
},
  "geometry": {"coordinates":[-76.737313,38.947495],"type":"Point"}
}