{
  "type": "Feature",
  "properties": {
    "addr:full":"22 W Padonia Rd Ste C110 Lutherville Timonium MD 21093",
    "addr:housenumber":"22",
    "addr:postcode":"21093",
    "addr:street":"W Padonia Rd Ste C110",
    "iso:country":"US",
    "sg:address":"22 W Padonia Rd Ste C110",
    "sg:city":"Lutherville Timonium",
    "sg:classifiers":[
        {
            "category":"Restaurant",
            "type":"Food & Drink"
        }
    ],
    "sg:phone":"+1 410 560 0905",
    "sg:postcode":"21093",
    "sg:province":"MD",
    "sg:tags":[
        "steakhouse"
    ],
    "wof:name":"Rib N Reef",
    "wof:placetype":"venue"
},
  "geometry": {"coordinates":[-76.63419,39.456014],"type":"Point"}
}