{
  "type": "Feature",
  "properties": {
    "iso:country":"US",
    "sg:address":"5411 Southern Maryland Blvd",
    "sg:city":"Lothian",
    "sg:classifiers":[
        {
            "category":"Professional",
            "subcategory":"Detective & Security Services",
            "type":"Services"
        }
    ],
    "sg:phone":"+1 410 741 0654",
    "sg:postcode":"20711",
    "sg:province":"MD",
    "sg:tags":[
        "control",
        "monitoring",
        "system"
    ],
    "wof:name":"United Security & Communications Inc",
    "wof:placetype":"venue"
},
  "geometry": {"coordinates":[-76.70080299999999,38.810998],"type":"Point"}
}