{
  "type": "Feature",
  "properties": {
    "addr:full":"843 W 36th St Baltimore MD 21211",
    "addr:housenumber":"843",
    "addr:postcode":"21211",
    "addr:street":"W 36Th St",
    "iso:country":"US",
    "sg:address":"843 W 36th St",
    "sg:city":"Baltimore",
    "sg:classifiers":[
        {
            "category":"Professional",
            "subcategory":"Advertising",
            "type":"Services"
        }
    ],
    "sg:phone":"+1 410 771 4441",
    "sg:postcode":"21211",
    "sg:province":"MD",
    "wof:name":"Wall To Wall Indoor Advg",
    "wof:placetype":"venue"
},
  "geometry": {"coordinates":[-76.630903,39.331114],"type":"Point"}
}