{
  "type": "Feature",
  "properties": {
    "iso:country":"US",
    "sg:address":"3000 Chestnut Ave",
    "sg:city":"Baltimore",
    "sg:classifiers":[
        {
            "category":"Communications",
            "subcategory":"Film & Video Production",
            "type":"Services"
        }
    ],
    "sg:phone":"+1 410 467 3570",
    "sg:postcode":"21211",
    "sg:province":"MD",
    "sg:tags":[
        "taping"
    ],
    "wof:name":"Stonebridge Communications Inc",
    "wof:placetype":"venue"
},
  "geometry": {"coordinates":[-76.629339,39.324748],"type":"Point"}
}