{
  "type": "Feature",
  "properties": {
    "addr:full":"2819 Ruscombe Ln Baltimore MD 21215",
    "addr:housenumber":"2819",
    "addr:postcode":"21215",
    "addr:street":"Ruscombe Ln",
    "iso:country":"US",
    "sg:address":"2819 Ruscombe Ln",
    "sg:city":"Baltimore",
    "sg:classifiers":[
        {
            "category":"Organizations",
            "subcategory":"Professional Association",
            "type":"Services"
        }
    ],
    "sg:phone":"+1 410 466 2355",
    "sg:postcode":"21215",
    "sg:province":"MD",
    "sg:tags":[
        "sale"
    ],
    "wof:name":"Tm Suma",
    "wof:placetype":"venue"
},
  "geometry": {"coordinates":[-76.66447599999999,39.348168],"type":"Point"}
}