{
  "type": "Feature",
  "properties": {
    "iso:country":"US",
    "sg:address":"6628 Harford Rd",
    "sg:city":"Baltimore",
    "sg:classifiers":[
        {
            "category":"Shopping",
            "subcategory":"Pawn Shop",
            "type":"Retail Goods"
        }
    ],
    "sg:phone":"+1 410 426 2274",
    "sg:postcode":"21214",
    "sg:province":"MD",
    "wof:name":"Harford Exchange Llc",
    "wof:placetype":"venue"
},
  "geometry": {"coordinates":[-76.552639,39.362743],"type":"Point"}
}