{
  "type": "Feature",
  "properties": {
    "iso:country":"US",
    "sg:address":"804 Janice Dr",
    "sg:city":"Annapolis",
    "sg:classifiers":[
        {
            "category":"Retail",
            "subcategory":"Laundry & Dry Cleaning",
            "type":"Services"
        },
        {
            "category":"Building & Trades",
            "subcategory":"Cleaning & Sanitation",
            "type":"Services"
        }
    ],
    "sg:phone":"+1 410 263 9750",
    "sg:postcode":"21403",
    "sg:province":"MD",
    "sg:tags":[
        "cleaner",
        "house"
    ],
    "sg:website":"http://www.cleanadv.com",
    "wof:name":"Clean Advantage Corp",
    "wof:placetype":"venue"
},
  "geometry": {"coordinates":[-76.48766500000001,38.957234],"type":"Point"}
}