{
  "type": "Feature",
  "properties": {
    "iso:country":"US",
    "sg:address":"12317 Winchester Rd SW",
    "sg:city":"Cumberland",
    "sg:classifiers":[
        {
            "category":"Home & Garden",
            "subcategory":"Garden Supply",
            "type":"Retail Goods"
        }
    ],
    "sg:phone":"+1 301 729 1700",
    "sg:postcode":"21502",
    "sg:province":"MD",
    "sg:tags":[
        "lawn",
        "mower"
    ],
    "wof:name":"Maple Mountain Industries",
    "wof:placetype":"venue"
},
  "geometry": {"coordinates":[-78.838751,39.627956],"type":"Point"}
}