{
  "type": "Feature",
  "properties": {
    "iso:country":"US",
    "sg:address":"9021 Woodyard Rd",
    "sg:city":"Clinton",
    "sg:classifiers":[
        {
            "category":"Restaurant",
            "type":"Food & Drink"
        }
    ],
    "sg:phone":"+1 301 599 0011",
    "sg:postcode":"20735",
    "sg:province":"MD",
    "sg:website":"http://www.hogsbythelake.com",
    "wof:name":"Hogs On The Hill",
    "wof:placetype":"venue"
},
  "geometry": {"coordinates":[-76.89624000000001,38.76582],"type":"Point"}
}