{
  "type": "Feature",
  "properties": {
    "addr:full":"2601 Medical Hall Rd W Bel Air MD 21015",
    "addr:housenumber":"2601",
    "addr:postcode":"21015",
    "addr:street":"Medical Hall Rd W",
    "iso:country":"US",
    "sg:address":"2601 Medical Hall Rd W",
    "sg:city":"Bel Air",
    "sg:classifiers":[
        {
            "category":"Building & Trades",
            "subcategory":"Landscaping Services",
            "type":"Services"
        }
    ],
    "sg:phone":"+1 410 836 5296",
    "sg:postcode":"21015",
    "sg:province":"MD",
    "wof:name":"Natural Art Landscaping",
    "wof:placetype":"venue"
},
  "geometry": {"coordinates":[-76.273993,39.57363],"type":"Point"}
}