{
  "type": "Feature",
  "properties": {
    "iso:country":"US",
    "sg:address":"7505 Greenway Center Dr",
    "sg:city":"Greenbelt",
    "sg:classifiers":[
        {
            "category":"Health Services",
            "subcategory":"Doctor",
            "type":"Services"
        }
    ],
    "sg:phone":"+1 301 220 3515",
    "sg:postcode":"20770",
    "sg:province":"MD",
    "sg:tags":[
        "physician",
        "surgeon"
    ],
    "wof:name":"Radiation Management",
    "wof:placetype":"venue"
},
  "geometry": {"coordinates":[-76.880301,38.991285],"type":"Point"}
}