{
  "type": "Feature",
  "properties": {
    "iso:country":"US",
    "sg:address":"4700 Auth Pl",
    "sg:city":"Suitland",
    "sg:classifiers":[
        {
            "category":"Professional",
            "subcategory":"Lawyer & Legal Services",
            "type":"Services"
        }
    ],
    "sg:phone":"+1 301 423 5552",
    "sg:postcode":"20746",
    "sg:province":"MD",
    "sg:tags":[
        "attorney"
    ],
    "wof:name":"Thatcher Law Firm",
    "wof:placetype":"venue"
},
  "geometry": {"coordinates":[-76.92005,38.824588],"type":"Point"}
}