{
  "type": "Feature",
  "properties": {
    "iso:country":"US",
    "sg:address":"7501 Liberty Rd",
    "sg:city":"Baltimore",
    "sg:classifiers":[
        {
            "category":"Health Services",
            "subcategory":"Health Practitioner",
            "type":"Services"
        }
    ],
    "sg:phone":"+1 410 944 4990",
    "sg:postcode":"21207",
    "sg:province":"MD",
    "wof:name":"George H Wall",
    "wof:placetype":"venue"
},
  "geometry": {"coordinates":[-76.741417,39.347665],"type":"Point"}
}