{
  "type": "Feature",
  "properties": {
    "addr:full":"9810 Bald Hill Rd Bowie MD 20721",
    "addr:housenumber":"9810",
    "addr:postcode":"20721",
    "addr:street":"Bald Hill Rd",
    "iso:country":"US",
    "sg:address":"9810 Bald Hill Rd",
    "sg:city":"Bowie",
    "sg:classifiers":[
        {
            "category":"Organizations",
            "subcategory":"Religious Organization",
            "type":"Services"
        }
    ],
    "sg:phone":"+1 301 918 2160",
    "sg:postcode":"20721",
    "sg:province":"MD",
    "sg:tags":[
        "clergy"
    ],
    "wof:name":"Charles H Doom",
    "wof:placetype":"venue"
},
  "geometry": {"coordinates":[-76.830033,38.940147],"type":"Point"}
}