{
  "type": "Feature",
  "properties": {
    "addr:full":"11749 Bragdon Wood Clarksville MD 21029",
    "addr:postcode":"11749;21029",
    "addr:street":"Bragdon Wood",
    "iso:country":"US",
    "sg:address":"11749 Bragdon Wood",
    "sg:city":"Clarksville",
    "sg:classifiers":[
        {
            "category":"Building & Trades",
            "subcategory":"Construction",
            "type":"Services"
        }
    ],
    "sg:phone":"+1 443 535 0835",
    "sg:postcode":"21029",
    "sg:province":"MD",
    "sg:tags":[
        "nonresidential"
    ],
    "wof:name":"Woodside Construction",
    "wof:placetype":"venue"
},
  "geometry": {"coordinates":[-76.91768999999999,39.229212],"type":"Point"}
}