{
  "type": "Feature",
  "properties": {
    "iso:country":"US",
    "sg:address":"3923 Madison St",
    "sg:city":"Hyattsville",
    "sg:classifiers":[
        {
            "category":"Arena",
            "subcategory":"Sports Club",
            "type":"Entertainment"
        }
    ],
    "sg:phone":"+1 301 864 4095",
    "sg:postcode":"20781",
    "sg:province":"MD",
    "sg:tags":[
        "manager",
        "recruiter",
        "promoter"
    ],
    "wof:name":"B & S Sales Representatives",
    "wof:placetype":"venue"
},
  "geometry": {"coordinates":[-76.950908,38.958344],"type":"Point"}
}