{
  "type": "Feature",
  "properties": {
    "addr:full":"34 Jones Station Rd W Severna Park MD 21146",
    "addr:housenumber":"34",
    "addr:postcode":"21146",
    "addr:street":"Jones Station Rd W",
    "iso:country":"US",
    "sg:address":"34 Jones Station Rd W",
    "sg:city":"Severna Park",
    "sg:classifiers":[
        {
            "category":"Professional",
            "subcategory":"Business Services",
            "type":"Services"
        }
    ],
    "sg:phone":"+1 410 647 2605",
    "sg:postcode":"21146",
    "sg:province":"MD",
    "wof:name":"Do MO Construction Co",
    "wof:placetype":"venue"
},
  "geometry": {"coordinates":[-76.529815,39.055804],"type":"Point"}
}