{
  "type": "Feature",
  "properties": {
    "iso:country":"US",
    "sg:address":"5808 Clarksville Sq Dr",
    "sg:city":"Clarksville",
    "sg:classifiers":[
        {
            "category":"Restaurant",
            "type":"Food & Drink"
        }
    ],
    "sg:phone":"+1 443 535 9777",
    "sg:postcode":"21029",
    "sg:province":"MD",
    "sg:tags":[
        "pizza"
    ],
    "wof:name":"Squisito Benvenuti Pizza Pasta & More",
    "wof:placetype":"venue"
},
  "geometry": {"coordinates":[-76.90679900000001,39.168499],"type":"Point"}
}