{
  "type": "Feature",
  "properties": {
    "addr:full":"1415 Fallsmead Way Rockville MD 20854",
    "addr:housenumber":"1415",
    "addr:postcode":"20854",
    "addr:street":"Fallsmead Way",
    "iso:country":"US",
    "sg:address":"1415 Fallsmead Way",
    "sg:city":"Rockville",
    "sg:classifiers":[
        {
            "category":"Social Services",
            "type":"Services"
        }
    ],
    "sg:phone":"+1 301 424 3949",
    "sg:postcode":"20854",
    "sg:province":"MD",
    "sg:tags":[
        "counselor",
        "marriage",
        "family"
    ],
    "wof:name":"Patricia Hartman",
    "wof:placetype":"venue"
},
  "geometry": {"coordinates":[-77.17547999999999,39.074739],"type":"Point"}
}