{
  "type": "Feature",
  "properties": {
    "iso:country":"US",
    "sg:address":"5 34th St",
    "sg:city":"Ocean City",
    "sg:classifiers":[
        {
            "category":"Travel",
            "subcategory":"Hotels & Motels",
            "type":"Entertainment"
        }
    ],
    "sg:phone":"+1 410 289 6295",
    "sg:postcode":"21842",
    "sg:province":"MD",
    "wof:name":"Ocean Side Motel & Apartments",
    "wof:placetype":"venue"
},
  "geometry": {"coordinates":[-75.072238,38.362348],"type":"Point"}
}