{
  "type": "Feature",
  "properties": {
    "addr:full":"920 Todds Ln Rosedale MD 21237",
    "addr:housenumber":"920",
    "addr:postcode":"21237",
    "addr:street":"Todds Ln",
    "iso:country":"US",
    "sg:address":"920 Todds Ln",
    "sg:city":"Rosedale",
    "sg:classifiers":[
        {
            "category":"Retail",
            "subcategory":"Auto Rental",
            "type":"Services"
        },
        {
            "category":"Professional",
            "subcategory":"Business Services",
            "type":"Services"
        },
        {
            "category":"Retail",
            "subcategory":"Storage",
            "type":"Services"
        }
    ],
    "sg:postcode":"21237",
    "sg:province":"MD",
    "sg:tags":[
        "renting",
        "leasing",
        "portable",
        "mobile",
        "commercial",
        "trailer",
        "unit"
    ],
    "sg:website":"http://N",
    "wof:name":"Modspace",
    "wof:placetype":"venue"
},
  "geometry": {"coordinates":[-76.49677200000001,39.320369],"type":"Point"}
}