{
  "type": "Feature",
  "properties": {
    "iso:country":"US",
    "sg:address":"3455 Wilkens Ave Ste 308",
    "sg:city":"Baltimore",
    "sg:classifiers":[
        {
            "category":"Social Services",
            "type":"Services"
        },
        {
            "category":"Personal",
            "type":"Services"
        }
    ],
    "sg:phone":"+1 410 525 8601",
    "sg:postcode":"21229",
    "sg:province":"MD",
    "sg:tags":[
        "family",
        "counselors-licensed",
        "individual",
        "marriage",
        "child",
        "professional",
        "counselor"
    ],
    "wof:name":"Contemporary Family Services Inc",
    "wof:placetype":"venue"
},
  "geometry": {"coordinates":[-76.675933,39.272333],"type":"Point"}
}