{
  "type": "Feature",
  "properties": {
    "addr:full":"1018 Haverhill Rd Baltimore MD 21229",
    "addr:housenumber":"1018",
    "addr:postcode":"21229",
    "addr:street":"Haverhill Rd",
    "iso:country":"US",
    "sg:address":"1018 Haverhill Rd",
    "sg:city":"Baltimore",
    "sg:classifiers":[
        {
            "category":"Organizations",
            "subcategory":"Religious Organization",
            "type":"Services"
        }
    ],
    "sg:phone":"+1 410 644 7106",
    "sg:postcode":"21229",
    "sg:province":"MD",
    "wof:name":"Bethany Lutheran Church Violetville",
    "wof:placetype":"venue"
},
  "geometry": {"coordinates":[-76.678802,39.269402],"type":"Point"}
}