{
  "type": "Feature",
  "properties": {
    "iso:country":"US",
    "sg:address":"7802 Coastal Hwy",
    "sg:city":"Ocean City",
    "sg:classifiers":[
        {
            "category":"Real Estate",
            "subcategory":"Real Estate Agent",
            "type":"Services"
        }
    ],
    "sg:phone":"+1 410 723 0988",
    "sg:postcode":"21842",
    "sg:province":"MD",
    "wof:name":"Condo Realty Inc",
    "wof:placetype":"venue"
},
  "geometry": {"coordinates":[-75.062389,38.396995],"type":"Point"}
}