{
  "type": "Feature",
  "properties": {
    "iso:country":"US",
    "sg:address":"12609 Fork Rd",
    "sg:city":"Fork",
    "sg:classifiers":[
        {
            "category":"Restaurant",
            "type":"Food & Drink"
        }
    ],
    "sg:phone":"+1 410 592 5739",
    "sg:postcode":"21051",
    "sg:province":"MD",
    "sg:tags":[
        "delicatessen"
    ],
    "wof:name":"Fork Deli & Bakery Inc",
    "wof:placetype":"venue"
},
  "geometry": {"coordinates":[-76.44585499999999,39.470628],"type":"Point"}
}