{
  "type": "Feature",
  "properties": {
    "iso:country":"US",
    "sg:address":"4300 Montgomery Ave",
    "sg:city":"Bethesda",
    "sg:classifiers":[
        {
            "category":"Professional",
            "subcategory":"Research",
            "type":"Services"
        }
    ],
    "sg:phone":"+1 301 654 3376",
    "sg:postcode":"20814",
    "sg:province":"MD",
    "sg:tags":[
        "organization",
        "noncommercial"
    ],
    "wof:name":"Foundation Trust Group",
    "wof:placetype":"venue"
},
  "geometry": {"coordinates":[-77.090826,38.984096],"type":"Point"}
}