{
  "type": "Feature",
  "properties": {
    "iso:country":"US",
    "sg:address":"3016 Texas Ave",
    "sg:city":"Parkville",
    "sg:classifiers":[
        {
            "category":"Organizations",
            "subcategory":"Religious Organization",
            "type":"Services"
        }
    ],
    "sg:phone":"+1 410 668 2037",
    "sg:postcode":"21234",
    "sg:province":"MD",
    "sg:tags":[
        "clergy"
    ],
    "wof:name":"Elwood L Ulmer",
    "wof:placetype":"venue"
},
  "geometry": {"coordinates":[-76.532949,39.377263],"type":"Point"}
}