{
  "type": "Feature",
  "properties": {
    "addr:full":"6401 S Orchard Rd Linthicum Heights MD 21090",
    "addr:housenumber":"6401",
    "addr:postcode":"21090",
    "addr:street":"S Orchard Rd",
    "iso:country":"US",
    "sg:address":"6401 S Orchard Rd",
    "sg:city":"Linthicum Heights",
    "sg:classifiers":[
        {
            "category":"Education",
            "subcategory":"School",
            "type":"Public Place"
        }
    ],
    "sg:phone":"+1 410 859 1212",
    "sg:postcode":"21090",
    "sg:province":"MD",
    "sg:tags":[
        "high",
        "middle",
        "elementary"
    ],
    "sg:website":"www.philip-neri.org",
    "wof:name":"St Philip Neri School",
    "wof:placetype":"venue"
},
  "geometry": {"coordinates":[-76.64569899999999,39.202999],"type":"Point"}
}