{
  "type": "Feature",
  "properties": {
    "iso:country":"US",
    "sg:address":"7409 Coastal Hwy",
    "sg:city":"Ocean City",
    "sg:classifiers":[
        {
            "category":"Shopping",
            "subcategory":"Clothing, Apparel, & Fashions",
            "type":"Retail Goods"
        }
    ],
    "sg:phone":"+1 410 723 1313",
    "sg:postcode":"21842",
    "sg:province":"MD",
    "sg:tags":[
        "sportswear"
    ],
    "wof:name":"Quiet Storm",
    "wof:placetype":"venue"
},
  "geometry": {"coordinates":[-75.063191,38.395393],"type":"Point"}
}