{
  "type": "Feature",
  "properties": {
    "iso:country":"US",
    "sg:address":"27671 Three Notch Rd",
    "sg:city":"Mechanicsville",
    "sg:classifiers":[
        {
            "category":"Professional",
            "subcategory":"Detective & Security Services",
            "type":"Services"
        }
    ],
    "sg:phone":"+1 240 273 6012",
    "sg:postcode":"20659",
    "sg:province":"MD",
    "sg:tags":[
        "information",
        "bureau"
    ],
    "wof:name":"Seaboch's Auto Sales And Service",
    "wof:placetype":"venue"
},
  "geometry": {"coordinates":[-76.705337,38.422682],"type":"Point"}
}