{
  "type": "Feature",
  "properties": {
    "addr:full":"1400 Patapsco St Baltimore MD 21230",
    "addr:housenumber":"1400",
    "addr:postcode":"21230",
    "addr:street":"Patapsco St",
    "iso:country":"US",
    "sg:address":"1400 Patapsco St",
    "sg:city":"Baltimore",
    "sg:classifiers":[
        {
            "category":"Wholesale",
            "subcategory":"Scrap",
            "type":"Manufacturing & Wholesale Goods"
        }
    ],
    "sg:phone":"+1 410 752 7714",
    "sg:postcode":"21230",
    "sg:province":"MD",
    "sg:tags":[
        "material"
    ],
    "wof:name":"Gilbert Marine Supply Company",
    "wof:placetype":"venue"
},
  "geometry": {"coordinates":[-76.61336300000001,39.274834],"type":"Point"}
}