{
  "type": "Feature",
  "properties": {
    "iso:country":"US",
    "sg:address":"6200 Chillum Pl NW",
    "sg:city":"Washington",
    "sg:classifiers":[
        {
            "category":"Organizations",
            "subcategory":"Religious Organization",
            "type":"Services"
        }
    ],
    "sg:phone":"+1 202 829 8003",
    "sg:postcode":"20011",
    "sg:province":"MD",
    "sg:tags":[
        "church"
    ],
    "wof:name":"Celestial Church",
    "wof:placetype":"venue"
},
  "geometry": {"coordinates":[-77.01072499999999,38.966325],"type":"Point"}
}