{
  "type": "Feature",
  "properties": {
    "iso:country":"US",
    "sg:address":"621 E Pratt St Ste 100A",
    "sg:city":"Baltimore",
    "sg:classifiers":[
        {
            "category":"Restaurant",
            "type":"Food & Drink"
        }
    ],
    "sg:phone":"+1 443 453 5961",
    "sg:postcode":"21202",
    "sg:province":"MD",
    "sg:website":"www.dickslastresort.com",
    "wof:name":"Dick's Last Resort",
    "wof:placetype":"venue"
},
  "geometry": {"coordinates":[-76.607066,39.285403],"type":"Point"}
}