{
  "type": "Feature",
  "properties": {
    "iso:country":"US",
    "sg:address":"2410 Rockwell Ave",
    "sg:city":"Baltimore",
    "sg:classifiers":[
        {
            "category":"Professional",
            "subcategory":"Computer Services",
            "type":"Services"
        }
    ],
    "sg:phone":"+1 410 719 1322",
    "sg:postcode":"21228",
    "sg:province":"MD",
    "sg:tags":[
        "programing",
        "custom"
    ],
    "wof:name":"Geomethods LLC",
    "wof:placetype":"venue"
},
  "geometry": {"coordinates":[-76.773606,39.280144],"type":"Point"}
}