{
  "type": "Feature",
  "properties": {
    "addr:full":"4366 Sycamore Dr Hampstead MD 21074",
    "addr:housenumber":"4366",
    "addr:postcode":"21074",
    "addr:street":"Sycamore Dr",
    "iso:country":"US",
    "sg:address":"4366 Sycamore Dr",
    "sg:city":"Hampstead",
    "sg:classifiers":[
        {
            "category":"Professional",
            "subcategory":"Business Services",
            "type":"Services"
        }
    ],
    "sg:phone":"+1 410 239 4960",
    "sg:postcode":"21074",
    "sg:province":"MD",
    "wof:name":"M S H Technologies Inc",
    "wof:placetype":"venue"
},
  "geometry": {"coordinates":[-76.8403,39.600772],"type":"Point"}
}