{
  "type": "Feature",
  "properties": {
    "addr:full":"13425 Reid Cir Fort Washington MD 20744",
    "addr:housenumber":"13425",
    "addr:postcode":"20744",
    "addr:street":"Reid Cir",
    "iso:country":"US",
    "sg:address":"13425 Reid Cir",
    "sg:city":"Fort Washington",
    "sg:classifiers":[
        {
            "category":"Retail",
            "subcategory":"Repair Shop",
            "type":"Services"
        }
    ],
    "sg:phone":"+1 301 292 5501",
    "sg:postcode":"20744",
    "sg:province":"MD",
    "sg:tags":[
        "furniture"
    ],
    "wof:name":"David Gamache",
    "wof:placetype":"venue"
},
  "geometry": {"coordinates":[-77.023096,38.704754],"type":"Point"}
}