{
  "type": "Feature",
  "properties": {
    "addr:full":"1 Main St Mccoole MD 21562",
    "addr:housenumber":"1",
    "addr:postcode":"21562",
    "addr:street":"Main St",
    "iso:country":"US",
    "sg:address":"1 Main St",
    "sg:city":"Mccoole",
    "sg:classifiers":[
        {
            "category":"Manufacturing",
            "subcategory":"Printing",
            "type":"Manufacturing & Wholesale Goods"
        }
    ],
    "sg:phone":"+1 301 786 4151",
    "sg:postcode":"21562",
    "sg:province":"MD",
    "sg:tags":[
        "newspaper"
    ],
    "wof:name":"Cumberland Times",
    "wof:placetype":"venue"
},
  "geometry": {"coordinates":[-79.044552,39.486004],"type":"Point"}
}