{
  "type": "Feature",
  "properties": {
    "addr:full":"5318 Park Heights Ave Baltimore MD 21215",
    "addr:housenumber":"5318",
    "addr:postcode":"21215",
    "addr:street":"Park Heights Ave",
    "iso:country":"US",
    "sg:address":"5318 Park Heights Ave",
    "sg:city":"Baltimore",
    "sg:classifiers":[
        {
            "category":"Food & Beverages",
            "subcategory":"Groceries & Convenience Stores",
            "type":"Retail Goods"
        }
    ],
    "sg:phone":"+1 410 664 1818",
    "sg:postcode":"21215",
    "sg:province":"MD",
    "sg:tags":[
        "grocer"
    ],
    "wof:name":"West Indian Import",
    "wof:placetype":"venue"
},
  "geometry": {"coordinates":[-76.67942600000001,39.349995],"type":"Point"}
}