{
  "type": "Feature",
  "properties": {
    "addr:full":"1412 Fenwick Ln Silver Spring MD 20910",
    "addr:housenumber":"1412",
    "addr:postcode":"20910",
    "addr:street":"Fenwick Ln",
    "iso:country":"US",
    "sg:address":"1412 Fenwick Ln",
    "sg:city":"Silver Spring",
    "sg:classifiers":[
        {
            "category":"Professional",
            "subcategory":"Computer Services",
            "type":"Services"
        }
    ],
    "sg:phone":"+1 301 681 0123",
    "sg:postcode":"20910",
    "sg:province":"MD",
    "sg:tags":[
        "programing",
        "custom"
    ],
    "wof:name":"Pal Technology Group Inc",
    "wof:placetype":"venue"
},
  "geometry": {"coordinates":[-77.03402699999999,38.996333],"type":"Point"}
}