{
  "type": "Feature",
  "properties": {
    "iso:country":"US",
    "sg:address":"3603 43rd Ave",
    "sg:city":"Brentwood",
    "sg:classifiers":[
        {
            "category":"Building & Trades",
            "subcategory":"Construction",
            "type":"Services"
        }
    ],
    "sg:phone":"+1 301 277 3919",
    "sg:postcode":"20722",
    "sg:province":"MD",
    "sg:tags":[
        "general",
        "contractor"
    ],
    "wof:name":"Matheson Remodeling",
    "wof:placetype":"venue"
},
  "geometry": {"coordinates":[-76.944582,38.936486],"type":"Point"}
}