{
  "type": "Feature",
  "properties": {
    "iso:country":"US",
    "sg:address":"920 Ingleside Ave",
    "sg:city":"Catonsville",
    "sg:classifiers":[
        {
            "category":"Wholesale",
            "subcategory":"Auto Parts",
            "type":"Manufacturing & Wholesale Goods"
        }
    ],
    "sg:phone":"+1 410 744 8566",
    "sg:postcode":"21228",
    "sg:province":"MD",
    "sg:tags":[
        "equipment",
        "towing"
    ],
    "wof:name":"Green's Towing",
    "wof:placetype":"venue"
},
  "geometry": {"coordinates":[-76.731325,39.289243],"type":"Point"}
}