{
  "type": "Feature",
  "properties": {
    "addr:full":"920 Ingleside Ave Catonsville MD 21228",
    "addr:housenumber":"920",
    "addr:postcode":"21228",
    "addr:street":"Ingleside Ave",
    "iso:country":"US",
    "sg:address":"920 Ingleside Ave",
    "sg:city":"Catonsville",
    "sg:classifiers":[
        {
            "category":"Wholesale",
            "subcategory":"Auto Parts",
            "type":"Manufacturing & Wholesale Goods"
        }
    ],
    "sg:phone":"+1 410 744 8566",
    "sg:postcode":"21228",
    "sg:province":"MD",
    "sg:tags":[
        "equipment",
        "towing"
    ],
    "wof:name":"Green's Towing",
    "wof:placetype":"venue"
},
  "geometry": {"coordinates":[-76.731325,39.289243],"type":"Point"}
}