{
  "type": "Feature",
  "properties": {
    "addr:full":"13204 Yorkton St Upper Marlboro MD 20774",
    "addr:postcode":"13204;20774",
    "addr:street":"Yorkton St",
    "iso:country":"US",
    "sg:address":"13204 Yorkton St",
    "sg:city":"Upper Marlboro",
    "sg:classifiers":[
        {
            "category":"Professional",
            "type":"Services"
        }
    ],
    "sg:phone":"+1 301 249 7342",
    "sg:postcode":"20774",
    "sg:province":"MD",
    "sg:tags":[
        "establishment"
    ],
    "wof:name":"Okjie Assocaites",
    "wof:placetype":"venue"
},
  "geometry": {"coordinates":[-76.776757,38.888529],"type":"Point"}
}