{
  "type": "Feature",
  "properties": {
    "iso:country":"US",
    "sg:address":"830 W 40th St",
    "sg:city":"Baltimore",
    "sg:classifiers":[
        {
            "category":"Health Services",
            "subcategory":"Health Practitioner",
            "type":"Services"
        }
    ],
    "sg:phone":"+1 410 366 0780",
    "sg:postcode":"21211",
    "sg:province":"MD",
    "sg:tags":[
        "psychologist"
    ],
    "wof:name":"Eileen Higham",
    "wof:placetype":"venue"
},
  "geometry": {"coordinates":[-76.632988,39.337194],"type":"Point"}
}