{
  "type": "Feature",
  "properties": {
    "iso:country":"US",
    "sg:address":"10601 Martin Luther King Jr Hwy",
    "sg:city":"Bowie",
    "sg:classifiers":[
        {
            "category":"Fast Food",
            "type":"Food & Drink"
        }
    ],
    "sg:phone":"+1 301 464 9292",
    "sg:postcode":"20720",
    "sg:province":"MD",
    "sg:tags":[
        "chicken",
        "wing"
    ],
    "sg:website":"www.buffalowildwings.com",
    "wof:name":"Buffalo Wild Wings",
    "wof:placetype":"venue"
},
  "geometry": {"coordinates":[-76.820497,38.956082],"type":"Point"}
}