{
  "type": "Feature",
  "properties": {
    "addr:full":"394 Plankwood Dr Westminster MD 21158",
    "addr:housenumber":"394",
    "addr:postcode":"21158",
    "addr:street":"Plankwood Dr",
    "iso:country":"US",
    "sg:address":"394 Plankwood Dr",
    "sg:city":"Westminster",
    "sg:classifiers":[
        {
            "category":"Manufacturing",
            "subcategory":"Signs",
            "type":"Manufacturing & Wholesale Goods"
        }
    ],
    "sg:phone":"+1 410 871 1770",
    "sg:postcode":"21158",
    "sg:province":"MD",
    "sg:website":"www.chesapeakegraphics.com",
    "wof:name":"Chesapeake Graphics Inc",
    "wof:placetype":"venue"
},
  "geometry": {"coordinates":[-77.00662,39.635736],"type":"Point"}
}