{
  "type": "Feature",
  "properties": {
    "addr:full":"12201 Nebel St Rockville MD 20852",
    "addr:housenumber":"12201",
    "addr:postcode":"20852",
    "addr:street":"Nebel St",
    "iso:country":"US",
    "sg:address":"12201 Nebel St",
    "sg:city":"Rockville",
    "sg:classifiers":[
        {
            "category":"Manufacturing",
            "subcategory":"Apparel",
            "type":"Manufacturing & Wholesale Goods"
        },
        {
            "category":"Manufacturing",
            "subcategory":"Wood Products",
            "type":"Manufacturing & Wholesale Goods"
        }
    ],
    "sg:phone":"+1 301 468 9394",
    "sg:postcode":"20852",
    "sg:province":"MD",
    "sg:tags":[
        "mfg",
        "closet",
        "accessory"
    ],
    "wof:name":"Closet Stretchers Inc",
    "wof:placetype":"venue"
},
  "geometry": {"coordinates":[-77.11073,39.052869],"type":"Point"}
}