{
  "type": "Feature",
  "properties": {
    "iso:country":"US",
    "sg:address":"819 W Seminary Ave",
    "sg:city":"Lutherville",
    "sg:classifiers":[
        {
            "category":"Sports & Exercise",
            "subcategory":"Gym",
            "type":"Entertainment"
        }
    ],
    "sg:phone":"+1 410 296 0103",
    "sg:postcode":"21093",
    "sg:province":"MD",
    "sg:tags":[
        "club",
        "health",
        "studio",
        "gymnasium"
    ],
    "wof:name":"R T Fitness Inc",
    "wof:placetype":"venue"
},
  "geometry": {"coordinates":[-76.642212,39.424176],"type":"Point"}
}