{
  "type": "Feature",
  "properties": {
    "iso:country":"US",
    "sg:address":"4 Kincaid Ct",
    "sg:city":"Baldwin",
    "sg:classifiers":[
        {
            "category":"Retail",
            "subcategory":"Veterinary Services",
            "type":"Services"
        }
    ],
    "sg:phone":"+1 410 592 3313",
    "sg:postcode":"21013",
    "sg:province":"MD",
    "sg:tags":[
        "veterinarian"
    ],
    "wof:name":"Francis J Bertozzi",
    "wof:placetype":"venue"
},
  "geometry": {"coordinates":[-76.529022,39.511532],"type":"Point"}
}