{
  "type": "Feature",
  "properties": {
    "iso:country":"US",
    "sg:address":"1008 W Main St",
    "sg:city":"Salisbury",
    "sg:classifiers":[
        {
            "category":"Shopping",
            "type":"Retail Goods"
        }
    ],
    "sg:phone":"+1 410 219 5088",
    "sg:postcode":"21801",
    "sg:province":"MD",
    "sg:tags":[
        "hearing",
        "equipment",
        "supply",
        "impaired"
    ],
    "wof:name":"Sound Advice Hearing Aid Ctr",
    "wof:placetype":"venue"
},
  "geometry": {"coordinates":[-75.612509,38.367896],"type":"Point"}
}