{
  "type": "Feature",
  "properties": {
    "addr:full":"7005 Governor Ritchie Hwy Glen Burnie MD 21061",
    "addr:housenumber":"7005",
    "addr:postcode":"21061",
    "addr:street":"Governor Ritchie Hwy",
    "iso:country":"US",
    "sg:address":"7005 Governor Ritchie Hwy",
    "sg:city":"Glen Burnie",
    "sg:classifiers":[
        {
            "category":"Restaurant",
            "type":"Food & Drink"
        }
    ],
    "sg:phone":"+1 410 590 1562",
    "sg:postcode":"21061",
    "sg:province":"MD",
    "wof:name":"Popeyes Chicken & Biscuits",
    "wof:placetype":"venue"
},
  "geometry": {"coordinates":[-76.613133,39.182228],"type":"Point"}
}