{
  "type": "Feature",
  "properties": {
    "addr:full":"12700 Falls Rd Cockysvl Hnt Vly MD 21030",
    "addr:housenumber":"12700",
    "addr:postcode":"21030",
    "addr:street":"Falls Rd;Hnt Vly",
    "iso:country":"US",
    "sg:address":"12700 Falls Rd",
    "sg:city":"Cockysvl Hnt Vly",
    "sg:classifiers":[
        {
            "category":"Health Services",
            "subcategory":"Doctor",
            "type":"Services"
        }
    ],
    "sg:phone":"+1 410 252 5456",
    "sg:postcode":"21030",
    "sg:province":"MD",
    "sg:tags":[
        "physician",
        "surgeon"
    ],
    "wof:name":"Georgetown University",
    "wof:placetype":"venue"
},
  "geometry": {"coordinates":[-76.705817,39.474693],"type":"Point"}
}