{
  "type": "Feature",
  "properties": {
    "iso:country":"US",
    "sg:address":"1532 Pointer Ridge Pl",
    "sg:city":"Bowie",
    "sg:classifiers":[
        {
            "category":"Shopping",
            "subcategory":"Hobbies, Toys, & Games",
            "type":"Retail Goods"
        }
    ],
    "sg:phone":"+1 301 249 0846",
    "sg:postcode":"20716",
    "sg:province":"MD",
    "sg:tags":[
        "product",
        "ceramic"
    ],
    "sg:website":"www.nowell.net",
    "wof:name":"Nowells Molds",
    "wof:placetype":"venue"
},
  "geometry": {"coordinates":[-76.71900599999999,38.90994],"type":"Point"}
}