{
  "type": "Feature",
  "properties": {
    "iso:country":"US",
    "sg:address":"1308 S Baylis St",
    "sg:city":"Baltimore",
    "sg:classifiers":[
        {
            "category":"Professional",
            "subcategory":"Engineering",
            "type":"Services"
        }
    ],
    "sg:phone":"+1 410 563 4131",
    "sg:postcode":"21224",
    "sg:province":"MD",
    "sg:tags":[
        "engineer"
    ],
    "wof:name":"Adams Mirza Engineering",
    "wof:placetype":"venue"
},
  "geometry": {"coordinates":[-76.567622,39.278237],"type":"Point"}
}