{
  "type": "Feature",
  "properties": {
    "iso:country":"US",
    "sg:address":"628 E Bay Front Rd",
    "sg:city":"Deale",
    "sg:classifiers":[
        {
            "category":"Personal",
            "subcategory":"Barber",
            "type":"Services"
        }
    ],
    "sg:phone":"+1 410 867 2096",
    "sg:postcode":"20751",
    "sg:province":"MD",
    "wof:name":"Bay Front Styling",
    "wof:placetype":"venue"
},
  "geometry": {"coordinates":[-76.555187,38.793641],"type":"Point"}
}