{
  "type": "Feature",
  "properties": {
    "addr:full":"8322 Mennonite Church Rd Westover MD 21871",
    "addr:housenumber":"8322",
    "addr:postcode":"21871",
    "addr:street":"Church Rd",
    "iso:country":"US",
    "sg:address":"8322 Mennonite Church Rd",
    "sg:city":"Westover",
    "sg:classifiers":[
        {
            "category":"Farming",
            "subcategory":"Poultry Farm",
            "type":"Manufacturing & Wholesale Goods"
        }
    ],
    "sg:phone":"+1 410 957 0308",
    "sg:postcode":"21871",
    "sg:province":"MD",
    "sg:tags":[
        "chicken"
    ],
    "wof:name":"Shreeves Otha",
    "wof:placetype":"venue"
},
  "geometry": {"coordinates":[-75.67065599999999,38.105319],"type":"Point"}
}