{
  "type": "Feature",
  "properties": {
    "iso:country":"US",
    "sg:address":"144 Westbury Rd",
    "sg:city":"Lutherville",
    "sg:classifiers":[
        {
            "category":"Building & Trades",
            "subcategory":"Construction",
            "type":"Services"
        }
    ],
    "sg:phone":"+1 410 828 4571",
    "sg:postcode":"21093",
    "sg:province":"MD",
    "sg:tags":[
        "painter"
    ],
    "wof:name":"Regalbuto Painting",
    "wof:placetype":"venue"
},
  "geometry": {"coordinates":[-76.622635,39.417372],"type":"Point"}
}