{
  "type": "Feature",
  "properties": {
    "addr:full":"8794 Magnolia Rd Perry Hall MD 21128",
    "addr:housenumber":"8794",
    "addr:postcode":"21128",
    "addr:street":"Magnolia Rd",
    "iso:country":"US",
    "sg:address":"8794 Magnolia Rd",
    "sg:city":"Perry Hall",
    "sg:classifiers":[
        {
            "category":"Recreation",
            "type":"Entertainment"
        }
    ],
    "sg:phone":"+1 410 931 0648",
    "sg:postcode":"21128",
    "sg:province":"MD",
    "sg:tags":[
        "guide"
    ],
    "wof:name":"Maryland State Games & Fishing",
    "wof:placetype":"venue"
},
  "geometry": {"coordinates":[-76.4586,39.389083],"type":"Point"}
}