{
  "type": "Feature",
  "properties": {
    "addr:full":"2507 Plainfield Rd Dundalk MD 21222",
    "addr:housenumber":"2507",
    "addr:postcode":"21222",
    "addr:street":"Plainfield Rd",
    "iso:country":"US",
    "sg:address":"2507 Plainfield Rd",
    "sg:city":"Dundalk",
    "sg:classifiers":[
        {
            "category":"Manufacturing",
            "subcategory":"Printing",
            "type":"Manufacturing & Wholesale Goods"
        }
    ],
    "sg:phone":"+1 410 282 8300",
    "sg:postcode":"21222",
    "sg:province":"MD",
    "sg:tags":[
        "printer"
    ],
    "wof:name":"Star Graphix",
    "wof:placetype":"venue"
},
  "geometry": {"coordinates":[-76.501373,39.278749],"type":"Point"}
}