{
  "type": "Feature",
  "properties": {
    "addr:full":"13665 Triadelphia Rd Glenelg MD 21737",
    "addr:housenumber":"13665",
    "addr:postcode":"21737",
    "addr:street":"Triadelphia Rd",
    "iso:country":"US",
    "sg:address":"13665 Triadelphia Rd",
    "sg:city":"Glenelg",
    "sg:classifiers":[
        {
            "category":"Building & Trades",
            "subcategory":"Plumbing",
            "type":"Services"
        }
    ],
    "sg:phone":"+1 410 531 2939",
    "sg:postcode":"21737",
    "sg:province":"MD",
    "sg:tags":[
        "septic"
    ],
    "wof:name":"Jack Fyock Septic Svc Inc",
    "wof:placetype":"venue"
},
  "geometry": {"coordinates":[-76.991699,39.26385],"type":"Point"}
}