{
  "type": "Feature",
  "properties": {
    "iso:country":"US",
    "sg:address":"13785 Bottom Rd",
    "sg:city":"Hydes",
    "sg:classifiers":[
        {
            "category":"Real Estate",
            "subcategory":"Real Estate Agent",
            "type":"Services"
        }
    ],
    "sg:phone":"+1 410 592 2300",
    "sg:postcode":"21082",
    "sg:province":"MD",
    "wof:name":"Alexander Realty Inc",
    "wof:placetype":"venue"
},
  "geometry": {"coordinates":[-76.438919,39.498874],"type":"Point"}
}