{
  "type": "Feature",
  "properties": {
    "iso:country":"US",
    "sg:address":"325 Sandown Park Ct",
    "sg:city":"Bel Air",
    "sg:classifiers":[
        {
            "category":"Retail",
            "subcategory":"Repair Shop",
            "type":"Services"
        }
    ],
    "sg:phone":"+1 410 838 1221",
    "sg:postcode":"21015",
    "sg:province":"MD",
    "sg:tags":[
        "lock",
        "locksmith"
    ],
    "wof:name":"ABC Safe & Lock Svc",
    "wof:placetype":"venue"
},
  "geometry": {"coordinates":[-76.318282,39.500118],"type":"Point"}
}