{
  "type": "Feature",
  "properties": {
    "addr:full":"3600 Georgetown Rd Baltimore MD 21227",
    "addr:housenumber":"3600",
    "addr:postcode":"21227",
    "addr:street":"Georgetown Rd",
    "iso:country":"US",
    "sg:address":"3600 Georgetown Rd",
    "sg:city":"Baltimore",
    "sg:classifiers":[
        {
            "category":"Freight",
            "type":"Transportation"
        }
    ],
    "sg:phone":"+1 410 247 1886",
    "sg:postcode":"21227",
    "sg:province":"MD",
    "sg:tags":[
        "trucking"
    ],
    "sg:website":"www.nemf.com",
    "wof:name":"New England Motor Freight",
    "wof:placetype":"venue"
},
  "geometry": {"coordinates":[-76.67014,39.255207],"type":"Point"}
}