{
  "type": "Feature",
  "properties": {
    "iso:country":"US",
    "sg:address":"8218 Wisconsin Ave",
    "sg:city":"Bethesda",
    "sg:classifiers":[
        {
            "category":"Health Services",
            "subcategory":"Doctor",
            "type":"Services"
        }
    ],
    "sg:phone":"+1 301 951 5244",
    "sg:postcode":"20814",
    "sg:province":"MD",
    "sg:tags":[
        "dentist"
    ],
    "wof:name":"James Buchanan DDS",
    "wof:placetype":"venue"
},
  "geometry": {"coordinates":[-77.096043,38.992335],"type":"Point"}
}