{
  "type": "Feature",
  "properties": {
    "addr:full":"75 Industrial Park Dr Waldorf MD 20602",
    "addr:housenumber":"75",
    "addr:postcode":"20602",
    "addr:street":"Industrial Park Dr",
    "iso:country":"US",
    "sg:address":"75 Industrial Park Dr",
    "sg:city":"Waldorf",
    "sg:classifiers":[
        {
            "category":"Social Services",
            "type":"Services"
        }
    ],
    "sg:phone":"+1 301 843 2960",
    "sg:postcode":"20602",
    "sg:province":"MD",
    "sg:tags":[
        "organization",
        "welfare"
    ],
    "wof:name":"Tri-County Youth Svc Bureau",
    "wof:placetype":"venue"
},
  "geometry": {"coordinates":[-76.91700299999999,38.610989],"type":"Point"}
}