{
  "type": "Feature",
  "properties": {
    "iso:country":"US",
    "sg:address":"75 Industrial Park Dr",
    "sg:city":"Waldorf",
    "sg:classifiers":[
        {
            "category":"Social Services",
            "type":"Services"
        }
    ],
    "sg:phone":"+1 301 843 2960",
    "sg:postcode":"20602",
    "sg:province":"MD",
    "sg:tags":[
        "organization",
        "welfare"
    ],
    "wof:name":"Tri-County Youth Svc Bureau",
    "wof:placetype":"venue"
},
  "geometry": {"coordinates":[-76.917003,38.610989],"type":"Point"}
}