{
  "type": "Feature",
  "properties": {
    "addr:full":"113 W Saratoga St Baltimore MD 21201",
    "addr:housenumber":"113",
    "addr:postcode":"21201",
    "addr:street":"W Saratoga St",
    "iso:country":"US",
    "sg:address":"113 W Saratoga St",
    "sg:city":"Baltimore",
    "sg:classifiers":[
        {
            "category":"Shopping",
            "subcategory":"Clothing, Apparel, & Fashions",
            "type":"Retail Goods"
        }
    ],
    "sg:phone":"+1 410 837 7623",
    "sg:postcode":"21201",
    "sg:province":"MD",
    "sg:tags":[
        "apparel",
        "women's"
    ],
    "wof:name":"Elite. Designer Clergy Apparel",
    "wof:placetype":"venue"
},
  "geometry": {"coordinates":[-76.61691399999999,39.293011],"type":"Point"}
}