{
  "type": "Feature",
  "properties": {
    "iso:country":"US",
    "sg:address":"17008 Old Baltimore Rd",
    "sg:city":"Olney",
    "sg:classifiers":[
        {
            "category":"Professional",
            "subcategory":"Computer Services",
            "type":"Services"
        }
    ],
    "sg:phone":"+1 301 340 5159",
    "sg:postcode":"20832",
    "sg:province":"MD",
    "sg:tags":[
        "network",
        "teleprocessing"
    ],
    "wof:name":"GE",
    "wof:placetype":"venue"
},
  "geometry": {"coordinates":[-77.073716,39.13507],"type":"Point"}
}