{
  "type": "Feature",
  "properties": {
    "addr:full":"839 Elkridge Landing Rd Linthicum Hts MD 21090",
    "addr:housenumber":"839",
    "addr:postcode":"21090",
    "addr:street":"Elkridge Landing Rd",
    "iso:country":"US",
    "sg:address":"839 Elkridge Landing Rd",
    "sg:city":"Linthicum Hts",
    "sg:classifiers":[
        {
            "category":"Professional",
            "subcategory":"Engineering",
            "type":"Services"
        }
    ],
    "sg:phone":"+1 443 203 0393",
    "sg:postcode":"21090",
    "sg:province":"MD",
    "sg:tags":[
        "general",
        "contractor"
    ],
    "wof:name":"Dot Engineering Inc",
    "wof:placetype":"venue"
},
  "geometry": {"coordinates":[-76.686834,39.196465],"type":"Point"}
}