{
  "type": "Feature",
  "properties": {
    "iso:country":"US",
    "sg:address":"9251 Baltimore National Pike",
    "sg:city":"Ellicott City",
    "sg:classifiers":[
        {
            "category":"Food & Beverages",
            "subcategory":"Groceries & Convenience Stores",
            "type":"Retail Goods"
        }
    ],
    "sg:phone":"+1 410 461 0610",
    "sg:postcode":"21042",
    "sg:province":"MD",
    "sg:tags":[
        "grocer"
    ],
    "wof:name":"Coco Food Market",
    "wof:placetype":"venue"
},
  "geometry": {"coordinates":[-76.830653,39.277153],"type":"Point"}
}