{
  "type": "Feature",
  "properties": {
    "iso:country":"US",
    "sg:address":"4799 Mid County Ct",
    "sg:city":"Monrovia",
    "sg:classifiers":[
        {
            "category":"Professional",
            "type":"Services"
        }
    ],
    "sg:phone":"+1 301 831 6207",
    "sg:postcode":"21770",
    "sg:province":"MD",
    "wof:name":"Integritours and Services Inc",
    "wof:placetype":"venue"
},
  "geometry": {"coordinates":[-77.24365899999999,39.365227],"type":"Point"}
}