{
  "type": "Feature",
  "properties": {
    "addr:full":"622 Warfield Dr Rockville MD 20850",
    "addr:housenumber":"622",
    "addr:postcode":"20850",
    "addr:street":"Warfield Dr",
    "iso:country":"US",
    "sg:address":"622 Warfield Dr",
    "sg:city":"Rockville",
    "sg:classifiers":[
        {
            "category":"Professional",
            "subcategory":"Computer Services",
            "type":"Services"
        }
    ],
    "sg:phone":"+1 301 294 6336",
    "sg:postcode":"20850",
    "sg:province":"MD",
    "sg:tags":[
        "datum"
    ],
    "wof:name":"Data Works",
    "wof:placetype":"venue"
},
  "geometry": {"coordinates":[-77.16406600000001,39.092965],"type":"Point"}
}