{
  "type": "Feature",
  "properties": {
    "addr:full":"12927 Saint Paul Rd Clear Spring MD 21722",
    "addr:housenumber":"12927",
    "addr:postcode":"21722",
    "addr:street":"Saint Paul Rd",
    "iso:country":"US",
    "sg:address":"12927 Saint Paul Rd",
    "sg:city":"Clear Spring",
    "sg:classifiers":[
        {
            "category":"Real Estate",
            "subcategory":"Real Estate Operator",
            "type":"Services"
        }
    ],
    "sg:phone":"+1 301 842 2078",
    "sg:postcode":"21722",
    "sg:province":"MD",
    "sg:tags":[
        "property",
        "lessor"
    ],
    "wof:name":"Arthur Litton",
    "wof:placetype":"venue"
},
  "geometry": {"coordinates":[-77.884619,39.662575],"type":"Point"}
}