{
  "type": "Feature",
  "properties": {
    "addr:full":"405 Brock Bridge Rd Laurel MD 20724",
    "addr:housenumber":"405",
    "addr:postcode":"20724",
    "addr:street":"Brock Bridge Rd",
    "iso:country":"US",
    "sg:address":"405 Brock Bridge Rd",
    "sg:city":"Laurel",
    "sg:classifiers":[
        {
            "category":"Education",
            "subcategory":"School",
            "type":"Public Place"
        }
    ],
    "sg:phone":"+1 301 498 6280",
    "sg:postcode":"20724",
    "sg:province":"MD",
    "wof:name":"Brock Bridge Elementary",
    "wof:placetype":"venue"
},
  "geometry": {"coordinates":[-76.823339,39.084312],"type":"Point"}
}