{
  "type": "Feature",
  "properties": {
    "iso:country":"US",
    "sg:address":"12528 Bradbury Ave",
    "sg:city":"Smithsburg",
    "sg:classifiers":[
        {
            "category":"Building & Trades",
            "subcategory":"Construction",
            "type":"Services"
        }
    ],
    "sg:phone":"+1 301 824 6878",
    "sg:postcode":"21783",
    "sg:province":"MD",
    "sg:tags":[
        "drywall",
        "contractor"
    ],
    "wof:name":"Eric Viar Drywall",
    "wof:placetype":"venue"
},
  "geometry": {"coordinates":[-77.57100699999999,39.657242],"type":"Point"}
}