{
  "type": "Feature",
  "properties": {
    "addr:full":"600 Ridgely Ave Annapolis MD 21401",
    "addr:housenumber":"600",
    "addr:postcode":"21401",
    "addr:street":"Ridgely Ave",
    "iso:country":"US",
    "sg:address":"600 Ridgely Ave",
    "sg:city":"Annapolis",
    "sg:classifiers":[
        {
            "category":"Health Services",
            "subcategory":"Health Practitioner",
            "type":"Services"
        }
    ],
    "sg:phone":"+1 410 266 8555",
    "sg:postcode":"21401",
    "sg:province":"MD",
    "wof:name":"Elizabeth Sherwood",
    "wof:placetype":"venue"
},
  "geometry": {"coordinates":[-76.513166,38.995798],"type":"Point"}
}