{
  "type": "Feature",
  "properties": {
    "iso:country":"US",
    "sg:address":"8812 Mary Mead Ct",
    "sg:city":"Potomac",
    "sg:classifiers":[
        {
            "category":"Professional",
            "subcategory":"Management & Consulting",
            "type":"Services"
        }
    ],
    "sg:phone":"+1 301 299 4820",
    "sg:postcode":"20854",
    "sg:province":"MD",
    "sg:tags":[
        "marketing",
        "consultant"
    ],
    "wof:name":"QSI Inc",
    "wof:placetype":"venue"
},
  "geometry": {"coordinates":[-77.182375,39.015308],"type":"Point"}
}