{
  "type": "Feature",
  "properties": {
    "iso:country":"US",
    "sg:address":"3227 Crain Hwy",
    "sg:city":"Waldorf",
    "sg:classifiers":[
        {
            "category":"Shopping",
            "subcategory":"Jewelry",
            "type":"Retail Goods"
        }
    ],
    "sg:phone":"+1 301 645 0499",
    "sg:postcode":"20603",
    "sg:province":"MD",
    "sg:tags":[
        "jeweler"
    ],
    "wof:name":"J W Jewelers",
    "wof:placetype":"venue"
},
  "geometry": {"coordinates":[-76.913586,38.623779],"type":"Point"}
}