{
  "type": "Feature",
  "properties": {
    "iso:country":"US",
    "sg:address":"1201 E 25th St",
    "sg:city":"Baltimore",
    "sg:classifiers":[
        {
            "category":"Retail",
            "subcategory":"Auto Repair",
            "type":"Services"
        }
    ],
    "sg:phone":"+1 410 243 5443",
    "sg:postcode":"21218",
    "sg:province":"MD",
    "wof:name":"Y L E Auto Body & Fender",
    "wof:placetype":"venue"
},
  "geometry": {"coordinates":[-76.59819,39.31731],"type":"Point"}
}