{
  "type": "Feature",
  "properties": {
    "addr:full":"227 Bank St Chesapeake City MD 21915",
    "addr:housenumber":"227",
    "addr:postcode":"21915",
    "addr:street":"Bank St",
    "iso:country":"US",
    "sg:address":"227 Bank St",
    "sg:city":"Chesapeake City",
    "sg:classifiers":[
        {
            "category":"Freight",
            "type":"Transportation"
        }
    ],
    "sg:phone":"+1 410 885 2992",
    "sg:postcode":"21915",
    "sg:province":"MD",
    "sg:tags":[
        "operator",
        "local",
        "trucking"
    ],
    "wof:name":"Nonantum Farm Inc",
    "wof:placetype":"venue"
},
  "geometry": {"coordinates":[-75.812974,39.530631],"type":"Point"}
}