{
  "type": "Feature",
  "properties": {
    "addr:full":"531 N Bentz St Frederick MD 21701",
    "addr:housenumber":"531",
    "addr:postcode":"21701",
    "addr:street":"N Bentz St",
    "iso:country":"US",
    "sg:address":"531 N Bentz St",
    "sg:city":"Frederick",
    "sg:classifiers":[
        {
            "category":"Food & Beverages",
            "subcategory":"Liquor & Beverages",
            "type":"Retail Goods"
        }
    ],
    "sg:phone":"+1 301 663 3891",
    "sg:postcode":"21701",
    "sg:province":"MD",
    "wof:name":"Frederick Discount Liquors",
    "wof:placetype":"venue"
},
  "geometry": {"coordinates":[-77.41253,39.420914],"type":"Point"}
}