{
  "type": "Feature",
  "properties": {
    "addr:full":"9 W Aylesbury Rd Lutherville MD 21093",
    "addr:housenumber":"9",
    "addr:postcode":"21093",
    "addr:street":"W Aylesbury Rd",
    "iso:country":"US",
    "sg:address":"9 W Aylesbury Rd",
    "sg:city":"Lutherville",
    "sg:classifiers":[
        {
            "category":"Food & Beverages",
            "subcategory":"Candy",
            "type":"Retail Goods"
        }
    ],
    "sg:phone":"+1 410 252 6601",
    "sg:postcode":"21093",
    "sg:province":"MD",
    "sg:tags":[
        "confectionery"
    ],
    "wof:name":"Glarus Chocolatier",
    "wof:placetype":"venue"
},
  "geometry": {"coordinates":[-76.626412,39.43506],"type":"Point"}
}