{
  "type": "Feature",
  "properties": {
    "addr:full":"6100 Dobbin Rd Columbia MD 21045",
    "addr:housenumber":"6100",
    "addr:postcode":"21045",
    "addr:street":"Dobbin Rd",
    "iso:country":"US",
    "sg:address":"6100 Dobbin Rd",
    "sg:city":"Columbia",
    "sg:classifiers":[
        {
            "category":"Home & Garden",
            "subcategory":"Carpets & Floor Coverings",
            "type":"Retail Goods"
        },
        {
            "category":"Home & Garden",
            "subcategory":"Building Materials",
            "type":"Retail Goods"
        },
        {
            "category":"Building & Trades",
            "subcategory":"Construction",
            "type":"Services"
        },
        {
            "category":"Wholesale",
            "subcategory":"Home Furnishings",
            "type":"Manufacturing & Wholesale Goods"
        }
    ],
    "sg:phone":"+1 443 259 7900",
    "sg:postcode":"21045",
    "sg:province":"MD",
    "sg:tags":[
        "blind",
        "carpeting",
        "fixture",
        "contractor",
        "equipment",
        "lighting",
        "shade",
        "interior",
        "design"
    ],
    "sg:website":"www.expo.com",
    "wof:name":"EXPO Design Center",
    "wof:placetype":"venue"
},
  "geometry": {"coordinates":[-76.81123700000001,39.196832],"type":"Point"}
}