{
  "type": "Feature",
  "properties": {
    "iso:country":"US",
    "sg:address":"15 Visitors Center Dr",
    "sg:city":"Mc Henry",
    "sg:classifiers":[
        {
            "category":"Organizations",
            "subcategory":"Professional Association",
            "type":"Services"
        }
    ],
    "sg:phone":"+1 301 387 4386",
    "sg:postcode":"21541",
    "sg:province":"MD",
    "sg:tags":[
        "chambers",
        "commerce"
    ],
    "wof:name":"Garrett County Chamber-Cmmrc",
    "wof:placetype":"venue"
},
  "geometry": {"coordinates":[-79.35909700000001,39.561707],"type":"Point"}
}