{
  "type": "Feature",
  "properties": {
    "addr:full":"109 N Salisbury Blvd Salisbury MD 21801",
    "addr:housenumber":"109",
    "addr:postcode":"21801",
    "addr:street":"N Salisbury Blvd",
    "iso:country":"US",
    "sg:address":"109 N Salisbury Blvd",
    "sg:city":"Salisbury",
    "sg:classifiers":[
        {
            "category":"Autos & Motor Vehicles",
            "subcategory":"Auto Supplies",
            "type":"Retail Goods"
        }
    ],
    "sg:phone":"+1 410 749 9119",
    "sg:postcode":"21801",
    "sg:province":"MD",
    "sg:tags":[
        "tire"
    ],
    "wof:name":"M D Tire Ctr",
    "wof:placetype":"venue"
},
  "geometry": {"coordinates":[-75.595477,38.367224],"type":"Point"}
}