{
  "type": "Feature",
  "properties": {
    "iso:country":"US",
    "sg:address":"2410 Crofton Blvd",
    "sg:city":"Crofton",
    "sg:classifiers":[
        {
            "category":"Manufacturing",
            "subcategory":"Printing",
            "type":"Manufacturing & Wholesale Goods"
        }
    ],
    "sg:phone":"+1 301 261 0522",
    "sg:postcode":"21114",
    "sg:province":"MD",
    "sg:tags":[
        "printer"
    ],
    "wof:name":"MHS Printing Enterprises Inc",
    "wof:placetype":"venue"
},
  "geometry": {"coordinates":[-76.69785,39.01714],"type":"Point"}
}