{
  "type": "Feature",
  "properties": {
    "iso:country":"US",
    "sg:address":"3542 Dean Dr",
    "sg:city":"Hyattsville",
    "sg:classifiers":[
        {
            "category":"Freight",
            "type":"Transportation"
        }
    ],
    "sg:phone":"+1 301 343 0195",
    "sg:postcode":"20782",
    "sg:province":"MD",
    "sg:tags":[
        "operator",
        "local",
        "trucking"
    ],
    "wof:name":"Fuentes Trucking",
    "wof:placetype":"venue"
},
  "geometry": {"coordinates":[-76.96087,38.973203],"type":"Point"}
}