{
  "type": "Feature",
  "properties": {
    "addr:full":"5410 Edson Ln Ste 300 Rockville MD 20852",
    "addr:housenumber":"5410",
    "addr:postcode":"20852",
    "addr:street":"Edson Ln Ste 300",
    "iso:country":"US",
    "sg:address":"5410 Edson Ln Ste 300",
    "sg:city":"Rockville",
    "sg:classifiers":[
        {
            "category":"Professional",
            "subcategory":"Testing Lab",
            "type":"Services"
        }
    ],
    "sg:phone":"+1 301 893 2026",
    "sg:postcode":"20852",
    "sg:province":"MD",
    "sg:tags":[
        "apparatus"
    ],
    "sg:website":"http://www.sensormatic.com",
    "wof:name":"Sensormatic Electronics",
    "wof:placetype":"venue"
},
  "geometry": {"coordinates":[-77.109962,39.040315],"type":"Point"}
}