{
  "type": "Feature",
  "properties": {
    "addr:full":"1921 E Pratt St Baltimore MD 21231",
    "addr:housenumber":"1921",
    "addr:postcode":"21231",
    "addr:street":"E Pratt St",
    "iso:country":"US",
    "sg:address":"1921 E Pratt St",
    "sg:city":"Baltimore",
    "sg:classifiers":[
        {
            "category":"Professional",
            "subcategory":"Business Services",
            "type":"Services"
        }
    ],
    "sg:phone":"+1 443 708 4385",
    "sg:postcode":"21231",
    "sg:province":"MD",
    "sg:tags":[
        "consultant",
        "coach"
    ],
    "wof:name":"Bolin International Consulting",
    "wof:placetype":"venue"
},
  "geometry": {"coordinates":[-76.58961499999999,39.28941],"type":"Point"}
}