{
  "type": "Feature",
  "properties": {
    "iso:country":"US",
    "sg:address":"10215 Fernwood Rd Ste 98",
    "sg:city":"Bethesda",
    "sg:classifiers":[
        {
            "category":"Health Services",
            "subcategory":"Doctor",
            "type":"Services"
        }
    ],
    "sg:phone":"+1 301 493 6404",
    "sg:postcode":"20817",
    "sg:province":"MD",
    "sg:tags":[
        "physician",
        "pediatrics-otorhinolaryngology",
        "surgeons",
        "otorhinolaryngology",
        "nose",
        "throat",
        "surgeon",
        "ear"
    ],
    "wof:name":"Cataract & Laser Eye Institute",
    "wof:placetype":"venue"
},
  "geometry": {"coordinates":[-77.135046,39.022656],"type":"Point"}
}