{
  "type": "Feature",
  "properties": {
    "iso:country":"US",
    "sg:address":"12602 Glissans Mill Rd",
    "sg:city":"Mount Airy",
    "sg:phone":"+1 301 829 0412",
    "sg:postcode":"21771",
    "sg:province":"MD",
    "sg:tags":[
        "farm",
        "field",
        "corn",
        "crop"
    ],
    "wof:name":"Glisson Farms Inc",
    "wof:placetype":"venue"
},
  "geometry": {"coordinates":[-77.234658,39.441833],"type":"Point"}
}