{
  "type": "Feature",
  "properties": {
    "iso:country":"US",
    "sg:address":"5921 Moravia Park Dr",
    "sg:city":"Baltimore",
    "sg:classifiers":[
        {
            "category":"Retail",
            "subcategory":"Auto Repair",
            "type":"Services"
        }
    ],
    "sg:phone":"+1 410 325 1800",
    "sg:postcode":"21206",
    "sg:province":"MD",
    "wof:name":"L & A Industrial Truck Service",
    "wof:placetype":"venue"
},
  "geometry": {"coordinates":[-76.547302,39.315701],"type":"Point"}
}