{
  "type": "Feature",
  "properties": {
    "addr:full":"3002 Trellis Ln Abingdon MD 21009",
    "addr:housenumber":"3002",
    "addr:postcode":"21009",
    "addr:street":"Trellis Ln",
    "iso:country":"US",
    "sg:address":"3002 Trellis Ln",
    "sg:city":"Abingdon",
    "sg:classifiers":[
        {
            "category":"Building & Trades",
            "subcategory":"Plumbing",
            "type":"Services"
        }
    ],
    "sg:phone":"+1 410 569 5115",
    "sg:postcode":"21009",
    "sg:province":"MD",
    "sg:tags":[
        "plumbing",
        "contractor"
    ],
    "wof:name":"Pete's Plumbing & Heating Inc",
    "wof:placetype":"venue"
},
  "geometry": {"coordinates":[-76.316667,39.475526],"type":"Point"}
}