{
  "type": "Feature",
  "properties": {
    "addr:full":"411 N Fruitland Blvd Salisbury MD 21801",
    "addr:housenumber":"411",
    "addr:postcode":"21801",
    "addr:street":"N Fruitland Blvd",
    "iso:country":"US",
    "sg:address":"411 N Fruitland Blvd",
    "sg:city":"Salisbury",
    "sg:classifiers":[
        {
            "category":"Shopping",
            "subcategory":"Department Store",
            "type":"Retail Goods"
        }
    ],
    "sg:phone":"+1 410 219 5151",
    "sg:postcode":"21801",
    "sg:province":"MD",
    "sg:tags":[
        "shop"
    ],
    "wof:name":"Dollar Tree",
    "wof:placetype":"venue"
},
  "geometry": {"coordinates":[-75.615129,38.327362],"type":"Point"}
}