{
  "type": "Feature",
  "properties": {
    "addr:full":"2941 N Charles St Baltimore MD 21218",
    "addr:housenumber":"2941",
    "addr:postcode":"21218",
    "addr:street":"N Charles St",
    "iso:country":"US",
    "sg:address":"2941 N Charles St",
    "sg:city":"Baltimore",
    "sg:classifiers":[
        {
            "category":"Organizations",
            "subcategory":"Religious Organization",
            "type":"Services"
        }
    ],
    "sg:phone":"+1 410 243 7066",
    "sg:postcode":"21218",
    "sg:province":"MD",
    "wof:name":"Catholic Campus Ministry",
    "wof:placetype":"venue"
},
  "geometry": {"coordinates":[-76.617155,39.323972],"type":"Point"}
}