{
  "type": "Feature",
  "properties": {
    "iso:country":"US",
    "sg:address":"425 E Baltimore St",
    "sg:city":"Baltimore",
    "sg:classifiers":[
        {
            "category":"Organizations",
            "subcategory":"Community Association",
            "type":"Services"
        }
    ],
    "sg:phone":"+1 410 385 0475",
    "sg:postcode":"21202",
    "sg:province":"MD",
    "sg:tags":[
        "club",
        "nightlife"
    ],
    "sg:website":"http://www.kougl.com",
    "wof:name":"Club Harem",
    "wof:placetype":"venue"
},
  "geometry": {"coordinates":[-76.6091,39.289902],"type":"Point"}
}