{
  "type": "Feature",
  "properties": {
    "addr:full":"12505 Coastal Hwy Ocean City MD 21842",
    "addr:housenumber":"12505",
    "addr:postcode":"21842",
    "addr:street":"Coastal Hwy",
    "iso:country":"US",
    "sg:address":"12505 Coastal Hwy",
    "sg:city":"Ocean City",
    "sg:classifiers":[
        {
            "category":"Food & Beverages",
            "subcategory":"Bakery",
            "type":"Retail Goods"
        }
    ],
    "sg:phone":"+1 410 250 5944",
    "sg:postcode":"21842",
    "sg:province":"MD",
    "wof:name":"Bagels N Buns LC",
    "wof:placetype":"venue"
},
  "geometry": {"coordinates":[-75.05507299999999,38.431357],"type":"Point"}
}