{
  "type": "Feature",
  "properties": {
    "iso:country":"US",
    "sg:address":"7847 Ocean Gateway",
    "sg:city":"Easton",
    "sg:classifiers":[
        {
            "category":"Professional",
            "subcategory":"Employment Agencies",
            "type":"Services"
        }
    ],
    "sg:phone":"+1 410 822 3030",
    "sg:postcode":"21601",
    "sg:province":"MD",
    "sg:tags":[
        "consultant",
        "outplacement"
    ],
    "wof:name":"US Economic Employment Dept",
    "wof:placetype":"venue"
},
  "geometry": {"coordinates":[-76.06047,38.763909],"type":"Point"}
}