{
  "type": "Feature",
  "properties": {
    "addr:full":"204 South St Accident MD 21520",
    "addr:housenumber":"204",
    "addr:postcode":"21520",
    "addr:street":"South St",
    "iso:country":"US",
    "sg:address":"204 South St",
    "sg:city":"Accident",
    "sg:classifiers":[
        {
            "category":"Social Services",
            "type":"Services"
        }
    ],
    "sg:phone":"+1 301 746 7404",
    "sg:postcode":"21520",
    "sg:province":"MD",
    "sg:tags":[
        "care",
        "center",
        "day"
    ],
    "wof:name":"Garrett Covenant House",
    "wof:placetype":"venue"
},
  "geometry": {"coordinates":[-79.32019200000001,39.627053],"type":"Point"}
}