{
  "type": "Feature",
  "properties": {
    "addr:full":"8208 Reservoir Rd Fulton MD 20759",
    "addr:housenumber":"8208",
    "addr:postcode":"20759",
    "addr:street":"Reservoir Rd",
    "iso:country":"US",
    "sg:address":"8208 Reservoir Rd",
    "sg:city":"Fulton",
    "sg:classifiers":[
        {
            "category":"Building & Trades",
            "subcategory":"Construction",
            "type":"Services"
        }
    ],
    "sg:phone":"+1 240 456 0336",
    "sg:postcode":"20759",
    "sg:province":"MD",
    "sg:tags":[
        "general",
        "contractor"
    ],
    "wof:name":"RES Construction",
    "wof:placetype":"venue"
},
  "geometry": {"coordinates":[-76.94131,39.146769],"type":"Point"}
}