{
  "type": "Feature",
  "properties": {
    "addr:full":"7712 Charleston Dr Bethesda MD 20817",
    "addr:housenumber":"7712",
    "addr:postcode":"20817",
    "addr:street":"Charleston Dr",
    "iso:country":"US",
    "sg:address":"7712 Charleston Dr",
    "sg:city":"Bethesda",
    "sg:classifiers":[
        {
            "category":"Health Services",
            "subcategory":"Dentist",
            "type":"Services"
        }
    ],
    "sg:phone":"+1 301 365 0353",
    "sg:postcode":"20817",
    "sg:province":"MD",
    "wof:name":"Tenen Charles DDS",
    "wof:placetype":"venue"
},
  "geometry": {"coordinates":[-77.157802,39.017083],"type":"Point"}
}