{
  "type": "Feature",
  "properties": {
    "addr:full":"8721 Baltimore Ave College Park MD 20740",
    "addr:housenumber":"8721",
    "addr:postcode":"20740",
    "addr:street":"Baltimore Ave",
    "iso:country":"US",
    "sg:address":"8721 Baltimore Ave",
    "sg:city":"College Park",
    "sg:classifiers":[
        {
            "category":"Professional",
            "type":"Services"
        }
    ],
    "sg:phone":"+1 301 474 0177",
    "sg:postcode":"20740",
    "sg:province":"MD",
    "sg:tags":[
        "establishment"
    ],
    "wof:name":"Xtra Mart",
    "wof:placetype":"venue"
},
  "geometry": {"coordinates":[-76.931577,38.996849],"type":"Point"}
}