{
  "type": "Feature",
  "properties": {
    "iso:country":"US",
    "sg:address":"4152 Henhawk Ct",
    "sg:city":"Ellicott City",
    "sg:classifiers":[
        {
            "category":"Professional",
            "subcategory":"Employment Agencies",
            "type":"Services"
        }
    ],
    "sg:phone":"+1 410 750 3093",
    "sg:postcode":"21042",
    "sg:province":"MD",
    "sg:tags":[
        "opportunity"
    ],
    "wof:name":"Vettek Inc",
    "wof:placetype":"venue"
},
  "geometry": {"coordinates":[-76.84007699999999,39.256824],"type":"Point"}
}