{
  "type": "Feature",
  "properties": {
    "iso:country":"US",
    "sg:address":"1100 Brown Ave",
    "sg:city":"Cumberland",
    "sg:classifiers":[
        {
            "category":"Government",
            "subcategory":"Office",
            "type":"Public Place"
        }
    ],
    "sg:phone":"+1 301 759 2619",
    "sg:postcode":"21502",
    "sg:province":"MD",
    "sg:tags":[
        "state",
        "security"
    ],
    "wof:name":"Military Dept",
    "wof:placetype":"venue"
},
  "geometry": {"coordinates":[-78.788824,39.641475],"type":"Point"}
}