{
  "type": "Feature",
  "properties": {
    "addr:full":"3107 Saint Paul St Baltimore MD 21218",
    "addr:housenumber":"3107",
    "addr:postcode":"21218",
    "addr:street":"Saint Paul St",
    "iso:country":"US",
    "sg:address":"3107 Saint Paul St",
    "sg:city":"Baltimore",
    "sg:classifiers":[
        {
            "category":"Bars & Pubs",
            "type":"Food & Drink"
        },
        {
            "category":"Restaurant",
            "type":"Food & Drink"
        },
        {
            "category":"Bars & Pubs",
            "subcategory":"Lounge",
            "type":"Food & Drink"
        }
    ],
    "sg:phone":"+1 410 243 1611",
    "sg:postcode":"21218",
    "sg:province":"MD",
    "sg:tags":[
        "brew",
        "style",
        "family",
        "cocktail"
    ],
    "sg:website":"http://www.boski.com",
    "wof:name":"Charles Village Pub",
    "wof:placetype":"venue"
},
  "geometry": {"coordinates":[-76.615594,39.326152],"type":"Point"}
}