{
  "type": "Feature",
  "properties": {
    "addr:full":"811 Uniontown Rd Westminster MD 21158",
    "addr:housenumber":"811",
    "addr:postcode":"21158",
    "addr:street":"Uniontown Rd",
    "iso:country":"US",
    "sg:address":"811 Uniontown Rd",
    "sg:city":"Westminster",
    "sg:classifiers":[
        {
            "category":"Education",
            "subcategory":"School",
            "type":"Public Place"
        }
    ],
    "sg:phone":"+1 410 751 3222",
    "sg:postcode":"21158",
    "sg:province":"MD",
    "wof:name":"Westminster Elementary School",
    "wof:placetype":"venue"
},
  "geometry": {"coordinates":[-77.02453300000001,39.580438],"type":"Point"}
}