{
  "type": "Feature",
  "properties": {
    "iso:country":"US",
    "sg:address":"500 McCormick Dr",
    "sg:city":"Glen Burnie",
    "sg:classifiers":[
        {
            "category":"Wholesale",
            "subcategory":"Office Equipment",
            "type":"Manufacturing & Wholesale Goods"
        }
    ],
    "sg:phone":"+1 410 766 0200",
    "sg:postcode":"21061",
    "sg:province":"MD",
    "sg:tags":[
        "machine",
        "duplicating",
        "copying"
    ],
    "sg:website":"www.icponline.com",
    "wof:name":"Innovative Copy Products",
    "wof:placetype":"venue"
},
  "geometry": {"coordinates":[-76.67401,39.160707],"type":"Point"}
}