{
  "type": "Feature",
  "properties": {
    "iso:country":"US",
    "sg:address":"660 S River Landing Rd",
    "sg:city":"Edgewater",
    "sg:classifiers":[
        {
            "category":"Professional",
            "type":"Services"
        }
    ],
    "sg:phone":"+1 410 974 9422",
    "sg:postcode":"21037",
    "sg:province":"MD",
    "sg:tags":[
        "consultant",
        "geological"
    ],
    "wof:name":"Douglas W Edsall",
    "wof:placetype":"venue"
},
  "geometry": {"coordinates":[-76.547535,38.94435],"type":"Point"}
}