{
  "type": "Feature",
  "properties": {
    "addr:full":"7101 Radnor Rd Bethesda MD 20817",
    "addr:housenumber":"7101",
    "addr:postcode":"20817",
    "addr:street":"Radnor Rd",
    "iso:country":"US",
    "sg:address":"7101 Radnor Rd",
    "sg:city":"Bethesda",
    "sg:classifiers":[
        {
            "category":"Professional",
            "subcategory":"Research",
            "type":"Services"
        }
    ],
    "sg:phone":"+1 301 320 9591",
    "sg:postcode":"20817",
    "sg:province":"MD",
    "wof:name":"Changle Inc",
    "wof:placetype":"venue"
},
  "geometry": {"coordinates":[-77.11497300000001,38.98054],"type":"Point"}
}