{
  "type": "Feature",
  "properties": {
    "addr:full":"9122 Bronze Bell Cir Columbia MD 21045",
    "addr:housenumber":"9122",
    "addr:postcode":"21045",
    "addr:street":"Bronze Bell Cir",
    "iso:country":"US",
    "sg:address":"9122 Bronze Bell Cir",
    "sg:city":"Columbia",
    "sg:classifiers":[
        {
            "category":"Retail",
            "subcategory":"Repair Shop",
            "type":"Services"
        }
    ],
    "sg:phone":"+1 410 730 7838",
    "sg:postcode":"21045",
    "sg:province":"MD",
    "sg:tags":[
        "equipment"
    ],
    "wof:name":"Metro Appliance Svc",
    "wof:placetype":"venue"
},
  "geometry": {"coordinates":[-76.82145300000001,39.209182],"type":"Point"}
}