{
  "type": "Feature",
  "properties": {
    "addr:full":"737 Deepdene Rd Baltimore MD 21210",
    "addr:housenumber":"737",
    "addr:postcode":"21210",
    "addr:street":"Deepdene Rd",
    "iso:country":"US",
    "sg:address":"737 Deepdene Rd",
    "sg:city":"Baltimore",
    "sg:classifiers":[
        {
            "category":"Shopping",
            "subcategory":"Books",
            "type":"Retail Goods"
        }
    ],
    "sg:phone":"+1 410 532 2000",
    "sg:postcode":"21210",
    "sg:province":"MD",
    "sg:tags":[
        "bookstore"
    ],
    "sg:website":"www.thecbstore.com",
    "wof:name":"The Children's Bookstore",
    "wof:placetype":"venue"
},
  "geometry": {"coordinates":[-76.634399,39.3564],"type":"Point"}
}