{
  "type": "Feature",
  "properties": {
    "iso:country":"US",
    "sg:address":"503 E Seminary Ave",
    "sg:city":"Towson",
    "sg:classifiers":[
        {
            "category":"Building & Trades",
            "subcategory":"Landscaping Services",
            "type":"Services"
        }
    ],
    "sg:phone":"+1 410 828 0509",
    "sg:postcode":"21286",
    "sg:province":"MD",
    "sg:tags":[
        "landscape",
        "contractor"
    ],
    "wof:name":"Azaleas To Zinnias",
    "wof:placetype":"venue"
},
  "geometry": {"coordinates":[-76.59504200000001,39.424928],"type":"Point"}
}