{
  "type": "Feature",
  "properties": {
    "iso:country":"US",
    "sg:address":"9702 Wedgewood Dr",
    "sg:city":"Fort Washington",
    "sg:classifiers":[
        {
            "category":"Building & Trades",
            "subcategory":"Landscaping Services",
            "type":"Services"
        }
    ],
    "sg:phone":"+1 301 567 2385",
    "sg:postcode":"20744",
    "sg:province":"MD",
    "sg:tags":[
        "landscape"
    ],
    "wof:name":"Dallas Hugh Lee & Carolyn",
    "wof:placetype":"venue"
},
  "geometry": {"coordinates":[-77.017135,38.755528],"type":"Point"}
}