{
  "type": "Feature",
  "properties": {
    "iso:country":"US",
    "sg:address":"2127 Shuresville Rd",
    "sg:city":"Darlington",
    "sg:classifiers":[
        {
            "category":"Home & Garden",
            "subcategory":"Carpets & Floor Coverings",
            "type":"Retail Goods"
        }
    ],
    "sg:phone":"+1 410 803 2724",
    "sg:postcode":"21034",
    "sg:province":"MD",
    "sg:tags":[
        "flooring",
        "contractor"
    ],
    "wof:name":"Darlington Sealer",
    "wof:placetype":"venue"
},
  "geometry": {"coordinates":[-76.199484,39.636951],"type":"Point"}
}