{
  "type": "Feature",
  "properties": {
    "addr:full":"11520 Laurel Bowie Rd Laurel MD 20708",
    "addr:housenumber":"11520",
    "addr:postcode":"20708",
    "addr:street":"Laurel Bowie Rd",
    "iso:country":"US",
    "sg:address":"11520 Laurel Bowie Rd",
    "sg:city":"Laurel",
    "sg:classifiers":[
        {
            "category":"Building & Trades",
            "subcategory":"Construction",
            "type":"Services"
        }
    ],
    "sg:phone":"+1 301 725 3433",
    "sg:postcode":"20708",
    "sg:province":"MD",
    "sg:tags":[
        "builder",
        "deck"
    ],
    "sg:website":"www.lefflerconstruction.com",
    "wof:name":"Leffler Construction",
    "wof:placetype":"venue"
},
  "geometry": {"coordinates":[-76.82706399999999,39.046283],"type":"Point"}
}