{
  "type": "Feature",
  "properties": {
    "iso:country":"US",
    "sg:address":"4000 Virginia Pl",
    "sg:city":"Bethesda",
    "sg:classifiers":[
        {
            "category":"Social Services",
            "subcategory":"Child Care",
            "type":"Services"
        }
    ],
    "sg:phone":"+1 301 320 6780",
    "sg:postcode":"20816",
    "sg:province":"MD",
    "sg:tags":[
        "day"
    ],
    "wof:name":"Cabin John-Brookmont Program",
    "wof:placetype":"venue"
},
  "geometry": {"coordinates":[-77.12200199999999,38.944698],"type":"Point"}
}