{
  "type": "Feature",
  "properties": {
    "iso:country":"US",
    "sg:address":"2101 Brightseat Rd",
    "sg:city":"Hyattsville",
    "sg:classifiers":[
        {
            "category":"Shopping",
            "subcategory":"Department Store",
            "type":"Retail Goods"
        }
    ],
    "sg:phone":"+1 301 322 6200",
    "sg:postcode":"20785",
    "sg:province":"MD",
    "sg:website":"www.sears.com",
    "wof:name":"Sears Roebuck and Co",
    "wof:placetype":"venue"
},
  "geometry": {"coordinates":[-76.860298,38.916801],"type":"Point"}
}