{
  "type": "Feature",
  "properties": {
    "iso:country":"US",
    "sg:address":"5061 E Eager St",
    "sg:city":"Baltimore",
    "sg:classifiers":[
        {
            "category":"Recreation",
            "type":"Entertainment"
        }
    ],
    "sg:phone":"+1 410 396 9089",
    "sg:postcode":"21205",
    "sg:province":"MD",
    "sg:tags":[
        "center"
    ],
    "wof:name":"Carroll F Cook Recreation Ctr",
    "wof:placetype":"venue"
},
  "geometry": {"coordinates":[-76.553687,39.30484],"type":"Point"}
}