{
  "type": "Feature",
  "properties": {
    "iso:country":"US",
    "sg:address":"16813 Cashell Rd",
    "sg:city":"Olney",
    "sg:classifiers":[
        {
            "category":"Real Estate",
            "subcategory":"Real Estate Agent",
            "type":"Services"
        }
    ],
    "sg:phone":"+1 301 924 4111",
    "sg:postcode":"20832",
    "sg:province":"MD",
    "sg:tags":[
        "manager"
    ],
    "wof:name":"Steve Graham CRS Gri",
    "wof:placetype":"venue"
},
  "geometry": {"coordinates":[-77.085583,39.133944],"type":"Point"}
}