{
  "type": "Feature",
  "properties": {
    "iso:country":"US",
    "sg:address":"429 Wingate Rd",
    "sg:city":"Baltimore",
    "sg:classifiers":[
        {
            "category":"Personal",
            "type":"Services"
        },
        {
            "category":"Professional",
            "subcategory":"Art Services",
            "type":"Services"
        }
    ],
    "sg:phone":"+1 410 366 2166",
    "sg:postcode":"21210",
    "sg:province":"MD",
    "sg:tags":[
        "photography",
        "videography",
        "wedding"
    ],
    "wof:name":"Hartlove Chnris Photographer",
    "wof:placetype":"venue"
},
  "geometry": {"coordinates":[-76.629013,39.343626],"type":"Point"}
}