{
  "type": "Feature",
  "properties": {
    "addr:full":"Wildewood Shopping C California MD 20619",
    "addr:housenumber":"c",
    "addr:postcode":"20619",
    "addr:street":"California",
    "iso:country":"US",
    "sg:address":"Wildewood Shopping C",
    "sg:city":"California",
    "sg:classifiers":[
        {
            "category":"Health Services",
            "subcategory":"Doctor",
            "type":"Services"
        }
    ],
    "sg:phone":"+1 301 862 3721",
    "sg:postcode":"20619",
    "sg:province":"MD",
    "sg:tags":[
        "medicine",
        "practice",
        "internal",
        "family"
    ],
    "wof:name":"Jani Parul S MD",
    "wof:placetype":"venue"
},
  "geometry": {"coordinates":[-76.5159,38.293499],"type":"Point"}
}