{
  "type": "Feature",
  "properties": {
    "iso:country":"US",
    "sg:address":"3007 Emmorton Rd",
    "sg:city":"Abingdon",
    "sg:classifiers":[
        {
            "category":"Professional",
            "subcategory":"Engineering",
            "type":"Services"
        }
    ],
    "sg:phone":"+1 443 512 8800",
    "sg:postcode":"21009",
    "sg:province":"MD",
    "sg:tags":[
        "engineer"
    ],
    "wof:name":"Optec Inc",
    "wof:placetype":"venue"
},
  "geometry": {"coordinates":[-76.30898000000001,39.474334],"type":"Point"}
}