{
  "type": "Feature",
  "properties": {
    "iso:country":"US",
    "sg:address":"3230 Wheeler Rd SE",
    "sg:city":"Washington",
    "sg:classifiers":[
        {
            "category":"Building & Trades",
            "subcategory":"Construction",
            "type":"Services"
        }
    ],
    "sg:phone":"+1 202 561 2661",
    "sg:postcode":"20032",
    "sg:province":"MD",
    "sg:tags":[
        "masonry",
        "contractor"
    ],
    "wof:name":"T & D Co",
    "wof:placetype":"venue"
},
  "geometry": {"coordinates":[-76.99396,38.842707],"type":"Point"}
}