{
  "type": "Feature",
  "properties": {
    "iso:country":"US",
    "sg:address":"10320 Little Patuxent Pkwy",
    "sg:city":"Columbia",
    "sg:classifiers":[
        {
            "category":"Professional",
            "subcategory":"Lawyer & Legal Services",
            "type":"Services"
        }
    ],
    "sg:phone":"+1 410 997 6300",
    "sg:postcode":"21044",
    "sg:province":"MD",
    "sg:tags":[
        "attorney"
    ],
    "wof:name":"Robert W Guth",
    "wof:placetype":"venue"
},
  "geometry": {"coordinates":[-76.85831399999999,39.217959],"type":"Point"}
}