{
  "type": "Feature",
  "properties": {
    "addr:full":"135 Deep Creek Dr Mc Henry MD 21541",
    "addr:housenumber":"135",
    "addr:postcode":"21541",
    "addr:street":"Deep Creek Dr",
    "iso:country":"US",
    "sg:address":"135 Deep Creek Dr",
    "sg:city":"Mc Henry",
    "sg:classifiers":[
        {
            "category":"Building & Trades",
            "subcategory":"Equipment Rental",
            "type":"Services"
        }
    ],
    "sg:phone":"+1 301 387 5827",
    "sg:postcode":"21541",
    "sg:province":"MD",
    "sg:tags":[
        "television"
    ],
    "wof:name":"Remote Equipment Rentals Inc",
    "wof:placetype":"venue"
},
  "geometry": {"coordinates":[-79.34611099999999,39.537729],"type":"Point"}
}