{
  "type": "Feature",
  "properties": {
    "iso:country":"US",
    "sg:address":"9932 Liberty Rd",
    "sg:city":"Randallstown",
    "sg:classifiers":[
        {
            "category":"Professional",
            "subcategory":"Accounting & Tax Preparation",
            "type":"Services"
        }
    ],
    "sg:phone":"+1 410 655 6319",
    "sg:postcode":"21133",
    "sg:province":"MD",
    "sg:tags":[
        "return",
        "filing"
    ],
    "wof:name":"Barry J Berman Co",
    "wof:placetype":"venue"
},
  "geometry": {"coordinates":[-76.825945,39.382737],"type":"Point"}
}