{
  "type": "Feature",
  "properties": {
    "iso:country":"US",
    "sg:address":"12410 Buckley Dr",
    "sg:city":"Silver Spring",
    "sg:classifiers":[
        {
            "category":"Health Services",
            "subcategory":"Optometrist",
            "type":"Services"
        }
    ],
    "sg:phone":"+1 301 622 1044",
    "sg:postcode":"20904",
    "sg:province":"MD",
    "wof:name":"Miller Laurence W",
    "wof:placetype":"venue"
},
  "geometry": {"coordinates":[-76.996201,39.060799],"type":"Point"}
}