{
  "type": "Feature",
  "properties": {
    "iso:country":"US",
    "sg:address":"1819 Bay Ridge Ave",
    "sg:city":"Annapolis",
    "sg:classifiers":[
        {
            "category":"Real Estate",
            "subcategory":"Real Estate Agent",
            "type":"Services"
        }
    ],
    "sg:phone":"+1 410 295 3400",
    "sg:postcode":"21403",
    "sg:province":"MD",
    "wof:name":"Frontgate Realty LLC",
    "wof:placetype":"venue"
},
  "geometry": {"coordinates":[-76.492541,38.955434],"type":"Point"}
}