{
  "type": "Feature",
  "properties": {
    "addr:full":"7903 Crisford Pl Pikesville MD 21208",
    "addr:housenumber":"7903",
    "addr:postcode":"21208",
    "addr:street":"Crisford Pl",
    "iso:country":"US",
    "sg:address":"7903 Crisford Pl",
    "sg:city":"Pikesville",
    "sg:classifiers":[
        {
            "category":"Communications",
            "type":"Services"
        },
        {
            "category":"Professional",
            "subcategory":"Computer Services",
            "type":"Services"
        }
    ],
    "sg:phone":"+1 410 258 7503",
    "sg:postcode":"21208",
    "sg:province":"MD",
    "sg:tags":[
        "recovery",
        "technical",
        "consultant",
        "assistance",
        "data",
        "support",
        "software"
    ],
    "sg:website":"http://www.meyeroff-c-c.com",
    "wof:name":"Meyeroff Computer Consultants",
    "wof:placetype":"venue"
},
  "geometry": {"coordinates":[-76.74825300000001,39.361858],"type":"Point"}
}