{
  "type": "Feature",
  "properties": {
    "addr:full":"107 E 2nd Ave Oakland MD 21550",
    "addr:housenumber":"107",
    "addr:postcode":"21550",
    "addr:street":"E 2Nd Ave",
    "iso:country":"US",
    "sg:address":"107 E 2nd Ave",
    "sg:city":"Oakland",
    "sg:classifiers":[
        {
            "category":"Autos & Motor Vehicles",
            "subcategory":"Automobile Sales",
            "type":"Retail Goods"
        }
    ],
    "sg:phone":"+1 301 334 9119",
    "sg:postcode":"21550",
    "sg:province":"MD",
    "sg:tags":[
        "car",
        "dealer"
    ],
    "wof:name":"R & S Automotive & Used Cars",
    "wof:placetype":"venue"
},
  "geometry": {"coordinates":[-79.370307,39.395142],"type":"Point"}
}