{
  "type": "Feature",
  "properties": {
    "iso:country":"US",
    "sg:address":"9914 Lewis Dr",
    "sg:city":"Damascus",
    "sg:classifiers":[
        {
            "category":"Manufacturing",
            "subcategory":"Printing",
            "type":"Manufacturing & Wholesale Goods"
        }
    ],
    "sg:phone":"+1 301 253 4640",
    "sg:postcode":"20872",
    "sg:province":"MD",
    "sg:tags":[
        "commercial"
    ],
    "wof:name":"Dovetail Printing Signs",
    "wof:placetype":"venue"
},
  "geometry": {"coordinates":[-77.206091,39.288619],"type":"Point"}
}