{
  "type": "Feature",
  "properties": {
    "addr:full":"8925 Old Harford Rd Parkville MD 21234",
    "addr:housenumber":"8925",
    "addr:postcode":"21234",
    "addr:street":"Old Harford Rd",
    "iso:country":"US",
    "sg:address":"8925 Old Harford Rd",
    "sg:city":"Parkville",
    "sg:classifiers":[
        {
            "category":"Building & Trades",
            "subcategory":"Plumbing",
            "type":"Services"
        }
    ],
    "sg:phone":"+1 410 665 5164",
    "sg:postcode":"21234",
    "sg:province":"MD",
    "sg:tags":[
        "plumbing",
        "contractor"
    ],
    "wof:name":"Saffer Plumbing",
    "wof:placetype":"venue"
},
  "geometry": {"coordinates":[-76.536069,39.398537],"type":"Point"}
}