{
  "type": "Feature",
  "properties": {
    "iso:country":"US",
    "sg:address":"2483 Lake Dr",
    "sg:city":"Waldorf",
    "sg:classifiers":[
        {
            "category":"Professional",
            "subcategory":"Management & Consulting",
            "type":"Services"
        }
    ],
    "sg:phone":"+1 301 645 9600",
    "sg:postcode":"20601",
    "sg:province":"MD",
    "sg:tags":[
        "consultant",
        "training"
    ],
    "wof:name":"C G Child Training Inc",
    "wof:placetype":"venue"
},
  "geometry": {"coordinates":[-76.89582,38.645527],"type":"Point"}
}