{
  "type": "Feature",
  "properties": {
    "addr:full":"201 Ballard Ave Ste A Middle River MD 21220",
    "addr:housenumber":"201",
    "addr:postcode":"21220",
    "addr:street":"Ballard Ave Ste A",
    "iso:country":"US",
    "sg:address":"201 Ballard Ave Ste A",
    "sg:city":"Middle River",
    "sg:classifiers":[
        {
            "category":"Health Services",
            "subcategory":"Doctor",
            "type":"Services"
        }
    ],
    "sg:phone":"+1 410 574 1188",
    "sg:postcode":"21220",
    "sg:province":"MD",
    "sg:tags":[
        "surgeon",
        "oral"
    ],
    "wof:name":"Kurek Rita M DDS",
    "wof:placetype":"venue"
},
  "geometry": {"coordinates":[-76.444397,39.334301],"type":"Point"}
}