{
  "type": "Feature",
  "properties": {
    "addr:full":"8322 Dalesford Rd Parkville MD 21234",
    "addr:housenumber":"8322",
    "addr:postcode":"21234",
    "addr:street":"Dalesford Rd",
    "iso:country":"US",
    "sg:address":"8322 Dalesford Rd",
    "sg:city":"Parkville",
    "sg:classifiers":[
        {
            "category":"Wholesale",
            "subcategory":"Non-durable Goods",
            "type":"Manufacturing & Wholesale Goods"
        }
    ],
    "sg:phone":"+1 410 661 6260",
    "sg:postcode":"21234",
    "sg:province":"MD",
    "sg:tags":[
        "advertising"
    ],
    "sg:website":"www.armuproducts.com",
    "wof:name":"Armu Products",
    "wof:placetype":"venue"
},
  "geometry": {"coordinates":[-76.560447,39.389548],"type":"Point"}
}