{
  "type": "Feature",
  "properties": {
    "addr:full":"12715 River Rd Potomac MD 20854",
    "addr:housenumber":"12715",
    "addr:postcode":"20854",
    "addr:street":"River Rd",
    "iso:country":"US",
    "sg:address":"12715 River Rd",
    "sg:city":"Potomac",
    "sg:classifiers":[
        {
            "category":"Building & Trades",
            "subcategory":"Construction",
            "type":"Services"
        }
    ],
    "sg:phone":"+1 301 963 4534",
    "sg:postcode":"20854",
    "sg:province":"MD",
    "sg:tags":[
        "home",
        "builder"
    ],
    "wof:name":"Deepwell Development",
    "wof:placetype":"venue"
},
  "geometry": {"coordinates":[-77.262275,39.045715],"type":"Point"}
}