{
  "type": "Feature",
  "properties": {
    "addr:full":"8220 Stone Trail Dr Bethesda MD 20817",
    "addr:housenumber":"8220",
    "addr:postcode":"20817",
    "addr:street":"Stone Trail Dr",
    "iso:country":"US",
    "sg:address":"8220 Stone Trail Dr",
    "sg:city":"Bethesda",
    "sg:classifiers":[
        {
            "category":"Professional",
            "subcategory":"Computer Services",
            "type":"Services"
        }
    ],
    "sg:phone":"+1 301 365 4585",
    "sg:postcode":"20817",
    "sg:province":"MD",
    "sg:tags":[
        "field",
        "consulting",
        "engineering",
        "strategic"
    ],
    "wof:name":"Zem Press",
    "wof:placetype":"venue"
},
  "geometry": {"coordinates":[-77.169915,38.984255],"type":"Point"}
}