{
  "type": "Feature",
  "properties": {
    "addr:full":"121 Holy Cross Rd Street MD 21154",
    "addr:housenumber":"121",
    "addr:postcode":"21154",
    "addr:street":"Holy Cross Rd Street",
    "iso:country":"US",
    "sg:address":"121 Holy Cross Rd",
    "sg:city":"Street",
    "sg:classifiers":[
        {
            "category":"Building & Trades",
            "subcategory":"Construction",
            "type":"Services"
        }
    ],
    "sg:phone":"+1 410 557 0933",
    "sg:postcode":"21154",
    "sg:province":"MD",
    "sg:tags":[
        "home",
        "improvement"
    ],
    "wof:name":"S & A Contractors Inc",
    "wof:placetype":"venue"
},
  "geometry": {"coordinates":[-76.397097,39.665315],"type":"Point"}
}