{
  "type": "Feature",
  "properties": {
    "iso:country":"US",
    "sg:address":"2300 N Salisbury Blvd",
    "sg:city":"Salisbury",
    "sg:classifiers":[
        {
            "category":"Restaurant",
            "type":"Food & Drink"
        }
    ],
    "sg:menulink":"http://www.allmenus.com/md/parsons/103677-ruby-tuesdays/menu/",
    "sg:phone":"+1 410 546 5049",
    "sg:postcode":"21801",
    "sg:province":"MD",
    "sg:tags":[
        "burger",
        "american"
    ],
    "wof:name":"Ruby Tuesdays",
    "wof:placetype":"venue"
},
  "geometry": {"coordinates":[-75.569822,38.401925],"type":"Point"}
}