{
  "type": "Feature",
  "properties": {
    "iso:country":"US",
    "sg:address":"406 Brewster Bridge Rd",
    "sg:city":"Elkton",
    "sg:classifiers":[
        {
            "category":"Farming",
            "subcategory":"Farm",
            "type":"Manufacturing & Wholesale Goods"
        }
    ],
    "sg:phone":"+1 410 398 3067",
    "sg:postcode":"21921",
    "sg:province":"MD",
    "sg:tags":[
        "crop",
        "general"
    ],
    "wof:name":"Lawrence Birney",
    "wof:placetype":"venue"
},
  "geometry": {"coordinates":[-75.819334,39.66931],"type":"Point"}
}