{
  "type": "Feature",
  "properties": {
    "iso:country":"US",
    "sg:address":"2809 Boston St",
    "sg:city":"Baltimore",
    "sg:classifiers":[
        {
            "category":"Food & Beverages",
            "subcategory":"Liquor & Beverages",
            "type":"Retail Goods"
        }
    ],
    "sg:phone":"+1 410 276 3236",
    "sg:postcode":"21224",
    "sg:province":"MD",
    "sg:tags":[
        "beer",
        "ale"
    ],
    "wof:name":"Heineken Usa",
    "wof:placetype":"venue"
},
  "geometry": {"coordinates":[-76.576599,39.278454],"type":"Point"}
}