{
  "type": "Feature",
  "properties": {
    "iso:country":"US",
    "sg:address":"14354 Beaker Ct",
    "sg:city":"Burtonsville",
    "sg:classifiers":[
        {
            "category":"Shopping",
            "subcategory":"Gifts & Souvenirs",
            "type":"Retail Goods"
        }
    ],
    "sg:phone":"+1 301 890 2467",
    "sg:postcode":"20866",
    "sg:province":"MD",
    "sg:tags":[
        "basket",
        "parcel"
    ],
    "wof:name":"Simply Unique Gift Baskets",
    "wof:placetype":"venue"
},
  "geometry": {"coordinates":[-76.933903,39.09052],"type":"Point"}
}