{
  "type": "Feature",
  "properties": {
    "iso:country":"US",
    "sg:address":"2701 Port Covington Dr",
    "sg:city":"Baltimore",
    "sg:classifiers":[
        {
            "category":"Shopping",
            "subcategory":"Department Store",
            "type":"Retail Goods"
        },
        {
            "category":"Autos & Motor Vehicles",
            "subcategory":"Auto Supplies",
            "type":"Retail Goods"
        }
    ],
    "sg:phone":"+1 410 625 1356",
    "sg:postcode":"21230",
    "sg:province":"MD",
    "sg:tags":[
        "tire"
    ],
    "wof:name":"Wal-Mart Complex-Tire & Lube",
    "wof:placetype":"venue"
},
  "geometry": {"coordinates":[-76.60880299999999,39.259201],"type":"Point"}
}