{
  "type": "Feature",
  "properties": {
    "addr:full":"12745 Bexley Ter Silver Spring MD 20904",
    "addr:housenumber":"12745",
    "addr:postcode":"20904",
    "addr:street":"Bexley Ter",
    "iso:country":"US",
    "sg:address":"12745 Bexley Ter",
    "sg:city":"Silver Spring",
    "sg:classifiers":[
        {
            "category":"Building & Trades",
            "subcategory":"Construction",
            "type":"Services"
        }
    ],
    "sg:phone":"+1 301 586 8100",
    "sg:postcode":"20904",
    "sg:province":"MD",
    "sg:tags":[
        "home",
        "improvement"
    ],
    "wof:name":"American Bath Refinishing",
    "wof:placetype":"venue"
},
  "geometry": {"coordinates":[-76.956609,39.064685],"type":"Point"}
}