{
  "type": "Feature",
  "properties": {
    "iso:country":"US",
    "sg:address":"7843 Jersey Rd",
    "sg:city":"Salisbury",
    "sg:classifiers":[
        {
            "category":"Organizations",
            "subcategory":"Religious Organization",
            "type":"Services"
        }
    ],
    "sg:phone":"+1 410 341 4023",
    "sg:postcode":"21801",
    "sg:province":"MD",
    "sg:tags":[
        "church"
    ],
    "wof:name":"Islamic Society Of Delmarva",
    "wof:placetype":"venue"
},
  "geometry": {"coordinates":[-75.60334,38.406149],"type":"Point"}
}