{
  "type": "Feature",
  "properties": {
    "addr:full":"10630 Little Patuxent Pkwy Columbia MD 21044",
    "addr:housenumber":"10630",
    "addr:postcode":"21044",
    "addr:street":"Little Patuxent Pkwy",
    "iso:country":"US",
    "sg:address":"10630 Little Patuxent Pkwy",
    "sg:city":"Columbia",
    "sg:classifiers":[
        {
            "category":"Professional",
            "subcategory":"Management & Consulting",
            "type":"Services"
        }
    ],
    "sg:phone":"+1 410 772 2210",
    "sg:postcode":"21044",
    "sg:province":"MD",
    "sg:tags":[
        "personnel",
        "consultant"
    ],
    "wof:name":"Spherion",
    "wof:placetype":"venue"
},
  "geometry": {"coordinates":[-76.871849,39.214306],"type":"Point"}
}