{
  "type": "Feature",
  "properties": {
    "addr:full":"7377 Washington Blvd Elkridge MD 21075",
    "addr:housenumber":"7377",
    "addr:postcode":"21075",
    "addr:street":"Washington Blvd",
    "iso:country":"US",
    "sg:address":"7377 Washington Blvd",
    "sg:city":"Elkridge",
    "sg:classifiers":[
        {
            "category":"Retail",
            "subcategory":"Auto Repair",
            "type":"Services"
        }
    ],
    "sg:phone":"+1 410 799 5854",
    "sg:postcode":"21075",
    "sg:province":"MD",
    "sg:tags":[
        "exchanging",
        "engine"
    ],
    "sg:website":"www.jasperengines.com",
    "wof:name":"Jasper Engines & Transmissions",
    "wof:placetype":"venue"
},
  "geometry": {"coordinates":[-76.76858300000001,39.18068],"type":"Point"}
}