{
  "type": "Feature",
  "properties": {
    "addr:full":"2243 Thomas Run Rd Bel Air MD 21015",
    "addr:housenumber":"2243",
    "addr:postcode":"21015",
    "addr:street":"Thomas Run Rd",
    "iso:country":"US",
    "sg:address":"2243 Thomas Run Rd",
    "sg:city":"Bel Air",
    "sg:classifiers":[
        {
            "category":"Building & Trades",
            "subcategory":"Construction",
            "type":"Services"
        }
    ],
    "sg:phone":"+1 410 838 1187",
    "sg:postcode":"21015",
    "sg:province":"MD",
    "sg:tags":[
        "repair",
        "welding",
        "contractor"
    ],
    "wof:name":"Nicks Welding",
    "wof:placetype":"venue"
},
  "geometry": {"coordinates":[-76.316216,39.574401],"type":"Point"}
}