{
  "type": "Feature",
  "properties": {
    "iso:country":"US",
    "sg:address":"11433 Cronridge Dr",
    "sg:city":"Owings Mills",
    "sg:classifiers":[
        {
            "category":"Shopping",
            "subcategory":"Hobbies, Toys, & Games",
            "type":"Retail Goods"
        }
    ],
    "sg:phone":"+1 443 394 8501",
    "sg:postcode":"21117",
    "sg:province":"MD",
    "sg:website":"www.liveandlearn.com",
    "wof:name":"Live & Learn",
    "wof:placetype":"venue"
},
  "geometry": {"coordinates":[-76.77621000000001,39.440098],"type":"Point"}
}