{
  "type": "Feature",
  "properties": {
    "addr:full":"526 Valleywood Rd Millersville MD 21108",
    "addr:housenumber":"526",
    "addr:postcode":"21108",
    "addr:street":"Valleywood Rd",
    "iso:country":"US",
    "sg:address":"526 Valleywood Rd",
    "sg:city":"Millersville",
    "sg:classifiers":[
        {
            "category":"Building & Trades",
            "subcategory":"Construction",
            "type":"Services"
        }
    ],
    "sg:phone":"+1 410 729 3232",
    "sg:postcode":"21108",
    "sg:province":"MD",
    "sg:tags":[
        "system",
        "specialty",
        "heating",
        "contractor",
        "air conditioning"
    ],
    "wof:name":"All Systems Inc Heating & Air Conditioning",
    "wof:placetype":"venue"
},
  "geometry": {"coordinates":[-76.616236,39.114033],"type":"Point"}
}