{
  "type": "Feature",
  "properties": {
    "addr:full":"233 S Broadway Baltimore MD 21231",
    "addr:housenumber":"233",
    "addr:postcode":"21231",
    "addr:street":"S Broadway",
    "iso:country":"US",
    "sg:address":"233 S Broadway",
    "sg:city":"Baltimore",
    "sg:classifiers":[
        {
            "category":"Food & Beverages",
            "subcategory":"Groceries & Convenience Stores",
            "type":"Retail Goods"
        }
    ],
    "sg:phone":"+1 410 675 2770",
    "sg:postcode":"21231",
    "sg:province":"MD",
    "wof:name":"Bodeguita Delguey",
    "wof:placetype":"venue"
},
  "geometry": {"coordinates":[-76.593653,39.287858],"type":"Point"}
}