{
  "type": "Feature",
  "properties": {
    "iso:country":"US",
    "sg:address":"3333 Gapland Rd",
    "sg:city":"Rohrersville",
    "sg:classifiers":[
        {
            "category":"Autos & Motor Vehicles",
            "subcategory":"Motorcycle Sales",
            "type":"Retail Goods"
        }
    ],
    "sg:phone":"+1 301 432 2275",
    "sg:postcode":"21779",
    "sg:province":"MD",
    "wof:name":"Antietam Classic Cycle",
    "wof:placetype":"venue"
},
  "geometry": {"coordinates":[-77.659616,39.401816],"type":"Point"}
}