{
  "type": "Feature",
  "properties": {
    "iso:country":"US",
    "sg:address":"1030 S Linwood Ave",
    "sg:city":"Baltimore",
    "sg:classifiers":[
        {
            "category":"Organizations",
            "subcategory":"Labor Organization",
            "type":"Services"
        }
    ],
    "sg:phone":"+1 410 276 6964",
    "sg:postcode":"21224",
    "sg:province":"MD",
    "sg:website":"www.baltimorefireofficers.com",
    "wof:name":"Baltimore City Fire Officers",
    "wof:placetype":"venue"
},
  "geometry": {"coordinates":[-76.575417,39.280338],"type":"Point"}
}