{
  "type": "Feature",
  "properties": {
    "iso:country":"US",
    "sg:address":"10631 Jones Rd",
    "sg:city":"Kingsville",
    "sg:classifiers":[
        {
            "category":"Wholesale",
            "subcategory":"Machinery & Supplies",
            "type":"Manufacturing & Wholesale Goods"
        }
    ],
    "sg:phone":"+1 410 679 2800",
    "sg:postcode":"21087",
    "sg:province":"MD",
    "sg:tags":[
        "carpet",
        "cleaning",
        "rug"
    ],
    "wof:name":"Truckmount Svc",
    "wof:placetype":"venue"
},
  "geometry": {"coordinates":[-76.389934,39.415985],"type":"Point"}
}