{
  "type": "Feature",
  "properties": {
    "iso:country":"US",
    "sg:address":"12300 Twinbrook Pkwy",
    "sg:city":"Rockville",
    "sg:classifiers":[
        {
            "category":"Organizations",
            "subcategory":"Professional Association",
            "type":"Services"
        }
    ],
    "sg:phone":"+1 301 770 2920",
    "sg:postcode":"20852",
    "sg:province":"MD",
    "wof:name":"Regulatory Affairs Profs Soc",
    "wof:placetype":"venue"
},
  "geometry": {"coordinates":[-77.11902499999999,39.058731],"type":"Point"}
}