{
  "type": "Feature",
  "properties": {
    "iso:country":"US",
    "sg:address":"9504 Philadelphia Rd",
    "sg:city":"Rosedale",
    "sg:classifiers":[
        {
            "category":"Building & Trades",
            "subcategory":"Locksmith",
            "type":"Services"
        }
    ],
    "sg:phone":"+1 410 406 7699",
    "sg:postcode":"21237",
    "sg:province":"MD",
    "sg:tags":[
        "key"
    ],
    "wof:name":"Locksmith and Son's",
    "wof:placetype":"venue"
},
  "geometry": {"coordinates":[-76.462507,39.354473],"type":"Point"}
}