{
  "type": "Feature",
  "properties": {
    "iso:country":"US",
    "sg:address":"10 Irongate Dr",
    "sg:city":"Waldorf",
    "sg:classifiers":[
        {
            "category":"Professional",
            "subcategory":"Engineering",
            "type":"Services"
        }
    ],
    "sg:phone":"+1 301 932 9292",
    "sg:postcode":"20602",
    "sg:province":"MD",
    "sg:tags":[
        "consulting",
        "engineer"
    ],
    "wof:name":"Mckewon Motorsport Engineering Inc",
    "wof:placetype":"venue"
},
  "geometry": {"coordinates":[-76.910557,38.614682],"type":"Point"}
}