{
  "type": "Feature",
  "properties": {
    "addr:full":"8640 Damascus Rd Damascus MD 20872",
    "addr:housenumber":"8640",
    "addr:postcode":"20872",
    "addr:street":"Damascus Rd",
    "iso:country":"US",
    "sg:address":"8640 Damascus Rd",
    "sg:city":"Damascus",
    "sg:classifiers":[
        {
            "category":"Building & Trades",
            "subcategory":"Construction",
            "type":"Services"
        }
    ],
    "sg:phone":"+1 301 926 5246",
    "sg:postcode":"20872",
    "sg:province":"MD",
    "sg:tags":[
        "repair",
        "handyman",
        "maintenance",
        "home"
    ],
    "sg:website":"http://www.jimnesshandyman.com",
    "wof:name":"Jim Ness Handyman",
    "wof:placetype":"venue"
},
  "geometry": {"coordinates":[-77.177851,39.283419],"type":"Point"}
}