{
  "type": "Feature",
  "properties": {
    "addr:full":"3508 Marlbrough Way College Park MD 20740",
    "addr:housenumber":"3508",
    "addr:postcode":"20740",
    "addr:street":"Marlbrough Way",
    "iso:country":"US",
    "sg:address":"3508 Marlbrough Way",
    "sg:city":"College Park",
    "sg:classifiers":[
        {
            "category":"Manufacturing",
            "subcategory":"Toys & Sporting Goods",
            "type":"Manufacturing & Wholesale Goods"
        }
    ],
    "sg:phone":"+1 301 935 4865",
    "sg:postcode":"20740",
    "sg:province":"MD",
    "sg:tags":[
        "mfg"
    ],
    "wof:name":"Aniva Samal",
    "wof:placetype":"venue"
},
  "geometry": {"coordinates":[-76.95299,39.010416],"type":"Point"}
}