{
  "type": "Feature",
  "properties": {
    "iso:country":"US",
    "sg:address":"18230 Flower Hill Way",
    "sg:city":"Gaithersburg",
    "sg:classifiers":[
        {
            "category":"Retail",
            "subcategory":"Laundry & Dry Cleaning",
            "type":"Services"
        }
    ],
    "sg:phone":"+1 301 963 3903",
    "sg:postcode":"20879",
    "sg:province":"MD",
    "sg:tags":[
        "cleaners"
    ],
    "wof:name":"Flower Hill Cleaners",
    "wof:placetype":"venue"
},
  "geometry": {"coordinates":[-77.164744,39.155637],"type":"Point"}
}