{
  "type": "Feature",
  "properties": {
    "iso:country":"US",
    "sg:address":"1040 Deer Ridge Dr",
    "sg:city":"Baltimore",
    "sg:classifiers":[
        {
            "category":"Wholesale",
            "subcategory":"Medical Equipment & Supplies",
            "type":"Manufacturing & Wholesale Goods"
        }
    ],
    "sg:phone":"+1 410 366 6965",
    "sg:postcode":"21210",
    "sg:province":"MD",
    "wof:name":"Ridge Supply Group",
    "wof:placetype":"venue"
},
  "geometry": {"coordinates":[-76.639359,39.343027],"type":"Point"}
}