{
  "type": "Feature",
  "properties": {
    "addr:full":"5801 Tuxedo Rd Hyattsville MD 20781",
    "addr:housenumber":"5801",
    "addr:postcode":"20781",
    "addr:street":"Tuxedo Rd",
    "iso:country":"US",
    "sg:address":"5801 Tuxedo Rd",
    "sg:city":"Hyattsville",
    "sg:classifiers":[
        {
            "category":"Organizations",
            "subcategory":"Religious Organization",
            "type":"Services"
        }
    ],
    "sg:phone":"+1 301 772 5031",
    "sg:postcode":"20781",
    "sg:province":"MD",
    "sg:tags":[
        "church"
    ],
    "wof:name":"Celestial Church Of Christ",
    "wof:placetype":"venue"
},
  "geometry": {"coordinates":[-76.92099899999999,38.917335],"type":"Point"}
}