{
  "type": "Feature",
  "properties": {
    "iso:country":"US",
    "sg:address":"115 S Main St",
    "sg:city":"Mount Airy",
    "sg:classifiers":[
        {
            "category":"Personal",
            "subcategory":"Beauty Salon",
            "type":"Services"
        }
    ],
    "sg:phone":"+1 301 829 1252",
    "sg:postcode":"21771",
    "sg:province":"MD",
    "sg:tags":[
        "shop"
    ],
    "wof:name":"Carousel Beauty Hut",
    "wof:placetype":"venue"
},
  "geometry": {"coordinates":[-77.154878,39.376284],"type":"Point"}
}