{
  "type": "Feature",
  "properties": {
    "iso:country":"US",
    "sg:address":"10 S Wolfe St Ste 100",
    "sg:city":"Baltimore",
    "sg:classifiers":[
        {
            "category":"Real Estate",
            "subcategory":"Real Estate Services",
            "type":"Services"
        }
    ],
    "sg:phone":"+1 443 569 7400",
    "sg:postcode":"21231",
    "sg:province":"MD",
    "sg:tags":[
        "management",
        "property"
    ],
    "sg:website":"www.indebleu.com",
    "wof:name":"IndeBleu Properties - Baltimore Property Management Services",
    "wof:placetype":"venue"
},
  "geometry": {"coordinates":[-76.59047700000001,39.291478],"type":"Point"}
}