{
  "type": "Feature",
  "properties": {
    "addr:full":"12828 Clear Spring Rd Clear Spring MD 21722",
    "addr:housenumber":"12828",
    "addr:postcode":"21722",
    "addr:street":"Clear Spring Rd",
    "iso:country":"US",
    "sg:address":"12828 Clear Spring Rd",
    "sg:city":"Clear Spring",
    "sg:classifiers":[
        {
            "category":"Autos & Motor Vehicles",
            "subcategory":"Fuel & Gas Station",
            "type":"Retail Goods"
        }
    ],
    "sg:phone":"+1 301 842 0098",
    "sg:postcode":"21722",
    "sg:province":"MD",
    "sg:tags":[
        "oil"
    ],
    "wof:name":"Clear Spring Svc Station",
    "wof:placetype":"venue"
},
  "geometry": {"coordinates":[-77.92729,39.654309],"type":"Point"}
}