{
  "type": "Feature",
  "properties": {
    "iso:country":"US",
    "sg:address":"14609 Baltimore Ave",
    "sg:city":"Laurel",
    "sg:classifiers":[
        {
            "category":"Building & Trades",
            "subcategory":"Locksmith",
            "type":"Services"
        }
    ],
    "sg:phone":"+1 301 957 9405",
    "sg:postcode":"20707",
    "sg:province":"MD",
    "sg:tags":[
        "key"
    ],
    "wof:name":"Locksmith 24 by 7 Alarms",
    "wof:placetype":"venue"
},
  "geometry": {"coordinates":[-76.85837100000001,39.089983],"type":"Point"}
}