{
  "type": "Feature",
  "properties": {
    "addr:full":"13828 Outlet Dr Silver Spring MD 20904",
    "addr:housenumber":"13828",
    "addr:postcode":"20904",
    "addr:street":"Outlet Dr",
    "iso:country":"US",
    "sg:address":"13828 Outlet Dr",
    "sg:city":"Silver Spring",
    "sg:classifiers":[
        {
            "category":"Retail",
            "subcategory":"Laundry & Dry Cleaning",
            "type":"Services"
        }
    ],
    "sg:phone":"+1 301 890 7772",
    "sg:postcode":"20904",
    "sg:province":"MD",
    "wof:name":"Seung Muk You",
    "wof:placetype":"venue"
},
  "geometry": {"coordinates":[-76.94684700000001,39.082634],"type":"Point"}
}