{
  "type": "Feature",
  "properties": {
    "addr:full":"6301 Sykesville Rd Eldersburg MD 21784",
    "addr:housenumber":"6301",
    "addr:postcode":"21784",
    "addr:street":"Sykesville Rd",
    "iso:country":"US",
    "sg:address":"6301 Sykesville Rd",
    "sg:city":"Eldersburg",
    "sg:classifiers":[
        {
            "category":"Retail",
            "subcategory":"Car Wash",
            "type":"Services"
        }
    ],
    "sg:phone":"+1 410 549 2549",
    "sg:postcode":"21784",
    "sg:province":"MD",
    "sg:tags":[
        "polishing",
        "carwash",
        "washing"
    ],
    "wof:name":"Eldersburg Carwash",
    "wof:placetype":"venue"
},
  "geometry": {"coordinates":[-76.952091,39.400478],"type":"Point"}
}