{
  "type": "Feature",
  "properties": {
    "addr:full":"6216 Greenbelt Rd Greenbelt MD 20770",
    "addr:housenumber":"6216",
    "addr:postcode":"20770",
    "addr:street":"Greenbelt Rd",
    "iso:country":"US",
    "sg:address":"6216 Greenbelt Rd",
    "sg:city":"Greenbelt",
    "sg:classifiers":[
        {
            "category":"Shopping",
            "subcategory":"Computers & Home Electronics",
            "type":"Retail Goods"
        }
    ],
    "sg:phone":"+1 301 441 8816",
    "sg:postcode":"20770",
    "sg:province":"MD",
    "sg:tags":[
        "equipment",
        "dealer"
    ],
    "wof:name":"SO2 Computers & Software",
    "wof:placetype":"venue"
},
  "geometry": {"coordinates":[-76.905393,38.997012],"type":"Point"}
}