{
  "type": "Feature",
  "properties": {
    "addr:full":"8657 Philadelphia Rd Baltimore MD 21237",
    "addr:housenumber":"8657",
    "addr:postcode":"21237",
    "addr:street":"Philadelphia Rd",
    "iso:country":"US",
    "sg:address":"8657 Philadelphia Rd",
    "sg:city":"Baltimore",
    "sg:classifiers":[
        {
            "category":"Shopping",
            "subcategory":"Gifts & Souvenirs",
            "type":"Retail Goods"
        }
    ],
    "sg:phone":"+1 410 686 9420",
    "sg:postcode":"21237",
    "sg:province":"MD",
    "sg:tags":[
        "shop"
    ],
    "wof:name":"Ann Marie's Hallmark",
    "wof:placetype":"venue"
},
  "geometry": {"coordinates":[-76.492813,39.335351],"type":"Point"}
}