{
  "type": "Feature",
  "properties": {
    "iso:country":"US",
    "sg:address":"12 E Mount Vernon Pl",
    "sg:city":"Baltimore",
    "sg:classifiers":[
        {
            "category":"Health Services",
            "subcategory":"Health Practitioner",
            "type":"Services"
        }
    ],
    "sg:phone":"+1 410 230 0886",
    "sg:postcode":"21202",
    "sg:province":"MD",
    "sg:tags":[
        "physician",
        "naturopathic/holistic"
    ],
    "wof:name":"E Mimi Palenque",
    "wof:placetype":"venue"
},
  "geometry": {"coordinates":[-76.61556,39.297722],"type":"Point"}
}