{
  "type": "Feature",
  "properties": {
    "addr:full":"4319 Arabia Ave Baltimore MD 21214",
    "addr:housenumber":"4319",
    "addr:postcode":"21214",
    "addr:street":"Arabia Ave",
    "iso:country":"US",
    "sg:address":"4319 Arabia Ave",
    "sg:city":"Baltimore",
    "sg:classifiers":[
        {
            "category":"Professional",
            "subcategory":"Management & Consulting",
            "type":"Services"
        }
    ],
    "sg:phone":"+1 410 644 3455",
    "sg:postcode":"21214",
    "sg:province":"MD",
    "sg:tags":[
        "consultant"
    ],
    "wof:name":"C&B Strategic Consulting Inc.",
    "wof:placetype":"venue"
},
  "geometry": {"coordinates":[-76.571184,39.338107],"type":"Point"}
}