{
  "type": "Feature",
  "properties": {
    "iso:country":"US",
    "sg:address":"2712 Johnson Mill Rd",
    "sg:city":"Forest Hill",
    "sg:classifiers":[
        {
            "category":"Building & Trades",
            "subcategory":"Construction",
            "type":"Services"
        }
    ],
    "sg:phone":"+1 410 638 6824",
    "sg:postcode":"21050",
    "sg:province":"MD",
    "sg:tags":[
        "house"
    ],
    "wof:name":"NV Homes Inc",
    "wof:placetype":"venue"
},
  "geometry": {"coordinates":[-76.37406799999999,39.598797],"type":"Point"}
}