{
  "type": "Feature",
  "properties": {
    "addr:full":"14921 Shady Grove Rd Rockville MD 20850",
    "addr:housenumber":"14921",
    "addr:postcode":"20850",
    "addr:street":"Shady Grove Rd",
    "iso:country":"US",
    "sg:address":"14921 Shady Grove Rd",
    "sg:city":"Rockville",
    "sg:classifiers":[
        {
            "category":"Bakery",
            "type":"Food & Drink"
        }
    ],
    "sg:menulink":"http://www.allmenus.com/md/rockville/103067-panera-bread/menu/",
    "sg:phone":"+1 301 545 1874",
    "sg:postcode":"20850",
    "sg:province":"MD",
    "sg:tags":[
        "american",
        "sandwich",
        "pastry"
    ],
    "wof:name":"Panera Bread",
    "wof:placetype":"venue"
},
  "geometry": {"coordinates":[-77.192392,39.099154],"type":"Point"}
}