{
  "type": "Feature",
  "properties": {
    "iso:country":"US",
    "sg:address":"1100 Old Eastern Ave",
    "sg:city":"Essex",
    "sg:classifiers":[
        {
            "category":"Building & Trades",
            "subcategory":"Plumbing",
            "type":"Services"
        }
    ],
    "sg:phone":"+1 410 574 9675",
    "sg:postcode":"21221",
    "sg:province":"MD",
    "wof:name":"Griffith Heating and Plumbing",
    "wof:placetype":"venue"
},
  "geometry": {"coordinates":[-76.46190900000001,39.313275],"type":"Point"}
}