{
  "type": "Feature",
  "properties": {
    "addr:full":"1318 Eastern Blvd Essex MD 21221",
    "addr:housenumber":"1318",
    "addr:postcode":"21221",
    "addr:street":"Eastern Blvd",
    "iso:country":"US",
    "sg:address":"1318 Eastern Blvd",
    "sg:city":"Essex",
    "sg:classifiers":[
        {
            "category":"Shopping",
            "subcategory":"Clothing, Apparel, & Fashions",
            "type":"Retail Goods"
        }
    ],
    "sg:phone":"+1 410 636 7990",
    "sg:postcode":"21221",
    "sg:province":"MD",
    "wof:name":"Dana's Discount Ladies Apparel",
    "wof:placetype":"venue"
},
  "geometry": {"coordinates":[-76.461392,39.315123],"type":"Point"}
}