{
  "type": "Feature",
  "properties": {
    "addr:full":"4107 Frederick Ave Baltimore MD 21229",
    "addr:housenumber":"4107",
    "addr:postcode":"21229",
    "addr:street":"Frederick Ave",
    "iso:country":"US",
    "sg:address":"4107 Frederick Ave",
    "sg:city":"Baltimore",
    "sg:classifiers":[
        {
            "category":"Personal",
            "subcategory":"Beauty Salon",
            "type":"Services"
        }
    ],
    "sg:phone":"+1 410 644 2800",
    "sg:postcode":"21229",
    "sg:province":"MD",
    "wof:name":"Fatimas African Hair Braiding",
    "wof:placetype":"venue"
},
  "geometry": {"coordinates":[-76.683852,39.281656],"type":"Point"}
}