{
  "type": "Feature",
  "properties": {
    "addr:full":"224 Barnhart Rd Westminster MD 21158",
    "addr:housenumber":"224",
    "addr:postcode":"21158",
    "addr:street":"Barnhart Rd",
    "iso:country":"US",
    "sg:address":"224 Barnhart Rd",
    "sg:city":"Westminster",
    "sg:classifiers":[
        {
            "category":"Professional",
            "subcategory":"Detective & Security Services",
            "type":"Services"
        }
    ],
    "sg:phone":"+1 443 227 9639",
    "sg:postcode":"21158",
    "sg:province":"MD",
    "sg:tags":[
        "information",
        "bureau"
    ],
    "wof:name":"Rlw Services",
    "wof:placetype":"venue"
},
  "geometry": {"coordinates":[-76.984779,39.717789],"type":"Point"}
}