{
  "type": "Feature",
  "properties": {
    "addr:full":"9536 Hallhurst Rd Baltimore MD 21236",
    "addr:housenumber":"9536",
    "addr:postcode":"21236",
    "addr:street":"Hallhurst Rd",
    "iso:country":"US",
    "sg:address":"9536 Hallhurst Rd",
    "sg:city":"Baltimore",
    "sg:classifiers":[
        {
            "category":"Wholesale",
            "subcategory":"Hardware",
            "type":"Manufacturing & Wholesale Goods"
        }
    ],
    "sg:phone":"+1 410 529 3644",
    "sg:postcode":"21236",
    "sg:province":"MD",
    "sg:tags":[
        "purifying",
        "cleaning",
        "air"
    ],
    "wof:name":"Frallicciardi Environmental",
    "wof:placetype":"venue"
},
  "geometry": {"coordinates":[-76.48207600000001,39.415147],"type":"Point"}
}