{
  "type": "Feature",
  "properties": {
    "addr:full":"94 Childs Rd Elkton MD 21921",
    "addr:housenumber":"94",
    "addr:postcode":"21921",
    "addr:street":"Childs Rd",
    "iso:country":"US",
    "sg:address":"94 Childs Rd",
    "sg:city":"Elkton",
    "sg:classifiers":[
        {
            "category":"Building & Trades",
            "subcategory":"Construction",
            "type":"Services"
        }
    ],
    "sg:phone":"+1 410 398 8481",
    "sg:postcode":"21921",
    "sg:province":"MD",
    "sg:tags":[
        "maker",
        "cabinet"
    ],
    "wof:name":"Kevin W Jones Inc",
    "wof:placetype":"venue"
},
  "geometry": {"coordinates":[-75.86980699999999,39.647681],"type":"Point"}
}