{
  "type": "Feature",
  "properties": {
    "addr:full":"5531 Nicholson Ln Rockville MD 20852",
    "addr:housenumber":"5531",
    "addr:postcode":"20852",
    "addr:street":"Nicholson Ln",
    "iso:country":"US",
    "sg:address":"5531 Nicholson Ln",
    "sg:city":"Rockville",
    "sg:classifiers":[
        {
            "category":"Wholesale",
            "subcategory":"Auto Parts",
            "type":"Manufacturing & Wholesale Goods"
        }
    ],
    "sg:phone":"+1 301 881 2220",
    "sg:postcode":"20852",
    "sg:province":"MD",
    "sg:tags":[
        "automobile"
    ],
    "wof:name":"Pro Imports",
    "wof:placetype":"venue"
},
  "geometry": {"coordinates":[-77.111211,39.044966],"type":"Point"}
}