{
  "type": "Feature",
  "properties": {
    "addr:full":"8 E Fayette St Baltimore MD 21231",
    "addr:housenumber":"8",
    "addr:postcode":"21231",
    "addr:street":"E Fayette St",
    "iso:country":"US",
    "sg:address":"8 E Fayette St",
    "sg:city":"Baltimore",
    "sg:classifiers":[
        {
            "category":"Restaurant",
            "type":"Food & Drink"
        }
    ],
    "sg:phone":"+1 410 727 1090",
    "sg:postcode":"21231",
    "sg:province":"MD",
    "wof:name":"Burger King",
    "wof:placetype":"venue"
},
  "geometry": {"coordinates":[-76.613972,39.29056],"type":"Point"}
}