{
  "type": "Feature",
  "properties": {
    "iso:country":"US",
    "sg:address":"4407 Oaktree Rd",
    "sg:city":"Rockville",
    "sg:classifiers":[
        {
            "category":"Retail",
            "subcategory":"Photofinishing",
            "type":"Services"
        },
        {
            "category":"Professional",
            "subcategory":"Art Services",
            "type":"Services"
        },
        {
            "category":"Professional",
            "subcategory":"Printing & Photocopies",
            "type":"Services"
        }
    ],
    "sg:phone":"+1 240 678 9233",
    "sg:postcode":"20853",
    "sg:province":"MD",
    "sg:tags":[
        "photo",
        "photographers-portrait",
        "restoration",
        "photographers-commercial",
        "retouching"
    ],
    "wof:name":"Jason Weil Photography",
    "wof:placetype":"venue"
},
  "geometry": {"coordinates":[-77.08866,39.119848],"type":"Point"}
}