{
  "type": "Feature",
  "properties": {
    "iso:country":"US",
    "sg:address":"1831 Forest Dr",
    "sg:city":"Annapolis",
    "sg:classifiers":[
        {
            "category":"Health Services",
            "subcategory":"Doctor",
            "type":"Services"
        }
    ],
    "sg:phone":"+1 410 267 9311",
    "sg:postcode":"21401",
    "sg:province":"MD",
    "sg:tags":[
        "dentist"
    ],
    "wof:name":"James P Segerstrom DDS",
    "wof:placetype":"venue"
},
  "geometry": {"coordinates":[-76.524836,38.973158],"type":"Point"}
}