{
  "type": "Feature",
  "properties": {
    "addr:full":"1501 Sulgrave Ave Baltimore MD 21209",
    "addr:housenumber":"1501",
    "addr:postcode":"21209",
    "addr:street":"Sulgrave Ave",
    "iso:country":"US",
    "sg:address":"1501 Sulgrave Ave",
    "sg:city":"Baltimore",
    "sg:classifiers":[
        {
            "category":"Real Estate",
            "subcategory":"Real Estate Services",
            "type":"Services"
        }
    ],
    "sg:phone":"+1 410 367 6800",
    "sg:postcode":"21209",
    "sg:province":"MD",
    "sg:tags":[
        "management",
        "property"
    ],
    "wof:name":"Gorn Samuel G",
    "wof:placetype":"venue"
},
  "geometry": {"coordinates":[-76.65149700000001,39.367802],"type":"Point"}
}