{
  "type": "Feature",
  "properties": {
    "iso:country":"US",
    "sg:address":"21779 Tulagi Pl",
    "sg:city":"Lexington Park",
    "sg:classifiers":[
        {
            "category":"Organizations",
            "subcategory":"Religious Organization",
            "type":"Services"
        }
    ],
    "sg:phone":"+1 301 862 5630",
    "sg:postcode":"20653",
    "sg:province":"MD",
    "sg:tags":[
        "church"
    ],
    "wof:name":"Praise & Deliverance Fllwshp",
    "wof:placetype":"venue"
},
  "geometry": {"coordinates":[-76.452345,38.264494],"type":"Point"}
}