{
  "type": "Feature",
  "properties": {
    "addr:full":"608 Water St Baltimore MD 21202",
    "addr:housenumber":"608",
    "addr:postcode":"21202",
    "addr:street":"Water St",
    "iso:country":"US",
    "sg:address":"608 Water St",
    "sg:city":"Baltimore",
    "sg:classifiers":[
        {
            "category":"Social Services",
            "type":"Services"
        }
    ],
    "sg:phone":"+1 410 752 7590",
    "sg:postcode":"21202",
    "sg:province":"MD",
    "sg:tags":[
        "counseling"
    ],
    "wof:name":"Chocolate Factory",
    "wof:placetype":"venue"
},
  "geometry": {"coordinates":[-76.60714299999999,39.288776],"type":"Point"}
}