{
  "type": "Feature",
  "properties": {
    "addr:full":"912 Eastern Shore Dr Salisbury MD 21804",
    "addr:housenumber":"912",
    "addr:postcode":"21804",
    "addr:street":"Eastern Shore Dr",
    "iso:country":"US",
    "sg:address":"912 Eastern Shore Dr",
    "sg:city":"Salisbury",
    "sg:classifiers":[
        {
            "category":"Professional",
            "subcategory":"Business Services",
            "type":"Services"
        }
    ],
    "sg:phone":"+1 410 546 4232",
    "sg:postcode":"21804",
    "sg:province":"MD",
    "wof:name":"B Eric Rychener",
    "wof:placetype":"venue"
},
  "geometry": {"coordinates":[-75.59787,38.352201],"type":"Point"}
}