{
  "type": "Feature",
  "properties": {
    "addr:full":"2018 Rock Spring Rd Forest Hill MD 21050",
    "addr:housenumber":"2018",
    "addr:postcode":"21050",
    "addr:street":"Rock Spring Rd",
    "iso:country":"US",
    "sg:address":"2018 Rock Spring Rd",
    "sg:city":"Forest Hill",
    "sg:classifiers":[
        {
            "category":"Health Services",
            "subcategory":"Chiropractor",
            "type":"Services"
        }
    ],
    "sg:phone":"+1 410 879 0400",
    "sg:postcode":"21050",
    "sg:province":"MD",
    "wof:name":"Blaker Chiropractic",
    "wof:placetype":"venue"
},
  "geometry": {"coordinates":[-76.38410399999999,39.572553],"type":"Point"}
}