{
  "type": "Feature",
  "properties": {
    "addr:full":"10121 Three Notch Rd California MD 20619",
    "addr:housenumber":"10121",
    "addr:postcode":"20619",
    "addr:street":"Three Notch Rd",
    "iso:country":"US",
    "sg:address":"10121 Three Notch Rd",
    "sg:city":"California",
    "sg:classifiers":[
        {
            "category":"Social Services",
            "subcategory":"Child Care",
            "type":"Services"
        }
    ],
    "sg:phone":"+1 301 862 2393",
    "sg:postcode":"20619",
    "sg:province":"MD",
    "wof:name":"Small World Day Care Ctr",
    "wof:placetype":"venue"
},
  "geometry": {"coordinates":[-76.50282,38.29555],"type":"Point"}
}