{
  "type": "Feature",
  "properties": {
    "addr:full":"110 Depaul St Emmitsburg MD 21727",
    "addr:housenumber":"110",
    "addr:postcode":"21727",
    "addr:street":"Depaul St",
    "iso:country":"US",
    "sg:address":"110 Depaul St",
    "sg:city":"Emmitsburg",
    "sg:classifiers":[
        {
            "category":"Retail",
            "subcategory":"Portrait Studio",
            "type":"Services"
        }
    ],
    "sg:phone":"+1 301 447 6643",
    "sg:postcode":"21727",
    "sg:province":"MD",
    "sg:tags":[
        "photo"
    ],
    "wof:name":"Rosensteel Robert A Sr",
    "wof:placetype":"venue"
},
  "geometry": {"coordinates":[-77.323471,39.705058],"type":"Point"}
}