{
  "type": "Feature",
  "properties": {
    "addr:full":"RR 170 Elkridge MD 21075",
    "addr:housenumber":"170",
    "addr:postcode":"21075",
    "iso:country":"US",
    "sg:address":"RR 170",
    "sg:city":"Elkridge",
    "sg:classifiers":[
        {
            "category":"Travel",
            "subcategory":"Hotels & Motels",
            "type":"Entertainment"
        }
    ],
    "sg:phone":"+1 410 850 7600",
    "sg:postcode":"21075",
    "sg:province":"MD",
    "wof:name":"Red Roof Inc",
    "wof:placetype":"venue"
},
  "geometry": {"coordinates":[-76.746399,39.201],"type":"Point"}
}