{
  "type": "Feature",
  "properties": {
    "addr:full":"206 Mechanics Valley Rd North East MD 21901",
    "addr:housenumber":"206",
    "addr:postcode":"21901",
    "addr:street":"Mechanics Valley Rd",
    "iso:country":"US",
    "sg:address":"206 Mechanics Valley Rd",
    "sg:city":"North East",
    "sg:classifiers":[
        {
            "category":"Organizations",
            "subcategory":"Religious Organization",
            "type":"Services"
        }
    ],
    "sg:phone":"+1 410 287 6247",
    "sg:postcode":"21901",
    "sg:province":"MD",
    "sg:tags":[
        "church"
    ],
    "sg:website":"www.fbne.org",
    "wof:name":"First Baptist Church",
    "wof:placetype":"venue"
},
  "geometry": {"coordinates":[-75.935322,39.604027],"type":"Point"}
}