{
  "type": "Feature",
  "properties": {
    "iso:country":"US",
    "sg:address":"11212 Grandview Ave",
    "sg:city":"Wheaton",
    "sg:classifiers":[
        {
            "category":"Social Services",
            "type":"Services"
        }
    ],
    "sg:phone":"+1 301 942 2240",
    "sg:postcode":"20902",
    "sg:province":"MD",
    "sg:tags":[
        "organization",
        "welfare"
    ],
    "wof:name":"Un Dia A LA Vez",
    "wof:placetype":"venue"
},
  "geometry": {"coordinates":[-77.052601,39.039492],"type":"Point"}
}