{
  "type": "Feature",
  "properties": {
    "addr:full":"7719 Normandy Rd Hyattsville MD 20785",
    "addr:housenumber":"7719",
    "addr:postcode":"20785",
    "addr:street":"Normandy Rd",
    "iso:country":"US",
    "sg:address":"7719 Normandy Rd",
    "sg:city":"Hyattsville",
    "sg:classifiers":[
        {
            "category":"Building & Trades",
            "subcategory":"Cleaning & Sanitation",
            "type":"Services"
        }
    ],
    "sg:phone":"+1 301 341 7850",
    "sg:postcode":"20785",
    "sg:province":"MD",
    "sg:tags":[
        "janitor"
    ],
    "wof:name":"PCSI",
    "wof:placetype":"venue"
},
  "geometry": {"coordinates":[-76.87489600000001,38.9221],"type":"Point"}
}