{
  "type": "Feature",
  "properties": {
    "iso:country":"US",
    "sg:address":"106 Duvall Ln",
    "sg:city":"Gaithersburg",
    "sg:classifiers":[
        {
            "category":"Wholesale",
            "subcategory":"Electrical",
            "type":"Manufacturing & Wholesale Goods"
        }
    ],
    "sg:phone":"+1 301 977 5951",
    "sg:postcode":"20877",
    "sg:province":"MD",
    "sg:tags":[
        "equipment"
    ],
    "wof:name":"Top Sound & Security",
    "wof:placetype":"venue"
},
  "geometry": {"coordinates":[-77.203112,39.129428],"type":"Point"}
}