{
  "type": "Feature",
  "properties": {
    "iso:country":"US",
    "sg:address":"11202 Racetrack Rd Ste 102",
    "sg:city":"Berlin",
    "sg:classifiers":[
        {
            "category":"Professional",
            "subcategory":"Engineering",
            "type":"Services"
        }
    ],
    "sg:phone":"+1 410 208 4190",
    "sg:postcode":"21811",
    "sg:province":"MD",
    "sg:tags":[
        "consulting",
        "engineer"
    ],
    "wof:name":"Traffic Group",
    "wof:placetype":"venue"
},
  "geometry": {"coordinates":[-75.190876,38.388784],"type":"Point"}
}