{
  "type": "Feature",
  "properties": {
    "iso:country":"US",
    "sg:address":"26271 Tunis Mills Rd",
    "sg:city":"Easton",
    "sg:classifiers":[
        {
            "category":"Professional",
            "subcategory":"Business Services",
            "type":"Services"
        }
    ],
    "sg:phone":"+1 410 770 9695",
    "sg:postcode":"21601",
    "sg:province":"MD",
    "sg:tags":[
        "holding"
    ],
    "sg:website":"http://www.tommccallphotography.com",
    "wof:name":"Max Holdings",
    "wof:placetype":"venue"
},
  "geometry": {"coordinates":[-76.165688,38.82058],"type":"Point"}
}