{
  "type": "Feature",
  "properties": {
    "iso:country":"US",
    "sg:address":"11350 McCormick Rd",
    "sg:city":"Cockysvl Hnt Vly",
    "sg:classifiers":[
        {
            "category":"Banks & Credit Unions",
            "subcategory":"Bank",
            "type":"Services"
        }
    ],
    "sg:phone":"+1 410 527 0977",
    "sg:postcode":"21031",
    "sg:province":"MD",
    "sg:tags":[
        "savings",
        "loan",
        "association"
    ],
    "wof:name":"Waypoint Bank",
    "wof:placetype":"venue"
},
  "geometry": {"coordinates":[-76.659015,39.494913],"type":"Point"}
}