{
  "type": "Feature",
  "properties": {
    "addr:full":"9013 Allenswood Rd Randallstown MD 21133",
    "addr:housenumber":"9013",
    "addr:postcode":"21133",
    "addr:street":"Allenswood Rd",
    "iso:country":"US",
    "sg:address":"9013 Allenswood Rd",
    "sg:city":"Randallstown",
    "sg:classifiers":[
        {
            "category":"Building & Trades",
            "subcategory":"Electrical",
            "type":"Services"
        }
    ],
    "sg:phone":"+1 410 922 5588",
    "sg:postcode":"21133",
    "sg:province":"MD",
    "sg:tags":[
        "electric",
        "contractor"
    ],
    "wof:name":"Howard Electric Co",
    "wof:placetype":"venue"
},
  "geometry": {"coordinates":[-76.793924,39.371531],"type":"Point"}
}