{
  "type": "Feature",
  "properties": {
    "iso:country":"US",
    "sg:address":"5419 East Dr",
    "sg:city":"Halethorpe",
    "sg:classifiers":[
        {
            "category":"Personal",
            "subcategory":"Shoe Repair & Shine",
            "type":"Services"
        }
    ],
    "sg:phone":"+1 410 242 4730",
    "sg:postcode":"21227",
    "sg:province":"MD",
    "sg:tags":[
        "repairing",
        "boot"
    ],
    "wof:name":"Bob's Shoe Repair",
    "wof:placetype":"venue"
},
  "geometry": {"coordinates":[-76.693647,39.248469],"type":"Point"}
}