{
  "type": "Feature",
  "properties": {
    "iso:country":"US",
    "sg:address":"571 Baltimore Pike",
    "sg:city":"Bel Air",
    "sg:classifiers":[
        {
            "category":"Home & Garden",
            "subcategory":"Carpets & Floor Coverings",
            "type":"Retail Goods"
        }
    ],
    "sg:phone":"+1 410 638 2300",
    "sg:postcode":"21014",
    "sg:province":"MD",
    "sg:tags":[
        "dealer",
        "rug"
    ],
    "wof:name":"Bill's Carpet Fair",
    "wof:placetype":"venue"
},
  "geometry": {"coordinates":[-76.354912,39.525845],"type":"Point"}
}