{
  "type": "Feature",
  "properties": {
    "iso:country":"US",
    "sg:address":"206 Main St",
    "sg:city":"Annapolis",
    "sg:classifiers":[
        {
            "category":"Personal",
            "type":"Services"
        }
    ],
    "sg:phone":"+1 410 216 9898",
    "sg:postcode":"21401",
    "sg:province":"MD",
    "sg:tags":[
        "consultant",
        "fashion"
    ],
    "wof:name":"Alpaca International",
    "wof:placetype":"venue"
},
  "geometry": {"coordinates":[-76.491783,38.978253],"type":"Point"}
}