{
  "type": "Feature",
  "properties": {
    "iso:country":"US",
    "sg:address":"217 E Baltimore St",
    "sg:city":"Baltimore",
    "sg:classifiers":[
        {
            "category":"Shopping",
            "subcategory":"Jewelry",
            "type":"Retail Goods"
        }
    ],
    "sg:phone":"+1 410 547 1832",
    "sg:postcode":"21202",
    "sg:province":"MD",
    "sg:tags":[
        "jeweler"
    ],
    "wof:name":"Sound Advice Check Cashing",
    "wof:placetype":"venue"
},
  "geometry": {"coordinates":[-76.611161,39.289621],"type":"Point"}
}