{
  "type": "Feature",
  "properties": {
    "iso:country":"US",
    "sg:address":"14407 Dolbrook Ln",
    "sg:city":"Bowie",
    "sg:classifiers":[
        {
            "category":"Professional",
            "type":"Services"
        }
    ],
    "sg:phone":"+1 301 390 7734",
    "sg:postcode":"20721",
    "sg:province":"MD",
    "sg:tags":[
        "establishment"
    ],
    "wof:name":"Charlie's T-Shirts",
    "wof:placetype":"venue"
},
  "geometry": {"coordinates":[-76.753551,38.910188],"type":"Point"}
}