{
  "type": "Feature",
  "properties": {
    "addr:full":"725 Virginia Ave Hagerstown MD 21740",
    "addr:housenumber":"725",
    "addr:postcode":"21740",
    "addr:street":"Virginia Ave",
    "iso:country":"US",
    "sg:address":"725 Virginia Ave",
    "sg:city":"Hagerstown",
    "sg:classifiers":[
        {
            "category":"Organizations",
            "subcategory":"Religious Organization",
            "type":"Services"
        }
    ],
    "sg:phone":"+1 301 665 1985",
    "sg:postcode":"21740",
    "sg:province":"MD",
    "sg:tags":[
        "clergy"
    ],
    "wof:name":"James E Moore",
    "wof:placetype":"venue"
},
  "geometry": {"coordinates":[-77.733853,39.631205],"type":"Point"}
}