{
  "type": "Feature",
  "properties": {
    "addr:full":"2 E Potomac St Brunswick MD 21716",
    "addr:housenumber":"2",
    "addr:postcode":"21716",
    "addr:street":"E Potomac St",
    "iso:country":"US",
    "sg:address":"2 E Potomac St",
    "sg:city":"Brunswick",
    "sg:classifiers":[
        {
            "category":"Building & Trades",
            "subcategory":"Construction",
            "type":"Services"
        }
    ],
    "sg:phone":"+1 301 834 5061",
    "sg:postcode":"21716",
    "sg:province":"MD",
    "sg:tags":[
        "utility",
        "contractor"
    ],
    "wof:name":"Alpha Enterprises",
    "wof:placetype":"venue"
},
  "geometry": {"coordinates":[-77.626942,39.312926],"type":"Point"}
}