{
  "type": "Feature",
  "properties": {
    "iso:country":"US",
    "sg:address":"9470 Annapolis Rd",
    "sg:city":"Lanham",
    "sg:classifiers":[
        {
            "category":"Professional",
            "subcategory":"Detective & Security Services",
            "type":"Services"
        }
    ],
    "sg:phone":"+1 301 306 3890",
    "sg:postcode":"20706",
    "sg:province":"MD",
    "sg:tags":[
        "guard",
        "patrol"
    ],
    "wof:name":"Security Services Of America",
    "wof:placetype":"venue"
},
  "geometry": {"coordinates":[-76.841284,38.964931],"type":"Point"}
}