{
  "type": "Feature",
  "properties": {
    "iso:country":"US",
    "sg:address":"571 Baltimore Pike",
    "sg:city":"Bel Air",
    "sg:classifiers":[
        {
            "category":"Wholesale",
            "subcategory":"Stationery",
            "type":"Manufacturing & Wholesale Goods"
        }
    ],
    "sg:phone":"+1 410 638 1200",
    "sg:postcode":"21014",
    "sg:province":"MD",
    "sg:tags":[
        "school",
        "supply"
    ],
    "wof:name":"Learning How",
    "wof:placetype":"venue"
},
  "geometry": {"coordinates":[-76.354912,39.525845],"type":"Point"}
}