{
  "type": "Feature",
  "properties": {
    "addr:full":"5212 Campbell Blvd Nottingham MD 21236",
    "addr:housenumber":"5212",
    "addr:postcode":"21236",
    "addr:street":"Campbell Blvd",
    "iso:country":"US",
    "sg:address":"5212 Campbell Blvd",
    "sg:city":"Nottingham",
    "sg:classifiers":[
        {
            "category":"Shopping",
            "subcategory":"Crafts & Fabrics",
            "type":"Retail Goods"
        }
    ],
    "sg:phone":"+1 410 933 8443",
    "sg:postcode":"21236",
    "sg:province":"MD",
    "sg:tags":[
        "art",
        "supply"
    ],
    "sg:website":"www.michaels.com",
    "wof:name":"Michaels Arts & Crafts",
    "wof:placetype":"venue"
},
  "geometry": {"coordinates":[-76.4552,39.370499],"type":"Point"}
}