{
  "type": "Feature",
  "properties": {
    "iso:country":"US",
    "sg:address":"127 Greene St",
    "sg:city":"Cumberland",
    "sg:classifiers":[
        {
            "category":"Communications",
            "subcategory":"Film & Video Production",
            "type":"Services"
        }
    ],
    "sg:phone":"+1 919 349 7643",
    "sg:postcode":"21502",
    "sg:province":"MD",
    "sg:tags":[
        "tv",
        "radio",
        "services-commercial",
        "companies-film"
    ],
    "wof:name":"Guerrilla Productions",
    "wof:placetype":"venue"
},
  "geometry": {"coordinates":[-78.767914,39.650037],"type":"Point"}
}