{
  "type": "Feature",
  "properties": {
    "iso:country":"US",
    "sg:address":"4905 Roland Ave",
    "sg:city":"Baltimore",
    "sg:classifiers":[
        {
            "category":"Social Services",
            "type":"Services"
        }
    ],
    "sg:phone":"+1 410 235 9282",
    "sg:postcode":"21210",
    "sg:province":"MD",
    "wof:name":"Marylnd Wmns Pltfrm Fr Actn",
    "wof:placetype":"venue"
},
  "geometry": {"coordinates":[-76.633996,39.352402],"type":"Point"}
}