{
  "type": "Feature",
  "properties": {
    "iso:country":"US",
    "sg:address":"1 Center Dr",
    "sg:city":"North East",
    "sg:classifiers":[
        {
            "category":"Travel",
            "subcategory":"Hotels & Motels",
            "type":"Entertainment"
        }
    ],
    "sg:phone":"+1 410 287 7100",
    "sg:postcode":"21901",
    "sg:province":"MD",
    "sg:tags":[
        "operation"
    ],
    "sg:website":"www.crystalinns.com",
    "wof:name":"Crystal Inn",
    "wof:placetype":"venue"
},
  "geometry": {"coordinates":[-75.948219,39.62853],"type":"Point"}
}