{
  "type": "Feature",
  "properties": {
    "iso:country":"US",
    "sg:address":"14 N Potomac St",
    "sg:city":"Hagerstown",
    "sg:classifiers":[
        {
            "category":"Education",
            "subcategory":"Dance Studio",
            "type":"Public Place"
        }
    ],
    "sg:phone":"+1 301 733 5833",
    "sg:postcode":"21740",
    "sg:province":"MD",
    "sg:tags":[
        "instruction",
        "dancing"
    ],
    "wof:name":"City Ballet School",
    "wof:placetype":"venue"
},
  "geometry": {"coordinates":[-77.71989,39.642396],"type":"Point"}
}