{
  "type": "Feature",
  "properties": {
    "addr:full":"706 E Alder St Oakland MD 21550",
    "addr:housenumber":"706",
    "addr:postcode":"21550",
    "addr:street":"E Alder St",
    "iso:country":"US",
    "sg:address":"706 E Alder St",
    "sg:city":"Oakland",
    "sg:classifiers":[
        {
            "category":"Health Services",
            "subcategory":"Nursing And Care Facility",
            "type":"Services"
        }
    ],
    "sg:phone":"+1 301 359 3996",
    "sg:postcode":"21550",
    "sg:province":"MD",
    "sg:tags":[
        "home",
        "skilled",
        "convalescent"
    ],
    "wof:name":"Cuppett & Weeks Nursing Home",
    "wof:placetype":"venue"
},
  "geometry": {"coordinates":[-79.401871,39.406267],"type":"Point"}
}