{
  "type": "Feature",
  "properties": {
    "iso:country":"US",
    "sg:address":"30 W Gude Dr",
    "sg:city":"Rockville",
    "sg:classifiers":[
        {
            "category":"Health Services",
            "subcategory":"Clinic",
            "type":"Services"
        }
    ],
    "sg:phone":"+1 301 795 2021",
    "sg:postcode":"20850",
    "sg:province":"MD",
    "wof:name":"Synertech Health Symstem",
    "wof:placetype":"venue"
},
  "geometry": {"coordinates":[-77.16117199999999,39.10655],"type":"Point"}
}