{
  "type": "Feature",
  "properties": {
    "addr:full":"66 E Main St Ste 102 Westminster MD 21157",
    "addr:housenumber":"66",
    "addr:postcode":"21157",
    "addr:street":"E Main St Ste 102",
    "iso:country":"US",
    "sg:address":"66 E Main St Ste 102",
    "sg:city":"Westminster",
    "sg:classifiers":[
        {
            "category":"Food & Beverages",
            "subcategory":"Specialty",
            "type":"Retail Goods"
        },
        {
            "category":"Food & Beverages",
            "subcategory":"Supermarket",
            "type":"Retail Goods"
        }
    ],
    "sg:phone":"+1 410 857 1970",
    "sg:postcode":"21157",
    "sg:province":"MD",
    "sg:tags":[
        "super",
        "product",
        "health",
        "store",
        "diet"
    ],
    "wof:name":"Harvestion Natural Foods",
    "wof:placetype":"venue"
},
  "geometry": {"coordinates":[-76.99458300000001,39.573796],"type":"Point"}
}