{
  "type": "Feature",
  "properties": {
    "addr:full":"42 S Mulberry St Hagerstown MD 21740",
    "addr:housenumber":"42",
    "addr:postcode":"21740",
    "addr:street":"S Mulberry St",
    "iso:country":"US",
    "sg:address":"42 S Mulberry St",
    "sg:city":"Hagerstown",
    "sg:classifiers":[
        {
            "category":"Organizations",
            "subcategory":"Non-profit Organization",
            "type":"Services"
        }
    ],
    "sg:phone":"+1 301 797 7682",
    "sg:postcode":"21740",
    "sg:province":"MD",
    "wof:name":"Washington Cnty Teachers Assn",
    "wof:placetype":"venue"
},
  "geometry": {"coordinates":[-77.717114,39.638917],"type":"Point"}
}