{
  "type": "Feature",
  "properties": {
    "iso:country":"US",
    "sg:address":"4801 Massachusetts Ave NW",
    "sg:city":"Washington",
    "sg:classifiers":[
        {
            "category":"Professional",
            "type":"Services"
        }
    ],
    "sg:phone":"+1 202 895 1610",
    "sg:postcode":"20016",
    "sg:province":"MD",
    "sg:tags":[
        "establishment"
    ],
    "wof:name":"Thelonious Monk Ctr For Jazz",
    "wof:placetype":"venue"
},
  "geometry": {"coordinates":[-77.096763,38.945844],"type":"Point"}
}