{
  "type": "Feature",
  "properties": {
    "addr:full":"18711 Sparkling Water Dr Germantown MD 20874",
    "addr:housenumber":"18711",
    "addr:postcode":"20874",
    "addr:street":"Sparkling Water Dr",
    "iso:country":"US",
    "sg:address":"18711 Sparkling Water Dr",
    "sg:city":"Germantown",
    "sg:classifiers":[
        {
            "category":"Professional",
            "subcategory":"Accounting & Tax Preparation",
            "type":"Services"
        }
    ],
    "sg:phone":"+1 301 515 9665",
    "sg:postcode":"20874",
    "sg:province":"MD",
    "sg:tags":[
        "return",
        "preparation-business"
    ],
    "wof:name":"Rush Taxes",
    "wof:placetype":"venue"
},
  "geometry": {"coordinates":[-77.27531399999999,39.162162],"type":"Point"}
}