{
  "type": "Feature",
  "properties": {
    "addr:full":"109 Ednor Rd Silver Spring MD 20905",
    "addr:housenumber":"109",
    "addr:postcode":"20905",
    "addr:street":"Ednor Rd",
    "iso:country":"US",
    "sg:address":"109 Ednor Rd",
    "sg:city":"Silver Spring",
    "sg:classifiers":[
        {
            "category":"Building & Trades",
            "subcategory":"Landscaping Services",
            "type":"Services"
        }
    ],
    "sg:phone":"+1 301 774 5091",
    "sg:postcode":"20905",
    "sg:province":"MD",
    "wof:name":"Trapani Lawn Care",
    "wof:placetype":"venue"
},
  "geometry": {"coordinates":[-77.02420100000001,39.126499],"type":"Point"}
}