{
  "type": "Feature",
  "properties": {
    "iso:country":"US",
    "sg:address":"7820 Eastern Ave NW",
    "sg:city":"Washington",
    "sg:classifiers":[
        {
            "category":"Banks & Credit Unions",
            "subcategory":"Bank",
            "type":"Services"
        }
    ],
    "sg:phone":"+1 202 829 2200",
    "sg:postcode":"20012",
    "sg:province":"MD",
    "sg:tags":[
        "cashing",
        "check"
    ],
    "wof:name":"Check 'n Go",
    "wof:placetype":"venue"
},
  "geometry": {"coordinates":[-77.027913,38.985426],"type":"Point"}
}