{
  "type": "Feature",
  "properties": {
    "addr:full":"7738 Garrison Rd Hyattsville MD 20784",
    "addr:housenumber":"7738",
    "addr:postcode":"20784",
    "addr:street":"Garrison Rd",
    "iso:country":"US",
    "sg:address":"7738 Garrison Rd",
    "sg:city":"Hyattsville",
    "sg:classifiers":[
        {
            "category":"Freight",
            "type":"Transportation"
        }
    ],
    "sg:phone":"+1 301 577 7162",
    "sg:postcode":"20784",
    "sg:province":"MD",
    "sg:tags":[
        "courier"
    ],
    "wof:name":"GM Express Courier Service",
    "wof:placetype":"venue"
},
  "geometry": {"coordinates":[-76.87541,38.949794],"type":"Point"}
}