{
  "type": "Feature",
  "properties": {
    "addr:full":"110 E 2nd St Frederick MD 21701",
    "addr:housenumber":"110",
    "addr:postcode":"21701",
    "addr:street":"E 2Nd St",
    "iso:country":"US",
    "sg:address":"110 E 2nd St",
    "sg:city":"Frederick",
    "sg:classifiers":[
        {
            "category":"Organizations",
            "subcategory":"Religious Organization",
            "type":"Services"
        }
    ],
    "sg:phone":"+1 301 662 2623",
    "sg:postcode":"21701",
    "sg:province":"MD",
    "sg:tags":[
        "monastery",
        "convent"
    ],
    "wof:name":"St John's Convent",
    "wof:placetype":"venue"
},
  "geometry": {"coordinates":[-77.408658,39.416391],"type":"Point"}
}