{
  "type": "Feature",
  "properties": {
    "addr:full":"14 Gwynnswood Rd Owings Mills MD 21117",
    "addr:housenumber":"14",
    "addr:postcode":"21117",
    "addr:street":"Gwynnswood Rd",
    "iso:country":"US",
    "sg:address":"14 Gwynnswood Rd",
    "sg:city":"Owings Mills",
    "sg:classifiers":[
        {
            "category":"Building & Trades",
            "subcategory":"Cleaning & Sanitation",
            "type":"Services"
        }
    ],
    "sg:phone":"+1 443 394 0400",
    "sg:postcode":"21117",
    "sg:province":"MD",
    "sg:tags":[
        "janitor"
    ],
    "wof:name":"Infinity Cleaning Svc Inc",
    "wof:placetype":"venue"
},
  "geometry": {"coordinates":[-76.792152,39.429279],"type":"Point"}
}