{
  "type": "Feature",
  "properties": {
    "addr:full":"728 Hollywood Pl Forest Hill MD 21050",
    "addr:housenumber":"728",
    "addr:postcode":"21050",
    "addr:street":"Hollywood Pl",
    "iso:country":"US",
    "sg:address":"728 Hollywood Pl",
    "sg:city":"Forest Hill",
    "sg:classifiers":[
        {
            "category":"Retail",
            "subcategory":"Laundry & Dry Cleaning",
            "type":"Services"
        }
    ],
    "sg:phone":"+1 410 803 1913",
    "sg:postcode":"21050",
    "sg:province":"MD",
    "sg:tags":[
        "cleaners",
        "rug",
        "carpet"
    ],
    "wof:name":"B & L Carpet Care",
    "wof:placetype":"venue"
},
  "geometry": {"coordinates":[-76.383135,39.566723],"type":"Point"}
}