{
  "type": "Feature",
  "properties": {
    "addr:full":"10024 Harbor Ave Glenn Dale MD 20769",
    "addr:housenumber":"10024",
    "addr:postcode":"20769",
    "addr:street":"Harbor Ave",
    "iso:country":"US",
    "sg:address":"10024 Harbor Ave",
    "sg:city":"Glenn Dale",
    "sg:classifiers":[
        {
            "category":"Professional",
            "subcategory":"Management & Consulting",
            "type":"Services"
        }
    ],
    "sg:phone":"+1 301 809 9147",
    "sg:postcode":"20769",
    "sg:province":"MD",
    "sg:tags":[
        "business"
    ],
    "wof:name":"Sme Solutions",
    "wof:placetype":"venue"
},
  "geometry": {"coordinates":[-76.816163,38.978858],"type":"Point"}
}