{
  "type": "Feature",
  "properties": {
    "iso:country":"US",
    "sg:address":"256 Tilghman Rd",
    "sg:city":"Salisbury",
    "sg:classifiers":[
        {
            "category":"Personal",
            "type":"Services"
        }
    ],
    "sg:phone":"+1 410 334 3903",
    "sg:postcode":"21804",
    "sg:province":"MD",
    "sg:tags":[
        "control",
        "weight"
    ],
    "wof:name":"Ladies Workout Express",
    "wof:placetype":"venue"
},
  "geometry": {"coordinates":[-75.547611,38.368155],"type":"Point"}
}