{
  "type": "Feature",
  "properties": {
    "iso:country":"US",
    "sg:address":"4305 Saint Barnabas Rd Ste 402",
    "sg:city":"Temple Hills",
    "sg:classifiers":[
        {
            "category":"Education",
            "subcategory":"University",
            "type":"Public Place"
        },
        {
            "category":"Organizations",
            "subcategory":"Religious Organization",
            "type":"Services"
        }
    ],
    "sg:phone":"+1 301 702 2100",
    "sg:postcode":"20748",
    "sg:province":"MD",
    "sg:tags":[
        "college"
    ],
    "wof:name":"Breakthrough Bible College",
    "wof:placetype":"venue"
},
  "geometry": {"coordinates":[-76.941187,38.831106],"type":"Point"}
}