{
  "type": "Feature",
  "properties": {
    "iso:country":"US",
    "sg:address":"3905 Forest School Rd",
    "sg:city":"Smithsburg",
    "sg:classifiers":[
        {
            "category":"Professional",
            "subcategory":"Engineering",
            "type":"Services"
        }
    ],
    "sg:phone":"+1 301 416 0306",
    "sg:postcode":"21783",
    "sg:province":"MD",
    "wof:name":"Arjay Enterprises",
    "wof:placetype":"venue"
},
  "geometry": {"coordinates":[-77.529533,39.595395],"type":"Point"}
}