{
  "type": "Feature",
  "properties": {
    "addr:full":"4104 Upper Beckleysville Rd Hampstead MD 21074",
    "addr:housenumber":"4104",
    "addr:postcode":"21074",
    "addr:street":"Upper Beckleysville Rd",
    "iso:country":"US",
    "sg:address":"4104 Upper Beckleysville Rd",
    "sg:city":"Hampstead",
    "sg:classifiers":[
        {
            "category":"Insurance",
            "subcategory":"Hazard Insurance",
            "type":"Services"
        }
    ],
    "sg:phone":"+1 410 374 8474",
    "sg:postcode":"21074",
    "sg:province":"MD",
    "sg:tags":[
        "bond"
    ],
    "wof:name":"Mike John's Hampstead Bail",
    "wof:placetype":"venue"
},
  "geometry": {"coordinates":[-76.848716,39.611274],"type":"Point"}
}