{
  "type": "Feature",
  "properties": {
    "addr:full":"5454 Wisconsin Ave Ste 745 Chevy Chase MD 20815",
    "addr:housenumber":"5454",
    "addr:postcode":"20815",
    "addr:street":"Wisconsin Ave Ste 745",
    "iso:country":"US",
    "sg:address":"5454 Wisconsin Ave Ste 745",
    "sg:city":"Chevy Chase",
    "sg:classifiers":[
        {
            "category":"Health Services",
            "subcategory":"Doctor",
            "type":"Services"
        }
    ],
    "sg:phone":"+1 301 652 5155",
    "sg:postcode":"20815",
    "sg:province":"MD",
    "sg:tags":[
        "dermatologist"
    ],
    "wof:name":"Ugel Arthur MD",
    "wof:placetype":"venue"
},
  "geometry": {"coordinates":[-77.08669999999999,38.9627],"type":"Point"}
}