{
  "type": "Feature",
  "properties": {
    "addr:full":"822 Dulaney Valley Rd Baltimore MD 21204",
    "addr:housenumber":"822",
    "addr:postcode":"21204",
    "addr:street":"Dulaney Valley Rd",
    "iso:country":"US",
    "sg:address":"822 Dulaney Valley Rd",
    "sg:city":"Baltimore",
    "sg:classifiers":[
        {
            "category":"Restaurant",
            "type":"Food & Drink"
        }
    ],
    "sg:phone":"+1 410 825 2222",
    "sg:postcode":"21204",
    "sg:province":"MD",
    "wof:name":"Boston Market",
    "wof:placetype":"venue"
},
  "geometry": {"coordinates":[-76.601679,39.404807],"type":"Point"}
}