{
  "type": "Feature",
  "properties": {
    "iso:country":"US",
    "sg:address":"9633 Oakdale Ave",
    "sg:city":"Parkville",
    "sg:classifiers":[
        {
            "category":"Building & Trades",
            "subcategory":"Cleaning & Sanitation",
            "type":"Services"
        }
    ],
    "sg:phone":"+1 443 802 1660",
    "sg:postcode":"21234",
    "sg:province":"MD",
    "sg:tags":[
        "janitorial"
    ],
    "wof:name":"D&L Foreclosure Cleanup",
    "wof:placetype":"venue"
},
  "geometry": {"coordinates":[-76.515702,39.398205],"type":"Point"}
}