{
  "type": "Feature",
  "properties": {
    "addr:full":"152 Pennsylvania Ave Westminster MD 21157",
    "addr:housenumber":"152",
    "addr:postcode":"21157",
    "addr:street":"Pennsylvania Ave",
    "iso:country":"US",
    "sg:address":"152 Pennsylvania Ave",
    "sg:city":"Westminster",
    "sg:classifiers":[
        {
            "category":"Health Services",
            "subcategory":"Doctor",
            "type":"Services"
        }
    ],
    "sg:phone":"+1 410 876 0345",
    "sg:postcode":"21157",
    "sg:province":"MD",
    "sg:tags":[
        "dentist"
    ],
    "wof:name":"Paul P Mallek DDS",
    "wof:placetype":"venue"
},
  "geometry": {"coordinates":[-76.99903999999999,39.584994],"type":"Point"}
}