{
  "type": "Feature",
  "properties": {
    "addr:full":"6478 Crain Hwy La Plata MD 20646",
    "addr:housenumber":"6478",
    "addr:postcode":"20646",
    "addr:street":"Crain Hwy",
    "iso:country":"US",
    "sg:address":"6478 Crain Hwy",
    "sg:city":"La Plata",
    "sg:classifiers":[
        {
            "category":"Shopping",
            "type":"Retail Goods"
        }
    ],
    "sg:phone":"+1 301 392 1600",
    "sg:postcode":"20646",
    "sg:province":"MD",
    "sg:tags":[
        "merchandise"
    ],
    "wof:name":"Cellular City",
    "wof:placetype":"venue"
},
  "geometry": {"coordinates":[-76.98313899999999,38.532776],"type":"Point"}
}