{
  "type": "Feature",
  "properties": {
    "addr:full":"9140 Edgeworth Dr Capitol Heights MD 20743",
    "addr:housenumber":"9140",
    "addr:postcode":"20743",
    "addr:street":"Edgeworth Dr",
    "iso:country":"US",
    "sg:address":"9140 Edgeworth Dr",
    "sg:city":"Capitol Heights",
    "sg:classifiers":[
        {
            "category":"Deli",
            "type":"Food & Drink"
        },
        {
            "category":"Food & Beverages",
            "subcategory":"Bakery",
            "type":"Retail Goods"
        }
    ],
    "sg:phone":"+1 301 350 4141",
    "sg:postcode":"20743",
    "sg:province":"MD",
    "sg:tags":[
        "sandwich"
    ],
    "wof:name":"McKay's Carry Out",
    "wof:placetype":"venue"
},
  "geometry": {"coordinates":[-76.84929700000001,38.881302],"type":"Point"}
}