{
  "type": "Feature",
  "properties": {
    "addr:full":"1822 Chester Way Bel Air MD 21015",
    "addr:housenumber":"1822",
    "addr:postcode":"21015",
    "addr:street":"Chester Way",
    "iso:country":"US",
    "sg:address":"1822 Chester Way",
    "sg:city":"Bel Air",
    "sg:classifiers":[
        {
            "category":"Real Estate",
            "subcategory":"Real Estate Agent",
            "type":"Services"
        }
    ],
    "sg:phone":"+1 410 836 8689",
    "sg:postcode":"21015",
    "sg:province":"MD",
    "sg:tags":[
        "management"
    ],
    "wof:name":"R Hutchins Property Management",
    "wof:placetype":"venue"
},
  "geometry": {"coordinates":[-76.322345,39.564008],"type":"Point"}
}