{
  "type": "Feature",
  "properties": {
    "iso:country":"US",
    "sg:address":"2138 Generals Hwy",
    "sg:city":"Annapolis",
    "sg:classifiers":[
        {
            "category":"Home & Garden",
            "subcategory":"Household Appliances",
            "type":"Retail Goods"
        }
    ],
    "sg:phone":"+1 410 224 7500",
    "sg:postcode":"21401",
    "sg:province":"MD",
    "sg:tags":[
        "cleaners",
        "vacuum"
    ],
    "wof:name":"Oreck Vacuum",
    "wof:placetype":"venue"
},
  "geometry": {"coordinates":[-76.548816,38.988488],"type":"Point"}
}