{
  "type": "Feature",
  "properties": {
    "addr:full":"12102 Ashcroft Ct Monrovia MD 21770",
    "addr:housenumber":"12102",
    "addr:postcode":"21770",
    "addr:street":"Ashcroft Ct",
    "iso:country":"US",
    "sg:address":"12102 Ashcroft Ct",
    "sg:city":"Monrovia",
    "sg:classifiers":[
        {
            "category":"Shopping",
            "subcategory":"Gifts & Souvenirs",
            "type":"Retail Goods"
        }
    ],
    "sg:phone":"+1 301 831 6135",
    "sg:postcode":"21770",
    "sg:province":"MD",
    "wof:name":"Secret Stork",
    "wof:placetype":"venue"
},
  "geometry": {"coordinates":[-77.240149,39.321665],"type":"Point"}
}