{
  "type": "Feature",
  "properties": {
    "iso:country":"US",
    "sg:address":"12939 Laurel Bowie Rd",
    "sg:city":"Laurel",
    "sg:classifiers":[
        {
            "category":"Education",
            "subcategory":"Special Training",
            "type":"Public Place"
        }
    ],
    "sg:phone":"+1 301 980 4339",
    "sg:postcode":"20708",
    "sg:province":"MD",
    "sg:tags":[
        "educational"
    ],
    "wof:name":"Idda Grant Writers",
    "wof:placetype":"venue"
},
  "geometry": {"coordinates":[-76.843577,39.070566],"type":"Point"}
}