{
  "type": "Feature",
  "properties": {
    "addr:full":"8087 Parston Dr District Heights MD 20747",
    "addr:housenumber":"8087",
    "addr:postcode":"20747",
    "addr:street":"Parston Dr",
    "iso:country":"US",
    "sg:address":"8087 Parston Dr",
    "sg:city":"District Heights",
    "sg:classifiers":[
        {
            "category":"Manufacturing",
            "subcategory":"Petroleum Products",
            "type":"Manufacturing & Wholesale Goods"
        }
    ],
    "sg:phone":"+1 301 568 0251",
    "sg:postcode":"20747",
    "sg:province":"MD",
    "wof:name":"Petroleum Heat & Power",
    "wof:placetype":"venue"
},
  "geometry": {"coordinates":[-76.869191,38.845858],"type":"Point"}
}