{
  "type": "Feature",
  "properties": {
    "iso:country":"US",
    "sg:address":"26828 Ocean Gtwy",
    "sg:city":"Hebron",
    "sg:classifiers":[
        {
            "category":"Food & Beverages",
            "subcategory":"Groceries & Convenience Stores",
            "type":"Retail Goods"
        }
    ],
    "sg:phone":"+1 410 749 1889",
    "sg:postcode":"21830",
    "sg:province":"MD",
    "sg:tags":[
        "market"
    ],
    "wof:name":"Jack's Market",
    "wof:placetype":"venue"
},
  "geometry": {"coordinates":[-75.682526,38.437279],"type":"Point"}
}