{
  "type": "Feature",
  "properties": {
    "iso:country":"US",
    "sg:address":"5 Cedar Ave",
    "sg:city":"Gaithersburg",
    "sg:classifiers":[
        {
            "category":"Professional",
            "subcategory":"Computer Services",
            "type":"Services"
        }
    ],
    "sg:phone":"+1 301 948 2682",
    "sg:postcode":"20877",
    "sg:province":"MD",
    "sg:tags":[
        "consultant"
    ],
    "wof:name":"Marie A Rundquist",
    "wof:placetype":"venue"
},
  "geometry": {"coordinates":[-77.197996,39.138383],"type":"Point"}
}