{
  "type": "Feature",
  "properties": {
    "iso:country":"US",
    "sg:address":"175 Penrod Ct",
    "sg:city":"Glen Burnie",
    "sg:classifiers":[
        {
            "category":"Freight",
            "type":"Transportation"
        }
    ],
    "sg:phone":"+1 410 477 4021",
    "sg:postcode":"21061",
    "sg:province":"MD",
    "sg:tags":[
        "packing",
        "crating"
    ],
    "wof:name":"World Point Svc",
    "wof:placetype":"venue"
},
  "geometry": {"coordinates":[-76.62240799999999,39.177343],"type":"Point"}
}