{
  "type": "Feature",
  "properties": {
    "addr:full":"1400 Sulphur Spring Rd Halethorpe MD 21227",
    "addr:housenumber":"1400",
    "addr:postcode":"21227",
    "addr:street":"Sulphur Spring Rd",
    "iso:country":"US",
    "sg:address":"1400 Sulphur Spring Rd",
    "sg:city":"Halethorpe",
    "sg:classifiers":[
        {
            "category":"Shopping",
            "subcategory":"Pharmacy",
            "type":"Retail Goods"
        }
    ],
    "sg:phone":"+1 410 737 9221",
    "sg:postcode":"21227",
    "sg:province":"MD",
    "sg:tags":[
        "drugstore"
    ],
    "sg:website":"www.riteaid.com",
    "wof:name":"Rite Aid Pharmacies",
    "wof:placetype":"venue"
},
  "geometry": {"coordinates":[-76.693821,39.247297],"type":"Point"}
}