{
  "type": "Feature",
  "properties": {
    "addr:full":"13302 Pennsylvania Ave Hagerstown MD 21742",
    "addr:housenumber":"13302",
    "addr:postcode":"21742",
    "addr:street":"Pennsylvania Ave",
    "iso:country":"US",
    "sg:address":"13302 Pennsylvania Ave",
    "sg:city":"Hagerstown",
    "sg:classifiers":[
        {
            "category":"Shopping",
            "subcategory":"Discount & Variety Stores",
            "type":"Retail Goods"
        }
    ],
    "sg:phone":"+1 301 745 3013",
    "sg:postcode":"21742",
    "sg:province":"MD",
    "sg:tags":[
        "merchandise",
        "general"
    ],
    "wof:name":"Shearer Industrial Supply",
    "wof:placetype":"venue"
},
  "geometry": {"coordinates":[-77.72013800000001,39.677457],"type":"Point"}
}