{
  "type": "Feature",
  "properties": {
    "addr:full":"38311 New Market Turner Rd Mechanicsville MD 20659",
    "addr:housenumber":"38311",
    "addr:postcode":"20659",
    "addr:street":"New Market Turner Rd",
    "iso:country":"US",
    "sg:address":"38311 New Market Turner Rd",
    "sg:city":"Mechanicsville",
    "sg:classifiers":[
        {
            "category":"Shopping",
            "subcategory":"Bicycles & Sporting Goods",
            "type":"Retail Goods"
        }
    ],
    "sg:phone":"+1 301 274 9450",
    "sg:postcode":"20659",
    "sg:province":"MD",
    "sg:tags":[
        "tackle",
        "fishing"
    ],
    "wof:name":"Tip To Tip Inc",
    "wof:placetype":"venue"
},
  "geometry": {"coordinates":[-76.74729600000001,38.468631],"type":"Point"}
}