{
  "type": "Feature",
  "properties": {
    "iso:country":"US",
    "sg:address":"7389 Washington Blvd",
    "sg:city":"Elkridge",
    "sg:classifiers":[
        {
            "category":"Building & Trades",
            "subcategory":"Construction",
            "type":"Services"
        }
    ],
    "sg:phone":"+1 410 879 9696",
    "sg:postcode":"21075",
    "sg:province":"MD",
    "sg:tags":[
        "system",
        "specialty",
        "supply",
        "sales",
        "heating",
        "contractor",
        "air conditioning",
        "radiators-heating"
    ],
    "wof:name":"Blue Dot Heating & Air Conditioning",
    "wof:placetype":"venue"
},
  "geometry": {"coordinates":[-76.766621,39.182005],"type":"Point"}
}