{
  "type": "Feature",
  "properties": {
    "addr:full":"4 Harko Ct Essex MD 21221",
    "addr:housenumber":"4",
    "addr:postcode":"21221",
    "addr:street":"Harko Ct",
    "iso:country":"US",
    "sg:address":"4 Harko Ct",
    "sg:city":"Essex",
    "sg:classifiers":[
        {
            "category":"Building & Trades",
            "subcategory":"Equipment Rental",
            "type":"Services"
        }
    ],
    "sg:phone":"+1 410 391 5860",
    "sg:postcode":"21221",
    "sg:province":"MD",
    "sg:tags":[
        "toilet",
        "toilets-portable"
    ],
    "wof:name":"Spot-A-Pot Inc",
    "wof:placetype":"venue"
},
  "geometry": {"coordinates":[-76.466285,39.339456],"type":"Point"}
}