{
  "type": "Feature",
  "properties": {
    "addr:full":"22252 Nanticoke Rd Tyaskin MD 21865",
    "addr:postcode":"22252;21865",
    "addr:street":"Nanticoke Rd",
    "iso:country":"US",
    "sg:address":"22252 Nanticoke Rd",
    "sg:city":"Tyaskin",
    "sg:phone":"+1 410 873 2233",
    "sg:postcode":"21865",
    "sg:province":"MD",
    "sg:tags":[
        "farm",
        "soybean"
    ],
    "wof:name":"James Farrington",
    "wof:placetype":"venue"
},
  "geometry": {"coordinates":[-75.84218300000001,38.3066],"type":"Point"}
}