{
  "type": "Feature",
  "properties": {
    "iso:country":"US",
    "sg:address":"14219 Travilah Rd",
    "sg:city":"Rockville",
    "sg:classifiers":[
        {
            "category":"Building & Trades",
            "subcategory":"Construction",
            "type":"Services"
        }
    ],
    "sg:phone":"+1 301 309 8450",
    "sg:postcode":"20850",
    "sg:province":"MD",
    "sg:tags":[
        "home",
        "builder"
    ],
    "wof:name":"NVR Homes Inc",
    "wof:placetype":"venue"
},
  "geometry": {"coordinates":[-77.21424399999999,39.08883],"type":"Point"}
}