{
  "type": "Feature",
  "properties": {
    "addr:full":"506 Mauser Dr Bel Air MD 21015",
    "addr:housenumber":"506",
    "addr:postcode":"21015",
    "addr:street":"Mauser Dr",
    "iso:country":"US",
    "sg:address":"506 Mauser Dr",
    "sg:city":"Bel Air",
    "sg:classifiers":[
        {
            "category":"Building & Trades",
            "subcategory":"Electrical",
            "type":"Services"
        }
    ],
    "sg:phone":"+1 410 838 8004",
    "sg:postcode":"21015",
    "sg:province":"MD",
    "sg:tags":[
        "electrical",
        "contractor"
    ],
    "wof:name":"Phase Electric",
    "wof:placetype":"venue"
},
  "geometry": {"coordinates":[-76.30210700000001,39.543879],"type":"Point"}
}