{
  "type": "Feature",
  "properties": {
    "iso:country":"US",
    "sg:address":"306 Tilghman Rd",
    "sg:city":"Salisbury",
    "sg:classifiers":[
        {
            "category":"Social Services",
            "subcategory":"Child Care",
            "type":"Services"
        }
    ],
    "sg:phone":"+1 410 546 9911",
    "sg:postcode":"21804",
    "sg:province":"MD",
    "wof:name":"Step Ahead Early Learning Ctr",
    "wof:placetype":"venue"
},
  "geometry": {"coordinates":[-75.54797000000001,38.363903],"type":"Point"}
}