{
  "type": "Feature",
  "properties": {
    "addr:full":"176 Thomas Johnson Dr Frederick MD 21702",
    "addr:housenumber":"176",
    "addr:postcode":"21702",
    "addr:street":"Thomas Johnson Dr",
    "iso:country":"US",
    "sg:address":"176 Thomas Johnson Dr",
    "sg:city":"Frederick",
    "sg:classifiers":[
        {
            "category":"Health Services",
            "subcategory":"Health Practitioner",
            "type":"Services"
        }
    ],
    "sg:phone":"+1 301 668 1140",
    "sg:postcode":"21702",
    "sg:province":"MD",
    "wof:name":"A Positive Stroke",
    "wof:placetype":"venue"
},
  "geometry": {"coordinates":[-77.406227,39.442339],"type":"Point"}
}