{
  "type": "Feature",
  "properties": {
    "iso:country":"US",
    "sg:address":"4329 E Lombard St",
    "sg:city":"Baltimore",
    "sg:classifiers":[
        {
            "category":"Restaurant",
            "type":"Food & Drink"
        }
    ],
    "sg:phone":"+1 410 675 9222",
    "sg:postcode":"21224",
    "sg:province":"MD",
    "sg:tags":[
        "eating"
    ],
    "wof:name":"Lomba Sub Shop",
    "wof:placetype":"venue"
},
  "geometry": {"coordinates":[-76.560102,39.29162],"type":"Point"}
}