{
  "type": "Feature",
  "properties": {
    "iso:country":"US",
    "sg:address":"1330 Black Walnut Ct",
    "sg:city":"Annapolis",
    "sg:classifiers":[
        {
            "category":"Professional",
            "subcategory":"Computer Services",
            "type":"Services"
        }
    ],
    "sg:phone":"+1 410 263 0479",
    "sg:postcode":"21403",
    "sg:province":"MD",
    "sg:tags":[
        "related"
    ],
    "wof:name":"Britz Networks",
    "wof:placetype":"venue"
},
  "geometry": {"coordinates":[-76.479618,38.939283],"type":"Point"}
}