{
  "type": "Feature",
  "properties": {
    "iso:country":"US",
    "sg:address":"9216 Bells Mill Rd",
    "sg:city":"Potomac",
    "sg:classifiers":[
        {
            "category":"Sports & Exercise",
            "subcategory":"Gym",
            "type":"Entertainment"
        }
    ],
    "sg:phone":"+1 301 983 2715",
    "sg:postcode":"20854",
    "sg:province":"MD",
    "sg:tags":[
        "trainer"
    ],
    "wof:name":"Gymworks Company",
    "wof:placetype":"venue"
},
  "geometry": {"coordinates":[-77.189409,39.035401],"type":"Point"}
}