{
  "type": "Feature",
  "properties": {
    "addr:full":"10095 N 2nd St Laurel MD 20723",
    "addr:housenumber":"10095",
    "addr:postcode":"20723",
    "addr:street":"N 2Nd St",
    "iso:country":"US",
    "sg:address":"10095 N 2nd St",
    "sg:city":"Laurel",
    "sg:classifiers":[
        {
            "category":"Autos & Motor Vehicles",
            "subcategory":"Automobile Sales",
            "type":"Retail Goods"
        }
    ],
    "sg:phone":"+1 301 725 7888",
    "sg:postcode":"20723",
    "sg:province":"MD",
    "sg:tags":[
        "dealers-used",
        "car",
        "used",
        "cars-wholesale"
    ],
    "wof:name":"Fuentes Motors, Inc.",
    "wof:placetype":"venue"
},
  "geometry": {"coordinates":[-76.836877,39.1089],"type":"Point"}
}