{
  "type": "Feature",
  "properties": {
    "addr:full":"5055 Mussetter Rd Ijamsville MD 21754",
    "addr:housenumber":"5055",
    "addr:postcode":"21754",
    "addr:street":"Mussetter Rd",
    "iso:country":"US",
    "sg:address":"5055 Mussetter Rd",
    "sg:city":"Ijamsville",
    "sg:classifiers":[
        {
            "category":"Professional",
            "subcategory":"Management & Consulting",
            "type":"Services"
        }
    ],
    "sg:phone":"+1 301 865 0090",
    "sg:postcode":"21754",
    "sg:province":"MD",
    "sg:tags":[
        "consultant",
        "training"
    ],
    "wof:name":"Comworks",
    "wof:placetype":"venue"
},
  "geometry": {"coordinates":[-77.309071,39.376883],"type":"Point"}
}