{
  "type": "Feature",
  "properties": {
    "iso:country":"US",
    "sg:address":"9913 Brookhaven Ln",
    "sg:city":"Upper Marlboro",
    "sg:classifiers":[
        {
            "category":"Building & Trades",
            "subcategory":"Electrical",
            "type":"Services"
        }
    ],
    "sg:phone":"+1 301 780 7332",
    "sg:postcode":"20772",
    "sg:province":"MD",
    "sg:tags":[
        "electric",
        "contractor"
    ],
    "wof:name":"Critical Mission Electric",
    "wof:placetype":"venue"
},
  "geometry": {"coordinates":[-76.789428,38.749647],"type":"Point"}
}