{
  "type": "Feature",
  "properties": {
    "iso:country":"US",
    "sg:address":"301 N Charles St",
    "sg:city":"Baltimore",
    "sg:classifiers":[
        {
            "category":"Professional",
            "subcategory":"Engineering",
            "type":"Services"
        }
    ],
    "sg:phone":"+1 443 524 2700",
    "sg:postcode":"21201",
    "sg:province":"MD",
    "sg:tags":[
        "engineer"
    ],
    "wof:name":"Navarro & Wright Consulting",
    "wof:placetype":"venue"
},
  "geometry": {"coordinates":[-76.615462,39.293579],"type":"Point"}
}