{
  "type": "Feature",
  "properties": {
    "addr:full":"1900 Broening Hwy Baltimore MD 21224",
    "addr:housenumber":"1900",
    "addr:postcode":"21224",
    "addr:street":"Broening Hwy",
    "iso:country":"US",
    "sg:address":"1900 Broening Hwy",
    "sg:city":"Baltimore",
    "sg:classifiers":[
        {
            "category":"Military Area",
            "type":"Public Place"
        }
    ],
    "sg:phone":"+1 410 631 7733",
    "sg:postcode":"21224",
    "sg:province":"MD",
    "sg:tags":[
        "force",
        "armed",
        "recruiting"
    ],
    "wof:name":"United States Government Departments Army Unit",
    "wof:placetype":"venue"
},
  "geometry": {"coordinates":[-76.543119,39.269333],"type":"Point"}
}