{
  "type": "Feature",
  "properties": {
    "addr:full":"2340 Riggs Ave Baltimore MD 21216",
    "addr:housenumber":"2340",
    "addr:postcode":"21216",
    "addr:street":"Riggs Ave",
    "iso:country":"US",
    "sg:address":"2340 Riggs Ave",
    "sg:city":"Baltimore",
    "sg:classifiers":[
        {
            "category":"Transit Center",
            "subcategory":"Freight",
            "type":"Transportation"
        }
    ],
    "sg:phone":"+1 410 566 1209",
    "sg:postcode":"21216",
    "sg:province":"MD",
    "sg:tags":[
        "trucking-light",
        "hauling"
    ],
    "wof:name":"G R Moving Hauling",
    "wof:placetype":"venue"
},
  "geometry": {"coordinates":[-76.65419199999999,39.300658],"type":"Point"}
}