{
  "type": "Feature",
  "properties": {
    "addr:full":"8601 Walther Blvd Ste 103 Nottingham MD 21236",
    "addr:housenumber":"8601",
    "addr:postcode":"21236",
    "addr:street":"Walther Blvd Ste 103",
    "iso:country":"US",
    "sg:address":"8601 Walther Blvd Ste 103",
    "sg:city":"Nottingham",
    "sg:classifiers":[
        {
            "category":"Coffee & Tea",
            "type":"Food & Drink"
        },
        {
            "category":"Health Services",
            "subcategory":"Health Practitioner",
            "type":"Services"
        }
    ],
    "sg:phone":"+1 410 663 8333",
    "sg:postcode":"21236",
    "sg:province":"MD",
    "sg:tags":[
        "naturopathic/holistic"
    ],
    "sg:website":"mystickalvoyage.com",
    "wof:name":"Mystickal Voyage",
    "wof:placetype":"venue"
},
  "geometry": {"coordinates":[-76.445396,39.374594],"type":"Point"}
}