{
  "type": "Feature",
  "properties": {
    "addr:full":"918 Morris Ave Lutherville Timonium MD 21093",
    "addr:housenumber":"918",
    "addr:postcode":"21093",
    "addr:street":"Morris Ave",
    "iso:country":"US",
    "sg:address":"918 Morris Ave",
    "sg:city":"Lutherville Timonium",
    "sg:classifiers":[
        {
            "category":"Building & Trades",
            "subcategory":"Landscaping Services",
            "type":"Services"
        }
    ],
    "sg:phone":"+1 410 252 8889",
    "sg:postcode":"21093",
    "sg:province":"MD",
    "wof:name":"Barrons Lawn Service",
    "wof:placetype":"venue"
},
  "geometry": {"coordinates":[-76.63351299999999,39.432604],"type":"Point"}
}