{
  "type": "Feature",
  "properties": {
    "iso:country":"US",
    "sg:address":"22528 Goose Hollow Dr",
    "sg:city":"Chestertown",
    "sg:classifiers":[
        {
            "category":"Organizations",
            "subcategory":"Community Association",
            "type":"Services"
        }
    ],
    "sg:phone":"+1 410 778 1345",
    "sg:postcode":"21620",
    "sg:province":"MD",
    "wof:name":"Fairlee Creek Civic Assn",
    "wof:placetype":"venue"
},
  "geometry": {"coordinates":[-76.187934,39.24036],"type":"Point"}
}