{
  "type": "Feature",
  "properties": {
    "addr:full":"4373 Northview Dr Bowie MD 20716",
    "addr:housenumber":"4373",
    "addr:postcode":"20716",
    "addr:street":"Northview Dr",
    "iso:country":"US",
    "sg:address":"4373 Northview Dr",
    "sg:city":"Bowie",
    "sg:classifiers":[
        {
            "category":"Health Services",
            "subcategory":"Doctor",
            "type":"Services"
        }
    ],
    "sg:phone":"+1 301 464 8707",
    "sg:postcode":"20716",
    "sg:province":"MD",
    "sg:tags":[
        "dentist"
    ],
    "wof:name":"Gary P Ludka DDS",
    "wof:placetype":"venue"
},
  "geometry": {"coordinates":[-76.734949,38.949811],"type":"Point"}
}