{
  "type": "Feature",
  "properties": {
    "addr:full":"6251 Columbia Xing Columbia MD 21045",
    "addr:housenumber":"6251",
    "addr:postcode":"21045",
    "addr:street":"Columbia Xing",
    "iso:country":"US",
    "sg:address":"6251 Columbia Xing",
    "sg:city":"Columbia",
    "sg:classifiers":[
        {
            "category":"Autos & Motor Vehicles",
            "subcategory":"Fuel & Gas Station",
            "type":"Retail Goods"
        }
    ],
    "sg:phone":"+1 410 312 0028",
    "sg:postcode":"21045",
    "sg:province":"MD",
    "sg:tags":[
        "oil"
    ],
    "wof:name":"Columbia Crossing Amoco",
    "wof:placetype":"venue"
},
  "geometry": {"coordinates":[-76.814753,39.198031],"type":"Point"}
}