{
  "type": "Feature",
  "properties": {
    "iso:country":"US",
    "sg:address":"2401 Blueridge Ave",
    "sg:city":"Silver Spring",
    "sg:classifiers":[
        {
            "category":"Professional",
            "subcategory":"Lawyer & Legal Services",
            "type":"Services"
        }
    ],
    "sg:phone":"+1 301 949 4106",
    "sg:postcode":"20902",
    "sg:province":"MD",
    "wof:name":"Venable David C",
    "wof:placetype":"venue"
},
  "geometry": {"coordinates":[-77.052047,39.043082],"type":"Point"}
}