{
  "type": "Feature",
  "properties": {
    "addr:full":"3515 Milford Mill Rd Baltimore MD 21244",
    "addr:housenumber":"3515",
    "addr:postcode":"21244",
    "addr:street":"Milford Mill Rd",
    "iso:country":"US",
    "sg:address":"3515 Milford Mill Rd",
    "sg:city":"Baltimore",
    "sg:classifiers":[
        {
            "category":"Shopping",
            "subcategory":"Florist",
            "type":"Retail Goods"
        }
    ],
    "sg:phone":"+1 410 922 0138",
    "sg:postcode":"21244",
    "sg:province":"MD",
    "wof:name":"Enchanted Unicorn",
    "wof:placetype":"venue"
},
  "geometry": {"coordinates":[-76.75964500000001,39.352654],"type":"Point"}
}