{
  "type": "Feature",
  "properties": {
    "addr:full":"1209 East St Frederick MD 21701",
    "addr:housenumber":"1209",
    "addr:postcode":"21701",
    "addr:street":"East St",
    "iso:country":"US",
    "sg:address":"1209 East St",
    "sg:city":"Frederick",
    "sg:classifiers":[
        {
            "category":"Real Estate",
            "subcategory":"Real Estate Agent",
            "type":"Services"
        }
    ],
    "sg:phone":"+1 301 694 0277",
    "sg:postcode":"21701",
    "sg:province":"MD",
    "wof:name":"Frederick Business Properties",
    "wof:placetype":"venue"
},
  "geometry": {"coordinates":[-77.40333200000001,39.429091],"type":"Point"}
}