{
  "type": "Feature",
  "properties": {
    "addr:full":"106 Marlboro Ave Ste 4 Easton MD 21601",
    "addr:housenumber":"106",
    "addr:postcode":"21601",
    "addr:street":"Marlboro Ave Ste 4",
    "iso:country":"US",
    "sg:address":"106 Marlboro Ave Ste 4",
    "sg:city":"Easton",
    "sg:classifiers":[
        {
            "category":"Health Services",
            "subcategory":"Clinic",
            "type":"Services"
        }
    ],
    "sg:phone":"+1 410 770 9623",
    "sg:postcode":"21601",
    "sg:province":"MD",
    "sg:tags":[
        "welfare"
    ],
    "wof:name":"Pet Health Clinic",
    "wof:placetype":"venue"
},
  "geometry": {"coordinates":[-76.075667,38.780819],"type":"Point"}
}