{
  "type": "Feature",
  "properties": {
    "iso:country":"US",
    "sg:address":"10815 Beaver Dam Rd",
    "sg:city":"Cockysvl Hnt Vly",
    "sg:classifiers":[
        {
            "category":"Building & Trades",
            "subcategory":"Plumbing",
            "type":"Services"
        }
    ],
    "sg:phone":"+1 410 785 1116",
    "sg:postcode":"21030",
    "sg:province":"MD",
    "sg:tags":[
        "plumbing",
        "contractor"
    ],
    "wof:name":"D & I Mechanical Contractors",
    "wof:placetype":"venue"
},
  "geometry": {"coordinates":[-76.65475600000001,39.479669],"type":"Point"}
}