{
  "type": "Feature",
  "properties": {
    "iso:country":"US",
    "sg:address":"450 Guilford Ave Ste 204",
    "sg:city":"Hagerstown",
    "sg:classifiers":[
        {
            "category":"Organizations",
            "subcategory":"Community Association",
            "type":"Services"
        }
    ],
    "sg:phone":"+1 301 797 1201",
    "sg:postcode":"21740",
    "sg:province":"MD",
    "sg:tags":[
        "club"
    ],
    "wof:name":"National Assoc To Advance Fat Acceptance",
    "wof:placetype":"venue"
},
  "geometry": {"coordinates":[-77.72745,39.634824],"type":"Point"}
}