{
  "type": "Feature",
  "properties": {
    "addr:full":"8 Church Ln Baltimore MD 21208",
    "addr:housenumber":"8",
    "addr:postcode":"21208",
    "addr:street":"Church Ln",
    "iso:country":"US",
    "sg:address":"8 Church Ln",
    "sg:city":"Baltimore",
    "sg:classifiers":[
        {
            "category":"Insurance",
            "subcategory":"Insurance Agent",
            "type":"Services"
        }
    ],
    "sg:phone":"+1 410 653 6116",
    "sg:postcode":"21208",
    "sg:province":"MD",
    "sg:website":"www.cissubstandard.com",
    "wof:name":"Competitive Insurance Svc",
    "wof:placetype":"venue"
},
  "geometry": {"coordinates":[-76.724508,39.375038],"type":"Point"}
}