{
  "type": "Feature",
  "properties": {
    "iso:country":"US",
    "sg:address":"1932 Hanover Pike",
    "sg:city":"Hampstead",
    "sg:classifiers":[
        {
            "category":"Professional",
            "subcategory":"Art Services",
            "type":"Services"
        }
    ],
    "sg:phone":"+1 410 787 2278",
    "sg:postcode":"21074",
    "sg:province":"MD",
    "sg:tags":[
        "graphic",
        "designer"
    ],
    "wof:name":"Core Reaction",
    "wof:placetype":"venue"
},
  "geometry": {"coordinates":[-76.860356,39.626431],"type":"Point"}
}