{
  "type": "Feature",
  "properties": {
    "iso:country":"US",
    "sg:address":"3653 Leonardtown Rd",
    "sg:city":"Waldorf",
    "sg:classifiers":[
        {
            "category":"Personal",
            "subcategory":"Beauty Salon",
            "type":"Services"
        }
    ],
    "sg:phone":"+1 301 885 3393",
    "sg:postcode":"20601",
    "sg:province":"MD",
    "wof:name":"Dede Quality Hair Braiding",
    "wof:placetype":"venue"
},
  "geometry": {"coordinates":[-76.893438,38.617869],"type":"Point"}
}