{
  "type": "Feature",
  "properties": {
    "addr:full":"22 W Main St New Market MD 21774",
    "addr:housenumber":"22",
    "addr:postcode":"21774",
    "addr:street":"W Main St",
    "iso:country":"US",
    "sg:address":"22 W Main St",
    "sg:city":"New Market",
    "sg:classifiers":[
        {
            "category":"Home & Garden",
            "subcategory":"Garden Supply",
            "type":"Retail Goods"
        }
    ],
    "sg:phone":"+1 301 865 2787",
    "sg:postcode":"21774",
    "sg:province":"MD",
    "sg:tags":[
        "center"
    ],
    "wof:name":"Fiacre A Secret Garden",
    "wof:placetype":"venue"
},
  "geometry": {"coordinates":[-77.270962,39.382909],"type":"Point"}
}