{
  "type": "Feature",
  "properties": {
    "addr:full":"401 Frederick Rd Catonsville MD 21228",
    "addr:housenumber":"401",
    "addr:postcode":"21228",
    "addr:street":"Frederick Rd",
    "iso:country":"US",
    "sg:address":"401 Frederick Rd",
    "sg:city":"Catonsville",
    "sg:classifiers":[
        {
            "category":"Professional",
            "subcategory":"Lawyer & Legal Services",
            "type":"Services"
        }
    ],
    "sg:phone":"+1 410 747 3330",
    "sg:postcode":"21228",
    "sg:province":"MD",
    "wof:name":"Gosnell Wm Franklin",
    "wof:placetype":"venue"
},
  "geometry": {"coordinates":[-76.726794,39.272887],"type":"Point"}
}