{
  "type": "Feature",
  "properties": {
    "iso:country":"US",
    "sg:address":"7501 Greenway Center Dr",
    "sg:city":"Greenbelt",
    "sg:classifiers":[
        {
            "category":"Restaurant",
            "type":"Food & Drink"
        }
    ],
    "sg:phone":"+1 301 345 3300",
    "sg:postcode":"20770",
    "sg:province":"MD",
    "sg:tags":[
        "delicatessen"
    ],
    "wof:name":"Uptown Deli",
    "wof:placetype":"venue"
},
  "geometry": {"coordinates":[-76.881028,38.990939],"type":"Point"}
}