{
  "type": "Feature",
  "properties": {
    "addr:full":"5370 Deale Churchton Rd Churchton MD 20733",
    "addr:housenumber":"5370",
    "addr:postcode":"20733",
    "addr:street":"Deale Churchton Rd",
    "iso:country":"US",
    "sg:address":"5370 Deale Churchton Rd",
    "sg:city":"Churchton",
    "sg:classifiers":[
        {
            "category":"Retail",
            "subcategory":"Repair Shop",
            "type":"Services"
        },
        {
            "category":"Professional",
            "subcategory":"Detective & Security Services",
            "type":"Services"
        }
    ],
    "sg:phone":"+1 410 867 4559",
    "sg:postcode":"20733",
    "sg:province":"MD",
    "sg:tags":[
        "skip",
        "tracing",
        "bail",
        "bond"
    ],
    "wof:name":"Paco's Bail Bonds",
    "wof:placetype":"venue"
},
  "geometry": {"coordinates":[-76.539123,38.810995],"type":"Point"}
}