{
  "type": "Feature",
  "properties": {
    "addr:full":"19220 Gatlin Dr Gaithersburg MD 20879",
    "addr:postcode":"19220;20879",
    "addr:street":"Gatlin Dr",
    "iso:country":"US",
    "sg:address":"19220 Gatlin Dr",
    "sg:city":"Gaithersburg",
    "sg:classifiers":[
        {
            "category":"Restaurant",
            "type":"Food & Drink"
        }
    ],
    "sg:phone":"+1 301 740 9865",
    "sg:postcode":"20879",
    "sg:province":"MD",
    "sg:tags":[
        "mexican"
    ],
    "wof:name":"Latin Mex Rest",
    "wof:placetype":"venue"
},
  "geometry": {"coordinates":[-77.22007000000001,39.170998],"type":"Point"}
}