{
  "type": "Feature",
  "properties": {
    "addr:full":"12551 Carrington Hill Dr Gaithersburg MD 20878",
    "addr:housenumber":"12551",
    "addr:postcode":"20878",
    "addr:street":"Carrington Hill Dr",
    "iso:country":"US",
    "sg:address":"12551 Carrington Hill Dr",
    "sg:city":"Gaithersburg",
    "sg:classifiers":[
        {
            "category":"Professional",
            "subcategory":"Management & Consulting",
            "type":"Services"
        }
    ],
    "sg:phone":"+1 301 975 0050",
    "sg:postcode":"20878",
    "sg:province":"MD",
    "sg:tags":[
        "consultant",
        "telecommunication"
    ],
    "wof:name":"Campbell Associates",
    "wof:placetype":"venue"
},
  "geometry": {"coordinates":[-77.262376,39.120593],"type":"Point"}
}