{
  "type": "Feature",
  "properties": {
    "iso:country":"US",
    "sg:address":"1220 Tech Ct",
    "sg:city":"Westminster",
    "sg:classifiers":[
        {
            "category":"Manufacturing",
            "subcategory":"Electronics",
            "type":"Manufacturing & Wholesale Goods"
        }
    ],
    "sg:phone":"+1 410 848 5542",
    "sg:postcode":"21157",
    "sg:province":"MD",
    "sg:tags":[
        "equipment",
        "electronic",
        "supply"
    ],
    "sg:website":"www.integralcomponents.com",
    "wof:name":"Integral Components LLC",
    "wof:placetype":"venue"
},
  "geometry": {"coordinates":[-76.991787,39.608621],"type":"Point"}
}