{
  "type": "Feature",
  "properties": {
    "iso:country":"US",
    "sg:address":"1635 Eastern Ave 2",
    "sg:city":"Baltimore",
    "sg:classifiers":[
        {
            "category":"Professional",
            "subcategory":"Accounting & Tax Preparation",
            "type":"Services"
        },
        {
            "category":"Insurance",
            "subcategory":"Hazard Insurance",
            "type":"Services"
        }
    ],
    "sg:phone":"+1 410 342 6134",
    "sg:postcode":"21231",
    "sg:province":"MD",
    "sg:tags":[
        "commercial",
        "return",
        "business",
        "preparation-business"
    ],
    "wof:name":"Kopera Tax Service",
    "wof:placetype":"venue"
},
  "geometry": {"coordinates":[-76.594402,39.285559],"type":"Point"}
}