{
  "type": "Feature",
  "properties": {
    "addr:full":"1534 Falstone Ln Crofton MD 21114",
    "addr:housenumber":"1534",
    "addr:postcode":"21114",
    "addr:street":"Falstone Ln",
    "iso:country":"US",
    "sg:address":"1534 Falstone Ln",
    "sg:city":"Crofton",
    "sg:classifiers":[
        {
            "category":"Building & Trades",
            "subcategory":"Construction",
            "type":"Services"
        }
    ],
    "sg:phone":"+1 410 451 0300",
    "sg:postcode":"21114",
    "sg:province":"MD",
    "sg:tags":[
        "contractor"
    ],
    "wof:name":"Wayson Construction",
    "wof:placetype":"venue"
},
  "geometry": {"coordinates":[-76.675685,39.024128],"type":"Point"}
}