{
  "type": "Feature",
  "properties": {
    "addr:full":"133 Defense Hwy Annapolis MD 21401",
    "addr:housenumber":"133",
    "addr:postcode":"21401",
    "addr:street":"Defense Hwy",
    "iso:country":"US",
    "sg:address":"133 Defense Hwy",
    "sg:city":"Annapolis",
    "sg:classifiers":[
        {
            "category":"Professional",
            "subcategory":"Accounting & Tax Preparation",
            "type":"Services"
        }
    ],
    "sg:phone":"+1 410 224 7559",
    "sg:postcode":"21401",
    "sg:province":"MD",
    "sg:tags":[
        "bookkeeping",
        "general"
    ],
    "wof:name":"Roberta Ward & Assoc",
    "wof:placetype":"venue"
},
  "geometry": {"coordinates":[-76.551784,38.985517],"type":"Point"}
}