{
  "type": "Feature",
  "properties": {
    "addr:full":"6590 Old Waterloo Rd Elkridge MD 21075",
    "addr:housenumber":"6590",
    "addr:postcode":"21075",
    "addr:street":"Old Waterloo Rd",
    "iso:country":"US",
    "sg:address":"6590 Old Waterloo Rd",
    "sg:city":"Elkridge",
    "sg:classifiers":[
        {
            "category":"Personal",
            "subcategory":"Tanning Parlor",
            "type":"Services"
        }
    ],
    "sg:phone":"+1 410 799 4690",
    "sg:postcode":"21075",
    "sg:province":"MD",
    "sg:tags":[
        "salon"
    ],
    "wof:name":"Lark Brown Tanning Salon",
    "wof:placetype":"venue"
},
  "geometry": {"coordinates":[-76.79150199999999,39.188973],"type":"Point"}
}