{
  "type": "Feature",
  "properties": {
    "addr:full":"14524 Cutstone Way Silver Spring MD 20905",
    "addr:housenumber":"14524",
    "addr:postcode":"20905",
    "addr:street":"Cutstone Way",
    "iso:country":"US",
    "sg:address":"14524 Cutstone Way",
    "sg:city":"Silver Spring",
    "sg:classifiers":[
        {
            "category":"Professional",
            "subcategory":"Management & Consulting",
            "type":"Services"
        }
    ],
    "sg:phone":"+1 301 989 0354",
    "sg:postcode":"20905",
    "sg:province":"MD",
    "sg:tags":[
        "retail",
        "direct",
        "sales"
    ],
    "wof:name":"Marcia Nilson Ruf",
    "wof:placetype":"venue"
},
  "geometry": {"coordinates":[-77.02646,39.102754],"type":"Point"}
}