{
  "type": "Feature",
  "properties": {
    "iso:country":"US",
    "sg:address":"6400 Central Ave",
    "sg:city":"Capitol Heights",
    "sg:classifiers":[
        {
            "category":"Autos & Motor Vehicles",
            "subcategory":"Fuel & Gas Station",
            "type":"Retail Goods"
        }
    ],
    "sg:phone":"+1 301 499 4340",
    "sg:postcode":"20743",
    "sg:province":"MD",
    "wof:name":"Central Exxon",
    "wof:placetype":"venue"
},
  "geometry": {"coordinates":[-76.89769699999999,38.886799],"type":"Point"}
}