{
  "type": "Feature",
  "properties": {
    "addr:full":"4101 N Point Blvd Baltimore MD 21222",
    "addr:housenumber":"4101",
    "addr:postcode":"21222",
    "addr:street":"N Point Blvd",
    "iso:country":"US",
    "sg:address":"4101 N Point Blvd",
    "sg:city":"Baltimore",
    "sg:classifiers":[
        {
            "category":"Autos & Motor Vehicles",
            "subcategory":"Auto Supplies",
            "type":"Retail Goods"
        }
    ],
    "sg:phone":"+1 410 477 9035",
    "sg:postcode":"21222",
    "sg:province":"MD",
    "sg:tags":[
        "automobile",
        "parts"
    ],
    "sg:website":"www.hatmachine.com",
    "wof:name":"Hat's Auto Parts & Machine Co",
    "wof:placetype":"venue"
},
  "geometry": {"coordinates":[-76.46743499999999,39.26593],"type":"Point"}
}