{
  "type": "Feature",
  "properties": {
    "addr:full":"1510 Old Eastern Ave Essex MD 21221",
    "addr:housenumber":"1510",
    "addr:postcode":"21221",
    "addr:street":"Old Eastern Ave",
    "iso:country":"US",
    "sg:address":"1510 Old Eastern Ave",
    "sg:city":"Essex",
    "sg:classifiers":[
        {
            "category":"Professional",
            "subcategory":"Accounting & Tax Preparation",
            "type":"Services"
        }
    ],
    "sg:phone":"+1 410 574 4023",
    "sg:postcode":"21221",
    "sg:province":"MD",
    "sg:tags":[
        "return",
        "filing"
    ],
    "wof:name":"SMG Tax Svc",
    "wof:placetype":"venue"
},
  "geometry": {"coordinates":[-76.454368,39.314444],"type":"Point"}
}