{
  "type": "Feature",
  "properties": {
    "addr:full":"8900 Edgeworth Dr Ste J Capitol Hgts MD 20743",
    "addr:housenumber":"8900",
    "addr:postcode":"20743",
    "addr:street":"Edgeworth Dr Ste J Capitol",
    "iso:country":"US",
    "sg:address":"8900 Edgeworth Dr Ste J",
    "sg:city":"Capitol Hgts",
    "sg:classifiers":[
        {
            "category":"Building & Trades",
            "subcategory":"Construction",
            "type":"Services"
        }
    ],
    "sg:phone":"+1 301 333 9547",
    "sg:postcode":"20743",
    "sg:province":"MD",
    "sg:tags":[
        "contractor"
    ],
    "wof:name":"A & A General Contractors Llc",
    "wof:placetype":"venue"
},
  "geometry": {"coordinates":[-76.852813,38.881374],"type":"Point"}
}