{
  "type": "Feature",
  "properties": {
    "iso:country":"US",
    "sg:address":"6401 Annapolis Rd",
    "sg:city":"Hyattsville",
    "sg:classifiers":[
        {
            "category":"Building & Trades",
            "subcategory":"Locksmith",
            "type":"Services"
        }
    ],
    "sg:phone":"+1 800 975 2070",
    "sg:postcode":"20784",
    "sg:province":"MD",
    "sg:tags":[
        "key"
    ],
    "wof:name":"A 24 Hour Emergency Locksmith",
    "wof:placetype":"venue"
},
  "geometry": {"coordinates":[-76.908422,38.938734],"type":"Point"}
}