{
  "type": "Feature",
  "properties": {
    "iso:country":"US",
    "sg:address":"7505 New Hampshire Ave",
    "sg:city":"Takoma Park",
    "sg:classifiers":[
        {
            "category":"Professional",
            "subcategory":"Accounting & Tax Preparation",
            "type":"Services"
        }
    ],
    "sg:phone":"+1 301 431 4733",
    "sg:postcode":"20912",
    "sg:province":"MD",
    "sg:tags":[
        "return",
        "filing"
    ],
    "wof:name":"James M Newby & Assoc",
    "wof:placetype":"venue"
},
  "geometry": {"coordinates":[-76.98806399999999,38.985856],"type":"Point"}
}