{
  "type": "Feature",
  "properties": {
    "iso:country":"US",
    "sg:address":"4715 Cordell Ave",
    "sg:city":"Bethesda",
    "sg:classifiers":[
        {
            "category":"Home & Garden",
            "subcategory":"Furniture",
            "type":"Retail Goods"
        }
    ],
    "sg:phone":"+1 301 656 0400",
    "sg:postcode":"20814",
    "sg:province":"MD",
    "sg:tags":[
        "store"
    ],
    "wof:name":"Asian Home Furnishings",
    "wof:placetype":"venue"
},
  "geometry": {"coordinates":[-77.095901,38.991001],"type":"Point"}
}