{
  "type": "Feature",
  "properties": {
    "iso:country":"US",
    "sg:address":"3680 Warwick Rd",
    "sg:city":"East New Market",
    "sg:classifiers":[
        {
            "category":"Organizations",
            "subcategory":"Non-profit Organization",
            "type":"Services"
        }
    ],
    "sg:phone":"+1 410 943 8108",
    "sg:postcode":"21631",
    "sg:province":"MD",
    "sg:tags":[
        "info",
        "addiction",
        "abuse",
        "treatment",
        "drug"
    ],
    "wof:name":"Warwick Manor Behavioral Hlth",
    "wof:placetype":"venue"
},
  "geometry": {"coordinates":[-75.953346,38.614521],"type":"Point"}
}