{
  "type": "Feature",
  "properties": {
    "addr:full":"22 Bloomsbury Ave Catonsville MD 21228",
    "addr:housenumber":"22",
    "addr:postcode":"21228",
    "addr:street":"Bloomsbury Ave",
    "iso:country":"US",
    "sg:address":"22 Bloomsbury Ave",
    "sg:city":"Catonsville",
    "sg:classifiers":[
        {
            "category":"Real Estate",
            "subcategory":"Real Estate Agent",
            "type":"Services"
        }
    ],
    "sg:phone":"+1 410 788 4039",
    "sg:postcode":"21228",
    "sg:province":"MD",
    "wof:name":"NPBA LLC",
    "wof:placetype":"venue"
},
  "geometry": {"coordinates":[-76.731128,39.271018],"type":"Point"}
}