{
  "type": "Feature",
  "properties": {
    "addr:full":"110 Saint Paul St Baltimore MD 21202",
    "addr:housenumber":"110",
    "addr:postcode":"21202",
    "addr:street":"Saint Paul St",
    "iso:country":"US",
    "sg:address":"110 Saint Paul St",
    "sg:city":"Baltimore",
    "sg:classifiers":[
        {
            "category":"Professional",
            "subcategory":"Lawyer & Legal Services",
            "type":"Services"
        }
    ],
    "sg:phone":"+1 410 539 4447",
    "sg:postcode":"21202",
    "sg:province":"MD",
    "sg:tags":[
        "attorney"
    ],
    "wof:name":"Myles R Eisenstein",
    "wof:placetype":"venue"
},
  "geometry": {"coordinates":[-76.614045,39.291094],"type":"Point"}
}