{
  "type": "Feature",
  "properties": {
    "iso:country":"US",
    "sg:address":"6425 Walther Ave",
    "sg:city":"Baltimore",
    "sg:classifiers":[
        {
            "category":"Personal",
            "subcategory":"Beauty Salon",
            "type":"Services"
        }
    ],
    "sg:phone":"+1 410 426 9433",
    "sg:postcode":"21206",
    "sg:province":"MD",
    "wof:name":"Family Hair Ctr",
    "wof:placetype":"venue"
},
  "geometry": {"coordinates":[-76.541657,39.355933],"type":"Point"}
}