{
  "type": "Feature",
  "properties": {
    "iso:country":"US",
    "sg:address":"3611 Branch Ave Ste 301",
    "sg:city":"Temple Hills",
    "sg:classifiers":[
        {
            "category":"Health Services",
            "subcategory":"Doctor",
            "type":"Services"
        }
    ],
    "sg:phone":"+1 301 702 2700",
    "sg:postcode":"20748",
    "sg:province":"MD",
    "sg:tags":[
        "surgeon",
        "oral"
    ],
    "wof:name":"Adgerson Pearstine DDS",
    "wof:placetype":"venue"
},
  "geometry": {"coordinates":[-76.948402,38.841801],"type":"Point"}
}