{
  "type": "Feature",
  "properties": {
    "iso:country":"US",
    "sg:address":"325 Cypress St",
    "sg:city":"Millington",
    "sg:classifiers":[
        {
            "category":"Building & Trades",
            "subcategory":"Plumbing",
            "type":"Services"
        }
    ],
    "sg:phone":"+1 410 928 5900",
    "sg:postcode":"21651",
    "sg:province":"MD",
    "sg:tags":[
        "heating",
        "contractor"
    ],
    "wof:name":"Starkey Mechanical",
    "wof:placetype":"venue"
},
  "geometry": {"coordinates":[-75.851888,39.260952],"type":"Point"}
}