{
  "type": "Feature",
  "properties": {
    "addr:full":"1618 Farnborn St Crofton MD 21114",
    "addr:housenumber":"1618",
    "addr:postcode":"21114",
    "addr:street":"Farnborn St",
    "iso:country":"US",
    "sg:address":"1618 Farnborn St",
    "sg:city":"Crofton",
    "sg:classifiers":[
        {
            "category":"Health Services",
            "subcategory":"Doctor",
            "type":"Services"
        }
    ],
    "sg:phone":"+1 410 721 1573",
    "sg:postcode":"21114",
    "sg:province":"MD",
    "sg:tags":[
        "medical"
    ],
    "wof:name":"Sharon A Penland PA",
    "wof:placetype":"venue"
},
  "geometry": {"coordinates":[-76.67946999999999,39.008197],"type":"Point"}
}