{
  "type": "Feature",
  "properties": {
    "iso:country":"US",
    "sg:address":"15300 McMullen Hwy SW",
    "sg:city":"Cumberland",
    "sg:classifiers":[
        {
            "category":"Insurance",
            "subcategory":"Insurance Agent",
            "type":"Services"
        }
    ],
    "sg:phone":"+1 301 729 6750",
    "sg:postcode":"21502",
    "sg:province":"MD",
    "wof:name":"Monumental Life Insurance Co",
    "wof:placetype":"venue"
},
  "geometry": {"coordinates":[-78.84291,39.584542],"type":"Point"}
}