{
  "type": "Feature",
  "properties": {
    "iso:country":"US",
    "sg:address":"4129 Valley View Rd",
    "sg:city":"Middletown",
    "sg:classifiers":[
        {
            "category":"Insurance",
            "subcategory":"Insurance Agent",
            "type":"Services"
        }
    ],
    "sg:phone":"+1 301 371 8341",
    "sg:postcode":"21769",
    "sg:province":"MD",
    "wof:name":"Joint Venture Ranch",
    "wof:placetype":"venue"
},
  "geometry": {"coordinates":[-77.524599,39.460285],"type":"Point"}
}