{
  "type": "Feature",
  "properties": {
    "addr:full":"7811 Montrose Rd Potomac MD 20854",
    "addr:housenumber":"7811",
    "addr:postcode":"20854",
    "addr:street":"Montrose Rd",
    "iso:country":"US",
    "sg:address":"7811 Montrose Rd",
    "sg:city":"Potomac",
    "sg:classifiers":[
        {
            "category":"Professional",
            "subcategory":"Lawyer & Legal Services",
            "type":"Services"
        }
    ],
    "sg:phone":"+1 301 738 1150",
    "sg:postcode":"20854",
    "sg:province":"MD",
    "sg:tags":[
        "attorney"
    ],
    "wof:name":"Julia Schoenfeld Esq",
    "wof:placetype":"venue"
},
  "geometry": {"coordinates":[-77.157251,39.056857],"type":"Point"}
}