{
  "type": "Feature",
  "properties": {
    "iso:country":"US",
    "sg:address":"9207 Town Gate Ln",
    "sg:city":"Bethesda",
    "sg:classifiers":[
        {
            "category":"Professional",
            "subcategory":"Business Services",
            "type":"Services"
        }
    ],
    "sg:phone":"+1 301 365 7753",
    "sg:postcode":"20817",
    "sg:province":"MD",
    "wof:name":"Rok Enterprises Inc",
    "wof:placetype":"venue"
},
  "geometry": {"coordinates":[-77.18939899999999,38.987864],"type":"Point"}
}