{
  "type": "Feature",
  "properties": {
    "addr:full":"416 Baldwin Park Dr T4 Westminster MD 21157",
    "addr:housenumber":"416",
    "addr:postcode":"21157",
    "addr:street":"Baldwin Park Dr",
    "iso:country":"US",
    "sg:address":"416 Baldwin Park Dr T4",
    "sg:city":"Westminster",
    "sg:classifiers":[
        {
            "category":"Professional",
            "subcategory":"Management & Consulting",
            "type":"Services"
        }
    ],
    "sg:phone":"+1 410 848 2791",
    "sg:postcode":"21157",
    "sg:province":"MD",
    "sg:tags":[
        "consultant",
        "safety"
    ],
    "wof:name":"Symniotics, Inc",
    "wof:placetype":"venue"
},
  "geometry": {"coordinates":[-76.99453,39.56353],"type":"Point"}
}