{
  "type": "Feature",
  "properties": {
    "iso:country":"US",
    "sg:address":"10201 Martin Luther King Jr Hwy",
    "sg:city":"Bowie",
    "sg:classifiers":[
        {
            "category":"Museum",
            "type":"Entertainment"
        }
    ],
    "sg:phone":"+1 301 809 0440",
    "sg:postcode":"20720",
    "sg:province":"MD",
    "wof:name":"Prince Georges African American Museum and Cultural Center",
    "wof:placetype":"venue"
},
  "geometry": {"coordinates":[-76.82763,38.955823],"type":"Point"}
}