{
  "type": "Feature",
  "properties": {
    "iso:country":"US",
    "sg:address":"2 Village Sq",
    "sg:city":"Baltimore",
    "sg:classifiers":[
        {
            "category":"Real Estate",
            "subcategory":"Real Estate Services",
            "type":"Services"
        }
    ],
    "sg:phone":"+1 410 435 4665",
    "sg:postcode":"21210",
    "sg:province":"MD",
    "sg:tags":[
        "company",
        "title"
    ],
    "wof:name":"Fountainhead Title",
    "wof:placetype":"venue"
},
  "geometry": {"coordinates":[-76.645211,39.354685],"type":"Point"}
}