{
  "type": "Feature",
  "properties": {
    "addr:full":"5811 Chesapeake Villa Rd Rock Hall MD 21661",
    "addr:housenumber":"5811",
    "addr:postcode":"21661",
    "addr:street":"Chesapeake Villa Rd",
    "iso:country":"US",
    "sg:address":"5811 Chesapeake Villa Rd",
    "sg:city":"Rock Hall",
    "sg:classifiers":[
        {
            "category":"Home & Garden",
            "subcategory":"Hardware",
            "type":"Retail Goods"
        }
    ],
    "sg:phone":"+1 410 639 7014",
    "sg:postcode":"21661",
    "sg:province":"MD",
    "wof:name":"Village Hardware & Garden Ctr",
    "wof:placetype":"venue"
},
  "geometry": {"coordinates":[-76.228708,39.135904],"type":"Point"}
}