{
  "type": "Feature",
  "properties": {
    "iso:country":"US",
    "sg:address":"39 Yost Pl",
    "sg:city":"Capitol Heights",
    "sg:classifiers":[
        {
            "category":"Personal",
            "subcategory":"Beauty Salon",
            "type":"Services"
        }
    ],
    "sg:phone":"+1 301 499 7200",
    "sg:postcode":"20743",
    "sg:province":"MD",
    "wof:name":"Sassi Beauty & Barber Salon",
    "wof:placetype":"venue"
},
  "geometry": {"coordinates":[-76.903432,38.888374],"type":"Point"}
}