{
  "type": "Feature",
  "properties": {
    "iso:country":"US",
    "sg:address":"14021 Triadelphia Rd",
    "sg:city":"Glenelg",
    "sg:classifiers":[
        {
            "category":"Insurance",
            "subcategory":"Hazard Insurance",
            "type":"Services"
        }
    ],
    "sg:phone":"+1 410 489 5220",
    "sg:postcode":"21737",
    "sg:province":"MD",
    "wof:name":"Calvin Ray Kinna",
    "wof:placetype":"venue"
},
  "geometry": {"coordinates":[-76.999134,39.262685],"type":"Point"}
}