{
  "type": "Feature",
  "properties": {
    "iso:country":"US",
    "sg:address":"6701 Park Heights Ave",
    "sg:city":"Baltimore",
    "sg:classifiers":[
        {
            "category":"Professional",
            "subcategory":"Accounting & Tax Preparation",
            "type":"Services"
        }
    ],
    "sg:phone":"+1 410 764 9989",
    "sg:postcode":"21215",
    "sg:province":"MD",
    "sg:tags":[
        "accountant",
        "public",
        "accountants-certified"
    ],
    "wof:name":"G Belaga Cpa",
    "wof:placetype":"venue"
},
  "geometry": {"coordinates":[-76.69976,39.362339],"type":"Point"}
}