{
  "type": "Feature",
  "properties": {
    "addr:full":"120 N Somerset Ave Crisfield MD 21817",
    "addr:housenumber":"120",
    "addr:postcode":"21817",
    "addr:street":"N Somerset Ave",
    "iso:country":"US",
    "sg:address":"120 N Somerset Ave",
    "sg:city":"Crisfield",
    "sg:classifiers":[
        {
            "category":"Shopping",
            "subcategory":"Hobbies, Toys, & Games",
            "type":"Retail Goods"
        }
    ],
    "sg:phone":"+1 410 968 2231",
    "sg:postcode":"21817",
    "sg:province":"MD",
    "sg:tags":[
        "craft",
        "supply"
    ],
    "wof:name":"R & R Crafts & Supplies",
    "wof:placetype":"venue"
},
  "geometry": {"coordinates":[-75.84455699999999,37.982883],"type":"Point"}
}