{
  "type": "Feature",
  "properties": {
    "iso:country":"US",
    "sg:address":"5833 Park Heights Ave Apt 301",
    "sg:city":"Baltimore",
    "sg:classifiers":[
        {
            "category":"Professional",
            "subcategory":"Lawyer & Legal Services",
            "type":"Services"
        }
    ],
    "sg:phone":"+1 410 484 8844",
    "sg:postcode":"21215",
    "sg:province":"MD",
    "wof:name":"Carmel Alan S Atty",
    "wof:placetype":"venue"
},
  "geometry": {"coordinates":[-76.687078,39.35484],"type":"Point"}
}