{
  "type": "Feature",
  "properties": {
    "addr:full":"32 Mellor Ave Catonsville MD 21228",
    "addr:housenumber":"32",
    "addr:postcode":"21228",
    "addr:street":"Mellor Ave",
    "iso:country":"US",
    "sg:address":"32 Mellor Ave",
    "sg:city":"Catonsville",
    "sg:classifiers":[
        {
            "category":"Retail",
            "subcategory":"Veterinary Services",
            "type":"Services"
        }
    ],
    "sg:phone":"+1 410 788 5200",
    "sg:postcode":"21228",
    "sg:province":"MD",
    "sg:tags":[
        "veterinarian"
    ],
    "wof:name":"Veterinary Imaging",
    "wof:placetype":"venue"
},
  "geometry": {"coordinates":[-76.733495,39.270358],"type":"Point"}
}