{
  "type": "Feature",
  "properties": {
    "addr:full":"1900 Corbridge Ln Monkton MD 21111",
    "addr:housenumber":"1900",
    "addr:postcode":"21111",
    "addr:street":"Corbridge Ln",
    "iso:country":"US",
    "sg:address":"1900 Corbridge Ln",
    "sg:city":"Monkton",
    "sg:classifiers":[
        {
            "category":"Professional",
            "type":"Services"
        }
    ],
    "sg:phone":"+1 410 329 3300",
    "sg:postcode":"21111",
    "sg:province":"MD",
    "wof:name":"Absolutely Organized",
    "wof:placetype":"venue"
},
  "geometry": {"coordinates":[-76.611153,39.563729],"type":"Point"}
}