{
  "type": "Feature",
  "properties": {
    "iso:country":"US",
    "sg:address":"6480 New Hampshire Ave",
    "sg:city":"Takoma Park",
    "sg:classifiers":[
        {
            "category":"Professional",
            "type":"Services"
        }
    ],
    "sg:phone":"+1 301 891 1340",
    "sg:postcode":"20912",
    "sg:province":"MD",
    "sg:tags":[
        "establishment"
    ],
    "wof:name":"Jaf Help Ctr",
    "wof:placetype":"venue"
},
  "geometry": {"coordinates":[-77.001397,38.966808],"type":"Point"}
}