{
  "type": "Feature",
  "properties": {
    "iso:country":"US",
    "sg:address":"17 W Franklin St",
    "sg:city":"Hagerstown",
    "sg:classifiers":[
        {
            "category":"Personal",
            "subcategory":"Tattoo Parlor",
            "type":"Services"
        }
    ],
    "sg:phone":"+1 240 420 1843",
    "sg:postcode":"21740",
    "sg:province":"MD",
    "sg:tags":[
        "tattooing"
    ],
    "wof:name":"Eternal Tattooing & Body Prcng",
    "wof:placetype":"venue"
},
  "geometry": {"coordinates":[-77.719651,39.643339],"type":"Point"}
}