{
  "type": "Feature",
  "properties": {
    "iso:country":"US",
    "sg:address":"13021 Beaver Dam Rd",
    "sg:city":"Cockeysville",
    "sg:classifiers":[
        {
            "category":"Wholesale",
            "subcategory":"Farm Supplies",
            "type":"Manufacturing & Wholesale Goods"
        }
    ],
    "sg:phone":"+1 410 584 2606",
    "sg:postcode":"21030",
    "sg:province":"MD",
    "sg:tags":[
        "seed"
    ],
    "wof:name":"Traagri Inc",
    "wof:placetype":"venue"
},
  "geometry": {"coordinates":[-76.66603499999999,39.482097],"type":"Point"}
}