{
  "type": "Feature",
  "properties": {
    "iso:country":"US",
    "sg:address":"11110 Mall Cir",
    "sg:city":"Waldorf",
    "sg:classifiers":[
        {
            "category":"Coffee & Tea",
            "type":"Food & Drink"
        }
    ],
    "sg:menulink":"http://www.allmenus.com/md/waldorf/119107-starbucks-coffee/menu/",
    "sg:phone":"+1 301 638 4969",
    "sg:postcode":"20603",
    "sg:province":"MD",
    "sg:tags":[
        "american"
    ],
    "wof:name":"Starbucks Coffee",
    "wof:placetype":"venue"
},
  "geometry": {"coordinates":[-76.927198,38.61963],"type":"Point"}
}