{
  "type": "Feature",
  "properties": {
    "addr:full":"1372 Cape Saint Claire Rd Annapolis MD 21409",
    "addr:housenumber":"1372",
    "addr:postcode":"21409",
    "addr:street":"Cape Saint Claire Rd",
    "iso:country":"US",
    "sg:address":"1372 Cape Saint Claire Rd",
    "sg:city":"Annapolis",
    "sg:classifiers":[
        {
            "category":"Banks & Credit Unions",
            "subcategory":"Bank",
            "type":"Services"
        }
    ],
    "sg:phone":"+1 410 974 1515",
    "sg:postcode":"21409",
    "sg:province":"MD",
    "wof:name":"Bank Annapolis",
    "wof:placetype":"venue"
},
  "geometry": {"coordinates":[-76.439227,39.037396],"type":"Point"}
}