{
  "type": "Feature",
  "properties": {
    "addr:full":"4641 Montgomery Ave Bethesda MD 20814",
    "addr:housenumber":"4641",
    "addr:postcode":"20814",
    "addr:street":"Montgomery Ave",
    "iso:country":"US",
    "sg:address":"4641 Montgomery Ave",
    "sg:city":"Bethesda",
    "sg:classifiers":[
        {
            "category":"Professional",
            "subcategory":"Research",
            "type":"Services"
        }
    ],
    "sg:phone":"+1 301 907 8685",
    "sg:postcode":"20814",
    "sg:province":"MD",
    "sg:tags":[
        "opinion",
        "market"
    ],
    "wof:name":"Angus Reid Group",
    "wof:placetype":"venue"
},
  "geometry": {"coordinates":[-77.093312,38.983823],"type":"Point"}
}