{
  "type": "Feature",
  "properties": {
    "iso:country":"US",
    "sg:address":"5825 Buckeystown Pike",
    "sg:city":"Frederick",
    "sg:classifiers":[
        {
            "category":"Autos & Motor Vehicles",
            "subcategory":"Auto Supplies",
            "type":"Retail Goods"
        }
    ],
    "sg:phone":"+1 301 696 0669",
    "sg:postcode":"21704",
    "sg:province":"MD",
    "sg:tags":[
        "tire"
    ],
    "wof:name":"S & S Tire Svc Inc",
    "wof:placetype":"venue"
},
  "geometry": {"coordinates":[-77.408997,39.394811],"type":"Point"}
}