{
  "type": "Feature",
  "properties": {
    "addr:full":"869 Boxwood Trl Crownsville MD 21032",
    "addr:housenumber":"869",
    "addr:postcode":"21032",
    "addr:street":"Boxwood Trl",
    "iso:country":"US",
    "sg:address":"869 Boxwood Trl",
    "sg:city":"Crownsville",
    "sg:classifiers":[
        {
            "category":"Professional",
            "subcategory":"Accounting & Tax Preparation",
            "type":"Services"
        }
    ],
    "sg:phone":"+1 410 923 3507",
    "sg:postcode":"21032",
    "sg:province":"MD",
    "wof:name":"Your Every Service",
    "wof:placetype":"venue"
},
  "geometry": {"coordinates":[-76.573047,39.049624],"type":"Point"}
}