{
  "type": "Feature",
  "properties": {
    "addr:full":"9332 Links Rd Walkersville MD 21793",
    "addr:housenumber":"9332",
    "addr:postcode":"21793",
    "addr:street":"Links Rd",
    "iso:country":"US",
    "sg:address":"9332 Links Rd",
    "sg:city":"Walkersville",
    "sg:classifiers":[
        {
            "category":"Farming",
            "subcategory":"Farm",
            "type":"Manufacturing & Wholesale Goods"
        }
    ],
    "sg:phone":"+1 301 898 7131",
    "sg:postcode":"21793",
    "sg:province":"MD",
    "wof:name":"Glade Link Farms",
    "wof:placetype":"venue"
},
  "geometry": {"coordinates":[-77.348584,39.523168],"type":"Point"}
}