{
  "type": "Feature",
  "properties": {
    "iso:country":"US",
    "sg:address":"8502 Wilkesboro Ln",
    "sg:city":"Potomac",
    "sg:classifiers":[
        {
            "category":"Education",
            "subcategory":"Special Training",
            "type":"Public Place"
        }
    ],
    "sg:phone":"+1 301 983 9086",
    "sg:postcode":"20854",
    "sg:province":"MD",
    "sg:tags":[
        "teacher"
    ],
    "wof:name":"Heginbotham Earland",
    "wof:placetype":"venue"
},
  "geometry": {"coordinates":[-77.174595,39.051388],"type":"Point"}
}