{
  "type": "Feature",
  "properties": {
    "iso:country":"US",
    "sg:address":"6915 Golden Ring Rd",
    "sg:city":"Rosedale",
    "sg:classifiers":[
        {
            "category":"Manufacturing",
            "subcategory":"Printing",
            "type":"Manufacturing & Wholesale Goods"
        }
    ],
    "sg:phone":"+1 410 780 4308",
    "sg:postcode":"21237",
    "sg:province":"MD",
    "sg:tags":[
        "business",
        "form",
        "system"
    ],
    "wof:name":"Standard Register Co",
    "wof:placetype":"venue"
},
  "geometry": {"coordinates":[-76.490048,39.331881],"type":"Point"}
}