{
  "type": "Feature",
  "properties": {
    "addr:full":"11324 Country Club Rd New Market MD 21774",
    "addr:housenumber":"11324",
    "addr:postcode":"21774",
    "addr:street":"Country Club Rd",
    "iso:country":"US",
    "sg:address":"11324 Country Club Rd",
    "sg:city":"New Market",
    "sg:classifiers":[
        {
            "category":"Professional",
            "subcategory":"Art Services",
            "type":"Services"
        }
    ],
    "sg:phone":"+1 301 865 8663",
    "sg:postcode":"21774",
    "sg:province":"MD",
    "sg:tags":[
        "commercial",
        "design"
    ],
    "wof:name":"Holly Rathman",
    "wof:placetype":"venue"
},
  "geometry": {"coordinates":[-77.270776,39.422592],"type":"Point"}
}