{
  "type": "Feature",
  "properties": {
    "addr:full":"7404 Baltimore Ave College Park MD 20740",
    "addr:housenumber":"7404",
    "addr:postcode":"20740",
    "addr:street":"Baltimore Ave",
    "iso:country":"US",
    "sg:address":"7404 Baltimore Ave",
    "sg:city":"College Park",
    "sg:classifiers":[
        {
            "category":"Travel",
            "subcategory":"Travel Agent",
            "type":"Entertainment"
        }
    ],
    "sg:phone":"+1 301 864 1000",
    "sg:postcode":"20740",
    "sg:province":"MD",
    "sg:tags":[
        "agency",
        "bureau"
    ],
    "wof:name":"Beach Life Vacations",
    "wof:placetype":"venue"
},
  "geometry": {"coordinates":[-76.93806600000001,38.981343],"type":"Point"}
}