{
  "type": "Feature",
  "properties": {
    "addr:full":"408 Fox Den Ln Millersville MD 21108",
    "addr:housenumber":"408",
    "addr:postcode":"21108",
    "addr:street":"Fox Den Ln",
    "iso:country":"US",
    "sg:address":"408 Fox Den Ln",
    "sg:city":"Millersville",
    "sg:classifiers":[
        {
            "category":"Manufacturing",
            "subcategory":"Retail Goods",
            "type":"Manufacturing & Wholesale Goods"
        }
    ],
    "sg:phone":"+1 410 987 2864",
    "sg:postcode":"21108",
    "sg:province":"MD",
    "sg:tags":[
        "manufacturer"
    ],
    "wof:name":"Ram Manufacturing Svc",
    "wof:placetype":"venue"
},
  "geometry": {"coordinates":[-76.612528,39.105195],"type":"Point"}
}