{
  "type": "Feature",
  "properties": {
    "iso:country":"US",
    "sg:address":"116 S Commerce St",
    "sg:city":"Centreville",
    "sg:classifiers":[
        {
            "category":"Manufacturing",
            "subcategory":"Food",
            "type":"Manufacturing & Wholesale Goods"
        }
    ],
    "sg:phone":"+1 410 758 3991",
    "sg:postcode":"21617",
    "sg:province":"MD",
    "sg:tags":[
        "frozen",
        "specialty",
        "mfg"
    ],
    "wof:name":"Rose Tree Bed & Breakfast",
    "wof:placetype":"venue"
},
  "geometry": {"coordinates":[-76.065496,39.044138],"type":"Point"}
}