{
  "type": "Feature",
  "properties": {
    "addr:full":"305 1st St Laurel MD 20707",
    "addr:housenumber":"305",
    "addr:postcode":"20707",
    "addr:street":"1St St",
    "iso:country":"US",
    "sg:address":"305 1st St",
    "sg:city":"Laurel",
    "sg:classifiers":[
        {
            "category":"Building & Trades",
            "subcategory":"Construction",
            "type":"Services"
        }
    ],
    "sg:phone":"+1 301 725 0088",
    "sg:postcode":"20707",
    "sg:province":"MD",
    "sg:tags":[
        "marking",
        "maintenance",
        "parking"
    ],
    "wof:name":"Laurel Public Works",
    "wof:placetype":"venue"
},
  "geometry": {"coordinates":[-76.84382100000001,39.100853],"type":"Point"}
}