{
  "type": "Feature",
  "properties": {
    "addr:full":"316 Eastern Blvd Baltimore MD 21221",
    "addr:housenumber":"316",
    "addr:postcode":"21221",
    "addr:street":"Eastern Blvd",
    "iso:country":"US",
    "sg:address":"316 Eastern Blvd",
    "sg:city":"Baltimore",
    "sg:classifiers":[
        {
            "category":"Autos & Motor Vehicles",
            "subcategory":"Automobile Sales",
            "type":"Retail Goods"
        }
    ],
    "sg:phone":"+1 410 686 7700",
    "sg:postcode":"21221",
    "sg:province":"MD",
    "sg:tags":[
        "car",
        "dealer"
    ],
    "wof:name":"G & W Motors",
    "wof:placetype":"venue"
},
  "geometry": {"coordinates":[-76.480476,39.306515],"type":"Point"}
}