{
  "type": "Feature",
  "properties": {
    "iso:country":"US",
    "sg:address":"14 Bloomsbury Ave",
    "sg:city":"Catonsville",
    "sg:classifiers":[
        {
            "category":"Building & Trades",
            "subcategory":"Locksmith",
            "type":"Services"
        }
    ],
    "sg:phone":"+1 410 747 5625",
    "sg:postcode":"21228",
    "sg:province":"MD",
    "sg:tags":[
        "key"
    ],
    "wof:name":"Cencat Llc",
    "wof:placetype":"venue"
},
  "geometry": {"coordinates":[-76.731391,39.271363],"type":"Point"}
}