{
  "type": "Feature",
  "properties": {
    "addr:full":"16915 Darnestown Rd Boyds MD 20841",
    "addr:housenumber":"16915",
    "addr:postcode":"20841",
    "addr:street":"Darnestown Rd",
    "iso:country":"US",
    "sg:address":"16915 Darnestown Rd",
    "sg:city":"Boyds",
    "sg:classifiers":[
        {
            "category":"Recreation",
            "type":"Entertainment"
        }
    ],
    "sg:phone":"+1 301 948 4055",
    "sg:postcode":"20841",
    "sg:province":"MD",
    "wof:name":"Allen S Kline",
    "wof:placetype":"venue"
},
  "geometry": {"coordinates":[-77.354901,39.138117],"type":"Point"}
}