{
  "type": "Feature",
  "properties": {
    "addr:full":"1010 Hull St Baltimore MD 21230",
    "addr:housenumber":"1010",
    "addr:postcode":"21230",
    "addr:street":"Hull St",
    "iso:country":"US",
    "sg:address":"1010 Hull St",
    "sg:city":"Baltimore",
    "sg:phone":"+1 410 547 8884",
    "sg:postcode":"21230",
    "sg:province":"MD",
    "sg:website":"http://www.martinlauer.com",
    "wof:name":"Martin-Lauer Assoc",
    "wof:placetype":"venue"
},
  "geometry": {"coordinates":[-76.590132,39.275228],"type":"Point"}
}