{
  "type": "Feature",
  "properties": {
    "iso:country":"US",
    "sg:address":"3209 Leighton Ave",
    "sg:city":"Baltimore",
    "sg:classifiers":[
        {
            "category":"Building & Trades",
            "subcategory":"Construction",
            "type":"Services"
        }
    ],
    "sg:phone":"+1 410 523 6961",
    "sg:postcode":"21215",
    "sg:province":"MD",
    "sg:tags":[
        "contractor"
    ],
    "wof:name":"Joseph O & Barbara S Clemons",
    "wof:placetype":"venue"
},
  "geometry": {"coordinates":[-76.65886999999999,39.319267],"type":"Point"}
}