{
  "type": "Feature",
  "properties": {
    "iso:country":"US",
    "sg:address":"2341p Forest Dr",
    "sg:city":"Annapolis",
    "sg:classifiers":[
        {
            "category":"Restaurant",
            "type":"Food & Drink"
        }
    ],
    "sg:menulink":"http://www.allmenus.com/md/annapolis/83580-three-brothers-italian-restaurant/menu/",
    "sg:phone":"+1 410 573 0807",
    "sg:postcode":"21401",
    "sg:province":"MD",
    "sg:tags":[
        "american",
        "pizza"
    ],
    "wof:name":"Three Brothers Italian Restaurant",
    "wof:placetype":"venue"
},
  "geometry": {"coordinates":[-76.53812499999999,38.978395],"type":"Point"}
}