{
  "type": "Feature",
  "properties": {
    "iso:country":"US",
    "sg:address":"8630 Fenton St",
    "sg:city":"Silver Spring",
    "sg:classifiers":[
        {
            "category":"Professional",
            "subcategory":"Lawyer & Legal Services",
            "type":"Services"
        }
    ],
    "sg:phone":"+1 301 563 4022",
    "sg:postcode":"20910",
    "sg:province":"MD",
    "sg:tags":[
        "attorney"
    ],
    "wof:name":"Emmanuel D Akpan Law Offices",
    "wof:placetype":"venue"
},
  "geometry": {"coordinates":[-77.02838800000001,38.998098],"type":"Point"}
}