{
  "type": "Feature",
  "properties": {
    "iso:country":"US",
    "sg:address":"14212 Plum Run Way",
    "sg:city":"Silver Spring",
    "sg:classifiers":[
        {
            "category":"Professional",
            "subcategory":"Management & Consulting",
            "type":"Services"
        }
    ],
    "sg:phone":"+1 301 871 3852",
    "sg:postcode":"20906",
    "sg:province":"MD",
    "sg:tags":[
        "museum"
    ],
    "wof:name":"Mary Lou Gjernes",
    "wof:placetype":"venue"
},
  "geometry": {"coordinates":[-77.046434,39.089349],"type":"Point"}
}