{
  "type": "Feature",
  "properties": {
    "addr:full":"3569 Phillips Rd Salisbury MD 21804",
    "addr:housenumber":"3569",
    "addr:postcode":"21804",
    "addr:street":"Phillips Rd",
    "iso:country":"US",
    "sg:address":"3569 Phillips Rd",
    "sg:city":"Salisbury",
    "sg:classifiers":[
        {
            "category":"Manufacturing",
            "subcategory":"Lumber",
            "type":"Manufacturing & Wholesale Goods"
        }
    ],
    "sg:phone":"+1 410 677 0600",
    "sg:postcode":"21804",
    "sg:province":"MD",
    "sg:tags":[
        "company",
        "logging"
    ],
    "wof:name":"Ota Stevenson Inc",
    "wof:placetype":"venue"
},
  "geometry": {"coordinates":[-75.608817,38.290746],"type":"Point"}
}