{
  "type": "Feature",
  "properties": {
    "iso:country":"US",
    "sg:address":"1100 Kennebec St",
    "sg:city":"Oxon Hill",
    "sg:classifiers":[
        {
            "category":"Professional",
            "subcategory":"Management & Consulting",
            "type":"Services"
        }
    ],
    "sg:phone":"+1 240 353 5554",
    "sg:postcode":"20745",
    "sg:province":"MD",
    "sg:tags":[
        "business"
    ],
    "wof:name":"Seyfal Communications",
    "wof:placetype":"venue"
},
  "geometry": {"coordinates":[-76.991741,38.819705],"type":"Point"}
}