{
  "type": "Feature",
  "properties": {
    "iso:country":"US",
    "sg:address":"920 S Potomac St",
    "sg:city":"Hagerstown",
    "sg:classifiers":[
        {
            "category":"Retail",
            "subcategory":"Auto Repair",
            "type":"Services"
        }
    ],
    "sg:phone":"+1 301 739 7802",
    "sg:postcode":"21740",
    "sg:province":"MD",
    "sg:tags":[
        "body",
        "automobile",
        "painting"
    ],
    "wof:name":"Central Auto Body Inc",
    "wof:placetype":"venue"
},
  "geometry": {"coordinates":[-77.727558,39.624883],"type":"Point"}
}