{
  "type": "Feature",
  "properties": {
    "addr:full":"131 Fountain Green Ln Gaithersburg MD 20878",
    "addr:housenumber":"131",
    "addr:postcode":"20878",
    "addr:street":"Fountain Green Ln",
    "iso:country":"US",
    "sg:address":"131 Fountain Green Ln",
    "sg:city":"Gaithersburg",
    "sg:classifiers":[
        {
            "category":"Health Services",
            "subcategory":"Health Practitioner",
            "type":"Services"
        }
    ],
    "sg:phone":"+1 301 990 8202",
    "sg:postcode":"20878",
    "sg:province":"MD",
    "sg:tags":[
        "consulting"
    ],
    "wof:name":"Makarehchi Farzaneh",
    "wof:placetype":"venue"
},
  "geometry": {"coordinates":[-77.22663300000001,39.12691],"type":"Point"}
}