{
  "type": "Feature",
  "properties": {
    "addr:full":"115 Idlewild Ave Easton MD 21601",
    "addr:housenumber":"115",
    "addr:postcode":"21601",
    "addr:street":"Idlewild Ave",
    "iso:country":"US",
    "sg:address":"115 Idlewild Ave",
    "sg:city":"Easton",
    "sg:classifiers":[
        {
            "category":"Organizations",
            "subcategory":"Religious Organization",
            "type":"Services"
        }
    ],
    "sg:phone":"+1 410 822 4241",
    "sg:postcode":"21601",
    "sg:province":"MD",
    "sg:tags":[
        "church"
    ],
    "sg:website":"www.fbceaston.org",
    "wof:name":"First Baptist Church",
    "wof:placetype":"venue"
},
  "geometry": {"coordinates":[-76.073808,38.764965],"type":"Point"}
}