{
  "type": "Feature",
  "properties": {
    "addr:full":"10845 Philadelphia Rd White Marsh MD 21162",
    "addr:housenumber":"10845",
    "addr:postcode":"21162",
    "addr:street":"Philadelphia Rd",
    "iso:country":"US",
    "sg:address":"10845 Philadelphia Rd",
    "sg:city":"White Marsh",
    "sg:classifiers":[
        {
            "category":"Health Services",
            "subcategory":"Clinic",
            "type":"Services"
        }
    ],
    "sg:phone":"+1 410 335 0008",
    "sg:postcode":"21162",
    "sg:province":"MD",
    "sg:tags":[
        "organization",
        "medical",
        "surgical"
    ],
    "wof:name":"Physicians Medical Billing",
    "wof:placetype":"venue"
},
  "geometry": {"coordinates":[-76.429176,39.387468],"type":"Point"}
}