{
  "type": "Feature",
  "properties": {
    "addr:full":"15619 Norman Dr North Potomac MD 20878",
    "addr:housenumber":"15619",
    "addr:postcode":"20878",
    "addr:street":"Norman Dr",
    "iso:country":"US",
    "sg:address":"15619 Norman Dr",
    "sg:city":"North Potomac",
    "sg:classifiers":[
        {
            "category":"Building & Trades",
            "subcategory":"Plumbing",
            "type":"Services"
        }
    ],
    "sg:phone":"+1 301 963 9399",
    "sg:postcode":"20878",
    "sg:province":"MD",
    "sg:tags":[
        "tank",
        "septic"
    ],
    "wof:name":"Leigh & Sons",
    "wof:placetype":"venue"
},
  "geometry": {"coordinates":[-77.263363,39.113517],"type":"Point"}
}