{
  "type": "Feature",
  "properties": {
    "iso:country":"US",
    "sg:address":"5289 Hawkeye Rd",
    "sg:city":"Rhodesdale",
    "sg:classifiers":[
        {
            "category":"Wholesale",
            "subcategory":"Farm Supplies",
            "type":"Manufacturing & Wholesale Goods"
        },
        {
            "category":"Farming",
            "subcategory":"Farm",
            "type":"Manufacturing & Wholesale Goods"
        }
    ],
    "sg:phone":"+1 410 228 6655",
    "sg:postcode":"21659",
    "sg:province":"MD",
    "sg:tags":[
        "grain"
    ],
    "wof:name":"William Palechek",
    "wof:placetype":"venue"
},
  "geometry": {"coordinates":[-75.899896,38.542271],"type":"Point"}
}