{
  "type": "Feature",
  "properties": {
    "addr:full":"11315 Appledowre Way Germantown MD 20876",
    "addr:housenumber":"11315",
    "addr:postcode":"20876",
    "addr:street":"Appledowre Way",
    "iso:country":"US",
    "sg:address":"11315 Appledowre Way",
    "sg:city":"Germantown",
    "sg:classifiers":[
        {
            "category":"Shopping",
            "subcategory":"Gifts & Souvenirs",
            "type":"Retail Goods"
        }
    ],
    "sg:phone":"+1 301 540 6700",
    "sg:postcode":"20876",
    "sg:province":"MD",
    "sg:tags":[
        "shop"
    ],
    "wof:name":"Memories Design Decor & Gifts",
    "wof:placetype":"venue"
},
  "geometry": {"coordinates":[-77.23552599999999,39.1851],"type":"Point"}
}