{
  "type": "Feature",
  "properties": {
    "addr:full":"5813 Eastern Ave Hyattsville MD 20782",
    "addr:housenumber":"5813",
    "addr:postcode":"20782",
    "addr:street":"Eastern Ave",
    "iso:country":"US",
    "sg:address":"5813 Eastern Ave",
    "sg:city":"Hyattsville",
    "sg:classifiers":[
        {
            "category":"Health Services",
            "subcategory":"Dentist",
            "type":"Services"
        }
    ],
    "sg:phone":"+1 301 559 2000",
    "sg:postcode":"20782",
    "sg:province":"MD",
    "wof:name":"Signature Smiles",
    "wof:placetype":"venue"
},
  "geometry": {"coordinates":[-76.995903,38.960499],"type":"Point"}
}