{
  "type": "Feature",
  "properties": {
    "iso:country":"US",
    "sg:address":"421 Sherwood Rd",
    "sg:city":"Cockeysville",
    "sg:classifiers":[
        {
            "category":"Home & Garden",
            "subcategory":"Garden Supply",
            "type":"Retail Goods"
        }
    ],
    "sg:phone":"+1 410 628 7647",
    "sg:postcode":"21030",
    "sg:province":"MD",
    "sg:tags":[
        "nursery",
        "gardening"
    ],
    "wof:name":"Turfco Inc",
    "wof:placetype":"venue"
},
  "geometry": {"coordinates":[-76.62679300000001,39.481531],"type":"Point"}
}