{
  "type": "Feature",
  "properties": {
    "addr:full":"2500 Liberty Heights Ave Baltimore MD 21215",
    "addr:housenumber":"2500",
    "addr:postcode":"21215",
    "addr:street":"Liberty Heights Ave",
    "iso:country":"US",
    "sg:address":"2500 Liberty Heights Ave",
    "sg:city":"Baltimore",
    "sg:classifiers":[
        {
            "category":"Food & Beverages",
            "subcategory":"Groceries & Convenience Stores",
            "type":"Retail Goods"
        }
    ],
    "sg:phone":"+1 410 523 1193",
    "sg:postcode":"21215",
    "sg:province":"MD",
    "sg:website":"www.7-eleven.com",
    "wof:name":"7-Eleven Stores",
    "wof:placetype":"venue"
},
  "geometry": {"coordinates":[-76.652665,39.318686],"type":"Point"}
}