{
  "type": "Feature",
  "properties": {
    "iso:country":"US",
    "sg:address":"5802 Queens Chapel Rd",
    "sg:city":"Hyattsville",
    "sg:classifiers":[
        {
            "category":"Professional",
            "subcategory":"Detective & Security Services",
            "type":"Services"
        }
    ],
    "sg:phone":"+1 301 559 1059",
    "sg:postcode":"20782",
    "sg:province":"MD",
    "sg:tags":[
        "information",
        "bureau"
    ],
    "wof:name":"Umbrella Theraputic Svcs",
    "wof:placetype":"venue"
},
  "geometry": {"coordinates":[-76.958473,38.958475],"type":"Point"}
}