{
  "type": "Feature",
  "properties": {
    "iso:country":"US",
    "sg:address":"8101 Lasalle Rd",
    "sg:city":"Baltimore",
    "sg:classifiers":[
        {
            "category":"Education",
            "subcategory":"School",
            "type":"Public Place"
        }
    ],
    "sg:phone":"+1 410 887 3518",
    "sg:postcode":"21286",
    "sg:province":"MD",
    "wof:name":"Loch Raven Technical School",
    "wof:placetype":"venue"
},
  "geometry": {"coordinates":[-76.58053,39.389914],"type":"Point"}
}