{
  "type": "Feature",
  "properties": {
    "addr:full":"7003 Southwark Ter Hyattsville MD 20782",
    "addr:housenumber":"7003",
    "addr:postcode":"20782",
    "addr:street":"Southwark Ter",
    "iso:country":"US",
    "sg:address":"7003 Southwark Ter",
    "sg:city":"Hyattsville",
    "sg:classifiers":[
        {
            "category":"Professional",
            "type":"Services"
        }
    ],
    "sg:phone":"+1 301 779 4451",
    "sg:postcode":"20782",
    "sg:province":"MD",
    "sg:tags":[
        "establishment"
    ],
    "wof:name":"Drakes & Drakes",
    "wof:placetype":"venue"
},
  "geometry": {"coordinates":[-76.94640800000001,38.978849],"type":"Point"}
}