{
  "type": "Feature",
  "properties": {
    "addr:full":"8320 Bowie Rd Nanjemoy MD 20662",
    "addr:housenumber":"8320",
    "addr:postcode":"20662",
    "addr:street":"Bowie Rd",
    "iso:country":"US",
    "sg:address":"8320 Bowie Rd",
    "sg:city":"Nanjemoy",
    "sg:classifiers":[
        {
            "category":"Building & Trades",
            "subcategory":"Plumbing",
            "type":"Services"
        }
    ],
    "sg:phone":"+1 301 246 4262",
    "sg:postcode":"20662",
    "sg:province":"MD",
    "sg:tags":[
        "heating",
        "contractor"
    ],
    "wof:name":"D & R Heating & Air Cond",
    "wof:placetype":"venue"
},
  "geometry": {"coordinates":[-77.182483,38.4851],"type":"Point"}
}