{
  "type": "Feature",
  "properties": {
    "iso:country":"US",
    "sg:address":"2420 Blueridge Ave",
    "sg:city":"Wheaton",
    "sg:classifiers":[
        {
            "category":"Restaurant",
            "type":"Food & Drink"
        }
    ],
    "sg:phone":"+1 301 933 1066",
    "sg:postcode":"20902",
    "sg:province":"MD",
    "wof:name":"Los Chorro's Restaurant",
    "wof:placetype":"venue"
},
  "geometry": {"coordinates":[-77.051723,39.042989],"type":"Point"}
}