{
  "type": "Feature",
  "properties": {
    "addr:full":"3905 Sunflower Cir Bowie MD 20721",
    "addr:housenumber":"3905",
    "addr:postcode":"20721",
    "addr:street":"Sunflower Cir",
    "iso:country":"US",
    "sg:address":"3905 Sunflower Cir",
    "sg:city":"Bowie",
    "sg:classifiers":[
        {
            "category":"Shopping",
            "type":"Retail Goods"
        }
    ],
    "sg:phone":"+1 301 464 2282",
    "sg:postcode":"20721",
    "sg:province":"MD",
    "sg:tags":[
        "item",
        "boutique"
    ],
    "wof:name":"Lady Elegant Boutique",
    "wof:placetype":"venue"
},
  "geometry": {"coordinates":[-76.817879,38.940525],"type":"Point"}
}