{
  "type": "Feature",
  "properties": {
    "addr:full":"1185 Mount Aetna Rd Hagerstown MD 21740",
    "addr:housenumber":"1185",
    "addr:postcode":"21740",
    "addr:street":"Mount Aetna Rd",
    "iso:country":"US",
    "sg:address":"1185 Mount Aetna Rd",
    "sg:city":"Hagerstown",
    "sg:classifiers":[
        {
            "category":"Real Estate",
            "subcategory":"Real Estate Services",
            "type":"Services"
        }
    ],
    "sg:phone":"+1 301 797 0600",
    "sg:postcode":"21740",
    "sg:province":"MD",
    "sg:tags":[
        "company",
        "title"
    ],
    "wof:name":"Signature Settlements",
    "wof:placetype":"venue"
},
  "geometry": {"coordinates":[-77.694311,39.622976],"type":"Point"}
}