{
  "type": "Feature",
  "properties": {
    "iso:country":"US",
    "sg:address":"2018 Rock Spring Rd",
    "sg:city":"Forest Hill",
    "sg:classifiers":[
        {
            "category":"Social Services",
            "type":"Services"
        }
    ],
    "sg:phone":"+1 410 838 2493",
    "sg:postcode":"21050",
    "sg:province":"MD",
    "sg:tags":[
        "counselor",
        "marriage",
        "family"
    ],
    "wof:name":"Family & Couple Therapy Svc",
    "wof:placetype":"venue"
},
  "geometry": {"coordinates":[-76.384104,39.572553],"type":"Point"}
}