{
  "type": "Feature",
  "properties": {
    "addr:full":"5 Crain Hwy N Glen Burnie MD 21061",
    "addr:housenumber":"5",
    "addr:postcode":"21061",
    "addr:street":"Crain Hwy N",
    "iso:country":"US",
    "sg:address":"5 Crain Hwy N",
    "sg:city":"Glen Burnie",
    "sg:classifiers":[
        {
            "category":"Professional",
            "type":"Services"
        }
    ],
    "sg:phone":"+1 410 762 5790",
    "sg:postcode":"21061",
    "sg:province":"MD",
    "sg:tags":[
        "establishment"
    ],
    "wof:name":"Choice Program",
    "wof:placetype":"venue"
},
  "geometry": {"coordinates":[-76.62502000000001,39.164579],"type":"Point"}
}