{
  "type": "Feature",
  "properties": {
    "addr:full":"1750 N Rolling Rd Windsor Mill MD 21244",
    "addr:housenumber":"1750",
    "addr:postcode":"21244",
    "addr:street":"N Rolling Rd",
    "iso:country":"US",
    "sg:address":"1750 N Rolling Rd",
    "sg:city":"Windsor Mill",
    "sg:classifiers":[
        {
            "category":"Banks & Credit Unions",
            "subcategory":"Bank",
            "type":"Services"
        }
    ],
    "sg:phone":"+1 410 944 8282",
    "sg:postcode":"21244",
    "sg:province":"MD",
    "sg:website":"www.wachovia.com",
    "wof:name":"Wachovia",
    "wof:placetype":"venue"
},
  "geometry": {"coordinates":[-76.753818,39.309852],"type":"Point"}
}