{
  "type": "Feature",
  "properties": {
    "iso:country":"US",
    "sg:address":"200 N Tollgate Rd",
    "sg:city":"Bel Air",
    "sg:classifiers":[
        {
            "category":"Shopping",
            "subcategory":"Musical Instruments",
            "type":"Retail Goods"
        }
    ],
    "sg:phone":"+1 410 879 8201",
    "sg:postcode":"21014",
    "sg:province":"MD",
    "sg:tags":[
        "organs"
    ],
    "wof:name":"Yeager's Music Of Bel Air Inc",
    "wof:placetype":"venue"
},
  "geometry": {"coordinates":[-76.363479,39.524402],"type":"Point"}
}