{
  "type": "Feature",
  "properties": {
    "addr:full":"1 Research Ct Rockville MD 20850",
    "addr:housenumber":"1",
    "addr:postcode":"20850",
    "addr:street":"Research Ct",
    "iso:country":"US",
    "sg:address":"1 Research Ct",
    "sg:city":"Rockville",
    "sg:classifiers":[
        {
            "category":"Shopping",
            "subcategory":"Computers & Home Electronics",
            "type":"Retail Goods"
        }
    ],
    "sg:phone":"+1 301 208 7007",
    "sg:postcode":"20850",
    "sg:province":"MD",
    "sg:tags":[
        "software"
    ],
    "wof:name":"APL 2000 Inc",
    "wof:placetype":"venue"
},
  "geometry": {"coordinates":[-77.186965,39.10662],"type":"Point"}
}