{
  "type": "Feature",
  "properties": {
    "addr:full":"5615 Fishers Ln Rockville MD 20852",
    "addr:housenumber":"5615",
    "addr:postcode":"20852",
    "addr:street":"Fishers Ln",
    "iso:country":"US",
    "sg:address":"5615 Fishers Ln",
    "sg:city":"Rockville",
    "sg:classifiers":[
        {
            "category":"Manufacturing",
            "subcategory":"Metals",
            "type":"Manufacturing & Wholesale Goods"
        }
    ],
    "sg:phone":"+1 301 984 1800",
    "sg:postcode":"20852",
    "sg:province":"MD",
    "wof:name":"RCI Systems Inc",
    "wof:placetype":"venue"
},
  "geometry": {"coordinates":[-77.11387499999999,39.062874],"type":"Point"}
}