{
  "type": "Feature",
  "properties": {
    "addr:full":"7800 Coastal Hwy Ocean City MD 21842",
    "addr:housenumber":"7800",
    "addr:postcode":"21842",
    "addr:street":"Coastal Hwy",
    "iso:country":"US",
    "sg:address":"7800 Coastal Hwy",
    "sg:city":"Ocean City",
    "sg:classifiers":[
        {
            "category":"Professional",
            "subcategory":"Management & Consulting",
            "type":"Services"
        }
    ],
    "sg:phone":"+1 410 723 5911",
    "sg:postcode":"21842",
    "sg:province":"MD",
    "sg:tags":[
        "marketing",
        "consultant"
    ],
    "wof:name":"Creative Marketing Conslnts",
    "wof:placetype":"venue"
},
  "geometry": {"coordinates":[-75.062389,38.396995],"type":"Point"}
}