{
  "type": "Feature",
  "properties": {
    "iso:country":"US",
    "sg:address":"105 E Elm Ave",
    "sg:city":"Baltimore",
    "sg:classifiers":[
        {
            "category":"Building & Trades",
            "subcategory":"Construction",
            "type":"Services"
        }
    ],
    "sg:phone":"+1 410 947 1179",
    "sg:postcode":"21206",
    "sg:province":"MD",
    "sg:tags":[
        "hanging",
        "paper",
        "painting",
        "contractor"
    ],
    "wof:name":"Custom Coating Inc",
    "wof:placetype":"venue"
},
  "geometry": {"coordinates":[-76.522589,39.357274],"type":"Point"}
}