{
  "type": "Feature",
  "properties": {
    "iso:country":"US",
    "sg:address":"1118 Stevenson Ln",
    "sg:city":"Towson",
    "sg:classifiers":[
        {
            "category":"Professional",
            "subcategory":"Lawyer & Legal Services",
            "type":"Services"
        }
    ],
    "sg:phone":"+1 410 285 8883",
    "sg:postcode":"21286",
    "sg:province":"MD",
    "sg:tags":[
        "attorney"
    ],
    "wof:name":"J K Ehlers",
    "wof:placetype":"venue"
},
  "geometry": {"coordinates":[-76.590389,39.387305],"type":"Point"}
}