{
  "type": "Feature",
  "properties": {
    "iso:country":"US",
    "sg:address":"48236 Beachville Rd",
    "sg:city":"St Inigoes",
    "sg:classifiers":[
        {
            "category":"Arts & Performance",
            "subcategory":"Theater",
            "type":"Entertainment"
        }
    ],
    "sg:phone":"+1 301 872 9554",
    "sg:postcode":"20684",
    "sg:province":"MD",
    "sg:tags":[
        "live",
        "music"
    ],
    "wof:name":"SWEET-T-DJ Svc",
    "wof:placetype":"venue"
},
  "geometry": {"coordinates":[-76.40965300000001,38.147257],"type":"Point"}
}