{
  "type": "Feature",
  "properties": {
    "iso:country":"US",
    "sg:address":"804 Rockville Pike",
    "sg:city":"Rockville",
    "sg:classifiers":[
        {
            "category":"Retail",
            "subcategory":"Laundry & Dry Cleaning",
            "type":"Services"
        }
    ],
    "sg:phone":"+1 301 762 4200",
    "sg:postcode":"20852",
    "sg:province":"MD",
    "sg:tags":[
        "cleaners"
    ],
    "wof:name":"Cleaners Max",
    "wof:placetype":"venue"
},
  "geometry": {"coordinates":[-77.139632,39.077308],"type":"Point"}
}