{
  "type": "Feature",
  "properties": {
    "iso:country":"US",
    "sg:address":"8200 Perry Hall Blvd 2130",
    "sg:city":"Nottingham",
    "sg:classifiers":[
        {
            "category":"Shopping",
            "subcategory":"Clothing, Apparel, & Fashions",
            "type":"Retail Goods"
        }
    ],
    "sg:phone":"+1 410 933 4811",
    "sg:postcode":"21236",
    "sg:province":"MD",
    "sg:tags":[
        "shop",
        "cap",
        "hat",
        "sportswear"
    ],
    "sg:website":"http://www.lids.com",
    "wof:name":"Lids",
    "wof:placetype":"venue"
},
  "geometry": {"coordinates":[-76.472458,39.375381],"type":"Point"}
}