{
  "type": "Feature",
  "properties": {
    "addr:full":"1019 University Blvd E Silver Spring MD 20903",
    "addr:housenumber":"1019",
    "addr:postcode":"20903",
    "addr:street":"University Blvd E",
    "iso:country":"US",
    "sg:address":"1019 University Blvd E",
    "sg:city":"Silver Spring",
    "sg:classifiers":[
        {
            "category":"Insurance",
            "subcategory":"Insurance Agent",
            "type":"Services"
        }
    ],
    "sg:phone":"+1 301 445 0760",
    "sg:postcode":"20903",
    "sg:province":"MD",
    "wof:name":"Herb Krusen Ins Group Inc",
    "wof:placetype":"venue"
},
  "geometry": {"coordinates":[-76.990799,38.992194],"type":"Point"}
}