{
  "type": "Feature",
  "properties": {
    "addr:full":"11476 Applegrath Way Germantown MD 20876",
    "addr:housenumber":"11476",
    "addr:postcode":"20876",
    "addr:street":"Applegrath Way",
    "iso:country":"US",
    "sg:address":"11476 Applegrath Way",
    "sg:city":"Germantown",
    "sg:classifiers":[
        {
            "category":"Shopping",
            "subcategory":"Computers & Home Electronics",
            "type":"Retail Goods"
        }
    ],
    "sg:phone":"+1 301 428 1445",
    "sg:postcode":"20876",
    "sg:province":"MD",
    "sg:tags":[
        "software"
    ],
    "wof:name":"Synectix Technologies",
    "wof:placetype":"venue"
},
  "geometry": {"coordinates":[-77.23894799999999,39.18921],"type":"Point"}
}