{
  "type": "Feature",
  "properties": {
    "iso:country":"US",
    "sg:address":"6803 Breezewood Ter",
    "sg:city":"Rockville",
    "sg:classifiers":[
        {
            "category":"Personal",
            "subcategory":"Beauty Salon",
            "type":"Services"
        }
    ],
    "sg:phone":"+1 301 984 9007",
    "sg:postcode":"20852",
    "sg:province":"MD",
    "wof:name":"Elegant Hair By Giselle",
    "wof:placetype":"venue"
},
  "geometry": {"coordinates":[-77.141566,39.0468],"type":"Point"}
}