{
  "type": "Feature",
  "properties": {
    "iso:country":"US",
    "sg:address":"15621 Kelbaugh Rd",
    "sg:city":"Thurmont",
    "sg:classifiers":[
        {
            "category":"Professional",
            "subcategory":"Business Services",
            "type":"Services"
        }
    ],
    "sg:phone":"+1 301 271 4468",
    "sg:postcode":"21788",
    "sg:province":"MD",
    "wof:name":"Majestic Express LLC",
    "wof:placetype":"venue"
},
  "geometry": {"coordinates":[-77.386867,39.664472],"type":"Point"}
}