{
  "type": "Feature",
  "properties": {
    "addr:full":"5509 Urbana Pike Frederick MD 21704",
    "addr:housenumber":"5509",
    "addr:postcode":"21704",
    "addr:street":"Urbana Pike",
    "iso:country":"US",
    "sg:address":"5509 Urbana Pike",
    "sg:city":"Frederick",
    "sg:classifiers":[
        {
            "category":"Utilities",
            "subcategory":"Mobile Phone",
            "type":"Services"
        },
        {
            "category":"Shopping",
            "subcategory":"Mobile Phones",
            "type":"Retail Goods"
        },
        {
            "category":"Communications",
            "type":"Services"
        },
        {
            "category":"Internet Cafe",
            "subcategory":"None",
            "type":"Food & Drink"
        }
    ],
    "sg:phone":"+1 301 682 5766",
    "sg:postcode":"21704",
    "sg:province":"MD",
    "sg:tags":[
        "supply",
        "telephone",
        "wireless",
        "equipment",
        "paging",
        "signaling",
        "cellular",
        "provider"
    ],
    "sg:website":"http://www.att.com",
    "wof:name":"AT&T",
    "wof:placetype":"venue"
},
  "geometry": {"coordinates":[-77.4008,39.382552],"type":"Point"}
}