{
  "type": "Feature",
  "properties": {
    "iso:country":"US",
    "sg:address":"3113 Murkle Rd",
    "sg:city":"Westminster",
    "sg:classifiers":[
        {
            "category":"Professional",
            "subcategory":"Business Services",
            "type":"Services"
        }
    ],
    "sg:phone":"+1 410 848 9078",
    "sg:postcode":"21158",
    "sg:province":"MD",
    "sg:tags":[
        "drafting"
    ],
    "wof:name":"Cook Design Group LLC",
    "wof:placetype":"venue"
},
  "geometry": {"coordinates":[-77.024597,39.654108],"type":"Point"}
}