{
  "type": "Feature",
  "properties": {
    "addr:full":"12736 Greensboro Rd Greensboro MD 21639",
    "addr:housenumber":"12736",
    "addr:postcode":"21639",
    "addr:street":"Greensboro Rd",
    "iso:country":"US",
    "sg:address":"12736 Greensboro Rd",
    "sg:city":"Greensboro",
    "sg:classifiers":[
        {
            "category":"Building & Trades",
            "subcategory":"Plumbing",
            "type":"Services"
        }
    ],
    "sg:phone":"+1 410 482 9308",
    "sg:postcode":"21639",
    "sg:province":"MD",
    "sg:tags":[
        "sheet",
        "work",
        "metal",
        "contractor"
    ],
    "wof:name":"Stromberg Sheet Metals Works",
    "wof:placetype":"venue"
},
  "geometry": {"coordinates":[-75.799097,38.95805],"type":"Point"}
}