{
  "type": "Feature",
  "properties": {
    "addr:full":"1 Saffron Ct Reisterstown MD 21136",
    "addr:housenumber":"1",
    "addr:postcode":"21136",
    "addr:street":"Saffron Ct",
    "iso:country":"US",
    "sg:address":"1 Saffron Ct",
    "sg:city":"Reisterstown",
    "sg:classifiers":[
        {
            "category":"Professional",
            "subcategory":"Business Services",
            "type":"Services"
        }
    ],
    "sg:phone":"+1 410 833 6265",
    "sg:postcode":"21136",
    "sg:province":"MD",
    "sg:tags":[
        "interior",
        "design"
    ],
    "wof:name":"ABC Home Interiors",
    "wof:placetype":"venue"
},
  "geometry": {"coordinates":[-76.823897,39.449132],"type":"Point"}
}