{
  "type": "Feature",
  "properties": {
    "iso:country":"US",
    "sg:address":"4209 Rail St",
    "sg:city":"Capitol Heights",
    "sg:classifiers":[
        {
            "category":"Retail",
            "subcategory":"Repair Shop",
            "type":"Services"
        }
    ],
    "sg:phone":"+1 301 735 5234",
    "sg:postcode":"20743",
    "sg:province":"MD",
    "wof:name":"W C Repairs",
    "wof:placetype":"venue"
},
  "geometry": {"coordinates":[-76.934793,38.871975],"type":"Point"}
}