{
  "type": "Feature",
  "properties": {
    "iso:country":"US",
    "sg:address":"3700 Commerce Dr",
    "sg:city":"Baltimore",
    "sg:classifiers":[
        {
            "category":"Professional",
            "subcategory":"Management & Consulting",
            "type":"Services"
        }
    ],
    "sg:phone":"+1 410 536 0656",
    "sg:postcode":"21227",
    "sg:province":"MD",
    "sg:tags":[
        "consultant",
        "business"
    ],
    "sg:website":"www.zust.com",
    "wof:name":"Zust Bachmeier Of Switzerland",
    "wof:placetype":"venue"
},
  "geometry": {"coordinates":[-76.674041,39.251066],"type":"Point"}
}