{
  "type": "Feature",
  "properties": {
    "addr:full":"740 Generals Hwy Millersville MD 21108",
    "addr:housenumber":"740",
    "addr:postcode":"21108",
    "addr:street":"Generals Hwy",
    "iso:country":"US",
    "sg:address":"740 Generals Hwy",
    "sg:city":"Millersville",
    "sg:classifiers":[
        {
            "category":"Manufacturing",
            "subcategory":"Metals",
            "type":"Manufacturing & Wholesale Goods"
        }
    ],
    "sg:phone":"+1 410 987 9397",
    "sg:postcode":"21108",
    "sg:province":"MD",
    "sg:tags":[
        "fabricator",
        "aluminum"
    ],
    "wof:name":"Carter Fabrications Inc",
    "wof:placetype":"venue"
},
  "geometry": {"coordinates":[-76.63046300000001,39.067266],"type":"Point"}
}