{
  "type": "Feature",
  "properties": {
    "iso:country":"US",
    "sg:address":"1442 Farmcrest Way",
    "sg:city":"Silver Spring",
    "sg:classifiers":[
        {
            "category":"Real Estate",
            "subcategory":"Real Estate Agent",
            "type":"Services"
        }
    ],
    "sg:phone":"+1 301 384 3644",
    "sg:postcode":"20905",
    "sg:province":"MD",
    "wof:name":"Denise Rosado",
    "wof:placetype":"venue"
},
  "geometry": {"coordinates":[-76.983518,39.093782],"type":"Point"}
}