{
  "type": "Feature",
  "properties": {
    "addr:full":"302 Ridgemede Rd Baltimore MD 21210",
    "addr:housenumber":"302",
    "addr:postcode":"21210",
    "addr:street":"Ridgemede Rd",
    "iso:country":"US",
    "sg:address":"302 Ridgemede Rd",
    "sg:city":"Baltimore",
    "sg:classifiers":[
        {
            "category":"Real Estate",
            "subcategory":"Real Estate Services",
            "type":"Services"
        }
    ],
    "sg:phone":"+1 410 235 8900",
    "sg:postcode":"21210",
    "sg:province":"MD",
    "wof:name":"German R Dennis Real Estate",
    "wof:placetype":"venue"
},
  "geometry": {"coordinates":[-76.624702,39.339298],"type":"Point"}
}