{
  "type": "Feature",
  "properties": {
    "addr:full":"11 Bohemia Ave Chesapeake City MD 21915",
    "addr:housenumber":"11",
    "addr:postcode":"21915",
    "addr:street":"Bohemia Ave",
    "iso:country":"US",
    "sg:address":"11 Bohemia Ave",
    "sg:city":"Chesapeake City",
    "sg:classifiers":[
        {
            "category":"Restaurant",
            "type":"Food & Drink"
        }
    ],
    "sg:phone":"+1 410 885 5040",
    "sg:postcode":"21915",
    "sg:province":"MD",
    "sg:website":"www.bayardhouse.com",
    "wof:name":"Bayard House Restaurant",
    "wof:placetype":"venue"
},
  "geometry": {"coordinates":[-75.81193500000001,39.527522],"type":"Point"}
}