{
  "type": "Feature",
  "properties": {
    "addr:full":"17 W Frederick St Walkersville MD 21793",
    "addr:housenumber":"17",
    "addr:postcode":"21793",
    "addr:street":"W Frederick St",
    "iso:country":"US",
    "sg:address":"17 W Frederick St",
    "sg:city":"Walkersville",
    "sg:classifiers":[
        {
            "category":"Retail",
            "subcategory":"Laundry & Dry Cleaning",
            "type":"Services"
        }
    ],
    "sg:phone":"+1 301 845 8351",
    "sg:postcode":"21793",
    "sg:province":"MD",
    "sg:tags":[
        "cleaners"
    ],
    "wof:name":"Prosperity Cleaners",
    "wof:placetype":"venue"
},
  "geometry": {"coordinates":[-77.35015799999999,39.481918],"type":"Point"}
}