{
  "type": "Feature",
  "properties": {
    "iso:country":"US",
    "sg:address":"1730 Whitehead Rd",
    "sg:city":"Gwynn Oak",
    "sg:classifiers":[
        {
            "category":"Building & Trades",
            "subcategory":"Plumbing",
            "type":"Services"
        }
    ],
    "sg:phone":"+1 410 265 1100",
    "sg:postcode":"21207",
    "sg:province":"MD",
    "sg:tags":[
        "sheet",
        "work",
        "metal",
        "contractor"
    ],
    "wof:name":"Tech-Industrial Inc",
    "wof:placetype":"venue"
},
  "geometry": {"coordinates":[-76.740786,39.313739],"type":"Point"}
}