{
  "type": "Feature",
  "properties": {
    "addr:full":"105 Newlands St Chevy Chase MD 20815",
    "addr:housenumber":"105",
    "addr:postcode":"20815",
    "addr:street":"Newlands St",
    "iso:country":"US",
    "sg:address":"105 Newlands St",
    "sg:city":"Chevy Chase",
    "sg:classifiers":[
        {
            "category":"Health Services",
            "subcategory":"Doctor",
            "type":"Services"
        }
    ],
    "sg:phone":"+1 301 657 8665",
    "sg:postcode":"20815",
    "sg:province":"MD",
    "wof:name":"Boinis Geo A MD",
    "wof:placetype":"venue"
},
  "geometry": {"coordinates":[-77.073196,38.973099],"type":"Point"}
}