{
  "type": "Feature",
  "properties": {
    "addr:full":"815 Silver Spring Ave Silver Spring MD 20910",
    "addr:housenumber":"815",
    "addr:postcode":"20910",
    "addr:street":"Silver Spring Ave",
    "iso:country":"US",
    "sg:address":"815 Silver Spring Ave",
    "sg:city":"Silver Spring",
    "sg:classifiers":[
        {
            "category":"Social Services",
            "type":"Services"
        }
    ],
    "sg:phone":"+1 301 565 9333",
    "sg:postcode":"20910",
    "sg:province":"MD",
    "sg:tags":[
        "organization",
        "welfare"
    ],
    "wof:name":"Florence Crittenton Svc",
    "wof:placetype":"venue"
},
  "geometry": {"coordinates":[-77.02381,38.991779],"type":"Point"}
}