{
  "type": "Feature",
  "properties": {
    "addr:full":"618 Stamford Rd Baltimore MD 21229",
    "addr:housenumber":"618",
    "addr:postcode":"21229",
    "addr:street":"Stamford Rd",
    "iso:country":"US",
    "sg:address":"618 Stamford Rd",
    "sg:city":"Baltimore",
    "sg:classifiers":[
        {
            "category":"Building & Trades",
            "subcategory":"Construction",
            "type":"Services"
        }
    ],
    "sg:phone":"+1 410 566 8262",
    "sg:postcode":"21229",
    "sg:province":"MD",
    "sg:tags":[
        "tile",
        "dealer"
    ],
    "wof:name":"Atlas Tile & Terrazzo Inc",
    "wof:placetype":"venue"
},
  "geometry": {"coordinates":[-76.707314,39.291073],"type":"Point"}
}