{
  "type": "Feature",
  "properties": {
    "iso:country":"US",
    "sg:address":"815 Bowie Rd",
    "sg:city":"Rockville",
    "sg:classifiers":[
        {
            "category":"Professional",
            "subcategory":"Management & Consulting",
            "type":"Services"
        }
    ],
    "sg:phone":"+1 301 762 3724",
    "sg:postcode":"20852",
    "sg:province":"MD",
    "sg:tags":[
        "communications",
        "consultant"
    ],
    "wof:name":"Barbara S Lynch",
    "wof:placetype":"venue"
},
  "geometry": {"coordinates":[-77.146624,39.073759],"type":"Point"}
}