{
  "type": "Feature",
  "properties": {
    "iso:country":"US",
    "sg:address":"10807 Railroad Ave",
    "sg:city":"White Marsh",
    "sg:classifiers":[
        {
            "category":"Shopping",
            "subcategory":"Antiques",
            "type":"Retail Goods"
        }
    ],
    "sg:phone":"+1 410 335 3313",
    "sg:postcode":"21162",
    "sg:province":"MD",
    "wof:name":"Linnemann's Store",
    "wof:placetype":"venue"
},
  "geometry": {"coordinates":[-76.42814,39.382246],"type":"Point"}
}