{
  "type": "Feature",
  "properties": {
    "addr:full":"3800 Newgate Ave Baltimore MD 21224",
    "addr:housenumber":"3800",
    "addr:postcode":"21224",
    "addr:street":"Newgate Ave",
    "iso:country":"US",
    "sg:address":"3800 Newgate Ave",
    "sg:city":"Baltimore",
    "sg:classifiers":[
        {
            "category":"Manufacturing",
            "subcategory":"Metals",
            "type":"Manufacturing & Wholesale Goods"
        }
    ],
    "sg:phone":"+1 410 633 1601",
    "sg:postcode":"21224",
    "sg:province":"MD",
    "sg:tags":[
        "stevedoring",
        "contractor"
    ],
    "sg:website":"http://www.cantonmaritime.com",
    "wof:name":"Canton Stevedoring Company",
    "wof:placetype":"venue"
},
  "geometry": {"coordinates":[-76.563502,39.260591],"type":"Point"}
}