{
  "type": "Feature",
  "properties": {
    "addr:full":"9047 Early April Way Columbia MD 21046",
    "addr:housenumber":"9047",
    "addr:postcode":"21046",
    "addr:street":"Early April Way",
    "iso:country":"US",
    "sg:address":"9047 Early April Way",
    "sg:city":"Columbia",
    "sg:classifiers":[
        {
            "category":"Professional",
            "subcategory":"Management & Consulting",
            "type":"Services"
        }
    ],
    "sg:phone":"+1 410 309 0088",
    "sg:postcode":"21046",
    "sg:province":"MD",
    "sg:tags":[
        "personnel",
        "consultant"
    ],
    "wof:name":"Tec Edge Corp",
    "wof:placetype":"venue"
},
  "geometry": {"coordinates":[-76.855228,39.165133],"type":"Point"}
}