{
  "type": "Feature",
  "properties": {
    "iso:country":"US",
    "sg:address":"1101 Mercy Ln Ste 220",
    "sg:city":"Hyattsville",
    "sg:classifiers":[
        {
            "category":"Social Services",
            "subcategory":"Job Training",
            "type":"Services"
        },
        {
            "category":"Social Services",
            "subcategory":"Adult Care",
            "type":"Services"
        }
    ],
    "sg:phone":"+1 301 925 1515",
    "sg:postcode":"20785",
    "sg:province":"MD",
    "sg:tags":[
        "day",
        "centers-adult",
        "nursing",
        "homes-skilled",
        "facility"
    ],
    "wof:name":"We Care Adult Services Inc",
    "wof:placetype":"venue"
},
  "geometry": {"coordinates":[-76.91989100000001,38.93045],"type":"Point"}
}