{
  "type": "Feature",
  "properties": {
    "iso:country":"US",
    "sg:address":"3821 Ferndale Ave",
    "sg:city":"Gwynn Oak",
    "sg:classifiers":[
        {
            "category":"Organizations",
            "subcategory":"Religious Organization",
            "type":"Services"
        }
    ],
    "sg:phone":"+1 410 466 6711",
    "sg:postcode":"21207",
    "sg:province":"MD",
    "wof:name":"Haskins James Otis Rev",
    "wof:placetype":"venue"
},
  "geometry": {"coordinates":[-76.698402,39.337002],"type":"Point"}
}