{
  "type": "Feature",
  "properties": {
    "addr:full":"7909 Dorsey Run Rd Jessup MD 20794",
    "addr:housenumber":"7909",
    "addr:postcode":"20794",
    "addr:street":"Dorsey Run Rd",
    "iso:country":"US",
    "sg:address":"7909 Dorsey Run Rd",
    "sg:city":"Jessup",
    "sg:classifiers":[
        {
            "category":"Retail",
            "subcategory":"Auto Repair",
            "type":"Services"
        }
    ],
    "sg:phone":"+1 410 799 8114",
    "sg:postcode":"20794",
    "sg:province":"MD",
    "sg:tags":[
        "repairing",
        "automobile"
    ],
    "wof:name":"Jessup Total Car Care",
    "wof:placetype":"venue"
},
  "geometry": {"coordinates":[-76.781059,39.152612],"type":"Point"}
}