{
  "type": "Feature",
  "properties": {
    "iso:country":"US",
    "sg:address":"11010 Rockville Pike",
    "sg:city":"Rockville",
    "sg:classifiers":[
        {
            "category":"Bars & Pubs",
            "type":"Food & Drink"
        }
    ],
    "sg:phone":"+1 301 881 8711",
    "sg:postcode":"20852",
    "sg:province":"MD",
    "wof:name":"Dietle's Tavern",
    "wof:placetype":"venue"
},
  "geometry": {"coordinates":[-77.107697,39.036598],"type":"Point"}
}