{
  "type": "Feature",
  "properties": {
    "addr:full":"6 Arch St Cumberland MD 21502",
    "addr:housenumber":"6",
    "addr:postcode":"21502",
    "addr:street":"Arch St",
    "iso:country":"US",
    "sg:address":"6 Arch St",
    "sg:city":"Cumberland",
    "sg:classifiers":[
        {
            "category":"Organizations",
            "subcategory":"Religious Organization",
            "type":"Services"
        }
    ],
    "sg:phone":"+1 301 724 1245",
    "sg:postcode":"21502",
    "sg:province":"MD",
    "sg:tags":[
        "clergy"
    ],
    "wof:name":"Sherrill Dillon",
    "wof:placetype":"venue"
},
  "geometry": {"coordinates":[-78.76083800000001,39.638755],"type":"Point"}
}