{
  "type": "Feature",
  "properties": {
    "addr:full":"9505 Buckhorn Rd Parkville MD 21234",
    "addr:housenumber":"9505",
    "addr:postcode":"21234",
    "addr:street":"Buckhorn Rd",
    "iso:country":"US",
    "sg:address":"9505 Buckhorn Rd",
    "sg:city":"Parkville",
    "sg:classifiers":[
        {
            "category":"Shopping",
            "subcategory":"Clothing, Apparel, & Fashions",
            "type":"Retail Goods"
        }
    ],
    "sg:phone":"+1 410 661 2716",
    "sg:postcode":"21234",
    "sg:province":"MD",
    "sg:tags":[
        "apparel",
        "women's"
    ],
    "wof:name":"Balto Embroidery Sportsware",
    "wof:placetype":"venue"
},
  "geometry": {"coordinates":[-76.52518499999999,39.419419],"type":"Point"}
}