{
  "type": "Feature",
  "properties": {
    "addr:full":"8503 Oxon Hill Rd Fort Washington MD 20744",
    "addr:housenumber":"8503",
    "addr:postcode":"20744",
    "addr:street":"Oxon Hill Rd",
    "iso:country":"US",
    "sg:address":"8503 Oxon Hill Rd",
    "sg:city":"Fort Washington",
    "sg:classifiers":[
        {
            "category":"Personal",
            "subcategory":"Beauty Salon",
            "type":"Services"
        }
    ],
    "sg:phone":"+1 301 686 1010",
    "sg:postcode":"20744",
    "sg:province":"MD",
    "sg:tags":[
        "manicuring"
    ],
    "wof:name":"Tracy Nails",
    "wof:placetype":"venue"
},
  "geometry": {"coordinates":[-77.006135,38.772966],"type":"Point"}
}