{
  "type": "Feature",
  "properties": {
    "iso:country":"US",
    "sg:address":"7709 Hamilton Spring Rd",
    "sg:city":"Bethesda",
    "sg:classifiers":[
        {
            "category":"Professional",
            "subcategory":"Engineering",
            "type":"Services"
        }
    ],
    "sg:phone":"+1 301 365 0209",
    "sg:postcode":"20817",
    "sg:province":"MD",
    "wof:name":"Anro Engineering Inc",
    "wof:placetype":"venue"
},
  "geometry": {"coordinates":[-77.16669,38.984353],"type":"Point"}
}