{
  "type": "Feature",
  "properties": {
    "iso:country":"US",
    "sg:address":"1101 Gold Mine Rd",
    "sg:city":"Brookeville",
    "sg:classifiers":[
        {
            "category":"Food & Beverages",
            "subcategory":"Specialty",
            "type":"Retail Goods"
        }
    ],
    "sg:phone":"+1 301 774 8181",
    "sg:postcode":"20833",
    "sg:province":"MD",
    "sg:tags":[
        "product",
        "health",
        "diet"
    ],
    "wof:name":"Matol Botanical International",
    "wof:placetype":"venue"
},
  "geometry": {"coordinates":[-77.027771,39.178921],"type":"Point"}
}