{
  "type": "Feature",
  "properties": {
    "addr:full":"400 Washington Ave Rm M3 Towson MD 21204",
    "addr:housenumber":"400",
    "addr:postcode":"21204",
    "addr:street":"Washington Ave",
    "iso:country":"US",
    "sg:address":"400 Washington Ave Rm M3",
    "sg:city":"Towson",
    "sg:classifiers":[
        {
            "category":"Banks & Credit Unions",
            "subcategory":"Investment Brokerage",
            "type":"Services"
        },
        {
            "category":"Professional",
            "subcategory":"Business Services",
            "type":"Services"
        }
    ],
    "sg:phone":"+1 410 887 8000",
    "sg:postcode":"21204",
    "sg:province":"MD",
    "sg:tags":[
        "development",
        "councils",
        "commissions",
        "economic",
        "authorities"
    ],
    "sg:website":"http://www.bc-works.com",
    "wof:name":"Economic Dev- Admin",
    "wof:placetype":"venue"
},
  "geometry": {"coordinates":[-76.6054,39.39967],"type":"Point"}
}