{
  "type": "Feature",
  "properties": {
    "iso:country":"US",
    "sg:address":"20812 Townsend Rd",
    "sg:city":"Rohrersville",
    "sg:classifiers":[
        {
            "category":"Building & Trades",
            "subcategory":"Construction",
            "type":"Services"
        }
    ],
    "sg:phone":"+1 301 432 0678",
    "sg:postcode":"21779",
    "sg:province":"MD",
    "sg:tags":[
        "contractor"
    ],
    "wof:name":"Team Prestine",
    "wof:placetype":"venue"
},
  "geometry": {"coordinates":[-77.65949999999999,39.411098],"type":"Point"}
}