{
  "type": "Feature",
  "properties": {
    "addr:full":"395 Club House Dr Lusby MD 20657",
    "addr:housenumber":"395",
    "addr:postcode":"20657",
    "addr:street":"Club House Dr",
    "iso:country":"US",
    "sg:address":"395 Club House Dr",
    "sg:city":"Lusby",
    "sg:classifiers":[
        {
            "category":"Organizations",
            "subcategory":"Community Association",
            "type":"Services"
        }
    ],
    "sg:phone":"+1 410 326 3182",
    "sg:postcode":"20657",
    "sg:province":"MD",
    "sg:tags":[
        "club"
    ],
    "wof:name":"Chesapeake Ranch Estates",
    "wof:placetype":"venue"
},
  "geometry": {"coordinates":[-76.41842,38.343026],"type":"Point"}
}