{
  "type": "Feature",
  "properties": {
    "iso:country":"US",
    "sg:address":"4716 Berwyn Rd",
    "sg:city":"Berwyn Heights",
    "sg:classifiers":[
        {
            "category":"Social Services",
            "subcategory":"Child Care",
            "type":"Services"
        }
    ],
    "sg:phone":"+1 240 684 5200",
    "sg:postcode":"20740",
    "sg:province":"MD",
    "wof:name":"UMUC Headstart",
    "wof:placetype":"venue"
},
  "geometry": {"coordinates":[-76.93039400000001,38.99574],"type":"Point"}
}