{
  "type": "Feature",
  "properties": {
    "addr:full":"8001 New Hampshire Ave Hyattsville MD 20783",
    "addr:housenumber":"8001",
    "addr:postcode":"20783",
    "addr:street":"New Hampshire Ave",
    "iso:country":"US",
    "sg:address":"8001 New Hampshire Ave",
    "sg:city":"Hyattsville",
    "sg:classifiers":[
        {
            "category":"Shopping",
            "subcategory":"Gifts & Souvenirs",
            "type":"Retail Goods"
        }
    ],
    "sg:phone":"+1 240 450 0333",
    "sg:postcode":"20783",
    "sg:province":"MD",
    "sg:tags":[
        "indian"
    ],
    "wof:name":"Khoobsurat",
    "wof:placetype":"venue"
},
  "geometry": {"coordinates":[-76.98745,38.990594],"type":"Point"}
}