{
  "type": "Feature",
  "properties": {
    "iso:country":"US",
    "sg:address":"3500 E West Hwy",
    "sg:city":"Hyattsville",
    "sg:classifiers":[
        {
            "category":"Shopping",
            "subcategory":"Clothing, Apparel, & Fashions",
            "type":"Retail Goods"
        }
    ],
    "sg:phone":"+1 301 853 2355",
    "sg:postcode":"20782",
    "sg:province":"MD",
    "sg:tags":[
        "accessory",
        "clothing",
        "women's"
    ],
    "wof:name":"Lucaya",
    "wof:placetype":"venue"
},
  "geometry": {"coordinates":[-76.959503,38.9669],"type":"Point"}
}