{
  "type": "Feature",
  "properties": {
    "addr:full":"118 Shawan Rd Cockysvl Hnt Vly MD 21030",
    "addr:housenumber":"118",
    "addr:postcode":"21030",
    "addr:street":"Shawan Rd;Hnt Vly",
    "iso:country":"US",
    "sg:address":"118 Shawan Rd",
    "sg:city":"Cockysvl Hnt Vly",
    "sg:classifiers":[
        {
            "category":"Recreation",
            "type":"Entertainment"
        }
    ],
    "sg:phone":"+1 410 527 1522",
    "sg:postcode":"21030",
    "sg:province":"MD",
    "sg:tags":[
        "paint",
        "ball",
        "sport"
    ],
    "wof:name":"Warped Sportz",
    "wof:placetype":"venue"
},
  "geometry": {"coordinates":[-76.658456,39.495704],"type":"Point"}
}