{
  "type": "Feature",
  "properties": {
    "iso:country":"US",
    "sg:address":"231 Carvel Rd",
    "sg:city":"Pasadena",
    "sg:classifiers":[
        {
            "category":"Retail",
            "subcategory":"Car Wash",
            "type":"Services"
        }
    ],
    "sg:phone":"+1 410 437 8492",
    "sg:postcode":"21122",
    "sg:province":"MD",
    "wof:name":"Total Detail",
    "wof:placetype":"venue"
},
  "geometry": {"coordinates":[-76.505295,39.162423],"type":"Point"}
}