{
  "type": "Feature",
  "properties": {
    "iso:country":"US",
    "sg:address":"11728 Nebel St",
    "sg:city":"Rockville",
    "sg:phone":"+1 301 984 1394",
    "sg:postcode":"20852",
    "sg:province":"MD",
    "sg:tags":[
        "equipment",
        "supply"
    ],
    "wof:name":"Silver Spoon",
    "wof:placetype":"venue"
},
  "geometry": {"coordinates":[-77.10575900000001,39.048149],"type":"Point"}
}