{
  "type": "Feature",
  "properties": {
    "iso:country":"US",
    "sg:address":"2159 York Rd",
    "sg:city":"Timonium",
    "sg:classifiers":[
        {
            "category":"Home & Garden",
            "subcategory":"Building Materials",
            "type":"Retail Goods"
        }
    ],
    "sg:phone":"+1 410 252 6440",
    "sg:postcode":"21093",
    "sg:province":"MD",
    "sg:tags":[
        "paint"
    ],
    "wof:name":"Sherwin-Williams Paints",
    "wof:placetype":"venue"
},
  "geometry": {"coordinates":[-76.627734,39.444016],"type":"Point"}
}