{
  "type": "Feature",
  "properties": {
    "addr:full":"1509 Ralworth Rd Baltimore MD 21218",
    "addr:housenumber":"1509",
    "addr:postcode":"21218",
    "addr:street":"Ralworth Rd",
    "iso:country":"US",
    "sg:address":"1509 Ralworth Rd",
    "sg:city":"Baltimore",
    "sg:classifiers":[
        {
            "category":"Manufacturing",
            "subcategory":"Printing",
            "type":"Manufacturing & Wholesale Goods"
        }
    ],
    "sg:phone":"+1 410 467 6795",
    "sg:postcode":"21218",
    "sg:province":"MD",
    "sg:tags":[
        "periodical"
    ],
    "wof:name":"Natural Roots Magazine Inc",
    "wof:placetype":"venue"
},
  "geometry": {"coordinates":[-76.591613,39.33929],"type":"Point"}
}