{
  "type": "Feature",
  "properties": {
    "iso:country":"US",
    "sg:address":"2707 Henson Valley Way",
    "sg:city":"Fort Washington",
    "sg:classifiers":[
        {
            "category":"Building & Trades",
            "subcategory":"Construction",
            "type":"Services"
        }
    ],
    "sg:phone":"+1 301 248 9351",
    "sg:postcode":"20744",
    "sg:province":"MD",
    "sg:tags":[
        "home",
        "builder"
    ],
    "wof:name":"Ryan Homes",
    "wof:placetype":"venue"
},
  "geometry": {"coordinates":[-76.96192499999999,38.791066],"type":"Point"}
}