{
  "type": "Feature",
  "properties": {
    "iso:country":"US",
    "sg:address":"1200 S Washington St",
    "sg:city":"Easton",
    "sg:classifiers":[
        {
            "category":"Freight",
            "type":"Transportation"
        }
    ],
    "sg:phone":"+1 410 476 9790",
    "sg:postcode":"21601",
    "sg:province":"MD",
    "sg:tags":[
        "mover"
    ],
    "wof:name":"TNT Inc",
    "wof:placetype":"venue"
},
  "geometry": {"coordinates":[-76.071634,38.750825],"type":"Point"}
}