{
  "type": "Feature",
  "properties": {
    "addr:full":"5852 Urbana Pike Frederick MD 21704",
    "addr:housenumber":"5852",
    "addr:postcode":"21704",
    "addr:street":"Urbana Pike",
    "iso:country":"US",
    "sg:address":"5852 Urbana Pike",
    "sg:city":"Frederick",
    "sg:classifiers":[
        {
            "category":"Autos & Motor Vehicles",
            "subcategory":"Automobile Sales",
            "type":"Retail Goods"
        }
    ],
    "sg:phone":"+1 301 631 0300",
    "sg:postcode":"21704",
    "sg:province":"MD",
    "sg:tags":[
        "car",
        "dealer"
    ],
    "wof:name":"Mount Pleasant Auto Sales",
    "wof:placetype":"venue"
},
  "geometry": {"coordinates":[-77.40586,39.3924],"type":"Point"}
}