{
  "type": "Feature",
  "properties": {
    "addr:full":"12588 National Pike Grantsville MD 21536",
    "addr:housenumber":"12588",
    "addr:postcode":"21536",
    "addr:street":"National Pike",
    "iso:country":"US",
    "sg:address":"12588 National Pike",
    "sg:city":"Grantsville",
    "sg:classifiers":[
        {
            "category":"Insurance",
            "subcategory":"Insurance Agent",
            "type":"Services"
        }
    ],
    "sg:phone":"+1 301 895 5011",
    "sg:postcode":"21536",
    "sg:province":"MD",
    "wof:name":"Yoder-Hershberger Insurance",
    "wof:placetype":"venue"
},
  "geometry": {"coordinates":[-79.103708,39.694682],"type":"Point"}
}