{
  "type": "Feature",
  "properties": {
    "iso:country":"US",
    "sg:address":"839 Elkridge Landing Rd",
    "sg:city":"Linthicum Hts",
    "sg:classifiers":[
        {
            "category":"Professional",
            "subcategory":"Detective & Security Services",
            "type":"Services"
        }
    ],
    "sg:phone":"+1 410 694 0322",
    "sg:postcode":"21090",
    "sg:province":"MD",
    "wof:name":"Promia",
    "wof:placetype":"venue"
},
  "geometry": {"coordinates":[-76.686834,39.196465],"type":"Point"}
}