{
  "type": "Feature",
  "properties": {
    "addr:full":"600 Cherry Hill Rd Brooklyn MD 21225",
    "addr:housenumber":"600",
    "addr:postcode":"21225",
    "addr:street":"Cherry Hill Rd",
    "iso:country":"US",
    "sg:address":"600 Cherry Hill Rd",
    "sg:city":"Brooklyn",
    "sg:classifiers":[
        {
            "category":"Health Services",
            "subcategory":"Clinic",
            "type":"Services"
        }
    ],
    "sg:phone":"+1 410 383 7291",
    "sg:postcode":"21225",
    "sg:province":"MD",
    "sg:tags":[
        "welfare"
    ],
    "wof:name":"Total Health Care",
    "wof:placetype":"venue"
},
  "geometry": {"coordinates":[-76.622017,39.250381],"type":"Point"}
}