{
  "type": "Feature",
  "properties": {
    "iso:country":"US",
    "sg:address":"147 Old Solomons Island Rd",
    "sg:city":"Annapolis",
    "sg:classifiers":[
        {
            "category":"Organizations",
            "subcategory":"Professional Association",
            "type":"Services"
        }
    ],
    "sg:phone":"+1 410 573 0400",
    "sg:postcode":"21401",
    "sg:province":"MD",
    "wof:name":"Wholesale Florist & Florist",
    "wof:placetype":"venue"
},
  "geometry": {"coordinates":[-76.53717899999999,38.978003],"type":"Point"}
}