{
  "type": "Feature",
  "properties": {
    "iso:country":"US",
    "sg:address":"815 Turkey Point Rd",
    "sg:city":"North East",
    "sg:classifiers":[
        {
            "category":"Social Services",
            "type":"Services"
        }
    ],
    "sg:phone":"+1 410 287 7817",
    "sg:postcode":"21901",
    "sg:province":"MD",
    "sg:tags":[
        "organization",
        "welfare"
    ],
    "wof:name":"Veterans Of Foreign Wars 6027",
    "wof:placetype":"venue"
},
  "geometry": {"coordinates":[-75.94172,39.592214],"type":"Point"}
}