{
  "type": "Feature",
  "properties": {
    "iso:country":"US",
    "sg:address":"1183 Merritt Blvd",
    "sg:city":"Baltimore",
    "sg:classifiers":[
        {
            "category":"Building & Trades",
            "subcategory":"Equipment Rental",
            "type":"Services"
        }
    ],
    "sg:phone":"+1 410 285 7368",
    "sg:postcode":"21222",
    "sg:province":"MD",
    "sg:tags":[
        "yard"
    ],
    "wof:name":"Color Tyme",
    "wof:placetype":"venue"
},
  "geometry": {"coordinates":[-76.505382,39.281327],"type":"Point"}
}