{
  "type": "Feature",
  "properties": {
    "addr:full":"6704 Maple Ave Chevy Chase MD 20815",
    "addr:housenumber":"6704",
    "addr:postcode":"20815",
    "addr:street":"Maple Ave",
    "iso:country":"US",
    "sg:address":"6704 Maple Ave",
    "sg:city":"Chevy Chase",
    "sg:classifiers":[
        {
            "category":"Professional",
            "subcategory":"Lawyer & Legal Services",
            "type":"Services"
        }
    ],
    "sg:phone":"+1 301 656 3929",
    "sg:postcode":"20815",
    "sg:province":"MD",
    "wof:name":"Heiman Richard J Atty",
    "wof:placetype":"venue"
},
  "geometry": {"coordinates":[-77.084636,38.977106],"type":"Point"}
}