{
  "type": "Feature",
  "properties": {
    "addr:full":"34 Bush Cabin Ct Parkton MD 21120",
    "addr:housenumber":"34",
    "addr:postcode":"21120",
    "addr:street":"Bush Cabin Ct",
    "iso:country":"US",
    "sg:address":"34 Bush Cabin Ct",
    "sg:city":"Parkton",
    "sg:classifiers":[
        {
            "category":"Professional",
            "subcategory":"Engineering",
            "type":"Services"
        }
    ],
    "sg:phone":"+1 410 357 4946",
    "sg:postcode":"21120",
    "sg:province":"MD",
    "sg:tags":[
        "consulting",
        "engineer"
    ],
    "wof:name":"Simple Solutions Consulting",
    "wof:placetype":"venue"
},
  "geometry": {"coordinates":[-76.728438,39.591503],"type":"Point"}
}