{
  "type": "Feature",
  "properties": {
    "addr:full":"910 W Pulaski Hwy Elkton MD 21921",
    "addr:housenumber":"910",
    "addr:postcode":"21921",
    "addr:street":"W Pulaski Hwy",
    "iso:country":"US",
    "sg:address":"910 W Pulaski Hwy",
    "sg:city":"Elkton",
    "sg:classifiers":[
        {
            "category":"Home & Garden",
            "subcategory":"Building Materials",
            "type":"Retail Goods"
        }
    ],
    "sg:phone":"+1 410 398 1111",
    "sg:postcode":"21921",
    "sg:province":"MD",
    "wof:name":"Ace Hardware",
    "wof:placetype":"venue"
},
  "geometry": {"coordinates":[-75.88661500000001,39.608971],"type":"Point"}
}