{
  "type": "Feature",
  "properties": {
    "iso:country":"US",
    "sg:address":"1592 Kimblewick Rd",
    "sg:city":"Rockville",
    "sg:classifiers":[
        {
            "category":"Organizations",
            "subcategory":"Religious Organization",
            "type":"Services"
        }
    ],
    "sg:phone":"+1 301 762 2143",
    "sg:postcode":"20854",
    "sg:province":"MD",
    "sg:tags":[
        "church"
    ],
    "wof:name":"St Raphael's Catholic Church",
    "wof:placetype":"venue"
},
  "geometry": {"coordinates":[-77.175343,39.060792],"type":"Point"}
}