{
  "type": "Feature",
  "properties": {
    "iso:country":"US",
    "sg:address":"200 W Cold Spring Ln",
    "sg:city":"Baltimore",
    "sg:classifiers":[
        {
            "category":"Professional",
            "subcategory":"Management & Consulting",
            "type":"Services"
        }
    ],
    "sg:phone":"+1 410 243 1974",
    "sg:postcode":"21210",
    "sg:province":"MD",
    "sg:tags":[
        "consultant"
    ],
    "wof:name":"Livingston Associates",
    "wof:placetype":"venue"
},
  "geometry": {"coordinates":[-76.626623,39.345034],"type":"Point"}
}