{
  "type": "Feature",
  "properties": {
    "iso:country":"US",
    "sg:address":"121 Chessie Ct",
    "sg:city":"Chester",
    "sg:classifiers":[
        {
            "category":"Personal",
            "type":"Services"
        }
    ],
    "sg:phone":"+1 410 643 5648",
    "sg:postcode":"21619",
    "sg:province":"MD",
    "sg:tags":[
        "pet",
        "exercising"
    ],
    "wof:name":"Chessie Petsitting",
    "wof:placetype":"venue"
},
  "geometry": {"coordinates":[-76.281155,38.971955],"type":"Point"}
}