{
  "type": "Feature",
  "properties": {
    "addr:full":"5302 Cecil Ave Gwynn Oak MD 21207",
    "addr:housenumber":"5302",
    "addr:postcode":"21207",
    "addr:street":"Cecil Ave",
    "iso:country":"US",
    "sg:address":"5302 Cecil Ave",
    "sg:city":"Gwynn Oak",
    "sg:classifiers":[
        {
            "category":"Organizations",
            "subcategory":"Community Association",
            "type":"Services"
        }
    ],
    "sg:phone":"+1 410 298 6758",
    "sg:postcode":"21207",
    "sg:province":"MD",
    "sg:tags":[
        "environmental",
        "org"
    ],
    "wof:name":"Woodrow Gardner & Assoc",
    "wof:placetype":"venue"
},
  "geometry": {"coordinates":[-76.713071,39.308916],"type":"Point"}
}