{
  "type": "Feature",
  "properties": {
    "iso:country":"US",
    "sg:address":"8660 Cherry Ln",
    "sg:city":"Laurel",
    "sg:classifiers":[
        {
            "category":"Professional",
            "type":"Services"
        }
    ],
    "sg:phone":"+1 866 350 7295",
    "sg:postcode":"20707",
    "sg:province":"MD",
    "sg:tags":[
        "spa",
        "hot",
        "tubs-repair"
    ],
    "wof:name":"Outdoor Leisure, Inc.",
    "wof:placetype":"venue"
},
  "geometry": {"coordinates":[-76.85563500000001,39.090589],"type":"Point"}
}