{
  "type": "Feature",
  "properties": {
    "iso:country":"US",
    "sg:address":"30500 Prince William St",
    "sg:city":"Princess Anne",
    "sg:classifiers":[
        {
            "category":"Government",
            "subcategory":"Court House",
            "type":"Public Place"
        }
    ],
    "sg:phone":"+1 410 651 3333",
    "sg:postcode":"21853",
    "sg:province":"MD",
    "sg:tags":[
        "state",
        "counsel"
    ],
    "wof:name":"Somerset County State Attorney",
    "wof:placetype":"venue"
},
  "geometry": {"coordinates":[-75.693411,38.204156],"type":"Point"}
}