{
  "type": "Feature",
  "properties": {
    "iso:country":"US",
    "sg:address":"2400 Queens Chapel Rd Apt 316",
    "sg:city":"Hyattsville",
    "sg:classifiers":[
        {
            "category":"Local Transit",
            "type":"Transportation"
        }
    ],
    "sg:phone":"+1 202 409 8874",
    "sg:postcode":"20782",
    "sg:province":"MD",
    "sg:tags":[
        "shuttle"
    ],
    "wof:name":"Modern X Press",
    "wof:placetype":"venue"
},
  "geometry": {"coordinates":[-76.972359,38.947689],"type":"Point"}
}