{
  "type": "Feature",
  "properties": {
    "addr:full":"2501 Belair Rd Baltimore MD 21213",
    "addr:housenumber":"2501",
    "addr:postcode":"21213",
    "addr:street":"Belair Rd",
    "iso:country":"US",
    "sg:address":"2501 Belair Rd",
    "sg:city":"Baltimore",
    "sg:classifiers":[
        {
            "category":"Shopping",
            "subcategory":"Department Store",
            "type":"Retail Goods"
        }
    ],
    "sg:phone":"+1 410 327 6710",
    "sg:postcode":"21213",
    "sg:province":"MD",
    "wof:name":"T J Maxx",
    "wof:placetype":"venue"
},
  "geometry": {"coordinates":[-76.576398,39.319038],"type":"Point"}
}