{
  "type": "Feature",
  "properties": {
    "iso:country":"US",
    "sg:address":"6551 Mid Cities Ave",
    "sg:city":"Beltsville",
    "sg:classifiers":[
        {
            "category":"Professional",
            "subcategory":"Research",
            "type":"Services"
        }
    ],
    "sg:phone":"+1 301 595 3997",
    "sg:postcode":"20705",
    "sg:province":"MD",
    "sg:tags":[
        "development",
        "laboratory"
    ],
    "wof:name":"Berkeley Research Assoc Inc",
    "wof:placetype":"venue"
},
  "geometry": {"coordinates":[-76.88920299999999,39.053669],"type":"Point"}
}