{
  "type": "Feature",
  "properties": {
    "iso:country":"US",
    "sg:address":"3202 Tower Oaks Blvd",
    "sg:city":"Rockville",
    "sg:classifiers":[
        {
            "category":"Professional",
            "subcategory":"Management & Consulting",
            "type":"Services"
        }
    ],
    "sg:phone":"+1 301 770 0534",
    "sg:postcode":"20852",
    "sg:province":"MD",
    "sg:tags":[
        "consultant",
        "business"
    ],
    "wof:name":"Mrf Consulting",
    "wof:placetype":"venue"
},
  "geometry": {"coordinates":[-77.15081600000001,39.057456],"type":"Point"}
}