{
  "type": "Feature",
  "properties": {
    "addr:full":"4210 Lowell Dr Pikesville MD 21208",
    "addr:housenumber":"4210",
    "addr:postcode":"21208",
    "addr:street":"Lowell Dr",
    "iso:country":"US",
    "sg:address":"4210 Lowell Dr",
    "sg:city":"Pikesville",
    "sg:classifiers":[
        {
            "category":"Professional",
            "subcategory":"Management & Consulting",
            "type":"Services"
        }
    ],
    "sg:phone":"+1 410 580 5480",
    "sg:postcode":"21208",
    "sg:province":"MD",
    "sg:tags":[
        "consultant",
        "business"
    ],
    "wof:name":"Campbell Consulting",
    "wof:placetype":"venue"
},
  "geometry": {"coordinates":[-76.71803300000001,39.362397],"type":"Point"}
}