{
  "type": "Feature",
  "properties": {
    "addr:full":"14713 Baltimore Ave Laurel MD 20707",
    "addr:housenumber":"14713",
    "addr:postcode":"20707",
    "addr:street":"Baltimore Ave",
    "iso:country":"US",
    "sg:address":"14713 Baltimore Ave",
    "sg:city":"Laurel",
    "sg:classifiers":[
        {
            "category":"Professional",
            "type":"Services"
        }
    ],
    "sg:phone":"+1 301 604 0000",
    "sg:postcode":"20707",
    "sg:province":"MD",
    "sg:tags":[
        "establishment"
    ],
    "wof:name":"Oriental Express",
    "wof:placetype":"venue"
},
  "geometry": {"coordinates":[-76.856855,39.091799],"type":"Point"}
}