{
  "type": "Feature",
  "properties": {
    "iso:country":"US",
    "sg:address":"10020 Southern Maryland Blvd",
    "sg:city":"Dunkirk",
    "sg:classifiers":[
        {
            "category":"Health Services",
            "subcategory":"Dentist",
            "type":"Services"
        }
    ],
    "sg:phone":"+1 410 257 0353",
    "sg:postcode":"20754",
    "sg:province":"MD",
    "sg:tags":[
        "dentists-orthodontists"
    ],
    "wof:name":"Sheldon R Seidel Dds",
    "wof:placetype":"venue"
},
  "geometry": {"coordinates":[-76.660078,38.726031],"type":"Point"}
}