{
  "type": "Feature",
  "properties": {
    "addr:full":"1403 Old Musket Ln Fort Washington MD 20744",
    "addr:housenumber":"1403",
    "addr:postcode":"20744",
    "addr:street":"Old Musket Ln",
    "iso:country":"US",
    "sg:address":"1403 Old Musket Ln",
    "sg:city":"Fort Washington",
    "sg:classifiers":[
        {
            "category":"Wholesale",
            "subcategory":"Machinery & Supplies",
            "type":"Manufacturing & Wholesale Goods"
        }
    ],
    "sg:phone":"+1 301 203 0772",
    "sg:postcode":"20744",
    "sg:province":"MD",
    "sg:tags":[
        "snow",
        "plowing"
    ],
    "wof:name":"Bobo & Babygirl Trucking",
    "wof:placetype":"venue"
},
  "geometry": {"coordinates":[-76.985676,38.740306],"type":"Point"}
}