{
  "type": "Feature",
  "properties": {
    "addr:full":"1864 Burley Rd Annapolis MD 21409",
    "addr:housenumber":"1864",
    "addr:postcode":"21409",
    "addr:street":"Burley Rd",
    "iso:country":"US",
    "sg:address":"1864 Burley Rd",
    "sg:city":"Annapolis",
    "sg:classifiers":[
        {
            "category":"Professional",
            "subcategory":"Computer Services",
            "type":"Services"
        }
    ],
    "sg:phone":"+1 410 757 5361",
    "sg:postcode":"21409",
    "sg:province":"MD",
    "sg:tags":[
        "related"
    ],
    "wof:name":"Larry H Westerland",
    "wof:placetype":"venue"
},
  "geometry": {"coordinates":[-76.450036,38.99921],"type":"Point"}
}