{
  "type": "Feature",
  "properties": {
    "iso:country":"US",
    "sg:address":"22523 Leitersburg Smithsburg Rd",
    "sg:city":"Smithsburg",
    "sg:classifiers":[
        {
            "category":"Utilities",
            "subcategory":"Refuse",
            "type":"Services"
        }
    ],
    "sg:phone":"+1 301 824 3249",
    "sg:postcode":"21783",
    "sg:province":"MD",
    "sg:tags":[
        "disposal",
        "plant"
    ],
    "wof:name":"Waste Water Treatment Plant",
    "wof:placetype":"venue"
},
  "geometry": {"coordinates":[-77.586614,39.666586],"type":"Point"}
}