{
  "type": "Feature",
  "properties": {
    "addr:full":"2125 Harford Rd Baltimore MD 21218",
    "addr:housenumber":"2125",
    "addr:postcode":"21218",
    "addr:street":"Harford Rd",
    "iso:country":"US",
    "sg:address":"2125 Harford Rd",
    "sg:city":"Baltimore",
    "sg:classifiers":[
        {
            "category":"Retail",
            "subcategory":"Auto Repair",
            "type":"Services"
        }
    ],
    "sg:phone":"+1 410 342 0026",
    "sg:postcode":"21218",
    "sg:province":"MD",
    "sg:tags":[
        "repairing",
        "automobile"
    ],
    "wof:name":"S & S Arlington Auto Repair",
    "wof:placetype":"venue"
},
  "geometry": {"coordinates":[-76.597702,39.314701],"type":"Point"}
}