{
  "type": "Feature",
  "properties": {
    "addr:full":"12 Wall St Rockville MD 20850",
    "addr:housenumber":"12",
    "addr:postcode":"20850",
    "addr:street":"Wall St",
    "iso:country":"US",
    "sg:address":"12 Wall St",
    "sg:city":"Rockville",
    "sg:classifiers":[
        {
            "category":"Shopping",
            "subcategory":"Hobbies, Toys, & Games",
            "type":"Retail Goods"
        }
    ],
    "sg:phone":"+1 301 340 6525",
    "sg:postcode":"20850",
    "sg:province":"MD",
    "sg:tags":[
        "craft",
        "supply"
    ],
    "wof:name":"Craftique Limited",
    "wof:placetype":"venue"
},
  "geometry": {"coordinates":[-77.160957,39.082823],"type":"Point"}
}