{
  "type": "Feature",
  "properties": {
    "iso:country":"US",
    "sg:address":"10200 Old Fort Rd",
    "sg:city":"Fort Washington",
    "sg:classifiers":[
        {
            "category":"Food & Beverages",
            "subcategory":"Groceries & Convenience Stores",
            "type":"Retail Goods"
        }
    ],
    "sg:phone":"+1 301 248 4400",
    "sg:postcode":"20744",
    "sg:province":"MD",
    "wof:name":"Joy Food Market",
    "wof:placetype":"venue"
},
  "geometry": {"coordinates":[-76.97796099999999,38.751162],"type":"Point"}
}