{
  "type": "Feature",
  "properties": {
    "iso:country":"US",
    "sg:address":"37680 Mohawk Dr",
    "sg:city":"Charlotte Hall",
    "sg:classifiers":[
        {
            "category":"Restaurant",
            "type":"Food & Drink"
        }
    ],
    "sg:menulink":"http://www.allmenus.com/md/mechanicsville/71361-ledo-pizza/menu/",
    "sg:phone":"+1 301 290 0111",
    "sg:postcode":"20622",
    "sg:province":"MD",
    "sg:tags":[
        "american",
        "pizza"
    ],
    "wof:name":"Ledo Pizza",
    "wof:placetype":"venue"
},
  "geometry": {"coordinates":[-76.772012,38.507645],"type":"Point"}
}