{
  "type": "Feature",
  "properties": {
    "iso:country":"US",
    "sg:address":"1449 Key Hwy",
    "sg:city":"Baltimore",
    "sg:classifiers":[
        {
            "category":"Manufacturing",
            "subcategory":"Metals",
            "type":"Manufacturing & Wholesale Goods"
        },
        {
            "category":"Manufacturing",
            "subcategory":"Building Materials",
            "type":"Manufacturing & Wholesale Goods"
        }
    ],
    "sg:phone":"+1 410 752 7620",
    "sg:postcode":"21230",
    "sg:province":"MD",
    "sg:tags":[
        "fabricator",
        "work",
        "sheet"
    ],
    "wof:name":"Baltimore Metal Works",
    "wof:placetype":"venue"
},
  "geometry": {"coordinates":[-76.60032699999999,39.272902],"type":"Point"}
}