{
  "type": "Feature",
  "properties": {
    "iso:country":"US",
    "sg:address":"805 Grundy St",
    "sg:city":"Baltimore",
    "sg:classifiers":[
        {
            "category":"Building & Trades",
            "subcategory":"Construction",
            "type":"Services"
        }
    ],
    "sg:phone":"+1 410 327 6416",
    "sg:postcode":"21224",
    "sg:province":"MD",
    "sg:tags":[
        "contractor"
    ],
    "wof:name":"Point Contractors",
    "wof:placetype":"venue"
},
  "geometry": {"coordinates":[-76.56313900000001,39.283669],"type":"Point"}
}