{
  "type": "Feature",
  "properties": {
    "addr:full":"11 Old Spring Ct Cockysvl Hnt Vly MD 21030",
    "addr:housenumber":"11",
    "addr:postcode":"21030",
    "addr:street":"Old Spring Ct Cockysvl Hnt Vly",
    "iso:country":"US",
    "sg:address":"11 Old Spring Ct",
    "sg:city":"Cockysvl Hnt Vly",
    "sg:classifiers":[
        {
            "category":"Professional",
            "subcategory":"Lawyer & Legal Services",
            "type":"Services"
        }
    ],
    "sg:phone":"+1 410 628 0973",
    "sg:postcode":"21030",
    "sg:province":"MD",
    "sg:tags":[
        "attorney"
    ],
    "wof:name":"George J Cocoros",
    "wof:placetype":"venue"
},
  "geometry": {"coordinates":[-76.600965,39.473656],"type":"Point"}
}