{
  "type": "Feature",
  "properties": {
    "iso:country":"US",
    "sg:address":"813 Branford Cir",
    "sg:city":"Lutherville Timonium",
    "sg:classifiers":[
        {
            "category":"Shopping",
            "subcategory":"Gifts & Souvenirs",
            "type":"Retail Goods"
        }
    ],
    "sg:phone":"+1 410 825 0568",
    "sg:postcode":"21093",
    "sg:province":"MD",
    "wof:name":"Auxillary Board St Vincents",
    "wof:placetype":"venue"
},
  "geometry": {"coordinates":[-76.638257,39.425373],"type":"Point"}
}