{
  "type": "Feature",
  "properties": {
    "iso:country":"US",
    "sg:address":"3718 Ligon Rd",
    "sg:city":"Ellicott City",
    "sg:classifiers":[
        {
            "category":"Building & Trades",
            "subcategory":"Construction",
            "type":"Services"
        }
    ],
    "sg:phone":"+1 410 465 3770",
    "sg:postcode":"21042",
    "sg:province":"MD",
    "sg:tags":[
        "general",
        "contractor"
    ],
    "sg:website":"www.radiationvaults.com",
    "wof:name":"Rhs Builders",
    "wof:placetype":"venue"
},
  "geometry": {"coordinates":[-76.831443,39.26991],"type":"Point"}
}