{
  "type": "Feature",
  "properties": {
    "addr:full":"2021 Pulaski Hwy Havre De Grace MD 21078",
    "addr:housenumber":"2021",
    "addr:postcode":"21078",
    "addr:street":"Pulaski Hwy",
    "iso:country":"US",
    "sg:address":"2021 Pulaski Hwy",
    "sg:city":"Havre De Grace",
    "sg:classifiers":[
        {
            "category":"Restaurant",
            "type":"Food & Drink"
        }
    ],
    "sg:menulink":"http://www.allmenus.com/md/havre-de-grace/285725-bill-batemans-bistro/menu/",
    "sg:phone":"+1 410 939 7667",
    "sg:postcode":"21078",
    "sg:province":"MD",
    "sg:tags":[
        "american"
    ],
    "wof:name":"Bill Batemans Bistro",
    "wof:placetype":"venue"
},
  "geometry": {"coordinates":[-76.130067,39.528661],"type":"Point"}
}