{
  "type": "Feature",
  "properties": {
    "addr:full":"8908 Loughran Ter Fort Washington MD 20744",
    "addr:housenumber":"8908",
    "addr:postcode":"20744",
    "addr:street":"Loughran Ter",
    "iso:country":"US",
    "sg:address":"8908 Loughran Ter",
    "sg:city":"Fort Washington",
    "sg:classifiers":[
        {
            "category":"Professional",
            "type":"Services"
        }
    ],
    "sg:phone":"+1 301 749 7300",
    "sg:postcode":"20744",
    "sg:province":"MD",
    "sg:tags":[
        "establishment"
    ],
    "wof:name":"Koba Institute",
    "wof:placetype":"venue"
},
  "geometry": {"coordinates":[-77.01558,38.767531],"type":"Point"}
}