{
  "type": "Feature",
  "properties": {
    "addr:full":"3728 Tudor Arms Ave Baltimore MD 21211",
    "addr:housenumber":"3728",
    "addr:postcode":"21211",
    "addr:street":"Tudor Arms Ave",
    "iso:country":"US",
    "sg:address":"3728 Tudor Arms Ave",
    "sg:city":"Baltimore",
    "sg:classifiers":[
        {
            "category":"Organizations",
            "subcategory":"Religious Organization",
            "type":"Services"
        }
    ],
    "sg:phone":"+1 410 243 4746",
    "sg:postcode":"21211",
    "sg:province":"MD",
    "sg:tags":[
        "clergy"
    ],
    "wof:name":"T Stewart Lucas",
    "wof:placetype":"venue"
},
  "geometry": {"coordinates":[-76.62588100000001,39.333157],"type":"Point"}
}