{
  "type": "Feature",
  "properties": {
    "addr:full":"12451 Algonquin Trl Lusby MD 20657",
    "addr:housenumber":"12451",
    "addr:postcode":"20657",
    "addr:street":"Algonquin Trl",
    "iso:country":"US",
    "sg:address":"12451 Algonquin Trl",
    "sg:city":"Lusby",
    "sg:classifiers":[
        {
            "category":"Building & Trades",
            "subcategory":"Pest Control",
            "type":"Services"
        }
    ],
    "sg:phone":"+1 301 855 1699",
    "sg:postcode":"20657",
    "sg:province":"MD",
    "wof:name":"Norco",
    "wof:placetype":"venue"
},
  "geometry": {"coordinates":[-76.399941,38.35281],"type":"Point"}
}