{
  "type": "Feature",
  "properties": {
    "iso:country":"US",
    "sg:address":"14 Dulaney Hills Ct",
    "sg:city":"Cockeysville",
    "sg:classifiers":[
        {
            "category":"Shopping",
            "type":"Retail Goods"
        }
    ],
    "sg:phone":"+1 410 404 0174",
    "sg:postcode":"21030",
    "sg:province":"MD",
    "sg:tags":[
        "merchandise"
    ],
    "wof:name":"Party Cake Shoppe",
    "wof:placetype":"venue"
},
  "geometry": {"coordinates":[-76.59705700000001,39.470198],"type":"Point"}
}