{
  "type": "Feature",
  "properties": {
    "iso:country":"US",
    "sg:address":"513 Grant Pl",
    "sg:city":"Frederick",
    "sg:classifiers":[
        {
            "category":"Real Estate",
            "subcategory":"Real Estate Agent",
            "type":"Services"
        }
    ],
    "sg:phone":"+1 301 695 3453",
    "sg:postcode":"21702",
    "sg:province":"MD",
    "sg:tags":[
        "brokerage",
        "appraisal"
    ],
    "wof:name":"Martin Real Estate Svcs LLC",
    "wof:placetype":"venue"
},
  "geometry": {"coordinates":[-77.425505,39.429115],"type":"Point"}
}