{
  "type": "Feature",
  "properties": {
    "addr:full":"2001 Race St Baltimore MD 21230",
    "addr:housenumber":"2001",
    "addr:postcode":"21230",
    "addr:street":"Race St",
    "iso:country":"US",
    "sg:address":"2001 Race St",
    "sg:city":"Baltimore",
    "sg:classifiers":[
        {
            "category":"Home & Garden",
            "subcategory":"Building Materials",
            "type":"Retail Goods"
        }
    ],
    "sg:phone":"+1 410 837 2044",
    "sg:postcode":"21230",
    "sg:province":"MD",
    "sg:website":"www.rewmaterials.com",
    "wof:name":"Rew Materials",
    "wof:placetype":"venue"
},
  "geometry": {"coordinates":[-76.61608699999999,39.265122],"type":"Point"}
}