{
  "type": "Feature",
  "properties": {
    "addr:full":"3809 31st St Mt Rainier MD 20712",
    "addr:housenumber":"3809",
    "addr:postcode":"20712",
    "addr:street":"31St St",
    "iso:country":"US",
    "sg:address":"3809 31st St",
    "sg:city":"Mt Rainier",
    "sg:classifiers":[
        {
            "category":"Shopping",
            "type":"Retail Goods"
        }
    ],
    "sg:phone":"+1 301 927 4600",
    "sg:postcode":"20712",
    "sg:province":"MD",
    "sg:tags":[
        "cosmetic",
        "perfume"
    ],
    "wof:name":"Commy Hair Design & Cosmetic",
    "wof:placetype":"venue"
},
  "geometry": {"coordinates":[-76.964387,38.938034],"type":"Point"}
}