{
  "type": "Feature",
  "properties": {
    "iso:country":"US",
    "sg:address":"612 3rd St",
    "sg:city":"Annapolis",
    "sg:classifiers":[
        {
            "category":"Recreation",
            "type":"Entertainment"
        },
        {
            "category":"Organizations",
            "subcategory":"Community Association",
            "type":"Services"
        }
    ],
    "sg:phone":"+1 410 269 1194",
    "sg:postcode":"21403",
    "sg:province":"MD",
    "sg:tags":[
        "club",
        "yacht",
        "membership",
        "racing"
    ],
    "wof:name":"Chesapeake Bay Yacht Racg Assn",
    "wof:placetype":"venue"
},
  "geometry": {"coordinates":[-76.478483,38.969067],"type":"Point"}
}