{
  "type": "Feature",
  "properties": {
    "addr:full":"702 W Sunset Ave Greensboro MD 21639",
    "addr:housenumber":"702",
    "addr:postcode":"21639",
    "addr:street":"W Sunset Ave",
    "iso:country":"US",
    "sg:address":"702 W Sunset Ave",
    "sg:city":"Greensboro",
    "sg:phone":"+1 410 482 6211",
    "sg:postcode":"21639",
    "sg:province":"MD",
    "sg:tags":[
        "oil"
    ],
    "wof:name":"Greensboro Supply Co",
    "wof:placetype":"venue"
},
  "geometry": {"coordinates":[-75.816624,38.977944],"type":"Point"}
}