{
  "type": "Feature",
  "properties": {
    "addr:full":"7668 Belair Rd Baltimore MD 21236",
    "addr:housenumber":"7668",
    "addr:postcode":"21236",
    "addr:street":"Belair Rd",
    "iso:country":"US",
    "sg:address":"7668 Belair Rd",
    "sg:city":"Baltimore",
    "sg:classifiers":[
        {
            "category":"Insurance",
            "subcategory":"Insurance Agent",
            "type":"Services"
        }
    ],
    "sg:phone":"+1 410 882 2900",
    "sg:postcode":"21236",
    "sg:province":"MD",
    "wof:name":"American General Life & Accdnt",
    "wof:placetype":"venue"
},
  "geometry": {"coordinates":[-76.51762100000001,39.366412],"type":"Point"}
}