{
  "type": "Feature",
  "properties": {
    "addr:full":"904 Pulaski Hwy Joppa MD 21085",
    "addr:housenumber":"904",
    "addr:postcode":"21085",
    "addr:street":"Pulaski Hwy",
    "iso:country":"US",
    "sg:address":"904 Pulaski Hwy",
    "sg:city":"Joppa",
    "sg:classifiers":[
        {
            "category":"Autos & Motor Vehicles",
            "subcategory":"Recreational Vehicle Sales",
            "type":"Retail Goods"
        }
    ],
    "sg:phone":"+1 410 676 2967",
    "sg:postcode":"21085",
    "sg:province":"MD",
    "sg:tags":[
        "parts",
        "trailer"
    ],
    "wof:name":"PSL Trailer Sales",
    "wof:placetype":"venue"
},
  "geometry": {"coordinates":[-76.342597,39.431208],"type":"Point"}
}