{
  "type": "Feature",
  "properties": {
    "iso:country":"US",
    "sg:address":"2024 West St",
    "sg:city":"Annapolis",
    "sg:classifiers":[
        {
            "category":"Communications",
            "type":"Services"
        },
        {
            "category":"Communications",
            "subcategory":"Television Station",
            "type":"Services"
        }
    ],
    "sg:phone":"+1 410 571 2068",
    "sg:postcode":"21401",
    "sg:province":"MD",
    "sg:tags":[
        "consultant",
        "satellite",
        "telecommunication",
        "cable"
    ],
    "wof:name":"Telecommumnication Systems",
    "wof:placetype":"venue"
},
  "geometry": {"coordinates":[-76.53527099999999,38.983002],"type":"Point"}
}