{
  "type": "Feature",
  "properties": {
    "iso:country":"US",
    "sg:address":"6901 Security Blvd",
    "sg:city":"Windsor Mill",
    "sg:classifiers":[
        {
            "category":"Professional",
            "type":"Services"
        }
    ],
    "sg:phone":"+1 410 265 0186",
    "sg:postcode":"21244",
    "sg:province":"MD",
    "sg:tags":[
        "caterer"
    ],
    "wof:name":"Seoul Catering",
    "wof:placetype":"venue"
},
  "geometry": {"coordinates":[-76.74913599999999,39.309433],"type":"Point"}
}