{
  "type": "Feature",
  "properties": {
    "addr:full":"11131 Maryland Manor Ct Germantown MD 20876",
    "addr:housenumber":"11131",
    "addr:postcode":"20876",
    "addr:street":"Maryland Manor Ct",
    "iso:country":"US",
    "sg:address":"11131 Maryland Manor Ct",
    "sg:city":"Germantown",
    "sg:classifiers":[
        {
            "category":"Professional",
            "subcategory":"Computer Services",
            "type":"Services"
        }
    ],
    "sg:phone":"+1 301 515 5651",
    "sg:postcode":"20876",
    "sg:province":"MD",
    "sg:tags":[
        "repair"
    ],
    "sg:website":"www.positivecomputers.com",
    "wof:name":"Positive Images Computer Svc",
    "wof:placetype":"venue"
},
  "geometry": {"coordinates":[-77.22901,39.176012],"type":"Point"}
}