{
  "type": "Feature",
  "properties": {
    "iso:country":"US",
    "sg:address":"12504 Naves Crossroads NE",
    "sg:city":"Cumberland",
    "sg:classifiers":[
        {
            "category":"Professional",
            "subcategory":"Management & Consulting",
            "type":"Services"
        }
    ],
    "sg:phone":"+1 301 724 4467",
    "sg:postcode":"21502",
    "sg:province":"MD",
    "sg:tags":[
        "food"
    ],
    "wof:name":"Healing Hunger Food Svc",
    "wof:placetype":"venue"
},
  "geometry": {"coordinates":[-78.731307,39.676558],"type":"Point"}
}