{
  "type": "Feature",
  "properties": {
    "addr:full":"5540 Norbeck Rd Rockville MD 20853",
    "addr:housenumber":"5540",
    "addr:postcode":"20853",
    "addr:street":"Norbeck Rd",
    "iso:country":"US",
    "sg:address":"5540 Norbeck Rd",
    "sg:city":"Rockville",
    "sg:classifiers":[
        {
            "category":"Professional",
            "type":"Services"
        },
        {
            "category":"Professional",
            "subcategory":"Business Services",
            "type":"Services"
        }
    ],
    "sg:phone":"+1 301 598 1200",
    "sg:postcode":"20853",
    "sg:province":"MD",
    "sg:tags":[
        "organization",
        "membership",
        "establishment"
    ],
    "wof:name":"Carl Freeman & Associates",
    "wof:placetype":"venue"
},
  "geometry": {"coordinates":[-77.111715,39.095511],"type":"Point"}
}