{
  "type": "Feature",
  "properties": {
    "iso:country":"US",
    "sg:address":"132 W Main St",
    "sg:city":"Westminster",
    "sg:classifiers":[
        {
            "category":"Banks & Credit Unions",
            "subcategory":"Bank",
            "type":"Services"
        }
    ],
    "sg:phone":"+1 410 848 7351",
    "sg:postcode":"21157",
    "sg:province":"MD",
    "wof:name":"Westminster Union Bank",
    "wof:placetype":"venue"
},
  "geometry": {"coordinates":[-76.999925,39.579192],"type":"Point"}
}