{
  "type": "Feature",
  "properties": {
    "iso:country":"US",
    "sg:address":"10210 Norwood Ct",
    "sg:city":"Charlotte Hall",
    "sg:classifiers":[
        {
            "category":"Building & Trades",
            "subcategory":"Construction",
            "type":"Services"
        }
    ],
    "sg:phone":"+1 301 609 6023",
    "sg:postcode":"20622",
    "sg:province":"MD",
    "sg:tags":[
        "general",
        "contractor"
    ],
    "wof:name":"Donald L Major Construction",
    "wof:placetype":"venue"
},
  "geometry": {"coordinates":[-76.867892,38.432831],"type":"Point"}
}