{
  "type": "Feature",
  "properties": {
    "iso:country":"US",
    "sg:address":"13549 Baltimore Ave",
    "sg:city":"Laurel",
    "sg:classifiers":[
        {
            "category":"Autos & Motor Vehicles",
            "subcategory":"Auto Supplies",
            "type":"Retail Goods"
        },
        {
            "category":"Retail",
            "subcategory":"Auto Repair",
            "type":"Services"
        },
        {
            "category":"Professional",
            "subcategory":"Computer Services",
            "type":"Services"
        }
    ],
    "sg:phone":"+1 301 210 0800",
    "sg:postcode":"20707",
    "sg:province":"MD",
    "sg:tags":[
        "detailing",
        "stereo",
        "installation",
        "glass"
    ],
    "sg:website":"www.hallstartint.com/",
    "wof:name":"Hallstar Tint & Detail",
    "wof:placetype":"venue"
},
  "geometry": {"coordinates":[-76.869336,39.075217],"type":"Point"}
}