{
  "type": "Feature",
  "properties": {
    "iso:country":"US",
    "sg:address":"8006 Oat Ridge Ct",
    "sg:city":"Bowie",
    "sg:classifiers":[
        {
            "category":"Shopping",
            "subcategory":"Clothing, Apparel, & Fashions",
            "type":"Retail Goods"
        }
    ],
    "sg:phone":"+1 301 464 7609",
    "sg:postcode":"20715",
    "sg:province":"MD",
    "sg:tags":[
        "apparel",
        "handbag",
        "accessory",
        "women's"
    ],
    "sg:website":"http://www.catofashions.com/",
    "wof:name":"Cato",
    "wof:placetype":"venue"
},
  "geometry": {"coordinates":[-76.737003,39.000907],"type":"Point"}
}