{
  "type": "Feature",
  "properties": {
    "iso:country":"US",
    "sg:address":"5335 Reisterstown Rd",
    "sg:city":"Baltimore",
    "sg:classifiers":[
        {
            "category":"Education",
            "subcategory":"Kindergarten",
            "type":"Public Place"
        }
    ],
    "sg:phone":"+1 410 764 1133",
    "sg:postcode":"21215",
    "sg:province":"MD",
    "sg:tags":[
        "school",
        "driving"
    ],
    "wof:name":"Drivers Edu Driving School",
    "wof:placetype":"venue"
},
  "geometry": {"coordinates":[-76.687523,39.345922],"type":"Point"}
}