{
  "type": "Feature",
  "properties": {
    "iso:country":"US",
    "sg:address":"14815 Baltimore Ave",
    "sg:city":"Laurel",
    "sg:classifiers":[
        {
            "category":"Food & Beverages",
            "subcategory":"Specialty",
            "type":"Retail Goods"
        }
    ],
    "sg:phone":"+1 240 568 9100",
    "sg:postcode":"20707",
    "sg:province":"MD",
    "sg:tags":[
        "supplement",
        "vitamin"
    ],
    "sg:website":"http://VitaminShoppe.com",
    "wof:name":"Vitamin Shoppe",
    "wof:placetype":"venue"
},
  "geometry": {"coordinates":[-76.85489699999999,39.093654],"type":"Point"}
}