{
  "type": "Feature",
  "properties": {
    "addr:full":"4800 Montgomery Ln Ste 100 Bethesda MD 20814",
    "addr:housenumber":"4800",
    "addr:postcode":"20814",
    "addr:street":"Montgomery Ln Ste 100",
    "iso:country":"US",
    "sg:address":"4800 Montgomery Ln Ste 100",
    "sg:city":"Bethesda",
    "sg:classifiers":[
        {
            "category":"Professional",
            "subcategory":"Lawyer & Legal Services",
            "type":"Services"
        }
    ],
    "sg:phone":"+1 301 907 7000",
    "sg:postcode":"20814",
    "sg:province":"MD",
    "wof:name":"Sandground New and Lowinger PC",
    "wof:placetype":"venue"
},
  "geometry": {"coordinates":[-77.094989,38.983343],"type":"Point"}
}