{
  "type": "Feature",
  "properties": {
    "addr:full":"4937 Green Valley Rd Monrovia MD 21770",
    "addr:housenumber":"4937",
    "addr:postcode":"21770",
    "addr:street":"Green Valley Rd",
    "iso:country":"US",
    "sg:address":"4937 Green Valley Rd",
    "sg:city":"Monrovia",
    "sg:classifiers":[
        {
            "category":"Building & Trades",
            "subcategory":"Landscaping Services",
            "type":"Services"
        }
    ],
    "sg:phone":"+1 301 831 3731",
    "sg:postcode":"21770",
    "sg:province":"MD",
    "sg:tags":[
        "lawn",
        "maintenance",
        "grounds"
    ],
    "wof:name":"Royal Greens Inc",
    "wof:placetype":"venue"
},
  "geometry": {"coordinates":[-77.271883,39.370342],"type":"Point"}
}