{
  "type": "Feature",
  "properties": {
    "addr:full":"9200 Basil Ct Upper Marlboro MD 20774",
    "addr:housenumber":"9200",
    "addr:postcode":"20774",
    "addr:street":"Basil Ct",
    "iso:country":"US",
    "sg:address":"9200 Basil Ct",
    "sg:city":"Upper Marlboro",
    "sg:classifiers":[
        {
            "category":"Professional",
            "subcategory":"Management & Consulting",
            "type":"Services"
        }
    ],
    "sg:phone":"+1 301 925 1900",
    "sg:postcode":"20774",
    "sg:province":"MD",
    "wof:name":"Sodexho Inc",
    "wof:placetype":"venue"
},
  "geometry": {"coordinates":[-76.846622,38.914923],"type":"Point"}
}