{
  "type": "Feature",
  "properties": {
    "addr:full":"1006 Beards Hill Rd Aberdeen MD 21001",
    "addr:housenumber":"1006",
    "addr:postcode":"21001",
    "addr:street":"Beards Hill Rd",
    "iso:country":"US",
    "sg:address":"1006 Beards Hill Rd",
    "sg:city":"Aberdeen",
    "sg:classifiers":[
        {
            "category":"Restaurant",
            "type":"Food & Drink"
        }
    ],
    "sg:menulink":"http://www.allmenus.com/md/halls-cross-roads/197062-burger-king/menu/",
    "sg:phone":"+1 410 272 7734",
    "sg:postcode":"21001",
    "sg:province":"MD",
    "sg:tags":[
        "burger",
        "american"
    ],
    "wof:name":"Burger King",
    "wof:placetype":"venue"
},
  "geometry": {"coordinates":[-76.184738,39.521721],"type":"Point"}
}