{
  "type": "Feature",
  "properties": {
    "addr:full":"1712 Blount Dr Fort Washington MD 20744",
    "addr:housenumber":"1712",
    "addr:postcode":"20744",
    "addr:street":"Blount Dr",
    "iso:country":"US",
    "sg:address":"1712 Blount Dr",
    "sg:city":"Fort Washington",
    "sg:classifiers":[
        {
            "category":"Professional",
            "subcategory":"Management & Consulting",
            "type":"Services"
        }
    ],
    "sg:phone":"+1 301 248 3821",
    "sg:postcode":"20744",
    "sg:province":"MD",
    "wof:name":"Ijs Consulting",
    "wof:placetype":"venue"
},
  "geometry": {"coordinates":[-76.98249,38.761414],"type":"Point"}
}