{
  "type": "Feature",
  "properties": {
    "iso:country":"US",
    "sg:address":"11 Maple Ave",
    "sg:city":"Walkersville",
    "sg:classifiers":[
        {
            "category":"Personal",
            "subcategory":"Beauty Salon",
            "type":"Services"
        }
    ],
    "sg:phone":"+1 301 694 3698",
    "sg:postcode":"21793",
    "sg:province":"MD",
    "wof:name":"Oasis Styling Salon",
    "wof:placetype":"venue"
},
  "geometry": {"coordinates":[-77.352378,39.481858],"type":"Point"}
}