{
  "type": "Feature",
  "properties": {
    "iso:country":"US",
    "sg:address":"9315 Riggs Rd",
    "sg:city":"Hyattsville",
    "sg:classifiers":[
        {
            "category":"Building & Trades",
            "subcategory":"Cleaning & Sanitation",
            "type":"Services"
        }
    ],
    "sg:phone":"+1 301 445 6688",
    "sg:postcode":"20783",
    "sg:province":"MD",
    "sg:tags":[
        "janitor"
    ],
    "wof:name":"H & N Cleaning Svc",
    "wof:placetype":"venue"
},
  "geometry": {"coordinates":[-76.965776,39.008841],"type":"Point"}
}