{
  "type": "Feature",
  "properties": {
    "addr:full":"3051 Washington Blvd Baltimore MD 21230",
    "addr:housenumber":"3051",
    "addr:postcode":"21230",
    "addr:street":"Washington Blvd",
    "iso:country":"US",
    "sg:address":"3051 Washington Blvd",
    "sg:city":"Baltimore",
    "sg:classifiers":[
        {
            "category":"Utilities",
            "subcategory":"Refuse",
            "type":"Services"
        }
    ],
    "sg:phone":"+1 443 524 0225",
    "sg:postcode":"21230",
    "sg:province":"MD",
    "sg:tags":[
        "waste",
        "removal"
    ],
    "wof:name":"Antaeus Group",
    "wof:placetype":"venue"
},
  "geometry": {"coordinates":[-76.659829,39.260075],"type":"Point"}
}