{
  "type": "Feature",
  "properties": {
    "iso:country":"US",
    "sg:address":"11116 Hurdle Hill Dr",
    "sg:city":"Potomac",
    "sg:classifiers":[
        {
            "category":"Wholesale",
            "subcategory":"Stationery",
            "type":"Manufacturing & Wholesale Goods"
        }
    ],
    "sg:phone":"+1 301 983 0747",
    "sg:postcode":"20854",
    "sg:province":"MD",
    "sg:tags":[
        "supply"
    ],
    "wof:name":"Creative Albums Inc",
    "wof:placetype":"venue"
},
  "geometry": {"coordinates":[-77.175228,39.039305],"type":"Point"}
}