{
  "type": "Feature",
  "properties": {
    "addr:full":"20 Lore Rd Solomons MD 20688",
    "addr:housenumber":"20",
    "addr:postcode":"20688",
    "addr:street":"Lore Rd",
    "iso:country":"US",
    "sg:address":"20 Lore Rd",
    "sg:city":"Solomons",
    "sg:classifiers":[
        {
            "category":"Autos & Motor Vehicles",
            "subcategory":"Automobile Sales",
            "type":"Retail Goods"
        }
    ],
    "sg:phone":"+1 410 535 5678",
    "sg:postcode":"20688",
    "sg:province":"MD",
    "sg:tags":[
        "limo"
    ],
    "wof:name":"Limo Scene",
    "wof:placetype":"venue"
},
  "geometry": {"coordinates":[-76.466103,38.344299],"type":"Point"}
}