{
  "type": "Feature",
  "properties": {
    "iso:country":"US",
    "sg:address":"18133 Oak Ridge Dr",
    "sg:city":"Hagerstown",
    "sg:classifiers":[
        {
            "category":"Professional",
            "subcategory":"Advertising",
            "type":"Services"
        },
        {
            "category":"Manufacturing",
            "subcategory":"Signs",
            "type":"Manufacturing & Wholesale Goods"
        }
    ],
    "sg:phone":"+1 301 766 4095",
    "sg:postcode":"21740",
    "sg:province":"MD",
    "sg:tags":[
        "specialty"
    ],
    "wof:name":"Star Grafx & Lettering",
    "wof:placetype":"venue"
},
  "geometry": {"coordinates":[-77.741867,39.61317],"type":"Point"}
}