{
  "type": "Feature",
  "properties": {
    "iso:country":"US",
    "sg:address":"76 E Main St",
    "sg:city":"Westminster",
    "sg:classifiers":[
        {
            "category":"Retail",
            "subcategory":"Repair Shop",
            "type":"Services"
        },
        {
            "category":"Professional",
            "subcategory":"Detective & Security Services",
            "type":"Services"
        }
    ],
    "sg:phone":"+1 410 871 1662",
    "sg:postcode":"21157",
    "sg:province":"MD",
    "sg:tags":[
        "skip",
        "tracing",
        "bail",
        "bond"
    ],
    "wof:name":"Jim Frank Chase",
    "wof:placetype":"venue"
},
  "geometry": {"coordinates":[-76.99436,39.573577],"type":"Point"}
}