{
  "type": "Feature",
  "properties": {
    "addr:full":"178 Thomas Johnson Dr Frederick MD 21702",
    "addr:housenumber":"178",
    "addr:postcode":"21702",
    "addr:street":"Thomas Johnson Dr",
    "iso:country":"US",
    "sg:address":"178 Thomas Johnson Dr",
    "sg:city":"Frederick",
    "sg:classifiers":[
        {
            "category":"Insurance",
            "subcategory":"Insurance Agent",
            "type":"Services"
        },
        {
            "category":"Insurance",
            "subcategory":"Hazard Insurance",
            "type":"Services"
        },
        {
            "category":"Insurance",
            "subcategory":"Title Insurance",
            "type":"Services"
        },
        {
            "category":"Insurance",
            "subcategory":"Life Insurance",
            "type":"Services"
        }
    ],
    "sg:phone":"+1 301 662 4199",
    "sg:postcode":"21702",
    "sg:province":"MD",
    "sg:tags":[
        "business",
        "auto",
        "commercial",
        "homeowner",
        "motorcycle",
        "renter"
    ],
    "wof:name":"Allstate Insurance Company - Michelle Turner",
    "wof:placetype":"venue"
},
  "geometry": {"coordinates":[-77.408011,39.43972],"type":"Point"}
}