{
  "type": "Feature",
  "properties": {
    "addr:full":"3412 Chiswick Ct Silver Spring MD 20906",
    "addr:housenumber":"3412",
    "addr:postcode":"20906",
    "addr:street":"Chiswick Ct",
    "iso:country":"US",
    "sg:address":"3412 Chiswick Ct",
    "sg:city":"Silver Spring",
    "sg:classifiers":[
        {
            "category":"Professional",
            "type":"Services"
        }
    ],
    "sg:phone":"+1 301 598 7627",
    "sg:postcode":"20906",
    "sg:province":"MD",
    "wof:name":"Andrew J Adams",
    "wof:placetype":"venue"
},
  "geometry": {"coordinates":[-77.068805,39.098069],"type":"Point"}
}