{
  "type": "Feature",
  "properties": {
    "iso:country":"US",
    "sg:address":"717 Winans Way",
    "sg:city":"Baltimore",
    "sg:classifiers":[
        {
            "category":"Restaurant",
            "type":"Food & Drink"
        }
    ],
    "sg:phone":"+1 410 522 7100",
    "sg:postcode":"21229",
    "sg:province":"MD",
    "sg:tags":[
        "caterer"
    ],
    "wof:name":"Ambrosia Caterers Inc",
    "wof:placetype":"venue"
},
  "geometry": {"coordinates":[-76.700911,39.296839],"type":"Point"}
}