{
  "type": "Feature",
  "properties": {
    "iso:country":"US",
    "sg:address":"915 Romancoke Rd",
    "sg:city":"Stevensville",
    "sg:classifiers":[
        {
            "category":"Home & Garden",
            "subcategory":"Garden Supply",
            "type":"Retail Goods"
        }
    ],
    "sg:phone":"+1 410 604 2121",
    "sg:postcode":"21666",
    "sg:province":"MD",
    "sg:tags":[
        "center"
    ],
    "wof:name":"Wild Flower Nursery",
    "wof:placetype":"venue"
},
  "geometry": {"coordinates":[-76.337926,38.961129],"type":"Point"}
}