{
  "type": "Feature",
  "properties": {
    "addr:full":"4703 Wissahican Ave Rockville MD 20853",
    "addr:housenumber":"4703",
    "addr:postcode":"20853",
    "addr:street":"Wissahican Ave",
    "iso:country":"US",
    "sg:address":"4703 Wissahican Ave",
    "sg:city":"Rockville",
    "sg:classifiers":[
        {
            "category":"Professional",
            "subcategory":"Management & Consulting",
            "type":"Services"
        }
    ],
    "sg:phone":"+1 301 946 0282",
    "sg:postcode":"20853",
    "sg:province":"MD",
    "sg:tags":[
        "consultant",
        "business"
    ],
    "wof:name":"Durant Associates Inc",
    "wof:placetype":"venue"
},
  "geometry": {"coordinates":[-77.096799,39.067569],"type":"Point"}
}