{
  "type": "Feature",
  "properties": {
    "iso:country":"US",
    "sg:address":"2 E Chase St Ms55",
    "sg:city":"Baltimore",
    "sg:classifiers":[
        {
            "category":"Insurance",
            "subcategory":"Insurance Agent",
            "type":"Services"
        },
        {
            "category":"Insurance",
            "subcategory":"Hazard Insurance",
            "type":"Services"
        }
    ],
    "sg:phone":"+1 410 385 6990",
    "sg:postcode":"21202",
    "sg:province":"MD",
    "sg:tags":[
        "fire",
        "property",
        "casualty"
    ],
    "wof:name":"Independent Mutual Fire Insurance Company (Il)",
    "wof:placetype":"venue"
},
  "geometry": {"coordinates":[-76.615959,39.302368],"type":"Point"}
}