{
  "type": "Feature",
  "properties": {
    "addr:full":"13243 Autumn Mist Cir Germantown MD 20874",
    "addr:housenumber":"13243",
    "addr:postcode":"20874",
    "addr:street":"Autumn Mist Cir",
    "iso:country":"US",
    "sg:address":"13243 Autumn Mist Cir",
    "sg:city":"Germantown",
    "sg:classifiers":[
        {
            "category":"Social Services",
            "type":"Services"
        }
    ],
    "sg:phone":"+1 301 916 9374",
    "sg:postcode":"20874",
    "sg:province":"MD",
    "wof:name":"Blong Elaine A Lcsw PA",
    "wof:placetype":"venue"
},
  "geometry": {"coordinates":[-77.27430099999999,39.161481],"type":"Point"}
}