{
  "type": "Feature",
  "properties": {
    "iso:country":"US",
    "sg:address":"2255 Crain Hwy",
    "sg:city":"Waldorf",
    "sg:classifiers":[
        {
            "category":"Professional",
            "subcategory":"Accounting & Tax Preparation",
            "type":"Services"
        }
    ],
    "sg:phone":"+1 301 870 7598",
    "sg:postcode":"20601",
    "sg:province":"MD",
    "sg:tags":[
        "accountant"
    ],
    "wof:name":"Satish P Shah CPA",
    "wof:placetype":"venue"
},
  "geometry": {"coordinates":[-76.887664,38.647861],"type":"Point"}
}