{
  "type": "Feature",
  "properties": {
    "addr:full":"1915 N Salisbury Blvd Salisbury MD 21801",
    "addr:housenumber":"1915",
    "addr:postcode":"21801",
    "addr:street":"N Salisbury Blvd",
    "iso:country":"US",
    "sg:address":"1915 N Salisbury Blvd",
    "sg:city":"Salisbury",
    "sg:classifiers":[
        {
            "category":"Shopping",
            "subcategory":"Bicycles & Sporting Goods",
            "type":"Retail Goods"
        }
    ],
    "sg:phone":"+1 410 742 3300",
    "sg:postcode":"21801",
    "sg:province":"MD",
    "sg:tags":[
        "equipment",
        "golf",
        "supply"
    ],
    "wof:name":"Chesapeake Golf",
    "wof:placetype":"venue"
},
  "geometry": {"coordinates":[-75.57831400000001,38.388936],"type":"Point"}
}