{
  "type": "Feature",
  "properties": {
    "addr:full":"15 E Frederick St Walkersville MD 21793",
    "addr:housenumber":"15",
    "addr:postcode":"21793",
    "addr:street":"E Frederick St",
    "iso:country":"US",
    "sg:address":"15 E Frederick St",
    "sg:city":"Walkersville",
    "sg:classifiers":[
        {
            "category":"Health Services",
            "subcategory":"Doctor",
            "type":"Services"
        }
    ],
    "sg:phone":"+1 301 898 5200",
    "sg:postcode":"21793",
    "sg:province":"MD",
    "sg:tags":[
        "physician",
        "surgeon"
    ],
    "wof:name":"Glade Valley Family Practice",
    "wof:placetype":"venue"
},
  "geometry": {"coordinates":[-77.348277,39.482935],"type":"Point"}
}