{
  "type": "Feature",
  "properties": {
    "addr:full":"2007 Paulette Rd Baltimore MD 21222",
    "addr:housenumber":"2007",
    "addr:postcode":"21222",
    "addr:street":"Paulette Rd",
    "iso:country":"US",
    "sg:address":"2007 Paulette Rd",
    "sg:city":"Baltimore",
    "sg:classifiers":[
        {
            "category":"Health Services",
            "subcategory":"Hospital",
            "type":"Services"
        },
        {
            "category":"Health Services",
            "subcategory":"Clinic",
            "type":"Services"
        }
    ],
    "sg:phone":"+1 410 477 6701",
    "sg:postcode":"21222",
    "sg:province":"MD",
    "sg:tags":[
        "mental",
        "outpatient",
        "specialty"
    ],
    "wof:name":"Key Point Inc",
    "wof:placetype":"venue"
},
  "geometry": {"coordinates":[-76.48485700000001,39.255315],"type":"Point"}
}