{
  "type": "Feature",
  "properties": {
    "addr:full":"Howard Ave & Montgomery Ave Kensington Train Station Lot Kensington MD 20891",
    "addr:postcode":"20891",
    "addr:street":"Howard;Montgomery Ave;Train",
    "iso:country":"US",
    "sg:address":"Howard Ave & Montgomery Ave Kensington Train Station Lot",
    "sg:city":"Kensington",
    "sg:classifiers":[
        {
            "category":"Food & Beverages",
            "subcategory":"Farmers Market",
            "type":"Retail Goods"
        }
    ],
    "sg:phone":"+1 301 949 2424",
    "sg:postcode":"20891",
    "sg:province":"MD",
    "wof:name":"Kensington Farmers Market",
    "wof:placetype":"venue"
},
  "geometry": {"coordinates":[-77.072197,39.02667],"type":"Point"}
}