{
  "type": "Feature",
  "properties": {
    "iso:country":"US",
    "sg:address":"8355 Blossom Point Rd",
    "sg:city":"Welcome",
    "sg:classifiers":[
        {
            "category":"Personal",
            "subcategory":"Beauty Salon",
            "type":"Services"
        }
    ],
    "sg:phone":"+1 301 392 3009",
    "sg:postcode":"20693",
    "sg:province":"MD",
    "wof:name":"Gracious Cuts",
    "wof:placetype":"venue"
},
  "geometry": {"coordinates":[-77.06891400000001,38.48289],"type":"Point"}
}