{
  "type": "Feature",
  "properties": {
    "iso:country":"US",
    "sg:address":"1211 N Boardwalk",
    "sg:city":"Ocean City",
    "sg:classifiers":[
        {
            "category":"Recreation",
            "type":"Entertainment"
        }
    ],
    "sg:phone":"+1 410 289 9485",
    "sg:postcode":"21842",
    "sg:province":"MD",
    "wof:name":"Accurate Inspection",
    "wof:placetype":"venue"
},
  "geometry": {"coordinates":[-75.078801,38.342806],"type":"Point"}
}