{
  "type": "Feature",
  "properties": {
    "iso:country":"US",
    "sg:address":"4903 Battery Ln Apt 3",
    "sg:city":"Bethesda",
    "sg:classifiers":[
        {
            "category":"Retail",
            "subcategory":"Repair Shop",
            "type":"Services"
        }
    ],
    "sg:phone":"+1 301 656 6819",
    "sg:postcode":"20814",
    "sg:province":"MD",
    "sg:tags":[
        "reupholstery",
        "furniture"
    ],
    "wof:name":"Mr Vinyl",
    "wof:placetype":"venue"
},
  "geometry": {"coordinates":[-77.09936500000001,38.992627],"type":"Point"}
}