{
  "type": "Feature",
  "properties": {
    "addr:full":"426 S Commerce St Centreville MD 21617",
    "addr:housenumber":"426",
    "addr:postcode":"21617",
    "addr:street":"S Commerce St",
    "iso:country":"US",
    "sg:address":"426 S Commerce St",
    "sg:city":"Centreville",
    "sg:classifiers":[
        {
            "category":"Autos & Motor Vehicles",
            "subcategory":"Fuel & Gas Station",
            "type":"Retail Goods"
        }
    ],
    "sg:phone":"+1 410 758 8570",
    "sg:postcode":"21617",
    "sg:province":"MD",
    "sg:tags":[
        "oil"
    ],
    "wof:name":"Jun's Centreville Citgo Inc",
    "wof:placetype":"venue"
},
  "geometry": {"coordinates":[-76.069287,39.040541],"type":"Point"}
}