{
  "type": "Feature",
  "properties": {
    "addr:full":"1076 Augustine Herman Hwy Elkton MD 21921",
    "addr:housenumber":"1076",
    "addr:postcode":"21921",
    "addr:street":"Augustine Herman Hwy",
    "iso:country":"US",
    "sg:address":"1076 Augustine Herman Hwy",
    "sg:city":"Elkton",
    "sg:classifiers":[
        {
            "category":"Banks & Credit Unions",
            "subcategory":"Bank",
            "type":"Services"
        }
    ],
    "sg:phone":"+1 410 620 4197",
    "sg:postcode":"21921",
    "sg:province":"MD",
    "sg:tags":[
        "loan",
        "real estate"
    ],
    "wof:name":"Destiny Home Mortgage",
    "wof:placetype":"venue"
},
  "geometry": {"coordinates":[-75.811567,39.567154],"type":"Point"}
}