{
  "type": "Feature",
  "properties": {
    "addr:full":"209 Cedarcroft Rd Baltimore MD 21212",
    "addr:housenumber":"209",
    "addr:postcode":"21212",
    "addr:street":"Cedarcroft Rd",
    "iso:country":"US",
    "sg:address":"209 Cedarcroft Rd",
    "sg:city":"Baltimore",
    "sg:classifiers":[
        {
            "category":"Wholesale",
            "subcategory":"Construction Materials",
            "type":"Manufacturing & Wholesale Goods"
        }
    ],
    "sg:phone":"+1 410 235 4584",
    "sg:postcode":"21212",
    "sg:province":"MD",
    "sg:tags":[
        "lumber"
    ],
    "wof:name":"Royal Lumber Co",
    "wof:placetype":"venue"
},
  "geometry": {"coordinates":[-76.61561399999999,39.369025],"type":"Point"}
}