{
  "type": "Feature",
  "properties": {
    "addr:full":"405 W Pennsylvania Ave Baltimore MD 21204",
    "addr:housenumber":"405",
    "addr:postcode":"21204",
    "addr:street":"W Pennsylvania Ave",
    "iso:country":"US",
    "sg:address":"405 W Pennsylvania Ave",
    "sg:city":"Baltimore",
    "sg:classifiers":[
        {
            "category":"Professional",
            "subcategory":"Lawyer & Legal Services",
            "type":"Services"
        }
    ],
    "sg:phone":"+1 410 321 0818",
    "sg:postcode":"21204",
    "sg:province":"MD",
    "sg:tags":[
        "law"
    ],
    "wof:name":"Barnes Clay M",
    "wof:placetype":"venue"
},
  "geometry": {"coordinates":[-76.60998600000001,39.401157],"type":"Point"}
}