{
  "type": "Feature",
  "properties": {
    "iso:country":"US",
    "sg:address":"4312 Puller Dr",
    "sg:city":"Kensington",
    "sg:classifiers":[
        {
            "category":"Real Estate",
            "subcategory":"Real Estate Agent",
            "type":"Services"
        }
    ],
    "sg:phone":"+1 301 897 2000",
    "sg:postcode":"20895",
    "sg:province":"MD",
    "sg:tags":[
        "appraiser"
    ],
    "wof:name":"Donnelly & Associates",
    "wof:placetype":"venue"
},
  "geometry": {"coordinates":[-77.08466199999999,39.024525],"type":"Point"}
}