{
  "type": "Feature",
  "properties": {
    "addr:full":"17 Neerwinder Ct Germantown MD 20874",
    "addr:housenumber":"17",
    "addr:postcode":"20874",
    "addr:street":"Neerwinder Ct",
    "iso:country":"US",
    "sg:address":"17 Neerwinder Ct",
    "sg:city":"Germantown",
    "sg:classifiers":[
        {
            "category":"Building & Trades",
            "subcategory":"Construction",
            "type":"Services"
        }
    ],
    "sg:phone":"+1 301 972 1068",
    "sg:postcode":"20874",
    "sg:province":"MD",
    "sg:tags":[
        "house",
        "contractor",
        "roofing"
    ],
    "wof:name":"W T Michael Construction Inc",
    "wof:placetype":"venue"
},
  "geometry": {"coordinates":[-77.27825799999999,39.194586],"type":"Point"}
}