{
  "type": "Feature",
  "properties": {
    "iso:country":"US",
    "sg:address":"5246 Harford Rd",
    "sg:city":"Baltimore",
    "sg:classifiers":[
        {
            "category":"Building & Trades",
            "subcategory":"Locksmith",
            "type":"Services"
        }
    ],
    "sg:phone":"+1 443 378 3414",
    "sg:postcode":"21214",
    "sg:province":"MD",
    "sg:tags":[
        "key"
    ],
    "wof:name":"Locksmith Available",
    "wof:placetype":"venue"
},
  "geometry": {"coordinates":[-76.563768,39.349801],"type":"Point"}
}