{
  "type": "Feature",
  "properties": {
    "iso:country":"US",
    "sg:address":"20951 Great Mills Rd",
    "sg:city":"Lexington Park",
    "sg:classifiers":[
        {
            "category":"Personal",
            "subcategory":"Beauty Salon",
            "type":"Services"
        }
    ],
    "sg:phone":"+1 301 866 0088",
    "sg:postcode":"20653",
    "sg:province":"MD",
    "wof:name":"Eve A Lution Micro Spa",
    "wof:placetype":"venue"
},
  "geometry": {"coordinates":[-76.49130700000001,38.244329],"type":"Point"}
}