{
  "type": "Feature",
  "properties": {
    "iso:country":"US",
    "sg:address":"1114 Hendrix Ct",
    "sg:city":"Bel Air",
    "sg:classifiers":[
        {
            "category":"Shopping",
            "subcategory":"Used Merchandise",
            "type":"Retail Goods"
        }
    ],
    "sg:phone":"+1 410 838 8347",
    "sg:postcode":"21014",
    "sg:province":"MD",
    "wof:name":"Spenceola Antiques",
    "wof:placetype":"venue"
},
  "geometry": {"coordinates":[-76.33774099999999,39.545091],"type":"Point"}
}