{
  "type": "Feature",
  "properties": {
    "iso:country":"US",
    "sg:address":"7340 Greenbank Rd",
    "sg:city":"Baltimore",
    "sg:classifiers":[
        {
            "category":"Recreation",
            "type":"Entertainment"
        }
    ],
    "sg:phone":"+1 410 335 5352",
    "sg:postcode":"21220",
    "sg:province":"MD",
    "sg:tags":[
        "riding",
        "academy"
    ],
    "wof:name":"Baltimore Boardsailing Academy",
    "wof:placetype":"venue"
},
  "geometry": {"coordinates":[-76.34230100000001,39.37375],"type":"Point"}
}