{
  "type": "Feature",
  "properties": {
    "addr:full":"2201 Eastern Blvd Ste E Middle River MD 21220",
    "addr:housenumber":"2201",
    "addr:postcode":"21220",
    "addr:street":"Eastern Blvd Ste E",
    "iso:country":"US",
    "sg:address":"2201 Eastern Blvd Ste E",
    "sg:city":"Middle River",
    "sg:classifiers":[
        {
            "category":"Restaurant",
            "type":"Food & Drink"
        },
        {
            "category":"Food & Beverages",
            "subcategory":"Groceries & Convenience Stores",
            "type":"Retail Goods"
        }
    ],
    "sg:phone":"+1 410 780 9323",
    "sg:postcode":"21220",
    "sg:province":"MD",
    "wof:name":"All African Delights",
    "wof:placetype":"venue"
},
  "geometry": {"coordinates":[-76.439796,39.3297],"type":"Point"}
}