{
  "type": "Feature",
  "properties": {
    "iso:country":"US",
    "sg:address":"2433 Coon Club Rd",
    "sg:city":"Westminster",
    "sg:classifiers":[
        {
            "category":"Building & Trades",
            "subcategory":"Landscaping Services",
            "type":"Services"
        }
    ],
    "sg:phone":"+1 410 876 5700",
    "sg:postcode":"21157",
    "sg:province":"MD",
    "sg:tags":[
        "landscape",
        "contractor"
    ],
    "wof:name":"CLS Professional Lawn Care",
    "wof:placetype":"venue"
},
  "geometry": {"coordinates":[-76.908786,39.586469],"type":"Point"}
}