{
  "type": "Feature",
  "properties": {
    "addr:full":"211 24th St Westminster MD 21157",
    "addr:housenumber":"211",
    "addr:postcode":"21157",
    "addr:street":"24Th St",
    "iso:country":"US",
    "sg:address":"211 24th St",
    "sg:city":"Westminster",
    "sg:classifiers":[
        {
            "category":"Manufacturing",
            "subcategory":"Metals",
            "type":"Manufacturing & Wholesale Goods"
        },
        {
            "category":"Manufacturing",
            "subcategory":"Building Materials",
            "type":"Manufacturing & Wholesale Goods"
        }
    ],
    "sg:phone":"+1 410 751 5481",
    "sg:postcode":"21157",
    "sg:province":"MD",
    "sg:tags":[
        "work-manufacturers",
        "fabricator",
        "work",
        "sheet"
    ],
    "wof:name":"R & M Manufacturing, Inc",
    "wof:placetype":"venue"
},
  "geometry": {"coordinates":[-76.985727,39.567493],"type":"Point"}
}