{
  "type": "Feature",
  "properties": {
    "iso:country":"US",
    "sg:address":"5505 Randolph Rd",
    "sg:city":"Rockville",
    "sg:classifiers":[
        {
            "category":"Retail",
            "subcategory":"Auto Repair",
            "type":"Services"
        }
    ],
    "sg:phone":"+1 301 881 8686",
    "sg:postcode":"20852",
    "sg:province":"MD",
    "sg:website":"www.randolphmotors.com",
    "wof:name":"Randolph Motors",
    "wof:placetype":"venue"
},
  "geometry": {"coordinates":[-77.111099,39.0532],"type":"Point"}
}