{
  "type": "Feature",
  "properties": {
    "addr:full":"39 Great Pines Ct Rockville MD 20850",
    "addr:housenumber":"39",
    "addr:postcode":"20850",
    "addr:street":"Great Pines Ct",
    "iso:country":"US",
    "sg:address":"39 Great Pines Ct",
    "sg:city":"Rockville",
    "sg:classifiers":[
        {
            "category":"Professional",
            "subcategory":"Business Services",
            "type":"Services"
        }
    ],
    "sg:phone":"+1 301 838 9289",
    "sg:postcode":"20850",
    "sg:province":"MD",
    "wof:name":"Cadenza Decorative Pntg Studio",
    "wof:placetype":"venue"
},
  "geometry": {"coordinates":[-77.18234699999999,39.086316],"type":"Point"}
}