{
  "type": "Feature",
  "properties": {
    "iso:country":"US",
    "sg:address":"4311 Havelock Rd",
    "sg:city":"Lanham",
    "sg:classifiers":[
        {
            "category":"Wholesale",
            "subcategory":"Apparel",
            "type":"Manufacturing & Wholesale Goods"
        }
    ],
    "sg:phone":"+1 301 918 1300",
    "sg:postcode":"20706",
    "sg:province":"MD",
    "sg:tags":[
        "fabric"
    ],
    "wof:name":"International Trading Co",
    "wof:placetype":"venue"
},
  "geometry": {"coordinates":[-76.851296,38.951184],"type":"Point"}
}