{
  "type": "Feature",
  "properties": {
    "addr:full":"22 E Fayette St Baltimore MD 21231",
    "addr:housenumber":"22",
    "addr:postcode":"21231",
    "addr:street":"E Fayette St",
    "iso:country":"US",
    "sg:address":"22 E Fayette St",
    "sg:city":"Baltimore",
    "sg:classifiers":[
        {
            "category":"Professional",
            "subcategory":"Lawyer & Legal Services",
            "type":"Services"
        }
    ],
    "sg:phone":"+1 410 244 0354",
    "sg:postcode":"21231",
    "sg:province":"MD",
    "sg:tags":[
        "attorney"
    ],
    "wof:name":"David F Albright",
    "wof:placetype":"venue"
},
  "geometry": {"coordinates":[-76.614126,39.290552],"type":"Point"}
}