{
  "type": "Feature",
  "properties": {
    "iso:country":"US",
    "sg:address":"11800 Nebel St",
    "sg:city":"Rockville",
    "sg:classifiers":[
        {
            "category":"Health Services",
            "subcategory":"Clinic",
            "type":"Services"
        }
    ],
    "sg:phone":"+1 301 468 3221",
    "sg:postcode":"20852",
    "sg:province":"MD",
    "sg:tags":[
        "kidney",
        "dialysis",
        "center"
    ],
    "wof:name":"DCA Of Rockville",
    "wof:placetype":"venue"
},
  "geometry": {"coordinates":[-77.106345,39.048803],"type":"Point"}
}