{
  "type": "Feature",
  "properties": {
    "iso:country":"US",
    "sg:address":"7401 Westlake Ter",
    "sg:city":"Bethesda",
    "sg:classifiers":[
        {
            "category":"Personal",
            "subcategory":"Adult",
            "type":"Services"
        }
    ],
    "sg:phone":"+1 240 463 7754",
    "sg:postcode":"20817",
    "sg:province":"MD",
    "sg:tags":[
        "escort"
    ],
    "wof:name":"Exquisite Escort",
    "wof:placetype":"venue"
},
  "geometry": {"coordinates":[-77.148815,39.027525],"type":"Point"}
}