{
  "type": "Feature",
  "properties": {
    "addr:full":"3872 Jefferson Pike Jefferson MD 21755",
    "addr:housenumber":"3872",
    "addr:postcode":"21755",
    "addr:street":"Jefferson Pike",
    "iso:country":"US",
    "sg:address":"3872 Jefferson Pike",
    "sg:city":"Jefferson",
    "sg:classifiers":[
        {
            "category":"Shopping",
            "subcategory":"Florist",
            "type":"Retail Goods"
        }
    ],
    "sg:phone":"+1 301 473 8330",
    "sg:postcode":"21755",
    "sg:province":"MD",
    "sg:website":"www.adrienne.com",
    "wof:name":"Adrienne's Flower Delights",
    "wof:placetype":"venue"
},
  "geometry": {"coordinates":[-77.53330200000001,39.361801],"type":"Point"}
}