{
  "type": "Feature",
  "properties": {
    "iso:country":"US",
    "sg:address":"7241 Hanover Pkwy",
    "sg:city":"Greenbelt",
    "sg:classifiers":[
        {
            "category":"Professional",
            "subcategory":"Accounting & Tax Preparation",
            "type":"Services"
        }
    ],
    "sg:phone":"+1 301 345 3450",
    "sg:postcode":"20770",
    "sg:province":"MD",
    "sg:tags":[
        "accountant"
    ],
    "wof:name":"Hetrick & Assoc",
    "wof:placetype":"venue"
},
  "geometry": {"coordinates":[-76.87820600000001,38.989294],"type":"Point"}
}