{
  "type": "Feature",
  "properties": {
    "iso:country":"US",
    "sg:address":"10689 Owen Brown Rd",
    "sg:city":"Columbia",
    "sg:classifiers":[
        {
            "category":"Organizations",
            "subcategory":"Religious Organization",
            "type":"Services"
        }
    ],
    "sg:phone":"+1 410 772 6396",
    "sg:postcode":"21044",
    "sg:province":"MD",
    "sg:tags":[
        "church"
    ],
    "wof:name":"Iglesia De Dios Pentecostal Mi",
    "wof:placetype":"venue"
},
  "geometry": {"coordinates":[-76.884072,39.198324],"type":"Point"}
}