{
  "type": "Feature",
  "properties": {
    "iso:country":"US",
    "sg:address":"14100 Darnestown Rd",
    "sg:city":"Germantown",
    "sg:classifiers":[
        {
            "category":"Retail",
            "subcategory":"Laundry & Dry Cleaning",
            "type":"Services"
        }
    ],
    "sg:phone":"+1 301 869 5400",
    "sg:postcode":"20874",
    "sg:province":"MD",
    "sg:tags":[
        "cleaners"
    ],
    "wof:name":"Secco Plus Cleaners Corp",
    "wof:placetype":"venue"
},
  "geometry": {"coordinates":[-77.29177,39.103263],"type":"Point"}
}