{
  "type": "Feature",
  "properties": {
    "iso:country":"US",
    "sg:address":"903 Baltimore Pike",
    "sg:city":"Bel Air",
    "sg:classifiers":[
        {
            "category":"Building & Trades",
            "subcategory":"Construction",
            "type":"Services"
        }
    ],
    "sg:phone":"+1 410 879 9235",
    "sg:postcode":"21014",
    "sg:province":"MD",
    "sg:tags":[
        "home",
        "improvement"
    ],
    "wof:name":"Burke Construction Co",
    "wof:placetype":"venue"
},
  "geometry": {"coordinates":[-76.365126,39.516887],"type":"Point"}
}