{
  "type": "Feature",
  "properties": {
    "addr:full":"806 Rockville Pike Rockville MD 20852",
    "addr:housenumber":"806",
    "addr:postcode":"20852",
    "addr:street":"Rockville Pike",
    "iso:country":"US",
    "sg:address":"806 Rockville Pike",
    "sg:city":"Rockville",
    "sg:classifiers":[
        {
            "category":"Autos & Motor Vehicles",
            "subcategory":"Auto Supplies",
            "type":"Retail Goods"
        },
        {
            "category":"Retail",
            "subcategory":"Auto Repair",
            "type":"Services"
        }
    ],
    "sg:phone":"+1 301 424 9531",
    "sg:postcode":"20852",
    "sg:province":"MD",
    "sg:tags":[
        "oil",
        "automotive",
        "automobile",
        "lube",
        "equipment-service",
        "air conditioning",
        "tune"
    ],
    "sg:website":"http://www.jiffylube.com",
    "wof:name":"Jiffy Lube",
    "wof:placetype":"venue"
},
  "geometry": {"coordinates":[-77.13854000000001,39.076558],"type":"Point"}
}