{
  "type": "Feature",
  "properties": {
    "iso:country":"US",
    "sg:address":"6701 Democracy Blvd",
    "sg:city":"Bethesda",
    "sg:classifiers":[
        {
            "category":"Real Estate",
            "subcategory":"Real Estate Services",
            "type":"Services"
        }
    ],
    "sg:phone":"+1 301 530 5246",
    "sg:postcode":"20817",
    "sg:province":"MD",
    "sg:tags":[
        "management",
        "property"
    ],
    "wof:name":"Jones Lang Lasalle",
    "wof:placetype":"venue"
},
  "geometry": {"coordinates":[-77.136349,39.021875],"type":"Point"}
}