{
  "type": "Feature",
  "properties": {
    "iso:country":"US",
    "sg:address":"8118 Harford Rd",
    "sg:city":"Baltimore",
    "sg:classifiers":[
        {
            "category":"Professional",
            "subcategory":"Computer Services",
            "type":"Services"
        }
    ],
    "sg:phone":"+1 410 665 3400",
    "sg:postcode":"21234",
    "sg:province":"MD",
    "sg:tags":[
        "repair"
    ],
    "sg:website":"www.computerrestoration.com",
    "wof:name":"Computer Restoration Svc",
    "wof:placetype":"venue"
},
  "geometry": {"coordinates":[-76.539489,39.377841],"type":"Point"}
}