{
  "type": "Feature",
  "properties": {
    "iso:country":"US",
    "sg:address":"1300 Smallwood Dr W",
    "sg:city":"Waldorf",
    "sg:classifiers":[
        {
            "category":"Shopping",
            "subcategory":"Stationery & Office Supplies",
            "type":"Retail Goods"
        }
    ],
    "sg:phone":"+1 301 632 2882",
    "sg:postcode":"20603",
    "sg:province":"MD",
    "sg:tags":[
        "educational",
        "material"
    ],
    "wof:name":"Educate & Celebrate Inc",
    "wof:placetype":"venue"
},
  "geometry": {"coordinates":[-76.926958,38.612675],"type":"Point"}
}