{
  "type": "Feature",
  "properties": {
    "addr:full":"10161 New Hampshire Ave Silver Spring MD 20903",
    "addr:housenumber":"10161",
    "addr:postcode":"20903",
    "addr:street":"New Hampshire Ave",
    "iso:country":"US",
    "sg:address":"10161 New Hampshire Ave",
    "sg:city":"Silver Spring",
    "sg:classifiers":[
        {
            "category":"Shopping",
            "subcategory":"Computers & Home Electronics",
            "type":"Retail Goods"
        }
    ],
    "sg:phone":"+1 301 439 6588",
    "sg:postcode":"20903",
    "sg:province":"MD",
    "sg:tags":[
        "equipment",
        "electronic",
        "supply"
    ],
    "wof:name":"Radio Shack",
    "wof:placetype":"venue"
},
  "geometry": {"coordinates":[-76.977296,39.022086],"type":"Point"}
}