{
  "type": "Feature",
  "properties": {
    "addr:full":"1265 Maryland Ave Hagerstown MD 21740",
    "addr:housenumber":"1265",
    "addr:postcode":"21740",
    "addr:street":"Maryland Ave",
    "iso:country":"US",
    "sg:address":"1265 Maryland Ave",
    "sg:city":"Hagerstown",
    "sg:classifiers":[
        {
            "category":"Railroad",
            "type":"Transportation"
        }
    ],
    "sg:phone":"+1 301 791 8964",
    "sg:postcode":"21740",
    "sg:province":"MD",
    "wof:name":"Norfolk Southern Railway Co",
    "wof:placetype":"venue"
},
  "geometry": {"coordinates":[-77.739524,39.615324],"type":"Point"}
}