{
  "type": "Feature",
  "properties": {
    "iso:country":"US",
    "sg:address":"3712 Gough St",
    "sg:city":"Baltimore",
    "sg:classifiers":[
        {
            "category":"Education",
            "subcategory":"Junior College",
            "type":"Public Place"
        }
    ],
    "sg:phone":"+1 443 742 1262",
    "sg:postcode":"21224",
    "sg:province":"MD",
    "sg:tags":[
        "doll"
    ],
    "wof:name":"Diva Dolls S/C Ltd",
    "wof:placetype":"venue"
},
  "geometry": {"coordinates":[-76.56646499999999,39.288673],"type":"Point"}
}