{
  "type": "Feature",
  "properties": {
    "iso:country":"US",
    "sg:address":"402 Frederick Rd",
    "sg:city":"Catonsville",
    "sg:classifiers":[
        {
            "category":"Personal",
            "subcategory":"Beauty Salon",
            "type":"Services"
        }
    ],
    "sg:phone":"+1 410 788 5644",
    "sg:postcode":"21228",
    "sg:province":"MD",
    "sg:website":"http://www.perfecttouchhair.com",
    "wof:name":"Perfect Touch Hair Salon & Day Spa",
    "wof:placetype":"venue"
},
  "geometry": {"coordinates":[-76.726406,39.273147],"type":"Point"}
}