{
  "type": "Feature",
  "properties": {
    "iso:country":"US",
    "sg:address":"18901 Blue Heron Ln",
    "sg:city":"Gaithersburg",
    "sg:classifiers":[
        {
            "category":"Professional",
            "subcategory":"Computer Services",
            "type":"Services"
        }
    ],
    "sg:phone":"+1 301 977 5182",
    "sg:postcode":"20879",
    "sg:province":"MD",
    "sg:tags":[
        "prepackaged",
        "software"
    ],
    "wof:name":"Software Applications Corp",
    "wof:placetype":"venue"
},
  "geometry": {"coordinates":[-77.181991,39.168292],"type":"Point"}
}