{
  "type": "Feature",
  "properties": {
    "iso:country":"US",
    "sg:address":"3240 Holland Cliffs Rd",
    "sg:city":"Huntingtown",
    "sg:classifiers":[
        {
            "category":"Professional",
            "subcategory":"Management & Consulting",
            "type":"Services"
        }
    ],
    "sg:phone":"+1 410 535 3713",
    "sg:postcode":"20639",
    "sg:province":"MD",
    "sg:tags":[
        "consultant",
        "business"
    ],
    "wof:name":"Robertson & Assoc Inc",
    "wof:placetype":"venue"
},
  "geometry": {"coordinates":[-76.667292,38.606323],"type":"Point"}
}