{
  "type": "Feature",
  "properties": {
    "addr:full":"507 West Dr Severna Park MD 21146",
    "addr:housenumber":"507",
    "addr:postcode":"21146",
    "addr:street":"West Dr",
    "iso:country":"US",
    "sg:address":"507 West Dr",
    "sg:city":"Severna Park",
    "sg:classifiers":[
        {
            "category":"Health Services",
            "subcategory":"Doctor",
            "type":"Services"
        }
    ],
    "sg:phone":"+1 410 647 4403",
    "sg:postcode":"21146",
    "sg:province":"MD",
    "sg:tags":[
        "physician",
        "surgeon"
    ],
    "wof:name":"Kenneth E Fligsten's Office",
    "wof:placetype":"venue"
},
  "geometry": {"coordinates":[-76.58473499999999,39.079174],"type":"Point"}
}