{
  "type": "Feature",
  "properties": {
    "iso:country":"US",
    "sg:address":"7939 Queenair Dr",
    "sg:city":"Gaithersburg",
    "sg:classifiers":[
        {
            "category":"Wholesale",
            "subcategory":"Electrical",
            "type":"Manufacturing & Wholesale Goods"
        }
    ],
    "sg:phone":"+1 301 840 0623",
    "sg:postcode":"20879",
    "sg:province":"MD",
    "sg:tags":[
        "battery"
    ],
    "wof:name":"American Battery Corp",
    "wof:placetype":"venue"
},
  "geometry": {"coordinates":[-77.161858,39.170044],"type":"Point"}
}