{
  "type": "Feature",
  "properties": {
    "iso:country":"US",
    "sg:address":"617 E 29th St",
    "sg:city":"Baltimore",
    "sg:classifiers":[
        {
            "category":"Organizations",
            "subcategory":"Religious Organization",
            "type":"Services"
        }
    ],
    "sg:phone":"+1 410 338 1623",
    "sg:postcode":"21218",
    "sg:province":"MD",
    "sg:tags":[
        "clergy"
    ],
    "wof:name":"L L Baylor Rev",
    "wof:placetype":"venue"
},
  "geometry": {"coordinates":[-76.608352,39.323759],"type":"Point"}
}