{
  "type": "Feature",
  "properties": {
    "iso:country":"US",
    "sg:address":"403 Compass Rd E",
    "sg:city":"Baltimore",
    "sg:classifiers":[
        {
            "category":"Government",
            "subcategory":"Office",
            "type":"Public Place"
        }
    ],
    "sg:phone":"+1 410 887 0235",
    "sg:postcode":"21220",
    "sg:province":"MD",
    "wof:name":"Victory Villa Senior Ctr",
    "wof:placetype":"venue"
},
  "geometry": {"coordinates":[-76.45588499999999,39.33788],"type":"Point"}
}