{
  "type": "Feature",
  "properties": {
    "addr:full":"2600 Queens Chapel Rd # 703 Hyattsville MD 20782",
    "addr:housenumber":"2600",
    "addr:postcode":"20782",
    "addr:street":"Queens Chapel Rd # 703",
    "iso:country":"US",
    "sg:address":"2600 Queens Chapel Rd # 703",
    "sg:city":"Hyattsville",
    "sg:classifiers":[
        {
            "category":"Place Of Worship",
            "type":"Public Place"
        }
    ],
    "sg:phone":"+1 301 927 6744",
    "sg:postcode":"20782",
    "sg:province":"MD",
    "sg:tags":[
        "church"
    ],
    "wof:name":"Brauer Micheal Theresa Sister",
    "wof:placetype":"venue"
},
  "geometry": {"coordinates":[-76.969948,38.948231],"type":"Point"}
}