{
  "type": "Feature",
  "properties": {
    "iso:country":"US",
    "sg:address":"402 York Rd",
    "sg:city":"Baltimore",
    "sg:classifiers":[
        {
            "category":"Shopping",
            "subcategory":"Clothing, Apparel, & Fashions",
            "type":"Retail Goods"
        }
    ],
    "sg:phone":"+1 410 825 2055",
    "sg:postcode":"21204",
    "sg:province":"MD",
    "sg:tags":[
        "lingerie"
    ],
    "wof:name":"Love Ones Lingerie & Gift Ctr",
    "wof:placetype":"venue"
},
  "geometry": {"coordinates":[-76.60251,39.400481],"type":"Point"}
}