{
  "type": "Feature",
  "properties": {
    "addr:full":"8 Council Dr Woodsboro MD 21798",
    "addr:housenumber":"8",
    "addr:postcode":"21798",
    "addr:street":"Council Dr",
    "iso:country":"US",
    "sg:address":"8 Council Dr",
    "sg:city":"Woodsboro",
    "sg:classifiers":[
        {
            "category":"Retail",
            "subcategory":"Auto Repair",
            "type":"Services"
        }
    ],
    "sg:phone":"+1 301 898 9300",
    "sg:postcode":"21798",
    "sg:province":"MD",
    "sg:tags":[
        "repairing",
        "automobile"
    ],
    "wof:name":"Gumption Enterprises",
    "wof:placetype":"venue"
},
  "geometry": {"coordinates":[-77.306117,39.528387],"type":"Point"}
}