{
  "type": "Feature",
  "properties": {
    "iso:country":"US",
    "sg:address":"5704 Dimes Rd",
    "sg:city":"Derwood",
    "sg:classifiers":[
        {
            "category":"Wholesale",
            "subcategory":"Computers",
            "type":"Manufacturing & Wholesale Goods"
        }
    ],
    "sg:phone":"+1 301 838 8928",
    "sg:postcode":"20855",
    "sg:province":"MD",
    "sg:tags":[
        "peripheral",
        "software"
    ],
    "wof:name":"S&B Sales Inc",
    "wof:placetype":"venue"
},
  "geometry": {"coordinates":[-77.120023,39.109316],"type":"Point"}
}