{
  "type": "Feature",
  "properties": {
    "addr:full":"2113 Bay Dr Annapolis MD 21409",
    "addr:housenumber":"2113",
    "addr:postcode":"21409",
    "addr:street":"Bay Dr",
    "iso:country":"US",
    "sg:address":"2113 Bay Dr",
    "sg:city":"Annapolis",
    "sg:classifiers":[
        {
            "category":"Ice Cream",
            "type":"Food & Drink"
        }
    ],
    "sg:phone":"+1 410 349 9256",
    "sg:postcode":"21409",
    "sg:province":"MD",
    "sg:tags":[
        "frozen",
        "dessert"
    ],
    "wof:name":"Chateau Sorbet",
    "wof:placetype":"venue"
},
  "geometry": {"coordinates":[-76.40450300000001,39.029542],"type":"Point"}
}