{
  "type": "Feature",
  "properties": {
    "addr:full":"10114 Brock Dr Silver Spring MD 20903",
    "addr:housenumber":"10114",
    "addr:postcode":"20903",
    "addr:street":"Brock Dr",
    "iso:country":"US",
    "sg:address":"10114 Brock Dr",
    "sg:city":"Silver Spring",
    "sg:classifiers":[
        {
            "category":"Professional",
            "subcategory":"Management & Consulting",
            "type":"Services"
        }
    ],
    "sg:phone":"+1 301 439 4917",
    "sg:postcode":"20903",
    "sg:province":"MD",
    "wof:name":"Ethel Briggs & Consultants",
    "wof:placetype":"venue"
},
  "geometry": {"coordinates":[-76.989831,39.021415],"type":"Point"}
}