{
  "type": "Feature",
  "properties": {
    "iso:country":"US",
    "sg:address":"2303 Eagle Rock Pl",
    "sg:city":"Silver Spring",
    "sg:classifiers":[
        {
            "category":"Professional",
            "type":"Services"
        }
    ],
    "sg:phone":"+1 301 603 0967",
    "sg:postcode":"20906",
    "sg:province":"MD",
    "wof:name":"Municipality Implementatin Svc",
    "wof:placetype":"venue"
},
  "geometry": {"coordinates":[-77.050062,39.07472],"type":"Point"}
}