{
  "type": "Feature",
  "properties": {
    "iso:country":"US",
    "sg:address":"182 Thomas Johnson Dr",
    "sg:city":"Frederick",
    "sg:classifiers":[
        {
            "category":"Professional",
            "subcategory":"Management & Consulting",
            "type":"Services"
        }
    ],
    "sg:phone":"+1 301 682 8045",
    "sg:postcode":"21702",
    "sg:province":"MD",
    "sg:tags":[
        "engineering"
    ],
    "wof:name":"J Omega Systems L L C",
    "wof:placetype":"venue"
},
  "geometry": {"coordinates":[-77.406268,39.442251],"type":"Point"}
}