{
  "type": "Feature",
  "properties": {
    "iso:country":"US",
    "sg:address":"125 Kemp Ln",
    "sg:city":"Easton",
    "sg:classifiers":[
        {
            "category":"Manufacturing",
            "subcategory":"Paper Products",
            "type":"Manufacturing & Wholesale Goods"
        }
    ],
    "sg:phone":"+1 410 763 6780",
    "sg:postcode":"21601",
    "sg:province":"MD",
    "sg:tags":[
        "stationery",
        "prod"
    ],
    "wof:name":"International Golf Art Inc",
    "wof:placetype":"venue"
},
  "geometry": {"coordinates":[-76.06709499999999,38.771578],"type":"Point"}
}