{
  "type": "Feature",
  "properties": {
    "addr:full":"11685 Doolittle Dr Waldorf MD 20602",
    "addr:housenumber":"11685",
    "addr:postcode":"20602",
    "addr:street":"Doolittle Dr",
    "iso:country":"US",
    "sg:address":"11685 Doolittle Dr",
    "sg:city":"Waldorf",
    "sg:classifiers":[
        {
            "category":"Retail",
            "subcategory":"Veterinary Services",
            "type":"Services"
        }
    ],
    "sg:phone":"+1 888 836 6298",
    "sg:postcode":"20602",
    "sg:province":"MD",
    "sg:tags":[
        "clinic",
        "veterinarian",
        "hospital"
    ],
    "sg:website":"http://local.ingenio.com/Listings/Details.aspx?NUM=a%3a9244353%3a13%3a4859924%3a14%3a0%3a7",
    "wof:name":"St Charles Animal Hosp",
    "wof:placetype":"venue"
},
  "geometry": {"coordinates":[-76.905755,38.611398],"type":"Point"}
}