{
  "type": "Feature",
  "properties": {
    "iso:country":"US",
    "sg:address":"18720 Bloomfield Rd",
    "sg:city":"Olney",
    "sg:classifiers":[
        {
            "category":"Building & Trades",
            "subcategory":"Landscaping Services",
            "type":"Services"
        }
    ],
    "sg:phone":"+1 301 570 1954",
    "sg:postcode":"20832",
    "sg:province":"MD",
    "sg:tags":[
        "lawn",
        "maintenance",
        "grounds"
    ],
    "wof:name":"Planet Green",
    "wof:placetype":"venue"
},
  "geometry": {"coordinates":[-77.074665,39.164241],"type":"Point"}
}