{
  "type": "Feature",
  "properties": {
    "addr:full":"5740 Executive Dr Catonsville MD 21228",
    "addr:housenumber":"5740",
    "addr:postcode":"21228",
    "addr:street":"Executive Dr",
    "iso:country":"US",
    "sg:address":"5740 Executive Dr",
    "sg:city":"Catonsville",
    "sg:classifiers":[
        {
            "category":"Professional",
            "subcategory":"Research",
            "type":"Services"
        }
    ],
    "sg:phone":"+1 410 744 2154",
    "sg:postcode":"21228",
    "sg:province":"MD",
    "sg:tags":[
        "market",
        "analysis"
    ],
    "wof:name":"International Guidelines",
    "wof:placetype":"venue"
},
  "geometry": {"coordinates":[-76.731449,39.283654],"type":"Point"}
}