{
  "type": "Feature",
  "properties": {
    "iso:country":"US",
    "sg:address":"529 Walker Ave",
    "sg:city":"Baltimore",
    "sg:classifiers":[
        {
            "category":"Place Of Worship",
            "type":"Public Place"
        },
        {
            "category":"Education",
            "subcategory":"School",
            "type":"Public Place"
        },
        {
            "category":"Education",
            "subcategory":"University",
            "type":"Public Place"
        }
    ],
    "sg:phone":"+1 410 323 6211",
    "sg:postcode":"21212",
    "sg:province":"MD",
    "sg:tags":[
        "religious",
        "college",
        "interest",
        "church"
    ],
    "sg:website":"http://www.faiththeological.org",
    "wof:name":"Faith Theological Seminary",
    "wof:placetype":"venue"
},
  "geometry": {"coordinates":[-76.607085,39.371649],"type":"Point"}
}