{
  "type": "Feature",
  "properties": {
    "addr:full":"8514 Portsmouth Dr Laurel MD 20708",
    "addr:housenumber":"8514",
    "addr:postcode":"20708",
    "addr:street":"Portsmouth Dr",
    "iso:country":"US",
    "sg:address":"8514 Portsmouth Dr",
    "sg:city":"Laurel",
    "sg:classifiers":[
        {
            "category":"Building & Trades",
            "subcategory":"Electrical",
            "type":"Services"
        }
    ],
    "sg:phone":"+1 301 953 1953",
    "sg:postcode":"20708",
    "sg:province":"MD",
    "sg:tags":[
        "electrician",
        "electric",
        "contractor"
    ],
    "wof:name":"Best Electric Co",
    "wof:placetype":"venue"
},
  "geometry": {"coordinates":[-76.8582,39.071701],"type":"Point"}
}