{
  "type": "Feature",
  "properties": {
    "iso:country":"US",
    "sg:address":"17 E Brook Hill Ct",
    "sg:city":"Bel Air",
    "sg:classifiers":[
        {
            "category":"Organizations",
            "subcategory":"Religious Organization",
            "type":"Services"
        }
    ],
    "sg:phone":"+1 443 643 9004",
    "sg:postcode":"21014",
    "sg:province":"MD",
    "sg:tags":[
        "clergy"
    ],
    "wof:name":"Steve Nam",
    "wof:placetype":"venue"
},
  "geometry": {"coordinates":[-76.324512,39.52629],"type":"Point"}
}