{
  "type": "Feature",
  "properties": {
    "iso:country":"US",
    "sg:address":"145 Chesapeake Mobile Ct",
    "sg:city":"Hanover",
    "sg:classifiers":[
        {
            "category":"Shopping",
            "subcategory":"Florist",
            "type":"Retail Goods"
        }
    ],
    "sg:phone":"+1 410 850 0317",
    "sg:postcode":"21076",
    "sg:province":"MD",
    "wof:name":"Dorothy Ellen Scott-Wright",
    "wof:placetype":"venue"
},
  "geometry": {"coordinates":[-76.716358,39.14885],"type":"Point"}
}