{
  "type": "Feature",
  "properties": {
    "addr:full":"2710 Bartol Ave Baltimore MD 21209",
    "addr:housenumber":"2710",
    "addr:postcode":"21209",
    "addr:street":"Bartol Ave",
    "iso:country":"US",
    "sg:address":"2710 Bartol Ave",
    "sg:city":"Baltimore",
    "sg:classifiers":[
        {
            "category":"Restaurant",
            "type":"Food & Drink"
        }
    ],
    "sg:phone":"+1 410 764 2533",
    "sg:postcode":"21209",
    "sg:province":"MD",
    "sg:tags":[
        "house",
        "steak"
    ],
    "wof:name":"Bandana Bonanza",
    "wof:placetype":"venue"
},
  "geometry": {"coordinates":[-76.680983,39.366576],"type":"Point"}
}