{
  "type": "Feature",
  "properties": {
    "iso:country":"US",
    "sg:address":"6106 Biltmore Ave",
    "sg:city":"Baltimore",
    "sg:classifiers":[
        {
            "category":"Professional",
            "subcategory":"Employment Agencies",
            "type":"Services"
        }
    ],
    "sg:phone":"+1 410 358 4373",
    "sg:postcode":"21215",
    "sg:province":"MD",
    "sg:tags":[
        "help",
        "contractor"
    ],
    "wof:name":"Charles Prophet & Hamilton Inc",
    "wof:placetype":"venue"
},
  "geometry": {"coordinates":[-76.693407,39.356864],"type":"Point"}
}