{
  "type": "Feature",
  "properties": {
    "iso:country":"US",
    "sg:address":"949 Bonifant St",
    "sg:city":"Silver Spring",
    "sg:classifiers":[
        {
            "category":"Shopping",
            "subcategory":"Used Merchandise",
            "type":"Retail Goods"
        },
        {
            "category":"Professional",
            "subcategory":"Business Services",
            "type":"Services"
        }
    ],
    "sg:phone":"+1 301 585 1239",
    "sg:postcode":"20910",
    "sg:province":"MD",
    "sg:tags":[
        "flea",
        "market"
    ],
    "wof:name":"Ogun Gulcin",
    "wof:placetype":"venue"
},
  "geometry": {"coordinates":[-77.025454,38.993885],"type":"Point"}
}