{
  "type": "Feature",
  "properties": {
    "addr:full":"9 Bohemia Ave Chesapeake City MD 21915",
    "addr:housenumber":"9",
    "addr:postcode":"21915",
    "addr:street":"Bohemia Ave",
    "iso:country":"US",
    "sg:address":"9 Bohemia Ave",
    "sg:city":"Chesapeake City",
    "sg:classifiers":[
        {
            "category":"Restaurant",
            "type":"Food & Drink"
        }
    ],
    "sg:phone":"+1 410 885 3030",
    "sg:postcode":"21915",
    "sg:province":"MD",
    "sg:tags":[
        "eating"
    ],
    "wof:name":"Canal Creamery",
    "wof:placetype":"venue"
},
  "geometry": {"coordinates":[-75.811931,39.527526],"type":"Point"}
}