{
  "type": "Feature",
  "properties": {
    "addr:full":"2730 University Blvd W Wheaton MD 20902",
    "addr:housenumber":"2730",
    "addr:postcode":"20902",
    "addr:street":"University Blvd W",
    "iso:country":"US",
    "sg:address":"2730 University Blvd W",
    "sg:city":"Wheaton",
    "sg:classifiers":[
        {
            "category":"Government",
            "subcategory":"Office",
            "type":"Public Place"
        }
    ],
    "sg:phone":"+1 301 949 6030",
    "sg:postcode":"20902",
    "sg:province":"MD",
    "sg:tags":[
        "state",
        "taxation"
    ],
    "wof:name":"Comptroller Treasury",
    "wof:placetype":"venue"
},
  "geometry": {"coordinates":[-77.056248,39.03954],"type":"Point"}
}