{
  "type": "Feature",
  "properties": {
    "iso:country":"US",
    "sg:address":"9919 Good Luck Rd",
    "sg:city":"Lanham",
    "sg:classifiers":[
        {
            "category":"Professional",
            "subcategory":"Business Services",
            "type":"Services"
        }
    ],
    "sg:phone":"+1 301 794 6013",
    "sg:postcode":"20706",
    "sg:province":"MD",
    "wof:name":"Dots Demo",
    "wof:placetype":"venue"
},
  "geometry": {"coordinates":[-76.83595,38.992527],"type":"Point"}
}