{
  "type": "Feature",
  "properties": {
    "addr:full":"35 E Montgomery St Baltimore MD 21230",
    "addr:housenumber":"35",
    "addr:postcode":"21230",
    "addr:street":"E Montgomery St",
    "iso:country":"US",
    "sg:address":"35 E Montgomery St",
    "sg:city":"Baltimore",
    "sg:classifiers":[
        {
            "category":"Shopping",
            "subcategory":"Used Merchandise",
            "type":"Retail Goods"
        }
    ],
    "sg:phone":"+1 410 539 5437",
    "sg:postcode":"21230",
    "sg:province":"MD",
    "wof:name":"Old Lane Antiques",
    "wof:placetype":"venue"
},
  "geometry": {"coordinates":[-76.612933,39.279907],"type":"Point"}
}