{
  "type": "Feature",
  "properties": {
    "addr:full":"1000 Milchling Dr Bel Air MD 21015",
    "addr:housenumber":"1000",
    "addr:postcode":"21015",
    "addr:street":"Milchling Dr",
    "iso:country":"US",
    "sg:address":"1000 Milchling Dr",
    "sg:city":"Bel Air",
    "sg:classifiers":[
        {
            "category":"Wholesale",
            "subcategory":"Machinery & Supplies",
            "type":"Manufacturing & Wholesale Goods"
        }
    ],
    "sg:phone":"+1 410 638 8200",
    "sg:postcode":"21015",
    "sg:province":"MD",
    "sg:tags":[
        "equipment",
        "industrial"
    ],
    "wof:name":"Strategic Distribution Inc",
    "wof:placetype":"venue"
},
  "geometry": {"coordinates":[-76.32036600000001,39.563449],"type":"Point"}
}