{
  "type": "Feature",
  "properties": {
    "iso:country":"US",
    "sg:address":"2141 Industrial Pkwy Ste 102",
    "sg:city":"Silver Spring",
    "sg:classifiers":[
        {
            "category":"Home & Garden",
            "subcategory":"Household Appliances",
            "type":"Retail Goods"
        }
    ],
    "sg:phone":"+1 301 593 7676",
    "sg:postcode":"20904",
    "sg:province":"MD",
    "sg:tags":[
        "repair"
    ],
    "wof:name":"A-1 TV Sales & Service",
    "wof:placetype":"venue"
},
  "geometry": {"coordinates":[-76.969309,39.05407],"type":"Point"}
}