{
  "type": "Feature",
  "properties": {
    "addr:full":"41950 Satchel Paige Way Hollywood MD 20636",
    "addr:postcode":"41950;20636",
    "addr:street":"Paige Way",
    "iso:country":"US",
    "sg:address":"41950 Satchel Paige Way",
    "sg:city":"Hollywood",
    "sg:classifiers":[
        {
            "category":"Social Services",
            "subcategory":"Child Care",
            "type":"Services"
        }
    ],
    "sg:phone":"+1 301 475 0120",
    "sg:postcode":"20636",
    "sg:province":"MD",
    "wof:name":"Holland Forest Head Start Ctr",
    "wof:placetype":"venue"
},
  "geometry": {"coordinates":[-76.623859,38.323223],"type":"Point"}
}