{
  "type": "Feature",
  "properties": {
    "iso:country":"US",
    "sg:address":"9500 Livingston Rd",
    "sg:city":"Fort Washington",
    "sg:classifiers":[
        {
            "category":"Health Services",
            "subcategory":"Doctor",
            "type":"Services"
        }
    ],
    "sg:phone":"+1 301 265 1650",
    "sg:postcode":"20744",
    "sg:province":"MD",
    "sg:tags":[
        "dentist"
    ],
    "wof:name":"Evelyn Campbell-Leach DDS",
    "wof:placetype":"venue"
},
  "geometry": {"coordinates":[-76.995314,38.761069],"type":"Point"}
}