{
  "type": "Feature",
  "properties": {
    "addr:full":"727 E Main St Salisbury MD 21804",
    "addr:housenumber":"727",
    "addr:postcode":"21804",
    "addr:street":"E Main St",
    "iso:country":"US",
    "sg:address":"727 E Main St",
    "sg:city":"Salisbury",
    "sg:classifiers":[
        {
            "category":"Organizations",
            "subcategory":"Religious Organization",
            "type":"Services"
        }
    ],
    "sg:phone":"+1 410 219 1174",
    "sg:postcode":"21804",
    "sg:province":"MD",
    "sg:tags":[
        "church"
    ],
    "wof:name":"Calvary Chapel Ocean Gateway",
    "wof:placetype":"venue"
},
  "geometry": {"coordinates":[-75.586343,38.36602],"type":"Point"}
}