{
  "type": "Feature",
  "properties": {
    "iso:country":"US",
    "sg:address":"204 S Chapel St",
    "sg:city":"Baltimore",
    "sg:classifiers":[
        {
            "category":"Manufacturing",
            "subcategory":"Printing",
            "type":"Manufacturing & Wholesale Goods"
        }
    ],
    "sg:phone":"+1 410 732 7575",
    "sg:postcode":"21231",
    "sg:province":"MD",
    "sg:tags":[
        "printer"
    ],
    "wof:name":"Reliable Printing Plates Inc",
    "wof:placetype":"venue"
},
  "geometry": {"coordinates":[-76.589668,39.287866],"type":"Point"}
}