{
  "type": "Feature",
  "properties": {
    "iso:country":"US",
    "sg:address":"2444 Ennalls Ave",
    "sg:city":"Wheaton",
    "sg:classifiers":[
        {
            "category":"Food & Beverages",
            "subcategory":"Groceries & Convenience Stores",
            "type":"Retail Goods"
        }
    ],
    "sg:phone":"+1 301 942 0503",
    "sg:postcode":"20902",
    "sg:province":"MD",
    "sg:tags":[
        "market"
    ],
    "wof:name":"Latin & American Market",
    "wof:placetype":"venue"
},
  "geometry": {"coordinates":[-77.052553,39.040199],"type":"Point"}
}