{
  "type": "Feature",
  "properties": {
    "iso:country":"US",
    "sg:address":"32 Village Sq",
    "sg:city":"Baltimore",
    "sg:classifiers":[
        {
            "category":"Shopping",
            "subcategory":"Clothing, Apparel, & Fashions",
            "type":"Retail Goods"
        }
    ],
    "sg:phone":"+1 410 435 2676",
    "sg:postcode":"21210",
    "sg:province":"MD",
    "sg:tags":[
        "children's",
        "clothing"
    ],
    "wof:name":"Pied Piper Children's Wear",
    "wof:placetype":"venue"
},
  "geometry": {"coordinates":[-76.630302,39.350601],"type":"Point"}
}