{
  "type": "Feature",
  "properties": {
    "iso:country":"US",
    "sg:address":"9602 Wagner Trl",
    "sg:city":"Clinton",
    "sg:classifiers":[
        {
            "category":"Government",
            "subcategory":"Embassy",
            "type":"Public Place"
        }
    ],
    "sg:phone":"+1 301 877 8147",
    "sg:postcode":"20735",
    "sg:province":"MD",
    "sg:tags":[
        "representative",
        "consulate",
        "foreign"
    ],
    "wof:name":"Artesania Rincon Paraguay",
    "wof:placetype":"venue"
},
  "geometry": {"coordinates":[-76.869697,38.75843],"type":"Point"}
}