{
  "type": "Feature",
  "properties": {
    "addr:full":"2305 Gold Mine Rd Brookeville MD 20833",
    "addr:housenumber":"2305",
    "addr:postcode":"20833",
    "addr:street":"Gold Mine Rd",
    "iso:country":"US",
    "sg:address":"2305 Gold Mine Rd",
    "sg:city":"Brookeville",
    "sg:classifiers":[
        {
            "category":"Professional",
            "subcategory":"Management & Consulting",
            "type":"Services"
        }
    ],
    "sg:phone":"+1 301 570 0013",
    "sg:postcode":"20833",
    "sg:province":"MD",
    "sg:tags":[
        "business"
    ],
    "wof:name":"Health Plicy Rsurces Group LLC",
    "wof:placetype":"venue"
},
  "geometry": {"coordinates":[-77.058092,39.172306],"type":"Point"}
}