{
  "type": "Feature",
  "properties": {
    "addr:full":"504 Bonifant St Silver Spring MD 20910",
    "addr:housenumber":"504",
    "addr:postcode":"20910",
    "addr:street":"Bonifant St",
    "iso:country":"US",
    "sg:address":"504 Bonifant St",
    "sg:city":"Silver Spring",
    "sg:classifiers":[
        {
            "category":"Food & Beverages",
            "subcategory":"Groceries & Convenience Stores",
            "type":"Retail Goods"
        }
    ],
    "sg:phone":"+1 240 450 4100",
    "sg:postcode":"20910",
    "sg:province":"MD",
    "sg:tags":[
        "market"
    ],
    "wof:name":"Community Market",
    "wof:placetype":"venue"
},
  "geometry": {"coordinates":[-77.01711299999999,38.997949],"type":"Point"}
}