{
  "type": "Feature",
  "properties": {
    "iso:country":"US",
    "sg:address":"858 Snowfall Way",
    "sg:city":"Westminster",
    "sg:classifiers":[
        {
            "category":"Professional",
            "subcategory":"Detective & Security Services",
            "type":"Services"
        }
    ],
    "sg:phone":"+1 443 508 1207",
    "sg:postcode":"21157",
    "sg:province":"MD",
    "sg:tags":[
        "information",
        "bureau"
    ],
    "wof:name":"Dmc Home Services",
    "wof:placetype":"venue"
},
  "geometry": {"coordinates":[-76.99029899999999,39.597152],"type":"Point"}
}