{
  "type": "Feature",
  "properties": {
    "iso:country":"US",
    "sg:address":"4401 Southern Businss Park Dr",
    "sg:city":"White Plains",
    "sg:classifiers":[
        {
            "category":"Real Estate",
            "subcategory":"Developer",
            "type":"Services"
        }
    ],
    "sg:phone":"+1 301 870 3639",
    "sg:postcode":"20695",
    "sg:province":"MD",
    "wof:name":"Lenhart Development Corp",
    "wof:placetype":"venue"
},
  "geometry": {"coordinates":[-76.94791,38.59117],"type":"Point"}
}