{
  "type": "Feature",
  "properties": {
    "addr:full":"719 Frederick Rd Catonsville MD 21228",
    "addr:housenumber":"719",
    "addr:postcode":"21228",
    "addr:street":"Frederick Rd",
    "iso:country":"US",
    "sg:address":"719 Frederick Rd",
    "sg:city":"Catonsville",
    "sg:classifiers":[
        {
            "category":"Shopping",
            "subcategory":"Clothing, Apparel, & Fashions",
            "type":"Retail Goods"
        }
    ],
    "sg:phone":"+1 410 747 8760",
    "sg:postcode":"21228",
    "sg:province":"MD",
    "sg:tags":[
        "swimwear",
        "accessory"
    ],
    "wof:name":"Cy's Of Catonsville",
    "wof:placetype":"venue"
},
  "geometry": {"coordinates":[-76.73203599999999,39.271931],"type":"Point"}
}