{
  "type": "Feature",
  "properties": {
    "addr:full":"14108 Pleasant View Dr Bowie MD 20720",
    "addr:housenumber":"14108",
    "addr:postcode":"20720",
    "addr:street":"Pleasant View Dr",
    "iso:country":"US",
    "sg:address":"14108 Pleasant View Dr",
    "sg:city":"Bowie",
    "sg:classifiers":[
        {
            "category":"Professional",
            "subcategory":"Business Services",
            "type":"Services"
        }
    ],
    "sg:phone":"+1 301 805 4510",
    "sg:postcode":"20720",
    "sg:province":"MD",
    "wof:name":"Kerala Assoc of Greater W",
    "wof:placetype":"venue"
},
  "geometry": {"coordinates":[-76.760773,38.955257],"type":"Point"}
}