{
  "type": "Feature",
  "properties": {
    "iso:country":"US",
    "sg:address":"22901 Ridge Rd",
    "sg:city":"Germantown",
    "sg:classifiers":[
        {
            "category":"Education",
            "subcategory":"Preschool",
            "type":"Public Place"
        },
        {
            "category":"Organizations",
            "subcategory":"Religious Organization",
            "type":"Services"
        }
    ],
    "sg:phone":"+1 301 428 7957",
    "sg:postcode":"20876",
    "sg:province":"MD",
    "sg:tags":[
        "kindergarten",
        "god",
        "churches-assemblies"
    ],
    "sg:website":"http://www.pvachurch.com",
    "wof:name":"Potomac Valley Assembly Church",
    "wof:placetype":"venue"
},
  "geometry": {"coordinates":[-77.23706199999999,39.231605],"type":"Point"}
}