{
  "type": "Feature",
  "properties": {
    "addr:full":"25 Hooks Ln Pikesville MD 21208",
    "addr:housenumber":"25",
    "addr:postcode":"21208",
    "addr:street":"Hooks Ln",
    "iso:country":"US",
    "sg:address":"25 Hooks Ln",
    "sg:city":"Pikesville",
    "sg:classifiers":[
        {
            "category":"Education",
            "subcategory":"Special Training",
            "type":"Public Place"
        }
    ],
    "sg:phone":"+1 410 484 2000",
    "sg:postcode":"21208",
    "sg:province":"MD",
    "sg:tags":[
        "tutoring"
    ],
    "wof:name":"Huntington Learning Ctr",
    "wof:placetype":"venue"
},
  "geometry": {"coordinates":[-76.735241,39.387364],"type":"Point"}
}