{
  "type": "Feature",
  "properties": {
    "iso:country":"US",
    "sg:address":"711 W 40th St Ste 218",
    "sg:city":"Baltimore",
    "sg:classifiers":[
        {
            "category":"Health Services",
            "subcategory":"Doctor",
            "type":"Services"
        }
    ],
    "sg:phone":"+1 410 486 8156",
    "sg:postcode":"21211",
    "sg:province":"MD",
    "sg:tags":[
        "physician",
        "pediatrics-orthopedic",
        "surgeons",
        "orthopedics",
        "surgeon",
        "surgery"
    ],
    "wof:name":"Draper, Robert F Md Pa",
    "wof:placetype":"venue"
},
  "geometry": {"coordinates":[-76.628646,39.337208],"type":"Point"}
}