{
  "type": "Feature",
  "properties": {
    "iso:country":"US",
    "sg:address":"905 W 7th St",
    "sg:city":"Frederick",
    "sg:classifiers":[
        {
            "category":"Shopping",
            "subcategory":"Catalog Store",
            "type":"Retail Goods"
        }
    ],
    "sg:phone":"+1 301 846 0303",
    "sg:postcode":"21701",
    "sg:province":"MD",
    "sg:tags":[
        "mail",
        "house"
    ],
    "wof:name":"Canicone",
    "wof:placetype":"venue"
},
  "geometry": {"coordinates":[-77.417283,39.42635],"type":"Point"}
}