{
  "type": "Feature",
  "properties": {
    "iso:country":"US",
    "sg:address":"1 Annapolis St",
    "sg:city":"Annapolis",
    "sg:classifiers":[
        {
            "category":"Health Services",
            "subcategory":"Health Practitioner",
            "type":"Services"
        }
    ],
    "sg:phone":"+1 410 280 9450",
    "sg:postcode":"21401",
    "sg:province":"MD",
    "sg:tags":[
        "psychotherapist"
    ],
    "wof:name":"Mary Ann Sachs",
    "wof:placetype":"venue"
},
  "geometry": {"coordinates":[-76.502134,38.990031],"type":"Point"}
}