{
  "type": "Feature",
  "properties": {
    "addr:full":"1132 Taylor Rd Street MD 21154",
    "addr:housenumber":"1132",
    "addr:postcode":"21154",
    "addr:street":"Taylor Rd Street",
    "iso:country":"US",
    "sg:address":"1132 Taylor Rd",
    "sg:city":"Street",
    "sg:classifiers":[
        {
            "category":"Building & Trades",
            "subcategory":"Electrical",
            "type":"Services"
        }
    ],
    "sg:phone":"+1 410 452 5555",
    "sg:postcode":"21154",
    "sg:province":"MD",
    "sg:tags":[
        "electrical",
        "contractor"
    ],
    "wof:name":"Burmans Electric",
    "wof:placetype":"venue"
},
  "geometry": {"coordinates":[-76.338657,39.669046],"type":"Point"}
}