{
  "type": "Feature",
  "properties": {
    "addr:full":"1006 Haverhill Rd Baltimore MD 21229",
    "addr:housenumber":"1006",
    "addr:postcode":"21229",
    "addr:street":"Haverhill Rd",
    "iso:country":"US",
    "sg:address":"1006 Haverhill Rd",
    "sg:city":"Baltimore",
    "sg:classifiers":[
        {
            "category":"Building & Trades",
            "subcategory":"Plumbing",
            "type":"Services"
        }
    ],
    "sg:phone":"+1 410 525 3333",
    "sg:postcode":"21229",
    "sg:province":"MD",
    "sg:tags":[
        "cooling",
        "contractor",
        "tower",
        "mechanical"
    ],
    "wof:name":"Martec Services, Inc",
    "wof:placetype":"venue"
},
  "geometry": {"coordinates":[-76.67961099999999,39.270248],"type":"Point"}
}