{
  "type": "Feature",
  "properties": {
    "addr:full":"13604 Royal Crest Rd Phoenix MD 21131",
    "addr:housenumber":"13604",
    "addr:postcode":"21131",
    "addr:street":"Royal Crest Rd",
    "iso:country":"US",
    "sg:address":"13604 Royal Crest Rd",
    "sg:city":"Phoenix",
    "sg:classifiers":[
        {
            "category":"Manufacturing",
            "subcategory":"Retail Goods",
            "type":"Manufacturing & Wholesale Goods"
        }
    ],
    "sg:phone":"+1 410 628 7288",
    "sg:postcode":"21131",
    "sg:province":"MD",
    "sg:tags":[
        "product",
        "mfg"
    ],
    "wof:name":"Goldeagle Mfg Co",
    "wof:placetype":"venue"
},
  "geometry": {"coordinates":[-76.597694,39.498937],"type":"Point"}
}