{
  "type": "Feature",
  "properties": {
    "addr:full":"9275 Baltimore National Pike Ste 13 Ellicott City MD 21042",
    "addr:housenumber":"9275",
    "addr:postcode":"21042",
    "addr:street":"Baltimore National Pike Ste 13",
    "iso:country":"US",
    "sg:address":"9275 Baltimore National Pike Ste 13",
    "sg:city":"Ellicott City",
    "sg:classifiers":[
        {
            "category":"Retail",
            "subcategory":"Laundry & Dry Cleaning",
            "type":"Services"
        }
    ],
    "sg:phone":"+1 410 480 2200",
    "sg:postcode":"21042",
    "sg:province":"MD",
    "wof:name":"New York Cleaners",
    "wof:placetype":"venue"
},
  "geometry": {"coordinates":[-76.83150500000001,39.277271],"type":"Point"}
}