{
  "type": "Feature",
  "properties": {
    "addr:full":"8395 Oak Dr Pasadena MD 21122",
    "addr:housenumber":"8395",
    "addr:postcode":"21122",
    "addr:street":"Oak Dr",
    "iso:country":"US",
    "sg:address":"8395 Oak Dr",
    "sg:city":"Pasadena",
    "sg:classifiers":[
        {
            "category":"Home & Garden",
            "subcategory":"Home Furnishings",
            "type":"Retail Goods"
        }
    ],
    "sg:phone":"+1 410 437 1586",
    "sg:postcode":"21122",
    "sg:province":"MD",
    "sg:tags":[
        "house"
    ],
    "wof:name":"Lake Shore Home Improvement",
    "wof:placetype":"venue"
},
  "geometry": {"coordinates":[-76.49760000000001,39.109588],"type":"Point"}
}