{
  "type": "Feature",
  "properties": {
    "addr:full":"14753 Main St Upper Marlboro MD 20772",
    "addr:housenumber":"14753",
    "addr:postcode":"20772",
    "addr:street":"Main St",
    "iso:country":"US",
    "sg:address":"14753 Main St",
    "sg:city":"Upper Marlboro",
    "sg:classifiers":[
        {
            "category":"Professional",
            "subcategory":"Lawyer & Legal Services",
            "type":"Services"
        }
    ],
    "sg:phone":"+1 301 627 4000",
    "sg:postcode":"20772",
    "sg:province":"MD",
    "sg:tags":[
        "attorney"
    ],
    "wof:name":"L David Ritter Law Office",
    "wof:placetype":"venue"
},
  "geometry": {"coordinates":[-76.751419,38.816445],"type":"Point"}
}