{
  "type": "Feature",
  "properties": {
    "iso:country":"US",
    "sg:address":"702 Pulaski Hwy",
    "sg:city":"Joppa",
    "sg:classifiers":[
        {
            "category":"Building & Trades",
            "subcategory":"Cleaning & Sanitation",
            "type":"Services"
        }
    ],
    "sg:phone":"+1 410 420 4022",
    "sg:postcode":"21085",
    "sg:province":"MD",
    "sg:tags":[
        "carpet"
    ],
    "sg:website":"www.servpro.com",
    "wof:name":"Servpro of Belair",
    "wof:placetype":"venue"
},
  "geometry": {"coordinates":[-76.352188,39.429785],"type":"Point"}
}