{
  "type": "Feature",
  "properties": {
    "iso:country":"US",
    "sg:address":"7515 Bradley Blvd",
    "sg:city":"Bethesda",
    "sg:classifiers":[
        {
            "category":"Professional",
            "subcategory":"Management & Consulting",
            "type":"Services"
        }
    ],
    "sg:phone":"+1 301 365 1610",
    "sg:postcode":"20817",
    "sg:province":"MD",
    "sg:tags":[
        "consultant",
        "educational"
    ],
    "wof:name":"Innovation Network Inc",
    "wof:placetype":"venue"
},
  "geometry": {"coordinates":[-77.151982,39.009346],"type":"Point"}
}