{
  "type": "Feature",
  "properties": {
    "addr:full":"922 East St Frederick MD 21701",
    "addr:housenumber":"922",
    "addr:postcode":"21701",
    "addr:street":"East St",
    "iso:country":"US",
    "sg:address":"922 East St",
    "sg:city":"Frederick",
    "sg:classifiers":[
        {
            "category":"Professional",
            "subcategory":"Engineering",
            "type":"Services"
        }
    ],
    "sg:phone":"+1 301 360 9534",
    "sg:postcode":"21701",
    "sg:province":"MD",
    "sg:tags":[
        "engineer"
    ],
    "sg:website":"www.ryanandassociates.net",
    "wof:name":"Ryan & Assoc",
    "wof:placetype":"venue"
},
  "geometry": {"coordinates":[-77.40339899999999,39.426904],"type":"Point"}
}