{
  "type": "Feature",
  "properties": {
    "iso:country":"US",
    "sg:address":"2101 Washington Blvd",
    "sg:city":"Baltimore",
    "sg:classifiers":[
        {
            "category":"Building & Trades",
            "subcategory":"Construction",
            "type":"Services"
        }
    ],
    "sg:phone":"+1 443 524 9500",
    "sg:postcode":"21230",
    "sg:province":"MD",
    "sg:tags":[
        "contractor"
    ],
    "wof:name":"Plano-Coudon",
    "wof:placetype":"venue"
},
  "geometry": {"coordinates":[-76.646855,39.271374],"type":"Point"}
}