{
  "type": "Feature",
  "properties": {
    "addr:full":"930 Spaniard Neck Rd Centreville MD 21617",
    "addr:housenumber":"930",
    "addr:postcode":"21617",
    "addr:street":"Spaniard Neck Rd",
    "iso:country":"US",
    "sg:address":"930 Spaniard Neck Rd",
    "sg:city":"Centreville",
    "sg:classifiers":[
        {
            "category":"Professional",
            "subcategory":"Business Services",
            "type":"Services"
        }
    ],
    "sg:phone":"+1 410 758 0901",
    "sg:postcode":"21617",
    "sg:province":"MD",
    "wof:name":"Midshore Technology",
    "wof:placetype":"venue"
},
  "geometry": {"coordinates":[-76.078062,39.081612],"type":"Point"}
}