{
  "type": "Feature",
  "properties": {
    "iso:country":"US",
    "sg:address":"423 W Antietam St",
    "sg:city":"Hagerstown",
    "sg:classifiers":[
        {
            "category":"Retail",
            "subcategory":"Auto Repair",
            "type":"Services"
        }
    ],
    "sg:phone":"+1 301 797 8716",
    "sg:postcode":"21740",
    "sg:province":"MD",
    "sg:tags":[
        "body",
        "automobile",
        "painting"
    ],
    "wof:name":"Dietrich's Auto Body Shop",
    "wof:placetype":"venue"
},
  "geometry": {"coordinates":[-77.72907600000001,39.645678],"type":"Point"}
}