{
  "type": "Feature",
  "properties": {
    "iso:country":"US",
    "sg:address":"9 Quail Hill Ct",
    "sg:city":"Parkton",
    "sg:classifiers":[
        {
            "category":"Professional",
            "subcategory":"Management & Consulting",
            "type":"Services"
        }
    ],
    "sg:phone":"+1 410 357 5498",
    "sg:postcode":"21120",
    "sg:province":"MD",
    "sg:tags":[
        "business"
    ],
    "wof:name":"Claus & Associates Inc",
    "wof:placetype":"venue"
},
  "geometry": {"coordinates":[-76.727036,39.600567],"type":"Point"}
}