{
  "type": "Feature",
  "properties": {
    "iso:country":"US",
    "sg:address":"5901 Pulaski Hwy",
    "sg:city":"Baltimore",
    "sg:classifiers":[
        {
            "category":"Autos & Motor Vehicles",
            "subcategory":"Automobile Sales",
            "type":"Retail Goods"
        }
    ],
    "sg:phone":"+1 410 485 2805",
    "sg:postcode":"21205",
    "sg:province":"MD",
    "sg:tags":[
        "new",
        "used",
        "car"
    ],
    "wof:name":"Premiere Motors Inc.",
    "wof:placetype":"venue"
},
  "geometry": {"coordinates":[-76.547729,39.301899],"type":"Point"}
}