{
  "type": "Feature",
  "properties": {
    "iso:country":"US",
    "sg:address":"1035 S Kenwood Ave",
    "sg:city":"Baltimore",
    "sg:classifiers":[
        {
            "category":"Education",
            "subcategory":"School",
            "type":"Public Place"
        }
    ],
    "sg:phone":"+1 410 342 2681",
    "sg:postcode":"21224",
    "sg:province":"MD",
    "sg:tags":[
        "elementary"
    ],
    "wof:name":"Father Kolbe School",
    "wof:placetype":"venue"
},
  "geometry": {"coordinates":[-76.57669799999999,39.280201],"type":"Point"}
}