{
  "type": "Feature",
  "properties": {
    "addr:full":"2416 Blueridge Ave Wheaton MD 20902",
    "addr:housenumber":"2416",
    "addr:postcode":"20902",
    "addr:street":"Blueridge Ave",
    "iso:country":"US",
    "sg:address":"2416 Blueridge Ave",
    "sg:city":"Wheaton",
    "sg:classifiers":[
        {
            "category":"Health Services",
            "subcategory":"Doctor",
            "type":"Services"
        }
    ],
    "sg:phone":"+1 301 929 0093",
    "sg:postcode":"20902",
    "sg:province":"MD",
    "sg:tags":[
        "dentist"
    ],
    "wof:name":"Stanback Dental Care",
    "wof:placetype":"venue"
},
  "geometry": {"coordinates":[-77.051789,39.042993],"type":"Point"}
}