{
  "type": "Feature",
  "properties": {
    "iso:country":"US",
    "sg:address":"111 Vine St",
    "sg:city":"Pocomoke City",
    "sg:classifiers":[
        {
            "category":"Professional",
            "subcategory":"Lawyer & Legal Services",
            "type":"Services"
        }
    ],
    "sg:phone":"+1 410 957 2323",
    "sg:postcode":"21851",
    "sg:province":"MD",
    "sg:tags":[
        "attorney"
    ],
    "wof:name":"James H Porter Jr Law Offices",
    "wof:placetype":"venue"
},
  "geometry": {"coordinates":[-75.568252,38.076094],"type":"Point"}
}