{
  "type": "Feature",
  "properties": {
    "addr:full":"312 Safety Dr Centreville MD 21617",
    "addr:postcode":"21617",
    "addr:street":"Safety Dr",
    "iso:country":"US",
    "sg:address":"312 Safety Dr",
    "sg:city":"Centreville",
    "sg:classifiers":[
        {
            "category":"Building & Trades",
            "subcategory":"Construction",
            "type":"Services"
        }
    ],
    "sg:phone":"+1 410 758 0925",
    "sg:postcode":"21617",
    "sg:province":"MD",
    "sg:tags":[
        "grading",
        "contractor"
    ],
    "sg:website":"www.quc.org",
    "wof:name":"Department Of Public Works",
    "wof:placetype":"venue"
},
  "geometry": {"coordinates":[-76.015382,39.037075],"type":"Point"}
}