{
  "type": "Feature",
  "properties": {
    "addr:full":"531 Main St Laurel MD 20707",
    "addr:housenumber":"531",
    "addr:postcode":"20707",
    "addr:street":"Main St",
    "iso:country":"US",
    "sg:address":"531 Main St",
    "sg:city":"Laurel",
    "sg:classifiers":[
        {
            "category":"Building & Trades",
            "subcategory":"Locksmith",
            "type":"Services"
        }
    ],
    "sg:phone":"+1 240 396 1469",
    "sg:postcode":"20707",
    "sg:province":"MD",
    "sg:tags":[
        "key"
    ],
    "wof:name":"1 24 7 Locksmith",
    "wof:placetype":"venue"
},
  "geometry": {"coordinates":[-76.852042,39.107925],"type":"Point"}
}