{
  "type": "Feature",
  "properties": {
    "addr:full":"105 Highgate Ct Owings Mills MD 21117",
    "addr:housenumber":"105",
    "addr:postcode":"21117",
    "addr:street":"Highgate Ct",
    "iso:country":"US",
    "sg:address":"105 Highgate Ct",
    "sg:city":"Owings Mills",
    "sg:classifiers":[
        {
            "category":"Retail",
            "subcategory":"Repair Shop",
            "type":"Services"
        }
    ],
    "sg:phone":"+1 410 581 8584",
    "sg:postcode":"21117",
    "sg:province":"MD",
    "sg:tags":[
        "electrical"
    ],
    "wof:name":"Phil Com",
    "wof:placetype":"venue"
},
  "geometry": {"coordinates":[-76.79469400000001,39.419665],"type":"Point"}
}