{
  "type": "Feature",
  "properties": {
    "iso:country":"US",
    "sg:address":"300 E Joppa Rd",
    "sg:city":"Baltimore",
    "sg:classifiers":[
        {
            "category":"Government",
            "subcategory":"Office",
            "type":"Public Place"
        }
    ],
    "sg:phone":"+1 410 321 4136",
    "sg:postcode":"21286",
    "sg:province":"MD",
    "wof:name":"Uninsured Employer's Fund",
    "wof:placetype":"venue"
},
  "geometry": {"coordinates":[-76.59754,39.402172],"type":"Point"}
}