{
  "type": "Feature",
  "properties": {
    "iso:country":"US",
    "sg:address":"8646 Liberty Rd",
    "sg:city":"Randallstown",
    "sg:classifiers":[
        {
            "category":"Building & Trades",
            "subcategory":"Equipment Rental",
            "type":"Services"
        }
    ],
    "sg:phone":"+1 410 521 8696",
    "sg:postcode":"21133",
    "sg:province":"MD",
    "sg:tags":[
        "leasing",
        "television",
        "radio-renting",
        "yard"
    ],
    "sg:website":"http://www.rentacenter.com/",
    "wof:name":"Rent-A-Center",
    "wof:placetype":"venue"
},
  "geometry": {"coordinates":[-76.780995,39.362223],"type":"Point"}
}