{
  "type": "Feature",
  "properties": {
    "addr:full":"3550 Bladensburg Rd Brentwood MD 20722",
    "addr:housenumber":"3550",
    "addr:postcode":"20722",
    "addr:street":"Bladensburg Rd",
    "iso:country":"US",
    "sg:address":"3550 Bladensburg Rd",
    "sg:city":"Brentwood",
    "sg:classifiers":[
        {
            "category":"Autos & Motor Vehicles",
            "subcategory":"Fuel & Gas Station",
            "type":"Retail Goods"
        }
    ],
    "sg:phone":"+1 301 277 2911",
    "sg:postcode":"20722",
    "sg:province":"MD",
    "sg:tags":[
        "oil"
    ],
    "wof:name":"R2R Auto Repair Ctr Inc",
    "wof:placetype":"venue"
},
  "geometry": {"coordinates":[-76.95424800000001,38.933202],"type":"Point"}
}