{
  "type": "Feature",
  "properties": {
    "iso:country":"US",
    "sg:address":"4514 Emerson St",
    "sg:city":"Hyattsville",
    "sg:classifiers":[
        {
            "category":"Manufacturing",
            "subcategory":"Printing",
            "type":"Manufacturing & Wholesale Goods"
        }
    ],
    "sg:phone":"+1 301 864 8138",
    "sg:postcode":"20781",
    "sg:province":"MD",
    "sg:tags":[
        "commercial"
    ],
    "wof:name":"Century Printing House",
    "wof:placetype":"venue"
},
  "geometry": {"coordinates":[-76.940443,38.949807],"type":"Point"}
}