{
  "type": "Feature",
  "properties": {
    "iso:country":"US",
    "sg:address":"724 Farnham Pl",
    "sg:city":"Bel Air",
    "sg:classifiers":[
        {
            "category":"Retail",
            "subcategory":"Repair Shop",
            "type":"Services"
        }
    ],
    "sg:phone":"+1 410 638 8115",
    "sg:postcode":"21014",
    "sg:province":"MD",
    "sg:tags":[
        "welding"
    ],
    "wof:name":"W S Donnell Welding",
    "wof:placetype":"venue"
},
  "geometry": {"coordinates":[-76.324749,39.552805],"type":"Point"}
}