{
  "type": "Feature",
  "properties": {
    "iso:country":"US",
    "sg:address":"2318 Weymouth Ln",
    "sg:city":"Crofton",
    "sg:classifiers":[
        {
            "category":"Organizations",
            "subcategory":"Religious Organization",
            "type":"Services"
        }
    ],
    "sg:phone":"+1 410 451 2925",
    "sg:postcode":"21114",
    "sg:province":"MD",
    "sg:tags":[
        "church"
    ],
    "wof:name":"Abundant Life Revival Center",
    "wof:placetype":"venue"
},
  "geometry": {"coordinates":[-76.674187,39.025472],"type":"Point"}
}