{
  "type": "Feature",
  "properties": {
    "iso:country":"US",
    "sg:address":"110 S Washington St",
    "sg:city":"Havre De Grace",
    "sg:classifiers":[
        {
            "category":"Shopping",
            "type":"Retail Goods"
        }
    ],
    "sg:phone":"+1 410 272 7445",
    "sg:postcode":"21078",
    "sg:province":"MD",
    "sg:tags":[
        "water",
        "heater"
    ],
    "wof:name":"Expert Plumbing Svc Inc",
    "wof:placetype":"venue"
},
  "geometry": {"coordinates":[-76.089826,39.546702],"type":"Point"}
}