{
  "type": "Feature",
  "properties": {
    "iso:country":"US",
    "sg:address":"224 N Adams St",
    "sg:city":"Rockville",
    "sg:classifiers":[
        {
            "category":"Professional",
            "subcategory":"Lawyer & Legal Services",
            "type":"Services"
        }
    ],
    "sg:phone":"+1 301 294 9340",
    "sg:postcode":"20850",
    "sg:province":"MD",
    "sg:tags":[
        "attorney"
    ],
    "wof:name":"Jennifer Evans Law Offices",
    "wof:placetype":"venue"
},
  "geometry": {"coordinates":[-77.154978,39.08779],"type":"Point"}
}