{
  "type": "Feature",
  "properties": {
    "iso:country":"US",
    "sg:address":"6820 Virginia Manor Rd",
    "sg:city":"Beltsville",
    "sg:classifiers":[
        {
            "category":"Utilities",
            "subcategory":"Mobile Phone",
            "type":"Services"
        },
        {
            "category":"Communications",
            "type":"Services"
        }
    ],
    "sg:phone":"+1 301 210 1610",
    "sg:postcode":"20705",
    "sg:province":"MD",
    "sg:tags":[
        "data",
        "telephone",
        "cellular"
    ],
    "sg:website":"http://www.cingular.com",
    "wof:name":"AT&T Wireless",
    "wof:placetype":"venue"
},
  "geometry": {"coordinates":[-76.893641,39.059456],"type":"Point"}
}