{
  "type": "Feature",
  "properties": {
    "addr:full":"4234 Glenn Dale Rd Bowie MD 20720",
    "addr:housenumber":"4234",
    "addr:postcode":"20720",
    "addr:street":"Glenn Dale Rd",
    "iso:country":"US",
    "sg:address":"4234 Glenn Dale Rd",
    "sg:city":"Bowie",
    "sg:classifiers":[
        {
            "category":"Professional",
            "subcategory":"Engineering",
            "type":"Services"
        }
    ],
    "sg:phone":"+1 301 262 9334",
    "sg:postcode":"20720",
    "sg:province":"MD",
    "sg:tags":[
        "engineer"
    ],
    "wof:name":"J & Z Engineering Inc",
    "wof:placetype":"venue"
},
  "geometry": {"coordinates":[-76.81116400000001,38.948932],"type":"Point"}
}