{
  "type": "Feature",
  "properties": {
    "iso:country":"US",
    "sg:address":"1 Clear Skys Ct",
    "sg:city":"Baltimore",
    "sg:classifiers":[
        {
            "category":"Real Estate",
            "subcategory":"Real Estate Operator",
            "type":"Services"
        }
    ],
    "sg:phone":"+1 410 653 0035",
    "sg:postcode":"21209",
    "sg:province":"MD",
    "sg:tags":[
        "apartment"
    ],
    "wof:name":"Tr-1 LTD Partnership",
    "wof:placetype":"venue"
},
  "geometry": {"coordinates":[-76.665976,39.385024],"type":"Point"}
}