{
  "type": "Feature",
  "properties": {
    "iso:country":"US",
    "sg:address":"11009 Stewart Neck Rd",
    "sg:city":"Princess Anne",
    "sg:classifiers":[
        {
            "category":"Wholesale",
            "subcategory":"Electrical",
            "type":"Manufacturing & Wholesale Goods"
        }
    ],
    "sg:phone":"+1 410 546 9699",
    "sg:postcode":"21853",
    "sg:province":"MD",
    "sg:tags":[
        "telecommunication"
    ],
    "wof:name":"Wilkins Electronics Inc",
    "wof:placetype":"venue"
},
  "geometry": {"coordinates":[-75.698734,38.183023],"type":"Point"}
}