{
  "type": "Feature",
  "properties": {
    "iso:country":"US",
    "sg:address":"4510 Coulbourn Mill Rd",
    "sg:city":"Salisbury",
    "sg:classifiers":[
        {
            "category":"Professional",
            "subcategory":"Engineering",
            "type":"Services"
        }
    ],
    "sg:phone":"+1 410 546 2861",
    "sg:postcode":"21804",
    "sg:province":"MD",
    "wof:name":"Preston Waller",
    "wof:placetype":"venue"
},
  "geometry": {"coordinates":[-75.57082800000001,38.316732],"type":"Point"}
}