{
  "type": "Feature",
  "properties": {
    "addr:full":"7181 Parsonsburg Rd Parsonsburg MD 21849",
    "addr:housenumber":"7181",
    "addr:postcode":"21849",
    "addr:street":"Parsonsburg Rd",
    "iso:country":"US",
    "sg:address":"7181 Parsonsburg Rd",
    "sg:city":"Parsonsburg",
    "sg:classifiers":[
        {
            "category":"Food & Beverages",
            "subcategory":"Groceries & Convenience Stores",
            "type":"Retail Goods"
        }
    ],
    "sg:phone":"+1 410 860 4895",
    "sg:postcode":"21849",
    "sg:province":"MD",
    "wof:name":"Parsonsburg Quick Shop",
    "wof:placetype":"venue"
},
  "geometry": {"coordinates":[-75.468056,38.388283],"type":"Point"}
}