{
  "type": "Feature",
  "properties": {
    "addr:full":"8525 Baltimore National Pike Ellicott City MD 21043",
    "addr:housenumber":"8525",
    "addr:postcode":"21043",
    "addr:street":"Baltimore National Pike",
    "iso:country":"US",
    "sg:address":"8525 Baltimore National Pike",
    "sg:city":"Ellicott City",
    "sg:classifiers":[
        {
            "category":"Restaurant",
            "type":"Food & Drink"
        }
    ],
    "sg:menulink":"http://www.allmenus.com/md/ellicott-city/131576-quiznos-sub/menu/",
    "sg:phone":"+1 410 465 6004",
    "sg:postcode":"21043",
    "sg:province":"MD",
    "sg:tags":[
        "wrap",
        "american",
        "sandwich"
    ],
    "wof:name":"Quiznos Sub",
    "wof:placetype":"venue"
},
  "geometry": {"coordinates":[-76.807523,39.284289],"type":"Point"}
}