{
  "type": "Feature",
  "properties": {
    "addr:full":"803 S Bethel St Baltimore MD 21231",
    "addr:housenumber":"803",
    "addr:postcode":"21231",
    "addr:street":"S Bethel St",
    "iso:country":"US",
    "sg:address":"803 S Bethel St",
    "sg:city":"Baltimore",
    "sg:classifiers":[
        {
            "category":"Professional",
            "subcategory":"Business Services",
            "type":"Services"
        }
    ],
    "sg:phone":"+1 410 271 3797",
    "sg:postcode":"21231",
    "sg:province":"MD",
    "sg:tags":[
        "holding"
    ],
    "wof:name":"Nkk Holding Corporation",
    "wof:placetype":"venue"
},
  "geometry": {"coordinates":[-76.59424199999999,39.282485],"type":"Point"}
}