{
  "type": "Feature",
  "properties": {
    "addr:full":"10300 Little Patuxent Pkwy Ste 1605 Columbia MD 21044",
    "addr:housenumber":"10300",
    "addr:postcode":"21044",
    "addr:street":"Little Patuxent Pkwy Ste 1605",
    "iso:country":"US",
    "sg:address":"10300 Little Patuxent Pkwy Ste 1605",
    "sg:city":"Columbia",
    "sg:classifiers":[
        {
            "category":"Personal",
            "subcategory":"Beauty Salon",
            "type":"Services"
        },
        {
            "category":"Personal",
            "subcategory":"Barber",
            "type":"Services"
        }
    ],
    "sg:phone":"+1 410 992 4295",
    "sg:postcode":"21044",
    "sg:province":"MD",
    "sg:tags":[
        "hair",
        "stylist"
    ],
    "sg:website":"http://www.mastercuts.com",
    "wof:name":"MasterCuts",
    "wof:placetype":"venue"
},
  "geometry": {"coordinates":[-76.85784099999999,39.216591],"type":"Point"}
}