{
  "type": "Feature",
  "properties": {
    "addr:full":"4 Aurora St Cambridge MD 21613",
    "addr:housenumber":"4",
    "addr:postcode":"21613",
    "addr:street":"Aurora St",
    "iso:country":"US",
    "sg:address":"4 Aurora St",
    "sg:city":"Cambridge",
    "sg:classifiers":[
        {
            "category":"Health Services",
            "subcategory":"Doctor",
            "type":"Services"
        }
    ],
    "sg:phone":"+1 410 221 0557",
    "sg:postcode":"21613",
    "sg:province":"MD",
    "sg:tags":[
        "physician",
        "surgeon"
    ],
    "wof:name":"Chesapeake Cardiology Clinic",
    "wof:placetype":"venue"
},
  "geometry": {"coordinates":[-76.06708399999999,38.570955],"type":"Point"}
}