{
  "type": "Feature",
  "properties": {
    "addr:full":"7 Park Center Ct Owings Mills MD 21117",
    "addr:housenumber":"7",
    "addr:postcode":"21117",
    "addr:street":"Park Center Ct",
    "iso:country":"US",
    "sg:address":"7 Park Center Ct",
    "sg:city":"Owings Mills",
    "sg:classifiers":[
        {
            "category":"Real Estate",
            "subcategory":"Real Estate Operator",
            "type":"Services"
        }
    ],
    "sg:phone":"+1 410 654 6900",
    "sg:postcode":"21117",
    "sg:province":"MD",
    "sg:tags":[
        "building",
        "operates",
        "commercial",
        "an"
    ],
    "wof:name":"Honolulu Ltd",
    "wof:placetype":"venue"
},
  "geometry": {"coordinates":[-76.752994,39.398623],"type":"Point"}
}