{
  "type": "Feature",
  "properties": {
    "iso:country":"US",
    "sg:address":"4222 Ridgewood Ave",
    "sg:city":"Baltimore",
    "sg:classifiers":[
        {
            "category":"Professional",
            "subcategory":"Business Services",
            "type":"Services"
        }
    ],
    "sg:phone":"+1 410 466 0809",
    "sg:postcode":"21215",
    "sg:province":"MD",
    "sg:tags":[
        "water",
        "treatment"
    ],
    "wof:name":"G R Simpson & Co",
    "wof:placetype":"venue"
},
  "geometry": {"coordinates":[-76.691264,39.336719],"type":"Point"}
}