{
  "type": "Feature",
  "properties": {
    "addr:full":"8715 Central Ave Capitol Heights MD 20743",
    "addr:housenumber":"8715",
    "addr:postcode":"20743",
    "addr:street":"Central Ave",
    "iso:country":"US",
    "sg:address":"8715 Central Ave",
    "sg:city":"Capitol Heights",
    "sg:classifiers":[
        {
            "category":"Autos & Motor Vehicles",
            "subcategory":"Fuel & Gas Station",
            "type":"Retail Goods"
        }
    ],
    "sg:phone":"+1 301 350 1409",
    "sg:postcode":"20743",
    "sg:province":"MD",
    "sg:tags":[
        "oil"
    ],
    "wof:name":"Hampton Crown Inc",
    "wof:placetype":"venue"
},
  "geometry": {"coordinates":[-76.855678,38.890277],"type":"Point"}
}