{
  "type": "Feature",
  "properties": {
    "addr:full":"14213 Platinum Dr North Potomac MD 20878",
    "addr:housenumber":"14213",
    "addr:postcode":"20878",
    "addr:street":"Platinum Dr",
    "iso:country":"US",
    "sg:address":"14213 Platinum Dr",
    "sg:city":"North Potomac",
    "sg:classifiers":[
        {
            "category":"Banks & Credit Unions",
            "subcategory":"Bank",
            "type":"Services"
        }
    ],
    "sg:phone":"+1 301 340 2828",
    "sg:postcode":"20878",
    "sg:province":"MD",
    "sg:tags":[
        "loan",
        "real estate"
    ],
    "wof:name":"USA Mortgage Corp",
    "wof:placetype":"venue"
},
  "geometry": {"coordinates":[-77.21936599999999,39.091944],"type":"Point"}
}