{
  "type": "Feature",
  "properties": {
    "iso:country":"US",
    "sg:address":"9801 Rhode Island Ave",
    "sg:city":"College Park",
    "sg:classifiers":[
        {
            "category":"Shopping",
            "subcategory":"Bicycles & Sporting Goods",
            "type":"Retail Goods"
        }
    ],
    "sg:phone":"+1 301 982 9681",
    "sg:postcode":"20740",
    "sg:province":"MD",
    "wof:name":"REI-Recreational Equipment Inc",
    "wof:placetype":"venue"
},
  "geometry": {"coordinates":[-76.920834,39.016042],"type":"Point"}
}