{
  "type": "Feature",
  "properties": {
    "addr:full":"11300 Rockville Pike Rockville MD 20852",
    "addr:housenumber":"11300",
    "addr:postcode":"20852",
    "addr:street":"Rockville Pike",
    "iso:country":"US",
    "sg:address":"11300 Rockville Pike",
    "sg:city":"Rockville",
    "sg:classifiers":[
        {
            "category":"Professional",
            "subcategory":"Lawyer & Legal Services",
            "type":"Services"
        }
    ],
    "sg:phone":"+1 301 770 9440",
    "sg:postcode":"20852",
    "sg:province":"MD",
    "sg:tags":[
        "personal",
        "injury"
    ],
    "wof:name":"Marmelstein Michael E",
    "wof:placetype":"venue"
},
  "geometry": {"coordinates":[-77.11024999999999,39.041078],"type":"Point"}
}