{
  "type": "Feature",
  "properties": {
    "iso:country":"US",
    "sg:address":"9945 Canvasback Way",
    "sg:city":"Damascus",
    "sg:classifiers":[
        {
            "category":"Professional",
            "subcategory":"Secretarial Services",
            "type":"Services"
        }
    ],
    "sg:phone":"+1 301 253 1827",
    "sg:postcode":"20872",
    "sg:province":"MD",
    "sg:tags":[
        "reporting"
    ],
    "wof:name":"Bonita Louise Cole",
    "wof:placetype":"venue"
},
  "geometry": {"coordinates":[-77.205181,39.27711],"type":"Point"}
}