{
  "type": "Feature",
  "properties": {
    "addr:full":"9824 Owen Brown Rd Columbia MD 21045",
    "addr:housenumber":"9824",
    "addr:postcode":"21045",
    "addr:street":"Owen Brown Rd",
    "iso:country":"US",
    "sg:address":"9824 Owen Brown Rd",
    "sg:city":"Columbia",
    "sg:classifiers":[
        {
            "category":"Restaurant",
            "type":"Food & Drink"
        }
    ],
    "sg:phone":"+1 410 964 9114",
    "sg:postcode":"21045",
    "sg:province":"MD",
    "wof:name":"Jesse Wong's Hong Kong",
    "wof:placetype":"venue"
},
  "geometry": {"coordinates":[-76.853188,39.200629],"type":"Point"}
}