{
  "type": "Feature",
  "properties": {
    "iso:country":"US",
    "sg:address":"35 Owensville Rd",
    "sg:city":"West River",
    "sg:classifiers":[
        {
            "category":"Professional",
            "subcategory":"Lawyer & Legal Services",
            "type":"Services"
        }
    ],
    "sg:phone":"+1 410 867 1696",
    "sg:postcode":"20778",
    "sg:province":"MD",
    "sg:tags":[
        "attorney"
    ],
    "wof:name":"William E KIRK Attorney",
    "wof:placetype":"venue"
},
  "geometry": {"coordinates":[-76.606425,38.845879],"type":"Point"}
}