{
  "type": "Feature",
  "properties": {
    "addr:full":"828 Kenilworth Dr Baltimore MD 21204",
    "addr:housenumber":"828",
    "addr:postcode":"21204",
    "addr:street":"Kenilworth Dr",
    "iso:country":"US",
    "sg:address":"828 Kenilworth Dr",
    "sg:city":"Baltimore",
    "sg:classifiers":[
        {
            "category":"Shopping",
            "subcategory":"Gifts & Souvenirs",
            "type":"Retail Goods"
        }
    ],
    "sg:phone":"+1 410 296 9199",
    "sg:postcode":"21204",
    "sg:province":"MD",
    "sg:tags":[
        "shop"
    ],
    "wof:name":"Card Connection",
    "wof:placetype":"venue"
},
  "geometry": {"coordinates":[-76.61629499999999,39.41003],"type":"Point"}
}