{
  "type": "Feature",
  "properties": {
    "iso:country":"US",
    "sg:address":"828 Kenilworth Dr",
    "sg:city":"Baltimore",
    "sg:classifiers":[
        {
            "category":"Shopping",
            "subcategory":"Gifts & Souvenirs",
            "type":"Retail Goods"
        }
    ],
    "sg:phone":"+1 410 296 9199",
    "sg:postcode":"21204",
    "sg:province":"MD",
    "sg:tags":[
        "shop"
    ],
    "wof:name":"Card Connection",
    "wof:placetype":"venue"
},
  "geometry": {"coordinates":[-76.61629499999999,39.41003],"type":"Point"}
}