{
  "type": "Feature",
  "properties": {
    "addr:full":"7649 Hayward Rd Frederick MD 21702",
    "addr:housenumber":"7649",
    "addr:postcode":"21702",
    "addr:street":"Hayward Rd",
    "iso:country":"US",
    "sg:address":"7649 Hayward Rd",
    "sg:city":"Frederick",
    "sg:classifiers":[
        {
            "category":"Building & Trades",
            "subcategory":"Equipment Rental",
            "type":"Services"
        }
    ],
    "sg:phone":"+1 301 663 9200",
    "sg:postcode":"21702",
    "sg:province":"MD",
    "sg:tags":[
        "contractor"
    ],
    "sg:website":"www.rentalsunlimited.com",
    "wof:name":"Rentals Unlimited Inc",
    "wof:placetype":"venue"
},
  "geometry": {"coordinates":[-77.400356,39.45576],"type":"Point"}
}