{
  "type": "Feature",
  "properties": {
    "addr:full":"1132 Annapolis Rd Odenton MD 21113",
    "addr:housenumber":"1132",
    "addr:postcode":"21113",
    "addr:street":"Annapolis Rd",
    "iso:country":"US",
    "sg:address":"1132 Annapolis Rd",
    "sg:city":"Odenton",
    "sg:classifiers":[
        {
            "category":"Shopping",
            "subcategory":"Pharmacy",
            "type":"Retail Goods"
        }
    ],
    "sg:phone":"+1 410 519 2460",
    "sg:postcode":"21113",
    "sg:province":"MD",
    "wof:name":"Rite Aid Pharmacy",
    "wof:placetype":"venue"
},
  "geometry": {"coordinates":[-76.681659,39.075358],"type":"Point"}
}