{
  "type": "Feature",
  "properties": {
    "addr:full":"901 S Bond Street Baltimore MD 21231",
    "addr:housenumber":"901",
    "addr:postcode":"21231",
    "addr:street":"S Bond Street",
    "iso:country":"US",
    "sg:address":"901 S Bond Street",
    "sg:city":"Baltimore",
    "sg:classifiers":[
        {
            "category":"Home & Garden",
            "subcategory":"Home Furnishings",
            "type":"Retail Goods"
        }
    ],
    "sg:phone":"+1 410 522 7010",
    "sg:postcode":"21231",
    "sg:province":"MD",
    "sg:tags":[
        "decor"
    ],
    "sg:website":"www.esucasa.com/",
    "wof:name":"Su Casa",
    "wof:placetype":"venue"
},
  "geometry": {"coordinates":[-76.594764,39.280842],"type":"Point"}
}