{
  "type": "Feature",
  "properties": {
    "iso:country":"US",
    "sg:address":"7968 Honeygo Blvd",
    "sg:city":"Baltimore",
    "sg:classifiers":[
        {
            "category":"Food & Beverages",
            "subcategory":"Liquor & Beverages",
            "type":"Retail Goods"
        }
    ],
    "sg:phone":"+1 410 931 4055",
    "sg:postcode":"21236",
    "sg:province":"MD",
    "wof:name":"White Marsh Plaza Liquors",
    "wof:placetype":"venue"
},
  "geometry": {"coordinates":[-76.470892,39.372707],"type":"Point"}
}