{
  "type": "Feature",
  "properties": {
    "iso:country":"US",
    "sg:address":"823-B Elkridge Landing Rd",
    "sg:city":"Linthicum Heights",
    "sg:classifiers":[
        {
            "category":"Restaurant",
            "type":"Food & Drink"
        }
    ],
    "sg:phone":"+1 410 691 0060",
    "sg:postcode":"21090",
    "sg:province":"MD",
    "sg:tags":[
        "traditional",
        "american"
    ],
    "sg:website":"passportbistrolive.com",
    "wof:name":"Passport Bistro",
    "wof:placetype":"venue"
},
  "geometry": {"coordinates":[-76.68490300000001,39.194786],"type":"Point"}
}