{
  "type": "Feature",
  "properties": {
    "addr:full":"211 E Fort Ave Baltimore MD 21230",
    "addr:housenumber":"211",
    "addr:postcode":"21230",
    "addr:street":"E Fort Ave",
    "iso:country":"US",
    "sg:address":"211 E Fort Ave",
    "sg:city":"Baltimore",
    "sg:classifiers":[
        {
            "category":"Home & Garden",
            "subcategory":"Hardware",
            "type":"Retail Goods"
        }
    ],
    "sg:phone":"+1 410 625 1190",
    "sg:postcode":"21230",
    "sg:province":"MD",
    "wof:name":"South Baltimore Supply & Hrdwr",
    "wof:placetype":"venue"
},
  "geometry": {"coordinates":[-76.610052,39.272771],"type":"Point"}
}