{
  "type": "Feature",
  "properties": {
    "addr:full":"6431 Baltimore National Pike Ste 109 Catonsville MD 21228",
    "addr:housenumber":"6431",
    "addr:postcode":"21228",
    "addr:street":"Baltimore National Pike Ste 109",
    "iso:country":"US",
    "sg:address":"6431 Baltimore National Pike Ste 109",
    "sg:city":"Catonsville",
    "sg:classifiers":[
        {
            "category":"Retail",
            "subcategory":"Auto Repair",
            "type":"Services"
        }
    ],
    "sg:phone":"+1 410 869 8080",
    "sg:postcode":"21228",
    "sg:province":"MD",
    "wof:name":"Norm's First Class Automotive",
    "wof:placetype":"venue"
},
  "geometry": {"coordinates":[-76.760049,39.283707],"type":"Point"}
}