{
  "type": "Feature",
  "properties": {
    "addr:full":"5017 Acorn Dr Temple Hills MD 20748",
    "addr:housenumber":"5017",
    "addr:postcode":"20748",
    "addr:street":"Acorn Dr",
    "iso:country":"US",
    "sg:address":"5017 Acorn Dr",
    "sg:city":"Temple Hills",
    "sg:classifiers":[
        {
            "category":"Arts & Performance",
            "subcategory":"Theater",
            "type":"Entertainment"
        }
    ],
    "sg:phone":"+1 301 449 0373",
    "sg:postcode":"20748",
    "sg:province":"MD",
    "sg:tags":[
        "group"
    ],
    "wof:name":"Doreen M Crank",
    "wof:placetype":"venue"
},
  "geometry": {"coordinates":[-76.919811,38.799583],"type":"Point"}
}