{
  "type": "Feature",
  "properties": {
    "addr:full":"1942 Winston Dr Hagerstown MD 21740",
    "addr:housenumber":"1942",
    "addr:postcode":"21740",
    "addr:street":"Winston Dr",
    "iso:country":"US",
    "sg:address":"1942 Winston Dr",
    "sg:city":"Hagerstown",
    "sg:classifiers":[
        {
            "category":"Building & Trades",
            "subcategory":"Electrical",
            "type":"Services"
        }
    ],
    "sg:phone":"+1 301 791 5268",
    "sg:postcode":"21740",
    "sg:province":"MD",
    "sg:tags":[
        "electric",
        "contractor"
    ],
    "wof:name":"Nea Electric",
    "wof:placetype":"venue"
},
  "geometry": {"coordinates":[-77.676732,39.612007],"type":"Point"}
}