{
  "type": "Feature",
  "properties": {
    "addr:full":"1003 Clovis St Baltimore MD 21224",
    "addr:housenumber":"1003",
    "addr:postcode":"21224",
    "addr:street":"Clovis St",
    "iso:country":"US",
    "sg:address":"1003 Clovis St",
    "sg:city":"Baltimore",
    "sg:classifiers":[
        {
            "category":"Manufacturing",
            "subcategory":"Buildings",
            "type":"Manufacturing & Wholesale Goods"
        },
        {
            "category":"Structure",
            "subcategory":"Warehouse",
            "type":"Public Place"
        },
        {
            "category":"Building & Trades",
            "subcategory":"Construction",
            "type":"Services"
        }
    ],
    "sg:phone":"+1 410 288 4076",
    "sg:postcode":"21224",
    "sg:province":"MD",
    "sg:tags":[
        "warehouses-merchandise",
        "warehouses-public-commercial",
        "builder",
        "contractor",
        "home",
        "estimate"
    ],
    "wof:name":"Flaco Construction Inc",
    "wof:placetype":"venue"
},
  "geometry": {"coordinates":[-76.509032,39.286175],"type":"Point"}
}