{
  "type": "Feature",
  "properties": {
    "iso:country":"US",
    "sg:address":"3236 Crain Hwy",
    "sg:city":"Waldorf",
    "sg:classifiers":[
        {
            "category":"Restaurant",
            "type":"Food & Drink"
        }
    ],
    "sg:phone":"+1 301 645 9390",
    "sg:postcode":"20603",
    "sg:province":"MD",
    "sg:website":"http://theoriginalszechuangarden.com",
    "wof:name":"Szechuan Garden Restaurant",
    "wof:placetype":"venue"
},
  "geometry": {"coordinates":[-76.914013,38.62286],"type":"Point"}
}