{
  "type": "Feature",
  "properties": {
    "addr:full":"308 S Main St Woodsboro MD 21798",
    "addr:housenumber":"308",
    "addr:postcode":"21798",
    "addr:street":"S Main St",
    "iso:country":"US",
    "sg:address":"308 S Main St",
    "sg:city":"Woodsboro",
    "sg:classifiers":[
        {
            "category":"Building & Trades",
            "subcategory":"Construction",
            "type":"Services"
        }
    ],
    "sg:phone":"+1 301 898 9098",
    "sg:postcode":"21798",
    "sg:province":"MD",
    "sg:tags":[
        "shop",
        "siding",
        "fix-it",
        "contractor"
    ],
    "sg:website":"http://www.troutvillehomerepairs.com",
    "wof:name":"Troutville Home Repairs Inc",
    "wof:placetype":"venue"
},
  "geometry": {"coordinates":[-77.314857,39.531029],"type":"Point"}
}