{
  "type": "Feature",
  "properties": {
    "iso:country":"US",
    "sg:address":"4124 Howard Ave",
    "sg:city":"Kensington",
    "sg:classifiers":[
        {
            "category":"Home & Garden",
            "subcategory":"Home Furnishings",
            "type":"Retail Goods"
        },
        {
            "category":"Home & Garden",
            "subcategory":"Building Materials",
            "type":"Retail Goods"
        },
        {
            "category":"Building & Trades",
            "subcategory":"Construction",
            "type":"Services"
        },
        {
            "category":"Manufacturing",
            "subcategory":"Building Materials",
            "type":"Manufacturing & Wholesale Goods"
        }
    ],
    "sg:phone":"+1 301 571 4200",
    "sg:postcode":"20895",
    "sg:province":"MD",
    "sg:tags":[
        "bathroom",
        "altering",
        "consultant",
        "top",
        "counter",
        "surface",
        "contractor",
        "solid",
        "sinks-repair",
        "bathtub",
        "remodeling",
        "refinish"
    ],
    "sg:website":"http://www.miraclemethod.com/bathtub-refinishing-washington-dc.php",
    "wof:name":"Miracle Method",
    "wof:placetype":"venue"
},
  "geometry": {"coordinates":[-77.079892,39.030331],"type":"Point"}
}