{
  "type": "Feature",
  "properties": {
    "iso:country":"US",
    "sg:address":"12641 Ocean Gtwy",
    "sg:city":"Ocean City",
    "sg:classifiers":[
        {
            "category":"Restaurant",
            "type":"Food & Drink"
        }
    ],
    "sg:menulink":"http://www.allmenus.com/md/ocean-city/176318-kfc---kentucky-fried-chicken/menu/",
    "sg:phone":"+1 410 213 2553",
    "sg:postcode":"21842",
    "sg:province":"MD",
    "sg:tags":[
        "american",
        "chicken"
    ],
    "wof:name":"KFC - Kentucky Fried Chicken",
    "wof:placetype":"venue"
},
  "geometry": {"coordinates":[-75.100486,38.334984],"type":"Point"}
}