{
  "type": "Feature",
  "properties": {
    "addr:full":"832 S Bond St Baltimore MD 21231",
    "addr:housenumber":"832",
    "addr:postcode":"21231",
    "addr:street":"S Bond St",
    "iso:country":"US",
    "sg:address":"832 S Bond St",
    "sg:city":"Baltimore",
    "sg:classifiers":[
        {
            "category":"Manufacturing",
            "subcategory":"Building Materials",
            "type":"Manufacturing & Wholesale Goods"
        },
        {
            "category":"Home & Garden",
            "subcategory":"Carpets & Floor Coverings",
            "type":"Retail Goods"
        }
    ],
    "sg:phone":"+1 410 522 2244",
    "sg:postcode":"21231",
    "sg:province":"MD",
    "sg:tags":[
        "materials-wholesale",
        "carpeting",
        "manufacturer"
    ],
    "sg:website":"http://www.corridorflooring.com",
    "wof:name":"Corridor Flooring Associates",
    "wof:placetype":"venue"
},
  "geometry": {"coordinates":[-76.5951,39.2813],"type":"Point"}
}