{
  "type": "Feature",
  "properties": {
    "addr:full":"14308 Marian Dr Rockville MD 20850",
    "addr:housenumber":"14308",
    "addr:postcode":"20850",
    "addr:street":"Marian Dr",
    "iso:country":"US",
    "sg:address":"14308 Marian Dr",
    "sg:city":"Rockville",
    "sg:classifiers":[
        {
            "category":"Real Estate",
            "subcategory":"Real Estate Agent",
            "type":"Services"
        }
    ],
    "sg:phone":"+1 301 948 9191",
    "sg:postcode":"20850",
    "sg:province":"MD",
    "wof:name":"Hightower Real Estate Inc",
    "wof:placetype":"venue"
},
  "geometry": {"coordinates":[-77.196654,39.09094],"type":"Point"}
}