{
  "type": "Feature",
  "properties": {
    "iso:country":"US",
    "sg:address":"22335 Exploration Dr",
    "sg:city":"Lexington Park",
    "sg:classifiers":[
        {
            "category":"Professional",
            "subcategory":"Lawyer & Legal Services",
            "type":"Services"
        }
    ],
    "sg:phone":"+1 301 862 4400",
    "sg:postcode":"20653",
    "sg:province":"MD",
    "sg:website":"www.baldwinbriscoe.com",
    "wof:name":"Baldwin Samuel C P Jr Atty",
    "wof:placetype":"venue"
},
  "geometry": {"coordinates":[-76.466499,38.278599],"type":"Point"}
}