{
  "type": "Feature",
  "properties": {
    "addr:full":"8243 Friendsville Rd Friendsville MD 21531",
    "addr:housenumber":"8243",
    "addr:postcode":"21531",
    "addr:street":"Friendsville Rd",
    "iso:country":"US",
    "sg:address":"8243 Friendsville Rd",
    "sg:city":"Friendsville",
    "sg:classifiers":[
        {
            "category":"Personal",
            "subcategory":"Beauty Salon",
            "type":"Services"
        }
    ],
    "sg:phone":"+1 301 746 5400",
    "sg:postcode":"21531",
    "sg:province":"MD",
    "sg:tags":[
        "shop"
    ],
    "wof:name":"Jan's Hair Styling",
    "wof:placetype":"venue"
},
  "geometry": {"coordinates":[-79.41895599999999,39.663898],"type":"Point"}
}