{
  "type": "Feature",
  "properties": {
    "iso:country":"US",
    "sg:address":"9411 Colesville Rd",
    "sg:city":"Silver Spring",
    "sg:classifiers":[
        {
            "category":"Insurance",
            "subcategory":"Insurance Agent",
            "type":"Services"
        }
    ],
    "sg:phone":"+1 301 920 0409",
    "sg:postcode":"20901",
    "sg:province":"MD",
    "wof:name":"Servimax LLC",
    "wof:placetype":"venue"
},
  "geometry": {"coordinates":[-77.01741800000001,39.010476],"type":"Point"}
}