{
  "type": "Feature",
  "properties": {
    "iso:country":"US",
    "sg:address":"18740 Mesa Ter",
    "sg:city":"Hagerstown",
    "sg:classifiers":[
        {
            "category":"Manufacturing",
            "subcategory":"Buildings",
            "type":"Manufacturing & Wholesale Goods"
        },
        {
            "category":"Building & Trades",
            "subcategory":"Construction",
            "type":"Services"
        }
    ],
    "sg:phone":"+1 301 988 5206",
    "sg:postcode":"21742",
    "sg:province":"MD",
    "sg:tags":[
        "home",
        "builder",
        "contractor"
    ],
    "wof:name":"Greg Adkins",
    "wof:placetype":"venue"
},
  "geometry": {"coordinates":[-77.72126299999999,39.698018],"type":"Point"}
}