{
  "type": "Feature",
  "properties": {
    "addr:full":"2037 York Rd Timonium MD 21093",
    "addr:housenumber":"2037",
    "addr:postcode":"21093",
    "addr:street":"York Rd",
    "iso:country":"US",
    "sg:address":"2037 York Rd",
    "sg:city":"Timonium",
    "sg:classifiers":[
        {
            "category":"Building & Trades",
            "subcategory":"Construction",
            "type":"Services"
        }
    ],
    "sg:phone":"+1 410 560 1423",
    "sg:postcode":"21093",
    "sg:province":"MD",
    "sg:tags":[
        "concrete",
        "contractor"
    ],
    "wof:name":"Sody Concrete Construction Inc",
    "wof:placetype":"venue"
},
  "geometry": {"coordinates":[-76.62488500000001,39.437844],"type":"Point"}
}