{
  "type": "Feature",
  "properties": {
    "iso:country":"US",
    "sg:address":"7474 Landover Rd",
    "sg:city":"Landover",
    "sg:classifiers":[
        {
            "category":"Retail",
            "subcategory":"Funeral Services",
            "type":"Services"
        }
    ],
    "sg:phone":"+1 301 322 2300",
    "sg:postcode":"20785",
    "sg:province":"MD",
    "sg:tags":[
        "director"
    ],
    "wof:name":"J B Jenkins Funeral Home",
    "wof:placetype":"venue"
},
  "geometry": {"coordinates":[-76.88802800000001,38.926762],"type":"Point"}
}