{
  "type": "Feature",
  "properties": {
    "iso:country":"US",
    "sg:address":"11950 Bargate Ct",
    "sg:city":"Rockville",
    "sg:classifiers":[
        {
            "category":"Education",
            "subcategory":"Special Training",
            "type":"Public Place"
        }
    ],
    "sg:phone":"+1 301 231 0526",
    "sg:postcode":"20852",
    "sg:province":"MD",
    "sg:tags":[
        "instructor"
    ],
    "wof:name":"Queiroz Vctria Mria Frriria De",
    "wof:placetype":"venue"
},
  "geometry": {"coordinates":[-77.132141,39.052649],"type":"Point"}
}