{
  "type": "Feature",
  "properties": {
    "addr:full":"3508 Offutt Rd Randallstown MD 21133",
    "addr:housenumber":"3508",
    "addr:postcode":"21133",
    "addr:street":"Offutt Rd",
    "iso:country":"US",
    "sg:address":"3508 Offutt Rd",
    "sg:city":"Randallstown",
    "sg:classifiers":[
        {
            "category":"Retail",
            "subcategory":"Auto Repair",
            "type":"Services"
        }
    ],
    "sg:phone":"+1 410 521 4770",
    "sg:postcode":"21133",
    "sg:province":"MD",
    "sg:tags":[
        "body",
        "automobile",
        "painting"
    ],
    "wof:name":"Automotive Collision Tech Inc",
    "wof:placetype":"venue"
},
  "geometry": {"coordinates":[-76.79976499999999,39.368568],"type":"Point"}
}