{
  "type": "Feature",
  "properties": {
    "addr:full":"25384 Goldsboro Rd Henderson MD 21640",
    "addr:housenumber":"25384",
    "addr:postcode":"21640",
    "addr:street":"Goldsboro Rd",
    "iso:country":"US",
    "sg:address":"25384 Goldsboro Rd",
    "sg:city":"Henderson",
    "sg:classifiers":[
        {
            "category":"Shopping",
            "subcategory":"Catalog Store",
            "type":"Retail Goods"
        }
    ],
    "sg:phone":"+1 410 441 0463",
    "sg:postcode":"21640",
    "sg:province":"MD",
    "sg:tags":[
        "mail",
        "order",
        "online"
    ],
    "wof:name":"Pamela L Lloyd",
    "wof:placetype":"venue"
},
  "geometry": {"coordinates":[-75.821178,39.046108],"type":"Point"}
}