{
  "type": "Feature",
  "properties": {
    "addr:full":"8016 Cindy Ln Bethesda MD 20817",
    "addr:housenumber":"8016",
    "addr:postcode":"20817",
    "addr:street":"Cindy Ln",
    "iso:country":"US",
    "sg:address":"8016 Cindy Ln",
    "sg:city":"Bethesda",
    "sg:classifiers":[
        {
            "category":"Professional",
            "subcategory":"Management & Consulting",
            "type":"Services"
        }
    ],
    "sg:phone":"+1 301 469 0827",
    "sg:postcode":"20817",
    "sg:province":"MD",
    "sg:tags":[
        "consultant",
        "business"
    ],
    "wof:name":"Innovative Management Systems",
    "wof:placetype":"venue"
},
  "geometry": {"coordinates":[-77.166117,39.000719],"type":"Point"}
}