{
  "type": "Feature",
  "properties": {
    "iso:country":"US",
    "sg:address":"3624 Anton Farms Rd",
    "sg:city":"Pikesville",
    "sg:classifiers":[
        {
            "category":"Real Estate",
            "subcategory":"Real Estate Agent",
            "type":"Services"
        }
    ],
    "sg:phone":"+1 410 486 9000",
    "sg:postcode":"21208",
    "sg:province":"MD",
    "wof:name":"Admiral Properties Inc",
    "wof:placetype":"venue"
},
  "geometry": {"coordinates":[-76.714711,39.398855],"type":"Point"}
}