{
  "type": "Feature",
  "properties": {
    "addr:full":"3624 Anton Farms Rd Pikesville MD 21208",
    "addr:housenumber":"3624",
    "addr:postcode":"21208",
    "addr:street":"Anton Farms Rd",
    "iso:country":"US",
    "sg:address":"3624 Anton Farms Rd",
    "sg:city":"Pikesville",
    "sg:classifiers":[
        {
            "category":"Real Estate",
            "subcategory":"Real Estate Agent",
            "type":"Services"
        }
    ],
    "sg:phone":"+1 410 486 9000",
    "sg:postcode":"21208",
    "sg:province":"MD",
    "wof:name":"Admiral Properties Inc",
    "wof:placetype":"venue"
},
  "geometry": {"coordinates":[-76.71471099999999,39.398855],"type":"Point"}
}