{
  "type": "Feature",
  "properties": {
    "iso:country":"US",
    "sg:address":"10753 Falls Rd",
    "sg:city":"Lutherville",
    "sg:classifiers":[
        {
            "category":"Professional",
            "type":"Services"
        }
    ],
    "sg:phone":"+1 410 583 2707",
    "sg:postcode":"21093",
    "sg:province":"MD",
    "sg:tags":[
        "establishment"
    ],
    "wof:name":"Ultrasound At Greenspring Stat",
    "wof:placetype":"venue"
},
  "geometry": {"coordinates":[-76.670151,39.420759],"type":"Point"}
}