{
  "type": "Feature",
  "properties": {
    "iso:country":"US",
    "sg:address":"117 Roesler Rd",
    "sg:city":"Glen Burnie",
    "sg:classifiers":[
        {
            "category":"Professional",
            "type":"Services"
        }
    ],
    "sg:phone":"+1 301 261 2282",
    "sg:postcode":"21060",
    "sg:province":"MD",
    "wof:name":"Hexatrac Inc",
    "wof:placetype":"venue"
},
  "geometry": {"coordinates":[-76.615645,39.177525],"type":"Point"}
}