{
  "type": "Feature",
  "properties": {
    "iso:country":"US",
    "sg:address":"107 E Preston St",
    "sg:city":"Baltimore",
    "sg:classifiers":[
        {
            "category":"Restaurant",
            "type":"Food & Drink"
        }
    ],
    "sg:phone":"+1 410 234 9866",
    "sg:postcode":"21202",
    "sg:province":"MD",
    "wof:name":"Tiki Temple Juice & Vegetarian",
    "wof:placetype":"venue"
},
  "geometry": {"coordinates":[-76.613385,39.304632],"type":"Point"}
}