{
  "type": "Feature",
  "properties": {
    "addr:full":"1130 Gypsy Ln W Towson MD 21286",
    "addr:housenumber":"1130",
    "addr:postcode":"21286",
    "addr:street":"Gypsy Ln W",
    "iso:country":"US",
    "sg:address":"1130 Gypsy Ln W",
    "sg:city":"Towson",
    "sg:classifiers":[
        {
            "category":"Shopping",
            "subcategory":"Hobbies, Toys, & Games",
            "type":"Retail Goods"
        }
    ],
    "sg:phone":"+1 410 448 2610",
    "sg:postcode":"21286",
    "sg:province":"MD",
    "sg:tags":[
        "coin",
        "supply"
    ],
    "wof:name":"Richard Gross Rare Coins Inc",
    "wof:placetype":"venue"
},
  "geometry": {"coordinates":[-76.585035,39.415028],"type":"Point"}
}