{
  "type": "Feature",
  "properties": {
    "iso:country":"US",
    "sg:address":"107 Market St",
    "sg:city":"Gaithersburg",
    "sg:classifiers":[
        {
            "category":"Home & Garden",
            "subcategory":"Home Furnishings",
            "type":"Retail Goods"
        }
    ],
    "sg:phone":"+1 301 977 8555",
    "sg:postcode":"20878",
    "sg:province":"MD",
    "sg:tags":[
        "window",
        "covering"
    ],
    "wof:name":"Next Day Blinds",
    "wof:placetype":"venue"
},
  "geometry": {"coordinates":[-77.235077,39.122103],"type":"Point"}
}