{
  "type": "Feature",
  "properties": {
    "addr:full":"23042 Pembrook Dr Hollywood MD 20636",
    "addr:housenumber":"23042",
    "addr:postcode":"20636",
    "addr:street":"Pembrook Dr",
    "iso:country":"US",
    "sg:address":"23042 Pembrook Dr",
    "sg:city":"Hollywood",
    "sg:classifiers":[
        {
            "category":"Professional",
            "subcategory":"Employment Agencies",
            "type":"Services"
        }
    ],
    "sg:phone":"+1 301 475 1551",
    "sg:postcode":"20636",
    "sg:province":"MD",
    "sg:tags":[
        "employer"
    ],
    "wof:name":"Get Organized Soluti",
    "wof:placetype":"venue"
},
  "geometry": {"coordinates":[-76.581575,38.30486],"type":"Point"}
}