{
  "type": "Feature",
  "properties": {
    "iso:country":"US",
    "sg:address":"3829 Mount Olney Ln",
    "sg:city":"Olney",
    "sg:classifiers":[
        {
            "category":"Communications",
            "type":"Services"
        }
    ],
    "sg:phone":"+1 301 774 2329",
    "sg:postcode":"20832",
    "sg:province":"MD",
    "sg:tags":[
        "consultant",
        "engineer"
    ],
    "wof:name":"Adorable U Custom Caps",
    "wof:placetype":"venue"
},
  "geometry": {"coordinates":[-77.074276,39.171793],"type":"Point"}
}