{
  "type": "Feature",
  "properties": {
    "iso:country":"US",
    "sg:address":"337 Annapolis Mall",
    "sg:city":"Annapolis",
    "sg:classifiers":[
        {
            "category":"Shopping",
            "subcategory":"Jewelry",
            "type":"Retail Goods"
        },
        {
            "category":"Manufacturing",
            "subcategory":"Jewelry",
            "type":"Manufacturing & Wholesale Goods"
        }
    ],
    "sg:phone":"+1 410 573 0600",
    "sg:postcode":"21401",
    "sg:province":"MD",
    "sg:tags":[
        "designer",
        "jeweler"
    ],
    "wof:name":"Gold Palace",
    "wof:placetype":"venue"
},
  "geometry": {"coordinates":[-76.504448,38.991711],"type":"Point"}
}