{
  "type": "Feature",
  "properties": {
    "addr:full":"851 Brightseat Rd Landover MD 20785",
    "addr:housenumber":"851",
    "addr:postcode":"20785",
    "addr:street":"Brightseat Rd",
    "iso:country":"US",
    "sg:address":"851 Brightseat Rd",
    "sg:city":"Landover",
    "sg:classifiers":[
        {
            "category":"Retail",
            "subcategory":"Laundry & Dry Cleaning",
            "type":"Services"
        }
    ],
    "sg:phone":"+1 301 877 7183",
    "sg:postcode":"20785",
    "sg:province":"MD",
    "sg:tags":[
        "cleaners",
        "rug",
        "carpet"
    ],
    "wof:name":"Centurion National Corp",
    "wof:placetype":"venue"
},
  "geometry": {"coordinates":[-76.85321399999999,38.900243],"type":"Point"}
}