{
  "type": "Feature",
  "properties": {
    "iso:country":"US",
    "sg:address":"Owings Court Profess",
    "sg:city":"Reisterstown",
    "sg:classifiers":[
        {
            "category":"Health Services",
            "subcategory":"Doctor",
            "type":"Services"
        }
    ],
    "sg:phone":"+1 410 833 3742",
    "sg:postcode":"21136",
    "sg:province":"MD",
    "sg:tags":[
        "surgeon",
        "oral"
    ],
    "wof:name":"Garfinkel Allan V DDS",
    "wof:placetype":"venue"
},
  "geometry": {"coordinates":[-76.80909699999999,39.4636],"type":"Point"}
}