{
  "type": "Feature",
  "properties": {
    "addr:full":"5500 Buckeystown Pike Ste K7 Frederick MD 21703",
    "addr:housenumber":"5500",
    "addr:postcode":"21703",
    "addr:street":"Buckeystown Pike Ste K7",
    "iso:country":"US",
    "sg:address":"5500 Buckeystown Pike Ste K7",
    "sg:city":"Frederick",
    "sg:classifiers":[
        {
            "category":"Utilities",
            "subcategory":"Mobile Phone",
            "type":"Services"
        },
        {
            "category":"Shopping",
            "subcategory":"Mobile Phones",
            "type":"Retail Goods"
        },
        {
            "category":"Utilities",
            "subcategory":"Telephone",
            "type":"Services"
        },
        {
            "category":"Professional",
            "subcategory":"Computer Services",
            "type":"Services"
        }
    ],
    "sg:phone":"+1 301 620 2400",
    "sg:postcode":"21703",
    "sg:province":"MD",
    "sg:tags":[
        "telecommunication",
        "supply",
        "communication",
        "system",
        "wireless",
        "equipment",
        "cellular"
    ],
    "sg:website":"http://clickserve.dartsearch.net/link/click?lid=43000000308049899",
    "wof:name":"T-Mobile",
    "wof:placetype":"venue"
},
  "geometry": {"coordinates":[-77.409569,39.384708],"type":"Point"}
}