{
  "type": "Feature",
  "properties": {
    "addr:full":"8480 Baltimore National Pike Ellicott City MD 21043",
    "addr:housenumber":"8480",
    "addr:postcode":"21043",
    "addr:street":"Baltimore National Pike",
    "iso:country":"US",
    "sg:address":"8480 Baltimore National Pike",
    "sg:city":"Ellicott City",
    "sg:classifiers":[
        {
            "category":"Insurance",
            "subcategory":"Insurance Agent",
            "type":"Services"
        }
    ],
    "sg:phone":"+1 410 465 9094",
    "sg:postcode":"21043",
    "sg:province":"MD",
    "wof:name":"David C Parkhurst",
    "wof:placetype":"venue"
},
  "geometry": {"coordinates":[-76.807863,39.284517],"type":"Point"}
}