{
  "type": "Feature",
  "properties": {
    "addr:full":"329 S Kresson St Baltimore MD 21224",
    "addr:housenumber":"329",
    "addr:postcode":"21224",
    "addr:street":"S Kresson St",
    "iso:country":"US",
    "sg:address":"329 S Kresson St",
    "sg:city":"Baltimore",
    "sg:classifiers":[
        {
            "category":"Building & Trades",
            "subcategory":"Equipment Rental",
            "type":"Services"
        }
    ],
    "sg:phone":"+1 410 563 4007",
    "sg:postcode":"21224",
    "sg:province":"MD",
    "sg:tags":[
        "yard",
        "leasing",
        "store"
    ],
    "wof:name":"Setco Scenic Services",
    "wof:placetype":"venue"
},
  "geometry": {"coordinates":[-76.559668,39.288859],"type":"Point"}
}