{
  "type": "Feature",
  "properties": {
    "addr:full":"1448 W Patrick St Frederick MD 21702",
    "addr:housenumber":"1448",
    "addr:postcode":"21702",
    "addr:street":"W Patrick St",
    "iso:country":"US",
    "sg:address":"1448 W Patrick St",
    "sg:city":"Frederick",
    "sg:classifiers":[
        {
            "category":"Restaurant",
            "type":"Food & Drink"
        }
    ],
    "sg:menulink":"http://www.allmenus.com/md/frederick/197137-burger-king/menu/",
    "sg:phone":"+1 301 620 9611",
    "sg:postcode":"21702",
    "sg:province":"MD",
    "sg:tags":[
        "burger",
        "american"
    ],
    "wof:name":"Burger King",
    "wof:placetype":"venue"
},
  "geometry": {"coordinates":[-77.464344,39.420866],"type":"Point"}
}