{
  "type": "Feature",
  "properties": {
    "addr:full":"8168 Elliott Rd Easton MD 21601",
    "addr:housenumber":"8168",
    "addr:postcode":"21601",
    "addr:street":"Elliott Rd",
    "iso:country":"US",
    "sg:address":"8168 Elliott Rd",
    "sg:city":"Easton",
    "sg:classifiers":[
        {
            "category":"Shopping",
            "subcategory":"Stationery & Office Supplies",
            "type":"Retail Goods"
        }
    ],
    "sg:phone":"+1 410 770 3839",
    "sg:postcode":"21601",
    "sg:province":"MD",
    "wof:name":"Staples The Office Superstore",
    "wof:placetype":"venue"
},
  "geometry": {"coordinates":[-76.05690199999999,38.774944],"type":"Point"}
}