{
  "type": "Feature",
  "properties": {
    "addr:full":"31768 Dagsboro Rd Delmar MD 21875",
    "addr:postcode":"31768;21875",
    "addr:street":"Dagsboro Rd",
    "iso:country":"US",
    "sg:address":"31768 Dagsboro Rd",
    "sg:city":"Delmar",
    "sg:classifiers":[
        {
            "category":"Professional",
            "subcategory":"Testing Lab",
            "type":"Services"
        },
        {
            "category":"Health Services",
            "subcategory":"Medical Lab",
            "type":"Services"
        },
        {
            "category":"Health Services",
            "subcategory":"Dentist",
            "type":"Services"
        }
    ],
    "sg:phone":"+1 410 546 0670",
    "sg:postcode":"21875",
    "sg:province":"MD",
    "sg:tags":[
        "laboratory",
        "dental",
        "clinic"
    ],
    "wof:name":"Creative Crown & Bridge Dental Lab Inc",
    "wof:placetype":"venue"
},
  "geometry": {"coordinates":[-75.479416,38.415024],"type":"Point"}
}