{
  "type": "Feature",
  "properties": {
    "addr:full":"2181 Misty Meadow Rd Finksburg MD 21048",
    "addr:housenumber":"2181",
    "addr:postcode":"21048",
    "addr:street":"Misty Meadow Rd",
    "iso:country":"US",
    "sg:address":"2181 Misty Meadow Rd",
    "sg:city":"Finksburg",
    "sg:classifiers":[
        {
            "category":"Shopping",
            "subcategory":"Computers & Home Electronics",
            "type":"Retail Goods"
        },
        {
            "category":"Wholesale",
            "subcategory":"Computers",
            "type":"Manufacturing & Wholesale Goods"
        }
    ],
    "sg:phone":"+1 410 751 3795",
    "sg:postcode":"21048",
    "sg:province":"MD",
    "sg:tags":[
        "equipment",
        "printer",
        "supply"
    ],
    "wof:name":"Chesapeake Systems",
    "wof:placetype":"venue"
},
  "geometry": {"coordinates":[-76.916495,39.503612],"type":"Point"}
}