{
  "type": "Feature",
  "properties": {
    "iso:country":"US",
    "sg:address":"55 E Oak St",
    "sg:city":"Oakland",
    "sg:classifiers":[
        {
            "category":"Professional",
            "subcategory":"Computer Services",
            "type":"Services"
        }
    ],
    "sg:phone":"+1 301 334 2666",
    "sg:postcode":"21550",
    "sg:province":"MD",
    "sg:tags":[
        "consultant",
        "designer"
    ],
    "sg:website":"www.pennswoods.net",
    "wof:name":"PENNSWOODS.NET",
    "wof:placetype":"venue"
},
  "geometry": {"coordinates":[-79.4104,39.407972],"type":"Point"}
}