{
  "type": "Feature",
  "properties": {
    "addr:full":"174 Landons Dam Rd Oakland MD 21550",
    "addr:housenumber":"174",
    "addr:postcode":"21550",
    "addr:street":"Landons Dam Rd",
    "iso:country":"US",
    "sg:address":"174 Landons Dam Rd",
    "sg:city":"Oakland",
    "sg:classifiers":[
        {
            "category":"Manufacturing",
            "subcategory":"Furniture",
            "type":"Manufacturing & Wholesale Goods"
        }
    ],
    "sg:phone":"+1 301 334 2980",
    "sg:postcode":"21550",
    "sg:province":"MD",
    "sg:tags":[
        "household",
        "wood",
        "mfg"
    ],
    "wof:name":"Swiss Valley Craft",
    "wof:placetype":"venue"
},
  "geometry": {"coordinates":[-79.368977,39.369753],"type":"Point"}
}