{
  "type": "Feature",
  "properties": {
    "iso:country":"US",
    "sg:address":"204 Somerset Ct",
    "sg:city":"Queenstown",
    "sg:classifiers":[
        {
            "category":"Building & Trades",
            "subcategory":"Construction",
            "type":"Services"
        }
    ],
    "sg:phone":"+1 410 827 9211",
    "sg:postcode":"21658",
    "sg:province":"MD",
    "sg:tags":[
        "residential"
    ],
    "wof:name":"S & S Homes",
    "wof:placetype":"venue"
},
  "geometry": {"coordinates":[-76.17574399999999,38.914053],"type":"Point"}
}