{
  "type": "Feature",
  "properties": {
    "addr:full":"111 W Lexington St Baltimore MD 21201",
    "addr:housenumber":"111",
    "addr:postcode":"21201",
    "addr:street":"W Lexington St",
    "iso:country":"US",
    "sg:address":"111 W Lexington St",
    "sg:city":"Baltimore",
    "sg:classifiers":[
        {
            "category":"Shopping",
            "subcategory":"Optical Goods",
            "type":"Retail Goods"
        }
    ],
    "sg:phone":"+1 410 727 7310",
    "sg:postcode":"21201",
    "sg:province":"MD",
    "sg:tags":[
        "contact",
        "lense"
    ],
    "wof:name":"Maryland Optical Co",
    "wof:placetype":"venue"
},
  "geometry": {"coordinates":[-76.61798400000001,39.291576],"type":"Point"}
}