{
  "type": "Feature",
  "properties": {
    "iso:country":"US",
    "sg:address":"38 Gwynns Mill Ct",
    "sg:city":"Owings Mills",
    "sg:classifiers":[
        {
            "category":"Restaurant",
            "type":"Food & Drink"
        }
    ],
    "sg:phone":"+1 410 363 7802",
    "sg:postcode":"21117",
    "sg:province":"MD",
    "sg:tags":[
        "parlor",
        "ice",
        "cream"
    ],
    "wof:name":"Totally Cool Inc",
    "wof:placetype":"venue"
},
  "geometry": {"coordinates":[-76.78137700000001,39.415704],"type":"Point"}
}