{
  "type": "Feature",
  "properties": {
    "addr:full":"2504 Ennalls Ave Wheaton MD 20902",
    "addr:housenumber":"2504",
    "addr:postcode":"20902",
    "addr:street":"Ennalls Ave",
    "iso:country":"US",
    "sg:address":"2504 Ennalls Ave",
    "sg:city":"Wheaton",
    "sg:classifiers":[
        {
            "category":"Restaurant",
            "type":"Food & Drink"
        }
    ],
    "sg:phone":"+1 301 942 7859",
    "sg:postcode":"20902",
    "sg:province":"MD",
    "wof:name":"Sabang Restaurant",
    "wof:placetype":"venue"
},
  "geometry": {"coordinates":[-77.053718,39.039045],"type":"Point"}
}