{
  "type": "Feature",
  "properties": {
    "iso:country":"US",
    "sg:address":"25 E Chestnut Hill Ln",
    "sg:city":"Reisterstown",
    "sg:classifiers":[
        {
            "category":"Social Services",
            "subcategory":"Child Care",
            "type":"Services"
        }
    ],
    "sg:phone":"+1 410 833 5529",
    "sg:postcode":"21136",
    "sg:province":"MD",
    "sg:website":"www.reisterstownbaptist.org",
    "wof:name":"Reisterstown Bapt Chr-Day Care",
    "wof:placetype":"venue"
},
  "geometry": {"coordinates":[-76.810057,39.44829],"type":"Point"}
}