{
  "type": "Feature",
  "properties": {
    "addr:full":"2221 Cape Leonard Dr Saint Leonard MD 20685",
    "addr:housenumber":"2221",
    "addr:postcode":"20685",
    "addr:street":"Cape Leonard Dr",
    "iso:country":"US",
    "sg:address":"2221 Cape Leonard Dr",
    "sg:city":"Saint Leonard",
    "sg:classifiers":[
        {
            "category":"Building & Trades",
            "subcategory":"Construction",
            "type":"Services"
        }
    ],
    "sg:phone":"+1 301 855 1628",
    "sg:postcode":"20685",
    "sg:province":"MD",
    "sg:tags":[
        "hanging",
        "contractor"
    ],
    "wof:name":"Wright Decorators",
    "wof:placetype":"venue"
},
  "geometry": {"coordinates":[-76.49120499999999,38.403534],"type":"Point"}
}