{
  "type": "Feature",
  "properties": {
    "iso:country":"US",
    "sg:address":"8213 Windsor View Ter",
    "sg:city":"Potomac",
    "sg:classifiers":[
        {
            "category":"Restaurant",
            "type":"Food & Drink"
        }
    ],
    "sg:phone":"+1 301 983 9190",
    "sg:postcode":"20854",
    "sg:province":"MD",
    "sg:tags":[
        "mfg",
        "eating",
        "jewelry",
        "costume"
    ],
    "wof:name":"Pies Shelia Jewelry",
    "wof:placetype":"venue"
},
  "geometry": {"coordinates":[-77.170723,39.025148],"type":"Point"}
}