{
  "type": "Feature",
  "properties": {
    "addr:full":"6200 Columbia Park Rd Landover MD 20785",
    "addr:housenumber":"6200",
    "addr:postcode":"20785",
    "addr:street":"Columbia Park Rd",
    "iso:country":"US",
    "sg:address":"6200 Columbia Park Rd",
    "sg:city":"Landover",
    "sg:classifiers":[
        {
            "category":"Local Transit",
            "type":"Transportation"
        }
    ],
    "sg:phone":"+1 301 773 3399",
    "sg:postcode":"20785",
    "sg:province":"MD",
    "sg:tags":[
        "limousine"
    ],
    "sg:website":"www.davel.com",
    "wof:name":"Dav El Baltimore Inc",
    "wof:placetype":"venue"
},
  "geometry": {"coordinates":[-76.900779,38.917944],"type":"Point"}
}