{
  "type": "Feature",
  "properties": {
    "addr:full":"7850 Walker Dr Greenbelt MD 20770",
    "addr:housenumber":"7850",
    "addr:postcode":"20770",
    "addr:street":"Walker Dr",
    "iso:country":"US",
    "sg:address":"7850 Walker Dr",
    "sg:city":"Greenbelt",
    "sg:classifiers":[
        {
            "category":"Real Estate",
            "subcategory":"Real Estate Services",
            "type":"Services"
        }
    ],
    "sg:phone":"+1 301 623 1502",
    "sg:postcode":"20770",
    "sg:province":"MD",
    "sg:tags":[
        "management"
    ],
    "wof:name":"Silverwood Apartments",
    "wof:placetype":"venue"
},
  "geometry": {"coordinates":[-76.895054,38.997973],"type":"Point"}
}