{
  "type": "Feature",
  "properties": {
    "addr:full":"616 Firestone Dr Silver Spring MD 20905",
    "addr:housenumber":"616",
    "addr:postcode":"20905",
    "addr:street":"Firestone Dr",
    "iso:country":"US",
    "sg:address":"616 Firestone Dr",
    "sg:city":"Silver Spring",
    "sg:classifiers":[
        {
            "category":"Sports & Exercise",
            "subcategory":"Golf",
            "type":"Entertainment"
        }
    ],
    "sg:phone":"+1 301 476 7999",
    "sg:postcode":"20905",
    "sg:province":"MD",
    "sg:tags":[
        "course"
    ],
    "sg:website":"www.montgomerycountygolf.com",
    "wof:name":"Hampshire Greens Golf Course",
    "wof:placetype":"venue"
},
  "geometry": {"coordinates":[-77.001884,39.126501],"type":"Point"}
}