{
  "type": "Feature",
  "properties": {
    "iso:country":"US",
    "sg:address":"8300 Gue Rd",
    "sg:city":"Damascus",
    "sg:classifiers":[
        {
            "category":"Professional",
            "subcategory":"Art Services",
            "type":"Services"
        }
    ],
    "sg:phone":"+1 301 253 5407",
    "sg:postcode":"20872",
    "sg:province":"MD",
    "sg:tags":[
        "photography",
        "commercial"
    ],
    "wof:name":"Trade Winds",
    "wof:placetype":"venue"
},
  "geometry": {"coordinates":[-77.165045,39.299972],"type":"Point"}
}