{
  "type": "Feature",
  "properties": {
    "iso:country":"US",
    "sg:address":"5249 Kenilworth Ave",
    "sg:city":"Hyattsville",
    "sg:classifiers":[
        {
            "category":"Home & Garden",
            "subcategory":"Furniture",
            "type":"Retail Goods"
        }
    ],
    "sg:phone":"+1 301 927 0141",
    "sg:postcode":"20781",
    "sg:province":"MD",
    "sg:tags":[
        "sales"
    ],
    "wof:name":"Installers Plus LLC",
    "wof:placetype":"venue"
},
  "geometry": {"coordinates":[-76.923451,38.953584],"type":"Point"}
}