{
  "type": "Feature",
  "properties": {
    "addr:full":"4810 Marlboro Pike Capitol Hgts MD 20743",
    "addr:housenumber":"4810",
    "addr:postcode":"20743",
    "addr:street":"Marlboro Pike",
    "iso:country":"US",
    "sg:address":"4810 Marlboro Pike",
    "sg:city":"Capitol Hgts",
    "sg:classifiers":[
        {
            "category":"Restaurant",
            "type":"Food & Drink"
        }
    ],
    "sg:phone":"+1 301 967 0900",
    "sg:postcode":"20743",
    "sg:province":"MD",
    "wof:name":"Tasty Carry Out",
    "wof:placetype":"venue"
},
  "geometry": {"coordinates":[-76.930199,38.873199],"type":"Point"}
}