{
  "type": "Feature",
  "properties": {
    "iso:country":"US",
    "sg:address":"611 Fagley St",
    "sg:city":"Baltimore",
    "sg:classifiers":[
        {
            "category":"Restaurant",
            "type":"Food & Drink"
        }
    ],
    "sg:phone":"+1 410 563 7577",
    "sg:postcode":"21224",
    "sg:province":"MD",
    "wof:name":"Eichenkranz Restaurant",
    "wof:placetype":"venue"
},
  "geometry": {"coordinates":[-76.564003,39.285599],"type":"Point"}
}