{
  "type": "Feature",
  "properties": {
    "addr:full":"3 Main St Reisterstown MD 21136",
    "addr:housenumber":"3",
    "addr:postcode":"21136",
    "addr:street":"Main St",
    "iso:country":"US",
    "sg:address":"3 Main St",
    "sg:city":"Reisterstown",
    "sg:classifiers":[
        {
            "category":"Education",
            "subcategory":"Dance Studio",
            "type":"Public Place"
        }
    ],
    "sg:phone":"+1 410 833 3733",
    "sg:postcode":"21136",
    "sg:province":"MD",
    "sg:tags":[
        "art",
        "performing",
        "instruction",
        "dancing"
    ],
    "sg:website":"http://www.karensachsdance.com",
    "wof:name":"Karen Sachs Academy of Dance",
    "wof:placetype":"venue"
},
  "geometry": {"coordinates":[-76.82959700000001,39.469601],"type":"Point"}
}