{
  "type": "Feature",
  "properties": {
    "addr:full":"4304 Old National Pike Middletown MD 21769",
    "addr:housenumber":"4304",
    "addr:postcode":"21769",
    "addr:street":"Old National Pike",
    "iso:country":"US",
    "sg:address":"4304 Old National Pike",
    "sg:city":"Middletown",
    "sg:classifiers":[
        {
            "category":"Autos & Motor Vehicles",
            "subcategory":"Fuel & Gas Station",
            "type":"Retail Goods"
        }
    ],
    "sg:phone":"+1 301 371 9961",
    "sg:postcode":"21769",
    "sg:province":"MD",
    "sg:tags":[
        "oil"
    ],
    "wof:name":"Fountaindale Sunoco",
    "wof:placetype":"venue"
},
  "geometry": {"coordinates":[-77.518944,39.434701],"type":"Point"}
}