{
  "type": "Feature",
  "properties": {
    "addr:full":"823 Hr Dr SE Washington MD 20032",
    "addr:housenumber":"823",
    "addr:postcode":"20032",
    "addr:street":"Hr Dr Se",
    "iso:country":"US",
    "sg:address":"823 Hr Dr SE",
    "sg:city":"Washington",
    "sg:classifiers":[
        {
            "category":"Professional",
            "subcategory":"Management & Consulting",
            "type":"Services"
        }
    ],
    "sg:phone":"+1 202 373 0663",
    "sg:postcode":"20032",
    "sg:province":"MD",
    "sg:tags":[
        "consultant",
        "business"
    ],
    "wof:name":"Davis Consulting Inc",
    "wof:placetype":"venue"
},
  "geometry": {"coordinates":[-76.99011299999999,38.82993],"type":"Point"}
}