{
  "type": "Feature",
  "properties": {
    "iso:country":"US",
    "sg:address":"14452 Old Mill Rd",
    "sg:city":"Upper Marlboro",
    "sg:classifiers":[
        {
            "category":"Professional",
            "subcategory":"Lawyer & Legal Services",
            "type":"Services"
        }
    ],
    "sg:phone":"+1 301 574 4100",
    "sg:postcode":"20772",
    "sg:province":"MD",
    "sg:tags":[
        "attorney"
    ],
    "wof:name":"Boehm Law Firm",
    "wof:placetype":"venue"
},
  "geometry": {"coordinates":[-76.756168,38.817821],"type":"Point"}
}