{
  "type": "Feature",
  "properties": {
    "addr:full":"2049 E Monument St Baltimore MD 21205",
    "addr:housenumber":"2049",
    "addr:postcode":"21205",
    "addr:street":"E Monument St",
    "iso:country":"US",
    "sg:address":"2049 E Monument St",
    "sg:city":"Baltimore",
    "sg:classifiers":[
        {
            "category":"Restaurant",
            "type":"Food & Drink"
        }
    ],
    "sg:phone":"+1 410 327 5454",
    "sg:postcode":"21205",
    "sg:province":"MD",
    "wof:name":"Happy Teriyaki",
    "wof:placetype":"venue"
},
  "geometry": {"coordinates":[-76.588065,39.298561],"type":"Point"}
}