{
  "type": "Feature",
  "properties": {
    "addr:full":"2509 Kingsway Rd Fort Washington MD 20744",
    "addr:housenumber":"2509",
    "addr:postcode":"20744",
    "addr:street":"Kingsway Rd",
    "iso:country":"US",
    "sg:address":"2509 Kingsway Rd",
    "sg:city":"Fort Washington",
    "sg:classifiers":[
        {
            "category":"Shopping",
            "subcategory":"Crafts & Fabrics",
            "type":"Retail Goods"
        }
    ],
    "sg:phone":"+1 301 248 3434",
    "sg:postcode":"20744",
    "sg:province":"MD",
    "sg:tags":[
        "yarn"
    ],
    "wof:name":"Yarn Crafters",
    "wof:placetype":"venue"
},
  "geometry": {"coordinates":[-76.964,38.787852],"type":"Point"}
}