{
  "type": "Feature",
  "properties": {
    "iso:country":"US",
    "sg:address":"4705 Ilkley Moor Ln",
    "sg:city":"Ellicott City",
    "sg:classifiers":[
        {
            "category":"Organizations",
            "subcategory":"Religious Organization",
            "type":"Services"
        }
    ],
    "sg:phone":"+1 410 461 3210",
    "sg:postcode":"21043",
    "sg:province":"MD",
    "wof:name":"St Timothys Tennis Club",
    "wof:placetype":"venue"
},
  "geometry": {"coordinates":[-76.808831,39.243041],"type":"Point"}
}