{
  "type": "Feature",
  "properties": {
    "iso:country":"US",
    "sg:address":"12234 Weller Rd",
    "sg:city":"Monrovia",
    "sg:classifiers":[
        {
            "category":"Building & Trades",
            "subcategory":"Construction",
            "type":"Services"
        }
    ],
    "sg:phone":"+1 301 865 1261",
    "sg:postcode":"21770",
    "sg:province":"MD",
    "sg:tags":[
        "floor",
        "laying",
        "contractor"
    ],
    "wof:name":"Ruppert Enterprises Inc",
    "wof:placetype":"venue"
},
  "geometry": {"coordinates":[-77.23682100000001,39.345778],"type":"Point"}
}