{
  "type": "Feature",
  "properties": {
    "addr:full":"615 Scarlet Oak Ct Woodsboro MD 21798",
    "addr:housenumber":"615",
    "addr:postcode":"21798",
    "addr:street":"Scarlet Oak Ct",
    "iso:country":"US",
    "sg:address":"615 Scarlet Oak Ct",
    "sg:city":"Woodsboro",
    "sg:classifiers":[
        {
            "category":"Professional",
            "subcategory":"Management & Consulting",
            "type":"Services"
        }
    ],
    "sg:phone":"+1 301 898 9175",
    "sg:postcode":"21798",
    "sg:province":"MD",
    "sg:tags":[
        "business"
    ],
    "wof:name":"Joe Botics",
    "wof:placetype":"venue"
},
  "geometry": {"coordinates":[-77.30128499999999,39.535984],"type":"Point"}
}