{
  "type": "Feature",
  "properties": {
    "iso:country":"US",
    "sg:address":"16001 Indian Head Hwy",
    "sg:city":"Accokeek",
    "sg:classifiers":[
        {
            "category":"Building & Trades",
            "subcategory":"Construction",
            "type":"Services"
        }
    ],
    "sg:phone":"+1 301 292 9414",
    "sg:postcode":"20607",
    "sg:province":"MD",
    "sg:tags":[
        "contractor"
    ],
    "wof:name":"Sun Pools",
    "wof:placetype":"venue"
},
  "geometry": {"coordinates":[-77.013532,38.668849],"type":"Point"}
}