{
  "type": "Feature",
  "properties": {
    "iso:country":"US",
    "sg:address":"17301 Valley Mall Rd",
    "sg:city":"Hagerstown",
    "sg:classifiers":[
        {
            "category":"Retail",
            "subcategory":"Portrait Studio",
            "type":"Services"
        }
    ],
    "sg:phone":"+1 301 582 1154",
    "sg:postcode":"21740",
    "sg:province":"MD",
    "sg:tags":[
        "photo"
    ],
    "wof:name":"Lifetouch",
    "wof:placetype":"venue"
},
  "geometry": {"coordinates":[-77.77246,39.62226],"type":"Point"}
}