{
  "type": "Feature",
  "properties": {
    "iso:country":"US",
    "sg:address":"27571 Holland Crossing Rd",
    "sg:city":"Marion Station",
    "sg:classifiers":[
        {
            "category":"Autos & Motor Vehicles",
            "subcategory":"Auto Supplies",
            "type":"Retail Goods"
        }
    ],
    "sg:phone":"+1 410 623 3911",
    "sg:postcode":"21838",
    "sg:province":"MD",
    "sg:tags":[
        "automobile",
        "parts"
    ],
    "wof:name":"T & T Automotive Inc",
    "wof:placetype":"venue"
},
  "geometry": {"coordinates":[-75.777017,38.011894],"type":"Point"}
}