{
  "type": "Feature",
  "properties": {
    "addr:full":"13380 Clarksville Pike Highland MD 20777",
    "addr:housenumber":"13380",
    "addr:postcode":"20777",
    "addr:street":"Clarksville Pike",
    "iso:country":"US",
    "sg:address":"13380 Clarksville Pike",
    "sg:city":"Highland",
    "sg:classifiers":[
        {
            "category":"Retail",
            "subcategory":"Laundry & Dry Cleaning",
            "type":"Services"
        }
    ],
    "sg:phone":"+1 301 854 3735",
    "sg:postcode":"20777",
    "sg:province":"MD",
    "wof:name":"High Cleaners",
    "wof:placetype":"venue"
},
  "geometry": {"coordinates":[-76.95739399999999,39.179629],"type":"Point"}
}