{
  "type": "Feature",
  "properties": {
    "addr:full":"321 Laburnum Rd Edgewood MD 21040",
    "addr:housenumber":"321",
    "addr:postcode":"21040",
    "addr:street":"Laburnum Rd",
    "iso:country":"US",
    "sg:address":"321 Laburnum Rd",
    "sg:city":"Edgewood",
    "sg:classifiers":[
        {
            "category":"Personal",
            "subcategory":"Beauty Salon",
            "type":"Services"
        }
    ],
    "sg:phone":"+1 410 671 6328",
    "sg:postcode":"21040",
    "sg:province":"MD",
    "wof:name":"Joyce's Hair Choices",
    "wof:placetype":"venue"
},
  "geometry": {"coordinates":[-76.271548,39.429897],"type":"Point"}
}