{
  "type": "Feature",
  "properties": {
    "addr:full":"4820 Marlboro Pike Capitol Heights MD 20743",
    "addr:housenumber":"4820",
    "addr:postcode":"20743",
    "addr:street":"Marlboro Pike",
    "iso:country":"US",
    "sg:address":"4820 Marlboro Pike",
    "sg:city":"Capitol Heights",
    "sg:classifiers":[
        {
            "category":"Shopping",
            "subcategory":"Pharmacy",
            "type":"Retail Goods"
        }
    ],
    "sg:phone":"+1 301 669 0465",
    "sg:postcode":"20743",
    "sg:province":"MD",
    "sg:tags":[
        "drugstore"
    ],
    "sg:website":"www.cvs.com",
    "wof:name":"Cvs Pharmacy",
    "wof:placetype":"venue"
},
  "geometry": {"coordinates":[-76.929635,38.873366],"type":"Point"}
}