{
  "type": "Feature",
  "properties": {
    "iso:country":"US",
    "sg:address":"3403 Eastern Ave",
    "sg:city":"Baltimore",
    "sg:classifiers":[
        {
            "category":"Shopping",
            "subcategory":"Clothing, Apparel, & Fashions",
            "type":"Retail Goods"
        }
    ],
    "sg:phone":"+1 410 732 7729",
    "sg:postcode":"21224",
    "sg:province":"MD",
    "sg:tags":[
        "accessory",
        "clothing",
        "women's"
    ],
    "wof:name":"Gallo Clothing Inc",
    "wof:placetype":"venue"
},
  "geometry": {"coordinates":[-76.56860399999999,39.286701],"type":"Point"}
}