{
  "type": "Feature",
  "properties": {
    "addr:full":"30170 Mount Vernon Rd Princess Anne MD 21853",
    "addr:housenumber":"30170",
    "addr:postcode":"21853",
    "addr:street":"Mount Vernon Rd",
    "iso:country":"US",
    "sg:address":"30170 Mount Vernon Rd",
    "sg:city":"Princess Anne",
    "sg:classifiers":[
        {
            "category":"Retail",
            "subcategory":"Auto Repair",
            "type":"Services"
        }
    ],
    "sg:phone":"+1 410 651 9600",
    "sg:postcode":"21853",
    "sg:province":"MD",
    "sg:tags":[
        "automotive"
    ],
    "wof:name":"Ltd Auto Center",
    "wof:placetype":"venue"
},
  "geometry": {"coordinates":[-75.70604400000001,38.213072],"type":"Point"}
}