{
  "type": "Feature",
  "properties": {
    "addr:full":"109 Marley Rd Elkton MD 21921",
    "addr:housenumber":"109",
    "addr:postcode":"21921",
    "addr:street":"Marley Rd",
    "iso:country":"US",
    "sg:address":"109 Marley Rd",
    "sg:city":"Elkton",
    "sg:classifiers":[
        {
            "category":"Organizations",
            "subcategory":"Religious Organization",
            "type":"Services"
        }
    ],
    "sg:phone":"+1 410 398 9006",
    "sg:postcode":"21921",
    "sg:province":"MD",
    "sg:tags":[
        "church"
    ],
    "wof:name":"Full Gospel Church Inc",
    "wof:placetype":"venue"
},
  "geometry": {"coordinates":[-75.90060699999999,39.619085],"type":"Point"}
}