{
  "type": "Feature",
  "properties": {
    "addr:full":"2002 Furnace Rd Fallston MD 21047",
    "addr:housenumber":"2002",
    "addr:postcode":"21047",
    "addr:street":"Furnace Rd",
    "iso:country":"US",
    "sg:address":"2002 Furnace Rd",
    "sg:city":"Fallston",
    "sg:classifiers":[
        {
            "category":"Organizations",
            "subcategory":"Religious Organization",
            "type":"Services"
        }
    ],
    "sg:phone":"+1 410 692 9631",
    "sg:postcode":"21047",
    "sg:province":"MD",
    "sg:tags":[
        "clergy"
    ],
    "wof:name":"Darcy R Hunt",
    "wof:placetype":"venue"
},
  "geometry": {"coordinates":[-76.484172,39.581885],"type":"Point"}
}