{
  "type": "Feature",
  "properties": {
    "iso:country":"US",
    "sg:address":"800 Middle River Rd",
    "sg:city":"Middle River",
    "sg:classifiers":[
        {
            "category":"Education",
            "subcategory":"School",
            "type":"Public Place"
        }
    ],
    "sg:phone":"+1 410 918 1949",
    "sg:postcode":"21220",
    "sg:province":"MD",
    "wof:name":"Baltimore County Public Schools",
    "wof:placetype":"venue"
},
  "geometry": {"coordinates":[-76.449997,39.345798],"type":"Point"}
}