{
  "type": "Feature",
  "properties": {
    "addr:full":"19313 Cypress Hill Way Gaithersburg MD 20879",
    "addr:housenumber":"19313",
    "addr:postcode":"20879",
    "addr:street":"Cypress Hill Way",
    "iso:country":"US",
    "sg:address":"19313 Cypress Hill Way",
    "sg:city":"Gaithersburg",
    "sg:classifiers":[
        {
            "category":"Building & Trades",
            "subcategory":"Plumbing",
            "type":"Services"
        }
    ],
    "sg:phone":"+1 301 367 0927",
    "sg:postcode":"20879",
    "sg:province":"MD",
    "sg:tags":[
        "plumbing",
        "electrical",
        "heating"
    ],
    "wof:name":"Rapidhaps",
    "wof:placetype":"venue"
},
  "geometry": {"coordinates":[-77.140007,39.172606],"type":"Point"}
}