{
  "type": "Feature",
  "properties": {
    "addr:full":"15 Arlen Rd Baltimore MD 21236",
    "addr:housenumber":"15",
    "addr:postcode":"21236",
    "addr:street":"Arlen Rd",
    "iso:country":"US",
    "sg:address":"15 Arlen Rd",
    "sg:city":"Baltimore",
    "sg:classifiers":[
        {
            "category":"Insurance",
            "subcategory":"Insurance Agent",
            "type":"Services"
        }
    ],
    "sg:phone":"+1 410 933 9699",
    "sg:postcode":"21236",
    "sg:province":"MD",
    "wof:name":"New York Life",
    "wof:placetype":"venue"
},
  "geometry": {"coordinates":[-76.475599,39.390622],"type":"Point"}
}