{
  "type": "Feature",
  "properties": {
    "addr:full":"1021 W Baltimore St Baltimore MD 21223",
    "addr:housenumber":"1021",
    "addr:postcode":"21223",
    "addr:street":"W Baltimore St",
    "iso:country":"US",
    "sg:address":"1021 W Baltimore St",
    "sg:city":"Baltimore",
    "sg:classifiers":[
        {
            "category":"Shopping",
            "subcategory":"Clothing, Apparel, & Fashions",
            "type":"Retail Goods"
        }
    ],
    "sg:phone":"+1 410 752 2981",
    "sg:postcode":"21223",
    "sg:province":"MD",
    "sg:tags":[
        "accessory"
    ],
    "wof:name":"Ladies Boutique",
    "wof:placetype":"venue"
},
  "geometry": {"coordinates":[-76.634399,39.288601],"type":"Point"}
}