{
  "type": "Feature",
  "properties": {
    "addr:full":"2465 Golders Green Ct Baltimore MD 21244",
    "addr:housenumber":"2465",
    "addr:postcode":"21244",
    "addr:street":"Golders Green Ct",
    "iso:country":"US",
    "sg:address":"2465 Golders Green Ct",
    "sg:city":"Baltimore",
    "sg:classifiers":[
        {
            "category":"Building & Trades",
            "subcategory":"Cleaning & Sanitation",
            "type":"Services"
        }
    ],
    "sg:phone":"+1 410 594 7162",
    "sg:postcode":"21244",
    "sg:province":"MD",
    "sg:tags":[
        "carpet"
    ],
    "wof:name":"Biz-Zee Bee",
    "wof:placetype":"venue"
},
  "geometry": {"coordinates":[-76.76352799999999,39.326948],"type":"Point"}
}