{
  "type": "Feature",
  "properties": {
    "iso:country":"US",
    "sg:address":"5101 Dudley Ln",
    "sg:city":"Bethesda",
    "sg:classifiers":[
        {
            "category":"Professional",
            "subcategory":"Accounting & Tax Preparation",
            "type":"Services"
        }
    ],
    "sg:phone":"+1 301 896 0515",
    "sg:postcode":"20814",
    "sg:province":"MD",
    "wof:name":"Bill Keene",
    "wof:placetype":"venue"
},
  "geometry": {"coordinates":[-77.09953299999999,39.013782],"type":"Point"}
}