{
  "type": "Feature",
  "properties": {
    "addr:full":"451 S 8th St Oakland MD 21550",
    "addr:housenumber":"451",
    "addr:postcode":"21550",
    "addr:street":"S 8Th St",
    "iso:country":"US",
    "sg:address":"451 S 8th St",
    "sg:city":"Oakland",
    "sg:classifiers":[
        {
            "category":"Shopping",
            "subcategory":"Used Merchandise",
            "type":"Retail Goods"
        }
    ],
    "sg:phone":"+1 301 334 3939",
    "sg:postcode":"21550",
    "sg:province":"MD",
    "sg:tags":[
        "clothing"
    ],
    "wof:name":"Turn Around",
    "wof:placetype":"venue"
},
  "geometry": {"coordinates":[-79.401303,39.403712],"type":"Point"}
}