{
  "type": "Feature",
  "properties": {
    "addr:full":"18749 N Frederick Ave Gaithersburg MD 20877",
    "addr:housenumber":"18749",
    "addr:postcode":"20877",
    "addr:street":"N Frederick Ave",
    "iso:country":"US",
    "sg:address":"18749 N Frederick Ave",
    "sg:city":"Gaithersburg",
    "sg:classifiers":[
        {
            "category":"Government",
            "subcategory":"Police Station",
            "type":"Public Place"
        }
    ],
    "sg:phone":"+1 240 773 5700",
    "sg:postcode":"20877",
    "sg:province":"MD",
    "sg:tags":[
        "protection"
    ],
    "wof:name":"Police Dept- 6th Dist",
    "wof:placetype":"venue"
},
  "geometry": {"coordinates":[-77.22262000000001,39.16151],"type":"Point"}
}