{
  "type": "Feature",
  "properties": {
    "iso:country":"US",
    "sg:address":"8003 Greenwood Ave",
    "sg:city":"Takoma Park",
    "sg:classifiers":[
        {
            "category":"Professional",
            "subcategory":"Computer Services",
            "type":"Services"
        }
    ],
    "sg:phone":"+1 301 928 2365",
    "sg:postcode":"20912",
    "sg:province":"MD",
    "sg:tags":[
        "design",
        "system"
    ],
    "wof:name":"Massarian Corp",
    "wof:placetype":"venue"
},
  "geometry": {"coordinates":[-77.000471,38.990103],"type":"Point"}
}