{
  "type": "Feature",
  "properties": {
    "iso:country":"US",
    "sg:address":"1910 Glen Ross Rd",
    "sg:city":"Silver Spring",
    "sg:classifiers":[
        {
            "category":"Arts & Performance",
            "subcategory":"Theater",
            "type":"Entertainment"
        }
    ],
    "sg:phone":"+1 301 589 3021",
    "sg:postcode":"20910",
    "sg:province":"MD",
    "sg:tags":[
        "entertainer",
        "group"
    ],
    "wof:name":"Lees Andy Magic With A Comic",
    "wof:placetype":"venue"
},
  "geometry": {"coordinates":[-77.042772,39.005871],"type":"Point"}
}