{
  "type": "Feature",
  "properties": {
    "addr:full":"4700 Drexel Rd College Park MD 20740",
    "addr:housenumber":"4700",
    "addr:postcode":"20740",
    "addr:street":"Drexel Rd",
    "iso:country":"US",
    "sg:address":"4700 Drexel Rd",
    "sg:city":"College Park",
    "sg:classifiers":[
        {
            "category":"Professional",
            "subcategory":"Computer Services",
            "type":"Services"
        }
    ],
    "sg:phone":"+1 301 699 5954",
    "sg:postcode":"20740",
    "sg:province":"MD",
    "sg:tags":[
        "high"
    ],
    "wof:name":"Aquarian Systems Inc",
    "wof:placetype":"venue"
},
  "geometry": {"coordinates":[-76.933387,38.975313],"type":"Point"}
}