{
  "type": "Feature",
  "properties": {
    "iso:country":"US",
    "sg:address":"8315 Carrollton Pkwy",
    "sg:city":"Hyattsville",
    "sg:classifiers":[
        {
            "category":"Building & Trades",
            "subcategory":"Equipment Rental",
            "type":"Services"
        }
    ],
    "sg:phone":"+1 301 577 0229",
    "sg:postcode":"20784",
    "sg:province":"MD",
    "wof:name":"S & G Sounds",
    "wof:placetype":"venue"
},
  "geometry": {"coordinates":[-76.879476,38.969841],"type":"Point"}
}