{
  "type": "Feature",
  "properties": {
    "iso:country":"US",
    "sg:address":"1996 Milboro Dr",
    "sg:city":"Rockville",
    "sg:classifiers":[
        {
            "category":"Professional",
            "subcategory":"Business Services",
            "type":"Services"
        }
    ],
    "sg:phone":"+1 301 424 7692",
    "sg:postcode":"20854",
    "sg:province":"MD",
    "sg:tags":[
        "patent",
        "searcher"
    ],
    "wof:name":"Airmail Patent Svc",
    "wof:placetype":"venue"
},
  "geometry": {"coordinates":[-77.170382,39.06541],"type":"Point"}
}