{
  "type": "Feature",
  "properties": {
    "iso:country":"US",
    "sg:address":"5353 Westbard Ave",
    "sg:city":"Bethesda",
    "sg:phone":"+1 301 652 0955",
    "sg:postcode":"20816",
    "sg:province":"MD",
    "sg:website":"http://national.citysearch.com/profile/external/601752286/bethesda_md/strike_bethesda.html?publisher=yellowpages&reference_id=1&placement=ypwebsitemip",
    "wof:name":"Strike Bethesda",
    "wof:placetype":"venue"
},
  "geometry": {"coordinates":[-77.10639999999999,38.962628],"type":"Point"}
}