{
  "type": "Feature",
  "properties": {
    "addr:full":"61 Greene St Cumberland MD 21502",
    "addr:housenumber":"61",
    "addr:postcode":"21502",
    "addr:street":"Greene St",
    "iso:country":"US",
    "sg:address":"61 Greene St",
    "sg:city":"Cumberland",
    "sg:classifiers":[
        {
            "category":"Professional",
            "subcategory":"Lawyer & Legal Services",
            "type":"Services"
        }
    ],
    "sg:phone":"+1 301 724 5040",
    "sg:postcode":"21502",
    "sg:province":"MD",
    "sg:tags":[
        "attorney"
    ],
    "wof:name":"Cumberland City Attorney",
    "wof:placetype":"venue"
},
  "geometry": {"coordinates":[-78.76469,39.65021],"type":"Point"}
}