{
  "type": "Feature",
  "properties": {
    "iso:country":"US",
    "sg:address":"825 Milford Mill Rd",
    "sg:city":"Pikesville",
    "sg:classifiers":[
        {
            "category":"Social Services",
            "subcategory":"Adult Care",
            "type":"Services"
        },
        {
            "category":"Social Services",
            "type":"Services"
        }
    ],
    "sg:phone":"+1 410 602 3672",
    "sg:postcode":"21208",
    "sg:province":"MD",
    "sg:tags":[
        "home",
        "residential"
    ],
    "wof:name":"Nelly Nell's Golden Pond",
    "wof:placetype":"venue"
},
  "geometry": {"coordinates":[-76.73492400000001,39.361831],"type":"Point"}
}