{
  "type": "Feature",
  "properties": {
    "iso:country":"US",
    "sg:address":"7505 Putt Rd",
    "sg:city":"Fort Washington",
    "sg:classifiers":[
        {
            "category":"Retail",
            "subcategory":"Repair Shop",
            "type":"Services"
        }
    ],
    "sg:phone":"+1 301 265 9808",
    "sg:postcode":"20744",
    "sg:province":"MD",
    "wof:name":"Clean Clear Sewer & Drain Clg",
    "wof:placetype":"venue"
},
  "geometry": {"coordinates":[-76.93707999999999,38.78615],"type":"Point"}
}