{
  "type": "Feature",
  "properties": {
    "iso:country":"US",
    "sg:address":"194 E Main St",
    "sg:city":"Westminster",
    "sg:classifiers":[
        {
            "category":"Real Estate",
            "subcategory":"Surveying",
            "type":"Services"
        }
    ],
    "sg:phone":"+1 410 857 0822",
    "sg:postcode":"21157",
    "sg:province":"MD",
    "sg:tags":[
        "surveyor"
    ],
    "wof:name":"ALS Inc",
    "wof:placetype":"venue"
},
  "geometry": {"coordinates":[-76.990923,39.570229],"type":"Point"}
}