{
  "type": "Feature",
  "properties": {
    "addr:full":"12815 Coastal Hwy Ocean City MD 21842",
    "addr:housenumber":"12815",
    "addr:postcode":"21842",
    "addr:street":"Coastal Hwy",
    "iso:country":"US",
    "sg:address":"12815 Coastal Hwy",
    "sg:city":"Ocean City",
    "sg:classifiers":[
        {
            "category":"Wholesale",
            "subcategory":"Hardware",
            "type":"Manufacturing & Wholesale Goods"
        }
    ],
    "sg:phone":"+1 410 250 7050",
    "sg:postcode":"21842",
    "sg:province":"MD",
    "sg:tags":[
        "air",
        "parts",
        "conditioning",
        "supply"
    ],
    "wof:name":"Trible's Inc & Assoc",
    "wof:placetype":"venue"
},
  "geometry": {"coordinates":[-75.05461200000001,38.434284],"type":"Point"}
}