{
  "type": "Feature",
  "properties": {
    "addr:full":"11110 Medical Campus Rd Ste 246 Hagerstown MD 21742",
    "addr:housenumber":"11110",
    "addr:postcode":"21742",
    "addr:street":"Medical Campus Rd Ste 246",
    "iso:country":"US",
    "sg:address":"11110 Medical Campus Rd Ste 246",
    "sg:city":"Hagerstown",
    "sg:classifiers":[
        {
            "category":"Health Services",
            "subcategory":"Medical Lab",
            "type":"Services"
        }
    ],
    "sg:phone":"+1 301 714 4025",
    "sg:postcode":"21742",
    "sg:province":"MD",
    "wof:name":"Robinwood Medical Center",
    "wof:placetype":"venue"
},
  "geometry": {"coordinates":[-77.679839,39.621314],"type":"Point"}
}