{
  "type": "Feature",
  "properties": {
    "iso:country":"US",
    "sg:address":"4101 Harvard Pl",
    "sg:city":"Frederick",
    "sg:classifiers":[
        {
            "category":"Building & Trades",
            "subcategory":"Plumbing",
            "type":"Services"
        }
    ],
    "sg:phone":"+1 301 874 1840",
    "sg:postcode":"21703",
    "sg:province":"MD",
    "sg:tags":[
        "conditioning",
        "air",
        "system",
        "contractor"
    ],
    "wof:name":"W M Brown Inc",
    "wof:placetype":"venue"
},
  "geometry": {"coordinates":[-77.498003,39.347799],"type":"Point"}
}