{
  "type": "Feature",
  "properties": {
    "iso:country":"US",
    "sg:address":"5309 Annapolis Rd",
    "sg:city":"Bladensburg",
    "sg:classifiers":[
        {
            "category":"Building & Trades",
            "subcategory":"Plumbing",
            "type":"Services"
        }
    ],
    "sg:phone":"+1 301 927 3888",
    "sg:postcode":"20710",
    "sg:province":"MD",
    "wof:name":"Eberly Dutch Plumbing Contractor",
    "wof:placetype":"venue"
},
  "geometry": {"coordinates":[-76.92837299999999,38.93931],"type":"Point"}
}