{
  "type": "Feature",
  "properties": {
    "addr:full":"44178 Airport View Dr Hollywood MD 20636",
    "addr:housenumber":"44178",
    "addr:postcode":"20636",
    "addr:street":"Airport View Dr",
    "iso:country":"US",
    "sg:address":"44178 Airport View Dr",
    "sg:city":"Hollywood",
    "sg:classifiers":[
        {
            "category":"Professional",
            "subcategory":"Computer Services",
            "type":"Services"
        }
    ],
    "sg:phone":"+1 301 373 9696",
    "sg:postcode":"20636",
    "sg:province":"MD",
    "sg:tags":[
        "system",
        "integration"
    ],
    "wof:name":"Readycom Services LLC",
    "wof:placetype":"venue"
},
  "geometry": {"coordinates":[-76.548214,38.319812],"type":"Point"}
}