{
  "type": "Feature",
  "properties": {
    "iso:country":"US",
    "sg:address":"10410 Kensington Pkwy Ste 222",
    "sg:city":"Kensington",
    "sg:classifiers":[
        {
            "category":"Real Estate",
            "subcategory":"Real Estate Services",
            "type":"Services"
        }
    ],
    "sg:phone":"+1 301 946 4050",
    "sg:postcode":"20895",
    "sg:province":"MD",
    "wof:name":"Menkis Real Estate",
    "wof:placetype":"venue"
},
  "geometry": {"coordinates":[-77.069532,39.026923],"type":"Point"}
}