{
  "type": "Feature",
  "properties": {
    "iso:country":"US",
    "sg:address":"SunTrust Building 120 E Baltimore St",
    "sg:city":"Baltimore",
    "sg:classifiers":[
        {
            "category":"Restaurant",
            "type":"Food & Drink"
        }
    ],
    "sg:phone":"+1 410 837 7482",
    "sg:postcode":"21275",
    "sg:province":"MD",
    "sg:tags":[
        "greek",
        "mediterranean"
    ],
    "sg:website":"www.cypriana.com",
    "wof:name":"Cypriana Cafe",
    "wof:placetype":"venue"
},
  "geometry": {"coordinates":[-76.61307100000001,39.289616],"type":"Point"}
}