{
  "type": "Feature",
  "properties": {
    "iso:country":"US",
    "sg:address":"105 120th St",
    "sg:city":"Ocean City",
    "sg:classifiers":[
        {
            "category":"Real Estate",
            "subcategory":"Real Estate Agent",
            "type":"Services"
        }
    ],
    "sg:phone":"+1 410 524 8452",
    "sg:postcode":"21842",
    "sg:province":"MD",
    "wof:name":"Club Ocean Villa II Sales",
    "wof:placetype":"venue"
},
  "geometry": {"coordinates":[-75.056773,38.425672],"type":"Point"}
}