{
  "type": "Feature",
  "properties": {
    "addr:full":"8931 Woodyard Rd Clinton MD 20735",
    "addr:housenumber":"8931",
    "addr:postcode":"20735",
    "addr:street":"Woodyard Rd",
    "iso:country":"US",
    "sg:address":"8931 Woodyard Rd",
    "sg:city":"Clinton",
    "sg:classifiers":[
        {
            "category":"Health Services",
            "subcategory":"Optometrist",
            "type":"Services"
        }
    ],
    "sg:phone":"+1 301 877 1770",
    "sg:postcode":"20735",
    "sg:province":"MD",
    "sg:website":"www.lifetime.com",
    "wof:name":"Lifetime Eyecare Ctr",
    "wof:placetype":"venue"
},
  "geometry": {"coordinates":[-76.889274,38.766906],"type":"Point"}
}