{
  "type": "Feature",
  "properties": {
    "addr:full":"825 Dulaney Valley Rd Towson MD 21204",
    "addr:housenumber":"825",
    "addr:postcode":"21204",
    "addr:street":"Dulaney Valley Rd",
    "iso:country":"US",
    "sg:address":"825 Dulaney Valley Rd",
    "sg:city":"Towson",
    "sg:classifiers":[
        {
            "category":"Utilities",
            "subcategory":"Mobile Phone",
            "type":"Services"
        },
        {
            "category":"Shopping",
            "subcategory":"Mobile Phones",
            "type":"Retail Goods"
        },
        {
            "category":"Utilities",
            "subcategory":"Telephone",
            "type":"Services"
        },
        {
            "category":"Professional",
            "subcategory":"Computer Services",
            "type":"Services"
        }
    ],
    "sg:phone":"+1 410 494 1086",
    "sg:postcode":"21204",
    "sg:province":"MD",
    "sg:tags":[
        "telecommunication",
        "supply",
        "communication",
        "system",
        "wireless",
        "equipment",
        "cellular"
    ],
    "sg:website":"http://clickserve.dartsearch.net/link/click?lid=43000000308049899",
    "wof:name":"T-Mobile",
    "wof:placetype":"venue"
},
  "geometry": {"coordinates":[-76.60149800000001,39.40463],"type":"Point"}
}