{
  "type": "Feature",
  "properties": {
    "iso:country":"US",
    "sg:address":"10026 Crystal Falls Dr",
    "sg:city":"Hagerstown",
    "sg:classifiers":[
        {
            "category":"Autos & Motor Vehicles",
            "subcategory":"Automobile Sales",
            "type":"Retail Goods"
        }
    ],
    "sg:phone":"+1 301 739 8453",
    "sg:postcode":"21740",
    "sg:province":"MD",
    "sg:tags":[
        "car",
        "dealer"
    ],
    "wof:name":"Davidson Auto Ctr",
    "wof:placetype":"venue"
},
  "geometry": {"coordinates":[-77.604455,39.590551],"type":"Point"}
}