{
  "type": "Feature",
  "properties": {
    "addr:full":"1420 Maryland Ave Baltimore MD 21201",
    "addr:housenumber":"1420",
    "addr:postcode":"21201",
    "addr:street":"Maryland Ave",
    "iso:country":"US",
    "sg:address":"1420 Maryland Ave",
    "sg:city":"Baltimore",
    "sg:classifiers":[
        {
            "category":"Education",
            "subcategory":"Library",
            "type":"Public Place"
        }
    ],
    "sg:phone":"+1 410 837 4318",
    "sg:postcode":"21201",
    "sg:province":"MD",
    "wof:name":"Langsdale Library",
    "wof:placetype":"venue"
},
  "geometry": {"coordinates":[-76.617546,39.305703],"type":"Point"}
}