{
  "type": "Feature",
  "properties": {
    "iso:country":"US",
    "sg:address":"11619 Beltsville Dr",
    "sg:city":"Beltsville",
    "sg:classifiers":[
        {
            "category":"Restaurant",
            "type":"Food & Drink"
        }
    ],
    "sg:phone":"+1 301 572 7830",
    "sg:postcode":"20705",
    "sg:province":"MD",
    "sg:tags":[
        "tex-mex"
    ],
    "wof:name":"Sierras Grill & Taqueria Inc",
    "wof:placetype":"venue"
},
  "geometry": {"coordinates":[-76.9384,39.049099],"type":"Point"}
}