{
  "type": "Feature",
  "properties": {
    "addr:full":"102 N Main St Greensboro MD 21639",
    "addr:housenumber":"102",
    "addr:postcode":"21639",
    "addr:street":"N Main St",
    "iso:country":"US",
    "sg:address":"102 N Main St",
    "sg:city":"Greensboro",
    "sg:classifiers":[
        {
            "category":"Shopping",
            "subcategory":"Pharmacy",
            "type":"Retail Goods"
        }
    ],
    "sg:phone":"+1 410 482 6256",
    "sg:postcode":"21639",
    "sg:province":"MD",
    "sg:website":"http://www.greensboropharmacy.com",
    "wof:name":"Health Mart",
    "wof:placetype":"venue"
},
  "geometry": {"coordinates":[-75.805368,38.973892],"type":"Point"}
}