{
  "type": "Feature",
  "properties": {
    "iso:country":"US",
    "sg:address":"10223 Day Ave",
    "sg:city":"Kensington",
    "sg:classifiers":[
        {
            "category":"Arts & Performance",
            "subcategory":"Theater",
            "type":"Entertainment"
        }
    ],
    "sg:phone":"+1 301 933 7639",
    "sg:postcode":"20895",
    "sg:province":"MD",
    "sg:tags":[
        "magician"
    ],
    "sg:website":"www.nu-magic.com",
    "wof:name":"Mysteries Of Nu",
    "wof:placetype":"venue"
},
  "geometry": {"coordinates":[-77.06182,39.025157],"type":"Point"}
}