{
  "type": "Feature",
  "properties": {
    "addr:full":"9007 Marshall Ave Laurel MD 20707",
    "addr:housenumber":"9007",
    "addr:postcode":"20707",
    "addr:street":"Marshall Ave",
    "iso:country":"US",
    "sg:address":"9007 Marshall Ave",
    "sg:city":"Laurel",
    "sg:classifiers":[
        {
            "category":"Freight",
            "type":"Transportation"
        }
    ],
    "sg:phone":"+1 301 498 2626",
    "sg:postcode":"20707",
    "sg:province":"MD",
    "sg:tags":[
        "trucking"
    ],
    "wof:name":"Roadway Express Inc",
    "wof:placetype":"venue"
},
  "geometry": {"coordinates":[-76.85023099999999,39.095884],"type":"Point"}
}