{
  "type": "Feature",
  "properties": {
    "addr:full":"4617 Norwich Rd College Park MD 20740",
    "addr:housenumber":"4617",
    "addr:postcode":"20740",
    "addr:street":"Norwich Rd",
    "iso:country":"US",
    "sg:address":"4617 Norwich Rd",
    "sg:city":"College Park",
    "sg:classifiers":[
        {
            "category":"Organizations",
            "subcategory":"Community Association",
            "type":"Services"
        }
    ],
    "sg:phone":"+1 301 277 7592",
    "sg:postcode":"20740",
    "sg:province":"MD",
    "sg:tags":[
        "sorority",
        "fraternity"
    ],
    "wof:name":"Delta Phi Chapter Of Sigma Nu",
    "wof:placetype":"venue"
},
  "geometry": {"coordinates":[-76.931544,38.981921],"type":"Point"}
}