{
  "type": "Feature",
  "properties": {
    "iso:country":"US",
    "sg:address":"1418 Mason St",
    "sg:city":"Baltimore",
    "sg:classifiers":[
        {
            "category":"Professional",
            "subcategory":"Management & Consulting",
            "type":"Services"
        }
    ],
    "sg:phone":"+1 410 669 3266",
    "sg:postcode":"21217",
    "sg:province":"MD",
    "wof:name":"Khorramshahi Ali LLC",
    "wof:placetype":"venue"
},
  "geometry": {"coordinates":[-76.627458,39.307268],"type":"Point"}
}