{
  "type": "Feature",
  "properties": {
    "addr:full":"6727 Mid Cities Ave Beltsville MD 20705",
    "addr:housenumber":"6727",
    "addr:postcode":"20705",
    "addr:street":"Mid Cities Ave",
    "iso:country":"US",
    "sg:address":"6727 Mid Cities Ave",
    "sg:city":"Beltsville",
    "sg:classifiers":[
        {
            "category":"Wholesale",
            "subcategory":"Machinery & Supplies",
            "type":"Manufacturing & Wholesale Goods"
        }
    ],
    "sg:phone":"+1 301 937 4777",
    "sg:postcode":"20705",
    "sg:province":"MD",
    "sg:tags":[
        "washing",
        "mach"
    ],
    "sg:website":"www.creativelaundry.com",
    "wof:name":"Creative Laundry Systems",
    "wof:placetype":"venue"
},
  "geometry": {"coordinates":[-76.887843,39.053521],"type":"Point"}
}