{
  "type": "Feature",
  "properties": {
    "iso:country":"US",
    "sg:address":"608 N Stuart St",
    "sg:city":"Essex",
    "sg:classifiers":[
        {
            "category":"Manufacturing",
            "subcategory":"Tools & Machinery",
            "type":"Manufacturing & Wholesale Goods"
        }
    ],
    "sg:phone":"+1 410 682 2334",
    "sg:postcode":"21221",
    "sg:province":"MD",
    "sg:tags":[
        "springs-wholesale",
        "manufacturer"
    ],
    "wof:name":"Spring Williow Pleasure Club",
    "wof:placetype":"venue"
},
  "geometry": {"coordinates":[-76.472801,39.313781],"type":"Point"}
}