{
  "type": "Feature",
  "properties": {
    "iso:country":"US",
    "sg:address":"6005 Oxon Hill Rd",
    "sg:city":"Oxon Hill",
    "sg:classifiers":[
        {
            "category":"Shopping",
            "type":"Retail Goods"
        }
    ],
    "sg:phone":"+1 301 839 4900",
    "sg:postcode":"20745",
    "sg:province":"MD",
    "sg:tags":[
        "pet",
        "shop",
        "training"
    ],
    "sg:website":"www.petsmart.com",
    "wof:name":"Petsmart",
    "wof:placetype":"venue"
},
  "geometry": {"coordinates":[-76.9748,38.805401],"type":"Point"}
}