{
  "type": "Feature",
  "properties": {
    "iso:country":"US",
    "sg:address":"1712 Fleet St",
    "sg:city":"Baltimore",
    "sg:classifiers":[
        {
            "category":"Shopping",
            "subcategory":"Pets & Pet Supplies",
            "type":"Retail Goods"
        },
        {
            "category":"Retail",
            "subcategory":"Animal Services",
            "type":"Services"
        }
    ],
    "sg:phone":"+1 410 522 3434",
    "sg:postcode":"21231",
    "sg:province":"MD",
    "sg:tags":[
        "dog",
        "cat",
        "furnishing",
        "grooming",
        "store"
    ],
    "wof:name":"Pampered Pooch",
    "wof:placetype":"venue"
},
  "geometry": {"coordinates":[-76.592887,39.284568],"type":"Point"}
}