{
  "type": "Feature",
  "properties": {
    "iso:country":"US",
    "sg:address":"7628 Old Georgetown Rd",
    "sg:city":"Bethesda",
    "sg:classifiers":[
        {
            "category":"Autos & Motor Vehicles",
            "subcategory":"Fuel & Gas Station",
            "type":"Retail Goods"
        }
    ],
    "sg:phone":"+1 301 654 9513",
    "sg:postcode":"20814",
    "sg:province":"MD",
    "wof:name":"Zee Business Enterprise Inc",
    "wof:placetype":"venue"
},
  "geometry": {"coordinates":[-77.09729799999999,38.986599],"type":"Point"}
}