{
  "type": "Feature",
  "properties": {
    "iso:country":"US",
    "sg:address":"9 West St",
    "sg:city":"Annapolis",
    "sg:classifiers":[
        {
            "category":"Building & Trades",
            "subcategory":"Equipment Rental",
            "type":"Services"
        }
    ],
    "sg:phone":"+1 301 858 8008",
    "sg:postcode":"21401",
    "sg:province":"MD",
    "sg:tags":[
        "camping"
    ],
    "wof:name":"Party Perfect",
    "wof:placetype":"venue"
},
  "geometry": {"coordinates":[-76.495481,38.978284],"type":"Point"}
}