{
  "type": "Feature",
  "properties": {
    "addr:full":"5426 Sinclair Ln Baltimore MD 21206",
    "addr:housenumber":"5426",
    "addr:postcode":"21206",
    "addr:street":"Sinclair Ln",
    "iso:country":"US",
    "sg:address":"5426 Sinclair Ln",
    "sg:city":"Baltimore",
    "sg:classifiers":[
        {
            "category":"Restaurant",
            "type":"Food & Drink"
        }
    ],
    "sg:phone":"+1 410 485 8350",
    "sg:postcode":"21206",
    "sg:province":"MD",
    "sg:tags":[
        "pizza"
    ],
    "wof:name":"Little Joe's Pizzaria",
    "wof:placetype":"venue"
},
  "geometry": {"coordinates":[-76.53890199999999,39.324501],"type":"Point"}
}