{
  "type": "Feature",
  "properties": {
    "iso:country":"US",
    "sg:address":"225 Lore Rd",
    "sg:city":"Solomons",
    "sg:classifiers":[
        {
            "category":"Shopping",
            "subcategory":"Used Merchandise",
            "type":"Retail Goods"
        }
    ],
    "sg:phone":"+1 410 326 3582",
    "sg:postcode":"20688",
    "sg:province":"MD",
    "sg:tags":[
        "antique"
    ],
    "wof:name":"Island Trader Antiques",
    "wof:placetype":"venue"
},
  "geometry": {"coordinates":[-76.464736,38.332411],"type":"Point"}
}