{
  "type": "Feature",
  "properties": {
    "addr:full":"2620 Mountain Rd Joppa MD 21085",
    "addr:housenumber":"2620",
    "addr:postcode":"21085",
    "addr:street":"Mountain Rd",
    "iso:country":"US",
    "sg:address":"2620 Mountain Rd",
    "sg:city":"Joppa",
    "sg:classifiers":[
        {
            "category":"Food & Beverages",
            "subcategory":"Groceries & Convenience Stores",
            "type":"Retail Goods"
        }
    ],
    "sg:phone":"+1 410 679 7490",
    "sg:postcode":"21085",
    "sg:province":"MD",
    "sg:website":"www.royalfarms.com",
    "wof:name":"Royal Farms",
    "wof:placetype":"venue"
},
  "geometry": {"coordinates":[-76.357889,39.45519],"type":"Point"}
}