{
  "type": "Feature",
  "properties": {
    "iso:country":"US",
    "sg:address":"11121 Baltimore Ave.",
    "sg:city":"Beltsville",
    "sg:classifiers":[
        {
            "category":"Restaurant",
            "type":"Food & Drink"
        }
    ],
    "sg:phone":"+1 301 595 1820",
    "sg:postcode":"20705",
    "sg:province":"MD",
    "sg:tags":[
        "barbeque"
    ],
    "sg:website":"www.dickeys.com",
    "wof:name":"Dickey's Barbeque Pit",
    "wof:placetype":"venue"
},
  "geometry": {"coordinates":[-76.906451,39.03551],"type":"Point"}
}