{
  "type": "Feature",
  "properties": {
    "addr:full":"5072 Dorsey Hall Dr Ellicott City MD 21042",
    "addr:housenumber":"5072",
    "addr:postcode":"21042",
    "addr:street":"Dorsey Hall Dr",
    "iso:country":"US",
    "sg:address":"5072 Dorsey Hall Dr",
    "sg:city":"Ellicott City",
    "sg:classifiers":[
        {
            "category":"Health Services",
            "subcategory":"Doctor",
            "type":"Services"
        }
    ],
    "sg:phone":"+1 410 740 2884",
    "sg:postcode":"21042",
    "sg:province":"MD",
    "sg:tags":[
        "dentist"
    ],
    "wof:name":"Bill De Long DDS",
    "wof:placetype":"venue"
},
  "geometry": {"coordinates":[-76.83624399999999,39.243363],"type":"Point"}
}