{
  "type": "Feature",
  "properties": {
    "iso:country":"US",
    "sg:address":"10410 Brightfield Ln",
    "sg:city":"Upper Marlboro",
    "sg:classifiers":[
        {
            "category":"Professional",
            "subcategory":"Management & Consulting",
            "type":"Services"
        }
    ],
    "sg:phone":"+1 301 877 6098",
    "sg:postcode":"20772",
    "sg:province":"MD",
    "sg:tags":[
        "construction"
    ],
    "wof:name":"Ford Management Services Ltd",
    "wof:placetype":"venue"
},
  "geometry": {"coordinates":[-76.826804,38.786246],"type":"Point"}
}