{
  "type": "Feature",
  "properties": {
    "iso:country":"US",
    "sg:address":"764 W Baltimore St",
    "sg:city":"Baltimore",
    "sg:classifiers":[
        {
            "category":"Restaurant",
            "type":"Food & Drink"
        }
    ],
    "sg:phone":"+1 410 547 2638",
    "sg:postcode":"21201",
    "sg:province":"MD",
    "wof:name":"Silvermoon Carryout",
    "wof:placetype":"venue"
},
  "geometry": {"coordinates":[-76.628433,39.288991],"type":"Point"}
}