{
  "type": "Feature",
  "properties": {
    "addr:full":"1262 Vocke Rd Ste 418 Cumberland MD 21502",
    "addr:housenumber":"1262",
    "addr:postcode":"21502",
    "addr:street":"Vocke Rd Ste 418",
    "iso:country":"US",
    "sg:address":"1262 Vocke Rd Ste 418",
    "sg:city":"Cumberland",
    "sg:classifiers":[
        {
            "category":"Health Services",
            "subcategory":"Optometrist",
            "type":"Services"
        },
        {
            "category":"Shopping",
            "subcategory":"Optical Goods",
            "type":"Retail Goods"
        },
        {
            "category":"Shopping",
            "subcategory":"Optician",
            "type":"Retail Goods"
        }
    ],
    "sg:phone":"+1 301 729 4240",
    "sg:postcode":"21502",
    "sg:province":"MD",
    "sg:tags":[
        "lens",
        "eyeglass",
        "contact"
    ],
    "sg:website":"http://www.sterlingoptical.com",
    "wof:name":"Sterling Optical",
    "wof:placetype":"venue"
},
  "geometry": {"coordinates":[-78.831963,39.632725],"type":"Point"}
}