{
  "type": "Feature",
  "properties": {
    "iso:country":"US",
    "sg:address":"3803 Cedar Dr",
    "sg:city":"Gwynn Oak",
    "sg:classifiers":[
        {
            "category":"Arts & Performance",
            "subcategory":"Arts Center",
            "type":"Entertainment"
        }
    ],
    "sg:phone":"+1 410 265 6782",
    "sg:postcode":"21207",
    "sg:province":"MD",
    "sg:tags":[
        "performing"
    ],
    "wof:name":"Elifrey Caribbean School of Dance",
    "wof:placetype":"venue"
},
  "geometry": {"coordinates":[-76.720654,39.346387],"type":"Point"}
}