{
  "type": "Feature",
  "properties": {
    "iso:country":"US",
    "sg:address":"3411 Pennsy Dr",
    "sg:city":"Landover",
    "sg:classifiers":[
        {
            "category":"Wholesale",
            "subcategory":"Groceries",
            "type":"Manufacturing & Wholesale Goods"
        }
    ],
    "sg:phone":"+1 301 772 3006",
    "sg:postcode":"20785",
    "sg:province":"MD",
    "sg:tags":[
        "grocer"
    ],
    "wof:name":"John Sexton & Co",
    "wof:placetype":"venue"
},
  "geometry": {"coordinates":[-76.877597,38.936281],"type":"Point"}
}