{
  "type": "Feature",
  "properties": {
    "addr:full":"1428 Grimm Rd Severn MD 21144",
    "addr:housenumber":"1428",
    "addr:postcode":"21144",
    "addr:street":"Grimm Rd",
    "iso:country":"US",
    "sg:address":"1428 Grimm Rd",
    "sg:city":"Severn",
    "sg:classifiers":[
        {
            "category":"Professional",
            "subcategory":"Engineering",
            "type":"Services"
        }
    ],
    "sg:phone":"+1 410 551 8469",
    "sg:postcode":"21144",
    "sg:province":"MD",
    "sg:tags":[
        "general",
        "contractor"
    ],
    "wof:name":"Allied Graphic Engineering Svc",
    "wof:placetype":"venue"
},
  "geometry": {"coordinates":[-76.692673,39.111122],"type":"Point"}
}