{
  "type": "Feature",
  "properties": {
    "iso:country":"US",
    "sg:address":"11010 Grassy Knoll Ter",
    "sg:city":"Germantown",
    "sg:classifiers":[
        {
            "category":"Professional",
            "subcategory":"Management & Consulting",
            "type":"Services"
        }
    ],
    "sg:phone":"+1 301 916 2793",
    "sg:postcode":"20876",
    "sg:province":"MD",
    "sg:tags":[
        "training",
        "program"
    ],
    "wof:name":"Signs & Culture Exchange Svcs",
    "wof:placetype":"venue"
},
  "geometry": {"coordinates":[-77.22462,39.178217],"type":"Point"}
}