{
  "type": "Feature",
  "properties": {
    "addr:full":"6903 E Clinton St Clinton MD 20735",
    "addr:housenumber":"6903",
    "addr:postcode":"20735",
    "addr:street":"E Clinton St",
    "iso:country":"US",
    "sg:address":"6903 E Clinton St",
    "sg:city":"Clinton",
    "sg:classifiers":[
        {
            "category":"Freight",
            "type":"Transportation"
        }
    ],
    "sg:phone":"+1 301 868 1339",
    "sg:postcode":"20735",
    "sg:province":"MD",
    "sg:tags":[
        "local",
        "mover",
        "storage",
        "trucking"
    ],
    "wof:name":"National Office Moving Company",
    "wof:placetype":"venue"
},
  "geometry": {"coordinates":[-76.886067,38.779202],"type":"Point"}
}