{
  "type": "Feature",
  "properties": {
    "iso:country":"US",
    "sg:address":"130 N Washington St",
    "sg:city":"Easton",
    "sg:classifiers":[
        {
            "category":"Professional",
            "subcategory":"Lawyer & Legal Services",
            "type":"Services"
        }
    ],
    "sg:phone":"+1 410 822 6800",
    "sg:postcode":"21601",
    "sg:province":"MD",
    "sg:tags":[
        "attorney",
        "practice"
    ],
    "sg:website":"http://www.ctklaw.com",
    "wof:name":"Cowdrey, Thompson & Karsten, P.A.",
    "wof:placetype":"venue"
},
  "geometry": {"coordinates":[-76.0763,38.776751],"type":"Point"}
}