{
  "type": "Feature",
  "properties": {
    "iso:country":"US",
    "sg:address":"11402 Stewart Ln",
    "sg:city":"Silver Spring",
    "sg:classifiers":[
        {
            "category":"Freight",
            "type":"Transportation"
        }
    ],
    "sg:phone":"+1 301 625 5001",
    "sg:postcode":"20904",
    "sg:province":"MD",
    "sg:tags":[
        "commercial",
        "storage"
    ],
    "wof:name":"All Points Moving",
    "wof:placetype":"venue"
},
  "geometry": {"coordinates":[-76.981415,39.045166],"type":"Point"}
}