{
  "type": "Feature",
  "properties": {
    "iso:country":"US",
    "sg:address":"9103 Contee Rd",
    "sg:city":"Laurel",
    "sg:classifiers":[
        {
            "category":"Building & Trades",
            "subcategory":"Construction",
            "type":"Services"
        }
    ],
    "sg:phone":"+1 301 776 0795",
    "sg:postcode":"20708",
    "sg:province":"MD",
    "sg:tags":[
        "carpentry",
        "contractor"
    ],
    "wof:name":"Trim Xperts",
    "wof:placetype":"venue"
},
  "geometry": {"coordinates":[-76.84921199999999,39.073497],"type":"Point"}
}