{
  "type": "Feature",
  "properties": {
    "addr:full":"649 Shore Acres Rd Arnold MD 21012",
    "addr:housenumber":"649",
    "addr:postcode":"21012",
    "addr:street":"Shore Acres Rd",
    "iso:country":"US",
    "sg:address":"649 Shore Acres Rd",
    "sg:city":"Arnold",
    "sg:classifiers":[
        {
            "category":"Cinema",
            "subcategory":"Movie Theater",
            "type":"Entertainment"
        }
    ],
    "sg:phone":"+1 410 757 2281",
    "sg:postcode":"21012",
    "sg:province":"MD",
    "sg:tags":[
        "motion",
        "picture"
    ],
    "wof:name":"Childrens Theater of Annapolis",
    "wof:placetype":"venue"
},
  "geometry": {"coordinates":[-76.475275,39.051276],"type":"Point"}
}