{
  "type": "Feature",
  "properties": {
    "iso:country":"US",
    "sg:address":"140 N Bond St",
    "sg:city":"Bel Air",
    "sg:classifiers":[
        {
            "category":"Shopping",
            "subcategory":"Used Merchandise",
            "type":"Retail Goods"
        }
    ],
    "sg:phone":"+1 410 838 6469",
    "sg:postcode":"21014",
    "sg:province":"MD",
    "sg:tags":[
        "shop",
        "consignment"
    ],
    "wof:name":"Bows & Britches Consignment",
    "wof:placetype":"venue"
},
  "geometry": {"coordinates":[-76.35198,39.537194],"type":"Point"}
}