{
  "type": "Feature",
  "properties": {
    "iso:country":"US",
    "sg:address":"2803 Dede Rd",
    "sg:city":"Finksburg",
    "sg:classifiers":[
        {
            "category":"Manufacturing",
            "subcategory":"Petroleum Products",
            "type":"Manufacturing & Wholesale Goods"
        }
    ],
    "sg:phone":"+1 410 833 3780",
    "sg:postcode":"21048",
    "sg:province":"MD",
    "sg:tags":[
        "asphalt"
    ],
    "wof:name":"Miller Asphalt Products Inc",
    "wof:placetype":"venue"
},
  "geometry": {"coordinates":[-76.88229699999999,39.495385],"type":"Point"}
}