{
  "type": "Feature",
  "properties": {
    "addr:full":"11717 Old National Pike New Market MD 21774",
    "addr:housenumber":"11717",
    "addr:postcode":"21774",
    "addr:street":"Old National Pike",
    "iso:country":"US",
    "sg:address":"11717 Old National Pike",
    "sg:city":"New Market",
    "sg:classifiers":[
        {
            "category":"Food & Beverages",
            "subcategory":"Liquor & Beverages",
            "type":"Retail Goods"
        }
    ],
    "sg:phone":"+1 301 695 9544",
    "sg:postcode":"21774",
    "sg:province":"MD",
    "wof:name":"Country Side Liquors",
    "wof:placetype":"venue"
},
  "geometry": {"coordinates":[-77.259129,39.385308],"type":"Point"}
}