{
  "type": "Feature",
  "properties": {
    "addr:full":"9401 Linden Ave Bethesda MD 20814",
    "addr:housenumber":"9401",
    "addr:postcode":"20814",
    "addr:street":"Linden Ave",
    "iso:country":"US",
    "sg:address":"9401 Linden Ave",
    "sg:city":"Bethesda",
    "sg:classifiers":[
        {
            "category":"Organizations",
            "subcategory":"Non-profit Organization",
            "type":"Services"
        }
    ],
    "sg:phone":"+1 301 530 6744",
    "sg:postcode":"20814",
    "sg:province":"MD",
    "wof:name":"Cyber Sustainable Networks",
    "wof:placetype":"venue"
},
  "geometry": {"coordinates":[-77.10760399999999,39.010608],"type":"Point"}
}