{
  "type": "Feature",
  "properties": {
    "iso:country":"US",
    "sg:address":"5219 Cedgate Rd",
    "sg:city":"Baltimore",
    "sg:classifiers":[
        {
            "category":"Building & Trades",
            "subcategory":"Landscaping Services",
            "type":"Services"
        }
    ],
    "sg:phone":"+1 443 676 9316",
    "sg:postcode":"21206",
    "sg:province":"MD",
    "sg:tags":[
        "landscape"
    ],
    "wof:name":"Shawn Porter",
    "wof:placetype":"venue"
},
  "geometry": {"coordinates":[-76.53364500000001,39.328094],"type":"Point"}
}