{
  "type": "Feature",
  "properties": {
    "addr:full":"4765 Dorsey Hall Dr Ellicott City MD 21042",
    "addr:housenumber":"4765",
    "addr:postcode":"21042",
    "addr:street":"Dorsey Hall Dr",
    "iso:country":"US",
    "sg:address":"4765 Dorsey Hall Dr",
    "sg:city":"Ellicott City",
    "sg:classifiers":[
        {
            "category":"Education",
            "subcategory":"Special Training",
            "type":"Public Place"
        }
    ],
    "sg:phone":"+1 410 964 9025",
    "sg:postcode":"21042",
    "sg:province":"MD",
    "sg:tags":[
        "tutoring"
    ],
    "wof:name":"Kumon USA Inc",
    "wof:placetype":"venue"
},
  "geometry": {"coordinates":[-76.842596,39.244299],"type":"Point"}
}