{
  "type": "Feature",
  "properties": {
    "addr:full":"305 Kentlands Blvd Gaithersburg MD 20878",
    "addr:housenumber":"305",
    "addr:postcode":"20878",
    "addr:street":"Kentlands Blvd",
    "iso:country":"US",
    "sg:address":"305 Kentlands Blvd",
    "sg:city":"Gaithersburg",
    "sg:classifiers":[
        {
            "category":"Food & Beverages",
            "subcategory":"Liquor & Beverages",
            "type":"Retail Goods"
        }
    ],
    "sg:phone":"+1 301 869 8880",
    "sg:postcode":"20878",
    "sg:province":"MD",
    "sg:tags":[
        "beer",
        "ale"
    ],
    "wof:name":"Kentlands Gourmet",
    "wof:placetype":"venue"
},
  "geometry": {"coordinates":[-77.23999000000001,39.123922],"type":"Point"}
}