{
  "type": "Feature",
  "properties": {
    "iso:country":"US",
    "sg:address":"6700 German Hill Rd",
    "sg:city":"Baltimore",
    "sg:classifiers":[
        {
            "category":"Bars & Pubs",
            "type":"Food & Drink"
        },
        {
            "category":"Restaurant",
            "type":"Food & Drink"
        },
        {
            "category":"Bars & Pubs",
            "subcategory":"Sports Bar",
            "type":"Food & Drink"
        }
    ],
    "sg:phone":"+1 410 633 2665",
    "sg:postcode":"21222",
    "sg:province":"MD",
    "sg:tags":[
        "brew"
    ],
    "wof:name":"Playbook Sports Bar & Grill",
    "wof:placetype":"venue"
},
  "geometry": {"coordinates":[-76.53368399999999,39.281279],"type":"Point"}
}