{
  "type": "Feature",
  "properties": {
    "iso:country":"US",
    "sg:address":"3570 Saint Johns Ln",
    "sg:city":"Ellicott City",
    "sg:classifiers":[
        {
            "category":"Health Services",
            "subcategory":"Doctor",
            "type":"Services"
        }
    ],
    "sg:phone":"+1 410 480 0082",
    "sg:postcode":"21042",
    "sg:province":"MD",
    "sg:tags":[
        "medical",
        "imaging"
    ],
    "wof:name":"Ellicot Open Mri",
    "wof:placetype":"venue"
},
  "geometry": {"coordinates":[-76.82637800000001,39.272826],"type":"Point"}
}