{
  "type": "Feature",
  "properties": {
    "iso:country":"US",
    "sg:address":"1809 Bloomingdale Rd",
    "sg:city":"Queenstown",
    "sg:classifiers":[
        {
            "category":"Farming",
            "subcategory":"Livestock Farm",
            "type":"Manufacturing & Wholesale Goods"
        }
    ],
    "sg:phone":"+1 410 827 9010",
    "sg:postcode":"21658",
    "sg:province":"MD",
    "sg:tags":[
        "ranch"
    ],
    "wof:name":"Circle S Horse Ranch",
    "wof:placetype":"venue"
},
  "geometry": {"coordinates":[-76.09847600000001,38.993548],"type":"Point"}
}