{
  "type": "Feature",
  "properties": {
    "addr:full":"586 Bellerive Rd Ste 2A Annapolis MD 21409",
    "addr:housenumber":"586",
    "addr:postcode":"21409",
    "addr:street":"Bellerive Rd Ste 2A",
    "iso:country":"US",
    "sg:address":"586 Bellerive Rd Ste 2A",
    "sg:city":"Annapolis",
    "sg:classifiers":[
        {
            "category":"Professional",
            "subcategory":"Business Services",
            "type":"Services"
        },
        {
            "category":"Conference Center",
            "type":"Public Place"
        }
    ],
    "sg:phone":"+1 410 349 2868",
    "sg:postcode":"21409",
    "sg:province":"MD",
    "sg:tags":[
        "facility",
        "supply",
        "convention"
    ],
    "wof:name":"National Artists Corporation",
    "wof:placetype":"venue"
},
  "geometry": {"coordinates":[-76.46367600000001,39.036732],"type":"Point"}
}