{
  "type": "Feature",
  "properties": {
    "iso:country":"US",
    "sg:address":"4733 Elm St 4th Fl",
    "sg:city":"Bethesda",
    "sg:classifiers":[
        {
            "category":"Sports & Exercise",
            "subcategory":"Gym",
            "type":"Entertainment"
        }
    ],
    "sg:phone":"+1 301 654 9644",
    "sg:postcode":"20814",
    "sg:province":"MD",
    "sg:tags":[
        "yoga"
    ],
    "sg:website":"www.downdogyoga.com",
    "wof:name":"Down Dog Yoga",
    "wof:placetype":"venue"
},
  "geometry": {"coordinates":[-77.09410800000001,38.982493],"type":"Point"}
}