{
  "type": "Feature",
  "properties": {
    "addr:full":"300 Tilghman Rd Salisbury MD 21804",
    "addr:housenumber":"300",
    "addr:postcode":"21804",
    "addr:street":"Tilghman Rd",
    "iso:country":"US",
    "sg:address":"300 Tilghman Rd",
    "sg:city":"Salisbury",
    "sg:classifiers":[
        {
            "category":"Banks & Credit Unions",
            "subcategory":"Bank",
            "type":"Services"
        }
    ],
    "sg:phone":"+1 410 749 4200",
    "sg:postcode":"21804",
    "sg:province":"MD",
    "wof:name":"Bank Of America",
    "wof:placetype":"venue"
},
  "geometry": {"coordinates":[-75.547887,38.364087],"type":"Point"}
}