{
  "type": "Feature",
  "properties": {
    "addr:full":"16001 Avery Rd Derwood MD 20855",
    "addr:housenumber":"16001",
    "addr:postcode":"20855",
    "addr:street":"Avery Rd",
    "iso:country":"US",
    "sg:address":"16001 Avery Rd",
    "sg:city":"Derwood",
    "sg:classifiers":[
        {
            "category":"Travel",
            "subcategory":"Travel Agent",
            "type":"Entertainment"
        }
    ],
    "sg:phone":"+1 301 251 4457",
    "sg:postcode":"20855",
    "sg:province":"MD",
    "sg:tags":[
        "cruise"
    ],
    "sg:website":"www.crus-sun.com",
    "wof:name":"Islands In The Sun Cruises",
    "wof:placetype":"venue"
},
  "geometry": {"coordinates":[-77.11960500000001,39.118415],"type":"Point"}
}