{
  "type": "Feature",
  "properties": {
    "addr:full":"1641 State Route 3 N Crofton MD 21114",
    "addr:housenumber":"1641",
    "addr:postcode":"21114",
    "addr:street":"State Route 3 N",
    "iso:country":"US",
    "sg:address":"1641 State Route 3 N",
    "sg:city":"Crofton",
    "sg:classifiers":[
        {
            "category":"Restaurant",
            "type":"Food & Drink"
        }
    ],
    "sg:menulink":"http://www.allmenus.com/md/annapolis/256726-super-suppers/menu/",
    "sg:phone":"+1 410 451 3322",
    "sg:postcode":"21114",
    "sg:province":"MD",
    "sg:tags":[
        "new",
        "american"
    ],
    "wof:name":"Super Suppers",
    "wof:placetype":"venue"
},
  "geometry": {"coordinates":[-76.701635,38.99442],"type":"Point"}
}