{
  "type": "Feature",
  "properties": {
    "iso:country":"US",
    "sg:address":"17 Ridge Rd",
    "sg:city":"Greenbelt",
    "sg:classifiers":[
        {
            "category":"Professional",
            "subcategory":"Business Services",
            "type":"Services"
        }
    ],
    "sg:phone":"+1 301 513 0433",
    "sg:postcode":"20770",
    "sg:province":"MD",
    "wof:name":"Avis Cohen",
    "wof:placetype":"venue"
},
  "geometry": {"coordinates":[-76.875164,38.999021],"type":"Point"}
}