{
  "type": "Feature",
  "properties": {
    "iso:country":"US",
    "sg:address":"7925 Bent Bough Rd",
    "sg:city":"Severn",
    "sg:classifiers":[
        {
            "category":"Banks & Credit Unions",
            "subcategory":"Investment Brokerage",
            "type":"Services"
        }
    ],
    "sg:phone":"+1 410 551 0200",
    "sg:postcode":"21144",
    "sg:province":"MD",
    "sg:tags":[
        "advisory",
        "financial"
    ],
    "wof:name":"Lincoln Financial Group",
    "wof:placetype":"venue"
},
  "geometry": {"coordinates":[-76.705822,39.13088],"type":"Point"}
}