{
  "type": "Feature",
  "properties": {
    "addr:full":"3709 Pulaski Hwy Abingdon MD 21009",
    "addr:housenumber":"3709",
    "addr:postcode":"21009",
    "addr:street":"Pulaski Hwy",
    "iso:country":"US",
    "sg:address":"3709 Pulaski Hwy",
    "sg:city":"Abingdon",
    "sg:classifiers":[
        {
            "category":"Personal",
            "subcategory":"Beauty Salon",
            "type":"Services"
        }
    ],
    "sg:phone":"+1 410 612 0819",
    "sg:postcode":"21009",
    "sg:province":"MD",
    "sg:tags":[
        "manicuring"
    ],
    "wof:name":"C T Nails II",
    "wof:placetype":"venue"
},
  "geometry": {"coordinates":[-76.258667,39.458445],"type":"Point"}
}