{
  "type": "Feature",
  "properties": {
    "addr:full":"5700 Spring St Clinton MD 20735",
    "addr:housenumber":"5700",
    "addr:postcode":"20735",
    "addr:street":"Spring St",
    "iso:country":"US",
    "sg:address":"5700 Spring St",
    "sg:city":"Clinton",
    "sg:classifiers":[
        {
            "category":"Wholesale",
            "subcategory":"Electrical",
            "type":"Manufacturing & Wholesale Goods"
        }
    ],
    "sg:phone":"+1 301 234 9881",
    "sg:postcode":"20735",
    "sg:province":"MD",
    "sg:tags":[
        "alarm",
        "burglar",
        "system"
    ],
    "wof:name":"Dave's Auto Alarm",
    "wof:placetype":"venue"
},
  "geometry": {"coordinates":[-76.909374,38.784686],"type":"Point"}
}