{
  "type": "Feature",
  "properties": {
    "iso:country":"US",
    "sg:address":"19505 Bodmer Ave",
    "sg:city":"Poolesville",
    "sg:classifiers":[
        {
            "category":"Professional",
            "subcategory":"Engineering",
            "type":"Services"
        }
    ],
    "sg:phone":"+1 301 972 7245",
    "sg:postcode":"20837",
    "sg:province":"MD",
    "sg:tags":[
        "engineer"
    ],
    "wof:name":"Purdy Engineering",
    "wof:placetype":"venue"
},
  "geometry": {"coordinates":[-77.409794,39.135355],"type":"Point"}
}