{
  "type": "Feature",
  "properties": {
    "addr:full":"4807 Lydell Rd Hyattsville MD 20781",
    "addr:housenumber":"4807",
    "addr:postcode":"20781",
    "addr:street":"Lydell Rd",
    "iso:country":"US",
    "sg:address":"4807 Lydell Rd",
    "sg:city":"Hyattsville",
    "sg:classifiers":[
        {
            "category":"Manufacturing",
            "subcategory":"Tools & Machinery",
            "type":"Manufacturing & Wholesale Goods"
        }
    ],
    "sg:phone":"+1 301 341 2000",
    "sg:postcode":"20781",
    "sg:province":"MD",
    "sg:tags":[
        "equipment",
        "system",
        "automation"
    ],
    "sg:website":"www.tsgdc.com",
    "wof:name":"Technical Services Group Inc",
    "wof:placetype":"venue"
},
  "geometry": {"coordinates":[-76.92430899999999,38.925653],"type":"Point"}
}