{
  "type": "Feature",
  "properties": {
    "iso:country":"US",
    "sg:address":"940 Clopper Rd",
    "sg:city":"Gaithersburg",
    "sg:classifiers":[
        {
            "category":"Wholesale",
            "subcategory":"Electrical",
            "type":"Manufacturing & Wholesale Goods"
        }
    ],
    "sg:phone":"+1 301 840 1650",
    "sg:postcode":"20878",
    "sg:province":"MD",
    "sg:tags":[
        "equipment",
        "electric",
        "supply"
    ],
    "sg:website":"www.hitachi-hhta.com",
    "wof:name":"Hitachi High-Tech America Inc",
    "wof:placetype":"venue"
},
  "geometry": {"coordinates":[-77.22770300000001,39.145486],"type":"Point"}
}