{
  "type": "Feature",
  "properties": {
    "addr:full":"11917 Ocean Gtwy Ocean City MD 21842",
    "addr:housenumber":"11917",
    "addr:postcode":"21842",
    "addr:street":"Ocean Gtwy",
    "iso:country":"US",
    "sg:address":"11917 Ocean Gtwy",
    "sg:city":"Ocean City",
    "sg:classifiers":[
        {
            "category":"Autos & Motor Vehicles",
            "subcategory":"Automobile Sales",
            "type":"Retail Goods"
        }
    ],
    "sg:phone":"+1 410 213 9505",
    "sg:postcode":"21842",
    "sg:province":"MD",
    "sg:tags":[
        "car",
        "dealer"
    ],
    "wof:name":"Coastal Auto Inc",
    "wof:placetype":"venue"
},
  "geometry": {"coordinates":[-75.14164100000001,38.33759],"type":"Point"}
}