{
  "type": "Feature",
  "properties": {
    "addr:full":"10101 Grosvenor Pl Rockville MD 20852",
    "addr:housenumber":"10101",
    "addr:postcode":"20852",
    "addr:street":"Grosvenor Pl",
    "iso:country":"US",
    "sg:address":"10101 Grosvenor Pl",
    "sg:city":"Rockville",
    "sg:classifiers":[
        {
            "category":"Professional",
            "subcategory":"Computer Services",
            "type":"Services"
        }
    ],
    "sg:phone":"+1 301 530 7670",
    "sg:postcode":"20852",
    "sg:province":"MD",
    "sg:tags":[
        "design",
        "datum",
        "system"
    ],
    "wof:name":"Oak Tree Web Internet Cmpt Svc",
    "wof:placetype":"venue"
},
  "geometry": {"coordinates":[-77.103741,39.024523],"type":"Point"}
}