{
  "type": "Feature",
  "properties": {
    "addr:full":"607 Eastern Blvd Essex MD 21221",
    "addr:housenumber":"607",
    "addr:postcode":"21221",
    "addr:street":"Eastern Blvd",
    "iso:country":"US",
    "sg:address":"607 Eastern Blvd",
    "sg:city":"Essex",
    "sg:classifiers":[
        {
            "category":"Building & Trades",
            "subcategory":"Construction",
            "type":"Services"
        }
    ],
    "sg:phone":"+1 410 686 6162",
    "sg:postcode":"21221",
    "sg:province":"MD",
    "sg:tags":[
        "general",
        "contractor"
    ],
    "wof:name":"Hammerhead Construction Inc",
    "wof:placetype":"venue"
},
  "geometry": {"coordinates":[-76.471388,39.310033],"type":"Point"}
}