{
  "type": "Feature",
  "properties": {
    "iso:country":"US",
    "sg:address":"10211 River Rd",
    "sg:city":"Potomac",
    "sg:classifiers":[
        {
            "category":"Building & Trades",
            "subcategory":"Equipment Rental",
            "type":"Services"
        }
    ],
    "sg:phone":"+1 301 299 0005",
    "sg:postcode":"20854",
    "sg:province":"MD",
    "sg:tags":[
        "aircraft",
        "leasing",
        "charter"
    ],
    "sg:website":"www.cortassociates.com",
    "wof:name":"Cort & Assoc Inc",
    "wof:placetype":"venue"
},
  "geometry": {"coordinates":[-77.210998,39.019415],"type":"Point"}
}