{
  "type": "Feature",
  "properties": {
    "iso:country":"US",
    "sg:address":"52 Stirrup Ct",
    "sg:city":"Pikesville",
    "sg:classifiers":[
        {
            "category":"Health Services",
            "subcategory":"Doctor",
            "type":"Services"
        }
    ],
    "sg:phone":"+1 410 580 2984",
    "sg:postcode":"21208",
    "sg:province":"MD",
    "sg:tags":[
        "dentist"
    ],
    "wof:name":"Fred M Scholnick DDS",
    "wof:placetype":"venue"
},
  "geometry": {"coordinates":[-76.72936,39.389284],"type":"Point"}
}