{
  "type": "Feature",
  "properties": {
    "addr:full":"2331 Barclay St Baltimore MD 21218",
    "addr:housenumber":"2331",
    "addr:postcode":"21218",
    "addr:street":"Barclay St",
    "iso:country":"US",
    "sg:address":"2331 Barclay St",
    "sg:city":"Baltimore",
    "sg:classifiers":[
        {
            "category":"Bars & Pubs",
            "subcategory":"Lounge",
            "type":"Food & Drink"
        },
        {
            "category":"Food & Beverages",
            "subcategory":"Liquor & Beverages",
            "type":"Retail Goods"
        }
    ],
    "sg:phone":"+1 410 243 4342",
    "sg:postcode":"21218",
    "sg:province":"MD",
    "sg:tags":[
        "cocktail",
        "store"
    ],
    "wof:name":"A J Cutrate Liquors",
    "wof:placetype":"venue"
},
  "geometry": {"coordinates":[-76.61122400000001,39.315945],"type":"Point"}
}