{
  "type": "Feature",
  "properties": {
    "iso:country":"US",
    "sg:address":"31741 Peggy Neck Rd",
    "sg:city":"Princess Anne",
    "sg:classifiers":[
        {
            "category":"Retail",
            "subcategory":"Animal Services",
            "type":"Services"
        }
    ],
    "sg:phone":"+1 410 957 4669",
    "sg:postcode":"21853",
    "sg:province":"MD",
    "wof:name":"Sterrett Kennels",
    "wof:placetype":"venue"
},
  "geometry": {"coordinates":[-75.646637,38.252638],"type":"Point"}
}