{
  "type": "Feature",
  "properties": {
    "iso:country":"US",
    "sg:address":"15789 Livingston Rd",
    "sg:city":"Accokeek",
    "sg:classifiers":[
        {
            "category":"Shopping",
            "type":"Retail Goods"
        }
    ],
    "sg:phone":"+1 301 292 8929",
    "sg:postcode":"20607",
    "sg:province":"MD",
    "sg:tags":[
        "merchandise"
    ],
    "wof:name":"Wireless Zone 135",
    "wof:placetype":"venue"
},
  "geometry": {"coordinates":[-77.010648,38.670089],"type":"Point"}
}