{
  "type": "Feature",
  "properties": {
    "addr:full":"2619 Baltimore Blvd Finksburg MD 21048",
    "addr:housenumber":"2619",
    "addr:postcode":"21048",
    "addr:street":"Baltimore Blvd",
    "iso:country":"US",
    "sg:address":"2619 Baltimore Blvd",
    "sg:city":"Finksburg",
    "sg:classifiers":[
        {
            "category":"Personal",
            "subcategory":"Beauty Salon",
            "type":"Services"
        }
    ],
    "sg:phone":"+1 410 861 9099",
    "sg:postcode":"21048",
    "sg:province":"MD",
    "sg:tags":[
        "shop"
    ],
    "wof:name":"Patti Parks Pizzaz",
    "wof:placetype":"venue"
},
  "geometry": {"coordinates":[-76.902092,39.505839],"type":"Point"}
}