{
  "type": "Feature",
  "properties": {
    "addr:full":"2916 Blue Goose Rd Friendsville MD 21531",
    "addr:housenumber":"2916",
    "addr:postcode":"21531",
    "addr:street":"Blue Goose Rd",
    "iso:country":"US",
    "sg:address":"2916 Blue Goose Rd",
    "sg:city":"Friendsville",
    "sg:classifiers":[
        {
            "category":"Building & Trades",
            "subcategory":"Electrical",
            "type":"Services"
        }
    ],
    "sg:phone":"+1 301 746 4226",
    "sg:postcode":"21531",
    "sg:province":"MD",
    "sg:tags":[
        "electrical",
        "contractor"
    ],
    "wof:name":"Richard Fortune",
    "wof:placetype":"venue"
},
  "geometry": {"coordinates":[-79.454086,39.680316],"type":"Point"}
}