{
  "type": "Feature",
  "properties": {
    "iso:country":"US",
    "sg:address":"2749 Flintridge Dr",
    "sg:city":"Myersville",
    "sg:classifiers":[
        {
            "category":"Professional",
            "type":"Services"
        }
    ],
    "sg:phone":"+1 301 293 8931",
    "sg:postcode":"21773",
    "sg:province":"MD",
    "wof:name":"Thoughtful Things",
    "wof:placetype":"venue"
},
  "geometry": {"coordinates":[-77.571805,39.5109],"type":"Point"}
}