{
  "type": "Feature",
  "properties": {
    "iso:country":"US",
    "sg:address":"6600 Ronald Rd",
    "sg:city":"Capitol Heights",
    "sg:classifiers":[
        {
            "category":"Shopping",
            "type":"Retail Goods"
        }
    ],
    "sg:phone":"+1 301 350 4775",
    "sg:postcode":"20743",
    "sg:province":"MD",
    "sg:tags":[
        "merchandise",
        "african"
    ],
    "wof:name":"African Images Inc",
    "wof:placetype":"venue"
},
  "geometry": {"coordinates":[-76.892179,38.872602],"type":"Point"}
}