{
  "type": "Feature",
  "properties": {
    "addr:full":"900 E Fayette St Baltimore MD 21233",
    "addr:housenumber":"900",
    "addr:postcode":"21233",
    "addr:street":"E Fayette St",
    "iso:country":"US",
    "sg:address":"900 E Fayette St",
    "sg:city":"Baltimore",
    "sg:classifiers":[
        {
            "category":"Banks & Credit Unions",
            "subcategory":"Bank",
            "type":"Services"
        }
    ],
    "sg:phone":"+1 410 727 5469",
    "sg:postcode":"21233",
    "sg:province":"MD",
    "wof:name":"Post Office Credit Union of Maryland Inc",
    "wof:placetype":"venue"
},
  "geometry": {"coordinates":[-76.60459899999999,39.291199],"type":"Point"}
}