{
  "type": "Feature",
  "properties": {
    "addr:full":"2050 Baile Dr New Windsor MD 21776",
    "addr:housenumber":"2050",
    "addr:postcode":"21776",
    "addr:street":"Baile Dr",
    "iso:country":"US",
    "sg:address":"2050 Baile Dr",
    "sg:city":"New Windsor",
    "sg:classifiers":[
        {
            "category":"Building & Trades",
            "subcategory":"Plumbing",
            "type":"Services"
        }
    ],
    "sg:phone":"+1 410 875 0300",
    "sg:postcode":"21776",
    "sg:province":"MD",
    "sg:tags":[
        "plumbing",
        "contractor"
    ],
    "wof:name":"Gregory C Fryfogle Plumbing",
    "wof:placetype":"venue"
},
  "geometry": {"coordinates":[-77.069258,39.515895],"type":"Point"}
}