{
  "type": "Feature",
  "properties": {
    "addr:full":"1519 E North Ave Baltimore MD 21213",
    "addr:housenumber":"1519",
    "addr:postcode":"21213",
    "addr:street":"E North Ave",
    "iso:country":"US",
    "sg:address":"1519 E North Ave",
    "sg:city":"Baltimore",
    "sg:classifiers":[
        {
            "category":"Health Services",
            "subcategory":"Dentist",
            "type":"Services"
        }
    ],
    "sg:phone":"+1 410 962 1620",
    "sg:postcode":"21213",
    "sg:province":"MD",
    "wof:name":"Blakely Maurice W Dntst",
    "wof:placetype":"venue"
},
  "geometry": {"coordinates":[-76.59760300000001,39.312099],"type":"Point"}
}