{
  "type": "Feature",
  "properties": {
    "addr:full":"535 S Philadelphia Blvd Aberdeen MD 21001",
    "addr:housenumber":"535",
    "addr:postcode":"21001",
    "addr:street":"S Philadelphia Blvd",
    "iso:country":"US",
    "sg:address":"535 S Philadelphia Blvd",
    "sg:city":"Aberdeen",
    "sg:classifiers":[
        {
            "category":"Banks & Credit Unions",
            "subcategory":"Bank",
            "type":"Services"
        }
    ],
    "sg:phone":"+1 410 272 8056",
    "sg:postcode":"21001",
    "sg:province":"MD",
    "sg:tags":[
        "financing"
    ],
    "wof:name":"Chesapeake Acceptance Corp",
    "wof:placetype":"venue"
},
  "geometry": {"coordinates":[-76.167818,39.502218],"type":"Point"}
}