{
  "type": "Feature",
  "properties": {
    "iso:country":"US",
    "sg:address":"12710 Veirs Mill Rd",
    "sg:city":"Rockville",
    "sg:classifiers":[
        {
            "category":"Professional",
            "type":"Services"
        }
    ],
    "sg:phone":"+1 301 949 4335",
    "sg:postcode":"20853",
    "sg:province":"MD",
    "wof:name":"R D R Multi Services Incorpora",
    "wof:placetype":"venue"
},
  "geometry": {"coordinates":[-77.103285,39.067879],"type":"Point"}
}