{
  "type": "Feature",
  "properties": {
    "addr:full":"4979 Mercantile Rd Baltimore MD 21236",
    "addr:housenumber":"4979",
    "addr:postcode":"21236",
    "addr:street":"Mercantile Rd",
    "iso:country":"US",
    "sg:address":"4979 Mercantile Rd",
    "sg:city":"Baltimore",
    "sg:classifiers":[
        {
            "category":"Government",
            "subcategory":"Office",
            "type":"Public Place"
        }
    ],
    "sg:phone":"+1 410 529 7332",
    "sg:postcode":"21236",
    "sg:province":"MD",
    "sg:tags":[
        "state",
        "program",
        "health"
    ],
    "wof:name":"Helix-Medstar Health",
    "wof:placetype":"venue"
},
  "geometry": {"coordinates":[-76.459964,39.376971],"type":"Point"}
}