{
  "type": "Feature",
  "properties": {
    "iso:country":"US",
    "sg:address":"801 Cromwell Park Dr",
    "sg:city":"Glen Burnie",
    "sg:classifiers":[
        {
            "category":"Manufacturing",
            "subcategory":"Printing",
            "type":"Manufacturing & Wholesale Goods"
        }
    ],
    "sg:phone":"+1 410 689 0690",
    "sg:postcode":"21061",
    "sg:province":"MD",
    "sg:tags":[
        "printer"
    ],
    "wof:name":"Tray Business Systems Inc",
    "wof:placetype":"venue"
},
  "geometry": {"coordinates":[-76.641215,39.177044],"type":"Point"}
}