{
  "type": "Feature",
  "properties": {
    "addr:full":"211 Wellington Woods Ct Bel Air MD 21014",
    "addr:housenumber":"211",
    "addr:postcode":"21014",
    "addr:street":"Wellington Woods Ct",
    "iso:country":"US",
    "sg:address":"211 Wellington Woods Ct",
    "sg:city":"Bel Air",
    "sg:classifiers":[
        {
            "category":"Professional",
            "subcategory":"Business Services",
            "type":"Services"
        }
    ],
    "sg:phone":"+1 410 836 7242",
    "sg:postcode":"21014",
    "sg:province":"MD",
    "wof:name":"Holly R Theuns",
    "wof:placetype":"venue"
},
  "geometry": {"coordinates":[-76.349583,39.543243],"type":"Point"}
}