{
  "type": "Feature",
  "properties": {
    "addr:full":"219 Stacey Lee Dr Westminster MD 21158",
    "addr:housenumber":"219",
    "addr:postcode":"21158",
    "addr:street":"Stacey Lee Dr",
    "iso:country":"US",
    "sg:address":"219 Stacey Lee Dr",
    "sg:city":"Westminster",
    "sg:classifiers":[
        {
            "category":"Organizations",
            "subcategory":"Professional Association",
            "type":"Services"
        }
    ],
    "sg:phone":"+1 410 848 1233",
    "sg:postcode":"21158",
    "sg:province":"MD",
    "wof:name":"Greens Homeowners Assn",
    "wof:placetype":"venue"
},
  "geometry": {"coordinates":[-77.030101,39.584251],"type":"Point"}
}