{
  "type": "Feature",
  "properties": {
    "iso:country":"US",
    "sg:address":"1500 Country Ridge Ln",
    "sg:city":"Essex",
    "sg:classifiers":[
        {
            "category":"Shopping",
            "subcategory":"Used Merchandise",
            "type":"Retail Goods"
        }
    ],
    "sg:phone":"+1 410 391 1111",
    "sg:postcode":"21221",
    "sg:province":"MD",
    "sg:tags":[
        "shop",
        "thrift"
    ],
    "wof:name":"B & B Thrift Store",
    "wof:placetype":"venue"
},
  "geometry": {"coordinates":[-76.446635,39.310638],"type":"Point"}
}