{
  "type": "Feature",
  "properties": {
    "addr:full":"7315 Wisconsin Ave Suite 910 Bethesda MD 20814",
    "addr:housenumber":"7315",
    "addr:postcode":"20814",
    "addr:street":"Wisconsin Ave Suite 910",
    "iso:country":"US",
    "sg:address":"7315 Wisconsin Ave Suite 910",
    "sg:city":"Bethesda",
    "sg:classifiers":[
        {
            "category":"Professional",
            "subcategory":"Lawyer & Legal Services",
            "type":"Services"
        }
    ],
    "sg:phone":"+1 301 961 6430",
    "sg:postcode":"20814",
    "sg:province":"MD",
    "sg:tags":[
        "attorney",
        "law",
        "contract"
    ],
    "sg:website":"http://www.whiteandhorton.com",
    "wof:name":"White & Horton, Attorneys At Law",
    "wof:placetype":"venue"
},
  "geometry": {"coordinates":[-77.093277,38.982601],"type":"Point"}
}