{
  "type": "Feature",
  "properties": {
    "iso:country":"US",
    "sg:address":"8692 Doves Fly Way",
    "sg:city":"Laurel",
    "sg:classifiers":[
        {
            "category":"Professional",
            "subcategory":"Business Services",
            "type":"Services"
        }
    ],
    "sg:phone":"+1 301 490 0572",
    "sg:postcode":"20723",
    "sg:province":"MD",
    "wof:name":"Janmar Sales Inc",
    "wof:placetype":"venue"
},
  "geometry": {"coordinates":[-76.868399,39.133782],"type":"Point"}
}