{
  "type": "Feature",
  "properties": {
    "addr:full":"6931 Arlington Rd Ste 410 Bethesda MD 20814",
    "addr:housenumber":"6931",
    "addr:postcode":"20814",
    "addr:street":"Arlington Rd Ste 410",
    "iso:country":"US",
    "sg:address":"6931 Arlington Rd Ste 410",
    "sg:city":"Bethesda",
    "sg:classifiers":[
        {
            "category":"Real Estate",
            "subcategory":"Real Estate Services",
            "type":"Services"
        }
    ],
    "sg:phone":"+1 301 656 0465",
    "sg:postcode":"20814",
    "sg:province":"MD",
    "sg:tags":[
        "management",
        "property"
    ],
    "wof:name":"Harvey Property Management Co Inc",
    "wof:placetype":"venue"
},
  "geometry": {"coordinates":[-77.09870100000001,38.9785],"type":"Point"}
}