{
  "type": "Feature",
  "properties": {
    "iso:country":"US",
    "sg:address":"13 N 3rd St",
    "sg:city":"Denton",
    "sg:classifiers":[
        {
            "category":"Government",
            "subcategory":"Office",
            "type":"Public Place"
        }
    ],
    "sg:phone":"+1 410 479 2050",
    "sg:postcode":"21629",
    "sg:province":"MD",
    "sg:tags":[
        "village"
    ],
    "wof:name":"Denton City Commissioners Ofc",
    "wof:placetype":"venue"
},
  "geometry": {"coordinates":[-75.831529,38.886469],"type":"Point"}
}