{
  "type": "Feature",
  "properties": {
    "iso:country":"US",
    "sg:address":"991 Generals Hwy",
    "sg:city":"Crownsville",
    "sg:classifiers":[
        {
            "category":"Building & Trades",
            "subcategory":"Construction",
            "type":"Services"
        }
    ],
    "sg:phone":"+1 410 923 2237",
    "sg:postcode":"21032",
    "sg:province":"MD",
    "sg:tags":[
        "consultant",
        "industrial",
        "contractors-commercial"
    ],
    "wof:name":"All Tides Marine Contracting",
    "wof:placetype":"venue"
},
  "geometry": {"coordinates":[-76.621696,39.055119],"type":"Point"}
}