{
  "type": "Feature",
  "properties": {
    "iso:country":"US",
    "sg:address":"11120 New Hampshire Ave",
    "sg:city":"Silver Spring",
    "sg:classifiers":[
        {
            "category":"Social Services",
            "type":"Services"
        }
    ],
    "sg:phone":"+1 301 593 9200",
    "sg:postcode":"20904",
    "sg:province":"MD",
    "sg:tags":[
        "counselor",
        "marriage",
        "family"
    ],
    "sg:website":"www.adoptionsupport.org",
    "wof:name":"Center For Adoption Support",
    "wof:placetype":"venue"
},
  "geometry": {"coordinates":[-76.991264,39.040994],"type":"Point"}
}