{
  "type": "Feature",
  "properties": {
    "addr:full":"9601 Medical Center Dr Rockville MD 20850",
    "addr:housenumber":"9601",
    "addr:postcode":"20850",
    "addr:street":"Medical Center Dr",
    "iso:country":"US",
    "sg:address":"9601 Medical Center Dr",
    "sg:city":"Rockville",
    "sg:classifiers":[
        {
            "category":"Education",
            "subcategory":"College",
            "type":"Public Place"
        }
    ],
    "sg:phone":"+1 301 294 7000",
    "sg:postcode":"20850",
    "sg:province":"MD",
    "sg:tags":[
        "academic",
        "school"
    ],
    "sg:website":"www.jhu.edu",
    "wof:name":"Johns Hopkins University",
    "wof:placetype":"venue"
},
  "geometry": {"coordinates":[-77.195449,39.101436],"type":"Point"}
}