{
  "type": "Feature",
  "properties": {
    "iso:country":"US",
    "sg:address":"7505 Democracy Blvd",
    "sg:city":"Bethesda",
    "sg:classifiers":[
        {
            "category":"Professional",
            "subcategory":"Management & Consulting",
            "type":"Services"
        }
    ],
    "sg:phone":"+1 301 365 1187",
    "sg:postcode":"20817",
    "sg:province":"MD",
    "sg:tags":[
        "consultant",
        "business"
    ],
    "wof:name":"Garvin Group",
    "wof:placetype":"venue"
},
  "geometry": {"coordinates":[-77.152326,39.023002],"type":"Point"}
}