{
  "type": "Feature",
  "properties": {
    "addr:full":"15 Visitors Center Dr Mc Henry MD 21541",
    "addr:postcode":"21541",
    "addr:street":"Mc Henry",
    "iso:country":"US",
    "sg:address":"15 Visitors Center Dr",
    "sg:city":"Mc Henry",
    "sg:classifiers":[
        {
            "category":"Travel",
            "subcategory":"Travel Agent",
            "type":"Entertainment"
        }
    ],
    "sg:phone":"+1 301 387 6171",
    "sg:postcode":"21541",
    "sg:province":"MD",
    "sg:tags":[
        "information",
        "tourist"
    ],
    "sg:website":"www.garrettchamber.com",
    "wof:name":"Deep Creek Lake Information",
    "wof:placetype":"venue"
},
  "geometry": {"coordinates":[-79.35909700000001,39.561707],"type":"Point"}
}