{
  "type": "Feature",
  "properties": {
    "addr:full":"4101 Suit Rd District Heights MD 20747",
    "addr:housenumber":"4101",
    "addr:postcode":"20747",
    "addr:street":"Suit Rd",
    "iso:country":"US",
    "sg:address":"4101 Suit Rd",
    "sg:city":"District Heights",
    "sg:classifiers":[
        {
            "category":"Building & Trades",
            "subcategory":"Construction",
            "type":"Services"
        }
    ],
    "sg:phone":"+1 240 353 3034",
    "sg:postcode":"20747",
    "sg:province":"MD",
    "sg:tags":[
        "roofing"
    ],
    "wof:name":"Forestville Roofing",
    "wof:placetype":"venue"
},
  "geometry": {"coordinates":[-76.877399,38.834888],"type":"Point"}
}