{
  "type": "Feature",
  "properties": {
    "iso:country":"US",
    "sg:address":"201 Booth St",
    "sg:city":"Elkton",
    "sg:classifiers":[
        {
            "category":"Education",
            "subcategory":"School",
            "type":"Public Place"
        }
    ],
    "sg:phone":"+1 410 996 5400",
    "sg:postcode":"21921",
    "sg:province":"MD",
    "sg:website":"www.ccps.org",
    "wof:name":"Cecil County Public Schools",
    "wof:placetype":"venue"
},
  "geometry": {"coordinates":[-75.826117,39.613046],"type":"Point"}
}