{
  "type": "Feature",
  "properties": {
    "addr:full":"633 Ocean Hwy Pocomoke City MD 21851",
    "addr:housenumber":"633",
    "addr:postcode":"21851",
    "addr:street":"Ocean Hwy",
    "iso:country":"US",
    "sg:address":"633 Ocean Hwy",
    "sg:city":"Pocomoke City",
    "sg:classifiers":[
        {
            "category":"Home & Garden",
            "subcategory":"Building Materials",
            "type":"Retail Goods"
        }
    ],
    "sg:phone":"+1 410 957 6184",
    "sg:postcode":"21851",
    "sg:province":"MD",
    "sg:website":"www.84lumber.com",
    "wof:name":"84 Lumber Co",
    "wof:placetype":"venue"
},
  "geometry": {"coordinates":[-75.543719,38.015838],"type":"Point"}
}