{
  "type": "Feature",
  "properties": {
    "iso:country":"US",
    "sg:address":"6701 Democracy Blvd",
    "sg:city":"Bethesda",
    "sg:classifiers":[
        {
            "category":"Banks & Credit Unions",
            "subcategory":"Bank",
            "type":"Services"
        }
    ],
    "sg:phone":"+1 301 571 9399",
    "sg:postcode":"20817",
    "sg:province":"MD",
    "sg:tags":[
        "loan",
        "real estate"
    ],
    "wof:name":"First Women's Mortgage",
    "wof:placetype":"venue"
},
  "geometry": {"coordinates":[-77.13637199999999,39.021812],"type":"Point"}
}