{
  "type": "Feature",
  "properties": {
    "addr:full":"1 Silversage Ct Cockysvl Hnt Vly MD 21030",
    "addr:housenumber":"1",
    "addr:postcode":"21030",
    "addr:street":"Silversage Ct Cockysvl Hnt Vly",
    "iso:country":"US",
    "sg:address":"1 Silversage Ct",
    "sg:city":"Cockysvl Hnt Vly",
    "sg:classifiers":[
        {
            "category":"Banks & Credit Unions",
            "subcategory":"Bank",
            "type":"Services"
        }
    ],
    "sg:phone":"+1 410 527 1488",
    "sg:postcode":"21030",
    "sg:province":"MD",
    "sg:tags":[
        "loan",
        "real estate"
    ],
    "wof:name":"Personal Mortgage Bankers",
    "wof:placetype":"venue"
},
  "geometry": {"coordinates":[-76.64090299999999,39.497583],"type":"Point"}
}