{
  "type": "Feature",
  "properties": {
    "iso:country":"US",
    "sg:address":"8600 Lasalle Rd",
    "sg:city":"Baltimore",
    "sg:classifiers":[
        {
            "category":"Health Services",
            "subcategory":"Doctor",
            "type":"Services"
        }
    ],
    "sg:phone":"+1 410 321 9595",
    "sg:postcode":"21286",
    "sg:province":"MD",
    "sg:tags":[
        "dentist"
    ],
    "wof:name":"Richard Mao DDS",
    "wof:placetype":"venue"
},
  "geometry": {"coordinates":[-76.57597699999999,39.395913],"type":"Point"}
}