{
  "type": "Feature",
  "properties": {
    "iso:country":"US",
    "sg:address":"7261 Eden Brook Dr 206",
    "sg:city":"Columbia",
    "sg:classifiers":[
        {
            "category":"Real Estate",
            "subcategory":"Real Estate Operator",
            "type":"Services"
        }
    ],
    "sg:phone":"+1 410 381 8500",
    "sg:postcode":"21046",
    "sg:province":"MD",
    "sg:tags":[
        "apartment"
    ],
    "wof:name":"St Matthews Housing Inc",
    "wof:placetype":"venue"
},
  "geometry": {"coordinates":[-76.866348,39.169706],"type":"Point"}
}