{
  "type": "Feature",
  "properties": {
    "iso:country":"US",
    "sg:address":"328 S Cleveland Ave",
    "sg:city":"Hagerstown",
    "sg:classifiers":[
        {
            "category":"Bakery",
            "type":"Food & Drink"
        }
    ],
    "sg:phone":"+1 240 674 1039",
    "sg:postcode":"21740",
    "sg:province":"MD",
    "wof:name":"Brown's Tropical Treats",
    "wof:placetype":"venue"
},
  "geometry": {"coordinates":[-77.71116600000001,39.63417],"type":"Point"}
}