{
  "type": "Feature",
  "properties": {
    "iso:country":"US",
    "sg:address":"3135 E West Hwy",
    "sg:city":"Chevy Chase",
    "sg:classifiers":[
        {
            "category":"Building & Trades",
            "subcategory":"Locksmith",
            "type":"Services"
        }
    ],
    "sg:phone":"+1 202 621 2367",
    "sg:postcode":"20815",
    "sg:province":"MD",
    "sg:tags":[
        "key"
    ],
    "wof:name":"Fast Locksmith",
    "wof:placetype":"venue"
},
  "geometry": {"coordinates":[-77.064329,38.99335],"type":"Point"}
}