{
  "type": "Feature",
  "properties": {
    "iso:country":"US",
    "sg:address":"222 Main St",
    "sg:city":"Annapolis",
    "sg:classifiers":[
        {
            "category":"Food & Beverages",
            "subcategory":"Groceries & Convenience Stores",
            "type":"Retail Goods"
        }
    ],
    "sg:phone":"+1 410 626 2099",
    "sg:postcode":"21401",
    "sg:province":"MD",
    "wof:name":"Main St Mini Mart",
    "wof:placetype":"venue"
},
  "geometry": {"coordinates":[-76.491511,38.978189],"type":"Point"}
}