{
  "type": "Feature",
  "properties": {
    "addr:full":"1025 Washington Blvd S Laurel MD 20707",
    "addr:housenumber":"1025",
    "addr:postcode":"20707",
    "addr:street":"Washington Blvd S",
    "iso:country":"US",
    "sg:address":"1025 Washington Blvd S",
    "sg:city":"Laurel",
    "sg:classifiers":[
        {
            "category":"Banks & Credit Unions",
            "subcategory":"Bank",
            "type":"Services"
        }
    ],
    "sg:phone":"+1 301 725 3900",
    "sg:postcode":"20707",
    "sg:province":"MD",
    "sg:website":"www.citizensnatbank.com",
    "wof:name":"Citizens National Bank",
    "wof:placetype":"venue"
},
  "geometry": {"coordinates":[-76.85095800000001,39.097333],"type":"Point"}
}