{
  "type": "Feature",
  "properties": {
    "iso:country":"US",
    "sg:address":"347 N Calvert St",
    "sg:city":"Baltimore",
    "sg:classifiers":[
        {
            "category":"Restaurant",
            "type":"Food & Drink"
        }
    ],
    "sg:phone":"+1 410 244 1815",
    "sg:postcode":"21202",
    "sg:province":"MD",
    "wof:name":"Cuba Cafe",
    "wof:placetype":"venue"
},
  "geometry": {"coordinates":[-76.612584,39.293869],"type":"Point"}
}