{
  "type": "Feature",
  "properties": {
    "addr:full":"3262 Superior Ln Ste 268 Bowie MD 20715",
    "addr:housenumber":"3262",
    "addr:postcode":"20715",
    "addr:street":"Superior Ln Ste 268",
    "iso:country":"US",
    "sg:address":"3262 Superior Ln Ste 268",
    "sg:city":"Bowie",
    "sg:classifiers":[
        {
            "category":"Wholesale",
            "subcategory":"Office Equipment",
            "type":"Manufacturing & Wholesale Goods"
        },
        {
            "category":"Shopping",
            "subcategory":"Computers & Home Electronics",
            "type":"Retail Goods"
        }
    ],
    "sg:phone":"+1 301 262 5476",
    "sg:postcode":"20715",
    "sg:province":"MD",
    "sg:tags":[
        "scanning",
        "printer",
        "plotting",
        "supply"
    ],
    "wof:name":"Ameritech Office Systems",
    "wof:placetype":"venue"
},
  "geometry": {"coordinates":[-76.732612,38.977796],"type":"Point"}
}