{
  "type": "Feature",
  "properties": {
    "addr:full":"6107 Greenbelt Rd College Park MD 20740",
    "addr:housenumber":"6107",
    "addr:postcode":"20740",
    "addr:street":"Greenbelt Rd",
    "iso:country":"US",
    "sg:address":"6107 Greenbelt Rd",
    "sg:city":"College Park",
    "sg:classifiers":[
        {
            "category":"Banks & Credit Unions",
            "subcategory":"Bank",
            "type":"Services"
        }
    ],
    "sg:phone":"+1 301 345 2424",
    "sg:postcode":"20740",
    "sg:province":"MD",
    "sg:tags":[
        "federal",
        "savings",
        "institution"
    ],
    "wof:name":"Chevy Chase Bank",
    "wof:placetype":"venue"
},
  "geometry": {"coordinates":[-76.90723300000001,38.996997],"type":"Point"}
}