{
  "type": "Feature",
  "properties": {
    "addr:full":"4256 N Point Rd Dundalk MD 21222",
    "addr:housenumber":"4256",
    "addr:postcode":"21222",
    "addr:street":"N Point Rd",
    "iso:country":"US",
    "sg:address":"4256 N Point Rd",
    "sg:city":"Dundalk",
    "sg:classifiers":[
        {
            "category":"Freight",
            "type":"Transportation"
        }
    ],
    "sg:phone":"+1 410 477 9882",
    "sg:postcode":"21222",
    "sg:province":"MD",
    "sg:tags":[
        "trucking"
    ],
    "wof:name":"Nu Joy Inc",
    "wof:placetype":"venue"
},
  "geometry": {"coordinates":[-76.462452,39.260396],"type":"Point"}
}