{
  "type": "Feature",
  "properties": {
    "iso:country":"US",
    "sg:address":"130 Love Point Rd",
    "sg:city":"Stevensville",
    "sg:classifiers":[
        {
            "category":"Retail",
            "subcategory":"Portrait Studio",
            "type":"Services"
        }
    ],
    "sg:phone":"+1 410 643 5420",
    "sg:postcode":"21666",
    "sg:province":"MD",
    "sg:tags":[
        "photographer"
    ],
    "wof:name":"Creative Images By",
    "wof:placetype":"venue"
},
  "geometry": {"coordinates":[-76.31922,38.979225],"type":"Point"}
}