{
  "type": "Feature",
  "properties": {
    "iso:country":"US",
    "sg:address":"1020 Devere Dr",
    "sg:city":"Silver Spring",
    "sg:classifiers":[
        {
            "category":"Banks & Credit Unions",
            "subcategory":"Investment Brokerage",
            "type":"Services"
        }
    ],
    "sg:phone":"+1 301 439 5393",
    "sg:postcode":"20903",
    "sg:province":"MD",
    "sg:tags":[
        "advisory"
    ],
    "wof:name":"Great Falls Asset Managers",
    "wof:placetype":"venue"
},
  "geometry": {"coordinates":[-76.9879,39.021824],"type":"Point"}
}