{
  "type": "Feature",
  "properties": {
    "iso:country":"US",
    "sg:address":"318 Franklin St",
    "sg:city":"Bel Air",
    "sg:classifiers":[
        {
            "category":"Retail",
            "subcategory":"Auto Repair",
            "type":"Services"
        }
    ],
    "sg:phone":"+1 410 879 7004",
    "sg:postcode":"21014",
    "sg:province":"MD",
    "sg:tags":[
        "automobile",
        "customizing"
    ],
    "wof:name":"Auto Accents",
    "wof:placetype":"venue"
},
  "geometry": {"coordinates":[-76.35291100000001,39.541708],"type":"Point"}
}