{
  "type": "Feature",
  "properties": {
    "addr:full":"2784 Old Washington Rd Waldorf MD 20601",
    "addr:housenumber":"2784",
    "addr:postcode":"20601",
    "addr:street":"Old Washington Rd",
    "iso:country":"US",
    "sg:address":"2784 Old Washington Rd",
    "sg:city":"Waldorf",
    "sg:classifiers":[
        {
            "category":"Personal",
            "subcategory":"Tanning Parlor",
            "type":"Services"
        }
    ],
    "sg:phone":"+1 301 632 6773",
    "sg:postcode":"20601",
    "sg:province":"MD",
    "sg:tags":[
        "salon"
    ],
    "wof:name":"Gold Tanning",
    "wof:placetype":"venue"
},
  "geometry": {"coordinates":[-76.89964999999999,38.633246],"type":"Point"}
}