{
  "type": "Feature",
  "properties": {
    "iso:country":"US",
    "sg:address":"21108 Mount Aetna Rd",
    "sg:city":"Hagerstown",
    "sg:classifiers":[
        {
            "category":"Organizations",
            "subcategory":"Non-profit Organization",
            "type":"Services"
        }
    ],
    "sg:phone":"+1 301 745 6226",
    "sg:postcode":"21742",
    "sg:province":"MD",
    "wof:name":"Present Truth Ministries Inc",
    "wof:placetype":"venue"
},
  "geometry": {"coordinates":[-77.636244,39.608608],"type":"Point"}
}