{
  "type": "Feature",
  "properties": {
    "addr:full":"222 Main St Annapolis MD 21401",
    "addr:housenumber":"222",
    "addr:postcode":"21401",
    "addr:street":"Main St",
    "iso:country":"US",
    "sg:address":"222 Main St",
    "sg:city":"Annapolis",
    "sg:classifiers":[
        {
            "category":"Professional",
            "subcategory":"Engineering",
            "type":"Services"
        }
    ],
    "sg:phone":"+1 410 280 0228",
    "sg:postcode":"21401",
    "sg:province":"MD",
    "sg:tags":[
        "engineer"
    ],
    "sg:website":"www.formasic.com",
    "wof:name":"Formal Asics LTD",
    "wof:placetype":"venue"
},
  "geometry": {"coordinates":[-76.491511,38.978189],"type":"Point"}
}