{
  "type": "Feature",
  "properties": {
    "addr:full":"616 W Baker Ave Abingdon MD 21009",
    "addr:housenumber":"616",
    "addr:postcode":"21009",
    "addr:street":"W Baker Ave",
    "iso:country":"US",
    "sg:address":"616 W Baker Ave",
    "sg:city":"Abingdon",
    "sg:classifiers":[
        {
            "category":"Autos & Motor Vehicles",
            "subcategory":"Automobile Sales",
            "type":"Retail Goods"
        }
    ],
    "sg:phone":"+1 410 676 3131",
    "sg:postcode":"21009",
    "sg:province":"MD",
    "sg:tags":[
        "car",
        "dealer"
    ],
    "wof:name":"Tom Amrein Automobiles WHOL",
    "wof:placetype":"venue"
},
  "geometry": {"coordinates":[-76.25223099999999,39.451372],"type":"Point"}
}