{
  "type": "Feature",
  "properties": {
    "iso:country":"US",
    "sg:address":"602 Cherry Hill Rd",
    "sg:city":"Brooklyn",
    "sg:classifiers":[
        {
            "category":"Personal",
            "subcategory":"Nail Salon",
            "type":"Services"
        }
    ],
    "sg:phone":"+1 410 350 0490",
    "sg:postcode":"21225",
    "sg:province":"MD",
    "wof:name":"V I P Nails",
    "wof:placetype":"venue"
},
  "geometry": {"coordinates":[-76.622051,39.250367],"type":"Point"}
}