{
  "type": "Feature",
  "properties": {
    "addr:full":"2008 Maryland Hwy Mountain Lake Pk MD 21550",
    "addr:housenumber":"2008",
    "addr:postcode":"21550",
    "addr:street":"Maryland Hwy",
    "iso:country":"US",
    "sg:address":"2008 Maryland Hwy",
    "sg:city":"Mountain Lake Pk",
    "sg:classifiers":[
        {
            "category":"Government",
            "subcategory":"Office",
            "type":"Public Place"
        }
    ],
    "sg:phone":"+1 301 334 6916",
    "sg:postcode":"21550",
    "sg:province":"MD",
    "wof:name":"State Office",
    "wof:placetype":"venue"
},
  "geometry": {"coordinates":[-79.362686,39.401978],"type":"Point"}
}