{
  "type": "Feature",
  "properties": {
    "iso:country":"US",
    "sg:address":"560 Lees Mill Rd",
    "sg:city":"Hampstead",
    "sg:classifiers":[
        {
            "category":"Banks & Credit Unions",
            "subcategory":"Investment Brokerage",
            "type":"Services"
        }
    ],
    "sg:phone":"+1 410 239 1133",
    "sg:postcode":"21074",
    "sg:province":"MD",
    "sg:tags":[
        "advisory",
        "financial"
    ],
    "wof:name":"Mason Dixon Financial LLC",
    "wof:placetype":"venue"
},
  "geometry": {"coordinates":[-76.865292,39.556917],"type":"Point"}
}