{
  "type": "Feature",
  "properties": {
    "addr:full":"10716 Powell Rd Thurmont MD 21788",
    "addr:housenumber":"10716",
    "addr:postcode":"21788",
    "addr:street":"Powell Rd",
    "iso:country":"US",
    "sg:address":"10716 Powell Rd",
    "sg:city":"Thurmont",
    "sg:classifiers":[
        {
            "category":"Shopping",
            "subcategory":"Hobbies, Toys, & Games",
            "type":"Retail Goods"
        }
    ],
    "sg:phone":"+1 301 898 8966",
    "sg:postcode":"21788",
    "sg:province":"MD",
    "wof:name":"Collection Connectin",
    "wof:placetype":"venue"
},
  "geometry": {"coordinates":[-77.433271,39.521737],"type":"Point"}
}