{
  "type": "Feature",
  "properties": {
    "addr:full":"1568 Clifton Ave Baltimore MD 21217",
    "addr:housenumber":"1568",
    "addr:postcode":"21217",
    "addr:street":"Clifton Ave",
    "iso:country":"US",
    "sg:address":"1568 Clifton Ave",
    "sg:city":"Baltimore",
    "sg:classifiers":[
        {
            "category":"Building & Trades",
            "subcategory":"Construction",
            "type":"Services"
        }
    ],
    "sg:phone":"+1 410 728 8350",
    "sg:postcode":"21217",
    "sg:province":"MD",
    "sg:tags":[
        "general",
        "contractor"
    ],
    "wof:name":"Allender Contracting Co",
    "wof:placetype":"venue"
},
  "geometry": {"coordinates":[-76.645156,39.31285],"type":"Point"}
}