{
  "type": "Feature",
  "properties": {
    "iso:country":"US",
    "sg:address":"1190 W Northern Pkwy",
    "sg:city":"Baltimore",
    "sg:classifiers":[
        {
            "category":"Professional",
            "type":"Services"
        }
    ],
    "sg:phone":"+1 410 464 6161",
    "sg:postcode":"21210",
    "sg:province":"MD",
    "sg:tags":[
        "establishment"
    ],
    "wof:name":"Politicom",
    "wof:placetype":"venue"
},
  "geometry": {"coordinates":[-76.64619,39.361551],"type":"Point"}
}