{
  "type": "Feature",
  "properties": {
    "iso:country":"US",
    "sg:address":"115 W Washington St",
    "sg:city":"Hagerstown",
    "sg:classifiers":[
        {
            "category":"Banks & Credit Unions",
            "subcategory":"Bank",
            "type":"Services"
        }
    ],
    "sg:phone":"+1 301 714 2061",
    "sg:postcode":"21740",
    "sg:province":"MD",
    "sg:tags":[
        "loan",
        "real estate"
    ],
    "wof:name":"Allied Mortgage Group Inc",
    "wof:placetype":"venue"
},
  "geometry": {"coordinates":[-77.724164,39.643764],"type":"Point"}
}