{
  "type": "Feature",
  "properties": {
    "iso:country":"US",
    "sg:address":"244 Main St",
    "sg:city":"Gaithersburg",
    "sg:classifiers":[
        {
            "category":"Personal",
            "subcategory":"Beauty Salon",
            "type":"Services"
        }
    ],
    "sg:phone":"+1 301 355 6609",
    "sg:postcode":"20878",
    "sg:province":"MD",
    "sg:tags":[
        "hair",
        "stylist"
    ],
    "wof:name":"J E M Beauty Salon",
    "wof:placetype":"venue"
},
  "geometry": {"coordinates":[-77.23854900000001,39.12297],"type":"Point"}
}