{
  "type": "Feature",
  "properties": {
    "addr:full":"8041 Snouffer School Rd Gaithersburg MD 20879",
    "addr:housenumber":"8041",
    "addr:postcode":"20879",
    "addr:street":"Snouffer School Rd",
    "iso:country":"US",
    "sg:address":"8041 Snouffer School Rd",
    "sg:city":"Gaithersburg",
    "sg:classifiers":[
        {
            "category":"Autos & Motor Vehicles",
            "subcategory":"Auto Supplies",
            "type":"Retail Goods"
        }
    ],
    "sg:phone":"+1 301 926 6736",
    "sg:postcode":"20879",
    "sg:province":"MD",
    "sg:tags":[
        "wheel",
        "tire"
    ],
    "wof:name":"Paul's Used Tires & Rims",
    "wof:placetype":"venue"
},
  "geometry": {"coordinates":[-77.16198199999999,39.160236],"type":"Point"}
}