{
  "type": "Feature",
  "properties": {
    "addr:full":"134 Main St Prince Frederick MD 20678",
    "addr:housenumber":"134",
    "addr:postcode":"20678",
    "addr:street":"Main St",
    "iso:country":"US",
    "sg:address":"134 Main St",
    "sg:city":"Prince Frederick",
    "sg:classifiers":[
        {
            "category":"Professional",
            "subcategory":"Accounting & Tax Preparation",
            "type":"Services"
        }
    ],
    "sg:phone":"+1 410 535 4930",
    "sg:postcode":"20678",
    "sg:province":"MD",
    "sg:tags":[
        "accountant"
    ],
    "wof:name":"Harrison & Co",
    "wof:placetype":"venue"
},
  "geometry": {"coordinates":[-76.584315,38.539952],"type":"Point"}
}