{
  "type": "Feature",
  "properties": {
    "addr:full":"11840 Walnut Point Rd Hagerstown MD 21740",
    "addr:housenumber":"11840",
    "addr:postcode":"21740",
    "addr:street":"Walnut Point Rd",
    "iso:country":"US",
    "sg:address":"11840 Walnut Point Rd",
    "sg:city":"Hagerstown",
    "sg:classifiers":[
        {
            "category":"Autos & Motor Vehicles",
            "subcategory":"Auto Supplies",
            "type":"Retail Goods"
        }
    ],
    "sg:phone":"+1 301 223 8525",
    "sg:postcode":"21740",
    "sg:province":"MD",
    "sg:tags":[
        "automobile",
        "part",
        "tire"
    ],
    "wof:name":"Hagerstown Tire Service",
    "wof:placetype":"venue"
},
  "geometry": {"coordinates":[-77.822091,39.63632],"type":"Point"}
}