{
  "type": "Feature",
  "properties": {
    "addr:full":"1085 Cedar Ridge Ct Annapolis MD 21403",
    "addr:housenumber":"1085",
    "addr:postcode":"21403",
    "addr:street":"Cedar Ridge Ct",
    "iso:country":"US",
    "sg:address":"1085 Cedar Ridge Ct",
    "sg:city":"Annapolis",
    "sg:classifiers":[
        {
            "category":"Wholesale",
            "subcategory":"Sporting Goods",
            "type":"Manufacturing & Wholesale Goods"
        }
    ],
    "sg:phone":"+1 410 349 3013",
    "sg:postcode":"21403",
    "sg:province":"MD",
    "sg:tags":[
        "hose",
        "inflatable",
        "sail",
        "rope",
        "boat",
        "belt"
    ],
    "wof:name":"Voyager U S A Inc",
    "wof:placetype":"venue"
},
  "geometry": {"coordinates":[-76.495627,38.959225],"type":"Point"}
}