{
  "type": "Feature",
  "properties": {
    "addr:full":"750 W Lexington St Baltimore MD 21201",
    "addr:housenumber":"750",
    "addr:postcode":"21201",
    "addr:street":"W Lexington St",
    "iso:country":"US",
    "sg:address":"750 W Lexington St",
    "sg:city":"Baltimore",
    "sg:classifiers":[
        {
            "category":"Professional",
            "subcategory":"Computer Services",
            "type":"Services"
        }
    ],
    "sg:phone":"+1 443 844 1557",
    "sg:postcode":"21201",
    "sg:province":"MD",
    "sg:tags":[
        "repair",
        "equipment-service"
    ],
    "wof:name":"Installations R Us Company",
    "wof:placetype":"venue"
},
  "geometry": {"coordinates":[-76.62905600000001,39.291163],"type":"Point"}
}