{
  "type": "Feature",
  "properties": {
    "addr:full":"2800 52nd Ave Hyattsville MD 20781",
    "addr:housenumber":"2800",
    "addr:postcode":"20781",
    "addr:street":"52Nd Ave",
    "iso:country":"US",
    "sg:address":"2800 52nd Ave",
    "sg:city":"Hyattsville",
    "sg:classifiers":[
        {
            "category":"Home & Garden",
            "subcategory":"Building Materials",
            "type":"Retail Goods"
        },
        {
            "category":"Building & Trades",
            "subcategory":"Construction",
            "type":"Services"
        }
    ],
    "sg:phone":"+1 301 779 2690",
    "sg:postcode":"20781",
    "sg:province":"MD",
    "sg:tags":[
        "concrete-stamped",
        "concrete",
        "shape",
        "decorative",
        "block"
    ],
    "wof:name":"Merit Concrete Inc",
    "wof:placetype":"venue"
},
  "geometry": {"coordinates":[-76.93108100000001,38.92481],"type":"Point"}
}