{
  "type": "Feature",
  "properties": {
    "iso:country":"US",
    "sg:address":"245 Hammarlee Rd",
    "sg:city":"Glen Burnie",
    "sg:classifiers":[
        {
            "category":"Shopping",
            "subcategory":"Computers & Home Electronics",
            "type":"Retail Goods"
        }
    ],
    "sg:phone":"+1 410 787 9200",
    "sg:postcode":"21060",
    "sg:province":"MD",
    "sg:tags":[
        "software"
    ],
    "sg:website":"www.eccnet.com",
    "wof:name":"ECC",
    "wof:placetype":"venue"
},
  "geometry": {"coordinates":[-76.602325,39.177899],"type":"Point"}
}