{
  "type": "Feature",
  "properties": {
    "addr:full":"200 Cedar St Cambridge MD 21613",
    "addr:housenumber":"200",
    "addr:postcode":"21613",
    "addr:street":"Cedar St",
    "iso:country":"US",
    "sg:address":"200 Cedar St",
    "sg:city":"Cambridge",
    "sg:classifiers":[
        {
            "category":"Building & Trades",
            "subcategory":"Construction",
            "type":"Services"
        }
    ],
    "sg:phone":"+1 410 901 8383",
    "sg:postcode":"21613",
    "sg:province":"MD",
    "sg:tags":[
        "contractor"
    ],
    "wof:name":"Whiting-Turner Contracting Co",
    "wof:placetype":"venue"
},
  "geometry": {"coordinates":[-76.073516,38.565097],"type":"Point"}
}