{
  "type": "Feature",
  "properties": {
    "iso:country":"US",
    "sg:address":"101 Amberleigh Dr",
    "sg:city":"Silver Spring",
    "sg:classifiers":[
        {
            "category":"Professional",
            "subcategory":"Management & Consulting",
            "type":"Services"
        }
    ],
    "sg:phone":"+1 301 388 2444",
    "sg:postcode":"20905",
    "sg:province":"MD",
    "sg:tags":[
        "consultant"
    ],
    "wof:name":"Dp Consulting LLC",
    "wof:placetype":"venue"
},
  "geometry": {"coordinates":[-77.002136,39.090469],"type":"Point"}
}