{
  "type": "Feature",
  "properties": {
    "addr:full":"5469 Enberend Ter Columbia MD 21045",
    "addr:housenumber":"5469",
    "addr:postcode":"21045",
    "addr:street":"Enberend Ter",
    "iso:country":"US",
    "sg:address":"5469 Enberend Ter",
    "sg:city":"Columbia",
    "sg:classifiers":[
        {
            "category":"Professional",
            "subcategory":"Management & Consulting",
            "type":"Services"
        }
    ],
    "sg:phone":"+1 410 740 0045",
    "sg:postcode":"21045",
    "sg:province":"MD",
    "sg:tags":[
        "consultant",
        "business"
    ],
    "wof:name":"Monterey Apartments",
    "wof:placetype":"venue"
},
  "geometry": {"coordinates":[-76.822337,39.22285],"type":"Point"}
}