{
  "type": "Feature",
  "properties": {
    "addr:full":"3109 Bunker Dr Ellicott City MD 21042",
    "addr:housenumber":"3109",
    "addr:postcode":"21042",
    "addr:street":"Bunker Dr",
    "iso:country":"US",
    "sg:address":"3109 Bunker Dr",
    "sg:city":"Ellicott City",
    "sg:classifiers":[
        {
            "category":"Insurance",
            "subcategory":"Insurance Agent",
            "type":"Services"
        }
    ],
    "sg:phone":"+1 410 750 9604",
    "sg:postcode":"21042",
    "sg:province":"MD",
    "wof:name":"Met Life",
    "wof:placetype":"venue"
},
  "geometry": {"coordinates":[-76.86751599999999,39.28452],"type":"Point"}
}