{
  "type": "Feature",
  "properties": {
    "iso:country":"US",
    "sg:address":"2 Crain Hwy",
    "sg:city":"Upper Marlboro",
    "sg:classifiers":[
        {
            "category":"Wholesale",
            "subcategory":"Construction Materials",
            "type":"Manufacturing & Wholesale Goods"
        }
    ],
    "sg:phone":"+1 301 249 5100",
    "sg:postcode":"20774",
    "sg:province":"MD",
    "sg:tags":[
        "lumber"
    ],
    "sg:website":"www.gefrisco.com",
    "wof:name":"G E Frisco & Co",
    "wof:placetype":"venue"
},
  "geometry": {"coordinates":[-76.71842599999999,38.896834],"type":"Point"}
}