{
  "type": "Feature",
  "properties": {
    "iso:country":"US",
    "sg:address":"5007 Linganore Cir",
    "sg:city":"Monrovia",
    "sg:classifiers":[
        {
            "category":"Manufacturing",
            "subcategory":"Electronics",
            "type":"Manufacturing & Wholesale Goods"
        }
    ],
    "sg:phone":"+1 301 865 3154",
    "sg:postcode":"21770",
    "sg:province":"MD",
    "sg:tags":[
        "mfg",
        "boards",
        "circuit",
        "printed"
    ],
    "wof:name":"Robert Gallo",
    "wof:placetype":"venue"
},
  "geometry": {"coordinates":[-77.232792,39.372954],"type":"Point"}
}