{
  "type": "Feature",
  "properties": {
    "iso:country":"US",
    "sg:address":"11500 Baltimore Ave",
    "sg:city":"Beltsville",
    "sg:classifiers":[
        {
            "category":"Restaurant",
            "type":"Food & Drink"
        }
    ],
    "sg:phone":"+1 301 937 6809",
    "sg:postcode":"20705",
    "sg:province":"MD",
    "wof:name":"Remington's",
    "wof:placetype":"venue"
},
  "geometry": {"coordinates":[-76.903603,39.0424],"type":"Point"}
}