{
  "type": "Feature",
  "properties": {
    "addr:full":"10504 Scaggsville Rd Laurel MD 20723",
    "addr:housenumber":"10504",
    "addr:postcode":"20723",
    "addr:street":"Scaggsville Rd",
    "iso:country":"US",
    "sg:address":"10504 Scaggsville Rd",
    "sg:city":"Laurel",
    "sg:classifiers":[
        {
            "category":"Wholesale",
            "subcategory":"Machinery & Supplies",
            "type":"Manufacturing & Wholesale Goods"
        }
    ],
    "sg:phone":"+1 301 725 4264",
    "sg:postcode":"20723",
    "sg:province":"MD",
    "sg:tags":[
        "machine",
        "knitting"
    ],
    "wof:name":"Frans Knitting Boutique",
    "wof:placetype":"venue"
},
  "geometry": {"coordinates":[-76.877379,39.135749],"type":"Point"}
}