{
  "type": "Feature",
  "properties": {
    "addr:full":"6395 Dobbin Rd Columbia MD 21045",
    "addr:housenumber":"6395",
    "addr:postcode":"21045",
    "addr:street":"Dobbin Rd",
    "iso:country":"US",
    "sg:address":"6395 Dobbin Rd",
    "sg:city":"Columbia",
    "sg:classifiers":[
        {
            "category":"Real Estate",
            "subcategory":"Real Estate Agent",
            "type":"Services"
        }
    ],
    "sg:phone":"+1 410 772 0410",
    "sg:postcode":"21045",
    "sg:province":"MD",
    "sg:tags":[
        "desk",
        "space"
    ],
    "wof:name":"Continental Wingate Capital",
    "wof:placetype":"venue"
},
  "geometry": {"coordinates":[-76.818319,39.198516],"type":"Point"}
}