{
  "type": "Feature",
  "properties": {
    "iso:country":"US",
    "sg:address":"1524 S Salisbury Blvd",
    "sg:city":"Salisbury",
    "sg:classifiers":[
        {
            "category":"Sports & Exercise",
            "subcategory":"Bowling",
            "type":"Entertainment"
        }
    ],
    "sg:phone":"+1 410 742 3030",
    "sg:postcode":"21801",
    "sg:province":"MD",
    "sg:tags":[
        "center"
    ],
    "wof:name":"Cherokee Bowling Lanes",
    "wof:placetype":"venue"
},
  "geometry": {"coordinates":[-75.610129,38.334384],"type":"Point"}
}