{
  "type": "Feature",
  "properties": {
    "addr:full":"8994 Yellow Brick Rd Essex MD 21237",
    "addr:housenumber":"8994",
    "addr:postcode":"21237",
    "addr:street":"Yellow Brick Rd",
    "iso:country":"US",
    "sg:address":"8994 Yellow Brick Rd",
    "sg:city":"Essex",
    "sg:classifiers":[
        {
            "category":"Home & Garden",
            "subcategory":"Carpets & Floor Coverings",
            "type":"Retail Goods"
        }
    ],
    "sg:phone":"+1 410 391 3382",
    "sg:postcode":"21237",
    "sg:province":"MD",
    "sg:tags":[
        "dealer",
        "rug"
    ],
    "wof:name":"Premier Flooring Installation",
    "wof:placetype":"venue"
},
  "geometry": {"coordinates":[-76.47667,39.341721],"type":"Point"}
}