{
  "type": "Feature",
  "properties": {
    "iso:country":"US",
    "sg:address":"4 North Ave",
    "sg:city":"Bel Air",
    "sg:classifiers":[
        {
            "category":"Health Services",
            "subcategory":"Doctor",
            "type":"Services"
        }
    ],
    "sg:phone":"+1 410 638 0883",
    "sg:postcode":"21014",
    "sg:province":"MD",
    "sg:tags":[
        "physician",
        "surgeon"
    ],
    "wof:name":"Adam T Faill MD",
    "wof:placetype":"venue"
},
  "geometry": {"coordinates":[-76.36294100000001,39.551486],"type":"Point"}
}