{
  "type": "Feature",
  "properties": {
    "addr:full":"3910 Dot Ln Huntingtown MD 20639",
    "addr:housenumber":"3910",
    "addr:postcode":"20639",
    "addr:street":"Dot Ln",
    "iso:country":"US",
    "sg:address":"3910 Dot Ln",
    "sg:city":"Huntingtown",
    "sg:classifiers":[
        {
            "category":"Social Services",
            "subcategory":"Child Care",
            "type":"Services"
        }
    ],
    "sg:phone":"+1 410 257 2876",
    "sg:postcode":"20639",
    "sg:province":"MD",
    "wof:name":"Cindy's Little Stars Day Care",
    "wof:placetype":"venue"
},
  "geometry": {"coordinates":[-76.556917,38.625489],"type":"Point"}
}