{
  "type": "Feature",
  "properties": {
    "iso:country":"US",
    "sg:address":"1525 Presstman St",
    "sg:city":"Baltimore",
    "sg:classifiers":[
        {
            "category":"Organizations",
            "subcategory":"Religious Organization",
            "type":"Services"
        }
    ],
    "sg:phone":"+1 410 728 1772",
    "sg:postcode":"21217",
    "sg:province":"MD",
    "sg:tags":[
        "church"
    ],
    "wof:name":"New Song Urban Ministry Inc",
    "wof:placetype":"venue"
},
  "geometry": {"coordinates":[-76.642595,39.305273],"type":"Point"}
}