{
  "type": "Feature",
  "properties": {
    "iso:country":"US",
    "sg:address":"12800 Old Fort Rd",
    "sg:city":"Fort Washington",
    "sg:classifiers":[
        {
            "category":"Autos & Motor Vehicles",
            "subcategory":"Fuel & Gas Station",
            "type":"Retail Goods"
        }
    ],
    "sg:phone":"+1 301 292 9707",
    "sg:postcode":"20744",
    "sg:province":"MD",
    "sg:tags":[
        "oil"
    ],
    "wof:name":"Fort Washington Exxon",
    "wof:placetype":"venue"
},
  "geometry": {"coordinates":[-76.98790099999999,38.713114],"type":"Point"}
}