{
  "type": "Feature",
  "properties": {
    "iso:country":"US",
    "sg:address":"3649 Falls Rd",
    "sg:city":"Baltimore",
    "sg:classifiers":[
        {
            "category":"Airline",
            "type":"Transportation"
        },
        {
            "category":"Travel",
            "subcategory":"Travel Agent",
            "type":"Entertainment"
        }
    ],
    "sg:phone":"+1 410 467 2600",
    "sg:postcode":"21211",
    "sg:province":"MD",
    "sg:tags":[
        "ticket",
        "agency",
        "services-commercial"
    ],
    "sg:website":"http://www.mdschooloftravel.com",
    "wof:name":"Falls Road Travel",
    "wof:placetype":"venue"
},
  "geometry": {"coordinates":[-76.635165,39.331748],"type":"Point"}
}