{
  "type": "Feature",
  "properties": {
    "iso:country":"US",
    "sg:address":"107 W Baltimore St",
    "sg:city":"Taneytown",
    "sg:classifiers":[
        {
            "category":"Retail",
            "subcategory":"Auto Repair",
            "type":"Services"
        }
    ],
    "sg:phone":"+1 410 756 6608",
    "sg:postcode":"21787",
    "sg:province":"MD",
    "sg:tags":[
        "repairing",
        "automobile"
    ],
    "wof:name":"Inman's Service Ctr",
    "wof:placetype":"venue"
},
  "geometry": {"coordinates":[-77.18009600000001,39.663037],"type":"Point"}
}