{
  "type": "Feature",
  "properties": {
    "addr:full":"550 Crain Hwy N Glen Burnie MD 21061",
    "addr:housenumber":"550",
    "addr:postcode":"21061",
    "addr:street":"Crain Hwy N",
    "iso:country":"US",
    "sg:address":"550 Crain Hwy N",
    "sg:city":"Glen Burnie",
    "sg:classifiers":[
        {
            "category":"Food & Beverages",
            "subcategory":"Meat & Fish",
            "type":"Retail Goods"
        }
    ],
    "sg:phone":"+1 410 760 3100",
    "sg:postcode":"21061",
    "sg:province":"MD",
    "sg:tags":[
        "seafood"
    ],
    "wof:name":"R & K Lake Trout",
    "wof:placetype":"venue"
},
  "geometry": {"coordinates":[-76.619062,39.174567],"type":"Point"}
}