{
  "type": "Feature",
  "properties": {
    "addr:full":"11515 Bennington Dr Upper Marlboro MD 20774",
    "addr:housenumber":"11515",
    "addr:postcode":"20774",
    "addr:street":"Bennington Dr",
    "iso:country":"US",
    "sg:address":"11515 Bennington Dr",
    "sg:city":"Upper Marlboro",
    "sg:classifiers":[
        {
            "category":"Recreation",
            "type":"Entertainment"
        }
    ],
    "sg:phone":"+1 301 336 2827",
    "sg:postcode":"20774",
    "sg:province":"MD",
    "wof:name":"Janet Polite-Penn",
    "wof:placetype":"venue"
},
  "geometry": {"coordinates":[-76.805677,38.885544],"type":"Point"}
}