{
  "type": "Feature",
  "properties": {
    "iso:country":"US",
    "sg:address":"11004 Herrington Ct",
    "sg:city":"Upper Marlboro",
    "sg:classifiers":[
        {
            "category":"Freight",
            "type":"Transportation"
        }
    ],
    "sg:phone":"+1 301 499 4720",
    "sg:postcode":"20774",
    "sg:province":"MD",
    "sg:tags":[
        "sand",
        "gravel",
        "transporting",
        "dirt",
        "rock"
    ],
    "wof:name":"L R Waller and Sons Inc",
    "wof:placetype":"venue"
},
  "geometry": {"coordinates":[-76.813714,38.888631],"type":"Point"}
}