{
  "type": "Feature",
  "properties": {
    "addr:full":"156 South St Annapolis MD 21401",
    "addr:housenumber":"156",
    "addr:postcode":"21401",
    "addr:street":"South St",
    "iso:country":"US",
    "sg:address":"156 South St",
    "sg:city":"Annapolis",
    "sg:classifiers":[
        {
            "category":"Professional",
            "subcategory":"Lawyer & Legal Services",
            "type":"Services"
        }
    ],
    "sg:phone":"+1 888 740 8943",
    "sg:postcode":"21401",
    "sg:province":"MD",
    "sg:tags":[
        "living",
        "attorney",
        "estate",
        "planning",
        "trust",
        "probate"
    ],
    "sg:website":"http://local.ingenio.com/Listings/Details.aspx?NUM=a%3a9482490%3a13%3a4859924%3a14%3a0%3a7",
    "wof:name":"David A Wanger Attorney",
    "wof:placetype":"venue"
},
  "geometry": {"coordinates":[-76.49272999999999,38.977142],"type":"Point"}
}