{
  "type": "Feature",
  "properties": {
    "iso:country":"US",
    "sg:address":"1902 Emmorton Rd",
    "sg:city":"Bel Air",
    "sg:classifiers":[
        {
            "category":"Autos & Motor Vehicles",
            "subcategory":"Fuel & Gas Station",
            "type":"Retail Goods"
        }
    ],
    "sg:phone":"+1 410 893 5617",
    "sg:postcode":"21015",
    "sg:province":"MD",
    "sg:tags":[
        "oil"
    ],
    "wof:name":"Emmorton Crown",
    "wof:placetype":"venue"
},
  "geometry": {"coordinates":[-76.327316,39.503566],"type":"Point"}
}