{
  "type": "Feature",
  "properties": {
    "iso:country":"US",
    "sg:address":"3349 WILKENS AVE STE 202",
    "sg:city":"Baltimore",
    "sg:classifiers":[
        {
            "category":"Community Center",
            "type":"Public Place"
        }
    ],
    "sg:phone":"+1 888 840 8688",
    "sg:postcode":"21229",
    "sg:province":"MD",
    "sg:tags":[
        "medical"
    ],
    "sg:website":"www.nonprofitstdtesting.org",
    "wof:name":"Baltimore HIV/STD Testing",
    "wof:placetype":"venue"
},
  "geometry": {"coordinates":[-76.673207,39.273237],"type":"Point"}
}