{
  "type": "Feature",
  "properties": {
    "addr:full":"2355 Carrollton Rd Westminster MD 21157",
    "addr:housenumber":"2355",
    "addr:postcode":"21157",
    "addr:street":"Carrollton Rd",
    "iso:country":"US",
    "sg:address":"2355 Carrollton Rd",
    "sg:city":"Westminster",
    "sg:phone":"+1 410 848 5941",
    "sg:postcode":"21157",
    "sg:province":"MD",
    "sg:tags":[
        "farm",
        "corn"
    ],
    "wof:name":"George Rill",
    "wof:placetype":"venue"
},
  "geometry": {"coordinates":[-76.910805,39.560657],"type":"Point"}
}