{
  "type": "Feature",
  "properties": {
    "iso:country":"US",
    "sg:address":"3534 Frederick Ave",
    "sg:city":"Baltimore",
    "sg:classifiers":[
        {
            "category":"Personal",
            "subcategory":"Beauty Salon",
            "type":"Services"
        }
    ],
    "sg:phone":"+1 410 945 0308",
    "sg:postcode":"21229",
    "sg:province":"MD",
    "wof:name":"Personal Touch Beauty Salon",
    "wof:placetype":"venue"
},
  "geometry": {"coordinates":[-76.67731,39.28178],"type":"Point"}
}