{
  "type": "Feature",
  "properties": {
    "addr:full":"10370 Whitewasher Way Columbia MD 21044",
    "addr:housenumber":"10370",
    "addr:postcode":"21044",
    "addr:street":"Whitewasher Way",
    "iso:country":"US",
    "sg:address":"10370 Whitewasher Way",
    "sg:city":"Columbia",
    "sg:classifiers":[
        {
            "category":"Professional",
            "subcategory":"Management & Consulting",
            "type":"Services"
        },
        {
            "category":"Professional",
            "subcategory":"Advertising",
            "type":"Services"
        }
    ],
    "sg:phone":"+1 410 715 8511",
    "sg:postcode":"21044",
    "sg:province":"MD",
    "sg:tags":[
        "marketing",
        "program",
        "consultant"
    ],
    "wof:name":"Manufacturing Support Group",
    "wof:placetype":"venue"
},
  "geometry": {"coordinates":[-76.872783,39.195124],"type":"Point"}
}