{
  "type": "Feature",
  "properties": {
    "addr:full":"2913 Odonnell St Baltimore MD 21224",
    "addr:housenumber":"2913",
    "addr:postcode":"21224",
    "addr:street":"Odonnell St",
    "iso:country":"US",
    "sg:address":"2913 Odonnell St",
    "sg:city":"Baltimore",
    "sg:classifiers":[
        {
            "category":"Professional",
            "subcategory":"Accounting & Tax Preparation",
            "type":"Services"
        }
    ],
    "sg:phone":"+1 410 675 2727",
    "sg:postcode":"21224",
    "sg:province":"MD",
    "sg:tags":[
        "accountant"
    ],
    "wof:name":"Klein T R Co CPA",
    "wof:placetype":"venue"
},
  "geometry": {"coordinates":[-76.574997,39.280201],"type":"Point"}
}