{
  "type": "Feature",
  "properties": {
    "addr:full":"5 Jonathans Ct Cockeysville MD 21030",
    "addr:housenumber":"5",
    "addr:postcode":"21030",
    "addr:street":"Jonathans Ct",
    "iso:country":"US",
    "sg:address":"5 Jonathans Ct",
    "sg:city":"Cockeysville",
    "sg:classifiers":[
        {
            "category":"Building & Trades",
            "subcategory":"Construction",
            "type":"Services"
        }
    ],
    "sg:phone":"+1 410 628 8080",
    "sg:postcode":"21030",
    "sg:province":"MD",
    "sg:tags":[
        "house"
    ],
    "wof:name":"Summerfield Homes",
    "wof:placetype":"venue"
},
  "geometry": {"coordinates":[-76.70691100000001,39.485245],"type":"Point"}
}