{
  "type": "Feature",
  "properties": {
    "addr:full":"4604 Eastern Ave Baltimore MD 21224",
    "addr:housenumber":"4604",
    "addr:postcode":"21224",
    "addr:street":"Eastern Ave",
    "iso:country":"US",
    "sg:address":"4604 Eastern Ave",
    "sg:city":"Baltimore",
    "sg:classifiers":[
        {
            "category":"Food & Beverages",
            "subcategory":"Groceries & Convenience Stores",
            "type":"Retail Goods"
        }
    ],
    "sg:phone":"+1 443 759 6637",
    "sg:postcode":"21224",
    "sg:province":"MD",
    "wof:name":"Market El Sol",
    "wof:placetype":"venue"
},
  "geometry": {"coordinates":[-76.55726,39.287147],"type":"Point"}
}