{
  "type": "Feature",
  "properties": {
    "addr:full":"108 Kenilworth Park Cir Baltimore MD 21204",
    "addr:housenumber":"108",
    "addr:postcode":"21204",
    "addr:street":"Kenilworth Park Cir",
    "iso:country":"US",
    "sg:address":"108 Kenilworth Park Cir",
    "sg:city":"Baltimore",
    "sg:classifiers":[
        {
            "category":"Professional",
            "subcategory":"Art Services",
            "type":"Services"
        }
    ],
    "sg:phone":"+1 410 583 9712",
    "sg:postcode":"21204",
    "sg:province":"MD",
    "sg:tags":[
        "graphic",
        "designer"
    ],
    "sg:website":"www.dot2design.com",
    "wof:name":"Dot 2 Design Inc",
    "wof:placetype":"venue"
},
  "geometry": {"coordinates":[-76.621595,39.411533],"type":"Point"}
}