{
  "type": "Feature",
  "properties": {
    "addr:full":"2224 E Fayette St Baltimore MD 21231",
    "addr:housenumber":"2224",
    "addr:postcode":"21231",
    "addr:street":"E Fayette St",
    "iso:country":"US",
    "sg:address":"2224 E Fayette St",
    "sg:city":"Baltimore",
    "sg:classifiers":[
        {
            "category":"Wholesale",
            "subcategory":"Machinery & Supplies",
            "type":"Manufacturing & Wholesale Goods"
        }
    ],
    "sg:phone":"+1 410 362 0050",
    "sg:postcode":"21231",
    "sg:province":"MD",
    "sg:tags":[
        "washing",
        "mach"
    ],
    "sg:website":"www.calleps.com",
    "wof:name":"Express Parts & Svc",
    "wof:placetype":"venue"
},
  "geometry": {"coordinates":[-76.584862,39.294318],"type":"Point"}
}