{
  "type": "Feature",
  "properties": {
    "addr:full":"2318 Allendale Rd Baltimore MD 21216",
    "addr:housenumber":"2318",
    "addr:postcode":"21216",
    "addr:street":"Allendale Rd",
    "iso:country":"US",
    "sg:address":"2318 Allendale Rd",
    "sg:city":"Baltimore",
    "sg:classifiers":[
        {
            "category":"Social Services",
            "type":"Services"
        },
        {
            "category":"Personal",
            "type":"Services"
        }
    ],
    "sg:phone":"+1 410 367 7452",
    "sg:postcode":"21216",
    "sg:province":"MD",
    "sg:tags":[
        "family",
        "counselors-licensed",
        "individual",
        "marriage",
        "child",
        "professional",
        "counselor"
    ],
    "wof:name":"Olson Jeannine Ma Ms Cpc",
    "wof:placetype":"venue"
},
  "geometry": {"coordinates":[-76.680182,39.314273],"type":"Point"}
}