{
  "type": "Feature",
  "properties": {
    "addr:full":"8 Music Fair Rd Owings Mills MD 21117",
    "addr:housenumber":"8",
    "addr:postcode":"21117",
    "addr:street":"Music Fair Rd",
    "iso:country":"US",
    "sg:address":"8 Music Fair Rd",
    "sg:city":"Owings Mills",
    "sg:classifiers":[
        {
            "category":"Manufacturing",
            "subcategory":"Furniture",
            "type":"Manufacturing & Wholesale Goods"
        }
    ],
    "sg:phone":"+1 410 654 9777",
    "sg:postcode":"21117",
    "sg:province":"MD",
    "sg:tags":[
        "fixture"
    ],
    "sg:website":"www.accentkitchenandbath.com",
    "wof:name":"Accent Kitchens & Baths",
    "wof:placetype":"venue"
},
  "geometry": {"coordinates":[-76.777111,39.412013],"type":"Point"}
}