{
  "type": "Feature",
  "properties": {
    "iso:country":"US",
    "sg:address":"1009 E Churchville Rd",
    "sg:city":"Bel Air",
    "sg:classifiers":[
        {
            "category":"Banks & Credit Unions",
            "subcategory":"Bank",
            "type":"Services"
        }
    ],
    "sg:phone":"+1 410 879 8701",
    "sg:postcode":"21014",
    "sg:province":"MD",
    "sg:tags":[
        "savings",
        "loan",
        "association"
    ],
    "wof:name":"Rosedale Federal S & L Assn",
    "wof:placetype":"venue"
},
  "geometry": {"coordinates":[-76.332337,39.540546],"type":"Point"}
}