{
  "type": "Feature",
  "properties": {
    "addr:full":"13635 Darnestown Rd Gaithersburg MD 20878",
    "addr:housenumber":"13635",
    "addr:postcode":"20878",
    "addr:street":"Darnestown Rd",
    "iso:country":"US",
    "sg:address":"13635 Darnestown Rd",
    "sg:city":"Gaithersburg",
    "sg:classifiers":[
        {
            "category":"Building & Trades",
            "subcategory":"Landscaping Services",
            "type":"Services"
        }
    ],
    "sg:phone":"+1 301 948 0093",
    "sg:postcode":"20878",
    "sg:province":"MD",
    "sg:tags":[
        "tree"
    ],
    "wof:name":"Gerald T Christner Tree Svc",
    "wof:placetype":"venue"
},
  "geometry": {"coordinates":[-77.28229399999999,39.107488],"type":"Point"}
}