{
  "type": "Feature",
  "properties": {
    "iso:country":"US",
    "sg:address":"7900 Avis Mill Rd",
    "sg:city":"Williamsport",
    "sg:classifiers":[
        {
            "category":"Restaurant",
            "type":"Food & Drink"
        }
    ],
    "sg:phone":"+1 301 223 9314",
    "sg:postcode":"21795",
    "sg:province":"MD",
    "sg:website":"http://www.mcmahonsmill.com",
    "wof:name":"Mc Mahon Mill",
    "wof:placetype":"venue"
},
  "geometry": {"coordinates":[-77.823593,39.530609],"type":"Point"}
}