{
  "type": "Feature",
  "properties": {
    "iso:country":"US",
    "sg:address":"1109 Spring St",
    "sg:city":"Silver Spring",
    "sg:classifiers":[
        {
            "category":"Professional",
            "subcategory":"Management & Consulting",
            "type":"Services"
        }
    ],
    "sg:phone":"+1 301 585 2424",
    "sg:postcode":"20910",
    "sg:province":"MD",
    "sg:tags":[
        "marketing",
        "consultant"
    ],
    "wof:name":"Skyhawk Logistics Inc",
    "wof:placetype":"venue"
},
  "geometry": {"coordinates":[-77.02903000000001,39.00021],"type":"Point"}
}