{
  "type": "Feature",
  "properties": {
    "iso:country":"US",
    "sg:address":"45970 Foxchase Dr",
    "sg:city":"Great Mills",
    "sg:classifiers":[
        {
            "category":"Real Estate",
            "subcategory":"Real Estate Operator",
            "type":"Services"
        }
    ],
    "sg:phone":"+1 301 863 8230",
    "sg:postcode":"20634",
    "sg:province":"MD",
    "sg:tags":[
        "apartment"
    ],
    "wof:name":"Foxchase Village",
    "wof:placetype":"venue"
},
  "geometry": {"coordinates":[-76.489403,38.257198],"type":"Point"}
}