{
  "type": "Feature",
  "properties": {
    "addr:full":"14912 Talking Rock Ct Gaithersburg MD 20878",
    "addr:postcode":"14912;20878",
    "addr:street":"Talking Rock Ct",
    "iso:country":"US",
    "sg:address":"14912 Talking Rock Ct",
    "sg:city":"Gaithersburg",
    "sg:classifiers":[
        {
            "category":"Professional",
            "subcategory":"Business Services",
            "type":"Services"
        }
    ],
    "sg:phone":"+1 301 340 2422",
    "sg:postcode":"20878",
    "sg:province":"MD",
    "wof:name":"Woodard Enterprises Inc",
    "wof:placetype":"venue"
},
  "geometry": {"coordinates":[-77.244501,39.100691],"type":"Point"}
}