{
  "type": "Feature",
  "properties": {
    "addr:full":"404 S Caton Ave Baltimore MD 21229",
    "addr:housenumber":"404",
    "addr:postcode":"21229",
    "addr:street":"S Caton Ave",
    "iso:country":"US",
    "sg:address":"404 S Caton Ave",
    "sg:city":"Baltimore",
    "sg:classifiers":[
        {
            "category":"Shopping",
            "type":"Retail Goods"
        }
    ],
    "sg:phone":"+1 410 242 4380",
    "sg:postcode":"21229",
    "sg:province":"MD",
    "sg:tags":[
        "ice"
    ],
    "sg:website":"www.capitolcarboniccorp.com",
    "wof:name":"Capitol Carbonic Corp",
    "wof:placetype":"venue"
},
  "geometry": {"coordinates":[-76.671694,39.278829],"type":"Point"}
}