{
  "type": "Feature",
  "properties": {
    "addr:full":"306 Franklin St Denton MD 21629",
    "addr:housenumber":"306",
    "addr:postcode":"21629",
    "addr:street":"Franklin St",
    "iso:country":"US",
    "sg:address":"306 Franklin St",
    "sg:city":"Denton",
    "sg:classifiers":[
        {
            "category":"Personal",
            "subcategory":"Beauty Salon",
            "type":"Services"
        }
    ],
    "sg:phone":"+1 410 479 1268",
    "sg:postcode":"21629",
    "sg:province":"MD",
    "wof:name":"Hair Fashion Unlimited",
    "wof:placetype":"venue"
},
  "geometry": {"coordinates":[-75.831975,38.885047],"type":"Point"}
}