{
  "type": "Feature",
  "properties": {
    "addr:full":"218 E Lexington St # 201 Baltimore MD 21202",
    "addr:housenumber":"218",
    "addr:postcode":"21202",
    "addr:street":"E Lexington St # 201",
    "iso:country":"US",
    "sg:address":"218 E Lexington St # 201",
    "sg:city":"Baltimore",
    "sg:classifiers":[
        {
            "category":"Professional",
            "subcategory":"Lawyer & Legal Services",
            "type":"Services"
        }
    ],
    "sg:phone":"+1 410 685 5672",
    "sg:postcode":"21202",
    "sg:province":"MD",
    "sg:tags":[
        "plan"
    ],
    "wof:name":"The Law Office Of Linda L Shields Attorney",
    "wof:placetype":"venue"
},
  "geometry": {"coordinates":[-76.61182599999999,39.291207],"type":"Point"}
}