{
  "type": "Feature",
  "properties": {
    "iso:country":"US",
    "sg:address":"2029 Sue Ave",
    "sg:city":"Baltimore",
    "sg:classifiers":[
        {
            "category":"Shopping",
            "subcategory":"Florist",
            "type":"Retail Goods"
        }
    ],
    "sg:phone":"+1 410 391 2777",
    "sg:postcode":"21221",
    "sg:province":"MD",
    "wof:name":"About Flowers Inc",
    "wof:placetype":"venue"
},
  "geometry": {"coordinates":[-76.414096,39.292286],"type":"Point"}
}