{
  "type": "Feature",
  "properties": {
    "addr:full":"5332 Bryantown Rd Waldorf MD 20601",
    "addr:postcode":"5332;20601",
    "addr:street":"Bryantown Rd",
    "iso:country":"US",
    "sg:address":"5332 Bryantown Rd",
    "sg:city":"Waldorf",
    "sg:classifiers":[
        {
            "category":"Professional",
            "subcategory":"Computer Services",
            "type":"Services"
        }
    ],
    "sg:phone":"+1 301 399 9487",
    "sg:postcode":"20601",
    "sg:province":"MD",
    "sg:tags":[
        "technical",
        "assistance",
        "support"
    ],
    "wof:name":"Truitt Solutions",
    "wof:placetype":"venue"
},
  "geometry": {"coordinates":[-76.83968299999999,38.566573],"type":"Point"}
}