{
  "type": "Feature",
  "properties": {
    "addr:full":"6801 Eastern Ave Baltimore MD 21224",
    "addr:housenumber":"6801",
    "addr:postcode":"21224",
    "addr:street":"Eastern Ave",
    "iso:country":"US",
    "sg:address":"6801 Eastern Ave",
    "sg:city":"Baltimore",
    "sg:classifiers":[
        {
            "category":"Professional",
            "type":"Services"
        }
    ],
    "sg:phone":"+1 443 524 2479",
    "sg:postcode":"21224",
    "sg:province":"MD",
    "sg:tags":[
        "establishment"
    ],
    "wof:name":"RBC Enterprises",
    "wof:placetype":"venue"
},
  "geometry": {"coordinates":[-76.53107,39.288033],"type":"Point"}
}