{
  "type": "Feature",
  "properties": {
    "addr:full":"20201 Darlington Dr Gaithersburg MD 20886",
    "addr:housenumber":"20201",
    "addr:postcode":"20886",
    "addr:street":"Darlington Dr",
    "iso:country":"US",
    "sg:address":"20201 Darlington Dr",
    "sg:city":"Gaithersburg",
    "sg:classifiers":[
        {
            "category":"Professional",
            "subcategory":"Art Services",
            "type":"Services"
        },
        {
            "category":"Manufacturing",
            "subcategory":"Printing",
            "type":"Manufacturing & Wholesale Goods"
        }
    ],
    "sg:phone":"+1 301 869 3291",
    "sg:postcode":"20886",
    "sg:province":"MD",
    "sg:tags":[
        "commercial",
        "printer",
        "design"
    ],
    "wof:name":"Dartmouth Graphics Inc",
    "wof:placetype":"venue"
},
  "geometry": {"coordinates":[-77.20880200000001,39.187249],"type":"Point"}
}