{
  "type": "Feature",
  "properties": {
    "addr:full":"10728 Lady Slipper Ter Rockville MD 20852",
    "addr:housenumber":"10728",
    "addr:postcode":"20852",
    "addr:street":"Lady Slipper Ter",
    "iso:country":"US",
    "sg:address":"10728 Lady Slipper Ter",
    "sg:city":"Rockville",
    "sg:classifiers":[
        {
            "category":"Professional",
            "subcategory":"Management & Consulting",
            "type":"Services"
        }
    ],
    "sg:phone":"+1 301 881 0812",
    "sg:postcode":"20852",
    "sg:province":"MD",
    "sg:tags":[
        "consultant",
        "resource",
        "human"
    ],
    "wof:name":"H R Dynamics",
    "wof:placetype":"venue"
},
  "geometry": {"coordinates":[-77.12316300000001,39.032085],"type":"Point"}
}