{
  "type": "Feature",
  "properties": {
    "addr:full":"9101 Franklin Square Dr # 308 Rosedale MD 21237",
    "addr:housenumber":"9101",
    "addr:postcode":"21237",
    "addr:street":"Franklin Square Dr # 308",
    "iso:country":"US",
    "sg:address":"9101 Franklin Square Dr # 308",
    "sg:city":"Rosedale",
    "sg:classifiers":[
        {
            "category":"Health Services",
            "subcategory":"Doctor",
            "type":"Services"
        }
    ],
    "sg:phone":"+1 410 686 7876",
    "sg:postcode":"21237",
    "sg:province":"MD",
    "sg:tags":[
        "dermatology",
        "physician",
        "surgeon",
        "surgeons"
    ],
    "wof:name":"Poulton Acri & Smith",
    "wof:placetype":"venue"
},
  "geometry": {"coordinates":[-76.476448,39.351622],"type":"Point"}
}