{
  "type": "Feature",
  "properties": {
    "addr:full":"7515 Annapolis Rd Hyattsville MD 20784",
    "addr:housenumber":"7515",
    "addr:postcode":"20784",
    "addr:street":"Annapolis Rd",
    "iso:country":"US",
    "sg:address":"7515 Annapolis Rd",
    "sg:city":"Hyattsville",
    "sg:classifiers":[
        {
            "category":"Health Services",
            "subcategory":"Health Practitioner",
            "type":"Services"
        }
    ],
    "sg:phone":"+1 301 731 3433",
    "sg:postcode":"20784",
    "sg:province":"MD",
    "sg:tags":[
        "nurse",
        "registry"
    ],
    "wof:name":"Metro Nursing Svc",
    "wof:placetype":"venue"
},
  "geometry": {"coordinates":[-76.885869,38.950776],"type":"Point"}
}