{
  "type": "Feature",
  "properties": {
    "addr:full":"313 S Camden Ave Fruitland MD 21826",
    "addr:housenumber":"313",
    "addr:postcode":"21826",
    "addr:street":"S Camden Ave",
    "iso:country":"US",
    "sg:address":"313 S Camden Ave",
    "sg:city":"Fruitland",
    "sg:classifiers":[
        {
            "category":"Shopping",
            "subcategory":"Gifts & Souvenirs",
            "type":"Retail Goods"
        }
    ],
    "sg:phone":"+1 410 546 3471",
    "sg:postcode":"21826",
    "sg:province":"MD",
    "sg:tags":[
        "shop"
    ],
    "wof:name":"Tasteful Treasures By Cathy",
    "wof:placetype":"venue"
},
  "geometry": {"coordinates":[-75.628664,38.323592],"type":"Point"}
}