{
  "type": "Feature",
  "properties": {
    "iso:country":"US",
    "sg:address":"16 S Castle St",
    "sg:city":"Baltimore",
    "sg:classifiers":[
        {
            "category":"Health Services",
            "subcategory":"Health Practitioner",
            "type":"Services"
        }
    ],
    "sg:phone":"+1 410 576 9191",
    "sg:postcode":"21231",
    "sg:province":"MD",
    "wof:name":"Recovery Network",
    "wof:placetype":"venue"
},
  "geometry": {"coordinates":[-76.588307,39.291706],"type":"Point"}
}