{
  "type": "Feature",
  "properties": {
    "iso:country":"US",
    "sg:address":"10331 Orleans Rd NE",
    "sg:city":"Little Orleans",
    "sg:classifiers":[
        {
            "category":"Manufacturing",
            "subcategory":"Lumber",
            "type":"Manufacturing & Wholesale Goods"
        }
    ],
    "sg:phone":"+1 301 478 3121",
    "sg:postcode":"21766",
    "sg:province":"MD",
    "sg:tags":[
        "company",
        "logging"
    ],
    "wof:name":"Mc Cusker Logging",
    "wof:placetype":"venue"
},
  "geometry": {"coordinates":[-78.37677600000001,39.660909],"type":"Point"}
}