{
  "type": "Feature",
  "properties": {
    "addr:full":"10870 Sandringham Rd Cockeysville MD 21030",
    "addr:housenumber":"10870",
    "addr:postcode":"21030",
    "addr:street":"Sandringham Rd",
    "iso:country":"US",
    "sg:address":"10870 Sandringham Rd",
    "sg:city":"Cockeysville",
    "sg:classifiers":[
        {
            "category":"Professional",
            "subcategory":"Management & Consulting",
            "type":"Services"
        }
    ],
    "sg:phone":"+1 410 628 6464",
    "sg:postcode":"21030",
    "sg:province":"MD",
    "sg:tags":[
        "business"
    ],
    "wof:name":"Donna Keuck-Becker PHD",
    "wof:placetype":"venue"
},
  "geometry": {"coordinates":[-76.604226,39.485343],"type":"Point"}
}