{
  "type": "Feature",
  "properties": {
    "iso:country":"US",
    "sg:address":"1523 Ridge Rd",
    "sg:city":"Whiteford",
    "sg:classifiers":[
        {
            "category":"Building & Trades",
            "subcategory":"Construction",
            "type":"Services"
        }
    ],
    "sg:phone":"+1 410 879 3094",
    "sg:postcode":"21160",
    "sg:province":"MD",
    "sg:tags":[
        "home",
        "improvement"
    ],
    "wof:name":"Cicone Cy & Sons Inc",
    "wof:placetype":"venue"
},
  "geometry": {"coordinates":[-76.332384,39.702481],"type":"Point"}
}