{
  "type": "Feature",
  "properties": {
    "addr:full":"7601 Eastern Ave Baltimore MD 21224",
    "addr:housenumber":"7601",
    "addr:postcode":"21224",
    "addr:street":"Eastern Ave",
    "iso:country":"US",
    "sg:address":"7601 Eastern Ave",
    "sg:city":"Baltimore",
    "sg:classifiers":[
        {
            "category":"Food & Beverages",
            "subcategory":"Groceries & Convenience Stores",
            "type":"Retail Goods"
        }
    ],
    "sg:phone":"+1 410 285 0909",
    "sg:postcode":"21224",
    "sg:province":"MD",
    "sg:website":"www.chevron.com",
    "wof:name":"Eastern Avenue Chevron",
    "wof:placetype":"venue"
},
  "geometry": {"coordinates":[-76.520337,39.291655],"type":"Point"}
}