{
  "type": "Feature",
  "properties": {
    "iso:country":"US",
    "sg:address":"200 E 31st St",
    "sg:city":"Baltimore",
    "sg:classifiers":[
        {
            "category":"Building & Trades",
            "subcategory":"Pest Control",
            "type":"Services"
        }
    ],
    "sg:phone":"+1 410 243 3660",
    "sg:postcode":"21218",
    "sg:province":"MD",
    "sg:tags":[
        "mothproofing"
    ],
    "wof:name":"B&B Exterminators",
    "wof:placetype":"venue"
},
  "geometry": {"coordinates":[-76.614761,39.325851],"type":"Point"}
}