{
  "type": "Feature",
  "properties": {
    "iso:country":"US",
    "sg:address":"821 Ellsworth Dr",
    "sg:city":"Silver Spring",
    "sg:classifiers":[
        {
            "category":"Ice Cream",
            "type":"Food & Drink"
        }
    ],
    "sg:menulink":"http://www.allmenus.com/md/silver-spring/184869-cold-stone-creamery/menu/",
    "sg:phone":"+1 301 588 1230",
    "sg:postcode":"20910",
    "sg:province":"MD",
    "sg:tags":[
        "smoothy",
        "juice",
        "american"
    ],
    "wof:name":"Cold Stone Creamery",
    "wof:placetype":"venue"
},
  "geometry": {"coordinates":[-77.025915,38.996387],"type":"Point"}
}