{
  "type": "Feature",
  "properties": {
    "iso:country":"US",
    "sg:address":"5601 Loch Raven Blvd",
    "sg:city":"Baltimore",
    "sg:classifiers":[
        {
            "category":"Health Services",
            "subcategory":"Doctor",
            "type":"Services"
        }
    ],
    "sg:phone":"+1 410 532 4290",
    "sg:postcode":"21239",
    "sg:province":"MD",
    "wof:name":"Salmon Duncan MD",
    "wof:placetype":"venue"
},
  "geometry": {"coordinates":[-76.58695,39.357093],"type":"Point"}
}