{
  "type": "Feature",
  "properties": {
    "iso:country":"US",
    "sg:address":"1801 Jackson St",
    "sg:city":"Baltimore",
    "sg:classifiers":[
        {
            "category":"Professional",
            "subcategory":"Management & Consulting",
            "type":"Services"
        }
    ],
    "sg:phone":"+1 443 629 5418",
    "sg:postcode":"21230",
    "sg:province":"MD",
    "sg:tags":[
        "business"
    ],
    "wof:name":"Gensor Consulting LLC",
    "wof:placetype":"venue"
},
  "geometry": {"coordinates":[-76.604896,39.2688],"type":"Point"}
}