{
  "type": "Feature",
  "properties": {
    "addr:full":"12700 Brandywine Rd Brandywine MD 20613",
    "addr:housenumber":"12700",
    "addr:postcode":"20613",
    "addr:street":"Brandywine Rd",
    "iso:country":"US",
    "sg:address":"12700 Brandywine Rd",
    "sg:city":"Brandywine",
    "sg:classifiers":[
        {
            "category":"Transit Center",
            "subcategory":"Freight",
            "type":"Transportation"
        }
    ],
    "sg:phone":"+1 240 441 9888",
    "sg:postcode":"20613",
    "sg:province":"MD",
    "sg:tags":[
        "trucking-motor"
    ],
    "wof:name":"Freightmax",
    "wof:placetype":"venue"
},
  "geometry": {"coordinates":[-76.886099,38.714323],"type":"Point"}
}