{
  "type": "Feature",
  "properties": {
    "addr:full":"1902 Ridgeway Ave Timonium MD 21093",
    "addr:housenumber":"1902",
    "addr:postcode":"21093",
    "addr:street":"Ridgeway Ave",
    "iso:country":"US",
    "sg:address":"1902 Ridgeway Ave",
    "sg:city":"Timonium",
    "sg:classifiers":[
        {
            "category":"Building & Trades",
            "subcategory":"Construction",
            "type":"Services"
        }
    ],
    "sg:phone":"+1 410 252 0055",
    "sg:postcode":"21093",
    "sg:province":"MD",
    "sg:tags":[
        "home",
        "improvement"
    ],
    "wof:name":"Improvements By Design LTD",
    "wof:placetype":"venue"
},
  "geometry": {"coordinates":[-76.714901,39.437016],"type":"Point"}
}