{
  "type": "Feature",
  "properties": {
    "iso:country":"US",
    "sg:address":"24439 Garrett Hwy",
    "sg:city":"Mc Henry",
    "sg:classifiers":[
        {
            "category":"Real Estate",
            "subcategory":"Real Estate Agent",
            "type":"Services"
        }
    ],
    "sg:phone":"+1 301 387 5303",
    "sg:postcode":"21541",
    "sg:province":"MD",
    "sg:website":"www.deepcreekrealty.com",
    "wof:name":"Deep Creek Realty",
    "wof:placetype":"venue"
},
  "geometry": {"coordinates":[-79.344695,39.53479],"type":"Point"}
}