{
  "type": "Feature",
  "properties": {
    "iso:country":"US",
    "sg:address":"300 W Lexington St",
    "sg:city":"Baltimore",
    "sg:classifiers":[
        {
            "category":"Government",
            "subcategory":"Office",
            "type":"Public Place"
        }
    ],
    "sg:phone":"+1 410 859 7665",
    "sg:postcode":"21201",
    "sg:province":"MD",
    "wof:name":"Car-Van Pool Information",
    "wof:placetype":"venue"
},
  "geometry": {"coordinates":[-76.62049399999999,39.291568],"type":"Point"}
}