{
  "type": "Feature",
  "properties": {
    "iso:country":"US",
    "sg:address":"281 E Main St",
    "sg:city":"Rising Sun",
    "sg:classifiers":[
        {
            "category":"Health Services",
            "subcategory":"Doctor",
            "type":"Services"
        }
    ],
    "sg:phone":"+1 410 658 4099",
    "sg:postcode":"21911",
    "sg:province":"MD",
    "sg:tags":[
        "physician",
        "surgeon"
    ],
    "wof:name":"Union Medical Clinic",
    "wof:placetype":"venue"
},
  "geometry": {"coordinates":[-76.054519,39.698988],"type":"Point"}
}