{
  "type": "Feature",
  "properties": {
    "addr:full":"17430 Hoskinson Rd Poolesville MD 20837",
    "addr:housenumber":"17430",
    "addr:postcode":"20837",
    "addr:street":"Hoskinson Rd",
    "iso:country":"US",
    "sg:address":"17430 Hoskinson Rd",
    "sg:city":"Poolesville",
    "sg:classifiers":[
        {
            "category":"Cinema",
            "subcategory":"Movie Rental",
            "type":"Entertainment"
        }
    ],
    "sg:phone":"+1 301 972 8084",
    "sg:postcode":"20837",
    "sg:province":"MD",
    "sg:tags":[
        "motion",
        "picture",
        "distributor",
        "film",
        "exchange"
    ],
    "wof:name":"Powell Productions",
    "wof:placetype":"venue"
},
  "geometry": {"coordinates":[-77.412522,39.140684],"type":"Point"}
}