{
  "type": "Feature",
  "properties": {
    "addr:full":"8638 Veterans Hwy Millersville MD 21108",
    "addr:housenumber":"8638",
    "addr:postcode":"21108",
    "addr:street":"Veterans Hwy",
    "iso:country":"US",
    "sg:address":"8638 Veterans Hwy",
    "sg:city":"Millersville",
    "sg:classifiers":[
        {
            "category":"Professional",
            "subcategory":"Management & Consulting",
            "type":"Services"
        },
        {
            "category":"Banks & Credit Unions",
            "subcategory":"Investment Brokerage",
            "type":"Services"
        },
        {
            "category":"Banks & Credit Unions",
            "subcategory":"Financial Services",
            "type":"Services"
        }
    ],
    "sg:phone":"+1 410 729 9080",
    "sg:postcode":"21108",
    "sg:province":"MD",
    "sg:tags":[
        "planning",
        "advisory",
        "financing",
        "planner",
        "consultant"
    ],
    "sg:website":"http://www.concordfinancialadvisors.com",
    "wof:name":"Ameriprise Financial Services, Inc.",
    "wof:placetype":"venue"
},
  "geometry": {"coordinates":[-76.623322,39.088118],"type":"Point"}
}