{
  "type": "Feature",
  "properties": {
    "iso:country":"US",
    "sg:address":"5225 Raccoon Ct",
    "sg:city":"Columbia",
    "sg:classifiers":[
        {
            "category":"Professional",
            "type":"Services"
        }
    ],
    "sg:phone":"+1 410 730 6262",
    "sg:postcode":"21045",
    "sg:province":"MD",
    "sg:tags":[
        "actuary"
    ],
    "wof:name":"Columbia Actuary",
    "wof:placetype":"venue"
},
  "geometry": {"coordinates":[-76.829357,39.226741],"type":"Point"}
}