{
  "type": "Feature",
  "properties": {
    "iso:country":"US",
    "sg:address":"327 Spry Island Rd",
    "sg:city":"Joppa",
    "sg:classifiers":[
        {
            "category":"Professional",
            "subcategory":"Detective & Security Services",
            "type":"Services"
        }
    ],
    "sg:phone":"+1 410 679 0852",
    "sg:postcode":"21085",
    "sg:province":"MD",
    "sg:tags":[
        "guard",
        "contract"
    ],
    "wof:name":"Bravett M Bull",
    "wof:placetype":"venue"
},
  "geometry": {"coordinates":[-76.36649800000001,39.440991],"type":"Point"}
}