{
  "type": "Feature",
  "properties": {
    "iso:country":"US",
    "sg:address":"9332 Annapolis Rd",
    "sg:city":"Lanham",
    "sg:classifiers":[
        {
            "category":"Shopping",
            "type":"Retail Goods"
        }
    ],
    "sg:phone":"+1 301 306 7985",
    "sg:postcode":"20706",
    "sg:province":"MD",
    "sg:tags":[
        "cosmetic",
        "perfume"
    ],
    "wof:name":"Marykay Cosmetics Training Ctr",
    "wof:placetype":"venue"
},
  "geometry": {"coordinates":[-76.848079,38.965051],"type":"Point"}
}