{
  "type": "Feature",
  "properties": {
    "iso:country":"US",
    "sg:address":"5916 York Rd",
    "sg:city":"Baltimore",
    "sg:classifiers":[
        {
            "category":"Restaurant",
            "type":"Food & Drink"
        }
    ],
    "sg:phone":"+1 410 323 3368",
    "sg:postcode":"21212",
    "sg:province":"MD",
    "sg:tags":[
        "style",
        "mexican",
        "family"
    ],
    "wof:name":"Zen West Roadside Cantina",
    "wof:placetype":"venue"
},
  "geometry": {"coordinates":[-76.609921,39.364251],"type":"Point"}
}