{
  "type": "Feature",
  "properties": {
    "addr:full":"1928 Lincoln Dr Annapolis MD 21401",
    "addr:housenumber":"1928",
    "addr:postcode":"21401",
    "addr:street":"Lincoln Dr",
    "iso:country":"US",
    "sg:address":"1928 Lincoln Dr",
    "sg:city":"Annapolis",
    "sg:classifiers":[
        {
            "category":"Retail",
            "subcategory":"Auto Repair",
            "type":"Services"
        }
    ],
    "sg:phone":"+1 410 280 2436",
    "sg:postcode":"21401",
    "sg:province":"MD",
    "sg:tags":[
        "repairing",
        "automobile"
    ],
    "wof:name":"Green Automotive",
    "wof:placetype":"venue"
},
  "geometry": {"coordinates":[-76.52149300000001,38.973464],"type":"Point"}
}