{
  "type": "Feature",
  "properties": {
    "addr:full":"9770 Basket Ring Rd Columbia MD 21045",
    "addr:postcode":"9770;21045",
    "addr:street":"Basket Ring Rd",
    "iso:country":"US",
    "sg:address":"9770 Basket Ring Rd",
    "sg:city":"Columbia",
    "sg:classifiers":[
        {
            "category":"Shopping",
            "subcategory":"Books",
            "type":"Retail Goods"
        }
    ],
    "sg:phone":"+1 410 730 1484",
    "sg:postcode":"21045",
    "sg:province":"MD",
    "wof:name":"Culpepper Hughes & Head Black",
    "wof:placetype":"venue"
},
  "geometry": {"coordinates":[-76.845929,39.213517],"type":"Point"}
}