{
  "type": "Feature",
  "properties": {
    "iso:country":"US",
    "sg:address":"8256 Tuckahoe Rd",
    "sg:city":"Denton",
    "sg:classifiers":[
        {
            "category":"Building & Trades",
            "subcategory":"Plumbing",
            "type":"Services"
        }
    ],
    "sg:phone":"+1 410 479 2022",
    "sg:postcode":"21629",
    "sg:province":"MD",
    "sg:tags":[
        "conditioning",
        "air",
        "system",
        "contractor"
    ],
    "wof:name":"JNL Mechanical",
    "wof:placetype":"venue"
},
  "geometry": {"coordinates":[-75.93416499999999,38.90464],"type":"Point"}
}