{
  "type": "Feature",
  "properties": {
    "addr:full":"20717 National Pike Boonsboro MD 21713",
    "addr:housenumber":"20717",
    "addr:postcode":"21713",
    "addr:street":"National Pike",
    "iso:country":"US",
    "sg:address":"20717 National Pike",
    "sg:city":"Boonsboro",
    "sg:classifiers":[
        {
            "category":"Food & Beverages",
            "subcategory":"Groceries & Convenience Stores",
            "type":"Retail Goods"
        }
    ],
    "sg:phone":"+1 240 420 5003",
    "sg:postcode":"21713",
    "sg:province":"MD",
    "wof:name":"National Pike Flea Market",
    "wof:placetype":"venue"
},
  "geometry": {"coordinates":[-77.65074300000001,39.574167],"type":"Point"}
}