{
  "type": "Feature",
  "properties": {
    "iso:country":"US",
    "sg:address":"3541 Foxhall Dr",
    "sg:city":"Davidsonville",
    "sg:classifiers":[
        {
            "category":"Professional",
            "subcategory":"Business Services",
            "type":"Services"
        }
    ],
    "sg:phone":"+1 410 798 4366",
    "sg:postcode":"21035",
    "sg:province":"MD",
    "wof:name":"Burdette Enterprises LLC",
    "wof:placetype":"venue"
},
  "geometry": {"coordinates":[-76.634067,38.912747],"type":"Point"}
}