{
  "type": "Feature",
  "properties": {
    "iso:country":"US",
    "sg:address":"8120 Fenton St",
    "sg:city":"Silver Spring",
    "sg:classifiers":[
        {
            "category":"Insurance",
            "subcategory":"Insurance Agent",
            "type":"Services"
        }
    ],
    "sg:phone":"+1 301 589 0200",
    "sg:postcode":"20910",
    "sg:province":"MD",
    "wof:name":"Gibralter Insurance",
    "wof:placetype":"venue"
},
  "geometry": {"coordinates":[-77.024102,38.991387],"type":"Point"}
}