{
  "type": "Feature",
  "properties": {
    "addr:full":"205 E Joppa Rd Towson MD 21286",
    "addr:housenumber":"205",
    "addr:postcode":"21286",
    "addr:street":"E Joppa Rd",
    "iso:country":"US",
    "sg:address":"205 E Joppa Rd",
    "sg:city":"Towson",
    "sg:classifiers":[
        {
            "category":"Personal",
            "subcategory":"Beauty Salon",
            "type":"Services"
        }
    ],
    "sg:phone":"+1 410 296 1114",
    "sg:postcode":"21286",
    "sg:province":"MD",
    "wof:name":"Hands For Hair Studio Inc",
    "wof:placetype":"venue"
},
  "geometry": {"coordinates":[-76.596289,39.401777],"type":"Point"}
}