{
  "type": "Feature",
  "properties": {
    "addr:full":"5200 Kenwood Ave Baltimore MD 21206",
    "addr:housenumber":"5200",
    "addr:postcode":"21206",
    "addr:street":"Kenwood Ave",
    "iso:country":"US",
    "sg:address":"5200 Kenwood Ave",
    "sg:city":"Baltimore",
    "sg:classifiers":[
        {
            "category":"Food & Beverages",
            "subcategory":"Groceries & Convenience Stores",
            "type":"Retail Goods"
        }
    ],
    "sg:phone":"+1 410 661 7677",
    "sg:postcode":"21206",
    "sg:province":"MD",
    "sg:tags":[
        "grocer"
    ],
    "wof:name":"Grandpop's Place Inc",
    "wof:placetype":"venue"
},
  "geometry": {"coordinates":[-76.513199,39.354698],"type":"Point"}
}