{
  "type": "Feature",
  "properties": {
    "iso:country":"US",
    "sg:address":"1737 E Joppa Rd",
    "sg:city":"Parkville",
    "sg:classifiers":[
        {
            "category":"Retail",
            "subcategory":"Auto Repair",
            "type":"Services"
        }
    ],
    "sg:phone":"+1 410 882 9964",
    "sg:postcode":"21234",
    "sg:province":"MD",
    "sg:tags":[
        "repairing",
        "automobile"
    ],
    "wof:name":"Joppa Car Care",
    "wof:placetype":"venue"
},
  "geometry": {"coordinates":[-76.55965500000001,39.398396],"type":"Point"}
}