{
  "type": "Feature",
  "properties": {
    "iso:country":"US",
    "sg:address":"79 S Market St",
    "sg:city":"Frederick",
    "sg:classifiers":[
        {
            "category":"Government",
            "subcategory":"Fire Station",
            "type":"Public Place"
        }
    ],
    "sg:phone":"+1 301 694 1711",
    "sg:postcode":"21701",
    "sg:province":"MD",
    "sg:tags":[
        "department",
        "volunteer"
    ],
    "wof:name":"United Steam Fire Engine Co 3",
    "wof:placetype":"venue"
},
  "geometry": {"coordinates":[-77.41129599999999,39.412308],"type":"Point"}
}