{
  "type": "Feature",
  "properties": {
    "addr:full":"1231 N Calvert St Baltimore MD 21202",
    "addr:housenumber":"1231",
    "addr:postcode":"21202",
    "addr:street":"N Calvert St",
    "iso:country":"US",
    "sg:address":"1231 N Calvert St",
    "sg:city":"Baltimore",
    "sg:classifiers":[
        {
            "category":"Professional",
            "subcategory":"Research",
            "type":"Services"
        }
    ],
    "sg:phone":"+1 410 332 1231",
    "sg:postcode":"21202",
    "sg:province":"MD",
    "sg:tags":[
        "nonphysical",
        "commercial"
    ],
    "wof:name":"Commercial R E LLC",
    "wof:placetype":"venue"
},
  "geometry": {"coordinates":[-76.613293,39.304309],"type":"Point"}
}