{
  "type": "Feature",
  "properties": {
    "addr:full":"820 Diamond Dr Gaithersburg MD 20878",
    "addr:housenumber":"820",
    "addr:postcode":"20878",
    "addr:street":"Diamond Dr",
    "iso:country":"US",
    "sg:address":"820 Diamond Dr",
    "sg:city":"Gaithersburg",
    "sg:classifiers":[
        {
            "category":"Real Estate",
            "subcategory":"Real Estate Agent",
            "type":"Services"
        }
    ],
    "sg:phone":"+1 301 869 5198",
    "sg:postcode":"20878",
    "sg:province":"MD",
    "wof:name":"Rosecliff Realty Inc",
    "wof:placetype":"venue"
},
  "geometry": {"coordinates":[-77.231025,39.134086],"type":"Point"}
}