{
  "type": "Feature",
  "properties": {
    "iso:country":"US",
    "sg:address":"5112 Sunnyside Ave",
    "sg:city":"Beltsville",
    "sg:classifiers":[
        {
            "category":"Freight",
            "type":"Transportation"
        }
    ],
    "sg:phone":"+1 301 441 8715",
    "sg:postcode":"20705",
    "sg:province":"MD",
    "sg:tags":[
        "mover"
    ],
    "wof:name":"Ryder Van Lines",
    "wof:placetype":"venue"
},
  "geometry": {"coordinates":[-76.912507,39.023642],"type":"Point"}
}