{
  "type": "Feature",
  "properties": {
    "addr:full":"8201 16th St Silver Spring MD 20910",
    "addr:housenumber":"8201",
    "addr:postcode":"20910",
    "addr:street":"16Th St",
    "iso:country":"US",
    "sg:address":"8201 16th St",
    "sg:city":"Silver Spring",
    "sg:classifiers":[
        {
            "category":"Professional",
            "subcategory":"Employment Agencies",
            "type":"Services"
        }
    ],
    "sg:phone":"+1 301 920 0892",
    "sg:postcode":"20910",
    "sg:province":"MD",
    "sg:tags":[
        "recruiting"
    ],
    "wof:name":"Sharma Shami",
    "wof:placetype":"venue"
},
  "geometry": {"coordinates":[-77.036163,38.99235],"type":"Point"}
}