{
  "type": "Feature",
  "properties": {
    "addr:full":"101 Court House Plz Elkton MD 21921",
    "addr:housenumber":"101",
    "addr:postcode":"21921",
    "addr:street":"Court House Plz",
    "iso:country":"US",
    "sg:address":"101 Court House Plz",
    "sg:city":"Elkton",
    "sg:classifiers":[
        {
            "category":"Professional",
            "subcategory":"Lawyer & Legal Services",
            "type":"Services"
        }
    ],
    "sg:phone":"+1 410 398 6663",
    "sg:postcode":"21921",
    "sg:province":"MD",
    "sg:tags":[
        "attorney",
        "practice"
    ],
    "wof:name":"Calvert, William B Attorney At Law",
    "wof:placetype":"venue"
},
  "geometry": {"coordinates":[-75.828941,39.608158],"type":"Point"}
}