{
  "type": "Feature",
  "properties": {
    "iso:country":"US",
    "sg:address":"6229 Harmony Rd",
    "sg:city":"Preston",
    "sg:classifiers":[
        {
            "category":"Food & Beverages",
            "subcategory":"Specialty",
            "type":"Retail Goods"
        }
    ],
    "sg:phone":"+1 410 820 8617",
    "sg:postcode":"21655",
    "sg:province":"MD",
    "sg:tags":[
        "water",
        "bulk",
        "company"
    ],
    "wof:name":"Eastern Springs Water Co",
    "wof:placetype":"venue"
},
  "geometry": {"coordinates":[-75.880622,38.778335],"type":"Point"}
}