{
  "type": "Feature",
  "properties": {
    "addr:full":"3537 Clipper Mill Rd Baltimore MD 21211",
    "addr:housenumber":"3537",
    "addr:postcode":"21211",
    "addr:street":"Clipper Mill Rd",
    "iso:country":"US",
    "sg:address":"3537 Clipper Mill Rd",
    "sg:city":"Baltimore",
    "sg:classifiers":[
        {
            "category":"Manufacturing",
            "subcategory":"Furniture",
            "type":"Manufacturing & Wholesale Goods"
        },
        {
            "category":"Home & Garden",
            "subcategory":"Furniture",
            "type":"Retail Goods"
        }
    ],
    "sg:phone":"+1 410 235 7770",
    "sg:postcode":"21211",
    "sg:province":"MD",
    "sg:tags":[
        "builder",
        "designer",
        "store",
        "custom"
    ],
    "wof:name":"Scolati Furniture & Chair Making",
    "wof:placetype":"venue"
},
  "geometry": {"coordinates":[-76.640353,39.328214],"type":"Point"}
}