{
  "type": "Feature",
  "properties": {
    "iso:country":"US",
    "sg:address":"40738 Bobwhite Ln",
    "sg:city":"Leonardtown",
    "sg:classifiers":[
        {
            "category":"Wholesale",
            "subcategory":"Durable Goods & Equipment",
            "type":"Manufacturing & Wholesale Goods"
        }
    ],
    "sg:phone":"+1 301 997 0596",
    "sg:postcode":"20650",
    "sg:province":"MD",
    "wof:name":"Krystals Keepsakes",
    "wof:placetype":"venue"
},
  "geometry": {"coordinates":[-76.666821,38.291115],"type":"Point"}
}