{
  "type": "Feature",
  "properties": {
    "addr:full":"614 Old Edmondson Ave Catonsville MD 21228",
    "addr:housenumber":"614",
    "addr:postcode":"21228",
    "addr:street":"Old Edmondson Ave",
    "iso:country":"US",
    "sg:address":"614 Old Edmondson Ave",
    "sg:city":"Catonsville",
    "sg:classifiers":[
        {
            "category":"Professional",
            "subcategory":"Lawyer & Legal Services",
            "type":"Services"
        }
    ],
    "sg:phone":"+1 410 747 6199",
    "sg:postcode":"21228",
    "sg:province":"MD",
    "sg:tags":[
        "attorney"
    ],
    "wof:name":"Behre & Herbert",
    "wof:placetype":"venue"
},
  "geometry": {"coordinates":[-76.731903,39.277994],"type":"Point"}
}