{
  "type": "Feature",
  "properties": {
    "iso:country":"US",
    "sg:address":"16566 Three Notch Rd",
    "sg:city":"Ridge",
    "sg:classifiers":[
        {
            "category":"Organizations",
            "subcategory":"Religious Organization",
            "type":"Services"
        }
    ],
    "sg:phone":"+1 301 872 4321",
    "sg:postcode":"20680",
    "sg:province":"MD",
    "sg:tags":[
        "church"
    ],
    "wof:name":"St Michael's",
    "wof:placetype":"venue"
},
  "geometry": {"coordinates":[-76.36844,38.122265],"type":"Point"}
}