{
  "type": "Feature",
  "properties": {
    "iso:country":"US",
    "sg:address":"1900 Belair Rd",
    "sg:city":"Baltimore",
    "sg:classifiers":[
        {
            "category":"Autos & Motor Vehicles",
            "subcategory":"Fuel & Gas Station",
            "type":"Retail Goods"
        }
    ],
    "sg:phone":"+1 443 524 2327",
    "sg:postcode":"21213",
    "sg:province":"MD",
    "wof:name":"Middle Branch Park Service Station Inc",
    "wof:placetype":"venue"
},
  "geometry": {"coordinates":[-76.58290100000001,39.3134],"type":"Point"}
}