{
  "type": "Feature",
  "properties": {
    "iso:country":"US",
    "sg:address":"11100 Reisterstown Rd",
    "sg:city":"Owings Mills",
    "sg:classifiers":[
        {
            "category":"Real Estate",
            "subcategory":"Real Estate Agent",
            "type":"Services"
        }
    ],
    "sg:phone":"+1 410 654 1530",
    "sg:postcode":"21117",
    "sg:province":"MD",
    "wof:name":"Aaron M Max",
    "wof:placetype":"venue"
},
  "geometry": {"coordinates":[-76.797765,39.433473],"type":"Point"}
}