{
  "type": "Feature",
  "properties": {
    "iso:country":"US",
    "sg:address":"7474 Greenway Center Dr",
    "sg:city":"Greenbelt",
    "sg:classifiers":[
        {
            "category":"Professional",
            "subcategory":"Lawyer & Legal Services",
            "type":"Services"
        }
    ],
    "sg:phone":"+1 301 313 7200",
    "sg:postcode":"20770",
    "sg:province":"MD",
    "sg:tags":[
        "firm",
        "law"
    ],
    "wof:name":"Lockheed Martin",
    "wof:placetype":"venue"
},
  "geometry": {"coordinates":[-76.881648,38.99164],"type":"Point"}
}