{
  "type": "Feature",
  "properties": {
    "addr:full":"7814 Clarksworth Pl Parkville MD 21234",
    "addr:housenumber":"7814",
    "addr:postcode":"21234",
    "addr:street":"Clarksworth Pl",
    "iso:country":"US",
    "sg:address":"7814 Clarksworth Pl",
    "sg:city":"Parkville",
    "sg:classifiers":[
        {
            "category":"Professional",
            "subcategory":"Lawyer & Legal Services",
            "type":"Services"
        }
    ],
    "sg:phone":"+1 410 750 8260",
    "sg:postcode":"21234",
    "sg:province":"MD",
    "sg:tags":[
        "attorney",
        "practice"
    ],
    "wof:name":"Karp & Turkington L L C",
    "wof:placetype":"venue"
},
  "geometry": {"coordinates":[-76.539835,39.372135],"type":"Point"}
}