{
  "type": "Feature",
  "properties": {
    "iso:country":"US",
    "sg:address":"4315 Ebenezer Rd",
    "sg:city":"Baltimore",
    "sg:classifiers":[
        {
            "category":"Professional",
            "subcategory":"Accounting & Tax Preparation",
            "type":"Services"
        }
    ],
    "sg:phone":"+1 410 256 7920",
    "sg:postcode":"21236",
    "sg:province":"MD",
    "sg:tags":[
        "return",
        "filing"
    ],
    "wof:name":"H & R Block Tax Svc",
    "wof:placetype":"venue"
},
  "geometry": {"coordinates":[-76.47658199999999,39.397693],"type":"Point"}
}