{
  "type": "Feature",
  "properties": {
    "iso:country":"US",
    "sg:address":"4818 Suitland Rd",
    "sg:city":"Suitland",
    "sg:classifiers":[
        {
            "category":"Organizations",
            "subcategory":"Religious Organization",
            "type":"Services"
        }
    ],
    "sg:phone":"+1 301 735 0347",
    "sg:postcode":"20746",
    "sg:province":"MD",
    "sg:tags":[
        "churches-baptist",
        "church"
    ],
    "wof:name":"Mount Ararat Baptist Church",
    "wof:placetype":"venue"
},
  "geometry": {"coordinates":[-76.924344,38.848642],"type":"Point"}
}