{
  "type": "Feature",
  "properties": {
    "addr:full":"2025 Heritage Dr Baltimore MD 21209",
    "addr:housenumber":"2025",
    "addr:postcode":"21209",
    "addr:street":"Heritage Dr",
    "iso:country":"US",
    "sg:address":"2025 Heritage Dr",
    "sg:city":"Baltimore",
    "sg:classifiers":[
        {
            "category":"Local Transit",
            "type":"Transportation"
        }
    ],
    "sg:phone":"+1 410 486 0407",
    "sg:postcode":"21209",
    "sg:province":"MD",
    "sg:tags":[
        "passenger"
    ],
    "wof:name":"Airport Transportation",
    "wof:placetype":"venue"
},
  "geometry": {"coordinates":[-76.66433600000001,39.376979],"type":"Point"}
}