{
  "type": "Feature",
  "properties": {
    "iso:country":"US",
    "sg:address":"6339 Allentown Rd",
    "sg:city":"Temple Hills",
    "sg:classifiers":[
        {
            "category":"Personal",
            "type":"Services"
        }
    ],
    "sg:phone":"+1 301 449 5252",
    "sg:postcode":"20748",
    "sg:province":"MD",
    "sg:tags":[
        "wear",
        "formal"
    ],
    "wof:name":"Paulines Bridal Boutique",
    "wof:placetype":"venue"
},
  "geometry": {"coordinates":[-76.908303,38.80269],"type":"Point"}
}