{
  "type": "Feature",
  "properties": {
    "addr:full":"6720 Olney Laytonsville Rd Laytonsville MD 20882",
    "addr:housenumber":"6720",
    "addr:postcode":"20882",
    "addr:street":"Olney Laytonsville Rd",
    "iso:country":"US",
    "sg:address":"6720 Olney Laytonsville Rd",
    "sg:city":"Laytonsville",
    "sg:classifiers":[
        {
            "category":"Building & Trades",
            "subcategory":"Landscaping Services",
            "type":"Services"
        }
    ],
    "sg:phone":"+1 301 774 6768",
    "sg:postcode":"20882",
    "sg:province":"MD",
    "sg:tags":[
        "landscape",
        "contractor"
    ],
    "wof:name":"J B Kline Lawn Maintenance",
    "wof:placetype":"venue"
},
  "geometry": {"coordinates":[-77.137794,39.202734],"type":"Point"}
}