{
  "type": "Feature",
  "properties": {
    "addr:full":"2244 Hanson Rd Edgewood MD 21040",
    "addr:housenumber":"2244",
    "addr:postcode":"21040",
    "addr:street":"Hanson Rd",
    "iso:country":"US",
    "sg:address":"2244 Hanson Rd",
    "sg:city":"Edgewood",
    "sg:classifiers":[
        {
            "category":"Restaurant",
            "type":"Food & Drink"
        }
    ],
    "sg:phone":"+1 410 612 8000",
    "sg:postcode":"21040",
    "sg:province":"MD",
    "sg:tags":[
        "chinese"
    ],
    "wof:name":"Great Wall Chinese Restaurant",
    "wof:placetype":"venue"
},
  "geometry": {"coordinates":[-76.296204,39.4282],"type":"Point"}
}