{
  "type": "Feature",
  "properties": {
    "iso:country":"US",
    "sg:address":"4088 Howard Ave",
    "sg:city":"Kensington",
    "sg:classifiers":[
        {
            "category":"Restaurant",
            "type":"Food & Drink"
        }
    ],
    "sg:phone":"+1 301 897 8181",
    "sg:postcode":"20895",
    "sg:province":"MD",
    "sg:tags":[
        "caterer"
    ],
    "sg:website":"www.federalcity.com",
    "wof:name":"Federal City Caterers Inc",
    "wof:placetype":"venue"
},
  "geometry": {"coordinates":[-77.08452699999999,39.030799],"type":"Point"}
}