{
  "type": "Feature",
  "properties": {
    "iso:country":"US",
    "sg:address":"6400 Waterloo Rd",
    "sg:city":"Columbia",
    "sg:classifiers":[
        {
            "category":"Home & Garden",
            "subcategory":"Building Materials",
            "type":"Retail Goods"
        }
    ],
    "sg:phone":"+1 410 799 9998",
    "sg:postcode":"21045",
    "sg:province":"MD",
    "sg:tags":[
        "windows"
    ],
    "wof:name":"Guardian Door & Window",
    "wof:placetype":"venue"
},
  "geometry": {"coordinates":[-76.794069,39.195757],"type":"Point"}
}