{
  "type": "Feature",
  "properties": {
    "iso:country":"US",
    "sg:address":"1702 South Rd",
    "sg:city":"Baltimore",
    "sg:classifiers":[
        {
            "category":"Organizations",
            "subcategory":"Religious Organization",
            "type":"Services"
        }
    ],
    "sg:phone":"+1 410 367 7287",
    "sg:postcode":"21209",
    "sg:province":"MD",
    "sg:tags":[
        "church"
    ],
    "wof:name":"St John's Episcopal Church",
    "wof:placetype":"venue"
},
  "geometry": {"coordinates":[-76.653105,39.366059],"type":"Point"}
}