{
  "type": "Feature",
  "properties": {
    "addr:full":"3774 New Hampshire Ave Andrews Afb MD 20762",
    "addr:housenumber":"3774",
    "addr:postcode":"20762",
    "addr:street":"New Hampshire Ave",
    "iso:country":"US",
    "sg:address":"3774 New Hampshire Ave",
    "sg:city":"Andrews Afb",
    "sg:classifiers":[
        {
            "category":"Retail",
            "subcategory":"Auto Repair",
            "type":"Services"
        }
    ],
    "sg:phone":"+1 301 568 8460",
    "sg:postcode":"20762",
    "sg:province":"MD",
    "sg:tags":[
        "repairing",
        "automobile"
    ],
    "wof:name":"Mobile Oil Change & Lube",
    "wof:placetype":"venue"
},
  "geometry": {"coordinates":[-76.855993,38.819603],"type":"Point"}
}