{
  "type": "Feature",
  "properties": {
    "addr:full":"6111 Columbian Way Bowie MD 20715",
    "addr:housenumber":"6111",
    "addr:postcode":"20715",
    "addr:street":"Columbian Way",
    "iso:country":"US",
    "sg:address":"6111 Columbian Way",
    "sg:city":"Bowie",
    "sg:classifiers":[
        {
            "category":"Organizations",
            "subcategory":"Community Association",
            "type":"Services"
        }
    ],
    "sg:phone":"+1 301 262 1041",
    "sg:postcode":"20715",
    "sg:province":"MD",
    "sg:tags":[
        "fraternal"
    ],
    "wof:name":"Knights Of Columbus",
    "wof:placetype":"venue"
},
  "geometry": {"coordinates":[-76.71302900000001,38.977536],"type":"Point"}
}