{
  "type": "Feature",
  "properties": {
    "iso:country":"US",
    "sg:address":"139 N Gorsuch Rd",
    "sg:city":"Westminster",
    "sg:classifiers":[
        {
            "category":"Building & Trades",
            "subcategory":"Construction",
            "type":"Services"
        }
    ],
    "sg:phone":"+1 410 876 4792",
    "sg:postcode":"21157",
    "sg:province":"MD",
    "sg:tags":[
        "home",
        "improvement"
    ],
    "wof:name":"Double Diamond Construction",
    "wof:placetype":"venue"
},
  "geometry": {"coordinates":[-76.94158299999999,39.572926],"type":"Point"}
}