{
  "type": "Feature",
  "properties": {
    "addr:full":"218 N Charles St Ste 200 Baltimore MD 21201",
    "addr:housenumber":"218",
    "addr:postcode":"21201",
    "addr:street":"N Charles St Ste 200",
    "iso:country":"US",
    "sg:address":"218 N Charles St Ste 200",
    "sg:city":"Baltimore",
    "sg:classifiers":[
        {
            "category":"Professional",
            "subcategory":"Lawyer & Legal Services",
            "type":"Services"
        }
    ],
    "sg:phone":"+1 410 752 5383",
    "sg:postcode":"21201",
    "sg:province":"MD",
    "wof:name":"Law Offices of John G Packard",
    "wof:placetype":"venue"
},
  "geometry": {"coordinates":[-76.615196,39.2915],"type":"Point"}
}