{
  "type": "Feature",
  "properties": {
    "addr:full":"7625 Murray Hill Rd Columbia MD 20723",
    "addr:housenumber":"7625",
    "addr:postcode":"20723",
    "addr:street":"Murray Hill Rd",
    "iso:country":"US",
    "sg:address":"7625 Murray Hill Rd",
    "sg:city":"Columbia",
    "sg:classifiers":[
        {
            "category":"Food & Beverages",
            "subcategory":"Groceries & Convenience Stores",
            "type":"Retail Goods"
        }
    ],
    "sg:phone":"+1 410 792 9011",
    "sg:postcode":"20723",
    "sg:province":"MD",
    "wof:name":"High's Of Baltimore",
    "wof:placetype":"venue"
},
  "geometry": {"coordinates":[-76.849711,39.163915],"type":"Point"}
}