{
  "type": "Feature",
  "properties": {
    "addr:full":"2804 Beechland Ave Baltimore MD 21214",
    "addr:housenumber":"2804",
    "addr:postcode":"21214",
    "addr:street":"Beechland Ave",
    "iso:country":"US",
    "sg:address":"2804 Beechland Ave",
    "sg:city":"Baltimore",
    "sg:classifiers":[
        {
            "category":"Communications",
            "subcategory":"Film & Video Production",
            "type":"Services"
        }
    ],
    "sg:phone":"+1 443 850 7756",
    "sg:postcode":"21214",
    "sg:province":"MD",
    "sg:tags":[
        "recording",
        "service-sound"
    ],
    "wof:name":"Rachel Boikai",
    "wof:placetype":"venue"
},
  "geometry": {"coordinates":[-76.561588,39.359054],"type":"Point"}
}