{
  "type": "Feature",
  "properties": {
    "addr:full":"10626 York Rd Cockysvl Hnt Vly MD 21030",
    "addr:housenumber":"10626",
    "addr:postcode":"21030",
    "addr:street":"York Rd;Hnt Vly",
    "iso:country":"US",
    "sg:address":"10626 York Rd",
    "sg:city":"Cockysvl Hnt Vly",
    "sg:classifiers":[
        {
            "category":"Communications",
            "subcategory":"Film & Video Production",
            "type":"Services"
        }
    ],
    "sg:phone":"+1 410 667 1400",
    "sg:postcode":"21030",
    "sg:province":"MD",
    "sg:tags":[
        "taping"
    ],
    "sg:website":"www.renegadeproductions.com",
    "wof:name":"Renegade Productions",
    "wof:placetype":"venue"
},
  "geometry": {"coordinates":[-76.64272,39.478578],"type":"Point"}
}