{
  "type": "Feature",
  "properties": {
    "addr:full":"6462 Galway Dr Clarksville MD 21029",
    "addr:housenumber":"6462",
    "addr:postcode":"21029",
    "addr:street":"Galway Dr",
    "iso:country":"US",
    "sg:address":"6462 Galway Dr",
    "sg:city":"Clarksville",
    "sg:classifiers":[
        {
            "category":"Building & Trades",
            "subcategory":"Construction",
            "type":"Services"
        }
    ],
    "sg:phone":"+1 410 997 4580",
    "sg:postcode":"21029",
    "sg:province":"MD",
    "sg:tags":[
        "house"
    ],
    "wof:name":"Maintenance Services Group",
    "wof:placetype":"venue"
},
  "geometry": {"coordinates":[-76.935118,39.201282],"type":"Point"}
}