{
  "type": "Feature",
  "properties": {
    "iso:country":"US",
    "sg:address":"401 W Pratt St",
    "sg:city":"Baltimore",
    "sg:classifiers":[
        {
            "category":"Food & Beverages",
            "subcategory":"Bakery",
            "type":"Retail Goods"
        }
    ],
    "sg:phone":"+1 410 685 3377",
    "sg:postcode":"21201",
    "sg:province":"MD",
    "sg:tags":[
        "sandwich"
    ],
    "sg:website":"www.jimmyjohns.com",
    "wof:name":"Jimmy Johns",
    "wof:placetype":"venue"
},
  "geometry": {"coordinates":[-76.621393,39.28574],"type":"Point"}
}