{
  "type": "Feature",
  "properties": {
    "addr:full":"120 Sister Pierre Dr # 307 Towson MD 21204",
    "addr:housenumber":"120",
    "addr:postcode":"21204",
    "addr:street":"Sister Pierre Dr # 307",
    "iso:country":"US",
    "sg:address":"120 Sister Pierre Dr # 307",
    "sg:city":"Towson",
    "sg:classifiers":[
        {
            "category":"Health Services",
            "subcategory":"Doctor",
            "type":"Services"
        }
    ],
    "sg:phone":"+1 410 583 8722",
    "sg:postcode":"21204",
    "sg:province":"MD",
    "sg:tags":[
        "physician",
        "surgeons",
        "medicine",
        "surgeon",
        "rehabilitation",
        "physical"
    ],
    "wof:name":"Orgel, Laurie S",
    "wof:placetype":"venue"
},
  "geometry": {"coordinates":[-76.607204,39.387864],"type":"Point"}
}