{
  "type": "Feature",
  "properties": {
    "addr:full":"1525 Doxbury Rd Baltimore MD 21286",
    "addr:housenumber":"1525",
    "addr:postcode":"21286",
    "addr:street":"Doxbury Rd",
    "iso:country":"US",
    "sg:address":"1525 Doxbury Rd",
    "sg:city":"Baltimore",
    "sg:classifiers":[
        {
            "category":"Professional",
            "subcategory":"Management & Consulting",
            "type":"Services"
        }
    ],
    "sg:phone":"+1 410 821 6984",
    "sg:postcode":"21286",
    "sg:province":"MD",
    "wof:name":"Mike Palm Inc",
    "wof:placetype":"venue"
},
  "geometry": {"coordinates":[-76.570579,39.395313],"type":"Point"}
}