{
  "type": "Feature",
  "properties": {
    "addr:full":"4809 Tallahassee Ave Rockville MD 20853",
    "addr:housenumber":"4809",
    "addr:postcode":"20853",
    "addr:street":"Tallahassee Ave",
    "iso:country":"US",
    "sg:address":"4809 Tallahassee Ave",
    "sg:city":"Rockville",
    "sg:classifiers":[
        {
            "category":"Manufacturing",
            "subcategory":"Printing",
            "type":"Manufacturing & Wholesale Goods"
        }
    ],
    "sg:phone":"+1 301 933 1636",
    "sg:postcode":"20853",
    "sg:province":"MD",
    "sg:tags":[
        "publishing"
    ],
    "wof:name":"Image Library",
    "wof:placetype":"venue"
},
  "geometry": {"coordinates":[-77.097461,39.068739],"type":"Point"}
}