{
  "type": "Feature",
  "properties": {
    "addr:full":"1 W Pennsylvania Ave Towson MD 21204",
    "addr:housenumber":"1",
    "addr:postcode":"21204",
    "addr:street":"W Pennsylvania Ave",
    "iso:country":"US",
    "sg:address":"1 W Pennsylvania Ave",
    "sg:city":"Towson",
    "sg:classifiers":[
        {
            "category":"Communications",
            "type":"Services"
        }
    ],
    "sg:phone":"+1 410 769 8300",
    "sg:postcode":"21204",
    "sg:province":"MD",
    "wof:name":"Tango Communications",
    "wof:placetype":"venue"
},
  "geometry": {"coordinates":[-76.605254,39.400765],"type":"Point"}
}