{
  "type": "Feature",
  "properties": {
    "addr:full":"988 Hospitality Way Aberdeen MD 21001",
    "addr:housenumber":"988",
    "addr:postcode":"21001",
    "addr:street":"Hospitality Way",
    "iso:country":"US",
    "sg:address":"988 Hospitality Way",
    "sg:city":"Aberdeen",
    "sg:classifiers":[
        {
            "category":"Travel",
            "subcategory":"Hotels & Motels",
            "type":"Entertainment"
        }
    ],
    "sg:phone":"+1 410 273 7800",
    "sg:postcode":"21001",
    "sg:province":"MD",
    "wof:name":"Red Roof Inn",
    "wof:placetype":"venue"
},
  "geometry": {"coordinates":[-76.18691699999999,39.524054],"type":"Point"}
}