{
  "type": "Feature",
  "properties": {
    "addr:full":"40 S Dundalk Ave Dundalk MD 21222",
    "addr:housenumber":"40",
    "addr:postcode":"21222",
    "addr:street":"S Dundalk Ave",
    "iso:country":"US",
    "sg:address":"40 S Dundalk Ave",
    "sg:city":"Dundalk",
    "sg:classifiers":[
        {
            "category":"Professional",
            "subcategory":"Lawyer & Legal Services",
            "type":"Services"
        }
    ],
    "sg:phone":"+1 410 282 2112",
    "sg:postcode":"21222",
    "sg:province":"MD",
    "sg:tags":[
        "attorney"
    ],
    "wof:name":"Wittstadt & Wittstadt Pa",
    "wof:placetype":"venue"
},
  "geometry": {"coordinates":[-76.523747,39.257015],"type":"Point"}
}