{
  "type": "Feature",
  "properties": {
    "addr:full":"2131 Charles Henry Ln Baltimore MD 21209",
    "addr:housenumber":"2131",
    "addr:postcode":"21209",
    "addr:street":"Charles Henry Ln",
    "iso:country":"US",
    "sg:address":"2131 Charles Henry Ln",
    "sg:city":"Baltimore",
    "sg:classifiers":[
        {
            "category":"Sports & Exercise",
            "subcategory":"Gym",
            "type":"Entertainment"
        }
    ],
    "sg:phone":"+1 443 739 3319",
    "sg:postcode":"21209",
    "sg:province":"MD",
    "sg:tags":[
        "instruction",
        "gymnastics"
    ],
    "wof:name":"Technique Tumble Inc.",
    "wof:placetype":"venue"
},
  "geometry": {"coordinates":[-76.66986900000001,39.384341],"type":"Point"}
}