{
  "type": "Feature",
  "properties": {
    "iso:country":"US",
    "sg:address":"2837 Odonnell St",
    "sg:city":"Baltimore",
    "sg:classifiers":[
        {
            "category":"Restaurant",
            "type":"Food & Drink"
        }
    ],
    "sg:menulink":"http://www.allmenus.com/md/baltimore/131553-quiznos-sub/menu/",
    "sg:phone":"+1 410 276 3457",
    "sg:postcode":"21224",
    "sg:province":"MD",
    "sg:tags":[
        "wrap",
        "american",
        "sandwich"
    ],
    "wof:name":"Quiznos Sub",
    "wof:placetype":"venue"
},
  "geometry": {"coordinates":[-76.57595000000001,39.280025],"type":"Point"}
}