{
  "type": "Feature",
  "properties": {
    "addr:full":"9 Doolittle Dr Waldorf MD 20602",
    "addr:housenumber":"9",
    "addr:postcode":"20602",
    "addr:street":"Doolittle Dr",
    "iso:country":"US",
    "sg:address":"9 Doolittle Dr",
    "sg:city":"Waldorf",
    "sg:classifiers":[
        {
            "category":"Professional",
            "subcategory":"Lawyer & Legal Services",
            "type":"Services"
        }
    ],
    "sg:phone":"+1 301 374 2502",
    "sg:postcode":"20602",
    "sg:province":"MD",
    "sg:tags":[
        "attorney"
    ],
    "wof:name":"Whitworth Smith & Trunnell",
    "wof:placetype":"venue"
},
  "geometry": {"coordinates":[-76.903302,38.611479],"type":"Point"}
}