{
  "type": "Feature",
  "properties": {
    "addr:full":"1933 W Pratt St Baltimore MD 21223",
    "addr:housenumber":"1933",
    "addr:postcode":"21223",
    "addr:street":"W Pratt St",
    "iso:country":"US",
    "sg:address":"1933 W Pratt St",
    "sg:city":"Baltimore",
    "sg:classifiers":[
        {
            "category":"Organizations",
            "subcategory":"Non-profit Organization",
            "type":"Services"
        }
    ],
    "sg:phone":"+1 410 837 3977",
    "sg:postcode":"21223",
    "sg:province":"MD",
    "wof:name":"Friends Care Program",
    "wof:placetype":"venue"
},
  "geometry": {"coordinates":[-76.64719700000001,39.285086],"type":"Point"}
}