{
  "type": "Feature",
  "properties": {
    "iso:country":"US",
    "sg:address":"8800 Walther Blvd",
    "sg:city":"Baltimore",
    "sg:classifiers":[
        {
            "category":"Insurance",
            "subcategory":"Insurance Agent",
            "type":"Services"
        }
    ],
    "sg:phone":"+1 410 661 0296",
    "sg:postcode":"21234",
    "sg:province":"MD",
    "wof:name":"Reinhard Insurance Agency",
    "wof:placetype":"venue"
},
  "geometry": {"coordinates":[-76.50533799999999,39.392187],"type":"Point"}
}