{
  "type": "Feature",
  "properties": {
    "addr:full":"4601 Presidents Dr Lanham MD 20706",
    "addr:housenumber":"4601",
    "addr:postcode":"20706",
    "addr:street":"Presidents Dr",
    "iso:country":"US",
    "sg:address":"4601 Presidents Dr",
    "sg:city":"Lanham",
    "sg:classifiers":[
        {
            "category":"Professional",
            "subcategory":"Management & Consulting",
            "type":"Services"
        }
    ],
    "sg:phone":"+1 301 459 8986",
    "sg:postcode":"20706",
    "sg:province":"MD",
    "sg:tags":[
        "consultant",
        "business"
    ],
    "wof:name":"Duhaney Consulting Svc",
    "wof:placetype":"venue"
},
  "geometry": {"coordinates":[-76.83058,38.952597],"type":"Point"}
}