{
  "type": "Feature",
  "properties": {
    "iso:country":"US",
    "sg:address":"112 E Lexington St",
    "sg:city":"Baltimore",
    "sg:classifiers":[
        {
            "category":"Personal",
            "type":"Services"
        }
    ],
    "sg:phone":"+1 443 451 1891",
    "sg:postcode":"21202",
    "sg:province":"MD",
    "sg:tags":[
        "mover"
    ],
    "sg:website":"www.moversbaltimorestorage.com",
    "wof:name":"Baltimore Movers",
    "wof:placetype":"venue"
},
  "geometry": {"coordinates":[-76.613085,39.291248],"type":"Point"}
}