{
  "type": "Feature",
  "properties": {
    "addr:full":"1607 Ramblewood Rd Baltimore MD 21239",
    "addr:housenumber":"1607",
    "addr:postcode":"21239",
    "addr:street":"Ramblewood Rd",
    "iso:country":"US",
    "sg:address":"1607 Ramblewood Rd",
    "sg:city":"Baltimore",
    "sg:classifiers":[
        {
            "category":"Organizations",
            "subcategory":"Religious Organization",
            "type":"Services"
        }
    ],
    "sg:phone":"+1 410 323 5287",
    "sg:postcode":"21239",
    "sg:province":"MD",
    "sg:tags":[
        "clergy"
    ],
    "wof:name":"Calvin E Monroe",
    "wof:placetype":"venue"
},
  "geometry": {"coordinates":[-76.584029,39.359284],"type":"Point"}
}