{
  "type": "Feature",
  "properties": {
    "addr:full":"2406 Pot Spring Rd Lutherville Timonium MD 21093",
    "addr:housenumber":"2406",
    "addr:postcode":"21093",
    "addr:street":"Pot Spring Rd",
    "iso:country":"US",
    "sg:address":"2406 Pot Spring Rd",
    "sg:city":"Lutherville Timonium",
    "sg:classifiers":[
        {
            "category":"Personal",
            "subcategory":"Hair Removal",
            "type":"Services"
        }
    ],
    "sg:phone":"+1 410 560 1828",
    "sg:postcode":"21093",
    "sg:province":"MD",
    "wof:name":"William McVay",
    "wof:placetype":"venue"
},
  "geometry": {"coordinates":[-76.604246,39.455245],"type":"Point"}
}