{
  "type": "Feature",
  "properties": {
    "addr:full":"1515 Open St Baltimore MD 21226",
    "addr:housenumber":"1515",
    "addr:postcode":"21226",
    "addr:street":"Open St",
    "iso:country":"US",
    "sg:address":"1515 Open St",
    "sg:city":"Baltimore",
    "sg:classifiers":[
        {
            "category":"Manufacturing",
            "subcategory":"Food",
            "type":"Manufacturing & Wholesale Goods"
        }
    ],
    "sg:phone":"+1 410 355 4800",
    "sg:postcode":"21226",
    "sg:province":"MD",
    "sg:tags":[
        "rendering",
        "company"
    ],
    "wof:name":"Valley Proteins Inc",
    "wof:placetype":"venue"
},
  "geometry": {"coordinates":[-76.590069,39.21398],"type":"Point"}
}