{
  "type": "Feature",
  "properties": {
    "addr:full":"18200 Flower Hill Way Gaithersburg MD 20879",
    "addr:housenumber":"18200",
    "addr:postcode":"20879",
    "addr:street":"Flower Hill Way",
    "iso:country":"US",
    "sg:address":"18200 Flower Hill Way",
    "sg:city":"Gaithersburg",
    "sg:classifiers":[
        {
            "category":"Banks & Credit Unions",
            "subcategory":"Bank",
            "type":"Services"
        },
        {
            "category":"Banks & Credit Unions",
            "subcategory":"Financial Services",
            "type":"Services"
        }
    ],
    "sg:phone":"+1 240 631 3040",
    "sg:postcode":"20879",
    "sg:province":"MD",
    "sg:tags":[
        "financing",
        "loan"
    ],
    "sg:website":"http://www.SunTrust.com",
    "wof:name":"SunTrust Bank - Flower Hill",
    "wof:placetype":"venue"
},
  "geometry": {"coordinates":[-77.16454299999999,39.155392],"type":"Point"}
}