{
  "type": "Feature",
  "properties": {
    "addr:full":"3761 Commerce Dr Halethorpe MD 21227",
    "addr:housenumber":"3761",
    "addr:postcode":"21227",
    "addr:street":"Commerce Dr",
    "iso:country":"US",
    "sg:address":"3761 Commerce Dr",
    "sg:city":"Halethorpe",
    "sg:classifiers":[
        {
            "category":"Professional",
            "subcategory":"Computer Services",
            "type":"Services"
        }
    ],
    "sg:phone":"+1 410 242 8540",
    "sg:postcode":"21227",
    "sg:province":"MD",
    "sg:tags":[
        "repair"
    ],
    "wof:name":"PCI Data Systems",
    "wof:placetype":"venue"
},
  "geometry": {"coordinates":[-76.673221,39.249596],"type":"Point"}
}