{
  "type": "Feature",
  "properties": {
    "iso:country":"US",
    "sg:address":"239 N Bridge St",
    "sg:city":"Elkton",
    "sg:classifiers":[
        {
            "category":"Autos & Motor Vehicles",
            "subcategory":"Fuel & Gas Station",
            "type":"Retail Goods"
        }
    ],
    "sg:phone":"+1 410 398 2810",
    "sg:postcode":"21921",
    "sg:province":"MD",
    "sg:tags":[
        "oil"
    ],
    "wof:name":"Elk Service Ctr",
    "wof:placetype":"venue"
},
  "geometry": {"coordinates":[-75.835275,39.609846],"type":"Point"}
}