{
  "type": "Feature",
  "properties": {
    "iso:country":"US",
    "sg:address":"3440 Fort Meade Rd",
    "sg:city":"Laurel",
    "sg:classifiers":[
        {
            "category":"Travel",
            "subcategory":"Hotels & Motels",
            "type":"Entertainment"
        }
    ],
    "sg:phone":"+1 301 490 9595",
    "sg:postcode":"20724",
    "sg:province":"MD",
    "wof:name":"Red Carpet Inn",
    "wof:placetype":"venue"
},
  "geometry": {"coordinates":[-76.81597499999999,39.100384],"type":"Point"}
}