{
  "type": "Feature",
  "properties": {
    "addr:full":"8903 Woodyard Rd Clinton MD 20735",
    "addr:housenumber":"8903",
    "addr:postcode":"20735",
    "addr:street":"Woodyard Rd",
    "iso:country":"US",
    "sg:address":"8903 Woodyard Rd",
    "sg:city":"Clinton",
    "sg:classifiers":[
        {
            "category":"Utilities",
            "subcategory":"Mobile Phone",
            "type":"Services"
        },
        {
            "category":"Shopping",
            "subcategory":"Mobile Phones",
            "type":"Retail Goods"
        },
        {
            "category":"Utilities",
            "subcategory":"Telephone",
            "type":"Services"
        },
        {
            "category":"Professional",
            "subcategory":"Computer Services",
            "type":"Services"
        }
    ],
    "sg:phone":"+1 301 599 5627",
    "sg:postcode":"20735",
    "sg:province":"MD",
    "sg:tags":[
        "telecommunication",
        "supply",
        "communication",
        "system",
        "wireless",
        "equipment",
        "cellular"
    ],
    "sg:website":"http://clickserve.dartsearch.net/link/click?lid=43000000308049899",
    "wof:name":"T-Mobile",
    "wof:placetype":"venue"
},
  "geometry": {"coordinates":[-76.886612,38.767422],"type":"Point"}
}