{
  "type": "Feature",
  "properties": {
    "addr:full":"16400 Crain Hwy Brandywine MD 20613",
    "addr:housenumber":"16400",
    "addr:postcode":"20613",
    "addr:street":"Crain Hwy",
    "iso:country":"US",
    "sg:address":"16400 Crain Hwy",
    "sg:city":"Brandywine",
    "sg:classifiers":[
        {
            "category":"Banks & Credit Unions",
            "subcategory":"Financial Services",
            "type":"Services"
        },
        {
            "category":"Banks & Credit Unions",
            "subcategory":"Atm",
            "type":"Services"
        },
        {
            "category":"Food & Beverages",
            "subcategory":"Groceries & Convenience Stores",
            "type":"Retail Goods"
        }
    ],
    "sg:phone":"+1 301 782 4036",
    "sg:postcode":"20613",
    "sg:province":"MD",
    "sg:tags":[
        "money",
        "location",
        "order"
    ],
    "sg:website":"http://www.7-eleven.com",
    "wof:name":"7-Eleven",
    "wof:placetype":"venue"
},
  "geometry": {"coordinates":[-76.87460299999999,38.664146],"type":"Point"}
}