{
  "type": "Feature",
  "properties": {
    "iso:country":"US",
    "sg:address":"601 N Caroline St",
    "sg:city":"Baltimore",
    "sg:classifiers":[
        {
            "category":"Health Services",
            "subcategory":"Doctor",
            "type":"Services"
        }
    ],
    "sg:phone":"+1 410 955 3116",
    "sg:postcode":"21205",
    "sg:province":"MD",
    "sg:tags":[
        "physician",
        "surgeon"
    ],
    "wof:name":"Hopkins Cardiology",
    "wof:placetype":"venue"
},
  "geometry": {"coordinates":[-76.597475,39.296136],"type":"Point"}
}