{
  "type": "Feature",
  "properties": {
    "addr:full":"508 S Rolling Rd Baltimore MD 21228",
    "addr:housenumber":"508",
    "addr:postcode":"21228",
    "addr:street":"S Rolling Rd",
    "iso:country":"US",
    "sg:address":"508 S Rolling Rd",
    "sg:city":"Baltimore",
    "sg:classifiers":[
        {
            "category":"Building & Trades",
            "subcategory":"Construction",
            "type":"Services"
        }
    ],
    "sg:phone":"+1 410 747 1273",
    "sg:postcode":"21228",
    "sg:province":"MD",
    "sg:tags":[
        "general",
        "contractor"
    ],
    "wof:name":"Jtk Home Improvements LLC",
    "wof:placetype":"venue"
},
  "geometry": {"coordinates":[-76.736031,39.261717],"type":"Point"}
}