{
  "type": "Feature",
  "properties": {
    "addr:full":"3302 Pulaski Hwy Edgewood MD 21040",
    "addr:housenumber":"3302",
    "addr:postcode":"21040",
    "addr:street":"Pulaski Hwy",
    "iso:country":"US",
    "sg:address":"3302 Pulaski Hwy",
    "sg:city":"Edgewood",
    "sg:classifiers":[
        {
            "category":"Retail",
            "subcategory":"Auto Repair",
            "type":"Services"
        }
    ],
    "sg:phone":"+1 410 676 1441",
    "sg:postcode":"21040",
    "sg:province":"MD",
    "sg:tags":[
        "repairing",
        "automobile",
        "radiator"
    ],
    "wof:name":"Mc New Repair",
    "wof:placetype":"venue"
},
  "geometry": {"coordinates":[-76.266986,39.455149],"type":"Point"}
}