{
  "type": "Feature",
  "properties": {
    "addr:full":"1290 W Pulaski Hwy Elkton MD 21921",
    "addr:housenumber":"1290",
    "addr:postcode":"21921",
    "addr:street":"W Pulaski Hwy",
    "iso:country":"US",
    "sg:address":"1290 W Pulaski Hwy",
    "sg:city":"Elkton",
    "sg:classifiers":[
        {
            "category":"Professional",
            "type":"Services"
        }
    ],
    "sg:phone":"+1 410 398 6349",
    "sg:postcode":"21921",
    "sg:province":"MD",
    "sg:tags":[
        "establishment"
    ],
    "wof:name":"Sunny Acres",
    "wof:placetype":"venue"
},
  "geometry": {"coordinates":[-75.89924999999999,39.610137],"type":"Point"}
}