{
  "type": "Feature",
  "properties": {
    "iso:country":"US",
    "sg:address":"928 Ellsworth Dr",
    "sg:city":"Silver Spring",
    "sg:classifiers":[
        {
            "category":"Restaurant",
            "type":"Food & Drink"
        }
    ],
    "sg:menulink":"http://www.allmenus.com/md/silver-spring/24861-redrock-canyon-grill/menu/",
    "sg:phone":"+1 301 589 1330",
    "sg:postcode":"20910",
    "sg:province":"MD",
    "sg:tags":[
        "american",
        "steakhouse"
    ],
    "wof:name":"Redrock Canyon Grill",
    "wof:placetype":"venue"
},
  "geometry": {"coordinates":[-77.026191,38.996176],"type":"Point"}
}