{
  "type": "Feature",
  "properties": {
    "addr:full":"1011 Kevin Rd Baltimore MD 21229",
    "addr:housenumber":"1011",
    "addr:postcode":"21229",
    "addr:street":"Kevin Rd",
    "iso:country":"US",
    "sg:address":"1011 Kevin Rd",
    "sg:city":"Baltimore",
    "sg:classifiers":[
        {
            "category":"Personal",
            "type":"Services"
        },
        {
            "category":"Professional",
            "subcategory":"Art Services",
            "type":"Services"
        }
    ],
    "sg:phone":"+1 443 858 9823",
    "sg:postcode":"21229",
    "sg:province":"MD",
    "sg:tags":[
        "photography",
        "videography",
        "wedding"
    ],
    "wof:name":"Latonia Sanders Photography",
    "wof:placetype":"venue"
},
  "geometry": {"coordinates":[-76.68899999999999,39.297682],"type":"Point"}
}