{
  "type": "Feature",
  "properties": {
    "addr:full":"2 Candlestick Dr Lutherville MD 21093",
    "addr:housenumber":"2",
    "addr:postcode":"21093",
    "addr:street":"Candlestick Dr",
    "iso:country":"US",
    "sg:address":"2 Candlestick Dr",
    "sg:city":"Lutherville",
    "sg:classifiers":[
        {
            "category":"Professional",
            "subcategory":"Computer Services",
            "type":"Services"
        },
        {
            "category":"Shopping",
            "subcategory":"Computers & Home Electronics",
            "type":"Retail Goods"
        }
    ],
    "sg:phone":"+1 410 337 5015",
    "sg:postcode":"21093",
    "sg:province":"MD",
    "sg:tags":[
        "prepackaged",
        "software"
    ],
    "wof:name":"9 Dots Inc",
    "wof:placetype":"venue"
},
  "geometry": {"coordinates":[-76.693871,39.43375],"type":"Point"}
}