{
  "type": "Feature",
  "properties": {
    "iso:country":"US",
    "sg:address":"11334 Frances Dr",
    "sg:city":"Beltsville",
    "sg:classifiers":[
        {
            "category":"Professional",
            "subcategory":"Detective & Security Services",
            "type":"Services"
        }
    ],
    "sg:phone":"+1 301 931 2525",
    "sg:postcode":"20705",
    "sg:province":"MD",
    "sg:tags":[
        "investigator"
    ],
    "wof:name":"Laurel Investigative Svc",
    "wof:placetype":"venue"
},
  "geometry": {"coordinates":[-76.92206299999999,39.043676],"type":"Point"}
}