{
  "type": "Feature",
  "properties": {
    "iso:country":"US",
    "sg:address":"11408 Fairoak Dr",
    "sg:city":"Silver Spring",
    "sg:classifiers":[
        {
            "category":"Health Services",
            "subcategory":"Health Practitioner",
            "type":"Services"
        }
    ],
    "sg:phone":"+1 301 593 7744",
    "sg:postcode":"20902",
    "sg:province":"MD",
    "sg:tags":[
        "psychotherapist"
    ],
    "wof:name":"Adult Children Of Alcoholics",
    "wof:placetype":"venue"
},
  "geometry": {"coordinates":[-77.01326299999999,39.043166],"type":"Point"}
}