{
  "type": "Feature",
  "properties": {
    "iso:country":"US",
    "sg:address":"5410 Edson Ln",
    "sg:city":"Rockville",
    "sg:classifiers":[
        {
            "category":"Real Estate",
            "subcategory":"Real Estate Services",
            "type":"Services"
        }
    ],
    "sg:phone":"+1 301 816 1511",
    "sg:postcode":"20852",
    "sg:province":"MD",
    "sg:tags":[
        "rental"
    ],
    "wof:name":"Dennis L Berman",
    "wof:placetype":"venue"
},
  "geometry": {"coordinates":[-77.109962,39.040315],"type":"Point"}
}