{
  "type": "Feature",
  "properties": {
    "addr:full":"3403 Ripple Rd Windsor Mill MD 21244",
    "addr:housenumber":"3403",
    "addr:postcode":"21244",
    "addr:street":"Ripple Rd",
    "iso:country":"US",
    "sg:address":"3403 Ripple Rd",
    "sg:city":"Windsor Mill",
    "sg:classifiers":[
        {
            "category":"Retail",
            "subcategory":"Laundry & Dry Cleaning",
            "type":"Services"
        }
    ],
    "sg:phone":"+1 410 655 8075",
    "sg:postcode":"21244",
    "sg:province":"MD",
    "sg:tags":[
        "cleaners",
        "rug",
        "carpet"
    ],
    "wof:name":"Set The Standard Cleaning Svc",
    "wof:placetype":"venue"
},
  "geometry": {"coordinates":[-76.749458,39.34864],"type":"Point"}
}