{
  "type": "Feature",
  "properties": {
    "addr:full":"114 Wyndcrest Ave Catonsville MD 21228",
    "addr:housenumber":"114",
    "addr:postcode":"21228",
    "addr:street":"Wyndcrest Ave",
    "iso:country":"US",
    "sg:address":"114 Wyndcrest Ave",
    "sg:city":"Catonsville",
    "sg:classifiers":[
        {
            "category":"Professional",
            "subcategory":"Business Services",
            "type":"Services"
        },
        {
            "category":"Professional",
            "subcategory":"Printing & Photocopies",
            "type":"Services"
        }
    ],
    "sg:phone":"+1 410 744 7103",
    "sg:postcode":"21228",
    "sg:province":"MD",
    "sg:tags":[
        "system",
        "form",
        "printers-business"
    ],
    "wof:name":"Pdf Smartforms, Inc",
    "wof:placetype":"venue"
},
  "geometry": {"coordinates":[-76.745598,39.273441],"type":"Point"}
}