{
  "type": "Feature",
  "properties": {
    "addr:full":"1437 W Hamburg St Baltimore MD 21230",
    "addr:housenumber":"1437",
    "addr:postcode":"21230",
    "addr:street":"W Hamburg St",
    "iso:country":"US",
    "sg:address":"1437 W Hamburg St",
    "sg:city":"Baltimore",
    "sg:classifiers":[
        {
            "category":"Utilities",
            "subcategory":"Refuse",
            "type":"Services"
        },
        {
            "category":"Utilities",
            "subcategory":"Recycling",
            "type":"Services"
        },
        {
            "category":"Building & Trades",
            "subcategory":"Landfill",
            "type":"Services"
        }
    ],
    "sg:phone":"+1 877 247 7815",
    "sg:postcode":"21230",
    "sg:province":"MD",
    "sg:tags":[
        "garbage",
        "disposal",
        "collection",
        "equipment",
        "waste"
    ],
    "sg:website":"http://baltimore.citysearch.com/profile/external/603896922/baltimore_md/waste_management_baltimore_processing_center.html?publisher=yellowpages&reference_id=1&placement=ypwebsitemip",
    "wof:name":"Waste Management Baltimore Processing Center",
    "wof:placetype":"venue"
},
  "geometry": {"coordinates":[-76.63419399999999,39.276878],"type":"Point"}
}