{
  "type": "Feature",
  "properties": {
    "iso:country":"US",
    "sg:address":"3126 Greenmount Ave",
    "sg:city":"Baltimore",
    "sg:classifiers":[
        {
            "category":"Bars & Pubs",
            "type":"Food & Drink"
        }
    ],
    "sg:phone":"+1 410 366 6536",
    "sg:postcode":"21218",
    "sg:province":"MD",
    "wof:name":"Melba's Place",
    "wof:placetype":"venue"
},
  "geometry": {"coordinates":[-76.609415,39.326282],"type":"Point"}
}