{
  "type": "Feature",
  "properties": {
    "addr:full":"4214 Manorview Rd Glen Arm MD 21057",
    "addr:housenumber":"4214",
    "addr:postcode":"21057",
    "addr:street":"Manorview Rd",
    "iso:country":"US",
    "sg:address":"4214 Manorview Rd",
    "sg:city":"Glen Arm",
    "sg:classifiers":[
        {
            "category":"Professional",
            "subcategory":"Business Services",
            "type":"Services"
        }
    ],
    "sg:phone":"+1 410 592 8068",
    "sg:postcode":"21057",
    "sg:province":"MD",
    "sg:tags":[
        "recording",
        "studio"
    ],
    "wof:name":"Sound Museum",
    "wof:placetype":"venue"
},
  "geometry": {"coordinates":[-76.527294,39.460899],"type":"Point"}
}