{
  "type": "Feature",
  "properties": {
    "addr:full":"10705 York Rd Cockeysville MD 21030",
    "addr:housenumber":"10705",
    "addr:postcode":"21030",
    "addr:street":"York Rd",
    "iso:country":"US",
    "sg:address":"10705 York Rd",
    "sg:city":"Cockeysville",
    "sg:classifiers":[
        {
            "category":"Professional",
            "subcategory":"Computer Services",
            "type":"Services"
        }
    ],
    "sg:phone":"+1 410 628 1132",
    "sg:postcode":"21030",
    "sg:province":"MD",
    "sg:tags":[
        "repair"
    ],
    "wof:name":"Computer Pro's",
    "wof:placetype":"venue"
},
  "geometry": {"coordinates":[-76.642878,39.47939],"type":"Point"}
}