{
  "type": "Feature",
  "properties": {
    "addr:full":"1150 Professional Ct Hagerstown MD 21740",
    "addr:housenumber":"1150",
    "addr:postcode":"21740",
    "addr:street":"Professional Ct",
    "iso:country":"US",
    "sg:address":"1150 Professional Ct",
    "sg:city":"Hagerstown",
    "sg:classifiers":[
        {
            "category":"Health Services",
            "subcategory":"Doctor",
            "type":"Services"
        }
    ],
    "sg:phone":"+1 301 797 4343",
    "sg:postcode":"21740",
    "sg:province":"MD",
    "sg:tags":[
        "physician",
        "surgeon"
    ],
    "wof:name":"Surgical Associates",
    "wof:placetype":"venue"
},
  "geometry": {"coordinates":[-77.692604,39.636396],"type":"Point"}
}