{
  "type": "Feature",
  "properties": {
    "addr:full":"1205 Bedford St Cumberland MD 21502",
    "addr:housenumber":"1205",
    "addr:postcode":"21502",
    "addr:street":"Bedford St",
    "iso:country":"US",
    "sg:address":"1205 Bedford St",
    "sg:city":"Cumberland",
    "sg:classifiers":[
        {
            "category":"Wholesale",
            "subcategory":"Groceries",
            "type":"Manufacturing & Wholesale Goods"
        }
    ],
    "sg:phone":"+1 301 777 5287",
    "sg:postcode":"21502",
    "sg:province":"MD",
    "wof:name":"Pepperrdge Farms Cookies",
    "wof:placetype":"venue"
},
  "geometry": {"coordinates":[-78.75080699999999,39.669797],"type":"Point"}
}