{
  "type": "Feature",
  "properties": {
    "addr:full":"5471 Wisconsin Ave Chevy Chase MD 20815",
    "addr:housenumber":"5471",
    "addr:postcode":"20815",
    "addr:street":"Wisconsin Ave",
    "iso:country":"US",
    "sg:address":"5471 Wisconsin Ave",
    "sg:city":"Chevy Chase",
    "sg:classifiers":[
        {
            "category":"Food & Beverages",
            "subcategory":"Candy",
            "type":"Retail Goods"
        },
        {
            "category":"Restaurant",
            "type":"Food & Drink"
        }
    ],
    "sg:phone":"+1 301 986 4818",
    "sg:postcode":"20815",
    "sg:province":"MD",
    "sg:tags":[
        "dessert",
        "breakfast",
        "brunch",
        "italian"
    ],
    "sg:website":"www.mcafebar.com/about-mcafe.htm",
    "wof:name":"M Cafe Bar",
    "wof:placetype":"venue"
},
  "geometry": {"coordinates":[-77.086817,38.963165],"type":"Point"}
}