{
  "type": "Feature",
  "properties": {
    "addr:full":"3 Maple Ave Walkersville MD 21793",
    "addr:housenumber":"3",
    "addr:postcode":"21793",
    "addr:street":"Maple Ave",
    "iso:country":"US",
    "sg:address":"3 Maple Ave",
    "sg:city":"Walkersville",
    "sg:classifiers":[
        {
            "category":"Personal",
            "subcategory":"Beauty Salon",
            "type":"Services"
        }
    ],
    "sg:phone":"+1 301 845 2100",
    "sg:postcode":"21793",
    "sg:province":"MD",
    "wof:name":"Gloria's Beauty Shop",
    "wof:placetype":"venue"
},
  "geometry": {"coordinates":[-77.352823,39.482664],"type":"Point"}
}