{
  "type": "Feature",
  "properties": {
    "addr:full":"4 Deauville Ct Pikesville MD 21208",
    "addr:postcode":"21208",
    "addr:street":"Deauville Ct",
    "iso:country":"US",
    "sg:address":"4 Deauville Ct",
    "sg:city":"Pikesville",
    "sg:classifiers":[
        {
            "category":"Real Estate",
            "subcategory":"Real Estate Operator",
            "type":"Services"
        }
    ],
    "sg:phone":"+1 410 484 5700",
    "sg:postcode":"21208",
    "sg:province":"MD",
    "sg:tags":[
        "apartment"
    ],
    "wof:name":"Brittany Apartments",
    "wof:placetype":"venue"
},
  "geometry": {"coordinates":[-76.74237100000001,39.374282],"type":"Point"}
}