{
  "type": "Feature",
  "properties": {
    "addr:full":"8855 Annapolis Rd Lanham MD 20706",
    "addr:housenumber":"8855",
    "addr:postcode":"20706",
    "addr:street":"Annapolis Rd",
    "iso:country":"US",
    "sg:address":"8855 Annapolis Rd",
    "sg:city":"Lanham",
    "sg:classifiers":[
        {
            "category":"Freight",
            "type":"Transportation"
        }
    ],
    "sg:phone":"+1 301 306 0003",
    "sg:postcode":"20706",
    "sg:province":"MD",
    "sg:tags":[
        "mover"
    ],
    "wof:name":"Midas Movers & Messanger Svc",
    "wof:placetype":"venue"
},
  "geometry": {"coordinates":[-76.86291799999999,38.961299],"type":"Point"}
}