{
  "type": "Feature",
  "properties": {
    "iso:country":"US",
    "sg:address":"15 Washington St",
    "sg:city":"Cambridge",
    "sg:classifiers":[
        {
            "category":"Real Estate",
            "subcategory":"Surveying",
            "type":"Services"
        }
    ],
    "sg:phone":"+1 410 476 9940",
    "sg:postcode":"21613",
    "sg:province":"MD",
    "sg:tags":[
        "surveyor"
    ],
    "wof:name":"Dave Milhollan Assoc Inc",
    "wof:placetype":"venue"
},
  "geometry": {"coordinates":[-76.067546,38.560514],"type":"Point"}
}