{
  "type": "Feature",
  "properties": {
    "addr:full":"617 Wheat Mill Ct E Millersville MD 21108",
    "addr:housenumber":"617",
    "addr:postcode":"21108",
    "addr:street":"Wheat Mill Ct E",
    "iso:country":"US",
    "sg:address":"617 Wheat Mill Ct E",
    "sg:city":"Millersville",
    "sg:classifiers":[
        {
            "category":"Retail",
            "subcategory":"Repair Shop",
            "type":"Services"
        }
    ],
    "sg:phone":"+1 410 987 5443",
    "sg:postcode":"21108",
    "sg:province":"MD",
    "sg:tags":[
        "welding"
    ],
    "wof:name":"Bruce L Walker",
    "wof:placetype":"venue"
},
  "geometry": {"coordinates":[-76.626819,39.112799],"type":"Point"}
}