{
  "type": "Feature",
  "properties": {
    "addr:full":"1908 Fox St Hyattsville MD 20783",
    "addr:housenumber":"1908",
    "addr:postcode":"20783",
    "addr:street":"Fox St",
    "iso:country":"US",
    "sg:address":"1908 Fox St",
    "sg:city":"Hyattsville",
    "sg:classifiers":[
        {
            "category":"Building & Trades",
            "subcategory":"Construction",
            "type":"Services"
        }
    ],
    "sg:phone":"+1 301 431 2003",
    "sg:postcode":"20783",
    "sg:province":"MD",
    "sg:tags":[
        "contractor"
    ],
    "wof:name":"Carlos Borromeo Carcamo",
    "wof:placetype":"venue"
},
  "geometry": {"coordinates":[-76.97470199999999,39.008491],"type":"Point"}
}