{
  "type": "Feature",
  "properties": {
    "iso:country":"US",
    "sg:address":"233 E Redwood St",
    "sg:city":"Baltimore",
    "sg:classifiers":[
        {
            "category":"Professional",
            "subcategory":"Lawyer & Legal Services",
            "type":"Services"
        }
    ],
    "sg:phone":"+1 410 576 4137",
    "sg:postcode":"21202",
    "sg:province":"MD",
    "wof:name":"Klein Susan",
    "wof:placetype":"venue"
},
  "geometry": {"coordinates":[-76.611802,39.288849],"type":"Point"}
}