{
  "type": "Feature",
  "properties": {
    "iso:country":"US",
    "sg:address":"4725 Dorsey Hall Dr",
    "sg:city":"Ellicott City",
    "sg:classifiers":[
        {
            "category":"Professional",
            "subcategory":"Computer Services",
            "type":"Services"
        }
    ],
    "sg:phone":"+1 410 880 0171",
    "sg:postcode":"21042",
    "sg:province":"MD",
    "sg:tags":[
        "consultant"
    ],
    "wof:name":"Riverside Computer Consultants",
    "wof:placetype":"venue"
},
  "geometry": {"coordinates":[-76.84313400000001,39.244385],"type":"Point"}
}