{
  "type": "Feature",
  "properties": {
    "addr:full":"7503 Greenway Center Dr Greenbelt MD 20770",
    "addr:housenumber":"7503",
    "addr:postcode":"20770",
    "addr:street":"Greenway Center Dr",
    "iso:country":"US",
    "sg:address":"7503 Greenway Center Dr",
    "sg:city":"Greenbelt",
    "sg:classifiers":[
        {
            "category":"Health Services",
            "subcategory":"Doctor",
            "type":"Services"
        }
    ],
    "sg:phone":"+1 301 446 3540",
    "sg:postcode":"20770",
    "sg:province":"MD",
    "sg:tags":[
        "physician",
        "surgeon"
    ],
    "wof:name":"Greenbelt Radiation Oncology",
    "wof:placetype":"venue"
},
  "geometry": {"coordinates":[-76.880707,38.991051],"type":"Point"}
}