{
  "type": "Feature",
  "properties": {
    "addr:full":"6644 Corina Ct Columbia MD 21044",
    "addr:housenumber":"6644",
    "addr:postcode":"21044",
    "addr:street":"Corina Ct",
    "iso:country":"US",
    "sg:address":"6644 Corina Ct",
    "sg:city":"Columbia",
    "sg:classifiers":[
        {
            "category":"Autos & Motor Vehicles",
            "subcategory":"Automobile Sales",
            "type":"Retail Goods"
        }
    ],
    "sg:phone":"+1 410 531 5437",
    "sg:postcode":"21044",
    "sg:province":"MD",
    "sg:tags":[
        "new",
        "car"
    ],
    "wof:name":"Mike Calvert",
    "wof:placetype":"venue"
},
  "geometry": {"coordinates":[-76.888048,39.190922],"type":"Point"}
}