{
  "type": "Feature",
  "properties": {
    "iso:country":"US",
    "sg:address":"99 Cathedral St",
    "sg:city":"Annapolis",
    "sg:classifiers":[
        {
            "category":"Building & Trades",
            "subcategory":"Landscaping Services",
            "type":"Services"
        }
    ],
    "sg:phone":"+1 410 216 9642",
    "sg:postcode":"21401",
    "sg:province":"MD",
    "sg:tags":[
        "designer",
        "landscape"
    ],
    "wof:name":"Emerald Gardens-English Formal",
    "wof:placetype":"venue"
},
  "geometry": {"coordinates":[-76.495802,38.978187],"type":"Point"}
}