{
  "type": "Feature",
  "properties": {
    "addr:full":"6335 Sykesville Rd Sykesville MD 21784",
    "addr:housenumber":"6335",
    "addr:postcode":"21784",
    "addr:street":"Sykesville Rd",
    "iso:country":"US",
    "sg:address":"6335 Sykesville Rd",
    "sg:city":"Sykesville",
    "sg:classifiers":[
        {
            "category":"Retail",
            "subcategory":"Repair Shop",
            "type":"Services"
        }
    ],
    "sg:phone":"+1 410 781 6737",
    "sg:postcode":"21784",
    "sg:province":"MD",
    "sg:tags":[
        "electrical"
    ],
    "wof:name":"Gilbert L Rubin",
    "wof:placetype":"venue"
},
  "geometry": {"coordinates":[-76.951797,39.401002],"type":"Point"}
}