{
  "type": "Feature",
  "properties": {
    "addr:full":"15830 Redland Rd Rockville MD 20855",
    "addr:housenumber":"15830",
    "addr:postcode":"20855",
    "addr:street":"Redland Rd",
    "iso:country":"US",
    "sg:address":"15830 Redland Rd",
    "sg:city":"Rockville",
    "sg:classifiers":[
        {
            "category":"Manufacturing",
            "subcategory":"Chemicals & Compounds",
            "type":"Manufacturing & Wholesale Goods"
        }
    ],
    "sg:phone":"+1 301 948 8100",
    "sg:postcode":"20855",
    "sg:province":"MD",
    "sg:tags":[
        "gas"
    ],
    "sg:website":"www.robertsoxygen.com",
    "wof:name":"Roberts Oxygen Co",
    "wof:placetype":"venue"
},
  "geometry": {"coordinates":[-77.157949,39.121767],"type":"Point"}
}