{
  "type": "Feature",
  "properties": {
    "iso:country":"US",
    "sg:address":"706 Great Bay Ave",
    "sg:city":"Annapolis",
    "sg:classifiers":[
        {
            "category":"Shopping",
            "subcategory":"Department Store",
            "type":"Retail Goods"
        }
    ],
    "sg:phone":"+1 410 268 0749",
    "sg:postcode":"21401",
    "sg:province":"MD",
    "wof:name":"Stores of Many",
    "wof:placetype":"venue"
},
  "geometry": {"coordinates":[-76.526625,38.968179],"type":"Point"}
}