{
  "type": "Feature",
  "properties": {
    "addr:full":"100 S Highland Ave Baltimore MD 21224",
    "addr:housenumber":"100",
    "addr:postcode":"21224",
    "addr:street":"S Highland Ave",
    "iso:country":"US",
    "sg:address":"100 S Highland Ave",
    "sg:city":"Baltimore",
    "sg:classifiers":[
        {
            "category":"Retail",
            "subcategory":"Repair Shop",
            "type":"Services"
        },
        {
            "category":"Building & Trades",
            "subcategory":"Construction",
            "type":"Services"
        }
    ],
    "sg:phone":"+1 410 675 6747",
    "sg:postcode":"21224",
    "sg:province":"MD",
    "sg:tags":[
        "system",
        "major",
        "refinishing",
        "appliance",
        "heating",
        "specialty",
        "contractor",
        "air conditioning"
    ],
    "wof:name":"Jonsco Air Conditioning & Htg",
    "wof:placetype":"venue"
},
  "geometry": {"coordinates":[-76.569328,39.291321],"type":"Point"}
}