{
  "type": "Feature",
  "properties": {
    "addr:full":"5111 Hampden Ln Bethesda MD 20814",
    "addr:housenumber":"5111",
    "addr:postcode":"20814",
    "addr:street":"Hampden Ln",
    "iso:country":"US",
    "sg:address":"5111 Hampden Ln",
    "sg:city":"Bethesda",
    "sg:classifiers":[
        {
            "category":"Professional",
            "subcategory":"Management & Consulting",
            "type":"Services"
        }
    ],
    "sg:phone":"+1 301 654 9731",
    "sg:postcode":"20814",
    "sg:province":"MD",
    "sg:tags":[
        "reporting",
        "analysis",
        "research"
    ],
    "wof:name":"Janice K Anderson",
    "wof:placetype":"venue"
},
  "geometry": {"coordinates":[-77.103031,38.983259],"type":"Point"}
}