{
  "type": "Feature",
  "properties": {
    "iso:country":"US",
    "sg:address":"1016 Lenton Ave",
    "sg:city":"Baltimore",
    "sg:classifiers":[
        {
            "category":"Health Services",
            "subcategory":"Doctor",
            "type":"Services"
        },
        {
            "category":"Health Services",
            "subcategory":"Hospital",
            "type":"Services"
        },
        {
            "category":"Professional",
            "subcategory":"Research",
            "type":"Services"
        }
    ],
    "sg:phone":"+1 410 323 7212",
    "sg:postcode":"21212",
    "sg:province":"MD",
    "sg:tags":[
        "nursing",
        "consultant",
        "medical",
        "practice",
        "analysis",
        "home",
        "market"
    ],
    "wof:name":"Two Gems Consulting Services",
    "wof:placetype":"venue"
},
  "geometry": {"coordinates":[-76.59943800000001,39.362698],"type":"Point"}
}