{
  "type": "Feature",
  "properties": {
    "iso:country":"US",
    "sg:address":"8405 Irvington Ave",
    "sg:city":"Bethesda",
    "sg:classifiers":[
        {
            "category":"Building & Trades",
            "subcategory":"Construction",
            "type":"Services"
        }
    ],
    "sg:phone":"+1 301 652 5244",
    "sg:postcode":"20817",
    "sg:province":"MD",
    "sg:tags":[
        "hanging",
        "contractor"
    ],
    "wof:name":"Spectrum Painting & Plastering",
    "wof:placetype":"venue"
},
  "geometry": {"coordinates":[-77.118301,38.994338],"type":"Point"}
}