{
  "type": "Feature",
  "properties": {
    "iso:country":"US",
    "sg:address":"10806 Reisterstown Rd",
    "sg:city":"Owings Mills",
    "sg:classifiers":[
        {
            "category":"Retail",
            "subcategory":"Laundry & Dry Cleaning",
            "type":"Services"
        }
    ],
    "sg:phone":"+1 410 356 2233",
    "sg:postcode":"21117",
    "sg:province":"MD",
    "sg:tags":[
        "cleaners",
        "rug",
        "carpet"
    ],
    "wof:name":"Scientific Carpet Care Inc",
    "wof:placetype":"venue"
},
  "geometry": {"coordinates":[-76.790057,39.427359],"type":"Point"}
}