{
  "type": "Feature",
  "properties": {
    "addr:full":"11400 Rockville Pike Ste 510 Rockville MD 20852",
    "addr:housenumber":"11400",
    "addr:postcode":"20852",
    "addr:street":"Rockville Pike Ste 510",
    "iso:country":"US",
    "sg:address":"11400 Rockville Pike Ste 510",
    "sg:city":"Rockville",
    "sg:classifiers":[
        {
            "category":"Health Services",
            "subcategory":"Dentist",
            "type":"Services"
        }
    ],
    "sg:phone":"+1 301 881 5500",
    "sg:postcode":"20852",
    "sg:province":"MD",
    "wof:name":"Austin Judith L DMD",
    "wof:placetype":"venue"
},
  "geometry": {"coordinates":[-77.120499,39.048901],"type":"Point"}
}