{
  "type": "Feature",
  "properties": {
    "addr:full":"7718 Belair Rd Nottingham MD 21236",
    "addr:housenumber":"7718",
    "addr:postcode":"21236",
    "addr:street":"Belair Rd",
    "iso:country":"US",
    "sg:address":"7718 Belair Rd",
    "sg:city":"Nottingham",
    "sg:classifiers":[
        {
            "category":"Shopping",
            "subcategory":"Bridal",
            "type":"Retail Goods"
        }
    ],
    "sg:phone":"+1 410 882 5050",
    "sg:postcode":"21236",
    "sg:province":"MD",
    "wof:name":"Francesca's Bridal Salon",
    "wof:placetype":"venue"
},
  "geometry": {"coordinates":[-76.5158,39.367802],"type":"Point"}
}