{
  "type": "Feature",
  "properties": {
    "addr:full":"13801 Eck Rd Hydes MD 21082",
    "addr:housenumber":"13801",
    "addr:postcode":"21082",
    "addr:street":"Eck Rd",
    "iso:country":"US",
    "sg:address":"13801 Eck Rd",
    "sg:city":"Hydes",
    "sg:classifiers":[
        {
            "category":"Professional",
            "subcategory":"Management & Consulting",
            "type":"Services"
        }
    ],
    "sg:phone":"+1 410 592 2060",
    "sg:postcode":"21082",
    "sg:province":"MD",
    "sg:tags":[
        "consultant"
    ],
    "sg:website":"http://www.siennapartners.com",
    "wof:name":"Sienna Partners",
    "wof:placetype":"venue"
},
  "geometry": {"coordinates":[-76.448125,39.502504],"type":"Point"}
}