{
  "type": "Feature",
  "properties": {
    "iso:country":"US",
    "sg:address":"1000 E Joppa Rd",
    "sg:city":"Towson",
    "sg:classifiers":[
        {
            "category":"Personal",
            "subcategory":"Beauty Salon",
            "type":"Services"
        }
    ],
    "sg:phone":"+1 410 828 5665",
    "sg:postcode":"21286",
    "sg:province":"MD",
    "wof:name":"Generations",
    "wof:placetype":"venue"
},
  "geometry": {"coordinates":[-76.580392,39.397248],"type":"Point"}
}