{
  "type": "Feature",
  "properties": {
    "addr:full":"4123 Bark Hill Rd Union Bridge MD 21791",
    "addr:housenumber":"4123",
    "addr:postcode":"21791",
    "addr:street":"Bark Hill Rd",
    "iso:country":"US",
    "sg:address":"4123 Bark Hill Rd",
    "sg:city":"Union Bridge",
    "sg:classifiers":[
        {
            "category":"Retail",
            "subcategory":"Repair Shop",
            "type":"Services"
        }
    ],
    "sg:phone":"+1 410 775 0583",
    "sg:postcode":"21791",
    "sg:province":"MD",
    "sg:tags":[
        "welding"
    ],
    "wof:name":"Stambaughs Welding",
    "wof:placetype":"venue"
},
  "geometry": {"coordinates":[-77.14371199999999,39.589795],"type":"Point"}
}