{
  "type": "Feature",
  "properties": {
    "iso:country":"US",
    "sg:address":"8640 Liberty Rd",
    "sg:city":"Randallstown",
    "sg:classifiers":[
        {
            "category":"Restaurant",
            "type":"Food & Drink"
        }
    ],
    "sg:phone":"+1 410 521 9150",
    "sg:postcode":"21133",
    "sg:province":"MD",
    "wof:name":"Suzie Baik",
    "wof:placetype":"venue"
},
  "geometry": {"coordinates":[-76.780731,39.362231],"type":"Point"}
}