{
  "type": "Feature",
  "properties": {
    "iso:country":"US",
    "sg:address":"6352 York Rd",
    "sg:city":"Baltimore",
    "sg:classifiers":[
        {
            "category":"Shopping",
            "type":"Retail Goods"
        }
    ],
    "sg:phone":"+1 410 377 4605",
    "sg:postcode":"21212",
    "sg:province":"MD",
    "sg:tags":[
        "picture",
        "frame"
    ],
    "wof:name":"Moon Gallery",
    "wof:placetype":"venue"
},
  "geometry": {"coordinates":[-76.60983899999999,39.372313],"type":"Point"}
}