{
  "type": "Feature",
  "properties": {
    "addr:full":"15890 Oakland Rd Henderson MD 21640",
    "addr:housenumber":"15890",
    "addr:postcode":"21640",
    "addr:street":"Oakland Rd",
    "iso:country":"US",
    "sg:address":"15890 Oakland Rd",
    "sg:city":"Henderson",
    "sg:classifiers":[
        {
            "category":"Building & Trades",
            "subcategory":"Construction",
            "type":"Services"
        }
    ],
    "sg:phone":"+1 410 482 7525",
    "sg:postcode":"21640",
    "sg:province":"MD",
    "sg:tags":[
        "concrete",
        "contractor"
    ],
    "wof:name":"C & D Concrete Co",
    "wof:placetype":"venue"
},
  "geometry": {"coordinates":[-75.86652100000001,39.042968],"type":"Point"}
}