{
  "type": "Feature",
  "properties": {
    "iso:country":"US",
    "sg:address":"2002 Presstman St",
    "sg:city":"Baltimore",
    "sg:classifiers":[
        {
            "category":"Building & Trades",
            "subcategory":"Construction",
            "type":"Services"
        }
    ],
    "sg:phone":"+1 410 383 0754",
    "sg:postcode":"21217",
    "sg:province":"MD",
    "sg:tags":[
        "contractor"
    ],
    "wof:name":"Green Silver L",
    "wof:placetype":"venue"
},
  "geometry": {"coordinates":[-76.649946,39.305234],"type":"Point"}
}