{
  "type": "Feature",
  "properties": {
    "iso:country":"US",
    "sg:address":"2326 Belair Rd",
    "sg:city":"Baltimore",
    "sg:classifiers":[
        {
            "category":"Real Estate",
            "subcategory":"Real Estate Agent",
            "type":"Services"
        }
    ],
    "sg:phone":"+1 410 276 9500",
    "sg:postcode":"21213",
    "sg:province":"MD",
    "wof:name":"Mark A Burnham Realty",
    "wof:placetype":"venue"
},
  "geometry": {"coordinates":[-76.576016,39.319694],"type":"Point"}
}