{
  "type": "Feature",
  "properties": {
    "iso:country":"US",
    "sg:address":"11350 McCormick Rd",
    "sg:city":"Hunt Valley",
    "sg:classifiers":[
        {
            "category":"Banks & Credit Unions",
            "subcategory":"Bank",
            "type":"Services"
        },
        {
            "category":"Banks & Credit Unions",
            "subcategory":"Financial Services",
            "type":"Services"
        }
    ],
    "sg:phone":"+1 410 785 2200",
    "sg:postcode":"21031",
    "sg:province":"MD",
    "sg:tags":[
        "broker",
        "mortgage"
    ],
    "wof:name":"Eastern Savings Bank Fsb",
    "wof:placetype":"venue"
},
  "geometry": {"coordinates":[-76.658798,39.493599],"type":"Point"}
}