{
  "type": "Feature",
  "properties": {
    "iso:country":"US",
    "sg:address":"78 Bureau Dr",
    "sg:city":"Gaithersburg",
    "sg:classifiers":[
        {
            "category":"Banks & Credit Unions",
            "subcategory":"Bank",
            "type":"Services"
        }
    ],
    "sg:phone":"+1 301 998 8550",
    "sg:postcode":"20878",
    "sg:province":"MD",
    "wof:name":"Sun Trust Bank",
    "wof:placetype":"venue"
},
  "geometry": {"coordinates":[-77.217252,39.143095],"type":"Point"}
}