{
  "type": "Feature",
  "properties": {
    "addr:full":"310 Gorsuch Rd Westminster MD 21157",
    "addr:housenumber":"310",
    "addr:postcode":"21157",
    "addr:street":"Gorsuch Rd",
    "iso:country":"US",
    "sg:address":"310 Gorsuch Rd",
    "sg:city":"Westminster",
    "sg:classifiers":[
        {
            "category":"Organizations",
            "subcategory":"Religious Organization",
            "type":"Services"
        }
    ],
    "sg:phone":"+1 410 848 3364",
    "sg:postcode":"21157",
    "sg:province":"MD",
    "sg:tags":[
        "church"
    ],
    "wof:name":"Westminster Bible Church",
    "wof:placetype":"venue"
},
  "geometry": {"coordinates":[-76.980864,39.568397],"type":"Point"}
}