{
  "type": "Feature",
  "properties": {
    "addr:full":"600 Baltimore Ave Ste 301 Towson MD 21204",
    "addr:housenumber":"600",
    "addr:postcode":"21204",
    "addr:street":"Baltimore Ave Ste 301",
    "iso:country":"US",
    "sg:address":"600 Baltimore Ave Ste 301",
    "sg:city":"Towson",
    "sg:classifiers":[
        {
            "category":"Health Services",
            "subcategory":"Hospital",
            "type":"Services"
        },
        {
            "category":"Community Center",
            "type":"Public Place"
        },
        {
            "category":"Health Services",
            "subcategory":"Clinic",
            "type":"Services"
        }
    ],
    "sg:phone":"+1 410 332 0736",
    "sg:postcode":"21204",
    "sg:province":"MD",
    "sg:tags":[
        "medical",
        "sleep",
        "treatment",
        "disorders-information"
    ],
    "wof:name":"Maryland Podiatric Medical Association",
    "wof:placetype":"venue"
},
  "geometry": {"coordinates":[-76.606956,39.402039],"type":"Point"}
}