{
  "type": "Feature",
  "properties": {
    "iso:country":"US",
    "sg:address":"Reisterstown Village Shopping Center 38 Main St",
    "sg:city":"Reisterstown",
    "sg:classifiers":[
        {
            "category":"Restaurant",
            "type":"Food & Drink"
        },
        {
            "category":"Food & Beverages",
            "subcategory":"Bakery",
            "type":"Retail Goods"
        }
    ],
    "sg:phone":"+1 410 833 7660",
    "sg:postcode":"21136",
    "sg:province":"MD",
    "sg:tags":[
        "sandwich",
        "pizza"
    ],
    "wof:name":"Village Pizza",
    "wof:placetype":"venue"
},
  "geometry": {"coordinates":[-76.82957399999999,39.468362],"type":"Point"}
}