{
  "type": "Feature",
  "properties": {
    "iso:country":"US",
    "sg:address":"1629 Druid Hill Ave",
    "sg:city":"Baltimore",
    "sg:classifiers":[
        {
            "category":"Organizations",
            "subcategory":"Political Organization",
            "type":"Services"
        }
    ],
    "sg:phone":"+1 410 752 6653",
    "sg:postcode":"21217",
    "sg:province":"MD",
    "wof:name":"John Douglas",
    "wof:placetype":"venue"
},
  "geometry": {"coordinates":[-76.632141,39.305012],"type":"Point"}
}