{
  "type": "Feature",
  "properties": {
    "iso:country":"US",
    "sg:address":"930 N East St #1",
    "sg:city":"Frederick",
    "sg:classifiers":[
        {
            "category":"Insurance",
            "subcategory":"Insurance Agent",
            "type":"Services"
        },
        {
            "category":"Insurance",
            "subcategory":"Hazard Insurance",
            "type":"Services"
        }
    ],
    "sg:phone":"+1 301 663 1328",
    "sg:postcode":"21701",
    "sg:province":"MD",
    "sg:tags":[
        "auto",
        "recreational",
        "motorcycle",
        "vehicle",
        "marine",
        "boat"
    ],
    "sg:website":"http://www.keyinsurancegroup.com",
    "wof:name":"Key Insurance Group, LLC",
    "wof:placetype":"venue"
},
  "geometry": {"coordinates":[-77.40339,39.426023],"type":"Point"}
}