{
  "type": "Feature",
  "properties": {
    "addr:full":"319 Bloomingdale Ave Federalsburg MD 21632",
    "addr:housenumber":"319",
    "addr:postcode":"21632",
    "addr:street":"Bloomingdale Ave",
    "iso:country":"US",
    "sg:address":"319 Bloomingdale Ave",
    "sg:city":"Federalsburg",
    "sg:classifiers":[
        {
            "category":"Insurance",
            "subcategory":"Insurance Agent",
            "type":"Services"
        }
    ],
    "sg:phone":"+1 410 754 9945",
    "sg:postcode":"21632",
    "sg:province":"MD",
    "wof:name":"Frank M Adams Insurance",
    "wof:placetype":"venue"
},
  "geometry": {"coordinates":[-75.783631,38.697823],"type":"Point"}
}