{
  "type": "Feature",
  "properties": {
    "addr:full":"1612 Brightseat Rd Hyattsville MD 20785",
    "addr:housenumber":"1612",
    "addr:postcode":"20785",
    "addr:street":"Brightseat Rd",
    "iso:country":"US",
    "sg:address":"1612 Brightseat Rd",
    "sg:city":"Hyattsville",
    "sg:classifiers":[
        {
            "category":"Professional",
            "subcategory":"Art Services",
            "type":"Services"
        }
    ],
    "sg:phone":"+1 301 484 1633",
    "sg:postcode":"20785",
    "sg:province":"MD",
    "sg:tags":[
        "commercial",
        "design"
    ],
    "wof:name":"Dlash Graphic Design",
    "wof:placetype":"venue"
},
  "geometry": {"coordinates":[-76.85593,38.915666],"type":"Point"}
}