{
  "type": "Feature",
  "properties": {
    "addr:full":"7805 Parston Dr Forestville MD 20747",
    "addr:housenumber":"7805",
    "addr:postcode":"20747",
    "addr:street":"Parston Dr",
    "iso:country":"US",
    "sg:address":"7805 Parston Dr",
    "sg:city":"Forestville",
    "sg:classifiers":[
        {
            "category":"Building & Trades",
            "subcategory":"Cleaning & Sanitation",
            "type":"Services"
        }
    ],
    "sg:phone":"+1 301 735 3586",
    "sg:postcode":"20747",
    "sg:province":"MD",
    "sg:tags":[
        "janitor"
    ],
    "wof:name":"K 7 Cleaners",
    "wof:placetype":"venue"
},
  "geometry": {"coordinates":[-76.870908,38.846657],"type":"Point"}
}