{
  "type": "Feature",
  "properties": {
    "addr:full":"110 Carville Ct Stevensville MD 21666",
    "addr:housenumber":"110",
    "addr:postcode":"21666",
    "addr:street":"Carville Ct",
    "iso:country":"US",
    "sg:address":"110 Carville Ct",
    "sg:city":"Stevensville",
    "sg:classifiers":[
        {
            "category":"Organizations",
            "subcategory":"Religious Organization",
            "type":"Services"
        }
    ],
    "sg:phone":"+1 410 643 1931",
    "sg:postcode":"21666",
    "sg:province":"MD",
    "wof:name":"St Michaels Conference Inc",
    "wof:placetype":"venue"
},
  "geometry": {"coordinates":[-76.35956400000001,38.862174],"type":"Point"}
}