{
  "type": "Feature",
  "properties": {
    "addr:full":"18554 Office Park Dr Gaithersburg MD 20886",
    "addr:postcode":"20886",
    "addr:street":"Park Dr",
    "iso:country":"US",
    "sg:address":"18554 Office Park Dr",
    "sg:city":"Gaithersburg",
    "sg:classifiers":[
        {
            "category":"Professional",
            "subcategory":"Credit Reporting & Collection",
            "type":"Services"
        }
    ],
    "sg:phone":"+1 301 921 9700",
    "sg:postcode":"20886",
    "sg:province":"MD",
    "sg:tags":[
        "agency"
    ],
    "wof:name":"JRM Associates Inc",
    "wof:placetype":"venue"
},
  "geometry": {"coordinates":[-77.203419,39.16199],"type":"Point"}
}