{
  "type": "Feature",
  "properties": {
    "addr:full":"11433 Belair Rd Kingsville MD 21087",
    "addr:housenumber":"11433",
    "addr:postcode":"21087",
    "addr:street":"Belair Rd",
    "iso:country":"US",
    "sg:address":"11433 Belair Rd",
    "sg:city":"Kingsville",
    "sg:classifiers":[
        {
            "category":"Building & Trades",
            "subcategory":"Plumbing",
            "type":"Services"
        }
    ],
    "sg:phone":"+1 410 529 3234",
    "sg:postcode":"21087",
    "sg:province":"MD",
    "sg:tags":[
        "conditioning",
        "air",
        "system",
        "contractor"
    ],
    "wof:name":"Olympic Heating & Air Cond Inc",
    "wof:placetype":"venue"
},
  "geometry": {"coordinates":[-76.430249,39.436106],"type":"Point"}
}