{
  "type": "Feature",
  "properties": {
    "iso:country":"US",
    "sg:address":"418 Eastern Blvd 2",
    "sg:city":"Essex",
    "sg:classifiers":[
        {
            "category":"Building & Trades",
            "subcategory":"Construction",
            "type":"Services"
        }
    ],
    "sg:phone":"+1 410 602 6474",
    "sg:postcode":"21221",
    "sg:province":"MD",
    "sg:tags":[
        "waterproofing",
        "contractor"
    ],
    "wof:name":"Anchor Waterproofing",
    "wof:placetype":"venue"
},
  "geometry": {"coordinates":[-76.478465,39.30734],"type":"Point"}
}