{
  "type": "Feature",
  "properties": {
    "iso:country":"US",
    "sg:address":"7760 Crescent Run Ct",
    "sg:city":"La Plata",
    "sg:classifiers":[
        {
            "category":"Manufacturing",
            "subcategory":"Printing",
            "type":"Manufacturing & Wholesale Goods"
        }
    ],
    "sg:phone":"+1 301 609 9699",
    "sg:postcode":"20646",
    "sg:province":"MD",
    "sg:tags":[
        "work"
    ],
    "wof:name":"Browns Press & Bindery Service",
    "wof:placetype":"venue"
},
  "geometry": {"coordinates":[-76.86440899999999,38.497504],"type":"Point"}
}