{
  "type": "Feature",
  "properties": {
    "addr:full":"27012 Anthony Mill Rd Denton MD 21629",
    "addr:housenumber":"27012",
    "addr:postcode":"21629",
    "addr:street":"Anthony Mill Rd",
    "iso:country":"US",
    "sg:address":"27012 Anthony Mill Rd",
    "sg:city":"Denton",
    "sg:classifiers":[
        {
            "category":"Insurance",
            "subcategory":"Insurance Agent",
            "type":"Services"
        },
        {
            "category":"Insurance",
            "subcategory":"Hazard Insurance",
            "type":"Services"
        }
    ],
    "sg:phone":"+1 410 479 1571",
    "sg:postcode":"21629",
    "sg:province":"MD",
    "sg:tags":[
        "fire",
        "property",
        "casualty"
    ],
    "wof:name":"Tuckahoe Products Limited Liability Company",
    "wof:placetype":"venue"
},
  "geometry": {"coordinates":[-75.768078,38.877075],"type":"Point"}
}