{
  "type": "Feature",
  "properties": {
    "addr:full":"35 E Frederick St Walkersville MD 21793",
    "addr:housenumber":"35",
    "addr:postcode":"21793",
    "addr:street":"E Frederick St",
    "iso:country":"US",
    "sg:address":"35 E Frederick St",
    "sg:city":"Walkersville",
    "sg:classifiers":[
        {
            "category":"Social Services",
            "subcategory":"Child Care",
            "type":"Services"
        }
    ],
    "sg:phone":"+1 301 845 4803",
    "sg:postcode":"21793",
    "sg:province":"MD",
    "wof:name":"Children's Center-Walkersville",
    "wof:placetype":"venue"
},
  "geometry": {"coordinates":[-77.347266,39.483428],"type":"Point"}
}