{
  "type": "Feature",
  "properties": {
    "iso:country":"US",
    "sg:address":"200 W Main St",
    "sg:city":"Salisbury",
    "sg:classifiers":[
        {
            "category":"Banks & Credit Unions",
            "subcategory":"Bank",
            "type":"Services"
        }
    ],
    "sg:phone":"+1 410 742 8699",
    "sg:postcode":"21801",
    "sg:province":"MD",
    "sg:tags":[
        "box",
        "safe",
        "deposit"
    ],
    "wof:name":"Maryland National Bank",
    "wof:placetype":"venue"
},
  "geometry": {"coordinates":[-75.601528,38.365362],"type":"Point"}
}