{
  "type": "Feature",
  "properties": {
    "addr:full":"428 Kent Narrows Way N Grasonville MD 21638",
    "addr:housenumber":"428",
    "addr:postcode":"21638",
    "addr:street":"Kent Narrows Way N",
    "iso:country":"US",
    "sg:address":"428 Kent Narrows Way N",
    "sg:city":"Grasonville",
    "sg:classifiers":[
        {
            "category":"Freight",
            "type":"Transportation"
        }
    ],
    "sg:phone":"+1 410 827 3937",
    "sg:postcode":"21638",
    "sg:province":"MD",
    "sg:tags":[
        "dock"
    ],
    "wof:name":"Red Eye's Dock Bar",
    "wof:placetype":"venue"
},
  "geometry": {"coordinates":[-76.243824,38.971135],"type":"Point"}
}