{
  "type": "Feature",
  "properties": {
    "addr:full":"4212 Jefferson St Hyattsville MD 20781",
    "addr:housenumber":"4212",
    "addr:postcode":"20781",
    "addr:street":"Jefferson St",
    "iso:country":"US",
    "sg:address":"4212 Jefferson St",
    "sg:city":"Hyattsville",
    "sg:classifiers":[
        {
            "category":"Wholesale",
            "subcategory":"Books, Periodicals, & Newspapers",
            "type":"Manufacturing & Wholesale Goods"
        }
    ],
    "sg:phone":"+1 301 927 1897",
    "sg:postcode":"20781",
    "sg:province":"MD",
    "sg:tags":[
        "publisher",
        "book"
    ],
    "wof:name":"Earth Home Publishing",
    "wof:placetype":"venue"
},
  "geometry": {"coordinates":[-76.944175,38.955041],"type":"Point"}
}