{
  "type": "Feature",
  "properties": {
    "iso:country":"US",
    "sg:address":"21 Goucher Woods Ct",
    "sg:city":"Baltimore",
    "sg:classifiers":[
        {
            "category":"Professional",
            "subcategory":"Management & Consulting",
            "type":"Services"
        }
    ],
    "sg:phone":"+1 410 296 1228",
    "sg:postcode":"21286",
    "sg:province":"MD",
    "sg:tags":[
        "consultant",
        "financial"
    ],
    "wof:name":"Pcg",
    "wof:placetype":"venue"
},
  "geometry": {"coordinates":[-76.586776,39.401618],"type":"Point"}
}