{
  "type": "Feature",
  "properties": {
    "iso:country":"US",
    "sg:address":"11449 Georgia Ave",
    "sg:city":"Silver Spring",
    "sg:classifiers":[
        {
            "category":"Shopping",
            "subcategory":"Florist",
            "type":"Retail Goods"
        }
    ],
    "sg:phone":"+1 301 933 5895",
    "sg:postcode":"20902",
    "sg:province":"MD",
    "sg:website":"www.thegalleryflowers.com",
    "wof:name":"Gallery Flowers & Gifts",
    "wof:placetype":"venue"
},
  "geometry": {"coordinates":[-77.051952,39.042772],"type":"Point"}
}