{
  "type": "Feature",
  "properties": {
    "addr:full":"3403 Stone Gate Boulevard Elkton MD 21921",
    "addr:housenumber":"3403",
    "addr:postcode":"21921",
    "addr:street":"Stone Gate Boulevard",
    "iso:country":"US",
    "sg:address":"3403 Stone Gate Boulevard",
    "sg:city":"Elkton",
    "sg:classifiers":[
        {
            "category":"Personal",
            "subcategory":"Beauty Salon",
            "type":"Services"
        }
    ],
    "sg:phone":"+1 443 406 7632",
    "sg:postcode":"21921",
    "sg:province":"MD",
    "sg:website":"http://www.youravon.com/sbognacki",
    "wof:name":"Avon Representative",
    "wof:placetype":"venue"
},
  "geometry": {"coordinates":[-75.79014599999999,39.648444],"type":"Point"}
}