{
  "type": "Feature",
  "properties": {
    "iso:country":"US",
    "sg:address":"1300 Jackson St",
    "sg:city":"Baltimore",
    "sg:classifiers":[
        {
            "category":"Shopping",
            "subcategory":"Used Merchandise",
            "type":"Retail Goods"
        }
    ],
    "sg:phone":"+1 410 659 9948",
    "sg:postcode":"21230",
    "sg:province":"MD",
    "sg:tags":[
        "antique"
    ],
    "sg:website":"www.richardsindlerantiques.com",
    "wof:name":"Richard Sindler Fine Arts",
    "wof:placetype":"venue"
},
  "geometry": {"coordinates":[-76.60539199999999,39.274606],"type":"Point"}
}