{
  "type": "Feature",
  "properties": {
    "addr:full":"3924 Glenhunt Rd Baltimore MD 21229",
    "addr:housenumber":"3924",
    "addr:postcode":"21229",
    "addr:street":"Glenhunt Rd",
    "iso:country":"US",
    "sg:address":"3924 Glenhunt Rd",
    "sg:city":"Baltimore",
    "sg:classifiers":[
        {
            "category":"Social Services",
            "subcategory":"Child Care",
            "type":"Services"
        }
    ],
    "sg:phone":"+1 410 233 4771",
    "sg:postcode":"21229",
    "sg:province":"MD",
    "sg:tags":[
        "day"
    ],
    "wof:name":"Golden Key Day Care",
    "wof:placetype":"venue"
},
  "geometry": {"coordinates":[-76.681731,39.300143],"type":"Point"}
}