{
  "type": "Feature",
  "properties": {
    "iso:country":"US",
    "sg:address":"9194 Red Branch Rd Ste F",
    "sg:city":"Columbia",
    "sg:classifiers":[
        {
            "category":"Personal",
            "subcategory":"Nail Salon",
            "type":"Services"
        }
    ],
    "sg:phone":"+1 410 997 2087",
    "sg:postcode":"21045",
    "sg:province":"MD",
    "wof:name":"Especially For You Inc by Velma",
    "wof:placetype":"venue"
},
  "geometry": {"coordinates":[-76.82710299999999,39.230499],"type":"Point"}
}