{
  "type": "Feature",
  "properties": {
    "addr:full":"17800 New Hampshire Ave Ashton MD 20861",
    "addr:housenumber":"17800",
    "addr:postcode":"20861",
    "addr:street":"New Hampshire Ave",
    "iso:country":"US",
    "sg:address":"17800 New Hampshire Ave",
    "sg:city":"Ashton",
    "sg:classifiers":[
        {
            "category":"Wholesale",
            "subcategory":"Stationery",
            "type":"Manufacturing & Wholesale Goods"
        }
    ],
    "sg:phone":"+1 301 774 4242",
    "sg:postcode":"20861",
    "sg:province":"MD",
    "sg:tags":[
        "card"
    ],
    "wof:name":"Cricket Book Shop",
    "wof:placetype":"venue"
},
  "geometry": {"coordinates":[-77.01129899999999,39.148102],"type":"Point"}
}