{
  "type": "Feature",
  "properties": {
    "iso:country":"US",
    "sg:address":"11986 Long Lake Dr",
    "sg:city":"Reisterstown",
    "sg:classifiers":[
        {
            "category":"Shopping",
            "subcategory":"Computers & Home Electronics",
            "type":"Retail Goods"
        }
    ],
    "sg:phone":"+1 410 526 0322",
    "sg:postcode":"21136",
    "sg:province":"MD",
    "sg:tags":[
        "software"
    ],
    "wof:name":"Elico Business Svc",
    "wof:placetype":"venue"
},
  "geometry": {"coordinates":[-76.79556,39.461739],"type":"Point"}
}