{
  "type": "Feature",
  "properties": {
    "addr:full":"8008 Liberty Rd Windsor Mill MD 21244",
    "addr:housenumber":"8008",
    "addr:postcode":"21244",
    "addr:street":"Liberty Rd",
    "iso:country":"US",
    "sg:address":"8008 Liberty Rd",
    "sg:city":"Windsor Mill",
    "sg:classifiers":[
        {
            "category":"Personal",
            "subcategory":"Beauty Salon",
            "type":"Services"
        }
    ],
    "sg:phone":"+1 410 521 3770",
    "sg:postcode":"21244",
    "sg:province":"MD",
    "wof:name":"Stacie's Hair Studio",
    "wof:placetype":"venue"
},
  "geometry": {"coordinates":[-76.754603,39.352518],"type":"Point"}
}