{
  "type": "Feature",
  "properties": {
    "iso:country":"US",
    "sg:address":"5624 Gregory Dr",
    "sg:city":"Lanham",
    "sg:classifiers":[
        {
            "category":"Building & Trades",
            "subcategory":"Electrical",
            "type":"Services"
        }
    ],
    "sg:phone":"+1 301 577 0764",
    "sg:postcode":"20706",
    "sg:province":"MD",
    "sg:tags":[
        "industrial",
        "electrician",
        "contractors-commercial",
        "electric"
    ],
    "wof:name":"Swope Electric",
    "wof:placetype":"venue"
},
  "geometry": {"coordinates":[-76.853897,38.962002],"type":"Point"}
}