{
  "type": "Feature",
  "properties": {
    "iso:country":"US",
    "sg:address":"8051 Mount Harmony Ln",
    "sg:city":"Owings",
    "sg:classifiers":[
        {
            "category":"Retail",
            "subcategory":"Auto Repair",
            "type":"Services"
        }
    ],
    "sg:phone":"+1 301 855 3119",
    "sg:postcode":"20736",
    "sg:province":"MD",
    "sg:tags":[
        "machine",
        "automobile",
        "shop"
    ],
    "wof:name":"Bullseye Machine Works Lc",
    "wof:placetype":"venue"
},
  "geometry": {"coordinates":[-76.60405,38.694802],"type":"Point"}
}