{
  "type": "Feature",
  "properties": {
    "iso:country":"US",
    "sg:address":"17823 Central Ave",
    "sg:city":"Upper Marlboro",
    "sg:classifiers":[
        {
            "category":"Wholesale",
            "subcategory":"Electrical",
            "type":"Manufacturing & Wholesale Goods"
        }
    ],
    "sg:phone":"+1 301 249 4380",
    "sg:postcode":"20774",
    "sg:province":"MD",
    "sg:tags":[
        "alarm",
        "burglar",
        "system"
    ],
    "wof:name":"Abbey Security Systems",
    "wof:placetype":"venue"
},
  "geometry": {"coordinates":[-76.707485,38.898434],"type":"Point"}
}