{
  "type": "Feature",
  "properties": {
    "iso:country":"US",
    "sg:address":"301 Light St",
    "sg:city":"Baltimore",
    "sg:classifiers":[
        {
            "category":"Shopping Center",
            "type":"Public Place"
        }
    ],
    "sg:phone":"+1 410 347 5757",
    "sg:postcode":"21202",
    "sg:province":"MD",
    "wof:name":"Gholan Kazemian",
    "wof:placetype":"venue"
},
  "geometry": {"coordinates":[-76.612934,39.284893],"type":"Point"}
}