{
  "type": "Feature",
  "properties": {
    "iso:country":"US",
    "sg:address":"2225 Defense Hwy",
    "sg:city":"Crofton",
    "sg:classifiers":[
        {
            "category":"Restaurant",
            "type":"Food & Drink"
        }
    ],
    "sg:phone":"+1 410 721 7800",
    "sg:postcode":"21114",
    "sg:province":"MD",
    "wof:name":"Crystal Hunan Restaurant",
    "wof:placetype":"venue"
},
  "geometry": {"coordinates":[-76.69822499999999,38.992],"type":"Point"}
}