{
  "type": "Feature",
  "properties": {
    "iso:country":"US",
    "sg:address":"122 Lafayette Ave",
    "sg:city":"Laurel",
    "sg:classifiers":[
        {
            "category":"Building & Trades",
            "subcategory":"Construction",
            "type":"Services"
        }
    ],
    "sg:phone":"+1 410 880 6130",
    "sg:postcode":"20707",
    "sg:province":"MD",
    "sg:tags":[
        "contractor"
    ],
    "sg:website":"www.svwinc.com",
    "wof:name":"Security Vault Works Inc",
    "wof:placetype":"venue"
},
  "geometry": {"coordinates":[-76.84139999999999,39.102402],"type":"Point"}
}