{
  "type": "Feature",
  "properties": {
    "iso:country":"US",
    "sg:address":"2 Malibu Ct",
    "sg:city":"Baltimore",
    "sg:classifiers":[
        {
            "category":"Communications",
            "subcategory":"Film & Video Production",
            "type":"Services"
        }
    ],
    "sg:phone":"+1 410 821 5848",
    "sg:postcode":"21204",
    "sg:province":"MD",
    "sg:tags":[
        "motion"
    ],
    "wof:name":"Little Gidding Ltd",
    "wof:placetype":"venue"
},
  "geometry": {"coordinates":[-76.635218,39.414432],"type":"Point"}
}