{
  "type": "Feature",
  "properties": {
    "iso:country":"US",
    "sg:address":"2772 Rutland Rd",
    "sg:city":"Davidsonville",
    "sg:classifiers":[
        {
            "category":"Health Services",
            "subcategory":"Doctor",
            "type":"Services"
        }
    ],
    "sg:phone":"+1 410 798 1600",
    "sg:postcode":"21035",
    "sg:province":"MD",
    "sg:tags":[
        "physician",
        "surgeon"
    ],
    "wof:name":"Ancillary Services Inc",
    "wof:placetype":"venue"
},
  "geometry": {"coordinates":[-76.637556,38.958982],"type":"Point"}
}