{
  "type": "Feature",
  "properties": {
    "addr:full":"6501 Huntshire dr ste 105 Elkridge MD 21075",
    "addr:housenumber":"6501",
    "addr:postcode":"21075",
    "addr:street":"Huntshire Dr Ste 105",
    "iso:country":"US",
    "sg:address":"6501 Huntshire dr ste 105",
    "sg:city":"Elkridge",
    "sg:classifiers":[
        {
            "category":"Personal",
            "subcategory":"Barber",
            "type":"Services"
        }
    ],
    "sg:phone":"+1 410 379 1362",
    "sg:postcode":"21075",
    "sg:province":"MD",
    "wof:name":"Supreme Cuts",
    "wof:placetype":"venue"
},
  "geometry": {"coordinates":[-76.773534,39.192544],"type":"Point"}
}