{
  "type": "Feature",
  "properties": {
    "iso:country":"US",
    "sg:address":"6660 Dobbin Rd",
    "sg:city":"Columbia",
    "sg:classifiers":[
        {
            "category":"Recreation",
            "type":"Entertainment"
        }
    ],
    "sg:phone":"+1 410 381 7831",
    "sg:postcode":"21045",
    "sg:province":"MD",
    "sg:tags":[
        "martial",
        "arts",
        "instruction"
    ],
    "wof:name":"Columbia Tae KWON Do Inst Inc",
    "wof:placetype":"venue"
},
  "geometry": {"coordinates":[-76.825785,39.186326],"type":"Point"}
}