{
  "type": "Feature",
  "properties": {
    "iso:country":"US",
    "sg:address":"1023 E Church St",
    "sg:city":"Salisbury",
    "sg:classifiers":[
        {
            "category":"Restaurant",
            "type":"Food & Drink"
        }
    ],
    "sg:phone":"+1 410 749 1122",
    "sg:postcode":"21804",
    "sg:province":"MD",
    "wof:name":"Potomac Foods",
    "wof:placetype":"venue"
},
  "geometry": {"coordinates":[-75.579598,38.373133],"type":"Point"}
}