{
  "type": "Feature",
  "properties": {
    "addr:full":"4337 Old Taneytown Rd Taneytown MD 21787",
    "addr:housenumber":"4337",
    "addr:postcode":"21787",
    "addr:street":"Old Taneytown Rd",
    "iso:country":"US",
    "sg:address":"4337 Old Taneytown Rd",
    "sg:city":"Taneytown",
    "sg:classifiers":[
        {
            "category":"Sports & Exercise",
            "subcategory":"Bowling",
            "type":"Entertainment"
        }
    ],
    "sg:phone":"+1 410 751 1750",
    "sg:postcode":"21787",
    "sg:province":"MD",
    "sg:tags":[
        "center"
    ],
    "wof:name":"Thunderhead Bowl & Family Fun",
    "wof:placetype":"venue"
},
  "geometry": {"coordinates":[-77.152171,39.646892],"type":"Point"}
}