{
  "type": "Feature",
  "properties": {
    "addr:full":"1317 Chrome Hill Rd Jarrettsville MD 21084",
    "addr:housenumber":"1317",
    "addr:postcode":"21084",
    "addr:street":"Chrome Hill Rd",
    "iso:country":"US",
    "sg:address":"1317 Chrome Hill Rd",
    "sg:city":"Jarrettsville",
    "sg:phone":"+1 410 692 6788",
    "sg:postcode":"21084",
    "sg:province":"MD",
    "sg:tags":[
        "farm",
        "field",
        "corn",
        "wheat",
        "crop"
    ],
    "wof:name":"Norman Knopp",
    "wof:placetype":"venue"
},
  "geometry": {"coordinates":[-76.43654100000001,39.616964],"type":"Point"}
}