{
  "type": "Feature",
  "properties": {
    "iso:country":"US",
    "sg:address":"6440 Dobbin Center Way",
    "sg:city":"Laurel",
    "sg:classifiers":[
        {
            "category":"Retail",
            "subcategory":"Auto Repair",
            "type":"Services"
        }
    ],
    "sg:phone":"+1 301 596 5049",
    "sg:postcode":"20707",
    "sg:province":"MD",
    "wof:name":"Lmt Auto Repair",
    "wof:placetype":"venue"
},
  "geometry": {"coordinates":[-76.869202,39.098301],"type":"Point"}
}