{
  "type": "Feature",
  "properties": {
    "addr:full":"1200 W Mosher St Baltimore MD 21217",
    "addr:housenumber":"1200",
    "addr:postcode":"21217",
    "addr:street":"W Mosher St",
    "iso:country":"US",
    "sg:address":"1200 W Mosher St",
    "sg:city":"Baltimore",
    "sg:classifiers":[
        {
            "category":"Food & Beverages",
            "subcategory":"Groceries & Convenience Stores",
            "type":"Retail Goods"
        }
    ],
    "sg:phone":"+1 410 728 2444",
    "sg:postcode":"21217",
    "sg:province":"MD",
    "wof:name":"L & S Grocery Store",
    "wof:placetype":"venue"
},
  "geometry": {"coordinates":[-76.63734599999999,39.300247],"type":"Point"}
}