{
  "type": "Feature",
  "properties": {
    "iso:country":"US",
    "sg:address":"2444 Parallel Ln",
    "sg:city":"Silver Spring",
    "sg:classifiers":[
        {
            "category":"Shopping",
            "subcategory":"Computers & Home Electronics",
            "type":"Retail Goods"
        }
    ],
    "sg:phone":"+1 301 384 2520",
    "sg:postcode":"20904",
    "sg:province":"MD",
    "sg:website":"www.allaccessaudio.com",
    "wof:name":"All Access Audio Inc",
    "wof:placetype":"venue"
},
  "geometry": {"coordinates":[-76.963623,39.081116],"type":"Point"}
}