{
  "type": "Feature",
  "properties": {
    "iso:country":"US",
    "sg:address":"3417 Dundalk Ave",
    "sg:city":"Dundalk",
    "sg:classifiers":[
        {
            "category":"Building & Trades",
            "subcategory":"Locksmith",
            "type":"Services"
        }
    ],
    "sg:phone":"+1 410 650 5096",
    "sg:postcode":"21222",
    "sg:province":"MD",
    "sg:tags":[
        "key"
    ],
    "wof:name":"All Day All Night Emergency Locksmith",
    "wof:placetype":"venue"
},
  "geometry": {"coordinates":[-76.51999000000001,39.250083],"type":"Point"}
}