{
  "type": "Feature",
  "properties": {
    "addr:full":"3118 Parkington Ave Baltimore MD 21215",
    "addr:housenumber":"3118",
    "addr:postcode":"21215",
    "addr:street":"Parkington Ave",
    "iso:country":"US",
    "sg:address":"3118 Parkington Ave",
    "sg:city":"Baltimore",
    "sg:classifiers":[
        {
            "category":"Personal",
            "subcategory":"Beauty Salon",
            "type":"Services"
        }
    ],
    "sg:phone":"+1 410 358 4526",
    "sg:postcode":"21215",
    "sg:province":"MD",
    "wof:name":"Add Glamour",
    "wof:placetype":"venue"
},
  "geometry": {"coordinates":[-76.684664,39.360697],"type":"Point"}
}