{
  "type": "Feature",
  "properties": {
    "addr:full":"222 Severn Ave Ste 38 Annapolis MD 21403",
    "addr:housenumber":"222;38",
    "addr:postcode":"21403",
    "addr:street":"Severn Ave Ste",
    "iso:country":"US",
    "sg:address":"222 Severn Ave Ste 38",
    "sg:city":"Annapolis",
    "sg:classifiers":[
        {
            "category":"Train Station",
            "subcategory":"Rail",
            "type":"Transportation"
        }
    ],
    "sg:phone":"+1 410 267 0997",
    "sg:postcode":"21403",
    "sg:province":"MD",
    "sg:tags":[
        "marine",
        "engineer"
    ],
    "wof:name":"Maritime Operations Analysis Inc",
    "wof:placetype":"venue"
},
  "geometry": {"coordinates":[-76.480688,38.97272],"type":"Point"}
}