{
  "type": "Feature",
  "properties": {
    "addr:full":"7330 Woodmont Ave Ste A Bethesda MD 20814",
    "addr:housenumber":"7330",
    "addr:postcode":"20814",
    "addr:street":"Woodmont Ave Ste A",
    "iso:country":"US",
    "sg:address":"7330 Woodmont Ave Ste A",
    "sg:city":"Bethesda",
    "sg:classifiers":[
        {
            "category":"Health Services",
            "subcategory":"Dentist",
            "type":"Services"
        }
    ],
    "sg:phone":"+1 301 951 1877",
    "sg:postcode":"20814",
    "sg:province":"MD",
    "sg:tags":[
        "orthodontist"
    ],
    "wof:name":"Bethesda Dental Associates PA",
    "wof:placetype":"venue"
},
  "geometry": {"coordinates":[-77.095398,38.9813],"type":"Point"}
}