{
  "type": "Feature",
  "properties": {
    "addr:full":"800 W Saratoga St Baltimore MD 21201",
    "addr:housenumber":"800",
    "addr:postcode":"21201",
    "addr:street":"W Saratoga St",
    "iso:country":"US",
    "sg:address":"800 W Saratoga St",
    "sg:city":"Baltimore",
    "sg:classifiers":[
        {
            "category":"Real Estate",
            "subcategory":"Real Estate Services",
            "type":"Services"
        }
    ],
    "sg:phone":"+1 410 234 3681",
    "sg:postcode":"21201",
    "sg:province":"MD",
    "sg:tags":[
        "vacancy",
        "rental",
        "listing"
    ],
    "wof:name":"The Townes At The Terrace",
    "wof:placetype":"venue"
},
  "geometry": {"coordinates":[-76.63088999999999,39.29258],"type":"Point"}
}