{
  "type": "Feature",
  "properties": {
    "iso:country":"US",
    "sg:address":"6019 Mustang Ct",
    "sg:city":"Riverdale",
    "sg:classifiers":[
        {
            "category":"Professional",
            "subcategory":"Management & Consulting",
            "type":"Services"
        }
    ],
    "sg:phone":"+1 301 699 5490",
    "sg:postcode":"20737",
    "sg:province":"MD",
    "sg:tags":[
        "business"
    ],
    "wof:name":"Mochizuki Ents",
    "wof:placetype":"venue"
},
  "geometry": {"coordinates":[-76.91095199999999,38.959104],"type":"Point"}
}