{
  "type": "Feature",
  "properties": {
    "addr:full":"19028 Coltfield Ct Montgomery Village MD 20886",
    "addr:postcode":"19028;20886",
    "addr:street":"Coltfield Ct",
    "iso:country":"US",
    "sg:address":"19028 Coltfield Ct",
    "sg:city":"Montgomery Village",
    "sg:classifiers":[
        {
            "category":"Building & Trades",
            "subcategory":"Landscaping Services",
            "type":"Services"
        }
    ],
    "sg:phone":"+1 301 990 1545",
    "sg:postcode":"20886",
    "sg:province":"MD",
    "wof:name":"Inside Out Services LLC",
    "wof:placetype":"venue"
},
  "geometry": {"coordinates":[-77.211361,39.168664],"type":"Point"}
}