{
  "type": "Feature",
  "properties": {
    "addr:full":"15 Park Dr Catonsville MD 21228",
    "addr:housenumber":"15",
    "addr:postcode":"21228",
    "addr:street":"Park Dr",
    "iso:country":"US",
    "sg:address":"15 Park Dr",
    "sg:city":"Catonsville",
    "sg:classifiers":[
        {
            "category":"Professional",
            "subcategory":"Computer Services",
            "type":"Services"
        }
    ],
    "sg:phone":"+1 410 585 7250",
    "sg:postcode":"21228",
    "sg:province":"MD",
    "sg:tags":[
        "graphic"
    ],
    "wof:name":"Hotplate Web Design",
    "wof:placetype":"venue"
},
  "geometry": {"coordinates":[-76.742203,39.268372],"type":"Point"}
}