{
  "type": "Feature",
  "properties": {
    "addr:full":"8925 Old Princess Anne Rd Westover MD 21871",
    "addr:housenumber":"8925",
    "addr:postcode":"21871",
    "addr:street":"Old Princess Anne Rd",
    "iso:country":"US",
    "sg:address":"8925 Old Princess Anne Rd",
    "sg:city":"Westover",
    "sg:classifiers":[
        {
            "category":"Organizations",
            "subcategory":"Religious Organization",
            "type":"Services"
        }
    ],
    "sg:phone":"+1 410 651 5995",
    "sg:postcode":"21871",
    "sg:province":"MD",
    "sg:tags":[
        "church"
    ],
    "wof:name":"New Psalmist Nondenominational",
    "wof:placetype":"venue"
},
  "geometry": {"coordinates":[-75.688406,38.129219],"type":"Point"}
}