{
  "type": "Feature",
  "properties": {
    "iso:country":"US",
    "sg:address":"1 Oak Run Rd",
    "sg:city":"Laurel",
    "sg:classifiers":[
        {
            "category":"Government",
            "subcategory":"Office",
            "type":"Public Place"
        }
    ],
    "sg:phone":"+1 301 776 6918",
    "sg:postcode":"20724",
    "sg:province":"MD",
    "sg:tags":[
        "environmental",
        "consulting"
    ],
    "wof:name":"William Lawrence",
    "wof:placetype":"venue"
},
  "geometry": {"coordinates":[-76.801368,39.109708],"type":"Point"}
}