{
  "type": "Feature",
  "properties": {
    "addr:full":"3601 West St Ste D Hyattsville MD 20785",
    "addr:housenumber":"3601",
    "addr:postcode":"20785",
    "addr:street":"West St Ste D",
    "iso:country":"US",
    "sg:address":"3601 West St Ste D",
    "sg:city":"Hyattsville",
    "sg:classifiers":[
        {
            "category":"Personal",
            "subcategory":"Beauty Salon",
            "type":"Services"
        }
    ],
    "sg:phone":"+1 240 876 2304",
    "sg:postcode":"20785",
    "sg:province":"MD",
    "wof:name":"Beauty Botanical Distributing",
    "wof:placetype":"venue"
},
  "geometry": {"coordinates":[-76.86080200000001,38.939621],"type":"Point"}
}