{
  "type": "Feature",
  "properties": {
    "iso:country":"US",
    "sg:address":"19290 Montgomery Village Ave",
    "sg:city":"Montgomery Village",
    "sg:classifiers":[
        {
            "category":"Restaurant",
            "type":"Food & Drink"
        }
    ],
    "sg:menulink":"http://www.allmenus.com/md/gaithersburg/11210-dennys/menu/",
    "sg:phone":"+1 301 987 8432",
    "sg:postcode":"20886",
    "sg:province":"MD",
    "sg:tags":[
        "american",
        "diner"
    ],
    "wof:name":"Denny's",
    "wof:placetype":"venue"
},
  "geometry": {"coordinates":[-77.203945,39.171756],"type":"Point"}
}