{
  "type": "Feature",
  "properties": {
    "addr:full":"11601 Beltsville Dr Beltsville MD 20705",
    "addr:housenumber":"11601",
    "addr:postcode":"20705",
    "addr:street":"Beltsville Dr",
    "iso:country":"US",
    "sg:address":"11601 Beltsville Dr",
    "sg:city":"Beltsville",
    "sg:classifiers":[
        {
            "category":"Ice Cream",
            "type":"Food & Drink"
        }
    ],
    "sg:phone":"+1 301 572 5533",
    "sg:postcode":"20705",
    "sg:province":"MD",
    "sg:tags":[
        "frozen",
        "yogurt"
    ],
    "sg:website":"www.baskinrobbins.com",
    "wof:name":"Baskin-Robbins 31 Ice Cream Stores",
    "wof:placetype":"venue"
},
  "geometry": {"coordinates":[-76.93764899999999,39.04977],"type":"Point"}
}