{
  "type": "Feature",
  "properties": {
    "addr:full":"234 N Eutaw St Baltimore MD 21201",
    "addr:housenumber":"234",
    "addr:postcode":"21201",
    "addr:street":"N Eutaw St",
    "iso:country":"US",
    "sg:address":"234 N Eutaw St",
    "sg:city":"Baltimore",
    "sg:classifiers":[
        {
            "category":"Manufacturing",
            "subcategory":"Textiles",
            "type":"Manufacturing & Wholesale Goods"
        }
    ],
    "sg:phone":"+1 410 837 0787",
    "sg:postcode":"21201",
    "sg:province":"MD",
    "sg:tags":[
        "watch",
        "hat",
        "jewelry",
        "store"
    ],
    "wof:name":"Price Rite",
    "wof:placetype":"venue"
},
  "geometry": {"coordinates":[-76.621002,39.292599],"type":"Point"}
}