{
  "type": "Feature",
  "properties": {
    "addr:full":"1900 Bel Air Rd Fallston MD 21047",
    "addr:postcode":"1900;21047",
    "addr:street":"Bel Air Rd",
    "iso:country":"US",
    "sg:address":"1900 Bel Air Rd",
    "sg:city":"Fallston",
    "sg:classifiers":[
        {
            "category":"Autos & Motor Vehicles",
            "subcategory":"Fuel & Gas Station",
            "type":"Retail Goods"
        },
        {
            "category":"Retail",
            "subcategory":"Auto Repair",
            "type":"Services"
        }
    ],
    "sg:phone":"+1 410 879 6040",
    "sg:postcode":"21047",
    "sg:province":"MD",
    "sg:tags":[
        "engine",
        "rebuilding",
        "installation",
        "tire",
        "exchange",
        "automobile",
        "retread",
        "diagnostic",
        "recap",
        "inspection"
    ],
    "sg:website":"http://www.karsauto.net/",
    "wof:name":"Kar Auto Repair Inc",
    "wof:placetype":"venue"
},
  "geometry": {"coordinates":[-76.38689599999999,39.499191],"type":"Point"}
}