{
  "type": "Feature",
  "properties": {
    "addr:full":"2429 E Monument St Baltimore MD 21205",
    "addr:housenumber":"2429",
    "addr:postcode":"21205",
    "addr:street":"E Monument St",
    "iso:country":"US",
    "sg:address":"2429 E Monument St",
    "sg:city":"Baltimore",
    "sg:classifiers":[
        {
            "category":"Retail",
            "subcategory":"Repair Shop",
            "type":"Services"
        }
    ],
    "sg:phone":"+1 410 563 0420",
    "sg:postcode":"21205",
    "sg:province":"MD",
    "sg:tags":[
        "television",
        "radio"
    ],
    "wof:name":"National TV",
    "wof:placetype":"venue"
},
  "geometry": {"coordinates":[-76.582358,39.298783],"type":"Point"}
}