{
  "type": "Feature",
  "properties": {
    "iso:country":"US",
    "sg:address":"7000 Wisconsin Ave",
    "sg:city":"Chevy Chase",
    "sg:classifiers":[
        {
            "category":"Banks & Credit Unions",
            "subcategory":"Financial Services",
            "type":"Services"
        }
    ],
    "sg:phone":"+1 301 907 8030",
    "sg:postcode":"20815",
    "sg:province":"MD",
    "sg:tags":[
        "broker",
        "mortgage"
    ],
    "wof:name":"Fidelity & Trust Mortgage Inc",
    "wof:placetype":"venue"
},
  "geometry": {"coordinates":[-77.084396,38.979198],"type":"Point"}
}