{
  "type": "Feature",
  "properties": {
    "iso:country":"US",
    "sg:address":"28 Allegheny Ave",
    "sg:city":"Baltimore",
    "sg:classifiers":[
        {
            "category":"Professional",
            "subcategory":"Business Services",
            "type":"Services"
        }
    ],
    "sg:phone":"+1 410 225 0316",
    "sg:postcode":"21204",
    "sg:province":"MD",
    "sg:tags":[
        "interior",
        "consultant",
        "design",
        "decorator"
    ],
    "wof:name":"D B Interiors",
    "wof:placetype":"venue"
},
  "geometry": {"coordinates":[-76.603043,39.401747],"type":"Point"}
}