{
  "type": "Feature",
  "properties": {
    "addr:full":"5 Wesley Woods Ct Kingsville MD 21087",
    "addr:housenumber":"5",
    "addr:postcode":"21087",
    "addr:street":"Wesley Woods Ct",
    "iso:country":"US",
    "sg:address":"5 Wesley Woods Ct",
    "sg:city":"Kingsville",
    "sg:classifiers":[
        {
            "category":"Professional",
            "subcategory":"Engineering",
            "type":"Services"
        }
    ],
    "sg:phone":"+1 410 592 5611",
    "sg:postcode":"21087",
    "sg:province":"MD",
    "sg:tags":[
        "chemical"
    ],
    "wof:name":"Narula Rahul",
    "wof:placetype":"venue"
},
  "geometry": {"coordinates":[-76.41215099999999,39.470746],"type":"Point"}
}