{
  "type": "Feature",
  "properties": {
    "iso:country":"US",
    "sg:address":"7835 Eastern Ave NW",
    "sg:city":"Silver Spring",
    "sg:classifiers":[
        {
            "category":"Professional",
            "subcategory":"Advertising",
            "type":"Services"
        }
    ],
    "sg:phone":"+1 301 587 1505",
    "sg:postcode":"20910",
    "sg:province":"MD",
    "wof:name":"Renaissance Communications Inc",
    "wof:placetype":"venue"
},
  "geometry": {"coordinates":[-77.027202,38.984936],"type":"Point"}
}