{
  "type": "Feature",
  "properties": {
    "addr:full":"40 Sullivan Ave Westminster MD 21157",
    "addr:housenumber":"40",
    "addr:postcode":"21157",
    "addr:street":"Sullivan Ave",
    "iso:country":"US",
    "sg:address":"40 Sullivan Ave",
    "sg:city":"Westminster",
    "sg:classifiers":[
        {
            "category":"Professional",
            "subcategory":"Computer Services",
            "type":"Services"
        }
    ],
    "sg:phone":"+1 410 596 5668",
    "sg:postcode":"21157",
    "sg:province":"MD",
    "sg:tags":[
        "technical",
        "assistance",
        "support"
    ],
    "wof:name":"Theta Systems, Inc.",
    "wof:placetype":"venue"
},
  "geometry": {"coordinates":[-76.997505,39.587912],"type":"Point"}
}