{
  "type": "Feature",
  "properties": {
    "iso:country":"US",
    "sg:address":"10710 Baltimore Ave",
    "sg:city":"Beltsville",
    "sg:classifiers":[
        {
            "category":"Professional",
            "subcategory":"Accounting & Tax Preparation",
            "type":"Services"
        }
    ],
    "sg:phone":"+1 301 595 2793",
    "sg:postcode":"20705",
    "sg:province":"MD",
    "sg:tags":[
        "accountant"
    ],
    "wof:name":"Robert C Newland & Assoc",
    "wof:placetype":"venue"
},
  "geometry": {"coordinates":[-76.913984,39.030391],"type":"Point"}
}