{
  "type": "Feature",
  "properties": {
    "iso:country":"US",
    "sg:address":"4422 Wheeler Rd",
    "sg:city":"Oxon Hill",
    "sg:classifiers":[
        {
            "category":"Food & Beverages",
            "subcategory":"Liquor & Beverages",
            "type":"Retail Goods"
        }
    ],
    "sg:phone":"+1 301 894 5566",
    "sg:postcode":"20745",
    "sg:province":"MD",
    "sg:tags":[
        "beer",
        "spirit",
        "wine"
    ],
    "wof:name":"Tops Liquors",
    "wof:placetype":"venue"
},
  "geometry": {"coordinates":[-76.987297,38.832001],"type":"Point"}
}