{
  "type": "Feature",
  "properties": {
    "iso:country":"US",
    "sg:address":"61 Rockland Rd",
    "sg:city":"Westminster",
    "sg:classifiers":[
        {
            "category":"Building & Trades",
            "subcategory":"Construction",
            "type":"Services"
        }
    ],
    "sg:phone":"+1 410 857 0980",
    "sg:postcode":"21158",
    "sg:province":"MD",
    "sg:tags":[
        "contractor"
    ],
    "wof:name":"Family Homes Inc",
    "wof:placetype":"venue"
},
  "geometry": {"coordinates":[-77.038749,39.581455],"type":"Point"}
}