{
  "type": "Feature",
  "properties": {
    "addr:full":"105 Annapolis St Ste A Annapolis MD 21401",
    "addr:housenumber":"105",
    "addr:postcode":"21401",
    "addr:street":"Annapolis St Ste A",
    "iso:country":"US",
    "sg:address":"105 Annapolis St Ste A",
    "sg:city":"Annapolis",
    "sg:classifiers":[
        {
            "category":"Shopping",
            "subcategory":"Jewelry",
            "type":"Retail Goods"
        },
        {
            "category":"Manufacturing",
            "subcategory":"Jewelry",
            "type":"Manufacturing & Wholesale Goods"
        }
    ],
    "sg:phone":"+1 410 268 5900",
    "sg:postcode":"21401",
    "sg:province":"MD",
    "sg:tags":[
        "manufacturer",
        "designer",
        "jewelers-wholesale",
        "jeweler"
    ],
    "sg:website":"http://www.tigereyejewels.com",
    "wof:name":"Tiger's Eye",
    "wof:placetype":"venue"
},
  "geometry": {"coordinates":[-76.50217600000001,38.990063],"type":"Point"}
}