{
  "type": "Feature",
  "properties": {
    "addr:full":"3 Linden Ter Pikesville MD 21208",
    "addr:housenumber":"3",
    "addr:postcode":"21208",
    "addr:street":"Linden Ter",
    "iso:country":"US",
    "sg:address":"3 Linden Ter",
    "sg:city":"Pikesville",
    "sg:classifiers":[
        {
            "category":"Professional",
            "subcategory":"Business Services",
            "type":"Services"
        }
    ],
    "sg:phone":"+1 410 653 1681",
    "sg:postcode":"21208",
    "sg:province":"MD",
    "wof:name":"Charles A Dubman",
    "wof:placetype":"venue"
},
  "geometry": {"coordinates":[-76.71847,39.367178],"type":"Point"}
}