{
  "type": "Feature",
  "properties": {
    "iso:country":"US",
    "sg:address":"3920 Vero Rd",
    "sg:city":"Baltimore",
    "sg:classifiers":[
        {
            "category":"Shopping",
            "subcategory":"Department Store",
            "type":"Retail Goods"
        }
    ],
    "sg:phone":"+1 410 247 0670",
    "sg:postcode":"21227",
    "sg:province":"MD",
    "sg:tags":[
        "shop"
    ],
    "wof:name":"Village Economy Stores",
    "wof:placetype":"venue"
},
  "geometry": {"coordinates":[-76.676706,39.260977],"type":"Point"}
}