{
  "type": "Feature",
  "properties": {
    "addr:full":"11427 Eastern Ave Baltimore MD 21220",
    "addr:housenumber":"11427",
    "addr:postcode":"21220",
    "addr:street":"Eastern Ave",
    "iso:country":"US",
    "sg:address":"11427 Eastern Ave",
    "sg:city":"Baltimore",
    "sg:classifiers":[
        {
            "category":"Freight",
            "type":"Transportation"
        }
    ],
    "sg:phone":"+1 410 335 7984",
    "sg:postcode":"21220",
    "sg:province":"MD",
    "sg:tags":[
        "delivery"
    ],
    "wof:name":"Action Deliveries",
    "wof:placetype":"venue"
},
  "geometry": {"coordinates":[-76.40100099999999,39.339708],"type":"Point"}
}