{
  "type": "Feature",
  "properties": {
    "addr:full":"2709 Poffenberger Rd Middletown MD 21769",
    "addr:housenumber":"2709",
    "addr:postcode":"21769",
    "addr:street":"Poffenberger Rd",
    "iso:country":"US",
    "sg:address":"2709 Poffenberger Rd",
    "sg:city":"Middletown",
    "sg:classifiers":[
        {
            "category":"Shopping",
            "subcategory":"Used Merchandise",
            "type":"Retail Goods"
        }
    ],
    "sg:phone":"+1 301 371 7006",
    "sg:postcode":"21769",
    "sg:province":"MD",
    "wof:name":"An Old Time Past Antiques & Co",
    "wof:placetype":"venue"
},
  "geometry": {"coordinates":[-77.578222,39.389003],"type":"Point"}
}