{
  "type": "Feature",
  "properties": {
    "iso:country":"US",
    "sg:address":"222 E Baltimore St",
    "sg:city":"Taneytown",
    "sg:classifiers":[
        {
            "category":"Organizations",
            "subcategory":"Non-profit Organization",
            "type":"Services"
        }
    ],
    "sg:phone":"+1 410 756 1158",
    "sg:postcode":"21787",
    "sg:province":"MD",
    "wof:name":"Interfaith Housing Alliance",
    "wof:placetype":"venue"
},
  "geometry": {"coordinates":[-77.17143799999999,39.655975],"type":"Point"}
}