{
  "type": "Feature",
  "properties": {
    "addr:full":"15411 New Hampshire Ave Silver Spring MD 20905",
    "addr:housenumber":"15411",
    "addr:postcode":"20905",
    "addr:street":"New Hampshire Ave",
    "iso:country":"US",
    "sg:address":"15411 New Hampshire Ave",
    "sg:city":"Silver Spring",
    "sg:classifiers":[
        {
            "category":"Shopping",
            "subcategory":"Pharmacy",
            "type":"Retail Goods"
        }
    ],
    "sg:phone":"+1 301 476 8303",
    "sg:postcode":"20905",
    "sg:province":"MD",
    "sg:tags":[
        "drugstore"
    ],
    "wof:name":"Safeway Pharmacy",
    "wof:placetype":"venue"
},
  "geometry": {"coordinates":[-76.997902,39.108799],"type":"Point"}
}