{
  "type": "Feature",
  "properties": {
    "addr:full":"20926 Frederick Rd Germantown MD 20876",
    "addr:housenumber":"20926",
    "addr:postcode":"20876",
    "addr:street":"Frederick Rd",
    "iso:country":"US",
    "sg:address":"20926 Frederick Rd",
    "sg:city":"Germantown",
    "sg:classifiers":[
        {
            "category":"Coffee & Tea",
            "type":"Food & Drink"
        },
        {
            "category":"Bakery",
            "type":"Food & Drink"
        }
    ],
    "sg:menulink":"http://www.allmenus.com/md/clarksburg/137068-seattles-best-coffee/menu/",
    "sg:phone":"+1 301 528 0862",
    "sg:postcode":"20876",
    "sg:province":"MD",
    "sg:tags":[
        "american",
        "diner",
        "pastry"
    ],
    "wof:name":"Seattle's Best Coffee",
    "wof:placetype":"venue"
},
  "geometry": {"coordinates":[-77.245031,39.198813],"type":"Point"}
}