{
  "type": "Feature",
  "properties": {
    "addr:full":"2540 E Fayette St Baltimore MD 21224",
    "addr:housenumber":"2540",
    "addr:postcode":"21224",
    "addr:street":"E Fayette St",
    "iso:country":"US",
    "sg:address":"2540 E Fayette St",
    "sg:city":"Baltimore",
    "sg:classifiers":[
        {
            "category":"Food & Beverages",
            "subcategory":"Liquor & Beverages",
            "type":"Retail Goods"
        }
    ],
    "sg:phone":"+1 410 732 5916",
    "sg:postcode":"21224",
    "sg:province":"MD",
    "sg:tags":[
        "beer",
        "spirit",
        "wine"
    ],
    "wof:name":"Winn's Food & Liquor",
    "wof:placetype":"venue"
},
  "geometry": {"coordinates":[-76.580704,39.294399],"type":"Point"}
}