{
  "type": "Feature",
  "properties": {
    "iso:country":"US",
    "sg:address":"15 Treeway Ct",
    "sg:city":"Towson",
    "sg:classifiers":[
        {
            "category":"Professional",
            "subcategory":"Management & Consulting",
            "type":"Services"
        }
    ],
    "sg:phone":"+1 410 821 7599",
    "sg:postcode":"21286",
    "sg:province":"MD",
    "sg:tags":[
        "consultant",
        "business"
    ],
    "wof:name":"Tri-City Management",
    "wof:placetype":"venue"
},
  "geometry": {"coordinates":[-76.57912,39.404427],"type":"Point"}
}