{
  "type": "Feature",
  "properties": {
    "addr:full":"5457 Woodenhawk Cir Columbia MD 21044",
    "addr:housenumber":"5457",
    "addr:postcode":"21044",
    "addr:street":"Woodenhawk Cir",
    "iso:country":"US",
    "sg:address":"5457 Woodenhawk Cir",
    "sg:city":"Columbia",
    "sg:classifiers":[
        {
            "category":"Building & Trades",
            "subcategory":"Construction",
            "type":"Services"
        }
    ],
    "sg:phone":"+1 410 772 5895",
    "sg:postcode":"21044",
    "sg:province":"MD",
    "sg:tags":[
        "general",
        "contractor"
    ],
    "wof:name":"S & B Restoration & Contr",
    "wof:placetype":"venue"
},
  "geometry": {"coordinates":[-76.88571,39.219646],"type":"Point"}
}