{
  "type": "Feature",
  "properties": {
    "iso:country":"US",
    "sg:address":"111 N Calvert St",
    "sg:city":"Baltimore",
    "sg:classifiers":[
        {
            "category":"Government",
            "subcategory":"Court House",
            "type":"Public Place"
        }
    ],
    "sg:phone":"+1 410 333 3700",
    "sg:postcode":"21202",
    "sg:province":"MD",
    "wof:name":"Baltimore City Circuit Court",
    "wof:placetype":"venue"
},
  "geometry": {"coordinates":[-76.612402,39.291142],"type":"Point"}
}