{
  "type": "Feature",
  "properties": {
    "addr:full":"100 Woodlawn Rd Baltimore MD 21210",
    "addr:housenumber":"100",
    "addr:postcode":"21210",
    "addr:street":"Woodlawn Rd",
    "iso:country":"US",
    "sg:address":"100 Woodlawn Rd",
    "sg:city":"Baltimore",
    "sg:classifiers":[
        {
            "category":"Shopping",
            "subcategory":"Clothing, Apparel, & Fashions",
            "type":"Retail Goods"
        }
    ],
    "sg:phone":"+1 410 889 7801",
    "sg:postcode":"21210",
    "sg:province":"MD",
    "sg:tags":[
        "t-shirt"
    ],
    "wof:name":"Cloud 9 Clothing",
    "wof:placetype":"venue"
},
  "geometry": {"coordinates":[-76.633728,39.344299],"type":"Point"}
}