{
  "type": "Feature",
  "properties": {
    "iso:country":"US",
    "sg:address":"224 N Washington St",
    "sg:city":"Havre De Grace",
    "sg:classifiers":[
        {
            "category":"Professional",
            "type":"Services"
        }
    ],
    "sg:phone":"+1 410 939 4909",
    "sg:postcode":"21078",
    "sg:province":"MD",
    "sg:tags":[
        "establishment"
    ],
    "wof:name":"Data Place",
    "wof:placetype":"venue"
},
  "geometry": {"coordinates":[-76.08985800000001,39.548687],"type":"Point"}
}