{
  "type": "Feature",
  "properties": {
    "iso:country":"US",
    "sg:address":"3062 Tudor Hall Rd",
    "sg:city":"Riva",
    "sg:classifiers":[
        {
            "category":"Professional",
            "subcategory":"Accounting & Tax Preparation",
            "type":"Services"
        }
    ],
    "sg:phone":"+1 301 261 7107",
    "sg:postcode":"21140",
    "sg:province":"MD",
    "sg:tags":[
        "accountant"
    ],
    "wof:name":"Krista A Garrett CPA",
    "wof:placetype":"venue"
},
  "geometry": {"coordinates":[-76.578019,38.951273],"type":"Point"}
}