{
  "type": "Feature",
  "properties": {
    "addr:full":"7936 Johnson Ave Glenarden MD 20706",
    "addr:housenumber":"7936",
    "addr:postcode":"20706",
    "addr:street":"Johnson Ave",
    "iso:country":"US",
    "sg:address":"7936 Johnson Ave",
    "sg:city":"Glenarden",
    "sg:classifiers":[
        {
            "category":"Personal",
            "subcategory":"Beauty Salon",
            "type":"Services"
        }
    ],
    "sg:phone":"+1 301 773 3552",
    "sg:postcode":"20706",
    "sg:province":"MD",
    "wof:name":"Thompson's Beauty Salon",
    "wof:placetype":"venue"
},
  "geometry": {"coordinates":[-76.865015,38.934092],"type":"Point"}
}