{
  "type": "Feature",
  "properties": {
    "addr:full":"17600 Macduff Ave Olney MD 20832",
    "addr:housenumber":"17600",
    "addr:postcode":"20832",
    "addr:street":"Macduff Ave",
    "iso:country":"US",
    "sg:address":"17600 Macduff Ave",
    "sg:city":"Olney",
    "sg:classifiers":[
        {
            "category":"Shopping",
            "subcategory":"Computers & Home Electronics",
            "type":"Retail Goods"
        }
    ],
    "sg:phone":"+1 301 570 0422",
    "sg:postcode":"20832",
    "sg:province":"MD",
    "sg:tags":[
        "software"
    ],
    "wof:name":"Flank Associates",
    "wof:placetype":"venue"
},
  "geometry": {"coordinates":[-77.08839999999999,39.141352],"type":"Point"}
}