{
  "type": "Feature",
  "properties": {
    "iso:country":"US",
    "sg:address":"3601 Fords Ln",
    "sg:city":"Baltimore",
    "sg:classifiers":[
        {
            "category":"Social Services",
            "subcategory":"Retirement Home",
            "type":"Services"
        }
    ],
    "sg:phone":"+1 410 358 5581",
    "sg:postcode":"21215",
    "sg:province":"MD",
    "wof:name":"Har Sinai Senior Citizens Housing Corp",
    "wof:placetype":"venue"
},
  "geometry": {"coordinates":[-76.696602,39.3601],"type":"Point"}
}