{
  "type": "Feature",
  "properties": {
    "iso:country":"US",
    "sg:address":"8900 Brookridge Dr",
    "sg:city":"Upper Marlboro",
    "sg:classifiers":[
        {
            "category":"Building & Trades",
            "subcategory":"Construction",
            "type":"Services"
        }
    ],
    "sg:phone":"+1 301 952 0700",
    "sg:postcode":"20772",
    "sg:province":"MD",
    "sg:tags":[
        "elevator"
    ],
    "wof:name":"Avery Elevator Corp",
    "wof:placetype":"venue"
},
  "geometry": {"coordinates":[-76.754551,38.769286],"type":"Point"}
}