{
  "type": "Feature",
  "properties": {
    "addr:full":"4 Marwood Ct Rockville MD 20850",
    "addr:housenumber":"4",
    "addr:postcode":"20850",
    "addr:street":"Marwood Ct",
    "iso:country":"US",
    "sg:address":"4 Marwood Ct",
    "sg:city":"Rockville",
    "sg:classifiers":[
        {
            "category":"Building & Trades",
            "subcategory":"Landscaping Services",
            "type":"Services"
        }
    ],
    "sg:phone":"+1 301 762 6330",
    "sg:postcode":"20850",
    "sg:province":"MD",
    "sg:tags":[
        "landscape",
        "contractor"
    ],
    "wof:name":"Mc Guigan Landscaping Install",
    "wof:placetype":"venue"
},
  "geometry": {"coordinates":[-77.17450599999999,39.083572],"type":"Point"}
}