{
  "type": "Feature",
  "properties": {
    "iso:country":"US",
    "sg:address":"129 W Patrick St",
    "sg:city":"Frederick",
    "sg:classifiers":[
        {
            "category":"Professional",
            "subcategory":"Business Services",
            "type":"Services"
        }
    ],
    "sg:phone":"+1 301 698 5758",
    "sg:postcode":"21701",
    "sg:province":"MD",
    "wof:name":"Js Quick Business Svc",
    "wof:placetype":"venue"
},
  "geometry": {"coordinates":[-77.412924,39.414381],"type":"Point"}
}