{
  "type": "Feature",
  "properties": {
    "iso:country":"US",
    "sg:address":"2736 Greenmount Ave",
    "sg:city":"Baltimore",
    "sg:classifiers":[
        {
            "category":"Food & Beverages",
            "subcategory":"Liquor & Beverages",
            "type":"Retail Goods"
        }
    ],
    "sg:phone":"+1 410 235 1165",
    "sg:postcode":"21218",
    "sg:province":"MD",
    "sg:tags":[
        "beer",
        "spirit",
        "wine"
    ],
    "wof:name":"Sbs Liquor Store",
    "wof:placetype":"venue"
},
  "geometry": {"coordinates":[-76.60929899999999,39.321701],"type":"Point"}
}