{
  "type": "Feature",
  "properties": {
    "iso:country":"US",
    "sg:address":"7100 Sollers Point Rd",
    "sg:city":"Dundalk",
    "sg:classifiers":[
        {
            "category":"Restaurant",
            "type":"Food & Drink"
        }
    ],
    "sg:phone":"+1 410 285 5828",
    "sg:postcode":"21222",
    "sg:province":"MD",
    "wof:name":"Minnick's Restaurant",
    "wof:placetype":"venue"
},
  "geometry": {"coordinates":[-76.516998,39.264801],"type":"Point"}
}