{
  "type": "Feature",
  "properties": {
    "iso:country":"US",
    "sg:address":"12 W Church St",
    "sg:city":"Frederick",
    "sg:classifiers":[
        {
            "category":"Insurance",
            "subcategory":"Hazard Insurance",
            "type":"Services"
        }
    ],
    "sg:phone":"+1 301 695 6400",
    "sg:postcode":"21701",
    "sg:province":"MD",
    "sg:tags":[
        "profit",
        "sharing",
        "pension",
        "plan"
    ],
    "sg:website":"www.quadsweb.com",
    "wof:name":"QUADS Financial Group",
    "wof:placetype":"venue"
},
  "geometry": {"coordinates":[-77.412023,39.415348],"type":"Point"}
}