{
  "type": "Feature",
  "properties": {
    "iso:country":"US",
    "sg:address":"21 S Summit Ave",
    "sg:city":"Gaithersburg",
    "sg:classifiers":[
        {
            "category":"Government",
            "subcategory":"Post Office",
            "type":"Public Place"
        }
    ],
    "sg:phone":"+1 301 208 3700",
    "sg:postcode":"20877",
    "sg:province":"MD",
    "wof:name":"US Post Office",
    "wof:placetype":"venue"
},
  "geometry": {"coordinates":[-77.193473,39.141334],"type":"Point"}
}