{
  "type": "Feature",
  "properties": {
    "iso:country":"US",
    "sg:address":"1730 W Lexington St",
    "sg:city":"Baltimore",
    "sg:classifiers":[
        {
            "category":"Social Services",
            "subcategory":"Child Care",
            "type":"Services"
        }
    ],
    "sg:phone":"+1 443 708 2717",
    "sg:postcode":"21223",
    "sg:province":"MD",
    "sg:tags":[
        "nursery",
        "day"
    ],
    "wof:name":"Rosaling Murray Day Care",
    "wof:placetype":"venue"
},
  "geometry": {"coordinates":[-76.64467500000001,39.290629],"type":"Point"}
}