{
  "type": "Feature",
  "properties": {
    "iso:country":"US",
    "sg:address":"9106 McDonald Dr",
    "sg:city":"Bethesda",
    "sg:classifiers":[
        {
            "category":"Professional",
            "subcategory":"Management & Consulting",
            "type":"Services"
        }
    ],
    "sg:phone":"+1 301 469 7573",
    "sg:postcode":"20817",
    "sg:province":"MD",
    "sg:tags":[
        "nuclear"
    ],
    "wof:name":"Thomas Murley",
    "wof:placetype":"venue"
},
  "geometry": {"coordinates":[-77.16867499999999,39.005837],"type":"Point"}
}