{
  "type": "Feature",
  "properties": {
    "iso:country":"US",
    "sg:address":"18033 Cottage Garden Dr",
    "sg:city":"Germantown",
    "sg:classifiers":[
        {
            "category":"Professional",
            "subcategory":"Engineering",
            "type":"Services"
        }
    ],
    "sg:phone":"+1 301 528 5428",
    "sg:postcode":"20874",
    "sg:province":"MD",
    "wof:name":"Son H Bui",
    "wof:placetype":"venue"
},
  "geometry": {"coordinates":[-77.27476,39.152367],"type":"Point"}
}