{
  "type": "Feature",
  "properties": {
    "addr:full":"657 Main St Laurel MD 20707",
    "addr:housenumber":"657",
    "addr:postcode":"20707",
    "addr:street":"Main St",
    "iso:country":"US",
    "sg:address":"657 Main St",
    "sg:city":"Laurel",
    "sg:classifiers":[
        {
            "category":"Sports & Exercise",
            "subcategory":"Gym",
            "type":"Entertainment"
        }
    ],
    "sg:phone":"+1 301 953 3115",
    "sg:postcode":"20707",
    "sg:province":"MD",
    "sg:tags":[
        "club",
        "health",
        "studio",
        "gymnasium"
    ],
    "wof:name":"School Of T'Ai Chi Chuan",
    "wof:placetype":"venue"
},
  "geometry": {"coordinates":[-76.852981,39.108222],"type":"Point"}
}