{
  "type": "Feature",
  "properties": {
    "iso:country":"US",
    "sg:address":"6603 Sweet Air Ln",
    "sg:city":"Sykesville",
    "sg:classifiers":[
        {
            "category":"Building & Trades",
            "subcategory":"Construction",
            "type":"Services"
        }
    ],
    "sg:phone":"+1 410 781 4758",
    "sg:postcode":"21784",
    "sg:province":"MD",
    "sg:tags":[
        "contractor",
        "mason"
    ],
    "wof:name":"Brick-Works Inc",
    "wof:placetype":"venue"
},
  "geometry": {"coordinates":[-76.919489,39.392175],"type":"Point"}
}