{
  "type": "Feature",
  "properties": {
    "iso:country":"US",
    "sg:address":"6505 Old Branch Ave",
    "sg:city":"Temple Hills",
    "sg:classifiers":[
        {
            "category":"Personal",
            "subcategory":"Beauty Salon",
            "type":"Services"
        }
    ],
    "sg:phone":"+1 301 449 4409",
    "sg:postcode":"20748",
    "sg:province":"MD",
    "wof:name":"Meissa Hair Braiding",
    "wof:placetype":"venue"
},
  "geometry": {"coordinates":[-76.904005,38.800576],"type":"Point"}
}