{
  "type": "Feature",
  "properties": {
    "iso:country":"US",
    "sg:address":"2404 A and Eagle Blvd",
    "sg:city":"Annapolis",
    "sg:classifiers":[
        {
            "category":"Wholesale",
            "subcategory":"Beer",
            "type":"Manufacturing & Wholesale Goods"
        }
    ],
    "sg:phone":"+1 410 224 2391",
    "sg:postcode":"21401",
    "sg:province":"MD",
    "sg:tags":[
        "ale"
    ],
    "wof:name":"Katcef Brothers Inc",
    "wof:placetype":"venue"
},
  "geometry": {"coordinates":[-76.564474,38.984658],"type":"Point"}
}