{
  "type": "Feature",
  "properties": {
    "addr:full":"12240 Wilkens Ave Kensington MD 20895",
    "addr:housenumber":"12240",
    "addr:postcode":"20895",
    "addr:street":"Wilkens Ave",
    "iso:country":"US",
    "sg:address":"12240 Wilkens Ave",
    "sg:city":"Kensington",
    "sg:classifiers":[
        {
            "category":"Retail",
            "subcategory":"Auto Rental",
            "type":"Services"
        }
    ],
    "sg:phone":"+1 301 761 4067",
    "sg:postcode":"20895",
    "sg:province":"MD",
    "sg:tags":[
        "car"
    ],
    "sg:website":"avis.com",
    "wof:name":"Avis Rent A Car",
    "wof:placetype":"venue"
},
  "geometry": {"coordinates":[-77.110086,39.055302],"type":"Point"}
}