{
  "type": "Feature",
  "properties": {
    "addr:full":"112 Soper Ln Capitol Heights MD 20743",
    "addr:housenumber":"112",
    "addr:postcode":"20743",
    "addr:street":"Soper Ln",
    "iso:country":"US",
    "sg:address":"112 Soper Ln",
    "sg:city":"Capitol Heights",
    "sg:classifiers":[
        {
            "category":"Professional",
            "type":"Services"
        }
    ],
    "sg:phone":"+1 301 808 6400",
    "sg:postcode":"20743",
    "sg:province":"MD",
    "sg:tags":[
        "establishment"
    ],
    "wof:name":"Institute For Strengthing",
    "wof:placetype":"venue"
},
  "geometry": {"coordinates":[-76.89399899999999,38.888796],"type":"Point"}
}