{
  "type": "Feature",
  "properties": {
    "iso:country":"US",
    "sg:address":"319 W Monument St",
    "sg:city":"Baltimore",
    "sg:classifiers":[
        {
            "category":"Social Services",
            "subcategory":"Job Training",
            "type":"Services"
        }
    ],
    "sg:phone":"+1 410 752 8954",
    "sg:postcode":"21201",
    "sg:province":"MD",
    "sg:tags":[
        "rehabilitation"
    ],
    "wof:name":"Patuxent Institution",
    "wof:placetype":"venue"
},
  "geometry": {"coordinates":[-76.621448,39.297269],"type":"Point"}
}