{
  "type": "Feature",
  "properties": {
    "addr:full":"844 Hayfields Rd Cockysvl Hnt Vly MD 21030",
    "addr:housenumber":"844",
    "addr:postcode":"21030",
    "addr:street":"Hayfields Rd;Hnt Vly",
    "iso:country":"US",
    "sg:address":"844 Hayfields Rd",
    "sg:city":"Cockysvl Hnt Vly",
    "sg:classifiers":[
        {
            "category":"Home & Garden",
            "subcategory":"Building Materials",
            "type":"Retail Goods"
        }
    ],
    "sg:phone":"+1 410 771 1225",
    "sg:postcode":"21030",
    "sg:province":"MD",
    "sg:tags":[
        "plywood",
        "veneer"
    ],
    "wof:name":"Allstate Veneer Corp",
    "wof:placetype":"venue"
},
  "geometry": {"coordinates":[-76.672842,39.506634],"type":"Point"}
}