{
  "type": "Feature",
  "properties": {
    "addr:full":"2324 W Joppa Rd Timonium MD 21093",
    "addr:housenumber":"2324",
    "addr:postcode":"21093",
    "addr:street":"W Joppa Rd",
    "iso:country":"US",
    "sg:address":"2324 W Joppa Rd",
    "sg:city":"Timonium",
    "sg:classifiers":[
        {
            "category":"Social Services",
            "type":"Services"
        }
    ],
    "sg:phone":"+1 410 321 6035",
    "sg:postcode":"21093",
    "sg:province":"MD",
    "sg:tags":[
        "worker"
    ],
    "wof:name":"Rochelle U Hayward",
    "wof:placetype":"venue"
},
  "geometry": {"coordinates":[-76.668066,39.41839],"type":"Point"}
}