{
  "type": "Feature",
  "properties": {
    "iso:country":"US",
    "sg:address":"2107 Laurel Bush Rd",
    "sg:city":"Bel Air",
    "sg:classifiers":[
        {
            "category":"Banks & Credit Unions",
            "subcategory":"Bank",
            "type":"Services"
        }
    ],
    "sg:phone":"+1 410 515 3900",
    "sg:postcode":"21015",
    "sg:province":"MD",
    "sg:tags":[
        "loan",
        "real estate"
    ],
    "wof:name":"First Choice Home Equity",
    "wof:placetype":"venue"
},
  "geometry": {"coordinates":[-76.324275,39.498069],"type":"Point"}
}