{
  "type": "Feature",
  "properties": {
    "iso:country":"US",
    "sg:address":"111 N Calvert St Ste 618",
    "sg:city":"Baltimore",
    "sg:classifiers":[
        {
            "category":"Education",
            "subcategory":"Special Training",
            "type":"Public Place"
        }
    ],
    "sg:phone":"+1 410 704 2730",
    "sg:postcode":"21202",
    "sg:province":"MD",
    "sg:tags":[
        "educational"
    ],
    "wof:name":"Maryland Career Consortium, Inc.",
    "wof:placetype":"venue"
},
  "geometry": {"coordinates":[-76.612337,39.290497],"type":"Point"}
}