{
  "type": "Feature",
  "properties": {
    "addr:full":"3109 Main St Manchester MD 21102",
    "addr:housenumber":"3109",
    "addr:postcode":"21102",
    "addr:street":"Main St",
    "iso:country":"US",
    "sg:address":"3109 Main St",
    "sg:city":"Manchester",
    "sg:classifiers":[
        {
            "category":"Restaurant",
            "type":"Food & Drink"
        }
    ],
    "sg:phone":"+1 410 374 8455",
    "sg:postcode":"21102",
    "sg:province":"MD",
    "wof:name":"Main Street Country Kitchen",
    "wof:placetype":"venue"
},
  "geometry": {"coordinates":[-76.883966,39.65988],"type":"Point"}
}