{
  "type": "Feature",
  "properties": {
    "addr:full":"9806 Croom Rd Upper Marlboro MD 20772",
    "addr:housenumber":"9806",
    "addr:postcode":"20772",
    "addr:street":"Croom Rd",
    "iso:country":"US",
    "sg:address":"9806 Croom Rd",
    "sg:city":"Upper Marlboro",
    "sg:classifiers":[
        {
            "category":"Professional",
            "type":"Services"
        }
    ],
    "sg:phone":"+1 301 627 2637",
    "sg:postcode":"20772",
    "sg:province":"MD",
    "wof:name":"Creamer Elizabeth A (dba Scie",
    "wof:placetype":"venue"
},
  "geometry": {"coordinates":[-76.763306,38.756759],"type":"Point"}
}