{
  "type": "Feature",
  "properties": {
    "addr:full":"11503 Blue Flame Ct Clarksville MD 21029",
    "addr:housenumber":"11503",
    "addr:postcode":"21029",
    "addr:street":"Blue Flame Ct",
    "iso:country":"US",
    "sg:address":"11503 Blue Flame Ct",
    "sg:city":"Clarksville",
    "sg:classifiers":[
        {
            "category":"Professional",
            "subcategory":"Art Services",
            "type":"Services"
        }
    ],
    "sg:phone":"+1 410 792 9447",
    "sg:postcode":"21029",
    "sg:province":"MD",
    "sg:tags":[
        "graphic",
        "designer"
    ],
    "wof:name":"J K Graphics",
    "wof:placetype":"venue"
},
  "geometry": {"coordinates":[-76.90745099999999,39.166071],"type":"Point"}
}