{
  "type": "Feature",
  "properties": {
    "iso:country":"US",
    "sg:address":"4934 Hampden Ln",
    "sg:city":"Bethesda",
    "sg:classifiers":[
        {
            "category":"Manufacturing",
            "subcategory":"Printing",
            "type":"Manufacturing & Wholesale Goods"
        }
    ],
    "sg:phone":"+1 301 652 9157",
    "sg:postcode":"20814",
    "sg:province":"MD",
    "sg:tags":[
        "printer"
    ],
    "wof:name":"Altogether Printing",
    "wof:placetype":"venue"
},
  "geometry": {"coordinates":[-77.097864,38.98259],"type":"Point"}
}