{
  "type": "Feature",
  "properties": {
    "addr:full":"1415 Perryman Rd Aberdeen MD 21001",
    "addr:housenumber":"1415",
    "addr:postcode":"21001",
    "addr:street":"Perryman Rd",
    "iso:country":"US",
    "sg:address":"1415 Perryman Rd",
    "sg:city":"Aberdeen",
    "sg:classifiers":[
        {
            "category":"Autos & Motor Vehicles",
            "subcategory":"Automobile Sales",
            "type":"Retail Goods"
        }
    ],
    "sg:phone":"+1 410 297 2304",
    "sg:postcode":"21001",
    "sg:province":"MD",
    "sg:tags":[
        "new",
        "car"
    ],
    "wof:name":"Wave - North America",
    "wof:placetype":"venue"
},
  "geometry": {"coordinates":[-76.20140000000001,39.475851],"type":"Point"}
}