{
  "type": "Feature",
  "properties": {
    "addr:full":"211 S Jefferson St Frederick MD 21701",
    "addr:housenumber":"211",
    "addr:postcode":"21701",
    "addr:street":"S Jefferson St",
    "iso:country":"US",
    "sg:address":"211 S Jefferson St",
    "sg:city":"Frederick",
    "sg:classifiers":[
        {
            "category":"Professional",
            "subcategory":"Printing & Photocopies",
            "type":"Services"
        }
    ],
    "sg:phone":"+1 301 682 6502",
    "sg:postcode":"21701",
    "sg:province":"MD",
    "sg:tags":[
        "duplicating",
        "copying"
    ],
    "wof:name":"Digital Supply Corp",
    "wof:placetype":"venue"
},
  "geometry": {"coordinates":[-77.42436600000001,39.41013],"type":"Point"}
}