{
  "type": "Feature",
  "properties": {
    "iso:country":"US",
    "sg:address":"5708 Sunrise Hill Rd",
    "sg:city":"Derwood",
    "sg:classifiers":[
        {
            "category":"Health Services",
            "subcategory":"Doctor",
            "type":"Services"
        }
    ],
    "sg:phone":"+1 301 990 8578",
    "sg:postcode":"20855",
    "sg:province":"MD",
    "sg:tags":[
        "medical"
    ],
    "wof:name":"Cynthia Bailey PC",
    "wof:placetype":"venue"
},
  "geometry": {"coordinates":[-77.11474,39.159064],"type":"Point"}
}