{
  "type": "Feature",
  "properties": {
    "addr:full":"7135 Minstrel Way Ste 104 Columbia MD 21045",
    "addr:housenumber":"7135",
    "addr:postcode":"21045",
    "addr:street":"Minstrel Way Ste 104",
    "iso:country":"US",
    "sg:address":"7135 Minstrel Way Ste 104",
    "sg:city":"Columbia",
    "sg:classifiers":[
        {
            "category":"Organizations",
            "subcategory":"Community Association",
            "type":"Services"
        }
    ],
    "sg:phone":"+1 301 490 8413",
    "sg:postcode":"21045",
    "sg:province":"MD",
    "wof:name":"Health Facilities Assn Of Md",
    "wof:placetype":"venue"
},
  "geometry": {"coordinates":[-76.844506,39.177615],"type":"Point"}
}