{
  "type": "Feature",
  "properties": {
    "addr:full":"341 Montevue Ln Frederick MD 21702",
    "addr:housenumber":"341",
    "addr:postcode":"21702",
    "addr:street":"Montevue Ln",
    "iso:country":"US",
    "sg:address":"341 Montevue Ln",
    "sg:city":"Frederick",
    "sg:classifiers":[
        {
            "category":"Government",
            "subcategory":"Office",
            "type":"Public Place"
        }
    ],
    "sg:phone":"+1 301 694 1068",
    "sg:postcode":"21702",
    "sg:province":"MD",
    "wof:name":"Frederick County Warehouse",
    "wof:placetype":"venue"
},
  "geometry": {"coordinates":[-77.437209,39.43241],"type":"Point"}
}