{
  "type": "Feature",
  "properties": {
    "iso:country":"US",
    "sg:address":"5938 15th Ave",
    "sg:city":"Hyattsville",
    "sg:classifiers":[
        {
            "category":"Building & Trades",
            "subcategory":"Cleaning & Sanitation",
            "type":"Services"
        }
    ],
    "sg:phone":"+1 301 559 0652",
    "sg:postcode":"20782",
    "sg:province":"MD",
    "sg:tags":[
        "maintenance"
    ],
    "wof:name":"J&J House Cleaning",
    "wof:placetype":"venue"
},
  "geometry": {"coordinates":[-76.98040399999999,38.96102],"type":"Point"}
}