{
  "type": "Feature",
  "properties": {
    "iso:country":"US",
    "sg:address":"11214 Orleans Way",
    "sg:city":"Kensington",
    "sg:classifiers":[
        {
            "category":"Education",
            "subcategory":"Special Training",
            "type":"Public Place"
        }
    ],
    "sg:phone":"+1 301 933 1916",
    "sg:postcode":"20895",
    "sg:province":"MD",
    "sg:tags":[
        "educational"
    ],
    "wof:name":"Lucia Daubresse",
    "wof:placetype":"venue"
},
  "geometry": {"coordinates":[-77.102998,39.041375],"type":"Point"}
}