{
  "type": "Feature",
  "properties": {
    "addr:full":"6601 Seven Locks Rd Cabin John MD 20818",
    "addr:housenumber":"6601",
    "addr:postcode":"md 20818",
    "addr:street":"Seven Locks Rd",
    "iso:country":"US",
    "sg:address":"6601 Seven Locks Rd",
    "sg:city":"Cabin John",
    "sg:classifiers":[
        {
            "category":"Retail",
            "subcategory":"Portrait Studio",
            "type":"Services"
        }
    ],
    "sg:phone":"+1 301 320 4434",
    "sg:postcode":"20818",
    "sg:province":"MD",
    "sg:tags":[
        "photo"
    ],
    "wof:name":"Photo One Studio",
    "wof:placetype":"venue"
},
  "geometry": {"coordinates":[-77.16139,38.975648],"type":"Point"}
}