{
  "type": "Feature",
  "properties": {
    "addr:full":"2132 N Old Bachmans Valley Rd Westminster MD 21157",
    "addr:housenumber":"2132",
    "addr:postcode":"21157",
    "addr:street":"N Old Bachmans Valley Rd",
    "iso:country":"US",
    "sg:address":"2132 N Old Bachmans Valley Rd",
    "sg:city":"Westminster",
    "sg:classifiers":[
        {
            "category":"Manufacturing",
            "subcategory":"Food",
            "type":"Manufacturing & Wholesale Goods"
        },
        {
            "category":"Farming",
            "subcategory":"Farm",
            "type":"Manufacturing & Wholesale Goods"
        }
    ],
    "sg:phone":"+1 410 848 5082",
    "sg:postcode":"21157",
    "sg:province":"MD",
    "sg:tags":[
        "corn",
        "product"
    ],
    "wof:name":"Hale Stonesifer",
    "wof:placetype":"venue"
},
  "geometry": {"coordinates":[-76.971523,39.633644],"type":"Point"}
}