{
  "type": "Feature",
  "properties": {
    "addr:full":"27912 Kemptown Church Rd Damascus MD 20872",
    "addr:housenumber":"27912",
    "addr:postcode":"20872",
    "addr:street":"Kemptown Church Rd",
    "iso:country":"US",
    "sg:address":"27912 Kemptown Church Rd",
    "sg:city":"Damascus",
    "sg:classifiers":[
        {
            "category":"Place Of Worship",
            "subcategory":"Church",
            "type":"Public Place"
        },
        {
            "category":"Place Of Worship",
            "type":"Public Place"
        }
    ],
    "sg:phone":"+1 301 253 2721",
    "sg:postcode":"20872",
    "sg:province":"MD",
    "sg:tags":[
        "churches-methodist"
    ],
    "wof:name":"Bethesda Methodist Church",
    "wof:placetype":"venue"
},
  "geometry": {"coordinates":[-77.246595,39.313517],"type":"Point"}
}