{
  "type": "Feature",
  "properties": {
    "addr:full":"6320 Powhatan St Riverdale MD 20737",
    "addr:housenumber":"6320",
    "addr:postcode":"20737",
    "addr:street":"Powhatan St",
    "iso:country":"US",
    "sg:address":"6320 Powhatan St",
    "sg:city":"Riverdale",
    "sg:classifiers":[
        {
            "category":"Restaurant",
            "type":"Food & Drink"
        }
    ],
    "sg:phone":"+1 301 277 0949",
    "sg:postcode":"20737",
    "sg:province":"MD",
    "sg:tags":[
        "out"
    ],
    "wof:name":"T's Place",
    "wof:placetype":"venue"
},
  "geometry": {"coordinates":[-76.907025,38.959701],"type":"Point"}
}