{
  "type": "Feature",
  "properties": {
    "iso:country":"US",
    "sg:address":"44055 Airport View Dr",
    "sg:city":"Hollywood",
    "sg:classifiers":[
        {
            "category":"Autos & Motor Vehicles",
            "subcategory":"Auto Supplies",
            "type":"Retail Goods"
        },
        {
            "category":"Retail",
            "subcategory":"Auto Repair",
            "type":"Services"
        }
    ],
    "sg:phone":"+1 301 373 3537",
    "sg:postcode":"20636",
    "sg:province":"MD",
    "sg:tags":[
        "tire"
    ],
    "sg:website":"www.agapeauto.com",
    "wof:name":"Agape Auto Service",
    "wof:placetype":"venue"
},
  "geometry": {"coordinates":[-76.553703,38.318199],"type":"Point"}
}