{
  "type": "Feature",
  "properties": {
    "addr:full":"14315 National Hwy SW Cumberland MD 21502",
    "addr:housenumber":"14315",
    "addr:postcode":"21502",
    "addr:street":"National Hwy Sw",
    "iso:country":"US",
    "sg:address":"14315 National Hwy SW",
    "sg:city":"Cumberland",
    "sg:classifiers":[
        {
            "category":"Social Services",
            "subcategory":"Child Care",
            "type":"Services"
        }
    ],
    "sg:phone":"+1 301 729 6680",
    "sg:postcode":"21502",
    "sg:province":"MD",
    "wof:name":"Discovery Days Childcare Ctr",
    "wof:placetype":"venue"
},
  "geometry": {"coordinates":[-78.87626,39.642893],"type":"Point"}
}