{
  "type": "Feature",
  "properties": {
    "addr:full":"6435 District Heights Pkwy District Heights MD 20747",
    "addr:postcode":"6435;20747",
    "addr:street":"District Heights Pkwy",
    "iso:country":"US",
    "sg:address":"6435 District Heights Pkwy",
    "sg:city":"District Heights",
    "sg:classifiers":[
        {
            "category":"Shopping",
            "subcategory":"Clothing, Apparel, & Fashions",
            "type":"Retail Goods"
        }
    ],
    "sg:phone":"+1 301 669 0775",
    "sg:postcode":"20747",
    "sg:province":"MD",
    "wof:name":"Simply Fashions",
    "wof:placetype":"venue"
},
  "geometry": {"coordinates":[-76.894891,38.85903],"type":"Point"}
}