{
  "type": "Feature",
  "properties": {
    "iso:country":"US",
    "sg:address":"2 Brandy Dr",
    "sg:city":"Williamsport",
    "sg:classifiers":[
        {
            "category":"Restaurant",
            "type":"Food & Drink"
        }
    ],
    "sg:phone":"+1 301 223 7070",
    "sg:postcode":"21795",
    "sg:province":"MD",
    "sg:tags":[
        "caterer"
    ],
    "sg:website":"www.leitersfinecatering.com",
    "wof:name":"Leiters' Fine Catering Inc",
    "wof:placetype":"venue"
},
  "geometry": {"coordinates":[-77.82003,39.59412],"type":"Point"}
}