{
  "type": "Feature",
  "properties": {
    "iso:country":"US",
    "sg:address":"1469 Oak Ridge Pl",
    "sg:city":"Hagerstown",
    "sg:classifiers":[
        {
            "category":"Building & Trades",
            "subcategory":"Landscaping Services",
            "type":"Services"
        }
    ],
    "sg:phone":"+1 301 416 8180",
    "sg:postcode":"21740",
    "sg:province":"MD",
    "sg:tags":[
        "lawn",
        "maintenance",
        "grounds"
    ],
    "wof:name":"US Lawns",
    "wof:placetype":"venue"
},
  "geometry": {"coordinates":[-77.712766,39.608801],"type":"Point"}
}