{
  "type": "Feature",
  "properties": {
    "addr:full":"7366 Edsworth Rd Baltimore MD 21222",
    "addr:housenumber":"7366",
    "addr:postcode":"21222",
    "addr:street":"Edsworth Rd",
    "iso:country":"US",
    "sg:address":"7366 Edsworth Rd",
    "sg:city":"Baltimore",
    "sg:classifiers":[
        {
            "category":"Building & Trades",
            "subcategory":"Construction",
            "type":"Services"
        }
    ],
    "sg:phone":"+1 410 285 7317",
    "sg:postcode":"21222",
    "sg:province":"MD",
    "sg:tags":[
        "contractor"
    ],
    "wof:name":"Jay M Dena",
    "wof:placetype":"venue"
},
  "geometry": {"coordinates":[-76.51353400000001,39.282894],"type":"Point"}
}