{
  "type": "Feature",
  "properties": {
    "addr:full":"17545 Hardy Rd Mount Airy MD 21771",
    "addr:housenumber":"17545",
    "addr:postcode":"21771",
    "addr:street":"Hardy Rd",
    "iso:country":"US",
    "sg:address":"17545 Hardy Rd",
    "sg:city":"Mount Airy",
    "sg:classifiers":[
        {
            "category":"Building & Trades",
            "subcategory":"Cleaning & Sanitation",
            "type":"Services"
        }
    ],
    "sg:phone":"+1 410 549 9383",
    "sg:postcode":"21771",
    "sg:province":"MD",
    "sg:tags":[
        "maintenance"
    ],
    "wof:name":"Dodds Handyman & HM Maint LLC",
    "wof:placetype":"venue"
},
  "geometry": {"coordinates":[-77.131608,39.346641],"type":"Point"}
}