{
  "type": "Feature",
  "properties": {
    "addr:full":"2120 Eastern Ave Baltimore MD 21231",
    "addr:housenumber":"2120",
    "addr:postcode":"21231",
    "addr:street":"Eastern Ave",
    "iso:country":"US",
    "sg:address":"2120 Eastern Ave",
    "sg:city":"Baltimore",
    "sg:classifiers":[
        {
            "category":"Government",
            "subcategory":"Fire Station",
            "type":"Public Place"
        }
    ],
    "sg:phone":"+1 410 396 9205",
    "sg:postcode":"21231",
    "sg:province":"MD",
    "sg:tags":[
        "consultant",
        "protection"
    ],
    "sg:website":"http://www.bccenter.org",
    "wof:name":"Fire Dept-Station 28",
    "wof:placetype":"venue"
},
  "geometry": {"coordinates":[-76.586415,39.285854],"type":"Point"}
}