{
  "type": "Feature",
  "properties": {
    "iso:country":"US",
    "sg:address":"2508 Laurel Bush Rd",
    "sg:city":"Abingdon",
    "sg:classifiers":[
        {
            "category":"Retail",
            "subcategory":"Repair Shop",
            "type":"Services"
        }
    ],
    "sg:phone":"+1 410 515 5550",
    "sg:postcode":"21009",
    "sg:province":"MD",
    "sg:tags":[
        "welding"
    ],
    "wof:name":"Machine Shop Welding",
    "wof:placetype":"venue"
},
  "geometry": {"coordinates":[-76.310503,39.490472],"type":"Point"}
}