{
  "type": "Feature",
  "properties": {
    "iso:country":"US",
    "sg:address":"10884 Mahlon Price Rd",
    "sg:city":"Deal Island",
    "sg:classifiers":[
        {
            "category":"Organizations",
            "subcategory":"Religious Organization",
            "type":"Services"
        }
    ],
    "sg:phone":"+1 410 784 2051",
    "sg:postcode":"21821",
    "sg:province":"MD",
    "wof:name":"Saint Chrles Untd Mthdst Chrch",
    "wof:placetype":"venue"
},
  "geometry": {"coordinates":[-75.937985,38.183041],"type":"Point"}
}