{
  "type": "Feature",
  "properties": {
    "iso:country":"US",
    "sg:address":"2670 Crain Hwy",
    "sg:city":"Waldorf",
    "sg:classifiers":[
        {
            "category":"Health Services",
            "subcategory":"Doctor",
            "type":"Services"
        }
    ],
    "sg:phone":"+1 301 645 7556",
    "sg:postcode":"20601",
    "sg:province":"MD",
    "sg:tags":[
        "physician",
        "surgeon"
    ],
    "wof:name":"Susan Shatzer MD",
    "wof:placetype":"venue"
},
  "geometry": {"coordinates":[-76.899515,38.637022],"type":"Point"}
}