{
  "type": "Feature",
  "properties": {
    "iso:country":"US",
    "sg:address":"1116 Marton St",
    "sg:city":"Laurel",
    "sg:classifiers":[
        {
            "category":"Building & Trades",
            "subcategory":"Electrical",
            "type":"Services"
        }
    ],
    "sg:phone":"+1 301 206 2990",
    "sg:postcode":"20707",
    "sg:province":"MD",
    "sg:tags":[
        "electrician"
    ],
    "wof:name":"Warner Electric Company, Inc.",
    "wof:placetype":"venue"
},
  "geometry": {"coordinates":[-76.868324,39.098189],"type":"Point"}
}