{
  "type": "Feature",
  "properties": {
    "iso:country":"US",
    "sg:address":"111 Water St",
    "sg:city":"Baltimore",
    "sg:classifiers":[
        {
            "category":"Restaurant",
            "type":"Food & Drink"
        }
    ],
    "sg:phone":"+1 410 727 9727",
    "sg:postcode":"21202",
    "sg:province":"MD",
    "wof:name":"Urban Wraps",
    "wof:placetype":"venue"
},
  "geometry": {"coordinates":[-76.613602,39.2882],"type":"Point"}
}