{
  "type": "Feature",
  "properties": {
    "iso:country":"US",
    "sg:address":"1808 Rosemont Ave",
    "sg:city":"Frederick",
    "sg:classifiers":[
        {
            "category":"Restaurant",
            "type":"Food & Drink"
        }
    ],
    "sg:phone":"+1 301 698 9596",
    "sg:postcode":"21702",
    "sg:province":"MD",
    "wof:name":"Callahan's Restaurant",
    "wof:placetype":"venue"
},
  "geometry": {"coordinates":[-77.433049,39.429864],"type":"Point"}
}