{
  "type": "Feature",
  "properties": {
    "addr:full":"300 Jasontown Rd Westminster MD 21158",
    "addr:housenumber":"300",
    "addr:postcode":"21158",
    "addr:street":"Jasontown Rd",
    "iso:country":"US",
    "sg:address":"300 Jasontown Rd",
    "sg:city":"Westminster",
    "sg:classifiers":[
        {
            "category":"Wholesale",
            "subcategory":"Machinery & Supplies",
            "type":"Manufacturing & Wholesale Goods"
        }
    ],
    "sg:phone":"+1 410 796 8646",
    "sg:postcode":"21158",
    "sg:province":"MD",
    "sg:tags":[
        "equipment",
        "industrial"
    ],
    "wof:name":"Ecr Co",
    "wof:placetype":"venue"
},
  "geometry": {"coordinates":[-77.07749200000001,39.578941],"type":"Point"}
}