{
  "type": "Feature",
  "properties": {
    "addr:full":"19601 Fisher Ave Poolesville MD 20837",
    "addr:housenumber":"19601",
    "addr:postcode":"20837",
    "addr:street":"Fisher Ave",
    "iso:country":"US",
    "sg:address":"19601 Fisher Ave",
    "sg:city":"Poolesville",
    "sg:classifiers":[
        {
            "category":"Health Services",
            "subcategory":"Doctor",
            "type":"Services"
        }
    ],
    "sg:phone":"+1 301 972 7171",
    "sg:postcode":"20837",
    "sg:province":"MD",
    "wof:name":"Stephen P Tigani DDS",
    "wof:placetype":"venue"
},
  "geometry": {"coordinates":[-77.411033,39.144527],"type":"Point"}
}