{
  "type": "Feature",
  "properties": {
    "addr:full":"36 W 25th St Baltimore MD 21218",
    "addr:housenumber":"36",
    "addr:postcode":"21218",
    "addr:street":"W 25Th St",
    "iso:country":"US",
    "sg:address":"36 W 25th St",
    "sg:city":"Baltimore",
    "sg:classifiers":[
        {
            "category":"Manufacturing",
            "subcategory":"Printing",
            "type":"Manufacturing & Wholesale Goods"
        }
    ],
    "sg:phone":"+1 410 235 3401",
    "sg:postcode":"21218",
    "sg:province":"MD",
    "sg:tags":[
        "newspaper"
    ],
    "wof:name":"Baltimore Alternative",
    "wof:placetype":"venue"
},
  "geometry": {"coordinates":[-76.618222,39.317888],"type":"Point"}
}