{
  "type": "Feature",
  "properties": {
    "iso:country":"US",
    "sg:address":"7514 Wisconsin Ave Ste 300",
    "sg:city":"Bethesda",
    "sg:classifiers":[
        {
            "category":"Juice Bar",
            "subcategory":"None",
            "type":"Food & Drink"
        },
        {
            "category":"Wholesale",
            "subcategory":"Fruits & Vegetables",
            "type":"Manufacturing & Wholesale Goods"
        },
        {
            "category":"Ice Cream",
            "type":"Food & Drink"
        }
    ],
    "sg:phone":"+1 301 657 3322",
    "sg:postcode":"20814",
    "sg:province":"MD",
    "sg:tags":[
        "smoothy",
        "frozen",
        "yogurt",
        "veggie"
    ],
    "sg:website":"www.ffbc.com",
    "wof:name":"Frest Fruit Bouquet Company",
    "wof:placetype":"venue"
},
  "geometry": {"coordinates":[-77.094776,38.985532],"type":"Point"}
}