{
  "type": "Feature",
  "properties": {
    "iso:country":"US",
    "sg:address":"2 N Charles St Ste 850",
    "sg:city":"Baltimore",
    "sg:classifiers":[
        {
            "category":"Real Estate",
            "subcategory":"Real Estate Services",
            "type":"Services"
        },
        {
            "category":"Real Estate",
            "subcategory":"Real Estate Agent",
            "type":"Services"
        }
    ],
    "sg:phone":"+1 410 783 3200",
    "sg:postcode":"21201",
    "sg:province":"MD",
    "sg:tags":[
        "management"
    ],
    "sg:website":"http://www.shopatcoloniecenter.com",
    "wof:name":"Jones Lang Lasalle Americas, Inc.",
    "wof:placetype":"venue"
},
  "geometry": {"coordinates":[-76.615143,39.289471],"type":"Point"}
}