{
  "type": "Feature",
  "properties": {
    "iso:country":"US",
    "sg:address":"5328 85th Ave",
    "sg:city":"New Carrollton",
    "sg:classifiers":[
        {
            "category":"Building & Trades",
            "subcategory":"Cleaning & Sanitation",
            "type":"Services"
        }
    ],
    "sg:phone":"+1 240 296 3794",
    "sg:postcode":"20784",
    "sg:province":"MD",
    "sg:tags":[
        "janitor"
    ],
    "wof:name":"Pro Care Cleaning Specialists",
    "wof:placetype":"venue"
},
  "geometry": {"coordinates":[-76.869147,38.952758],"type":"Point"}
}