{
  "type": "Feature",
  "properties": {
    "addr:full":"5810 67th Ave Riverdale MD 20737",
    "addr:housenumber":"5810",
    "addr:postcode":"20737",
    "addr:street":"67Th Ave",
    "iso:country":"US",
    "sg:address":"5810 67th Ave",
    "sg:city":"Riverdale",
    "sg:classifiers":[
        {
            "category":"Organizations",
            "subcategory":"Community Association",
            "type":"Services"
        }
    ],
    "sg:phone":"+1 301 577 0878",
    "sg:postcode":"20737",
    "sg:province":"MD",
    "wof:name":"Seventh Star Seventh Stripe",
    "wof:placetype":"venue"
},
  "geometry": {"coordinates":[-76.901494,38.95932],"type":"Point"}
}