{
  "type": "Feature",
  "properties": {
    "iso:country":"US",
    "sg:address":"8030 Main St",
    "sg:city":"Ellicott City",
    "sg:classifiers":[
        {
            "category":"Education",
            "subcategory":"School",
            "type":"Public Place"
        }
    ],
    "sg:phone":"+1 410 313 9623",
    "sg:postcode":"21043",
    "sg:province":"MD",
    "wof:name":"Teamworks Training & Development Inc",
    "wof:placetype":"venue"
},
  "geometry": {"coordinates":[-76.795197,39.267899],"type":"Point"}
}