{
  "type": "Feature",
  "properties": {
    "iso:country":"US",
    "sg:address":"15624 Columbia Pike",
    "sg:city":"Burtonsville",
    "sg:classifiers":[
        {
            "category":"Food & Beverages",
            "subcategory":"Groceries & Convenience Stores",
            "type":"Retail Goods"
        }
    ],
    "sg:phone":"+1 301 421 9650",
    "sg:postcode":"20866",
    "sg:province":"MD",
    "wof:name":"Yoders Poultry",
    "wof:placetype":"venue"
},
  "geometry": {"coordinates":[-76.932329,39.111699],"type":"Point"}
}