{
  "type": "Feature",
  "properties": {
    "iso:country":"US",
    "sg:address":"1413 Research Blvd",
    "sg:city":"Rockville",
    "sg:classifiers":[
        {
            "category":"Government",
            "subcategory":"Office",
            "type":"Public Place"
        }
    ],
    "sg:phone":"+1 301 319 0100",
    "sg:postcode":"20850",
    "sg:province":"MD",
    "sg:tags":[
        "development",
        "research"
    ],
    "wof:name":"Armed Forces Inst Pathology",
    "wof:placetype":"venue"
},
  "geometry": {"coordinates":[-77.178712,39.091229],"type":"Point"}
}