{
  "type": "Feature",
  "properties": {
    "addr:full":"29 W Susquehanna Ave Baltimore MD 21204",
    "addr:housenumber":"29",
    "addr:postcode":"21204",
    "addr:street":"W Susquehanna Ave",
    "iso:country":"US",
    "sg:address":"29 W Susquehanna Ave",
    "sg:city":"Baltimore",
    "sg:classifiers":[
        {
            "category":"Professional",
            "subcategory":"Lawyer & Legal Services",
            "type":"Services"
        }
    ],
    "sg:phone":"+1 410 832 8877",
    "sg:postcode":"21204",
    "sg:province":"MD",
    "sg:tags":[
        "attorney"
    ],
    "wof:name":"George R Hoffman",
    "wof:placetype":"venue"
},
  "geometry": {"coordinates":[-76.605228,39.398462],"type":"Point"}
}