{
  "type": "Feature",
  "properties": {
    "iso:country":"US",
    "sg:address":"201 Kent Ave",
    "sg:city":"La Plata",
    "sg:classifiers":[
        {
            "category":"Personal",
            "subcategory":"Beauty Salon",
            "type":"Services"
        }
    ],
    "sg:phone":"+1 301 934 9461",
    "sg:postcode":"20646",
    "sg:province":"MD",
    "wof:name":"Betti's Hairstyling Salon",
    "wof:placetype":"venue"
},
  "geometry": {"coordinates":[-76.975679,38.534984],"type":"Point"}
}