{
  "type": "Feature",
  "properties": {
    "addr:full":"201 W Hilltop Rd Brooklyn MD 21225",
    "addr:housenumber":"201",
    "addr:postcode":"21225",
    "addr:street":"W Hilltop Rd",
    "iso:country":"US",
    "sg:address":"201 W Hilltop Rd",
    "sg:city":"Brooklyn",
    "sg:classifiers":[
        {
            "category":"Place Of Worship",
            "subcategory":"Church",
            "type":"Public Place"
        },
        {
            "category":"Place Of Worship",
            "type":"Public Place"
        }
    ],
    "sg:phone":"+1 410 636 4347",
    "sg:postcode":"21225",
    "sg:province":"MD",
    "sg:tags":[
        "churches-interdenominational",
        "churches-various",
        "denomination"
    ],
    "wof:name":"Brooklyn Prk United Brthren Church",
    "wof:placetype":"venue"
},
  "geometry": {"coordinates":[-76.616508,39.234192],"type":"Point"}
}