{
  "type": "Feature",
  "properties": {
    "addr:full":"11411 Cedar Ln Kingsville MD 21087",
    "addr:housenumber":"11411",
    "addr:postcode":"21087",
    "addr:street":"Cedar Ln",
    "iso:country":"US",
    "sg:address":"11411 Cedar Ln",
    "sg:city":"Kingsville",
    "sg:classifiers":[
        {
            "category":"Professional",
            "subcategory":"Business Services",
            "type":"Services"
        }
    ],
    "sg:phone":"+1 410 592 9343",
    "sg:postcode":"21087",
    "sg:province":"MD",
    "wof:name":"Allen C Tochterman Svc",
    "wof:placetype":"venue"
},
  "geometry": {"coordinates":[-76.420131,39.435127],"type":"Point"}
}