{
  "type": "Feature",
  "properties": {
    "iso:country":"US",
    "sg:address":"2850 Quarry Lake Dr",
    "sg:city":"Baltimore",
    "sg:classifiers":[
        {
            "category":"Banks & Credit Unions",
            "subcategory":"Investment Brokerage",
            "type":"Services"
        }
    ],
    "sg:phone":"+1 800 698 7235",
    "sg:postcode":"21209",
    "sg:province":"MD",
    "sg:tags":[
        "trust"
    ],
    "wof:name":"The Campbell Multi-Strategy Trust",
    "wof:placetype":"venue"
},
  "geometry": {"coordinates":[-76.694929,39.383759],"type":"Point"}
}