{
  "type": "Feature",
  "properties": {
    "iso:country":"US",
    "sg:address":"9875 Adams Willett Rd",
    "sg:city":"Nanjemoy",
    "sg:classifiers":[
        {
            "category":"Education",
            "subcategory":"Dance Studio",
            "type":"Public Place"
        }
    ],
    "sg:phone":"+1 301 246 9225",
    "sg:postcode":"20662",
    "sg:province":"MD",
    "wof:name":"Dimensions Dance Co Inc",
    "wof:placetype":"venue"
},
  "geometry": {"coordinates":[-77.223022,38.429169],"type":"Point"}
}