{
  "type": "Feature",
  "properties": {
    "iso:country":"US",
    "sg:address":"425 4th St",
    "sg:city":"Annapolis",
    "sg:classifiers":[
        {
            "category":"Shopping",
            "subcategory":"Computers & Home Electronics",
            "type":"Retail Goods"
        }
    ],
    "sg:phone":"+1 410 268 0422",
    "sg:postcode":"21403",
    "sg:province":"MD",
    "sg:tags":[
        "software"
    ],
    "sg:website":"www.titlesupport.com",
    "wof:name":"Title Support Svc",
    "wof:placetype":"venue"
},
  "geometry": {"coordinates":[-76.48156,38.970702],"type":"Point"}
}