{
  "type": "Feature",
  "properties": {
    "iso:country":"US",
    "sg:address":"2118 W Patapsco Ave",
    "sg:city":"Baltimore",
    "sg:classifiers":[
        {
            "category":"Building & Trades",
            "subcategory":"Construction",
            "type":"Services"
        }
    ],
    "sg:phone":"+1 443 740 3602",
    "sg:postcode":"21230",
    "sg:province":"MD",
    "sg:tags":[
        "steel",
        "detailers",
        "industrial",
        "contractor",
        "contractors-commercial",
        "structural"
    ],
    "wof:name":"Yeargin & Sons Steel",
    "wof:placetype":"venue"
},
  "geometry": {"coordinates":[-76.64392100000001,39.25095],"type":"Point"}
}