{
  "type": "Feature",
  "properties": {
    "addr:full":"6095 Marshalee Ln Elkridge MD 21075",
    "addr:housenumber":"6095",
    "addr:postcode":"21075",
    "addr:street":"Marshalee Ln",
    "iso:country":"US",
    "sg:address":"6095 Marshalee Ln",
    "sg:city":"Elkridge",
    "sg:classifiers":[
        {
            "category":"Professional",
            "subcategory":"Business Services",
            "type":"Services"
        }
    ],
    "sg:phone":"+1 410 564 5300",
    "sg:postcode":"21075",
    "sg:province":"MD",
    "wof:name":"Storagetek",
    "wof:placetype":"venue"
},
  "geometry": {"coordinates":[-76.775542,39.205776],"type":"Point"}
}