{
  "type": "Feature",
  "properties": {
    "addr:full":"9070 Junction Dr Annapolis Jct MD 20701",
    "addr:housenumber":"9070",
    "addr:postcode":"20701",
    "addr:street":"Junction Dr",
    "iso:country":"US",
    "sg:address":"9070 Junction Dr",
    "sg:city":"Annapolis Jct",
    "sg:classifiers":[
        {
            "category":"Manufacturing",
            "subcategory":"Metals",
            "type":"Manufacturing & Wholesale Goods"
        }
    ],
    "sg:phone":"+1 301 362 0200",
    "sg:postcode":"20701",
    "sg:province":"MD",
    "sg:tags":[
        "grating"
    ],
    "wof:name":"Mc Nichols Co",
    "wof:placetype":"venue"
},
  "geometry": {"coordinates":[-76.80323,39.12354],"type":"Point"}
}