{
  "type": "Feature",
  "properties": {
    "addr:full":"8430 Bensville Rd Waldorf MD 20603",
    "addr:housenumber":"8430",
    "addr:postcode":"20603",
    "addr:street":"Bensville Rd",
    "iso:country":"US",
    "sg:address":"8430 Bensville Rd",
    "sg:city":"Waldorf",
    "sg:classifiers":[
        {
            "category":"Recreation",
            "type":"Entertainment"
        }
    ],
    "sg:phone":"+1 301 645 2969",
    "sg:postcode":"20603",
    "sg:province":"MD",
    "sg:tags":[
        "stable"
    ],
    "wof:name":"Cameo Farm",
    "wof:placetype":"venue"
},
  "geometry": {"coordinates":[-77.01511499999999,38.640607],"type":"Point"}
}