{
  "type": "Feature",
  "properties": {
    "addr:full":"136 Tockwogh Dr Earleville MD 21919",
    "addr:housenumber":"136",
    "addr:postcode":"21919",
    "addr:street":"Tockwogh Dr",
    "iso:country":"US",
    "sg:address":"136 Tockwogh Dr",
    "sg:city":"Earleville",
    "sg:classifiers":[
        {
            "category":"Wholesale",
            "subcategory":"Hardware",
            "type":"Manufacturing & Wholesale Goods"
        }
    ],
    "sg:phone":"+1 410 275 2755",
    "sg:postcode":"21919",
    "sg:province":"MD",
    "wof:name":"Sassafras River Marketing Inc",
    "wof:placetype":"venue"
},
  "geometry": {"coordinates":[-76.020675,39.393416],"type":"Point"}
}