{
  "type": "Feature",
  "properties": {
    "iso:country":"US",
    "sg:address":"11506 Tommy Ct",
    "sg:city":"Bowie",
    "sg:classifiers":[
        {
            "category":"Professional",
            "type":"Services"
        }
    ],
    "sg:phone":"+1 301 390 4943",
    "sg:postcode":"20721",
    "sg:province":"MD",
    "wof:name":"Marita Golden",
    "wof:placetype":"venue"
},
  "geometry": {"coordinates":[-76.807078,38.909371],"type":"Point"}
}