{
  "type": "Feature",
  "properties": {
    "addr:full":"7947 Queenair Dr Gaithersburg MD 20879",
    "addr:housenumber":"7947",
    "addr:postcode":"20879",
    "addr:street":"Queenair Dr",
    "iso:country":"US",
    "sg:address":"7947 Queenair Dr",
    "sg:city":"Gaithersburg",
    "sg:classifiers":[
        {
            "category":"Autos & Motor Vehicles",
            "subcategory":"Automobile Sales",
            "type":"Retail Goods"
        },
        {
            "category":"Manufacturing",
            "subcategory":"Motor Vehicles & Parts",
            "type":"Manufacturing & Wholesale Goods"
        }
    ],
    "sg:phone":"+1 301 670 1078",
    "sg:postcode":"20879",
    "sg:province":"MD",
    "sg:tags":[
        "performance",
        "race",
        "fabricator",
        "dealer",
        "car"
    ],
    "wof:name":"Rizzoli Competition Designs",
    "wof:placetype":"venue"
},
  "geometry": {"coordinates":[-77.161991,39.170146],"type":"Point"}
}