{
  "type": "Feature",
  "properties": {
    "addr:full":"5199 Raynor Ave Linthicum Heights MD 21090",
    "addr:housenumber":"5199",
    "addr:postcode":"21090",
    "addr:street":"Raynor Ave",
    "iso:country":"US",
    "sg:address":"5199 Raynor Ave",
    "sg:city":"Linthicum Heights",
    "sg:classifiers":[
        {
            "category":"Building & Trades",
            "subcategory":"Cleaning & Sanitation",
            "type":"Services"
        },
        {
            "category":"Home & Garden",
            "subcategory":"Carpets & Floor Coverings",
            "type":"Retail Goods"
        }
    ],
    "sg:phone":"+1 410 789 1155",
    "sg:postcode":"21090",
    "sg:province":"MD",
    "sg:tags":[
        "carpeting"
    ],
    "wof:name":"Carpet Liquidators",
    "wof:placetype":"venue"
},
  "geometry": {"coordinates":[-76.65920300000001,39.222401],"type":"Point"}
}