{
  "type": "Feature",
  "properties": {
    "iso:country":"US",
    "sg:address":"4400 Solomons Island Rd",
    "sg:city":"Harwood",
    "sg:classifiers":[
        {
            "category":"Education",
            "subcategory":"School",
            "type":"Public Place"
        }
    ],
    "sg:phone":"+1 410 867 7100",
    "sg:postcode":"20776",
    "sg:province":"MD",
    "wof:name":"Southern Senior High School",
    "wof:placetype":"venue"
},
  "geometry": {"coordinates":[-76.61102099999999,38.874109],"type":"Point"}
}