{
  "type": "Feature",
  "properties": {
    "iso:country":"US",
    "sg:address":"222 Herrington Ln",
    "sg:city":"Oakland",
    "sg:classifiers":[
        {
            "category":"Government",
            "subcategory":"Office",
            "type":"Public Place"
        }
    ],
    "sg:phone":"+1 301 387 6938",
    "sg:postcode":"21550",
    "sg:province":"MD",
    "sg:tags":[
        "state",
        "park"
    ],
    "wof:name":"Swallow Falls State Park",
    "wof:placetype":"venue"
},
  "geometry": {"coordinates":[-79.448185,39.453867],"type":"Point"}
}