{
  "type": "Feature",
  "properties": {
    "addr:full":"10215 Maxine St Ellicott City MD 21042",
    "addr:housenumber":"10215",
    "addr:postcode":"21042",
    "addr:street":"Maxine St",
    "iso:country":"US",
    "sg:address":"10215 Maxine St",
    "sg:city":"Ellicott City",
    "sg:classifiers":[
        {
            "category":"Real Estate",
            "subcategory":"Developer",
            "type":"Services"
        }
    ],
    "sg:phone":"+1 410 960 3648",
    "sg:postcode":"21042",
    "sg:province":"MD",
    "sg:tags":[
        "residential",
        "construction",
        "sub",
        "contractor"
    ],
    "wof:name":"Vall Properties LLC",
    "wof:placetype":"venue"
},
  "geometry": {"coordinates":[-76.86681799999999,39.245813],"type":"Point"}
}