{
  "type": "Feature",
  "properties": {
    "addr:full":"308 Huntsman Ct Bel Air MD 21015",
    "addr:housenumber":"308",
    "addr:postcode":"21015",
    "addr:street":"Huntsman Ct",
    "iso:country":"US",
    "sg:address":"308 Huntsman Ct",
    "sg:city":"Bel Air",
    "sg:classifiers":[
        {
            "category":"Professional",
            "subcategory":"Business Services",
            "type":"Services"
        }
    ],
    "sg:phone":"+1 410 515 1890",
    "sg:postcode":"21015",
    "sg:province":"MD",
    "wof:name":"Spanish Connection Inc",
    "wof:placetype":"venue"
},
  "geometry": {"coordinates":[-76.31932500000001,39.499137],"type":"Point"}
}