{
  "type": "Feature",
  "properties": {
    "iso:country":"US",
    "sg:address":"41690 Court House Dr",
    "sg:city":"Leonardtown",
    "sg:classifiers":[
        {
            "category":"Manufacturing",
            "subcategory":"Printing",
            "type":"Manufacturing & Wholesale Goods"
        }
    ],
    "sg:phone":"+1 301 475 5531",
    "sg:postcode":"20650",
    "sg:province":"MD",
    "sg:tags":[
        "commercial"
    ],
    "wof:name":"Printing Press Inc",
    "wof:placetype":"venue"
},
  "geometry": {"coordinates":[-76.910456,38.645483],"type":"Point"}
}