{
  "type": "Feature",
  "properties": {
    "iso:country":"US",
    "sg:address":"3539 Clipper Mill Rd",
    "sg:city":"Baltimore",
    "sg:classifiers":[
        {
            "category":"Professional",
            "subcategory":"Research",
            "type":"Services"
        },
        {
            "category":"Education",
            "subcategory":"Library",
            "type":"Public Place"
        }
    ],
    "sg:phone":"+1 410 235 6644",
    "sg:postcode":"21211",
    "sg:province":"MD",
    "wof:name":"Devmark Inc",
    "wof:placetype":"venue"
},
  "geometry": {"coordinates":[-76.640354,39.328215],"type":"Point"}
}