{
  "type": "Feature",
  "properties": {
    "iso:country":"US",
    "sg:address":"11908 Darnestown Rd",
    "sg:city":"Gaithersburg",
    "sg:classifiers":[
        {
            "category":"Health Services",
            "subcategory":"Dentist",
            "type":"Services"
        }
    ],
    "sg:phone":"+1 877 363 5781",
    "sg:postcode":"20878",
    "sg:province":"MD",
    "sg:tags":[
        "clinic",
        "dental",
        "dentistry",
        "dentists-cosmetic",
        "hygienist"
    ],
    "sg:website":"http://local.ingenio.com/Listings/Details.aspx?NUM=a%3a10352579%3a13%3a4859924%3a14%3a0%3a7",
    "wof:name":"Dr Gail M Davis DDS",
    "wof:placetype":"venue"
},
  "geometry": {"coordinates":[-77.24602299999999,39.115522],"type":"Point"}
}