{
  "type": "Feature",
  "properties": {
    "iso:country":"US",
    "sg:address":"4660 Suitland Rd",
    "sg:city":"Suitland",
    "sg:classifiers":[
        {
            "category":"Social Services",
            "type":"Services"
        }
    ],
    "sg:phone":"+1 301 967 1822",
    "sg:postcode":"20746",
    "sg:province":"MD",
    "sg:tags":[
        "youth",
        "organization",
        "center"
    ],
    "sg:website":"www.roja.bigstep.com",
    "wof:name":"ROJA Productions Inc",
    "wof:placetype":"venue"
},
  "geometry": {"coordinates":[-76.928054,38.850431],"type":"Point"}
}