{
  "type": "Feature",
  "properties": {
    "addr:full":"703 Amer Dr Fort Washington MD 20744",
    "addr:housenumber":"703",
    "addr:postcode":"20744",
    "addr:street":"Amer Dr",
    "iso:country":"US",
    "sg:address":"703 Amer Dr",
    "sg:city":"Fort Washington",
    "sg:classifiers":[
        {
            "category":"Professional",
            "subcategory":"Management & Consulting",
            "type":"Services"
        }
    ],
    "sg:phone":"+1 301 203 5300",
    "sg:postcode":"20744",
    "sg:province":"MD",
    "sg:tags":[
        "consultant",
        "business"
    ],
    "wof:name":"Integrated Management Resorce",
    "wof:placetype":"venue"
},
  "geometry": {"coordinates":[-77.01342200000001,38.73383],"type":"Point"}
}