{
  "type": "Feature",
  "properties": {
    "addr:full":"4962 Fairmont Ave Bethesda MD 20814",
    "addr:housenumber":"4962",
    "addr:postcode":"20814",
    "addr:street":"Fairmont Ave",
    "iso:country":"US",
    "sg:address":"4962 Fairmont Ave",
    "sg:city":"Bethesda",
    "sg:classifiers":[
        {
            "category":"Professional",
            "subcategory":"Computer Services",
            "type":"Services"
        }
    ],
    "sg:phone":"+1 240 880 4400",
    "sg:postcode":"20814",
    "sg:province":"MD",
    "sg:website":"http://www.koolspan.com",
    "wof:name":"KoolSpan",
    "wof:placetype":"venue"
},
  "geometry": {"coordinates":[-77.09723700000001,38.987909],"type":"Point"}
}