{
  "type": "Feature",
  "properties": {
    "addr:full":"131 Little Quarry Rd Gaithersburg MD 20878",
    "addr:housenumber":"131",
    "addr:postcode":"20878",
    "addr:street":"Little Quarry Rd",
    "iso:country":"US",
    "sg:address":"131 Little Quarry Rd",
    "sg:city":"Gaithersburg",
    "sg:classifiers":[
        {
            "category":"Professional",
            "subcategory":"Lawyer & Legal Services",
            "type":"Services"
        }
    ],
    "sg:phone":"+1 301 869 4247",
    "sg:postcode":"20878",
    "sg:province":"MD",
    "wof:name":"Howard Simcox Jr",
    "wof:placetype":"venue"
},
  "geometry": {"coordinates":[-77.24626000000001,39.117767],"type":"Point"}
}