{
  "type": "Feature",
  "properties": {
    "iso:country":"US",
    "sg:address":"7105 Allentown Rd",
    "sg:city":"Fort Washington",
    "sg:classifiers":[
        {
            "category":"Retail",
            "subcategory":"Laundry & Dry Cleaning",
            "type":"Services"
        }
    ],
    "sg:phone":"+1 301 449 4451",
    "sg:postcode":"20744",
    "sg:province":"MD",
    "sg:tags":[
        "cleaners"
    ],
    "wof:name":"VIP Cleaners",
    "wof:placetype":"venue"
},
  "geometry": {"coordinates":[-76.928931,38.793255],"type":"Point"}
}