{
  "type": "Feature",
  "properties": {
    "addr:full":"7105 Allentown Rd Fort Washington MD 20744",
    "addr:housenumber":"7105",
    "addr:postcode":"20744",
    "addr:street":"Allentown Rd",
    "iso:country":"US",
    "sg:address":"7105 Allentown Rd",
    "sg:city":"Fort Washington",
    "sg:classifiers":[
        {
            "category":"Retail",
            "subcategory":"Laundry & Dry Cleaning",
            "type":"Services"
        }
    ],
    "sg:phone":"+1 301 449 4451",
    "sg:postcode":"20744",
    "sg:province":"MD",
    "sg:tags":[
        "cleaners"
    ],
    "wof:name":"VIP Cleaners",
    "wof:placetype":"venue"
},
  "geometry": {"coordinates":[-76.92893100000001,38.793255],"type":"Point"}
}