{
  "type": "Feature",
  "properties": {
    "iso:country":"US",
    "sg:address":"106 Pembrooke View Ln",
    "sg:city":"Gaithersburg",
    "sg:classifiers":[
        {
            "category":"Recreation",
            "type":"Entertainment"
        }
    ],
    "sg:phone":"+1 301 519 9263",
    "sg:postcode":"20877",
    "sg:province":"MD",
    "sg:tags":[
        "entertainers-family",
        "business"
    ],
    "wof:name":"His.Story Entertainment",
    "wof:placetype":"venue"
},
  "geometry": {"coordinates":[-77.17395,39.148731],"type":"Point"}
}