{
  "type": "Feature",
  "properties": {
    "addr:full":"520 Chesapeake Dr Bel Air MD 21078",
    "addr:housenumber":"520",
    "addr:postcode":"21078",
    "addr:street":"Chesapeake Dr",
    "iso:country":"US",
    "sg:address":"520 Chesapeake Dr",
    "sg:city":"Bel Air",
    "sg:classifiers":[
        {
            "category":"Health Services",
            "subcategory":"Doctor",
            "type":"Services"
        }
    ],
    "sg:phone":"+1 410 638 7544",
    "sg:postcode":"21078",
    "sg:province":"MD",
    "sg:tags":[
        "physician",
        "surgeon"
    ],
    "wof:name":"Pulmonary & Critical Care",
    "wof:placetype":"venue"
},
  "geometry": {"coordinates":[-76.09365200000001,39.538409],"type":"Point"}
}