{
  "type": "Feature",
  "properties": {
    "addr:full":"6210 Reisterstown Rd Baltimore MD 21215",
    "addr:housenumber":"6210",
    "addr:postcode":"21215",
    "addr:street":"Reisterstown Rd",
    "iso:country":"US",
    "sg:address":"6210 Reisterstown Rd",
    "sg:city":"Baltimore",
    "sg:classifiers":[
        {
            "category":"Personal",
            "subcategory":"Barber",
            "type":"Services"
        }
    ],
    "sg:phone":"+1 443 872 5169",
    "sg:postcode":"21215",
    "sg:province":"MD",
    "wof:name":"The Men's Room",
    "wof:placetype":"venue"
},
  "geometry": {"coordinates":[-76.699127,39.353715],"type":"Point"}
}