{
  "type": "Feature",
  "properties": {
    "addr:full":"205 S Hays St Bel Air MD 21014",
    "addr:housenumber":"205",
    "addr:postcode":"21014",
    "addr:street":"S Hays St",
    "iso:country":"US",
    "sg:address":"205 S Hays St",
    "sg:city":"Bel Air",
    "sg:classifiers":[
        {
            "category":"Organizations",
            "subcategory":"Non-profit Organization",
            "type":"Services"
        }
    ],
    "sg:phone":"+1 410 638 4434",
    "sg:postcode":"21014",
    "sg:province":"MD",
    "sg:tags":[
        "human"
    ],
    "wof:name":"Habitat For Humanity",
    "wof:placetype":"venue"
},
  "geometry": {"coordinates":[-76.349672,39.533019],"type":"Point"}
}