{
  "type": "Feature",
  "properties": {
    "addr:full":"881 Wilson Rd Rising Sun MD 21911",
    "addr:housenumber":"881",
    "addr:postcode":"21911",
    "addr:street":"Wilson Rd",
    "iso:country":"US",
    "sg:address":"881 Wilson Rd",
    "sg:city":"Rising Sun",
    "sg:classifiers":[
        {
            "category":"Wholesale",
            "subcategory":"Farm Supplies",
            "type":"Manufacturing & Wholesale Goods"
        }
    ],
    "sg:phone":"+1 410 658 5518",
    "sg:postcode":"21911",
    "sg:province":"MD",
    "sg:tags":[
        "fertilizer"
    ],
    "wof:name":"Southern States Cooperative",
    "wof:placetype":"venue"
},
  "geometry": {"coordinates":[-76.011639,39.707411],"type":"Point"}
}