{
  "type": "Feature",
  "properties": {
    "iso:country":"US",
    "sg:address":"11425 Grandview Ave",
    "sg:city":"Wheaton",
    "sg:classifiers":[
        {
            "category":"Food & Beverages",
            "subcategory":"Groceries & Convenience Stores",
            "type":"Retail Goods"
        }
    ],
    "sg:phone":"+1 301 942 8412",
    "sg:postcode":"20902",
    "sg:province":"MD",
    "sg:tags":[
        "grocer"
    ],
    "wof:name":"Brazilian Market",
    "wof:placetype":"venue"
},
  "geometry": {"coordinates":[-77.053089,39.042886],"type":"Point"}
}