{
  "type": "Feature",
  "properties": {
    "addr:full":"4837 Evergreen Rd Oxford MD 21654",
    "addr:housenumber":"4837",
    "addr:postcode":"21654",
    "addr:street":"Evergreen Rd",
    "iso:country":"US",
    "sg:address":"4837 Evergreen Rd",
    "sg:city":"Oxford",
    "sg:classifiers":[
        {
            "category":"Travel",
            "subcategory":"Hotels & Motels",
            "type":"Entertainment"
        }
    ],
    "sg:phone":"+1 410 226 5353",
    "sg:postcode":"21654",
    "sg:province":"MD",
    "sg:tags":[
        "breakfast",
        "accommodation",
        "bed"
    ],
    "wof:name":"Combs Berry",
    "wof:placetype":"venue"
},
  "geometry": {"coordinates":[-76.14032899999999,38.684723],"type":"Point"}
}