{
  "type": "Feature",
  "properties": {
    "iso:country":"US",
    "sg:address":"501 N Calvert St",
    "sg:city":"Baltimore",
    "sg:classifiers":[
        {
            "category":"Shopping",
            "type":"Retail Goods"
        }
    ],
    "sg:phone":"+1 410 659 0243",
    "sg:postcode":"21202",
    "sg:province":"MD",
    "sg:tags":[
        "mobile",
        "phone",
        "telephone",
        "cellular"
    ],
    "sg:website":"www.celloneusa.com",
    "wof:name":"Cellular One",
    "wof:placetype":"venue"
},
  "geometry": {"coordinates":[-76.612584,39.295862],"type":"Point"}
}