{
  "type": "Feature",
  "properties": {
    "iso:country":"US",
    "sg:address":"4046 Lyndale Ave",
    "sg:city":"Baltimore",
    "sg:classifiers":[
        {
            "category":"Restaurant",
            "type":"Food & Drink"
        }
    ],
    "sg:phone":"+1 410 483 5670",
    "sg:postcode":"21213",
    "sg:province":"MD",
    "sg:tags":[
        "eating"
    ],
    "wof:name":"2 Bad Sistah Catering",
    "wof:placetype":"venue"
},
  "geometry": {"coordinates":[-76.559065,39.318992],"type":"Point"}
}