{
  "type": "Feature",
  "properties": {
    "addr:full":"8432 Hallmark Cir Baltimore MD 21234",
    "addr:housenumber":"8432",
    "addr:postcode":"21234",
    "addr:street":"Hallmark Cir",
    "iso:country":"US",
    "sg:address":"8432 Hallmark Cir",
    "sg:city":"Baltimore",
    "sg:classifiers":[
        {
            "category":"Wholesale",
            "subcategory":"Seafood",
            "type":"Manufacturing & Wholesale Goods"
        }
    ],
    "sg:phone":"+1 410 665 3355",
    "sg:postcode":"21234",
    "sg:province":"MD",
    "wof:name":"First In Fishing Crabbing LLC",
    "wof:placetype":"venue"
},
  "geometry": {"coordinates":[-76.524866,39.374044],"type":"Point"}
}