{
  "type": "Feature",
  "properties": {
    "iso:country":"US",
    "sg:address":"511 Shenandoah Ave",
    "sg:city":"Oakland",
    "sg:classifiers":[
        {
            "category":"Building & Trades",
            "subcategory":"Construction",
            "type":"Services"
        }
    ],
    "sg:phone":"+1 301 334 8471",
    "sg:postcode":"21550",
    "sg:province":"MD",
    "sg:tags":[
        "contractor"
    ],
    "wof:name":"L & M Masonry",
    "wof:placetype":"venue"
},
  "geometry": {"coordinates":[-79.374775,39.389075],"type":"Point"}
}