{
  "type": "Feature",
  "properties": {
    "addr:full":"104 Elaine Ave Westminster MD 21157",
    "addr:housenumber":"104",
    "addr:postcode":"21157",
    "addr:street":"Elaine Ave",
    "iso:country":"US",
    "sg:address":"104 Elaine Ave",
    "sg:city":"Westminster",
    "sg:classifiers":[
        {
            "category":"Building & Trades",
            "subcategory":"Construction",
            "type":"Services"
        }
    ],
    "sg:phone":"+1 410 871 2105",
    "sg:postcode":"21157",
    "sg:province":"MD",
    "sg:tags":[
        "house"
    ],
    "wof:name":"Livingston Homes",
    "wof:placetype":"venue"
},
  "geometry": {"coordinates":[-77.003012,39.517864],"type":"Point"}
}