{
  "type": "Feature",
  "properties": {
    "addr:full":"2717 Wilmarco Ave Baltimore MD 21223",
    "addr:housenumber":"2717",
    "addr:postcode":"21223",
    "addr:street":"Wilmarco Ave",
    "iso:country":"US",
    "sg:address":"2717 Wilmarco Ave",
    "sg:city":"Baltimore",
    "sg:classifiers":[
        {
            "category":"Professional",
            "type":"Services"
        }
    ],
    "sg:phone":"+1 410 947 5063",
    "sg:postcode":"21223",
    "sg:province":"MD",
    "sg:tags":[
        "establishment"
    ],
    "wof:name":"Maryland Thermoform Inc",
    "wof:placetype":"venue"
},
  "geometry": {"coordinates":[-76.658489,39.273468],"type":"Point"}
}