{
  "type": "Feature",
  "properties": {
    "addr:full":"1002 Frederick Rd Catonsville MD 21228",
    "addr:housenumber":"1002",
    "addr:postcode":"21228",
    "addr:street":"Frederick Rd",
    "iso:country":"US",
    "sg:address":"1002 Frederick Rd",
    "sg:city":"Catonsville",
    "sg:classifiers":[
        {
            "category":"Professional",
            "subcategory":"Engineering",
            "type":"Services"
        }
    ],
    "sg:phone":"+1 410 744 8367",
    "sg:postcode":"21228",
    "sg:province":"MD",
    "sg:tags":[
        "engineer"
    ],
    "wof:name":"Medcon",
    "wof:placetype":"venue"
},
  "geometry": {"coordinates":[-76.73847600000001,39.270447],"type":"Point"}
}