{
  "type": "Feature",
  "properties": {
    "addr:full":"608 Blandford St Rockville MD 20850",
    "addr:housenumber":"608",
    "addr:postcode":"20850",
    "addr:street":"Blandford St",
    "iso:country":"US",
    "sg:address":"608 Blandford St",
    "sg:city":"Rockville",
    "sg:classifiers":[
        {
            "category":"Building & Trades",
            "subcategory":"Cleaning & Sanitation",
            "type":"Services"
        }
    ],
    "sg:phone":"+1 301 738 3959",
    "sg:postcode":"20850",
    "sg:province":"MD",
    "sg:tags":[
        "janitor"
    ],
    "wof:name":"Santos & Assoc",
    "wof:placetype":"venue"
},
  "geometry": {"coordinates":[-77.15190800000001,39.075377],"type":"Point"}
}