{
  "type": "Feature",
  "properties": {
    "iso:country":"US",
    "sg:address":"223 Brierhill Dr",
    "sg:city":"Bel Air",
    "sg:classifiers":[
        {
            "category":"Banks & Credit Unions",
            "subcategory":"Bank",
            "type":"Services"
        }
    ],
    "sg:phone":"+1 410 638 8006",
    "sg:postcode":"21015",
    "sg:province":"MD",
    "sg:tags":[
        "loan",
        "real estate"
    ],
    "wof:name":"Beneficial Maryland Inc",
    "wof:placetype":"venue"
},
  "geometry": {"coordinates":[-76.326182,39.541385],"type":"Point"}
}