{
  "type": "Feature",
  "properties": {
    "iso:country":"US",
    "sg:address":"803 Snow Hill Rd",
    "sg:city":"Salisbury",
    "sg:classifiers":[
        {
            "category":"Professional",
            "type":"Services"
        }
    ],
    "sg:phone":"+1 410 334 6532",
    "sg:postcode":"21804",
    "sg:province":"MD",
    "wof:name":"Wicomico Memorial Svc",
    "wof:placetype":"venue"
},
  "geometry": {"coordinates":[-75.584862,38.352606],"type":"Point"}
}