{
  "type": "Feature",
  "properties": {
    "addr:full":"16 N Central Ave Ridgely MD 21660",
    "addr:housenumber":"16",
    "addr:postcode":"21660",
    "addr:street":"N Central Ave",
    "iso:country":"US",
    "sg:address":"16 N Central Ave",
    "sg:city":"Ridgely",
    "sg:classifiers":[
        {
            "category":"Real Estate",
            "subcategory":"Real Estate Agent",
            "type":"Services"
        }
    ],
    "sg:phone":"+1 410 820 1287",
    "sg:postcode":"21660",
    "sg:province":"MD",
    "wof:name":"Old Bay Realty Inc",
    "wof:placetype":"venue"
},
  "geometry": {"coordinates":[-75.883712,38.946639],"type":"Point"}
}