{
  "type": "Feature",
  "properties": {
    "addr:full":"301 N Front St Baltimore MD 21202",
    "addr:housenumber":"301",
    "addr:postcode":"21202",
    "addr:street":"N Front St",
    "iso:country":"US",
    "sg:address":"301 N Front St",
    "sg:city":"Baltimore",
    "sg:classifiers":[
        {
            "category":"Professional",
            "subcategory":"Business Services",
            "type":"Services"
        }
    ],
    "sg:phone":"+1 410 752 4141",
    "sg:postcode":"21202",
    "sg:province":"MD",
    "sg:tags":[
        "recording",
        "studio"
    ],
    "wof:name":"Phat Tracks Recording Std",
    "wof:placetype":"venue"
},
  "geometry": {"coordinates":[-76.60768299999999,39.293102],"type":"Point"}
}