{
  "type": "Feature",
  "properties": {
    "addr:full":"803 Central Ave Linthicum Hts MD 21090",
    "addr:housenumber":"803",
    "addr:postcode":"21090",
    "addr:street":"Central Ave",
    "iso:country":"US",
    "sg:address":"803 Central Ave",
    "sg:city":"Linthicum Hts",
    "sg:classifiers":[
        {
            "category":"Autos & Motor Vehicles",
            "subcategory":"Automobile Sales",
            "type":"Retail Goods"
        }
    ],
    "sg:phone":"+1 410 636 9330",
    "sg:postcode":"21090",
    "sg:province":"MD",
    "sg:tags":[
        "truck"
    ],
    "wof:name":"Baltimore Volvo",
    "wof:placetype":"venue"
},
  "geometry": {"coordinates":[-76.65607900000001,39.22666],"type":"Point"}
}