{
  "type": "Feature",
  "properties": {
    "addr:full":"15298 Union Chapel Rd Woodbine MD 21797",
    "addr:housenumber":"15298",
    "addr:postcode":"21797",
    "addr:street":"Union Chapel Rd",
    "iso:country":"US",
    "sg:address":"15298 Union Chapel Rd",
    "sg:city":"Woodbine",
    "sg:phone":"+1 877 458 6825",
    "sg:postcode":"21797",
    "sg:province":"MD",
    "sg:website":"http://www.digseptic.com",
    "wof:name":"Total Septic",
    "wof:placetype":"venue"
},
  "geometry": {"coordinates":[-77.045303,39.292999],"type":"Point"}
}