{
  "type": "Feature",
  "properties": {
    "iso:country":"US",
    "sg:address":"105 2nd St",
    "sg:city":"Ocean City",
    "sg:classifiers":[
        {
            "category":"Real Estate",
            "subcategory":"Real Estate Operator",
            "type":"Services"
        }
    ],
    "sg:phone":"+1 410 289 2179",
    "sg:postcode":"21842",
    "sg:province":"MD",
    "sg:tags":[
        "apartment"
    ],
    "wof:name":"Parks Ocean Block Efficiency",
    "wof:placetype":"venue"
},
  "geometry": {"coordinates":[-75.085121,38.333521],"type":"Point"}
}