{
  "type": "Feature",
  "properties": {
    "iso:country":"US",
    "sg:address":"213 Cinnamon Ln",
    "sg:city":"Edgewater",
    "sg:classifiers":[
        {
            "category":"Manufacturing",
            "subcategory":"Tools & Machinery",
            "type":"Manufacturing & Wholesale Goods"
        },
        {
            "category":"Retail",
            "subcategory":"Repair Shop",
            "type":"Services"
        }
    ],
    "sg:phone":"+1 410 798 5442",
    "sg:postcode":"21037",
    "sg:province":"MD",
    "sg:tags":[
        "machine",
        "machinery-rebuild"
    ],
    "wof:name":"Almax Co",
    "wof:placetype":"venue"
},
  "geometry": {"coordinates":[-76.556107,38.968891],"type":"Point"}
}