{
  "type": "Feature",
  "properties": {
    "addr:full":"338 Brunswick Pl Riva MD 21140",
    "addr:housenumber":"338",
    "addr:postcode":"21140",
    "addr:street":"Brunswick Pl",
    "iso:country":"US",
    "sg:address":"338 Brunswick Pl",
    "sg:city":"Riva",
    "sg:classifiers":[
        {
            "category":"Professional",
            "subcategory":"Business Services",
            "type":"Services"
        }
    ],
    "sg:phone":"+1 410 956 5586",
    "sg:postcode":"21140",
    "sg:province":"MD",
    "wof:name":"J&K Assoc",
    "wof:placetype":"venue"
},
  "geometry": {"coordinates":[-76.588632,38.948347],"type":"Point"}
}