{
  "type": "Feature",
  "properties": {
    "addr:full":"14024 Teaneck Ter Gaithersburg MD 20878",
    "addr:housenumber":"14024",
    "addr:postcode":"20878",
    "addr:street":"Teaneck Ter",
    "iso:country":"US",
    "sg:address":"14024 Teaneck Ter",
    "sg:city":"Gaithersburg",
    "sg:classifiers":[
        {
            "category":"Insurance",
            "subcategory":"Insurance Agent",
            "type":"Services"
        }
    ],
    "sg:phone":"+1 301 424 9464",
    "sg:postcode":"20878",
    "sg:province":"MD",
    "wof:name":"Pamela G Nicholson",
    "wof:placetype":"venue"
},
  "geometry": {"coordinates":[-77.24433399999999,39.087401],"type":"Point"}
}