{
  "type": "Feature",
  "properties": {
    "iso:country":"US",
    "sg:address":"7412 Harford Rd",
    "sg:city":"Baltimore",
    "sg:classifiers":[
        {
            "category":"Education",
            "subcategory":"School",
            "type":"Public Place"
        }
    ],
    "sg:phone":"+1 410 668 5308",
    "sg:postcode":"21234",
    "sg:province":"MD",
    "wof:name":"Coldspring Dev Ctr Ucp",
    "wof:placetype":"venue"
},
  "geometry": {"coordinates":[-76.545266,39.371113],"type":"Point"}
}