{
  "type": "Feature",
  "properties": {
    "iso:country":"US",
    "sg:address":"6209 Marlboro Pike",
    "sg:city":"District Heights",
    "sg:classifiers":[
        {
            "category":"Shopping",
            "subcategory":"Beauty & Cosmetics",
            "type":"Retail Goods"
        }
    ],
    "sg:phone":"+1 301 420 0202",
    "sg:postcode":"20747",
    "sg:province":"MD",
    "sg:tags":[
        "supply"
    ],
    "wof:name":"Kat's Beauty Supplies",
    "wof:placetype":"venue"
},
  "geometry": {"coordinates":[-76.90061,38.855035],"type":"Point"}
}