{
  "type": "Feature",
  "properties": {
    "iso:country":"US",
    "sg:address":"6725 Averill Rd",
    "sg:city":"Baltimore",
    "sg:classifiers":[
        {
            "category":"Professional",
            "type":"Services"
        }
    ],
    "sg:phone":"+1 301 863 4977",
    "sg:postcode":"21237",
    "sg:province":"MD",
    "sg:tags":[
        "technical",
        "writing"
    ],
    "wof:name":"Isis Group",
    "wof:placetype":"venue"
},
  "geometry": {"coordinates":[-76.487848,39.345021],"type":"Point"}
}