{
  "type": "Feature",
  "properties": {
    "addr:full":"6942 Laurel Bowie Rd Bowie MD 20715",
    "addr:housenumber":"6942",
    "addr:postcode":"20715",
    "addr:street":"Laurel Bowie Rd",
    "iso:country":"US",
    "sg:address":"6942 Laurel Bowie Rd",
    "sg:city":"Bowie",
    "sg:classifiers":[
        {
            "category":"Wholesale",
            "subcategory":"Medical Equipment & Supplies",
            "type":"Manufacturing & Wholesale Goods"
        }
    ],
    "sg:phone":"+1 301 262 0027",
    "sg:postcode":"20715",
    "sg:province":"MD",
    "sg:tags":[
        "physician",
        "surgeon"
    ],
    "wof:name":"American Home Medical Inc",
    "wof:placetype":"venue"
},
  "geometry": {"coordinates":[-76.757631,38.986253],"type":"Point"}
}