{
  "type": "Feature",
  "properties": {
    "iso:country":"US",
    "sg:address":"12200 River Rd",
    "sg:city":"Potomac",
    "sg:classifiers":[
        {
            "category":"Building & Trades",
            "subcategory":"Construction",
            "type":"Services"
        }
    ],
    "sg:phone":"+1 301 765 9702",
    "sg:postcode":"20854",
    "sg:province":"MD",
    "sg:tags":[
        "general",
        "contractor"
    ],
    "wof:name":"Johnston Construction Co",
    "wof:placetype":"venue"
},
  "geometry": {"coordinates":[-77.260795,39.044349],"type":"Point"}
}