{
  "type": "Feature",
  "properties": {
    "addr:full":"2931 Francis Scott Key Hwy Taneytown MD 21787",
    "addr:housenumber":"2931",
    "addr:postcode":"21787",
    "addr:street":"Francis Scott Key Hwy",
    "iso:country":"US",
    "sg:address":"2931 Francis Scott Key Hwy",
    "sg:city":"Taneytown",
    "sg:classifiers":[
        {
            "category":"Wholesale",
            "subcategory":"Stationery",
            "type":"Manufacturing & Wholesale Goods"
        }
    ],
    "sg:phone":"+1 410 756 9061",
    "sg:postcode":"21787",
    "sg:province":"MD",
    "sg:tags":[
        "box",
        "fiber"
    ],
    "wof:name":"F P Duffy Inc",
    "wof:placetype":"venue"
},
  "geometry": {"coordinates":[-77.18196399999999,39.655474],"type":"Point"}
}