{
  "type": "Feature",
  "properties": {
    "addr:full":"13329 Foxden Dr Rockville MD 20850",
    "addr:postcode":"13329;20850",
    "addr:street":"Foxden Dr",
    "iso:country":"US",
    "sg:address":"13329 Foxden Dr",
    "sg:city":"Rockville",
    "sg:classifiers":[
        {
            "category":"Building & Trades",
            "subcategory":"Landscaping Services",
            "type":"Services"
        }
    ],
    "sg:phone":"+1 301 610 6611",
    "sg:postcode":"20850",
    "sg:province":"MD",
    "sg:tags":[
        "landscape"
    ],
    "wof:name":"Landworks Unlimited Inc",
    "wof:placetype":"venue"
},
  "geometry": {"coordinates":[-77.193442,39.075904],"type":"Point"}
}