{
  "type": "Feature",
  "properties": {
    "addr:full":"5750 Rabbit Knaw Rd Stockton MD 21864",
    "addr:housenumber":"5750",
    "addr:postcode":"21864",
    "addr:street":"Rabbit Knaw Rd",
    "iso:country":"US",
    "sg:address":"5750 Rabbit Knaw Rd",
    "sg:city":"Stockton",
    "sg:classifiers":[
        {
            "category":"Farming",
            "subcategory":"Farm",
            "type":"Manufacturing & Wholesale Goods"
        }
    ],
    "sg:phone":"+1 410 632 1499",
    "sg:postcode":"21864",
    "sg:province":"MD",
    "wof:name":"Lambertson Farms Inc",
    "wof:placetype":"venue"
},
  "geometry": {"coordinates":[-75.407551,38.020104],"type":"Point"}
}