{
  "type": "Feature",
  "properties": {
    "iso:country":"US",
    "sg:address":"3936 S Main St",
    "sg:city":"Trappe",
    "sg:classifiers":[
        {
            "category":"Organizations",
            "subcategory":"Religious Organization",
            "type":"Services"
        }
    ],
    "sg:phone":"+1 410 476 3048",
    "sg:postcode":"21673",
    "sg:province":"MD",
    "sg:tags":[
        "church"
    ],
    "wof:name":"St Paul's Episcopal Chr",
    "wof:placetype":"venue"
},
  "geometry": {"coordinates":[-76.057028,38.65536],"type":"Point"}
}