{
  "type": "Feature",
  "properties": {
    "addr:full":"1009 Cloverdale St Apt 1W Baltimore MD 21217",
    "addr:housenumber":"1009",
    "addr:postcode":"21217",
    "addr:street":"Cloverdale St Apt 1W",
    "iso:country":"US",
    "sg:address":"1009 Cloverdale St Apt 1W",
    "sg:city":"Baltimore",
    "sg:classifiers":[
        {
            "category":"Personal",
            "type":"Services"
        },
        {
            "category":"Professional",
            "subcategory":"Art Services",
            "type":"Services"
        }
    ],
    "sg:phone":"+1 410 889 5945",
    "sg:postcode":"21217",
    "sg:province":"MD",
    "sg:tags":[
        "photography",
        "videography",
        "wedding"
    ],
    "wof:name":"Urban Photo Company",
    "wof:placetype":"venue"
},
  "geometry": {"coordinates":[-76.639332,39.315697],"type":"Point"}
}