{
  "type": "Feature",
  "properties": {
    "iso:country":"US",
    "sg:address":"115 W 25th St",
    "sg:city":"Baltimore",
    "sg:classifiers":[
        {
            "category":"Health Services",
            "subcategory":"Doctor",
            "type":"Services"
        }
    ],
    "sg:phone":"+1 410 467 0137",
    "sg:postcode":"21218",
    "sg:province":"MD",
    "sg:tags":[
        "physician",
        "surgeon"
    ],
    "wof:name":"CTC Communications Corp",
    "wof:placetype":"venue"
},
  "geometry": {"coordinates":[-76.619731,39.317752],"type":"Point"}
}