{
  "type": "Feature",
  "properties": {
    "addr:full":"5832 Hubbard Dr Rockville MD 20852",
    "addr:housenumber":"5832",
    "addr:postcode":"20852",
    "addr:street":"Hubbard Dr",
    "iso:country":"US",
    "sg:address":"5832 Hubbard Dr",
    "sg:city":"Rockville",
    "sg:classifiers":[
        {
            "category":"Health Services",
            "subcategory":"Doctor",
            "type":"Services"
        }
    ],
    "sg:phone":"+1 301 816 7846",
    "sg:postcode":"20852",
    "sg:province":"MD",
    "sg:tags":[
        "surgeon",
        "oral",
        "dentist"
    ],
    "wof:name":"Mimi Nguyen DDS PA",
    "wof:placetype":"venue"
},
  "geometry": {"coordinates":[-77.11900300000001,39.055099],"type":"Point"}
}