{
  "type": "Feature",
  "properties": {
    "iso:country":"US",
    "sg:address":"3399 Branch Ave",
    "sg:city":"Temple Hills",
    "sg:classifiers":[
        {
            "category":"Autos & Motor Vehicles",
            "subcategory":"Fuel & Gas Station",
            "type":"Retail Goods"
        }
    ],
    "sg:phone":"+1 301 894 3222",
    "sg:postcode":"20748",
    "sg:province":"MD",
    "sg:tags":[
        "oil"
    ],
    "wof:name":"Exxon",
    "wof:placetype":"venue"
},
  "geometry": {"coordinates":[-76.95263799999999,38.847263],"type":"Point"}
}