{
  "type": "Feature",
  "properties": {
    "iso:country":"US",
    "sg:address":"638 - A Lofstrand Lane",
    "sg:city":"Rockville",
    "sg:classifiers":[
        {
            "category":"Home & Garden",
            "subcategory":"Home Furnishings",
            "type":"Retail Goods"
        },
        {
            "category":"Building & Trades",
            "subcategory":"Construction",
            "type":"Services"
        },
        {
            "category":"Autos & Motor Vehicles",
            "subcategory":"Auto Supplies",
            "type":"Retail Goods"
        },
        {
            "category":"Retail",
            "subcategory":"Auto Repair",
            "type":"Services"
        },
        {
            "category":"Manufacturing",
            "subcategory":"Glass & Minerals",
            "type":"Manufacturing & Wholesale Goods"
        },
        {
            "category":"Manufacturing",
            "subcategory":"Building Materials",
            "type":"Manufacturing & Wholesale Goods"
        }
    ],
    "sg:phone":"+1 301 984 0544",
    "sg:postcode":"20850",
    "sg:province":"MD",
    "sg:tags":[
        "plate",
        "door",
        "shower",
        "windows-repair",
        "glazier",
        "window",
        "tinting",
        "replacement",
        "glass-wholesale",
        "glass-auto",
        "shape",
        "mirror",
        "installation",
        "circle",
        "windshield",
        "enclosure",
        "special",
        "manufacturer"
    ],
    "sg:website":"http://www.glassdoctor.com/YPland.htm",
    "wof:name":"Glass Doctor Of Montgomery County",
    "wof:placetype":"venue"
},
  "geometry": {"coordinates":[-77.139061,39.093652],"type":"Point"}
}