{
  "type": "Feature",
  "properties": {
    "iso:country":"US",
    "sg:address":"22 5th Ave",
    "sg:city":"Baltimore",
    "sg:classifiers":[
        {
            "category":"Organizations",
            "subcategory":"Community Association",
            "type":"Services"
        }
    ],
    "sg:phone":"+1 410 247 2757",
    "sg:postcode":"21227",
    "sg:province":"MD",
    "sg:tags":[
        "military"
    ],
    "wof:name":"Walter Howard Shaw Vfw 327",
    "wof:placetype":"venue"
},
  "geometry": {"coordinates":[-76.663884,39.241707],"type":"Point"}
}