{
  "type": "Feature",
  "properties": {
    "addr:full":"3401 Urbana Pike Frederick MD 21704",
    "addr:housenumber":"3401",
    "addr:postcode":"21704",
    "addr:street":"Urbana Pike",
    "iso:country":"US",
    "sg:address":"3401 Urbana Pike",
    "sg:city":"Frederick",
    "sg:classifiers":[
        {
            "category":"Professional",
            "subcategory":"Engineering",
            "type":"Services"
        }
    ],
    "sg:phone":"+1 301 874 1110",
    "sg:postcode":"21704",
    "sg:province":"MD",
    "sg:tags":[
        "engineer"
    ],
    "wof:name":"Bridgeteck",
    "wof:placetype":"venue"
},
  "geometry": {"coordinates":[-77.350245,39.325976],"type":"Point"}
}