{
  "type": "Feature",
  "properties": {
    "iso:country":"US",
    "sg:address":"4001 Edmondson Ave",
    "sg:city":"Baltimore",
    "sg:classifiers":[
        {
            "category":"Food & Beverages",
            "subcategory":"Liquor & Beverages",
            "type":"Retail Goods"
        }
    ],
    "sg:phone":"+1 410 566 7240",
    "sg:postcode":"21229",
    "sg:province":"MD",
    "sg:tags":[
        "beer",
        "spirit",
        "wine"
    ],
    "wof:name":"Upland Liquor",
    "wof:placetype":"venue"
},
  "geometry": {"coordinates":[-76.682582,39.293553],"type":"Point"}
}