{
  "type": "Feature",
  "properties": {
    "iso:country":"US",
    "sg:address":"422 Leppo Rd",
    "sg:city":"Westminster",
    "sg:classifiers":[
        {
            "category":"Professional",
            "subcategory":"Art Services",
            "type":"Services"
        }
    ],
    "sg:phone":"+1 410 876 7265",
    "sg:postcode":"21158",
    "sg:province":"MD",
    "sg:tags":[
        "interior",
        "designer",
        "decorator"
    ],
    "wof:name":"Andrew L Muska Inc",
    "wof:placetype":"venue"
},
  "geometry": {"coordinates":[-77.011377,39.700697],"type":"Point"}
}