{
  "type": "Feature",
  "properties": {
    "iso:country":"US",
    "sg:address":"19718 Germantown Rd",
    "sg:city":"Germantown",
    "sg:classifiers":[
        {
            "category":"Coffee & Tea",
            "type":"Food & Drink"
        }
    ],
    "sg:menulink":"http://www.allmenus.com/md/clarksburg/119042-starbucks-coffee/menu/",
    "sg:phone":"+1 301 916 8584",
    "sg:postcode":"20874",
    "sg:province":"MD",
    "sg:tags":[
        "american"
    ],
    "wof:name":"Starbucks Coffee",
    "wof:placetype":"venue"
},
  "geometry": {"coordinates":[-77.264332,39.180376],"type":"Point"}
}