{
  "type": "Feature",
  "properties": {
    "iso:country":"US",
    "sg:address":"4500 Frankford Ave",
    "sg:city":"Baltimore",
    "sg:classifiers":[
        {
            "category":"Organizations",
            "subcategory":"Religious Organization",
            "type":"Services"
        }
    ],
    "sg:phone":"+1 410 488 0054",
    "sg:postcode":"21206",
    "sg:province":"MD",
    "sg:tags":[
        "monastery",
        "convent"
    ],
    "wof:name":"St Anthony's Convent",
    "wof:placetype":"venue"
},
  "geometry": {"coordinates":[-76.548294,39.33468],"type":"Point"}
}