{
  "type": "Feature",
  "properties": {
    "iso:country":"US",
    "sg:address":"100 Railway Ln",
    "sg:city":"Hagerstown",
    "sg:classifiers":[
        {
            "category":"Restaurant",
            "type":"Food & Drink"
        }
    ],
    "sg:menulink":"http://www.allmenus.com/md/halfway/71682-pizza-hut/menu/",
    "sg:phone":"+1 301 739 8263",
    "sg:postcode":"21740",
    "sg:province":"MD",
    "sg:tags":[
        "american",
        "pizza"
    ],
    "wof:name":"Pizza Hut",
    "wof:placetype":"venue"
},
  "geometry": {"coordinates":[-77.764897,39.629096],"type":"Point"}
}