{
  "type": "Feature",
  "properties": {
    "iso:country":"US",
    "sg:address":"3724 Norrisville Rd",
    "sg:city":"Jarrettsville",
    "sg:classifiers":[
        {
            "category":"Building & Trades",
            "subcategory":"Construction",
            "type":"Services"
        }
    ],
    "sg:phone":"+1 410 692 5863",
    "sg:postcode":"21084",
    "sg:province":"MD",
    "sg:tags":[
        "contractor"
    ],
    "wof:name":"Southway Builders",
    "wof:placetype":"venue"
},
  "geometry": {"coordinates":[-76.479206,39.604166],"type":"Point"}
}