{
  "type": "Feature",
  "properties": {
    "iso:country":"US",
    "sg:address":"418 Loblolly Ln",
    "sg:city":"Salisbury",
    "sg:classifiers":[
        {
            "category":"Building & Trades",
            "subcategory":"Electrical",
            "type":"Services"
        }
    ],
    "sg:phone":"+1 410 546 3029",
    "sg:postcode":"21801",
    "sg:province":"MD",
    "sg:tags":[
        "electrical",
        "contractor"
    ],
    "wof:name":"AMP Electrical Services",
    "wof:placetype":"venue"
},
  "geometry": {"coordinates":[-75.612236,38.347515],"type":"Point"}
}