{
  "type": "Feature",
  "properties": {
    "iso:country":"US",
    "sg:address":"1138 Taft St",
    "sg:city":"Rockville",
    "sg:classifiers":[
        {
            "category":"Wholesale",
            "subcategory":"Stationery",
            "type":"Manufacturing & Wholesale Goods"
        }
    ],
    "sg:phone":"+1 301 762 8801",
    "sg:postcode":"20850",
    "sg:province":"MD",
    "sg:tags":[
        "product",
        "paper"
    ],
    "sg:website":"www.cleanorama.com",
    "wof:name":"Laniado Wholesale Co",
    "wof:placetype":"venue"
},
  "geometry": {"coordinates":[-77.137411,39.094142],"type":"Point"}
}