{
  "type": "Feature",
  "properties": {
    "iso:country":"US",
    "sg:address":"962 Wayne Ave",
    "sg:city":"Silver Spring",
    "sg:classifiers":[
        {
            "category":"Organizations",
            "subcategory":"Labor Organization",
            "type":"Services"
        }
    ],
    "sg:phone":"+1 301 562 8131",
    "sg:postcode":"20910",
    "sg:province":"MD",
    "wof:name":"C W A District Two",
    "wof:placetype":"venue"
},
  "geometry": {"coordinates":[-77.02442000000001,38.995399],"type":"Point"}
}