{
  "type": "Feature",
  "properties": {
    "iso:country":"US",
    "sg:address":"398 Stately Dr",
    "sg:city":"Pasadena",
    "sg:classifiers":[
        {
            "category":"Insurance",
            "subcategory":"Insurance Agent",
            "type":"Services"
        },
        {
            "category":"Banks & Credit Unions",
            "subcategory":"Financial Services",
            "type":"Services"
        }
    ],
    "sg:phone":"+1 410 626 0121",
    "sg:postcode":"21122",
    "sg:province":"MD",
    "sg:tags":[
        "counseling",
        "debt",
        "adjuster"
    ],
    "wof:name":"Intercoastal Financial Group I",
    "wof:placetype":"venue"
},
  "geometry": {"coordinates":[-76.467827,39.097031],"type":"Point"}
}