{
  "type": "Feature",
  "properties": {
    "addr:full":"3004 Courtside Rd Bowie MD 20721",
    "addr:housenumber":"3004",
    "addr:postcode":"20721",
    "addr:street":"Courtside Rd",
    "iso:country":"US",
    "sg:address":"3004 Courtside Rd",
    "sg:city":"Bowie",
    "sg:classifiers":[
        {
            "category":"Professional",
            "subcategory":"Testing Lab",
            "type":"Services"
        }
    ],
    "sg:phone":"+1 301 218 1491",
    "sg:postcode":"20721",
    "sg:province":"MD",
    "sg:tags":[
        "laboratory"
    ],
    "wof:name":"John Hargett Associates",
    "wof:placetype":"venue"
},
  "geometry": {"coordinates":[-76.79183399999999,38.930992],"type":"Point"}
}