{
  "type": "Feature",
  "properties": {
    "iso:country":"US",
    "sg:address":"4107 Tiverton Rd",
    "sg:city":"Randallstown",
    "sg:classifiers":[
        {
            "category":"Organizations",
            "subcategory":"Religious Organization",
            "type":"Services"
        }
    ],
    "sg:phone":"+1 410 655 1689",
    "sg:postcode":"21133",
    "sg:province":"MD",
    "sg:tags":[
        "clergy"
    ],
    "wof:name":"William A Thomas",
    "wof:placetype":"venue"
},
  "geometry": {"coordinates":[-76.816453,39.385441],"type":"Point"}
}