{
  "type": "Feature",
  "properties": {
    "iso:country":"US",
    "sg:address":"9 Loveton Cir",
    "sg:city":"Sparks Glencoe",
    "sg:classifiers":[
        {
            "category":"Wholesale",
            "subcategory":"Machinery & Supplies",
            "type":"Manufacturing & Wholesale Goods"
        }
    ],
    "sg:phone":"+1 410 472 0500",
    "sg:postcode":"21152",
    "sg:province":"MD",
    "sg:tags":[
        "hoist"
    ],
    "sg:website":"www.jdnc.com",
    "wof:name":"J D Neuhaus Corp",
    "wof:placetype":"venue"
},
  "geometry": {"coordinates":[-76.648378,39.520005],"type":"Point"}
}