{
  "type": "Feature",
  "properties": {
    "iso:country":"US",
    "sg:address":"5510 Cedella Ave",
    "sg:city":"Baltimore",
    "sg:classifiers":[
        {
            "category":"Education",
            "subcategory":"Special Training",
            "type":"Public Place"
        }
    ],
    "sg:phone":"+1 443 226 0535",
    "sg:postcode":"21206",
    "sg:province":"MD",
    "sg:tags":[
        "educational",
        "tutoring"
    ],
    "sg:website":"http://www.thewebbgroupinc.com/",
    "wof:name":"The Webb Group Inc",
    "wof:placetype":"venue"
},
  "geometry": {"coordinates":[-76.54169400000001,39.332211],"type":"Point"}
}