{
  "type": "Feature",
  "properties": {
    "addr:full":"4517 Valley Forge Dr Rockville MD 20853",
    "addr:housenumber":"4517",
    "addr:postcode":"20853",
    "addr:street":"Valley Forge Dr",
    "iso:country":"US",
    "sg:address":"4517 Valley Forge Dr",
    "sg:city":"Rockville",
    "sg:classifiers":[
        {
            "category":"Professional",
            "subcategory":"Advertising",
            "type":"Services"
        }
    ],
    "sg:phone":"+1 301 924 2400",
    "sg:postcode":"20853",
    "sg:province":"MD",
    "sg:tags":[
        "specialty"
    ],
    "wof:name":"Lyon Advertising Specialties",
    "wof:placetype":"venue"
},
  "geometry": {"coordinates":[-77.090616,39.134093],"type":"Point"}
}