{
  "type": "Feature",
  "properties": {
    "addr:full":"570 Benfield Rd Severna Park MD 21146",
    "addr:housenumber":"570",
    "addr:postcode":"21146",
    "addr:street":"Benfield Rd",
    "iso:country":"US",
    "sg:address":"570 Benfield Rd",
    "sg:city":"Severna Park",
    "sg:classifiers":[
        {
            "category":"Food & Beverages",
            "subcategory":"Specialty",
            "type":"Retail Goods"
        }
    ],
    "sg:phone":"+1 410 647 6602",
    "sg:postcode":"21146",
    "sg:province":"MD",
    "sg:tags":[
        "vitamin"
    ],
    "wof:name":"Good Life Natural Foods Inc",
    "wof:placetype":"venue"
},
  "geometry": {"coordinates":[-76.584598,39.082463],"type":"Point"}
}