{
  "type": "Feature",
  "properties": {
    "addr:full":"14223 Cherry Lane Ct Laurel MD 20707",
    "addr:housenumber":"14223",
    "addr:postcode":"20707",
    "addr:street":"Cherry Lane Ct",
    "iso:country":"US",
    "sg:address":"14223 Cherry Lane Ct",
    "sg:city":"Laurel",
    "sg:classifiers":[
        {
            "category":"Building & Trades",
            "subcategory":"Plumbing",
            "type":"Services"
        }
    ],
    "sg:phone":"+1 301 206 2067",
    "sg:postcode":"20707",
    "sg:province":"MD",
    "sg:tags":[
        "conditioning",
        "air",
        "system",
        "contractor"
    ],
    "wof:name":"CSI Mechanical Inc",
    "wof:placetype":"venue"
},
  "geometry": {"coordinates":[-76.855475,39.087158],"type":"Point"}
}