{
  "type": "Feature",
  "properties": {
    "addr:full":"5302 Norrisville Rd White Hall MD 21161",
    "addr:housenumber":"5302",
    "addr:postcode":"21161",
    "addr:street":"Norrisville Rd",
    "iso:country":"US",
    "sg:address":"5302 Norrisville Rd",
    "sg:city":"White Hall",
    "sg:classifiers":[
        {
            "category":"Education",
            "subcategory":"School",
            "type":"Public Place"
        }
    ],
    "sg:phone":"+1 410 692 7810",
    "sg:postcode":"21161",
    "sg:province":"MD",
    "wof:name":"Norrisville Elementary School",
    "wof:placetype":"venue"
},
  "geometry": {"coordinates":[-76.532971,39.701125],"type":"Point"}
}