{
  "type": "Feature",
  "properties": {
    "iso:country":"US",
    "sg:address":"650 Research Dr",
    "sg:city":"Frederick",
    "sg:classifiers":[
        {
            "category":"Manufacturing",
            "subcategory":"Tools & Machinery",
            "type":"Manufacturing & Wholesale Goods"
        }
    ],
    "sg:phone":"+1 301 846 4196",
    "sg:postcode":"21703",
    "sg:province":"MD",
    "sg:tags":[
        "equipment",
        "welding",
        "supply"
    ],
    "wof:name":"Binzel Abicor",
    "wof:placetype":"venue"
},
  "geometry": {"coordinates":[-77.432565,39.403319],"type":"Point"}
}