{
  "type": "Feature",
  "properties": {
    "iso:country":"US",
    "sg:address":"6974 Lennox Ave",
    "sg:city":"Elkridge",
    "sg:classifiers":[
        {
            "category":"Insurance",
            "subcategory":"Title Insurance",
            "type":"Services"
        }
    ],
    "sg:phone":"+1 410 796 6137",
    "sg:postcode":"21075",
    "sg:province":"MD",
    "sg:website":"http://www.startupinc.us",
    "wof:name":"Startup Inc",
    "wof:placetype":"venue"
},
  "geometry": {"coordinates":[-76.751034,39.179008],"type":"Point"}
}