{
  "type": "Feature",
  "properties": {
    "addr:full":"516 N Charles St Baltimore MD 21201",
    "addr:housenumber":"516",
    "addr:postcode":"21201",
    "addr:street":"N Charles St",
    "iso:country":"US",
    "sg:address":"516 N Charles St",
    "sg:city":"Baltimore",
    "sg:classifiers":[
        {
            "category":"Shopping",
            "subcategory":"Clothing, Apparel, & Fashions",
            "type":"Retail Goods"
        },
        {
            "category":"Shopping",
            "type":"Retail Goods"
        }
    ],
    "sg:phone":"+1 410 347 9348",
    "sg:postcode":"21201",
    "sg:province":"MD",
    "sg:tags":[
        "item",
        "boutique",
        "clothing",
        "store"
    ],
    "wof:name":"Baltimore Advisors",
    "wof:placetype":"venue"
},
  "geometry": {"coordinates":[-76.615529,39.295515],"type":"Point"}
}