{
  "type": "Feature",
  "properties": {
    "iso:country":"US",
    "sg:address":"31415 John Deere Dr",
    "sg:city":"Salisbury",
    "sg:classifiers":[
        {
            "category":"Wholesale",
            "subcategory":"Machinery & Supplies",
            "type":"Manufacturing & Wholesale Goods"
        }
    ],
    "sg:phone":"+1 410 860 0676",
    "sg:postcode":"21804",
    "sg:province":"MD",
    "sg:tags":[
        "farm",
        "equipment"
    ],
    "sg:website":"www.tyndalls.com",
    "wof:name":"Tyndalls' Inc",
    "wof:placetype":"venue"
},
  "geometry": {"coordinates":[-75.51594799999999,38.373101],"type":"Point"}
}