{
  "type": "Feature",
  "properties": {
    "addr:full":"1710 Joan Ave Baltimore MD 21234",
    "addr:housenumber":"1710",
    "addr:postcode":"21234",
    "addr:street":"Joan Ave",
    "iso:country":"US",
    "sg:address":"1710 Joan Ave",
    "sg:city":"Baltimore",
    "sg:classifiers":[
        {
            "category":"Home & Garden",
            "subcategory":"Household Appliances",
            "type":"Retail Goods"
        }
    ],
    "sg:phone":"+1 410 882 1027",
    "sg:postcode":"21234",
    "sg:province":"MD",
    "sg:tags":[
        "cleaners",
        "vacuum"
    ],
    "wof:name":"Electrolux",
    "wof:placetype":"venue"
},
  "geometry": {"coordinates":[-76.56254199999999,39.392727],"type":"Point"}
}