{
  "type": "Feature",
  "properties": {
    "addr:full":"4014 Mountville Rd Jefferson MD 21755",
    "addr:postcode":"4014;21755",
    "addr:street":"Mountville Rd",
    "iso:country":"US",
    "sg:address":"4014 Mountville Rd",
    "sg:city":"Jefferson",
    "sg:classifiers":[
        {
            "category":"Health Services",
            "subcategory":"Doctor",
            "type":"Services"
        }
    ],
    "sg:phone":"+1 301 834 7188",
    "sg:postcode":"21755",
    "sg:province":"MD",
    "sg:tags":[
        "medical",
        "center"
    ],
    "wof:name":"Brunswick Jfferson Med Clinics",
    "wof:placetype":"venue"
},
  "geometry": {"coordinates":[-77.53125900000001,39.35869],"type":"Point"}
}