{
  "type": "Feature",
  "properties": {
    "addr:full":"38265 Beach Rd Coltons Point MD 20626",
    "addr:housenumber":"38265",
    "addr:postcode":"20626",
    "addr:street":"Beach Rd",
    "iso:country":"US",
    "sg:address":"38265 Beach Rd",
    "sg:city":"Coltons Point",
    "sg:classifiers":[
        {
            "category":"Professional",
            "subcategory":"Management & Consulting",
            "type":"Services"
        }
    ],
    "sg:phone":"+1 301 769 2812",
    "sg:postcode":"20626",
    "sg:province":"MD",
    "sg:tags":[
        "business"
    ],
    "wof:name":"Custom Business Services",
    "wof:placetype":"venue"
},
  "geometry": {"coordinates":[-76.757582,38.224846],"type":"Point"}
}