{
  "type": "Feature",
  "properties": {
    "iso:country":"US",
    "sg:address":"Forest Village Park Mall",
    "sg:city":"Capitol Heights",
    "sg:classifiers":[
        {
            "category":"Sports & Exercise",
            "subcategory":"Bicycle Rental",
            "type":"Entertainment"
        }
    ],
    "sg:phone":"+1 301 420 6331",
    "sg:postcode":"20747",
    "sg:province":"MD",
    "sg:tags":[
        "wear"
    ],
    "wof:name":"Head 2 Head",
    "wof:placetype":"venue"
},
  "geometry": {"coordinates":[-76.887229,38.846413],"type":"Point"}
}