{
  "type": "Feature",
  "properties": {
    "iso:country":"US",
    "sg:address":"18425 Flower Hill Way",
    "sg:city":"Gaithersburg",
    "sg:classifiers":[
        {
            "category":"Social Services",
            "subcategory":"Child Care",
            "type":"Services"
        }
    ],
    "sg:phone":"+1 301 869 7770",
    "sg:postcode":"20879",
    "sg:province":"MD",
    "sg:tags":[
        "nursery",
        "day"
    ],
    "wof:name":"Day Kidsco Care",
    "wof:placetype":"venue"
},
  "geometry": {"coordinates":[-77.17208100000001,39.158798],"type":"Point"}
}