{
  "type": "Feature",
  "properties": {
    "iso:country":"US",
    "sg:address":"4401 Annapolis Rd",
    "sg:city":"Halethorpe",
    "sg:classifiers":[
        {
            "category":"Restaurant",
            "type":"Food & Drink"
        }
    ],
    "sg:phone":"+1 410 636 1601",
    "sg:postcode":"21227",
    "sg:province":"MD",
    "wof:name":"Our Place",
    "wof:placetype":"venue"
},
  "geometry": {"coordinates":[-76.64157,39.233849],"type":"Point"}
}