{
  "type": "Feature",
  "properties": {
    "iso:country":"US",
    "sg:address":"9950 Liberty Rd",
    "sg:city":"Randallstown",
    "sg:classifiers":[
        {
            "category":"Health Services",
            "subcategory":"Nursing And Care Facility",
            "type":"Services"
        },
        {
            "category":"Social Services",
            "type":"Services"
        }
    ],
    "sg:phone":"+1 410 521 7260",
    "sg:postcode":"21133",
    "sg:province":"MD",
    "sg:tags":[
        "organization",
        "intermediate",
        "welfare"
    ],
    "wof:name":"Athelas Institute Inc",
    "wof:placetype":"venue"
},
  "geometry": {"coordinates":[-76.825614,39.382518],"type":"Point"}
}