{
  "type": "Feature",
  "properties": {
    "iso:country":"US",
    "sg:address":"2105 Barrowfield Rd",
    "sg:city":"Fort Washington",
    "sg:classifiers":[
        {
            "category":"Arts & Performance",
            "subcategory":"Theater",
            "type":"Entertainment"
        }
    ],
    "sg:phone":"+1 301 839 4294",
    "sg:postcode":"20744",
    "sg:province":"MD",
    "sg:tags":[
        "group"
    ],
    "wof:name":"Nestell Entertainment Inc",
    "wof:placetype":"venue"
},
  "geometry": {"coordinates":[-76.973018,38.803345],"type":"Point"}
}