{
  "type": "Feature",
  "properties": {
    "addr:full":"4 Boileau Ct Middletown MD 21769",
    "addr:housenumber":"4",
    "addr:postcode":"21769",
    "addr:street":"Boileau Ct",
    "iso:country":"US",
    "sg:address":"4 Boileau Ct",
    "sg:city":"Middletown",
    "sg:classifiers":[
        {
            "category":"Shopping",
            "subcategory":"Computers & Home Electronics",
            "type":"Retail Goods"
        }
    ],
    "sg:phone":"+1 301 371 0693",
    "sg:postcode":"21769",
    "sg:province":"MD",
    "sg:tags":[
        "equipment",
        "dealer"
    ],
    "wof:name":"Hewlett-Packard Co",
    "wof:placetype":"venue"
},
  "geometry": {"coordinates":[-77.548627,39.442465],"type":"Point"}
}