{
  "type": "Feature",
  "properties": {
    "iso:country":"US",
    "sg:address":"7309 Grove Rd Ste D",
    "sg:city":"Frederick",
    "sg:classifiers":[
        {
            "category":"Wholesale",
            "subcategory":"Electrical",
            "type":"Manufacturing & Wholesale Goods"
        },
        {
            "category":"Communications",
            "subcategory":"Television Station",
            "type":"Services"
        }
    ],
    "sg:phone":"+1 301 682 8700",
    "sg:postcode":"21704",
    "sg:province":"MD",
    "sg:tags":[
        "systems-wholesale",
        "equipment",
        "radio",
        "manufacturer"
    ],
    "wof:name":"Bradley Broadcast Sales",
    "wof:placetype":"venue"
},
  "geometry": {"coordinates":[-77.413128,39.389848],"type":"Point"}
}