{
  "type": "Feature",
  "properties": {
    "iso:country":"US",
    "sg:address":"5409 Kenilworth Ave",
    "sg:city":"Riverdale",
    "sg:classifiers":[
        {
            "category":"Restaurant",
            "type":"Food & Drink"
        }
    ],
    "sg:phone":"+1 301 277 1926",
    "sg:postcode":"20737",
    "sg:province":"MD",
    "sg:tags":[
        "mexican"
    ],
    "wof:name":"El Campesino Mexican Restaurant",
    "wof:placetype":"venue"
},
  "geometry": {"coordinates":[-76.923103,38.955299],"type":"Point"}
}