{
  "type": "Feature",
  "properties": {
    "addr:full":"1321 Denbright Rd Catonsville MD 21228",
    "addr:housenumber":"1321",
    "addr:postcode":"21228",
    "addr:street":"Denbright Rd",
    "iso:country":"US",
    "sg:address":"1321 Denbright Rd",
    "sg:city":"Catonsville",
    "sg:classifiers":[
        {
            "category":"Health Services",
            "subcategory":"Podiatrist",
            "type":"Services"
        }
    ],
    "sg:phone":"+1 410 788 2371",
    "sg:postcode":"21228",
    "sg:province":"MD",
    "sg:tags":[
        "equipment",
        "supply"
    ],
    "wof:name":"Aimex Ltd Liability Co",
    "wof:placetype":"venue"
},
  "geometry": {"coordinates":[-76.746613,39.296371],"type":"Point"}
}