{
  "type": "Feature",
  "properties": {
    "iso:country":"US",
    "sg:address":"2248 Westwood Dr",
    "sg:city":"Waldorf",
    "sg:classifiers":[
        {
            "category":"Building & Trades",
            "subcategory":"Plumbing",
            "type":"Services"
        }
    ],
    "sg:phone":"+1 301 705 7600",
    "sg:postcode":"20601",
    "sg:province":"MD",
    "sg:tags":[
        "contractor"
    ],
    "wof:name":"All American Heating",
    "wof:placetype":"venue"
},
  "geometry": {"coordinates":[-76.939764,38.653016],"type":"Point"}
}