{
  "type": "Feature",
  "properties": {
    "addr:full":"6334 Dogwood Rd Baltimore MD 21207",
    "addr:housenumber":"6334",
    "addr:postcode":"21207",
    "addr:street":"Dogwood Rd",
    "iso:country":"US",
    "sg:address":"6334 Dogwood Rd",
    "sg:city":"Baltimore",
    "sg:classifiers":[
        {
            "category":"Professional",
            "subcategory":"Engineering",
            "type":"Services"
        }
    ],
    "sg:phone":"+1 410 944 3600",
    "sg:postcode":"21207",
    "sg:province":"MD",
    "sg:tags":[
        "engineer"
    ],
    "wof:name":"Datanet Engineering Inc",
    "wof:placetype":"venue"
},
  "geometry": {"coordinates":[-76.72877099999999,39.316644],"type":"Point"}
}