{
  "type": "Feature",
  "properties": {
    "addr:full":"11433 Cronridge Dr Owings Mills MD 21117",
    "addr:housenumber":"11433",
    "addr:postcode":"21117",
    "addr:street":"Cronridge Dr",
    "iso:country":"US",
    "sg:address":"11433 Cronridge Dr",
    "sg:city":"Owings Mills",
    "sg:classifiers":[
        {
            "category":"Wholesale",
            "subcategory":"Electrical",
            "type":"Manufacturing & Wholesale Goods"
        }
    ],
    "sg:phone":"+1 410 363 6161",
    "sg:postcode":"21117",
    "sg:province":"MD",
    "sg:tags":[
        "equipment",
        "electronic",
        "supply"
    ],
    "sg:website":"www.cameoelectronics.com",
    "wof:name":"Cameo Electronics Corp",
    "wof:placetype":"venue"
},
  "geometry": {"coordinates":[-76.77621000000001,39.440098],"type":"Point"}
}