{
  "type": "Feature",
  "properties": {
    "iso:country":"US",
    "sg:address":"7721 Maryknoll Ave",
    "sg:city":"Bethesda",
    "sg:classifiers":[
        {
            "category":"Health Services",
            "subcategory":"Health Practitioner",
            "type":"Services"
        }
    ],
    "sg:phone":"+1 301 320 9001",
    "sg:postcode":"20817",
    "sg:province":"MD",
    "sg:tags":[
        "medical"
    ],
    "wof:name":"Special Health Services A La",
    "wof:placetype":"venue"
},
  "geometry": {"coordinates":[-77.136534,38.989373],"type":"Point"}
}