{
  "type": "Feature",
  "properties": {
    "addr:full":"11228 Troy Rd Rockville MD 20852",
    "addr:housenumber":"11228",
    "addr:postcode":"20852",
    "addr:street":"Troy Rd",
    "iso:country":"US",
    "sg:address":"11228 Troy Rd",
    "sg:city":"Rockville",
    "sg:classifiers":[
        {
            "category":"Wholesale",
            "subcategory":"Toys & Hobbies",
            "type":"Manufacturing & Wholesale Goods"
        }
    ],
    "sg:phone":"+1 301 468 0828",
    "sg:postcode":"20852",
    "sg:province":"MD",
    "sg:tags":[
        "commercial",
        "design"
    ],
    "wof:name":"Tom Arvis Cartoon & Illustrat",
    "wof:placetype":"venue"
},
  "geometry": {"coordinates":[-77.09057900000001,39.037189],"type":"Point"}
}