{
  "type": "Feature",
  "properties": {
    "addr:full":"1829 Reisterstown Rd Pikesville MD 21208",
    "addr:housenumber":"1829",
    "addr:postcode":"21208",
    "addr:street":"Reisterstown Rd",
    "iso:country":"US",
    "sg:address":"1829 Reisterstown Rd",
    "sg:city":"Pikesville",
    "sg:classifiers":[
        {
            "category":"Professional",
            "subcategory":"Lawyer & Legal Services",
            "type":"Services"
        }
    ],
    "sg:phone":"+1 410 653 3200",
    "sg:postcode":"21208",
    "sg:province":"MD",
    "sg:tags":[
        "attorney"
    ],
    "sg:website":"www.medlawlegalteam.com",
    "wof:name":"Janet Willoughby & Gershon",
    "wof:placetype":"venue"
},
  "geometry": {"coordinates":[-76.738372,39.388385],"type":"Point"}
}