{
  "type": "Feature",
  "properties": {
    "addr:full":"836 Guilford Ave Baltimore MD 21202",
    "addr:housenumber":"836",
    "addr:postcode":"21202",
    "addr:street":"Guilford Ave",
    "iso:country":"US",
    "sg:address":"836 Guilford Ave",
    "sg:city":"Baltimore",
    "sg:classifiers":[
        {
            "category":"Health Services",
            "subcategory":"Chiropractor",
            "type":"Services"
        }
    ],
    "sg:phone":"+1 410 244 0441",
    "sg:postcode":"21202",
    "sg:province":"MD",
    "sg:tags":[
        "chiropractic"
    ],
    "wof:name":"Rowe Chiropractic & Physical T",
    "wof:placetype":"venue"
},
  "geometry": {"coordinates":[-76.611591,39.29914],"type":"Point"}
}