{
  "type": "Feature",
  "properties": {
    "addr:full":"8701 Winands Rd Randallstown MD 21133",
    "addr:housenumber":"8701",
    "addr:postcode":"21133",
    "addr:street":"Winands Rd",
    "iso:country":"US",
    "sg:address":"8701 Winands Rd",
    "sg:city":"Randallstown",
    "sg:classifiers":[
        {
            "category":"Organizations",
            "subcategory":"Religious Organization",
            "type":"Services"
        }
    ],
    "sg:phone":"+1 410 655 1353",
    "sg:postcode":"21133",
    "sg:province":"MD",
    "sg:tags":[
        "synagogue"
    ],
    "wof:name":"Winands Road Synagogue Ctr",
    "wof:placetype":"venue"
},
  "geometry": {"coordinates":[-76.78245099999999,39.380801],"type":"Point"}
}