{
  "type": "Feature",
  "properties": {
    "addr:full":"17404 Taunton Dr Gaithersburg MD 20877",
    "addr:housenumber":"17404",
    "addr:postcode":"20877",
    "addr:street":"Taunton Dr",
    "iso:country":"US",
    "sg:address":"17404 Taunton Dr",
    "sg:city":"Gaithersburg",
    "sg:classifiers":[
        {
            "category":"Shopping",
            "subcategory":"Computers & Home Electronics",
            "type":"Retail Goods"
        }
    ],
    "sg:phone":"+1 301 216 0624",
    "sg:postcode":"20877",
    "sg:province":"MD",
    "sg:tags":[
        "software"
    ],
    "wof:name":"Minnesota Super Computer Ctr",
    "wof:placetype":"venue"
},
  "geometry": {"coordinates":[-77.164694,39.141816],"type":"Point"}
}