{
  "type": "Feature",
  "properties": {
    "iso:country":"US",
    "sg:address":"5052 Nicholson Ln",
    "sg:city":"Rockville",
    "sg:classifiers":[
        {
            "category":"Shopping",
            "subcategory":"Books",
            "type":"Retail Goods"
        }
    ],
    "sg:phone":"+1 301 468 6284",
    "sg:postcode":"20852",
    "sg:province":"MD",
    "sg:tags":[
        "dealer"
    ],
    "wof:name":"Washington Christian Book",
    "wof:placetype":"venue"
},
  "geometry": {"coordinates":[-77.104545,39.04566],"type":"Point"}
}