{
  "type": "Feature",
  "properties": {
    "iso:country":"US",
    "sg:address":"11841 Enid Dr",
    "sg:city":"Potomac",
    "sg:classifiers":[
        {
            "category":"Professional",
            "subcategory":"Research",
            "type":"Services"
        },
        {
            "category":"Education",
            "subcategory":"Library",
            "type":"Public Place"
        }
    ],
    "sg:phone":"+1 301 765 9719",
    "sg:postcode":"20854",
    "sg:province":"MD",
    "sg:tags":[
        "educational"
    ],
    "wof:name":"Toni M Antalis",
    "wof:placetype":"venue"
},
  "geometry": {"coordinates":[-77.169583,39.048806],"type":"Point"}
}