{
  "type": "Feature",
  "properties": {
    "addr:full":"7820 Airpark Rd Gaithersburg MD 20879",
    "addr:housenumber":"7820",
    "addr:postcode":"20879",
    "addr:street":"Airpark Rd",
    "iso:country":"US",
    "sg:address":"7820 Airpark Rd",
    "sg:city":"Gaithersburg",
    "sg:classifiers":[
        {
            "category":"Retail",
            "subcategory":"Auto Repair",
            "type":"Services"
        }
    ],
    "sg:phone":"+1 301 926 0602",
    "sg:postcode":"20879",
    "sg:province":"MD",
    "sg:tags":[
        "body",
        "automobile",
        "painting"
    ],
    "wof:name":"Autosport Coachworks",
    "wof:placetype":"venue"
},
  "geometry": {"coordinates":[-77.16094099999999,39.169741],"type":"Point"}
}