{
  "type": "Feature",
  "properties": {
    "addr:full":"1011 Maple Ave Rockville MD 20851",
    "addr:housenumber":"1011",
    "addr:postcode":"20851",
    "addr:street":"Maple Ave",
    "iso:country":"US",
    "sg:address":"1011 Maple Ave",
    "sg:city":"Rockville",
    "sg:classifiers":[
        {
            "category":"Place Of Worship",
            "subcategory":"Church",
            "type":"Public Place"
        },
        {
            "category":"Place Of Worship",
            "type":"Public Place"
        }
    ],
    "sg:phone":"+1 301 251 9898",
    "sg:postcode":"20851",
    "sg:province":"MD",
    "sg:tags":[
        "churches-presbyterian-arp",
        "churches-presbyterian"
    ],
    "wof:name":"First Korean Presbt Ch Wash",
    "wof:placetype":"venue"
},
  "geometry": {"coordinates":[-77.133366,39.081766],"type":"Point"}
}