{
  "type": "Feature",
  "properties": {
    "iso:country":"US",
    "sg:address":"7803 Redwood Tree Rd",
    "sg:city":"Severn",
    "sg:classifiers":[
        {
            "category":"Professional",
            "subcategory":"Engineering",
            "type":"Services"
        }
    ],
    "sg:phone":"+1 410 969 8002",
    "sg:postcode":"21144",
    "sg:province":"MD",
    "sg:tags":[
        "engineer"
    ],
    "wof:name":"Q Systems Engineering Inc",
    "wof:placetype":"venue"
},
  "geometry": {"coordinates":[-76.670645,39.142392],"type":"Point"}
}