{
  "type": "Feature",
  "properties": {
    "iso:country":"US",
    "sg:address":"12650 Lee Ben Rd",
    "sg:city":"Kingsville",
    "sg:classifiers":[
        {
            "category":"Banks & Credit Unions",
            "subcategory":"Bank",
            "type":"Services"
        }
    ],
    "sg:phone":"+1 410 592 9455",
    "sg:postcode":"21087",
    "sg:province":"MD",
    "sg:tags":[
        "loan",
        "real estate"
    ],
    "wof:name":"Star Funding",
    "wof:placetype":"venue"
},
  "geometry": {"coordinates":[-76.420003,39.470578],"type":"Point"}
}