{
  "type": "Feature",
  "properties": {
    "addr:full":"12650 Lee Ben Rd Kingsville MD 21087",
    "addr:housenumber":"12650",
    "addr:postcode":"21087",
    "addr:street":"Lee Ben Rd",
    "iso:country":"US",
    "sg:address":"12650 Lee Ben Rd",
    "sg:city":"Kingsville",
    "sg:classifiers":[
        {
            "category":"Banks & Credit Unions",
            "subcategory":"Bank",
            "type":"Services"
        }
    ],
    "sg:phone":"+1 410 592 9455",
    "sg:postcode":"21087",
    "sg:province":"MD",
    "sg:tags":[
        "loan",
        "real estate"
    ],
    "wof:name":"Star Funding",
    "wof:placetype":"venue"
},
  "geometry": {"coordinates":[-76.42000299999999,39.470578],"type":"Point"}
}