{
  "type": "Feature",
  "properties": {
    "addr:full":"9025 Chevrolet Dr Ellicott City MD 21042",
    "addr:housenumber":"9025",
    "addr:postcode":"21042",
    "addr:street":"Chevrolet Dr",
    "iso:country":"US",
    "sg:address":"9025 Chevrolet Dr",
    "sg:city":"Ellicott City",
    "sg:classifiers":[
        {
            "category":"Organizations",
            "subcategory":"Professional Association",
            "type":"Services"
        }
    ],
    "sg:phone":"+1 410 277 9370",
    "sg:postcode":"21042",
    "sg:province":"MD",
    "sg:tags":[
        "sales"
    ],
    "wof:name":"Black Stone Intl LTD",
    "wof:placetype":"venue"
},
  "geometry": {"coordinates":[-76.825007,39.275268],"type":"Point"}
}