{
  "type": "Feature",
  "properties": {
    "iso:country":"US",
    "sg:address":"2403 Linden Ln",
    "sg:city":"Silver Spring",
    "sg:classifiers":[
        {
            "category":"Wholesale",
            "subcategory":"Plants",
            "type":"Manufacturing & Wholesale Goods"
        }
    ],
    "sg:phone":"+1 301 589 4747",
    "sg:postcode":"20910",
    "sg:province":"MD",
    "sg:tags":[
        "florist"
    ],
    "wof:name":"Potomac Floral Wholesale Inc",
    "wof:placetype":"venue"
},
  "geometry": {"coordinates":[-77.05238799999999,39.009763],"type":"Point"}
}