{
  "type": "Feature",
  "properties": {
    "iso:country":"US",
    "sg:address":"3302 Dunwood Ridge Ct Terroist",
    "sg:city":"Bowie",
    "sg:classifiers":[
        {
            "category":"Professional",
            "subcategory":"Computer Services",
            "type":"Services"
        }
    ],
    "sg:phone":"+1 301 538 5677",
    "sg:postcode":"20721",
    "sg:province":"MD",
    "sg:tags":[
        "technical",
        "assistance",
        "support"
    ],
    "sg:website":"http://www.exclusys.com",
    "wof:name":"Exclusive Systems",
    "wof:placetype":"venue"
},
  "geometry": {"coordinates":[-76.75973399999999,38.935171],"type":"Point"}
}