{
  "type": "Feature",
  "properties": {
    "addr:full":"8105 Harford Rd Parkville MD 21234",
    "addr:housenumber":"8105",
    "addr:postcode":"21234",
    "addr:street":"Harford Rd",
    "iso:country":"US",
    "sg:address":"8105 Harford Rd",
    "sg:city":"Parkville",
    "sg:classifiers":[
        {
            "category":"Shopping",
            "subcategory":"Bicycles & Sporting Goods",
            "type":"Retail Goods"
        }
    ],
    "sg:phone":"+1 410 668 6866",
    "sg:postcode":"21234",
    "sg:province":"MD",
    "sg:tags":[
        "equipment",
        "diver",
        "supply"
    ],
    "wof:name":"Divers Den Inc",
    "wof:placetype":"venue"
},
  "geometry": {"coordinates":[-76.54008399999999,39.37683],"type":"Point"}
}