{
  "type": "Feature",
  "properties": {
    "iso:country":"US",
    "sg:address":"313 E D St",
    "sg:city":"Brunswick",
    "sg:classifiers":[
        {
            "category":"Retail",
            "subcategory":"Car Wash",
            "type":"Services"
        }
    ],
    "sg:phone":"+1 301 834 7704",
    "sg:postcode":"21716",
    "sg:province":"MD",
    "sg:tags":[
        "automobile",
        "detail",
        "clean"
    ],
    "wof:name":"Welsh's Detailing",
    "wof:placetype":"venue"
},
  "geometry": {"coordinates":[-77.620909,39.315219],"type":"Point"}
}