{
  "type": "Feature",
  "properties": {
    "iso:country":"US",
    "sg:address":"400 W Franklin St",
    "sg:city":"Baltimore",
    "sg:classifiers":[
        {
            "category":"Health Services",
            "subcategory":"Medical Lab",
            "type":"Services"
        }
    ],
    "sg:phone":"+1 410 225 9595",
    "sg:postcode":"21201",
    "sg:province":"MD",
    "sg:tags":[
        "laboratory"
    ],
    "wof:name":"Baltimore Rh Typing Laboratory",
    "wof:placetype":"venue"
},
  "geometry": {"coordinates":[-76.621943,39.294883],"type":"Point"}
}