{
  "type": "Feature",
  "properties": {
    "addr:full":"2002 Medical Pkwy Ste 140 Annapolis MD 21401",
    "addr:housenumber":"2002",
    "addr:postcode":"21401",
    "addr:street":"Medical Pkwy Ste 140",
    "iso:country":"US",
    "sg:address":"2002 Medical Pkwy Ste 140",
    "sg:city":"Annapolis",
    "sg:classifiers":[
        {
            "category":"Coffee & Tea",
            "type":"Food & Drink"
        },
        {
            "category":"Restaurant",
            "type":"Food & Drink"
        }
    ],
    "sg:phone":"+1 410 266 1329",
    "sg:postcode":"21401",
    "sg:province":"MD",
    "sg:tags":[
        "lunch",
        "brunch",
        "cafeteria",
        "espresso",
        "breakfast"
    ],
    "wof:name":"City Roast Cafe",
    "wof:placetype":"venue"
},
  "geometry": {"coordinates":[-76.536202,38.989003],"type":"Point"}
}