{
  "type": "Feature",
  "properties": {
    "iso:country":"US",
    "sg:address":"8231 Rocky Ridge Rd",
    "sg:city":"Thurmont",
    "sg:classifiers":[
        {
            "category":"Organizations",
            "subcategory":"Religious Organization",
            "type":"Services"
        }
    ],
    "sg:phone":"+1 301 271 2379",
    "sg:postcode":"21788",
    "sg:province":"MD",
    "sg:tags":[
        "church"
    ],
    "sg:website":"www.gracehammoravian.com",
    "wof:name":"Graceham Moravian Church",
    "wof:placetype":"venue"
},
  "geometry": {"coordinates":[-77.377635,39.616104],"type":"Point"}
}