{
  "type": "Feature",
  "properties": {
    "addr:full":"1003 Dartford Ln Bowie MD 20721",
    "addr:housenumber":"1003",
    "addr:postcode":"20721",
    "addr:street":"Dartford Ln",
    "iso:country":"US",
    "sg:address":"1003 Dartford Ln",
    "sg:city":"Bowie",
    "sg:classifiers":[
        {
            "category":"Professional",
            "subcategory":"Computer Services",
            "type":"Services"
        }
    ],
    "sg:phone":"+1 301 218 3585",
    "sg:postcode":"20721",
    "sg:province":"MD",
    "sg:tags":[
        "related"
    ],
    "wof:name":"J P Business Solutions Inc",
    "wof:placetype":"venue"
},
  "geometry": {"coordinates":[-76.752402,38.905311],"type":"Point"}
}