{
  "type": "Feature",
  "properties": {
    "iso:country":"US",
    "sg:address":"2229 Fleet St",
    "sg:city":"Baltimore",
    "sg:classifiers":[
        {
            "category":"Personal",
            "subcategory":"Beauty Salon",
            "type":"Services"
        }
    ],
    "sg:phone":"+1 410 276 2242",
    "sg:postcode":"21231",
    "sg:province":"MD",
    "sg:tags":[
        "hair",
        "stylist"
    ],
    "wof:name":"Canton Hair Studio",
    "wof:placetype":"venue"
},
  "geometry": {"coordinates":[-76.58434800000001,39.28492],"type":"Point"}
}