{
  "type": "Feature",
  "properties": {
    "iso:country":"US",
    "sg:address":"9428 Stephen Decatur Hwy",
    "sg:city":"Berlin",
    "sg:classifiers":[
        {
            "category":"Building & Trades",
            "subcategory":"Construction",
            "type":"Services"
        }
    ],
    "sg:phone":"+1 410 213 1900",
    "sg:postcode":"21811",
    "sg:province":"MD",
    "sg:tags":[
        "home",
        "builder"
    ],
    "wof:name":"Mystic Harbour Corp",
    "wof:placetype":"venue"
},
  "geometry": {"coordinates":[-75.126712,38.317647],"type":"Point"}
}