{
  "type": "Feature",
  "properties": {
    "addr:full":"13800 Churchville Dr Upper Marlboro MD 20772",
    "addr:housenumber":"13800",
    "addr:postcode":"20772",
    "addr:street":"Churchville Dr",
    "iso:country":"US",
    "sg:address":"13800 Churchville Dr",
    "sg:city":"Upper Marlboro",
    "sg:classifiers":[
        {
            "category":"Banks & Credit Unions",
            "subcategory":"Bank",
            "type":"Services"
        }
    ],
    "sg:phone":"+1 301 627 5399",
    "sg:postcode":"20772",
    "sg:province":"MD",
    "sg:tags":[
        "loan",
        "real estate"
    ],
    "wof:name":"Mortgage Inc United Home",
    "wof:placetype":"venue"
},
  "geometry": {"coordinates":[-76.765901,38.825475],"type":"Point"}
}