{
  "type": "Feature",
  "properties": {
    "addr:full":"4650 E West Hwy Bethesda MD 20814",
    "addr:housenumber":"4650 e",
    "addr:postcode":"20814",
    "addr:street":"West Hwy",
    "iso:country":"US",
    "sg:address":"4650 E West Hwy",
    "sg:city":"Bethesda",
    "sg:classifiers":[
        {
            "category":"Professional",
            "subcategory":"Management & Consulting",
            "type":"Services"
        }
    ],
    "sg:phone":"+1 301 656 6011",
    "sg:postcode":"20814",
    "sg:province":"MD",
    "sg:tags":[
        "consultant"
    ],
    "wof:name":"Lenschaw Business Management",
    "wof:placetype":"venue"
},
  "geometry": {"coordinates":[-77.093587,38.984682],"type":"Point"}
}