{
  "type": "Feature",
  "properties": {
    "addr:full":"7130 Dorsey Rd Laytonsville MD 20882",
    "addr:housenumber":"7130",
    "addr:postcode":"20882",
    "addr:street":"Dorsey Rd",
    "iso:country":"US",
    "sg:address":"7130 Dorsey Rd",
    "sg:city":"Laytonsville",
    "sg:classifiers":[
        {
            "category":"Sports & Exercise",
            "subcategory":"Golf",
            "type":"Entertainment"
        }
    ],
    "sg:phone":"+1 301 948 5288",
    "sg:postcode":"20882",
    "sg:province":"MD",
    "sg:tags":[
        "course"
    ],
    "sg:website":"www.montgomerycountygolf.com",
    "wof:name":"Laytonsville Golf Course",
    "wof:placetype":"venue"
},
  "geometry": {"coordinates":[-77.142376,39.197621],"type":"Point"}
}