{
  "type": "Feature",
  "properties": {
    "iso:country":"US",
    "sg:address":"7714 Old Branch Ave",
    "sg:city":"Clinton",
    "sg:classifiers":[
        {
            "category":"Restaurant",
            "type":"Food & Drink"
        }
    ],
    "sg:phone":"+1 301 877 6699",
    "sg:postcode":"20735",
    "sg:province":"MD",
    "sg:tags":[
        "eating"
    ],
    "wof:name":"Quiznos Sub",
    "wof:placetype":"venue"
},
  "geometry": {"coordinates":[-76.89797900000001,38.78449],"type":"Point"}
}