{
  "type": "Feature",
  "properties": {
    "addr:full":"216 Compass Rd Essex MD 21221",
    "addr:housenumber":"216",
    "addr:postcode":"21221",
    "addr:street":"Compass Rd",
    "iso:country":"US",
    "sg:address":"216 Compass Rd",
    "sg:city":"Essex",
    "sg:classifiers":[
        {
            "category":"Building & Trades",
            "subcategory":"Cleaning & Sanitation",
            "type":"Services"
        }
    ],
    "sg:phone":"+1 410 574 9111",
    "sg:postcode":"21221",
    "sg:province":"MD",
    "sg:tags":[
        "janitor"
    ],
    "wof:name":"Hart's Cleaning Svc",
    "wof:placetype":"venue"
},
  "geometry": {"coordinates":[-76.462642,39.331244],"type":"Point"}
}