{
  "type": "Feature",
  "properties": {
    "iso:country":"US",
    "sg:address":"1300 E North Ave",
    "sg:city":"Baltimore",
    "sg:classifiers":[
        {
            "category":"Shopping",
            "subcategory":"Pawn Shop",
            "type":"Retail Goods"
        }
    ],
    "sg:phone":"+1 410 366 0000",
    "sg:postcode":"21213",
    "sg:province":"MD",
    "wof:name":"First Cash Pawn",
    "wof:placetype":"venue"
},
  "geometry": {"coordinates":[-76.599667,39.312033],"type":"Point"}
}