{
  "type": "Feature",
  "properties": {
    "iso:country":"US",
    "sg:address":"118 Walnut St",
    "sg:city":"Friendsville",
    "sg:classifiers":[
        {
            "category":"Wholesale",
            "subcategory":"Groceries",
            "type":"Manufacturing & Wholesale Goods"
        }
    ],
    "sg:phone":"+1 301 746 4333",
    "sg:postcode":"21531",
    "sg:province":"MD",
    "sg:tags":[
        "food",
        "product",
        "health"
    ],
    "wof:name":"Harding Ginseng Farm Inc",
    "wof:placetype":"venue"
},
  "geometry": {"coordinates":[-79.401748,39.664008],"type":"Point"}
}