{
  "type": "Feature",
  "properties": {
    "iso:country":"US",
    "sg:address":"801 E Chase St",
    "sg:city":"Baltimore",
    "sg:classifiers":[
        {
            "category":"Restaurant",
            "type":"Food & Drink"
        }
    ],
    "sg:phone":"+1 410 263 8100",
    "sg:postcode":"21202",
    "sg:province":"MD",
    "wof:name":"Cafe Beaux Arts At Maryland",
    "wof:placetype":"venue"
},
  "geometry": {"coordinates":[-76.604993,39.302831],"type":"Point"}
}