{
  "type": "Feature",
  "properties": {
    "iso:country":"US",
    "sg:address":"1200 Crain Hwy S",
    "sg:city":"Glen Burnie",
    "sg:classifiers":[
        {
            "category":"Autos & Motor Vehicles",
            "subcategory":"Auto Supplies",
            "type":"Retail Goods"
        }
    ],
    "sg:phone":"+1 410 766 7086",
    "sg:postcode":"21061",
    "sg:province":"MD",
    "sg:tags":[
        "automobile",
        "parts"
    ],
    "sg:website":"www.autozone.com",
    "wof:name":"Autozone",
    "wof:placetype":"venue"
},
  "geometry": {"coordinates":[-76.631856,39.15156],"type":"Point"}
}