{
  "type": "Feature",
  "properties": {
    "iso:country":"US",
    "sg:address":"7 Keen Valley Dr",
    "sg:city":"Baltimore",
    "sg:classifiers":[
        {
            "category":"Manufacturing",
            "subcategory":"Printing",
            "type":"Manufacturing & Wholesale Goods"
        }
    ],
    "sg:phone":"+1 410 247 1044",
    "sg:postcode":"21228",
    "sg:province":"MD",
    "sg:tags":[
        "book"
    ],
    "wof:name":"Tafsir Ibn Kathir DOT Co",
    "wof:placetype":"venue"
},
  "geometry": {"coordinates":[-76.705338,39.265015],"type":"Point"}
}