{
  "type": "Feature",
  "properties": {
    "addr:full":"355 Baltimore Blvd Westminster MD 21157",
    "addr:housenumber":"355",
    "addr:postcode":"21157",
    "addr:street":"Baltimore Blvd",
    "iso:country":"US",
    "sg:address":"355 Baltimore Blvd",
    "sg:city":"Westminster",
    "sg:phone":"+1 410 871 0300",
    "sg:postcode":"21157",
    "sg:province":"MD",
    "wof:name":"Carroll Computer Conection",
    "wof:placetype":"venue"
},
  "geometry": {"coordinates":[-76.98471499999999,39.574515],"type":"Point"}
}