{
  "type": "Feature",
  "properties": {
    "iso:country":"US",
    "sg:address":"6905 Rockledge Dr",
    "sg:city":"Bethesda",
    "sg:classifiers":[
        {
            "category":"Banks & Credit Unions",
            "subcategory":"Investment Brokerage",
            "type":"Services"
        }
    ],
    "sg:phone":"+1 301 896 9796",
    "sg:postcode":"20817",
    "sg:province":"MD",
    "sg:tags":[
        "advisory",
        "financial"
    ],
    "wof:name":"Charter Financial Inc",
    "wof:placetype":"venue"
},
  "geometry": {"coordinates":[-77.134536,39.029972],"type":"Point"}
}