{
  "type": "Feature",
  "properties": {
    "iso:country":"US",
    "sg:address":"8 Palmer Green Ct",
    "sg:city":"Baltimore",
    "sg:classifiers":[
        {
            "category":"Professional",
            "subcategory":"Business Services",
            "type":"Services"
        }
    ],
    "sg:phone":"+1 410 323 7595",
    "sg:postcode":"21210",
    "sg:province":"MD",
    "sg:tags":[
        "interior",
        "decorator"
    ],
    "wof:name":"Kathryn Rienhoff Interiors",
    "wof:placetype":"venue"
},
  "geometry": {"coordinates":[-76.64601,39.358274],"type":"Point"}
}