{
  "type": "Feature",
  "properties": {
    "addr:full":"18218 Flower Hill Way Gaithersburg MD 20879",
    "addr:housenumber":"18218",
    "addr:postcode":"20879",
    "addr:street":"Flower Hill Way",
    "iso:country":"US",
    "sg:address":"18218 Flower Hill Way",
    "sg:city":"Gaithersburg",
    "sg:classifiers":[
        {
            "category":"Health Services",
            "subcategory":"Doctor",
            "type":"Services"
        }
    ],
    "sg:phone":"+1 301 963 0665",
    "sg:postcode":"20879",
    "sg:province":"MD",
    "sg:tags":[
        "dentist"
    ],
    "wof:name":"Dental Suite",
    "wof:placetype":"venue"
},
  "geometry": {"coordinates":[-77.16440900000001,39.155225],"type":"Point"}
}