{
  "type": "Feature",
  "properties": {
    "iso:country":"US",
    "sg:address":"10011 Marriottsville Rd",
    "sg:city":"Randallstown",
    "sg:classifiers":[
        {
            "category":"Building & Trades",
            "subcategory":"Construction",
            "type":"Services"
        }
    ],
    "sg:phone":"+1 410 655 4510",
    "sg:postcode":"21133",
    "sg:province":"MD",
    "sg:tags":[
        "general",
        "contractor"
    ],
    "wof:name":"GRC Professional Chimney",
    "wof:placetype":"venue"
},
  "geometry": {"coordinates":[-76.835182,39.375502],"type":"Point"}
}