{
  "type": "Feature",
  "properties": {
    "iso:country":"US",
    "sg:address":"17462 Rock Point Rd",
    "sg:city":"Newburg",
    "sg:classifiers":[
        {
            "category":"Health Services",
            "subcategory":"Health Practitioner",
            "type":"Services"
        }
    ],
    "sg:phone":"+1 301 259 4708",
    "sg:postcode":"20664",
    "sg:province":"MD",
    "sg:tags":[
        "addiction",
        "abuse",
        "drug"
    ],
    "wof:name":"Aaron J Lucas",
    "wof:placetype":"venue"
},
  "geometry": {"coordinates":[-76.83728499999999,38.274632],"type":"Point"}
}