{
  "type": "Feature",
  "properties": {
    "addr:full":"1500 Woodlawn Dr Baltimore MD 21207",
    "addr:housenumber":"1500",
    "addr:postcode":"21207",
    "addr:street":"Woodlawn Dr",
    "iso:country":"US",
    "sg:address":"1500 Woodlawn Dr",
    "sg:city":"Baltimore",
    "sg:classifiers":[
        {
            "category":"Banks & Credit Unions",
            "subcategory":"Investment Brokerage",
            "type":"Services"
        }
    ],
    "sg:phone":"+1 410 944 2744",
    "sg:postcode":"21207",
    "sg:province":"MD",
    "sg:tags":[
        "stock",
        "bond"
    ],
    "wof:name":"Security Land & Development",
    "wof:placetype":"venue"
},
  "geometry": {"coordinates":[-76.73410199999999,39.306725],"type":"Point"}
}