{
  "type": "Feature",
  "properties": {
    "iso:country":"US",
    "sg:address":"3520 Eastern Ave",
    "sg:city":"Baltimore",
    "sg:classifiers":[
        {
            "category":"Health Services",
            "subcategory":"Optometrist",
            "type":"Services"
        },
        {
            "category":"Shopping",
            "subcategory":"Optician",
            "type":"Retail Goods"
        }
    ],
    "sg:phone":"+1 410 675 2275",
    "sg:postcode":"21224",
    "sg:province":"MD",
    "sg:tags":[
        "eyewear"
    ],
    "wof:name":"Pearle Vision",
    "wof:placetype":"venue"
},
  "geometry": {"coordinates":[-76.5672,39.286598],"type":"Point"}
}