{
  "type": "Feature",
  "properties": {
    "iso:country":"US",
    "sg:address":"1400 Liberty Rd",
    "sg:city":"Sykesville",
    "sg:classifiers":[
        {
            "category":"Retail",
            "subcategory":"Auto Repair",
            "type":"Services"
        }
    ],
    "sg:phone":"+1 410 795 9890",
    "sg:postcode":"21784",
    "sg:province":"MD",
    "sg:tags":[
        "repairing",
        "automobile"
    ],
    "wof:name":"Eagle Automotive",
    "wof:placetype":"venue"
},
  "geometry": {"coordinates":[-76.94946,39.403798],"type":"Point"}
}