{
  "type": "Feature",
  "properties": {
    "addr:full":"6350 Red Cedar Pl Baltimore MD 21209",
    "addr:housenumber":"6350",
    "addr:postcode":"21209",
    "addr:street":"Red Cedar Pl",
    "iso:country":"US",
    "sg:address":"6350 Red Cedar Pl",
    "sg:city":"Baltimore",
    "sg:classifiers":[
        {
            "category":"Building & Trades",
            "subcategory":"Construction",
            "type":"Services"
        }
    ],
    "sg:phone":"+1 410 486 6901",
    "sg:postcode":"21209",
    "sg:province":"MD",
    "sg:tags":[
        "contractor"
    ],
    "wof:name":"Window & Roofing Professionals",
    "wof:placetype":"venue"
},
  "geometry": {"coordinates":[-76.687343,39.366942],"type":"Point"}
}