{
  "type": "Feature",
  "properties": {
    "iso:country":"US",
    "sg:address":"97 Thomas Johnson Dr",
    "sg:city":"Frederick",
    "sg:classifiers":[
        {
            "category":"Professional",
            "subcategory":"Management & Consulting",
            "type":"Services"
        },
        {
            "category":"Professional",
            "subcategory":"Engineering",
            "type":"Services"
        }
    ],
    "sg:phone":"+1 301 620 1200",
    "sg:postcode":"21702",
    "sg:province":"MD",
    "sg:tags":[
        "environmental",
        "ecological",
        "engineer",
        "consultant"
    ],
    "sg:website":"http://www.spectrumenv.com",
    "wof:name":"Spectrum Enviromental Sciences, Inc",
    "wof:placetype":"venue"
},
  "geometry": {"coordinates":[-77.405098,39.447091],"type":"Point"}
}