{
  "type": "Feature",
  "properties": {
    "iso:country":"US",
    "sg:address":"3415 Lineboro Rd",
    "sg:city":"Manchester",
    "sg:classifiers":[
        {
            "category":"Shopping",
            "subcategory":"Party Supplies",
            "type":"Retail Goods"
        }
    ],
    "sg:phone":"+1 410 596 6605",
    "sg:postcode":"21102",
    "sg:province":"MD",
    "sg:tags":[
        "decoration",
        "rental"
    ],
    "wof:name":"Jump And Bounce",
    "wof:placetype":"venue"
},
  "geometry": {"coordinates":[-76.873192,39.69561],"type":"Point"}
}