{
  "type": "Feature",
  "properties": {
    "iso:country":"US",
    "sg:address":"4700 Belle Grove Rd Ste 7",
    "sg:city":"Brooklyn",
    "sg:classifiers":[
        {
            "category":"Personal",
            "type":"Services"
        },
        {
            "category":"Retail",
            "subcategory":"Auto Repair",
            "type":"Services"
        }
    ],
    "sg:phone":"+1 410 789 8863",
    "sg:postcode":"21225",
    "sg:province":"MD",
    "sg:tags":[
        "towing"
    ],
    "wof:name":"B & B Affordable Auto & Truck Repair",
    "wof:placetype":"venue"
},
  "geometry": {"coordinates":[-76.620903,39.228298],"type":"Point"}
}