{
  "type": "Feature",
  "properties": {
    "addr:full":"9881 Brokenland Pkwy Columbia MD 21046",
    "addr:postcode":"9881;21046",
    "addr:street":"Brokenland Pkwy",
    "iso:country":"US",
    "sg:address":"9881 Brokenland Pkwy",
    "sg:city":"Columbia",
    "sg:classifiers":[
        {
            "category":"Professional",
            "subcategory":"Lawyer & Legal Services",
            "type":"Services"
        }
    ],
    "sg:phone":"+1 301 854 3039",
    "sg:postcode":"21046",
    "sg:province":"MD",
    "wof:name":"Carroll R Stephen Lwyr",
    "wof:placetype":"venue"
},
  "geometry": {"coordinates":[-76.848,39.178699],"type":"Point"}
}