{
  "type": "Feature",
  "properties": {
    "iso:country":"US",
    "sg:address":"120 E Baltimore St",
    "sg:city":"Baltimore",
    "sg:classifiers":[
        {
            "category":"Professional",
            "subcategory":"Lawyer & Legal Services",
            "type":"Services"
        }
    ],
    "sg:phone":"+1 410 347 7379",
    "sg:postcode":"21202",
    "sg:province":"MD",
    "sg:tags":[
        "attorney",
        "practice"
    ],
    "wof:name":"Sharon A Snyder",
    "wof:placetype":"venue"
},
  "geometry": {"coordinates":[-76.613007,39.28957],"type":"Point"}
}