{
  "type": "Feature",
  "properties": {
    "addr:full":"9617 Lost Knife Rd Gaithersburg MD 20877",
    "addr:housenumber":"9617",
    "addr:postcode":"20877",
    "addr:street":"Lost Knife Rd",
    "iso:country":"US",
    "sg:address":"9617 Lost Knife Rd",
    "sg:city":"Gaithersburg",
    "sg:classifiers":[
        {
            "category":"Retail",
            "subcategory":"Laundry & Dry Cleaning",
            "type":"Services"
        }
    ],
    "sg:phone":"+1 301 921 9363",
    "sg:postcode":"20877",
    "sg:province":"MD",
    "sg:tags":[
        "cleaners"
    ],
    "wof:name":"Brite Cleaners",
    "wof:placetype":"venue"
},
  "geometry": {"coordinates":[-77.200672,39.154502],"type":"Point"}
}