{
  "type": "Feature",
  "properties": {
    "addr:full":"13726 Princess Anne Way Phoenix MD 21131",
    "addr:housenumber":"13726",
    "addr:postcode":"21131",
    "addr:street":"Princess Anne Way",
    "iso:country":"US",
    "sg:address":"13726 Princess Anne Way",
    "sg:city":"Phoenix",
    "sg:classifiers":[
        {
            "category":"Building & Trades",
            "subcategory":"Construction",
            "type":"Services"
        }
    ],
    "sg:phone":"+1 410 667 4700",
    "sg:postcode":"21131",
    "sg:province":"MD",
    "sg:tags":[
        "builder",
        "deck"
    ],
    "wof:name":"Decked Out",
    "wof:placetype":"venue"
},
  "geometry": {"coordinates":[-76.595094,39.502619],"type":"Point"}
}