{
  "type": "Feature",
  "properties": {
    "addr:full":"1560 Opossumtown Pike Frederick MD 21702",
    "addr:housenumber":"1560",
    "addr:postcode":"21702",
    "addr:street":"Opossumtown Pike",
    "iso:country":"US",
    "sg:address":"1560 Opossumtown Pike",
    "sg:city":"Frederick",
    "sg:classifiers":[
        {
            "category":"Social Services",
            "type":"Services"
        }
    ],
    "sg:phone":"+1 301 662 7171",
    "sg:postcode":"21702",
    "sg:province":"MD",
    "sg:tags":[
        "information",
        "planning",
        "center",
        "family"
    ],
    "wof:name":"Planned Parenthood",
    "wof:placetype":"venue"
},
  "geometry": {"coordinates":[-77.410365,39.440194],"type":"Point"}
}