{
  "type": "Feature",
  "properties": {
    "addr:full":"111 Maryland Ave Cambridge MD 21643",
    "addr:housenumber":"111",
    "addr:postcode":"21643",
    "addr:street":"Maryland Ave",
    "iso:country":"US",
    "sg:address":"111 Maryland Ave",
    "sg:city":"Cambridge",
    "sg:classifiers":[
        {
            "category":"Shopping",
            "type":"Retail Goods"
        },
        {
            "category":"Museum",
            "type":"Entertainment"
        }
    ],
    "sg:phone":"+1 410 228 7977",
    "sg:postcode":"21643",
    "sg:province":"MD",
    "sg:tags":[
        "picture",
        "frame",
        "gallery"
    ],
    "wof:name":"Wright's Art & Framing",
    "wof:placetype":"venue"
},
  "geometry": {"coordinates":[-75.86074000000001,38.633499],"type":"Point"}
}