{
  "type": "Feature",
  "properties": {
    "addr:full":"5732 Buckeystown Pike Frederick MD 21704",
    "addr:housenumber":"5732",
    "addr:postcode":"21704",
    "addr:street":"Buckeystown Pike",
    "iso:country":"US",
    "sg:address":"5732 Buckeystown Pike",
    "sg:city":"Frederick",
    "sg:classifiers":[
        {
            "category":"Personal",
            "type":"Services"
        }
    ],
    "sg:phone":"+1 301 663 4551",
    "sg:postcode":"21704",
    "sg:province":"MD",
    "sg:tags":[
        "electrolysis"
    ],
    "wof:name":"Blue Ridge Electrolysis",
    "wof:placetype":"venue"
},
  "geometry": {"coordinates":[-77.409494,39.391639],"type":"Point"}
}