{
  "type": "Feature",
  "properties": {
    "addr:full":"3701 Old Court Rd Ste 5B Pikesville MD 21208",
    "addr:housenumber":"3701",
    "addr:postcode":"21208",
    "addr:street":"Old Court Rd Ste 5B",
    "iso:country":"US",
    "sg:address":"3701 Old Court Rd Ste 5B",
    "sg:city":"Pikesville",
    "sg:classifiers":[
        {
            "category":"Social Services",
            "type":"Services"
        },
        {
            "category":"Professional",
            "subcategory":"Employment Agencies",
            "type":"Services"
        }
    ],
    "sg:phone":"+1 410 415 5854",
    "sg:postcode":"21208",
    "sg:province":"MD",
    "sg:tags":[
        "workers'",
        "placement",
        "volunteer"
    ],
    "wof:name":"The Joseph Smelkinson And Samuel Roth Foundation I",
    "wof:placetype":"venue"
},
  "geometry": {"coordinates":[-76.72183099999999,39.379424],"type":"Point"}
}