{
  "type": "Feature",
  "properties": {
    "addr:full":"8302 Pulaski Hwy Rosedale MD 21237",
    "addr:housenumber":"8302",
    "addr:postcode":"21237",
    "addr:street":"Pulaski Hwy",
    "iso:country":"US",
    "sg:address":"8302 Pulaski Hwy",
    "sg:city":"Rosedale",
    "sg:classifiers":[
        {
            "category":"Autos & Motor Vehicles",
            "subcategory":"Boat Sales",
            "type":"Retail Goods"
        }
    ],
    "sg:phone":"+1 410 574 7770",
    "sg:postcode":"21237",
    "sg:province":"MD",
    "sg:tags":[
        "equipment",
        "marine",
        "supply"
    ],
    "wof:name":"West Marine",
    "wof:placetype":"venue"
},
  "geometry": {"coordinates":[-76.502666,39.323334],"type":"Point"}
}