{
  "type": "Feature",
  "properties": {
    "iso:country":"US",
    "sg:address":"11845 Rt 216",
    "sg:city":"Fulton",
    "sg:classifiers":[
        {
            "category":"Restaurant",
            "type":"Food & Drink"
        }
    ],
    "sg:phone":"+1 301 776 5336",
    "sg:postcode":"20759",
    "sg:province":"MD",
    "sg:tags":[
        "pizza"
    ],
    "sg:website":"www.ledopizza.com",
    "wof:name":"Ledo Pizza",
    "wof:placetype":"venue"
},
  "geometry": {"coordinates":[-76.923973,39.152918],"type":"Point"}
}