{
  "type": "Feature",
  "properties": {
    "iso:country":"US",
    "sg:address":"9940 Washington Blvd N",
    "sg:city":"Laurel",
    "sg:classifiers":[
        {
            "category":"Retail",
            "subcategory":"Animal Services",
            "type":"Services"
        }
    ],
    "sg:phone":"+1 301 725 5494",
    "sg:postcode":"20723",
    "sg:province":"MD",
    "wof:name":"A Bath & Clip Place",
    "wof:placetype":"venue"
},
  "geometry": {"coordinates":[-76.83502900000001,39.112507],"type":"Point"}
}