{
  "type": "Feature",
  "properties": {
    "iso:country":"US",
    "sg:address":"5835 Allentown Rd",
    "sg:city":"Suitland",
    "sg:classifiers":[
        {
            "category":"Personal",
            "subcategory":"Beauty Salon",
            "type":"Services"
        }
    ],
    "sg:phone":"+1 301 316 8010",
    "sg:postcode":"20746",
    "sg:province":"MD",
    "wof:name":"Hair Nuvo",
    "wof:placetype":"venue"
},
  "geometry": {"coordinates":[-76.895557,38.811536],"type":"Point"}
}