{
  "type": "Feature",
  "properties": {
    "iso:country":"US",
    "sg:address":"333 Cassell Dr",
    "sg:city":"Baltimore",
    "sg:classifiers":[
        {
            "category":"Health Services",
            "subcategory":"Doctor",
            "type":"Services"
        }
    ],
    "sg:phone":"+1 410 550 0644",
    "sg:postcode":"21224",
    "sg:province":"MD",
    "sg:tags":[
        "physician",
        "surgeon"
    ],
    "sg:website":"www.gambrohealthcare.com",
    "wof:name":"Gambro Healthcare",
    "wof:placetype":"venue"
},
  "geometry": {"coordinates":[-76.55238,39.290325],"type":"Point"}
}