{
  "type": "Feature",
  "properties": {
    "addr:full":"7611 Baltimore Annapolis Blvd Glen Burnie MD 21060",
    "addr:housenumber":"7611",
    "addr:postcode":"21060",
    "addr:street":"Baltimore Annapolis Blvd",
    "iso:country":"US",
    "sg:address":"7611 Baltimore Annapolis Blvd",
    "sg:city":"Glen Burnie",
    "sg:classifiers":[
        {
            "category":"Retail",
            "subcategory":"Auto Repair",
            "type":"Services"
        }
    ],
    "sg:phone":"+1 410 761 5000",
    "sg:postcode":"21060",
    "sg:province":"MD",
    "sg:tags":[
        "body",
        "automobile",
        "painting"
    ],
    "wof:name":"Dockery's Body & Frame",
    "wof:placetype":"venue"
},
  "geometry": {"coordinates":[-76.61099299999999,39.158976],"type":"Point"}
}