{
  "type": "Feature",
  "properties": {
    "addr:full":"414 Water St Apt 1513 Baltimore MD 21202",
    "addr:housenumber":"414;1513",
    "addr:postcode":"21202",
    "addr:street":"Water St Apt",
    "iso:country":"US",
    "sg:address":"414 Water St Apt 1513",
    "sg:city":"Baltimore",
    "sg:classifiers":[
        {
            "category":"Real Estate",
            "subcategory":"Real Estate Services",
            "type":"Services"
        },
        {
            "category":"Banks & Credit Unions",
            "subcategory":"Financial Services",
            "type":"Services"
        }
    ],
    "sg:phone":"+1 410 360 2383",
    "sg:postcode":"21202",
    "sg:province":"MD",
    "sg:tags":[
        "loan",
        "processing"
    ],
    "wof:name":"City 1st Mortgage",
    "wof:placetype":"venue"
},
  "geometry": {"coordinates":[-76.609594,39.288595],"type":"Point"}
}