{
  "type": "Feature",
  "properties": {
    "addr:full":"8817 Belair Rd Nottingham MD 21236",
    "addr:housenumber":"8817",
    "addr:postcode":"21236",
    "addr:street":"Belair Rd",
    "iso:country":"US",
    "sg:address":"8817 Belair Rd",
    "sg:city":"Nottingham",
    "sg:classifiers":[
        {
            "category":"Professional",
            "subcategory":"Accounting & Tax Preparation",
            "type":"Services"
        }
    ],
    "sg:phone":"+1 410 256 5131",
    "sg:postcode":"21236",
    "sg:province":"MD",
    "sg:tags":[
        "bookkeeping",
        "public",
        "accountants-certified"
    ],
    "wof:name":"Driscoll & Assoc",
    "wof:placetype":"venue"
},
  "geometry": {"coordinates":[-76.48500199999999,39.394794],"type":"Point"}
}