{
  "type": "Feature",
  "properties": {
    "iso:country":"US",
    "sg:address":"2732 Howard Grove Rd",
    "sg:city":"Davidsonville",
    "sg:classifiers":[
        {
            "category":"Shopping",
            "type":"Retail Goods"
        }
    ],
    "sg:phone":"+1 410 264 7077",
    "sg:postcode":"21035",
    "sg:province":"MD",
    "sg:tags":[
        "equipment",
        "telephone",
        "supply"
    ],
    "wof:name":"Catherine Forbes Inc",
    "wof:placetype":"venue"
},
  "geometry": {"coordinates":[-76.63069400000001,38.960121],"type":"Point"}
}