{
  "type": "Feature",
  "properties": {
    "addr:full":"10820 Town Center Blvd Dunkirk MD 20754",
    "addr:housenumber":"10820",
    "addr:postcode":"20754",
    "addr:street":"Town Center Blvd",
    "iso:country":"US",
    "sg:address":"10820 Town Center Blvd",
    "sg:city":"Dunkirk",
    "sg:classifiers":[
        {
            "category":"Restaurant",
            "type":"Food & Drink"
        }
    ],
    "sg:menulink":"http://www.allmenus.com/md/sunderland/71370-ledo-pizza/menu/",
    "sg:phone":"+1 410 257 9111",
    "sg:postcode":"20754",
    "sg:province":"MD",
    "sg:tags":[
        "american",
        "pizza"
    ],
    "wof:name":"Ledo Pizza",
    "wof:placetype":"venue"
},
  "geometry": {"coordinates":[-76.65631999999999,38.724527],"type":"Point"}
}