{
  "type": "Feature",
  "properties": {
    "addr:full":"111 Llewelyn Ln Huntingtown MD 20639",
    "addr:housenumber":"111",
    "addr:postcode":"20639",
    "addr:street":"Llewelyn Ln",
    "iso:country":"US",
    "sg:address":"111 Llewelyn Ln",
    "sg:city":"Huntingtown",
    "sg:classifiers":[
        {
            "category":"Building & Trades",
            "subcategory":"Plumbing",
            "type":"Services"
        },
        {
            "category":"Building & Trades",
            "subcategory":"Cleaning & Sanitation",
            "type":"Services"
        },
        {
            "category":"Building & Trades",
            "subcategory":"Construction",
            "type":"Services"
        }
    ],
    "sg:phone":"+1 410 257 3025",
    "sg:postcode":"20639",
    "sg:province":"MD",
    "sg:tags":[
        "cleaner",
        "tank",
        "septic",
        "supply",
        "repairer",
        "system",
        "sewer",
        "contractor",
        "tanks-treatment",
        "plumbing-drain",
        "air conditioning"
    ],
    "wof:name":"Paul C Hayden Jr & Sons Plumbing & Heating Inc",
    "wof:placetype":"venue"
},
  "geometry": {"coordinates":[-76.60697500000001,38.655122],"type":"Point"}
}