{
  "type": "Feature",
  "properties": {
    "iso:country":"US",
    "sg:address":"3731 Turkeyfoot Rd",
    "sg:city":"Westminster",
    "sg:classifiers":[
        {
            "category":"Building & Trades",
            "subcategory":"Construction",
            "type":"Services"
        }
    ],
    "sg:phone":"+1 410 848 3481",
    "sg:postcode":"21158",
    "sg:province":"MD",
    "sg:tags":[
        "contractor"
    ],
    "wof:name":"Dustin Masonry Co",
    "wof:placetype":"venue"
},
  "geometry": {"coordinates":[-77.031316,39.675755],"type":"Point"}
}