{
  "type": "Feature",
  "properties": {
    "iso:country":"US",
    "sg:address":"1045 Carbondale Way",
    "sg:city":"Gambrills",
    "sg:phone":"+1 410 721 4142",
    "sg:postcode":"21054",
    "sg:province":"MD",
    "sg:website":"http://airbair.com",
    "wof:name":"BAIR Necessities, LLC Geothermal, Heating & Air Conditioning",
    "wof:placetype":"venue"
},
  "geometry": {"coordinates":[-76.67537,39.036336],"type":"Point"}
}