{
  "type": "Feature",
  "properties": {
    "iso:country":"US",
    "sg:address":"3 W 1st St",
    "sg:city":"Frederick",
    "sg:classifiers":[
        {
            "category":"Professional",
            "subcategory":"Management & Consulting",
            "type":"Services"
        }
    ],
    "sg:phone":"+1 301 668 1511",
    "sg:postcode":"21740",
    "sg:province":"MD",
    "sg:tags":[
        "consultant",
        "business"
    ],
    "sg:website":"www.smartrecruit.com",
    "wof:name":"Dolan Media Management Corp",
    "wof:placetype":"venue"
},
  "geometry": {"coordinates":[-77.728527,39.626362],"type":"Point"}
}