{
  "type": "Feature",
  "properties": {
    "addr:full":"7839 Eastpoint Mall Baltimore MD 21224",
    "addr:housenumber":"7839",
    "addr:postcode":"21224",
    "addr:street":"Eastpoint Mall",
    "iso:country":"US",
    "sg:address":"7839 Eastpoint Mall",
    "sg:city":"Baltimore",
    "sg:classifiers":[
        {
            "category":"Wholesale",
            "subcategory":"Medical Equipment & Supplies",
            "type":"Manufacturing & Wholesale Goods"
        },
        {
            "category":"Utilities",
            "subcategory":"Natural Gas",
            "type":"Services"
        }
    ],
    "sg:phone":"+1 410 282 9515",
    "sg:postcode":"21224",
    "sg:province":"MD",
    "sg:tags":[
        "aids-manufacturers",
        "hearing",
        "device",
        "assistive",
        "aid"
    ],
    "sg:website":"http://www.miracle-ear.com",
    "wof:name":"Miracle-Ear",
    "wof:placetype":"venue"
},
  "geometry": {"coordinates":[-76.509131,39.291753],"type":"Point"}
}