{
  "type": "Feature",
  "properties": {
    "addr:full":"7203 Rockland Hills Dr Baltimore MD 21209",
    "addr:housenumber":"7203",
    "addr:postcode":"21209",
    "addr:street":"Rockland Hills Dr",
    "iso:country":"US",
    "sg:address":"7203 Rockland Hills Dr",
    "sg:city":"Baltimore",
    "sg:phone":"+1 443 731 2337",
    "sg:postcode":"21209",
    "sg:province":"MD",
    "sg:website":"http://baltimore.citysearch.com/profile/external/653722650/baltimore_md/maryland_window_doors_floor_inc.html?publisher=yellowpages&reference_id=15&placement=ypwebsitemip",
    "wof:name":"Maryland Window, Doors, & Floor, Inc",
    "wof:placetype":"venue"
},
  "geometry": {"coordinates":[-76.668575,39.387441],"type":"Point"}
}