{
  "type": "Feature",
  "properties": {
    "addr:full":"8115 Bayou Bend Blvd Laurel MD 20724",
    "addr:housenumber":"8115",
    "addr:postcode":"20724",
    "addr:street":"Bayou Bend Blvd",
    "iso:country":"US",
    "sg:address":"8115 Bayou Bend Blvd",
    "sg:city":"Laurel",
    "sg:classifiers":[
        {
            "category":"Professional",
            "subcategory":"Accounting & Tax Preparation",
            "type":"Services"
        }
    ],
    "sg:phone":"+1 301 362 9083",
    "sg:postcode":"20724",
    "sg:province":"MD",
    "sg:tags":[
        "return",
        "filing"
    ],
    "wof:name":"C & C Tax Svc",
    "wof:placetype":"venue"
},
  "geometry": {"coordinates":[-76.803685,39.113932],"type":"Point"}
}