{
  "type": "Feature",
  "properties": {
    "addr:full":"7021 Pheasant Cross Dr Baltimore MD 21209",
    "addr:housenumber":"7021",
    "addr:postcode":"21209",
    "addr:street":"Pheasant Cross Dr",
    "iso:country":"US",
    "sg:address":"7021 Pheasant Cross Dr",
    "sg:city":"Baltimore",
    "sg:classifiers":[
        {
            "category":"Travel",
            "subcategory":"Travel Agent",
            "type":"Entertainment"
        }
    ],
    "sg:phone":"+1 410 484 1140",
    "sg:postcode":"21209",
    "sg:province":"MD",
    "sg:tags":[
        "agency"
    ],
    "wof:name":"Travel With Robin",
    "wof:placetype":"venue"
},
  "geometry": {"coordinates":[-76.67504099999999,39.385652],"type":"Point"}
}