{
  "type": "Feature",
  "properties": {
    "addr:full":"400 E Pratt St Fl 8 Baltimore MD 21202",
    "addr:housenumber":"400;8",
    "addr:postcode":"21202",
    "addr:street":"E Pratt St",
    "iso:country":"US",
    "sg:address":"400 E Pratt St Fl 8",
    "sg:city":"Baltimore",
    "sg:classifiers":[
        {
            "category":"Professional",
            "subcategory":"Management & Consulting",
            "type":"Services"
        },
        {
            "category":"Professional",
            "subcategory":"Business Services",
            "type":"Services"
        }
    ],
    "sg:phone":"+1 410 576 8337",
    "sg:postcode":"21202",
    "sg:province":"MD",
    "sg:tags":[
        "consultant",
        "organizing",
        "services-household"
    ],
    "wof:name":"H Gm Management",
    "wof:placetype":"venue"
},
  "geometry": {"coordinates":[-76.60929899999999,39.286652],"type":"Point"}
}