{
  "type": "Feature",
  "properties": {
    "iso:country":"US",
    "sg:address":"6301 Blackburn Ct",
    "sg:city":"Baltimore",
    "sg:classifiers":[
        {
            "category":"Building & Trades",
            "subcategory":"Construction",
            "type":"Services"
        }
    ],
    "sg:phone":"+1 410 433 7975",
    "sg:postcode":"21212",
    "sg:province":"MD",
    "sg:tags":[
        "home",
        "improvement"
    ],
    "wof:name":"Ms Fix-It Home Maintenance",
    "wof:placetype":"venue"
},
  "geometry": {"coordinates":[-76.61387499999999,39.371762],"type":"Point"}
}