{
  "type": "Feature",
  "properties": {
    "addr:full":"3517 Langrehr Rd Windsor Mill MD 21244",
    "addr:housenumber":"3517",
    "addr:postcode":"21244",
    "addr:street":"Langrehr Rd",
    "iso:country":"US",
    "sg:address":"3517 Langrehr Rd",
    "sg:city":"Windsor Mill",
    "sg:classifiers":[
        {
            "category":"Professional",
            "subcategory":"Accounting & Tax Preparation",
            "type":"Services"
        }
    ],
    "sg:phone":"+1 410 655 0600",
    "sg:postcode":"21244",
    "sg:province":"MD",
    "sg:tags":[
        "return",
        "filing"
    ],
    "wof:name":"Alfa Group Enterprises",
    "wof:placetype":"venue"
},
  "geometry": {"coordinates":[-76.76249799999999,39.355185],"type":"Point"}
}