{
  "type": "Feature",
  "properties": {
    "addr:full":"2545 Lord Baltimore Dr Windsor Mill MD 21244",
    "addr:housenumber":"2545",
    "addr:postcode":"21244",
    "addr:street":"Lord Baltimore Dr",
    "iso:country":"US",
    "sg:address":"2545 Lord Baltimore Dr",
    "sg:city":"Windsor Mill",
    "sg:classifiers":[
        {
            "category":"Wholesale",
            "subcategory":"Auto Parts",
            "type":"Manufacturing & Wholesale Goods"
        }
    ],
    "sg:phone":"+1 410 265 7265",
    "sg:postcode":"21244",
    "sg:province":"MD",
    "sg:tags":[
        "automobile",
        "supply"
    ],
    "wof:name":"TMI",
    "wof:placetype":"venue"
},
  "geometry": {"coordinates":[-76.74918099999999,39.324828],"type":"Point"}
}