{
  "type": "Feature",
  "properties": {
    "addr:full":"3425 Emory Church Rd Olney MD 20832",
    "addr:housenumber":"3425",
    "addr:postcode":"20832",
    "addr:street":"Emory Church Rd",
    "iso:country":"US",
    "sg:address":"3425 Emory Church Rd",
    "sg:city":"Olney",
    "sg:classifiers":[
        {
            "category":"Social Services",
            "subcategory":"Child Care",
            "type":"Services"
        }
    ],
    "sg:phone":"+1 301 774 5369",
    "sg:postcode":"20832",
    "sg:province":"MD",
    "sg:tags":[
        "kindergarten",
        "academic",
        "school"
    ],
    "wof:name":"Ark Children's Ctr",
    "wof:placetype":"venue"
},
  "geometry": {"coordinates":[-77.05805700000001,39.130234],"type":"Point"}
}