{
  "type": "Feature",
  "properties": {
    "iso:country":"US",
    "sg:address":"1123 E Baltimore St",
    "sg:city":"Baltimore",
    "sg:classifiers":[
        {
            "category":"Manufacturing",
            "subcategory":"Signs",
            "type":"Manufacturing & Wholesale Goods"
        }
    ],
    "sg:phone":"+1 410 342 9200",
    "sg:postcode":"21202",
    "sg:province":"MD",
    "sg:website":"www.intersignnational.org",
    "wof:name":"Inter Sign National Inc",
    "wof:placetype":"venue"
},
  "geometry": {"coordinates":[-76.601462,39.290842],"type":"Point"}
}