{
  "type": "Feature",
  "properties": {
    "addr:full":"7710 Annapolis Rd Lanham MD 20706",
    "addr:housenumber":"7710",
    "addr:postcode":"20706",
    "addr:street":"Annapolis Rd",
    "iso:country":"US",
    "sg:address":"7710 Annapolis Rd",
    "sg:city":"Lanham",
    "sg:classifiers":[
        {
            "category":"Autos & Motor Vehicles",
            "subcategory":"Automobile Sales",
            "type":"Retail Goods"
        }
    ],
    "sg:phone":"+1 301 731 0035",
    "sg:postcode":"20706",
    "sg:province":"MD",
    "sg:tags":[
        "car",
        "dealer"
    ],
    "wof:name":"KTK Chrysler Plymouth",
    "wof:placetype":"venue"
},
  "geometry": {"coordinates":[-76.878613,38.952842],"type":"Point"}
}