{
  "type": "Feature",
  "properties": {
    "addr:full":"72 Pershing St Cumberland MD 21502",
    "addr:housenumber":"72",
    "addr:postcode":"21502",
    "addr:street":"Pershing St",
    "iso:country":"US",
    "sg:address":"72 Pershing St",
    "sg:city":"Cumberland",
    "sg:classifiers":[
        {
            "category":"Professional",
            "subcategory":"Lawyer & Legal Services",
            "type":"Services"
        }
    ],
    "sg:phone":"+1 301 724 9234",
    "sg:postcode":"21502",
    "sg:province":"MD",
    "sg:tags":[
        "attorney"
    ],
    "wof:name":"Alexander & Cleaver",
    "wof:placetype":"venue"
},
  "geometry": {"coordinates":[-78.76148999999999,39.651001],"type":"Point"}
}