{
  "type": "Feature",
  "properties": {
    "iso:country":"US",
    "sg:address":"3869 Birdsville Rd",
    "sg:city":"Davidsonville",
    "sg:classifiers":[
        {
            "category":"Communications",
            "subcategory":"Film & Video Production",
            "type":"Services"
        }
    ],
    "sg:phone":"+1 301 261 7355",
    "sg:postcode":"21035",
    "sg:province":"MD",
    "sg:tags":[
        "motion"
    ],
    "wof:name":"Ellen M Buck Dvm",
    "wof:placetype":"venue"
},
  "geometry": {"coordinates":[-76.610901,38.899579],"type":"Point"}
}