{
  "type": "Feature",
  "properties": {
    "iso:country":"US",
    "sg:address":"1811 Castleton Rd",
    "sg:city":"Darlington",
    "sg:classifiers":[
        {
            "category":"Farming",
            "subcategory":"Farm",
            "type":"Manufacturing & Wholesale Goods"
        }
    ],
    "sg:phone":"+1 410 836 3939",
    "sg:postcode":"21034",
    "sg:province":"MD",
    "sg:tags":[
        "crop",
        "general"
    ],
    "wof:name":"Burcham Pervis",
    "wof:placetype":"venue"
},
  "geometry": {"coordinates":[-76.25163,39.674045],"type":"Point"}
}