{
  "type": "Feature",
  "properties": {
    "iso:country":"US",
    "sg:address":"9642 Cold Star Ct",
    "sg:city":"Columbia",
    "sg:classifiers":[
        {
            "category":"Professional",
            "subcategory":"Management & Consulting",
            "type":"Services"
        }
    ],
    "sg:phone":"+1 301 490 6716",
    "sg:postcode":"21046",
    "sg:province":"MD",
    "sg:tags":[
        "accounting",
        "consultant"
    ],
    "wof:name":"Enterprise Systems Sltions LLC",
    "wof:placetype":"venue"
},
  "geometry": {"coordinates":[-76.84009,39.161385],"type":"Point"}
}