{
  "type": "Feature",
  "properties": {
    "iso:country":"US",
    "sg:address":"251 Constant Ave",
    "sg:city":"Severn",
    "sg:classifiers":[
        {
            "category":"Local Transit",
            "type":"Transportation"
        }
    ],
    "sg:phone":"+1 410 672 3430",
    "sg:postcode":"21144",
    "sg:province":"MD",
    "sg:tags":[
        "bus",
        "line"
    ],
    "wof:name":"M & L Bus Svc Inc",
    "wof:placetype":"venue"
},
  "geometry": {"coordinates":[-76.67482800000001,39.096247],"type":"Point"}
}