{
  "type": "Feature",
  "properties": {
    "addr:full":"5820 Landover Rd Hyattsville MD 20784",
    "addr:housenumber":"5820",
    "addr:postcode":"20784",
    "addr:street":"Landover Rd",
    "iso:country":"US",
    "sg:address":"5820 Landover Rd",
    "sg:city":"Hyattsville",
    "sg:classifiers":[
        {
            "category":"Restaurant",
            "type":"Food & Drink"
        }
    ],
    "sg:phone":"+1 301 209 9006",
    "sg:postcode":"20784",
    "sg:province":"MD",
    "wof:name":"Fratelli",
    "wof:placetype":"venue"
},
  "geometry": {"coordinates":[-76.918098,38.935699],"type":"Point"}
}