{
  "type": "Feature",
  "properties": {
    "addr:full":"5814 Belair Rd Baltimore MD 21206",
    "addr:housenumber":"5814",
    "addr:postcode":"21206",
    "addr:street":"Belair Rd",
    "iso:country":"US",
    "sg:address":"5814 Belair Rd",
    "sg:city":"Baltimore",
    "sg:classifiers":[
        {
            "category":"Retail",
            "subcategory":"Repair Shop",
            "type":"Services"
        }
    ],
    "sg:phone":"+1 410 254 3333",
    "sg:postcode":"21206",
    "sg:province":"MD",
    "sg:tags":[
        "upholsterer"
    ],
    "wof:name":"Morton's Upholstery",
    "wof:placetype":"venue"
},
  "geometry": {"coordinates":[-76.543317,39.344025],"type":"Point"}
}