{
  "type": "Feature",
  "properties": {
    "iso:country":"US",
    "sg:address":"8503 Liberty Rd",
    "sg:city":"Randallstown",
    "sg:classifiers":[
        {
            "category":"Insurance",
            "subcategory":"Insurance Agent",
            "type":"Services"
        }
    ],
    "sg:phone":"+1 410 496 1457",
    "sg:postcode":"21133",
    "sg:province":"MD",
    "wof:name":"UHC Of Baltimore",
    "wof:placetype":"venue"
},
  "geometry": {"coordinates":[-76.77488200000001,39.359772],"type":"Point"}
}