{
  "type": "Feature",
  "properties": {
    "addr:full":"11812 Steam Mill Hill Rd Whaleysville MD 21872",
    "addr:housenumber":"11812",
    "addr:postcode":"21872",
    "addr:street":"Steam Mill Hill Rd",
    "iso:country":"US",
    "sg:address":"11812 Steam Mill Hill Rd",
    "sg:city":"Whaleysville",
    "sg:classifiers":[
        {
            "category":"Home & Garden",
            "subcategory":"Carpets & Floor Coverings",
            "type":"Retail Goods"
        }
    ],
    "sg:phone":"+1 410 629 1157",
    "sg:postcode":"21872",
    "sg:province":"MD",
    "wof:name":"D & B Carpet Installation",
    "wof:placetype":"venue"
},
  "geometry": {"coordinates":[-75.305931,38.402052],"type":"Point"}
}