{
  "type": "Feature",
  "properties": {
    "iso:country":"US",
    "sg:address":"2810 Old Washington Rd",
    "sg:city":"Waldorf",
    "sg:phone":"+1 301 645 7083",
    "sg:postcode":"20601",
    "sg:province":"MD",
    "sg:tags":[
        "gas"
    ],
    "wof:name":"Southern Maryland Gas Co",
    "wof:placetype":"venue"
},
  "geometry": {"coordinates":[-76.90110199999999,38.631747],"type":"Point"}
}