{
  "type": "Feature",
  "properties": {
    "addr:full":"7401 Willow Hill Dr Hyattsville MD 20785",
    "addr:housenumber":"7401",
    "addr:postcode":"20785",
    "addr:street":"Willow Hill Dr",
    "iso:country":"US",
    "sg:address":"7401 Willow Hill Dr",
    "sg:city":"Hyattsville",
    "sg:classifiers":[
        {
            "category":"Organizations",
            "subcategory":"Religious Organization",
            "type":"Services"
        }
    ],
    "sg:phone":"+1 301 324 8773",
    "sg:postcode":"20785",
    "sg:province":"MD",
    "sg:tags":[
        "church"
    ],
    "wof:name":"Royal Oak Pentecostal Church",
    "wof:placetype":"venue"
},
  "geometry": {"coordinates":[-76.87765400000001,38.895192],"type":"Point"}
}