{
  "type": "Feature",
  "properties": {
    "addr:full":"2600 Hollins Ferry Rd Baltimore MD 21230",
    "addr:housenumber":"2600",
    "addr:postcode":"21230",
    "addr:street":"Hollins Ferry Rd",
    "iso:country":"US",
    "sg:address":"2600 Hollins Ferry Rd",
    "sg:city":"Baltimore",
    "sg:classifiers":[
        {
            "category":"Food & Beverages",
            "subcategory":"Groceries & Convenience Stores",
            "type":"Retail Goods"
        }
    ],
    "sg:phone":"+1 410 837 1649",
    "sg:postcode":"21230",
    "sg:province":"MD",
    "wof:name":"Young's Grocery Store",
    "wof:placetype":"venue"
},
  "geometry": {"coordinates":[-76.642799,39.260201],"type":"Point"}
}