{
  "type": "Feature",
  "properties": {
    "iso:country":"US",
    "sg:address":"6010 University Blvd",
    "sg:city":"Ellicott City",
    "sg:classifiers":[
        {
            "category":"Retail",
            "subcategory":"Laundry & Dry Cleaning",
            "type":"Services"
        }
    ],
    "sg:phone":"+1 410 203 9833",
    "sg:postcode":"21043",
    "sg:province":"MD",
    "wof:name":"Pride Cleaners",
    "wof:placetype":"venue"
},
  "geometry": {"coordinates":[-76.797997,39.209202],"type":"Point"}
}