{
  "type": "Feature",
  "properties": {
    "iso:country":"US",
    "sg:address":"29466 Pintail Dr",
    "sg:city":"Easton",
    "sg:classifiers":[
        {
            "category":"Professional",
            "subcategory":"Business Services",
            "type":"Services"
        }
    ],
    "sg:phone":"+1 410 822 7753",
    "sg:postcode":"21601",
    "sg:province":"MD",
    "sg:tags":[
        "broker"
    ],
    "sg:website":"www.championrealty.com",
    "wof:name":"Champion LLD Commercial",
    "wof:placetype":"venue"
},
  "geometry": {"coordinates":[-76.053295,38.777058],"type":"Point"}
}