{
  "type": "Feature",
  "properties": {
    "iso:country":"US",
    "sg:address":"5308 Kelmscot Rd",
    "sg:city":"Rosedale",
    "sg:classifiers":[
        {
            "category":"Personal",
            "subcategory":"Nail Salon",
            "type":"Services"
        }
    ],
    "sg:phone":"+1 410 918 9989",
    "sg:postcode":"21237",
    "sg:province":"MD",
    "wof:name":"King Nail & Tan",
    "wof:placetype":"venue"
},
  "geometry": {"coordinates":[-76.469525,39.359847],"type":"Point"}
}