{
  "type": "Feature",
  "properties": {
    "addr:full":"200 Airport Rd Stevensville MD 21666",
    "addr:housenumber":"200",
    "addr:postcode":"21666",
    "addr:street":"Airport Rd",
    "iso:country":"US",
    "sg:address":"200 Airport Rd",
    "sg:city":"Stevensville",
    "sg:classifiers":[
        {
            "category":"Airport",
            "type":"Transportation"
        }
    ],
    "sg:phone":"+1 410 643 7728",
    "sg:postcode":"21666",
    "sg:province":"MD",
    "sg:tags":[
        "aircraft",
        "maintenance"
    ],
    "wof:name":"Safe Flight Inc",
    "wof:placetype":"venue"
},
  "geometry": {"coordinates":[-76.326739,38.974495],"type":"Point"}
}