{
  "type": "Feature",
  "properties": {
    "addr:full":"7701 Winterberry Pl Bethesda MD 20817",
    "addr:housenumber":"7701",
    "addr:postcode":"20817",
    "addr:street":"Winterberry Pl",
    "iso:country":"US",
    "sg:address":"7701 Winterberry Pl",
    "sg:city":"Bethesda",
    "sg:classifiers":[
        {
            "category":"Professional",
            "subcategory":"Lawyer & Legal Services",
            "type":"Services"
        }
    ],
    "sg:phone":"+1 301 229 1859",
    "sg:postcode":"20817",
    "sg:province":"MD",
    "wof:name":"Hickey J Patrick Atty",
    "wof:placetype":"venue"
},
  "geometry": {"coordinates":[-77.14070100000001,38.987701],"type":"Point"}
}