{
  "type": "Feature",
  "properties": {
    "addr:full":"24709 Hickory Hill Ln Rawlings MD 21557",
    "addr:housenumber":"24709",
    "addr:postcode":"21557",
    "addr:street":"Hickory Hill Ln",
    "iso:country":"US",
    "sg:address":"24709 Hickory Hill Ln",
    "sg:city":"Rawlings",
    "sg:classifiers":[
        {
            "category":"Professional",
            "subcategory":"Art Services",
            "type":"Services"
        }
    ],
    "sg:phone":"+1 301 786 4248",
    "sg:postcode":"21557",
    "sg:province":"MD",
    "sg:tags":[
        "photography",
        "commercial"
    ],
    "wof:name":"Life Images",
    "wof:placetype":"venue"
},
  "geometry": {"coordinates":[-78.96858,39.452517],"type":"Point"}
}