{
  "type": "Feature",
  "properties": {
    "iso:country":"US",
    "sg:address":"8633 Johnson Ave",
    "sg:city":"Glenarden",
    "sg:classifiers":[
        {
            "category":"Professional",
            "subcategory":"Lawyer & Legal Services",
            "type":"Services"
        }
    ],
    "sg:phone":"+1 301 772 5436",
    "sg:postcode":"20706",
    "sg:province":"MD",
    "sg:tags":[
        "attorney"
    ],
    "wof:name":"Patricia A Trivers",
    "wof:placetype":"venue"
},
  "geometry": {"coordinates":[-76.861001,38.932235],"type":"Point"}
}