{
  "type": "Feature",
  "properties": {
    "iso:country":"US",
    "sg:address":"5904 Woodland Dr",
    "sg:city":"Oxon Hill",
    "sg:classifiers":[
        {
            "category":"Professional",
            "subcategory":"Management & Consulting",
            "type":"Services"
        }
    ],
    "sg:phone":"+1 301 567 9599",
    "sg:postcode":"20745",
    "sg:province":"MD",
    "sg:tags":[
        "party",
        "planning"
    ],
    "wof:name":"Anita Minor Party",
    "wof:placetype":"venue"
},
  "geometry": {"coordinates":[-77.001549,38.807708],"type":"Point"}
}