{
  "type": "Feature",
  "properties": {
    "addr:full":"16507 Hunters Green Pkwy Hagerstown MD 21740",
    "addr:housenumber":"16507",
    "addr:postcode":"21740",
    "addr:street":"Hunters Green Pkwy",
    "iso:country":"US",
    "sg:address":"16507 Hunters Green Pkwy",
    "sg:city":"Hagerstown",
    "sg:classifiers":[
        {
            "category":"Professional",
            "subcategory":"Advertising",
            "type":"Services"
        }
    ],
    "sg:phone":"+1 301 582 3651",
    "sg:postcode":"21740",
    "sg:province":"MD",
    "sg:tags":[
        "distribution"
    ],
    "wof:name":"Lenox Distribution",
    "wof:placetype":"venue"
},
  "geometry": {"coordinates":[-77.79071999999999,39.624926],"type":"Point"}
}