{
  "type": "Feature",
  "properties": {
    "addr:full":"260 King George St Annapolis MD 21401",
    "addr:housenumber":"260",
    "addr:postcode":"21401",
    "addr:street":"King George St",
    "iso:country":"US",
    "sg:address":"260 King George St",
    "sg:city":"Annapolis",
    "sg:classifiers":[
        {
            "category":"Shopping",
            "subcategory":"Florist",
            "type":"Retail Goods"
        }
    ],
    "sg:phone":"+1 410 268 0188",
    "sg:postcode":"21401",
    "sg:province":"MD",
    "sg:website":"http://www.sandisflowershop.net",
    "wof:name":"Sandi's Flower Shop",
    "wof:placetype":"venue"
},
  "geometry": {"coordinates":[-76.489479,38.981918],"type":"Point"}
}