{
  "type": "Feature",
  "properties": {
    "addr:full":"3913 Emrick Ln Jarrettsville MD 21084",
    "addr:housenumber":"3913",
    "addr:postcode":"21084",
    "addr:street":"Emrick Ln",
    "iso:country":"US",
    "sg:address":"3913 Emrick Ln",
    "sg:city":"Jarrettsville",
    "sg:classifiers":[
        {
            "category":"Building & Trades",
            "subcategory":"Landscaping Services",
            "type":"Services"
        }
    ],
    "sg:phone":"+1 410 557 7301",
    "sg:postcode":"21084",
    "sg:province":"MD",
    "sg:tags":[
        "tree"
    ],
    "wof:name":"Centurion Tree Experts Inc",
    "wof:placetype":"venue"
},
  "geometry": {"coordinates":[-76.482933,39.628378],"type":"Point"}
}