{
  "type": "Feature",
  "properties": {
    "iso:country":"US",
    "sg:address":"534 Deale Rd",
    "sg:city":"Deale",
    "sg:classifiers":[
        {
            "category":"Personal",
            "subcategory":"Beauty Salon",
            "type":"Services"
        }
    ],
    "sg:phone":"+1 410 867 6990",
    "sg:postcode":"20751",
    "sg:province":"MD",
    "wof:name":"Hair Harbor",
    "wof:placetype":"venue"
},
  "geometry": {"coordinates":[-76.559995,38.781773],"type":"Point"}
}