{
  "type": "Feature",
  "properties": {
    "addr:full":"120 E Main St Elkton MD 21921",
    "addr:housenumber":"120",
    "addr:postcode":"21921",
    "addr:street":"E Main St",
    "iso:country":"US",
    "sg:address":"120 E Main St",
    "sg:city":"Elkton",
    "sg:classifiers":[
        {
            "category":"Shopping",
            "type":"Retail Goods"
        }
    ],
    "sg:phone":"+1 410 620 0300",
    "sg:postcode":"21921",
    "sg:province":"MD",
    "sg:tags":[
        "telephone",
        "cellular"
    ],
    "wof:name":"Sun Cellular",
    "wof:placetype":"venue"
},
  "geometry": {"coordinates":[-75.82839800000001,39.608368],"type":"Point"}
}