{
  "type": "Feature",
  "properties": {
    "iso:country":"US",
    "sg:address":"16477 Dunbar Ln",
    "sg:city":"Ridge",
    "sg:classifiers":[
        {
            "category":"Recreation",
            "type":"Entertainment"
        }
    ],
    "sg:phone":"+1 301 737 0255",
    "sg:postcode":"20680",
    "sg:province":"MD",
    "sg:tags":[
        "party",
        "fishing"
    ],
    "wof:name":"Playtime Fishing Charters Inc",
    "wof:placetype":"venue"
},
  "geometry": {"coordinates":[-76.389396,38.119855],"type":"Point"}
}