{
  "type": "Feature",
  "properties": {
    "addr:full":"7724 Old Alexandria Ferry Rd Clinton MD 20735",
    "addr:housenumber":"7724",
    "addr:postcode":"20735",
    "addr:street":"Old Alexandria Ferry Rd",
    "iso:country":"US",
    "sg:address":"7724 Old Alexandria Ferry Rd",
    "sg:city":"Clinton",
    "sg:classifiers":[
        {
            "category":"Retail",
            "subcategory":"Auto Repair",
            "type":"Services"
        }
    ],
    "sg:phone":"+1 301 856 8988",
    "sg:postcode":"20735",
    "sg:province":"MD",
    "sg:tags":[
        "wrecker"
    ],
    "wof:name":"Smitty Towing Svc",
    "wof:placetype":"venue"
},
  "geometry": {"coordinates":[-76.87213,38.778572],"type":"Point"}
}