{
  "type": "Feature",
  "properties": {
    "addr:full":"300 International Cir Cockeysville MD 21030",
    "addr:housenumber":"300",
    "addr:postcode":"21030",
    "addr:street":"International Cir",
    "iso:country":"US",
    "sg:address":"300 International Cir",
    "sg:city":"Cockeysville",
    "sg:classifiers":[
        {
            "category":"Building & Trades",
            "subcategory":"Construction",
            "type":"Services"
        }
    ],
    "sg:phone":"+1 410 527 0134",
    "sg:postcode":"21030",
    "sg:province":"MD",
    "sg:tags":[
        "contractor"
    ],
    "wof:name":"Maryland Masonic Homes",
    "wof:placetype":"venue"
},
  "geometry": {"coordinates":[-76.66419999999999,39.4972],"type":"Point"}
}