{
  "type": "Feature",
  "properties": {
    "addr:full":"6476 Dobbin Center Way Columbia MD 21045",
    "addr:housenumber":"6476",
    "addr:postcode":"21045",
    "addr:street":"Dobbin Center Way",
    "iso:country":"US",
    "sg:address":"6476 Dobbin Center Way",
    "sg:city":"Columbia",
    "sg:classifiers":[
        {
            "category":"Home & Garden",
            "subcategory":"Carpets & Floor Coverings",
            "type":"Retail Goods"
        }
    ],
    "sg:phone":"+1 410 730 0040",
    "sg:postcode":"21045",
    "sg:province":"MD",
    "sg:tags":[
        "mattress"
    ],
    "wof:name":"Mattress Discounters",
    "wof:placetype":"venue"
},
  "geometry": {"coordinates":[-76.82060199999999,39.1973],"type":"Point"}
}