{
  "type": "Feature",
  "properties": {
    "addr:full":"10055 Washington Blvd N Laurel MD 20723",
    "addr:housenumber":"10055",
    "addr:postcode":"20723",
    "addr:street":"Washington Blvd N",
    "iso:country":"US",
    "sg:address":"10055 Washington Blvd N",
    "sg:city":"Laurel",
    "sg:classifiers":[
        {
            "category":"Food & Beverages",
            "subcategory":"Liquor & Beverages",
            "type":"Retail Goods"
        }
    ],
    "sg:phone":"+1 301 497 7200",
    "sg:postcode":"20723",
    "sg:province":"MD",
    "sg:tags":[
        "beer",
        "spirit",
        "wine"
    ],
    "wof:name":"Island Liquors",
    "wof:placetype":"venue"
},
  "geometry": {"coordinates":[-76.83760100000001,39.109798],"type":"Point"}
}