{
  "type": "Feature",
  "properties": {
    "iso:country":"US",
    "sg:address":"7001 Golden Ring Rd",
    "sg:city":"Rosedale",
    "sg:classifiers":[
        {
            "category":"Building & Trades",
            "subcategory":"Equipment Rental",
            "type":"Services"
        }
    ],
    "sg:phone":"+1 410 780 0900",
    "sg:postcode":"21237",
    "sg:province":"MD",
    "sg:tags":[
        "contractor"
    ],
    "sg:website":"www.rentitatabc.com",
    "wof:name":"ABC Rental",
    "wof:placetype":"venue"
},
  "geometry": {"coordinates":[-76.493251,39.332771],"type":"Point"}
}