{
  "type": "Feature",
  "properties": {
    "addr:full":"1814 Oakland Rd Freeland MD 21053",
    "addr:housenumber":"1814",
    "addr:postcode":"21053",
    "addr:street":"Oakland Rd",
    "iso:country":"US",
    "sg:address":"1814 Oakland Rd",
    "sg:city":"Freeland",
    "sg:phone":"+1 410 357 8478",
    "sg:postcode":"21053",
    "sg:province":"MD",
    "sg:tags":[
        "farm",
        "grain",
        "cash"
    ],
    "wof:name":"Edward Bowman",
    "wof:placetype":"venue"
},
  "geometry": {"coordinates":[-76.71364699999999,39.715697],"type":"Point"}
}