{
  "type": "Feature",
  "properties": {
    "addr:full":"401 Central Ave Brunswick MD 21716",
    "addr:housenumber":"401",
    "addr:postcode":"21716",
    "addr:street":"Central Ave",
    "iso:country":"US",
    "sg:address":"401 Central Ave",
    "sg:city":"Brunswick",
    "sg:classifiers":[
        {
            "category":"Organizations",
            "subcategory":"Community Association",
            "type":"Services"
        }
    ],
    "sg:phone":"+1 301 834 6390",
    "sg:postcode":"21716",
    "sg:province":"MD",
    "sg:tags":[
        "fraternal"
    ],
    "wof:name":"Fraternal Order Of Eagles",
    "wof:placetype":"venue"
},
  "geometry": {"coordinates":[-77.634168,39.318],"type":"Point"}
}