{
  "type": "Feature",
  "properties": {
    "addr:full":"385 Muddy Branch Rd Gaithersburg MD 20878",
    "addr:housenumber":"385",
    "addr:postcode":"20878",
    "addr:street":"Muddy Branch Rd",
    "iso:country":"US",
    "sg:address":"385 Muddy Branch Rd",
    "sg:city":"Gaithersburg",
    "sg:classifiers":[
        {
            "category":"Cinema",
            "subcategory":"Movie Rental",
            "type":"Entertainment"
        }
    ],
    "sg:phone":"+1 301 417 0660",
    "sg:postcode":"20878",
    "sg:province":"MD",
    "sg:tags":[
        "leasing",
        "video",
        "disc",
        "tape"
    ],
    "wof:name":"Blockbuster Video",
    "wof:placetype":"venue"
},
  "geometry": {"coordinates":[-77.213807,39.12448],"type":"Point"}
}