{
  "type": "Feature",
  "properties": {
    "addr:full":"4412 Suitland Rd Suitland MD 20746",
    "addr:housenumber":"4412",
    "addr:postcode":"20746",
    "addr:street":"Suitland Rd",
    "iso:country":"US",
    "sg:address":"4412 Suitland Rd",
    "sg:city":"Suitland",
    "sg:classifiers":[
        {
            "category":"Autos & Motor Vehicles",
            "subcategory":"Auto Supplies",
            "type":"Retail Goods"
        }
    ],
    "sg:phone":"+1 301 420 5008",
    "sg:postcode":"20746",
    "sg:province":"MD",
    "sg:tags":[
        "tire"
    ],
    "wof:name":"Speedy Auto Center by Monro",
    "wof:placetype":"venue"
},
  "geometry": {"coordinates":[-76.932602,38.8521],"type":"Point"}
}