{
  "type": "Feature",
  "properties": {
    "addr:full":"1420 W Patrick St Frederick MD 21702",
    "addr:housenumber":"1420",
    "addr:postcode":"21702",
    "addr:street":"W Patrick St",
    "iso:country":"US",
    "sg:address":"1420 W Patrick St",
    "sg:city":"Frederick",
    "sg:classifiers":[
        {
            "category":"Real Estate",
            "subcategory":"Real Estate Services",
            "type":"Services"
        }
    ],
    "sg:phone":"+1 301 607 0070",
    "sg:postcode":"21702",
    "sg:province":"MD",
    "sg:tags":[
        "company",
        "title"
    ],
    "wof:name":"Keystone Title",
    "wof:placetype":"venue"
},
  "geometry": {"coordinates":[-77.46326000000001,39.420184],"type":"Point"}
}