{
  "type": "Feature",
  "properties": {
    "iso:country":"US",
    "sg:address":"15035 Burnt Store Rd",
    "sg:city":"Hughesville",
    "sg:classifiers":[
        {
            "category":"Utilities",
            "subcategory":"Electric",
            "type":"Services"
        }
    ],
    "sg:phone":"+1 301 274 3111",
    "sg:postcode":"20637",
    "sg:province":"MD",
    "wof:name":"Smeco",
    "wof:placetype":"venue"
},
  "geometry": {"coordinates":[-76.788005,38.532355],"type":"Point"}
}