{
  "type": "Feature",
  "properties": {
    "iso:country":"US",
    "sg:address":"5600 Wisconsin Ave",
    "sg:city":"Chevy Chase",
    "sg:classifiers":[
        {
            "category":"Professional",
            "subcategory":"Lawyer & Legal Services",
            "type":"Services"
        }
    ],
    "sg:phone":"+1 301 907 8727",
    "sg:postcode":"20815",
    "sg:province":"MD",
    "wof:name":"Schlosberg Hubert M Lwyr",
    "wof:placetype":"venue"
},
  "geometry": {"coordinates":[-77.088097,38.9655],"type":"Point"}
}