{
  "type": "Feature",
  "properties": {
    "addr:full":"4428 Southern Businss Park Dr White Plains MD 20695",
    "addr:housenumber":"4428",
    "addr:postcode":"20695",
    "addr:street":"Southern Businss Park Dr",
    "iso:country":"US",
    "sg:address":"4428 Southern Businss Park Dr",
    "sg:city":"White Plains",
    "sg:classifiers":[
        {
            "category":"Wholesale",
            "subcategory":"Hardware",
            "type":"Manufacturing & Wholesale Goods"
        }
    ],
    "sg:phone":"+1 301 870 3120",
    "sg:postcode":"20695",
    "sg:province":"MD",
    "wof:name":"Closet & Hardware Supply Inc",
    "wof:placetype":"venue"
},
  "geometry": {"coordinates":[-76.94834,38.591218],"type":"Point"}
}