{
  "type": "Feature",
  "properties": {
    "addr:full":"5550 Friendship Blvd Chevy Chase MD 20815",
    "addr:housenumber":"5550",
    "addr:postcode":"20815",
    "addr:street":"Friendship Blvd",
    "iso:country":"US",
    "sg:address":"5550 Friendship Blvd",
    "sg:city":"Chevy Chase",
    "sg:classifiers":[
        {
            "category":"Communications",
            "subcategory":"Newspaper",
            "type":"Services"
        }
    ],
    "sg:phone":"+1 301 657 9830",
    "sg:postcode":"20815",
    "sg:province":"MD",
    "sg:tags":[
        "print",
        "medium"
    ],
    "wof:name":"Weekly Pharmacy Reports Green",
    "wof:placetype":"venue"
},
  "geometry": {"coordinates":[-77.0895,38.963799],"type":"Point"}
}