{
  "type": "Feature",
  "properties": {
    "addr:full":"621 Wood Lot Trail Rd Annapolis MD 21401",
    "addr:housenumber":"621",
    "addr:postcode":"21401",
    "addr:street":"Wood Lot Trail Rd",
    "iso:country":"US",
    "sg:address":"621 Wood Lot Trail Rd",
    "sg:city":"Annapolis",
    "sg:classifiers":[
        {
            "category":"Professional",
            "type":"Services"
        }
    ],
    "sg:phone":"+1 410 897 0620",
    "sg:postcode":"21401",
    "sg:province":"MD",
    "wof:name":"Joseph Skufca",
    "wof:placetype":"venue"
},
  "geometry": {"coordinates":[-76.59907,38.996349],"type":"Point"}
}