{
  "type": "Feature",
  "properties": {
    "addr:full":"404 Byrn St Cambridge MD 21613",
    "addr:housenumber":"404",
    "addr:postcode":"21613",
    "addr:street":"Byrn St",
    "iso:country":"US",
    "sg:address":"404 Byrn St",
    "sg:city":"Cambridge",
    "sg:classifiers":[
        {
            "category":"Health Services",
            "subcategory":"Doctor",
            "type":"Services"
        }
    ],
    "sg:phone":"+1 410 221 0448",
    "sg:postcode":"21613",
    "sg:province":"MD",
    "sg:tags":[
        "physician",
        "surgeon"
    ],
    "wof:name":"Kamsheh Mw",
    "wof:placetype":"venue"
},
  "geometry": {"coordinates":[-76.06730399999999,38.57049],"type":"Point"}
}