{
  "type": "Feature",
  "properties": {
    "addr:full":"17 Fontana Ln Baltimore MD 21237",
    "addr:housenumber":"17",
    "addr:postcode":"21237",
    "addr:street":"Fontana Ln",
    "iso:country":"US",
    "sg:address":"17 Fontana Ln",
    "sg:city":"Baltimore",
    "sg:classifiers":[
        {
            "category":"Health Services",
            "subcategory":"Health Practitioner",
            "type":"Services"
        }
    ],
    "sg:phone":"+1 410 686 3001",
    "sg:postcode":"21237",
    "sg:province":"MD",
    "sg:tags":[
        "therapist",
        "physical"
    ],
    "wof:name":"Pacific Rehab Inc",
    "wof:placetype":"venue"
},
  "geometry": {"coordinates":[-76.488434,39.339018],"type":"Point"}
}