{
  "type": "Feature",
  "properties": {
    "addr:full":"30 Church St Prince Frederick MD 20678",
    "addr:housenumber":"30",
    "addr:postcode":"20678",
    "addr:street":"Church St",
    "iso:country":"US",
    "sg:address":"30 Church St",
    "sg:city":"Prince Frederick",
    "sg:classifiers":[
        {
            "category":"Health Services",
            "subcategory":"Clinic",
            "type":"Services"
        }
    ],
    "sg:phone":"+1 410 286 3030",
    "sg:postcode":"20678",
    "sg:province":"MD",
    "sg:tags":[
        "holistic",
        "practitioner"
    ],
    "wof:name":"Chesapeake Healing Arts Ctr",
    "wof:placetype":"venue"
},
  "geometry": {"coordinates":[-76.58708799999999,38.537977],"type":"Point"}
}