{
  "type": "Feature",
  "properties": {
    "addr:full":"1701 Russell St Baltimore MD 21230",
    "addr:housenumber":"1701",
    "addr:postcode":"21230",
    "addr:street":"Russell St",
    "iso:country":"US",
    "sg:address":"1701 Russell St",
    "sg:city":"Baltimore",
    "sg:classifiers":[
        {
            "category":"Restaurant",
            "type":"Food & Drink"
        }
    ],
    "sg:phone":"+1 410 837 1520",
    "sg:postcode":"21230",
    "sg:province":"MD",
    "wof:name":"P K's Restaurant",
    "wof:placetype":"venue"
},
  "geometry": {"coordinates":[-76.629274,39.273073],"type":"Point"}
}