{
  "type": "Feature",
  "properties": {
    "addr:full":"10443 Frederick Rd Ellicott City MD 21042",
    "addr:housenumber":"10443",
    "addr:postcode":"21042",
    "addr:street":"Frederick Rd",
    "iso:country":"US",
    "sg:address":"10443 Frederick Rd",
    "sg:city":"Ellicott City",
    "sg:classifiers":[
        {
            "category":"Retail",
            "subcategory":"Veterinary Services",
            "type":"Services"
        }
    ],
    "sg:phone":"+1 410 465 6676",
    "sg:postcode":"21042",
    "sg:province":"MD",
    "sg:tags":[
        "veterinarian"
    ],
    "wof:name":"Ellicott City Veterinary Clnc",
    "wof:placetype":"venue"
},
  "geometry": {"coordinates":[-76.875665,39.281808],"type":"Point"}
}