{
  "type": "Feature",
  "properties": {
    "addr:full":"1044 Virginia Ave Hagerstown MD 21740",
    "addr:housenumber":"1044",
    "addr:postcode":"21740",
    "addr:street":"Virginia Ave",
    "iso:country":"US",
    "sg:address":"1044 Virginia Ave",
    "sg:city":"Hagerstown",
    "sg:classifiers":[
        {
            "category":"Manufacturing",
            "subcategory":"Signs",
            "type":"Manufacturing & Wholesale Goods"
        }
    ],
    "sg:phone":"+1 301 797 7491",
    "sg:postcode":"21740",
    "sg:province":"MD",
    "wof:name":"Quality Signs",
    "wof:placetype":"venue"
},
  "geometry": {"coordinates":[-77.736996,39.627948],"type":"Point"}
}