{
  "type": "Feature",
  "properties": {
    "iso:country":"US",
    "sg:address":"9700 Great Seneca Hwy",
    "sg:city":"Rockville",
    "sg:classifiers":[
        {
            "category":"Professional",
            "type":"Services"
        }
    ],
    "sg:phone":"+1 240 453 6255",
    "sg:postcode":"20850",
    "sg:province":"MD",
    "sg:tags":[
        "establishment"
    ],
    "wof:name":"Stemron",
    "wof:placetype":"venue"
},
  "geometry": {"coordinates":[-77.20436,39.098617],"type":"Point"}
}