{
  "type": "Feature",
  "properties": {
    "iso:country":"US",
    "sg:address":"703 Trout Dale Pl",
    "sg:city":"Bel Air",
    "sg:classifiers":[
        {
            "category":"Professional",
            "subcategory":"Art Services",
            "type":"Services"
        }
    ],
    "sg:phone":"+1 410 893 2266",
    "sg:postcode":"21014",
    "sg:province":"MD",
    "sg:tags":[
        "graphic",
        "designer"
    ],
    "wof:name":"Williams Artworks",
    "wof:placetype":"venue"
},
  "geometry": {"coordinates":[-76.345497,39.545766],"type":"Point"}
}