{
  "type": "Feature",
  "properties": {
    "iso:country":"US",
    "sg:address":"2059 Baltimore Blvd",
    "sg:city":"Finksburg",
    "sg:classifiers":[
        {
            "category":"Health Services",
            "subcategory":"Doctor",
            "type":"Services"
        }
    ],
    "sg:phone":"+1 410 876 5481",
    "sg:postcode":"21048",
    "sg:province":"MD",
    "sg:tags":[
        "physician",
        "surgeon"
    ],
    "wof:name":"Eutaw Oncology Assoc",
    "wof:placetype":"venue"
},
  "geometry": {"coordinates":[-76.930164,39.537109],"type":"Point"}
}