{
  "type": "Feature",
  "properties": {
    "addr:full":"1000 Prime Outlets Blvd Hagerstown MD 21740",
    "addr:housenumber":"1000",
    "addr:postcode":"21740",
    "addr:street":"Prime Outlets Blvd",
    "iso:country":"US",
    "sg:address":"1000 Prime Outlets Blvd",
    "sg:city":"Hagerstown",
    "sg:classifiers":[
        {
            "category":"Restaurant",
            "type":"Food & Drink"
        }
    ],
    "sg:menulink":"http://www.allmenus.com/md/funkstown/98606-longhorn-steakhouse/menu/",
    "sg:phone":"+1 301 393 8119",
    "sg:postcode":"21740",
    "sg:province":"MD",
    "sg:tags":[
        "american",
        "steakhouse"
    ],
    "wof:name":"LongHorn Steakhouse",
    "wof:placetype":"venue"
},
  "geometry": {"coordinates":[-77.731785,39.607799],"type":"Point"}
}