{
  "type": "Feature",
  "properties": {
    "iso:country":"US",
    "sg:address":"12129 Darnestown Rd",
    "sg:city":"Gaithersburg",
    "sg:classifiers":[
        {
            "category":"Health Services",
            "subcategory":"Optometrist",
            "type":"Services"
        }
    ],
    "sg:phone":"+1 240 683 6220",
    "sg:postcode":"20878",
    "sg:province":"MD",
    "wof:name":"Potomac Eye Care",
    "wof:placetype":"venue"
},
  "geometry": {"coordinates":[-77.251763,39.117636],"type":"Point"}
}