{
  "type": "Feature",
  "properties": {
    "addr:full":"7839 Eastpoint Mall Baltimore MD 21224",
    "addr:housenumber":"7839",
    "addr:postcode":"21224",
    "addr:street":"Eastpoint Mall",
    "iso:country":"US",
    "sg:address":"7839 Eastpoint Mall",
    "sg:city":"Baltimore",
    "sg:classifiers":[
        {
            "category":"Travel",
            "subcategory":"Travel Agent",
            "type":"Entertainment"
        }
    ],
    "sg:phone":"+1 410 284 9200",
    "sg:postcode":"21224",
    "sg:province":"MD",
    "sg:tags":[
        "agency",
        "bureau"
    ],
    "sg:website":"www.goingplacesinc.com",
    "wof:name":"Going Places Inc",
    "wof:placetype":"venue"
},
  "geometry": {"coordinates":[-76.50648,39.29383],"type":"Point"}
}