{
  "type": "Feature",
  "properties": {
    "iso:country":"US",
    "sg:address":"301 W Pennsylvania Ave",
    "sg:city":"Towson",
    "sg:classifiers":[
        {
            "category":"Professional",
            "subcategory":"Lawyer & Legal Services",
            "type":"Services"
        }
    ],
    "sg:phone":"+1 443 519 5654",
    "sg:postcode":"21204",
    "sg:province":"MD",
    "sg:tags":[
        "attorney",
        "practice",
        "plan"
    ],
    "wof:name":"Law Office Of Jose A Molina",
    "wof:placetype":"venue"
},
  "geometry": {"coordinates":[-76.60855100000001,39.401089],"type":"Point"}
}