{
  "type": "Feature",
  "properties": {
    "addr:full":"2801 Caraway Ct Edgewater MD 21037",
    "addr:housenumber":"2801",
    "addr:postcode":"21037",
    "addr:street":"Caraway Ct",
    "iso:country":"US",
    "sg:address":"2801 Caraway Ct",
    "sg:city":"Edgewater",
    "sg:classifiers":[
        {
            "category":"Personal",
            "type":"Services"
        }
    ],
    "sg:phone":"+1 410 224 5678",
    "sg:postcode":"21037",
    "sg:province":"MD",
    "sg:tags":[
        "electrolysis"
    ],
    "wof:name":"Annapolis-Edgewater Elctrlys",
    "wof:placetype":"venue"
},
  "geometry": {"coordinates":[-76.555537,38.966778],"type":"Point"}
}