{
  "type": "Feature",
  "properties": {
    "addr:full":"8278 Vosges Rd Baltimore MD 21244",
    "addr:housenumber":"8278",
    "addr:postcode":"21244",
    "addr:street":"Vosges Rd",
    "iso:country":"US",
    "sg:address":"8278 Vosges Rd",
    "sg:city":"Baltimore",
    "sg:classifiers":[
        {
            "category":"Restaurant",
            "type":"Food & Drink"
        }
    ],
    "sg:phone":"+1 410 655 0226",
    "sg:postcode":"21244",
    "sg:province":"MD",
    "sg:tags":[
        "eating"
    ],
    "wof:name":"Descriptive Designs",
    "wof:placetype":"venue"
},
  "geometry": {"coordinates":[-76.75852399999999,39.360683],"type":"Point"}
}