{
  "type": "Feature",
  "properties": {
    "iso:country":"US",
    "sg:address":"40 W Gude Dr",
    "sg:city":"Rockville",
    "sg:classifiers":[
        {
            "category":"Utilities",
            "subcategory":"Cable",
            "type":"Services"
        }
    ],
    "sg:phone":"+1 301 309 5100",
    "sg:postcode":"20850",
    "sg:province":"MD",
    "sg:tags":[
        "television"
    ],
    "sg:website":"www.comcast.com",
    "wof:name":"Montgomery-Comcast Spotlight",
    "wof:placetype":"venue"
},
  "geometry": {"coordinates":[-77.1609,39.106537],"type":"Point"}
}