{
  "type": "Feature",
  "properties": {
    "iso:country":"US",
    "sg:address":"65 Washington Rd",
    "sg:city":"Westminster",
    "sg:classifiers":[
        {
            "category":"Social Services",
            "subcategory":"Child Care",
            "type":"Services"
        },
        {
            "category":"Education",
            "subcategory":"Preschool",
            "type":"Public Place"
        },
        {
            "category":"Education",
            "subcategory":"School",
            "type":"Public Place"
        }
    ],
    "sg:phone":"+1 410 857 4389",
    "sg:postcode":"21157",
    "sg:province":"MD",
    "sg:tags":[
        "kindergarten",
        "nursery",
        "day"
    ],
    "sg:website":"http://www.christianpreschoolkindergarten.com",
    "wof:name":"Christian Preschool & Kindergarten Program",
    "wof:placetype":"venue"
},
  "geometry": {"coordinates":[-76.987746,39.562148],"type":"Point"}
}