{
  "type": "Feature",
  "properties": {
    "addr:full":"1930 Spencerville Rd Spencerville MD 20868",
    "addr:housenumber":"1930",
    "addr:postcode":"20868",
    "addr:street":"Spencerville Rd",
    "iso:country":"US",
    "sg:address":"1930 Spencerville Rd",
    "sg:city":"Spencerville",
    "sg:classifiers":[
        {
            "category":"Organizations",
            "subcategory":"Religious Organization",
            "type":"Services"
        }
    ],
    "sg:phone":"+1 301 421 9298",
    "sg:postcode":"20868",
    "sg:province":"MD",
    "wof:name":"Buddha True",
    "wof:placetype":"venue"
},
  "geometry": {"coordinates":[-76.971948,39.118032],"type":"Point"}
}