{
  "type": "Feature",
  "properties": {
    "addr:full":"10274 Lake Arbor Way Bowie MD 20721",
    "addr:housenumber":"10274",
    "addr:postcode":"20721",
    "addr:street":"Lake Arbor Way",
    "iso:country":"US",
    "sg:address":"10274 Lake Arbor Way",
    "sg:city":"Bowie",
    "sg:classifiers":[
        {
            "category":"Health Services",
            "subcategory":"Doctor",
            "type":"Services"
        }
    ],
    "sg:phone":"+1 301 324 0054",
    "sg:postcode":"20721",
    "sg:province":"MD",
    "wof:name":"Southern Maryland Pediatrics",
    "wof:placetype":"venue"
},
  "geometry": {"coordinates":[-76.829432,38.90555],"type":"Point"}
}