{
  "type": "Feature",
  "properties": {
    "addr:full":"1201 Wicomico St Baltimore MD 21230",
    "addr:housenumber":"1201",
    "addr:postcode":"21230",
    "addr:street":"Wicomico St",
    "iso:country":"US",
    "sg:address":"1201 Wicomico St",
    "sg:city":"Baltimore",
    "sg:classifiers":[
        {
            "category":"Wholesale",
            "subcategory":"Hardware",
            "type":"Manufacturing & Wholesale Goods"
        }
    ],
    "sg:phone":"+1 410 962 8477",
    "sg:postcode":"21230",
    "sg:province":"MD",
    "sg:tags":[
        "tool"
    ],
    "wof:name":"Snap-On Tools Co",
    "wof:placetype":"venue"
},
  "geometry": {"coordinates":[-76.632848,39.276638],"type":"Point"}
}