{
  "type": "Feature",
  "properties": {
    "addr:full":"11 Broad St Berlin MD 21811",
    "addr:housenumber":"11",
    "addr:postcode":"21811",
    "addr:street":"Broad St",
    "iso:country":"US",
    "sg:address":"11 Broad St",
    "sg:city":"Berlin",
    "sg:classifiers":[
        {
            "category":"Building & Trades",
            "subcategory":"Landscaping Services",
            "type":"Services"
        }
    ],
    "sg:phone":"+1 410 641 2177",
    "sg:postcode":"21811",
    "sg:province":"MD",
    "sg:tags":[
        "landscape",
        "contractor"
    ],
    "sg:website":"www.moorecompanies.com",
    "wof:name":"Moore's Sod Farms Inc",
    "wof:placetype":"venue"
},
  "geometry": {"coordinates":[-75.219477,38.324927],"type":"Point"}
}