{
  "type": "Feature",
  "properties": {
    "iso:country":"US",
    "sg:address":"9081 Shady Grove Ct",
    "sg:city":"Gaithersburg",
    "sg:classifiers":[
        {
            "category":"Professional",
            "subcategory":"Accounting & Tax Preparation",
            "type":"Services"
        }
    ],
    "sg:phone":"+1 301 975 0093",
    "sg:postcode":"20877",
    "sg:province":"MD",
    "sg:tags":[
        "accountant"
    ],
    "wof:name":"Raman R Desai CPA",
    "wof:placetype":"venue"
},
  "geometry": {"coordinates":[-77.183987,39.119923],"type":"Point"}
}