{
  "type": "Feature",
  "properties": {
    "addr:full":"443 Harrisville Rd Colora MD 21917",
    "addr:housenumber":"443",
    "addr:postcode":"21917",
    "addr:street":"Harrisville Rd",
    "iso:country":"US",
    "sg:address":"443 Harrisville Rd",
    "sg:city":"Colora",
    "sg:classifiers":[
        {
            "category":"Professional",
            "subcategory":"Business Services",
            "type":"Services"
        }
    ],
    "sg:phone":"+1 410 658 2990",
    "sg:postcode":"21917",
    "sg:province":"MD",
    "sg:tags":[
        "auctioneer"
    ],
    "wof:name":"Nationwide Auction Systems",
    "wof:placetype":"venue"
},
  "geometry": {"coordinates":[-76.078761,39.678979],"type":"Point"}
}