{
  "type": "Feature",
  "properties": {
    "iso:country":"US",
    "sg:address":"2907 E Northern Pkwy",
    "sg:city":"Baltimore",
    "sg:classifiers":[
        {
            "category":"Building & Trades",
            "subcategory":"Construction",
            "type":"Services"
        }
    ],
    "sg:phone":"+1 443 794 3100",
    "sg:postcode":"21214",
    "sg:province":"MD",
    "sg:tags":[
        "waterproofing",
        "fireproofing",
        "contractor"
    ],
    "wof:name":"A T Professional Sealcoat",
    "wof:placetype":"venue"
},
  "geometry": {"coordinates":[-76.553308,39.363748],"type":"Point"}
}