{
  "type": "Feature",
  "properties": {
    "addr:full":"6000 Ritchie Hwy Brooklyn MD 21225",
    "addr:housenumber":"6000",
    "addr:postcode":"21225",
    "addr:street":"Ritchie Hwy",
    "iso:country":"US",
    "sg:address":"6000 Ritchie Hwy",
    "sg:city":"Brooklyn",
    "sg:classifiers":[
        {
            "category":"Autos & Motor Vehicles",
            "subcategory":"Automobile Sales",
            "type":"Retail Goods"
        }
    ],
    "sg:phone":"+1 410 636 3035",
    "sg:postcode":"21225",
    "sg:province":"MD",
    "sg:tags":[
        "dealers-used",
        "car",
        "used",
        "cars-wholesale"
    ],
    "wof:name":"R T M Motors",
    "wof:placetype":"venue"
},
  "geometry": {"coordinates":[-76.615021,39.211632],"type":"Point"}
}