{
  "type": "Feature",
  "properties": {
    "iso:country":"US",
    "sg:address":"4707 Schley Ave",
    "sg:city":"Braddock Heights",
    "sg:classifiers":[
        {
            "category":"Communications",
            "subcategory":"Radio Station",
            "type":"Services"
        }
    ],
    "sg:phone":"+1 301 662 9090",
    "sg:postcode":"21703",
    "sg:province":"MD",
    "sg:tags":[
        "company",
        "broadcasting"
    ],
    "sg:website":"www.wjtm.org",
    "wof:name":"WJTM",
    "wof:placetype":"venue"
},
  "geometry": {"coordinates":[-77.503169,39.419194],"type":"Point"}
}