{
  "type": "Feature",
  "properties": {
    "addr:full":"19342 Paradise Manor Dr Hagerstown MD 21742",
    "addr:housenumber":"19342",
    "addr:postcode":"21742",
    "addr:street":"Paradise Manor Dr",
    "iso:country":"US",
    "sg:address":"19342 Paradise Manor Dr",
    "sg:city":"Hagerstown",
    "sg:classifiers":[
        {
            "category":"Home & Garden",
            "subcategory":"Furniture",
            "type":"Retail Goods"
        }
    ],
    "sg:phone":"+1 301 745 3092",
    "sg:postcode":"21742",
    "sg:province":"MD",
    "sg:tags":[
        "store"
    ],
    "wof:name":"A N S Furniture Inc.",
    "wof:placetype":"venue"
},
  "geometry": {"coordinates":[-77.698519,39.692079],"type":"Point"}
}