{
  "type": "Feature",
  "properties": {
    "iso:country":"US",
    "sg:address":"2103 W Pratt St",
    "sg:city":"Baltimore",
    "sg:classifiers":[
        {
            "category":"Shopping",
            "subcategory":"Used Merchandise",
            "type":"Retail Goods"
        }
    ],
    "sg:phone":"+1 410 233 6011",
    "sg:postcode":"21223",
    "sg:province":"MD",
    "sg:tags":[
        "shop",
        "thrift"
    ],
    "wof:name":"WBR Flea Market Store",
    "wof:placetype":"venue"
},
  "geometry": {"coordinates":[-76.650541,39.284894],"type":"Point"}
}