{
  "type": "Feature",
  "properties": {
    "iso:country":"US",
    "sg:address":"659 E 25th St",
    "sg:city":"Baltimore",
    "sg:classifiers":[
        {
            "category":"Wholesale",
            "subcategory":"Auto Parts",
            "type":"Manufacturing & Wholesale Goods"
        }
    ],
    "sg:phone":"+1 410 467 8980",
    "sg:postcode":"21218",
    "sg:province":"MD",
    "sg:tags":[
        "automobile",
        "accessory"
    ],
    "sg:website":"www.fergusoncorp.net",
    "wof:name":"Ferguson Corp",
    "wof:placetype":"venue"
},
  "geometry": {"coordinates":[-76.605575,39.318262],"type":"Point"}
}