{
  "type": "Feature",
  "properties": {
    "addr:full":"21836 National Pike Boonsboro MD 21713",
    "addr:housenumber":"21836",
    "addr:postcode":"21713",
    "addr:street":"National Pike",
    "iso:country":"US",
    "sg:address":"21836 National Pike",
    "sg:city":"Boonsboro",
    "sg:classifiers":[
        {
            "category":"Bars & Pubs",
            "type":"Food & Drink"
        }
    ],
    "sg:phone":"+1 301 791 2844",
    "sg:postcode":"21713",
    "sg:province":"MD",
    "wof:name":"Greenbrier Inn",
    "wof:placetype":"venue"
},
  "geometry": {"coordinates":[-77.613162,39.551249],"type":"Point"}
}