{
  "type": "Feature",
  "properties": {
    "addr:full":"3005 Winifred Dr Burtonsville MD 20866",
    "addr:housenumber":"3005",
    "addr:postcode":"20866",
    "addr:street":"Winifred Dr",
    "iso:country":"US",
    "sg:address":"3005 Winifred Dr",
    "sg:city":"Burtonsville",
    "sg:classifiers":[
        {
            "category":"Building & Trades",
            "subcategory":"Plumbing",
            "type":"Services"
        }
    ],
    "sg:phone":"+1 301 422 8588",
    "sg:postcode":"20866",
    "sg:province":"MD",
    "sg:tags":[
        "plumbing",
        "contractor"
    ],
    "wof:name":"W H Winegar & Son Plumbing",
    "wof:placetype":"venue"
},
  "geometry": {"coordinates":[-76.94743200000001,39.11278],"type":"Point"}
}