{
  "type": "Feature",
  "properties": {
    "iso:country":"US",
    "sg:address":"13801 Coastal Hwy",
    "sg:city":"Ocean City",
    "sg:classifiers":[
        {
            "category":"Travel",
            "subcategory":"Hotels & Motels",
            "type":"Entertainment"
        }
    ],
    "sg:phone":"+1 410 250 1100",
    "sg:postcode":"21842",
    "sg:province":"MD",
    "sg:website":"www.fenwickinn.com",
    "wof:name":"Fenwick Inn",
    "wof:placetype":"venue"
},
  "geometry": {"coordinates":[-75.053062,38.444292],"type":"Point"}
}