{
  "type": "Feature",
  "properties": {
    "addr:full":"29 S Greene St Baltimore MD 21201",
    "addr:housenumber":"29",
    "addr:postcode":"21201",
    "addr:street":"S Greene St",
    "iso:country":"US",
    "sg:address":"29 S Greene St",
    "sg:city":"Baltimore",
    "sg:classifiers":[
        {
            "category":"Professional",
            "type":"Services"
        }
    ],
    "sg:phone":"+1 410 605 7193",
    "sg:postcode":"21201",
    "sg:province":"MD",
    "wof:name":"Harold C Standiford",
    "wof:placetype":"venue"
},
  "geometry": {"coordinates":[-76.62355100000001,39.287649],"type":"Point"}
}