{
  "type": "Feature",
  "properties": {
    "iso:country":"US",
    "sg:address":"201 W Padonia Rd",
    "sg:city":"Lutherville",
    "sg:classifiers":[
        {
            "category":"Professional",
            "subcategory":"Secretarial Services",
            "type":"Services"
        }
    ],
    "sg:phone":"+1 410 252 4666",
    "sg:postcode":"21093",
    "sg:province":"MD",
    "sg:tags":[
        "reporting",
        "court"
    ],
    "wof:name":"Executive Secretarial Pros",
    "wof:placetype":"venue"
},
  "geometry": {"coordinates":[-76.638196,39.455489],"type":"Point"}
}