{
  "type": "Feature",
  "properties": {
    "iso:country":"US",
    "sg:address":"3434 Wilkens Ave",
    "sg:city":"Baltimore",
    "sg:classifiers":[
        {
            "category":"Real Estate",
            "subcategory":"Real Estate Agent",
            "type":"Services"
        }
    ],
    "sg:phone":"+1 410 368 9000",
    "sg:postcode":"21229",
    "sg:province":"MD",
    "wof:name":"Amul Properties",
    "wof:placetype":"venue"
},
  "geometry": {"coordinates":[-76.674885,39.27269],"type":"Point"}
}