{
  "type": "Feature",
  "properties": {
    "addr:full":"102 Sandbar Ct La Plata MD 20646",
    "addr:housenumber":"102",
    "addr:postcode":"20646",
    "addr:street":"Sandbar Ct",
    "iso:country":"US",
    "sg:address":"102 Sandbar Ct",
    "sg:city":"La Plata",
    "sg:classifiers":[
        {
            "category":"Professional",
            "subcategory":"Business Services",
            "type":"Services"
        }
    ],
    "sg:phone":"+1 301 520 2145",
    "sg:postcode":"20646",
    "sg:province":"MD",
    "sg:tags":[
        "fine",
        "art"
    ],
    "wof:name":"Top Shelf Collectables",
    "wof:placetype":"venue"
},
  "geometry": {"coordinates":[-76.977767,38.543301],"type":"Point"}
}