{
  "type": "Feature",
  "properties": {
    "iso:country":"US",
    "sg:address":"12415 Nora Ln",
    "sg:city":"Bishopville",
    "sg:classifiers":[
        {
            "category":"Freight",
            "type":"Transportation"
        }
    ],
    "sg:phone":"+1 410 352 5981",
    "sg:postcode":"21813",
    "sg:province":"MD",
    "sg:tags":[
        "operator",
        "local",
        "trucking"
    ],
    "wof:name":"Truitt Inc",
    "wof:placetype":"venue"
},
  "geometry": {"coordinates":[-75.167282,38.421137],"type":"Point"}
}