{
  "type": "Feature",
  "properties": {
    "iso:country":"US",
    "sg:address":"7240 Woodmont Ave",
    "sg:city":"Bethesda",
    "sg:classifiers":[
        {
            "category":"Restaurant",
            "type":"Food & Drink"
        }
    ],
    "sg:phone":"+1 301 718 8680",
    "sg:postcode":"20814",
    "sg:province":"MD",
    "sg:tags":[
        "fusion",
        "asian"
    ],
    "sg:website":"www.rakuasiandining.com/",
    "wof:name":"Raku-An Asian Diner",
    "wof:placetype":"venue"
},
  "geometry": {"coordinates":[-77.09470399999999,38.9809],"type":"Point"}
}