{
  "type": "Feature",
  "properties": {
    "addr:full":"4812 Butler Rd Glyndon MD 21136",
    "addr:housenumber":"4812",
    "addr:postcode":"21136",
    "addr:street":"Butler Rd",
    "iso:country":"US",
    "sg:address":"4812 Butler Rd",
    "sg:city":"Glyndon",
    "sg:classifiers":[
        {
            "category":"Restaurant",
            "type":"Food & Drink"
        },
        {
            "category":"Government",
            "subcategory":"Fire Station",
            "type":"Public Place"
        }
    ],
    "sg:phone":"+1 410 833 1262",
    "sg:postcode":"21136",
    "sg:province":"MD",
    "sg:tags":[
        "personal",
        "protection",
        "banquet",
        "rooms"
    ],
    "wof:name":"Glyndon Fireman's Hall",
    "wof:placetype":"venue"
},
  "geometry": {"coordinates":[-76.82032100000001,39.475289],"type":"Point"}
}