{
  "type": "Feature",
  "properties": {
    "iso:country":"US",
    "sg:address":"419 Burnt Mills Ave",
    "sg:city":"Silver Spring",
    "sg:classifiers":[
        {
            "category":"Health Services",
            "subcategory":"Doctor",
            "type":"Services"
        }
    ],
    "sg:phone":"+1 301 593 4138",
    "sg:postcode":"20901",
    "sg:province":"MD",
    "sg:tags":[
        "surgeon",
        "oral"
    ],
    "wof:name":"Sullivan James R DDS",
    "wof:placetype":"venue"
},
  "geometry": {"coordinates":[-77.0009,39.036499],"type":"Point"}
}