{
  "type": "Feature",
  "properties": {
    "iso:country":"US",
    "sg:address":"105 Brookebury Dr",
    "sg:city":"Reisterstown",
    "sg:classifiers":[
        {
            "category":"Shopping",
            "type":"Retail Goods"
        }
    ],
    "sg:phone":"+1 410 532 2838",
    "sg:postcode":"21136",
    "sg:province":"MD",
    "sg:tags":[
        "religious"
    ],
    "wof:name":"Healthy Living In God's Word",
    "wof:placetype":"venue"
},
  "geometry": {"coordinates":[-76.824345,39.44537],"type":"Point"}
}