{
  "type": "Feature",
  "properties": {
    "addr:full":"2400 Boston St Baltimore MD 21224",
    "addr:housenumber":"2400",
    "addr:postcode":"21224",
    "addr:street":"Boston St",
    "iso:country":"US",
    "sg:address":"2400 Boston St",
    "sg:city":"Baltimore",
    "sg:classifiers":[
        {
            "category":"Restaurant",
            "type":"Food & Drink"
        }
    ],
    "sg:phone":"+1 410 522 7700",
    "sg:postcode":"21224",
    "sg:province":"MD",
    "wof:name":"Franco Zeppi",
    "wof:placetype":"venue"
},
  "geometry": {"coordinates":[-76.581436,39.281243],"type":"Point"}
}