{
  "type": "Feature",
  "properties": {
    "iso:country":"US",
    "sg:address":"1403 Martin Dr",
    "sg:city":"Baltimore",
    "sg:classifiers":[
        {
            "category":"Manufacturing",
            "subcategory":"Electronics",
            "type":"Manufacturing & Wholesale Goods"
        }
    ],
    "sg:phone":"+1 410 744 2050",
    "sg:postcode":"21229",
    "sg:province":"MD",
    "sg:tags":[
        "entertainers-family",
        "component",
        "business",
        "electronic",
        "mfg"
    ],
    "wof:name":"P H Productions Inc",
    "wof:placetype":"venue"
},
  "geometry": {"coordinates":[-76.71272,39.298113],"type":"Point"}
}