{
  "type": "Feature",
  "properties": {
    "addr:full":"20 Addleton Ct Reisterstown MD 21136",
    "addr:housenumber":"20",
    "addr:postcode":"21136",
    "addr:street":"Addleton Ct",
    "iso:country":"US",
    "sg:address":"20 Addleton Ct",
    "sg:city":"Reisterstown",
    "sg:classifiers":[
        {
            "category":"Professional",
            "subcategory":"Management & Consulting",
            "type":"Services"
        }
    ],
    "sg:phone":"+1 410 526 0071",
    "sg:postcode":"21136",
    "sg:province":"MD",
    "wof:name":"Intelsoft Consulting Inc",
    "wof:placetype":"venue"
},
  "geometry": {"coordinates":[-76.807287,39.457169],"type":"Point"}
}