{
  "type": "Feature",
  "properties": {
    "iso:country":"US",
    "sg:address":"910 Kentmorr Rd",
    "sg:city":"Stevensville",
    "sg:classifiers":[
        {
            "category":"Recreation",
            "subcategory":"Marina",
            "type":"Entertainment"
        }
    ],
    "sg:phone":"+1 410 643 1411",
    "sg:postcode":"21666",
    "sg:province":"MD",
    "sg:tags":[
        "repairing",
        "boat"
    ],
    "wof:name":"Brickhouse Yacht Yard",
    "wof:placetype":"venue"
},
  "geometry": {"coordinates":[-76.363856,38.915961],"type":"Point"}
}