{
  "type": "Feature",
  "properties": {
    "addr:full":"1401 W Lombard St Baltimore MD 21223",
    "addr:housenumber":"1401",
    "addr:postcode":"21223",
    "addr:street":"W Lombard St",
    "iso:country":"US",
    "sg:address":"1401 W Lombard St",
    "sg:city":"Baltimore",
    "sg:classifiers":[
        {
            "category":"Organizations",
            "subcategory":"Religious Organization",
            "type":"Services"
        }
    ],
    "sg:phone":"+1 410 233 7270",
    "sg:postcode":"21223",
    "sg:province":"MD",
    "wof:name":"Full Gospel True Mission",
    "wof:placetype":"venue"
},
  "geometry": {"coordinates":[-76.64015999999999,39.286457],"type":"Point"}
}