{
  "type": "Feature",
  "properties": {
    "addr:full":"309 Carroll Ave Laurel MD 20707",
    "addr:housenumber":"309",
    "addr:postcode":"20707",
    "addr:street":"Carroll Ave",
    "iso:country":"US",
    "sg:address":"309 Carroll Ave",
    "sg:city":"Laurel",
    "sg:classifiers":[
        {
            "category":"Real Estate",
            "subcategory":"Real Estate Services",
            "type":"Services"
        }
    ],
    "sg:phone":"+1 410 880 6777",
    "sg:postcode":"20707",
    "sg:province":"MD",
    "wof:name":"Save 6 Inc",
    "wof:placetype":"venue"
},
  "geometry": {"coordinates":[-76.848263,39.100909],"type":"Point"}
}