{
  "type": "Feature",
  "properties": {
    "addr:full":"8058 Philadelphia Rd Rosedale MD 21237",
    "addr:housenumber":"8058",
    "addr:postcode":"21237",
    "addr:street":"Philadelphia Rd",
    "iso:country":"US",
    "sg:address":"8058 Philadelphia Rd",
    "sg:city":"Rosedale",
    "sg:classifiers":[
        {
            "category":"Shopping",
            "subcategory":"Bicycles & Sporting Goods",
            "type":"Retail Goods"
        }
    ],
    "sg:phone":"+1 410 866 4787",
    "sg:postcode":"21237",
    "sg:province":"MD",
    "wof:name":"Golden Ring Bicycle Shop",
    "wof:placetype":"venue"
},
  "geometry": {"coordinates":[-76.510481,39.323578],"type":"Point"}
}