{
  "type": "Feature",
  "properties": {
    "iso:country":"US",
    "sg:address":"240 Business Center Dr",
    "sg:city":"Reisterstown",
    "sg:classifiers":[
        {
            "category":"Communications",
            "subcategory":"Film & Video Production",
            "type":"Services"
        }
    ],
    "sg:phone":"+1 410 526 9100",
    "sg:postcode":"21136",
    "sg:province":"MD",
    "sg:tags":[
        "motion",
        "picture",
        "services-commercial"
    ],
    "sg:website":"http://www.vpcinc.net",
    "wof:name":"Video Production Consulting",
    "wof:placetype":"venue"
},
  "geometry": {"coordinates":[-76.82787,39.465952],"type":"Point"}
}