{
  "type": "Feature",
  "properties": {
    "addr:full":"6111 Meadow Ave Baltimore MD 21207",
    "addr:housenumber":"6111",
    "addr:postcode":"21207",
    "addr:street":"Meadow Ave",
    "iso:country":"US",
    "sg:address":"6111 Meadow Ave",
    "sg:city":"Baltimore",
    "sg:classifiers":[
        {
            "category":"Professional",
            "subcategory":"Business Services",
            "type":"Services"
        }
    ],
    "sg:phone":"+1 410 298 3967",
    "sg:postcode":"21207",
    "sg:province":"MD",
    "wof:name":"Kulmi Inc",
    "wof:placetype":"venue"
},
  "geometry": {"coordinates":[-76.726445,39.313607],"type":"Point"}
}