{
  "type": "Feature",
  "properties": {
    "iso:country":"US",
    "sg:address":"2417 Houcks Mill Rd",
    "sg:city":"Monkton",
    "sg:classifiers":[
        {
            "category":"Railroad",
            "type":"Transportation"
        }
    ],
    "sg:phone":"+1 410 557 7274",
    "sg:postcode":"21111",
    "sg:province":"MD",
    "sg:tags":[
        "operator",
        "line"
    ],
    "wof:name":"RR Engineering Inc",
    "wof:placetype":"venue"
},
  "geometry": {"coordinates":[-76.512792,39.59369],"type":"Point"}
}