{
  "type": "Feature",
  "properties": {
    "addr:full":"9100 Coastal Hwy Ocean City MD 21842",
    "addr:housenumber":"9100",
    "addr:postcode":"21842",
    "addr:street":"Coastal Hwy",
    "iso:country":"US",
    "sg:address":"9100 Coastal Hwy",
    "sg:city":"Ocean City",
    "sg:classifiers":[
        {
            "category":"Shopping",
            "subcategory":"Jewelry",
            "type":"Retail Goods"
        }
    ],
    "sg:phone":"+1 410 524 0848",
    "sg:postcode":"21842",
    "sg:province":"MD",
    "sg:tags":[
        "jeweler"
    ],
    "wof:name":"Somerset At The Princess",
    "wof:placetype":"venue"
},
  "geometry": {"coordinates":[-75.05882099999999,38.408032],"type":"Point"}
}