{
  "type": "Feature",
  "properties": {
    "addr:full":"12409 Hanford Ct Monrovia MD 21770",
    "addr:housenumber":"12409",
    "addr:postcode":"21770",
    "addr:street":"Hanford Ct",
    "iso:country":"US",
    "sg:address":"12409 Hanford Ct",
    "sg:city":"Monrovia",
    "sg:classifiers":[
        {
            "category":"Professional",
            "subcategory":"Business Services",
            "type":"Services"
        }
    ],
    "sg:phone":"+1 301 253 1138",
    "sg:postcode":"21770",
    "sg:province":"MD",
    "sg:tags":[
        "consulting",
        "multimedia"
    ],
    "wof:name":"Public Media LLC",
    "wof:placetype":"venue"
},
  "geometry": {"coordinates":[-77.232732,39.327274],"type":"Point"}
}