{
  "type": "Feature",
  "properties": {
    "iso:country":"US",
    "sg:address":"3 Woodthorne Ct",
    "sg:city":"Owings Mills",
    "sg:classifiers":[
        {
            "category":"Real Estate",
            "subcategory":"Real Estate Operator",
            "type":"Services"
        }
    ],
    "sg:phone":"+1 410 363 6072",
    "sg:postcode":"21117",
    "sg:province":"MD",
    "sg:tags":[
        "apartment"
    ],
    "wof:name":"Milltown Village Apts",
    "wof:placetype":"venue"
},
  "geometry": {"coordinates":[-76.76902200000001,39.413298],"type":"Point"}
}