{
  "type": "Feature",
  "properties": {
    "iso:country":"US",
    "sg:address":"1547 Abbotston St",
    "sg:city":"Baltimore",
    "sg:classifiers":[
        {
            "category":"Manufacturing",
            "subcategory":"Petroleum Products",
            "type":"Manufacturing & Wholesale Goods"
        }
    ],
    "sg:phone":"+1 410 537 0193",
    "sg:postcode":"21218",
    "sg:province":"MD",
    "sg:tags":[
        "candles-wholesale",
        "manufacturer"
    ],
    "wof:name":"Great Scents/Gourmet Candles",
    "wof:placetype":"venue"
},
  "geometry": {"coordinates":[-76.595409,39.323464],"type":"Point"}
}