{
  "type": "Feature",
  "properties": {
    "iso:country":"US",
    "sg:address":"170 Jennifer Rd",
    "sg:city":"Annapolis",
    "sg:classifiers":[
        {
            "category":"Insurance",
            "subcategory":"Insurance Agent",
            "type":"Services"
        },
        {
            "category":"Insurance",
            "subcategory":"Hazard Insurance",
            "type":"Services"
        },
        {
            "category":"Insurance",
            "subcategory":"Title Insurance",
            "type":"Services"
        },
        {
            "category":"Insurance",
            "subcategory":"Life Insurance",
            "type":"Services"
        }
    ],
    "sg:phone":"+1 410 841 6311",
    "sg:postcode":"21401",
    "sg:province":"MD",
    "sg:tags":[
        "business",
        "auto",
        "commercial",
        "homeowner",
        "motorcycle",
        "renter"
    ],
    "wof:name":"Allstate Insurance Company - Wilton Colbert",
    "wof:placetype":"venue"
},
  "geometry": {"coordinates":[-76.541748,38.98798],"type":"Point"}
}