{
  "type": "Feature",
  "properties": {
    "iso:country":"US",
    "sg:address":"13925 New Hampshire Ave",
    "sg:city":"Colesville",
    "sg:classifiers":[
        {
            "category":"Organizations",
            "subcategory":"Religious Organization",
            "type":"Services"
        }
    ],
    "sg:phone":"+1 301 384 6264",
    "sg:postcode":"20904",
    "sg:province":"MD",
    "sg:tags":[
        "church"
    ],
    "sg:website":"www.transfig.org",
    "wof:name":"Transfiguration Episcopal Chr",
    "wof:placetype":"venue"
},
  "geometry": {"coordinates":[-76.999882,39.084455],"type":"Point"}
}