{
  "type": "Feature",
  "properties": {
    "addr:full":"12 W Ellendale St Bel Air MD 21014",
    "addr:housenumber":"12",
    "addr:postcode":"21014",
    "addr:street":"W Ellendale St",
    "iso:country":"US",
    "sg:address":"12 W Ellendale St",
    "sg:city":"Bel Air",
    "sg:classifiers":[
        {
            "category":"Building & Trades",
            "subcategory":"Equipment Rental",
            "type":"Services"
        }
    ],
    "sg:phone":"+1 410 879 9127",
    "sg:postcode":"21014",
    "sg:province":"MD",
    "sg:tags":[
        "yard"
    ],
    "wof:name":"Bay Country Rentals",
    "wof:placetype":"venue"
},
  "geometry": {"coordinates":[-76.357336,39.539115],"type":"Point"}
}