{
  "type": "Feature",
  "properties": {
    "iso:country":"US",
    "sg:address":"2633 Cory Ter",
    "sg:city":"Silver Spring",
    "sg:classifiers":[
        {
            "category":"Building & Trades",
            "subcategory":"Construction",
            "type":"Services"
        }
    ],
    "sg:phone":"+1 301 946 0333",
    "sg:postcode":"20902",
    "sg:province":"MD",
    "sg:tags":[
        "hanging",
        "contractor"
    ],
    "wof:name":"Estrella Painting",
    "wof:placetype":"venue"
},
  "geometry": {"coordinates":[-77.054896,39.052532],"type":"Point"}
}