{
  "type": "Feature",
  "properties": {
    "iso:country":"US",
    "sg:address":"528 Orchard St",
    "sg:city":"Baltimore",
    "sg:classifiers":[
        {
            "category":"Professional",
            "subcategory":"Accounting & Tax Preparation",
            "type":"Services"
        }
    ],
    "sg:phone":"+1 443 919 0308",
    "sg:postcode":"21201",
    "sg:province":"MD",
    "sg:tags":[
        "return",
        "filing"
    ],
    "wof:name":"Elite Tax",
    "wof:placetype":"venue"
},
  "geometry": {"coordinates":[-76.624455,39.297194],"type":"Point"}
}