{
  "type": "Feature",
  "properties": {
    "iso:country":"US",
    "sg:address":"2805 Shepperd Rd",
    "sg:city":"Monkton",
    "sg:classifiers":[
        {
            "category":"Farming",
            "subcategory":"Farm",
            "type":"Manufacturing & Wholesale Goods"
        }
    ],
    "sg:phone":"+1 410 472 9037",
    "sg:postcode":"21111",
    "sg:province":"MD",
    "sg:tags":[
        "crop",
        "general"
    ],
    "wof:name":"Bellefield Farm",
    "wof:placetype":"venue"
},
  "geometry": {"coordinates":[-76.58278199999999,39.584339],"type":"Point"}
}