{
  "type": "Feature",
  "properties": {
    "iso:country":"US",
    "sg:address":"7324 Westmore Rd",
    "sg:city":"Rockville",
    "sg:classifiers":[
        {
            "category":"Retail",
            "subcategory":"Auto Repair",
            "type":"Services"
        }
    ],
    "sg:phone":"+1 301 424 3886",
    "sg:postcode":"20850",
    "sg:province":"MD",
    "sg:tags":[
        "body",
        "automobile",
        "painting"
    ],
    "wof:name":"Rockville Central Auto Body",
    "wof:placetype":"venue"
},
  "geometry": {"coordinates":[-77.147722,39.099824],"type":"Point"}
}