{
  "type": "Feature",
  "properties": {
    "addr:full":"3026 Whiteford Rd Pylesville MD 21132",
    "addr:housenumber":"3026",
    "addr:postcode":"21132",
    "addr:street":"Whiteford Rd",
    "iso:country":"US",
    "sg:address":"3026 Whiteford Rd",
    "sg:city":"Pylesville",
    "sg:classifiers":[
        {
            "category":"Manufacturing",
            "subcategory":"Food",
            "type":"Manufacturing & Wholesale Goods"
        }
    ],
    "sg:phone":"+1 410 879 4007",
    "sg:postcode":"21132",
    "sg:province":"MD",
    "sg:tags":[
        "winery"
    ],
    "sg:website":"www.fiorewinery.com",
    "wof:name":"Fiore Winery",
    "wof:placetype":"venue"
},
  "geometry": {"coordinates":[-76.400395,39.712825],"type":"Point"}
}