{
  "type": "Feature",
  "properties": {
    "addr:full":"8218 Lookout Ln Frederick MD 21702",
    "addr:housenumber":"8218",
    "addr:postcode":"21702",
    "addr:street":"Lookout Ln",
    "iso:country":"US",
    "sg:address":"8218 Lookout Ln",
    "sg:city":"Frederick",
    "sg:classifiers":[
        {
            "category":"Professional",
            "subcategory":"Management & Consulting",
            "type":"Services"
        }
    ],
    "sg:phone":"+1 301 694 0397",
    "sg:postcode":"21702",
    "sg:province":"MD",
    "sg:tags":[
        "work",
        "administrative"
    ],
    "wof:name":"Judith Eyler",
    "wof:placetype":"venue"
},
  "geometry": {"coordinates":[-77.415648,39.458671],"type":"Point"}
}