{
  "type": "Feature",
  "properties": {
    "addr:full":"308 Legion Ave Annapolis MD 21401",
    "addr:housenumber":"308",
    "addr:postcode":"21401",
    "addr:street":"Legion Ave",
    "iso:country":"US",
    "sg:address":"308 Legion Ave",
    "sg:city":"Annapolis",
    "sg:classifiers":[
        {
            "category":"Home & Garden",
            "subcategory":"Building Materials",
            "type":"Retail Goods"
        }
    ],
    "sg:phone":"+1 410 268 9444",
    "sg:postcode":"21401",
    "sg:province":"MD",
    "sg:tags":[
        "glass",
        "window",
        "glazier",
        "plate"
    ],
    "sg:website":"http://www.americanglasscoinc.com",
    "wof:name":"American Glass Inc",
    "wof:placetype":"venue"
},
  "geometry": {"coordinates":[-76.52042400000001,38.976175],"type":"Point"}
}