{
  "type": "Feature",
  "properties": {
    "iso:country":"US",
    "sg:address":"901 Greenmount Ave",
    "sg:city":"Baltimore",
    "sg:classifiers":[
        {
            "category":"Professional",
            "type":"Services"
        }
    ],
    "sg:phone":"+1 410 685 6291",
    "sg:postcode":"21202",
    "sg:province":"MD",
    "sg:tags":[
        "establishment"
    ],
    "wof:name":"Telematic Corp",
    "wof:placetype":"venue"
},
  "geometry": {"coordinates":[-76.606874,39.300179],"type":"Point"}
}