{
  "type": "Feature",
  "properties": {
    "addr:full":"Shawan Plaza 11341 York Rd Cockeysville MD 21030",
    "addr:housenumber":"11341",
    "addr:postcode":"21030",
    "addr:street":"Shawan Plaza;York Rd",
    "iso:country":"US",
    "sg:address":"Shawan Plaza 11341 York Rd",
    "sg:city":"Cockeysville",
    "sg:classifiers":[
        {
            "category":"Personal",
            "subcategory":"Beauty Salon",
            "type":"Services"
        }
    ],
    "sg:phone":"+1 410 527 4630",
    "sg:postcode":"21030",
    "sg:province":"MD",
    "sg:tags":[
        "spa"
    ],
    "sg:website":"beebeautifulgreensalon.com",
    "wof:name":"Bee Beautiful",
    "wof:placetype":"venue"
},
  "geometry": {"coordinates":[-76.650043,39.495114],"type":"Point"}
}