{
  "type": "Feature",
  "properties": {
    "addr:full":"227 Market St Denton MD 21629",
    "addr:housenumber":"227",
    "addr:postcode":"21629",
    "addr:street":"Market St",
    "iso:country":"US",
    "sg:address":"227 Market St",
    "sg:city":"Denton",
    "sg:classifiers":[
        {
            "category":"Shopping",
            "subcategory":"Used Merchandise",
            "type":"Retail Goods"
        }
    ],
    "sg:phone":"+1 410 479 5115",
    "sg:postcode":"21629",
    "sg:province":"MD",
    "sg:tags":[
        "shop",
        "consignment"
    ],
    "wof:name":"Encore LLC",
    "wof:placetype":"venue"
},
  "geometry": {"coordinates":[-75.832318,38.886339],"type":"Point"}
}