{
  "type": "Feature",
  "properties": {
    "addr:full":"69 Baltimore St Cumberland MD 21502",
    "addr:housenumber":"69",
    "addr:postcode":"21502",
    "addr:street":"Baltimore St",
    "iso:country":"US",
    "sg:address":"69 Baltimore St",
    "sg:city":"Cumberland",
    "sg:classifiers":[
        {
            "category":"Travel",
            "subcategory":"Travel Agent",
            "type":"Entertainment"
        }
    ],
    "sg:phone":"+1 301 722 7821",
    "sg:postcode":"21502",
    "sg:province":"MD",
    "sg:tags":[
        "agency",
        "bureau"
    ],
    "wof:name":"Gateway Travel",
    "wof:placetype":"venue"
},
  "geometry": {"coordinates":[-78.763077,39.651173],"type":"Point"}
}