{
  "type": "Feature",
  "properties": {
    "addr:full":"102 Bobbitt Ct Stevensville MD 21666",
    "addr:housenumber":"102",
    "addr:postcode":"21666",
    "addr:street":"Bobbitt Ct",
    "iso:country":"US",
    "sg:address":"102 Bobbitt Ct",
    "sg:city":"Stevensville",
    "sg:classifiers":[
        {
            "category":"Professional",
            "type":"Services"
        }
    ],
    "sg:phone":"+1 410 604 3960",
    "sg:postcode":"21666",
    "sg:province":"MD",
    "wof:name":"Mark Hilditch",
    "wof:placetype":"venue"
},
  "geometry": {"coordinates":[-76.313864,38.984464],"type":"Point"}
}