{
  "type": "Feature",
  "properties": {
    "addr:full":"7809 Wise Ave Baltimore MD 21222",
    "addr:housenumber":"7809",
    "addr:postcode":"21222",
    "addr:street":"Wise Ave",
    "iso:country":"US",
    "sg:address":"7809 Wise Ave",
    "sg:city":"Baltimore",
    "sg:classifiers":[
        {
            "category":"Health Services",
            "subcategory":"Podiatrist",
            "type":"Services"
        }
    ],
    "sg:phone":"+1 410 285 0310",
    "sg:postcode":"21222",
    "sg:province":"MD",
    "wof:name":"David B Samuels DPM",
    "wof:placetype":"venue"
},
  "geometry": {"coordinates":[-76.498544,39.267997],"type":"Point"}
}