{
  "type": "Feature",
  "properties": {
    "addr:full":"8004 Craddock Rd Greenbelt MD 20770",
    "addr:housenumber":"8004",
    "addr:postcode":"20770",
    "addr:street":"Craddock Rd",
    "iso:country":"US",
    "sg:address":"8004 Craddock Rd",
    "sg:city":"Greenbelt",
    "sg:classifiers":[
        {
            "category":"Real Estate",
            "subcategory":"Real Estate Agent",
            "type":"Services"
        }
    ],
    "sg:phone":"+1 301 552 5511",
    "sg:postcode":"20770",
    "sg:province":"MD",
    "sg:tags":[
        "inspection"
    ],
    "wof:name":"Homebiz Inspection Team",
    "wof:placetype":"venue"
},
  "geometry": {"coordinates":[-76.87039300000001,38.98538],"type":"Point"}
}