{
  "type": "Feature",
  "properties": {
    "addr:full":"13200 New Hampshire Ave Silver Spring MD 20904",
    "addr:housenumber":"13200",
    "addr:postcode":"20904",
    "addr:street":"New Hampshire Ave",
    "iso:country":"US",
    "sg:address":"13200 New Hampshire Ave",
    "sg:city":"Silver Spring",
    "sg:classifiers":[
        {
            "category":"Personal",
            "subcategory":"Beauty Salon",
            "type":"Services"
        }
    ],
    "sg:phone":"+1 301 384 0115",
    "sg:postcode":"20904",
    "sg:province":"MD",
    "sg:tags":[
        "hair"
    ],
    "wof:name":"Lena's Hair Salon",
    "wof:placetype":"venue"
},
  "geometry": {"coordinates":[-77.003435,39.071829],"type":"Point"}
}