{
  "type": "Feature",
  "properties": {
    "iso:country":"US",
    "sg:address":"159 Main St",
    "sg:city":"Annapolis",
    "sg:classifiers":[
        {
            "category":"Professional",
            "subcategory":"Engineering",
            "type":"Services"
        }
    ],
    "sg:phone":"+1 410 267 0744",
    "sg:postcode":"21401",
    "sg:province":"MD",
    "sg:tags":[
        "engineer"
    ],
    "sg:website":"www.cdmeekins.com",
    "wof:name":"C D Meekins & Assoc Inc",
    "wof:placetype":"venue"
},
  "geometry": {"coordinates":[-76.489669,38.977658],"type":"Point"}
}