{
  "type": "Feature",
  "properties": {
    "addr:full":"6926 Holabird Ave Dundalk MD 21222",
    "addr:housenumber":"6926",
    "addr:postcode":"21222",
    "addr:street":"Holabird Ave",
    "iso:country":"US",
    "sg:address":"6926 Holabird Ave",
    "sg:city":"Dundalk",
    "sg:classifiers":[
        {
            "category":"Bars & Pubs",
            "subcategory":"Nightclub",
            "type":"Food & Drink"
        }
    ],
    "sg:phone":"+1 410 282 5387",
    "sg:postcode":"21222",
    "sg:province":"MD",
    "sg:tags":[
        "nightlife"
    ],
    "wof:name":"Dizzy Pleasure Club",
    "wof:placetype":"venue"
},
  "geometry": {"coordinates":[-76.525497,39.272499],"type":"Point"}
}