{
  "type": "Feature",
  "properties": {
    "addr:full":"14234 Bear Creek Dr Boyds MD 20841",
    "addr:housenumber":"14234",
    "addr:postcode":"20841",
    "addr:street":"Bear Creek Dr",
    "iso:country":"US",
    "sg:address":"14234 Bear Creek Dr",
    "sg:city":"Boyds",
    "sg:classifiers":[
        {
            "category":"Home & Garden",
            "subcategory":"Carpets & Floor Coverings",
            "type":"Retail Goods"
        }
    ],
    "sg:phone":"+1 301 972 9174",
    "sg:postcode":"20841",
    "sg:province":"MD",
    "sg:tags":[
        "material"
    ],
    "wof:name":"Yoon's Flooring Co",
    "wof:placetype":"venue"
},
  "geometry": {"coordinates":[-77.294071,39.162274],"type":"Point"}
}