{
  "type": "Feature",
  "properties": {
    "addr:full":"4930 Del Ray Ave Bethesda MD 20814",
    "addr:housenumber":"4930",
    "addr:postcode":"20814",
    "addr:street":"Del Ray Ave",
    "iso:country":"US",
    "sg:address":"4930 Del Ray Ave",
    "sg:city":"Bethesda",
    "sg:classifiers":[
        {
            "category":"Health Services",
            "subcategory":"Doctor",
            "type":"Services"
        }
    ],
    "sg:phone":"+1 301 571 5190",
    "sg:postcode":"20814",
    "sg:province":"MD",
    "wof:name":"Karson Evelyn M PHD MD Chartered",
    "wof:placetype":"venue"
},
  "geometry": {"coordinates":[-77.10019699999999,38.988701],"type":"Point"}
}