{
  "type": "Feature",
  "properties": {
    "addr:full":"806 Baltimore Pike Bel Air MD 21014",
    "addr:housenumber":"806",
    "addr:postcode":"21014",
    "addr:street":"Baltimore Pike",
    "iso:country":"US",
    "sg:address":"806 Baltimore Pike",
    "sg:city":"Bel Air",
    "sg:classifiers":[
        {
            "category":"Retail",
            "subcategory":"Auto Repair",
            "type":"Services"
        }
    ],
    "sg:phone":"+1 410 879 6007",
    "sg:postcode":"21014",
    "sg:province":"MD",
    "sg:tags":[
        "body",
        "automobile",
        "painting"
    ],
    "wof:name":"P J Body & Paint",
    "wof:placetype":"venue"
},
  "geometry": {"coordinates":[-76.361898,39.518982],"type":"Point"}
}