{
  "type": "Feature",
  "properties": {
    "iso:country":"US",
    "sg:address":"11 Edgemoor Rd",
    "sg:city":"Lutherville Timonium",
    "sg:classifiers":[
        {
            "category":"Manufacturing",
            "subcategory":"Printing",
            "type":"Manufacturing & Wholesale Goods"
        }
    ],
    "sg:phone":"+1 410 252 2509",
    "sg:postcode":"21093",
    "sg:province":"MD",
    "sg:tags":[
        "publishing"
    ],
    "wof:name":"Scesney Publications Inc",
    "wof:placetype":"venue"
},
  "geometry": {"coordinates":[-76.62450200000001,39.445139],"type":"Point"}
}