{
  "type": "Feature",
  "properties": {
    "iso:country":"US",
    "sg:address":"2003 Petersfield Pl",
    "sg:city":"Olney",
    "sg:classifiers":[
        {
            "category":"Professional",
            "subcategory":"Business Services",
            "type":"Services"
        }
    ],
    "sg:phone":"+1 301 774 3018",
    "sg:postcode":"20832",
    "sg:province":"MD",
    "sg:tags":[
        "independent",
        "company",
        "meeting"
    ],
    "wof:name":"J R P Inc",
    "wof:placetype":"venue"
},
  "geometry": {"coordinates":[-77.049159,39.149882],"type":"Point"}
}