{
  "type": "Feature",
  "properties": {
    "addr:full":"1306 E West Hwy Silver Spring MD 20910",
    "addr:housenumber":"1306 e",
    "addr:postcode":"20910",
    "addr:street":"West Hwy",
    "iso:country":"US",
    "sg:address":"1306 E West Hwy",
    "sg:city":"Silver Spring",
    "sg:classifiers":[
        {
            "category":"Personal",
            "subcategory":"Barber",
            "type":"Services"
        }
    ],
    "sg:phone":"+1 301 585 3344",
    "sg:postcode":"20910",
    "sg:province":"MD",
    "wof:name":"Brians Barber Shop",
    "wof:placetype":"venue"
},
  "geometry": {"coordinates":[-77.030978,38.991778],"type":"Point"}
}