{
  "type": "Feature",
  "properties": {
    "addr:full":"5304 Edmondson Ave Baltimore MD 21229",
    "addr:housenumber":"5304",
    "addr:postcode":"21229",
    "addr:street":"Edmondson Ave",
    "iso:country":"US",
    "sg:address":"5304 Edmondson Ave",
    "sg:city":"Baltimore",
    "sg:classifiers":[
        {
            "category":"Personal",
            "subcategory":"Barber",
            "type":"Services"
        }
    ],
    "sg:phone":"+1 410 744 6549",
    "sg:postcode":"21229",
    "sg:province":"MD",
    "wof:name":"Clipper Place the",
    "wof:placetype":"venue"
},
  "geometry": {"coordinates":[-76.711304,39.287399],"type":"Point"}
}