{
  "type": "Feature",
  "properties": {
    "addr:full":"2885 Prism Ct Lusby MD 20657",
    "addr:housenumber":"2885",
    "addr:postcode":"20657",
    "addr:street":"Prism Ct",
    "iso:country":"US",
    "sg:address":"2885 Prism Ct",
    "sg:city":"Lusby",
    "sg:classifiers":[
        {
            "category":"Building & Trades",
            "subcategory":"Construction",
            "type":"Services"
        }
    ],
    "sg:phone":"+1 410 326 2674",
    "sg:postcode":"20657",
    "sg:province":"MD",
    "sg:tags":[
        "home",
        "improvement"
    ],
    "wof:name":"Golden West Way Construction",
    "wof:placetype":"venue"
},
  "geometry": {"coordinates":[-76.39358900000001,38.376039],"type":"Point"}
}