{
  "type": "Feature",
  "properties": {
    "iso:country":"US",
    "sg:address":"13110 Coastal Hwy",
    "sg:city":"Ocean City",
    "sg:classifiers":[
        {
            "category":"Real Estate",
            "subcategory":"Real Estate Operator",
            "type":"Services"
        }
    ],
    "sg:phone":"+1 410 250 3180",
    "sg:postcode":"21842",
    "sg:province":"MD",
    "sg:tags":[
        "condominium"
    ],
    "wof:name":"Braemar Towers Condominium",
    "wof:placetype":"venue"
},
  "geometry": {"coordinates":[-75.053878,38.437422],"type":"Point"}
}