{
  "type": "Feature",
  "properties": {
    "addr:full":"7722 Old Branch Ave Clinton MD 20735",
    "addr:housenumber":"7722",
    "addr:postcode":"20735",
    "addr:street":"Old Branch Ave",
    "iso:country":"US",
    "sg:address":"7722 Old Branch Ave",
    "sg:city":"Clinton",
    "sg:classifiers":[
        {
            "category":"Banks & Credit Unions",
            "subcategory":"Bank",
            "type":"Services"
        }
    ],
    "sg:phone":"+1 301 877 1022",
    "sg:postcode":"20735",
    "sg:province":"MD",
    "sg:tags":[
        "cashing",
        "check"
    ],
    "wof:name":"KASH King",
    "wof:placetype":"venue"
},
  "geometry": {"coordinates":[-76.89804700000001,38.784228],"type":"Point"}
}