{
  "type": "Feature",
  "properties": {
    "addr:full":"4413 Reamy Dr Suitland MD 20746",
    "addr:housenumber":"4413",
    "addr:postcode":"20746",
    "addr:street":"Reamy Dr",
    "iso:country":"US",
    "sg:address":"4413 Reamy Dr",
    "sg:city":"Suitland",
    "sg:classifiers":[
        {
            "category":"Place Of Worship",
            "type":"Public Place"
        }
    ],
    "sg:phone":"+1 301 735 3601",
    "sg:postcode":"20746",
    "sg:province":"MD",
    "sg:tags":[
        "church"
    ],
    "wof:name":"Sharon Bible Fellowship Church",
    "wof:placetype":"venue"
},
  "geometry": {"coordinates":[-76.897701,38.830619],"type":"Point"}
}