{
  "type": "Feature",
  "properties": {
    "addr:full":"29509 Canvasback Dr Easton MD 21601",
    "addr:housenumber":"29509",
    "addr:postcode":"21601",
    "addr:street":"Canvasback Dr",
    "iso:country":"US",
    "sg:address":"29509 Canvasback Dr",
    "sg:city":"Easton",
    "sg:classifiers":[
        {
            "category":"Building & Trades",
            "subcategory":"Construction",
            "type":"Services"
        }
    ],
    "sg:phone":"+1 410 763 9681",
    "sg:postcode":"21601",
    "sg:province":"MD",
    "sg:tags":[
        "home",
        "builder"
    ],
    "wof:name":"Rbci",
    "wof:placetype":"venue"
},
  "geometry": {"coordinates":[-76.05347999999999,38.773492],"type":"Point"}
}