{
  "type": "Feature",
  "properties": {
    "iso:country":"US",
    "sg:address":"50 Cessna Ct",
    "sg:city":"Gaithersburg",
    "sg:classifiers":[
        {
            "category":"Wholesale",
            "subcategory":"Hardware",
            "type":"Manufacturing & Wholesale Goods"
        }
    ],
    "sg:phone":"+1 301 330 5963",
    "sg:postcode":"20879",
    "sg:province":"MD",
    "sg:tags":[
        "tool"
    ],
    "wof:name":"Snap-On Tools Co",
    "wof:placetype":"venue"
},
  "geometry": {"coordinates":[-77.161424,39.172592],"type":"Point"}
}