{
  "type": "Feature",
  "properties": {
    "addr:full":"46346 Fletcher Ct Lexington Park MD 20653",
    "addr:housenumber":"46346",
    "addr:postcode":"20653",
    "addr:street":"Fletcher Ct",
    "iso:country":"US",
    "sg:address":"46346 Fletcher Ct",
    "sg:city":"Lexington Park",
    "sg:classifiers":[
        {
            "category":"Communications",
            "subcategory":"Film & Video Production",
            "type":"Services"
        }
    ],
    "sg:phone":"+1 301 863 7788",
    "sg:postcode":"20653",
    "sg:province":"MD",
    "sg:tags":[
        "taping"
    ],
    "wof:name":"Phocus Video Communications",
    "wof:placetype":"venue"
},
  "geometry": {"coordinates":[-76.47267600000001,38.305117],"type":"Point"}
}