{
  "type": "Feature",
  "properties": {
    "iso:country":"US",
    "sg:address":"3300 N Chatham Rd",
    "sg:city":"Ellicott City",
    "sg:classifiers":[
        {
            "category":"Recreation",
            "type":"Entertainment"
        }
    ],
    "sg:phone":"+1 410 465 9803",
    "sg:postcode":"21042",
    "sg:province":"MD",
    "sg:tags":[
        "pool",
        "swimming"
    ],
    "wof:name":"Chatham Garden Apartments Pool",
    "wof:placetype":"venue"
},
  "geometry": {"coordinates":[-76.831654,39.280888],"type":"Point"}
}