{
  "type": "Feature",
  "properties": {
    "iso:country":"US",
    "sg:address":"18100 Vernon Estates Dr SE",
    "sg:city":"Oldtown",
    "sg:classifiers":[
        {
            "category":"Home & Garden",
            "subcategory":"Building Materials",
            "type":"Retail Goods"
        }
    ],
    "sg:phone":"+1 301 722 5052",
    "sg:postcode":"21555",
    "sg:province":"MD",
    "sg:tags":[
        "modular"
    ],
    "wof:name":"Modulars By Shryock",
    "wof:placetype":"venue"
},
  "geometry": {"coordinates":[-78.62900999999999,39.550191],"type":"Point"}
}