{
  "type": "Feature",
  "properties": {
    "iso:country":"US",
    "sg:address":"5649 Whitfield Chapel Rd",
    "sg:city":"Lanham",
    "sg:classifiers":[
        {
            "category":"Insurance",
            "subcategory":"Insurance Agent",
            "type":"Services"
        }
    ],
    "sg:phone":"+1 301 731 5650",
    "sg:postcode":"20706",
    "sg:province":"MD",
    "sg:website":"www.baltimorelife.com",
    "wof:name":"Baltimore Life Co",
    "wof:placetype":"venue"
},
  "geometry": {"coordinates":[-76.85739100000001,38.963106],"type":"Point"}
}