{
  "type": "Feature",
  "properties": {
    "addr:full":"6609 Oliver St Riverdale MD 20737",
    "addr:housenumber":"6609",
    "addr:postcode":"20737",
    "addr:street":"Oliver St",
    "iso:country":"US",
    "sg:address":"6609 Oliver St",
    "sg:city":"Riverdale",
    "sg:classifiers":[
        {
            "category":"Wholesale",
            "subcategory":"Books, Periodicals, & Newspapers",
            "type":"Manufacturing & Wholesale Goods"
        }
    ],
    "sg:phone":"+1 301 576 2244",
    "sg:postcode":"20737",
    "sg:province":"MD",
    "sg:tags":[
        "publisher",
        "book"
    ],
    "wof:name":"Jones-Mack Publishing",
    "wof:placetype":"venue"
},
  "geometry": {"coordinates":[-76.90242499999999,38.95738],"type":"Point"}
}