{
  "type": "Feature",
  "properties": {
    "iso:country":"US",
    "sg:address":"13415 Arada Ct",
    "sg:city":"Highland",
    "sg:classifiers":[
        {
            "category":"Building & Trades",
            "subcategory":"Construction",
            "type":"Services"
        }
    ],
    "sg:phone":"+1 301 854 1312",
    "sg:postcode":"20777",
    "sg:province":"MD",
    "sg:tags":[
        "contractor"
    ],
    "wof:name":"Xcellent Pools",
    "wof:placetype":"venue"
},
  "geometry": {"coordinates":[-76.975658,39.197383],"type":"Point"}
}