{
  "type": "Feature",
  "properties": {
    "iso:country":"US",
    "sg:address":"100 Old Largo Rd",
    "sg:city":"Upper Marlboro",
    "sg:classifiers":[
        {
            "category":"Insurance",
            "subcategory":"Insurance Agent",
            "type":"Services"
        }
    ],
    "sg:phone":"+1 301 350 4600",
    "sg:postcode":"20774",
    "sg:province":"MD",
    "wof:name":"Henry's Insurance",
    "wof:placetype":"venue"
},
  "geometry": {"coordinates":[-76.829256,38.897124],"type":"Point"}
}