{
  "type": "Feature",
  "properties": {
    "iso:country":"US",
    "sg:address":"4022 Seabird Way",
    "sg:city":"Ellicott City",
    "sg:classifiers":[
        {
            "category":"Professional",
            "subcategory":"Lawyer & Legal Services",
            "type":"Services"
        }
    ],
    "sg:phone":"+1 410 313 8692",
    "sg:postcode":"21042",
    "sg:province":"MD",
    "wof:name":"Robert B Goss Pa",
    "wof:placetype":"venue"
},
  "geometry": {"coordinates":[-76.842365,39.259838],"type":"Point"}
}