{
  "type": "Feature",
  "properties": {
    "iso:country":"US",
    "sg:address":"815 S North Point Rd",
    "sg:city":"Baltimore",
    "sg:classifiers":[
        {
            "category":"Building & Trades",
            "subcategory":"Construction",
            "type":"Services"
        }
    ],
    "sg:phone":"+1 410 483 7015",
    "sg:postcode":"21224",
    "sg:province":"MD",
    "sg:tags":[
        "contractor"
    ],
    "wof:name":"Chinquapin Contracting Inc",
    "wof:placetype":"venue"
},
  "geometry": {"coordinates":[-76.511615,39.290756],"type":"Point"}
}