{
  "type": "Feature",
  "properties": {
    "iso:country":"US",
    "sg:address":"10220 River Rd",
    "sg:city":"Potomac",
    "sg:classifiers":[
        {
            "category":"Banks & Credit Unions",
            "subcategory":"Bank",
            "type":"Services"
        }
    ],
    "sg:phone":"+1 301 983 0550",
    "sg:postcode":"20854",
    "sg:province":"MD",
    "wof:name":"Lafayette Federal Credit Union",
    "wof:placetype":"venue"
},
  "geometry": {"coordinates":[-77.211018,39.019232],"type":"Point"}
}