{
  "type": "Feature",
  "properties": {
    "iso:country":"US",
    "sg:address":"14505 Industry Dr",
    "sg:city":"Hagerstown",
    "sg:classifiers":[
        {
            "category":"Building & Trades",
            "subcategory":"Landscaping Services",
            "type":"Services"
        },
        {
            "category":"Building & Trades",
            "subcategory":"Pest Control",
            "type":"Services"
        }
    ],
    "sg:phone":"+1 301 797 2322",
    "sg:postcode":"21742",
    "sg:province":"MD",
    "sg:tags":[
        "lawn",
        "landscape",
        "maintenance",
        "contractor"
    ],
    "sg:website":"http://iyp.scottslawnservice.com",
    "wof:name":"Scotts LawnService",
    "wof:placetype":"venue"
},
  "geometry": {"coordinates":[-77.72162,39.712547],"type":"Point"}
}