{
  "type": "Feature",
  "properties": {
    "iso:country":"US",
    "sg:address":"6700 Rockledge Dr",
    "sg:city":"Bethesda",
    "sg:classifiers":[
        {
            "category":"Insurance",
            "subcategory":"Hazard Insurance",
            "type":"Services"
        }
    ],
    "sg:phone":"+1 301 530 5050",
    "sg:postcode":"20817",
    "sg:province":"MD",
    "sg:tags":[
        "fidelity",
        "bond"
    ],
    "sg:website":"www.willis.com",
    "wof:name":"Willis Of Maryland Inc",
    "wof:placetype":"venue"
},
  "geometry": {"coordinates":[-77.132259,39.028661],"type":"Point"}
}