{
  "type": "Feature",
  "properties": {
    "addr:full":"2686 W Patapsco Ave Baltimore MD 21230",
    "addr:housenumber":"2686",
    "addr:postcode":"21230",
    "addr:street":"W Patapsco Ave",
    "iso:country":"US",
    "sg:address":"2686 W Patapsco Ave",
    "sg:city":"Baltimore",
    "sg:classifiers":[
        {
            "category":"Professional",
            "type":"Services"
        }
    ],
    "sg:phone":"+1 410 252 1606",
    "sg:postcode":"21230",
    "sg:province":"MD",
    "sg:tags":[
        "establishment"
    ],
    "wof:name":"Mid-Atlantic Fountain Design",
    "wof:placetype":"venue"
},
  "geometry": {"coordinates":[-76.654332,39.253805],"type":"Point"}
}