{
  "type": "Feature",
  "properties": {
    "iso:country":"US",
    "sg:address":"8808 Centre Park Dr Ste 300",
    "sg:city":"Columbia",
    "sg:classifiers":[
        {
            "category":"Shopping",
            "subcategory":"Computers & Home Electronics",
            "type":"Retail Goods"
        }
    ],
    "sg:phone":"+1 410 772 1900",
    "sg:postcode":"21045",
    "sg:province":"MD",
    "wof:name":"Blockbuster North East Zone Development",
    "wof:placetype":"venue"
},
  "geometry": {"coordinates":[-76.816399,39.226601],"type":"Point"}
}