{
  "type": "Feature",
  "properties": {
    "iso:country":"US",
    "sg:address":"6333 Executive Blvd",
    "sg:city":"Rockville",
    "sg:classifiers":[
        {
            "category":"Professional",
            "subcategory":"Engineering",
            "type":"Services"
        }
    ],
    "sg:phone":"+1 301 231 5151",
    "sg:postcode":"20852",
    "sg:province":"MD",
    "sg:tags":[
        "engineer"
    ],
    "sg:website":"www.gpinet.com",
    "wof:name":"GREENMAN-Pedersen Inc",
    "wof:placetype":"venue"
},
  "geometry": {"coordinates":[-77.125567,39.048877],"type":"Point"}
}