{
  "type": "Feature",
  "properties": {
    "addr:full":"4259 Necker Ave Nottingham MD 21236",
    "addr:housenumber":"4259",
    "addr:postcode":"21236",
    "addr:street":"Necker Ave",
    "iso:country":"US",
    "sg:address":"4259 Necker Ave",
    "sg:city":"Nottingham",
    "sg:classifiers":[
        {
            "category":"Health Services",
            "subcategory":"Nursing And Care Facility",
            "type":"Services"
        }
    ],
    "sg:phone":"+1 410 256 2197",
    "sg:postcode":"21236",
    "sg:province":"MD",
    "sg:tags":[
        "hospice"
    ],
    "wof:name":"Seasons Hospice & Palliative",
    "wof:placetype":"venue"
},
  "geometry": {"coordinates":[-76.488326,39.385145],"type":"Point"}
}