{
  "type": "Feature",
  "properties": {
    "addr:full":"9402 Marlboro Pike Upper Marlboro MD 20772",
    "addr:housenumber":"9402",
    "addr:postcode":"20772",
    "addr:street":"Marlboro Pike",
    "iso:country":"US",
    "sg:address":"9402 Marlboro Pike",
    "sg:city":"Upper Marlboro",
    "sg:classifiers":[
        {
            "category":"Personal",
            "type":"Services"
        }
    ],
    "sg:phone":"+1 301 599 7600",
    "sg:postcode":"20772",
    "sg:province":"MD",
    "sg:tags":[
        "wedding",
        "chapel"
    ],
    "wof:name":"B & D Weddings",
    "wof:placetype":"venue"
},
  "geometry": {"coordinates":[-76.84365,38.817301],"type":"Point"}
}