{
  "type": "Feature",
  "properties": {
    "addr:full":"4545 42nd St NW Washington MD 20016",
    "addr:housenumber":"4545",
    "addr:postcode":"20016",
    "addr:street":"42Nd St Nw",
    "iso:country":"US",
    "sg:address":"4545 42nd St NW",
    "sg:city":"Washington",
    "sg:classifiers":[
        {
            "category":"Real Estate",
            "subcategory":"Real Estate Operator",
            "type":"Services"
        }
    ],
    "sg:phone":"+1 202 244 6470",
    "sg:postcode":"20016",
    "sg:province":"MD",
    "sg:tags":[
        "apartment"
    ],
    "wof:name":"Thomas P Brown Management Inc",
    "wof:placetype":"venue"
},
  "geometry": {"coordinates":[-77.08196700000001,38.947985],"type":"Point"}
}