{
  "type": "Feature",
  "properties": {
    "iso:country":"US",
    "sg:address":"501 S Gilmor St",
    "sg:city":"Baltimore",
    "sg:classifiers":[
        {
            "category":"Manufacturing",
            "subcategory":"Printing",
            "type":"Manufacturing & Wholesale Goods"
        }
    ],
    "sg:phone":"+1 410 947 2214",
    "sg:postcode":"21223",
    "sg:province":"MD",
    "sg:tags":[
        "printer"
    ],
    "wof:name":"Roundhouse Printing",
    "wof:placetype":"venue"
},
  "geometry": {"coordinates":[-76.641988,39.281604],"type":"Point"}
}