{
  "type": "Feature",
  "properties": {
    "iso:country":"US",
    "sg:address":"1355 Market St",
    "sg:city":"Denton",
    "sg:classifiers":[
        {
            "category":"Professional",
            "subcategory":"Accounting & Tax Preparation",
            "type":"Services"
        }
    ],
    "sg:phone":"+1 410 479 0022",
    "sg:postcode":"21629",
    "sg:province":"MD",
    "sg:tags":[
        "bookkeeping",
        "general"
    ],
    "wof:name":"Elliott & Elliott",
    "wof:placetype":"venue"
},
  "geometry": {"coordinates":[-75.805122,38.884249],"type":"Point"}
}