{
  "type": "Feature",
  "properties": {
    "addr:full":"5323 Sweet Air Rd Baldwin MD 21013",
    "addr:housenumber":"5323",
    "addr:postcode":"21013",
    "addr:street":"Sweet Air Rd",
    "iso:country":"US",
    "sg:address":"5323 Sweet Air Rd",
    "sg:city":"Baldwin",
    "sg:classifiers":[
        {
            "category":"Building & Trades",
            "subcategory":"Landscaping Services",
            "type":"Services"
        }
    ],
    "sg:phone":"+1 410 592 2711",
    "sg:postcode":"21013",
    "sg:province":"MD",
    "sg:tags":[
        "aged",
        "homes-institutional"
    ],
    "wof:name":"Oakleigh House",
    "wof:placetype":"venue"
},
  "geometry": {"coordinates":[-76.491399,39.50454],"type":"Point"}
}