{
  "type": "Feature",
  "properties": {
    "addr:full":"3247 Old Fence Ct Ellicott City MD 21042",
    "addr:housenumber":"3247",
    "addr:postcode":"21042",
    "addr:street":"Old Fence Ct",
    "iso:country":"US",
    "sg:address":"3247 Old Fence Ct",
    "sg:city":"Ellicott City",
    "sg:classifiers":[
        {
            "category":"Shopping",
            "subcategory":"Computers & Home Electronics",
            "type":"Retail Goods"
        }
    ],
    "sg:phone":"+1 410 465 7878",
    "sg:postcode":"21042",
    "sg:province":"MD",
    "sg:tags":[
        "publishing"
    ],
    "wof:name":"Typestyles",
    "wof:placetype":"venue"
},
  "geometry": {"coordinates":[-76.837636,39.282064],"type":"Point"}
}