{
  "type": "Feature",
  "properties": {
    "addr:full":"3528 Horton Ave Brooklyn MD 21225",
    "addr:housenumber":"3528",
    "addr:postcode":"21225",
    "addr:street":"Horton Ave",
    "iso:country":"US",
    "sg:address":"3528 Horton Ave",
    "sg:city":"Brooklyn",
    "sg:classifiers":[
        {
            "category":"Freight",
            "type":"Transportation"
        }
    ],
    "sg:phone":"+1 410 354 6500",
    "sg:postcode":"21225",
    "sg:province":"MD",
    "wof:name":"Hanover Transportation Co Inc",
    "wof:placetype":"venue"
},
  "geometry": {"coordinates":[-76.605467,39.239352],"type":"Point"}
}