{
  "type": "Feature",
  "properties": {
    "iso:country":"US",
    "sg:address":"2200 Saint Paul St",
    "sg:city":"Baltimore",
    "sg:classifiers":[
        {
            "category":"Place Of Worship",
            "subcategory":"Church",
            "type":"Public Place"
        },
        {
            "category":"Place Of Worship",
            "type":"Public Place"
        },
        {
            "category":"Organizations",
            "subcategory":"Religious Organization",
            "type":"Services"
        }
    ],
    "sg:phone":"+1 410 889 1512",
    "sg:postcode":"21218",
    "sg:province":"MD",
    "sg:tags":[
        "churches-methodist"
    ],
    "sg:website":"www.umc.org",
    "wof:name":"Lovely Lane United Methodist Church",
    "wof:placetype":"venue"
},
  "geometry": {"coordinates":[-76.614998,39.314701],"type":"Point"}
}