{
  "type": "Feature",
  "properties": {
    "iso:country":"US",
    "sg:address":"10613 Georgia Ave",
    "sg:city":"Silver Spring",
    "sg:classifiers":[
        {
            "category":"Organizations",
            "subcategory":"Religious Organization",
            "type":"Services"
        }
    ],
    "sg:phone":"+1 301 649 4131",
    "sg:postcode":"20902",
    "sg:province":"MD",
    "sg:tags":[
        "church"
    ],
    "sg:website":"www.atonement-arp.org",
    "wof:name":"Atonement Presbyterian Church",
    "wof:placetype":"venue"
},
  "geometry": {"coordinates":[-77.047595,39.029859],"type":"Point"}
}