{
  "type": "Feature",
  "properties": {
    "iso:country":"US",
    "sg:address":"13300 Greencastle Pike",
    "sg:city":"Hagerstown",
    "sg:classifiers":[
        {
            "category":"Retail",
            "subcategory":"Auto Repair",
            "type":"Services"
        }
    ],
    "sg:phone":"+1 301 790 3788",
    "sg:postcode":"21740",
    "sg:province":"MD",
    "wof:name":"Eci Transport & Truck Repair",
    "wof:placetype":"venue"
},
  "geometry": {"coordinates":[-77.791634,39.677605],"type":"Point"}
}