{
  "type": "Feature",
  "properties": {
    "iso:country":"US",
    "sg:address":"6 62nd St",
    "sg:city":"Ocean City",
    "sg:classifiers":[
        {
            "category":"Building & Trades",
            "subcategory":"Construction",
            "type":"Services"
        }
    ],
    "sg:phone":"+1 410 723 0195",
    "sg:postcode":"21842",
    "sg:province":"MD",
    "sg:tags":[
        "contractor"
    ],
    "wof:name":"Southern Builders",
    "wof:placetype":"venue"
},
  "geometry": {"coordinates":[-75.065943,38.385015],"type":"Point"}
}