{
  "type": "Feature",
  "properties": {
    "addr:full":"628 Talon Ct Arnold MD 21012",
    "addr:housenumber":"628",
    "addr:postcode":"21012",
    "addr:street":"Talon Ct",
    "iso:country":"US",
    "sg:address":"628 Talon Ct",
    "sg:city":"Arnold",
    "sg:classifiers":[
        {
            "category":"Retail",
            "subcategory":"Portrait Studio",
            "type":"Services"
        }
    ],
    "sg:phone":"+1 410 974 1751",
    "sg:postcode":"21012",
    "sg:province":"MD",
    "sg:tags":[
        "photo"
    ],
    "wof:name":"Vivienne Photography",
    "wof:placetype":"venue"
},
  "geometry": {"coordinates":[-76.46915300000001,39.03663],"type":"Point"}
}