{
  "type": "Feature",
  "properties": {
    "iso:country":"US",
    "sg:address":"10825 Pam Dr",
    "sg:city":"Waldorf",
    "sg:classifiers":[
        {
            "category":"Wholesale",
            "subcategory":"Medical Equipment & Supplies",
            "type":"Manufacturing & Wholesale Goods"
        }
    ],
    "sg:phone":"+1 301 396 5210",
    "sg:postcode":"20603",
    "sg:province":"MD",
    "sg:tags":[
        "physician",
        "surgeon"
    ],
    "wof:name":"Tier 1 Medical Products",
    "wof:placetype":"venue"
},
  "geometry": {"coordinates":[-76.936079,38.638045],"type":"Point"}
}