{
  "type": "Feature",
  "properties": {
    "addr:full":"6311 Old Branch Ave Temple Hills MD 20748",
    "addr:housenumber":"6311",
    "addr:postcode":"20748",
    "addr:street":"Old Branch Ave",
    "iso:country":"US",
    "sg:address":"6311 Old Branch Ave",
    "sg:city":"Temple Hills",
    "sg:classifiers":[
        {
            "category":"Organizations",
            "subcategory":"Community Association",
            "type":"Services"
        }
    ],
    "sg:phone":"+1 301 449 9793",
    "sg:postcode":"20748",
    "sg:province":"MD",
    "wof:name":"Camp Springs Masonic Lodge",
    "wof:placetype":"venue"
},
  "geometry": {"coordinates":[-76.906277,38.802893],"type":"Point"}
}