{
  "type": "Feature",
  "properties": {
    "iso:country":"US",
    "sg:address":"7130 Fox Harbor Way",
    "sg:city":"Elkridge",
    "sg:classifiers":[
        {
            "category":"Professional",
            "subcategory":"Computer Services",
            "type":"Services"
        }
    ],
    "sg:phone":"+1 410 579 1766",
    "sg:postcode":"21075",
    "sg:province":"MD",
    "sg:tags":[
        "information",
        "recovery",
        "processing",
        "system",
        "equipment",
        "data",
        "retrieval"
    ],
    "wof:name":"Solvdata Systems Solutions",
    "wof:placetype":"venue"
},
  "geometry": {"coordinates":[-76.784565,39.178079],"type":"Point"}
}