{
  "type": "Feature",
  "properties": {
    "addr:full":"9058 Double Hills Rd Denton MD 21629",
    "addr:housenumber":"9058",
    "addr:postcode":"21629",
    "addr:street":"Double Hills Rd",
    "iso:country":"US",
    "sg:address":"9058 Double Hills Rd",
    "sg:city":"Denton",
    "sg:classifiers":[
        {
            "category":"Place Of Worship",
            "subcategory":"Church",
            "type":"Public Place"
        },
        {
            "category":"Place Of Worship",
            "type":"Public Place"
        }
    ],
    "sg:phone":"+1 410 479 0585",
    "sg:postcode":"21629",
    "sg:province":"MD",
    "sg:tags":[
        "churches-pentecostal-independent",
        "churches-pentecostal"
    ],
    "wof:name":"Living Waters Assembly",
    "wof:placetype":"venue"
},
  "geometry": {"coordinates":[-75.81475399999999,38.855973],"type":"Point"}
}