{
  "type": "Feature",
  "properties": {
    "iso:country":"US",
    "sg:address":"3413 Metzerott Rd",
    "sg:city":"College Park",
    "sg:classifiers":[
        {
            "category":"Professional",
            "type":"Services"
        }
    ],
    "sg:phone":"+1 301 434 1823",
    "sg:postcode":"20740",
    "sg:province":"MD",
    "wof:name":"Cad Micro Services",
    "wof:placetype":"venue"
},
  "geometry": {"coordinates":[-76.95142800000001,39.002033],"type":"Point"}
}