{
  "type": "Feature",
  "properties": {
    "iso:country":"US",
    "sg:address":"14525 Barkwood Dr",
    "sg:city":"Rockville",
    "sg:classifiers":[
        {
            "category":"Arena",
            "subcategory":"Sports Club",
            "type":"Entertainment"
        }
    ],
    "sg:phone":"+1 301 871 2268",
    "sg:postcode":"20853",
    "sg:province":"MD",
    "sg:tags":[
        "soccer"
    ],
    "sg:website":"www.bethesdasoccer.org",
    "wof:name":"Bethesda Soccer Club Inc",
    "wof:placetype":"venue"
},
  "geometry": {"coordinates":[-77.102943,39.094699],"type":"Point"}
}