{
  "type": "Feature",
  "properties": {
    "iso:country":"US",
    "sg:address":"8655 Normal School Rd",
    "sg:city":"Bowie",
    "sg:classifiers":[
        {
            "category":"Health Services",
            "subcategory":"Health Practitioner",
            "type":"Services"
        }
    ],
    "sg:phone":"+1 301 262 5696",
    "sg:postcode":"20715",
    "sg:province":"MD",
    "sg:tags":[
        "addiction",
        "abuse",
        "drug"
    ],
    "wof:name":"Champ House Inc",
    "wof:placetype":"venue"
},
  "geometry": {"coordinates":[-76.76473900000001,39.008044],"type":"Point"}
}