{
  "type": "Feature",
  "properties": {
    "iso:country":"US",
    "sg:address":"1393 Dorsey Hotel Rd",
    "sg:city":"Grantsville",
    "sg:classifiers":[
        {
            "category":"Organizations",
            "subcategory":"Religious Organization",
            "type":"Services"
        }
    ],
    "sg:phone":"+1 301 895 3434",
    "sg:postcode":"21536",
    "sg:province":"MD",
    "sg:tags":[
        "church"
    ],
    "wof:name":"Church Of The Redeemer",
    "wof:placetype":"venue"
},
  "geometry": {"coordinates":[-79.138216,39.722393],"type":"Point"}
}