{
  "type": "Feature",
  "properties": {
    "iso:country":"US",
    "sg:address":"106 52nd St",
    "sg:city":"Ocean City",
    "sg:classifiers":[
        {
            "category":"Recreation",
            "subcategory":"Marina",
            "type":"Entertainment"
        }
    ],
    "sg:phone":"+1 410 723 9773",
    "sg:postcode":"21842",
    "sg:province":"MD",
    "sg:tags":[
        "repairing",
        "boat"
    ],
    "wof:name":"Bayside Jet Drive",
    "wof:placetype":"venue"
},
  "geometry": {"coordinates":[-75.069829,38.377221],"type":"Point"}
}