{
  "type": "Feature",
  "properties": {
    "iso:country":"US",
    "sg:address":"208 E Main St",
    "sg:city":"Elkton",
    "sg:classifiers":[
        {
            "category":"Professional",
            "subcategory":"Lawyer & Legal Services",
            "type":"Services"
        }
    ],
    "sg:phone":"+1 410 398 0166",
    "sg:postcode":"21921",
    "sg:province":"MD",
    "sg:tags":[
        "attorney"
    ],
    "wof:name":"Joseph J Mahoney",
    "wof:placetype":"venue"
},
  "geometry": {"coordinates":[-75.82649000000001,39.609079],"type":"Point"}
}