{
  "type": "Feature",
  "properties": {
    "addr:full":"731 Deepdene Rd Baltimore MD 21210",
    "addr:housenumber":"731",
    "addr:postcode":"21210",
    "addr:street":"Deepdene Rd",
    "iso:country":"US",
    "sg:address":"731 Deepdene Rd",
    "sg:city":"Baltimore",
    "sg:classifiers":[
        {
            "category":"Health Services",
            "subcategory":"Dentist",
            "type":"Services"
        }
    ],
    "sg:phone":"+1 410 323 3990",
    "sg:postcode":"21210",
    "sg:province":"MD",
    "wof:name":"Slotke Craig E DDS",
    "wof:placetype":"venue"
},
  "geometry": {"coordinates":[-76.633092,39.356372],"type":"Point"}
}