{
  "type": "Feature",
  "properties": {
    "addr:full":"1 W Pennsylvania Ave # 900 Towson MD 21204",
    "addr:housenumber":"1",
    "addr:postcode":"21204",
    "addr:street":"W Pennsylvania Ave # 900",
    "iso:country":"US",
    "sg:address":"1 W Pennsylvania Ave # 900",
    "sg:city":"Towson",
    "sg:classifiers":[
        {
            "category":"Professional",
            "subcategory":"Lawyer & Legal Services",
            "type":"Services"
        }
    ],
    "sg:phone":"+1 410 823 8250",
    "sg:postcode":"21204",
    "sg:province":"MD",
    "sg:tags":[
        "plan"
    ],
    "wof:name":"Alexander Wright Jr",
    "wof:placetype":"venue"
},
  "geometry": {"coordinates":[-76.602417,39.400471],"type":"Point"}
}