{
  "type": "Feature",
  "properties": {
    "addr:full":"4136 E Joppa Rd Baltimore MD 21236",
    "addr:housenumber":"4136 e",
    "addr:postcode":"21236",
    "addr:street":"Joppa Rd",
    "iso:country":"US",
    "sg:address":"4136 E Joppa Rd",
    "sg:city":"Baltimore",
    "sg:classifiers":[
        {
            "category":"Restaurant",
            "type":"Food & Drink"
        }
    ],
    "sg:menulink":"http://www.allmenus.com/md/batter-brook-farms/71635-pizza-hut/menu/",
    "sg:phone":"+1 410 248 0800",
    "sg:postcode":"21236",
    "sg:province":"MD",
    "sg:tags":[
        "american",
        "pizza"
    ],
    "wof:name":"Pizza Hut",
    "wof:placetype":"venue"
},
  "geometry": {"coordinates":[-76.481405,39.3987],"type":"Point"}
}