{
  "type": "Feature",
  "properties": {
    "addr:full":"5913 Fisher Rd Temple Hills MD 20748",
    "addr:housenumber":"5913",
    "addr:postcode":"20748",
    "addr:street":"Fisher Rd",
    "iso:country":"US",
    "sg:address":"5913 Fisher Rd",
    "sg:city":"Temple Hills",
    "sg:classifiers":[
        {
            "category":"Travel",
            "subcategory":"Travel Agent",
            "type":"Entertainment"
        }
    ],
    "sg:phone":"+1 301 630 1993",
    "sg:postcode":"20748",
    "sg:province":"MD",
    "sg:tags":[
        "tours",
        "promoter"
    ],
    "wof:name":"Coastal Tour Ways",
    "wof:placetype":"venue"
},
  "geometry": {"coordinates":[-76.95658299999999,38.807498],"type":"Point"}
}