{
  "type": "Feature",
  "properties": {
    "iso:country":"US",
    "sg:address":"2607 Dakota St",
    "sg:city":"Bryans Road",
    "sg:classifiers":[
        {
            "category":"Organizations",
            "subcategory":"Non-profit Organization",
            "type":"Services"
        }
    ],
    "sg:phone":"+1 301 375 8410",
    "sg:postcode":"20616",
    "sg:province":"MD",
    "sg:tags":[
        "fund",
        "counselor",
        "raising"
    ],
    "wof:name":"American Moose Enterprises",
    "wof:placetype":"venue"
},
  "geometry": {"coordinates":[-77.084323,38.636215],"type":"Point"}
}