{
  "type": "Feature",
  "properties": {
    "addr:full":"13006 Shamrock Glen Dr Germantown MD 20874",
    "addr:housenumber":"13006",
    "addr:postcode":"20874",
    "addr:street":"Shamrock Glen Dr",
    "iso:country":"US",
    "sg:address":"13006 Shamrock Glen Dr",
    "sg:city":"Germantown",
    "sg:classifiers":[
        {
            "category":"Personal",
            "type":"Services"
        }
    ],
    "sg:phone":"+1 301 528 4101",
    "sg:postcode":"20874",
    "sg:province":"MD",
    "sg:tags":[
        "credit",
        "debt",
        "counseling"
    ],
    "wof:name":"Debt Directors",
    "wof:placetype":"venue"
},
  "geometry": {"coordinates":[-77.269919,39.197907],"type":"Point"}
}