{
  "type": "Feature",
  "properties": {
    "addr:full":"14523 Parkvale Rd Rockville MD 20853",
    "addr:housenumber":"14523",
    "addr:postcode":"20853",
    "addr:street":"Parkvale Rd",
    "iso:country":"US",
    "sg:address":"14523 Parkvale Rd",
    "sg:city":"Rockville",
    "sg:classifiers":[
        {
            "category":"Shopping",
            "subcategory":"Used Merchandise",
            "type":"Retail Goods"
        }
    ],
    "sg:phone":"+1 301 871 5479",
    "sg:postcode":"20853",
    "sg:province":"MD",
    "wof:name":"Antique Station",
    "wof:placetype":"venue"
},
  "geometry": {"coordinates":[-77.114626,39.094114],"type":"Point"}
}