{
  "type": "Feature",
  "properties": {
    "addr:full":"8910 Belair Rd Nottingham MD 21236",
    "addr:housenumber":"8910",
    "addr:postcode":"21236",
    "addr:street":"Belair Rd",
    "iso:country":"US",
    "sg:address":"8910 Belair Rd",
    "sg:city":"Nottingham",
    "sg:classifiers":[
        {
            "category":"Coffee & Tea",
            "type":"Food & Drink"
        }
    ],
    "sg:menulink":"http://www.allmenus.com/md/batter-brook-farms/119064-starbucks-coffee/menu/",
    "sg:phone":"+1 410 529 3012",
    "sg:postcode":"21236",
    "sg:province":"MD",
    "sg:tags":[
        "american"
    ],
    "wof:name":"Starbucks Coffee",
    "wof:placetype":"venue"
},
  "geometry": {"coordinates":[-76.481522,39.39802],"type":"Point"}
}