{
  "type": "Feature",
  "properties": {
    "addr:full":"8628 Liberty Rd Randallstown MD 21133",
    "addr:housenumber":"8628",
    "addr:postcode":"21133",
    "addr:street":"Liberty Rd",
    "iso:country":"US",
    "sg:address":"8628 Liberty Rd",
    "sg:city":"Randallstown",
    "sg:classifiers":[
        {
            "category":"Personal",
            "subcategory":"Beauty Salon",
            "type":"Services"
        }
    ],
    "sg:phone":"+1 410 922 8988",
    "sg:postcode":"21133",
    "sg:province":"MD",
    "wof:name":"Vicky' S Salon",
    "wof:placetype":"venue"
},
  "geometry": {"coordinates":[-76.78104,39.362379],"type":"Point"}
}