{
  "type": "Feature",
  "properties": {
    "addr:full":"7566 E Howard Rd Glen Burnie MD 21060",
    "addr:housenumber":"7566",
    "addr:postcode":"21060",
    "addr:street":"E Howard Rd",
    "iso:country":"US",
    "sg:address":"7566 E Howard Rd",
    "sg:city":"Glen Burnie",
    "sg:classifiers":[
        {
            "category":"Organizations",
            "subcategory":"Religious Organization",
            "type":"Services"
        }
    ],
    "sg:phone":"+1 410 761 9272",
    "sg:postcode":"21060",
    "sg:province":"MD",
    "sg:tags":[
        "church"
    ],
    "wof:name":"St James Church Of Apostolic",
    "wof:placetype":"venue"
},
  "geometry": {"coordinates":[-76.585696,39.154511],"type":"Point"}
}