{
  "type": "Feature",
  "properties": {
    "addr:full":"9870 Main St Damascus MD 20872",
    "addr:housenumber":"9870",
    "addr:postcode":"20872",
    "addr:street":"Main St",
    "iso:country":"US",
    "sg:address":"9870 Main St",
    "sg:city":"Damascus",
    "sg:classifiers":[
        {
            "category":"Home & Garden",
            "subcategory":"Furniture",
            "type":"Retail Goods"
        }
    ],
    "sg:phone":"+1 301 391 6240",
    "sg:postcode":"20872",
    "sg:province":"MD",
    "wof:name":"Uniite Furniture & Carpet",
    "wof:placetype":"venue"
},
  "geometry": {"coordinates":[-77.202382,39.287858],"type":"Point"}
}