{
  "type": "Feature",
  "properties": {
    "iso:country":"US",
    "sg:address":"208 S University Ave",
    "sg:city":"Federalsburg",
    "sg:classifiers":[
        {
            "category":"Government",
            "subcategory":"Office",
            "type":"Public Place"
        }
    ],
    "sg:phone":"+1 410 479 4411",
    "sg:postcode":"21632",
    "sg:province":"MD",
    "wof:name":"Caroline County Advanced Life",
    "wof:placetype":"venue"
},
  "geometry": {"coordinates":[-75.780646,38.691903],"type":"Point"}
}