{
  "type": "Feature",
  "properties": {
    "addr:full":"4115 Farragut St Hyattsville MD 20781",
    "addr:housenumber":"4115",
    "addr:postcode":"20781",
    "addr:street":"Farragut St",
    "iso:country":"US",
    "sg:address":"4115 Farragut St",
    "sg:city":"Hyattsville",
    "sg:classifiers":[
        {
            "category":"Building & Trades",
            "subcategory":"Construction",
            "type":"Services"
        }
    ],
    "sg:phone":"+1 301 927 2176",
    "sg:postcode":"20781",
    "sg:province":"MD",
    "sg:tags":[
        "plastering",
        "subcontractor"
    ],
    "wof:name":"Jarman Plastering Service",
    "wof:placetype":"venue"
},
  "geometry": {"coordinates":[-76.94597400000001,38.951329],"type":"Point"}
}