{
  "type": "Feature",
  "properties": {
    "addr:full":"200 N Highland Ave Baltimore MD 21224",
    "addr:housenumber":"200",
    "addr:postcode":"21224",
    "addr:street":"N Highland Ave",
    "iso:country":"US",
    "sg:address":"200 N Highland Ave",
    "sg:city":"Baltimore",
    "sg:classifiers":[
        {
            "category":"Shopping",
            "subcategory":"Beauty & Cosmetics",
            "type":"Retail Goods"
        }
    ],
    "sg:phone":"+1 410 327 2700",
    "sg:postcode":"21224",
    "sg:province":"MD",
    "sg:tags":[
        "supply"
    ],
    "wof:name":"Clever Mart",
    "wof:placetype":"venue"
},
  "geometry": {"coordinates":[-76.569603,39.294899],"type":"Point"}
}