{
  "type": "Feature",
  "properties": {
    "addr:full":"140 E Main St Elkton MD 21921",
    "addr:housenumber":"140",
    "addr:postcode":"21921",
    "addr:street":"E Main St",
    "iso:country":"US",
    "sg:address":"140 E Main St",
    "sg:city":"Elkton",
    "sg:classifiers":[
        {
            "category":"Real Estate",
            "subcategory":"Developer",
            "type":"Services"
        }
    ],
    "sg:phone":"+1 410 620 5906",
    "sg:postcode":"21921",
    "sg:province":"MD",
    "wof:name":"Smart Growth Land Mgmt Co",
    "wof:placetype":"venue"
},
  "geometry": {"coordinates":[-75.827405,39.608693],"type":"Point"}
}