{
  "type": "Feature",
  "properties": {
    "iso:country":"US",
    "sg:address":"31530 Miller Rd",
    "sg:city":"Cordova",
    "sg:classifiers":[
        {
            "category":"Manufacturing",
            "subcategory":"Printing",
            "type":"Manufacturing & Wholesale Goods"
        }
    ],
    "sg:phone":"+1 410 820 2222",
    "sg:postcode":"21625",
    "sg:province":"MD",
    "sg:tags":[
        "printer"
    ],
    "wof:name":"Huber Printing",
    "wof:placetype":"venue"
},
  "geometry": {"coordinates":[-75.987325,38.833671],"type":"Point"}
}