{
  "type": "Feature",
  "properties": {
    "addr:full":"21 E Chatsworth Ave Reisterstown MD 21136",
    "addr:housenumber":"21",
    "addr:postcode":"21136",
    "addr:street":"E Chatsworth Ave",
    "iso:country":"US",
    "sg:address":"21 E Chatsworth Ave",
    "sg:city":"Reisterstown",
    "sg:classifiers":[
        {
            "category":"Professional",
            "subcategory":"Management & Consulting",
            "type":"Services"
        }
    ],
    "sg:phone":"+1 410 833 1477",
    "sg:postcode":"21136",
    "sg:province":"MD",
    "wof:name":"Denny Lockard Enterprises Inc",
    "wof:placetype":"venue"
},
  "geometry": {"coordinates":[-76.828838,39.466931],"type":"Point"}
}