{
  "type": "Feature",
  "properties": {
    "addr:full":"717 Pershing Dr Silver Spring MD 20910",
    "addr:housenumber":"717",
    "addr:postcode":"20910",
    "addr:street":"Pershing Dr",
    "iso:country":"US",
    "sg:address":"717 Pershing Dr",
    "sg:city":"Silver Spring",
    "sg:classifiers":[
        {
            "category":"Health Services",
            "subcategory":"Doctor",
            "type":"Services"
        }
    ],
    "sg:phone":"+1 301 589 5362",
    "sg:postcode":"20910",
    "sg:province":"MD",
    "sg:tags":[
        "physician",
        "surgeon"
    ],
    "wof:name":"Hugo G Graziani MD",
    "wof:placetype":"venue"
},
  "geometry": {"coordinates":[-77.022306,38.99919],"type":"Point"}
}