{
  "type": "Feature",
  "properties": {
    "iso:country":"US",
    "sg:address":"2021 Emmorton Rd",
    "sg:city":"Bel Air",
    "sg:classifiers":[
        {
            "category":"Health Services",
            "subcategory":"Doctor",
            "type":"Services"
        }
    ],
    "sg:phone":"+1 410 569 9040",
    "sg:postcode":"21015",
    "sg:province":"MD",
    "sg:tags":[
        "physician",
        "surgeon"
    ],
    "wof:name":"Smaldore Family Practice Assoc",
    "wof:placetype":"venue"
},
  "geometry": {"coordinates":[-76.32566199999999,39.500074],"type":"Point"}
}