{
  "type": "Feature",
  "properties": {
    "iso:country":"US",
    "sg:address":"1534 Gorsuch Ave",
    "sg:city":"Baltimore",
    "sg:classifiers":[
        {
            "category":"Personal",
            "subcategory":"Barber",
            "type":"Services"
        }
    ],
    "sg:phone":"+1 410 467 9120",
    "sg:postcode":"21218",
    "sg:province":"MD",
    "wof:name":"Session & Son Barber Shop",
    "wof:placetype":"venue"
},
  "geometry": {"coordinates":[-76.59694,39.322913],"type":"Point"}
}