{
  "type": "Feature",
  "properties": {
    "iso:country":"US",
    "sg:address":"2642 Mount Carmel Rd",
    "sg:city":"Parkton",
    "sg:classifiers":[
        {
            "category":"Retail",
            "subcategory":"Animal Services",
            "type":"Services"
        }
    ],
    "sg:phone":"+1 410 329 6380",
    "sg:postcode":"21120",
    "sg:province":"MD",
    "sg:tags":[
        "breeder",
        "horse"
    ],
    "sg:website":"www.imperialegyptianstud.com",
    "wof:name":"Imperial Egyptian Stud",
    "wof:placetype":"venue"
},
  "geometry": {"coordinates":[-76.739453,39.593673],"type":"Point"}
}