{
  "type": "Feature",
  "properties": {
    "addr:full":"12619 Wisteria Dr Germantown MD 20874",
    "addr:housenumber":"12619",
    "addr:postcode":"20874",
    "addr:street":"Wisteria Dr",
    "iso:country":"US",
    "sg:address":"12619 Wisteria Dr",
    "sg:city":"Germantown",
    "sg:classifiers":[
        {
            "category":"Shopping",
            "subcategory":"Clothing, Apparel, & Fashions",
            "type":"Retail Goods"
        }
    ],
    "sg:phone":"+1 301 540 0075",
    "sg:postcode":"20874",
    "sg:province":"MD",
    "sg:tags":[
        "swimwear",
        "accessory"
    ],
    "wof:name":"Underwater Wear LLC",
    "wof:placetype":"venue"
},
  "geometry": {"coordinates":[-77.261965,39.17038],"type":"Point"}
}