{
  "type": "Feature",
  "properties": {
    "addr:full":"5420 Klee Mill Rd S Sykesville MD 21784",
    "addr:postcode":"5420;21784",
    "addr:street":"Klee Mill Rd",
    "iso:country":"US",
    "sg:address":"5420 Klee Mill Rd S",
    "sg:city":"Sykesville",
    "sg:classifiers":[
        {
            "category":"Insurance",
            "subcategory":"Hazard Insurance",
            "type":"Services"
        }
    ],
    "sg:phone":"+1 410 781 6296",
    "sg:postcode":"21784",
    "sg:province":"MD",
    "sg:tags":[
        "commercial",
        "business"
    ],
    "sg:website":"http://www.allstate.com",
    "wof:name":"Allstate Insurance Companies",
    "wof:placetype":"venue"
},
  "geometry": {"coordinates":[-76.996353,39.424529],"type":"Point"}
}