{
  "type": "Feature",
  "properties": {
    "addr:full":"1955 Solomons Island Rd S Prince Frederick MD 20678",
    "addr:housenumber":"1955",
    "addr:postcode":"20678",
    "addr:street":"Solomons Island Rd",
    "iso:country":"US",
    "sg:address":"1955 Solomons Island Rd S",
    "sg:city":"Prince Frederick",
    "sg:classifiers":[
        {
            "category":"Retail",
            "subcategory":"Auto Rental",
            "type":"Services"
        }
    ],
    "sg:phone":"+1 410 535 9493",
    "sg:postcode":"20678",
    "sg:province":"MD",
    "sg:tags":[
        "renting",
        "truck",
        "leasing"
    ],
    "wof:name":"U-Haul Co",
    "wof:placetype":"venue"
},
  "geometry": {"coordinates":[-76.564627,38.510505],"type":"Point"}
}