{
  "type": "Feature",
  "properties": {
    "addr:full":"5581 Compton Ln Sykesville MD 21784",
    "addr:housenumber":"5581",
    "addr:postcode":"21784",
    "addr:street":"Compton Ln",
    "iso:country":"US",
    "sg:address":"5581 Compton Ln",
    "sg:city":"Sykesville",
    "sg:classifiers":[
        {
            "category":"Professional",
            "subcategory":"Management & Consulting",
            "type":"Services"
        }
    ],
    "sg:phone":"+1 410 781 6045",
    "sg:postcode":"21784",
    "sg:province":"MD",
    "wof:name":"Kimson Ent Inc",
    "wof:placetype":"venue"
},
  "geometry": {"coordinates":[-76.952185,39.422484],"type":"Point"}
}