{
  "type": "Feature",
  "properties": {
    "iso:country":"US",
    "sg:address":"500 W 29th St",
    "sg:city":"Baltimore",
    "sg:classifiers":[
        {
            "category":"Building & Trades",
            "subcategory":"Construction",
            "type":"Services"
        }
    ],
    "sg:phone":"+1 410 235 9400",
    "sg:postcode":"21211",
    "sg:province":"MD",
    "sg:tags":[
        "excavating",
        "contractor"
    ],
    "sg:website":"www.pottscallahan.com",
    "wof:name":"Potts & Callahan Inc",
    "wof:placetype":"venue"
},
  "geometry": {"coordinates":[-76.62552599999999,39.320908],"type":"Point"}
}