{
  "type": "Feature",
  "properties": {
    "iso:country":"US",
    "sg:address":"Air Rights Center, North Tower 4550 Montgomery Ave., Ste 601N",
    "sg:city":"Bethesda",
    "sg:classifiers":[
        {
            "category":"Professional",
            "subcategory":"Lawyer & Legal Services",
            "type":"Services"
        }
    ],
    "sg:phone":"+1 301 469 3498",
    "sg:postcode":"20814",
    "sg:province":"MD",
    "sg:website":"www.morrisfischerlaw.com",
    "wof:name":"Morris E. Fischer, Esq.",
    "wof:placetype":"venue"
},
  "geometry": {"coordinates":[-77.09182699999999,38.983582],"type":"Point"}
}