{
  "type": "Feature",
  "properties": {
    "addr:full":"6259 Deep River Canyon Columbia MD 21045",
    "addr:housenumber":"6259",
    "addr:postcode":"21045",
    "addr:street":"Deep River Canyon",
    "iso:country":"US",
    "sg:address":"6259 Deep River Canyon",
    "sg:city":"Columbia",
    "sg:classifiers":[
        {
            "category":"Professional",
            "subcategory":"Employment Agencies",
            "type":"Services"
        }
    ],
    "sg:phone":"+1 410 312 2982",
    "sg:postcode":"21045",
    "sg:province":"MD",
    "sg:tags":[
        "help",
        "supply"
    ],
    "wof:name":"Deepsoft Inc",
    "wof:placetype":"venue"
},
  "geometry": {"coordinates":[-76.806971,39.199809],"type":"Point"}
}