{
  "type": "Feature",
  "properties": {
    "iso:country":"US",
    "sg:address":"2604 Sisson St Ste 2",
    "sg:city":"Baltimore",
    "sg:classifiers":[
        {
            "category":"Shopping",
            "subcategory":"Stationery & Office Supplies",
            "type":"Retail Goods"
        },
        {
            "category":"Shopping",
            "subcategory":"Department Store",
            "type":"Retail Goods"
        }
    ],
    "sg:phone":"+1 410 467 6986",
    "sg:postcode":"21211",
    "sg:province":"MD",
    "sg:tags":[
        "equipment"
    ],
    "wof:name":"Price-Modern Inc",
    "wof:placetype":"venue"
},
  "geometry": {"coordinates":[-76.62359600000001,39.317699],"type":"Point"}
}