{
  "type": "Feature",
  "properties": {
    "addr:full":"1113 Dulaney Gate Cir Cockysvl Hnt Vly MD 21030",
    "addr:housenumber":"1113",
    "addr:postcode":"21030",
    "addr:street":"Dulaney Gate Cir Cockysvl Hnt Vly",
    "iso:country":"US",
    "sg:address":"1113 Dulaney Gate Cir",
    "sg:city":"Cockysvl Hnt Vly",
    "sg:classifiers":[
        {
            "category":"Health Services",
            "subcategory":"Doctor",
            "type":"Services"
        }
    ],
    "sg:phone":"+1 410 628 0965",
    "sg:postcode":"21030",
    "sg:province":"MD",
    "sg:tags":[
        "physician",
        "surgeon"
    ],
    "wof:name":"Suhayl Kalash MD",
    "wof:placetype":"venue"
},
  "geometry": {"coordinates":[-76.597094,39.473262],"type":"Point"}
}