{
  "type": "Feature",
  "properties": {
    "addr:full":"7941 Queenair Dr Gaithersburg MD 20879",
    "addr:housenumber":"7941",
    "addr:postcode":"20879",
    "addr:street":"Queenair Dr",
    "iso:country":"US",
    "sg:address":"7941 Queenair Dr",
    "sg:city":"Gaithersburg",
    "sg:classifiers":[
        {
            "category":"Wholesale",
            "subcategory":"Machinery & Supplies",
            "type":"Manufacturing & Wholesale Goods"
        }
    ],
    "sg:phone":"+1 301 840 5770",
    "sg:postcode":"20879",
    "sg:province":"MD",
    "sg:tags":[
        "janitor"
    ],
    "wof:name":"Metrochem Industries Inc",
    "wof:placetype":"venue"
},
  "geometry": {"coordinates":[-77.161891,39.17007],"type":"Point"}
}