{
  "type": "Feature",
  "properties": {
    "addr:full":"2302 Morgan Ct Finksburg MD 21048",
    "addr:housenumber":"2302",
    "addr:postcode":"21048",
    "addr:street":"Morgan Ct",
    "iso:country":"US",
    "sg:address":"2302 Morgan Ct",
    "sg:city":"Finksburg",
    "sg:classifiers":[
        {
            "category":"Health Services",
            "subcategory":"Doctor",
            "type":"Services"
        },
        {
            "category":"Health Services",
            "subcategory":"Hospital",
            "type":"Services"
        }
    ],
    "sg:phone":"+1 410 751 2671",
    "sg:postcode":"21048",
    "sg:province":"MD",
    "sg:tags":[
        "consultant",
        "medical",
        "practice",
        "nursing",
        "home"
    ],
    "wof:name":"Ron Milhorn",
    "wof:placetype":"venue"
},
  "geometry": {"coordinates":[-76.914879,39.522472],"type":"Point"}
}