{
  "type": "Feature",
  "properties": {
    "addr:full":"7812 Colonial Ln Clinton MD 20735",
    "addr:housenumber":"7812",
    "addr:postcode":"20735",
    "addr:street":"Colonial Ln",
    "iso:country":"US",
    "sg:address":"7812 Colonial Ln",
    "sg:city":"Clinton",
    "sg:classifiers":[
        {
            "category":"Personal",
            "subcategory":"Beauty Salon",
            "type":"Services"
        }
    ],
    "sg:phone":"+1 301 868 7546",
    "sg:postcode":"20735",
    "sg:province":"MD",
    "wof:name":"Virtuous Solutions, Inc.",
    "wof:placetype":"venue"
},
  "geometry": {"coordinates":[-76.86338000000001,38.782879],"type":"Point"}
}