{
  "type": "Feature",
  "properties": {
    "addr:full":"7313 15th Ave Takoma Park MD 20912",
    "addr:housenumber":"7313",
    "addr:postcode":"20912",
    "addr:street":"15Th Ave",
    "iso:country":"US",
    "sg:address":"7313 15th Ave",
    "sg:city":"Takoma Park",
    "sg:classifiers":[
        {
            "category":"Social Services",
            "type":"Services"
        }
    ],
    "sg:phone":"+1 301 445 6204",
    "sg:postcode":"20912",
    "sg:province":"MD",
    "sg:tags":[
        "worker"
    ],
    "wof:name":"Alicia Green",
    "wof:placetype":"venue"
},
  "geometry": {"coordinates":[-76.98533,38.982494],"type":"Point"}
}