{
  "type": "Feature",
  "properties": {
    "iso:country":"US",
    "sg:address":"1765 Sykesville Rd",
    "sg:city":"Sykesville",
    "sg:classifiers":[
        {
            "category":"Building & Trades",
            "subcategory":"Construction",
            "type":"Services"
        }
    ],
    "sg:phone":"+1 410 442 1007",
    "sg:postcode":"21784",
    "sg:province":"MD",
    "sg:tags":[
        "general",
        "contractor"
    ],
    "wof:name":"Dundee Contracting Co",
    "wof:placetype":"venue"
},
  "geometry": {"coordinates":[-76.948267,39.326106],"type":"Point"}
}