{
  "type": "Feature",
  "properties": {
    "addr:full":"8410 Piney Orchard Pkwy Odenton MD 21113",
    "addr:housenumber":"8410",
    "addr:postcode":"21113",
    "addr:street":"Piney Orchard Pkwy",
    "iso:country":"US",
    "sg:address":"8410 Piney Orchard Pkwy",
    "sg:city":"Odenton",
    "sg:classifiers":[
        {
            "category":"Education",
            "subcategory":"Preschool",
            "type":"Public Place"
        },
        {
            "category":"Education",
            "subcategory":"School",
            "type":"Public Place"
        }
    ],
    "sg:phone":"+1 410 551 9852",
    "sg:postcode":"21113",
    "sg:province":"MD",
    "sg:tags":[
        "kindergarten",
        "elementary",
        "religious",
        "interest"
    ],
    "sg:website":"http://www.ocs1.org",
    "wof:name":"Odenton Christian School",
    "wof:placetype":"venue"
},
  "geometry": {"coordinates":[-76.70075300000001,39.082904],"type":"Point"}
}