{
  "type": "Feature",
  "properties": {
    "iso:country":"US",
    "sg:address":"1043 Saxon Hill Dr",
    "sg:city":"Cockeysville",
    "sg:classifiers":[
        {
            "category":"Communications",
            "subcategory":"Film & Video Production",
            "type":"Services"
        }
    ],
    "sg:phone":"+1 410 628 2260",
    "sg:postcode":"21030",
    "sg:province":"MD",
    "sg:tags":[
        "motion"
    ],
    "wof:name":"Snow Productions Inc",
    "wof:placetype":"venue"
},
  "geometry": {"coordinates":[-76.599998,39.472746],"type":"Point"}
}