{
  "type": "Feature",
  "properties": {
    "addr:full":"410 Schley Rd Annapolis MD 21401",
    "addr:housenumber":"410",
    "addr:postcode":"21401",
    "addr:street":"Schley Rd",
    "iso:country":"US",
    "sg:address":"410 Schley Rd",
    "sg:city":"Annapolis",
    "sg:classifiers":[
        {
            "category":"Manufacturing",
            "subcategory":"Printing",
            "type":"Manufacturing & Wholesale Goods"
        }
    ],
    "sg:phone":"+1 410 268 0530",
    "sg:postcode":"21401",
    "sg:province":"MD",
    "sg:tags":[
        "periodical"
    ],
    "wof:name":"William O Lively",
    "wof:placetype":"venue"
},
  "geometry": {"coordinates":[-76.507435,38.987478],"type":"Point"}
}