{
  "type": "Feature",
  "properties": {
    "addr:full":"6681 Buttonhole Ct Columbia MD 21044",
    "addr:housenumber":"6681",
    "addr:postcode":"21044",
    "addr:street":"Buttonhole Ct",
    "iso:country":"US",
    "sg:address":"6681 Buttonhole Ct",
    "sg:city":"Columbia",
    "sg:classifiers":[
        {
            "category":"Professional",
            "subcategory":"Computer Services",
            "type":"Services"
        }
    ],
    "sg:phone":"+1 410 715 1300",
    "sg:postcode":"21044",
    "sg:province":"MD",
    "sg:tags":[
        "consultant",
        "designer",
        "datum",
        "system"
    ],
    "wof:name":"Cengen Consultanting & Engnr",
    "wof:placetype":"venue"
},
  "geometry": {"coordinates":[-76.87760400000001,39.188006],"type":"Point"}
}