{
  "type": "Feature",
  "properties": {
    "iso:country":"US",
    "sg:address":"9915 Lanham Severn Rd",
    "sg:city":"Lanham",
    "sg:classifiers":[
        {
            "category":"Recreation",
            "type":"Entertainment"
        }
    ],
    "sg:phone":"+1 301 577 8889",
    "sg:postcode":"20706",
    "sg:province":"MD",
    "sg:tags":[
        "skating",
        "rink"
    ],
    "wof:name":"Wheel-A-While Inc",
    "wof:placetype":"venue"
},
  "geometry": {"coordinates":[-76.836494,38.977854],"type":"Point"}
}