{
  "type": "Feature",
  "properties": {
    "addr:full":"13550 Forest Pl Hughesville MD 20637",
    "addr:housenumber":"13550",
    "addr:postcode":"20637",
    "addr:street":"Forest Pl",
    "iso:country":"US",
    "sg:address":"13550 Forest Pl",
    "sg:city":"Hughesville",
    "sg:classifiers":[
        {
            "category":"Real Estate",
            "subcategory":"Real Estate Agent",
            "type":"Services"
        },
        {
            "category":"Professional",
            "subcategory":"Business Services",
            "type":"Services"
        }
    ],
    "sg:phone":"+1 301 932 5881",
    "sg:postcode":"20637",
    "sg:province":"MD",
    "sg:tags":[
        "appraiser"
    ],
    "wof:name":"Signature Appraisal Services",
    "wof:placetype":"venue"
},
  "geometry": {"coordinates":[-76.84287999999999,38.505722],"type":"Point"}
}