{
  "type": "Feature",
  "properties": {
    "iso:country":"US",
    "sg:address":"9412 Woodington Dr",
    "sg:city":"Potomac",
    "sg:classifiers":[
        {
            "category":"Health Services",
            "subcategory":"Health Practitioner",
            "type":"Services"
        }
    ],
    "sg:phone":"+1 301 765 7615",
    "sg:postcode":"20854",
    "sg:province":"MD",
    "wof:name":"Rachel F Lenn",
    "wof:placetype":"venue"
},
  "geometry": {"coordinates":[-77.194429,39.041529],"type":"Point"}
}