{
  "type": "Feature",
  "properties": {
    "addr:full":"23277 Huckleberry Way Hollywood MD 20636",
    "addr:housenumber":"23277",
    "addr:postcode":"20636",
    "addr:street":"Huckleberry Way",
    "iso:country":"US",
    "sg:address":"23277 Huckleberry Way",
    "sg:city":"Hollywood",
    "sg:classifiers":[
        {
            "category":"Professional",
            "subcategory":"Business Services",
            "type":"Services"
        }
    ],
    "sg:phone":"+1 301 373 4200",
    "sg:postcode":"20636",
    "sg:province":"MD",
    "sg:tags":[
        "auctioneer"
    ],
    "wof:name":"Homestead Auction & Appraisal",
    "wof:placetype":"venue"
},
  "geometry": {"coordinates":[-76.56141599999999,38.317328],"type":"Point"}
}