{
  "type": "Feature",
  "properties": {
    "addr:full":"7210 Race Track Rd Bowie MD 20715",
    "addr:housenumber":"7210",
    "addr:postcode":"20715",
    "addr:street":"Race Track Rd",
    "iso:country":"US",
    "sg:address":"7210 Race Track Rd",
    "sg:city":"Bowie",
    "sg:classifiers":[
        {
            "category":"Place Of Worship",
            "subcategory":"Church",
            "type":"Public Place"
        },
        {
            "category":"Place Of Worship",
            "type":"Public Place"
        }
    ],
    "sg:phone":"+1 301 262 1767",
    "sg:postcode":"20715",
    "sg:province":"MD",
    "sg:tags":[
        "churches-baptist-general",
        "churches-baptist"
    ],
    "sg:website":"http://www.gracebaptist.org",
    "wof:name":"Board Of Trustees Of Grace Baptist Church",
    "wof:placetype":"venue"
},
  "geometry": {"coordinates":[-76.732427,38.988131],"type":"Point"}
}