{
  "type": "Feature",
  "properties": {
    "iso:country":"US",
    "sg:address":"4949 Beech Rd",
    "sg:city":"Temple Hills",
    "sg:classifiers":[
        {
            "category":"Building & Trades",
            "subcategory":"Construction",
            "type":"Services"
        }
    ],
    "sg:phone":"+1 301 292 4300",
    "sg:postcode":"20748",
    "sg:province":"MD",
    "sg:tags":[
        "general",
        "contractor"
    ],
    "wof:name":"Alpha Construction",
    "wof:placetype":"venue"
},
  "geometry": {"coordinates":[-76.937273,38.823089],"type":"Point"}
}