{
  "type": "Feature",
  "properties": {
    "iso:country":"US",
    "sg:address":"9644 Belair Rd",
    "sg:city":"Nottingham",
    "sg:classifiers":[
        {
            "category":"Bagels",
            "type":"Food & Drink"
        },
        {
            "category":"Coffee & Tea",
            "type":"Food & Drink"
        },
        {
            "category":"Food & Beverages",
            "subcategory":"Bakery",
            "type":"Retail Goods"
        },
        {
            "category":"Bakery",
            "type":"Food & Drink"
        },
        {
            "category":"Donuts",
            "type":"Food & Drink"
        }
    ],
    "sg:menulink":"http://www.allmenus.com/md/batter-brook-farms/148972-dunkin-donuts/menu/",
    "sg:phone":"+1 410 256 6652",
    "sg:postcode":"21236",
    "sg:province":"MD",
    "sg:tags":[
        "coffee",
        "sandwich",
        "tea",
        "american",
        "bagel",
        "bakery",
        "pastry",
        "wrap"
    ],
    "wof:name":"Dunkin' Donuts",
    "wof:placetype":"venue"
},
  "geometry": {"coordinates":[-76.46186,39.414812],"type":"Point"}
}