{
  "type": "Feature",
  "properties": {
    "iso:country":"US",
    "sg:address":"9512 Piscataway Rd",
    "sg:city":"Clinton",
    "sg:classifiers":[
        {
            "category":"Organizations",
            "subcategory":"Religious Organization",
            "type":"Services"
        }
    ],
    "sg:phone":"+1 301 868 5880",
    "sg:postcode":"20735",
    "sg:province":"MD",
    "sg:tags":[
        "church"
    ],
    "wof:name":"Greater Refuge Ministries Chr",
    "wof:placetype":"venue"
},
  "geometry": {"coordinates":[-76.91628300000001,38.76069],"type":"Point"}
}