{
  "type": "Feature",
  "properties": {
    "iso:country":"US",
    "sg:address":"1200 Baltimore Blvd",
    "sg:city":"Westminster",
    "sg:classifiers":[
        {
            "category":"Freight",
            "type":"Transportation"
        }
    ],
    "sg:phone":"+1 410 857 8080",
    "sg:postcode":"21157",
    "sg:province":"MD",
    "sg:tags":[
        "commercial",
        "storage"
    ],
    "wof:name":"E-Z Storage",
    "wof:placetype":"venue"
},
  "geometry": {"coordinates":[-76.953318,39.551876],"type":"Point"}
}