{
  "type": "Feature",
  "properties": {
    "addr:full":"8411 Old Marlboro Pike Upper Marlboro MD 20772",
    "addr:housenumber":"8411",
    "addr:postcode":"20772",
    "addr:street":"Old Marlboro Pike",
    "iso:country":"US",
    "sg:address":"8411 Old Marlboro Pike",
    "sg:city":"Upper Marlboro",
    "sg:classifiers":[
        {
            "category":"Wholesale",
            "subcategory":"Furniture",
            "type":"Manufacturing & Wholesale Goods"
        }
    ],
    "sg:phone":"+1 301 568 1343",
    "sg:postcode":"20772",
    "sg:province":"MD",
    "wof:name":"GMI",
    "wof:placetype":"venue"
},
  "geometry": {"coordinates":[-76.86113899999999,38.831957],"type":"Point"}
}