{
  "type": "Feature",
  "properties": {
    "iso:country":"US",
    "sg:address":"4530 Georgia Ave NW",
    "sg:city":"Washington",
    "sg:classifiers":[
        {
            "category":"Organizations",
            "subcategory":"Religious Organization",
            "type":"Services"
        }
    ],
    "sg:phone":"+1 202 723 3543",
    "sg:postcode":"20011",
    "sg:province":"MD",
    "sg:tags":[
        "clergy"
    ],
    "wof:name":"Bennie L Murphy",
    "wof:placetype":"venue"
},
  "geometry": {"coordinates":[-77.026613,38.945784],"type":"Point"}
}