{
  "type": "Feature",
  "properties": {
    "addr:full":"10012 Huxley Dr Lanham MD 20706",
    "addr:housenumber":"10012",
    "addr:postcode":"20706",
    "addr:street":"Huxley Dr",
    "iso:country":"US",
    "sg:address":"10012 Huxley Dr",
    "sg:city":"Lanham",
    "sg:classifiers":[
        {
            "category":"Professional",
            "type":"Services"
        }
    ],
    "sg:phone":"+1 301 731 1950",
    "sg:postcode":"20706",
    "sg:province":"MD",
    "sg:tags":[
        "establishment"
    ],
    "wof:name":"WHIZ Kidz",
    "wof:placetype":"venue"
},
  "geometry": {"coordinates":[-76.832652,38.975773],"type":"Point"}
}