{
  "type": "Feature",
  "properties": {
    "iso:country":"US",
    "sg:address":"1211 N Baltimore Ave",
    "sg:city":"Ocean City",
    "sg:classifiers":[
        {
            "category":"Real Estate",
            "subcategory":"Real Estate Operator",
            "type":"Services"
        }
    ],
    "sg:phone":"+1 410 289 7827",
    "sg:postcode":"21842",
    "sg:province":"MD",
    "sg:tags":[
        "apartment"
    ],
    "wof:name":"Ocean Terrace Apartments",
    "wof:placetype":"venue"
},
  "geometry": {"coordinates":[-75.079959,38.343283],"type":"Point"}
}