{
  "type": "Feature",
  "properties": {
    "addr:full":"1212 S Talbot St St Michaels MD 21663",
    "addr:housenumber":"1212",
    "addr:postcode":"21663",
    "addr:street":"S Talbot St",
    "iso:country":"US",
    "sg:address":"1212 S Talbot St",
    "sg:city":"St Michaels",
    "sg:classifiers":[
        {
            "category":"Food & Beverages",
            "subcategory":"Groceries & Convenience Stores",
            "type":"Retail Goods"
        }
    ],
    "sg:phone":"+1 410 745 3537",
    "sg:postcode":"21663",
    "sg:province":"MD",
    "sg:tags":[
        "market"
    ],
    "wof:name":"Clark's Supermarket Inc",
    "wof:placetype":"venue"
},
  "geometry": {"coordinates":[-76.208191,38.770901],"type":"Point"}
}