{
  "type": "Feature",
  "properties": {
    "iso:country":"US",
    "sg:address":"14760 Baltimore Ave",
    "sg:city":"Laurel",
    "sg:classifiers":[
        {
            "category":"Professional",
            "type":"Services"
        }
    ],
    "sg:phone":"+1 301 490 1781",
    "sg:postcode":"20707",
    "sg:province":"MD",
    "sg:tags":[
        "department",
        "store"
    ],
    "wof:name":"U S Vision",
    "wof:placetype":"venue"
},
  "geometry": {"coordinates":[-76.855301,39.093201],"type":"Point"}
}