{
  "type": "Feature",
  "properties": {
    "iso:country":"US",
    "sg:address":"936 Pointer Ridge Dr",
    "sg:city":"Gaithersburg",
    "sg:classifiers":[
        {
            "category":"Professional",
            "subcategory":"Management & Consulting",
            "type":"Services"
        }
    ],
    "sg:phone":"+1 301 977 6582",
    "sg:postcode":"20878",
    "sg:province":"MD",
    "sg:tags":[
        "business"
    ],
    "wof:name":"C D Rieg",
    "wof:placetype":"venue"
},
  "geometry": {"coordinates":[-77.23795,39.142948],"type":"Point"}
}