{
  "type": "Feature",
  "properties": {
    "iso:country":"US",
    "sg:address":"6421 Old Branch Ave",
    "sg:city":"Temple Hills",
    "sg:classifiers":[
        {
            "category":"Professional",
            "subcategory":"Accounting & Tax Preparation",
            "type":"Services"
        }
    ],
    "sg:phone":"+1 301 449 7511",
    "sg:postcode":"20748",
    "sg:province":"MD",
    "sg:tags":[
        "return",
        "filing"
    ],
    "wof:name":"Diamond Review & Assoc",
    "wof:placetype":"venue"
},
  "geometry": {"coordinates":[-76.904706,38.80132],"type":"Point"}
}