{
  "type": "Feature",
  "properties": {
    "iso:country":"US",
    "sg:address":"9 Newburg Ave",
    "sg:city":"Catonsville",
    "sg:classifiers":[
        {
            "category":"Building & Trades",
            "subcategory":"Construction",
            "type":"Services"
        }
    ],
    "sg:phone":"+1 410 788 3990",
    "sg:postcode":"21228",
    "sg:province":"MD",
    "sg:tags":[
        "contractor"
    ],
    "sg:website":"www.wall2wallconstruction.com",
    "wof:name":"Wall To Wall Construction Llc",
    "wof:placetype":"venue"
},
  "geometry": {"coordinates":[-76.735288,39.271004],"type":"Point"}
}