{
  "type": "Feature",
  "properties": {
    "iso:country":"US",
    "sg:address":"5755 CEDAR LN",
    "sg:city":"COLUMBIA",
    "sg:classifiers":[
        {
            "category":"Health Services",
            "subcategory":"Hospital",
            "type":"Services"
        },
        {
            "category":"Health Services",
            "subcategory":"Health Practitioner",
            "type":"Services"
        },
        {
            "category":"Health Services",
            "subcategory":"Clinic",
            "type":"Services"
        }
    ],
    "sg:phone":"+1 410 740 7890",
    "sg:postcode":"21044",
    "sg:province":"MD",
    "sg:tags":[
        "information",
        "drug",
        "alcoholism",
        "psychological",
        "abuse",
        "treatment",
        "surgery",
        "addiction",
        "rehabilitation"
    ],
    "sg:website":"http://www.howardjoblink.com",
    "wof:name":"Howard County General Hospital",
    "wof:placetype":"venue"
},
  "geometry": {"coordinates":[-76.88707700000001,39.21365],"type":"Point"}
}