{
  "type": "Feature",
  "properties": {
    "iso:country":"US",
    "sg:address":"25 N Chester St",
    "sg:city":"Baltimore",
    "sg:classifiers":[
        {
            "category":"Food & Beverages",
            "subcategory":"Groceries & Convenience Stores",
            "type":"Retail Goods"
        }
    ],
    "sg:phone":"+1 410 276 2529",
    "sg:postcode":"21231",
    "sg:province":"MD",
    "sg:tags":[
        "grocer"
    ],
    "wof:name":"Jo's Grocery Store",
    "wof:placetype":"venue"
},
  "geometry": {"coordinates":[-76.5877,39.292801],"type":"Point"}
}