{
  "type": "Feature",
  "properties": {
    "addr:full":"744 Dulaney Valley Rd Baltimore MD 21204",
    "addr:housenumber":"744",
    "addr:postcode":"21204",
    "addr:street":"Dulaney Valley Rd",
    "iso:country":"US",
    "sg:address":"744 Dulaney Valley Rd",
    "sg:city":"Baltimore",
    "sg:classifiers":[
        {
            "category":"Organizations",
            "subcategory":"Professional Association",
            "type":"Services"
        }
    ],
    "sg:phone":"+1 410 828 9526",
    "sg:postcode":"21204",
    "sg:province":"MD",
    "sg:website":"www.mdaap.org",
    "wof:name":"American Academy Of Pediatrics",
    "wof:placetype":"venue"
},
  "geometry": {"coordinates":[-76.602113,39.401896],"type":"Point"}
}