{
  "type": "Feature",
  "properties": {
    "addr:full":"723 Main St Reisterstown MD 21136",
    "addr:housenumber":"723",
    "addr:postcode":"21136",
    "addr:street":"Main St",
    "iso:country":"US",
    "sg:address":"723 Main St",
    "sg:city":"Reisterstown",
    "sg:classifiers":[
        {
            "category":"Home & Garden",
            "subcategory":"Home Furnishings",
            "type":"Retail Goods"
        }
    ],
    "sg:phone":"+1 410 526 2744",
    "sg:postcode":"21136",
    "sg:province":"MD",
    "sg:tags":[
        "venetian",
        "blind"
    ],
    "wof:name":"Window Wear & Walls",
    "wof:placetype":"venue"
},
  "geometry": {"coordinates":[-76.82007900000001,39.452008],"type":"Point"}
}