{
  "type": "Feature",
  "properties": {
    "iso:country":"US",
    "sg:address":"100 Holliday St Ste 204",
    "sg:city":"Baltimore",
    "sg:classifiers":[
        {
            "category":"Government",
            "subcategory":"Office",
            "type":"Public Place"
        }
    ],
    "sg:phone":"+1 410 396 4783",
    "sg:postcode":"21202",
    "sg:province":"MD",
    "sg:tags":[
        "township",
        "government-city",
        "village"
    ],
    "wof:name":"Baltimore City Audits",
    "wof:placetype":"venue"
},
  "geometry": {"coordinates":[-76.61022199999999,39.290501],"type":"Point"}
}