{
  "type": "Feature",
  "properties": {
    "addr:full":"1649 Elkton Rd Elkton MD 21921",
    "addr:housenumber":"1649",
    "addr:postcode":"21921",
    "addr:street":"Elkton Rd",
    "iso:country":"US",
    "sg:address":"1649 Elkton Rd",
    "sg:city":"Elkton",
    "sg:classifiers":[
        {
            "category":"Personal",
            "subcategory":"Beauty Salon",
            "type":"Services"
        },
        {
            "category":"Personal",
            "subcategory":"Tanning Parlor",
            "type":"Services"
        }
    ],
    "sg:phone":"+1 410 392 0074",
    "sg:postcode":"21921",
    "sg:province":"MD",
    "wof:name":"All About Details",
    "wof:placetype":"venue"
},
  "geometry": {"coordinates":[-75.79188600000001,39.651551],"type":"Point"}
}