{
  "type": "Feature",
  "properties": {
    "addr:full":"3601 Commerce Dr Halethorpe MD 21227",
    "addr:housenumber":"3601",
    "addr:postcode":"21227",
    "addr:street":"Commerce Dr",
    "iso:country":"US",
    "sg:address":"3601 Commerce Dr",
    "sg:city":"Halethorpe",
    "sg:classifiers":[
        {
            "category":"Organizations",
            "subcategory":"Religious Organization",
            "type":"Services"
        }
    ],
    "sg:phone":"+1 410 368 6004",
    "sg:postcode":"21227",
    "sg:province":"MD",
    "sg:tags":[
        "church"
    ],
    "wof:name":"RCCG House Of Glory",
    "wof:placetype":"venue"
},
  "geometry": {"coordinates":[-76.67364999999999,39.253287],"type":"Point"}
}