{
  "type": "Feature",
  "properties": {
    "iso:country":"US",
    "sg:address":"600 E Patapsco Ave",
    "sg:city":"Brooklyn",
    "sg:classifiers":[
        {
            "category":"Retail",
            "subcategory":"Car Wash",
            "type":"Services"
        }
    ],
    "sg:phone":"+1 410 355 0251",
    "sg:postcode":"21225",
    "sg:province":"MD",
    "sg:tags":[
        "automobile",
        "detail",
        "clean"
    ],
    "wof:name":"Ultimate Detailing",
    "wof:placetype":"venue"
},
  "geometry": {"coordinates":[-76.60333799999999,39.236637],"type":"Point"}
}