{
  "type": "Feature",
  "properties": {
    "addr:full":"13201 Dairymaid Dr Germantown MD 20874",
    "addr:housenumber":"13201",
    "addr:postcode":"20874",
    "addr:street":"Dairymaid Dr",
    "iso:country":"US",
    "sg:address":"13201 Dairymaid Dr",
    "sg:city":"Germantown",
    "sg:classifiers":[
        {
            "category":"Real Estate",
            "subcategory":"Real Estate Operator",
            "type":"Services"
        }
    ],
    "sg:phone":"+1 301 972 9899",
    "sg:postcode":"20874",
    "sg:province":"MD",
    "sg:tags":[
        "condominium"
    ],
    "wof:name":"Heritage Green Condominium",
    "wof:placetype":"venue"
},
  "geometry": {"coordinates":[-77.27425599999999,39.156885],"type":"Point"}
}