{
  "type": "Feature",
  "properties": {
    "iso:country":"US",
    "sg:address":"13201 Dairymaid Dr",
    "sg:city":"Germantown",
    "sg:classifiers":[
        {
            "category":"Real Estate",
            "subcategory":"Real Estate Operator",
            "type":"Services"
        }
    ],
    "sg:phone":"+1 301 972 9899",
    "sg:postcode":"20874",
    "sg:province":"MD",
    "sg:tags":[
        "condominium"
    ],
    "wof:name":"Heritage Green Condominium",
    "wof:placetype":"venue"
},
  "geometry": {"coordinates":[-77.274256,39.156885],"type":"Point"}
}