{
  "type": "Feature",
  "properties": {
    "addr:full":"7500 Woodmont Ave Bethesda MD 20814",
    "addr:housenumber":"7500",
    "addr:postcode":"20814",
    "addr:street":"Woodmont Ave",
    "iso:country":"US",
    "sg:address":"7500 Woodmont Ave",
    "sg:city":"Bethesda",
    "sg:classifiers":[
        {
            "category":"Building & Trades",
            "subcategory":"Locksmith",
            "type":"Services"
        }
    ],
    "sg:phone":"+1 240 383 5040",
    "sg:postcode":"20814",
    "sg:province":"MD",
    "sg:tags":[
        "key"
    ],
    "wof:name":"Emergency 24 Hour 7 Day Locksmith",
    "wof:placetype":"venue"
},
  "geometry": {"coordinates":[-77.096346,38.983403],"type":"Point"}
}