{
  "type": "Feature",
  "properties": {
    "addr:full":"4210 Harbour Town Dr Beltsville MD 20705",
    "addr:housenumber":"4210",
    "addr:postcode":"20705",
    "addr:street":"Harbour Town Dr",
    "iso:country":"US",
    "sg:address":"4210 Harbour Town Dr",
    "sg:city":"Beltsville",
    "sg:classifiers":[
        {
            "category":"Building & Trades",
            "subcategory":"Construction",
            "type":"Services"
        }
    ],
    "sg:phone":"+1 301 595 3899",
    "sg:postcode":"20705",
    "sg:province":"MD",
    "sg:tags":[
        "house"
    ],
    "wof:name":"NV Homes Maryland West",
    "wof:placetype":"venue"
},
  "geometry": {"coordinates":[-76.933145,39.065046],"type":"Point"}
}