{
  "type": "Feature",
  "properties": {
    "iso:country":"US",
    "sg:address":"525 Baltimore Annapolis Blvd",
    "sg:city":"Severna Park",
    "sg:classifiers":[
        {
            "category":"Restaurant",
            "type":"Food & Drink"
        }
    ],
    "sg:phone":"+1 410 544 0595",
    "sg:postcode":"21146",
    "sg:province":"MD",
    "wof:name":"Mc Donald's",
    "wof:placetype":"venue"
},
  "geometry": {"coordinates":[-76.548323,39.076288],"type":"Point"}
}