{
  "type": "Feature",
  "properties": {
    "addr:full":"1334 Ashton Rd Hanover MD 21076",
    "addr:housenumber":"1334",
    "addr:postcode":"21076",
    "addr:street":"Ashton Rd",
    "iso:country":"US",
    "sg:address":"1334 Ashton Rd",
    "sg:city":"Hanover",
    "sg:classifiers":[
        {
            "category":"Professional",
            "subcategory":"Engineering",
            "type":"Services"
        }
    ],
    "sg:phone":"+1 410 850 5000",
    "sg:postcode":"21076",
    "sg:province":"MD",
    "sg:tags":[
        "engineer"
    ],
    "sg:website":"www.saic.com",
    "wof:name":"Science Applications Intl Corp",
    "wof:placetype":"venue"
},
  "geometry": {"coordinates":[-76.70884599999999,39.161286],"type":"Point"}
}