{
  "type": "Feature",
  "properties": {
    "iso:country":"US",
    "sg:address":"12703 Sunset Ave",
    "sg:city":"Ocean City",
    "sg:classifiers":[
        {
            "category":"Shopping",
            "subcategory":"Used Merchandise",
            "type":"Retail Goods"
        }
    ],
    "sg:phone":"+1 410 213 4833",
    "sg:postcode":"21842",
    "sg:province":"MD",
    "sg:tags":[
        "antique"
    ],
    "sg:website":"www.upeweralley.com",
    "wof:name":"Up Ewer Alley",
    "wof:placetype":"venue"
},
  "geometry": {"coordinates":[-75.114453,38.32803],"type":"Point"}
}