{
  "type": "Feature",
  "properties": {
    "addr:full":"13431 McMullen Hwy SW Cumberland MD 21502",
    "addr:housenumber":"13431",
    "addr:postcode":"21502",
    "addr:street":"Mcmullen Hwy Sw",
    "iso:country":"US",
    "sg:address":"13431 McMullen Hwy SW",
    "sg:city":"Cumberland",
    "sg:classifiers":[
        {
            "category":"Building & Trades",
            "subcategory":"Construction",
            "type":"Services"
        }
    ],
    "sg:phone":"+1 301 729 2957",
    "sg:postcode":"21502",
    "sg:province":"MD",
    "sg:tags":[
        "hanging",
        "contractor"
    ],
    "wof:name":"Norris Jeffrey Painting Contr",
    "wof:placetype":"venue"
},
  "geometry": {"coordinates":[-78.80862500000001,39.611785],"type":"Point"}
}