{
  "type": "Feature",
  "properties": {
    "iso:country":"US",
    "sg:address":"2230 Cedar Barn Way",
    "sg:city":"Windsor Mill",
    "sg:classifiers":[
        {
            "category":"Shopping",
            "type":"Retail Goods"
        }
    ],
    "sg:phone":"+1 410 265 1185",
    "sg:postcode":"21244",
    "sg:province":"MD",
    "sg:tags":[
        "product",
        "wood"
    ],
    "wof:name":"Commercial Wood Finishing",
    "wof:placetype":"venue"
},
  "geometry": {"coordinates":[-76.77986,39.311625],"type":"Point"}
}