{
  "type": "Feature",
  "properties": {
    "addr:full":"12015 Rockville Pike D Rockville MD 20852",
    "addr:housenumber":"12015",
    "addr:postcode":"20852",
    "addr:street":"Rockville Pike",
    "iso:country":"US",
    "sg:address":"12015 Rockville Pike D",
    "sg:city":"Rockville",
    "sg:classifiers":[
        {
            "category":"Personal",
            "subcategory":"Beauty Salon",
            "type":"Services"
        }
    ],
    "sg:phone":"+1 301 881 8795",
    "sg:postcode":"20852",
    "sg:province":"MD",
    "wof:name":"Salon Vogue",
    "wof:placetype":"venue"
},
  "geometry": {"coordinates":[-77.11662,39.053221],"type":"Point"}
}