{
  "type": "Feature",
  "properties": {
    "iso:country":"US",
    "sg:address":"4201 Chapel Rd",
    "sg:city":"Perry Hall",
    "sg:classifiers":[
        {
            "category":"Banks & Credit Unions",
            "subcategory":"Bank",
            "type":"Services"
        }
    ],
    "sg:phone":"+1 410 256 7000",
    "sg:postcode":"21128",
    "sg:province":"MD",
    "wof:name":"Mercantile Mortgage Corporation",
    "wof:placetype":"venue"
},
  "geometry": {"coordinates":[-76.463898,39.4128],"type":"Point"}
}