{
  "type": "Feature",
  "properties": {
    "addr:full":"13424 Accent Way Germantown MD 20874",
    "addr:postcode":"13424;20874",
    "addr:street":"Accent Way",
    "iso:country":"US",
    "sg:address":"13424 Accent Way",
    "sg:city":"Germantown",
    "sg:classifiers":[
        {
            "category":"Building & Trades",
            "subcategory":"Landscaping Services",
            "type":"Services"
        }
    ],
    "sg:phone":"+1 301 916 0230",
    "sg:postcode":"20874",
    "sg:province":"MD",
    "sg:tags":[
        "lawn",
        "maintenance"
    ],
    "wof:name":"Talley Lawn Care",
    "wof:placetype":"venue"
},
  "geometry": {"coordinates":[-77.277537,39.167552],"type":"Point"}
}