{
  "type": "Feature",
  "properties": {
    "addr:full":"105 Evans Ave Grasonville MD 21638",
    "addr:housenumber":"105",
    "addr:postcode":"21638",
    "addr:street":"Evans Ave",
    "iso:country":"US",
    "sg:address":"105 Evans Ave",
    "sg:city":"Grasonville",
    "sg:classifiers":[
        {
            "category":"Recreation",
            "subcategory":"Marina",
            "type":"Entertainment"
        }
    ],
    "sg:phone":"+1 410 827 0276",
    "sg:postcode":"21638",
    "sg:province":"MD",
    "sg:tags":[
        "repairing",
        "boat"
    ],
    "wof:name":"Chesapeake Yacht Systems",
    "wof:placetype":"venue"
},
  "geometry": {"coordinates":[-76.19497,38.960316],"type":"Point"}
}