{
  "type": "Feature",
  "properties": {
    "addr:full":"100 Monoponsan Rd Stevensville MD 21666",
    "addr:housenumber":"100",
    "addr:postcode":"21666",
    "addr:street":"Monoponsan Rd",
    "iso:country":"US",
    "sg:address":"100 Monoponsan Rd",
    "sg:city":"Stevensville",
    "sg:classifiers":[
        {
            "category":"Shopping",
            "subcategory":"Clothing, Apparel, & Fashions",
            "type":"Retail Goods"
        }
    ],
    "sg:phone":"+1 410 643 2883",
    "sg:postcode":"21666",
    "sg:province":"MD",
    "sg:tags":[
        "garment"
    ],
    "wof:name":"Image First Pro Apparel",
    "wof:placetype":"venue"
},
  "geometry": {"coordinates":[-76.37295399999999,38.84155],"type":"Point"}
}