{
  "type": "Feature",
  "properties": {
    "iso:country":"US",
    "sg:address":"2323 Orleans St",
    "sg:city":"Baltimore",
    "sg:classifiers":[
        {
            "category":"Shopping",
            "subcategory":"Pharmacy",
            "type":"Retail Goods"
        }
    ],
    "sg:phone":"+1 410 732 7101",
    "sg:postcode":"21224",
    "sg:province":"MD",
    "sg:tags":[
        "drugstore"
    ],
    "wof:name":"Neighbor Care",
    "wof:placetype":"venue"
},
  "geometry": {"coordinates":[-76.584198,39.2957],"type":"Point"}
}