{
  "type": "Feature",
  "properties": {
    "addr:full":"608 Edmondson Ave Catonsville MD 21228",
    "addr:housenumber":"608",
    "addr:postcode":"21228",
    "addr:street":"Edmondson Ave",
    "iso:country":"US",
    "sg:address":"608 Edmondson Ave",
    "sg:city":"Catonsville",
    "sg:classifiers":[
        {
            "category":"Bars & Pubs",
            "type":"Food & Drink"
        },
        {
            "category":"Bars & Pubs",
            "subcategory":"Lounge",
            "type":"Food & Drink"
        },
        {
            "category":"Food & Beverages",
            "subcategory":"Liquor & Beverages",
            "type":"Retail Goods"
        },
        {
            "category":"Wholesale",
            "subcategory":"Wine & Distilled Alcoholic Beverages",
            "type":"Manufacturing & Wholesale Goods"
        }
    ],
    "sg:phone":"+1 410 747 2410",
    "sg:postcode":"21228",
    "sg:province":"MD",
    "sg:tags":[
        "liquors-wholesale",
        "beer",
        "store",
        "spirit",
        "cocktail"
    ],
    "wof:name":"Jin's Liquors",
    "wof:placetype":"venue"
},
  "geometry": {"coordinates":[-76.730904,39.278599],"type":"Point"}
}