{
  "type": "Feature",
  "properties": {
    "iso:country":"US",
    "sg:address":"6854 Race Track Rd",
    "sg:city":"Bowie",
    "sg:classifiers":[
        {
            "category":"Personal",
            "subcategory":"Beauty Salon",
            "type":"Services"
        }
    ],
    "sg:phone":"+1 301 352 8419",
    "sg:postcode":"20715",
    "sg:province":"MD",
    "sg:tags":[
        "nail",
        "manicuring"
    ],
    "wof:name":"Lt Nails",
    "wof:placetype":"venue"
},
  "geometry": {"coordinates":[-76.729145,38.98373],"type":"Point"}
}