{
  "type": "Feature",
  "properties": {
    "addr:full":"851 W Lexington St Baltimore MD 21201",
    "addr:housenumber":"851",
    "addr:postcode":"21201",
    "addr:street":"W Lexington St",
    "iso:country":"US",
    "sg:address":"851 W Lexington St",
    "sg:city":"Baltimore",
    "sg:classifiers":[
        {
            "category":"Real Estate",
            "subcategory":"Real Estate Operator",
            "type":"Services"
        }
    ],
    "sg:phone":"+1 410 669 6190",
    "sg:postcode":"21201",
    "sg:province":"MD",
    "sg:tags":[
        "apartment"
    ],
    "wof:name":"Poppleton Place Associates",
    "wof:placetype":"venue"
},
  "geometry": {"coordinates":[-76.63159899999999,39.291],"type":"Point"}
}