{
  "type": "Feature",
  "properties": {
    "addr:full":"29481 Laurwayn Dr Trappe MD 21673",
    "addr:postcode":"29481;21673",
    "addr:street":"Laurwayn Dr",
    "iso:country":"US",
    "sg:address":"29481 Laurwayn Dr",
    "sg:city":"Trappe",
    "sg:classifiers":[
        {
            "category":"Building & Trades",
            "subcategory":"Plumbing",
            "type":"Services"
        }
    ],
    "sg:phone":"+1 410 778 7373",
    "sg:postcode":"21673",
    "sg:province":"MD",
    "sg:tags":[
        "plumbing",
        "contractor"
    ],
    "wof:name":"Roto-Rooter Plumbing & Drain",
    "wof:placetype":"venue"
},
  "geometry": {"coordinates":[-76.055046,38.655145],"type":"Point"}
}