{
  "type": "Feature",
  "properties": {
    "addr:full":"264 Pumpkin Ct Severna Park MD 21146",
    "addr:housenumber":"264",
    "addr:postcode":"21146",
    "addr:street":"Pumpkin Ct",
    "iso:country":"US",
    "sg:address":"264 Pumpkin Ct",
    "sg:city":"Severna Park",
    "sg:classifiers":[
        {
            "category":"Wholesale",
            "subcategory":"Stationery",
            "type":"Manufacturing & Wholesale Goods"
        }
    ],
    "sg:phone":"+1 410 975 0914",
    "sg:postcode":"21146",
    "sg:province":"MD",
    "sg:tags":[
        "supply"
    ],
    "wof:name":"Scraps & Stuff",
    "wof:placetype":"venue"
},
  "geometry": {"coordinates":[-76.53985400000001,39.099904],"type":"Point"}
}