{
  "type": "Feature",
  "properties": {
    "addr:full":"18 Betlou James Pl Gwynn Oak MD 21207",
    "addr:housenumber":"18",
    "addr:postcode":"21207",
    "addr:street":"Betlou James Pl",
    "iso:country":"US",
    "sg:address":"18 Betlou James Pl",
    "sg:city":"Gwynn Oak",
    "sg:classifiers":[
        {
            "category":"Wholesale",
            "subcategory":"Durable Goods & Equipment",
            "type":"Manufacturing & Wholesale Goods"
        }
    ],
    "sg:phone":"+1 410 265 6373",
    "sg:postcode":"21207",
    "sg:province":"MD",
    "sg:tags":[
        "job",
        "lot",
        "merchandise"
    ],
    "wof:name":"Douglas Richburg Co",
    "wof:placetype":"venue"
},
  "geometry": {"coordinates":[-76.738668,39.336759],"type":"Point"}
}