{
  "type": "Feature",
  "properties": {
    "addr:full":"3825 Dupont Ave Kensington MD 20895",
    "addr:housenumber":"3825",
    "addr:postcode":"20895",
    "addr:street":"Dupont Ave",
    "iso:country":"US",
    "sg:address":"3825 Dupont Ave",
    "sg:city":"Kensington",
    "sg:classifiers":[
        {
            "category":"Autos & Motor Vehicles",
            "subcategory":"Fuel & Gas Station",
            "type":"Retail Goods"
        },
        {
            "category":"Retail",
            "subcategory":"Auto Repair",
            "type":"Services"
        }
    ],
    "sg:phone":"+1 301 933 0330",
    "sg:postcode":"20895",
    "sg:province":"MD",
    "sg:website":"www.gauchoautorepair.com",
    "wof:name":"Gaucho Auto Repair Inc",
    "wof:placetype":"venue"
},
  "geometry": {"coordinates":[-77.07592,39.031061],"type":"Point"}
}