{
  "type": "Feature",
  "properties": {
    "iso:country":"US",
    "sg:address":"5417 Powhatan St",
    "sg:city":"Riverdale",
    "sg:classifiers":[
        {
            "category":"Building & Trades",
            "subcategory":"Plumbing",
            "type":"Services"
        }
    ],
    "sg:phone":"+1 301 277 3900",
    "sg:postcode":"20737",
    "sg:province":"MD",
    "wof:name":"Caywood Plumbing Services",
    "wof:placetype":"venue"
},
  "geometry": {"coordinates":[-76.922262,38.960134],"type":"Point"}
}