{
  "type": "Feature",
  "properties": {
    "addr:full":"1429 Duckens St Odenton MD 21113",
    "addr:housenumber":"1429",
    "addr:postcode":"21113",
    "addr:street":"Duckens St",
    "iso:country":"US",
    "sg:address":"1429 Duckens St",
    "sg:city":"Odenton",
    "sg:classifiers":[
        {
            "category":"Building & Trades",
            "subcategory":"Electrical",
            "type":"Services"
        }
    ],
    "sg:phone":"+1 410 551 7331",
    "sg:postcode":"21113",
    "sg:province":"MD",
    "sg:tags":[
        "electric",
        "contractor"
    ],
    "wof:name":"L & C Electric",
    "wof:placetype":"venue"
},
  "geometry": {"coordinates":[-76.71065,39.089544],"type":"Point"}
}