{
  "type": "Feature",
  "properties": {
    "addr:full":"8808 Centre Park Dr Columbia MD 21045",
    "addr:housenumber":"8808",
    "addr:postcode":"21045",
    "addr:street":"Centre Park Dr",
    "iso:country":"US",
    "sg:address":"8808 Centre Park Dr",
    "sg:city":"Columbia",
    "sg:phone":"+1 410 997 3560",
    "sg:postcode":"21045",
    "sg:province":"MD",
    "sg:website":"http://www.cafedepariscolumbia.com",
    "wof:name":"Cafe De Paris",
    "wof:placetype":"venue"
},
  "geometry": {"coordinates":[-76.814291,39.227471],"type":"Point"}
}