{
  "type": "Feature",
  "properties": {
    "iso:country":"US",
    "sg:address":"1755 Monkton Farms Dr",
    "sg:city":"Monkton",
    "sg:classifiers":[
        {
            "category":"Shopping",
            "subcategory":"Computers & Home Electronics",
            "type":"Retail Goods"
        }
    ],
    "sg:phone":"+1 410 472 4769",
    "sg:postcode":"21111",
    "sg:province":"MD",
    "sg:tags":[
        "software"
    ],
    "sg:website":"www.sigmasix.com",
    "wof:name":"Sigma Six Corp",
    "wof:placetype":"venue"
},
  "geometry": {"coordinates":[-76.619135,39.559481],"type":"Point"}
}