{
  "type": "Feature",
  "properties": {
    "addr:full":"2702 Coriander Pl Edgewater MD 21037",
    "addr:housenumber":"2702",
    "addr:postcode":"21037",
    "addr:street":"Coriander Pl",
    "iso:country":"US",
    "sg:address":"2702 Coriander Pl",
    "sg:city":"Edgewater",
    "sg:classifiers":[
        {
            "category":"Professional",
            "subcategory":"Management & Consulting",
            "type":"Services"
        }
    ],
    "sg:phone":"+1 410 224 2653",
    "sg:postcode":"21037",
    "sg:province":"MD",
    "sg:tags":[
        "consultant"
    ],
    "wof:name":"Dennis H & Shirley A Parkinson",
    "wof:placetype":"venue"
},
  "geometry": {"coordinates":[-76.550461,38.9681],"type":"Point"}
}