{
  "type": "Feature",
  "properties": {
    "addr:full":"17313 Founders Mill Dr Derwood MD 20855",
    "addr:housenumber":"17313",
    "addr:postcode":"20855",
    "addr:street":"Founders Mill Dr",
    "iso:country":"US",
    "sg:address":"17313 Founders Mill Dr",
    "sg:city":"Derwood",
    "sg:classifiers":[
        {
            "category":"Education",
            "subcategory":"Special Training",
            "type":"Public Place"
        }
    ],
    "sg:phone":"+1 301 840 0629",
    "sg:postcode":"20855",
    "sg:province":"MD",
    "sg:tags":[
        "language"
    ],
    "wof:name":"Doris T Yee",
    "wof:placetype":"venue"
},
  "geometry": {"coordinates":[-77.151112,39.138379],"type":"Point"}
}