{
  "type": "Feature",
  "properties": {
    "iso:country":"US",
    "sg:address":"502 Washington Ave",
    "sg:city":"Towson",
    "sg:phone":"+1 410 321 0600",
    "sg:postcode":"21204",
    "sg:province":"MD",
    "wof:name":"Sandier Andrew R",
    "wof:placetype":"venue"
},
  "geometry": {"coordinates":[-76.605244,39.400783],"type":"Point"}
}