{
  "type": "Feature",
  "properties": {
    "iso:country":"US",
    "sg:address":"2945 Mozart Dr",
    "sg:city":"Silver Spring",
    "sg:classifiers":[
        {
            "category":"Professional",
            "subcategory":"Management & Consulting",
            "type":"Services"
        }
    ],
    "sg:phone":"+1 301 572 7474",
    "sg:postcode":"20904",
    "sg:province":"MD",
    "sg:tags":[
        "business"
    ],
    "wof:name":"Jackson Consulting",
    "wof:placetype":"venue"
},
  "geometry": {"coordinates":[-76.95114100000001,39.071513],"type":"Point"}
}