{
  "type": "Feature",
  "properties": {
    "addr:full":"1009 Old Eastern Ave Essex MD 21221",
    "addr:housenumber":"1009",
    "addr:postcode":"21221",
    "addr:street":"Old Eastern Ave",
    "iso:country":"US",
    "sg:address":"1009 Old Eastern Ave",
    "sg:city":"Essex",
    "sg:classifiers":[
        {
            "category":"Food & Beverages",
            "subcategory":"Groceries & Convenience Stores",
            "type":"Retail Goods"
        }
    ],
    "sg:phone":"+1 410 238 4150",
    "sg:postcode":"21221",
    "sg:province":"MD",
    "wof:name":"Latin American Store Inc",
    "wof:placetype":"venue"
},
  "geometry": {"coordinates":[-76.463173,39.312775],"type":"Point"}
}