{
  "type": "Feature",
  "properties": {
    "addr:full":"4910 Massachusetts Ave NW Washington MD 20016",
    "addr:housenumber":"4910",
    "addr:postcode":"20016",
    "addr:street":"Massachusetts Ave Nw",
    "iso:country":"US",
    "sg:address":"4910 Massachusetts Ave NW",
    "sg:city":"Washington",
    "sg:classifiers":[
        {
            "category":"Health Services",
            "subcategory":"Doctor",
            "type":"Services"
        }
    ],
    "sg:phone":"+1 202 686 6700",
    "sg:postcode":"20016",
    "sg:province":"MD",
    "sg:tags":[
        "physician",
        "surgeon"
    ],
    "wof:name":"Eye Associates Of Wash DC",
    "wof:placetype":"venue"
},
  "geometry": {"coordinates":[-77.09840800000001,38.946935],"type":"Point"}
}