{
  "type": "Feature",
  "properties": {
    "iso:country":"US",
    "sg:address":"801 Compass Way",
    "sg:city":"Annapolis",
    "sg:classifiers":[
        {
            "category":"Retail",
            "subcategory":"Portrait Studio",
            "type":"Services"
        }
    ],
    "sg:phone":"+1 410 224 6049",
    "sg:postcode":"21401",
    "sg:province":"MD",
    "sg:tags":[
        "photographer"
    ],
    "sg:website":"www.daphoto.com",
    "wof:name":"David Anderson Photography",
    "wof:placetype":"venue"
},
  "geometry": {"coordinates":[-76.58913,38.976392],"type":"Point"}
}