{
  "type": "Feature",
  "properties": {
    "iso:country":"US",
    "sg:address":"110 Market St",
    "sg:city":"Denton",
    "sg:classifiers":[
        {
            "category":"Real Estate",
            "subcategory":"Real Estate Agent",
            "type":"Services"
        }
    ],
    "sg:phone":"+1 410 479 9729",
    "sg:postcode":"21629",
    "sg:province":"MD",
    "wof:name":"Sunset Properties",
    "wof:placetype":"venue"
},
  "geometry": {"coordinates":[-75.833966,38.886692],"type":"Point"}
}