{
  "type": "Feature",
  "properties": {
    "iso:country":"US",
    "sg:address":"1221 Devere Dr",
    "sg:city":"Silver Spring",
    "sg:classifiers":[
        {
            "category":"Professional",
            "type":"Services"
        }
    ],
    "sg:phone":"+1 301 439 8601",
    "sg:postcode":"20903",
    "sg:province":"MD",
    "wof:name":"Dan B Lane",
    "wof:placetype":"venue"
},
  "geometry": {"coordinates":[-76.98553200000001,39.020736],"type":"Point"}
}