{
  "type": "Feature",
  "properties": {
    "iso:country":"US",
    "sg:address":"120 Chester Station Ln",
    "sg:city":"Chester",
    "sg:classifiers":[
        {
            "category":"Autos & Motor Vehicles",
            "subcategory":"Fuel & Gas Station",
            "type":"Retail Goods"
        }
    ],
    "sg:phone":"+1 410 604 0478",
    "sg:postcode":"21619",
    "sg:province":"MD",
    "sg:tags":[
        "oil"
    ],
    "wof:name":"Chester Exxon",
    "wof:placetype":"venue"
},
  "geometry": {"coordinates":[-76.28114,38.976474],"type":"Point"}
}