{
  "type": "Feature",
  "properties": {
    "iso:country":"US",
    "sg:address":"8684 Mitchell Rd",
    "sg:city":"Denton",
    "sg:classifiers":[
        {
            "category":"Personal",
            "type":"Services"
        },
        {
            "category":"Autos & Motor Vehicles",
            "subcategory":"Auto Supplies",
            "type":"Retail Goods"
        },
        {
            "category":"Retail",
            "subcategory":"Auto Repair",
            "type":"Services"
        }
    ],
    "sg:phone":"+1 410 479 3303",
    "sg:postcode":"21629",
    "sg:province":"MD",
    "sg:tags":[
        "recap",
        "towing",
        "retread",
        "tire"
    ],
    "wof:name":"Team Tire Service",
    "wof:placetype":"venue"
},
  "geometry": {"coordinates":[-75.80181399999999,38.846064],"type":"Point"}
}