{
  "type": "Feature",
  "properties": {
    "iso:country":"US",
    "sg:address":"11800 Cherry Hill Rd",
    "sg:city":"Silver Spring",
    "sg:classifiers":[
        {
            "category":"Professional",
            "subcategory":"Art Services",
            "type":"Services"
        }
    ],
    "sg:phone":"+1 301 937 6977",
    "sg:postcode":"20904",
    "sg:province":"MD",
    "sg:tags":[
        "commercial",
        "design"
    ],
    "wof:name":"Joanna",
    "wof:placetype":"venue"
},
  "geometry": {"coordinates":[-76.952972,39.051891],"type":"Point"}
}