{
  "type": "Feature",
  "properties": {
    "addr:full":"901 Dundalk Ave Baltimore MD 21224",
    "addr:housenumber":"901",
    "addr:postcode":"21224",
    "addr:street":"Dundalk Ave",
    "iso:country":"US",
    "sg:address":"901 Dundalk Ave",
    "sg:city":"Baltimore",
    "sg:classifiers":[
        {
            "category":"Personal",
            "type":"Services"
        },
        {
            "category":"Retail",
            "subcategory":"Auto Repair",
            "type":"Services"
        }
    ],
    "sg:phone":"+1 410 633 5900",
    "sg:postcode":"21224",
    "sg:province":"MD",
    "sg:tags":[
        "towing"
    ],
    "wof:name":"Eastern Auto and Inspection",
    "wof:placetype":"venue"
},
  "geometry": {"coordinates":[-76.5373,39.283798],"type":"Point"}
}