{
  "type": "Feature",
  "properties": {
    "addr:full":"14211 McMullen Hwy SW Cumberland MD 21502",
    "addr:housenumber":"14211",
    "addr:postcode":"21502",
    "addr:street":"Mcmullen Hwy Sw",
    "iso:country":"US",
    "sg:address":"14211 McMullen Hwy SW",
    "sg:city":"Cumberland",
    "sg:classifiers":[
        {
            "category":"Organizations",
            "subcategory":"Community Association",
            "type":"Services"
        }
    ],
    "sg:phone":"+1 301 689 6602",
    "sg:postcode":"21502",
    "sg:province":"MD",
    "sg:tags":[
        "club"
    ],
    "wof:name":"Maplehurst Country Club Pro",
    "wof:placetype":"venue"
},
  "geometry": {"coordinates":[-78.81983200000001,39.607062],"type":"Point"}
}