{
  "type": "Feature",
  "properties": {
    "addr:full":"528 Hilton Ave Catonsville MD 21228",
    "addr:housenumber":"528",
    "addr:postcode":"21228",
    "addr:street":"Hilton Ave",
    "iso:country":"US",
    "sg:address":"528 Hilton Ave",
    "sg:city":"Catonsville",
    "sg:classifiers":[
        {
            "category":"Building & Trades",
            "subcategory":"Construction",
            "type":"Services"
        }
    ],
    "sg:phone":"+1 410 747 0958",
    "sg:postcode":"21228",
    "sg:province":"MD",
    "sg:tags":[
        "waterproofing",
        "contractor"
    ],
    "wof:name":"Budget Basement Waterproofing",
    "wof:placetype":"venue"
},
  "geometry": {"coordinates":[-76.74368200000001,39.257981],"type":"Point"}
}