{
  "type": "Feature",
  "properties": {
    "iso:country":"US",
    "sg:address":"918 National Hwy",
    "sg:city":"Cumberland",
    "sg:classifiers":[
        {
            "category":"Retail",
            "subcategory":"Laundry & Dry Cleaning",
            "type":"Services"
        }
    ],
    "sg:phone":"+1 301 729 2000",
    "sg:postcode":"21502",
    "sg:province":"MD",
    "sg:tags":[
        "cleaners"
    ],
    "wof:name":"Footers Drive-In Cleaners",
    "wof:placetype":"venue"
},
  "geometry": {"coordinates":[-78.821213,39.645621],"type":"Point"}
}