{
  "type": "Feature",
  "properties": {
    "addr:full":"1826 W Pratt St Baltimore MD 21223",
    "addr:housenumber":"1826",
    "addr:postcode":"21223",
    "addr:street":"W Pratt St",
    "iso:country":"US",
    "sg:address":"1826 W Pratt St",
    "sg:city":"Baltimore",
    "sg:classifiers":[
        {
            "category":"Restaurant",
            "type":"Food & Drink"
        }
    ],
    "sg:phone":"+1 410 945 0980",
    "sg:postcode":"21223",
    "sg:province":"MD",
    "sg:tags":[
        "chinese"
    ],
    "wof:name":"Lucky Express",
    "wof:placetype":"venue"
},
  "geometry": {"coordinates":[-76.645911,39.285296],"type":"Point"}
}