{
  "type": "Feature",
  "properties": {
    "addr:full":"12124 Central Ave Mitchellville MD 20721",
    "addr:housenumber":"12124",
    "addr:postcode":"20721",
    "addr:street":"Central Ave",
    "iso:country":"US",
    "sg:address":"12124 Central Ave",
    "sg:city":"Mitchellville",
    "sg:classifiers":[
        {
            "category":"Personal",
            "subcategory":"Beauty Salon",
            "type":"Services"
        }
    ],
    "sg:phone":"+1 301 249 6805",
    "sg:postcode":"20721",
    "sg:province":"MD",
    "wof:name":"Shazzi Beauty Salon",
    "wof:placetype":"venue"
},
  "geometry": {"coordinates":[-76.798727,38.899166],"type":"Point"}
}