{
  "type": "Feature",
  "properties": {
    "iso:country":"US",
    "sg:address":"9210 Corporate Blvd",
    "sg:city":"Rockville",
    "sg:classifiers":[
        {
            "category":"Professional",
            "subcategory":"Research",
            "type":"Services"
        }
    ],
    "sg:phone":"+1 301 330 7133",
    "sg:postcode":"20850",
    "sg:province":"MD",
    "sg:tags":[
        "laboratory"
    ],
    "wof:name":"Doctors Vascular Laboratory",
    "wof:placetype":"venue"
},
  "geometry": {"coordinates":[-77.19169599999999,39.107311],"type":"Point"}
}