{
  "type": "Feature",
  "properties": {
    "iso:country":"US",
    "sg:address":"9219 Gross Ave",
    "sg:city":"Laurel",
    "sg:classifiers":[
        {
            "category":"Professional",
            "subcategory":"Management & Consulting",
            "type":"Services"
        }
    ],
    "sg:phone":"+1 301 776 6509",
    "sg:postcode":"20723",
    "sg:province":"MD",
    "sg:tags":[
        "communications",
        "product",
        "marketing"
    ],
    "wof:name":"Cimperium LLC",
    "wof:placetype":"venue"
},
  "geometry": {"coordinates":[-76.85833,39.116355],"type":"Point"}
}