{
  "type": "Feature",
  "properties": {
    "iso:country":"US",
    "sg:address":"4712 Greenspring Ave A1",
    "sg:city":"Baltimore",
    "sg:classifiers":[
        {
            "category":"Wholesale",
            "subcategory":"Books, Periodicals, & Newspapers",
            "type":"Manufacturing & Wholesale Goods"
        }
    ],
    "sg:phone":"+1 410 542 0156",
    "sg:postcode":"21209",
    "sg:province":"MD",
    "sg:tags":[
        "publisher",
        "book"
    ],
    "wof:name":"Education Rasberry Press",
    "wof:placetype":"venue"
},
  "geometry": {"coordinates":[-76.658991,39.344554],"type":"Point"}
}