{
  "type": "Feature",
  "properties": {
    "addr:full":"5317 Ritchie Hwy Brooklyn MD 21225",
    "addr:housenumber":"5317",
    "addr:postcode":"21225",
    "addr:street":"Ritchie Hwy",
    "iso:country":"US",
    "sg:address":"5317 Ritchie Hwy",
    "sg:city":"Brooklyn",
    "sg:classifiers":[
        {
            "category":"Restaurant",
            "type":"Food & Drink"
        }
    ],
    "sg:phone":"+1 410 354 0491",
    "sg:postcode":"21225",
    "sg:province":"MD",
    "wof:name":"Charles Brothers Inc",
    "wof:placetype":"venue"
},
  "geometry": {"coordinates":[-76.613899,39.222198],"type":"Point"}
}