{
  "type": "Feature",
  "properties": {
    "addr:full":"7918 Kings Bench Pl Pasadena MD 21122",
    "addr:housenumber":"7918",
    "addr:postcode":"21122",
    "addr:street":"Kings Bench Pl",
    "iso:country":"US",
    "sg:address":"7918 Kings Bench Pl",
    "sg:city":"Pasadena",
    "sg:classifiers":[
        {
            "category":"Social Services",
            "type":"Services"
        },
        {
            "category":"Professional",
            "subcategory":"Employment Agencies",
            "type":"Services"
        }
    ],
    "sg:phone":"+1 410 360 9145",
    "sg:postcode":"21122",
    "sg:province":"MD",
    "sg:tags":[
        "workers'",
        "placement",
        "volunteer"
    ],
    "wof:name":"International Assoc Of Li",
    "wof:placetype":"venue"
},
  "geometry": {"coordinates":[-76.534195,39.138434],"type":"Point"}
}