{
  "type": "Feature",
  "properties": {
    "iso:country":"US",
    "sg:address":"8226 Pulaski Hwy",
    "sg:city":"Baltimore",
    "sg:classifiers":[
        {
            "category":"Food & Beverages",
            "subcategory":"Liquor & Beverages",
            "type":"Retail Goods"
        }
    ],
    "sg:phone":"+1 410 686 2770",
    "sg:postcode":"21237",
    "sg:province":"MD",
    "sg:website":"www.kingliquors.com",
    "wof:name":"King's Liquors",
    "wof:placetype":"venue"
},
  "geometry": {"coordinates":[-76.505726,39.321807],"type":"Point"}
}