{
  "type": "Feature",
  "properties": {
    "addr:full":"10421 Armory Ave Kensington MD 20895",
    "addr:housenumber":"10421",
    "addr:postcode":"20895",
    "addr:street":"Armory Ave",
    "iso:country":"US",
    "sg:address":"10421 Armory Ave",
    "sg:city":"Kensington",
    "sg:classifiers":[
        {
            "category":"Professional",
            "subcategory":"Art Services",
            "type":"Services"
        }
    ],
    "sg:phone":"+1 301 933 8473",
    "sg:postcode":"20895",
    "sg:province":"MD",
    "sg:tags":[
        "photographer"
    ],
    "wof:name":"Mark Gregory Photography LLC",
    "wof:placetype":"venue"
},
  "geometry": {"coordinates":[-77.074607,39.027999],"type":"Point"}
}