{
  "type": "Feature",
  "properties": {
    "addr:full":"3110 River Bend Ct Laurel MD 20724",
    "addr:housenumber":"3110",
    "addr:postcode":"20724",
    "addr:street":"River Bend Ct",
    "iso:country":"US",
    "sg:address":"3110 River Bend Ct",
    "sg:city":"Laurel",
    "sg:classifiers":[
        {
            "category":"Building & Trades",
            "subcategory":"Cleaning & Sanitation",
            "type":"Services"
        }
    ],
    "sg:phone":"+1 301 953 3634",
    "sg:postcode":"20724",
    "sg:province":"MD",
    "wof:name":"Offers Cleaning Service",
    "wof:placetype":"venue"
},
  "geometry": {"coordinates":[-76.80712,39.110987],"type":"Point"}
}