{
  "type": "Feature",
  "properties": {
    "iso:country":"US",
    "sg:address":"5 N Frederick Ave",
    "sg:city":"Gaithersburg",
    "sg:classifiers":[
        {
            "category":"Professional",
            "type":"Services"
        }
    ],
    "sg:phone":"+1 301 208 9400",
    "sg:postcode":"20877",
    "sg:province":"MD",
    "wof:name":"Home Crafters",
    "wof:placetype":"venue"
},
  "geometry": {"coordinates":[-77.19926,39.14152],"type":"Point"}
}