{
  "type": "Feature",
  "properties": {
    "iso:country":"US",
    "sg:address":"304 Delaware Rd",
    "sg:city":"Frederick",
    "sg:classifiers":[
        {
            "category":"Insurance",
            "subcategory":"Hazard Insurance",
            "type":"Services"
        },
        {
            "category":"Insurance",
            "subcategory":"Life Insurance",
            "type":"Services"
        },
        {
            "category":"Banks & Credit Unions",
            "subcategory":"Financial Services",
            "type":"Services"
        }
    ],
    "sg:phone":"+1 301 662 8141",
    "sg:postcode":"21701",
    "sg:province":"MD",
    "sg:tags":[
        "annuity",
        "retirement",
        "commercial",
        "plan",
        "business"
    ],
    "wof:name":"Carey & Associates",
    "wof:placetype":"venue"
},
  "geometry": {"coordinates":[-77.40302200000001,39.427869],"type":"Point"}
}