{
  "type": "Feature",
  "properties": {
    "iso:country":"US",
    "sg:address":"11401 Coastal Hwy",
    "sg:city":"Ocean City",
    "sg:classifiers":[
        {
            "category":"Food & Beverages",
            "subcategory":"Liquor & Beverages",
            "type":"Retail Goods"
        }
    ],
    "sg:phone":"+1 410 524 9463",
    "sg:postcode":"21842",
    "sg:province":"MD",
    "sg:tags":[
        "beer",
        "ale"
    ],
    "wof:name":"Goldcoast Beer & Wine",
    "wof:placetype":"venue"
},
  "geometry": {"coordinates":[-75.056901,38.419732],"type":"Point"}
}