{
  "type": "Feature",
  "properties": {
    "iso:country":"US",
    "sg:address":"5 Brit Oak Ct",
    "sg:city":"Parkville",
    "sg:classifiers":[
        {
            "category":"Building & Trades",
            "subcategory":"Construction",
            "type":"Services"
        }
    ],
    "sg:phone":"+1 410 882 0921",
    "sg:postcode":"21234",
    "sg:province":"MD",
    "sg:tags":[
        "concrete",
        "contractor"
    ],
    "wof:name":"Artistic Stamped Concrete",
    "wof:placetype":"venue"
},
  "geometry": {"coordinates":[-76.501746,39.401493],"type":"Point"}
}