{
  "type": "Feature",
  "properties": {
    "addr:full":"5554 Randolph Rd Rockville MD 20852",
    "addr:housenumber":"5554",
    "addr:postcode":"20852",
    "addr:street":"Randolph Rd",
    "iso:country":"US",
    "sg:address":"5554 Randolph Rd",
    "sg:city":"Rockville",
    "sg:classifiers":[
        {
            "category":"Banks & Credit Unions",
            "subcategory":"Bank",
            "type":"Services"
        }
    ],
    "sg:phone":"+1 301 984 0267",
    "sg:postcode":"20852",
    "sg:province":"MD",
    "wof:name":"Maryland National Bank",
    "wof:placetype":"venue"
},
  "geometry": {"coordinates":[-77.113038,39.053184],"type":"Point"}
}