{
  "type": "Feature",
  "properties": {
    "iso:country":"US",
    "sg:address":"3355 Lowman Ln",
    "sg:city":"Union Bridge",
    "sg:classifiers":[
        {
            "category":"Manufacturing",
            "subcategory":"Chemicals & Compounds",
            "type":"Manufacturing & Wholesale Goods"
        }
    ],
    "sg:phone":"+1 410 635 6031",
    "sg:postcode":"21791",
    "sg:province":"MD",
    "sg:tags":[
        "compliance"
    ],
    "wof:name":"Edward Kuntze",
    "wof:placetype":"venue"
},
  "geometry": {"coordinates":[-77.122294,39.577105],"type":"Point"}
}