{
  "type": "Feature",
  "properties": {
    "addr:full":"15 N Centre St Cumberland MD 21502",
    "addr:housenumber":"15",
    "addr:postcode":"21502",
    "addr:street":"N Centre St",
    "iso:country":"US",
    "sg:address":"15 N Centre St",
    "sg:city":"Cumberland",
    "sg:classifiers":[
        {
            "category":"Shopping",
            "subcategory":"Books",
            "type":"Retail Goods"
        }
    ],
    "sg:phone":"+1 301 722 2284",
    "sg:postcode":"21502",
    "sg:province":"MD",
    "sg:tags":[
        "dealer"
    ],
    "wof:name":"Book Center",
    "wof:placetype":"venue"
},
  "geometry": {"coordinates":[-78.76179399999999,39.6526],"type":"Point"}
}