{
  "type": "Feature",
  "properties": {
    "addr:full":"10147 Colesville Rd Silver Spring MD 20901",
    "addr:housenumber":"10147",
    "addr:postcode":"20901",
    "addr:street":"Colesville Rd",
    "iso:country":"US",
    "sg:address":"10147 Colesville Rd",
    "sg:city":"Silver Spring",
    "sg:classifiers":[
        {
            "category":"Home & Garden",
            "subcategory":"Garden Supply",
            "type":"Retail Goods"
        }
    ],
    "sg:phone":"+1 301 681 4077",
    "sg:postcode":"20901",
    "sg:province":"MD",
    "sg:tags":[
        "house",
        "bird",
        "feeder"
    ],
    "wof:name":"Wild Bird Ctr",
    "wof:placetype":"venue"
},
  "geometry": {"coordinates":[-77.01212,39.02096],"type":"Point"}
}