{
  "type": "Feature",
  "properties": {
    "addr:full":"120 S Rolling Rd Catonsville MD 21228",
    "addr:housenumber":"120",
    "addr:postcode":"21228",
    "addr:street":"S Rolling Rd",
    "iso:country":"US",
    "sg:address":"120 S Rolling Rd",
    "sg:city":"Catonsville",
    "sg:classifiers":[
        {
            "category":"Education",
            "subcategory":"Preschool",
            "type":"Public Place"
        }
    ],
    "sg:phone":"+1 410 812 1689",
    "sg:postcode":"21228",
    "sg:province":"MD",
    "sg:tags":[
        "school",
        "nursery"
    ],
    "wof:name":"Abbott Memorial Nursery School",
    "wof:placetype":"venue"
},
  "geometry": {"coordinates":[-76.742876,39.266262],"type":"Point"}
}