{
  "type": "Feature",
  "properties": {
    "iso:country":"US",
    "sg:address":"7830 Old Georgetown Rd",
    "sg:city":"Bethesda",
    "sg:classifiers":[
        {
            "category":"Health Services",
            "subcategory":"Doctor",
            "type":"Services"
        }
    ],
    "sg:phone":"+1 301 656 0220",
    "sg:postcode":"20814",
    "sg:province":"MD",
    "wof:name":"McAuley Adrienne Pt",
    "wof:placetype":"venue"
},
  "geometry": {"coordinates":[-77.10080000000001,38.988701],"type":"Point"}
}