{
  "type": "Feature",
  "properties": {
    "addr:full":"8325 Mount Harmony Ln Owings MD 20736",
    "addr:housenumber":"8325",
    "addr:postcode":"20736",
    "addr:street":"Mount Harmony Ln",
    "iso:country":"US",
    "sg:address":"8325 Mount Harmony Ln",
    "sg:city":"Owings",
    "sg:classifiers":[
        {
            "category":"Retail",
            "subcategory":"Funeral Services",
            "type":"Services"
        }
    ],
    "sg:phone":"+1 410 257 6181",
    "sg:postcode":"20736",
    "sg:province":"MD",
    "sg:tags":[
        "director"
    ],
    "wof:name":"Rausch Funeral Home",
    "wof:placetype":"venue"
},
  "geometry": {"coordinates":[-76.604885,38.699673],"type":"Point"}
}