{
  "type": "Feature",
  "properties": {
    "addr:full":"15800 Darnestown Rd Germantown MD 20874",
    "addr:housenumber":"15800",
    "addr:postcode":"20874",
    "addr:street":"Darnestown Rd",
    "iso:country":"US",
    "sg:address":"15800 Darnestown Rd",
    "sg:city":"Germantown",
    "sg:classifiers":[
        {
            "category":"Manufacturing",
            "subcategory":"Paper Products",
            "type":"Manufacturing & Wholesale Goods"
        }
    ],
    "sg:phone":"+1 301 216 2500",
    "sg:postcode":"20874",
    "sg:province":"MD",
    "sg:tags":[
        "bamboo"
    ],
    "wof:name":"Ithaca Farm Nursery",
    "wof:placetype":"venue"
},
  "geometry": {"coordinates":[-77.33041299999999,39.126823],"type":"Point"}
}