{
  "type": "Feature",
  "properties": {
    "iso:country":"US",
    "sg:address":"6809 Dunnigan Dr",
    "sg:city":"Clinton",
    "sg:classifiers":[
        {
            "category":"Transit Center",
            "subcategory":"Freight",
            "type":"Transportation"
        },
        {
            "category":"Freight",
            "type":"Transportation"
        }
    ],
    "sg:phone":"+1 202 528 0952",
    "sg:postcode":"20735",
    "sg:province":"MD",
    "sg:tags":[
        "trucking-motor",
        "trucking"
    ],
    "wof:name":"Ellerbe Trucking",
    "wof:placetype":"venue"
},
  "geometry": {"coordinates":[-76.89031,38.746048],"type":"Point"}
}