{
  "type": "Feature",
  "properties": {
    "iso:country":"US",
    "sg:address":"9 Watch Hill Pl",
    "sg:city":"Gaithersburg",
    "sg:classifiers":[
        {
            "category":"Real Estate",
            "subcategory":"Architect",
            "type":"Services"
        }
    ],
    "sg:phone":"+1 301 921 0417",
    "sg:postcode":"20878",
    "sg:province":"MD",
    "sg:tags":[
        "architectural"
    ],
    "wof:name":"Glodt Charles L",
    "wof:placetype":"venue"
},
  "geometry": {"coordinates":[-77.211067,39.117736],"type":"Point"}
}