{
  "type": "Feature",
  "properties": {
    "iso:country":"US",
    "sg:address":"8531 Connecticut Ave",
    "sg:city":"Chevy Chase",
    "sg:classifiers":[
        {
            "category":"Food & Beverages",
            "subcategory":"Groceries & Convenience Stores",
            "type":"Retail Goods"
        }
    ],
    "sg:phone":"+1 301 656 5133",
    "sg:postcode":"20815",
    "sg:province":"MD",
    "sg:website":"www.chevychasesupermaket.com",
    "wof:name":"Chevy Chase Super Market",
    "wof:placetype":"venue"
},
  "geometry": {"coordinates":[-77.077095,38.995071],"type":"Point"}
}