{
  "type": "Feature",
  "properties": {
    "addr:full":"319 Mount Vernon Pl Rockville MD 20852",
    "addr:housenumber":"319",
    "addr:postcode":"20852",
    "addr:street":"Mount Vernon Pl",
    "iso:country":"US",
    "sg:address":"319 Mount Vernon Pl",
    "sg:city":"Rockville",
    "sg:classifiers":[
        {
            "category":"Retail",
            "subcategory":"Laundry & Dry Cleaning",
            "type":"Services"
        }
    ],
    "sg:phone":"+1 301 279 7767",
    "sg:postcode":"20852",
    "sg:province":"MD",
    "sg:tags":[
        "cleaners",
        "rug",
        "carpet"
    ],
    "wof:name":"Poseidon Dry Carpet Cleaning",
    "wof:placetype":"venue"
},
  "geometry": {"coordinates":[-77.14470799999999,39.076663],"type":"Point"}
}