{
  "type": "Feature",
  "properties": {
    "addr:full":"1206 Ridgely St Baltimore MD 21230",
    "addr:housenumber":"1206",
    "addr:postcode":"21230",
    "addr:street":"Ridgely St",
    "iso:country":"US",
    "sg:address":"1206 Ridgely St",
    "sg:city":"Baltimore",
    "sg:classifiers":[
        {
            "category":"Autos & Motor Vehicles",
            "subcategory":"Automobile Sales",
            "type":"Retail Goods"
        }
    ],
    "sg:phone":"+1 410 455 9292",
    "sg:postcode":"21230",
    "sg:province":"MD",
    "sg:tags":[
        "leasing"
    ],
    "sg:website":"http://www.cleancities.com",
    "wof:name":"Www.Cleancities.Com",
    "wof:placetype":"venue"
},
  "geometry": {"coordinates":[-76.626479,39.277589],"type":"Point"}
}