{
  "type": "Feature",
  "properties": {
    "iso:country":"US",
    "sg:address":"5644 3rd St NE",
    "sg:city":"Washington",
    "sg:classifiers":[
        {
            "category":"Shopping",
            "subcategory":"Clothing, Apparel, & Fashions",
            "type":"Retail Goods"
        }
    ],
    "sg:phone":"+1 202 526 8337",
    "sg:postcode":"20011",
    "sg:province":"MD",
    "sg:tags":[
        "t"
    ],
    "wof:name":"East Coast Printed Sportswear",
    "wof:placetype":"venue"
},
  "geometry": {"coordinates":[-77.002847,38.957178],"type":"Point"}
}