{
  "type": "Feature",
  "properties": {
    "iso:country":"US",
    "sg:address":"10621 Sourwood Ct",
    "sg:city":"Laurel",
    "sg:classifiers":[
        {
            "category":"Professional",
            "subcategory":"Computer Services",
            "type":"Services"
        }
    ],
    "sg:phone":"+1 301 604 4893",
    "sg:postcode":"20723",
    "sg:province":"MD",
    "sg:tags":[
        "related"
    ],
    "wof:name":"Iehorizon Inc",
    "wof:placetype":"venue"
},
  "geometry": {"coordinates":[-76.88057999999999,39.156664],"type":"Point"}
}