{
  "type": "Feature",
  "properties": {
    "addr:full":"4940 Eastern Ave Baltimore MD 21224",
    "addr:housenumber":"4940",
    "addr:postcode":"21224",
    "addr:street":"Eastern Ave",
    "iso:country":"US",
    "sg:address":"4940 Eastern Ave",
    "sg:city":"Baltimore",
    "sg:classifiers":[
        {
            "category":"Health Services",
            "subcategory":"Doctor",
            "type":"Services"
        }
    ],
    "sg:phone":"+1 410 550 0456",
    "sg:postcode":"21224",
    "sg:province":"MD",
    "wof:name":"Wenz James MD",
    "wof:placetype":"venue"
},
  "geometry": {"coordinates":[-76.554371,39.287287],"type":"Point"}
}