{
  "type": "Feature",
  "properties": {
    "addr:full":"5051 Greenspring Ave Ste 101 Baltimore MD 21209",
    "addr:housenumber":"5051",
    "addr:postcode":"21209",
    "addr:street":"Greenspring Ave Ste 101",
    "iso:country":"US",
    "sg:address":"5051 Greenspring Ave Ste 101",
    "sg:city":"Baltimore",
    "sg:classifiers":[
        {
            "category":"Health Services",
            "subcategory":"Doctor",
            "type":"Services"
        }
    ],
    "sg:phone":"+1 410 664 3680",
    "sg:postcode":"21209",
    "sg:province":"MD",
    "wof:name":"Conway James E MD",
    "wof:placetype":"venue"
},
  "geometry": {"coordinates":[-76.659921,39.353839],"type":"Point"}
}