{
  "type": "Feature",
  "properties": {
    "addr:full":"9401 Montpelier Dr Laurel MD 20708",
    "addr:housenumber":"9401",
    "addr:postcode":"20708",
    "addr:street":"Montpelier Dr",
    "iso:country":"US",
    "sg:address":"9401 Montpelier Dr",
    "sg:city":"Laurel",
    "sg:classifiers":[
        {
            "category":"Coffee & Tea",
            "type":"Food & Drink"
        }
    ],
    "sg:phone":"+1 301 498 8486",
    "sg:postcode":"20708",
    "sg:province":"MD",
    "sg:website":"www.the-little-teapot.com",
    "wof:name":"Little Teapot the",
    "wof:placetype":"venue"
},
  "geometry": {"coordinates":[-76.84429900000001,39.069],"type":"Point"}
}