{
  "type": "Feature",
  "properties": {
    "iso:country":"US",
    "sg:address":"1321 Riverside Pkwy",
    "sg:city":"Belcamp",
    "sg:classifiers":[
        {
            "category":"Insurance",
            "subcategory":"Insurance Agent",
            "type":"Services"
        }
    ],
    "sg:phone":"+1 410 273 6665",
    "sg:postcode":"21017",
    "sg:province":"MD",
    "wof:name":"Norris Agency",
    "wof:placetype":"venue"
},
  "geometry": {"coordinates":[-76.248132,39.478645],"type":"Point"}
}