{
  "type": "Feature",
  "properties": {
    "iso:country":"US",
    "sg:address":"16252 Toms Creek Church Rd",
    "sg:city":"Emmitsburg",
    "sg:classifiers":[
        {
            "category":"Organizations",
            "subcategory":"Religious Organization",
            "type":"Services"
        }
    ],
    "sg:phone":"+1 301 447 3171",
    "sg:postcode":"21727",
    "sg:province":"MD",
    "wof:name":"Toms Creek Untd Mthdst Church",
    "wof:placetype":"venue"
},
  "geometry": {"coordinates":[-77.285354,39.675992],"type":"Point"}
}