{
  "type": "Feature",
  "properties": {
    "iso:country":"US",
    "sg:address":"2713 Bel Air Rd",
    "sg:city":"Fallston",
    "sg:classifiers":[
        {
            "category":"Autos & Motor Vehicles",
            "subcategory":"Auto Supplies",
            "type":"Retail Goods"
        }
    ],
    "sg:phone":"+1 410 877 1890",
    "sg:postcode":"21047",
    "sg:province":"MD",
    "sg:tags":[
        "automobile",
        "parts"
    ],
    "wof:name":"Richman's Auto Supply Inc",
    "wof:placetype":"venue"
},
  "geometry": {"coordinates":[-76.400035,39.485684],"type":"Point"}
}