{
  "type": "Feature",
  "properties": {
    "iso:country":"US",
    "sg:address":"725 Herald Harbor Rd",
    "sg:city":"Crownsville",
    "sg:classifiers":[
        {
            "category":"Organizations",
            "subcategory":"Religious Organization",
            "type":"Services"
        }
    ],
    "sg:phone":"+1 410 923 6900",
    "sg:postcode":"21032",
    "sg:province":"MD",
    "wof:name":"South Shore Baptist Church",
    "wof:placetype":"venue"
},
  "geometry": {"coordinates":[-76.603476,39.038171],"type":"Point"}
}