{
  "type": "Feature",
  "properties": {
    "iso:country":"US",
    "sg:address":"18712 Purple Martin Ln",
    "sg:city":"Gaithersburg",
    "sg:classifiers":[
        {
            "category":"Professional",
            "subcategory":"Art Services",
            "type":"Services"
        }
    ],
    "sg:phone":"+1 301 948 5212",
    "sg:postcode":"20879",
    "sg:province":"MD",
    "sg:tags":[
        "photography",
        "commercial"
    ],
    "wof:name":"Photo Response",
    "wof:placetype":"venue"
},
  "geometry": {"coordinates":[-77.188022,39.163838],"type":"Point"}
}