{
  "type": "Feature",
  "properties": {
    "addr:full":"9 White Crane Dr Berlin MD 21811",
    "addr:housenumber":"9",
    "addr:postcode":"21811",
    "addr:street":"White Crane Dr",
    "iso:country":"US",
    "sg:address":"9 White Crane Dr",
    "sg:city":"Berlin",
    "sg:classifiers":[
        {
            "category":"Professional",
            "subcategory":"Management & Consulting",
            "type":"Services"
        }
    ],
    "sg:phone":"+1 410 213 7699",
    "sg:postcode":"21811",
    "sg:province":"MD",
    "wof:name":"Out of The Fire",
    "wof:placetype":"venue"
},
  "geometry": {"coordinates":[-75.115498,38.319274],"type":"Point"}
}