{
  "type": "Feature",
  "properties": {
    "iso:country":"US",
    "sg:address":"2210 Tall Pines Ct",
    "sg:city":"Baltimore",
    "sg:classifiers":[
        {
            "category":"Retail",
            "subcategory":"Repair Shop",
            "type":"Services"
        }
    ],
    "sg:phone":"+1 410 747 5416",
    "sg:postcode":"21228",
    "sg:province":"MD",
    "sg:tags":[
        "welding"
    ],
    "wof:name":"United Welding",
    "wof:placetype":"venue"
},
  "geometry": {"coordinates":[-76.774369,39.27749],"type":"Point"}
}