{
  "type": "Feature",
  "properties": {
    "addr:full":"7810 Bertha Rd Pasadena MD 21122",
    "addr:housenumber":"7810",
    "addr:postcode":"21122",
    "addr:street":"Bertha Rd",
    "iso:country":"US",
    "sg:address":"7810 Bertha Rd",
    "sg:city":"Pasadena",
    "sg:classifiers":[
        {
            "category":"Building & Trades",
            "subcategory":"Construction",
            "type":"Services"
        }
    ],
    "sg:phone":"+1 410 437 9516",
    "sg:postcode":"21122",
    "sg:province":"MD",
    "sg:tags":[
        "home",
        "improvement"
    ],
    "wof:name":"Northern Craft Construction",
    "wof:placetype":"venue"
},
  "geometry": {"coordinates":[-76.51517800000001,39.142967],"type":"Point"}
}