{
  "type": "Feature",
  "properties": {
    "iso:country":"US",
    "sg:address":"7810 Bertha Rd",
    "sg:city":"Pasadena",
    "sg:classifiers":[
        {
            "category":"Building & Trades",
            "subcategory":"Construction",
            "type":"Services"
        }
    ],
    "sg:phone":"+1 410 437 9516",
    "sg:postcode":"21122",
    "sg:province":"MD",
    "sg:tags":[
        "home",
        "improvement"
    ],
    "wof:name":"Northern Craft Construction",
    "wof:placetype":"venue"
},
  "geometry": {"coordinates":[-76.515178,39.142967],"type":"Point"}
}