{
  "type": "Feature",
  "properties": {
    "addr:full":"22711 Three Notch Rd California MD 20619",
    "addr:housenumber":"22711",
    "addr:postcode":"20619",
    "addr:street":"Three Notch Rd",
    "iso:country":"US",
    "sg:address":"22711 Three Notch Rd",
    "sg:city":"California",
    "sg:classifiers":[
        {
            "category":"Food & Beverages",
            "subcategory":"Groceries & Convenience Stores",
            "type":"Retail Goods"
        }
    ],
    "sg:phone":"+1 301 737 7700",
    "sg:postcode":"20619",
    "sg:province":"MD",
    "sg:website":"http://www.sheetz.com",
    "wof:name":"Sheetz 292",
    "wof:placetype":"venue"
},
  "geometry": {"coordinates":[-76.534442,38.312144],"type":"Point"}
}