{
  "type": "Feature",
  "properties": {
    "addr:full":"3227 Chestnut Ridge Rd Grantsville MD 21536",
    "addr:housenumber":"3227",
    "addr:postcode":"21536",
    "addr:street":"Chestnut Ridge Rd",
    "iso:country":"US",
    "sg:address":"3227 Chestnut Ridge Rd",
    "sg:city":"Grantsville",
    "sg:classifiers":[
        {
            "category":"Manufacturing",
            "subcategory":"Printing",
            "type":"Manufacturing & Wholesale Goods"
        }
    ],
    "sg:phone":"+1 301 746 8223",
    "sg:postcode":"21536",
    "sg:province":"MD",
    "sg:tags":[
        "newspaper"
    ],
    "wof:name":"Republican Newspaper",
    "wof:placetype":"venue"
},
  "geometry": {"coordinates":[-79.098214,39.698842],"type":"Point"}
}