{
  "type": "Feature",
  "properties": {
    "iso:country":"US",
    "sg:address":"2712 Harmon Rd",
    "sg:city":"Silver Spring",
    "sg:classifiers":[
        {
            "category":"Professional",
            "subcategory":"Employment Agencies",
            "type":"Services"
        }
    ],
    "sg:phone":"+1 301 942 5881",
    "sg:postcode":"20902",
    "sg:province":"MD",
    "wof:name":"Patty Buchek",
    "wof:placetype":"venue"
},
  "geometry": {"coordinates":[-77.056696,39.027873],"type":"Point"}
}