{
  "type": "Feature",
  "properties": {
    "iso:country":"US",
    "sg:address":"5715 Emerson St",
    "sg:city":"Bladensburg",
    "sg:classifiers":[
        {
            "category":"Education",
            "subcategory":"School",
            "type":"Public Place"
        }
    ],
    "sg:phone":"+1 301 864 4532",
    "sg:postcode":"20710",
    "sg:province":"MD",
    "sg:tags":[
        "high",
        "middle",
        "elementary"
    ],
    "wof:name":"Elizabeth Seton High School",
    "wof:placetype":"venue"
},
  "geometry": {"coordinates":[-76.915497,38.947399],"type":"Point"}
}