{
  "type": "Feature",
  "properties": {
    "addr:full":"102 Market St Havre De Grace MD 21078",
    "addr:housenumber":"102",
    "addr:postcode":"21078",
    "addr:street":"Market St",
    "iso:country":"US",
    "sg:address":"102 Market St",
    "sg:city":"Havre De Grace",
    "sg:classifiers":[
        {
            "category":"Organizations",
            "subcategory":"Religious Organization",
            "type":"Services"
        }
    ],
    "sg:phone":"+1 410 942 0944",
    "sg:postcode":"21078",
    "sg:province":"MD",
    "sg:tags":[
        "church"
    ],
    "wof:name":"Greater Faith Christian Church",
    "wof:placetype":"venue"
},
  "geometry": {"coordinates":[-76.088038,39.546637],"type":"Point"}
}