{
  "type": "Feature",
  "properties": {
    "iso:country":"US",
    "sg:address":"6095 Marshalee Ln",
    "sg:city":"Elkridge",
    "sg:classifiers":[
        {
            "category":"Professional",
            "subcategory":"Management & Consulting",
            "type":"Services"
        }
    ],
    "sg:phone":"+1 410 379 3400",
    "sg:postcode":"21075",
    "sg:province":"MD",
    "sg:tags":[
        "health",
        "care"
    ],
    "sg:website":"www.unitedhealthcare.com",
    "wof:name":"United Health Care",
    "wof:placetype":"venue"
},
  "geometry": {"coordinates":[-76.775542,39.205776],"type":"Point"}
}