{
  "type": "Feature",
  "properties": {
    "iso:country":"US",
    "sg:address":"2 Glenberry Ct",
    "sg:city":"Phoenix",
    "sg:classifiers":[
        {
            "category":"Bakery",
            "type":"Food & Drink"
        }
    ],
    "sg:phone":"+1 410 527 0824",
    "sg:postcode":"21131",
    "sg:province":"MD",
    "sg:tags":[
        "cake",
        "pastry",
        "wedding"
    ],
    "wof:name":"Cakes By Stephanie",
    "wof:placetype":"venue"
},
  "geometry": {"coordinates":[-76.571579,39.530369],"type":"Point"}
}