{
  "type": "Feature",
  "properties": {
    "iso:country":"US",
    "sg:address":"835 W Hillcrest Rd",
    "sg:city":"Hagerstown",
    "sg:classifiers":[
        {
            "category":"Food & Beverages",
            "subcategory":"Groceries & Convenience Stores",
            "type":"Retail Goods"
        }
    ],
    "sg:phone":"+1 301 733 5220",
    "sg:postcode":"21742",
    "sg:province":"MD",
    "sg:tags":[
        "grocer"
    ],
    "sg:website":"www.gianteagle.com",
    "wof:name":"Giant Eagle",
    "wof:placetype":"venue"
},
  "geometry": {"coordinates":[-77.71713200000001,39.658176],"type":"Point"}
}