{
  "type": "Feature",
  "properties": {
    "iso:country":"US",
    "sg:address":"9139 Red Branch Rd",
    "sg:city":"Columbia",
    "sg:classifiers":[
        {
            "category":"Retail",
            "subcategory":"Repair Shop",
            "type":"Services"
        }
    ],
    "sg:phone":"+1 410 964 0855",
    "sg:postcode":"21045",
    "sg:province":"MD",
    "sg:tags":[
        "reupholstery",
        "furniture"
    ],
    "wof:name":"Cover-Uph Inc the",
    "wof:placetype":"venue"
},
  "geometry": {"coordinates":[-76.8181,39.231499],"type":"Point"}
}