{
  "type": "Feature",
  "properties": {
    "iso:country":"US",
    "sg:address":"6420 Dobbin Rd",
    "sg:city":"Columbia",
    "sg:classifiers":[
        {
            "category":"Health Services",
            "subcategory":"Health Practitioner",
            "type":"Services"
        }
    ],
    "sg:phone":"+1 410 997 8081",
    "sg:postcode":"21045",
    "sg:province":"MD",
    "sg:tags":[
        "occupational",
        "therapist",
        "physical"
    ],
    "wof:name":"Children's Therapy Ctr",
    "wof:placetype":"venue"
},
  "geometry": {"coordinates":[-76.82094600000001,39.196336],"type":"Point"}
}