{
  "type": "Feature",
  "properties": {
    "addr:full":"15401 Mount Oak Rd Bowie MD 20716",
    "addr:housenumber":"15401",
    "addr:postcode":"20716",
    "addr:street":"Mount Oak Rd",
    "iso:country":"US",
    "sg:address":"15401 Mount Oak Rd",
    "sg:city":"Bowie",
    "sg:classifiers":[
        {
            "category":"Professional",
            "type":"Services"
        }
    ],
    "sg:phone":"+1 301 599 1218",
    "sg:postcode":"20716",
    "sg:province":"MD",
    "wof:name":"Bonnie Jean Born",
    "wof:placetype":"venue"
},
  "geometry": {"coordinates":[-76.739031,38.92611],"type":"Point"}
}