{
  "type": "Feature",
  "properties": {
    "addr:full":"5532 Randolph Rd Rockville MD 20852",
    "addr:housenumber":"5532",
    "addr:postcode":"20852",
    "addr:street":"Randolph Rd",
    "iso:country":"US",
    "sg:address":"5532 Randolph Rd",
    "sg:city":"Rockville",
    "sg:classifiers":[
        {
            "category":"Professional",
            "subcategory":"Printing & Photocopies",
            "type":"Services"
        }
    ],
    "sg:phone":"+1 301 984 4015",
    "sg:postcode":"20852",
    "sg:province":"MD",
    "sg:website":"www.alphagraphics.com",
    "wof:name":"Alphagraphics Printshops of the Future",
    "wof:placetype":"venue"
},
  "geometry": {"coordinates":[-77.111099,39.053398],"type":"Point"}
}