{
  "type": "Feature",
  "properties": {
    "addr:full":"7228 Kidmore Ln Lanham MD 20706",
    "addr:housenumber":"7228",
    "addr:postcode":"20706",
    "addr:street":"Kidmore Ln",
    "iso:country":"US",
    "sg:address":"7228 Kidmore Ln",
    "sg:city":"Lanham",
    "sg:classifiers":[
        {
            "category":"Professional",
            "subcategory":"Accounting & Tax Preparation",
            "type":"Services"
        }
    ],
    "sg:phone":"+1 301 249 2577",
    "sg:postcode":"20706",
    "sg:province":"MD",
    "sg:tags":[
        "bookkeeping",
        "general"
    ],
    "wof:name":"MRD Bookkeeping & Accounting",
    "wof:placetype":"venue"
},
  "geometry": {"coordinates":[-76.886815,38.958725],"type":"Point"}
}