{
  "type": "Feature",
  "properties": {
    "addr:full":"10424 Stansfield Rd Laurel MD 20723",
    "addr:housenumber":"10424",
    "addr:postcode":"20723",
    "addr:street":"Stansfield Rd",
    "iso:country":"US",
    "sg:address":"10424 Stansfield Rd",
    "sg:city":"Laurel",
    "sg:classifiers":[
        {
            "category":"Retail",
            "subcategory":"Repair Shop",
            "type":"Services"
        }
    ],
    "sg:phone":"+1 410 730 6886",
    "sg:postcode":"20723",
    "sg:province":"MD",
    "sg:tags":[
        "appliance"
    ],
    "wof:name":"Universal Appliance Svc Inc",
    "wof:placetype":"venue"
},
  "geometry": {"coordinates":[-76.874752,39.127412],"type":"Point"}
}