{
  "type": "Feature",
  "properties": {
    "iso:country":"US",
    "sg:address":"17 Golden Hill Ct",
    "sg:city":"Catonsville",
    "sg:classifiers":[
        {
            "category":"Wholesale",
            "subcategory":"Machinery & Supplies",
            "type":"Manufacturing & Wholesale Goods"
        }
    ],
    "sg:phone":"+1 410 788 1266",
    "sg:postcode":"21228",
    "sg:province":"MD",
    "sg:tags":[
        "craft",
        "industrial"
    ],
    "wof:name":"Terry Cunningham",
    "wof:placetype":"venue"
},
  "geometry": {"coordinates":[-76.772719,39.293677],"type":"Point"}
}