{
  "type": "Feature",
  "properties": {
    "addr:full":"8729 New Bridge Rd Denton MD 21629",
    "addr:housenumber":"8729",
    "addr:postcode":"21629",
    "addr:street":"New Bridge Rd",
    "iso:country":"US",
    "sg:address":"8729 New Bridge Rd",
    "sg:city":"Denton",
    "sg:classifiers":[
        {
            "category":"Farming",
            "subcategory":"Fish & Marine Products",
            "type":"Manufacturing & Wholesale Goods"
        }
    ],
    "sg:phone":"+1 410 479 3004",
    "sg:postcode":"21629",
    "sg:province":"MD",
    "sg:tags":[
        "preserves",
        "fishing",
        "hunting"
    ],
    "wof:name":"Caroline County Shooting Prsrv",
    "wof:placetype":"venue"
},
  "geometry": {"coordinates":[-75.881625,38.848785],"type":"Point"}
}