{
  "type": "Feature",
  "properties": {
    "iso:country":"US",
    "sg:address":"1110 S Philadelphia Blvd",
    "sg:city":"Aberdeen",
    "sg:classifiers":[
        {
            "category":"Manufacturing",
            "subcategory":"Metals",
            "type":"Manufacturing & Wholesale Goods"
        }
    ],
    "sg:phone":"+1 410 676 7138",
    "sg:postcode":"21001",
    "sg:province":"MD",
    "sg:tags":[
        "tower"
    ],
    "wof:name":"T & S Towing",
    "wof:placetype":"venue"
},
  "geometry": {"coordinates":[-76.192224,39.490747],"type":"Point"}
}