{
  "type": "Feature",
  "properties": {
    "addr:full":"3046 Waldorf Market Pl Waldorf MD 20603",
    "addr:housenumber":"3046",
    "addr:postcode":"20603",
    "addr:street":"Waldorf Market Pl",
    "iso:country":"US",
    "sg:address":"3046 Waldorf Market Pl",
    "sg:city":"Waldorf",
    "sg:classifiers":[
        {
            "category":"Restaurant",
            "type":"Food & Drink"
        }
    ],
    "sg:menulink":"http://www.allmenus.com/md/waldorf/10154-famous-daves/menu/",
    "sg:phone":"+1 301 885 1555",
    "sg:postcode":"20603",
    "sg:province":"MD",
    "sg:tags":[
        "barbecue",
        "american"
    ],
    "wof:name":"Famous Dave's",
    "wof:placetype":"venue"
},
  "geometry": {"coordinates":[-76.91703800000001,38.628575],"type":"Point"}
}