{
  "type": "Feature",
  "properties": {
    "addr:full":"365 Main St Laurel MD 20707",
    "addr:housenumber":"365",
    "addr:postcode":"20707",
    "addr:street":"Main St",
    "iso:country":"US",
    "sg:address":"365 Main St",
    "sg:city":"Laurel",
    "sg:classifiers":[
        {
            "category":"Shopping",
            "subcategory":"Comic Books",
            "type":"Retail Goods"
        }
    ],
    "sg:phone":"+1 301 490 9811",
    "sg:postcode":"20707",
    "sg:province":"MD",
    "wof:name":"Comic Classics",
    "wof:placetype":"venue"
},
  "geometry": {"coordinates":[-76.845596,39.104801],"type":"Point"}
}