{
  "type": "Feature",
  "properties": {
    "iso:country":"US",
    "sg:address":"2568 Riva Rd",
    "sg:city":"Annapolis",
    "sg:classifiers":[
        {
            "category":"Banks & Credit Unions",
            "subcategory":"Investment Brokerage",
            "type":"Services"
        }
    ],
    "sg:phone":"+1 410 295 9220",
    "sg:postcode":"21401",
    "sg:province":"MD",
    "sg:tags":[
        "consultant",
        "financing"
    ],
    "wof:name":"Linsco Private Ledger",
    "wof:placetype":"venue"
},
  "geometry": {"coordinates":[-76.555536,38.976126],"type":"Point"}
}