{
  "type": "Feature",
  "properties": {
    "addr:full":"417 Maryland Ave Baltimore MD 21221",
    "addr:housenumber":"417",
    "addr:postcode":"21221",
    "addr:street":"Maryland Ave",
    "iso:country":"US",
    "sg:address":"417 Maryland Ave",
    "sg:city":"Baltimore",
    "sg:classifiers":[
        {
            "category":"Building & Trades",
            "subcategory":"Plumbing",
            "type":"Services"
        }
    ],
    "sg:phone":"+1 410 282 0454",
    "sg:postcode":"21221",
    "sg:province":"MD",
    "sg:tags":[
        "conditioning",
        "air",
        "system",
        "contractor"
    ],
    "wof:name":"CNC Mechanical Svc",
    "wof:placetype":"venue"
},
  "geometry": {"coordinates":[-76.47461699999999,39.307668],"type":"Point"}
}