{
  "type": "Feature",
  "properties": {
    "iso:country":"US",
    "sg:address":"1307 Wilson Point Rd",
    "sg:city":"Baltimore",
    "sg:classifiers":[
        {
            "category":"Recreation",
            "type":"Entertainment"
        }
    ],
    "sg:phone":"+1 410 687 9795",
    "sg:postcode":"21220",
    "sg:province":"MD",
    "sg:tags":[
        "club",
        "membership"
    ],
    "wof:name":"Marco Hunting & Fishing Club",
    "wof:placetype":"venue"
},
  "geometry": {"coordinates":[-76.41820300000001,39.317903],"type":"Point"}
}