{
  "type": "Feature",
  "properties": {
    "addr:full":"6620 Ritchie Hwy Glen Burnie MD 21061",
    "addr:housenumber":"6620",
    "addr:postcode":"21061",
    "addr:street":"Ritchie Hwy",
    "iso:country":"US",
    "sg:address":"6620 Ritchie Hwy",
    "sg:city":"Glen Burnie",
    "sg:classifiers":[
        {
            "category":"Restaurant",
            "type":"Food & Drink"
        }
    ],
    "sg:menulink":"http://www.allmenus.com/md/glen-burnie/42209-bob-evans/menu/",
    "sg:phone":"+1 410 768 3034",
    "sg:postcode":"21061",
    "sg:province":"MD",
    "sg:tags":[
        "american"
    ],
    "wof:name":"Bob Evans",
    "wof:placetype":"venue"
},
  "geometry": {"coordinates":[-76.613322,39.194929],"type":"Point"}
}