{
  "type": "Feature",
  "properties": {
    "iso:country":"US",
    "sg:address":"Olney Shopping Ctr",
    "sg:city":"Ashton",
    "sg:classifiers":[
        {
            "category":"Professional",
            "subcategory":"Lawyer & Legal Services",
            "type":"Services"
        }
    ],
    "sg:phone":"+1 301 774 6627",
    "sg:postcode":"20861",
    "sg:province":"MD",
    "wof:name":"Carrozza Albert B Atty",
    "wof:placetype":"venue"
},
  "geometry": {"coordinates":[-76.99539900000001,39.151699],"type":"Point"}
}