{
  "type": "Feature",
  "properties": {
    "iso:country":"US",
    "sg:address":"5842 Silver Hill Rd",
    "sg:city":"District Heights",
    "sg:classifiers":[
        {
            "category":"Food & Beverages",
            "subcategory":"Liquor & Beverages",
            "type":"Retail Goods"
        }
    ],
    "sg:phone":"+1 301 420 6422",
    "sg:postcode":"20747",
    "sg:province":"MD",
    "sg:tags":[
        "beer",
        "spirit",
        "wine"
    ],
    "wof:name":"J B Liquours Inc",
    "wof:placetype":"venue"
},
  "geometry": {"coordinates":[-76.90562799999999,38.856097],"type":"Point"}
}