{
  "type": "Feature",
  "properties": {
    "iso:country":"US",
    "sg:address":"902 Seton Dr",
    "sg:city":"Cumberland",
    "sg:classifiers":[
        {
            "category":"Professional",
            "type":"Services"
        }
    ],
    "sg:phone":"+1 301 777 2736",
    "sg:postcode":"21502",
    "sg:province":"MD",
    "sg:tags":[
        "establishment"
    ],
    "wof:name":"E D Menchavez",
    "wof:placetype":"venue"
},
  "geometry": {"coordinates":[-78.801486,39.640663],"type":"Point"}
}