{
  "type": "Feature",
  "properties": {
    "iso:country":"US",
    "sg:address":"202 Jefferson Pike",
    "sg:city":"Knoxville",
    "sg:classifiers":[
        {
            "category":"Organizations",
            "subcategory":"Religious Organization",
            "type":"Services"
        }
    ],
    "sg:phone":"+1 301 834 7221",
    "sg:postcode":"21758",
    "sg:province":"MD",
    "sg:tags":[
        "church"
    ],
    "wof:name":"Feed The Hungry Ministry Inc",
    "wof:placetype":"venue"
},
  "geometry": {"coordinates":[-77.665142,39.327376],"type":"Point"}
}