{
  "type": "Feature",
  "properties": {
    "addr:full":"3714 Ardwick Pl Landover MD 20785",
    "addr:housenumber":"3714",
    "addr:postcode":"20785",
    "addr:street":"Ardwick Pl",
    "iso:country":"US",
    "sg:address":"3714 Ardwick Pl",
    "sg:city":"Landover",
    "sg:classifiers":[
        {
            "category":"Building & Trades",
            "subcategory":"Construction",
            "type":"Services"
        }
    ],
    "sg:phone":"+1 301 772 7227",
    "sg:postcode":"20785",
    "sg:province":"MD",
    "sg:tags":[
        "site",
        "clean"
    ],
    "wof:name":"Everready Rolloffs",
    "wof:placetype":"venue"
},
  "geometry": {"coordinates":[-76.87067399999999,38.942564],"type":"Point"}
}