{
  "type": "Feature",
  "properties": {
    "iso:country":"US",
    "sg:address":"9904 Norwood Ct",
    "sg:city":"Upper Marlboro",
    "sg:classifiers":[
        {
            "category":"Manufacturing",
            "subcategory":"Chemicals & Compounds",
            "type":"Manufacturing & Wholesale Goods"
        }
    ],
    "sg:phone":"+1 301 669 5301",
    "sg:postcode":"20774",
    "sg:province":"MD",
    "sg:tags":[
        "preparation",
        "toilet",
        "mfg"
    ],
    "wof:name":"Beauticontrol",
    "wof:placetype":"venue"
},
  "geometry": {"coordinates":[-76.834813,38.877343],"type":"Point"}
}