{
  "type": "Feature",
  "properties": {
    "iso:country":"US",
    "sg:address":"316 E 25th St",
    "sg:city":"Baltimore",
    "sg:classifiers":[
        {
            "category":"Building & Trades",
            "subcategory":"Construction",
            "type":"Services"
        }
    ],
    "sg:phone":"+1 410 235 2460",
    "sg:postcode":"21218",
    "sg:province":"MD",
    "sg:tags":[
        "general",
        "contractor"
    ],
    "wof:name":"Springdale Construction Co",
    "wof:placetype":"venue"
},
  "geometry": {"coordinates":[-76.612459,39.318122],"type":"Point"}
}