{
  "type": "Feature",
  "properties": {
    "iso:country":"US",
    "sg:address":"605 Dunsinnan Trl",
    "sg:city":"Bel Air",
    "sg:classifiers":[
        {
            "category":"Shopping",
            "subcategory":"Used Merchandise",
            "type":"Retail Goods"
        }
    ],
    "sg:phone":"+1 410 838 2052",
    "sg:postcode":"21014",
    "sg:province":"MD",
    "wof:name":"Country Roads Antiques & Colle",
    "wof:placetype":"venue"
},
  "geometry": {"coordinates":[-76.36436999999999,39.536072],"type":"Point"}
}