{
  "type": "Feature",
  "properties": {
    "iso:country":"US",
    "sg:address":"219 N Luzerne Ave",
    "sg:city":"Baltimore",
    "sg:classifiers":[
        {
            "category":"Retail",
            "subcategory":"Repair Shop",
            "type":"Services"
        }
    ],
    "sg:phone":"+1 410 675 2280",
    "sg:postcode":"21224",
    "sg:province":"MD",
    "sg:tags":[
        "equipment"
    ],
    "wof:name":"EDCO Commercial Gas Svc Inc",
    "wof:placetype":"venue"
},
  "geometry": {"coordinates":[-76.580608,39.295581],"type":"Point"}
}