{
  "type": "Feature",
  "properties": {
    "iso:country":"US",
    "sg:address":"308 North St",
    "sg:city":"Elkton",
    "sg:classifiers":[
        {
            "category":"Education",
            "subcategory":"Special Training",
            "type":"Public Place"
        }
    ],
    "sg:phone":"+1 410 392 4046",
    "sg:postcode":"21921",
    "sg:province":"MD",
    "sg:tags":[
        "instruction",
        "driving"
    ],
    "wof:name":"AAAA Driving School",
    "wof:placetype":"venue"
},
  "geometry": {"coordinates":[-75.830322,39.611044],"type":"Point"}
}