{
  "type": "Feature",
  "properties": {
    "iso:country":"US",
    "sg:address":"3732 Twin Lakes Ct",
    "sg:city":"Baltimore",
    "sg:classifiers":[
        {
            "category":"Health Services",
            "subcategory":"Health Practitioner",
            "type":"Services"
        }
    ],
    "sg:phone":"+1 410 496 5300",
    "sg:postcode":"21244",
    "sg:province":"MD",
    "sg:tags":[
        "nurse",
        "registry"
    ],
    "wof:name":"Tender Care Nursing Svc",
    "wof:placetype":"venue"
},
  "geometry": {"coordinates":[-76.756913,39.359486],"type":"Point"}
}