{
  "type": "Feature",
  "properties": {
    "iso:country":"US",
    "sg:address":"32 Diamond Crest Ct",
    "sg:city":"Baltimore",
    "sg:classifiers":[
        {
            "category":"Health Services",
            "subcategory":"Health Practitioner",
            "type":"Services"
        }
    ],
    "sg:phone":"+1 410 653 7965",
    "sg:postcode":"21209",
    "sg:province":"MD",
    "sg:tags":[
        "psychologist"
    ],
    "wof:name":"Michael S Oidick PHD",
    "wof:placetype":"venue"
},
  "geometry": {"coordinates":[-76.677113,39.382587],"type":"Point"}
}