{
  "type": "Feature",
  "properties": {
    "iso:country":"US",
    "sg:address":"6000 Executive Blvd",
    "sg:city":"Rockville",
    "sg:classifiers":[
        {
            "category":"Education",
            "subcategory":"School",
            "type":"Public Place"
        }
    ],
    "sg:phone":"+1 301 881 0078",
    "sg:postcode":"20852",
    "sg:province":"MD",
    "sg:tags":[
        "academic",
        "special"
    ],
    "wof:name":"Developmental School Fndtn",
    "wof:placetype":"venue"
},
  "geometry": {"coordinates":[-77.12447899999999,39.048643],"type":"Point"}
}