{
  "type": "Feature",
  "properties": {
    "iso:country":"US",
    "sg:address":"590 Solomons Island Rd N",
    "sg:city":"Prince Frederick",
    "sg:classifiers":[
        {
            "category":"Cinema",
            "subcategory":"Movie Rental",
            "type":"Entertainment"
        }
    ],
    "sg:phone":"+1 410 535 0042",
    "sg:postcode":"20678",
    "sg:province":"MD",
    "sg:tags":[
        "leasing",
        "video",
        "disc",
        "tape"
    ],
    "wof:name":"Blair's Video",
    "wof:placetype":"venue"
},
  "geometry": {"coordinates":[-76.59333700000001,38.551249],"type":"Point"}
}