{
  "type": "Feature",
  "properties": {
    "iso:country":"US",
    "sg:address":"3257 Plaza Way",
    "sg:city":"Waldorf",
    "sg:classifiers":[
        {
            "category":"Home & Garden",
            "subcategory":"Home Furnishings",
            "type":"Retail Goods"
        }
    ],
    "sg:phone":"+1 301 638 0720",
    "sg:postcode":"20603",
    "sg:province":"MD",
    "sg:tags":[
        "venetian",
        "blind"
    ],
    "wof:name":"Next Day Blinds",
    "wof:placetype":"venue"
},
  "geometry": {"coordinates":[-76.921807,38.625145],"type":"Point"}
}