{
  "type": "Feature",
  "properties": {
    "iso:country":"US",
    "sg:address":"3350 Paper Mill Rd",
    "sg:city":"Phoenix",
    "sg:classifiers":[
        {
            "category":"Retail",
            "subcategory":"Laundry & Dry Cleaning",
            "type":"Services"
        }
    ],
    "sg:phone":"+1 410 666 1313",
    "sg:postcode":"21131",
    "sg:province":"MD",
    "sg:tags":[
        "commercial"
    ],
    "wof:name":"Carousel Cleaning Center Inc",
    "wof:placetype":"venue"
},
  "geometry": {"coordinates":[-76.559956,39.518812],"type":"Point"}
}