{
  "type": "Feature",
  "properties": {
    "iso:country":"US",
    "sg:address":"8513 Timber Pine Ct",
    "sg:city":"Ellicott City",
    "sg:classifiers":[
        {
            "category":"Organizations",
            "subcategory":"Community Association",
            "type":"Services"
        }
    ],
    "sg:phone":"+1 410 313 9870",
    "sg:postcode":"21043",
    "sg:province":"MD",
    "wof:name":"Townhomes of Timberland I",
    "wof:placetype":"venue"
},
  "geometry": {"coordinates":[-76.801841,39.256677],"type":"Point"}
}