{
  "type": "Feature",
  "properties": {
    "iso:country":"US",
    "sg:address":"3400 N Charles St 600",
    "sg:city":"Baltimore",
    "sg:classifiers":[
        {
            "category":"Banks & Credit Unions",
            "subcategory":"Financial Services",
            "type":"Services"
        },
        {
            "category":"Education",
            "subcategory":"University",
            "type":"Public Place"
        }
    ],
    "sg:phone":"+1 410 516 8383",
    "sg:postcode":"21218",
    "sg:province":"MD",
    "sg:tags":[
        "college",
        "purchasing"
    ],
    "sg:website":"http://www.son.jhmi.edu",
    "wof:name":"Purchasing Department",
    "wof:placetype":"venue"
},
  "geometry": {"coordinates":[-76.617912,39.32914],"type":"Point"}
}