{
  "type": "Feature",
  "properties": {
    "addr:full":"10662 Weymouth St Bethesda MD 20814",
    "addr:housenumber":"10662",
    "addr:postcode":"20814",
    "addr:street":"Weymouth St",
    "iso:country":"US",
    "sg:address":"10662 Weymouth St",
    "sg:city":"Bethesda",
    "sg:classifiers":[
        {
            "category":"Professional",
            "subcategory":"Management & Consulting",
            "type":"Services"
        }
    ],
    "sg:phone":"+1 301 897 2994",
    "sg:postcode":"20814",
    "sg:province":"MD",
    "sg:tags":[
        "construction"
    ],
    "wof:name":"SDM Group",
    "wof:placetype":"venue"
},
  "geometry": {"coordinates":[-77.093666,39.028873],"type":"Point"}
}