{
  "type": "Feature",
  "properties": {
    "iso:country":"US",
    "sg:address":"1059 S. Charles Street",
    "sg:city":"Baltimore",
    "sg:classifiers":[
        {
            "category":"Real Estate",
            "subcategory":"Real Estate Services",
            "type":"Services"
        }
    ],
    "sg:phone":"+1 443 451 5310",
    "sg:postcode":"21230",
    "sg:province":"MD",
    "sg:tags":[
        "management"
    ],
    "wof:name":"Progressive Properties",
    "wof:placetype":"venue"
},
  "geometry": {"coordinates":[-76.614377,39.276903],"type":"Point"}
}