{
  "type": "Feature",
  "properties": {
    "iso:country":"US",
    "sg:address":"620 Riden St",
    "sg:city":"Odenton",
    "sg:classifiers":[
        {
            "category":"Wholesale",
            "subcategory":"Vending Machines",
            "type":"Manufacturing & Wholesale Goods"
        }
    ],
    "sg:phone":"+1 301 762 7828",
    "sg:postcode":"21113",
    "sg:province":"MD",
    "sg:tags":[
        "merchandise"
    ],
    "wof:name":"Rockville Vending",
    "wof:placetype":"venue"
},
  "geometry": {"coordinates":[-76.70279600000001,39.072332],"type":"Point"}
}