{
  "type": "Feature",
  "properties": {
    "addr:full":"15512 Emerald Way Bowie MD 20716",
    "addr:housenumber":"15512",
    "addr:postcode":"20716",
    "addr:street":"Emerald Way",
    "iso:country":"US",
    "sg:address":"15512 Emerald Way",
    "sg:city":"Bowie",
    "sg:classifiers":[
        {
            "category":"Shopping",
            "subcategory":"Clothing, Apparel, & Fashions",
            "type":"Retail Goods"
        }
    ],
    "sg:phone":"+1 301 805 4002",
    "sg:postcode":"20716",
    "sg:province":"MD",
    "sg:tags":[
        "apparel",
        "accessory",
        "women's"
    ],
    "sg:website":"http://www.anntaylor.com",
    "wof:name":"Ann Taylor",
    "wof:placetype":"venue"
},
  "geometry": {"coordinates":[-76.735365,38.943964],"type":"Point"}
}