{
  "type": "Feature",
  "properties": {
    "iso:country":"US",
    "sg:address":"6477 Whiton Rd",
    "sg:city":"Snow Hill",
    "sg:classifiers":[
        {
            "category":"Insurance",
            "subcategory":"Insurance Agent",
            "type":"Services"
        }
    ],
    "sg:phone":"+1 410 632 0050",
    "sg:postcode":"21863",
    "sg:province":"MD",
    "wof:name":"Brethren Mutual Insurance",
    "wof:placetype":"venue"
},
  "geometry": {"coordinates":[-75.377084,38.229143],"type":"Point"}
}