{
  "type": "Feature",
  "properties": {
    "iso:country":"US",
    "sg:address":"2204 E Monument St",
    "sg:city":"Baltimore",
    "sg:classifiers":[
        {
            "category":"Shopping",
            "subcategory":"Mobile Phones",
            "type":"Retail Goods"
        }
    ],
    "sg:phone":"+1 410 534 0440",
    "sg:postcode":"21205",
    "sg:province":"MD",
    "wof:name":"Boost Mobile",
    "wof:placetype":"venue"
},
  "geometry": {"coordinates":[-76.586484,39.298824],"type":"Point"}
}