{
  "type": "Feature",
  "properties": {
    "addr:full":"1719 Broadway Rd Timonium MD 21093",
    "addr:housenumber":"1719",
    "addr:postcode":"21093",
    "addr:street":"Broadway Rd",
    "iso:country":"US",
    "sg:address":"1719 Broadway Rd",
    "sg:city":"Timonium",
    "sg:classifiers":[
        {
            "category":"Social Services",
            "type":"Services"
        }
    ],
    "sg:phone":"+1 410 252 9563",
    "sg:postcode":"21093",
    "sg:province":"MD",
    "sg:tags":[
        "counselor",
        "marriage",
        "family"
    ],
    "wof:name":"Terrell Adsit",
    "wof:placetype":"venue"
},
  "geometry": {"coordinates":[-76.71020799999999,39.44656],"type":"Point"}
}