{
  "type": "Feature",
  "properties": {
    "addr:full":"908 Hackberry Ct Bel Air MD 21014",
    "addr:housenumber":"908",
    "addr:postcode":"21014",
    "addr:street":"Hackberry Ct",
    "iso:country":"US",
    "sg:address":"908 Hackberry Ct",
    "sg:city":"Bel Air",
    "sg:classifiers":[
        {
            "category":"Health Services",
            "subcategory":"Health Practitioner",
            "type":"Services"
        }
    ],
    "sg:phone":"+1 410 838 9411",
    "sg:postcode":"21014",
    "sg:province":"MD",
    "sg:tags":[
        "nurse",
        "registry"
    ],
    "wof:name":"In Good Hands Private Duty Nur",
    "wof:placetype":"venue"
},
  "geometry": {"coordinates":[-76.324061,39.531514],"type":"Point"}
}