{
  "type": "Feature",
  "properties": {
    "addr:full":"11642 Baltimore Ave Beltsville MD 20705",
    "addr:housenumber":"11642",
    "addr:postcode":"20705",
    "addr:street":"Baltimore Ave",
    "iso:country":"US",
    "sg:address":"11642 Baltimore Ave",
    "sg:city":"Beltsville",
    "sg:classifiers":[
        {
            "category":"Professional",
            "subcategory":"Management & Consulting",
            "type":"Services"
        }
    ],
    "sg:phone":"+1 301 572 7165",
    "sg:postcode":"20705",
    "sg:province":"MD",
    "sg:tags":[
        "consultant",
        "government"
    ],
    "wof:name":"E G & G Astrophysics",
    "wof:placetype":"venue"
},
  "geometry": {"coordinates":[-76.90204900000001,39.045357],"type":"Point"}
}