{
  "type": "Feature",
  "properties": {
    "addr:full":"2809 Moorgate Rd Dundalk MD 21222",
    "addr:housenumber":"2809",
    "addr:postcode":"21222",
    "addr:street":"Moorgate Rd",
    "iso:country":"US",
    "sg:address":"2809 Moorgate Rd",
    "sg:city":"Dundalk",
    "sg:classifiers":[
        {
            "category":"Professional",
            "subcategory":"Secretarial Services",
            "type":"Services"
        }
    ],
    "sg:phone":"+1 410 288 1755",
    "sg:postcode":"21222",
    "sg:province":"MD",
    "sg:tags":[
        "reporting",
        "court"
    ],
    "wof:name":"A Scribe Professional Svc",
    "wof:placetype":"venue"
},
  "geometry": {"coordinates":[-76.502863,39.262156],"type":"Point"}
}