{
  "type": "Feature",
  "properties": {
    "addr:full":"4624 S Chelsea Ln Bethesda MD 20814",
    "addr:housenumber":"4624",
    "addr:postcode":"20814",
    "addr:street":"S Chelsea Ln",
    "iso:country":"US",
    "sg:address":"4624 S Chelsea Ln",
    "sg:city":"Bethesda",
    "sg:classifiers":[
        {
            "category":"Professional",
            "subcategory":"Engineering",
            "type":"Services"
        }
    ],
    "sg:phone":"+1 301 986 0119",
    "sg:postcode":"20814",
    "sg:province":"MD",
    "sg:tags":[
        "engineer"
    ],
    "wof:name":"Geo Logics Corp",
    "wof:placetype":"venue"
},
  "geometry": {"coordinates":[-77.094899,38.994043],"type":"Point"}
}