{
  "type": "Feature",
  "properties": {
    "iso:country":"US",
    "sg:address":"4441 Buckeystown Pike",
    "sg:city":"Frederick",
    "sg:classifiers":[
        {
            "category":"Building & Trades",
            "subcategory":"Plumbing",
            "type":"Services"
        }
    ],
    "sg:phone":"+1 301 874 0909",
    "sg:postcode":"21704",
    "sg:province":"MD",
    "sg:tags":[
        "plumbing",
        "contractor"
    ],
    "sg:website":"www.hughessupply.com",
    "wof:name":"Hughes Supply",
    "wof:placetype":"venue"
},
  "geometry": {"coordinates":[-77.421701,39.356051],"type":"Point"}
}