{
  "type": "Feature",
  "properties": {
    "iso:country":"US",
    "sg:address":"6655 Belair Rd",
    "sg:city":"Baltimore",
    "sg:classifiers":[
        {
            "category":"Professional",
            "subcategory":"Credit Reporting & Collection",
            "type":"Services"
        }
    ],
    "sg:phone":"+1 410 444 7118",
    "sg:postcode":"21206",
    "sg:province":"MD",
    "sg:tags":[
        "agency"
    ],
    "wof:name":"Frost & Assoc",
    "wof:placetype":"venue"
},
  "geometry": {"coordinates":[-76.531277,39.354011],"type":"Point"}
}