{
  "type": "Feature",
  "properties": {
    "iso:country":"US",
    "sg:address":"125 Slade Ave",
    "sg:city":"Pikesville",
    "sg:classifiers":[
        {
            "category":"Insurance",
            "subcategory":"Hazard Insurance",
            "type":"Services"
        }
    ],
    "sg:phone":"+1 410 372 0888",
    "sg:postcode":"21208",
    "sg:province":"MD",
    "sg:website":"www.laninguyen.com",
    "wof:name":"Lani Nguyen Insurance Agency, State Farm",
    "wof:placetype":"venue"
},
  "geometry": {"coordinates":[-76.715371,39.365711],"type":"Point"}
}