{
  "type": "Feature",
  "properties": {
    "iso:country":"US",
    "sg:address":"500 Edgewood Rd",
    "sg:city":"Edgewood",
    "sg:classifiers":[
        {
            "category":"Professional",
            "type":"Services"
        }
    ],
    "sg:phone":"+1 410 676 9200",
    "sg:postcode":"21040",
    "sg:province":"MD",
    "sg:tags":[
        "establishment"
    ],
    "wof:name":"BAI Inc",
    "wof:placetype":"venue"
},
  "geometry": {"coordinates":[-76.294912,39.422449],"type":"Point"}
}