{
  "type": "Feature",
  "properties": {
    "addr:full":"4323 Rosedale Ave Bethesda MD 20814",
    "addr:housenumber":"4323",
    "addr:postcode":"20814",
    "addr:street":"Rosedale Ave",
    "iso:country":"US",
    "sg:address":"4323 Rosedale Ave",
    "sg:city":"Bethesda",
    "sg:classifiers":[
        {
            "category":"Professional",
            "subcategory":"Secretarial Services",
            "type":"Services"
        }
    ],
    "sg:phone":"+1 301 951 0926",
    "sg:postcode":"20814",
    "sg:province":"MD",
    "sg:tags":[
        "reporting"
    ],
    "wof:name":"A Plus Word Processing Service",
    "wof:placetype":"venue"
},
  "geometry": {"coordinates":[-77.085058,38.992284],"type":"Point"}
}