{
  "type": "Feature",
  "properties": {
    "addr:full":"215 S 3rd St Oakland MD 21550",
    "addr:housenumber":"215",
    "addr:postcode":"21550",
    "addr:street":"S 3Rd St",
    "iso:country":"US",
    "sg:address":"215 S 3rd St",
    "sg:city":"Oakland",
    "sg:classifiers":[
        {
            "category":"Organizations",
            "subcategory":"Non-profit Organization",
            "type":"Services"
        }
    ],
    "sg:phone":"+1 301 334 8445",
    "sg:postcode":"21550",
    "sg:province":"MD",
    "wof:name":"Western Maryland Consortium-Op",
    "wof:placetype":"venue"
},
  "geometry": {"coordinates":[-79.407264,39.407589],"type":"Point"}
}