{
  "type": "Feature",
  "properties": {
    "iso:country":"US",
    "sg:address":"118 N Main St",
    "sg:city":"Federalsburg",
    "sg:classifiers":[
        {
            "category":"Government",
            "subcategory":"Office",
            "type":"Public Place"
        }
    ],
    "sg:phone":"+1 410 754 5871",
    "sg:postcode":"21632",
    "sg:province":"MD",
    "sg:tags":[
        "village"
    ],
    "wof:name":"Federalsburg Code Enforcement",
    "wof:placetype":"venue"
},
  "geometry": {"coordinates":[-75.77391,38.695175],"type":"Point"}
}