{
  "type": "Feature",
  "properties": {
    "iso:country":"US",
    "sg:address":"16041 Beechnut Dr",
    "sg:city":"Brandywine",
    "sg:classifiers":[
        {
            "category":"Professional",
            "type":"Services"
        }
    ],
    "sg:phone":"+1 301 843 1869",
    "sg:postcode":"20613",
    "sg:province":"MD",
    "sg:tags":[
        "establishment"
    ],
    "wof:name":"A Professional Resume & Wrtng",
    "wof:placetype":"venue"
},
  "geometry": {"coordinates":[-76.750335,38.580294],"type":"Point"}
}