{
  "type": "Feature",
  "properties": {
    "addr:full":"3243 Walnut Dr Highland Beach MD 21403",
    "addr:housenumber":"3243",
    "addr:postcode":"21403",
    "addr:street":"Walnut Dr",
    "iso:country":"US",
    "sg:address":"3243 Walnut Dr",
    "sg:city":"Highland Beach",
    "sg:classifiers":[
        {
            "category":"Government",
            "subcategory":"Office",
            "type":"Public Place"
        }
    ],
    "sg:phone":"+1 410 268 2956",
    "sg:postcode":"21403",
    "sg:province":"MD",
    "sg:tags":[
        "village"
    ],
    "wof:name":"Town Of Highland Beach",
    "wof:placetype":"venue"
},
  "geometry": {"coordinates":[-76.468424,38.930374],"type":"Point"}
}