{
  "type": "Feature",
  "properties": {
    "iso:country":"US",
    "sg:address":"7859 Cessna Ave",
    "sg:city":"Gaithersburg",
    "sg:classifiers":[
        {
            "category":"Retail",
            "subcategory":"Auto Repair",
            "type":"Services"
        }
    ],
    "sg:phone":"+1 301 258 8888",
    "sg:postcode":"20879",
    "sg:province":"MD",
    "sg:tags":[
        "repairing",
        "automobile"
    ],
    "wof:name":"J & R Auto Svc Inc",
    "wof:placetype":"venue"
},
  "geometry": {"coordinates":[-77.161005,39.171903],"type":"Point"}
}