{
  "type": "Feature",
  "properties": {
    "iso:country":"US",
    "sg:address":"4100 Olney Laytonsville Rd",
    "sg:city":"Olney",
    "sg:classifiers":[
        {
            "category":"Place Of Worship",
            "subcategory":"Church",
            "type":"Public Place"
        },
        {
            "category":"Place Of Worship",
            "type":"Public Place"
        },
        {
            "category":"Education",
            "subcategory":"School",
            "type":"Public Place"
        }
    ],
    "sg:phone":"+1 301 570 2500",
    "sg:postcode":"20832",
    "sg:province":"MD",
    "sg:tags":[
        "christian",
        "churches-advent",
        "k-",
        "private",
        "churches-seventh-day",
        "adventist"
    ],
    "sg:website":"http://www.olneyprep.org",
    "wof:name":"Olney Adventist Preparatory School",
    "wof:placetype":"venue"
},
  "geometry": {"coordinates":[-77.07955200000001,39.160961],"type":"Point"}
}