{
  "type": "Feature",
  "properties": {
    "addr:full":"8800 Walther Blvd Ste 1 Parkville MD 21234",
    "addr:housenumber":"8800",
    "addr:postcode":"21234",
    "addr:street":"Walther Blvd Ste 1",
    "iso:country":"US",
    "sg:address":"8800 Walther Blvd Ste 1",
    "sg:city":"Parkville",
    "sg:classifiers":[
        {
            "category":"Health Services",
            "subcategory":"Nursing And Care Facility",
            "type":"Services"
        },
        {
            "category":"Social Services",
            "subcategory":"Adult Care",
            "type":"Services"
        }
    ],
    "sg:phone":"+1 410 665 7043",
    "sg:postcode":"21234",
    "sg:province":"MD",
    "sg:tags":[
        "living",
        "nurses-home",
        "assisted",
        "rest",
        "elder",
        "home"
    ],
    "wof:name":"Oak Crest Village",
    "wof:placetype":"venue"
},
  "geometry": {"coordinates":[-76.506157,39.391201],"type":"Point"}
}