{
  "type": "Feature",
  "properties": {
    "iso:country":"US",
    "sg:address":"500 Hopewell Rd",
    "sg:city":"Rising Sun",
    "sg:classifiers":[
        {
            "category":"Education",
            "subcategory":"School",
            "type":"Public Place"
        }
    ],
    "sg:phone":"+1 410 658 5925",
    "sg:postcode":"21911",
    "sg:province":"MD",
    "sg:website":"www.ccps.org",
    "wof:name":"Rising Sun Elementary School",
    "wof:placetype":"venue"
},
  "geometry": {"coordinates":[-76.064864,39.681151],"type":"Point"}
}