{
  "type": "Feature",
  "properties": {
    "addr:full":"24365 Nanticoke Rd Quantico MD 21856",
    "addr:postcode":"24365;21856",
    "addr:street":"Nanticoke Rd",
    "iso:country":"US",
    "sg:address":"24365 Nanticoke Rd",
    "sg:city":"Quantico",
    "sg:classifiers":[
        {
            "category":"Shopping",
            "type":"Retail Goods"
        }
    ],
    "sg:phone":"+1 410 543 9210",
    "sg:postcode":"21856",
    "sg:province":"MD",
    "sg:tags":[
        "merchandise"
    ],
    "wof:name":"C L Hillsinger The Shop",
    "wof:placetype":"venue"
},
  "geometry": {"coordinates":[-75.770055,38.35246],"type":"Point"}
}