{
  "type": "Feature",
  "properties": {
    "iso:country":"US",
    "sg:address":"787 Oella Ave",
    "sg:city":"Ellicott City",
    "sg:classifiers":[
        {
            "category":"Social Services",
            "subcategory":"Adult Care",
            "type":"Services"
        }
    ],
    "sg:phone":"+1 443 325 7777",
    "sg:postcode":"21043",
    "sg:province":"MD",
    "sg:tags":[
        "residential"
    ],
    "wof:name":"Infinity More",
    "wof:placetype":"venue"
},
  "geometry": {"coordinates":[-76.78027899999999,39.274671],"type":"Point"}
}