{
  "type": "Feature",
  "properties": {
    "addr:full":"14650 Baltimore Ave Laurel MD 20707",
    "addr:housenumber":"14650",
    "addr:postcode":"20707",
    "addr:street":"Baltimore Ave",
    "iso:country":"US",
    "sg:address":"14650 Baltimore Ave",
    "sg:city":"Laurel",
    "sg:classifiers":[
        {
            "category":"Restaurant",
            "type":"Food & Drink"
        }
    ],
    "sg:menulink":"http://www.allmenus.com/md/laurel/13813-olive-garden-italian-restaurant/menu/",
    "sg:phone":"+1 301 498 0881",
    "sg:postcode":"20707",
    "sg:province":"MD",
    "sg:tags":[
        "italian"
    ],
    "wof:name":"Olive Garden Italian Restaurant",
    "wof:placetype":"venue"
},
  "geometry": {"coordinates":[-76.85832499999999,39.09053],"type":"Point"}
}