{
  "type": "Feature",
  "properties": {
    "addr:full":"322 E Antietam St Hagerstown MD 21740",
    "addr:housenumber":"322",
    "addr:postcode":"21740",
    "addr:street":"E Antietam St",
    "iso:country":"US",
    "sg:address":"322 E Antietam St",
    "sg:city":"Hagerstown",
    "sg:classifiers":[
        {
            "category":"Banks & Credit Unions",
            "subcategory":"Investment Brokerage",
            "type":"Services"
        },
        {
            "category":"Banks & Credit Unions",
            "subcategory":"Financial Services",
            "type":"Services"
        }
    ],
    "sg:phone":"+1 301 733 4107",
    "sg:postcode":"21740",
    "sg:province":"MD",
    "sg:tags":[
        "advisory",
        "planner"
    ],
    "wof:name":"Capital T Partners",
    "wof:placetype":"venue"
},
  "geometry": {"coordinates":[-77.71432799999999,39.637603],"type":"Point"}
}