{
  "type": "Feature",
  "properties": {
    "addr:full":"112 Carriage Ln Queenstown MD 21658",
    "addr:housenumber":"112",
    "addr:postcode":"21658",
    "addr:street":"Carriage Ln",
    "iso:country":"US",
    "sg:address":"112 Carriage Ln",
    "sg:city":"Queenstown",
    "sg:classifiers":[
        {
            "category":"Professional",
            "type":"Services"
        }
    ],
    "sg:phone":"+1 410 827 5915",
    "sg:postcode":"21658",
    "sg:province":"MD",
    "wof:name":"Carol Rowan",
    "wof:placetype":"venue"
},
  "geometry": {"coordinates":[-76.153311,38.974516],"type":"Point"}
}