{
  "type": "Feature",
  "properties": {
    "iso:country":"US",
    "sg:address":"9005 Chevrolet Dr",
    "sg:city":"Ellicott City",
    "sg:classifiers":[
        {
            "category":"Health Services",
            "subcategory":"Dentist",
            "type":"Services"
        }
    ],
    "sg:phone":"+1 410 465 5253",
    "sg:postcode":"21042",
    "sg:province":"MD",
    "sg:tags":[
        "orthodontist"
    ],
    "wof:name":"Schoenbrodt Frederick Orthodntst",
    "wof:placetype":"venue"
},
  "geometry": {"coordinates":[-76.82260100000001,39.275299],"type":"Point"}
}