{
  "type": "Feature",
  "properties": {
    "addr:full":"8027 Corporate Dr Baltimore MD 21236",
    "addr:housenumber":"8027",
    "addr:postcode":"21236",
    "addr:street":"Corporate Dr",
    "iso:country":"US",
    "sg:address":"8027 Corporate Dr",
    "sg:city":"Baltimore",
    "sg:classifiers":[
        {
            "category":"Retail",
            "subcategory":"Auto Rental",
            "type":"Services"
        }
    ],
    "sg:phone":"+1 410 931 8786",
    "sg:postcode":"21236",
    "sg:province":"MD",
    "sg:tags":[
        "renting",
        "automobile"
    ],
    "wof:name":"Budget Rent A Car",
    "wof:placetype":"venue"
},
  "geometry": {"coordinates":[-76.467928,39.369912],"type":"Point"}
}