{
  "type": "Feature",
  "properties": {
    "addr:full":"12 E Patrick St Frederick MD 21701",
    "addr:housenumber":"12",
    "addr:postcode":"21701",
    "addr:street":"E Patrick St",
    "iso:country":"US",
    "sg:address":"12 E Patrick St",
    "sg:city":"Frederick",
    "sg:classifiers":[
        {
            "category":"Food & Beverages",
            "subcategory":"Bakery",
            "type":"Retail Goods"
        }
    ],
    "sg:phone":"+1 301 668 2303",
    "sg:postcode":"21701",
    "sg:province":"MD",
    "sg:tags":[
        "shop",
        "coffee",
        "baker"
    ],
    "sg:website":"http://proofbakery.com",
    "wof:name":"Proof Artisan Bakery & Barista",
    "wof:placetype":"venue"
},
  "geometry": {"coordinates":[-77.410764,39.414152],"type":"Point"}
}