{
  "type": "Feature",
  "properties": {
    "addr:full":"9 S Bridge St Elkton MD 21921",
    "addr:housenumber":"9",
    "addr:postcode":"21921",
    "addr:street":"S Bridge St",
    "iso:country":"US",
    "sg:address":"9 S Bridge St",
    "sg:city":"Elkton",
    "sg:classifiers":[
        {
            "category":"Health Services",
            "subcategory":"Clinic",
            "type":"Services"
        },
        {
            "category":"Health Services",
            "subcategory":"Health Practitioner",
            "type":"Services"
        }
    ],
    "sg:phone":"+1 410 392 0115",
    "sg:postcode":"21921",
    "sg:province":"MD",
    "sg:tags":[
        "therapist",
        "therapy",
        "physical"
    ],
    "wof:name":"Pro Physical Therapy",
    "wof:placetype":"venue"
},
  "geometry": {"coordinates":[-75.83223700000001,39.60556],"type":"Point"}
}