{
  "type": "Feature",
  "properties": {
    "iso:country":"US",
    "sg:address":"400 Central Ave",
    "sg:city":"Brunswick",
    "sg:classifiers":[
        {
            "category":"Education",
            "subcategory":"School",
            "type":"Public Place"
        }
    ],
    "sg:phone":"+1 240 236 2900",
    "sg:postcode":"21716",
    "sg:province":"MD",
    "sg:tags":[
        "high",
        "middle",
        "elementary"
    ],
    "wof:name":"Frederick County Public Schools",
    "wof:placetype":"venue"
},
  "geometry": {"coordinates":[-77.633698,39.318699],"type":"Point"}
}