{
  "type": "Feature",
  "properties": {
    "addr:full":"134 Industry Ln Forest Hill MD 21050",
    "addr:housenumber":"134",
    "addr:postcode":"21050",
    "addr:street":"Industry Ln",
    "iso:country":"US",
    "sg:address":"134 Industry Ln",
    "sg:city":"Forest Hill",
    "sg:classifiers":[
        {
            "category":"Real Estate",
            "subcategory":"Real Estate Services",
            "type":"Services"
        }
    ],
    "sg:phone":"+1 410 838 1212",
    "sg:postcode":"21050",
    "sg:province":"MD",
    "sg:tags":[
        "company",
        "title"
    ],
    "wof:name":"Equitable Settlement Svc",
    "wof:placetype":"venue"
},
  "geometry": {"coordinates":[-76.37332499999999,39.578001],"type":"Point"}
}