{
  "type": "Feature",
  "properties": {
    "addr:full":"30 Maryland Ave Annapolis MD 21401",
    "addr:housenumber":"30",
    "addr:postcode":"21401",
    "addr:street":"Maryland Ave",
    "iso:country":"US",
    "sg:address":"30 Maryland Ave",
    "sg:city":"Annapolis",
    "sg:classifiers":[
        {
            "category":"Real Estate",
            "subcategory":"Real Estate Agent",
            "type":"Services"
        }
    ],
    "sg:phone":"+1 410 570 3205",
    "sg:postcode":"21401",
    "sg:province":"MD",
    "sg:tags":[
        "management"
    ],
    "wof:name":"Janert Co",
    "wof:placetype":"venue"
},
  "geometry": {"coordinates":[-76.488641,38.981079],"type":"Point"}
}