{
  "type": "Feature",
  "properties": {
    "addr:full":"101 N Salisbury Blvd Salisbury MD 21801",
    "addr:housenumber":"101",
    "addr:postcode":"21801",
    "addr:street":"N Salisbury Blvd",
    "iso:country":"US",
    "sg:address":"101 N Salisbury Blvd",
    "sg:city":"Salisbury",
    "sg:classifiers":[
        {
            "category":"Food & Beverages",
            "subcategory":"Groceries & Convenience Stores",
            "type":"Retail Goods"
        }
    ],
    "sg:phone":"+1 410 219 2635",
    "sg:postcode":"21801",
    "sg:province":"MD",
    "sg:website":"www.royalfarms.com",
    "wof:name":"Royal Farms",
    "wof:placetype":"venue"
},
  "geometry": {"coordinates":[-75.59554799999999,38.367329],"type":"Point"}
}