{
  "type": "Feature",
  "properties": {
    "addr:full":"412 Carvel Beach Rd Baltimore MD 21226",
    "addr:housenumber":"412",
    "addr:postcode":"21226",
    "addr:street":"Carvel Beach Rd",
    "iso:country":"US",
    "sg:address":"412 Carvel Beach Rd",
    "sg:city":"Baltimore",
    "sg:classifiers":[
        {
            "category":"Banks & Credit Unions",
            "subcategory":"Bank",
            "type":"Services"
        }
    ],
    "sg:phone":"+1 410 437 4361",
    "sg:postcode":"21226",
    "sg:province":"MD",
    "sg:tags":[
        "loan",
        "real estate"
    ],
    "wof:name":"Chesapeak Discount Mortgage",
    "wof:placetype":"venue"
},
  "geometry": {"coordinates":[-76.536047,39.169274],"type":"Point"}
}