{
  "type": "Feature",
  "properties": {
    "iso:country":"US",
    "sg:address":"14203 Park Center Drive Suite 308",
    "sg:city":"Laurel",
    "sg:classifiers":[
        {
            "category":"Professional",
            "subcategory":"Art Services",
            "type":"Services"
        }
    ],
    "sg:phone":"+1 301 776 2812",
    "sg:postcode":"20707",
    "sg:province":"MD",
    "sg:tags":[
        "graphic",
        "design"
    ],
    "sg:website":"www.deverdesigns.com",
    "wof:name":"Dever Designs",
    "wof:placetype":"venue"
},
  "geometry": {"coordinates":[-76.878643,39.084505],"type":"Point"}
}