{
  "type": "Feature",
  "properties": {
    "iso:country":"US",
    "sg:address":"7719 Beachnut Rd",
    "sg:city":"Capitol Heights",
    "sg:classifiers":[
        {
            "category":"Professional",
            "subcategory":"Management & Consulting",
            "type":"Services"
        }
    ],
    "sg:phone":"+1 301 693 3321",
    "sg:postcode":"20743",
    "sg:province":"MD",
    "sg:tags":[
        "educational"
    ],
    "wof:name":"Barbara Futrell",
    "wof:placetype":"venue"
},
  "geometry": {"coordinates":[-76.877275,38.877868],"type":"Point"}
}