{
  "type": "Feature",
  "properties": {
    "iso:country":"US",
    "sg:address":"13801 York Rd",
    "sg:city":"Cockeysville",
    "sg:classifiers":[
        {
            "category":"Communications",
            "subcategory":"Radio Station",
            "type":"Services"
        }
    ],
    "sg:phone":"+1 410 229 0006",
    "sg:postcode":"21030",
    "sg:province":"MD",
    "sg:tags":[
        "educational"
    ],
    "wof:name":"Sarah C Duff",
    "wof:placetype":"venue"
},
  "geometry": {"coordinates":[-76.650136,39.502919],"type":"Point"}
}