{
  "type": "Feature",
  "properties": {
    "iso:country":"US",
    "sg:address":"15298 Union Chapel Rd",
    "sg:city":"Woodbine",
    "sg:classifiers":[
        {
            "category":"Building & Trades",
            "subcategory":"Cleaning & Sanitation",
            "type":"Services"
        }
    ],
    "sg:phone":"+1 410 489 4316",
    "sg:postcode":"21797",
    "sg:province":"MD",
    "sg:tags":[
        "maintenance"
    ],
    "wof:name":"White Oak Properties LLC",
    "wof:placetype":"venue"
},
  "geometry": {"coordinates":[-77.046744,39.291477],"type":"Point"}
}