{
  "type": "Feature",
  "properties": {
    "addr:full":"8119 Liberty Rd Baltimore MD 21244",
    "addr:housenumber":"8119",
    "addr:postcode":"21244",
    "addr:street":"Liberty Rd",
    "iso:country":"US",
    "sg:address":"8119 Liberty Rd",
    "sg:city":"Baltimore",
    "sg:classifiers":[
        {
            "category":"Shopping",
            "subcategory":"Used Merchandise",
            "type":"Retail Goods"
        }
    ],
    "sg:phone":"+1 410 655 6121",
    "sg:postcode":"21244",
    "sg:province":"MD",
    "wof:name":"Classic Decor",
    "wof:placetype":"venue"
},
  "geometry": {"coordinates":[-76.760783,39.354583],"type":"Point"}
}