{
  "type": "Feature",
  "properties": {
    "iso:country":"US",
    "sg:address":"4905 Ocean Gateway",
    "sg:city":"Vienna",
    "sg:classifiers":[
        {
            "category":"Education",
            "subcategory":"School",
            "type":"Public Place"
        }
    ],
    "sg:phone":"+1 410 376 3151",
    "sg:postcode":"21869",
    "sg:province":"MD",
    "sg:website":"www.viennaschool.com",
    "wof:name":"Vienna Elementary School",
    "wof:placetype":"venue"
},
  "geometry": {"coordinates":[-75.832342,38.488602],"type":"Point"}
}