{
  "type": "Feature",
  "properties": {
    "addr:full":"10815 Topbranch Ln Columbia MD 21044",
    "addr:housenumber":"10815",
    "addr:postcode":"21044",
    "addr:street":"Topbranch Ln",
    "iso:country":"US",
    "sg:address":"10815 Topbranch Ln",
    "sg:city":"Columbia",
    "sg:classifiers":[
        {
            "category":"Professional",
            "subcategory":"Business Services",
            "type":"Services"
        }
    ],
    "sg:phone":"+1 410 772 0140",
    "sg:postcode":"21044",
    "sg:province":"MD",
    "wof:name":"Debra L Norman",
    "wof:placetype":"venue"
},
  "geometry": {"coordinates":[-76.88758199999999,39.210244],"type":"Point"}
}