{
  "type": "Feature",
  "properties": {
    "iso:country":"US",
    "sg:address":"8576 Laureldale Dr",
    "sg:city":"Laurel",
    "sg:classifiers":[
        {
            "category":"Manufacturing",
            "subcategory":"Toys & Sporting Goods",
            "type":"Manufacturing & Wholesale Goods"
        }
    ],
    "sg:phone":"+1 301 776 3365",
    "sg:postcode":"20724",
    "sg:province":"MD",
    "sg:tags":[
        "fund",
        "game",
        "raising",
        "mdse"
    ],
    "wof:name":"Antonelli's Pro Fundraisers",
    "wof:placetype":"venue"
},
  "geometry": {"coordinates":[-76.8216,39.101245],"type":"Point"}
}