{
  "type": "Feature",
  "properties": {
    "addr:full":"5408 Silver Hill Rd Forestville MD 20747",
    "addr:housenumber":"5408",
    "addr:postcode":"20747",
    "addr:street":"Silver Hill Rd",
    "iso:country":"US",
    "sg:address":"5408 Silver Hill Rd",
    "sg:city":"Forestville",
    "sg:classifiers":[
        {
            "category":"Social Services",
            "type":"Services"
        }
    ],
    "sg:phone":"+1 301 420 6100",
    "sg:postcode":"20747",
    "sg:province":"MD",
    "sg:tags":[
        "probation"
    ],
    "sg:website":"www.dpscs.state.md.us",
    "wof:name":"Parole & Probation Office",
    "wof:placetype":"venue"
},
  "geometry": {"coordinates":[-76.911839,38.852824],"type":"Point"}
}