{
  "type": "Feature",
  "properties": {
    "addr:full":"6 Bell Bluff Ct Gaithersburg MD 20879",
    "addr:housenumber":"6",
    "addr:postcode":"20879",
    "addr:street":"Bell Bluff Ct",
    "iso:country":"US",
    "sg:address":"6 Bell Bluff Ct",
    "sg:city":"Gaithersburg",
    "sg:classifiers":[
        {
            "category":"Professional",
            "subcategory":"Secretarial Services",
            "type":"Services"
        }
    ],
    "sg:phone":"+1 301 216 2210",
    "sg:postcode":"20879",
    "sg:province":"MD",
    "sg:tags":[
        "reporting"
    ],
    "wof:name":"Roberta A Dolos",
    "wof:placetype":"venue"
},
  "geometry": {"coordinates":[-77.200901,39.194391],"type":"Point"}
}