{
  "type": "Feature",
  "properties": {
    "addr:full":"38050 Indian Creek Dr Charlotte Hall MD 20622",
    "addr:housenumber":"38050",
    "addr:postcode":"20622",
    "addr:street":"Indian Creek Dr",
    "iso:country":"US",
    "sg:address":"38050 Indian Creek Dr",
    "sg:city":"Charlotte Hall",
    "sg:classifiers":[
        {
            "category":"Building & Trades",
            "subcategory":"Construction",
            "type":"Services"
        }
    ],
    "sg:phone":"+1 301 266 6245",
    "sg:postcode":"20622",
    "sg:province":"MD",
    "sg:tags":[
        "painter"
    ],
    "wof:name":"Avery Atelier",
    "wof:placetype":"venue"
},
  "geometry": {"coordinates":[-76.76467599999999,38.505058],"type":"Point"}
}