{
  "type": "Feature",
  "properties": {
    "addr:full":"300 Byrn St Cambridge MD 21613",
    "addr:housenumber":"300",
    "addr:postcode":"21613",
    "addr:street":"Byrn St",
    "iso:country":"US",
    "sg:address":"300 Byrn St",
    "sg:city":"Cambridge",
    "sg:classifiers":[
        {
            "category":"Restaurant",
            "type":"Food & Drink"
        }
    ],
    "sg:phone":"+1 410 228 5511",
    "sg:postcode":"21613",
    "sg:province":"MD",
    "sg:website":"http://www.sodexo.com",
    "wof:name":"Sodexo, Inc.",
    "wof:placetype":"venue"
},
  "geometry": {"coordinates":[-76.068764,38.570911],"type":"Point"}
}