{
  "type": "Feature",
  "properties": {
    "iso:country":"US",
    "sg:address":"5402 McKinley St",
    "sg:city":"Bethesda",
    "sg:classifiers":[
        {
            "category":"Health Services",
            "subcategory":"Doctor",
            "type":"Services"
        }
    ],
    "sg:phone":"+1 301 564 0300",
    "sg:postcode":"20817",
    "sg:province":"MD",
    "sg:tags":[
        "physician",
        "surgeon"
    ],
    "wof:name":"Cosmetic Surgery LTD",
    "wof:placetype":"venue"
},
  "geometry": {"coordinates":[-77.111716,38.996212],"type":"Point"}
}