{
  "type": "Feature",
  "properties": {
    "addr:full":"1911 Rockville Pike Rockville MD 20852",
    "addr:housenumber":"1911",
    "addr:postcode":"20852",
    "addr:street":"Rockville Pike",
    "iso:country":"US",
    "sg:address":"1911 Rockville Pike",
    "sg:city":"Rockville",
    "sg:classifiers":[
        {
            "category":"Autos & Motor Vehicles",
            "subcategory":"Fuel & Gas Station",
            "type":"Retail Goods"
        }
    ],
    "sg:phone":"+1 301 881 6481",
    "sg:postcode":"20852",
    "sg:province":"MD",
    "sg:tags":[
        "oil"
    ],
    "wof:name":"Shell",
    "wof:placetype":"venue"
},
  "geometry": {"coordinates":[-77.12084900000001,39.058189],"type":"Point"}
}