{
  "type": "Feature",
  "properties": {
    "iso:country":"US",
    "sg:address":"6917 Richards Ave",
    "sg:city":"Baltimore",
    "sg:classifiers":[
        {
            "category":"Professional",
            "subcategory":"Business Services",
            "type":"Services"
        }
    ],
    "sg:phone":"+1 410 298 3713",
    "sg:postcode":"21244",
    "sg:province":"MD",
    "sg:tags":[
        "drafting"
    ],
    "wof:name":"Personal Cadd Svc",
    "wof:placetype":"venue"
},
  "geometry": {"coordinates":[-76.753484,39.320974],"type":"Point"}
}