{
  "type": "Feature",
  "properties": {
    "iso:country":"US",
    "sg:address":"8640 Guilford Rd",
    "sg:city":"Columbia",
    "sg:classifiers":[
        {
            "category":"Personal",
            "subcategory":"Barber",
            "type":"Services"
        }
    ],
    "sg:phone":"+1 410 290 6960",
    "sg:postcode":"21046",
    "sg:province":"MD",
    "wof:name":"Master Barber",
    "wof:placetype":"venue"
},
  "geometry": {"coordinates":[-76.864304,39.171101],"type":"Point"}
}