{
  "type": "Feature",
  "properties": {
    "iso:country":"US",
    "sg:address":"8 Market Space",
    "sg:city":"Annapolis",
    "sg:classifiers":[
        {
            "category":"Restaurant",
            "type":"Food & Drink"
        }
    ],
    "sg:phone":"+1 410 263 5700",
    "sg:postcode":"21401",
    "sg:province":"MD",
    "sg:website":"www.mcgarveyssaloon.com",
    "wof:name":"Mc Garvey's Saloon",
    "wof:placetype":"venue"
},
  "geometry": {"coordinates":[-76.486814,38.978009],"type":"Point"}
}