{
  "type": "Feature",
  "properties": {
    "iso:country":"US",
    "sg:address":"9145 Guilford Rd",
    "sg:city":"Columbia",
    "sg:classifiers":[
        {
            "category":"Shopping",
            "subcategory":"Pharmacy",
            "type":"Retail Goods"
        }
    ],
    "sg:phone":"+1 301 490 2128",
    "sg:postcode":"21046",
    "sg:province":"MD",
    "wof:name":"Blue Mountain Apothecary",
    "wof:placetype":"venue"
},
  "geometry": {"coordinates":[-76.84910600000001,39.169901],"type":"Point"}
}