{
  "type": "Feature",
  "properties": {
    "addr:full":"2931 Whittington Ave Baltimore MD 21230",
    "addr:housenumber":"2931",
    "addr:postcode":"21230",
    "addr:street":"Whittington Ave",
    "iso:country":"US",
    "sg:address":"2931 Whittington Ave",
    "sg:city":"Baltimore",
    "sg:classifiers":[
        {
            "category":"Manufacturing",
            "subcategory":"Metals",
            "type":"Manufacturing & Wholesale Goods"
        }
    ],
    "sg:phone":"+1 410 525 1293",
    "sg:postcode":"21230",
    "sg:province":"MD",
    "sg:tags":[
        "steel",
        "erectors"
    ],
    "wof:name":"Grubb Steel Erection Incorporated, W. O.",
    "wof:placetype":"venue"
},
  "geometry": {"coordinates":[-76.65660099999999,39.259129],"type":"Point"}
}