{
  "type": "Feature",
  "properties": {
    "iso:country":"US",
    "sg:address":"14901 N Bel Air Dr SW",
    "sg:city":"Cumberland",
    "sg:classifiers":[
        {
            "category":"Utilities",
            "subcategory":"Telephone",
            "type":"Services"
        }
    ],
    "sg:phone":"+1 301 729 0495",
    "sg:postcode":"21502",
    "sg:province":"MD",
    "sg:tags":[
        "communications"
    ],
    "wof:name":"Rapp Sales",
    "wof:placetype":"venue"
},
  "geometry": {"coordinates":[-78.86189899999999,39.583459],"type":"Point"}
}