{
  "type": "Feature",
  "properties": {
    "iso:country":"US",
    "sg:address":"10015 Old Columbia Road Suite B215",
    "sg:city":"Columbia",
    "sg:classifiers":[
        {
            "category":"Professional",
            "subcategory":"Accounting & Tax Preparation",
            "type":"Services"
        }
    ],
    "sg:phone":"+1 443 927 9161",
    "sg:postcode":"21046",
    "sg:province":"MD",
    "sg:tags":[
        "accountant"
    ],
    "sg:website":"www.ramlcpa.com",
    "wof:name":"Travis Raml, CPA",
    "wof:placetype":"venue"
},
  "geometry": {"coordinates":[-76.859095,39.174408],"type":"Point"}
}