{
  "type": "Feature",
  "properties": {
    "addr:full":"19211 Montgomery Village Ave Gaithersburg MD 20886",
    "addr:housenumber":"19211",
    "addr:postcode":"20886",
    "addr:street":"Montgomery Village Ave",
    "iso:country":"US",
    "sg:address":"19211 Montgomery Village Ave",
    "sg:city":"Gaithersburg",
    "sg:classifiers":[
        {
            "category":"Health Services",
            "subcategory":"Doctor",
            "type":"Services"
        }
    ],
    "sg:phone":"+1 301 948 8780",
    "sg:postcode":"20886",
    "sg:province":"MD",
    "sg:tags":[
        "physician",
        "surgeon"
    ],
    "wof:name":"Frekko Primary Care",
    "wof:placetype":"venue"
},
  "geometry": {"coordinates":[-77.203886,39.171473],"type":"Point"}
}