{
  "type": "Feature",
  "properties": {
    "addr:full":"3725 Federal Hill Rd Jarrettsville MD 21084",
    "addr:housenumber":"3725",
    "addr:postcode":"21084",
    "addr:street":"Federal Hill Rd",
    "iso:country":"US",
    "sg:address":"3725 Federal Hill Rd",
    "sg:city":"Jarrettsville",
    "sg:classifiers":[
        {
            "category":"Home & Garden",
            "subcategory":"Carpets & Floor Coverings",
            "type":"Retail Goods"
        }
    ],
    "sg:phone":"+1 410 692 5757",
    "sg:postcode":"21084",
    "sg:province":"MD",
    "wof:name":"Jarrettsville Floor Covering",
    "wof:placetype":"venue"
},
  "geometry": {"coordinates":[-76.477862,39.607316],"type":"Point"}
}