{
  "type": "Feature",
  "properties": {
    "iso:country":"US",
    "sg:address":"7758 Wisconsin Ave",
    "sg:city":"Bethesda",
    "sg:classifiers":[
        {
            "category":"Professional",
            "subcategory":"Lawyer & Legal Services",
            "type":"Services"
        }
    ],
    "sg:phone":"+1 301 656 1640",
    "sg:postcode":"20814",
    "sg:province":"MD",
    "wof:name":"Albert A Lakeland Lawyer",
    "wof:placetype":"venue"
},
  "geometry": {"coordinates":[-77.09504800000001,38.987767],"type":"Point"}
}