{
  "type": "Feature",
  "properties": {
    "iso:country":"US",
    "sg:address":"9011 Chevrolet Dr",
    "sg:city":"Ellicott City",
    "sg:classifiers":[
        {
            "category":"Personal",
            "subcategory":"Beauty Salon",
            "type":"Services"
        }
    ],
    "sg:phone":"+1 410 461 5818",
    "sg:postcode":"21042",
    "sg:province":"MD",
    "wof:name":"Jenny's Hair Salon",
    "wof:placetype":"venue"
},
  "geometry": {"coordinates":[-76.825355,39.275298],"type":"Point"}
}