{
  "type": "Feature",
  "properties": {
    "addr:full":"8415 Kelso Dr Essex MD 21221",
    "addr:housenumber":"8415",
    "addr:postcode":"21221",
    "addr:street":"Kelso Dr",
    "iso:country":"US",
    "sg:address":"8415 Kelso Dr",
    "sg:city":"Essex",
    "sg:classifiers":[
        {
            "category":"Freight",
            "type":"Transportation"
        }
    ],
    "sg:phone":"+1 410 574 0999",
    "sg:postcode":"21221",
    "sg:province":"MD",
    "sg:tags":[
        "commercial",
        "storage"
    ],
    "wof:name":"Public Storage",
    "wof:placetype":"venue"
},
  "geometry": {"coordinates":[-76.487847,39.32573],"type":"Point"}
}