{
  "type": "Feature",
  "properties": {
    "iso:country":"US",
    "sg:address":"1023 Spa Rd",
    "sg:city":"Annapolis",
    "sg:classifiers":[
        {
            "category":"Retail",
            "subcategory":"Auto Repair",
            "type":"Services"
        }
    ],
    "sg:phone":"+1 410 263 4650",
    "sg:postcode":"21403",
    "sg:province":"MD",
    "sg:tags":[
        "body",
        "automobile",
        "painting"
    ],
    "wof:name":"Annapolis Radiator & Body Shop",
    "wof:placetype":"venue"
},
  "geometry": {"coordinates":[-76.511793,38.968894],"type":"Point"}
}