{
  "type": "Feature",
  "properties": {
    "iso:country":"US",
    "sg:address":"11224 Triangle Ln",
    "sg:city":"Wheaton",
    "sg:classifiers":[
        {
            "category":"Food & Beverages",
            "subcategory":"Groceries & Convenience Stores",
            "type":"Retail Goods"
        }
    ],
    "sg:phone":"+1 301 949 4150",
    "sg:postcode":"20902",
    "sg:province":"MD",
    "sg:tags":[
        "grocer"
    ],
    "wof:name":"Marchone's Italian Deli",
    "wof:placetype":"venue"
},
  "geometry": {"coordinates":[-77.052087,39.040219],"type":"Point"}
}