{
  "type": "Feature",
  "properties": {
    "addr:full":"3940 Conowingo Rd Darlington MD 21034",
    "addr:housenumber":"3940",
    "addr:postcode":"21034",
    "addr:street":"Conowingo Rd",
    "iso:country":"US",
    "sg:address":"3940 Conowingo Rd",
    "sg:city":"Darlington",
    "sg:classifiers":[
        {
            "category":"Personal",
            "subcategory":"Tattoo Parlor",
            "type":"Services"
        }
    ],
    "sg:phone":"+1 410 457 5001",
    "sg:postcode":"21034",
    "sg:province":"MD",
    "sg:tags":[
        "tattooing"
    ],
    "wof:name":"Artistic Armor Tattooing",
    "wof:placetype":"venue"
},
  "geometry": {"coordinates":[-76.24711000000001,39.647401],"type":"Point"}
}