{
  "type": "Feature",
  "properties": {
    "iso:country":"US",
    "sg:address":"12585 Olde Mill Rd",
    "sg:city":"Charlotte Hall",
    "sg:classifiers":[
        {
            "category":"Wholesale",
            "subcategory":"Farm Supplies",
            "type":"Manufacturing & Wholesale Goods"
        }
    ],
    "sg:phone":"+1 301 934 4105",
    "sg:postcode":"20622",
    "sg:province":"MD",
    "sg:tags":[
        "grain"
    ],
    "wof:name":"Wicomico Grain Elevator",
    "wof:placetype":"venue"
},
  "geometry": {"coordinates":[-76.87738,38.412654],"type":"Point"}
}