{
  "type": "Feature",
  "properties": {
    "addr:full":"563 N Le Moyne King Rd Oakland MD 21550",
    "addr:housenumber":"563",
    "addr:postcode":"21550",
    "addr:street":"N Le Moyne King Rd",
    "iso:country":"US",
    "sg:address":"563 N Le Moyne King Rd",
    "sg:city":"Oakland",
    "sg:classifiers":[
        {
            "category":"Real Estate",
            "subcategory":"Real Estate Operator",
            "type":"Services"
        }
    ],
    "sg:phone":"+1 301 334 3979",
    "sg:postcode":"21550",
    "sg:province":"MD",
    "sg:tags":[
        "farm",
        "property",
        "dairy",
        "lessor"
    ],
    "wof:name":"Kearney Ridge Farm",
    "wof:placetype":"venue"
},
  "geometry": {"coordinates":[-79.326095,39.333763],"type":"Point"}
}