{
  "type": "Feature",
  "properties": {
    "iso:country":"US",
    "sg:address":"7064 Hanover Pkwy",
    "sg:city":"Greenbelt",
    "sg:classifiers":[
        {
            "category":"Professional",
            "type":"Services"
        }
    ],
    "sg:phone":"+1 301 982 1998",
    "sg:postcode":"20770",
    "sg:province":"MD",
    "wof:name":"Rashida Atobatele",
    "wof:placetype":"venue"
},
  "geometry": {"coordinates":[-76.877744,38.98784],"type":"Point"}
}