{
  "type": "Feature",
  "properties": {
    "iso:country":"US",
    "sg:address":"1502 S Salisbury Blvd",
    "sg:city":"Salisbury",
    "sg:classifiers":[
        {
            "category":"Restaurant",
            "type":"Food & Drink"
        }
    ],
    "sg:phone":"+1 410 749 5515",
    "sg:postcode":"21801",
    "sg:province":"MD",
    "wof:name":"Lighthouse Diner II",
    "wof:placetype":"venue"
},
  "geometry": {"coordinates":[-75.606621,38.339377],"type":"Point"}
}