{
  "type": "Feature",
  "properties": {
    "iso:country":"US",
    "sg:address":"1705 Reisterstown Rd",
    "sg:city":"Pikesville",
    "sg:classifiers":[
        {
            "category":"Professional",
            "subcategory":"Business Services",
            "type":"Services"
        }
    ],
    "sg:phone":"+1 410 653 2567",
    "sg:postcode":"21208",
    "sg:province":"MD",
    "wof:name":"Assoc For Jewish Outreach Pro",
    "wof:placetype":"venue"
},
  "geometry": {"coordinates":[-76.730269,39.381409],"type":"Point"}
}