{
  "type": "Feature",
  "properties": {
    "addr:full":"The Back Room at Glen Echo 7300 Macarthur Blvd Glen Echo MD 20812",
    "addr:housenumber":"7300",
    "addr:postcode":"20812",
    "addr:street":"Macarthur Blvd",
    "iso:country":"US",
    "sg:address":"The Back Room at Glen Echo 7300 Macarthur Blvd",
    "sg:city":"Glen Echo",
    "sg:classifiers":[
        {
            "category":"Recreation",
            "subcategory":"Dance Hall",
            "type":"Entertainment"
        }
    ],
    "sg:postcode":"20812",
    "sg:province":"MD",
    "sg:tags":[
        "club"
    ],
    "sg:website":"www.capitalblues.org/dances/back...",
    "wof:name":"Blues Dance",
    "wof:placetype":"venue"
},
  "geometry": {"coordinates":[-77.139664,38.968955],"type":"Point"}
}