{
  "type": "Feature",
  "properties": {
    "iso:country":"US",
    "sg:address":"4915 Holder Ave",
    "sg:city":"Baltimore",
    "sg:classifiers":[
        {
            "category":"Education",
            "subcategory":"Preschool",
            "type":"Public Place"
        },
        {
            "category":"Education",
            "subcategory":"School",
            "type":"Public Place"
        },
        {
            "category":"Government",
            "subcategory":"Office",
            "type":"Public Place"
        }
    ],
    "sg:phone":"+1 410 444 9267",
    "sg:postcode":"21214",
    "sg:province":"MD",
    "sg:tags":[
        "kindergarten",
        "parish",
        "k-",
        "high",
        "middle",
        "private",
        "elementary",
        "government-county"
    ],
    "wof:name":"Zion Christian Middle School",
    "wof:placetype":"venue"
},
  "geometry": {"coordinates":[-76.56220999999999,39.343221],"type":"Point"}
}