{
  "type": "Feature",
  "properties": {
    "iso:country":"US",
    "sg:address":"5315 85th Ave",
    "sg:city":"Hyattsville",
    "sg:classifiers":[
        {
            "category":"Professional",
            "subcategory":"Business Services",
            "type":"Services"
        }
    ],
    "sg:phone":"+1 301 459 0330",
    "sg:postcode":"20784",
    "sg:province":"MD",
    "wof:name":"Detco Group",
    "wof:placetype":"venue"
},
  "geometry": {"coordinates":[-76.868889,38.954575],"type":"Point"}
}