{
  "type": "Feature",
  "properties": {
    "addr:full":"304 Wyndhurst Ave Baltimore MD 21210",
    "addr:housenumber":"304",
    "addr:postcode":"21210",
    "addr:street":"Wyndhurst Ave",
    "iso:country":"US",
    "sg:address":"304 Wyndhurst Ave",
    "sg:city":"Baltimore",
    "sg:classifiers":[
        {
            "category":"Shopping",
            "subcategory":"Computers & Home Electronics",
            "type":"Retail Goods"
        }
    ],
    "sg:phone":"+1 410 435 5100",
    "sg:postcode":"21210",
    "sg:province":"MD",
    "sg:tags":[
        "software"
    ],
    "wof:name":"Noetic Systems Inc",
    "wof:placetype":"venue"
},
  "geometry": {"coordinates":[-76.62858300000001,39.353561],"type":"Point"}
}