{
  "type": "Feature",
  "properties": {
    "addr:full":"3701 Sweet Air Rd Phoenix MD 21131",
    "addr:housenumber":"3701",
    "addr:postcode":"21131",
    "addr:street":"Sweet Air Rd",
    "iso:country":"US",
    "sg:address":"3701 Sweet Air Rd",
    "sg:city":"Phoenix",
    "sg:classifiers":[
        {
            "category":"Organizations",
            "subcategory":"Religious Organization",
            "type":"Services"
        }
    ],
    "sg:phone":"+1 410 592 9121",
    "sg:postcode":"21131",
    "sg:province":"MD",
    "sg:tags":[
        "church"
    ],
    "wof:name":"Chestnut Grove Presbyterian",
    "wof:placetype":"venue"
},
  "geometry": {"coordinates":[-76.546874,39.513609],"type":"Point"}
}