{
  "type": "Feature",
  "properties": {
    "iso:country":"US",
    "sg:address":"513 Park Ave",
    "sg:city":"Baltimore",
    "sg:classifiers":[
        {
            "category":"Building & Trades",
            "subcategory":"Construction",
            "type":"Services"
        }
    ],
    "sg:phone":"+1 410 727 0200",
    "sg:postcode":"21201",
    "sg:province":"MD",
    "sg:tags":[
        "contractor"
    ],
    "wof:name":"Concord Associates Inc",
    "wof:placetype":"venue"
},
  "geometry": {"coordinates":[-76.618369,39.29562],"type":"Point"}
}