{
  "type": "Feature",
  "properties": {
    "iso:country":"US",
    "sg:address":"100 E Pennsylvania Ave",
    "sg:city":"Towson",
    "sg:classifiers":[
        {
            "category":"Professional",
            "subcategory":"Management & Consulting",
            "type":"Services"
        },
        {
            "category":"Professional",
            "subcategory":"Advertising",
            "type":"Services"
        },
        {
            "category":"Professional",
            "subcategory":"Business Services",
            "type":"Services"
        }
    ],
    "sg:phone":"+1 410 825 5378",
    "sg:postcode":"21286",
    "sg:province":"MD",
    "sg:tags":[
        "consultant",
        "program",
        "coach",
        "marketing"
    ],
    "wof:name":"Consumer Value Network",
    "wof:placetype":"venue"
},
  "geometry": {"coordinates":[-76.601158,39.40033],"type":"Point"}
}