{
  "type": "Feature",
  "properties": {
    "iso:country":"US",
    "sg:address":"8971 Woodyard Rd",
    "sg:city":"Clinton",
    "sg:classifiers":[
        {
            "category":"Personal",
            "subcategory":"Barber",
            "type":"Services"
        }
    ],
    "sg:phone":"+1 301 868 9891",
    "sg:postcode":"20735",
    "sg:province":"MD",
    "sg:tags":[
        "shop"
    ],
    "wof:name":"Clinton Barber Shop",
    "wof:placetype":"venue"
},
  "geometry": {"coordinates":[-76.89147699999999,38.766733],"type":"Point"}
}