{
  "type": "Feature",
  "properties": {
    "addr:full":"1782 N Market St Frederick MD 21701",
    "addr:housenumber":"1782",
    "addr:postcode":"21701",
    "addr:street":"N Market St",
    "iso:country":"US",
    "sg:address":"1782 N Market St",
    "sg:city":"Frederick",
    "sg:classifiers":[
        {
            "category":"Building & Trades",
            "subcategory":"Plumbing",
            "type":"Services"
        }
    ],
    "sg:phone":"+1 301 662 2515",
    "sg:postcode":"21701",
    "sg:province":"MD",
    "sg:tags":[
        "conditioning",
        "air",
        "system",
        "contractor"
    ],
    "sg:website":"www.watolbard.com",
    "wof:name":"W A Tolbard Refrigeration",
    "wof:placetype":"venue"
},
  "geometry": {"coordinates":[-77.398685,39.439807],"type":"Point"}
}