{
  "type": "Feature",
  "properties": {
    "iso:country":"US",
    "sg:address":"8651 Cherry Ln",
    "sg:city":"Laurel",
    "sg:classifiers":[
        {
            "category":"Insurance",
            "subcategory":"Insurance Agent",
            "type":"Services"
        }
    ],
    "sg:phone":"+1 301 725 6669",
    "sg:postcode":"20707",
    "sg:province":"MD",
    "wof:name":"Patuxent Financial Group",
    "wof:placetype":"venue"
},
  "geometry": {"coordinates":[-76.855702,39.090224],"type":"Point"}
}