{
  "type": "Feature",
  "properties": {
    "addr:full":"207 Market St Pocomoke City MD 21851",
    "addr:housenumber":"207",
    "addr:postcode":"21851",
    "addr:street":"Market St",
    "iso:country":"US",
    "sg:address":"207 Market St",
    "sg:city":"Pocomoke City",
    "sg:classifiers":[
        {
            "category":"Government",
            "subcategory":"Post Office",
            "type":"Public Place"
        }
    ],
    "sg:phone":"+1 410 957 1620",
    "sg:postcode":"21851",
    "sg:province":"MD",
    "wof:name":"US Post Office",
    "wof:placetype":"venue"
},
  "geometry": {"coordinates":[-75.567927,38.075062],"type":"Point"}
}