{
  "type": "Feature",
  "properties": {
    "addr:full":"2942 Beaver Brook Ct Pasadena MD 21122",
    "addr:housenumber":"2942",
    "addr:postcode":"21122",
    "addr:street":"Beaver Brook Ct",
    "iso:country":"US",
    "sg:address":"2942 Beaver Brook Ct",
    "sg:city":"Pasadena",
    "sg:classifiers":[
        {
            "category":"Building & Trades",
            "subcategory":"Construction",
            "type":"Services"
        }
    ],
    "sg:phone":"+1 410 360 9700",
    "sg:postcode":"21122",
    "sg:province":"MD",
    "sg:tags":[
        "general",
        "contractor"
    ],
    "wof:name":"Brewis Construction Inc",
    "wof:placetype":"venue"
},
  "geometry": {"coordinates":[-76.534391,39.137338],"type":"Point"}
}