{
  "type": "Feature",
  "properties": {
    "addr:full":"20758 Park Hall Rd Boonsboro MD 21713",
    "addr:housenumber":"20758",
    "addr:postcode":"21713",
    "addr:street":"Park Hall Rd",
    "iso:country":"US",
    "sg:address":"20758 Park Hall Rd",
    "sg:city":"Boonsboro",
    "sg:classifiers":[
        {
            "category":"Shopping",
            "subcategory":"Crafts & Fabrics",
            "type":"Retail Goods"
        }
    ],
    "sg:phone":"+1 301 432 2033",
    "sg:postcode":"21713",
    "sg:province":"MD",
    "sg:tags":[
        "art",
        "supply"
    ],
    "wof:name":"Brian Elliot",
    "wof:placetype":"venue"
},
  "geometry": {"coordinates":[-77.64118000000001,39.455562],"type":"Point"}
}