{
  "type": "Feature",
  "properties": {
    "iso:country":"US",
    "sg:address":"11832 Rocking Horse Rd",
    "sg:city":"Rockville",
    "sg:classifiers":[
        {
            "category":"Personal",
            "type":"Services"
        },
        {
            "category":"Sports & Exercise",
            "subcategory":"Gym",
            "type":"Entertainment"
        },
        {
            "category":"Arena",
            "subcategory":"Sports Club",
            "type":"Entertainment"
        }
    ],
    "sg:phone":"+1 301 244 8905",
    "sg:postcode":"20852",
    "sg:province":"MD",
    "sg:tags":[
        "trainer",
        "consultant",
        "program",
        "health",
        "fitness",
        "physical"
    ],
    "sg:website":"http://www.yext.com/p/superpages/olympic-fitness-rockville-maryland.html",
    "wof:name":"Olympic Fitness",
    "wof:placetype":"venue"
},
  "geometry": {"coordinates":[-77.097696,39.049316],"type":"Point"}
}