{
  "type": "Feature",
  "properties": {
    "addr:full":"19 Chipouras Rd Edgewater MD 21037",
    "addr:housenumber":"19",
    "addr:postcode":"21037",
    "addr:street":"Chipouras Rd",
    "iso:country":"US",
    "sg:address":"19 Chipouras Rd",
    "sg:city":"Edgewater",
    "sg:classifiers":[
        {
            "category":"Retail",
            "subcategory":"Auto Repair",
            "type":"Services"
        }
    ],
    "sg:phone":"+1 410 956 0923",
    "sg:postcode":"21037",
    "sg:province":"MD",
    "sg:tags":[
        "trailer"
    ],
    "wof:name":"A Trail Rite Trailers",
    "wof:placetype":"venue"
},
  "geometry": {"coordinates":[-76.56427600000001,38.935703],"type":"Point"}
}