{
  "type": "Feature",
  "properties": {
    "iso:country":"US",
    "sg:address":"865 Buckingham Cove Rd",
    "sg:city":"Severna Park",
    "sg:classifiers":[
        {
            "category":"Professional",
            "type":"Services"
        }
    ],
    "sg:phone":"+1 410 328 8655",
    "sg:postcode":"21146",
    "sg:province":"MD",
    "sg:tags":[
        "lecturing"
    ],
    "wof:name":"Karen McQuillan",
    "wof:placetype":"venue"
},
  "geometry": {"coordinates":[-76.525482,39.062419],"type":"Point"}
}