{
  "type": "Feature",
  "properties": {
    "iso:country":"US",
    "sg:address":"18723 Northridge Dr",
    "sg:city":"Hagerstown",
    "sg:classifiers":[
        {
            "category":"Building & Trades",
            "subcategory":"Construction",
            "type":"Services"
        }
    ],
    "sg:phone":"+1 301 393 9336",
    "sg:postcode":"21742",
    "sg:province":"MD",
    "sg:tags":[
        "general",
        "contractor"
    ],
    "wof:name":"Brownstone Construction Co",
    "wof:placetype":"venue"
},
  "geometry": {"coordinates":[-77.72089,39.694992],"type":"Point"}
}