{
  "type": "Feature",
  "properties": {
    "iso:country":"US",
    "sg:address":"8102 Rosebank Ave",
    "sg:city":"Baltimore",
    "sg:classifiers":[
        {
            "category":"Retail",
            "subcategory":"Auto Repair",
            "type":"Services"
        }
    ],
    "sg:phone":"+1 410 284 0218",
    "sg:postcode":"21222",
    "sg:province":"MD",
    "sg:tags":[
        "wrecker"
    ],
    "wof:name":"M & W Towing",
    "wof:placetype":"venue"
},
  "geometry": {"coordinates":[-76.477598,39.27589],"type":"Point"}
}