{
  "type": "Feature",
  "properties": {
    "addr:full":"6950 Carroll Ave Takoma Park MD 20912",
    "addr:housenumber":"6950",
    "addr:postcode":"20912",
    "addr:street":"Carroll Ave",
    "iso:country":"US",
    "sg:address":"6950 Carroll Ave",
    "sg:city":"Takoma Park",
    "sg:classifiers":[
        {
            "category":"Banks & Credit Unions",
            "subcategory":"Bank",
            "type":"Services"
        }
    ],
    "sg:phone":"+1 301 270 7095",
    "sg:postcode":"20912",
    "sg:province":"MD",
    "wof:name":"Bank Of America",
    "wof:placetype":"venue"
},
  "geometry": {"coordinates":[-77.013763,38.974781],"type":"Point"}
}