{
  "type": "Feature",
  "properties": {
    "iso:country":"US",
    "sg:address":"Union Memorial Hospi",
    "sg:city":"Baltimore",
    "sg:classifiers":[
        {
            "category":"Health Services",
            "subcategory":"Doctor",
            "type":"Services"
        }
    ],
    "sg:phone":"+1 410 554 2072",
    "sg:postcode":"21201",
    "sg:province":"MD",
    "wof:name":"Hildreth Arthur M MD",
    "wof:placetype":"venue"
},
  "geometry": {"coordinates":[-76.622597,39.2957],"type":"Point"}
}