{
  "type": "Feature",
  "properties": {
    "iso:country":"US",
    "sg:address":"4300 Orchard Ridge Blvd",
    "sg:city":"Baltimore",
    "sg:classifiers":[
        {
            "category":"Real Estate",
            "subcategory":"Real Estate Operator",
            "type":"Services"
        }
    ],
    "sg:phone":"+1 410 325 1982",
    "sg:postcode":"21201",
    "sg:province":"MD",
    "sg:tags":[
        "apartment"
    ],
    "wof:name":"Orchard Ridge Rental Homes",
    "wof:placetype":"venue"
},
  "geometry": {"coordinates":[-76.697965,39.252517],"type":"Point"}
}