{
  "type": "Feature",
  "properties": {
    "iso:country":"US",
    "sg:address":"634 Thomas Way",
    "sg:city":"Severna Park",
    "sg:classifiers":[
        {
            "category":"Manufacturing",
            "subcategory":"Printing",
            "type":"Manufacturing & Wholesale Goods"
        }
    ],
    "sg:phone":"+1 410 384 9667",
    "sg:postcode":"21146",
    "sg:province":"MD",
    "sg:tags":[
        "commercial"
    ],
    "wof:name":"Inviting Impressions",
    "wof:placetype":"venue"
},
  "geometry": {"coordinates":[-76.554795,39.079479],"type":"Point"}
}