{
  "type": "Feature",
  "properties": {
    "addr:full":"313 E Alder St Oakland MD 21550",
    "addr:housenumber":"313",
    "addr:postcode":"21550",
    "addr:street":"E Alder St",
    "iso:country":"US",
    "sg:address":"313 E Alder St",
    "sg:city":"Oakland",
    "sg:classifiers":[
        {
            "category":"Professional",
            "type":"Services"
        }
    ],
    "sg:phone":"+1 301 334 2183",
    "sg:postcode":"21550",
    "sg:province":"MD",
    "sg:tags":[
        "processing",
        "data"
    ],
    "wof:name":"Tdec",
    "wof:placetype":"venue"
},
  "geometry": {"coordinates":[-79.406864,39.407851],"type":"Point"}
}