{
  "type": "Feature",
  "properties": {
    "addr:full":"3633 Glengyle Ave Baltimore MD 21215",
    "addr:housenumber":"3633",
    "addr:postcode":"21215",
    "addr:street":"Glengyle Ave",
    "iso:country":"US",
    "sg:address":"3633 Glengyle Ave",
    "sg:city":"Baltimore",
    "sg:classifiers":[
        {
            "category":"Building & Trades",
            "subcategory":"Construction",
            "type":"Services"
        }
    ],
    "sg:phone":"+1 410 764 6916",
    "sg:postcode":"21215",
    "sg:province":"MD",
    "sg:tags":[
        "resurfacing",
        "laying",
        "refinishing",
        "floor"
    ],
    "wof:name":"Floor Finishers",
    "wof:placetype":"venue"
},
  "geometry": {"coordinates":[-76.70703899999999,39.366262],"type":"Point"}
}