{
  "type": "Feature",
  "properties": {
    "iso:country":"US",
    "sg:address":"11605 Edmonston Rd",
    "sg:city":"Beltsville",
    "sg:classifiers":[
        {
            "category":"Building & Trades",
            "subcategory":"Pest Control",
            "type":"Services"
        }
    ],
    "sg:phone":"+1 301 937 8200",
    "sg:postcode":"20705",
    "sg:province":"MD",
    "wof:name":"All Pest Solutions LLC",
    "wof:placetype":"venue"
},
  "geometry": {"coordinates":[-76.897608,39.043193],"type":"Point"}
}