{
  "type": "Feature",
  "properties": {
    "addr:full":"11605 Edmonston Rd Beltsville MD 20705",
    "addr:housenumber":"11605",
    "addr:postcode":"20705",
    "addr:street":"Edmonston Rd",
    "iso:country":"US",
    "sg:address":"11605 Edmonston Rd",
    "sg:city":"Beltsville",
    "sg:classifiers":[
        {
            "category":"Building & Trades",
            "subcategory":"Pest Control",
            "type":"Services"
        }
    ],
    "sg:phone":"+1 301 937 8200",
    "sg:postcode":"20705",
    "sg:province":"MD",
    "wof:name":"All Pest Solutions LLC",
    "wof:placetype":"venue"
},
  "geometry": {"coordinates":[-76.89760800000001,39.043193],"type":"Point"}
}