{
  "type": "Feature",
  "properties": {
    "addr:full":"8955 Edmonston Rd Greenbelt MD 20770",
    "addr:housenumber":"8955",
    "addr:postcode":"20770",
    "addr:street":"Edmonston Rd",
    "iso:country":"US",
    "sg:address":"8955 Edmonston Rd",
    "sg:city":"Greenbelt",
    "sg:classifiers":[
        {
            "category":"Professional",
            "subcategory":"Lawyer & Legal Services",
            "type":"Services"
        }
    ],
    "sg:phone":"+1 301 513 0511",
    "sg:postcode":"20770",
    "sg:province":"MD",
    "sg:tags":[
        "attorney"
    ],
    "wof:name":"Julia Colton-Bell",
    "wof:placetype":"venue"
},
  "geometry": {"coordinates":[-76.90093,38.997851],"type":"Point"}
}