{
  "type": "Feature",
  "properties": {
    "addr:full":"4701 Paul Hance Rd Huntingtown MD 20639",
    "addr:housenumber":"4701",
    "addr:postcode":"20639",
    "addr:street":"Paul Hance Rd",
    "iso:country":"US",
    "sg:address":"4701 Paul Hance Rd",
    "sg:city":"Huntingtown",
    "sg:classifiers":[
        {
            "category":"Professional",
            "subcategory":"Research",
            "type":"Services"
        }
    ],
    "sg:phone":"+1 410 414 5718",
    "sg:postcode":"20639",
    "sg:province":"MD",
    "sg:tags":[
        "market",
        "analysis"
    ],
    "wof:name":"Wedewer Group",
    "wof:placetype":"venue"
},
  "geometry": {"coordinates":[-76.523729,38.599018],"type":"Point"}
}