{
  "type": "Feature",
  "properties": {
    "iso:country":"US",
    "sg:address":"425 N 3rd St",
    "sg:city":"Oakland",
    "sg:classifiers":[
        {
            "category":"Shopping",
            "subcategory":"Computers & Home Electronics",
            "type":"Retail Goods"
        }
    ],
    "sg:phone":"+1 301 334 3439",
    "sg:postcode":"21550",
    "sg:province":"MD",
    "sg:tags":[
        "software"
    ],
    "sg:website":"www.idosoft.com",
    "wof:name":"Ido Soft",
    "wof:placetype":"venue"
},
  "geometry": {"coordinates":[-79.401856,39.416644],"type":"Point"}
}