{
  "type": "Feature",
  "properties": {
    "iso:country":"US",
    "sg:address":"2219 York Rd",
    "sg:city":"Timonium",
    "sg:classifiers":[
        {
            "category":"Professional",
            "subcategory":"Advertising",
            "type":"Services"
        }
    ],
    "sg:phone":"+1 410 453 9826",
    "sg:postcode":"21093",
    "sg:province":"MD",
    "sg:tags":[
        "counselor"
    ],
    "sg:website":"www.pivec.com",
    "wof:name":"Pivec Advertising LTD",
    "wof:placetype":"venue"
},
  "geometry": {"coordinates":[-76.629051,39.446999],"type":"Point"}
}