{
  "type": "Feature",
  "properties": {
    "iso:country":"US",
    "sg:address":"5108 Belair Rd",
    "sg:city":"Baltimore",
    "sg:classifiers":[
        {
            "category":"Health Services",
            "subcategory":"Medical Lab",
            "type":"Services"
        }
    ],
    "sg:phone":"+1 410 488 2727",
    "sg:postcode":"21206",
    "sg:province":"MD",
    "sg:tags":[
        "laboratory",
        "dental",
        "testing"
    ],
    "wof:name":"Paolantonio Dental Lab",
    "wof:placetype":"venue"
},
  "geometry": {"coordinates":[-76.55422799999999,39.336333],"type":"Point"}
}