{
  "type": "Feature",
  "properties": {
    "addr:full":"23 Allegheny Ave Towson MD 21204",
    "addr:housenumber":"23",
    "addr:postcode":"21204",
    "addr:street":"Allegheny Ave",
    "iso:country":"US",
    "sg:address":"23 Allegheny Ave",
    "sg:city":"Towson",
    "sg:classifiers":[
        {
            "category":"Shopping",
            "subcategory":"Clothing, Apparel, & Fashions",
            "type":"Retail Goods"
        },
        {
            "category":"Shopping",
            "subcategory":"Party Supplies",
            "type":"Retail Goods"
        },
        {
            "category":"Manufacturing",
            "subcategory":"Building Materials",
            "type":"Manufacturing & Wholesale Goods"
        },
        {
            "category":"Sports & Exercise",
            "subcategory":"Playing Field",
            "type":"Entertainment"
        },
        {
            "category":"Shopping",
            "subcategory":"Bridal",
            "type":"Retail Goods"
        }
    ],
    "sg:phone":"+1 410 828 4141",
    "sg:postcode":"21204",
    "sg:province":"MD",
    "sg:tags":[
        "repairing",
        "fur",
        "shop",
        "storage",
        "wedding",
        "remodeling"
    ],
    "sg:website":"http://www.kentfisher.com",
    "wof:name":"Kent Fisher Furs",
    "wof:placetype":"venue"
},
  "geometry": {"coordinates":[-76.60286600000001,39.401678],"type":"Point"}
}