{
  "type": "Feature",
  "properties": {
    "addr:full":"3216 Verona Dr Silver Spring MD 20906",
    "addr:housenumber":"3216",
    "addr:postcode":"20906",
    "addr:street":"Verona Dr",
    "iso:country":"US",
    "sg:address":"3216 Verona Dr",
    "sg:city":"Silver Spring",
    "sg:classifiers":[
        {
            "category":"Building & Trades",
            "subcategory":"Landscaping Services",
            "type":"Services"
        }
    ],
    "sg:phone":"+1 301 460 8786",
    "sg:postcode":"20906",
    "sg:province":"MD",
    "sg:tags":[
        "landscape",
        "contractor"
    ],
    "wof:name":"Seven Oaks Lanscaping Inc",
    "wof:placetype":"venue"
},
  "geometry": {"coordinates":[-77.06720199999999,39.075025],"type":"Point"}
}