{
  "type": "Feature",
  "properties": {
    "iso:country":"US",
    "sg:address":"3216 Verona Dr",
    "sg:city":"Silver Spring",
    "sg:classifiers":[
        {
            "category":"Building & Trades",
            "subcategory":"Landscaping Services",
            "type":"Services"
        }
    ],
    "sg:phone":"+1 301 460 8786",
    "sg:postcode":"20906",
    "sg:province":"MD",
    "sg:tags":[
        "landscape",
        "contractor"
    ],
    "wof:name":"Seven Oaks Lanscaping Inc",
    "wof:placetype":"venue"
},
  "geometry": {"coordinates":[-77.067202,39.075025],"type":"Point"}
}