{
  "type": "Feature",
  "properties": {
    "iso:country":"US",
    "sg:address":"10126 Liberty Rd",
    "sg:city":"Randallstown",
    "sg:classifiers":[
        {
            "category":"Building & Trades",
            "subcategory":"Construction",
            "type":"Services"
        }
    ],
    "sg:phone":"+1 410 655 5917",
    "sg:postcode":"21133",
    "sg:province":"MD",
    "sg:tags":[
        "contractor"
    ],
    "wof:name":"C Johnson Building Contractors",
    "wof:placetype":"venue"
},
  "geometry": {"coordinates":[-76.829752,39.384623],"type":"Point"}
}