{
  "type": "Feature",
  "properties": {
    "iso:country":"US",
    "sg:address":"8817 Annapolis Rd",
    "sg:city":"Lanham",
    "sg:classifiers":[
        {
            "category":"Wholesale",
            "subcategory":"Office Equipment",
            "type":"Manufacturing & Wholesale Goods"
        }
    ],
    "sg:phone":"+1 301 731 1962",
    "sg:postcode":"20706",
    "sg:province":"MD",
    "sg:tags":[
        "machine",
        "duplicating",
        "copying"
    ],
    "wof:name":"Metro Copiers",
    "wof:placetype":"venue"
},
  "geometry": {"coordinates":[-76.862918,38.961299],"type":"Point"}
}