{
  "type": "Feature",
  "properties": {
    "addr:full":"2 N Belnord Ave Baltimore MD 21224",
    "addr:housenumber":"2",
    "addr:postcode":"21224",
    "addr:street":"N Belnord Ave",
    "iso:country":"US",
    "sg:address":"2 N Belnord Ave",
    "sg:city":"Baltimore",
    "sg:classifiers":[
        {
            "category":"Organizations",
            "subcategory":"Religious Organization",
            "type":"Services"
        }
    ],
    "sg:phone":"+1 410 675 8260",
    "sg:postcode":"21224",
    "sg:province":"MD",
    "sg:tags":[
        "church"
    ],
    "wof:name":"St Elizabeth's Parish",
    "wof:placetype":"venue"
},
  "geometry": {"coordinates":[-76.578405,39.293305],"type":"Point"}
}