{
  "type": "Feature",
  "properties": {
    "iso:country":"US",
    "sg:address":"13527 Catoctin Furnace Rd",
    "sg:city":"Thurmont",
    "sg:classifiers":[
        {
            "category":"Arts & Performance",
            "subcategory":"Theater",
            "type":"Entertainment"
        }
    ],
    "sg:phone":"+1 301 271 3127",
    "sg:postcode":"21788",
    "sg:province":"MD",
    "sg:tags":[
        "group"
    ],
    "wof:name":"Culler Magic",
    "wof:placetype":"venue"
},
  "geometry": {"coordinates":[-77.42381899999999,39.603966],"type":"Point"}
}