{
  "type": "Feature",
  "properties": {
    "iso:country":"US",
    "sg:address":"812 Geipe Rd",
    "sg:city":"Catonsville",
    "sg:phone":"+1 410 744 1090",
    "sg:postcode":"21228",
    "sg:province":"MD",
    "wof:name":"Kyung Lee T-A Supreme Wash Car Wash",
    "wof:placetype":"venue"
},
  "geometry": {"coordinates":[-76.755376,39.281183],"type":"Point"}
}