{
  "type": "Feature",
  "properties": {
    "iso:country":"US",
    "sg:address":"14102 Arctic Ave",
    "sg:city":"Rockville",
    "sg:classifiers":[
        {
            "category":"Professional",
            "subcategory":"Management & Consulting",
            "type":"Services"
        }
    ],
    "sg:phone":"+1 301 871 5516",
    "sg:postcode":"20853",
    "sg:province":"MD",
    "sg:tags":[
        "consultant"
    ],
    "wof:name":"Harris H Shettel",
    "wof:placetype":"venue"
},
  "geometry": {"coordinates":[-77.095038,39.086931],"type":"Point"}
}