{
  "type": "Feature",
  "properties": {
    "iso:country":"US",
    "sg:address":"3133 W Belvedere Ave",
    "sg:city":"Baltimore",
    "sg:classifiers":[
        {
            "category":"Restaurant",
            "type":"Food & Drink"
        }
    ],
    "sg:phone":"+1 410 542 3125",
    "sg:postcode":"21215",
    "sg:province":"MD",
    "wof:name":"A & A's Caribbean American Carry Out",
    "wof:placetype":"venue"
},
  "geometry": {"coordinates":[-76.67559799999999,39.348999],"type":"Point"}
}