{
  "type": "Feature",
  "properties": {
    "iso:country":"US",
    "sg:address":"337 Hospital Dr",
    "sg:city":"Glen Burnie",
    "sg:classifiers":[
        {
            "category":"Shopping",
            "subcategory":"Optical Goods",
            "type":"Retail Goods"
        }
    ],
    "sg:phone":"+1 410 761 7673",
    "sg:postcode":"21061",
    "sg:province":"MD",
    "wof:name":"Clark Appler & Optical",
    "wof:placetype":"venue"
},
  "geometry": {"coordinates":[-76.624373,39.139447],"type":"Point"}
}