{
  "type": "Feature",
  "properties": {
    "addr:full":"7133 Rutherford Rd Baltimore MD 21244",
    "addr:housenumber":"7133",
    "addr:postcode":"21244",
    "addr:street":"Rutherford Rd",
    "iso:country":"US",
    "sg:address":"7133 Rutherford Rd",
    "sg:city":"Baltimore",
    "sg:classifiers":[
        {
            "category":"Social Services",
            "subcategory":"Adult Care",
            "type":"Services"
        }
    ],
    "sg:phone":"+1 410 277 9170",
    "sg:postcode":"21244",
    "sg:province":"MD",
    "sg:tags":[
        "home",
        "group"
    ],
    "wof:name":"Tuttie's Place",
    "wof:placetype":"venue"
},
  "geometry": {"coordinates":[-76.74715500000001,39.327774],"type":"Point"}
}