{
  "type": "Feature",
  "properties": {
    "addr:full":"6913 Belair Rd Baltimore MD 21206",
    "addr:housenumber":"6913",
    "addr:postcode":"21206",
    "addr:street":"Belair Rd",
    "iso:country":"US",
    "sg:address":"6913 Belair Rd",
    "sg:city":"Baltimore",
    "sg:classifiers":[
        {
            "category":"Professional",
            "subcategory":"Lawyer & Legal Services",
            "type":"Services"
        },
        {
            "category":"Shopping",
            "subcategory":"Pharmacy",
            "type":"Retail Goods"
        }
    ],
    "sg:phone":"+1 410 665 5192",
    "sg:postcode":"21206",
    "sg:province":"MD",
    "sg:tags":[
        "notary",
        "drugstore"
    ],
    "wof:name":"Kaye's Epic Pharmacy",
    "wof:placetype":"venue"
},
  "geometry": {"coordinates":[-76.528099,39.357201],"type":"Point"}
}