{
  "type": "Feature",
  "properties": {
    "addr:full":"1100 Parsons Rd Salisbury MD 21801",
    "addr:housenumber":"1100",
    "addr:postcode":"21801",
    "addr:street":"Parsons Rd",
    "iso:country":"US",
    "sg:address":"1100 Parsons Rd",
    "sg:city":"Salisbury",
    "sg:classifiers":[
        {
            "category":"Autos & Motor Vehicles",
            "subcategory":"Automobile Sales",
            "type":"Retail Goods"
        }
    ],
    "sg:phone":"+1 410 749 7744",
    "sg:postcode":"21801",
    "sg:province":"MD",
    "sg:tags":[
        "car",
        "dealer"
    ],
    "wof:name":"Prestigious Auto's",
    "wof:placetype":"venue"
},
  "geometry": {"coordinates":[-75.61648099999999,38.3664],"type":"Point"}
}