{
  "type": "Feature",
  "properties": {
    "iso:country":"US",
    "sg:address":"13406 Oriental St",
    "sg:city":"Rockville",
    "sg:classifiers":[
        {
            "category":"Insurance",
            "subcategory":"Insurance Agent",
            "type":"Services"
        }
    ],
    "sg:phone":"+1 301 933 6555",
    "sg:postcode":"20853",
    "sg:province":"MD",
    "wof:name":"John X Supinski Insurance",
    "wof:placetype":"venue"
},
  "geometry": {"coordinates":[-77.096954,39.075423],"type":"Point"}
}