{
  "type": "Feature",
  "properties": {
    "iso:country":"US",
    "sg:address":"555 Prime Outlets Blvd",
    "sg:city":"Hagerstown",
    "sg:classifiers":[
        {
            "category":"Shopping",
            "type":"Retail Goods"
        }
    ],
    "sg:phone":"+1 301 733 7738",
    "sg:postcode":"21740",
    "sg:province":"MD",
    "sg:tags":[
        "factory",
        "outlet"
    ],
    "wof:name":"Corning Revere Factory Store",
    "wof:placetype":"venue"
},
  "geometry": {"coordinates":[-77.730542,39.609745],"type":"Point"}
}