{
  "type": "Feature",
  "properties": {
    "iso:country":"US",
    "sg:address":"401 S Main St",
    "sg:city":"Woodsboro",
    "sg:classifiers":[
        {
            "category":"Manufacturing",
            "subcategory":"Tools & Machinery",
            "type":"Manufacturing & Wholesale Goods"
        }
    ],
    "sg:phone":"+1 301 845 2777",
    "sg:postcode":"21798",
    "sg:province":"MD",
    "sg:tags":[
        "respirator"
    ],
    "sg:website":"www.neoterik.com",
    "wof:name":"Global Secure Safety",
    "wof:placetype":"venue"
},
  "geometry": {"coordinates":[-77.314782,39.530744],"type":"Point"}
}