{
  "type": "Feature",
  "properties": {
    "iso:country":"US",
    "sg:address":"3742 Mcdowell Ln",
    "sg:city":"Halethorpe",
    "sg:classifiers":[
        {
            "category":"Banks & Credit Unions",
            "subcategory":"Financial Services",
            "type":"Services"
        }
    ],
    "sg:phone":"+1 410 878 2470",
    "sg:postcode":"21227",
    "sg:province":"MD",
    "sg:tags":[
        "alternative",
        "loan",
        "mortgage"
    ],
    "sg:website":"http://www.panammortgage.net",
    "wof:name":"Pan Am Mortgage Maryland Divison",
    "wof:placetype":"venue"
},
  "geometry": {"coordinates":[-76.64756199999999,39.240616],"type":"Point"}
}