{
  "type": "Feature",
  "properties": {
    "iso:country":"US",
    "sg:address":"6951 University Rd",
    "sg:city":"Keedysville",
    "sg:classifiers":[
        {
            "category":"Farming",
            "subcategory":"Livestock Farm",
            "type":"Manufacturing & Wholesale Goods"
        }
    ],
    "sg:phone":"+1 301 432 5977",
    "sg:postcode":"21756",
    "sg:province":"MD",
    "sg:tags":[
        "beef",
        "feedlot",
        "cattle"
    ],
    "wof:name":"Richard Lehman",
    "wof:placetype":"venue"
},
  "geometry": {"coordinates":[-77.724523,39.506264],"type":"Point"}
}