{
  "type": "Feature",
  "properties": {
    "addr:full":"6401 N Charles St Baltimore MD 21212",
    "addr:housenumber":"6401",
    "addr:postcode":"21212",
    "addr:street":"N Charles St",
    "iso:country":"US",
    "sg:address":"6401 N Charles St",
    "sg:city":"Baltimore",
    "sg:classifiers":[
        {
            "category":"Organizations",
            "subcategory":"Religious Organization",
            "type":"Services"
        }
    ],
    "sg:phone":"+1 410 377 0355",
    "sg:postcode":"21212",
    "sg:province":"MD",
    "sg:tags":[
        "clergy"
    ],
    "wof:name":"Patricia Murphy",
    "wof:placetype":"venue"
},
  "geometry": {"coordinates":[-76.62633599999999,39.384329],"type":"Point"}
}