{
  "type": "Feature",
  "properties": {
    "addr:full":"8342 Eastern Ave Baltimore MD 21224",
    "addr:housenumber":"8342",
    "addr:postcode":"21224",
    "addr:street":"Eastern Ave",
    "iso:country":"US",
    "sg:address":"8342 Eastern Ave",
    "sg:city":"Baltimore",
    "sg:classifiers":[
        {
            "category":"Personal",
            "type":"Services"
        }
    ],
    "sg:phone":"+1 410 282 5981",
    "sg:postcode":"21224",
    "sg:province":"MD",
    "sg:tags":[
        "control",
        "weight"
    ],
    "wof:name":"Jenny Craig Weight Loss Ctr",
    "wof:placetype":"venue"
},
  "geometry": {"coordinates":[-76.49175,39.300857],"type":"Point"}
}