{
  "type": "Feature",
  "properties": {
    "addr:full":"25 Crossroads Dr Owings Mills MD 21117",
    "addr:housenumber":"25",
    "addr:postcode":"21117",
    "addr:street":"Crossroads Dr",
    "iso:country":"US",
    "sg:address":"25 Crossroads Dr",
    "sg:city":"Owings Mills",
    "sg:classifiers":[
        {
            "category":"Real Estate",
            "subcategory":"Real Estate Services",
            "type":"Services"
        }
    ],
    "sg:phone":"+1 410 998 0888",
    "sg:postcode":"21117",
    "sg:province":"MD",
    "sg:tags":[
        "company",
        "title"
    ],
    "wof:name":"Century Title Co",
    "wof:placetype":"venue"
},
  "geometry": {"coordinates":[-76.75203500000001,39.397132],"type":"Point"}
}