{
  "type": "Feature",
  "properties": {
    "addr:full":"3700 Eastern Ave Baltimore MD 21224",
    "addr:housenumber":"3700",
    "addr:postcode":"21224",
    "addr:street":"Eastern Ave",
    "iso:country":"US",
    "sg:address":"3700 Eastern Ave",
    "sg:city":"Baltimore",
    "sg:classifiers":[
        {
            "category":"Professional",
            "subcategory":"Lawyer & Legal Services",
            "type":"Services"
        }
    ],
    "sg:phone":"+1 410 534 0800",
    "sg:postcode":"21224",
    "sg:province":"MD",
    "wof:name":"Latou Bernice L Lwyr",
    "wof:placetype":"venue"
},
  "geometry": {"coordinates":[-76.56619999999999,39.286598],"type":"Point"}
}