{
  "type": "Feature",
  "properties": {
    "iso:country":"US",
    "sg:address":"541 Ritchie Rd",
    "sg:city":"Capitol Heights",
    "sg:classifiers":[
        {
            "category":"Wholesale",
            "subcategory":"Hardware",
            "type":"Manufacturing & Wholesale Goods"
        }
    ],
    "sg:phone":"+1 301 350 1350",
    "sg:postcode":"20743",
    "sg:province":"MD",
    "sg:tags":[
        "plumbing",
        "fixture",
        "supply"
    ],
    "wof:name":"Ferguson Enterprises Inc",
    "wof:placetype":"venue"
},
  "geometry": {"coordinates":[-76.85956899999999,38.881794],"type":"Point"}
}