{
  "type": "Feature",
  "properties": {
    "iso:country":"US",
    "sg:address":"16077 Frederick Rd",
    "sg:city":"Rockville",
    "sg:classifiers":[
        {
            "category":"Retail",
            "subcategory":"Auto Repair",
            "type":"Services"
        }
    ],
    "sg:phone":"+1 301 975 9848",
    "sg:postcode":"20855",
    "sg:province":"MD",
    "sg:tags":[
        "muffler",
        "exhaust",
        "system"
    ],
    "wof:name":"Midas Auto Svc Experts",
    "wof:placetype":"venue"
},
  "geometry": {"coordinates":[-77.16645,39.115756],"type":"Point"}
}