{
  "type": "Feature",
  "properties": {
    "addr:full":"4601 Presidents Dr Ste 300 Lanham MD 20706",
    "addr:housenumber":"4601",
    "addr:postcode":"20706",
    "addr:street":"Presidents Dr Ste 300",
    "iso:country":"US",
    "sg:address":"4601 Presidents Dr Ste 300",
    "sg:city":"Lanham",
    "sg:classifiers":[
        {
            "category":"Professional",
            "subcategory":"Lawyer & Legal Services",
            "type":"Services"
        }
    ],
    "sg:phone":"+1 301 731 1057",
    "sg:postcode":"20706",
    "sg:province":"MD",
    "wof:name":"Electrical 26 Welfare Trust",
    "wof:placetype":"venue"
},
  "geometry": {"coordinates":[-76.83402,38.952251],"type":"Point"}
}