{
  "type": "Feature",
  "properties": {
    "addr:full":"532 Baltimore Blvd # 307 Westminster MD 21157",
    "addr:housenumber":"532",
    "addr:postcode":"21157",
    "addr:street":"Baltimore Blvd # 307",
    "iso:country":"US",
    "sg:address":"532 Baltimore Blvd # 307",
    "sg:city":"Westminster",
    "sg:classifiers":[
        {
            "category":"Professional",
            "subcategory":"Employment Agencies",
            "type":"Services"
        }
    ],
    "sg:phone":"+1 410 848 0983",
    "sg:postcode":"21157",
    "sg:province":"MD",
    "sg:tags":[
        "employer"
    ],
    "sg:website":"http://www.mstanea.org",
    "wof:name":"Ccea",
    "wof:placetype":"venue"
},
  "geometry": {"coordinates":[-76.978837,39.567612],"type":"Point"}
}