{
  "type": "Feature",
  "properties": {
    "iso:country":"US",
    "sg:address":"1327 Baltimore Pike",
    "sg:city":"Bel Air",
    "sg:classifiers":[
        {
            "category":"Food & Beverages",
            "subcategory":"Meat & Fish",
            "type":"Retail Goods"
        }
    ],
    "sg:phone":"+1 410 420 2222",
    "sg:postcode":"21014",
    "sg:province":"MD",
    "sg:tags":[
        "seafood"
    ],
    "wof:name":"Don's Crabs",
    "wof:placetype":"venue"
},
  "geometry": {"coordinates":[-76.381338,39.507816],"type":"Point"}
}