{
  "type": "Feature",
  "properties": {
    "addr:full":"9428 Garden Ct Potomac MD 20854",
    "addr:housenumber":"9428",
    "addr:postcode":"20854",
    "addr:street":"Garden Ct",
    "iso:country":"US",
    "sg:address":"9428 Garden Ct",
    "sg:city":"Potomac",
    "sg:classifiers":[
        {
            "category":"Professional",
            "subcategory":"Management & Consulting",
            "type":"Services"
        }
    ],
    "sg:phone":"+1 301 765 9551",
    "sg:postcode":"20854",
    "sg:province":"MD",
    "sg:tags":[
        "consultant",
        "business"
    ],
    "wof:name":"Renewal Resources",
    "wof:placetype":"venue"
},
  "geometry": {"coordinates":[-77.213543,39.009314],"type":"Point"}
}