{
  "type": "Feature",
  "properties": {
    "iso:country":"US",
    "sg:address":"8610 Liberty Rd",
    "sg:city":"Randallstown",
    "sg:classifiers":[
        {
            "category":"Restaurant",
            "type":"Food & Drink"
        }
    ],
    "sg:menulink":"http://www.allmenus.com/md/randallstown/173408-wendys/menu/",
    "sg:phone":"+1 410 922 8842",
    "sg:postcode":"21133",
    "sg:province":"MD",
    "sg:tags":[
        "burger",
        "american",
        "soup"
    ],
    "wof:name":"Wendy's",
    "wof:placetype":"venue"
},
  "geometry": {"coordinates":[-76.778958,39.361578],"type":"Point"}
}