{
  "type": "Feature",
  "properties": {
    "iso:country":"US",
    "sg:address":"2504 Burgundy Dr",
    "sg:city":"Fallston",
    "sg:classifiers":[
        {
            "category":"Wholesale",
            "subcategory":"Chemicals & Plastics",
            "type":"Manufacturing & Wholesale Goods"
        }
    ],
    "sg:phone":"+1 410 879 8389",
    "sg:postcode":"21047",
    "sg:province":"MD",
    "wof:name":"Chemcentral Corp",
    "wof:placetype":"venue"
},
  "geometry": {"coordinates":[-76.438401,39.525362],"type":"Point"}
}