{
  "type": "Feature",
  "properties": {
    "iso:country":"US",
    "sg:address":"823 W Lanvale St",
    "sg:city":"Baltimore",
    "sg:classifiers":[
        {
            "category":"Organizations",
            "subcategory":"Religious Organization",
            "type":"Services"
        }
    ],
    "sg:phone":"+1 410 225 7588",
    "sg:postcode":"21217",
    "sg:province":"MD",
    "sg:tags":[
        "church"
    ],
    "wof:name":"Mount Olivet Christian Church",
    "wof:placetype":"venue"
},
  "geometry": {"coordinates":[-76.63372099999999,39.297886],"type":"Point"}
}