{
  "type": "Feature",
  "properties": {
    "iso:country":"US",
    "sg:address":"4451 Parliament Pl",
    "sg:city":"Lanham",
    "sg:classifiers":[
        {
            "category":"Banks & Credit Unions",
            "subcategory":"Bank",
            "type":"Services"
        }
    ],
    "sg:phone":"+1 301 577 3111",
    "sg:postcode":"20706",
    "sg:province":"MD",
    "sg:tags":[
        "loan",
        "real estate"
    ],
    "wof:name":"Mortgage America Co LLC",
    "wof:placetype":"venue"
},
  "geometry": {"coordinates":[-76.837041,38.948832],"type":"Point"}
}