{
  "type": "Feature",
  "properties": {
    "addr:full":"3225 Wilkens Ave Baltimore MD 21229",
    "addr:housenumber":"3225",
    "addr:postcode":"21229",
    "addr:street":"Wilkens Ave",
    "iso:country":"US",
    "sg:address":"3225 Wilkens Ave",
    "sg:city":"Baltimore",
    "sg:classifiers":[
        {
            "category":"Education",
            "subcategory":"School",
            "type":"Public Place"
        }
    ],
    "sg:phone":"+1 410 644 1770",
    "sg:postcode":"21229",
    "sg:province":"MD",
    "sg:tags":[
        "high",
        "middle",
        "elementary"
    ],
    "sg:website":"www.cardinalgibbons.com",
    "wof:name":"Cardinal Gibbons School",
    "wof:placetype":"venue"
},
  "geometry": {"coordinates":[-76.669043,39.274599],"type":"Point"}
}