{
  "type": "Feature",
  "properties": {
    "iso:country":"US",
    "sg:address":"81 Armory Rd",
    "sg:city":"Prince Frederick",
    "sg:classifiers":[
        {
            "category":"Real Estate",
            "subcategory":"Architect",
            "type":"Services"
        }
    ],
    "sg:phone":"+1 410 257 9298",
    "sg:postcode":"20678",
    "sg:province":"MD",
    "wof:name":"Patuxent Architects Inc",
    "wof:placetype":"venue"
},
  "geometry": {"coordinates":[-76.585437,38.548431],"type":"Point"}
}