{
  "type": "Feature",
  "properties": {
    "addr:full":"3715 Branch Ave Temple Hills MD 20748",
    "addr:housenumber":"3715",
    "addr:postcode":"20748",
    "addr:street":"Branch Ave",
    "iso:country":"US",
    "sg:address":"3715 Branch Ave",
    "sg:city":"Temple Hills",
    "sg:classifiers":[
        {
            "category":"Shopping",
            "subcategory":"Clothing, Apparel, & Fashions",
            "type":"Retail Goods"
        }
    ],
    "sg:phone":"+1 301 423 8977",
    "sg:postcode":"20748",
    "sg:province":"MD",
    "wof:name":"Avenue",
    "wof:placetype":"venue"
},
  "geometry": {"coordinates":[-76.948233,38.841556],"type":"Point"}
}