{
  "type": "Feature",
  "properties": {
    "iso:country":"US",
    "sg:address":"4206 Ralph Ave",
    "sg:city":"Hampstead",
    "sg:classifiers":[
        {
            "category":"Building & Trades",
            "subcategory":"Construction",
            "type":"Services"
        }
    ],
    "sg:phone":"+1 410 239 0939",
    "sg:postcode":"21074",
    "sg:province":"MD",
    "sg:tags":[
        "concrete",
        "contractor"
    ],
    "wof:name":"Pro-Crete",
    "wof:placetype":"venue"
},
  "geometry": {"coordinates":[-76.847523,39.600237],"type":"Point"}
}