{
  "type": "Feature",
  "properties": {
    "addr:full":"26 The Strand Sparks Glencoe MD 21152",
    "addr:housenumber":"26",
    "addr:postcode":"21152",
    "addr:street":"The Strand",
    "iso:country":"US",
    "sg:address":"26 The Strand",
    "sg:city":"Sparks Glencoe",
    "sg:classifiers":[
        {
            "category":"Professional",
            "subcategory":"Management & Consulting",
            "type":"Services"
        }
    ],
    "sg:phone":"+1 410 329 3390",
    "sg:postcode":"21152",
    "sg:province":"MD",
    "sg:tags":[
        "marketing",
        "consultant"
    ],
    "wof:name":"Senior Care Resources Fndtn",
    "wof:placetype":"venue"
},
  "geometry": {"coordinates":[-76.636993,39.519429],"type":"Point"}
}