{
  "type": "Feature",
  "properties": {
    "addr:full":"19310 Club House Rd Montgomery Vlg MD 20886",
    "addr:housenumber":"19310",
    "addr:postcode":"20886",
    "addr:street":"Club House Rd",
    "iso:country":"US",
    "sg:address":"19310 Club House Rd",
    "sg:city":"Montgomery Vlg",
    "sg:classifiers":[
        {
            "category":"Social Services",
            "subcategory":"Adult Care",
            "type":"Services"
        }
    ],
    "sg:phone":"+1 301 921 0445",
    "sg:postcode":"20886",
    "sg:province":"MD",
    "sg:tags":[
        "home",
        "residential"
    ],
    "sg:website":"www.sunriseseniorliving.com",
    "wof:name":"Sunrise Independent Living",
    "wof:placetype":"venue"
},
  "geometry": {"coordinates":[-77.201515,39.172495],"type":"Point"}
}