{
  "type": "Feature",
  "properties": {
    "iso:country":"US",
    "sg:address":"700 N Eutaw St",
    "sg:city":"Baltimore",
    "sg:classifiers":[
        {
            "category":"Social Services",
            "type":"Services"
        }
    ],
    "sg:phone":"+1 410 462 2585",
    "sg:postcode":"21201",
    "sg:province":"MD",
    "sg:tags":[
        "shelter",
        "homeless"
    ],
    "wof:name":"South Baltimore Homeless Shltr",
    "wof:placetype":"venue"
},
  "geometry": {"coordinates":[-76.621448,39.297269],"type":"Point"}
}