{
  "type": "Feature",
  "properties": {
    "addr:full":"150 Nichols St Bel Air MD 21014",
    "addr:housenumber":"150",
    "addr:postcode":"21014",
    "addr:street":"Nichols St",
    "iso:country":"US",
    "sg:address":"150 Nichols St",
    "sg:city":"Bel Air",
    "sg:classifiers":[
        {
            "category":"Building & Trades",
            "subcategory":"Construction",
            "type":"Services"
        }
    ],
    "sg:phone":"+1 410 803 2949",
    "sg:postcode":"21014",
    "sg:province":"MD",
    "sg:tags":[
        "contractor"
    ],
    "wof:name":"Car Vel Sales",
    "wof:placetype":"venue"
},
  "geometry": {"coordinates":[-76.358098,39.53843],"type":"Point"}
}