{
  "type": "Feature",
  "properties": {
    "addr:full":"16823 Crabbs Branch Way Rockville MD 20855",
    "addr:housenumber":"16823",
    "addr:postcode":"20855",
    "addr:street":"Crabbs Branch Way",
    "iso:country":"US",
    "sg:address":"16823 Crabbs Branch Way",
    "sg:city":"Rockville",
    "sg:classifiers":[
        {
            "category":"Recreation",
            "type":"Entertainment"
        }
    ],
    "sg:phone":"+1 301 519 7515",
    "sg:postcode":"20855",
    "sg:province":"MD",
    "sg:tags":[
        "karate",
        "judo",
        "instr"
    ],
    "wof:name":"International Martial Arts",
    "wof:placetype":"venue"
},
  "geometry": {"coordinates":[-77.168425,39.130572],"type":"Point"}
}