{
  "type": "Feature",
  "properties": {
    "iso:country":"US",
    "sg:address":"1632 Aliceanna St",
    "sg:city":"Baltimore",
    "sg:classifiers":[
        {
            "category":"Food & Beverages",
            "subcategory":"Groceries & Convenience Stores",
            "type":"Retail Goods"
        }
    ],
    "sg:phone":"+1 410 276 9498",
    "sg:postcode":"21231",
    "sg:province":"MD",
    "sg:tags":[
        "market"
    ],
    "wof:name":"Baltimore Public Markets Corp",
    "wof:placetype":"venue"
},
  "geometry": {"coordinates":[-76.593616,39.283611],"type":"Point"}
}