{
  "type": "Feature",
  "properties": {
    "addr:full":"702 Elk Mills Rd Elk Mills MD 21921",
    "addr:housenumber":"702",
    "addr:postcode":"21921",
    "addr:street":"Elk Mills Rd",
    "iso:country":"US",
    "sg:address":"702 Elk Mills Rd",
    "sg:city":"Elk Mills",
    "sg:classifiers":[
        {
            "category":"Building & Trades",
            "subcategory":"Construction",
            "type":"Services"
        }
    ],
    "sg:phone":"+1 410 392 3733",
    "sg:postcode":"21921",
    "sg:province":"MD",
    "sg:tags":[
        "railroad",
        "contractor"
    ],
    "sg:website":"www.rescar.com",
    "wof:name":"Rescar",
    "wof:placetype":"venue"
},
  "geometry": {"coordinates":[-75.82623599999999,39.658513],"type":"Point"}
}