{
  "type": "Feature",
  "properties": {
    "addr:full":"7 Robinson Rd Severna Park MD 21146",
    "addr:housenumber":"7",
    "addr:postcode":"21146",
    "addr:street":"Robinson Rd",
    "iso:country":"US",
    "sg:address":"7 Robinson Rd",
    "sg:city":"Severna Park",
    "sg:classifiers":[
        {
            "category":"Health Services",
            "subcategory":"Chiropractor",
            "type":"Services"
        }
    ],
    "sg:phone":"+1 410 544 7074",
    "sg:postcode":"21146",
    "sg:province":"MD",
    "wof:name":"Back & Neck Care Ctr",
    "wof:placetype":"venue"
},
  "geometry": {"coordinates":[-76.55007999999999,39.080258],"type":"Point"}
}