{
  "type": "Feature",
  "properties": {
    "iso:country":"US",
    "sg:address":"333 Baltimore Pike",
    "sg:city":"Bel Air",
    "sg:classifiers":[
        {
            "category":"Banks & Credit Unions",
            "subcategory":"Bank",
            "type":"Services"
        }
    ],
    "sg:phone":"+1 410 893 1600",
    "sg:postcode":"21014",
    "sg:province":"MD",
    "wof:name":"B B & T",
    "wof:placetype":"venue"
},
  "geometry": {"coordinates":[-76.350308,39.530629],"type":"Point"}
}