{
  "type": "Feature",
  "properties": {
    "addr:full":"2423 Pimpernel Dr Waldorf MD 20603",
    "addr:housenumber":"2423",
    "addr:postcode":"20603",
    "addr:street":"Pimpernel Dr",
    "iso:country":"US",
    "sg:address":"2423 Pimpernel Dr",
    "sg:city":"Waldorf",
    "sg:classifiers":[
        {
            "category":"Professional",
            "subcategory":"Management & Consulting",
            "type":"Services"
        },
        {
            "category":"Professional",
            "subcategory":"Advertising",
            "type":"Services"
        }
    ],
    "sg:phone":"+1 301 932 4386",
    "sg:postcode":"20603",
    "sg:province":"MD",
    "sg:tags":[
        "marketing",
        "program",
        "consultant"
    ],
    "wof:name":"Altieri Briggs Consulting",
    "wof:placetype":"venue"
},
  "geometry": {"coordinates":[-77.00286,38.644645],"type":"Point"}
}