{
  "type": "Feature",
  "properties": {
    "iso:country":"US",
    "sg:address":"5425 Silver Hill Rd",
    "sg:city":"District Heights",
    "sg:classifiers":[
        {
            "category":"Restaurant",
            "type":"Food & Drink"
        }
    ],
    "sg:menulink":"http://www.allmenus.com/md/spauldings/173360-wendys/menu/",
    "sg:phone":"+1 301 568 0088",
    "sg:postcode":"20747",
    "sg:province":"MD",
    "sg:tags":[
        "burger",
        "american",
        "soup"
    ],
    "wof:name":"Wendy's",
    "wof:placetype":"venue"
},
  "geometry": {"coordinates":[-76.913561,38.852103],"type":"Point"}
}