{
  "type": "Feature",
  "properties": {
    "iso:country":"US",
    "sg:address":"12172 Central Ave",
    "sg:city":"Mitchellville",
    "sg:classifiers":[
        {
            "category":"Health Services",
            "subcategory":"Doctor",
            "type":"Services"
        }
    ],
    "sg:phone":"+1 301 390 5704",
    "sg:postcode":"20721",
    "sg:province":"MD",
    "sg:tags":[
        "physician",
        "surgeon"
    ],
    "wof:name":"Michelle Thomas MD",
    "wof:placetype":"venue"
},
  "geometry": {"coordinates":[-76.794038,38.899938],"type":"Point"}
}