{
  "type": "Feature",
  "properties": {
    "addr:full":"118 Ice St Frederick MD 21701",
    "addr:housenumber":"118",
    "addr:postcode":"21701",
    "addr:street":"Ice St",
    "iso:country":"US",
    "sg:address":"118 Ice St",
    "sg:city":"Frederick",
    "sg:classifiers":[
        {
            "category":"Professional",
            "subcategory":"Business Services",
            "type":"Services"
        }
    ],
    "sg:phone":"+1 301 620 2232",
    "sg:postcode":"21701",
    "sg:province":"MD",
    "wof:name":"Mnm Enterprises Inc",
    "wof:placetype":"venue"
},
  "geometry": {"coordinates":[-77.412453,39.411742],"type":"Point"}
}