{
  "type": "Feature",
  "properties": {
    "addr:full":"4002 Falls Rd Baltimore MD 21211",
    "addr:housenumber":"4002",
    "addr:postcode":"21211",
    "addr:street":"Falls Rd",
    "iso:country":"US",
    "sg:address":"4002 Falls Rd",
    "sg:city":"Baltimore",
    "sg:classifiers":[
        {
            "category":"Freight",
            "type":"Transportation"
        }
    ],
    "sg:phone":"+1 410 889 0880",
    "sg:postcode":"21211",
    "sg:province":"MD",
    "sg:tags":[
        "delivery",
        "courier"
    ],
    "wof:name":"Expressway Couriers",
    "wof:placetype":"venue"
},
  "geometry": {"coordinates":[-76.636803,39.337101],"type":"Point"}
}