{
  "type": "Feature",
  "properties": {
    "addr:full":"255 N Washington St Rockville MD 20850",
    "addr:housenumber":"255",
    "addr:postcode":"20850",
    "addr:street":"N Washington St",
    "iso:country":"US",
    "sg:address":"255 N Washington St",
    "sg:city":"Rockville",
    "sg:classifiers":[
        {
            "category":"Manufacturing",
            "subcategory":"Tools & Machinery",
            "type":"Manufacturing & Wholesale Goods"
        }
    ],
    "sg:phone":"+1 301 279 7300",
    "sg:postcode":"20850",
    "sg:province":"MD",
    "sg:tags":[
        "physician",
        "surgeon"
    ],
    "sg:website":"www.healthcheckcenter.com",
    "wof:name":"Healthguard International",
    "wof:placetype":"venue"
},
  "geometry": {"coordinates":[-77.153629,39.088034],"type":"Point"}
}