{
  "type": "Feature",
  "properties": {
    "iso:country":"US",
    "sg:address":"4533 Stanford St",
    "sg:city":"Chevy Chase",
    "sg:classifiers":[
        {
            "category":"Real Estate",
            "subcategory":"Real Estate Agent",
            "type":"Services"
        }
    ],
    "sg:phone":"+1 301 215 7551",
    "sg:postcode":"20815",
    "sg:province":"MD",
    "sg:tags":[
        "management"
    ],
    "wof:name":"Diverified Property Management",
    "wof:placetype":"venue"
},
  "geometry": {"coordinates":[-77.09096599999999,38.978619],"type":"Point"}
}