{
  "type": "Feature",
  "properties": {
    "addr:full":"1800 S Caton Ave Halethorpe MD 21227",
    "addr:housenumber":"1800 s",
    "addr:postcode":"21227",
    "addr:street":"Caton Ave",
    "iso:country":"US",
    "sg:address":"1800 S Caton Ave",
    "sg:city":"Halethorpe",
    "sg:classifiers":[
        {
            "category":"Autos & Motor Vehicles",
            "subcategory":"Automobile Sales",
            "type":"Retail Goods"
        }
    ],
    "sg:phone":"+1 410 644 5404",
    "sg:postcode":"21227",
    "sg:province":"MD",
    "sg:tags":[
        "used",
        "car",
        "broker",
        "dealers-used",
        "truck",
        "new",
        "cars-wholesale"
    ],
    "sg:website":"http://www.varietyautobrokers.com",
    "wof:name":"Variety Auto Brokers Incorporated",
    "wof:placetype":"venue"
},
  "geometry": {"coordinates":[-76.66476299999999,39.259212],"type":"Point"}
}