{
  "type": "Feature",
  "properties": {
    "iso:country":"US",
    "sg:address":"7018 Holabird Ave",
    "sg:city":"Baltimore",
    "sg:classifiers":[
        {
            "category":"Restaurant",
            "type":"Food & Drink"
        }
    ],
    "sg:phone":"+1 410 285 8318",
    "sg:postcode":"21222",
    "sg:province":"MD",
    "wof:name":"Phillip's Inn & Restaurant",
    "wof:placetype":"venue"
},
  "geometry": {"coordinates":[-76.522949,39.272757],"type":"Point"}
}