{
  "type": "Feature",
  "properties": {
    "iso:country":"US",
    "sg:address":"4713 42nd Pl",
    "sg:city":"Hyattsville",
    "sg:classifiers":[
        {
            "category":"Retail",
            "subcategory":"Auto Repair",
            "type":"Services"
        }
    ],
    "sg:phone":"+1 301 699 0190",
    "sg:postcode":"20781",
    "sg:province":"MD",
    "sg:tags":[
        "body"
    ],
    "wof:name":"Yves Louissaint",
    "wof:placetype":"venue"
},
  "geometry": {"coordinates":[-76.94206,38.945805],"type":"Point"}
}