{
  "type": "Feature",
  "properties": {
    "addr:full":"1934 Lincoln Dr Annapolis MD 21401",
    "addr:housenumber":"1934",
    "addr:postcode":"21401",
    "addr:street":"Lincoln Dr",
    "iso:country":"US",
    "sg:address":"1934 Lincoln Dr",
    "sg:city":"Annapolis",
    "sg:classifiers":[
        {
            "category":"Home & Garden",
            "subcategory":"Building Materials",
            "type":"Retail Goods"
        }
    ],
    "sg:phone":"+1 410 956 7272",
    "sg:postcode":"21401",
    "sg:province":"MD",
    "sg:tags":[
        "glass",
        "window",
        "plate"
    ],
    "wof:name":"Superior Windshield Repair",
    "wof:placetype":"venue"
},
  "geometry": {"coordinates":[-76.52136,38.973393],"type":"Point"}
}