{
  "type": "Feature",
  "properties": {
    "iso:country":"US",
    "sg:address":"7839 Eastpoint Mall Ste 2",
    "sg:city":"Baltimore",
    "sg:classifiers":[
        {
            "category":"Health Services",
            "subcategory":"Dentist",
            "type":"Services"
        }
    ],
    "sg:phone":"+1 410 282 8700",
    "sg:postcode":"21224",
    "sg:province":"MD",
    "sg:website":"www.eastpointmall.com",
    "wof:name":"Eastpoint Mall Family Dentistry",
    "wof:placetype":"venue"
},
  "geometry": {"coordinates":[-76.509697,39.291901],"type":"Point"}
}