{
  "type": "Feature",
  "properties": {
    "iso:country":"US",
    "sg:address":"12703 New Hampshire Ave",
    "sg:city":"Silver Spring",
    "sg:classifiers":[
        {
            "category":"Restaurant",
            "type":"Food & Drink"
        }
    ],
    "sg:phone":"+1 301 622 3304",
    "sg:postcode":"20904",
    "sg:province":"MD",
    "wof:name":"Huddle Convenience Store",
    "wof:placetype":"venue"
},
  "geometry": {"coordinates":[-77.00030700000001,39.065693],"type":"Point"}
}