{
  "type": "Feature",
  "properties": {
    "iso:country":"US",
    "sg:address":"350 Cypress St",
    "sg:city":"Salisbury",
    "sg:classifiers":[
        {
            "category":"Local Transit",
            "type":"Transportation"
        }
    ],
    "sg:phone":"+1 410 749 4121",
    "sg:postcode":"21801",
    "sg:province":"MD",
    "sg:tags":[
        "bus",
        "line"
    ],
    "wof:name":"Trailways Bus Terminal",
    "wof:placetype":"venue"
},
  "geometry": {"coordinates":[-75.60639999999999,38.369532],"type":"Point"}
}