{
  "type": "Feature",
  "properties": {
    "addr:full":"10918 York Rd Cockeysville MD 21030",
    "addr:housenumber":"10918",
    "addr:postcode":"21030",
    "addr:street":"York Rd",
    "iso:country":"US",
    "sg:address":"10918 York Rd",
    "sg:city":"Cockeysville",
    "sg:classifiers":[
        {
            "category":"Wholesale",
            "subcategory":"Motor Vehicles",
            "type":"Manufacturing & Wholesale Goods"
        }
    ],
    "sg:phone":"+1 410 771 9180",
    "sg:postcode":"21030",
    "sg:province":"MD",
    "wof:name":"Issa Auto Wholesale",
    "wof:placetype":"venue"
},
  "geometry": {"coordinates":[-76.64549700000001,39.484653],"type":"Point"}
}