{
  "type": "Feature",
  "properties": {
    "addr:full":"27 S Patterson Park Ave Baltimore MD 21231",
    "addr:housenumber":"27",
    "addr:postcode":"21231",
    "addr:street":"S Patterson;Ave",
    "iso:country":"US",
    "sg:address":"27 S Patterson Park Ave",
    "sg:city":"Baltimore",
    "sg:classifiers":[
        {
            "category":"Organizations",
            "subcategory":"Membership Organization",
            "type":"Services"
        }
    ],
    "sg:phone":"+1 410 276 3676",
    "sg:postcode":"21231",
    "sg:province":"MD",
    "sg:tags":[
        "professional",
        "employer"
    ],
    "wof:name":"Friends Of Patterson Park",
    "wof:placetype":"venue"
},
  "geometry": {"coordinates":[-76.584665,39.291249],"type":"Point"}
}