{
  "type": "Feature",
  "properties": {
    "iso:country":"US",
    "sg:address":"11 E Chase St Ste 8A",
    "sg:city":"Baltimore",
    "sg:classifiers":[
        {
            "category":"Real Estate",
            "subcategory":"Architect",
            "type":"Services"
        }
    ],
    "sg:phone":"+1 410 625 9383",
    "sg:postcode":"21202",
    "sg:province":"MD",
    "sg:tags":[
        "specification",
        "construction",
        "architectural",
        "engineer"
    ],
    "wof:name":"Fon Architect",
    "wof:placetype":"venue"
},
  "geometry": {"coordinates":[-76.615126,39.3024],"type":"Point"}
}