{
  "type": "Feature",
  "properties": {
    "iso:country":"US",
    "sg:address":"4117 Saul Rd",
    "sg:city":"Kensington",
    "sg:classifiers":[
        {
            "category":"Professional",
            "subcategory":"Business Services",
            "type":"Services"
        }
    ],
    "sg:phone":"+1 301 946 9449",
    "sg:postcode":"20895",
    "sg:province":"MD",
    "wof:name":"Rich Interiors Inc",
    "wof:placetype":"venue"
},
  "geometry": {"coordinates":[-77.08022699999999,39.015631],"type":"Point"}
}