{
  "type": "Feature",
  "properties": {
    "addr:full":"1598 Whitehall Rd Annapolis MD 21401",
    "addr:housenumber":"1598",
    "addr:postcode":"21401",
    "addr:street":"Whitehall Rd",
    "iso:country":"US",
    "sg:address":"1598 Whitehall Rd",
    "sg:city":"Annapolis",
    "sg:classifiers":[
        {
            "category":"Professional",
            "type":"Services"
        }
    ],
    "sg:phone":"+1 301 858 7437",
    "sg:postcode":"21401",
    "sg:province":"MD",
    "wof:name":"Pacific Animated Imaging Corp",
    "wof:placetype":"venue"
},
  "geometry": {"coordinates":[-76.426551,39.022978],"type":"Point"}
}