{
  "type": "Feature",
  "properties": {
    "iso:country":"US",
    "sg:address":"195 Pangborn Blvd",
    "sg:city":"Hagerstown",
    "sg:classifiers":[
        {
            "category":"Education",
            "subcategory":"School",
            "type":"Public Place"
        }
    ],
    "sg:phone":"+1 301 766 8282",
    "sg:postcode":"21740",
    "sg:province":"MD",
    "wof:name":"Pangborn Elementary School",
    "wof:placetype":"venue"
},
  "geometry": {"coordinates":[-77.700494,39.636017],"type":"Point"}
}