{
  "type": "Feature",
  "properties": {
    "addr:full":"1919 Fleet St Baltimore MD 21231",
    "addr:housenumber":"1919",
    "addr:postcode":"21231",
    "addr:street":"Fleet St",
    "iso:country":"US",
    "sg:address":"1919 Fleet St",
    "sg:city":"Baltimore",
    "sg:classifiers":[
        {
            "category":"Bars & Pubs",
            "type":"Food & Drink"
        }
    ],
    "sg:phone":"+1 410 342 3586",
    "sg:postcode":"21231",
    "sg:province":"MD",
    "sg:tags":[
        "drinking"
    ],
    "wof:name":"Fleet Street Company Inc",
    "wof:placetype":"venue"
},
  "geometry": {"coordinates":[-76.590059,39.284773],"type":"Point"}
}