{
  "type": "Feature",
  "properties": {
    "iso:country":"US",
    "sg:address":"178 Thomas Johnson Dr",
    "sg:city":"Frederick",
    "sg:classifiers":[
        {
            "category":"Professional",
            "subcategory":"Accounting & Tax Preparation",
            "type":"Services"
        }
    ],
    "sg:phone":"+1 301 694 8549",
    "sg:postcode":"21702",
    "sg:province":"MD",
    "sg:tags":[
        "accountant"
    ],
    "wof:name":"John W Balch CPA",
    "wof:placetype":"venue"
},
  "geometry": {"coordinates":[-77.406268,39.442251],"type":"Point"}
}