{
  "type": "Feature",
  "properties": {
    "iso:country":"US",
    "sg:address":"4017 Crow Rock Rd",
    "sg:city":"Myersville",
    "sg:classifiers":[
        {
            "category":"Building & Trades",
            "subcategory":"Construction",
            "type":"Services"
        }
    ],
    "sg:phone":"+1 301 371 6514",
    "sg:postcode":"21773",
    "sg:province":"MD",
    "sg:tags":[
        "builder",
        "deck"
    ],
    "wof:name":"All American Decking Inc",
    "wof:placetype":"venue"
},
  "geometry": {"coordinates":[-77.530294,39.524672],"type":"Point"}
}