{
  "type": "Feature",
  "properties": {
    "iso:country":"US",
    "sg:address":"6635 Belair Rd",
    "sg:city":"Baltimore",
    "sg:classifiers":[
        {
            "category":"Banks & Credit Unions",
            "subcategory":"Investment Brokerage",
            "type":"Services"
        }
    ],
    "sg:phone":"+1 410 254 9184",
    "sg:postcode":"21206",
    "sg:province":"MD",
    "sg:tags":[
        "investing"
    ],
    "wof:name":"E Trade",
    "wof:placetype":"venue"
},
  "geometry": {"coordinates":[-76.53092599999999,39.354315],"type":"Point"}
}