{
  "type": "Feature",
  "properties": {
    "addr:full":"6004 Princeton Ave Glen Echo MD 20812",
    "addr:housenumber":"6004",
    "addr:postcode":"20812",
    "addr:street":"Princeton Ave",
    "iso:country":"US",
    "sg:address":"6004 Princeton Ave",
    "sg:city":"Glen Echo",
    "sg:classifiers":[
        {
            "category":"Real Estate",
            "subcategory":"Architect",
            "type":"Services"
        }
    ],
    "sg:phone":"+1 301 320 6305",
    "sg:postcode":"20812",
    "sg:province":"MD",
    "wof:name":"Murray & Assoc",
    "wof:placetype":"venue"
},
  "geometry": {"coordinates":[-77.141271,38.968533],"type":"Point"}
}