{
  "type": "Feature",
  "properties": {
    "addr:full":"672 Old Mill Rd Millersville MD 21108",
    "addr:housenumber":"672",
    "addr:postcode":"21108",
    "addr:street":"Old Mill Rd",
    "iso:country":"US",
    "sg:address":"672 Old Mill Rd",
    "sg:city":"Millersville",
    "sg:classifiers":[
        {
            "category":"Cinema",
            "subcategory":"Movie Rental",
            "type":"Entertainment"
        }
    ],
    "sg:phone":"+1 410 987 9606",
    "sg:postcode":"21108",
    "sg:province":"MD",
    "sg:tags":[
        "leasing",
        "video",
        "disc",
        "tape"
    ],
    "wof:name":"West Coast Video-Millersville",
    "wof:placetype":"venue"
},
  "geometry": {"coordinates":[-76.632189,39.11773],"type":"Point"}
}