{
  "type": "Feature",
  "properties": {
    "iso:country":"US",
    "sg:address":"2846 Beckon Dr",
    "sg:city":"Edgewood",
    "sg:classifiers":[
        {
            "category":"Retail",
            "subcategory":"Repair Shop",
            "type":"Services"
        }
    ],
    "sg:phone":"+1 410 538 6435",
    "sg:postcode":"21040",
    "sg:province":"MD",
    "sg:tags":[
        "cleaning"
    ],
    "wof:name":"Kathleen J Holland",
    "wof:placetype":"venue"
},
  "geometry": {"coordinates":[-76.286852,39.442917],"type":"Point"}
}