{
  "type": "Feature",
  "properties": {
    "addr:full":"3306 Donnell Dr District Heights MD 20747",
    "addr:housenumber":"3306",
    "addr:postcode":"20747",
    "addr:street":"Donnell Dr",
    "iso:country":"US",
    "sg:address":"3306 Donnell Dr",
    "sg:city":"District Heights",
    "sg:classifiers":[
        {
            "category":"Shopping",
            "subcategory":"Clothing, Apparel, & Fashions",
            "type":"Retail Goods"
        }
    ],
    "sg:phone":"+1 301 568 2141",
    "sg:postcode":"20747",
    "sg:province":"MD",
    "sg:tags":[
        "accessory"
    ],
    "wof:name":"Avenue",
    "wof:placetype":"venue"
},
  "geometry": {"coordinates":[-76.885002,38.846401],"type":"Point"}
}