{
  "type": "Feature",
  "properties": {
    "iso:country":"US",
    "sg:address":"14605 Sturtevant Rd",
    "sg:city":"Silver Spring",
    "sg:classifiers":[
        {
            "category":"Manufacturing",
            "subcategory":"Printing",
            "type":"Manufacturing & Wholesale Goods"
        }
    ],
    "sg:phone":"+1 301 260 2280",
    "sg:postcode":"20905",
    "sg:province":"MD",
    "sg:tags":[
        "typesetting"
    ],
    "wof:name":"Phils Fonts",
    "wof:placetype":"venue"
},
  "geometry": {"coordinates":[-76.972015,39.096004],"type":"Point"}
}