{
  "type": "Feature",
  "properties": {
    "addr:full":"2604 Peters Corner Rd Marydel MD 21668",
    "addr:housenumber":"2604",
    "addr:postcode":"21668",
    "addr:street":"Peters Corner Rd",
    "iso:country":"US",
    "sg:address":"2604 Peters Corner Rd",
    "sg:city":"Marydel",
    "sg:classifiers":[
        {
            "category":"Personal",
            "subcategory":"Beauty Salon",
            "type":"Services"
        }
    ],
    "sg:phone":"+1 410 438 3840",
    "sg:postcode":"21668",
    "sg:province":"MD",
    "wof:name":"Hair Loft",
    "wof:placetype":"venue"
},
  "geometry": {"coordinates":[-75.78110700000001,39.161132],"type":"Point"}
}