{
  "type": "Feature",
  "properties": {
    "iso:country":"US",
    "sg:address":"6 W Churchill St",
    "sg:city":"Baltimore",
    "sg:classifiers":[
        {
            "category":"Professional",
            "subcategory":"Lawyer & Legal Services",
            "type":"Services"
        }
    ],
    "sg:phone":"+1 410 783 7607",
    "sg:postcode":"21230",
    "sg:province":"MD",
    "sg:tags":[
        "attorney",
        "practice"
    ],
    "wof:name":"Shaw Michael & ESQ",
    "wof:placetype":"venue"
},
  "geometry": {"coordinates":[-76.614598,39.279564],"type":"Point"}
}