{
  "type": "Feature",
  "properties": {
    "iso:country":"US",
    "sg:address":"1700 Rockville Pike",
    "sg:city":"Rockville",
    "sg:classifiers":[
        {
            "category":"Shopping",
            "subcategory":"Computers & Home Electronics",
            "type":"Retail Goods"
        }
    ],
    "sg:phone":"+1 301 998 6109",
    "sg:postcode":"20852",
    "sg:province":"MD",
    "sg:tags":[
        "software"
    ],
    "wof:name":"Lexicom",
    "wof:placetype":"venue"
},
  "geometry": {"coordinates":[-77.122665,39.060283],"type":"Point"}
}