{
  "type": "Feature",
  "properties": {
    "iso:country":"US",
    "sg:address":"10 Brookletts Ave",
    "sg:city":"Easton",
    "sg:classifiers":[
        {
            "category":"Professional",
            "subcategory":"Printing & Photocopies",
            "type":"Services"
        }
    ],
    "sg:phone":"+1 410 822 3240",
    "sg:postcode":"21601",
    "sg:province":"MD",
    "sg:tags":[
        "consultant"
    ],
    "wof:name":"Daniel J Arnold",
    "wof:placetype":"venue"
},
  "geometry": {"coordinates":[-76.075754,38.770463],"type":"Point"}
}