{
  "type": "Feature",
  "properties": {
    "iso:country":"US",
    "sg:address":"6009 Church Ln",
    "sg:city":"Hydes",
    "sg:classifiers":[
        {
            "category":"Professional",
            "subcategory":"Management & Consulting",
            "type":"Services"
        }
    ],
    "sg:phone":"+1 410 592 8040",
    "sg:postcode":"21082",
    "sg:province":"MD",
    "sg:tags":[
        "business"
    ],
    "wof:name":"Chason Consulting Co Inc",
    "wof:placetype":"venue"
},
  "geometry": {"coordinates":[-76.473066,39.48864],"type":"Point"}
}