{
  "type": "Feature",
  "properties": {
    "iso:country":"US",
    "sg:address":"1024 Rolandvue Rd",
    "sg:city":"Baltimore",
    "sg:classifiers":[
        {
            "category":"Banks & Credit Unions",
            "subcategory":"Investment Brokerage",
            "type":"Services"
        }
    ],
    "sg:phone":"+1 410 825 5380",
    "sg:postcode":"21204",
    "sg:province":"MD",
    "sg:tags":[
        "advisory"
    ],
    "wof:name":"Baldwin Investment Group Inc",
    "wof:placetype":"venue"
},
  "geometry": {"coordinates":[-76.63790899999999,39.393986],"type":"Point"}
}