{
  "type": "Feature",
  "properties": {
    "addr:full":"1836 Wye Mills Ln Bel Air MD 21015",
    "addr:housenumber":"1836",
    "addr:postcode":"21015",
    "addr:street":"Wye Mills Ln",
    "iso:country":"US",
    "sg:address":"1836 Wye Mills Ln",
    "sg:city":"Bel Air",
    "sg:classifiers":[
        {
            "category":"Building & Trades",
            "subcategory":"Electrical",
            "type":"Services"
        }
    ],
    "sg:phone":"+1 410 879 3252",
    "sg:postcode":"21015",
    "sg:province":"MD",
    "sg:tags":[
        "work",
        "electrical"
    ],
    "wof:name":"Baroch Electric Inc",
    "wof:placetype":"venue"
},
  "geometry": {"coordinates":[-76.32505500000001,39.563587],"type":"Point"}
}