{
  "type": "Feature",
  "properties": {
    "iso:country":"US",
    "sg:address":"13215 Yellow Row Rd NW",
    "sg:city":"Mount Savage",
    "sg:classifiers":[
        {
            "category":"Education",
            "subcategory":"Special Training",
            "type":"Public Place"
        }
    ],
    "sg:phone":"+1 301 264 4172",
    "sg:postcode":"21545",
    "sg:province":"MD",
    "sg:tags":[
        "instrument",
        "musical"
    ],
    "wof:name":"Ernies Music",
    "wof:placetype":"venue"
},
  "geometry": {"coordinates":[-78.886599,39.702637],"type":"Point"}
}