{
  "type": "Feature",
  "properties": {
    "addr:full":"8901 New Hampshire Ave Silver Spring MD 20903",
    "addr:housenumber":"8901",
    "addr:postcode":"20903",
    "addr:street":"New Hampshire Ave",
    "iso:country":"US",
    "sg:address":"8901 New Hampshire Ave",
    "sg:city":"Silver Spring",
    "sg:classifiers":[
        {
            "category":"Health Services",
            "subcategory":"Hospital",
            "type":"Services"
        }
    ],
    "sg:phone":"+1 301 445 7970",
    "sg:postcode":"20903",
    "sg:province":"MD",
    "sg:website":"www.sli.org",
    "wof:name":"St Luke Institute Inc",
    "wof:placetype":"venue"
},
  "geometry": {"coordinates":[-76.981393,39.002576],"type":"Point"}
}