{
  "type": "Feature",
  "properties": {
    "iso:country":"US",
    "sg:address":"12706 Shawnee Ct",
    "sg:city":"Clarksburg",
    "sg:classifiers":[
        {
            "category":"Professional",
            "subcategory":"Computer Services",
            "type":"Services"
        }
    ],
    "sg:phone":"+1 301 591 1720",
    "sg:postcode":"20871",
    "sg:province":"MD",
    "sg:tags":[
        "publisher",
        "developer",
        "software"
    ],
    "wof:name":"Braune It Consulting Company",
    "wof:placetype":"venue"
},
  "geometry": {"coordinates":[-77.265407,39.232395],"type":"Point"}
}