{
  "type": "Feature",
  "properties": {
    "iso:country":"US",
    "sg:address":"7343 Old Alexandria Ferry Rd",
    "sg:city":"Clinton",
    "sg:classifiers":[
        {
            "category":"Organizations",
            "subcategory":"Religious Organization",
            "type":"Services"
        }
    ],
    "sg:phone":"+1 301 877 7100",
    "sg:postcode":"20735",
    "sg:province":"MD",
    "sg:tags":[
        "church"
    ],
    "wof:name":"In His Image Christian Ministr",
    "wof:placetype":"venue"
},
  "geometry": {"coordinates":[-76.882507,38.783539],"type":"Point"}
}