{
  "type": "Feature",
  "properties": {
    "iso:country":"US",
    "sg:address":"8102 Pineberry Ct",
    "sg:city":"Pasadena",
    "sg:classifiers":[
        {
            "category":"Professional",
            "type":"Services"
        }
    ],
    "sg:phone":"+1 410 590 5375",
    "sg:postcode":"21122",
    "sg:province":"MD",
    "wof:name":"R&B Quality Carpert Services",
    "wof:placetype":"venue"
},
  "geometry": {"coordinates":[-76.587287,39.130854],"type":"Point"}
}