{
  "type": "Feature",
  "properties": {
    "iso:country":"US",
    "sg:address":"4401 Beckenham Pl",
    "sg:city":"Upper Marlboro",
    "sg:classifiers":[
        {
            "category":"Real Estate",
            "subcategory":"Real Estate Agent",
            "type":"Services"
        }
    ],
    "sg:phone":"+1 301 574 1570",
    "sg:postcode":"20772",
    "sg:province":"MD",
    "wof:name":"Kingdom Building MGT Svcs",
    "wof:placetype":"venue"
},
  "geometry": {"coordinates":[-76.77237599999999,38.829119],"type":"Point"}
}