{
  "type": "Feature",
  "properties": {
    "addr:full":"3411 Robey Ter Silver Spring MD 20904",
    "addr:housenumber":"3411",
    "addr:postcode":"20904",
    "addr:street":"Robey Ter",
    "iso:country":"US",
    "sg:address":"3411 Robey Ter",
    "sg:city":"Silver Spring",
    "sg:classifiers":[
        {
            "category":"Social Services",
            "subcategory":"Child Care",
            "type":"Services"
        }
    ],
    "sg:phone":"+1 301 890 3427",
    "sg:postcode":"20904",
    "sg:province":"MD",
    "sg:tags":[
        "day"
    ],
    "wof:name":"Barbaras Place",
    "wof:placetype":"venue"
},
  "geometry": {"coordinates":[-76.937253,39.082806],"type":"Point"}
}