{
  "type": "Feature",
  "properties": {
    "addr:full":"9515 Gerwig Ln Ste 108 Columbia MD 21046",
    "addr:housenumber":"9515",
    "addr:postcode":"21046",
    "addr:street":"Gerwig Ln Ste 108",
    "iso:country":"US",
    "sg:address":"9515 Gerwig Ln Ste 108",
    "sg:city":"Columbia",
    "sg:classifiers":[
        {
            "category":"Professional",
            "subcategory":"Computer Services",
            "type":"Services"
        }
    ],
    "sg:phone":"+1 410 309 7320",
    "sg:postcode":"21046",
    "sg:province":"MD",
    "sg:tags":[
        "repair"
    ],
    "wof:name":"Sharp Communication Service Inc",
    "wof:placetype":"venue"
},
  "geometry": {"coordinates":[-76.840698,39.171799],"type":"Point"}
}