{
  "type": "Feature",
  "properties": {
    "addr:full":"1209 N Salisbury Blvd Salisbury MD 21801",
    "addr:housenumber":"1209",
    "addr:postcode":"21801",
    "addr:street":"N Salisbury Blvd",
    "iso:country":"US",
    "sg:address":"1209 N Salisbury Blvd",
    "sg:city":"Salisbury",
    "sg:classifiers":[
        {
            "category":"Building & Trades",
            "subcategory":"Construction",
            "type":"Services"
        }
    ],
    "sg:phone":"+1 410 742 6163",
    "sg:postcode":"21801",
    "sg:province":"MD",
    "sg:tags":[
        "roofing",
        "industrial",
        "consultant",
        "contractor",
        "contractors-commercial"
    ],
    "sg:website":"http://www.peninsularoofing.com",
    "wof:name":"Peninsula Roofing CO",
    "wof:placetype":"venue"
},
  "geometry": {"coordinates":[-75.591222,38.37704],"type":"Point"}
}