{
  "type": "Feature",
  "properties": {
    "iso:country":"US",
    "sg:address":"4806 Holabird Ave",
    "sg:city":"Baltimore",
    "sg:classifiers":[
        {
            "category":"Building & Trades",
            "subcategory":"Construction",
            "type":"Services"
        }
    ],
    "sg:phone":"+1 410 327 6583",
    "sg:postcode":"21224",
    "sg:province":"MD",
    "sg:tags":[
        "roofing",
        "industrial",
        "contractors-commercial",
        "contractor"
    ],
    "wof:name":"Coastal Roofing Company Inc",
    "wof:placetype":"venue"
},
  "geometry": {"coordinates":[-76.554661,39.27168],"type":"Point"}
}