{
  "type": "Feature",
  "properties": {
    "addr:full":"2770 Solomons Island Rd Edgewater MD 21037",
    "addr:housenumber":"2770",
    "addr:postcode":"21037",
    "addr:street":"Solomons Island Rd",
    "iso:country":"US",
    "sg:address":"2770 Solomons Island Rd",
    "sg:city":"Edgewater",
    "sg:classifiers":[
        {
            "category":"Health Services",
            "subcategory":"Chiropractor",
            "type":"Services"
        }
    ],
    "sg:phone":"+1 410 224 3387",
    "sg:postcode":"21037",
    "sg:province":"MD",
    "wof:name":"Cohen Chiropractic",
    "wof:placetype":"venue"
},
  "geometry": {"coordinates":[-76.55266399999999,38.954855],"type":"Point"}
}