{
  "type": "Feature",
  "properties": {
    "iso:country":"US",
    "sg:address":"16 S Hays St",
    "sg:city":"Bel Air",
    "sg:classifiers":[
        {
            "category":"Social Services",
            "type":"Services"
        }
    ],
    "sg:phone":"+1 410 836 7464",
    "sg:postcode":"21014",
    "sg:province":"MD",
    "sg:tags":[
        "guidance",
        "child"
    ],
    "wof:name":"Richie Kerry Lcsw",
    "wof:placetype":"venue"
},
  "geometry": {"coordinates":[-76.351147,39.534189],"type":"Point"}
}