{
  "type": "Feature",
  "properties": {
    "iso:country":"US",
    "sg:address":"11809 Randy Ln",
    "sg:city":"Laurel",
    "sg:classifiers":[
        {
            "category":"Building & Trades",
            "subcategory":"Construction",
            "type":"Services"
        }
    ],
    "sg:phone":"+1 301 604 3636",
    "sg:postcode":"20708",
    "sg:province":"MD",
    "sg:tags":[
        "roofing",
        "siding",
        "work",
        "sheet",
        "metal"
    ],
    "sg:website":"www.mcgrawbrothers.com",
    "wof:name":"Mc Graw Brothers Co Inc",
    "wof:placetype":"venue"
},
  "geometry": {"coordinates":[-76.85034,39.051853],"type":"Point"}
}