{
  "type": "Feature",
  "properties": {
    "addr:full":"408 Military Rd Frederick MD 21702",
    "addr:housenumber":"408",
    "addr:postcode":"21702",
    "addr:street":"Military Rd",
    "iso:country":"US",
    "sg:address":"408 Military Rd",
    "sg:city":"Frederick",
    "sg:classifiers":[
        {
            "category":"Restaurant",
            "type":"Food & Drink"
        }
    ],
    "sg:phone":"+1 301 663 6409",
    "sg:postcode":"21702",
    "sg:province":"MD",
    "wof:name":"Freez-King",
    "wof:placetype":"venue"
},
  "geometry": {"coordinates":[-77.43213299999999,39.428478],"type":"Point"}
}