{
  "type": "Feature",
  "properties": {
    "iso:country":"US",
    "sg:address":"133 Centerway",
    "sg:city":"Greenbelt",
    "sg:classifiers":[
        {
            "category":"Personal",
            "type":"Services"
        }
    ],
    "sg:phone":"+1 301 345 1849",
    "sg:postcode":"20770",
    "sg:province":"MD",
    "sg:tags":[
        "therapist",
        "massage"
    ],
    "wof:name":"Pleasant Touch",
    "wof:placetype":"venue"
},
  "geometry": {"coordinates":[-76.87629,39.001169],"type":"Point"}
}