{
  "type": "Feature",
  "properties": {
    "addr:full":"632 Sligo Ave Silver Spring MD 20910",
    "addr:housenumber":"632",
    "addr:postcode":"20910",
    "addr:street":"Sligo Ave",
    "iso:country":"US",
    "sg:address":"632 Sligo Ave",
    "sg:city":"Silver Spring",
    "sg:classifiers":[
        {
            "category":"Professional",
            "subcategory":"Business Services",
            "type":"Services"
        }
    ],
    "sg:phone":"+1 301 608 0036",
    "sg:postcode":"20910",
    "sg:province":"MD",
    "sg:tags":[
        "painting",
        "sign"
    ],
    "wof:name":"Pump Tees",
    "wof:placetype":"venue"
},
  "geometry": {"coordinates":[-77.01628100000001,38.990749],"type":"Point"}
}