{
  "type": "Feature",
  "properties": {
    "iso:country":"US",
    "sg:address":"12 S Catherine St",
    "sg:city":"Baltimore",
    "sg:classifiers":[
        {
            "category":"Shopping",
            "subcategory":"Catalog Store",
            "type":"Retail Goods"
        }
    ],
    "sg:phone":"+1 410 566 4233",
    "sg:postcode":"21223",
    "sg:province":"MD",
    "sg:tags":[
        "gift"
    ],
    "wof:name":"Sir Floyd Showcase",
    "wof:placetype":"venue"
},
  "geometry": {"coordinates":[-76.656208,39.286974],"type":"Point"}
}