{
  "type": "Feature",
  "properties": {
    "iso:country":"US",
    "sg:address":"7228 Barcellona Dr",
    "sg:city":"Gaithersburg",
    "sg:classifiers":[
        {
            "category":"Building & Trades",
            "subcategory":"Plumbing",
            "type":"Services"
        }
    ],
    "sg:phone":"+1 301 948 6238",
    "sg:postcode":"20879",
    "sg:province":"MD",
    "sg:tags":[
        "system",
        "heating",
        "contractor",
        "air conditioning"
    ],
    "wof:name":"Air Mac Inc.",
    "wof:placetype":"venue"
},
  "geometry": {"coordinates":[-77.14916700000001,39.180034],"type":"Point"}
}