{
  "type": "Feature",
  "properties": {
    "addr:full":"1017 Fairground Dr Salisbury MD 21801",
    "addr:housenumber":"1017",
    "addr:postcode":"21801",
    "addr:street":"Fairground Dr",
    "iso:country":"US",
    "sg:address":"1017 Fairground Dr",
    "sg:city":"Salisbury",
    "sg:classifiers":[
        {
            "category":"Real Estate",
            "subcategory":"Real Estate Operator",
            "type":"Services"
        }
    ],
    "sg:phone":"+1 410 749 0559",
    "sg:postcode":"21801",
    "sg:province":"MD",
    "sg:tags":[
        "apartment"
    ],
    "wof:name":"Pemberton Manor Apartments",
    "wof:placetype":"venue"
},
  "geometry": {"coordinates":[-75.617093,38.365941],"type":"Point"}
}