{
  "type": "Feature",
  "properties": {
    "iso:country":"US",
    "sg:address":"2700 W Fairmount Ave",
    "sg:city":"Baltimore",
    "sg:classifiers":[
        {
            "category":"Food & Beverages",
            "subcategory":"Liquor & Beverages",
            "type":"Retail Goods"
        }
    ],
    "sg:phone":"+1 410 947 8617",
    "sg:postcode":"21223",
    "sg:province":"MD",
    "sg:tags":[
        "beer",
        "spirit",
        "wine"
    ],
    "wof:name":"Kim Yohn Sik",
    "wof:placetype":"venue"
},
  "geometry": {"coordinates":[-76.659302,39.288399],"type":"Point"}
}