{
  "type": "Feature",
  "properties": {
    "addr:full":"7715 Paradise Beach Rd Pasadena MD 21122",
    "addr:housenumber":"7715",
    "addr:postcode":"21122",
    "addr:street":"Paradise Beach Rd",
    "iso:country":"US",
    "sg:address":"7715 Paradise Beach Rd",
    "sg:city":"Pasadena",
    "sg:classifiers":[
        {
            "category":"Real Estate",
            "subcategory":"Real Estate Agent",
            "type":"Services"
        }
    ],
    "sg:phone":"+1 410 255 0139",
    "sg:postcode":"21122",
    "sg:province":"MD",
    "sg:tags":[
        "management"
    ],
    "wof:name":"Maximum Property Management",
    "wof:placetype":"venue"
},
  "geometry": {"coordinates":[-76.467862,39.144023],"type":"Point"}
}