{
  "type": "Feature",
  "properties": {
    "addr:full":"632 Round Oak Rd Towson MD 21204",
    "addr:housenumber":"632",
    "addr:postcode":"21204",
    "addr:street":"Round Oak Rd",
    "iso:country":"US",
    "sg:address":"632 Round Oak Rd",
    "sg:city":"Towson",
    "sg:classifiers":[
        {
            "category":"Real Estate",
            "subcategory":"Real Estate Services",
            "type":"Services"
        },
        {
            "category":"Real Estate",
            "subcategory":"Real Estate Agent",
            "type":"Services"
        }
    ],
    "sg:phone":"+1 410 252 6037",
    "sg:postcode":"21204",
    "sg:province":"MD",
    "sg:tags":[
        "buyer",
        "broker"
    ],
    "wof:name":"Virtual Real Estate",
    "wof:placetype":"venue"
},
  "geometry": {"coordinates":[-76.618088,39.40565],"type":"Point"}
}