{
  "type": "Feature",
  "properties": {
    "addr:full":"2725 Sisson St Baltimore MD 21211",
    "addr:housenumber":"2725",
    "addr:postcode":"21211",
    "addr:street":"Sisson St",
    "iso:country":"US",
    "sg:address":"2725 Sisson St",
    "sg:city":"Baltimore",
    "sg:classifiers":[
        {
            "category":"Autos & Motor Vehicles",
            "subcategory":"Fuel & Gas Station",
            "type":"Retail Goods"
        }
    ],
    "sg:phone":"+1 410 243 1120",
    "sg:postcode":"21211",
    "sg:province":"MD",
    "wof:name":"28th Street Mobile Mart",
    "wof:placetype":"venue"
},
  "geometry": {"coordinates":[-76.62449599999999,39.3186],"type":"Point"}
}