{
  "type": "Feature",
  "properties": {
    "iso:country":"US",
    "sg:address":"15 Old Solomons Island Rd",
    "sg:city":"Annapolis",
    "sg:classifiers":[
        {
            "category":"Professional",
            "subcategory":"Engineering",
            "type":"Services"
        }
    ],
    "sg:phone":"+1 410 897 1004",
    "sg:postcode":"21401",
    "sg:province":"MD",
    "sg:tags":[
        "engineer"
    ],
    "wof:name":"Andrews Miller & Assoc Inc",
    "wof:placetype":"venue"
},
  "geometry": {"coordinates":[-76.534745,38.98064],"type":"Point"}
}