{
  "type": "Feature",
  "properties": {
    "iso:country":"US",
    "sg:address":"1308 N Division St",
    "sg:city":"Salisbury",
    "sg:classifiers":[
        {
            "category":"Retail",
            "subcategory":"Auto Repair",
            "type":"Services"
        }
    ],
    "sg:phone":"+1 410 742 6772",
    "sg:postcode":"21801",
    "sg:province":"MD",
    "sg:tags":[
        "wrecker"
    ],
    "wof:name":"Simpson's Towing Svc",
    "wof:placetype":"venue"
},
  "geometry": {"coordinates":[-75.590962,38.378161],"type":"Point"}
}