{
  "type": "Feature",
  "properties": {
    "addr:full":"10492 Campus Way S Upper Marlboro MD 20774",
    "addr:housenumber":"10492",
    "addr:postcode":"20774",
    "addr:street":"Campus Way S Upper",
    "iso:country":"US",
    "sg:address":"10492 Campus Way S",
    "sg:city":"Upper Marlboro",
    "sg:classifiers":[
        {
            "category":"Wholesale",
            "subcategory":"Machinery & Supplies",
            "type":"Manufacturing & Wholesale Goods"
        }
    ],
    "sg:phone":"+1 301 324 7023",
    "sg:postcode":"20774",
    "sg:province":"MD",
    "sg:tags":[
        "salon",
        "beauty"
    ],
    "wof:name":"Sally Beauty Supply",
    "wof:placetype":"venue"
},
  "geometry": {"coordinates":[-76.82302799999999,38.894551],"type":"Point"}
}