{
  "type": "Feature",
  "properties": {
    "iso:country":"US",
    "sg:address":"13729 Shannon Ave",
    "sg:city":"Laurel",
    "sg:classifiers":[
        {
            "category":"Professional",
            "subcategory":"Management & Consulting",
            "type":"Services"
        }
    ],
    "sg:phone":"+1 301 792 4383",
    "sg:postcode":"20707",
    "sg:province":"MD",
    "sg:tags":[
        "consultant"
    ],
    "wof:name":"S/E Management Group",
    "wof:placetype":"venue"
},
  "geometry": {"coordinates":[-76.868438,39.082035],"type":"Point"}
}