{
  "type": "Feature",
  "properties": {
    "addr:full":"7111 Allentown Rd Fort Washington MD 20744",
    "addr:housenumber":"7111",
    "addr:postcode":"20744",
    "addr:street":"Allentown Rd",
    "iso:country":"US",
    "sg:address":"7111 Allentown Rd",
    "sg:city":"Fort Washington",
    "sg:classifiers":[
        {
            "category":"Health Services",
            "subcategory":"Doctor",
            "type":"Services"
        }
    ],
    "sg:phone":"+1 301 449 6226",
    "sg:postcode":"20744",
    "sg:province":"MD",
    "sg:tags":[
        "physician",
        "surgeon"
    ],
    "wof:name":"Metropolitan Family Ctr",
    "wof:placetype":"venue"
},
  "geometry": {"coordinates":[-76.92872199999999,38.793358],"type":"Point"}
}