{
  "type": "Feature",
  "properties": {
    "iso:country":"US",
    "sg:address":"12000 Indian Creek Ct",
    "sg:city":"Beltsville",
    "sg:classifiers":[
        {
            "category":"Real Estate",
            "subcategory":"Real Estate Agent",
            "type":"Services"
        }
    ],
    "sg:phone":"+1 301 419 3970",
    "sg:postcode":"20705",
    "sg:province":"MD",
    "sg:tags":[
        "management"
    ],
    "wof:name":"Liberty Property Trust",
    "wof:placetype":"venue"
},
  "geometry": {"coordinates":[-76.89676799999999,39.056176],"type":"Point"}
}