{
  "type": "Feature",
  "properties": {
    "iso:country":"US",
    "sg:address":"20 Pleasant Ridge Dr",
    "sg:city":"Owings Mills",
    "sg:classifiers":[
        {
            "category":"Social Services",
            "subcategory":"Child Care",
            "type":"Services"
        }
    ],
    "sg:phone":"+1 410 902 1151",
    "sg:postcode":"21117",
    "sg:province":"MD",
    "wof:name":"My Second Home",
    "wof:placetype":"venue"
},
  "geometry": {"coordinates":[-76.786639,39.424806],"type":"Point"}
}