{
  "type": "Feature",
  "properties": {
    "addr:full":"901 Crain Hwy S Glen Burnie MD 21061",
    "addr:housenumber":"901",
    "addr:postcode":"21061",
    "addr:street":"Crain Hwy S",
    "iso:country":"US",
    "sg:address":"901 Crain Hwy S",
    "sg:city":"Glen Burnie",
    "sg:classifiers":[
        {
            "category":"Retail",
            "subcategory":"Car Wash",
            "type":"Services"
        }
    ],
    "sg:phone":"+1 410 761 6935",
    "sg:postcode":"21061",
    "sg:province":"MD",
    "sg:tags":[
        "polishing",
        "washing"
    ],
    "wof:name":"Roy's Glen Burnie Car Wash",
    "wof:placetype":"venue"
},
  "geometry": {"coordinates":[-76.63082,39.154502],"type":"Point"}
}