{
  "type": "Feature",
  "properties": {
    "addr:full":"704 Quince Orchard Road Suite 330 Gaithersburg MD 20878",
    "addr:housenumber":"704",
    "addr:postcode":"20878",
    "addr:street":"Quince Orchard Road Suite 330",
    "iso:country":"US",
    "sg:address":"704 Quince Orchard Road Suite 330",
    "sg:city":"Gaithersburg",
    "sg:classifiers":[
        {
            "category":"Professional",
            "subcategory":"Computer Services",
            "type":"Services"
        }
    ],
    "sg:phone":"+1 443 248 4266",
    "sg:postcode":"20878",
    "sg:province":"MD",
    "sg:tags":[
        "entertainment",
        "medical-imaging",
        "security",
        "data-storage"
    ],
    "sg:website":"http://www.qbit.com",
    "wof:name":"Qbit",
    "wof:placetype":"venue"
},
  "geometry": {"coordinates":[-77.223833,39.134506],"type":"Point"}
}