{
  "type": "Feature",
  "properties": {
    "iso:country":"US",
    "sg:address":"12037 Belair Rd",
    "sg:city":"Kingsville",
    "sg:classifiers":[
        {
            "category":"Food & Beverages",
            "subcategory":"Groceries & Convenience Stores",
            "type":"Retail Goods"
        }
    ],
    "sg:phone":"+1 410 592 6202",
    "sg:postcode":"21087",
    "sg:province":"MD",
    "sg:tags":[
        "grocer"
    ],
    "wof:name":"Kingsville Market",
    "wof:placetype":"venue"
},
  "geometry": {"coordinates":[-76.417565,39.449908],"type":"Point"}
}