{
  "type": "Feature",
  "properties": {
    "iso:country":"US",
    "sg:address":"6565 N Charles St Ste 212",
    "sg:city":"Towson",
    "sg:classifiers":[
        {
            "category":"Health Services",
            "subcategory":"Doctor",
            "type":"Services"
        }
    ],
    "sg:phone":"+1 410 823 1120",
    "sg:postcode":"21204",
    "sg:province":"MD",
    "sg:tags":[
        "gynecology",
        "physician",
        "surgeon",
        "surgeons",
        "obstetrics"
    ],
    "sg:website":"http://www.csobgyn.com",
    "wof:name":"Charles Street Ob-Gyn Assoc",
    "wof:placetype":"venue"
},
  "geometry": {"coordinates":[-76.625832,39.388809],"type":"Point"}
}