{
  "type": "Feature",
  "properties": {
    "iso:country":"US",
    "sg:address":"825 Yale Ave",
    "sg:city":"Baltimore",
    "sg:classifiers":[
        {
            "category":"Professional",
            "type":"Services"
        }
    ],
    "sg:phone":"+1 410 368 1334",
    "sg:postcode":"21229",
    "sg:province":"MD",
    "sg:tags":[
        "caterer"
    ],
    "wof:name":"Class Act Catering by Jim Britton",
    "wof:placetype":"venue"
},
  "geometry": {"coordinates":[-76.691002,39.2729],"type":"Point"}
}