{
  "type": "Feature",
  "properties": {
    "addr:full":"102 W Joppa Rd Towson MD 21204",
    "addr:housenumber":"102",
    "addr:postcode":"21204",
    "addr:street":"W Joppa Rd",
    "iso:country":"US",
    "sg:address":"102 W Joppa Rd",
    "sg:city":"Towson",
    "sg:classifiers":[
        {
            "category":"Personal",
            "type":"Services"
        }
    ],
    "sg:phone":"+1 410 337 2808",
    "sg:postcode":"21204",
    "sg:province":"MD",
    "sg:tags":[
        "therapist",
        "massage"
    ],
    "wof:name":"Hands For Health",
    "wof:placetype":"venue"
},
  "geometry": {"coordinates":[-76.606697,39.40319],"type":"Point"}
}