{
  "type": "Feature",
  "properties": {
    "addr:full":"9019 Allenswood Rd Randallstown MD 21133",
    "addr:housenumber":"9019",
    "addr:postcode":"21133",
    "addr:street":"Allenswood Rd",
    "iso:country":"US",
    "sg:address":"9019 Allenswood Rd",
    "sg:city":"Randallstown",
    "sg:classifiers":[
        {
            "category":"Professional",
            "subcategory":"Management & Consulting",
            "type":"Services"
        }
    ],
    "sg:phone":"+1 410 521 3779",
    "sg:postcode":"21133",
    "sg:province":"MD",
    "sg:tags":[
        "business"
    ],
    "wof:name":"Associates Meeting and MGT",
    "wof:placetype":"venue"
},
  "geometry": {"coordinates":[-76.794561,39.373321],"type":"Point"}
}