{
  "type": "Feature",
  "properties": {
    "addr:full":"2232 E Monument St Baltimore MD 21205",
    "addr:housenumber":"2232",
    "addr:postcode":"21205",
    "addr:street":"E Monument St",
    "iso:country":"US",
    "sg:address":"2232 E Monument St",
    "sg:city":"Baltimore",
    "sg:classifiers":[
        {
            "category":"Shopping",
            "subcategory":"Clothing, Apparel, & Fashions",
            "type":"Retail Goods"
        }
    ],
    "sg:phone":"+1 410 558 0010",
    "sg:postcode":"21205",
    "sg:province":"MD",
    "sg:tags":[
        "men's",
        "clothing"
    ],
    "wof:name":"Stop Zone",
    "wof:placetype":"venue"
},
  "geometry": {"coordinates":[-76.585855,39.298693],"type":"Point"}
}