{
  "type": "Feature",
  "properties": {
    "addr:full":"23170 Kays Way Leonardtown MD 20609",
    "addr:postcode":"23170;20609",
    "addr:street":"Kays Way",
    "iso:country":"US",
    "sg:address":"23170 Kays Way",
    "sg:city":"Leonardtown",
    "sg:classifiers":[
        {
            "category":"Wholesale",
            "subcategory":"Construction Materials",
            "type":"Manufacturing & Wholesale Goods"
        }
    ],
    "sg:phone":"+1 301 481 1820",
    "sg:postcode":"20609",
    "sg:province":"MD",
    "sg:tags":[
        "fence"
    ],
    "wof:name":"Massey Fence Inc",
    "wof:placetype":"venue"
},
  "geometry": {"coordinates":[-76.74461599999999,38.304749],"type":"Point"}
}