{
  "type": "Feature",
  "properties": {
    "iso:country":"US",
    "sg:address":"23170 Kays Way",
    "sg:city":"Leonardtown",
    "sg:classifiers":[
        {
            "category":"Wholesale",
            "subcategory":"Construction Materials",
            "type":"Manufacturing & Wholesale Goods"
        }
    ],
    "sg:phone":"+1 301 481 1820",
    "sg:postcode":"20609",
    "sg:province":"MD",
    "sg:tags":[
        "fence"
    ],
    "wof:name":"Massey Fence Inc",
    "wof:placetype":"venue"
},
  "geometry": {"coordinates":[-76.744616,38.304749],"type":"Point"}
}