{
  "type": "Feature",
  "properties": {
    "addr:full":"3200 Cheverly Hills Ct Cheverly MD 20785",
    "addr:postcode":"3200;20785",
    "addr:street":"Cheverly Hills Ct",
    "iso:country":"US",
    "sg:address":"3200 Cheverly Hills Ct",
    "sg:city":"Cheverly",
    "sg:classifiers":[
        {
            "category":"Professional",
            "subcategory":"Advertising",
            "type":"Services"
        }
    ],
    "sg:phone":"+1 301 322 7779",
    "sg:postcode":"20785",
    "sg:province":"MD",
    "sg:tags":[
        "marketing"
    ],
    "sg:website":"www.wmgraphics.com",
    "wof:name":"WM Graphics",
    "wof:placetype":"venue"
},
  "geometry": {"coordinates":[-76.90483999999999,38.930422],"type":"Point"}
}