{
  "type": "Feature",
  "properties": {
    "iso:country":"US",
    "sg:address":"917 Wakefield Dr",
    "sg:city":"Havre De Grace",
    "sg:classifiers":[
        {
            "category":"Building & Trades",
            "subcategory":"Construction",
            "type":"Services"
        }
    ],
    "sg:phone":"+1 410 575 6558",
    "sg:postcode":"21078",
    "sg:province":"MD",
    "sg:tags":[
        "home",
        "improvement"
    ],
    "wof:name":"Churchville Home Improvement",
    "wof:placetype":"venue"
},
  "geometry": {"coordinates":[-76.114004,39.561918],"type":"Point"}
}