{
  "type": "Feature",
  "properties": {
    "addr:full":"11338 Chapel Rd Cordova MD 21625",
    "addr:housenumber":"11338",
    "addr:postcode":"21625",
    "addr:street":"Chapel Rd",
    "iso:country":"US",
    "sg:address":"11338 Chapel Rd",
    "sg:city":"Cordova",
    "sg:classifiers":[
        {
            "category":"Wholesale",
            "subcategory":"Machinery & Supplies",
            "type":"Manufacturing & Wholesale Goods"
        }
    ],
    "sg:phone":"+1 410 820 1400",
    "sg:postcode":"21625",
    "sg:province":"MD",
    "sg:tags":[
        "truck"
    ],
    "wof:name":"William H Foster Trucking",
    "wof:placetype":"venue"
},
  "geometry": {"coordinates":[-75.983422,38.846653],"type":"Point"}
}