{
  "type": "Feature",
  "properties": {
    "iso:country":"US",
    "sg:address":"808 E Oldtown Rd",
    "sg:city":"Cumberland",
    "sg:classifiers":[
        {
            "category":"Retail",
            "subcategory":"Portrait Studio",
            "type":"Services"
        }
    ],
    "sg:phone":"+1 301 722 2114",
    "sg:postcode":"21502",
    "sg:province":"MD",
    "sg:tags":[
        "photographer"
    ],
    "wof:name":"Chris Studio",
    "wof:placetype":"venue"
},
  "geometry": {"coordinates":[-78.749441,39.637643],"type":"Point"}
}