{
  "type": "Feature",
  "properties": {
    "addr:full":"7202 Central Ave Takoma Park MD 20912",
    "addr:housenumber":"7202",
    "addr:postcode":"20912",
    "addr:street":"Central Ave",
    "iso:country":"US",
    "sg:address":"7202 Central Ave",
    "sg:city":"Takoma Park",
    "sg:classifiers":[
        {
            "category":"Professional",
            "subcategory":"Business Services",
            "type":"Services"
        }
    ],
    "sg:phone":"+1 202 543 6614",
    "sg:postcode":"20912",
    "sg:province":"MD",
    "wof:name":"Message Design",
    "wof:placetype":"venue"
},
  "geometry": {"coordinates":[-76.99551200000001,38.983998],"type":"Point"}
}