{
  "type": "Feature",
  "properties": {
    "iso:country":"US",
    "sg:address":"508 Saint Paul St",
    "sg:city":"Baltimore",
    "sg:classifiers":[
        {
            "category":"Insurance",
            "subcategory":"Insurance Agent",
            "type":"Services"
        }
    ],
    "sg:phone":"+1 410 752 3036",
    "sg:postcode":"21202",
    "sg:province":"MD",
    "sg:website":"www.leizure.com",
    "wof:name":"Leizure Associates Inc",
    "wof:placetype":"venue"
},
  "geometry": {"coordinates":[-76.613991,39.296412],"type":"Point"}
}