{
  "type": "Feature",
  "properties": {
    "addr:full":"7906 Harford Rd Parkville MD 21234",
    "addr:housenumber":"7906",
    "addr:postcode":"21234",
    "addr:street":"Harford Rd",
    "iso:country":"US",
    "sg:address":"7906 Harford Rd",
    "sg:city":"Parkville",
    "sg:classifiers":[
        {
            "category":"Shopping",
            "subcategory":"Bicycles & Sporting Goods",
            "type":"Retail Goods"
        }
    ],
    "sg:phone":"+1 410 668 8050",
    "sg:postcode":"21234",
    "sg:province":"MD",
    "sg:tags":[
        "equipment",
        "camping"
    ],
    "wof:name":"Sunny's Great Outdoors Inc",
    "wof:placetype":"venue"
},
  "geometry": {"coordinates":[-76.541443,39.375357],"type":"Point"}
}