{
  "type": "Feature",
  "properties": {
    "iso:country":"US",
    "sg:address":"2209 Varnum St",
    "sg:city":"Mt Rainier",
    "sg:classifiers":[
        {
            "category":"Professional",
            "type":"Services"
        }
    ],
    "sg:phone":"+1 301 864 1780",
    "sg:postcode":"20712",
    "sg:province":"MD",
    "sg:tags":[
        "establishment"
    ],
    "wof:name":"Gfs Catering Inc",
    "wof:placetype":"venue"
},
  "geometry": {"coordinates":[-76.972562,38.94417],"type":"Point"}
}