{
  "type": "Feature",
  "properties": {
    "addr:full":"8124 Norris Ln Baltimore MD 21222",
    "addr:housenumber":"8124",
    "addr:postcode":"21222",
    "addr:street":"Norris Ln",
    "iso:country":"US",
    "sg:address":"8124 Norris Ln",
    "sg:city":"Baltimore",
    "sg:phone":"+1 410 288 0303",
    "sg:postcode":"21222",
    "sg:province":"MD",
    "sg:tags":[
        "bulk",
        "gas"
    ],
    "wof:name":"Praxair Distribution Inc",
    "wof:placetype":"venue"
},
  "geometry": {"coordinates":[-76.48504200000001,39.284452],"type":"Point"}
}