{
  "type": "Feature",
  "properties": {
    "iso:country":"US",
    "sg:address":"3211 Spartan Rd",
    "sg:city":"Olney",
    "sg:classifiers":[
        {
            "category":"Banks & Credit Unions",
            "subcategory":"Bank",
            "type":"Services"
        }
    ],
    "sg:phone":"+1 301 260 9711",
    "sg:postcode":"20832",
    "sg:province":"MD",
    "wof:name":"M & T Bank",
    "wof:placetype":"venue"
},
  "geometry": {"coordinates":[-77.062286,39.150743],"type":"Point"}
}