{
  "type": "Feature",
  "properties": {
    "addr:full":"311 Kentlands Blvd Gaithersburg MD 20878",
    "addr:housenumber":"311",
    "addr:postcode":"20878",
    "addr:street":"Kentlands Blvd",
    "iso:country":"US",
    "sg:address":"311 Kentlands Blvd",
    "sg:city":"Gaithersburg",
    "sg:classifiers":[
        {
            "category":"Restaurant",
            "type":"Food & Drink"
        }
    ],
    "sg:phone":"+1 301 519 1650",
    "sg:postcode":"20878",
    "sg:province":"MD",
    "sg:tags":[
        "seafood"
    ],
    "sg:website":"http://www.odonnellsrestaurant.com",
    "wof:name":"O'Donnell's; Sea Grill",
    "wof:placetype":"venue"
},
  "geometry": {"coordinates":[-77.238288,39.123393],"type":"Point"}
}