{
  "type": "Feature",
  "properties": {
    "addr:full":"813 E Main St Middletown MD 21769",
    "addr:housenumber":"813",
    "addr:postcode":"21769",
    "addr:street":"E Main St",
    "iso:country":"US",
    "sg:address":"813 E Main St",
    "sg:city":"Middletown",
    "sg:classifiers":[
        {
            "category":"Retail",
            "subcategory":"Laundry & Dry Cleaning",
            "type":"Services"
        }
    ],
    "sg:phone":"+1 301 371 9336",
    "sg:postcode":"21769",
    "sg:province":"MD",
    "wof:name":"Town Cleaners",
    "wof:placetype":"venue"
},
  "geometry": {"coordinates":[-77.525902,39.437401],"type":"Point"}
}