{
  "type": "Feature",
  "properties": {
    "addr:full":"1850 Dual Hwy Hagerstown MD 21740",
    "addr:housenumber":"1850",
    "addr:postcode":"21740",
    "addr:street":"Dual Hwy",
    "iso:country":"US",
    "sg:address":"1850 Dual Hwy",
    "sg:city":"Hagerstown",
    "sg:classifiers":[
        {
            "category":"Real Estate",
            "subcategory":"Real Estate Services",
            "type":"Services"
        }
    ],
    "sg:phone":"+1 240 420 0033",
    "sg:postcode":"21740",
    "sg:province":"MD",
    "sg:tags":[
        "company",
        "title"
    ],
    "wof:name":"Universal Title",
    "wof:placetype":"venue"
},
  "geometry": {"coordinates":[-77.68890399999999,39.611039],"type":"Point"}
}