{
  "type": "Feature",
  "properties": {
    "addr:full":"4966 Allan Rd Bethesda MD 20816",
    "addr:housenumber":"4966",
    "addr:postcode":"20816",
    "addr:street":"Allan Rd",
    "iso:country":"US",
    "sg:address":"4966 Allan Rd",
    "sg:city":"Bethesda",
    "sg:classifiers":[
        {
            "category":"Professional",
            "subcategory":"Research",
            "type":"Services"
        }
    ],
    "sg:phone":"+1 301 320 3849",
    "sg:postcode":"20816",
    "sg:province":"MD",
    "wof:name":"Research Center",
    "wof:placetype":"venue"
},
  "geometry": {"coordinates":[-77.09974800000001,38.952052],"type":"Point"}
}