{
  "type": "Feature",
  "properties": {
    "iso:country":"US",
    "sg:address":"4966 Allan Rd",
    "sg:city":"Bethesda",
    "sg:classifiers":[
        {
            "category":"Professional",
            "subcategory":"Research",
            "type":"Services"
        }
    ],
    "sg:phone":"+1 301 320 3849",
    "sg:postcode":"20816",
    "sg:province":"MD",
    "wof:name":"Research Center",
    "wof:placetype":"venue"
},
  "geometry": {"coordinates":[-77.099748,38.952052],"type":"Point"}
}