{
  "type": "Feature",
  "properties": {
    "addr:full":"46 Dungarrie Rd Catonsville MD 21228",
    "addr:housenumber":"46",
    "addr:postcode":"21228",
    "addr:street":"Dungarrie Rd",
    "iso:country":"US",
    "sg:address":"46 Dungarrie Rd",
    "sg:city":"Catonsville",
    "sg:classifiers":[
        {
            "category":"Retail",
            "subcategory":"Portrait Studio",
            "type":"Services"
        },
        {
            "category":"Professional",
            "subcategory":"Art Services",
            "type":"Services"
        }
    ],
    "sg:phone":"+1 443 975 4356",
    "sg:postcode":"21228",
    "sg:province":"MD",
    "sg:tags":[
        "rental",
        "photographers-portrait",
        "photographic",
        "darkroom"
    ],
    "wof:name":"Dawn Kearney Photography",
    "wof:placetype":"venue"
},
  "geometry": {"coordinates":[-76.722556,39.27701],"type":"Point"}
}