{
  "type": "Feature",
  "properties": {
    "iso:country":"US",
    "sg:address":"5406 East Dr",
    "sg:city":"Halethorpe",
    "sg:classifiers":[
        {
            "category":"Insurance",
            "subcategory":"Insurance Agent",
            "type":"Services"
        },
        {
            "category":"Insurance",
            "subcategory":"Hazard Insurance",
            "type":"Services"
        },
        {
            "category":"Insurance",
            "subcategory":"Title Insurance",
            "type":"Services"
        },
        {
            "category":"Insurance",
            "subcategory":"Life Insurance",
            "type":"Services"
        }
    ],
    "sg:phone":"+1 410 247 7804",
    "sg:postcode":"21227",
    "sg:province":"MD",
    "sg:tags":[
        "business",
        "auto",
        "commercial",
        "homeowner",
        "motorcycle",
        "renter"
    ],
    "wof:name":"Allstate Insurance Company - Andrew Pons",
    "wof:placetype":"venue"
},
  "geometry": {"coordinates":[-76.69372300000001,39.248353],"type":"Point"}
}