{
  "type": "Feature",
  "properties": {
    "addr:full":"38 Lee St Annapolis MD 21401",
    "addr:housenumber":"38",
    "addr:postcode":"21401",
    "addr:street":"Lee St",
    "iso:country":"US",
    "sg:address":"38 Lee St",
    "sg:city":"Annapolis",
    "sg:classifiers":[
        {
            "category":"Home & Garden",
            "subcategory":"Home Furnishings",
            "type":"Retail Goods"
        }
    ],
    "sg:phone":"+1 410 224 2214",
    "sg:postcode":"21401",
    "sg:province":"MD",
    "sg:tags":[
        "blind",
        "draperies",
        "installation",
        "vertical",
        "curtains",
        "blinds-venetian",
        "window",
        "treatment",
        "shade",
        "curtain"
    ],
    "sg:website":"http://annapoliswindowcovering.com",
    "wof:name":"Annapolis Window Covering",
    "wof:placetype":"venue"
},
  "geometry": {"coordinates":[-76.52747599999999,38.980213],"type":"Point"}
}