{
  "type": "Feature",
  "properties": {
    "addr:full":"5801 Baltimore Ave Riverdale MD 20737",
    "addr:housenumber":"5801",
    "addr:postcode":"20737",
    "addr:street":"Baltimore Ave",
    "iso:country":"US",
    "sg:address":"5801 Baltimore Ave",
    "sg:city":"Riverdale",
    "sg:classifiers":[
        {
            "category":"Professional",
            "subcategory":"Accounting & Tax Preparation",
            "type":"Services"
        }
    ],
    "sg:phone":"+1 301 864 8488",
    "sg:postcode":"20737",
    "sg:province":"MD",
    "sg:tags":[
        "return",
        "filing"
    ],
    "wof:name":"R & B Income Tax & Real Est",
    "wof:placetype":"venue"
},
  "geometry": {"coordinates":[-76.939858,38.95845],"type":"Point"}
}