{
  "type": "Feature",
  "properties": {
    "iso:country":"US",
    "sg:address":"600 Sunburst Hwy",
    "sg:city":"Cambridge",
    "sg:classifiers":[
        {
            "category":"Restaurant",
            "type":"Food & Drink"
        }
    ],
    "sg:phone":"+1 410 221 0022",
    "sg:postcode":"21613",
    "sg:province":"MD",
    "wof:name":"Pizza Palace Greek & Italian",
    "wof:placetype":"venue"
},
  "geometry": {"coordinates":[-76.065887,38.562416],"type":"Point"}
}