{
  "type": "Feature",
  "properties": {
    "addr:full":"4401 Eastern Ave Ste 37 Baltimore MD 21224",
    "addr:housenumber":"4401",
    "addr:postcode":"21224",
    "addr:street":"Eastern Ave Ste 37",
    "iso:country":"US",
    "sg:address":"4401 Eastern Ave Ste 37",
    "sg:city":"Baltimore",
    "sg:classifiers":[
        {
            "category":"Manufacturing",
            "subcategory":"Wood Products",
            "type":"Manufacturing & Wholesale Goods"
        }
    ],
    "sg:phone":"+1 410 732 4400",
    "sg:postcode":"21224",
    "sg:province":"MD",
    "sg:tags":[
        "cabinets-wholesale",
        "manufacturer"
    ],
    "wof:name":"J K Cabinet",
    "wof:placetype":"venue"
},
  "geometry": {"coordinates":[-76.55856300000001,39.28693],"type":"Point"}
}