{
  "type": "Feature",
  "properties": {
    "addr:full":"3001 Shepperd Rd Monkton MD 21111",
    "addr:housenumber":"3001",
    "addr:postcode":"21111",
    "addr:street":"Shepperd Rd",
    "iso:country":"US",
    "sg:address":"3001 Shepperd Rd",
    "sg:city":"Monkton",
    "sg:classifiers":[
        {
            "category":"Recreation",
            "type":"Entertainment"
        }
    ],
    "sg:phone":"+1 410 472 4475",
    "sg:postcode":"21111",
    "sg:province":"MD",
    "sg:tags":[
        "riding",
        "academy"
    ],
    "wof:name":"J-Mar Stables Inc",
    "wof:placetype":"venue"
},
  "geometry": {"coordinates":[-76.574207,39.590324],"type":"Point"}
}