{
  "type": "Feature",
  "properties": {
    "addr:full":"1100 Taft St Rockville MD 20850",
    "addr:housenumber":"1100",
    "addr:postcode":"20850",
    "addr:street":"Taft St",
    "iso:country":"US",
    "sg:address":"1100 Taft St",
    "sg:city":"Rockville",
    "sg:classifiers":[
        {
            "category":"Building & Trades",
            "subcategory":"Pest Control",
            "type":"Services"
        }
    ],
    "sg:phone":"+1 301 251 2080",
    "sg:postcode":"20850",
    "sg:province":"MD",
    "wof:name":"Horizon Pest Control",
    "wof:placetype":"venue"
},
  "geometry": {"coordinates":[-77.137168,39.094036],"type":"Point"}
}