{
  "type": "Feature",
  "properties": {
    "addr:full":"2280 Glenmore Ter Rockville MD 20850",
    "addr:housenumber":"2280",
    "addr:postcode":"20850",
    "addr:street":"Glenmore Ter",
    "iso:country":"US",
    "sg:address":"2280 Glenmore Ter",
    "sg:city":"Rockville",
    "sg:classifiers":[
        {
            "category":"Manufacturing",
            "subcategory":"Buildings",
            "type":"Manufacturing & Wholesale Goods"
        },
        {
            "category":"Building & Trades",
            "subcategory":"Construction",
            "type":"Services"
        }
    ],
    "sg:phone":"+1 301 424 6164",
    "sg:postcode":"20850",
    "sg:province":"MD",
    "sg:tags":[
        "industrial",
        "system",
        "specialty",
        "builder",
        "heating",
        "contractor",
        "contractors-commercial",
        "home",
        "air conditioning"
    ],
    "wof:name":"John L Dufief Inc",
    "wof:placetype":"venue"
},
  "geometry": {"coordinates":[-77.18647300000001,39.089578],"type":"Point"}
}