{
  "type": "Feature",
  "properties": {
    "addr:full":"9658 Baltimore Ave College Park MD 20740",
    "addr:housenumber":"9658",
    "addr:postcode":"20740",
    "addr:street":"Baltimore Ave",
    "iso:country":"US",
    "sg:address":"9658 Baltimore Ave",
    "sg:city":"College Park",
    "sg:classifiers":[
        {
            "category":"Professional",
            "subcategory":"Management & Consulting",
            "type":"Services"
        }
    ],
    "sg:phone":"+1 301 982 1574",
    "sg:postcode":"20740",
    "sg:province":"MD",
    "sg:tags":[
        "consultant",
        "broker"
    ],
    "wof:name":"Information Technology Support",
    "wof:placetype":"venue"
},
  "geometry": {"coordinates":[-76.92794000000001,39.013957],"type":"Point"}
}