{
  "type": "Feature",
  "properties": {
    "iso:country":"US",
    "sg:address":"10262 Lake Arbor Way",
    "sg:city":"Bowie",
    "sg:classifiers":[
        {
            "category":"Restaurant",
            "type":"Food & Drink"
        }
    ],
    "sg:menulink":"http://www.allmenus.com/md/kent/81456-papa-johns-pizza/menu/",
    "sg:phone":"+1 301 499 6262",
    "sg:postcode":"20721",
    "sg:province":"MD",
    "sg:tags":[
        "american",
        "pizza"
    ],
    "wof:name":"Papa John's Pizza",
    "wof:placetype":"venue"
},
  "geometry": {"coordinates":[-76.829846,38.90525],"type":"Point"}
}