{
  "type": "Feature",
  "properties": {
    "addr:full":"20 Delaware Ct Aberdeen Proving Ground MD 21005",
    "addr:housenumber":"20",
    "addr:postcode":"21005",
    "addr:street":"Delaware Ct",
    "iso:country":"US",
    "sg:address":"20 Delaware Ct",
    "sg:city":"Aberdeen Proving Ground",
    "sg:classifiers":[
        {
            "category":"Government",
            "subcategory":"Office",
            "type":"Public Place"
        }
    ],
    "sg:phone":"+1 410 297 9171",
    "sg:postcode":"21005",
    "sg:province":"MD",
    "sg:tags":[
        "safety",
        "order"
    ],
    "wof:name":"Mark Levario",
    "wof:placetype":"venue"
},
  "geometry": {"coordinates":[-76.15682,39.501885],"type":"Point"}
}