{
  "type": "Feature",
  "properties": {
    "iso:country":"US",
    "sg:address":"1811 Latham Dr",
    "sg:city":"Frederick",
    "sg:classifiers":[
        {
            "category":"Organizations",
            "subcategory":"Religious Organization",
            "type":"Services"
        }
    ],
    "sg:phone":"+1 301 695 9053",
    "sg:postcode":"21701",
    "sg:province":"MD",
    "sg:tags":[
        "church"
    ],
    "wof:name":"Church Of Jesus Christ Spanish",
    "wof:placetype":"venue"
},
  "geometry": {"coordinates":[-77.374046,39.45092],"type":"Point"}
}