{
  "type": "Feature",
  "properties": {
    "addr:full":"501 N Rolling Rd Catonsville MD 21228",
    "addr:housenumber":"501",
    "addr:postcode":"21228",
    "addr:street":"N Rolling Rd",
    "iso:country":"US",
    "sg:address":"501 N Rolling Rd",
    "sg:city":"Catonsville",
    "sg:classifiers":[
        {
            "category":"Community Center",
            "subcategory":"Senior",
            "type":"Public Place"
        },
        {
            "category":"Social Services",
            "subcategory":"Adult Care",
            "type":"Services"
        }
    ],
    "sg:phone":"+1 410 744 0170",
    "sg:postcode":"21228",
    "sg:province":"MD",
    "sg:tags":[
        "counseling",
        "citizen"
    ],
    "wof:name":"Greater Catonsville Senior",
    "wof:placetype":"venue"
},
  "geometry": {"coordinates":[-76.754593,39.279739],"type":"Point"}
}