{
  "type": "Feature",
  "properties": {
    "addr:full":"4639 Chatsworth Way Ellicott City MD 21043",
    "addr:housenumber":"4639",
    "addr:postcode":"21043",
    "addr:street":"Chatsworth Way",
    "iso:country":"US",
    "sg:address":"4639 Chatsworth Way",
    "sg:city":"Ellicott City",
    "sg:classifiers":[
        {
            "category":"Professional",
            "subcategory":"Computer Services",
            "type":"Services"
        }
    ],
    "sg:phone":"+1 410 461 8119",
    "sg:postcode":"21043",
    "sg:province":"MD",
    "sg:tags":[
        "related"
    ],
    "wof:name":"Daiva Computer Access Bus",
    "wof:placetype":"venue"
},
  "geometry": {"coordinates":[-76.80604700000001,39.242732],"type":"Point"}
}