{
  "type": "Feature",
  "properties": {
    "iso:country":"US",
    "sg:address":"9420 Key West Ave",
    "sg:city":"Rockville",
    "sg:classifiers":[
        {
            "category":"Banks & Credit Unions",
            "subcategory":"Investment Brokerage",
            "type":"Services"
        }
    ],
    "sg:phone":"+1 301 340 0135",
    "sg:postcode":"20850",
    "sg:province":"MD",
    "sg:tags":[
        "advisory",
        "financial"
    ],
    "wof:name":"Diversified Financial",
    "wof:placetype":"venue"
},
  "geometry": {"coordinates":[-77.18904499999999,39.102616],"type":"Point"}
}