{
  "type": "Feature",
  "properties": {
    "addr:full":"1515 W Mount Royal Ave Baltimore MD 21217",
    "addr:housenumber":"1515",
    "addr:postcode":"21217",
    "addr:street":"W Mount Royal Ave",
    "iso:country":"US",
    "sg:address":"1515 W Mount Royal Ave",
    "sg:city":"Baltimore",
    "sg:classifiers":[
        {
            "category":"Government",
            "subcategory":"Office",
            "type":"Public Place"
        }
    ],
    "sg:phone":"+1 410 333 6111",
    "sg:postcode":"21217",
    "sg:province":"MD",
    "sg:tags":[
        "state",
        "program"
    ],
    "wof:name":"Div Of Rehabilitation Svc",
    "wof:placetype":"venue"
},
  "geometry": {"coordinates":[-76.623591,39.310054],"type":"Point"}
}