{
  "type": "Feature",
  "properties": {
    "addr:full":"11114 Innsbrook Way Ijamsville MD 21754",
    "addr:housenumber":"11114",
    "addr:postcode":"21754",
    "addr:street":"Innsbrook Way",
    "iso:country":"US",
    "sg:address":"11114 Innsbrook Way",
    "sg:city":"Ijamsville",
    "sg:classifiers":[
        {
            "category":"Real Estate",
            "subcategory":"Architect",
            "type":"Services"
        }
    ],
    "sg:phone":"+1 301 798 0880",
    "sg:postcode":"21754",
    "sg:province":"MD",
    "sg:tags":[
        "architectural"
    ],
    "wof:name":"Urie Professional Corp",
    "wof:placetype":"venue"
},
  "geometry": {"coordinates":[-77.28200200000001,39.313749],"type":"Point"}
}