{
  "type": "Feature",
  "properties": {
    "addr:full":"813 S Sharp St Baltimore MD 21230",
    "addr:housenumber":"813",
    "addr:postcode":"21230",
    "addr:street":"S Sharp St",
    "iso:country":"US",
    "sg:address":"813 S Sharp St",
    "sg:city":"Baltimore",
    "sg:classifiers":[
        {
            "category":"Place Of Worship",
            "subcategory":"Church",
            "type":"Public Place"
        },
        {
            "category":"Place Of Worship",
            "type":"Public Place"
        }
    ],
    "sg:phone":"+1 410 727 9303",
    "sg:postcode":"21230",
    "sg:province":"MD",
    "sg:tags":[
        "churches-interdenominational",
        "churches-various",
        "denomination"
    ],
    "wof:name":"Christ Spiritual Temple",
    "wof:placetype":"venue"
},
  "geometry": {"coordinates":[-76.617756,39.280305],"type":"Point"}
}