{
  "type": "Feature",
  "properties": {
    "iso:country":"US",
    "sg:address":"5639 Annapolis Rd",
    "sg:city":"Bladensburg",
    "sg:classifiers":[
        {
            "category":"Professional",
            "subcategory":"Accounting & Tax Preparation",
            "type":"Services"
        }
    ],
    "sg:phone":"+1 301 779 2800",
    "sg:postcode":"20710",
    "sg:province":"MD",
    "sg:tags":[
        "accountant"
    ],
    "wof:name":"Olukoya & Associates CPA",
    "wof:placetype":"venue"
},
  "geometry": {"coordinates":[-76.919601,38.939201],"type":"Point"}
}