{
  "type": "Feature",
  "properties": {
    "addr:full":"4481 Nicole Dr Lanham MD 20706",
    "addr:housenumber":"4481",
    "addr:postcode":"20706",
    "addr:street":"Nicole Dr",
    "iso:country":"US",
    "sg:address":"4481 Nicole Dr",
    "sg:city":"Lanham",
    "sg:classifiers":[
        {
            "category":"Manufacturing",
            "subcategory":"Electronics",
            "type":"Manufacturing & Wholesale Goods"
        }
    ],
    "sg:phone":"+1 301 564 0600",
    "sg:postcode":"20706",
    "sg:province":"MD",
    "sg:tags":[
        "sound",
        "equipment",
        "system"
    ],
    "sg:website":"www.americanamplifier.com",
    "wof:name":"American Amplifier & TV Corp",
    "wof:placetype":"venue"
},
  "geometry": {"coordinates":[-76.829716,38.948811],"type":"Point"}
}