{
  "type": "Feature",
  "properties": {
    "addr:full":"7932 Mapleville Rd Boonsboro MD 21713",
    "addr:housenumber":"7932",
    "addr:postcode":"21713",
    "addr:street":"Mapleville Rd",
    "iso:country":"US",
    "sg:address":"7932 Mapleville Rd",
    "sg:city":"Boonsboro",
    "sg:classifiers":[
        {
            "category":"Health Services",
            "subcategory":"Clinic",
            "type":"Services"
        }
    ],
    "sg:phone":"+1 301 432 4402",
    "sg:postcode":"21713",
    "sg:province":"MD",
    "sg:tags":[
        "home",
        "care"
    ],
    "wof:name":"Sara Trevey",
    "wof:placetype":"venue"
},
  "geometry": {"coordinates":[-77.64748899999999,39.531162],"type":"Point"}
}