{
  "type": "Feature",
  "properties": {
    "addr:full":"3547 Chestnut Ave Baltimore MD 21211",
    "addr:housenumber":"3547",
    "addr:postcode":"21211",
    "addr:street":"Chestnut Ave",
    "iso:country":"US",
    "sg:address":"3547 Chestnut Ave",
    "sg:city":"Baltimore",
    "sg:classifiers":[
        {
            "category":"Bars & Pubs",
            "type":"Food & Drink"
        },
        {
            "category":"Restaurant",
            "type":"Food & Drink"
        },
        {
            "category":"Bars & Pubs",
            "subcategory":"Lounge",
            "type":"Food & Drink"
        }
    ],
    "sg:phone":"+1 443 438 7521",
    "sg:postcode":"21211",
    "sg:province":"MD",
    "sg:tags":[
        "tavern",
        "cocktail"
    ],
    "wof:name":"Grano",
    "wof:placetype":"venue"
},
  "geometry": {"coordinates":[-76.62936500000001,39.330766],"type":"Point"}
}