{
  "type": "Feature",
  "properties": {
    "iso:country":"US",
    "sg:address":"38325 Laurel Ridge Dr",
    "sg:city":"Mechanicsville",
    "sg:classifiers":[
        {
            "category":"Building & Trades",
            "subcategory":"Construction",
            "type":"Services"
        }
    ],
    "sg:phone":"+1 301 884 8440",
    "sg:postcode":"20659",
    "sg:province":"MD",
    "sg:tags":[
        "altering",
        "remodeling",
        "contractor"
    ],
    "sg:website":"http://www.worldclasshomeinspections.com",
    "wof:name":"World Class Home Improvement",
    "wof:placetype":"venue"
},
  "geometry": {"coordinates":[-76.749748,38.482189],"type":"Point"}
}