{
  "type": "Feature",
  "properties": {
    "iso:country":"US",
    "sg:address":"7851 Mayfield Ave",
    "sg:city":"Elkridge",
    "sg:classifiers":[
        {
            "category":"Personal",
            "type":"Services"
        }
    ],
    "sg:phone":"+1 410 799 4456",
    "sg:postcode":"21075",
    "sg:province":"MD",
    "wof:name":"American Service Call Inc",
    "wof:placetype":"venue"
},
  "geometry": {"coordinates":[-76.785479,39.194705],"type":"Point"}
}