{
  "type": "Feature",
  "properties": {
    "addr:full":"77 West St Annapolis MD 21401",
    "addr:housenumber":"77",
    "addr:postcode":"21401",
    "addr:street":"West St",
    "iso:country":"US",
    "sg:address":"77 West St",
    "sg:city":"Annapolis",
    "sg:classifiers":[
        {
            "category":"Social Services",
            "type":"Services"
        }
    ],
    "sg:phone":"+1 410 990 9054",
    "sg:postcode":"21401",
    "sg:province":"MD",
    "sg:tags":[
        "child",
        "referral",
        "care"
    ],
    "wof:name":"Arundle Child Care Connections",
    "wof:placetype":"venue"
},
  "geometry": {"coordinates":[-76.49609,38.978158],"type":"Point"}
}