{
  "type": "Feature",
  "properties": {
    "iso:country":"US",
    "sg:address":"5209 Deal Dr",
    "sg:city":"Oxon Hill",
    "sg:classifiers":[
        {
            "category":"Professional",
            "subcategory":"Art Services",
            "type":"Services"
        }
    ],
    "sg:phone":"+1 301 567 0035",
    "sg:postcode":"20745",
    "sg:province":"MD",
    "sg:tags":[
        "design",
        "graphics"
    ],
    "wof:name":"H L Holloway Productions",
    "wof:placetype":"venue"
},
  "geometry": {"coordinates":[-76.9935,38.818292],"type":"Point"}
}