{
  "type": "Feature",
  "properties": {
    "iso:country":"US",
    "sg:address":"3717 Decatur Ave Ste 2",
    "sg:city":"Kensington",
    "sg:classifiers":[
        {
            "category":"Professional",
            "subcategory":"Lawyer & Legal Services",
            "type":"Services"
        }
    ],
    "sg:phone":"+1 301 949 4656",
    "sg:postcode":"20895",
    "sg:province":"MD",
    "wof:name":"Harry B Sewell Jr",
    "wof:placetype":"venue"
},
  "geometry": {"coordinates":[-77.0728,39.033901],"type":"Point"}
}