{
  "type": "Feature",
  "properties": {
    "addr:full":"14100 Vom Hainberg Pl Charlotte Hall MD 20622",
    "addr:postcode":"14100;20622",
    "addr:street":"Hainberg Pl",
    "iso:country":"US",
    "sg:address":"14100 Vom Hainberg Pl",
    "sg:city":"Charlotte Hall",
    "sg:classifiers":[
        {
            "category":"Building & Trades",
            "subcategory":"Construction",
            "type":"Services"
        }
    ],
    "sg:phone":"+1 301 932 8687",
    "sg:postcode":"20622",
    "sg:province":"MD",
    "sg:tags":[
        "layer",
        "carpet"
    ],
    "wof:name":"Charles County Floors",
    "wof:placetype":"venue"
},
  "geometry": {"coordinates":[-76.82446299999999,38.494025],"type":"Point"}
}