{
  "type": "Feature",
  "properties": {
    "iso:country":"US",
    "sg:address":"130 Austin Cir",
    "sg:city":"Berlin",
    "sg:classifiers":[
        {
            "category":"Health Services",
            "subcategory":"Clinic",
            "type":"Services"
        }
    ],
    "sg:phone":"+1 410 641 0388",
    "sg:postcode":"21811",
    "sg:province":"MD",
    "sg:tags":[
        "information",
        "alcoholism",
        "treatment"
    ],
    "wof:name":"White Flint Recovery Easte",
    "wof:placetype":"venue"
},
  "geometry": {"coordinates":[-75.22444900000001,38.331907],"type":"Point"}
}