{
  "type": "Feature",
  "properties": {
    "iso:country":"US",
    "sg:address":"14300 Gallant Fox Ln",
    "sg:city":"Bowie",
    "sg:classifiers":[
        {
            "category":"Professional",
            "subcategory":"Computer Services",
            "type":"Services"
        }
    ],
    "sg:phone":"+1 301 262 7110",
    "sg:postcode":"20715",
    "sg:province":"MD",
    "sg:tags":[
        "processing",
        "datum"
    ],
    "wof:name":"Regional Data Processing Inc",
    "wof:placetype":"venue"
},
  "geometry": {"coordinates":[-76.75674600000001,38.972598],"type":"Point"}
}