{
  "type": "Feature",
  "properties": {
    "iso:country":"US",
    "sg:address":"12535 Brandenburg Hollow Rd",
    "sg:city":"Myersville",
    "sg:classifiers":[
        {
            "category":"Retail",
            "subcategory":"Animal Services",
            "type":"Services"
        }
    ],
    "sg:phone":"+1 301 662 8067",
    "sg:postcode":"21773",
    "sg:province":"MD",
    "wof:name":"Companions For Life Inc",
    "wof:placetype":"venue"
},
  "geometry": {"coordinates":[-77.546643,39.584771],"type":"Point"}
}