{
  "type": "Feature",
  "properties": {
    "iso:country":"US",
    "sg:address":"2214 Spencerville Rd",
    "sg:city":"Spencerville",
    "sg:classifiers":[
        {
            "category":"Building & Trades",
            "subcategory":"Landscaping Services",
            "type":"Services"
        }
    ],
    "sg:phone":"+1 301 421 1911",
    "sg:postcode":"20868",
    "sg:province":"MD",
    "wof:name":"C & M Nursery",
    "wof:placetype":"venue"
},
  "geometry": {"coordinates":[-76.963453,39.116378],"type":"Point"}
}