{
  "type": "Feature",
  "properties": {
    "iso:country":"US",
    "sg:address":"9127 Hampton Overlook",
    "sg:city":"Capitol Heights",
    "sg:classifiers":[
        {
            "category":"Building & Trades",
            "subcategory":"Construction",
            "type":"Services"
        }
    ],
    "sg:phone":"+1 240 475 5617",
    "sg:postcode":"20743",
    "sg:province":"MD",
    "sg:tags":[
        "handyman",
        "window",
        "installation"
    ],
    "sg:website":"restorationtechnologyinc.com",
    "wof:name":"Restoration Technology Inc.",
    "wof:placetype":"venue"
},
  "geometry": {"coordinates":[-76.849692,38.885851],"type":"Point"}
}