{
  "type": "Feature",
  "properties": {
    "addr:full":"34 Market Pl Baltimore MD 21202",
    "addr:housenumber":"34",
    "addr:postcode":"21202",
    "addr:street":"Market Pl",
    "iso:country":"US",
    "sg:address":"34 Market Pl",
    "sg:city":"Baltimore",
    "sg:classifiers":[
        {
            "category":"Shopping",
            "subcategory":"Computers & Home Electronics",
            "type":"Retail Goods"
        }
    ],
    "sg:phone":"+1 410 752 7910",
    "sg:postcode":"21202",
    "sg:province":"MD",
    "sg:tags":[
        "audio"
    ],
    "wof:name":"National Audio Supply Inc",
    "wof:placetype":"venue"
},
  "geometry": {"coordinates":[-76.60717200000001,39.289005],"type":"Point"}
}