{
  "type": "Feature",
  "properties": {
    "iso:country":"US",
    "sg:address":"7838 Beechcraft Ave",
    "sg:city":"Gaithersburg",
    "sg:classifiers":[
        {
            "category":"Wholesale",
            "subcategory":"Durable Goods & Equipment",
            "type":"Manufacturing & Wholesale Goods"
        }
    ],
    "sg:phone":"+1 301 208 0445",
    "sg:postcode":"20879",
    "sg:province":"MD",
    "sg:tags":[
        "laboratory",
        "supply"
    ],
    "wof:name":"Elmeco Engineering",
    "wof:placetype":"venue"
},
  "geometry": {"coordinates":[-77.16313100000001,39.163781],"type":"Point"}
}