{
  "type": "Feature",
  "properties": {
    "addr:full":"11606 Greencastle Pike Hagerstown MD 21740",
    "addr:housenumber":"11606",
    "addr:postcode":"21740",
    "addr:street":"Greencastle Pike",
    "iso:country":"US",
    "sg:address":"11606 Greencastle Pike",
    "sg:city":"Hagerstown",
    "sg:classifiers":[
        {
            "category":"Wholesale",
            "subcategory":"Machinery & Supplies",
            "type":"Manufacturing & Wholesale Goods"
        }
    ],
    "sg:phone":"+1 301 223 6877",
    "sg:postcode":"21740",
    "sg:province":"MD",
    "sg:tags":[
        "equipment",
        "dairy"
    ],
    "wof:name":"Agri-SERVICE LLC",
    "wof:placetype":"venue"
},
  "geometry": {"coordinates":[-77.807535,39.636278],"type":"Point"}
}