{
  "type": "Feature",
  "properties": {
    "addr:full":"8808 Baltimore Ave College Park MD 20740",
    "addr:housenumber":"8808",
    "addr:postcode":"20740",
    "addr:street":"Baltimore Ave",
    "iso:country":"US",
    "sg:address":"8808 Baltimore Ave",
    "sg:city":"College Park",
    "sg:classifiers":[
        {
            "category":"Retail",
            "subcategory":"Auto Repair",
            "type":"Services"
        }
    ],
    "sg:phone":"+1 301 982 2999",
    "sg:postcode":"20740",
    "sg:province":"MD",
    "sg:tags":[
        "automobile",
        "lubrication"
    ],
    "wof:name":"Jiffy Lube",
    "wof:placetype":"venue"
},
  "geometry": {"coordinates":[-76.931629,38.998359],"type":"Point"}
}