{
  "type": "Feature",
  "properties": {
    "addr:full":"207 Courtland Ave Ste 100 Towson MD 21204",
    "addr:housenumber":"207",
    "addr:postcode":"21204",
    "addr:street":"Courtland Ave Ste 100",
    "iso:country":"US",
    "sg:address":"207 Courtland Ave Ste 100",
    "sg:city":"Towson",
    "sg:classifiers":[
        {
            "category":"Organizations",
            "subcategory":"Community Association",
            "type":"Services"
        }
    ],
    "sg:phone":"+1 410 832 1812",
    "sg:postcode":"21204",
    "sg:province":"MD",
    "sg:tags":[
        "club"
    ],
    "wof:name":"Baltimore County Historical Trust",
    "wof:placetype":"venue"
},
  "geometry": {"coordinates":[-76.606651,39.397659],"type":"Point"}
}