{
  "type": "Feature",
  "properties": {
    "addr:full":"308 Sunburst Hwy Cambridge MD 21613",
    "addr:housenumber":"308",
    "addr:postcode":"21613",
    "addr:street":"Sunburst Hwy",
    "iso:country":"US",
    "sg:address":"308 Sunburst Hwy",
    "sg:city":"Cambridge",
    "sg:classifiers":[
        {
            "category":"Ice Cream",
            "type":"Food & Drink"
        }
    ],
    "sg:menulink":"http://www.allmenus.com/md/cambridge/234542-ritas-ice-custard-happiness/menu/",
    "sg:phone":"+1 410 228 8001",
    "sg:postcode":"21613",
    "sg:province":"MD",
    "sg:tags":[
        "american"
    ],
    "wof:name":"Rita's Ice Custard Happiness",
    "wof:placetype":"venue"
},
  "geometry": {"coordinates":[-76.064892,38.566538],"type":"Point"}
}