{
  "type": "Feature",
  "properties": {
    "addr:full":"15455 Emerald Way Bowie MD 20716",
    "addr:housenumber":"15455",
    "addr:postcode":"20716",
    "addr:street":"Emerald Way",
    "iso:country":"US",
    "sg:address":"15455 Emerald Way",
    "sg:city":"Bowie",
    "sg:classifiers":[
        {
            "category":"Shopping",
            "subcategory":"Books",
            "type":"Retail Goods"
        }
    ],
    "sg:phone":"+1 301 809 1552",
    "sg:postcode":"20716",
    "sg:province":"MD",
    "sg:tags":[
        "dealer"
    ],
    "wof:name":"Barnes & Noble Booksellers",
    "wof:placetype":"venue"
},
  "geometry": {"coordinates":[-76.73486800000001,38.943005],"type":"Point"}
}