{
  "type": "Feature",
  "properties": {
    "iso:country":"US",
    "sg:address":"122 Westway Apt 203",
    "sg:city":"Greenbelt",
    "sg:classifiers":[
        {
            "category":"Professional",
            "subcategory":"Research",
            "type":"Services"
        }
    ],
    "sg:phone":"+1 301 405 8038",
    "sg:postcode":"20770",
    "sg:province":"MD",
    "sg:tags":[
        "development",
        "electronics",
        "technology-research"
    ],
    "wof:name":"Calceepsc",
    "wof:placetype":"venue"
},
  "geometry": {"coordinates":[-76.883038,38.998576],"type":"Point"}
}