{
  "type": "Feature",
  "properties": {
    "addr:full":"555 Fairmount Ave Towson MD 21286",
    "addr:housenumber":"555",
    "addr:postcode":"21286",
    "addr:street":"Fairmount Ave",
    "iso:country":"US",
    "sg:address":"555 Fairmount Ave",
    "sg:city":"Towson",
    "sg:classifiers":[
        {
            "category":"Insurance",
            "subcategory":"Insurance Agent",
            "type":"Services"
        }
    ],
    "sg:phone":"+1 410 339 5860",
    "sg:postcode":"21286",
    "sg:province":"MD",
    "wof:name":"Monaghan Tilghman & Hoyle",
    "wof:placetype":"venue"
},
  "geometry": {"coordinates":[-76.596431,39.40009],"type":"Point"}
}