{
  "type": "Feature",
  "properties": {
    "iso:country":"US",
    "sg:address":"2620 Riva Rd",
    "sg:city":"Annapolis",
    "sg:classifiers":[
        {
            "category":"Health Services",
            "subcategory":"Hospital",
            "type":"Services"
        }
    ],
    "sg:phone":"+1 410 573 5400",
    "sg:postcode":"21401",
    "sg:province":"MD",
    "sg:tags":[
        "specialty"
    ],
    "sg:website":"www.pathways.org",
    "wof:name":"Pathways",
    "wof:placetype":"venue"
},
  "geometry": {"coordinates":[-76.558504,38.97546],"type":"Point"}
}