{
  "type": "Feature",
  "properties": {
    "iso:country":"US",
    "sg:address":"100 Joehill Dr",
    "sg:city":"Havre De Grace",
    "sg:classifiers":[
        {
            "category":"Education",
            "subcategory":"Special Training",
            "type":"Public Place"
        }
    ],
    "sg:phone":"+1 410 939 7592",
    "sg:postcode":"21078",
    "sg:province":"MD",
    "sg:tags":[
        "substance",
        "abuse"
    ],
    "wof:name":"Keith Hayes",
    "wof:placetype":"venue"
},
  "geometry": {"coordinates":[-76.109817,39.553248],"type":"Point"}
}