{
  "type": "Feature",
  "properties": {
    "iso:country":"US",
    "sg:address":"1227 Carroll St",
    "sg:city":"Baltimore",
    "sg:classifiers":[
        {
            "category":"Shopping",
            "subcategory":"Department Store",
            "type":"Retail Goods"
        }
    ],
    "sg:phone":"+1 410 385 2255",
    "sg:postcode":"21230",
    "sg:province":"MD",
    "sg:tags":[
        "variety"
    ],
    "wof:name":"Cents",
    "wof:placetype":"venue"
},
  "geometry": {"coordinates":[-76.63328,39.280613],"type":"Point"}
}