{
  "type": "Feature",
  "properties": {
    "addr:full":"13631 Cedar Creek Ln Silver Spring MD 20904",
    "addr:housenumber":"13631",
    "addr:postcode":"20904",
    "addr:street":"Cedar Creek Ln",
    "iso:country":"US",
    "sg:address":"13631 Cedar Creek Ln",
    "sg:city":"Silver Spring",
    "sg:classifiers":[
        {
            "category":"Professional",
            "subcategory":"Management & Consulting",
            "type":"Services"
        }
    ],
    "sg:phone":"+1 301 384 1952",
    "sg:postcode":"20904",
    "sg:province":"MD",
    "sg:tags":[
        "consultant",
        "business"
    ],
    "wof:name":"Decision Dynamics Inc",
    "wof:placetype":"venue"
},
  "geometry": {"coordinates":[-76.972528,39.077444],"type":"Point"}
}