{
  "type": "Feature",
  "properties": {
    "addr:full":"856 Ivy League Ln Rockville MD 20850",
    "addr:housenumber":"856",
    "addr:postcode":"20850",
    "addr:street":"Ivy League Ln",
    "iso:country":"US",
    "sg:address":"856 Ivy League Ln",
    "sg:city":"Rockville",
    "sg:classifiers":[
        {
            "category":"Professional",
            "subcategory":"Employment Agencies",
            "type":"Services"
        }
    ],
    "sg:phone":"+1 301 251 0853",
    "sg:postcode":"20850",
    "sg:province":"MD",
    "sg:tags":[
        "teachers'"
    ],
    "wof:name":"Washington Education Institute",
    "wof:placetype":"venue"
},
  "geometry": {"coordinates":[-77.154021,39.095033],"type":"Point"}
}