{
  "type": "Feature",
  "properties": {
    "iso:country":"US",
    "sg:address":"847 N Montford Ave",
    "sg:city":"Baltimore",
    "sg:classifiers":[
        {
            "category":"Food & Beverages",
            "subcategory":"Groceries & Convenience Stores",
            "type":"Retail Goods"
        }
    ],
    "sg:phone":"+1 410 732 1367",
    "sg:postcode":"21205",
    "sg:province":"MD",
    "sg:tags":[
        "grocer"
    ],
    "wof:name":"Mama's Grocery Store",
    "wof:placetype":"venue"
},
  "geometry": {"coordinates":[-76.5839,39.300301],"type":"Point"}
}