{
  "type": "Feature",
  "properties": {
    "iso:country":"US",
    "sg:address":"10243 York Rd",
    "sg:city":"Cockeysville",
    "sg:classifiers":[
        {
            "category":"Personal",
            "type":"Services"
        },
        {
            "category":"Retail",
            "subcategory":"Laundry & Dry Cleaning",
            "type":"Services"
        }
    ],
    "sg:phone":"+1 410 667 0768",
    "sg:postcode":"21030",
    "sg:province":"MD",
    "sg:tags":[
        "sewing",
        "alteration"
    ],
    "wof:name":"E M Lee Llc",
    "wof:placetype":"venue"
},
  "geometry": {"coordinates":[-76.63877100000001,39.470011],"type":"Point"}
}