{
  "type": "Feature",
  "properties": {
    "iso:country":"US",
    "sg:address":"1509 Garrett Dr",
    "sg:city":"Frederick",
    "sg:classifiers":[
        {
            "category":"Retail",
            "subcategory":"Car Wash",
            "type":"Services"
        }
    ],
    "sg:phone":"+1 301 631 1421",
    "sg:postcode":"21702",
    "sg:province":"MD",
    "sg:tags":[
        "polishing",
        "washing"
    ],
    "sg:website":"www.fredericktowneautospa.com",
    "wof:name":"Frederick Towne Auto Spa",
    "wof:placetype":"venue"
},
  "geometry": {"coordinates":[-77.468153,39.420638],"type":"Point"}
}