{
  "type": "Feature",
  "properties": {
    "iso:country":"US",
    "sg:address":"1239 Ocean Hwy",
    "sg:city":"Pocomoke City",
    "sg:classifiers":[
        {
            "category":"Wholesale",
            "subcategory":"Vending Machines",
            "type":"Manufacturing & Wholesale Goods"
        }
    ],
    "sg:phone":"+1 410 957 2781",
    "sg:postcode":"21851",
    "sg:province":"MD",
    "wof:name":"Delmarva Amusement Svc Inc",
    "wof:placetype":"venue"
},
  "geometry": {"coordinates":[-75.541929,38.035096],"type":"Point"}
}