{
  "type": "Feature",
  "properties": {
    "addr:full":"759 Washington Blvd Baltimore MD 21230",
    "addr:housenumber":"759",
    "addr:postcode":"21230",
    "addr:street":"Washington Blvd",
    "iso:country":"US",
    "sg:address":"759 Washington Blvd",
    "sg:city":"Baltimore",
    "sg:classifiers":[
        {
            "category":"Personal",
            "subcategory":"Barber",
            "type":"Services"
        }
    ],
    "sg:phone":"+1 410 528 8222",
    "sg:postcode":"21230",
    "sg:province":"MD",
    "wof:name":"Greg Esquire 2 Barber Shop",
    "wof:placetype":"venue"
},
  "geometry": {"coordinates":[-76.627719,39.282863],"type":"Point"}
}