{
  "type": "Feature",
  "properties": {
    "iso:country":"US",
    "sg:address":"12904 Sunset Ave",
    "sg:city":"Ocean City",
    "sg:classifiers":[
        {
            "category":"Wholesale",
            "subcategory":"Machinery & Supplies",
            "type":"Manufacturing & Wholesale Goods"
        }
    ],
    "sg:phone":"+1 410 213 9373",
    "sg:postcode":"21842",
    "sg:province":"MD",
    "sg:tags":[
        "contractor"
    ],
    "wof:name":"Alban Engine Power Systems",
    "wof:placetype":"venue"
},
  "geometry": {"coordinates":[-75.10942,38.327914],"type":"Point"}
}