{
  "type": "Feature",
  "properties": {
    "addr:full":"9400 Livingston Rd Fort Washington MD 20744",
    "addr:housenumber":"9400",
    "addr:postcode":"20744",
    "addr:street":"Livingston Rd",
    "iso:country":"US",
    "sg:address":"9400 Livingston Rd",
    "sg:city":"Fort Washington",
    "sg:classifiers":[
        {
            "category":"Banks & Credit Unions",
            "subcategory":"Investment Brokerage",
            "type":"Services"
        }
    ],
    "sg:phone":"+1 301 248 1307",
    "sg:postcode":"20744",
    "sg:province":"MD",
    "sg:tags":[
        "consultant",
        "financing"
    ],
    "wof:name":"Washington Consulting Ctr",
    "wof:placetype":"venue"
},
  "geometry": {"coordinates":[-76.99533,38.763805],"type":"Point"}
}