{
  "type": "Feature",
  "properties": {
    "addr:full":"1703 Guilford Ave Baltimore MD 21202",
    "addr:housenumber":"1703",
    "addr:postcode":"21202",
    "addr:street":"Guilford Ave",
    "iso:country":"US",
    "sg:address":"1703 Guilford Ave",
    "sg:city":"Baltimore",
    "sg:classifiers":[
        {
            "category":"Manufacturing",
            "subcategory":"Printing",
            "type":"Manufacturing & Wholesale Goods"
        }
    ],
    "sg:phone":"+1 410 685 2660",
    "sg:postcode":"21202",
    "sg:province":"MD",
    "sg:tags":[
        "newspaper"
    ],
    "wof:name":"Capital Region Reporter",
    "wof:placetype":"venue"
},
  "geometry": {"coordinates":[-76.612298,39.309974],"type":"Point"}
}