{
  "type": "Feature",
  "properties": {
    "addr:full":"1410 Crain Hwy S Glen Burnie MD 21061",
    "addr:housenumber":"1410",
    "addr:postcode":"21061",
    "addr:street":"Crain Hwy S",
    "iso:country":"US",
    "sg:address":"1410 Crain Hwy S",
    "sg:city":"Glen Burnie",
    "sg:classifiers":[
        {
            "category":"Health Services",
            "subcategory":"Doctor",
            "type":"Services"
        }
    ],
    "sg:phone":"+1 410 768 5566",
    "sg:postcode":"21061",
    "sg:province":"MD",
    "wof:name":"Kwon Jung D",
    "wof:placetype":"venue"
},
  "geometry": {"coordinates":[-76.631635,39.152503],"type":"Point"}
}