{
  "type": "Feature",
  "properties": {
    "addr:full":"10006 Falls Rd Potomac MD 20854",
    "addr:housenumber":"10006",
    "addr:postcode":"20854",
    "addr:street":"Falls Rd",
    "iso:country":"US",
    "sg:address":"10006 Falls Rd",
    "sg:city":"Potomac",
    "sg:classifiers":[
        {
            "category":"Health Services",
            "subcategory":"Dentist",
            "type":"Services"
        }
    ],
    "sg:phone":"+1 301 983 0371",
    "sg:postcode":"20854",
    "sg:province":"MD",
    "wof:name":"Tamami Farzam DDS",
    "wof:placetype":"venue"
},
  "geometry": {"coordinates":[-77.208634,39.019248],"type":"Point"}
}