{
  "type": "Feature",
  "properties": {
    "iso:country":"US",
    "sg:address":"1320 Crain Hwy",
    "sg:city":"Bowie",
    "sg:classifiers":[
        {
            "category":"Food & Beverages",
            "subcategory":"Meat & Fish",
            "type":"Retail Goods"
        }
    ],
    "sg:phone":"+1 301 390 2542",
    "sg:postcode":"20716",
    "sg:province":"MD",
    "sg:tags":[
        "seafood"
    ],
    "wof:name":"Fresh Blue Waters Inc",
    "wof:placetype":"venue"
},
  "geometry": {"coordinates":[-76.718479,38.907125],"type":"Point"}
}