{
  "type": "Feature",
  "properties": {
    "addr:full":"6505 Bock Rd Oxon Hill MD 20745",
    "addr:housenumber":"6505",
    "addr:postcode":"20745",
    "addr:street":"Bock Rd",
    "iso:country":"US",
    "sg:address":"6505 Bock Rd",
    "sg:city":"Oxon Hill",
    "sg:classifiers":[
        {
            "category":"Utilities",
            "subcategory":"Refuse",
            "type":"Services"
        }
    ],
    "sg:phone":"+1 301 567 1731",
    "sg:postcode":"20745",
    "sg:province":"MD",
    "sg:tags":[
        "garbage",
        "collection"
    ],
    "wof:name":"James Murphy Roll Off Svc",
    "wof:placetype":"venue"
},
  "geometry": {"coordinates":[-76.982631,38.800649],"type":"Point"}
}