{
  "type": "Feature",
  "properties": {
    "iso:country":"US",
    "sg:address":"126 Sherwood Ave",
    "sg:city":"Pikesville",
    "sg:classifiers":[
        {
            "category":"Health Services",
            "subcategory":"Doctor",
            "type":"Services"
        }
    ],
    "sg:phone":"+1 410 484 5945",
    "sg:postcode":"21208",
    "sg:province":"MD",
    "sg:tags":[
        "medicine",
        "physician",
        "practice",
        "surgeons",
        "family"
    ],
    "wof:name":"Levin & Levin L L C",
    "wof:placetype":"venue"
},
  "geometry": {"coordinates":[-76.724029,39.371465],"type":"Point"}
}