{
  "type": "Feature",
  "properties": {
    "iso:country":"US",
    "sg:address":"7935 Wisconsin Ave",
    "sg:city":"Bethesda",
    "sg:classifiers":[
        {
            "category":"Restaurant",
            "type":"Food & Drink"
        }
    ],
    "sg:menulink":"http://www.allmenus.com/md/bethesda/29599-benihana/menu/",
    "sg:phone":"+1 301 652 5391",
    "sg:postcode":"20814",
    "sg:province":"MD",
    "sg:tags":[
        "japanese",
        "asian"
    ],
    "wof:name":"Benihana",
    "wof:placetype":"venue"
},
  "geometry": {"coordinates":[-77.095354,38.989932],"type":"Point"}
}