{
  "type": "Feature",
  "properties": {
    "addr:full":"38980 Hodges Rd Avenue MD 20609",
    "addr:postcode":"38980;20609",
    "addr:street":"Hodges Rd Avenue",
    "iso:country":"US",
    "sg:address":"38980 Hodges Rd",
    "sg:city":"Avenue",
    "sg:phone":"+1 301 769 4853",
    "sg:postcode":"20609",
    "sg:province":"MD",
    "sg:tags":[
        "farm",
        "soybean"
    ],
    "wof:name":"David Seeman",
    "wof:placetype":"venue"
},
  "geometry": {"coordinates":[-76.724901,38.274157],"type":"Point"}
}