{
  "type": "Feature",
  "properties": {
    "iso:country":"US",
    "sg:address":"305 Dean Dr",
    "sg:city":"Rockville",
    "sg:classifiers":[
        {
            "category":"Wholesale",
            "subcategory":"Durable Goods & Equipment",
            "type":"Manufacturing & Wholesale Goods"
        }
    ],
    "sg:phone":"+1 301 251 4444",
    "sg:postcode":"20851",
    "sg:province":"MD",
    "wof:name":"Royal Imports",
    "wof:placetype":"venue"
},
  "geometry": {"coordinates":[-77.123859,39.079143],"type":"Point"}
}