{
  "type": "Feature",
  "properties": {
    "iso:country":"US",
    "sg:address":"13389 Rollie Rd W",
    "sg:city":"Bishopville",
    "sg:classifiers":[
        {
            "category":"Professional",
            "subcategory":"Advertising",
            "type":"Services"
        }
    ],
    "sg:phone":"+1 410 352 5683",
    "sg:postcode":"21813",
    "sg:province":"MD",
    "sg:tags":[
        "agency"
    ],
    "wof:name":"Ramb Assoc",
    "wof:placetype":"venue"
},
  "geometry": {"coordinates":[-75.128128,38.448269],"type":"Point"}
}