{
  "type": "Feature",
  "properties": {
    "iso:country":"US",
    "sg:address":"22521 Sweetleaf Ln",
    "sg:city":"Gaithersburg",
    "sg:classifiers":[
        {
            "category":"Home & Garden",
            "subcategory":"Home Furnishings",
            "type":"Retail Goods"
        },
        {
            "category":"Manufacturing",
            "subcategory":"Soap",
            "type":"Manufacturing & Wholesale Goods"
        }
    ],
    "sg:phone":"+1 301 414 0213",
    "sg:postcode":"20882",
    "sg:province":"MD",
    "sg:tags":[
        "housewares",
        "housewares-wholesale",
        "manufacturer"
    ],
    "wof:name":"Foreign Accents",
    "wof:placetype":"venue"
},
  "geometry": {"coordinates":[-77.187438,39.226377],"type":"Point"}
}