{
  "type": "Feature",
  "properties": {
    "iso:country":"US",
    "sg:address":"10451 Twin Rivers Rd",
    "sg:city":"Columbia",
    "sg:classifiers":[
        {
            "category":"Utilities",
            "subcategory":"Telephone",
            "type":"Services"
        }
    ],
    "sg:phone":"+1 410 997 9399",
    "sg:postcode":"21044",
    "sg:province":"MD",
    "sg:tags":[
        "communications"
    ],
    "wof:name":"Telemarketingdotcom",
    "wof:placetype":"venue"
},
  "geometry": {"coordinates":[-76.87546,39.221786],"type":"Point"}
}