{
  "type": "Feature",
  "properties": {
    "iso:country":"US",
    "sg:address":"401 Logan Dr",
    "sg:city":"Westminster",
    "sg:classifiers":[
        {
            "category":"Autos & Motor Vehicles",
            "subcategory":"Auto Supplies",
            "type":"Retail Goods"
        }
    ],
    "sg:phone":"+1 301 461 6866",
    "sg:postcode":"21157",
    "sg:province":"MD",
    "sg:tags":[
        "automobile",
        "accessory"
    ],
    "wof:name":"Lojack",
    "wof:placetype":"venue"
},
  "geometry": {"coordinates":[-76.98039300000001,39.579482],"type":"Point"}
}