{
  "type": "Feature",
  "properties": {
    "addr:full":"22741 Three Notch Rd California MD 20619",
    "addr:housenumber":"22741",
    "addr:postcode":"20619",
    "addr:street":"Three Notch Rd",
    "iso:country":"US",
    "sg:address":"22741 Three Notch Rd",
    "sg:city":"California",
    "sg:classifiers":[
        {
            "category":"Health Services",
            "subcategory":"Doctor",
            "type":"Services"
        }
    ],
    "sg:phone":"+1 301 862 3338",
    "sg:postcode":"20619",
    "sg:province":"MD",
    "sg:tags":[
        "podiatrist"
    ],
    "wof:name":"St Mary's Foot & Ankle",
    "wof:placetype":"venue"
},
  "geometry": {"coordinates":[-76.533897,38.3116],"type":"Point"}
}