{
  "type": "Feature",
  "properties": {
    "addr:full":"2790 Old Washington Rd Waldorf MD 20601",
    "addr:housenumber":"2790",
    "addr:postcode":"20601",
    "addr:street":"Old Washington Rd",
    "iso:country":"US",
    "sg:address":"2790 Old Washington Rd",
    "sg:city":"Waldorf",
    "sg:classifiers":[
        {
            "category":"Freight",
            "type":"Transportation"
        }
    ],
    "sg:phone":"+1 301 645 0883",
    "sg:postcode":"20601",
    "sg:province":"MD",
    "sg:tags":[
        "commercial",
        "storage"
    ],
    "wof:name":"Associates Secure Self-Storage",
    "wof:placetype":"venue"
},
  "geometry": {"coordinates":[-76.899562,38.633356],"type":"Point"}
}