{
  "type": "Feature",
  "properties": {
    "iso:country":"US",
    "sg:address":"2902 Mcgee Way",
    "sg:city":"Olney",
    "sg:classifiers":[
        {
            "category":"Professional",
            "subcategory":"Detective & Security Services",
            "type":"Services"
        }
    ],
    "sg:phone":"+1 301 570 8005",
    "sg:postcode":"20832",
    "sg:province":"MD",
    "sg:tags":[
        "information",
        "bureau"
    ],
    "wof:name":"Sage Services",
    "wof:placetype":"venue"
},
  "geometry": {"coordinates":[-77.059133,39.152202],"type":"Point"}
}