{
  "type": "Feature",
  "properties": {
    "iso:country":"US",
    "sg:address":"5260 Western Ave",
    "sg:city":"Chevy Chase",
    "sg:classifiers":[
        {
            "category":"Insurance",
            "subcategory":"Hazard Insurance",
            "type":"Services"
        }
    ],
    "sg:phone":"+1 301 986 2500",
    "sg:postcode":"20815",
    "sg:province":"MD",
    "sg:website":"www.geico.com",
    "wof:name":"Geico Insurance",
    "wof:placetype":"venue"
},
  "geometry": {"coordinates":[-77.0895,38.957802],"type":"Point"}
}