{
  "type": "Feature",
  "properties": {
    "iso:country":"US",
    "sg:address":"5119 Indian Head Hwy",
    "sg:city":"Oxon Hill",
    "sg:classifiers":[
        {
            "category":"Restaurant",
            "type":"Food & Drink"
        }
    ],
    "sg:menulink":"http://www.allmenus.com/md/oxon-hill/146934-subway/menu/",
    "sg:phone":"+1 301 839 0072",
    "sg:postcode":"20745",
    "sg:province":"MD",
    "sg:tags":[
        "american",
        "sandwich"
    ],
    "wof:name":"Subway",
    "wof:placetype":"venue"
},
  "geometry": {"coordinates":[-77.00040799999999,38.819171],"type":"Point"}
}