{
  "type": "Feature",
  "properties": {
    "iso:country":"US",
    "sg:address":"3090 Old Washington Rd",
    "sg:city":"Waldorf",
    "sg:classifiers":[
        {
            "category":"Bars & Pubs",
            "type":"Food & Drink"
        }
    ],
    "sg:phone":"+1 301 843 3566",
    "sg:postcode":"20601",
    "sg:province":"MD",
    "sg:tags":[
        "club",
        "night"
    ],
    "wof:name":"Gold Mine Saloon",
    "wof:placetype":"venue"
},
  "geometry": {"coordinates":[-76.908029,38.624827],"type":"Point"}
}