{
  "type": "Feature",
  "properties": {
    "addr:full":"4 Main St Walkersville MD 21793",
    "addr:housenumber":"4",
    "addr:postcode":"21793",
    "addr:street":"Main St",
    "iso:country":"US",
    "sg:address":"4 Main St",
    "sg:city":"Walkersville",
    "sg:classifiers":[
        {
            "category":"Shopping",
            "subcategory":"Antiques",
            "type":"Retail Goods"
        }
    ],
    "sg:phone":"+1 301 865 8578",
    "sg:postcode":"21793",
    "sg:province":"MD",
    "wof:name":"Hunting Doll",
    "wof:placetype":"venue"
},
  "geometry": {"coordinates":[-77.348913,39.482809],"type":"Point"}
}