{
  "type": "Feature",
  "properties": {
    "iso:country":"US",
    "sg:address":"901 E Main St",
    "sg:city":"Salisbury",
    "sg:classifiers":[
        {
            "category":"Insurance",
            "subcategory":"Insurance Agent",
            "type":"Services"
        }
    ],
    "sg:phone":"+1 410 546 1322",
    "sg:postcode":"21804",
    "sg:province":"MD",
    "sg:tags":[
        "life",
        "carrier"
    ],
    "wof:name":"Shore Benefit Services Inc",
    "wof:placetype":"venue"
},
  "geometry": {"coordinates":[-75.58297,38.367779],"type":"Point"}
}