{
  "type": "Feature",
  "properties": {
    "addr:full":"15942 Shady Grove Rd Gaithersburg MD 20850",
    "addr:housenumber":"15942",
    "addr:postcode":"20850",
    "addr:street":"Shady Grove Rd",
    "iso:country":"US",
    "sg:address":"15942 Shady Grove Rd",
    "sg:city":"Gaithersburg",
    "sg:classifiers":[
        {
            "category":"Restaurant",
            "type":"Food & Drink"
        }
    ],
    "sg:phone":"+1 240 632 9500",
    "sg:postcode":"20850",
    "sg:province":"MD",
    "wof:name":"Pho Nam Restaurant",
    "wof:placetype":"venue"
},
  "geometry": {"coordinates":[-77.18231900000001,39.119201],"type":"Point"}
}