{
  "type": "Feature",
  "properties": {
    "addr:full":"9617 Crystal Falls Dr Hagerstown MD 21740",
    "addr:housenumber":"9617",
    "addr:postcode":"21740",
    "addr:street":"Crystal Falls Dr",
    "iso:country":"US",
    "sg:address":"9617 Crystal Falls Dr",
    "sg:city":"Hagerstown",
    "sg:classifiers":[
        {
            "category":"Building & Trades",
            "subcategory":"Construction",
            "type":"Services"
        }
    ],
    "sg:phone":"+1 301 416 7493",
    "sg:postcode":"21740",
    "sg:province":"MD",
    "sg:tags":[
        "house"
    ],
    "wof:name":"J A Foltz Home Improvement",
    "wof:placetype":"venue"
},
  "geometry": {"coordinates":[-77.61032899999999,39.584234],"type":"Point"}
}