{
  "type": "Feature",
  "properties": {
    "addr:full":"7460 Conowingo Ave Ste 59 Jessup MD 20794",
    "addr:housenumber":"7460",
    "addr:postcode":"20794",
    "addr:street":"Conowingo Ave Ste 59",
    "iso:country":"US",
    "sg:address":"7460 Conowingo Ave Ste 59",
    "sg:city":"Jessup",
    "sg:classifiers":[
        {
            "category":"Wholesale",
            "subcategory":"Fruits & Vegetables",
            "type":"Manufacturing & Wholesale Goods"
        }
    ],
    "sg:phone":"+1 410 799 8074",
    "sg:postcode":"20794",
    "sg:province":"MD",
    "sg:tags":[
        "vegetables-wholesale"
    ],
    "wof:name":"New World Wholesale",
    "wof:placetype":"venue"
},
  "geometry": {"coordinates":[-76.783354,39.16553],"type":"Point"}
}