{
  "type": "Feature",
  "properties": {
    "addr:full":"4740 Hatcrown Point Dr Tyaskin MD 21865",
    "addr:housenumber":"4740",
    "addr:postcode":"21865",
    "addr:street":"Hatcrown Point Dr",
    "iso:country":"US",
    "sg:address":"4740 Hatcrown Point Dr",
    "sg:city":"Tyaskin",
    "sg:classifiers":[
        {
            "category":"Manufacturing",
            "subcategory":"Buildings",
            "type":"Manufacturing & Wholesale Goods"
        },
        {
            "category":"Building & Trades",
            "subcategory":"Construction",
            "type":"Services"
        }
    ],
    "sg:phone":"+1 410 873 2825",
    "sg:postcode":"21865",
    "sg:province":"MD",
    "sg:tags":[
        "home",
        "builder",
        "contractor"
    ],
    "wof:name":"Three J Construction",
    "wof:placetype":"venue"
},
  "geometry": {"coordinates":[-75.879153,38.326046],"type":"Point"}
}