{
  "type": "Feature",
  "properties": {
    "iso:country":"US",
    "sg:address":"3423 Fort Meade Rd",
    "sg:city":"Laurel",
    "sg:classifiers":[
        {
            "category":"Manufacturing",
            "subcategory":"Printing",
            "type":"Manufacturing & Wholesale Goods"
        }
    ],
    "sg:phone":"+1 301 986 6990",
    "sg:postcode":"20724",
    "sg:province":"MD",
    "sg:tags":[
        "publisher"
    ],
    "wof:name":"Teora USA",
    "wof:placetype":"venue"
},
  "geometry": {"coordinates":[-76.813434,39.099754],"type":"Point"}
}