{
  "type": "Feature",
  "properties": {
    "iso:country":"US",
    "sg:address":"2818 Urbana Dr",
    "sg:city":"Silver Spring",
    "sg:classifiers":[
        {
            "category":"Professional",
            "subcategory":"Accounting & Tax Preparation",
            "type":"Services"
        }
    ],
    "sg:phone":"+1 301 933 9400",
    "sg:postcode":"20906",
    "sg:province":"MD",
    "sg:tags":[
        "billing"
    ],
    "wof:name":"Accelerated Billing Concepts",
    "wof:placetype":"venue"
},
  "geometry": {"coordinates":[-77.061116,39.060229],"type":"Point"}
}