{
  "type": "Feature",
  "properties": {
    "addr:full":"214 Najoles Rd Millersville MD 21108",
    "addr:housenumber":"214",
    "addr:postcode":"21108",
    "addr:street":"Najoles Rd",
    "iso:country":"US",
    "sg:address":"214 Najoles Rd",
    "sg:city":"Millersville",
    "sg:classifiers":[
        {
            "category":"Freight",
            "type":"Transportation"
        }
    ],
    "sg:phone":"+1 410 987 0538",
    "sg:postcode":"21108",
    "sg:province":"MD",
    "sg:tags":[
        "broker",
        "trucking"
    ],
    "wof:name":"Beatty Trucking Inc",
    "wof:placetype":"venue"
},
  "geometry": {"coordinates":[-76.63147600000001,39.095062],"type":"Point"}
}