{
  "type": "Feature",
  "properties": {
    "iso:country":"US",
    "sg:address":"216 Emory St",
    "sg:city":"Baltimore",
    "sg:classifiers":[
        {
            "category":"Landmark",
            "subcategory":"Historic",
            "type":"Public Place"
        },
        {
            "category":"Landmark",
            "subcategory":"Tourist Information",
            "type":"Public Place"
        },
        {
            "category":"Museum",
            "type":"Entertainment"
        }
    ],
    "sg:phone":"+1 410 727 1539",
    "sg:postcode":"21230",
    "sg:province":"MD",
    "sg:tags":[
        "building",
        "historical",
        "attraction"
    ],
    "sg:website":"www.baberuthmuseum.com/",
    "wof:name":"Babe Ruth Birthplace Museum",
    "wof:placetype":"venue"
},
  "geometry": {"coordinates":[-76.624853,39.285576],"type":"Point"}
}