{
  "type": "Feature",
  "properties": {
    "addr:city":"Baltimore",
    "addr:full":"216 Emory St Baltimore, Md 21230-2203",
    "addr:house_number":"216",
    "addr:housenumber":"216",
    "addr:phone":"+1 410-727-1539",
    "addr:postcode":"21230-2203",
    "addr:road":"Emory St",
    "addr:state":"MD",
    "addr:street":"Emory St",
    "iso:country":"US",
    "sg:address":"216 Emory St",
    "sg:city":"Baltimore",
    "sg:classifiers":[
        {
            "category":"Landmark",
            "subcategory":"Historic",
            "type":"Public Place"
        },
        {
            "category":"Landmark",
            "subcategory":"Tourist Information",
            "type":"Public Place"
        },
        {
            "category":"Museum",
            "type":"Entertainment"
        }
    ],
    "sg:phone":"+1 410 727 1539",
    "sg:postcode":"21230",
    "sg:province":"MD",
    "sg:tags":[
        "building",
        "historical",
        "attraction"
    ],
    "sg:website":"www.baberuthmuseum.com/",
    "wof:airports":[
        102527121,
        102532047
    ],
    "wof:name":"Babe Ruth Birthplace",
    "wof:placetype":"venue"
},
  "geometry": {"coordinates":[-76.62475999999999,39.28564],"type":"Point"}
}