{
  "type": "Feature",
  "properties": {
    "iso:country":"US",
    "sg:address":"1013 Willowleaf Way",
    "sg:city":"Rockville",
    "sg:classifiers":[
        {
            "category":"Real Estate",
            "subcategory":"Real Estate Agent",
            "type":"Services"
        }
    ],
    "sg:phone":"+1 301 762 5954",
    "sg:postcode":"20854",
    "sg:province":"MD",
    "sg:tags":[
        "consultant"
    ],
    "wof:name":"Housing Perspectives Inc",
    "wof:placetype":"venue"
},
  "geometry": {"coordinates":[-77.166452,39.071398],"type":"Point"}
}