{
  "type": "Feature",
  "properties": {
    "addr:full":"1013 Willowleaf Way Rockville MD 20854",
    "addr:housenumber":"1013",
    "addr:postcode":"20854",
    "addr:street":"Willowleaf Way",
    "iso:country":"US",
    "sg:address":"1013 Willowleaf Way",
    "sg:city":"Rockville",
    "sg:classifiers":[
        {
            "category":"Real Estate",
            "subcategory":"Real Estate Agent",
            "type":"Services"
        }
    ],
    "sg:phone":"+1 301 762 5954",
    "sg:postcode":"20854",
    "sg:province":"MD",
    "sg:tags":[
        "consultant"
    ],
    "wof:name":"Housing Perspectives Inc",
    "wof:placetype":"venue"
},
  "geometry": {"coordinates":[-77.16645200000001,39.071398],"type":"Point"}
}