{
  "type": "Feature",
  "properties": {
    "addr:full":"8213 Jumpers Hole Rd Millersville MD 21108",
    "addr:housenumber":"8213",
    "addr:postcode":"21108",
    "addr:street":"Jumpers Hole Rd",
    "iso:country":"US",
    "sg:address":"8213 Jumpers Hole Rd",
    "sg:city":"Millersville",
    "sg:classifiers":[
        {
            "category":"Shopping",
            "subcategory":"Stationery & Office Supplies",
            "type":"Retail Goods"
        },
        {
            "category":"Professional",
            "subcategory":"Lawyer & Legal Services",
            "type":"Services"
        },
        {
            "category":"Professional",
            "subcategory":"Business Services",
            "type":"Services"
        }
    ],
    "sg:phone":"+1 443 871 6804",
    "sg:postcode":"21108",
    "sg:province":"MD",
    "sg:tags":[
        "machine",
        "attorney",
        "management",
        "copy"
    ],
    "sg:website":"http://mycopyguy.com",
    "wof:name":"My Copy Guy",
    "wof:placetype":"venue"
},
  "geometry": {"coordinates":[-76.57889900000001,39.103195],"type":"Point"}
}