{
  "type": "Feature",
  "properties": {
    "iso:country":"US",
    "sg:address":"6635 Benita Ave",
    "sg:city":"Salisbury",
    "sg:classifiers":[
        {
            "category":"Wholesale",
            "subcategory":"Electrical",
            "type":"Manufacturing & Wholesale Goods"
        }
    ],
    "sg:phone":"+1 410 546 3911",
    "sg:postcode":"21804",
    "sg:province":"MD",
    "sg:tags":[
        "equipment",
        "electronic",
        "supply"
    ],
    "wof:name":"Micro-Coax",
    "wof:placetype":"venue"
},
  "geometry": {"coordinates":[-75.537158,38.374136],"type":"Point"}
}