{
  "type": "Feature",
  "properties": {
    "iso:country":"US",
    "sg:address":"534 S Belnord Ave",
    "sg:city":"Baltimore",
    "sg:classifiers":[
        {
            "category":"Retail",
            "subcategory":"Auto Repair",
            "type":"Services"
        }
    ],
    "sg:phone":"+1 410 276 3360",
    "sg:postcode":"21224",
    "sg:province":"MD",
    "sg:tags":[
        "recreational",
        "campers-repair",
        "vehicle"
    ],
    "wof:name":"Surelock's Mobile Service",
    "wof:placetype":"venue"
},
  "geometry": {"coordinates":[-76.57791,39.285837],"type":"Point"}
}