{
  "type": "Feature",
  "properties": {
    "iso:country":"US",
    "sg:address":"7017 Brookville Rd",
    "sg:city":"Chevy Chase",
    "sg:classifiers":[
        {
            "category":"Retail",
            "subcategory":"Laundry & Dry Cleaning",
            "type":"Services"
        }
    ],
    "sg:phone":"+1 301 654 1661",
    "sg:postcode":"20815",
    "sg:province":"MD",
    "wof:name":"Galaxie VI",
    "wof:placetype":"venue"
},
  "geometry": {"coordinates":[-77.071297,38.980301],"type":"Point"}
}