{
  "type": "Feature",
  "properties": {
    "addr:full":"37 Watertown Rd Berlin MD 21811",
    "addr:housenumber":"37",
    "addr:postcode":"21811",
    "addr:street":"Watertown Rd",
    "iso:country":"US",
    "sg:address":"37 Watertown Rd",
    "sg:city":"Berlin",
    "sg:classifiers":[
        {
            "category":"Professional",
            "subcategory":"Employment Agencies",
            "type":"Services"
        }
    ],
    "sg:phone":"+1 410 641 8293",
    "sg:postcode":"21811",
    "sg:province":"MD",
    "wof:name":"A Provide Nurse",
    "wof:placetype":"venue"
},
  "geometry": {"coordinates":[-75.144313,38.376395],"type":"Point"}
}