{
  "type": "Feature",
  "properties": {
    "iso:country":"US",
    "sg:address":"1901 Kent Village Dr",
    "sg:city":"Hyattsville",
    "sg:classifiers":[
        {
            "category":"Education",
            "subcategory":"School",
            "type":"Public Place"
        }
    ],
    "sg:phone":"+1 301 925 1322",
    "sg:postcode":"20785",
    "sg:province":"MD",
    "sg:tags":[
        "high",
        "middle",
        "elementary"
    ],
    "wof:name":"Prince George's County School District",
    "wof:placetype":"venue"
},
  "geometry": {"coordinates":[-76.88758,38.916127],"type":"Point"}
}