{
  "type": "Feature",
  "properties": {
    "addr:full":"3106 6th Ave Parkville MD 21234",
    "addr:housenumber":"3106",
    "addr:postcode":"21234",
    "addr:street":"6Th Ave",
    "iso:country":"US",
    "sg:address":"3106 6th Ave",
    "sg:city":"Parkville",
    "sg:classifiers":[
        {
            "category":"Building & Trades",
            "subcategory":"Pest Control",
            "type":"Services"
        }
    ],
    "sg:phone":"+1 410 661 7471",
    "sg:postcode":"21234",
    "sg:province":"MD",
    "wof:name":"Priority Termite & Pest Cntrl",
    "wof:placetype":"venue"
},
  "geometry": {"coordinates":[-76.522082,39.393239],"type":"Point"}
}