{
  "type": "Feature",
  "properties": {
    "addr:full":"6338 Marlboro Pike District Heights MD 20747",
    "addr:housenumber":"6338",
    "addr:postcode":"20747",
    "addr:street":"Marlboro Pike",
    "iso:country":"US",
    "sg:address":"6338 Marlboro Pike",
    "sg:city":"District Heights",
    "sg:classifiers":[
        {
            "category":"Restaurant",
            "type":"Food & Drink"
        }
    ],
    "sg:phone":"+1 301 420 2300",
    "sg:postcode":"20747",
    "sg:province":"MD",
    "sg:tags":[
        "pizza"
    ],
    "wof:name":"Pizza A Bolis",
    "wof:placetype":"venue"
},
  "geometry": {"coordinates":[-76.89822100000001,38.85417],"type":"Point"}
}