{
  "type": "Feature",
  "properties": {
    "addr:full":"2410 Spring Lake Dr Timonium MD 21093",
    "addr:housenumber":"2410",
    "addr:postcode":"21093",
    "addr:street":"Spring Lake Dr",
    "iso:country":"US",
    "sg:address":"2410 Spring Lake Dr",
    "sg:city":"Timonium",
    "sg:classifiers":[
        {
            "category":"Education",
            "subcategory":"School",
            "type":"Public Place"
        }
    ],
    "sg:phone":"+1 410 887 7648",
    "sg:postcode":"21093",
    "sg:province":"MD",
    "wof:name":"Pot Spring Elementary School",
    "wof:placetype":"venue"
},
  "geometry": {"coordinates":[-76.613828,39.454073],"type":"Point"}
}