{
  "type": "Feature",
  "properties": {
    "iso:country":"US",
    "sg:address":"10753 Castleton Turn",
    "sg:city":"Upper Marlboro",
    "sg:classifiers":[
        {
            "category":"Government",
            "subcategory":"Office",
            "type":"Public Place"
        }
    ],
    "sg:phone":"+1 301 499 1326",
    "sg:postcode":"20774",
    "sg:province":"MD",
    "sg:tags":[
        "program",
        "center",
        "community"
    ],
    "wof:name":"Teens Club 1",
    "wof:placetype":"venue"
},
  "geometry": {"coordinates":[-76.818396,38.89035],"type":"Point"}
}