{
  "type": "Feature",
  "properties": {
    "iso:country":"US",
    "sg:address":"410 Race St",
    "sg:city":"Cambridge",
    "sg:classifiers":[
        {
            "category":"Shopping",
            "type":"Retail Goods"
        }
    ],
    "sg:phone":"+1 410 228 7000",
    "sg:postcode":"21613",
    "sg:province":"MD",
    "sg:tags":[
        "merchandise"
    ],
    "wof:name":"Joie De Vivre Gallery",
    "wof:placetype":"venue"
},
  "geometry": {"coordinates":[-76.07722,38.569775],"type":"Point"}
}