{
  "type": "Feature",
  "properties": {
    "addr:full":"200 Washington Ave Baltimore MD 21204",
    "addr:housenumber":"200",
    "addr:postcode":"21204",
    "addr:street":"Washington Ave",
    "iso:country":"US",
    "sg:address":"200 Washington Ave",
    "sg:city":"Baltimore",
    "sg:classifiers":[
        {
            "category":"Professional",
            "subcategory":"Accounting & Tax Preparation",
            "type":"Services"
        }
    ],
    "sg:phone":"+1 410 296 0087",
    "sg:postcode":"21204",
    "sg:province":"MD",
    "sg:tags":[
        "consultant"
    ],
    "wof:name":"Gayle Thomas Assoc",
    "wof:placetype":"venue"
},
  "geometry": {"coordinates":[-76.605519,39.397633],"type":"Point"}
}