{
  "type": "Feature",
  "properties": {
    "iso:country":"US",
    "sg:address":"8 W West St",
    "sg:city":"Baltimore",
    "sg:classifiers":[
        {
            "category":"Health Services",
            "subcategory":"Clinic",
            "type":"Services"
        }
    ],
    "sg:phone":"+1 410 752 2262",
    "sg:postcode":"21230",
    "sg:province":"MD",
    "sg:tags":[
        "surgery",
        "doctor",
        "center",
        "surgical"
    ],
    "sg:website":"http://www.posnerandish.com",
    "wof:name":"Downtown Baltimore Surgery Ctr",
    "wof:placetype":"venue"
},
  "geometry": {"coordinates":[-76.6147,39.275799],"type":"Point"}
}