{
  "type": "Feature",
  "properties": {
    "addr:full":"18410 Comus Rd Dickerson MD 20842",
    "addr:postcode":"18410;20842",
    "addr:street":"Comus Rd",
    "iso:country":"US",
    "sg:address":"18410 Comus Rd",
    "sg:city":"Dickerson",
    "sg:classifiers":[
        {
            "category":"Manufacturing",
            "subcategory":"Buildings",
            "type":"Manufacturing & Wholesale Goods"
        },
        {
            "category":"Building & Trades",
            "subcategory":"Construction",
            "type":"Services"
        },
        {
            "category":"Utilities",
            "type":"Services"
        }
    ],
    "sg:phone":"+1 301 349 0550",
    "sg:postcode":"20842",
    "sg:province":"MD",
    "sg:tags":[
        "excavation",
        "home",
        "builder",
        "contractor"
    ],
    "wof:name":"Comus Construction",
    "wof:placetype":"venue"
},
  "geometry": {"coordinates":[-77.384102,39.252165],"type":"Point"}
}