{
  "type": "Feature",
  "properties": {
    "iso:country":"US",
    "sg:address":"798 W Cross St",
    "sg:city":"Baltimore",
    "sg:classifiers":[
        {
            "category":"Restaurant",
            "type":"Food & Drink"
        }
    ],
    "sg:phone":"+1 410 685 1145",
    "sg:postcode":"21230",
    "sg:province":"MD",
    "sg:tags":[
        "deli"
    ],
    "wof:name":"Marty's Delicatessen & Restaurant",
    "wof:placetype":"venue"
},
  "geometry": {"coordinates":[-76.628502,39.280102],"type":"Point"}
}