{
  "type": "Feature",
  "properties": {
    "iso:country":"US",
    "sg:address":"2209 Aiken St",
    "sg:city":"Baltimore",
    "sg:classifiers":[
        {
            "category":"Professional",
            "subcategory":"Art Services",
            "type":"Services"
        }
    ],
    "sg:phone":"+1 410 366 3669",
    "sg:postcode":"21218",
    "sg:province":"MD",
    "sg:tags":[
        "picture",
        "frame"
    ],
    "wof:name":"Fleckenstein Gallery & Archival Framing",
    "wof:placetype":"venue"
},
  "geometry": {"coordinates":[-76.599339,39.315128],"type":"Point"}
}