{
  "type": "Feature",
  "properties": {
    "addr:full":"1123 Revolution St Havre De Grace MD 21078",
    "addr:housenumber":"1123",
    "addr:postcode":"21078",
    "addr:street":"Revolution St",
    "iso:country":"US",
    "sg:address":"1123 Revolution St",
    "sg:city":"Havre De Grace",
    "sg:classifiers":[
        {
            "category":"Food & Beverages",
            "subcategory":"Liquor & Beverages",
            "type":"Retail Goods"
        }
    ],
    "sg:phone":"+1 410 939 0990",
    "sg:postcode":"21078",
    "sg:province":"MD",
    "sg:tags":[
        "beer",
        "ale"
    ],
    "wof:name":"Post Road Liquors",
    "wof:placetype":"venue"
},
  "geometry": {"coordinates":[-76.10481299999999,39.540547],"type":"Point"}
}