{
  "type": "Feature",
  "properties": {
    "addr:full":"5236 Thunder Hill Rd Columbia MD 21045",
    "addr:housenumber":"5236",
    "addr:postcode":"21045",
    "addr:street":"Thunder Hill Rd",
    "iso:country":"US",
    "sg:address":"5236 Thunder Hill Rd",
    "sg:city":"Columbia",
    "sg:classifiers":[
        {
            "category":"Manufacturing",
            "subcategory":"Motor Vehicles & Parts",
            "type":"Manufacturing & Wholesale Goods"
        }
    ],
    "sg:phone":"+1 410 730 1036",
    "sg:postcode":"21045",
    "sg:province":"MD",
    "sg:tags":[
        "equipment",
        "railroad",
        "mfg"
    ],
    "wof:name":"Howard Zane Assoc",
    "wof:placetype":"venue"
},
  "geometry": {"coordinates":[-76.829976,39.227646],"type":"Point"}
}