{
  "type": "Feature",
  "properties": {
    "iso:country":"US",
    "sg:address":"3307 Kitchen Ct",
    "sg:city":"Waldorf",
    "sg:classifiers":[
        {
            "category":"Shopping",
            "subcategory":"Hobbies, Toys, & Games",
            "type":"Retail Goods"
        }
    ],
    "sg:phone":"+1 301 645 2338",
    "sg:postcode":"20602",
    "sg:province":"MD",
    "sg:tags":[
        "craft"
    ],
    "wof:name":"Heart's Desire",
    "wof:placetype":"venue"
},
  "geometry": {"coordinates":[-76.90065300000001,38.596765],"type":"Point"}
}