{
  "type": "Feature",
  "properties": {
    "iso:country":"US",
    "sg:address":"12 Aqueduct Ct",
    "sg:city":"Potomac",
    "sg:classifiers":[
        {
            "category":"Professional",
            "subcategory":"Business Services",
            "type":"Services"
        }
    ],
    "sg:phone":"+1 301 294 6518",
    "sg:postcode":"20854",
    "sg:province":"MD",
    "wof:name":"Lowes Business Services LLC",
    "wof:placetype":"venue"
},
  "geometry": {"coordinates":[-77.171514,39.059035],"type":"Point"}
}