{
  "type": "Feature",
  "properties": {
    "iso:country":"US",
    "sg:address":"328 S Lehigh St",
    "sg:city":"Baltimore",
    "sg:classifiers":[
        {
            "category":"Building & Trades",
            "subcategory":"Construction",
            "type":"Services"
        }
    ],
    "sg:phone":"+1 410 558 1370",
    "sg:postcode":"21224",
    "sg:province":"MD",
    "sg:tags":[
        "general",
        "contractor"
    ],
    "wof:name":"West West Street Properties",
    "wof:placetype":"venue"
},
  "geometry": {"coordinates":[-76.558233,39.288286],"type":"Point"}
}