{
  "type": "Feature",
  "properties": {
    "addr:full":"810 Ashton Rd Ashton MD 20861",
    "addr:housenumber":"810",
    "addr:postcode":"20861",
    "addr:street":"Ashton Rd",
    "iso:country":"US",
    "sg:address":"810 Ashton Rd",
    "sg:city":"Ashton",
    "sg:classifiers":[
        {
            "category":"Real Estate",
            "subcategory":"Real Estate Agent",
            "type":"Services"
        }
    ],
    "sg:phone":"+1 301 770 5574",
    "sg:postcode":"20861",
    "sg:province":"MD",
    "sg:tags":[
        "consultant"
    ],
    "wof:name":"Harcon Investment Group",
    "wof:placetype":"venue"
},
  "geometry": {"coordinates":[-76.99485199999999,39.157592],"type":"Point"}
}