{
  "type": "Feature",
  "properties": {
    "addr:full":"15221 Dino Dr Burtonsville MD 20866",
    "addr:postcode":"15221;20866",
    "addr:street":"Dino Dr",
    "iso:country":"US",
    "sg:address":"15221 Dino Dr",
    "sg:city":"Burtonsville",
    "sg:classifiers":[
        {
            "category":"Retail",
            "subcategory":"Storage",
            "type":"Services"
        }
    ],
    "sg:phone":"+1 301 476 7872",
    "sg:postcode":"20866",
    "sg:province":"MD",
    "sg:tags":[
        "self"
    ],
    "sg:website":"www.extraspace.com",
    "wof:name":"Extra Space Storage",
    "wof:placetype":"venue"
},
  "geometry": {"coordinates":[-76.924954,39.109718],"type":"Point"}
}