{
  "type": "Feature",
  "properties": {
    "addr:full":"3537 Spencerville Rd Burtonsville MD 20866",
    "addr:housenumber":"3537",
    "addr:postcode":"20866",
    "addr:street":"Spencerville Rd",
    "iso:country":"US",
    "sg:address":"3537 Spencerville Rd",
    "sg:city":"Burtonsville",
    "sg:classifiers":[
        {
            "category":"Building & Trades",
            "subcategory":"Construction",
            "type":"Services"
        }
    ],
    "sg:phone":"+1 301 421 4200",
    "sg:postcode":"20866",
    "sg:province":"MD",
    "sg:tags":[
        "masonry",
        "contractor"
    ],
    "wof:name":"H & H Masonry",
    "wof:placetype":"venue"
},
  "geometry": {"coordinates":[-76.937202,39.108175],"type":"Point"}
}