{
  "type": "Feature",
  "properties": {
    "addr:full":"7421 Chrome Mine Rd Gaithersburg MD 20882",
    "addr:housenumber":"7421",
    "addr:postcode":"20882",
    "addr:street":"Chrome Mine Rd",
    "iso:country":"US",
    "sg:address":"7421 Chrome Mine Rd",
    "sg:city":"Gaithersburg",
    "sg:classifiers":[
        {
            "category":"Professional",
            "subcategory":"Business Services",
            "type":"Services"
        }
    ],
    "sg:phone":"+1 301 253 3040",
    "sg:postcode":"20882",
    "sg:province":"MD",
    "sg:tags":[
        "consulting"
    ],
    "wof:name":"Print Group Inc",
    "wof:placetype":"venue"
},
  "geometry": {"coordinates":[-77.15216700000001,39.260912],"type":"Point"}
}