{
  "type": "Feature",
  "properties": {
    "iso:country":"US",
    "sg:address":"11910 Triadelphia Rd",
    "sg:city":"Ellicott City",
    "sg:classifiers":[
        {
            "category":"Personal",
            "type":"Services"
        }
    ],
    "sg:phone":"+1 410 531 1352",
    "sg:postcode":"21042",
    "sg:province":"MD",
    "wof:name":"Homeland Contractors",
    "wof:placetype":"venue"
},
  "geometry": {"coordinates":[-76.926591,39.289384],"type":"Point"}
}