{
  "type": "Feature",
  "properties": {
    "addr:full":"4801 Montgomery Ln Bethesda MD 20814",
    "addr:housenumber":"4801",
    "addr:postcode":"20814",
    "addr:street":"Montgomery Ln",
    "iso:country":"US",
    "sg:address":"4801 Montgomery Ln",
    "sg:city":"Bethesda",
    "sg:classifiers":[
        {
            "category":"Restaurant",
            "type":"Food & Drink"
        }
    ],
    "sg:phone":"+1 301 654 0043",
    "sg:postcode":"20814",
    "sg:province":"MD",
    "sg:tags":[
        "shop",
        "coffee"
    ],
    "wof:name":"Caffe Appassionato",
    "wof:placetype":"venue"
},
  "geometry": {"coordinates":[-77.09616699999999,38.983436],"type":"Point"}
}