{
  "type": "Feature",
  "properties": {
    "addr:full":"56 Souder Rd Brunswick MD 21716",
    "addr:housenumber":"56",
    "addr:postcode":"21716",
    "addr:street":"Souder Rd",
    "iso:country":"US",
    "sg:address":"56 Souder Rd",
    "sg:city":"Brunswick",
    "sg:classifiers":[
        {
            "category":"Personal",
            "subcategory":"Barber",
            "type":"Services"
        }
    ],
    "sg:phone":"+1 301 834 5420",
    "sg:postcode":"21716",
    "sg:province":"MD",
    "wof:name":"Brunswick Barbershp",
    "wof:placetype":"venue"
},
  "geometry": {"coordinates":[-77.619698,39.324402],"type":"Point"}
}