{
  "type": "Feature",
  "properties": {
    "addr:full":"1400 Exeter Hall Ave Baltimore MD 21218",
    "addr:housenumber":"1400",
    "addr:postcode":"21218",
    "addr:street":"Exeter Hall Ave",
    "iso:country":"US",
    "sg:address":"1400 Exeter Hall Ave",
    "sg:city":"Baltimore",
    "sg:classifiers":[
        {
            "category":"Education",
            "subcategory":"School",
            "type":"Public Place"
        }
    ],
    "sg:phone":"+1 410 396 6443",
    "sg:postcode":"21218",
    "sg:province":"MD",
    "sg:tags":[
        "high",
        "middle",
        "elementary"
    ],
    "sg:website":"www.bcps.k12.md.us",
    "wof:name":"Baltimore City School District",
    "wof:placetype":"venue"
},
  "geometry": {"coordinates":[-76.60079,39.319991],"type":"Point"}
}