{
  "type": "Feature",
  "properties": {
    "addr:full":"3831 Plyers Mill Rd Kensington MD 20895",
    "addr:housenumber":"3831",
    "addr:postcode":"20895",
    "addr:street":"Plyers Mill Rd",
    "iso:country":"US",
    "sg:address":"3831 Plyers Mill Rd",
    "sg:city":"Kensington",
    "sg:classifiers":[
        {
            "category":"Retail",
            "subcategory":"Auto Repair",
            "type":"Services"
        }
    ],
    "sg:phone":"+1 301 929 0355",
    "sg:postcode":"20895",
    "sg:province":"MD",
    "wof:name":"Toyota Repairing & Servicing",
    "wof:placetype":"venue"
},
  "geometry": {"coordinates":[-77.076599,39.029598],"type":"Point"}
}