{
  "type": "Feature",
  "properties": {
    "addr:full":"3303 E Fayette St Baltimore MD 21224",
    "addr:housenumber":"3303",
    "addr:postcode":"21224",
    "addr:street":"E Fayette St",
    "iso:country":"US",
    "sg:address":"3303 E Fayette St",
    "sg:city":"Baltimore",
    "sg:classifiers":[
        {
            "category":"Professional",
            "subcategory":"Computer Services",
            "type":"Services"
        }
    ],
    "sg:phone":"+1 410 563 3046",
    "sg:postcode":"21224",
    "sg:province":"MD",
    "sg:tags":[
        "stereo",
        "installation"
    ],
    "wof:name":"Car Plus Inc",
    "wof:placetype":"venue"
},
  "geometry": {"coordinates":[-76.57099599999999,39.294704],"type":"Point"}
}