{
  "type": "Feature",
  "properties": {
    "addr:full":"1020 Edgewood Rd Edgewood MD 21040",
    "addr:housenumber":"1020",
    "addr:postcode":"21040",
    "addr:street":"Edgewood Rd",
    "iso:country":"US",
    "sg:address":"1020 Edgewood Rd",
    "sg:city":"Edgewood",
    "sg:classifiers":[
        {
            "category":"Health Services",
            "subcategory":"Doctor",
            "type":"Services"
        }
    ],
    "sg:phone":"+1 410 679 5755",
    "sg:postcode":"21040",
    "sg:province":"MD",
    "wof:name":"Kulkarni Sanjeevani Dr",
    "wof:placetype":"venue"
},
  "geometry": {"coordinates":[-76.30680099999999,39.4361],"type":"Point"}
}