{
  "type": "Feature",
  "properties": {
    "addr:full":"14210 Maugansville Rd Hagerstown MD 21740",
    "addr:housenumber":"14210",
    "addr:postcode":"21740",
    "addr:street":"Maugansville Rd",
    "iso:country":"US",
    "sg:address":"14210 Maugansville Rd",
    "sg:city":"Hagerstown",
    "sg:classifiers":[
        {
            "category":"Building & Trades",
            "subcategory":"Construction",
            "type":"Services"
        }
    ],
    "sg:phone":"+1 301 733 0377",
    "sg:postcode":"21740",
    "sg:province":"MD",
    "sg:tags":[
        "home",
        "builder"
    ],
    "wof:name":"R B Keener & Sons Inc",
    "wof:placetype":"venue"
},
  "geometry": {"coordinates":[-77.744595,39.703773],"type":"Point"}
}