{
  "type": "Feature",
  "properties": {
    "iso:country":"US",
    "sg:address":"10800 Hanna St Ste D",
    "sg:city":"Beltsville",
    "sg:classifiers":[
        {
            "category":"Autos & Motor Vehicles",
            "subcategory":"Automobile Sales",
            "type":"Retail Goods"
        }
    ],
    "sg:phone":"+1 301 937 5900",
    "sg:postcode":"20705",
    "sg:province":"MD",
    "sg:tags":[
        "dealers-used",
        "used",
        "cars-wholesale",
        "car"
    ],
    "wof:name":"Cars Service Center D",
    "wof:placetype":"venue"
},
  "geometry": {"coordinates":[-76.908783,39.028751],"type":"Point"}
}