{
  "type": "Feature",
  "properties": {
    "addr:full":"1952 Catanna Ave Baltimore MD 21227",
    "addr:housenumber":"1952",
    "addr:postcode":"21227",
    "addr:street":"Catanna Ave",
    "iso:country":"US",
    "sg:address":"1952 Catanna Ave",
    "sg:city":"Baltimore",
    "sg:classifiers":[
        {
            "category":"Wholesale",
            "subcategory":"Durable Goods & Equipment",
            "type":"Manufacturing & Wholesale Goods"
        }
    ],
    "sg:phone":"+1 410 598 8670",
    "sg:postcode":"21227",
    "sg:province":"MD",
    "wof:name":"Big Dog Core Supply Inc",
    "wof:placetype":"venue"
},
  "geometry": {"coordinates":[-76.681207,39.235483],"type":"Point"}
}