{
  "type": "Feature",
  "properties": {
    "addr:full":"6511 Harford Rd Baltimore MD 21214",
    "addr:housenumber":"6511",
    "addr:postcode":"21214",
    "addr:street":"Harford Rd",
    "iso:country":"US",
    "sg:address":"6511 Harford Rd",
    "sg:city":"Baltimore",
    "sg:classifiers":[
        {
            "category":"Professional",
            "subcategory":"Engineering",
            "type":"Services"
        }
    ],
    "sg:phone":"+1 410 254 7500",
    "sg:postcode":"21214",
    "sg:province":"MD",
    "sg:tags":[
        "engineer",
        "structural"
    ],
    "sg:website":"http://www.mpm-engr.com",
    "wof:name":"Mincin Patel Milano",
    "wof:placetype":"venue"
},
  "geometry": {"coordinates":[-76.55291699999999,39.362141],"type":"Point"}
}