{
  "type": "Feature",
  "properties": {
    "addr:full":"200 S Arlington Ave Baltimore MD 21223",
    "addr:housenumber":"200",
    "addr:postcode":"21223",
    "addr:street":"S Arlington Ave",
    "iso:country":"US",
    "sg:address":"200 S Arlington Ave",
    "sg:city":"Baltimore",
    "sg:classifiers":[
        {
            "category":"Banks & Credit Unions",
            "subcategory":"Investment Brokerage",
            "type":"Services"
        },
        {
            "category":"Banks & Credit Unions",
            "subcategory":"Financial Services",
            "type":"Services"
        }
    ],
    "sg:phone":"+1 410 788 1572",
    "sg:postcode":"21223",
    "sg:province":"MD",
    "sg:tags":[
        "advisory",
        "closed"
    ],
    "wof:name":"Mc Intyre Financial Group",
    "wof:placetype":"venue"
},
  "geometry": {"coordinates":[-76.63522500000001,39.28601],"type":"Point"}
}