{
  "type": "Feature",
  "properties": {
    "iso:country":"US",
    "sg:address":"2805 Pulaski Hwy",
    "sg:city":"Edgewood",
    "sg:classifiers":[
        {
            "category":"Professional",
            "subcategory":"Lawyer & Legal Services",
            "type":"Services"
        }
    ],
    "sg:phone":"+1 410 676 4200",
    "sg:postcode":"21040",
    "sg:province":"MD",
    "sg:tags":[
        "attorney",
        "law",
        "estate",
        "family",
        "divorce",
        "planning",
        "criminal"
    ],
    "wof:name":"Hickey Jr., Michael C. - Hickey & Windsor, P.A.",
    "wof:placetype":"venue"
},
  "geometry": {"coordinates":[-76.290148,39.443056],"type":"Point"}
}