{
  "type": "Feature",
  "properties": {
    "addr:full":"905 Chester Rd Baltimore MD 21220",
    "addr:housenumber":"905",
    "addr:postcode":"21220",
    "addr:street":"Chester Rd",
    "iso:country":"US",
    "sg:address":"905 Chester Rd",
    "sg:city":"Baltimore",
    "sg:classifiers":[
        {
            "category":"Wholesale",
            "subcategory":"Machinery & Supplies",
            "type":"Manufacturing & Wholesale Goods"
        },
        {
            "category":"Manufacturing",
            "subcategory":"Tools & Machinery",
            "type":"Manufacturing & Wholesale Goods"
        }
    ],
    "sg:phone":"+1 410 335 6490",
    "sg:postcode":"21220",
    "sg:province":"MD",
    "sg:tags":[
        "engine",
        "mfg",
        "industrial",
        "internal",
        "combustion"
    ],
    "wof:name":"Hainis Diesel Engines",
    "wof:placetype":"venue"
},
  "geometry": {"coordinates":[-76.393545,39.315945],"type":"Point"}
}