{
  "type": "Feature",
  "properties": {
    "iso:country":"US",
    "sg:address":"15101 Baltimore Ave Suite 111",
    "sg:city":"Laurel",
    "sg:classifiers":[
        {
            "category":"Restaurant",
            "type":"Food & Drink"
        },
        {
            "category":"Food & Beverages",
            "subcategory":"Ethnic Foods",
            "type":"Retail Goods"
        }
    ],
    "sg:phone":"+1 301 362 4201",
    "sg:postcode":"20707",
    "sg:province":"MD",
    "sg:tags":[
        "caribbean",
        "soul"
    ],
    "sg:website":"www.auntsusanskitchen.com/index.php",
    "wof:name":"Aunt Susan's Kitchen",
    "wof:placetype":"venue"
},
  "geometry": {"coordinates":[-76.84920099999999,39.097226],"type":"Point"}
}