{
  "type": "Feature",
  "properties": {
    "iso:country":"US",
    "sg:address":"48042 Mary Lynn Dr",
    "sg:city":"Lexington Park",
    "sg:classifiers":[
        {
            "category":"Organizations",
            "subcategory":"Religious Organization",
            "type":"Services"
        }
    ],
    "sg:phone":"+1 301 866 0523",
    "sg:postcode":"20653",
    "sg:province":"MD",
    "wof:name":"Christ Jesus Worship Center In",
    "wof:placetype":"venue"
},
  "geometry": {"coordinates":[-76.41345200000001,38.25823],"type":"Point"}
}