{
  "type": "Feature",
  "properties": {
    "addr:full":"807 E South St Frederick MD 21701",
    "addr:housenumber":"807 e",
    "addr:postcode":"21701",
    "addr:street":"South St",
    "iso:country":"US",
    "sg:address":"807 E South St",
    "sg:city":"Frederick",
    "sg:classifiers":[
        {
            "category":"Home & Garden",
            "subcategory":"Carpets & Floor Coverings",
            "type":"Retail Goods"
        }
    ],
    "sg:phone":"+1 301 293 6390",
    "sg:postcode":"21701",
    "sg:province":"MD",
    "sg:tags":[
        "dealer",
        "rug"
    ],
    "wof:name":"Modern Floors LTD",
    "wof:placetype":"venue"
},
  "geometry": {"coordinates":[-77.39586199999999,39.406676],"type":"Point"}
}