{
  "type": "Feature",
  "properties": {
    "addr:full":"1937 Greenspring Dr Lutherville MD 21093",
    "addr:housenumber":"1937",
    "addr:postcode":"21093",
    "addr:street":"Greenspring Dr",
    "iso:country":"US",
    "sg:address":"1937 Greenspring Dr",
    "sg:city":"Lutherville",
    "sg:classifiers":[
        {
            "category":"Restaurant",
            "type":"Food & Drink"
        }
    ],
    "sg:phone":"+1 410 561 1801",
    "sg:postcode":"21093",
    "sg:province":"MD",
    "wof:name":"Qdoba Mexican Grill",
    "wof:placetype":"venue"
},
  "geometry": {"coordinates":[-76.62935,39.431257],"type":"Point"}
}