{
  "type": "Feature",
  "properties": {
    "addr:full":"900 W Lexington St Baltimore MD 21223",
    "addr:housenumber":"900",
    "addr:postcode":"21223",
    "addr:street":"W Lexington St",
    "iso:country":"US",
    "sg:address":"900 W Lexington St",
    "sg:city":"Baltimore",
    "sg:classifiers":[
        {
            "category":"Professional",
            "type":"Services"
        }
    ],
    "sg:phone":"+1 443 872 7507",
    "sg:postcode":"21223",
    "sg:province":"MD",
    "sg:tags":[
        "establishment"
    ],
    "wof:name":"Pamper Me Crazy",
    "wof:placetype":"venue"
},
  "geometry": {"coordinates":[-76.633185,39.291025],"type":"Point"}
}