{
  "type": "Feature",
  "properties": {
    "addr:full":"7410 Assateague Dr Jessup MD 20794",
    "addr:housenumber":"7410",
    "addr:postcode":"20794",
    "addr:street":"Assateague Dr",
    "iso:country":"US",
    "sg:address":"7410 Assateague Dr",
    "sg:city":"Jessup",
    "sg:classifiers":[
        {
            "category":"Fast Food",
            "type":"Food & Drink"
        },
        {
            "category":"Restaurant",
            "type":"Food & Drink"
        },
        {
            "category":"Food & Beverages",
            "subcategory":"Groceries & Convenience Stores",
            "type":"Retail Goods"
        }
    ],
    "sg:phone":"+1 301 621 1145",
    "sg:postcode":"20794",
    "sg:province":"MD",
    "sg:tags":[
        "shop",
        "american",
        "sandwich"
    ],
    "sg:website":"http://www.arbys.com",
    "wof:name":"Arby's",
    "wof:placetype":"venue"
},
  "geometry": {"coordinates":[-76.786751,39.168941],"type":"Point"}
}