{
  "type": "Feature",
  "properties": {
    "addr:full":"5241 Taneytown Pike Taneytown MD 21787",
    "addr:postcode":"5241;21787",
    "addr:street":"Taneytown Pike",
    "iso:country":"US",
    "sg:address":"5241 Taneytown Pike",
    "sg:city":"Taneytown",
    "sg:classifiers":[
        {
            "category":"Building & Trades",
            "subcategory":"Construction",
            "type":"Services"
        }
    ],
    "sg:phone":"+1 410 751 1512",
    "sg:postcode":"21787",
    "sg:province":"MD",
    "sg:tags":[
        "porch",
        "enclosure",
        "patio",
        "deck"
    ],
    "wof:name":"Central Maryland Sunrooms",
    "wof:placetype":"venue"
},
  "geometry": {"coordinates":[-77.19266500000001,39.667416],"type":"Point"}
}