{
  "type": "Feature",
  "properties": {
    "addr:full":"609 University Blvd E Silver Spring MD 20901",
    "addr:housenumber":"609",
    "addr:postcode":"20901",
    "addr:street":"University Blvd E",
    "iso:country":"US",
    "sg:address":"609 University Blvd E",
    "sg:city":"Silver Spring",
    "sg:classifiers":[
        {
            "category":"Building & Trades",
            "subcategory":"Construction",
            "type":"Services"
        }
    ],
    "sg:phone":"+1 301 431 2473",
    "sg:postcode":"20901",
    "sg:province":"MD",
    "sg:tags":[
        "house"
    ],
    "wof:name":"Escala Contractors Inc",
    "wof:placetype":"venue"
},
  "geometry": {"coordinates":[-76.99576399999999,39.002521],"type":"Point"}
}