{
  "type": "Feature",
  "properties": {
    "iso:country":"US",
    "sg:address":"8120 Hamilton Spring Rd",
    "sg:city":"Bethesda",
    "sg:classifiers":[
        {
            "category":"Real Estate",
            "subcategory":"Architect",
            "type":"Services"
        }
    ],
    "sg:phone":"+1 301 365 7546",
    "sg:postcode":"20817",
    "sg:province":"MD",
    "wof:name":"Architecture By Augusto Tono",
    "wof:placetype":"venue"
},
  "geometry": {"coordinates":[-77.169345,38.989936],"type":"Point"}
}