{
  "type": "Feature",
  "properties": {
    "iso:country":"US",
    "sg:address":"902 James Ct",
    "sg:city":"Salisbury",
    "sg:classifiers":[
        {
            "category":"Professional",
            "subcategory":"Accounting & Tax Preparation",
            "type":"Services"
        }
    ],
    "sg:phone":"+1 410 543 8329",
    "sg:postcode":"21804",
    "sg:province":"MD",
    "wof:name":"Frances L White",
    "wof:placetype":"venue"
},
  "geometry": {"coordinates":[-75.563887,38.357677],"type":"Point"}
}