{
  "type": "Feature",
  "properties": {
    "iso:country":"US",
    "sg:address":"200 N Mechanic St",
    "sg:city":"Cumberland",
    "sg:classifiers":[
        {
            "category":"Banks & Credit Unions",
            "subcategory":"Bank",
            "type":"Services"
        }
    ],
    "sg:phone":"+1 301 722 5770",
    "sg:postcode":"21502",
    "sg:province":"MD",
    "wof:name":"Hoblitzell National Bank",
    "wof:placetype":"venue"
},
  "geometry": {"coordinates":[-78.765225,39.65432],"type":"Point"}
}