{
  "type": "Feature",
  "properties": {
    "iso:country":"US",
    "sg:address":"33 Hamilton Ave",
    "sg:city":"Frederick",
    "sg:classifiers":[
        {
            "category":"Utilities",
            "subcategory":"Refuse",
            "type":"Services"
        }
    ],
    "sg:phone":"+1 301 682 7503",
    "sg:postcode":"21701",
    "sg:province":"MD",
    "sg:tags":[
        "garbage",
        "collection"
    ],
    "wof:name":"Regional Waste Svc",
    "wof:placetype":"venue"
},
  "geometry": {"coordinates":[-77.397029,39.410161],"type":"Point"}
}