{
  "type": "Feature",
  "properties": {
    "iso:country":"US",
    "sg:address":"4030 Fallstaff Rd",
    "sg:city":"Baltimore",
    "sg:classifiers":[
        {
            "category":"Personal",
            "subcategory":"Beauty Salon",
            "type":"Services"
        }
    ],
    "sg:phone":"+1 410 358 7005",
    "sg:postcode":"21215",
    "sg:province":"MD",
    "wof:name":"First Impression Hair Image",
    "wof:placetype":"venue"
},
  "geometry": {"coordinates":[-76.708389,39.362332],"type":"Point"}
}