{
  "type": "Feature",
  "properties": {
    "addr:full":"307 Gay St Salisbury MD 21801",
    "addr:housenumber":"307",
    "addr:postcode":"21801",
    "addr:street":"Gay St",
    "iso:country":"US",
    "sg:address":"307 Gay St",
    "sg:city":"Salisbury",
    "sg:classifiers":[
        {
            "category":"Government",
            "subcategory":"Fire Station",
            "type":"Public Place"
        }
    ],
    "sg:phone":"+1 410 228 1670",
    "sg:postcode":"21801",
    "sg:province":"MD",
    "sg:tags":[
        "department"
    ],
    "wof:name":"Rescue Fire Co",
    "wof:placetype":"venue"
},
  "geometry": {"coordinates":[-75.597543,38.36897],"type":"Point"}
}