{
  "type": "Feature",
  "properties": {
    "addr:full":"7484 Candlewood Rd Hanover MD 21076",
    "addr:housenumber":"7484",
    "addr:postcode":"21076",
    "addr:street":"Candlewood Rd",
    "iso:country":"US",
    "sg:address":"7484 Candlewood Rd",
    "sg:city":"Hanover",
    "sg:classifiers":[
        {
            "category":"Banks & Credit Unions",
            "subcategory":"Bank",
            "type":"Services"
        }
    ],
    "sg:phone":"+1 410 859 4100",
    "sg:postcode":"21076",
    "sg:province":"MD",
    "sg:tags":[
        "loan",
        "real estate"
    ],
    "sg:website":"www.baltimoreamericanmortgage.com",
    "wof:name":"Baltimore American Mortgage",
    "wof:placetype":"venue"
},
  "geometry": {"coordinates":[-76.70310499999999,39.164339],"type":"Point"}
}