{
  "type": "Feature",
  "properties": {
    "iso:country":"US",
    "sg:address":"52 Old Bonifant Rd",
    "sg:city":"Silver Spring",
    "sg:classifiers":[
        {
            "category":"Wholesale",
            "subcategory":"Durable Goods & Equipment",
            "type":"Manufacturing & Wholesale Goods"
        }
    ],
    "sg:phone":"+1 301 384 8952",
    "sg:postcode":"20905",
    "sg:province":"MD",
    "wof:name":"Treasures of Yesteryear",
    "wof:placetype":"venue"
},
  "geometry": {"coordinates":[-77.003699,39.093238],"type":"Point"}
}