{
  "type": "Feature",
  "properties": {
    "iso:country":"US",
    "sg:address":"5108 Dianna Dr",
    "sg:city":"Suitland",
    "sg:classifiers":[
        {
            "category":"Education",
            "subcategory":"School",
            "type":"Public Place"
        }
    ],
    "sg:phone":"+1 301 817 0533",
    "sg:postcode":"20746",
    "sg:province":"MD",
    "sg:tags":[
        "high",
        "middle",
        "elementary"
    ],
    "wof:name":"Prince George's County School District",
    "wof:placetype":"venue"
},
  "geometry": {"coordinates":[-76.91950900000001,38.839784],"type":"Point"}
}