{
  "type": "Feature",
  "properties": {
    "iso:country":"US",
    "sg:address":"323 Addisson Dr",
    "sg:city":"Glen Burnie",
    "sg:classifiers":[
        {
            "category":"Building & Trades",
            "subcategory":"Construction",
            "type":"Services"
        }
    ],
    "sg:phone":"+1 410 768 3916",
    "sg:postcode":"21060",
    "sg:province":"MD",
    "sg:tags":[
        "paving",
        "contractor"
    ],
    "wof:name":"T & M Paving",
    "wof:placetype":"venue"
},
  "geometry": {"coordinates":[-76.58115100000001,39.139272],"type":"Point"}
}