{
  "type": "Feature",
  "properties": {
    "addr:full":"901 Pope Ave Hagerstown MD 21740",
    "addr:housenumber":"901",
    "addr:postcode":"21740",
    "addr:street":"Pope Ave",
    "iso:country":"US",
    "sg:address":"901 Pope Ave",
    "sg:city":"Hagerstown",
    "sg:classifiers":[
        {
            "category":"Organizations",
            "subcategory":"Professional Association",
            "type":"Services"
        }
    ],
    "sg:phone":"+1 301 791 5686",
    "sg:postcode":"21740",
    "sg:province":"MD",
    "wof:name":"Girl Scouts",
    "wof:placetype":"venue"
},
  "geometry": {"coordinates":[-77.72627,39.623499],"type":"Point"}
}