{
  "type": "Feature",
  "properties": {
    "addr:full":"3908 Adams Dr Silver Spring MD 20902",
    "addr:housenumber":"3908",
    "addr:postcode":"20902",
    "addr:street":"Adams Dr",
    "iso:country":"US",
    "sg:address":"3908 Adams Dr",
    "sg:city":"Silver Spring",
    "sg:classifiers":[
        {
            "category":"Recreation",
            "type":"Entertainment"
        }
    ],
    "sg:phone":"+1 301 949 1938",
    "sg:postcode":"20902",
    "sg:province":"MD",
    "wof:name":"Christopher Glenn Lachat",
    "wof:placetype":"venue"
},
  "geometry": {"coordinates":[-77.078271,39.04568],"type":"Point"}
}