{
  "type": "Feature",
  "properties": {
    "addr:full":"120 E Baltimore St Ste 1210 Baltimore MD 21202",
    "addr:housenumber":"120",
    "addr:postcode":"21202",
    "addr:street":"E Baltimore St Ste 1210",
    "iso:country":"US",
    "sg:address":"120 E Baltimore St Ste 1210",
    "sg:city":"Baltimore",
    "sg:classifiers":[
        {
            "category":"Professional",
            "subcategory":"Lawyer & Legal Services",
            "type":"Services"
        }
    ],
    "sg:phone":"+1 410 547 8356",
    "sg:postcode":"21202",
    "sg:province":"MD",
    "wof:name":"Lauer Fred M Lawyer",
    "wof:placetype":"venue"
},
  "geometry": {"coordinates":[-76.6129,39.2896],"type":"Point"}
}