{
  "type": "Feature",
  "properties": {
    "iso:country":"US",
    "sg:address":"8999 Yellow Brick Rd",
    "sg:city":"Rosedale",
    "sg:classifiers":[
        {
            "category":"Manufacturing",
            "subcategory":"Building Materials",
            "type":"Manufacturing & Wholesale Goods"
        }
    ],
    "sg:phone":"+1 410 866 9000",
    "sg:postcode":"21237",
    "sg:province":"MD",
    "sg:tags":[
        "materials-wholesale",
        "manufacturer"
    ],
    "wof:name":"Beacon Sales Acquisitions, Inc.",
    "wof:placetype":"venue"
},
  "geometry": {"coordinates":[-76.476811,39.341615],"type":"Point"}
}