{
  "type": "Feature",
  "properties": {
    "addr:full":"408 High Bridge Rd Millington MD 21651",
    "addr:housenumber":"408",
    "addr:postcode":"21651",
    "addr:street":"High Bridge Rd",
    "iso:country":"US",
    "sg:address":"408 High Bridge Rd",
    "sg:city":"Millington",
    "sg:classifiers":[
        {
            "category":"Manufacturing",
            "subcategory":"Food",
            "type":"Manufacturing & Wholesale Goods"
        },
        {
            "category":"Farming",
            "subcategory":"Farm",
            "type":"Manufacturing & Wholesale Goods"
        }
    ],
    "sg:phone":"+1 410 928 3306",
    "sg:postcode":"21651",
    "sg:province":"MD",
    "sg:tags":[
        "corn",
        "product"
    ],
    "wof:name":"Edward Appenzeller",
    "wof:placetype":"venue"
},
  "geometry": {"coordinates":[-75.828542,39.239863],"type":"Point"}
}