{
  "type": "Feature",
  "properties": {
    "iso:country":"US",
    "sg:address":"5715 Industry Ln",
    "sg:city":"Frederick",
    "sg:classifiers":[
        {
            "category":"Shopping",
            "subcategory":"Bicycles & Sporting Goods",
            "type":"Retail Goods"
        },
        {
            "category":"Personal",
            "subcategory":"Day Spa",
            "type":"Services"
        },
        {
            "category":"Sports & Exercise",
            "subcategory":"Swimming Pool",
            "type":"Entertainment"
        }
    ],
    "sg:phone":"+1 301 663 4848",
    "sg:postcode":"21704",
    "sg:province":"MD",
    "sg:tags":[
        "equipment",
        "repair",
        "hot",
        "tub",
        "supply"
    ],
    "sg:website":"http://www.flamingopoolsupply.com/",
    "wof:name":"Flamingo Pool Supply",
    "wof:placetype":"venue"
},
  "geometry": {"coordinates":[-77.414602,39.391229],"type":"Point"}
}