{
  "type": "Feature",
  "properties": {
    "addr:full":"22865 Hog Creek Rd Preston MD 21655",
    "addr:housenumber":"22865",
    "addr:postcode":"21655",
    "addr:street":"Hog Creek Rd",
    "iso:country":"US",
    "sg:address":"22865 Hog Creek Rd",
    "sg:city":"Preston",
    "sg:classifiers":[
        {
            "category":"Building & Trades",
            "subcategory":"Construction",
            "type":"Services"
        }
    ],
    "sg:phone":"+1 410 673 9021",
    "sg:postcode":"21655",
    "sg:province":"MD",
    "sg:tags":[
        "home",
        "builder"
    ],
    "wof:name":"Hutchinson Builders",
    "wof:placetype":"venue"
},
  "geometry": {"coordinates":[-75.914148,38.779799],"type":"Point"}
}