{
  "type": "Feature",
  "properties": {
    "iso:country":"US",
    "sg:address":"5711 4th St NW",
    "sg:city":"Washington",
    "sg:classifiers":[
        {
            "category":"Organizations",
            "subcategory":"Religious Organization",
            "type":"Services"
        }
    ],
    "sg:phone":"+1 202 726 8476",
    "sg:postcode":"20011",
    "sg:province":"MD",
    "sg:tags":[
        "clergy"
    ],
    "wof:name":"William E Jones",
    "wof:placetype":"venue"
},
  "geometry": {"coordinates":[-77.017959,38.959052],"type":"Point"}
}