{
  "type": "Feature",
  "properties": {
    "addr:full":"8841 Monard Dr Silver Spring MD 20910",
    "addr:housenumber":"8841",
    "addr:postcode":"20910",
    "addr:street":"Monard Dr",
    "iso:country":"US",
    "sg:address":"8841 Monard Dr",
    "sg:city":"Silver Spring",
    "sg:classifiers":[
        {
            "category":"Shopping",
            "subcategory":"Florist",
            "type":"Retail Goods"
        }
    ],
    "sg:phone":"+1 301 495 2938",
    "sg:postcode":"20910",
    "sg:province":"MD",
    "wof:name":"Janet Flowers Wedding & Event",
    "wof:placetype":"venue"
},
  "geometry": {"coordinates":[-77.058589,39.001193],"type":"Point"}
}