{
  "type": "Feature",
  "properties": {
    "addr:full":"17340 Big Falls Rd Monkton MD 21111",
    "addr:housenumber":"17340",
    "addr:postcode":"21111",
    "addr:street":"Big Falls Rd",
    "iso:country":"US",
    "sg:address":"17340 Big Falls Rd",
    "sg:city":"Monkton",
    "sg:classifiers":[
        {
            "category":"Utilities",
            "subcategory":"Telephone",
            "type":"Services"
        }
    ],
    "sg:phone":"+1 410 357 5797",
    "sg:postcode":"21111",
    "sg:province":"MD",
    "sg:tags":[
        "access",
        "internet",
        "provider"
    ],
    "wof:name":"Netbrain",
    "wof:placetype":"venue"
},
  "geometry": {"coordinates":[-76.637388,39.605178],"type":"Point"}
}