{
  "type": "Feature",
  "properties": {
    "iso:country":"US",
    "sg:address":"5937 Central Ave",
    "sg:city":"Capitol Heights",
    "sg:classifiers":[
        {
            "category":"Retail",
            "subcategory":"Laundry & Dry Cleaning",
            "type":"Services"
        }
    ],
    "sg:phone":"+1 301 420 5556",
    "sg:postcode":"20743",
    "sg:province":"MD",
    "wof:name":"Forest 24 Hour Laundromat",
    "wof:placetype":"venue"
},
  "geometry": {"coordinates":[-76.91589500000001,38.884847],"type":"Point"}
}