{
  "type": "Feature",
  "properties": {
    "addr:full":"9803 Gable Ridge Ter Rockville MD 20850",
    "addr:housenumber":"9803",
    "addr:postcode":"20850",
    "addr:street":"Gable Ridge Ter",
    "iso:country":"US",
    "sg:address":"9803 Gable Ridge Ter",
    "sg:city":"Rockville",
    "sg:classifiers":[
        {
            "category":"Professional",
            "subcategory":"Computer Services",
            "type":"Services"
        }
    ],
    "sg:phone":"+1 301 527 0653",
    "sg:postcode":"20850",
    "sg:province":"MD",
    "sg:tags":[
        "programing",
        "custom"
    ],
    "wof:name":"Onyss Inc",
    "wof:placetype":"venue"
},
  "geometry": {"coordinates":[-77.205088,39.108421],"type":"Point"}
}