{
  "type": "Feature",
  "properties": {
    "addr:full":"6907 Lady Anne Ct Greenbelt MD 20770",
    "addr:housenumber":"6907",
    "addr:postcode":"20770",
    "addr:street":"Lady Anne Ct",
    "iso:country":"US",
    "sg:address":"6907 Lady Anne Ct",
    "sg:city":"Greenbelt",
    "sg:classifiers":[
        {
            "category":"Wholesale",
            "subcategory":"Non-durable Goods",
            "type":"Manufacturing & Wholesale Goods"
        }
    ],
    "sg:phone":"+1 301 474 6096",
    "sg:postcode":"20770",
    "sg:province":"MD",
    "wof:name":"Germaine Timmermans",
    "wof:placetype":"venue"
},
  "geometry": {"coordinates":[-76.889127,38.99818],"type":"Point"}
}