{
  "type": "Feature",
  "properties": {
    "addr:full":"8804 Logtown Rd Berlin MD 21811",
    "addr:housenumber":"8804",
    "addr:postcode":"21811",
    "addr:street":"Logtown Rd",
    "iso:country":"US",
    "sg:address":"8804 Logtown Rd",
    "sg:city":"Berlin",
    "sg:classifiers":[
        {
            "category":"Sports & Exercise",
            "subcategory":"Golf",
            "type":"Entertainment"
        }
    ],
    "sg:phone":"+1 410 629 0060",
    "sg:postcode":"21811",
    "sg:province":"MD",
    "sg:tags":[
        "course"
    ],
    "sg:website":"www.golfoceancity.com",
    "wof:name":"Deer Run Golf Club",
    "wof:placetype":"venue"
},
  "geometry": {"coordinates":[-75.266283,38.362104],"type":"Point"}
}