{
  "type": "Feature",
  "properties": {
    "addr:full":"9339 Baltimore Ave College Park MD 20740",
    "addr:housenumber":"9339",
    "addr:postcode":"20740",
    "addr:street":"Baltimore Ave",
    "iso:country":"US",
    "sg:address":"9339 Baltimore Ave",
    "sg:city":"College Park",
    "sg:classifiers":[
        {
            "category":"Home & Garden",
            "subcategory":"Furniture",
            "type":"Retail Goods"
        }
    ],
    "sg:phone":"+1 301 220 0866",
    "sg:postcode":"20740",
    "sg:province":"MD",
    "sg:tags":[
        "water",
        "bed"
    ],
    "wof:name":"A 1 Waterbeds",
    "wof:placetype":"venue"
},
  "geometry": {"coordinates":[-76.929498,39.007397],"type":"Point"}
}