{
  "type": "Feature",
  "properties": {
    "addr:full":"3640 Karen Dr Chesapeake Beach MD 20732",
    "addr:housenumber":"3640",
    "addr:postcode":"20732",
    "addr:street":"Karen Dr",
    "iso:country":"US",
    "sg:address":"3640 Karen Dr",
    "sg:city":"Chesapeake Beach",
    "sg:classifiers":[
        {
            "category":"Building & Trades",
            "subcategory":"Construction",
            "type":"Services"
        }
    ],
    "sg:phone":"+1 410 535 9153",
    "sg:postcode":"20732",
    "sg:province":"MD",
    "sg:tags":[
        "home",
        "improvement"
    ],
    "wof:name":"AMG General Contractor",
    "wof:placetype":"venue"
},
  "geometry": {"coordinates":[-76.54054600000001,38.659189],"type":"Point"}
}