{
  "type": "Feature",
  "properties": {
    "iso:country":"US",
    "sg:address":"9885 Washington Blvd N",
    "sg:city":"Laurel",
    "sg:classifiers":[
        {
            "category":"Home & Garden",
            "subcategory":"Furniture",
            "type":"Retail Goods"
        }
    ],
    "sg:phone":"+1 301 362 3100",
    "sg:postcode":"20723",
    "sg:province":"MD",
    "sg:tags":[
        "store"
    ],
    "sg:website":"www.galaxyelectronics.com",
    "wof:name":"Galaxy Electronics",
    "wof:placetype":"venue"
},
  "geometry": {"coordinates":[-76.833,39.114498],"type":"Point"}
}