{
  "type": "Feature",
  "properties": {
    "iso:country":"US",
    "sg:address":"205 Baltimore Pike",
    "sg:city":"Bel Air",
    "sg:classifiers":[
        {
            "category":"Retail",
            "subcategory":"Auto Repair",
            "type":"Services"
        }
    ],
    "sg:phone":"+1 410 893 9116",
    "sg:postcode":"21014",
    "sg:province":"MD",
    "sg:tags":[
        "repairing",
        "automobile"
    ],
    "wof:name":"Kimmel Tire & Auto Ctr",
    "wof:placetype":"venue"
},
  "geometry": {"coordinates":[-76.348903,39.531944],"type":"Point"}
}