{
  "type": "Feature",
  "properties": {
    "addr:full":"6700 Moravia Park Dr Baltimore MD 21206",
    "addr:housenumber":"6700",
    "addr:postcode":"21206",
    "addr:street":"Moravia Park Dr",
    "iso:country":"US",
    "sg:address":"6700 Moravia Park Dr",
    "sg:city":"Baltimore",
    "sg:classifiers":[
        {
            "category":"Wholesale",
            "subcategory":"Sporting Goods",
            "type":"Manufacturing & Wholesale Goods"
        }
    ],
    "sg:phone":"+1 410 325 6500",
    "sg:postcode":"21206",
    "sg:province":"MD",
    "sg:tags":[
        "equipment",
        "pool",
        "swimming"
    ],
    "wof:name":"Baltimore Pool Supply Inc",
    "wof:placetype":"venue"
},
  "geometry": {"coordinates":[-76.53440399999999,39.310462],"type":"Point"}
}