{
  "type": "Feature",
  "properties": {
    "iso:country":"US",
    "sg:address":"433 Midsummer Dr",
    "sg:city":"Gaithersburg",
    "sg:classifiers":[
        {
            "category":"Communications",
            "subcategory":"Film & Video Production",
            "type":"Services"
        }
    ],
    "sg:phone":"+1 301 840 9497",
    "sg:postcode":"20878",
    "sg:province":"MD",
    "sg:tags":[
        "motion"
    ],
    "wof:name":"Quality Image Production",
    "wof:placetype":"venue"
},
  "geometry": {"coordinates":[-77.222695,39.109905],"type":"Point"}
}