{
  "type": "Feature",
  "properties": {
    "addr:full":"2700 Thornbrook Rd Ellicott City MD 21042",
    "addr:housenumber":"2700",
    "addr:postcode":"21042",
    "addr:street":"Thornbrook Rd",
    "iso:country":"US",
    "sg:address":"2700 Thornbrook Rd",
    "sg:city":"Ellicott City",
    "sg:classifiers":[
        {
            "category":"Professional",
            "subcategory":"Computer Services",
            "type":"Services"
        }
    ],
    "sg:phone":"+1 410 313 9763",
    "sg:postcode":"21042",
    "sg:province":"MD",
    "sg:tags":[
        "consultant",
        "designer"
    ],
    "wof:name":"Advanced Performance Systems",
    "wof:placetype":"venue"
},
  "geometry": {"coordinates":[-76.842331,39.305807],"type":"Point"}
}