{
  "type": "Feature",
  "properties": {
    "iso:country":"US",
    "sg:address":"83 E Main St",
    "sg:city":"Westminster",
    "sg:classifiers":[
        {
            "category":"Professional",
            "subcategory":"Art Services",
            "type":"Services"
        }
    ],
    "sg:phone":"+1 410 840 3805",
    "sg:postcode":"21157",
    "sg:province":"MD",
    "sg:tags":[
        "graphic",
        "designer"
    ],
    "sg:website":"www.kohncreative.com",
    "wof:name":"Kohn Design & Printing Co Inc",
    "wof:placetype":"venue"
},
  "geometry": {"coordinates":[-76.993644,39.572872],"type":"Point"}
}