{
  "type": "Feature",
  "properties": {
    "addr:full":"881c Capital Centre Blvd Largo MD 20774",
    "addr:housenumber":"881c",
    "addr:postcode":"20774",
    "addr:street":"Capital Centre Blvd",
    "iso:country":"US",
    "sg:address":"881c Capital Centre Blvd",
    "sg:city":"Largo",
    "sg:classifiers":[
        {
            "category":"Restaurant",
            "type":"Food & Drink"
        }
    ],
    "sg:menulink":"http://www.allmenus.com/md/kent/252298-five-guys/menu/",
    "sg:phone":"+1 301 333 8494",
    "sg:postcode":"20774",
    "sg:province":"MD",
    "sg:tags":[
        "burger",
        "american"
    ],
    "wof:name":"Five Guys",
    "wof:placetype":"venue"
},
  "geometry": {"coordinates":[-76.845371,38.902435],"type":"Point"}
}