{
  "type": "Feature",
  "properties": {
    "iso:country":"US",
    "sg:address":"5344 Reisterstown Rd",
    "sg:city":"Baltimore",
    "sg:classifiers":[
        {
            "category":"Building & Trades",
            "subcategory":"Cleaning & Sanitation",
            "type":"Services"
        }
    ],
    "sg:phone":"+1 410 578 7847",
    "sg:postcode":"21215",
    "sg:province":"MD",
    "sg:tags":[
        "carpet"
    ],
    "wof:name":"Green's Mult-Service Enterprises Inc",
    "wof:placetype":"venue"
},
  "geometry": {"coordinates":[-76.6875,39.346001],"type":"Point"}
}