{
  "type": "Feature",
  "properties": {
    "addr:full":"18824 Woodfield Rd Gaithersburg MD 20879",
    "addr:housenumber":"18824",
    "addr:postcode":"20879",
    "addr:street":"Woodfield Rd",
    "iso:country":"US",
    "sg:address":"18824 Woodfield Rd",
    "sg:city":"Gaithersburg",
    "sg:classifiers":[
        {
            "category":"Retail",
            "subcategory":"Auto Repair",
            "type":"Services"
        }
    ],
    "sg:phone":"+1 301 417 9009",
    "sg:postcode":"20879",
    "sg:province":"MD",
    "sg:tags":[
        "repairing",
        "automobile"
    ],
    "wof:name":"Airpark Quick Lube",
    "wof:placetype":"venue"
},
  "geometry": {"coordinates":[-77.15714199999999,39.164611],"type":"Point"}
}