{
  "type": "Feature",
  "properties": {
    "iso:country":"US",
    "sg:address":"911 Galesville Rd",
    "sg:city":"Galesville",
    "sg:classifiers":[
        {
            "category":"Education",
            "subcategory":"Special Training",
            "type":"Public Place"
        }
    ],
    "sg:phone":"+1 410 222 1625",
    "sg:postcode":"20765",
    "sg:province":"MD",
    "sg:tags":[
        "educational"
    ],
    "sg:website":"http://www.arundelhigh.org",
    "wof:name":"Carrie Wdon Scnce Ctr Fndation",
    "wof:placetype":"venue"
},
  "geometry": {"coordinates":[-76.54944999999999,38.846451],"type":"Point"}
}