{
  "type": "Feature",
  "properties": {
    "addr:city":"Galesville",
    "addr:full":"911 Galesville Rd Galesville, Md 20765",
    "addr:house_number":"911",
    "addr:housenumber":"911",
    "addr:phone":"+1 410-222-1625",
    "addr:postcode":"20765",
    "addr:road":"Galesville Rd",
    "addr:state":"MD",
    "addr:street":"Galesville Rd",
    "iso:country":"US",
    "sg:address":"911 Galesville Rd",
    "sg:city":"Galesville",
    "sg:classifiers":[
        {
            "category":"Education",
            "subcategory":"Special Training",
            "type":"Public Place"
        }
    ],
    "sg:phone":"+1 410 222 1625",
    "sg:postcode":"20765",
    "sg:province":"MD",
    "sg:tags":[
        "educational"
    ],
    "sg:website":"http://www.arundelhigh.org",
    "wof:airports":[
        102531183
    ],
    "wof:name":"Carrie Weedon Science Center Foundation",
    "wof:placetype":"venue"
},
  "geometry": {"coordinates":[-76.54791,38.84575],"type":"Point"}
}