{
  "type": "Feature",
  "properties": {
    "addr:full":"800 S Frederick Ave Gaithersburg MD 20877",
    "addr:housenumber":"800",
    "addr:postcode":"20877",
    "addr:street":"S Frederick Ave",
    "iso:country":"US",
    "sg:address":"800 S Frederick Ave",
    "sg:city":"Gaithersburg",
    "sg:classifiers":[
        {
            "category":"Restaurant",
            "type":"Food & Drink"
        }
    ],
    "sg:phone":"+1 301 869 2342",
    "sg:postcode":"20877",
    "sg:province":"MD",
    "wof:name":"Tea Room",
    "wof:placetype":"venue"
},
  "geometry": {"coordinates":[-77.182266,39.125644],"type":"Point"}
}