{
  "type": "Feature",
  "properties": {
    "iso:country":"US",
    "sg:address":"5215 Lawrence Pl",
    "sg:city":"Hyattsville",
    "sg:classifiers":[
        {
            "category":"Professional",
            "subcategory":"Advertising",
            "type":"Services"
        }
    ],
    "sg:phone":"+1 301 864 7616",
    "sg:postcode":"20781",
    "sg:province":"MD",
    "sg:tags":[
        "shop",
        "letter"
    ],
    "wof:name":"Direct Mail Advertising Co",
    "wof:placetype":"venue"
},
  "geometry": {"coordinates":[-76.929369,38.932633],"type":"Point"}
}