{
  "type": "Feature",
  "properties": {
    "iso:country":"US",
    "sg:address":"19600 Frederick Rd",
    "sg:city":"Germantown",
    "sg:classifiers":[
        {
            "category":"Manufacturing",
            "subcategory":"Signs",
            "type":"Manufacturing & Wholesale Goods"
        }
    ],
    "sg:phone":"+1 301 972 2100",
    "sg:postcode":"20876",
    "sg:province":"MD",
    "wof:name":"Signs One Hour",
    "wof:placetype":"venue"
},
  "geometry": {"coordinates":[-77.23814400000001,39.17599],"type":"Point"}
}