{
  "type": "Feature",
  "properties": {
    "addr:full":"8820 Fearne Ave Baltimore MD 21234",
    "addr:housenumber":"8820",
    "addr:postcode":"21234",
    "addr:street":"Fearne Ave",
    "iso:country":"US",
    "sg:address":"8820 Fearne Ave",
    "sg:city":"Baltimore",
    "sg:classifiers":[
        {
            "category":"Building & Trades",
            "subcategory":"Electrical",
            "type":"Services"
        }
    ],
    "sg:phone":"+1 410 668 8778",
    "sg:postcode":"21234",
    "sg:province":"MD",
    "sg:tags":[
        "specializing",
        "work",
        "general",
        "electrical",
        "sing",
        "contractor"
    ],
    "wof:name":"Bruno Al Gen & Elec Contractin",
    "wof:placetype":"venue"
},
  "geometry": {"coordinates":[-76.52174100000001,39.381146],"type":"Point"}
}