{
  "type": "Feature",
  "properties": {
    "iso:country":"US",
    "sg:address":"3423 Branch Ave",
    "sg:city":"Temple Hills",
    "sg:classifiers":[
        {
            "category":"Personal",
            "type":"Services"
        }
    ],
    "sg:phone":"+1 301 702 7215",
    "sg:postcode":"20748",
    "sg:province":"MD",
    "sg:tags":[
        "sewing",
        "alteration"
    ],
    "wof:name":"Peoples Affair Custom Tailors",
    "wof:placetype":"venue"
},
  "geometry": {"coordinates":[-76.949203,38.842999],"type":"Point"}
}