{
  "type": "Feature",
  "properties": {
    "addr:full":"8903 Presidential Pkwy Upper Marlboro MD 20772",
    "addr:housenumber":"8903",
    "addr:postcode":"20772",
    "addr:street":"Presidential Pkwy",
    "iso:country":"US",
    "sg:address":"8903 Presidential Pkwy",
    "sg:city":"Upper Marlboro",
    "sg:classifiers":[
        {
            "category":"Travel",
            "subcategory":"Travel Agent",
            "type":"Entertainment"
        }
    ],
    "sg:phone":"+1 301 967 8687",
    "sg:postcode":"20772",
    "sg:province":"MD",
    "sg:tags":[
        "agency",
        "bureau"
    ],
    "wof:name":"Prince George's County MD",
    "wof:placetype":"venue"
},
  "geometry": {"coordinates":[-76.85004499999999,38.826401],"type":"Point"}
}