{
  "type": "Feature",
  "properties": {
    "iso:country":"US",
    "sg:address":"1131 University Blvd W Apt 1907",
    "sg:city":"Silver Spring",
    "sg:classifiers":[
        {
            "category":"Airline",
            "type":"Transportation"
        }
    ],
    "sg:phone":"+1 301 424 4600",
    "sg:postcode":"20902",
    "sg:province":"MD",
    "sg:tags":[
        "shuttle",
        "airport"
    ],
    "wof:name":"Pablo Buitrajo Dba Atlas Metro Airport Shuttle",
    "wof:placetype":"venue"
},
  "geometry": {"coordinates":[-77.030475,39.036786],"type":"Point"}
}