{
  "type": "Feature",
  "properties": {
    "addr:full":"5800 Annapolis Rd Bladensburg MD 20710",
    "addr:housenumber":"5800",
    "addr:postcode":"20710",
    "addr:street":"Annapolis Rd",
    "iso:country":"US",
    "sg:address":"5800 Annapolis Rd",
    "sg:city":"Bladensburg",
    "sg:classifiers":[
        {
            "category":"Insurance",
            "subcategory":"Insurance Agent",
            "type":"Services"
        }
    ],
    "sg:phone":"+1 301 497 6063",
    "sg:postcode":"20710",
    "sg:province":"MD",
    "wof:name":"Zenith Insurance",
    "wof:placetype":"venue"
},
  "geometry": {"coordinates":[-76.917013,38.939643],"type":"Point"}
}