{
  "type": "Feature",
  "properties": {
    "iso:country":"US",
    "sg:address":"6101 Hopeton Ave",
    "sg:city":"Baltimore",
    "sg:classifiers":[
        {
            "category":"Professional",
            "type":"Services"
        }
    ],
    "sg:phone":"+1 410 764 3439",
    "sg:postcode":"21215",
    "sg:province":"MD",
    "wof:name":"Ellis Y Pruce",
    "wof:placetype":"venue"
},
  "geometry": {"coordinates":[-76.694632,39.354993],"type":"Point"}
}