{
  "type": "Feature",
  "properties": {
    "iso:country":"US",
    "sg:address":"4886 Drawbridge Rd Apt 2",
    "sg:city":"Cambridge",
    "sg:classifiers":[
        {
            "category":"Utilities",
            "subcategory":"Refuse",
            "type":"Services"
        }
    ],
    "sg:phone":"+1 410 330 2617",
    "sg:postcode":"21613",
    "sg:province":"MD",
    "sg:tags":[
        "collection",
        "garbage"
    ],
    "wof:name":"Jaamm Rolloff Services",
    "wof:placetype":"venue"
},
  "geometry": {"coordinates":[-75.965801,38.511077],"type":"Point"}
}