{
  "type": "Feature",
  "properties": {
    "iso:country":"US",
    "sg:address":"100 Compromise St",
    "sg:city":"Annapolis",
    "sg:classifiers":[
        {
            "category":"Government",
            "subcategory":"Office",
            "type":"Public Place"
        }
    ],
    "sg:phone":"+1 410 263 4614",
    "sg:postcode":"21401",
    "sg:province":"MD",
    "sg:tags":[
        "federal",
        "security"
    ],
    "wof:name":"US Navy Dept",
    "wof:placetype":"venue"
},
  "geometry": {"coordinates":[-76.487084,38.977374],"type":"Point"}
}