{
  "type": "Feature",
  "properties": {
    "iso:country":"US",
    "sg:address":"6902 Crabapple Ct",
    "sg:city":"Frederick",
    "sg:classifiers":[
        {
            "category":"Social Services",
            "subcategory":"Adult Care",
            "type":"Services"
        }
    ],
    "sg:phone":"+1 301 662 0400",
    "sg:postcode":"21703",
    "sg:province":"MD",
    "sg:tags":[
        "living",
        "congregate",
        "facility"
    ],
    "wof:name":"Crestwood Village Clubhouse",
    "wof:placetype":"venue"
},
  "geometry": {"coordinates":[-77.42785,39.388245],"type":"Point"}
}