{
  "type": "Feature",
  "properties": {
    "addr:full":"15190 Frederick Rd Rockville MD 20850",
    "addr:housenumber":"15190",
    "addr:postcode":"20850",
    "addr:street":"Frederick Rd",
    "iso:country":"US",
    "sg:address":"15190 Frederick Rd",
    "sg:city":"Rockville",
    "sg:classifiers":[
        {
            "category":"Autos & Motor Vehicles",
            "subcategory":"Fuel & Gas Station",
            "type":"Retail Goods"
        }
    ],
    "sg:phone":"+1 301 424 5649",
    "sg:postcode":"20850",
    "sg:province":"MD",
    "sg:tags":[
        "oil"
    ],
    "wof:name":"Courthouse Amoco",
    "wof:placetype":"venue"
},
  "geometry": {"coordinates":[-77.156898,39.104119],"type":"Point"}
}