{
  "type": "Feature",
  "properties": {
    "addr:full":"115 Flower St Berlin MD 21811",
    "addr:housenumber":"115",
    "addr:postcode":"21811",
    "addr:street":"Flower St",
    "iso:country":"US",
    "sg:address":"115 Flower St",
    "sg:city":"Berlin",
    "sg:classifiers":[
        {
            "category":"Professional",
            "type":"Services"
        }
    ],
    "sg:phone":"+1 410 629 0004",
    "sg:postcode":"21811",
    "sg:province":"MD",
    "sg:tags":[
        "establishment"
    ],
    "wof:name":"Loving Hands",
    "wof:placetype":"venue"
},
  "geometry": {"coordinates":[-75.209557,38.325497],"type":"Point"}
}