{
  "type": "Feature",
  "properties": {
    "iso:country":"US",
    "sg:address":"4922 Cordell Ave",
    "sg:city":"Bethesda",
    "sg:classifiers":[
        {
            "category":"Bars & Pubs",
            "subcategory":"Sports Bar",
            "type":"Food & Drink"
        },
        {
            "category":"Restaurant",
            "type":"Food & Drink"
        }
    ],
    "sg:phone":"+1 301 215 7730",
    "sg:postcode":"20814",
    "sg:province":"MD",
    "sg:tags":[
        "traditional",
        "american"
    ],
    "sg:website":"www.caddiesoncordell.com",
    "wof:name":"Caddies On Cordell",
    "wof:placetype":"venue"
},
  "geometry": {"coordinates":[-77.098411,38.989069],"type":"Point"}
}