{
  "type": "Feature",
  "properties": {
    "iso:country":"US",
    "sg:address":"2505 Bounty Ct",
    "sg:city":"Bel Air",
    "sg:classifiers":[
        {
            "category":"Building & Trades",
            "subcategory":"Construction",
            "type":"Services"
        }
    ],
    "sg:phone":"+1 410 836 7244",
    "sg:postcode":"21015",
    "sg:province":"MD",
    "sg:tags":[
        "siding",
        "contractor"
    ],
    "wof:name":"Hidden Valley Contractors",
    "wof:placetype":"venue"
},
  "geometry": {"coordinates":[-76.275913,39.58874],"type":"Point"}
}