{
  "type": "Feature",
  "properties": {
    "iso:country":"US",
    "sg:address":"104 Forbes St",
    "sg:city":"Annapolis",
    "sg:classifiers":[
        {
            "category":"Organizations",
            "subcategory":"Religious Organization",
            "type":"Services"
        }
    ],
    "sg:phone":"+1 410 263 2800",
    "sg:postcode":"21401",
    "sg:province":"MD",
    "wof:name":"Wedding Savvy",
    "wof:placetype":"venue"
},
  "geometry": {"coordinates":[-76.50425300000001,38.988302],"type":"Point"}
}