{
  "type": "Feature",
  "properties": {
    "addr:full":"2618 Beckleysville Rd Freeland MD 21053",
    "addr:housenumber":"2618",
    "addr:postcode":"21053",
    "addr:street":"Beckleysville Rd",
    "iso:country":"US",
    "sg:address":"2618 Beckleysville Rd",
    "sg:city":"Freeland",
    "sg:classifiers":[
        {
            "category":"Building & Trades",
            "subcategory":"Plumbing",
            "type":"Services"
        }
    ],
    "sg:phone":"+1 410 343 1515",
    "sg:postcode":"21053",
    "sg:province":"MD",
    "sg:tags":[
        "septic"
    ],
    "wof:name":"Blevins & Sons Septic Svc",
    "wof:placetype":"venue"
},
  "geometry": {"coordinates":[-76.732947,39.673511],"type":"Point"}
}