{
  "type": "Feature",
  "properties": {
    "addr:full":"1443 Old Philadelphia Rd Aberdeen MD 21001",
    "addr:housenumber":"1443",
    "addr:postcode":"21001",
    "addr:street":"Old Philadelphia Rd",
    "iso:country":"US",
    "sg:address":"1443 Old Philadelphia Rd",
    "sg:city":"Aberdeen",
    "sg:classifiers":[
        {
            "category":"Manufacturing",
            "subcategory":"Printing",
            "type":"Manufacturing & Wholesale Goods"
        }
    ],
    "sg:phone":"+1 410 575 7866",
    "sg:postcode":"21001",
    "sg:province":"MD",
    "sg:tags":[
        "lithographic",
        "commercial"
    ],
    "wof:name":"North Star Printing Service",
    "wof:placetype":"venue"
},
  "geometry": {"coordinates":[-76.207491,39.491569],"type":"Point"}
}