{
  "type": "Feature",
  "properties": {
    "iso:country":"US",
    "sg:address":"8007 Norfolk Ave",
    "sg:city":"Bethesda",
    "sg:classifiers":[
        {
            "category":"Personal",
            "subcategory":"Barber",
            "type":"Services"
        }
    ],
    "sg:phone":"+1 301 656 6929",
    "sg:postcode":"20814",
    "sg:province":"MD",
    "sg:website":"www.hannahbarbershop.com",
    "wof:name":"Hannah's Barber & Hair Stylist",
    "wof:placetype":"venue"
},
  "geometry": {"coordinates":[-77.098912,38.989892],"type":"Point"}
}