{
  "type": "Feature",
  "properties": {
    "iso:country":"US",
    "sg:address":"7309 Waverly St",
    "sg:city":"Bethesda",
    "sg:classifiers":[
        {
            "category":"Manufacturing",
            "subcategory":"Printing",
            "type":"Manufacturing & Wholesale Goods"
        }
    ],
    "sg:phone":"+1 301 656 4456",
    "sg:postcode":"20814",
    "sg:province":"MD",
    "sg:tags":[
        "printer"
    ],
    "wof:name":"Controlled Quality Corp",
    "wof:placetype":"venue"
},
  "geometry": {"coordinates":[-77.092339,38.983824],"type":"Point"}
}