{
  "type": "Feature",
  "properties": {
    "iso:country":"US",
    "sg:address":"273 Michener Ct W",
    "sg:city":"Severna Park",
    "sg:classifiers":[
        {
            "category":"Organizations",
            "subcategory":"Religious Organization",
            "type":"Services"
        }
    ],
    "sg:phone":"+1 410 975 0718",
    "sg:postcode":"21146",
    "sg:province":"MD",
    "wof:name":"Renewal Ministries LLC",
    "wof:placetype":"venue"
},
  "geometry": {"coordinates":[-76.539868,39.090857],"type":"Point"}
}