{
  "type": "Feature",
  "properties": {
    "iso:country":"US",
    "sg:address":"15600 Lower Georges Creek Rd SW",
    "sg:city":"Lonaconing",
    "sg:classifiers":[
        {
            "category":"Education",
            "subcategory":"School",
            "type":"Public Place"
        }
    ],
    "sg:phone":"+1 301 463 6202",
    "sg:postcode":"21539",
    "sg:province":"MD",
    "wof:name":"George's Creek Elementary",
    "wof:placetype":"venue"
},
  "geometry": {"coordinates":[-78.971682,39.578739],"type":"Point"}
}