{
  "type": "Feature",
  "properties": {
    "iso:country":"US",
    "sg:address":"8061 Cryden Way",
    "sg:city":"Forestville",
    "sg:classifiers":[
        {
            "category":"Retail",
            "subcategory":"Auto Repair",
            "type":"Services"
        }
    ],
    "sg:phone":"+1 301 736 7766",
    "sg:postcode":"20747",
    "sg:province":"MD",
    "sg:tags":[
        "exchanging",
        "engine"
    ],
    "wof:name":"B & C Auto Machining",
    "wof:placetype":"venue"
},
  "geometry": {"coordinates":[-76.869264,38.847687],"type":"Point"}
}