{
  "type": "Feature",
  "properties": {
    "iso:country":"US",
    "sg:address":"701 Kelly Rd",
    "sg:city":"Cumberland",
    "sg:classifiers":[
        {
            "category":"Government",
            "subcategory":"Court House",
            "type":"Public Place"
        }
    ],
    "sg:phone":"+1 301 777 5823",
    "sg:postcode":"21502",
    "sg:province":"MD",
    "sg:tags":[
        "county",
        "counsel"
    ],
    "sg:website":"www.tccwmd.org",
    "wof:name":"Allegany County Attorney",
    "wof:placetype":"venue"
},
  "geometry": {"coordinates":[-78.777891,39.645502],"type":"Point"}
}