{
  "type": "Feature",
  "properties": {
    "iso:country":"US",
    "sg:address":"155 Central Dr",
    "sg:city":"Prince Frederick",
    "sg:classifiers":[
        {
            "category":"Autos & Motor Vehicles",
            "subcategory":"Auto Supplies",
            "type":"Retail Goods"
        }
    ],
    "sg:phone":"+1 410 257 4366",
    "sg:postcode":"20678",
    "sg:province":"MD",
    "sg:tags":[
        "automobile",
        "parts"
    ],
    "wof:name":"Tint Works Plus",
    "wof:placetype":"venue"
},
  "geometry": {"coordinates":[-76.57671,38.554571],"type":"Point"}
}