{
  "type": "Feature",
  "properties": {
    "iso:country":"US",
    "sg:address":"1830 Rosemont Ave",
    "sg:city":"Frederick",
    "sg:classifiers":[
        {
            "category":"Professional",
            "type":"Services"
        }
    ],
    "sg:phone":"+1 301 662 7842",
    "sg:postcode":"21702",
    "sg:province":"MD",
    "sg:tags":[
        "establishment"
    ],
    "wof:name":"BBN",
    "wof:placetype":"venue"
},
  "geometry": {"coordinates":[-77.433431,39.430328],"type":"Point"}
}