{
  "type": "Feature",
  "properties": {
    "addr:full":"6200 Baltimore National Pike Catonsville MD 21228",
    "addr:housenumber":"6200",
    "addr:postcode":"21228",
    "addr:street":"Baltimore National Pike",
    "iso:country":"US",
    "sg:address":"6200 Baltimore National Pike",
    "sg:city":"Catonsville",
    "sg:classifiers":[
        {
            "category":"Restaurant",
            "type":"Food & Drink"
        }
    ],
    "sg:menulink":"http://www.allmenus.com/md/catonsville/207680-taco-bell/menu/",
    "sg:phone":"+1 410 788 3379",
    "sg:postcode":"21228",
    "sg:province":"MD",
    "sg:tags":[
        "mexican"
    ],
    "wof:name":"Taco Bell",
    "wof:placetype":"venue"
},
  "geometry": {"coordinates":[-76.75056600000001,39.283873],"type":"Point"}
}