{
  "type": "Feature",
  "properties": {
    "iso:country":"US",
    "sg:address":"1219 Meridene Dr",
    "sg:city":"Baltimore",
    "sg:classifiers":[
        {
            "category":"Restaurant",
            "type":"Food & Drink"
        }
    ],
    "sg:phone":"+1 410 235 7762",
    "sg:postcode":"21239",
    "sg:province":"MD",
    "sg:tags":[
        "eating"
    ],
    "wof:name":"Lee Sheen Chinese Carry-Out",
    "wof:placetype":"venue"
},
  "geometry": {"coordinates":[-76.591797,39.368281],"type":"Point"}
}