{
  "type": "Feature",
  "properties": {
    "addr:full":"7466 New Ridge Rd Suite 9 Hanover MD 21076",
    "addr:housenumber":"7466",
    "addr:postcode":"21076",
    "addr:street":"New Ridge Rd Suite 9",
    "iso:country":"US",
    "sg:address":"7466 New Ridge Rd Suite 9",
    "sg:city":"Hanover",
    "sg:classifiers":[
        {
            "category":"Professional",
            "subcategory":"Business Services",
            "type":"Services"
        }
    ],
    "sg:phone":"+1 410 850 7110",
    "sg:postcode":"21076",
    "sg:province":"MD",
    "sg:tags":[
        "broker"
    ],
    "sg:website":"http://www.vrbb.com",
    "wof:name":"A VR Business Broker",
    "wof:placetype":"venue"
},
  "geometry": {"coordinates":[-76.70708999999999,39.165422],"type":"Point"}
}