{
  "type": "Feature",
  "properties": {
    "addr:full":"707 Conservation Ln Gaithersburg MD 20878",
    "addr:housenumber":"707",
    "addr:postcode":"20878",
    "addr:street":"Conservation Ln",
    "iso:country":"US",
    "sg:address":"707 Conservation Ln",
    "sg:city":"Gaithersburg",
    "sg:classifiers":[
        {
            "category":"Organizations",
            "subcategory":"Non-profit Organization",
            "type":"Services"
        }
    ],
    "sg:phone":"+1 301 330 0648",
    "sg:postcode":"20878",
    "sg:province":"MD",
    "wof:name":"Joseph P Kennedy Institute",
    "wof:placetype":"venue"
},
  "geometry": {"coordinates":[-77.22071699999999,39.121436],"type":"Point"}
}