{
  "type": "Feature",
  "properties": {
    "iso:country":"US",
    "sg:address":"111 W Chesapeake Ave",
    "sg:city":"Baltimore",
    "sg:classifiers":[
        {
            "category":"Government",
            "subcategory":"Office",
            "type":"Public Place"
        }
    ],
    "sg:phone":"+1 410 887 3610",
    "sg:postcode":"21204",
    "sg:province":"MD",
    "wof:name":"Baltimore County Permits Dept",
    "wof:placetype":"venue"
},
  "geometry": {"coordinates":[-76.605761,39.399612],"type":"Point"}
}