{
  "type": "Feature",
  "properties": {
    "iso:country":"US",
    "sg:address":"147 Sunnybrook Dr",
    "sg:city":"Elkton",
    "sg:classifiers":[
        {
            "category":"Building & Trades",
            "subcategory":"Electrical",
            "type":"Services"
        }
    ],
    "sg:phone":"+1 410 620 3186",
    "sg:postcode":"21921",
    "sg:province":"MD",
    "sg:tags":[
        "electric",
        "contractor"
    ],
    "wof:name":"T M Cooper",
    "wof:placetype":"venue"
},
  "geometry": {"coordinates":[-75.79974,39.562374],"type":"Point"}
}