{
  "type": "Feature",
  "properties": {
    "iso:country":"US",
    "sg:address":"10875 Alyssa Ln",
    "sg:city":"Waldorf",
    "sg:classifiers":[
        {
            "category":"Place Of Worship",
            "subcategory":"Church",
            "type":"Public Place"
        },
        {
            "category":"Place Of Worship",
            "type":"Public Place"
        }
    ],
    "sg:phone":"+1 301 861 0234",
    "sg:postcode":"20603",
    "sg:province":"MD",
    "sg:tags":[
        "christ",
        "churches-community"
    ],
    "wof:name":"Covenant Life Community C",
    "wof:placetype":"venue"
},
  "geometry": {"coordinates":[-76.9413,38.63927],"type":"Point"}
}