{
  "type": "Feature",
  "properties": {
    "addr:full":"530 Marvel Rd Salisbury MD 21801",
    "addr:housenumber":"530",
    "addr:postcode":"21801",
    "addr:street":"Marvel Rd",
    "iso:country":"US",
    "sg:address":"530 Marvel Rd",
    "sg:city":"Salisbury",
    "sg:classifiers":[
        {
            "category":"Wholesale",
            "subcategory":"Auto Parts",
            "type":"Manufacturing & Wholesale Goods"
        }
    ],
    "sg:phone":"+1 410 548 1400",
    "sg:postcode":"21801",
    "sg:province":"MD",
    "sg:tags":[
        "tire"
    ],
    "wof:name":"Itco Tire Co",
    "wof:placetype":"venue"
},
  "geometry": {"coordinates":[-75.58409899999999,38.400308],"type":"Point"}
}