{
  "type": "Feature",
  "properties": {
    "addr:full":"4700 Maple Grove Rd Hampstead MD 21074",
    "addr:housenumber":"4700",
    "addr:postcode":"21074",
    "addr:street":"Maple Grove Rd",
    "iso:country":"US",
    "sg:address":"4700 Maple Grove Rd",
    "sg:city":"Hampstead",
    "sg:classifiers":[
        {
            "category":"Building & Trades",
            "subcategory":"Construction",
            "type":"Services"
        }
    ],
    "sg:phone":"+1 410 239 8670",
    "sg:postcode":"21074",
    "sg:province":"MD",
    "sg:tags":[
        "contractor"
    ],
    "wof:name":"S & S Contractors",
    "wof:placetype":"venue"
},
  "geometry": {"coordinates":[-76.82402399999999,39.645903],"type":"Point"}
}