{
  "type": "Feature",
  "properties": {
    "addr:full":"7330 Guilford Dr Frederick MD 21704",
    "addr:housenumber":"7330",
    "addr:postcode":"21704",
    "addr:street":"Guilford Dr",
    "iso:country":"US",
    "sg:address":"7330 Guilford Dr",
    "sg:city":"Frederick",
    "sg:classifiers":[
        {
            "category":"Shopping",
            "subcategory":"Hobbies, Toys, & Games",
            "type":"Retail Goods"
        },
        {
            "category":"Shopping",
            "subcategory":"Crafts & Fabrics",
            "type":"Retail Goods"
        },
        {
            "category":"Professional",
            "subcategory":"Art Services",
            "type":"Services"
        },
        {
            "category":"Home & Garden",
            "subcategory":"Garden Supply",
            "type":"Retail Goods"
        }
    ],
    "sg:phone":"+1 301 668 3714",
    "sg:postcode":"21704",
    "sg:province":"MD",
    "sg:tags":[
        "shop",
        "picture",
        "frame",
        "instruction",
        "yarn",
        "embroidery",
        "hobby",
        "model"
    ],
    "wof:name":"Ac Moore",
    "wof:placetype":"venue"
},
  "geometry": {"coordinates":[-77.41619900000001,39.396881],"type":"Point"}
}