{
  "type": "Feature",
  "properties": {
    "addr:full":"4224 Red Haven Rd Pikesville MD 21208",
    "addr:housenumber":"4224",
    "addr:postcode":"21208",
    "addr:street":"Red Haven Rd",
    "iso:country":"US",
    "sg:address":"4224 Red Haven Rd",
    "sg:city":"Pikesville",
    "sg:classifiers":[
        {
            "category":"Professional",
            "subcategory":"Business Services",
            "type":"Services"
        }
    ],
    "sg:phone":"+1 410 602 5018",
    "sg:postcode":"21208",
    "sg:province":"MD",
    "wof:name":"I Q Business Solutions",
    "wof:placetype":"venue"
},
  "geometry": {"coordinates":[-76.725855,39.355222],"type":"Point"}
}