{
  "type": "Feature",
  "properties": {
    "iso:country":"US",
    "sg:address":"12370 Waldorf Business Sq",
    "sg:city":"Waldorf",
    "sg:classifiers":[
        {
            "category":"Home & Garden",
            "subcategory":"Building Materials",
            "type":"Retail Goods"
        }
    ],
    "sg:phone":"+1 301 843 0434",
    "sg:postcode":"20601",
    "sg:province":"MD",
    "sg:tags":[
        "paint"
    ],
    "wof:name":"Duron Paints & Wallcoverings",
    "wof:placetype":"venue"
},
  "geometry": {"coordinates":[-76.89937999999999,38.63936],"type":"Point"}
}