{
  "type": "Feature",
  "properties": {
    "iso:country":"US",
    "sg:address":"65 Strawhat Rd",
    "sg:city":"Owings Mills",
    "sg:classifiers":[
        {
            "category":"Personal",
            "type":"Services"
        }
    ],
    "sg:phone":"+1 443 386 5221",
    "sg:postcode":"21117",
    "sg:province":"MD",
    "sg:tags":[
        "home",
        "improvement"
    ],
    "wof:name":"Keith L Mallonee",
    "wof:placetype":"venue"
},
  "geometry": {"coordinates":[-76.78342600000001,39.425139],"type":"Point"}
}