{
  "type": "Feature",
  "properties": {
    "addr:full":"25 Wandsworth Bridge Way Lutherville MD 21093",
    "addr:housenumber":"25",
    "addr:postcode":"21093",
    "addr:street":"Wandsworth Bridge Way",
    "iso:country":"US",
    "sg:address":"25 Wandsworth Bridge Way",
    "sg:city":"Lutherville",
    "sg:classifiers":[
        {
            "category":"Professional",
            "subcategory":"Lawyer & Legal Services",
            "type":"Services"
        }
    ],
    "sg:phone":"+1 410 823 4455",
    "sg:postcode":"21093",
    "sg:province":"MD",
    "sg:tags":[
        "attorney"
    ],
    "wof:name":"Leslie M Pittler",
    "wof:placetype":"venue"
},
  "geometry": {"coordinates":[-76.64171399999999,39.434164],"type":"Point"}
}