{
  "type": "Feature",
  "properties": {
    "iso:country":"US",
    "sg:address":"3201 Mountain Rd",
    "sg:city":"Pasadena",
    "sg:classifiers":[
        {
            "category":"Retail",
            "subcategory":"Laundry & Dry Cleaning",
            "type":"Services"
        }
    ],
    "sg:phone":"+1 410 255 6250",
    "sg:postcode":"21122",
    "sg:province":"MD",
    "sg:tags":[
        "cleaners"
    ],
    "wof:name":"Youngs Cleaners",
    "wof:placetype":"venue"
},
  "geometry": {"coordinates":[-76.534792,39.125985],"type":"Point"}
}