{
  "type": "Feature",
  "properties": {
    "addr:full":"7522 Old Alexandria Ferry Rd Clinton MD 20735",
    "addr:housenumber":"7522",
    "addr:postcode":"20735",
    "addr:street":"Old Alexandria Ferry Rd",
    "iso:country":"US",
    "sg:address":"7522 Old Alexandria Ferry Rd",
    "sg:city":"Clinton",
    "sg:classifiers":[
        {
            "category":"Retail",
            "subcategory":"Auto Repair",
            "type":"Services"
        }
    ],
    "sg:phone":"+1 301 868 3778",
    "sg:postcode":"20735",
    "sg:province":"MD",
    "sg:tags":[
        "general"
    ],
    "wof:name":"Capitol Auto Service Inc",
    "wof:placetype":"venue"
},
  "geometry": {"coordinates":[-76.875711,38.780397],"type":"Point"}
}