{
  "type": "Feature",
  "properties": {
    "addr:full":"1253 Poole Rd Westminster MD 21157",
    "addr:housenumber":"1253",
    "addr:postcode":"21157",
    "addr:street":"Poole Rd",
    "iso:country":"US",
    "sg:address":"1253 Poole Rd",
    "sg:city":"Westminster",
    "sg:classifiers":[
        {
            "category":"Farming",
            "subcategory":"Farm",
            "type":"Manufacturing & Wholesale Goods"
        }
    ],
    "sg:phone":"+1 410 876 3458",
    "sg:postcode":"21157",
    "sg:province":"MD",
    "wof:name":"Hilly Acres",
    "wof:placetype":"venue"
},
  "geometry": {"coordinates":[-76.965327,39.54424],"type":"Point"}
}