{
  "type": "Feature",
  "properties": {
    "addr:full":"5333 Sheriff Rd Fairmount Hts MD 20743",
    "addr:housenumber":"5333",
    "addr:postcode":"20743",
    "addr:street":"Sheriff Rd",
    "iso:country":"US",
    "sg:address":"5333 Sheriff Rd",
    "sg:city":"Fairmount Hts",
    "sg:classifiers":[
        {
            "category":"Insurance",
            "subcategory":"Hazard Insurance",
            "type":"Services"
        }
    ],
    "sg:phone":"+1 301 773 6675",
    "sg:postcode":"20743",
    "sg:province":"MD",
    "sg:tags":[
        "bond"
    ],
    "wof:name":"Hamilton Bonding Svc",
    "wof:placetype":"venue"
},
  "geometry": {"coordinates":[-76.921166,38.904304],"type":"Point"}
}