{
  "type": "Feature",
  "properties": {
    "iso:country":"US",
    "sg:address":"15805 Paramount Dr",
    "sg:city":"Rockville",
    "sg:classifiers":[
        {
            "category":"Taxi",
            "type":"Transportation"
        }
    ],
    "sg:phone":"+1 301 926 2900",
    "sg:postcode":"20855",
    "sg:province":"MD",
    "sg:tags":[
        "taxicab"
    ],
    "wof:name":"Airport Taxi",
    "wof:placetype":"venue"
},
  "geometry": {"coordinates":[-77.16184800000001,39.116771],"type":"Point"}
}