{
  "type": "Feature",
  "properties": {
    "iso:country":"US",
    "sg:address":"8511 Liberty Rd",
    "sg:city":"Randallstown",
    "sg:classifiers":[
        {
            "category":"Restaurant",
            "type":"Food & Drink"
        }
    ],
    "sg:phone":"+1 410 496 4026",
    "sg:postcode":"21133",
    "sg:province":"MD",
    "sg:tags":[
        "parlor",
        "ice",
        "cream"
    ],
    "wof:name":"Randallstown Twin Kiss",
    "wof:placetype":"venue"
},
  "geometry": {"coordinates":[-76.776152,39.360366],"type":"Point"}
}