{
  "type": "Feature",
  "properties": {
    "iso:country":"US",
    "sg:address":"8211 Northview Ct",
    "sg:city":"Laurel",
    "sg:classifiers":[
        {
            "category":"Shopping",
            "subcategory":"Optical Goods",
            "type":"Retail Goods"
        }
    ],
    "sg:phone":"+1 301 171 2159",
    "sg:postcode":"20707",
    "sg:province":"MD",
    "sg:tags":[
        "product",
        "selling",
        "general",
        "over",
        "internet"
    ],
    "wof:name":"Shayshaycom",
    "wof:placetype":"venue"
},
  "geometry": {"coordinates":[-76.864853,39.092433],"type":"Point"}
}