{
  "type": "Feature",
  "properties": {
    "iso:country":"US",
    "sg:address":"121 el Camino Way",
    "sg:city":"Fort Washington",
    "sg:classifiers":[
        {
            "category":"Shopping",
            "type":"Retail Goods"
        }
    ],
    "sg:phone":"+1 703 538 5525",
    "sg:postcode":"20744",
    "sg:province":"MD",
    "sg:tags":[
        "coin",
        "dealer",
        "supply"
    ],
    "wof:name":"U S Penny & Coin Svc",
    "wof:placetype":"venue"
},
  "geometry": {"coordinates":[-77.00823800000001,38.764914],"type":"Point"}
}