{
  "type": "Feature",
  "properties": {
    "iso:country":"US",
    "sg:address":"5112 Westland Blvd",
    "sg:city":"Halethorpe",
    "sg:classifiers":[
        {
            "category":"Bakery",
            "type":"Food & Drink"
        }
    ],
    "sg:phone":"+1 443 838 3713",
    "sg:postcode":"21227",
    "sg:province":"MD",
    "sg:tags":[
        "cake",
        "pastry",
        "wedding"
    ],
    "wof:name":"Great Cakes For You",
    "wof:placetype":"venue"
},
  "geometry": {"coordinates":[-76.699883,39.256359],"type":"Point"}
}