{
  "type": "Feature",
  "properties": {
    "addr:full":"102 Edgerton Rd Baltimore MD 21286",
    "addr:housenumber":"102",
    "addr:postcode":"21286",
    "addr:street":"Edgerton Rd",
    "iso:country":"US",
    "sg:address":"102 Edgerton Rd",
    "sg:city":"Baltimore",
    "sg:classifiers":[
        {
            "category":"Organizations",
            "subcategory":"Membership Organization",
            "type":"Services"
        }
    ],
    "sg:phone":"+1 410 321 8252",
    "sg:postcode":"21286",
    "sg:province":"MD",
    "wof:name":"Oriole Advocates Inc",
    "wof:placetype":"venue"
},
  "geometry": {"coordinates":[-76.581841,39.398637],"type":"Point"}
}