{
  "type": "Feature",
  "properties": {
    "addr:full":"321 Burnside Ct Joppa MD 21085",
    "addr:housenumber":"321",
    "addr:postcode":"21085",
    "addr:street":"Burnside Ct",
    "iso:country":"US",
    "sg:address":"321 Burnside Ct",
    "sg:city":"Joppa",
    "sg:classifiers":[
        {
            "category":"Building & Trades",
            "subcategory":"Construction",
            "type":"Services"
        }
    ],
    "sg:phone":"+1 410 538 8378",
    "sg:postcode":"21085",
    "sg:province":"MD",
    "sg:tags":[
        "contractor"
    ],
    "wof:name":"Rocks Drywall",
    "wof:placetype":"venue"
},
  "geometry": {"coordinates":[-76.339414,39.398171],"type":"Point"}
}