{
  "type": "Feature",
  "properties": {
    "iso:country":"US",
    "sg:address":"8631 Cherry Ln",
    "sg:city":"Laurel",
    "sg:classifiers":[
        {
            "category":"Personal",
            "subcategory":"Beauty Salon",
            "type":"Services"
        }
    ],
    "sg:phone":"+1 301 317 9333",
    "sg:postcode":"20707",
    "sg:province":"MD",
    "wof:name":"Essential Essence Inc",
    "wof:placetype":"venue"
},
  "geometry": {"coordinates":[-76.85609700000001,39.090761],"type":"Point"}
}