{
  "type": "Feature",
  "properties": {
    "iso:country":"US",
    "sg:address":"6409 Frederick Rd",
    "sg:city":"Catonsville",
    "sg:classifiers":[
        {
            "category":"Personal",
            "subcategory":"Beauty Salon",
            "type":"Services"
        }
    ],
    "sg:phone":"+1 410 455 0454",
    "sg:postcode":"21228",
    "sg:province":"MD",
    "sg:tags":[
        "nail",
        "manicuring"
    ],
    "wof:name":"Ann Nail",
    "wof:placetype":"venue"
},
  "geometry": {"coordinates":[-76.717258,39.275348],"type":"Point"}
}