{
  "type": "Feature",
  "properties": {
    "iso:country":"US",
    "sg:address":"1720 E Joppa Rd",
    "sg:city":"Parkville",
    "sg:classifiers":[
        {
            "category":"Food & Beverages",
            "subcategory":"Meat & Fish",
            "type":"Retail Goods"
        }
    ],
    "sg:phone":"+1 410 665 3095",
    "sg:postcode":"21234",
    "sg:province":"MD",
    "sg:tags":[
        "seafood"
    ],
    "wof:name":"Joppa Seafood Market",
    "wof:placetype":"venue"
},
  "geometry": {"coordinates":[-76.560816,39.398168],"type":"Point"}
}