{
  "type": "Feature",
  "properties": {
    "iso:country":"US",
    "sg:address":"103 Stockton St",
    "sg:city":"Elkton",
    "sg:classifiers":[
        {
            "category":"Retail",
            "subcategory":"Funeral Services",
            "type":"Services"
        }
    ],
    "sg:phone":"+1 410 398 3122",
    "sg:postcode":"21921",
    "sg:province":"MD",
    "sg:tags":[
        "director"
    ],
    "wof:name":"Hicks Home For Funerals PA",
    "wof:placetype":"venue"
},
  "geometry": {"coordinates":[-75.828817,39.611756],"type":"Point"}
}