{
  "type": "Feature",
  "properties": {
    "addr:full":"6450 America Blvd. Hyattsville MD 20782",
    "addr:housenumber":"6450",
    "addr:postcode":"20782",
    "addr:street":"America Blvd.",
    "iso:country":"US",
    "sg:address":"6450 America Blvd.",
    "sg:city":"Hyattsville",
    "sg:classifiers":[
        {
            "category":"Shopping",
            "subcategory":"Department Store",
            "type":"Retail Goods"
        },
        {
            "category":"Building & Trades",
            "subcategory":"Cleaning & Sanitation",
            "type":"Services"
        },
        {
            "category":"Home & Garden",
            "subcategory":"Hardware",
            "type":"Retail Goods"
        },
        {
            "category":"Retail",
            "subcategory":"Laundry & Dry Cleaning",
            "type":"Services"
        }
    ],
    "sg:phone":"+1 301 699 7560",
    "sg:postcode":"20782",
    "sg:province":"MD",
    "sg:tags":[
        "cleaner",
        "supply",
        "contractor",
        "equipment",
        "cleaning-industrial",
        "janitor"
    ],
    "wof:name":"New Town Cleaners",
    "wof:placetype":"venue"
},
  "geometry": {"coordinates":[-76.952198,38.967524],"type":"Point"}
}