{
  "type": "Feature",
  "properties": {
    "addr:full":"112 Palmetto Dr Edgewood MD 21040",
    "addr:housenumber":"112",
    "addr:postcode":"21040",
    "addr:street":"Palmetto Dr",
    "iso:country":"US",
    "sg:address":"112 Palmetto Dr",
    "sg:city":"Edgewood",
    "sg:classifiers":[
        {
            "category":"Recreation",
            "type":"Entertainment"
        }
    ],
    "sg:phone":"+1 410 676 6592",
    "sg:postcode":"21040",
    "sg:province":"MD",
    "wof:name":"Horary Astrology",
    "wof:placetype":"venue"
},
  "geometry": {"coordinates":[-76.269265,39.428411],"type":"Point"}
}