{
  "type": "Feature",
  "properties": {
    "iso:country":"US",
    "sg:address":"11428 Rockville Pike",
    "sg:city":"Rockville",
    "sg:classifiers":[
        {
            "category":"Professional",
            "subcategory":"Employment Agencies",
            "type":"Services"
        }
    ],
    "sg:phone":"+1 301 984 8588",
    "sg:postcode":"20852",
    "sg:province":"MD",
    "sg:tags":[
        "help",
        "contractor"
    ],
    "wof:name":"Lawrence Associates Inc",
    "wof:placetype":"venue"
},
  "geometry": {"coordinates":[-77.110743,39.042053],"type":"Point"}
}