{
  "type": "Feature",
  "properties": {
    "addr:full":"1618 N Bend Rd Jarrettsville MD 21084",
    "addr:housenumber":"1618",
    "addr:postcode":"21084",
    "addr:street":"N Bend Rd",
    "iso:country":"US",
    "sg:address":"1618 N Bend Rd",
    "sg:city":"Jarrettsville",
    "sg:classifiers":[
        {
            "category":"Building & Trades",
            "subcategory":"Electrical",
            "type":"Services"
        }
    ],
    "sg:phone":"+1 410 692 5549",
    "sg:postcode":"21084",
    "sg:province":"MD",
    "sg:tags":[
        "electrician"
    ],
    "wof:name":"Liberty Electric Co Inc",
    "wof:placetype":"venue"
},
  "geometry": {"coordinates":[-76.46518399999999,39.625787],"type":"Point"}
}