{
  "type": "Feature",
  "properties": {
    "iso:country":"US",
    "sg:address":"7403 Liberty Rd",
    "sg:city":"Gwynn Oak",
    "sg:classifiers":[
        {
            "category":"Health Services",
            "subcategory":"Health Practitioner",
            "type":"Services"
        }
    ],
    "sg:phone":"+1 410 944 3337",
    "sg:postcode":"21207",
    "sg:province":"MD",
    "sg:tags":[
        "therapist",
        "physical"
    ],
    "wof:name":"Team CJB Med & Physical",
    "wof:placetype":"venue"
},
  "geometry": {"coordinates":[-76.74061,39.347335],"type":"Point"}
}