{
  "type": "Feature",
  "properties": {
    "addr:full":"18520 Office Park Dr Montgomery Vlg MD 20886",
    "addr:housenumber":"18520",
    "addr:postcode":"20886",
    "addr:street":"Office Park Dr",
    "iso:country":"US",
    "sg:address":"18520 Office Park Dr",
    "sg:city":"Montgomery Vlg",
    "sg:classifiers":[
        {
            "category":"Freight",
            "type":"Transportation"
        }
    ],
    "sg:phone":"+1 301 855 5339",
    "sg:postcode":"20886",
    "sg:province":"MD",
    "sg:tags":[
        "delivery"
    ],
    "wof:name":"Unishippers Association",
    "wof:placetype":"venue"
},
  "geometry": {"coordinates":[-77.202862,39.161874],"type":"Point"}
}