{
  "type": "Feature",
  "properties": {
    "addr:full":"14003 Gray Birch Way Rockville MD 20850",
    "addr:housenumber":"14003",
    "addr:postcode":"20850",
    "addr:street":"Gray Birch Way",
    "iso:country":"US",
    "sg:address":"14003 Gray Birch Way",
    "sg:city":"Rockville",
    "sg:classifiers":[
        {
            "category":"Communications",
            "type":"Services"
        }
    ],
    "sg:phone":"+1 301 315 0958",
    "sg:postcode":"20850",
    "sg:province":"MD",
    "sg:tags":[
        "consultant",
        "telecommunication"
    ],
    "wof:name":"Navitas Wireless",
    "wof:placetype":"venue"
},
  "geometry": {"coordinates":[-77.21280299999999,39.083152],"type":"Point"}
}