{
  "type": "Feature",
  "properties": {
    "iso:country":"US",
    "sg:address":"10331 Watkins Mill Dr",
    "sg:city":"Montgomery Village",
    "sg:classifiers":[
        {
            "category":"Professional",
            "type":"Services"
        }
    ],
    "sg:phone":"+1 301 840 2248",
    "sg:postcode":"20886",
    "sg:province":"MD",
    "sg:tags":[
        "resume",
        "writing"
    ],
    "wof:name":"Sam Blate Associates LLC",
    "wof:placetype":"venue"
},
  "geometry": {"coordinates":[-77.213632,39.168479],"type":"Point"}
}