{
  "type": "Feature",
  "properties": {
    "iso:country":"US",
    "sg:address":"9415 Philadelphia Rd",
    "sg:city":"Rosedale",
    "sg:classifiers":[
        {
            "category":"Bakery",
            "type":"Food & Drink"
        }
    ],
    "sg:phone":"+1 410 238 2253",
    "sg:postcode":"21237",
    "sg:province":"MD",
    "sg:website":"www.yiayiasbakery.com/",
    "wof:name":"Yia Yia's Bakery",
    "wof:placetype":"venue"
},
  "geometry": {"coordinates":[-76.463739,39.353218],"type":"Point"}
}