{
  "type": "Feature",
  "properties": {
    "addr:full":"2001 Liberty Heights Ave Baltimore MD 21217",
    "addr:housenumber":"2001",
    "addr:postcode":"21217",
    "addr:street":"Liberty Heights Ave",
    "iso:country":"US",
    "sg:address":"2001 Liberty Heights Ave",
    "sg:city":"Baltimore",
    "sg:classifiers":[
        {
            "category":"Organizations",
            "subcategory":"Religious Organization",
            "type":"Services"
        }
    ],
    "sg:phone":"+1 410 523 4375",
    "sg:postcode":"21217",
    "sg:province":"MD",
    "sg:tags":[
        "synagogue"
    ],
    "wof:name":"Shaarei Tfiloh Congregation",
    "wof:placetype":"venue"
},
  "geometry": {"coordinates":[-76.65065,39.32],"type":"Point"}
}