{
  "type": "Feature",
  "properties": {
    "iso:country":"US",
    "sg:address":"1374 W North Ave",
    "sg:city":"Baltimore",
    "sg:classifiers":[
        {
            "category":"Health Services",
            "subcategory":"Clinic",
            "type":"Services"
        }
    ],
    "sg:phone":"+1 410 396 0353",
    "sg:postcode":"21217",
    "sg:province":"MD",
    "sg:tags":[
        "welfare"
    ],
    "wof:name":"Baltimore City Health Department",
    "wof:placetype":"venue"
},
  "geometry": {"coordinates":[-76.64067,39.310134],"type":"Point"}
}