{
  "type": "Feature",
  "properties": {
    "addr:full":"10706 Lester St Silver Spring MD 20902",
    "addr:housenumber":"10706",
    "addr:postcode":"20902",
    "addr:street":"Lester St",
    "iso:country":"US",
    "sg:address":"10706 Lester St",
    "sg:city":"Silver Spring",
    "sg:classifiers":[
        {
            "category":"Building & Trades",
            "subcategory":"Construction",
            "type":"Services"
        }
    ],
    "sg:phone":"+1 301 649 4842",
    "sg:postcode":"20902",
    "sg:province":"MD",
    "sg:tags":[
        "hanging",
        "contractor"
    ],
    "wof:name":"Walters Pro Painting",
    "wof:placetype":"venue"
},
  "geometry": {"coordinates":[-77.03198999999999,39.03183],"type":"Point"}
}