{
  "type": "Feature",
  "properties": {
    "addr:full":"8620 Watershed Ct Gaithersburg MD 20877",
    "addr:housenumber":"8620",
    "addr:postcode":"20877",
    "addr:street":"Watershed Ct",
    "iso:country":"US",
    "sg:address":"8620 Watershed Ct",
    "sg:city":"Gaithersburg",
    "sg:classifiers":[
        {
            "category":"Restaurant",
            "type":"Food & Drink"
        }
    ],
    "sg:phone":"+1 301 762 3210",
    "sg:postcode":"20877",
    "sg:province":"MD",
    "wof:name":"Jerry's Subs & Pizza",
    "wof:placetype":"venue"
},
  "geometry": {"coordinates":[-77.17702,39.154898],"type":"Point"}
}