{
  "type": "Feature",
  "properties": {
    "addr:full":"2300 Fairland Rd Silver Spring MD 20904",
    "addr:housenumber":"2300",
    "addr:postcode":"20904",
    "addr:street":"Fairland Rd",
    "iso:country":"US",
    "sg:address":"2300 Fairland Rd",
    "sg:city":"Silver Spring",
    "sg:classifiers":[
        {
            "category":"Professional",
            "subcategory":"Printing & Photocopies",
            "type":"Services"
        }
    ],
    "sg:phone":"+1 301 384 6703",
    "sg:postcode":"20904",
    "sg:province":"MD",
    "wof:name":"Rani Reproduction Systems",
    "wof:placetype":"venue"
},
  "geometry": {"coordinates":[-76.963053,39.077996],"type":"Point"}
}