{
  "type": "Feature",
  "properties": {
    "iso:country":"US",
    "sg:address":"832 S Bond St 300",
    "sg:city":"Baltimore",
    "sg:classifiers":[
        {
            "category":"Home & Garden",
            "subcategory":"Carpets & Floor Coverings",
            "type":"Retail Goods"
        }
    ],
    "sg:phone":"+1 410 558 1300",
    "sg:postcode":"21231",
    "sg:province":"MD",
    "sg:tags":[
        "equipment",
        "rugs-layers",
        "supply"
    ],
    "wof:name":"Modular Concepts Inc",
    "wof:placetype":"venue"
},
  "geometry": {"coordinates":[-76.59504699999999,39.281442],"type":"Point"}
}