{
  "type": "Feature",
  "properties": {
    "addr:full":"6300 Kenilworth Ave Riverdale MD 20737",
    "addr:housenumber":"6300",
    "addr:postcode":"20737",
    "addr:street":"Kenilworth Ave",
    "iso:country":"US",
    "sg:address":"6300 Kenilworth Ave",
    "sg:city":"Riverdale",
    "sg:classifiers":[
        {
            "category":"Insurance",
            "subcategory":"Insurance Agent",
            "type":"Services"
        }
    ],
    "sg:phone":"+1 301 927 2010",
    "sg:postcode":"20737",
    "sg:province":"MD",
    "wof:name":"Insurance Link Agency",
    "wof:placetype":"venue"
},
  "geometry": {"coordinates":[-76.918966,38.965877],"type":"Point"}
}