{
  "type": "Feature",
  "properties": {
    "addr:full":"401 Headquarters Dr Ste 108 Millersville MD 21108",
    "addr:housenumber":"401",
    "addr:postcode":"21108",
    "addr:street":"Headquarters Dr Ste 108",
    "iso:country":"US",
    "sg:address":"401 Headquarters Dr Ste 108",
    "sg:city":"Millersville",
    "sg:classifiers":[
        {
            "category":"Donuts",
            "subcategory":"None",
            "type":"Food & Drink"
        }
    ],
    "sg:phone":"+1 410 987 6559",
    "sg:postcode":"21108",
    "sg:province":"MD",
    "sg:tags":[
        "shop"
    ],
    "wof:name":"Quad Donuts & Deli Carry",
    "wof:placetype":"venue"
},
  "geometry": {"coordinates":[-76.626938,39.100712],"type":"Point"}
}