{
  "type": "Feature",
  "properties": {
    "iso:country":"US",
    "sg:address":"6222 Dahlonega Rd",
    "sg:city":"Bethesda",
    "sg:classifiers":[
        {
            "category":"Professional",
            "subcategory":"Lawyer & Legal Services",
            "type":"Services"
        }
    ],
    "sg:phone":"+1 301 320 2152",
    "sg:postcode":"20816",
    "sg:province":"MD",
    "wof:name":"Platt Robert Lwyr",
    "wof:placetype":"venue"
},
  "geometry": {"coordinates":[-77.12690000000001,38.966],"type":"Point"}
}