{
  "type": "Feature",
  "properties": {
    "addr:full":"4618 Indian Head Hwy Indian Head MD 20640",
    "addr:housenumber":"4618",
    "addr:postcode":"20640",
    "addr:street":"Indian Head Hwy",
    "iso:country":"US",
    "sg:address":"4618 Indian Head Hwy",
    "sg:city":"Indian Head",
    "sg:classifiers":[
        {
            "category":"Retail",
            "subcategory":"Veterinary Services",
            "type":"Services"
        }
    ],
    "sg:phone":"+1 301 743 5411",
    "sg:postcode":"20640",
    "sg:province":"MD",
    "sg:tags":[
        "veterinarian"
    ],
    "wof:name":"Glymont Veterinary Clinic",
    "wof:placetype":"venue"
},
  "geometry": {"coordinates":[-77.14730900000001,38.60139],"type":"Point"}
}