{
  "type": "Feature",
  "properties": {
    "addr:full":"3545 Sixes Rd Prince Frederick MD 20678",
    "addr:housenumber":"3545",
    "addr:postcode":"20678",
    "addr:street":"Sixes Rd",
    "iso:country":"US",
    "sg:address":"3545 Sixes Rd",
    "sg:city":"Prince Frederick",
    "sg:classifiers":[
        {
            "category":"Building & Trades",
            "subcategory":"Construction",
            "type":"Services"
        }
    ],
    "sg:phone":"+1 410 535 9299",
    "sg:postcode":"20678",
    "sg:province":"MD",
    "sg:tags":[
        "carpentry",
        "contractor"
    ],
    "wof:name":"Howes Carpentry",
    "wof:placetype":"venue"
},
  "geometry": {"coordinates":[-76.599763,38.494885],"type":"Point"}
}