{
  "type": "Feature",
  "properties": {
    "addr:full":"8502 Buckhannon Dr Potomac MD 20854",
    "addr:housenumber":"8502",
    "addr:postcode":"20854",
    "addr:street":"Buckhannon Dr",
    "iso:country":"US",
    "sg:address":"8502 Buckhannon Dr",
    "sg:city":"Potomac",
    "sg:classifiers":[
        {
            "category":"Building & Trades",
            "subcategory":"Construction",
            "type":"Services"
        }
    ],
    "sg:phone":"+1 301 983 9777",
    "sg:postcode":"20854",
    "sg:province":"MD",
    "sg:tags":[
        "foundation",
        "contractor"
    ],
    "wof:name":"Sassi",
    "wof:placetype":"venue"
},
  "geometry": {"coordinates":[-77.175579,39.043593],"type":"Point"}
}