{
  "type": "Feature",
  "properties": {
    "addr:full":"1343 Old Water Oak Point Rd Pasadena MD 21122",
    "addr:housenumber":"1343",
    "addr:postcode":"21122",
    "addr:street":"Old Water Oak Point Rd",
    "iso:country":"US",
    "sg:address":"1343 Old Water Oak Point Rd",
    "sg:city":"Pasadena",
    "sg:classifiers":[
        {
            "category":"Recreation",
            "subcategory":"Marina",
            "type":"Entertainment"
        },
        {
            "category":"Autos & Motor Vehicles",
            "subcategory":"Boat Sales",
            "type":"Retail Goods"
        }
    ],
    "sg:phone":"+1 410 255 1007",
    "sg:postcode":"21122",
    "sg:province":"MD",
    "sg:tags":[
        "repair",
        "maintenance"
    ],
    "wof:name":"Anderson Marine Services",
    "wof:placetype":"venue"
},
  "geometry": {"coordinates":[-76.509773,39.145618],"type":"Point"}
}