{
  "type": "Feature",
  "properties": {
    "addr:full":"12749 Still Pond Rd Still Pond MD 21667",
    "addr:housenumber":"12749",
    "addr:postcode":"21667",
    "addr:street":"Still Pond Rd",
    "iso:country":"US",
    "sg:address":"12749 Still Pond Rd",
    "sg:city":"Still Pond",
    "sg:classifiers":[
        {
            "category":"Government",
            "subcategory":"Post Office",
            "type":"Public Place"
        }
    ],
    "sg:phone":"+1 410 348 5290",
    "sg:postcode":"21667",
    "sg:province":"MD",
    "wof:name":"US Post Office",
    "wof:placetype":"venue"
},
  "geometry": {"coordinates":[-76.04402399999999,39.325244],"type":"Point"}
}