{
  "type": "Feature",
  "properties": {
    "addr:full":"9800 Coastal Hwy Ocean City MD 21842",
    "addr:housenumber":"9800",
    "addr:postcode":"21842",
    "addr:street":"Coastal Hwy",
    "iso:country":"US",
    "sg:address":"9800 Coastal Hwy",
    "sg:city":"Ocean City",
    "sg:classifiers":[
        {
            "category":"Real Estate",
            "subcategory":"Real Estate Operator",
            "type":"Services"
        }
    ],
    "sg:phone":"+1 410 723 3300",
    "sg:postcode":"21842",
    "sg:province":"MD",
    "sg:tags":[
        "condominium"
    ],
    "wof:name":"Plaza Condominiums",
    "wof:placetype":"venue"
},
  "geometry": {"coordinates":[-75.058046,38.411649],"type":"Point"}
}