{
  "type": "Feature",
  "properties": {
    "iso:country":"US",
    "sg:address":"11813 Park Waldorf Ln",
    "sg:city":"Waldorf",
    "sg:classifiers":[
        {
            "category":"Health Services",
            "subcategory":"Chiropractor",
            "type":"Services"
        }
    ],
    "sg:phone":"+1 301 645 5390",
    "sg:postcode":"20601",
    "sg:province":"MD",
    "sg:website":"www.endpainnow.net",
    "wof:name":"Total Health Chiropractic",
    "wof:placetype":"venue"
},
  "geometry": {"coordinates":[-76.900871,38.635322],"type":"Point"}
}