{
  "type": "Feature",
  "properties": {
    "addr:full":"9090 Ridgefield Dr Frederick MD 21701",
    "addr:housenumber":"9090",
    "addr:postcode":"21701",
    "addr:street":"Ridgefield Dr",
    "iso:country":"US",
    "sg:address":"9090 Ridgefield Dr",
    "sg:city":"Frederick",
    "sg:classifiers":[
        {
            "category":"Real Estate",
            "subcategory":"Real Estate Operator",
            "type":"Services"
        }
    ],
    "sg:phone":"+1 301 620 0782",
    "sg:postcode":"21701",
    "sg:province":"MD",
    "sg:tags":[
        "building",
        "nonresidential"
    ],
    "wof:name":"Property Management People",
    "wof:placetype":"venue"
},
  "geometry": {"coordinates":[-77.34787,39.399529],"type":"Point"}
}