{
  "type": "Feature",
  "properties": {
    "iso:country":"US",
    "sg:address":"1619 Portland Ln",
    "sg:city":"Bowie",
    "sg:classifiers":[
        {
            "category":"Professional",
            "subcategory":"Management & Consulting",
            "type":"Services"
        }
    ],
    "sg:phone":"+1 301 249 6017",
    "sg:postcode":"20716",
    "sg:province":"MD",
    "sg:tags":[
        "business"
    ],
    "wof:name":"Le Branche & Associates Inc",
    "wof:placetype":"venue"
},
  "geometry": {"coordinates":[-76.72310299999999,38.913254],"type":"Point"}
}