{
  "type": "Feature",
  "properties": {
    "addr:full":"6426 Dry Barley Ln Columbia MD 21045",
    "addr:housenumber":"6426",
    "addr:postcode":"21045",
    "addr:street":"Dry Barley Ln",
    "iso:country":"US",
    "sg:address":"6426 Dry Barley Ln",
    "sg:city":"Columbia",
    "sg:classifiers":[
        {
            "category":"Professional",
            "subcategory":"Art Services",
            "type":"Services"
        },
        {
            "category":"Professional",
            "subcategory":"Business Services",
            "type":"Services"
        }
    ],
    "sg:phone":"+1 410 799 9326",
    "sg:postcode":"21045",
    "sg:province":"MD",
    "sg:tags":[
        "development",
        "product",
        "graphic",
        "designers-industrial",
        "marketing",
        "commercial",
        "designer",
        "design"
    ],
    "wof:name":"Nelson Brent B",
    "wof:placetype":"venue"
},
  "geometry": {"coordinates":[-76.79924699999999,39.192356],"type":"Point"}
}