{
  "type": "Feature",
  "properties": {
    "addr:full":"951 BEARDS HILL RD ABERDEEN MD 21001",
    "addr:housenumber":"951",
    "addr:postcode":"21001",
    "addr:street":"Beards Hill Rd",
    "iso:country":"US",
    "sg:address":"951 BEARDS HILL RD",
    "sg:city":"ABERDEEN",
    "sg:classifiers":[
        {
            "category":"Home & Garden",
            "subcategory":"Household Appliances",
            "type":"Retail Goods"
        },
        {
            "category":"Communications",
            "subcategory":"Radio Station",
            "type":"Services"
        },
        {
            "category":"Shopping",
            "subcategory":"Computers & Home Electronics",
            "type":"Retail Goods"
        },
        {
            "category":"Home & Garden",
            "subcategory":"Furniture",
            "type":"Retail Goods"
        }
    ],
    "sg:phone":"+1 410 273 7290",
    "sg:postcode":"21001",
    "sg:province":"MD",
    "sg:tags":[
        "renting",
        "television",
        "leasing",
        "radio-renting",
        "equipment",
        "rental"
    ],
    "sg:website":"http://www.rentacenter.com/",
    "wof:name":"Rent-A-Center",
    "wof:placetype":"venue"
},
  "geometry": {"coordinates":[-76.183646,39.524786],"type":"Point"}
}