{
  "type": "Feature",
  "properties": {
    "iso:country":"US",
    "sg:address":"3001 Elliott St",
    "sg:city":"Baltimore",
    "sg:classifiers":[
        {
            "category":"Professional",
            "subcategory":"Lawyer & Legal Services",
            "type":"Services"
        }
    ],
    "sg:phone":"+1 410 732 1315",
    "sg:postcode":"21224",
    "sg:province":"MD",
    "sg:website":"www.schultebooth.com",
    "wof:name":"Schulte Booth PC",
    "wof:placetype":"venue"
},
  "geometry": {"coordinates":[-76.573893,39.279063],"type":"Point"}
}