{
  "type": "Feature",
  "properties": {
    "iso:country":"US",
    "sg:address":"113 E Diamond Ave",
    "sg:city":"Gaithersburg",
    "sg:classifiers":[
        {
            "category":"Food & Beverages",
            "subcategory":"Groceries & Convenience Stores",
            "type":"Retail Goods"
        }
    ],
    "sg:phone":"+1 301 926 8647",
    "sg:postcode":"20877",
    "sg:province":"MD",
    "sg:tags":[
        "grocer"
    ],
    "wof:name":"Tienda LA Chiquita",
    "wof:placetype":"venue"
},
  "geometry": {"coordinates":[-77.19488,39.141952],"type":"Point"}
}