{
  "type": "Feature",
  "properties": {
    "addr:full":"115 Hastings Ln Pasadena MD 21122",
    "addr:housenumber":"115",
    "addr:postcode":"21122",
    "addr:street":"Hastings Ln",
    "iso:country":"US",
    "sg:address":"115 Hastings Ln",
    "sg:city":"Pasadena",
    "sg:classifiers":[
        {
            "category":"Building & Trades",
            "subcategory":"Construction",
            "type":"Services"
        }
    ],
    "sg:phone":"+1 410 544 4405",
    "sg:postcode":"21122",
    "sg:province":"MD",
    "sg:tags":[
        "downspouts",
        "gutter"
    ],
    "wof:name":"Zimmerman Seamless Gutters Inc",
    "wof:placetype":"venue"
},
  "geometry": {"coordinates":[-76.57343400000001,39.113714],"type":"Point"}
}