{
  "type": "Feature",
  "properties": {
    "iso:country":"US",
    "sg:address":"9601 Baltimore Ave",
    "sg:city":"College Park",
    "sg:classifiers":[
        {
            "category":"Professional",
            "subcategory":"Accounting & Tax Preparation",
            "type":"Services"
        }
    ],
    "sg:phone":"+1 301 313 9113",
    "sg:postcode":"20740",
    "sg:province":"MD",
    "sg:tags":[
        "accountant"
    ],
    "wof:name":"Wallace & Assoc",
    "wof:placetype":"venue"
},
  "geometry": {"coordinates":[-76.928253,39.012008],"type":"Point"}
}