{
  "type": "Feature",
  "properties": {
    "addr:full":"2236 Old Fort Schoolhouse Rd Hampstead MD 21074",
    "addr:housenumber":"2236",
    "addr:postcode":"21074",
    "addr:street":"Old Fort Schoolhouse Rd",
    "iso:country":"US",
    "sg:address":"2236 Old Fort Schoolhouse Rd",
    "sg:city":"Hampstead",
    "sg:classifiers":[
        {
            "category":"Organizations",
            "subcategory":"Religious Organization",
            "type":"Services"
        }
    ],
    "sg:phone":"+1 410 374 6112",
    "sg:postcode":"21074",
    "sg:province":"MD",
    "sg:tags":[
        "church"
    ],
    "wof:name":"Kirkridge Associate-Presby Chr",
    "wof:placetype":"venue"
},
  "geometry": {"coordinates":[-76.917244,39.641883],"type":"Point"}
}