{
  "type": "Feature",
  "properties": {
    "iso:country":"US",
    "sg:address":"5513 Twin Knolls Rd",
    "sg:city":"Columbia",
    "sg:classifiers":[
        {
            "category":"Professional",
            "subcategory":"Computer Services",
            "type":"Services"
        }
    ],
    "sg:phone":"+1 443 367 0030",
    "sg:postcode":"21045",
    "sg:province":"MD",
    "sg:tags":[
        "internet"
    ],
    "wof:name":"Global Tranquility Online Co",
    "wof:placetype":"venue"
},
  "geometry": {"coordinates":[-76.840419,39.219836],"type":"Point"}
}