{
  "type": "Feature",
  "properties": {
    "addr:full":"4000 Annapolis Rd Halethorpe MD 21227",
    "addr:housenumber":"4000",
    "addr:postcode":"21227",
    "addr:street":"Annapolis Rd",
    "iso:country":"US",
    "sg:address":"4000 Annapolis Rd",
    "sg:city":"Halethorpe",
    "sg:classifiers":[
        {
            "category":"Shopping",
            "type":"Retail Goods"
        }
    ],
    "sg:phone":"+1 410 243 1959",
    "sg:postcode":"21227",
    "sg:province":"MD",
    "sg:tags":[
        "hearing",
        "equipment",
        "supply",
        "impaired"
    ],
    "wof:name":"Audiphone Co",
    "wof:placetype":"venue"
},
  "geometry": {"coordinates":[-76.641262,39.240038],"type":"Point"}
}