{
  "type": "Feature",
  "properties": {
    "addr:full":"5398 Queens Chapel Rd Hyattsville MD 20782",
    "addr:housenumber":"5398",
    "addr:postcode":"20782",
    "addr:street":"Queens Chapel Rd",
    "iso:country":"US",
    "sg:address":"5398 Queens Chapel Rd",
    "sg:city":"Hyattsville",
    "sg:classifiers":[
        {
            "category":"Professional",
            "subcategory":"Engineering",
            "type":"Services"
        },
        {
            "category":"Home & Garden",
            "subcategory":"Building Materials",
            "type":"Retail Goods"
        }
    ],
    "sg:phone":"+1 301 559 2079",
    "sg:postcode":"20782",
    "sg:province":"MD",
    "sg:tags":[
        "insulation",
        "consultant",
        "product",
        "conservation",
        "energy"
    ],
    "wof:name":"Potomac Energy Holdings",
    "wof:placetype":"venue"
},
  "geometry": {"coordinates":[-76.962723,38.95565],"type":"Point"}
}