{
  "type": "Feature",
  "properties": {
    "addr:full":"2624 Lord Baltimore Dr Baltimore MD 21244",
    "addr:housenumber":"2624",
    "addr:postcode":"21244",
    "addr:street":"Lord Baltimore Dr",
    "iso:country":"US",
    "sg:address":"2624 Lord Baltimore Dr",
    "sg:city":"Baltimore",
    "sg:classifiers":[
        {
            "category":"Retail",
            "subcategory":"Photofinishing",
            "type":"Services"
        }
    ],
    "sg:phone":"+1 410 944 5517",
    "sg:postcode":"21244",
    "sg:province":"MD",
    "sg:tags":[
        "photo",
        "finishing"
    ],
    "wof:name":"Eclipse Photographic Inc",
    "wof:placetype":"venue"
},
  "geometry": {"coordinates":[-76.751441,39.328233],"type":"Point"}
}