{
  "type": "Feature",
  "properties": {
    "iso:country":"US",
    "sg:address":"12300 Rosslare Ridge Rd Unit 108",
    "sg:city":"Lutherville Timonium",
    "sg:classifiers":[
        {
            "category":"Real Estate",
            "subcategory":"Real Estate Operator",
            "type":"Services"
        }
    ],
    "sg:phone":"+1 410 252 3797",
    "sg:postcode":"21093",
    "sg:province":"MD",
    "sg:tags":[
        "apartment"
    ],
    "wof:name":"Mays Chapel North Condominiums",
    "wof:placetype":"venue"
},
  "geometry": {"coordinates":[-76.6651,39.461399],"type":"Point"}
}