{
  "type": "Feature",
  "properties": {
    "iso:country":"US",
    "sg:address":"3100 Granite Rd",
    "sg:city":"Woodstock",
    "sg:classifiers":[
        {
            "category":"Shopping",
            "subcategory":"Clothing, Apparel, & Fashions",
            "type":"Retail Goods"
        }
    ],
    "sg:phone":"+1 410 698 5793",
    "sg:postcode":"21163",
    "sg:province":"MD",
    "sg:tags":[
        "clothing",
        "boys'"
    ],
    "wof:name":"From Boys Ii Men Services",
    "wof:placetype":"venue"
},
  "geometry": {"coordinates":[-76.837588,39.354115],"type":"Point"}
}