{
  "type": "Feature",
  "properties": {
    "iso:country":"US",
    "sg:address":"29 Maryland Ave",
    "sg:city":"Rockville",
    "sg:classifiers":[
        {
            "category":"Restaurant",
            "type":"Food & Drink"
        }
    ],
    "sg:menulink":"http://www.allmenus.com/md/rockville/282991-thai-pavilion-restaurant/menu/",
    "sg:phone":"+1 301 545 0244",
    "sg:postcode":"20850",
    "sg:province":"MD",
    "sg:tags":[
        "thai",
        "asian"
    ],
    "wof:name":"Thai Pavilion Restaurant",
    "wof:placetype":"venue"
},
  "geometry": {"coordinates":[-77.15095100000001,39.085641],"type":"Point"}
}