{
  "type": "Feature",
  "properties": {
    "addr:full":"12 Juneway Ln Berlin MD 21811",
    "addr:housenumber":"12",
    "addr:postcode":"21811",
    "addr:street":"Juneway Ln",
    "iso:country":"US",
    "sg:address":"12 Juneway Ln",
    "sg:city":"Berlin",
    "sg:classifiers":[
        {
            "category":"Building & Trades",
            "subcategory":"Construction",
            "type":"Services"
        }
    ],
    "sg:phone":"+1 410 251 2167",
    "sg:postcode":"21811",
    "sg:province":"MD",
    "sg:tags":[
        "carpentry",
        "contractor"
    ],
    "wof:name":"C and D Poseidon",
    "wof:placetype":"venue"
},
  "geometry": {"coordinates":[-75.136584,38.380828],"type":"Point"}
}