{
  "type": "Feature",
  "properties": {
    "addr:full":"2507 Nicol Cir Bowie MD 20721",
    "addr:housenumber":"2507",
    "addr:postcode":"20721",
    "addr:street":"Nicol Cir",
    "iso:country":"US",
    "sg:address":"2507 Nicol Cir",
    "sg:city":"Bowie",
    "sg:classifiers":[
        {
            "category":"Health Services",
            "subcategory":"Clinic",
            "type":"Services"
        }
    ],
    "sg:phone":"+1 301 577 1490",
    "sg:postcode":"20721",
    "sg:province":"MD",
    "sg:tags":[
        "home"
    ],
    "wof:name":"TLC Home Care Svc Inc",
    "wof:placetype":"venue"
},
  "geometry": {"coordinates":[-76.830715,38.923292],"type":"Point"}
}