{
  "type": "Feature",
  "properties": {
    "addr:full":"3325 Lander Rd Jefferson MD 21755",
    "addr:housenumber":"3325",
    "addr:postcode":"21755",
    "addr:street":"Lander Rd",
    "iso:country":"US",
    "sg:address":"3325 Lander Rd",
    "sg:city":"Jefferson",
    "sg:classifiers":[
        {
            "category":"Building & Trades",
            "subcategory":"Cleaning & Sanitation",
            "type":"Services"
        }
    ],
    "sg:phone":"+1 301 834 7586",
    "sg:postcode":"21755",
    "sg:province":"MD",
    "sg:tags":[
        "janitor"
    ],
    "wof:name":"L & R Cleaning Systems",
    "wof:placetype":"venue"
},
  "geometry": {"coordinates":[-77.554817,39.32414],"type":"Point"}
}