{
  "type": "Feature",
  "properties": {
    "addr:full":"2270 Beaver Rd Landover MD 20785",
    "addr:housenumber":"2270",
    "addr:postcode":"20785",
    "addr:street":"Beaver Rd",
    "iso:country":"US",
    "sg:address":"2270 Beaver Rd",
    "sg:city":"Landover",
    "sg:classifiers":[
        {
            "category":"Wholesale",
            "subcategory":"Stationery",
            "type":"Manufacturing & Wholesale Goods"
        }
    ],
    "sg:phone":"+1 301 386 4700",
    "sg:postcode":"20785",
    "sg:province":"MD",
    "sg:tags":[
        "business",
        "form",
        "system"
    ],
    "sg:website":"www.frankparsons.com",
    "wof:name":"Frank Parsons Paper Co Inc",
    "wof:placetype":"venue"
},
  "geometry": {"coordinates":[-76.900543,38.92259],"type":"Point"}
}