{
  "type": "Feature",
  "properties": {
    "addr:full":"9018 Taylor St Springdale MD 20774",
    "addr:housenumber":"9018",
    "addr:postcode":"20774",
    "addr:street":"Taylor St",
    "iso:country":"US",
    "sg:address":"9018 Taylor St",
    "sg:city":"Springdale",
    "sg:classifiers":[
        {
            "category":"Professional",
            "subcategory":"Computer Services",
            "type":"Services"
        }
    ],
    "sg:phone":"+1 301 322 1791",
    "sg:postcode":"20774",
    "sg:province":"MD",
    "sg:tags":[
        "processing",
        "datum"
    ],
    "wof:name":"Sac's Data Express Svc",
    "wof:placetype":"venue"
},
  "geometry": {"coordinates":[-76.85318700000001,38.93923],"type":"Point"}
}