{
  "type": "Feature",
  "properties": {
    "addr:full":"988 Kirk Rd Elkton MD 21921",
    "addr:housenumber":"988",
    "addr:postcode":"21921",
    "addr:street":"Kirk Rd",
    "iso:country":"US",
    "sg:address":"988 Kirk Rd",
    "sg:city":"Elkton",
    "sg:classifiers":[
        {
            "category":"Building & Trades",
            "subcategory":"Construction",
            "type":"Services"
        }
    ],
    "sg:phone":"+1 410 398 7790",
    "sg:postcode":"21921",
    "sg:province":"MD",
    "sg:tags":[
        "woodworker"
    ],
    "wof:name":"Millrace Woodworks",
    "wof:placetype":"venue"
},
  "geometry": {"coordinates":[-75.873175,39.681313],"type":"Point"}
}