{
  "type": "Feature",
  "properties": {
    "iso:country":"US",
    "sg:address":"263 Woodrow Ln",
    "sg:city":"Port Deposit",
    "sg:classifiers":[
        {
            "category":"Farming",
            "subcategory":"Farm",
            "type":"Manufacturing & Wholesale Goods"
        }
    ],
    "sg:phone":"+1 410 378 2933",
    "sg:postcode":"21904",
    "sg:province":"MD",
    "wof:name":"Bell Property",
    "wof:placetype":"venue"
},
  "geometry": {"coordinates":[-76.13128399999999,39.634358],"type":"Point"}
}