{
  "type": "Feature",
  "properties": {
    "iso:country":"US",
    "sg:address":"309 Allegheny Ave",
    "sg:city":"Towson",
    "sg:phone":"+1 410 823 2800",
    "sg:postcode":"21204",
    "sg:province":"MD",
    "sg:website":"http://www.bpjfirm.com",
    "wof:name":"Price, Louis B - Brocato Price & Janofsky",
    "wof:placetype":"venue"
},
  "geometry": {"coordinates":[-76.608502,39.40217],"type":"Point"}
}