{
  "type": "Feature",
  "properties": {
    "addr:full":"111 Dorchester St Ocean City MD 21842",
    "addr:housenumber":"111",
    "addr:postcode":"21842",
    "addr:street":"Dorchester St",
    "iso:country":"US",
    "sg:address":"111 Dorchester St",
    "sg:city":"Ocean City",
    "sg:classifiers":[
        {
            "category":"Insurance",
            "subcategory":"Hazard Insurance",
            "type":"Services"
        }
    ],
    "sg:phone":"+1 410 289 2463",
    "sg:postcode":"21842",
    "sg:province":"MD",
    "sg:tags":[
        "bond"
    ],
    "wof:name":"Anchor Bail Bonds",
    "wof:placetype":"venue"
},
  "geometry": {"coordinates":[-75.08765,38.329933],"type":"Point"}
}