{
  "type": "Feature",
  "properties": {
    "iso:country":"US",
    "sg:address":"2443 Sidney Ave",
    "sg:city":"Baltimore",
    "sg:classifiers":[
        {
            "category":"Wholesale",
            "subcategory":"Stationery",
            "type":"Manufacturing & Wholesale Goods"
        }
    ],
    "sg:phone":"+1 410 204 7604",
    "sg:postcode":"21230",
    "sg:province":"MD",
    "sg:tags":[
        "card"
    ],
    "wof:name":"Baltimore Refuse Service",
    "wof:placetype":"venue"
},
  "geometry": {"coordinates":[-76.63400300000001,39.2607],"type":"Point"}
}