{
  "type": "Feature",
  "properties": {
    "iso:country":"US",
    "sg:address":"14405 Gaines Ave",
    "sg:city":"Rockville",
    "sg:classifiers":[
        {
            "category":"Shopping",
            "subcategory":"Clothing, Apparel, & Fashions",
            "type":"Retail Goods"
        }
    ],
    "sg:phone":"+1 301 871 7988",
    "sg:postcode":"20853",
    "sg:province":"MD",
    "wof:name":"Her Mothers Gown",
    "wof:placetype":"venue"
},
  "geometry": {"coordinates":[-77.085759,39.092699],"type":"Point"}
}