{
  "type": "Feature",
  "properties": {
    "addr:full":"1127 University Blvd E Hyattsville MD 20912",
    "addr:housenumber":"1127",
    "addr:postcode":"20912",
    "addr:street":"University Blvd E",
    "iso:country":"US",
    "sg:address":"1127 University Blvd E",
    "sg:city":"Hyattsville",
    "sg:classifiers":[
        {
            "category":"Professional",
            "subcategory":"Accounting & Tax Preparation",
            "type":"Services"
        }
    ],
    "sg:phone":"+1 301 434 3278",
    "sg:postcode":"20912",
    "sg:province":"MD",
    "sg:tags":[
        "return"
    ],
    "wof:name":"Jackson Hewitt Tax Service",
    "wof:placetype":"venue"
},
  "geometry": {"coordinates":[-76.98925800000001,38.990451],"type":"Point"}
}