{
  "type": "Feature",
  "properties": {
    "iso:country":"US",
    "sg:address":"6561 Quiet Ct",
    "sg:city":"St Leonard",
    "sg:classifiers":[
        {
            "category":"Wholesale",
            "subcategory":"Medical Equipment & Supplies",
            "type":"Manufacturing & Wholesale Goods"
        }
    ],
    "sg:phone":"+1 410 586 8704",
    "sg:postcode":"20685",
    "sg:province":"MD",
    "sg:tags":[
        "optical"
    ],
    "wof:name":"Nassau Lens",
    "wof:placetype":"venue"
},
  "geometry": {"coordinates":[-76.521049,38.448346],"type":"Point"}
}