{
  "type": "Feature",
  "properties": {
    "iso:country":"US",
    "sg:address":"939 Truro Ln",
    "sg:city":"Crofton",
    "sg:classifiers":[
        {
            "category":"Building & Trades",
            "subcategory":"Plumbing",
            "type":"Services"
        }
    ],
    "sg:phone":"+1 301 261 0981",
    "sg:postcode":"21114",
    "sg:province":"MD",
    "sg:tags":[
        "specializing",
        "contractor",
        "conditioning",
        "air"
    ],
    "wof:name":"Walker Services Corp",
    "wof:placetype":"venue"
},
  "geometry": {"coordinates":[-76.671751,39.02391],"type":"Point"}
}