{
  "type": "Feature",
  "properties": {
    "addr:full":"9080 Moonshine Hollow Laurel MD 20723",
    "addr:housenumber":"9080",
    "addr:postcode":"20723",
    "addr:street":"Moonshine Hollow",
    "iso:country":"US",
    "sg:address":"9080 Moonshine Hollow",
    "sg:city":"Laurel",
    "sg:classifiers":[
        {
            "category":"Building & Trades",
            "subcategory":"Construction",
            "type":"Services"
        }
    ],
    "sg:phone":"+1 301 725 5781",
    "sg:postcode":"20723",
    "sg:province":"MD",
    "sg:tags":[
        "contractor"
    ],
    "wof:name":"Tile Works By Christa",
    "wof:placetype":"venue"
},
  "geometry": {"coordinates":[-76.842163,39.123136],"type":"Point"}
}