{
  "type": "Feature",
  "properties": {
    "iso:country":"US",
    "sg:address":"101 Avon Beach Rd",
    "sg:city":"Dundalk",
    "sg:classifiers":[
        {
            "category":"Social Services",
            "subcategory":"Child Care",
            "type":"Services"
        }
    ],
    "sg:phone":"+1 410 282 6977",
    "sg:postcode":"21222",
    "sg:province":"MD",
    "sg:tags":[
        "day"
    ],
    "wof:name":"Head Start YMCA Baltimore County",
    "wof:placetype":"venue"
},
  "geometry": {"coordinates":[-76.512604,39.243301],"type":"Point"}
}