{
  "type": "Feature",
  "properties": {
    "addr:full":"125 N Main St Bel Air MD 21014",
    "addr:housenumber":"125",
    "addr:postcode":"21014",
    "addr:street":"N Main St",
    "iso:country":"US",
    "sg:address":"125 N Main St",
    "sg:city":"Bel Air",
    "sg:classifiers":[
        {
            "category":"Wholesale",
            "subcategory":"Non-durable Goods",
            "type":"Manufacturing & Wholesale Goods"
        },
        {
            "category":"Shopping",
            "subcategory":"Gifts & Souvenirs",
            "type":"Retail Goods"
        }
    ],
    "sg:phone":"+1 410 879 8401",
    "sg:postcode":"21014",
    "sg:province":"MD",
    "sg:tags":[
        "consulting",
        "management",
        "advertising"
    ],
    "sg:website":"www.skylightcreativeideas.com",
    "wof:name":"Skylight Creative Ideas",
    "wof:placetype":"venue"
},
  "geometry": {"coordinates":[-76.35135099999999,39.537941],"type":"Point"}
}