{
  "type": "Feature",
  "properties": {
    "addr:full":"568 Sudbrook Ln Pikesville MD 21208",
    "addr:housenumber":"568",
    "addr:postcode":"21208",
    "addr:street":"Sudbrook Ln",
    "iso:country":"US",
    "sg:address":"568 Sudbrook Ln",
    "sg:city":"Pikesville",
    "sg:classifiers":[
        {
            "category":"Real Estate",
            "subcategory":"Real Estate Agent",
            "type":"Services"
        }
    ],
    "sg:phone":"+1 410 484 4519",
    "sg:postcode":"21208",
    "sg:province":"MD",
    "sg:tags":[
        "inspection"
    ],
    "wof:name":"HLD Assoc",
    "wof:placetype":"venue"
},
  "geometry": {"coordinates":[-76.73095000000001,39.366443],"type":"Point"}
}