{
  "type": "Feature",
  "properties": {
    "iso:country":"US",
    "sg:address":"1576 Merritt Blvd",
    "sg:city":"Dundalk",
    "sg:classifiers":[
        {
            "category":"Real Estate",
            "subcategory":"Real Estate Agent",
            "type":"Services"
        }
    ],
    "sg:phone":"+1 410 284 8560",
    "sg:postcode":"21222",
    "sg:province":"MD",
    "sg:tags":[
        "management"
    ],
    "wof:name":"Albecon Property Management",
    "wof:placetype":"venue"
},
  "geometry": {"coordinates":[-76.503112,39.27351],"type":"Point"}
}