{
  "type": "Feature",
  "properties": {
    "addr:full":"4919 Bethesda Ave Bethesda MD 20814",
    "addr:housenumber":"4919",
    "addr:postcode":"20814",
    "addr:street":"Bethesda Ave",
    "iso:country":"US",
    "sg:address":"4919 Bethesda Ave",
    "sg:city":"Bethesda",
    "sg:classifiers":[
        {
            "category":"Professional",
            "type":"Services"
        }
    ],
    "sg:phone":"+1 301 656 2710",
    "sg:postcode":"20814",
    "sg:province":"MD",
    "sg:tags":[
        "establishment"
    ],
    "wof:name":"Northern Venture Corp",
    "wof:placetype":"venue"
},
  "geometry": {"coordinates":[-77.10042799999999,38.980854],"type":"Point"}
}