{
  "type": "Feature",
  "properties": {
    "iso:country":"US",
    "sg:address":"4919 Bethesda Ave",
    "sg:city":"Bethesda",
    "sg:classifiers":[
        {
            "category":"Professional",
            "type":"Services"
        }
    ],
    "sg:phone":"+1 301 656 2710",
    "sg:postcode":"20814",
    "sg:province":"MD",
    "sg:tags":[
        "establishment"
    ],
    "wof:name":"Northern Venture Corp",
    "wof:placetype":"venue"
},
  "geometry": {"coordinates":[-77.100428,38.980854],"type":"Point"}
}