{
  "type": "Feature",
  "properties": {
    "addr:full":"5303 Baltimore Ave Hyattsville MD 20781",
    "addr:housenumber":"5303",
    "addr:postcode":"20781",
    "addr:street":"Baltimore Ave",
    "iso:country":"US",
    "sg:address":"5303 Baltimore Ave",
    "sg:city":"Hyattsville",
    "sg:classifiers":[
        {
            "category":"Professional",
            "subcategory":"Lawyer & Legal Services",
            "type":"Services"
        }
    ],
    "sg:phone":"+1 301 277 1148",
    "sg:postcode":"20781",
    "sg:province":"MD",
    "wof:name":"Levitsky Carol L ESQ",
    "wof:placetype":"venue"
},
  "geometry": {"coordinates":[-76.940399,38.953701],"type":"Point"}
}