{
  "type": "Feature",
  "properties": {
    "addr:full":"337 Hospital Dr Glen Burnie MD 21061",
    "addr:housenumber":"337",
    "addr:postcode":"21061",
    "addr:street":"Hospital Dr",
    "iso:country":"US",
    "sg:address":"337 Hospital Dr",
    "sg:city":"Glen Burnie",
    "sg:classifiers":[
        {
            "category":"Shopping",
            "type":"Retail Goods"
        }
    ],
    "sg:phone":"+1 410 761 8767",
    "sg:postcode":"21061",
    "sg:province":"MD",
    "sg:tags":[
        "telephone",
        "cellular"
    ],
    "sg:website":"www.awc-md.com",
    "wof:name":"Advanced Wireless Comms Inc",
    "wof:placetype":"venue"
},
  "geometry": {"coordinates":[-76.62437300000001,39.139447],"type":"Point"}
}