{
  "type": "Feature",
  "properties": {
    "addr:full":"10730 Connecticut Ave Kensington MD 20895",
    "addr:housenumber":"10730",
    "addr:postcode":"20895",
    "addr:street":"Connecticut Ave",
    "iso:country":"US",
    "sg:address":"10730 Connecticut Ave",
    "sg:city":"Kensington",
    "sg:classifiers":[
        {
            "category":"Shopping",
            "subcategory":"Used Merchandise",
            "type":"Retail Goods"
        }
    ],
    "sg:phone":"+1 301 949 5731",
    "sg:postcode":"20895",
    "sg:province":"MD",
    "sg:tags":[
        "shop",
        "thrift"
    ],
    "wof:name":"NAMI Thrift Shop",
    "wof:placetype":"venue"
},
  "geometry": {"coordinates":[-77.07504299999999,39.033576],"type":"Point"}
}