{
  "type": "Feature",
  "properties": {
    "addr:full":"1007 Littlestown Pike Westminster MD 21157",
    "addr:housenumber":"1007",
    "addr:postcode":"21157",
    "addr:street":"Littlestown Pike",
    "iso:country":"US",
    "sg:address":"1007 Littlestown Pike",
    "sg:city":"Westminster",
    "sg:classifiers":[
        {
            "category":"Freight",
            "type":"Transportation"
        }
    ],
    "sg:phone":"+1 410 751 6152",
    "sg:postcode":"21157",
    "sg:province":"MD",
    "wof:name":"Charles E Yingling",
    "wof:placetype":"venue"
},
  "geometry": {"coordinates":[-76.998409,39.603915],"type":"Point"}
}