{
  "type": "Feature",
  "properties": {
    "iso:country":"US",
    "sg:address":"126 West St",
    "sg:city":"Annapolis",
    "sg:classifiers":[
        {
            "category":"Building & Trades",
            "subcategory":"Equipment Rental",
            "type":"Services"
        }
    ],
    "sg:phone":"+1 410 263 9058",
    "sg:postcode":"21401",
    "sg:province":"MD",
    "sg:tags":[
        "audio",
        "leasing"
    ],
    "wof:name":"KVL Audio Visual Svc Inc",
    "wof:placetype":"venue"
},
  "geometry": {"coordinates":[-76.497713,38.97795],"type":"Point"}
}