{
  "type": "Feature",
  "properties": {
    "iso:country":"US",
    "sg:address":"3908 Harrison Cir",
    "sg:city":"Trappe",
    "sg:classifiers":[
        {
            "category":"Personal",
            "subcategory":"Beauty Salon",
            "type":"Services"
        }
    ],
    "sg:phone":"+1 410 476 3898",
    "sg:postcode":"21673",
    "sg:province":"MD",
    "wof:name":"That Hair Place",
    "wof:placetype":"venue"
},
  "geometry": {"coordinates":[-76.061663,38.656141],"type":"Point"}
}