{
  "type": "Feature",
  "properties": {
    "addr:full":"1804 Chapel Hill Rd Silver Spring MD 20906",
    "addr:housenumber":"1804",
    "addr:postcode":"20906",
    "addr:street":"Chapel Hill Rd",
    "iso:country":"US",
    "sg:address":"1804 Chapel Hill Rd",
    "sg:city":"Silver Spring",
    "sg:classifiers":[
        {
            "category":"Shopping",
            "subcategory":"Computers & Home Electronics",
            "type":"Retail Goods"
        }
    ],
    "sg:phone":"+1 301 598 5618",
    "sg:postcode":"20906",
    "sg:province":"MD",
    "wof:name":"Guu Software Inc",
    "wof:placetype":"venue"
},
  "geometry": {"coordinates":[-77.039163,39.114652],"type":"Point"}
}