{
  "type": "Feature",
  "properties": {
    "iso:country":"US",
    "sg:address":"150 Railroad Ave",
    "sg:city":"Elkton",
    "sg:classifiers":[
        {
            "category":"Professional",
            "subcategory":"Lawyer & Legal Services",
            "type":"Services"
        }
    ],
    "sg:phone":"+1 410 398 0790",
    "sg:postcode":"21921",
    "sg:province":"MD",
    "sg:tags":[
        "attorney"
    ],
    "wof:name":"Fleming & Love",
    "wof:placetype":"venue"
},
  "geometry": {"coordinates":[-75.83174699999999,39.610676],"type":"Point"}
}