{
  "type": "Feature",
  "properties": {
    "iso:country":"US",
    "sg:address":"9210 Baltimore National Pike",
    "sg:city":"Ellicott City",
    "sg:classifiers":[
        {
            "category":"Shopping",
            "subcategory":"Hobbies, Toys, & Games",
            "type":"Retail Goods"
        },
        {
            "category":"Shopping",
            "subcategory":"Comic Books",
            "type":"Retail Goods"
        }
    ],
    "sg:phone":"+1 410 461 8664",
    "sg:postcode":"21042",
    "sg:province":"MD",
    "sg:tags":[
        "shop",
        "hobby"
    ],
    "sg:website":"www.dugoutzone.com",
    "wof:name":"The Dugout Zone",
    "wof:placetype":"venue"
},
  "geometry": {"coordinates":[-76.829573,39.277396],"type":"Point"}
}