{
  "type": "Feature",
  "properties": {
    "addr:full":"1321 Loflin Rd Aberdeen MD 21001",
    "addr:housenumber":"1321",
    "addr:postcode":"21001",
    "addr:street":"Loflin Rd",
    "iso:country":"US",
    "sg:address":"1321 Loflin Rd",
    "sg:city":"Aberdeen",
    "sg:classifiers":[
        {
            "category":"Autos & Motor Vehicles",
            "subcategory":"Automobile Sales",
            "type":"Retail Goods"
        }
    ],
    "sg:phone":"+1 410 297 9998",
    "sg:postcode":"21001",
    "sg:province":"MD",
    "sg:tags":[
        "car",
        "dealer"
    ],
    "wof:name":"Cars For Less",
    "wof:placetype":"venue"
},
  "geometry": {"coordinates":[-76.20316099999999,39.488623],"type":"Point"}
}