{
  "type": "Feature",
  "properties": {
    "iso:country":"US",
    "sg:address":"7477 Baltimore Annapolis Blvd",
    "sg:city":"Glen Burnie",
    "sg:classifiers":[
        {
            "category":"Restaurant",
            "type":"Food & Drink"
        }
    ],
    "sg:phone":"+1 410 761 8399",
    "sg:postcode":"21061",
    "sg:province":"MD",
    "wof:name":"Thai-Gour Cafe",
    "wof:placetype":"venue"
},
  "geometry": {"coordinates":[-76.623527,39.163593],"type":"Point"}
}