{
  "type": "Feature",
  "properties": {
    "iso:country":"US",
    "sg:address":"19225 Liberty Mill Rd",
    "sg:city":"Germantown",
    "sg:classifiers":[
        {
            "category":"Place Of Worship",
            "type":"Public Place"
        },
        {
            "category":"Place Of Worship",
            "subcategory":"Shrine",
            "type":"Public Place"
        }
    ],
    "sg:phone":"+1 301 353 9780",
    "sg:postcode":"20874",
    "sg:province":"MD",
    "sg:tags":[
        "churches-buddhist",
        "church"
    ],
    "sg:website":"http://www.uszen.org",
    "wof:name":"Us Zen Institute Inc",
    "wof:placetype":"venue"
},
  "geometry": {"coordinates":[-77.274118,39.170867],"type":"Point"}
}