{
  "type": "Feature",
  "properties": {
    "iso:country":"US",
    "sg:address":"303 E Water St",
    "sg:city":"Centreville",
    "sg:classifiers":[
        {
            "category":"Professional",
            "subcategory":"Accounting & Tax Preparation",
            "type":"Services"
        }
    ],
    "sg:phone":"+1 410 758 2788",
    "sg:postcode":"21617",
    "sg:province":"MD",
    "sg:tags":[
        "return",
        "accountants-certified",
        "preparation-business",
        "public"
    ],
    "wof:name":"Brent T Carroll Cpa",
    "wof:placetype":"venue"
},
  "geometry": {"coordinates":[-76.062495,39.042904],"type":"Point"}
}