{
  "type": "Feature",
  "properties": {
    "addr:full":"2509 Palmer View Dr Bel Air MD 21015",
    "addr:housenumber":"2509",
    "addr:postcode":"21015",
    "addr:street":"Palmer View Dr",
    "iso:country":"US",
    "sg:address":"2509 Palmer View Dr",
    "sg:city":"Bel Air",
    "sg:classifiers":[
        {
            "category":"Wholesale",
            "subcategory":"Vending Machines",
            "type":"Manufacturing & Wholesale Goods"
        }
    ],
    "sg:phone":"+1 410 676 3833",
    "sg:postcode":"21015",
    "sg:province":"MD",
    "sg:tags":[
        "operator"
    ],
    "wof:name":"Wojtysiak Sylvester P Inc",
    "wof:placetype":"venue"
},
  "geometry": {"coordinates":[-76.266791,39.59372],"type":"Point"}
}