{
  "type": "Feature",
  "properties": {
    "iso:country":"US",
    "sg:address":"7406 Westmore Rd",
    "sg:city":"Rockville",
    "sg:classifiers":[
        {
            "category":"Retail",
            "subcategory":"Auto Repair",
            "type":"Services"
        }
    ],
    "sg:phone":"+1 301 340 1085",
    "sg:postcode":"20850",
    "sg:province":"MD",
    "sg:tags":[
        "repairing",
        "automobile"
    ],
    "wof:name":"Americo's Foreign Auto Svc",
    "wof:placetype":"venue"
},
  "geometry": {"coordinates":[-77.147684,39.099805],"type":"Point"}
}