{
  "type": "Feature",
  "properties": {
    "iso:country":"US",
    "sg:address":"8 Sullivan Ave",
    "sg:city":"Westminster",
    "sg:phone":"+1 410 876 6600",
    "sg:postcode":"21157",
    "sg:province":"MD",
    "sg:tags":[
        "oil"
    ],
    "wof:name":"S L Bare",
    "wof:placetype":"venue"
},
  "geometry": {"coordinates":[-76.998621,39.587978],"type":"Point"}
}