{
  "type": "Feature",
  "properties": {
    "addr:full":"2605 Aspen Rd Port Republic MD 20676",
    "addr:housenumber":"2605",
    "addr:postcode":"20676",
    "addr:street":"Aspen Rd",
    "iso:country":"US",
    "sg:address":"2605 Aspen Rd",
    "sg:city":"Port Republic",
    "sg:classifiers":[
        {
            "category":"Organizations",
            "subcategory":"Non-profit Organization",
            "type":"Services"
        }
    ],
    "sg:phone":"+1 410 586 8780",
    "sg:postcode":"20676",
    "sg:province":"MD",
    "sg:tags":[
        "human"
    ],
    "wof:name":"Human Services Institute Inc",
    "wof:placetype":"venue"
},
  "geometry": {"coordinates":[-76.510503,38.510696],"type":"Point"}
}