{
  "type": "Feature",
  "properties": {
    "addr:full":"4951 Saint Elmo Ave Bethesda MD 20814",
    "addr:housenumber":"4951",
    "addr:postcode":"20814",
    "addr:street":"Saint Elmo Ave",
    "iso:country":"US",
    "sg:address":"4951 Saint Elmo Ave",
    "sg:city":"Bethesda",
    "sg:classifiers":[
        {
            "category":"Personal",
            "subcategory":"Barber",
            "type":"Services"
        }
    ],
    "sg:phone":"+1 301 215 7271",
    "sg:postcode":"20814",
    "sg:province":"MD",
    "wof:name":"Bethesda Barber Shop",
    "wof:placetype":"venue"
},
  "geometry": {"coordinates":[-77.098297,38.987701],"type":"Point"}
}