{
  "type": "Feature",
  "properties": {
    "addr:full":"6 Colgate Dr Forest Hill MD 21050",
    "addr:housenumber":"6",
    "addr:postcode":"21050",
    "addr:street":"Colgate Dr",
    "iso:country":"US",
    "sg:address":"6 Colgate Dr",
    "sg:city":"Forest Hill",
    "sg:classifiers":[
        {
            "category":"Retail",
            "subcategory":"Auto Repair",
            "type":"Services"
        }
    ],
    "sg:phone":"+1 410 836 8199",
    "sg:postcode":"21050",
    "sg:province":"MD",
    "sg:tags":[
        "repairing",
        "automobile"
    ],
    "wof:name":"Reg Dixon's Svc Ctr",
    "wof:placetype":"venue"
},
  "geometry": {"coordinates":[-76.380813,39.571136],"type":"Point"}
}