{
  "type": "Feature",
  "properties": {
    "iso:country":"US",
    "sg:address":"2404 Ash Grove Ln",
    "sg:city":"Odenton",
    "sg:classifiers":[
        {
            "category":"Real Estate",
            "subcategory":"Real Estate Operator",
            "type":"Services"
        }
    ],
    "sg:phone":"+1 410 695 0130",
    "sg:postcode":"21113",
    "sg:province":"MD",
    "sg:tags":[
        "apartment"
    ],
    "wof:name":"Groves At Piney Orchard",
    "wof:placetype":"venue"
},
  "geometry": {"coordinates":[-76.715091,39.066744],"type":"Point"}
}