{
  "type": "Feature",
  "properties": {
    "addr:full":"9130 September Ln Silver Spring MD 20901",
    "addr:housenumber":"9130",
    "addr:postcode":"20901",
    "addr:street":"September Ln",
    "iso:country":"US",
    "sg:address":"9130 September Ln",
    "sg:city":"Silver Spring",
    "sg:classifiers":[
        {
            "category":"Professional",
            "type":"Services"
        }
    ],
    "sg:phone":"+1 301 445 4615",
    "sg:postcode":"20901",
    "sg:province":"MD",
    "sg:tags":[
        "establishment"
    ],
    "wof:name":"John Cofton Assoc",
    "wof:placetype":"venue"
},
  "geometry": {"coordinates":[-76.996115,39.004561],"type":"Point"}
}