{
  "type": "Feature",
  "properties": {
    "iso:country":"US",
    "sg:address":"9908 Maidbrook Rd",
    "sg:city":"Baltimore",
    "sg:classifiers":[
        {
            "category":"Professional",
            "type":"Services"
        }
    ],
    "sg:phone":"+1 410 882 9168",
    "sg:postcode":"21234",
    "sg:province":"MD",
    "wof:name":"Nancy L Hanlin",
    "wof:placetype":"venue"
},
  "geometry": {"coordinates":[-76.508276,39.406234],"type":"Point"}
}