{
  "type": "Feature",
  "properties": {
    "iso:country":"US",
    "sg:address":"16409 Edgepark Ct",
    "sg:city":"Bowie",
    "sg:classifiers":[
        {
            "category":"Professional",
            "subcategory":"Business Services",
            "type":"Services"
        }
    ],
    "sg:phone":"+1 301 552 5290",
    "sg:postcode":"20716",
    "sg:province":"MD",
    "sg:tags":[
        "paralegal"
    ],
    "wof:name":"Frison & Frison",
    "wof:placetype":"venue"
},
  "geometry": {"coordinates":[-76.720037,38.931632],"type":"Point"}
}