{
  "type": "Feature",
  "properties": {
    "addr:full":"400 W 7th St Frederick MD 21701",
    "addr:housenumber":"400",
    "addr:postcode":"21701",
    "addr:street":"W 7Th St",
    "iso:country":"US",
    "sg:address":"400 W 7th St",
    "sg:city":"Frederick",
    "sg:classifiers":[
        {
            "category":"Health Services",
            "subcategory":"Doctor",
            "type":"Services"
        }
    ],
    "sg:phone":"+1 301 698 3800",
    "sg:postcode":"21701",
    "sg:province":"MD",
    "sg:tags":[
        "physician",
        "surgeon"
    ],
    "wof:name":"Anesthesia Consultants",
    "wof:placetype":"venue"
},
  "geometry": {"coordinates":[-77.41491499999999,39.424071],"type":"Point"}
}