{
  "type": "Feature",
  "properties": {
    "iso:country":"US",
    "sg:address":"14100 Brandywine Rd",
    "sg:city":"Brandywine",
    "sg:classifiers":[
        {
            "category":"Food & Beverages",
            "subcategory":"Groceries & Convenience Stores",
            "type":"Retail Goods"
        }
    ],
    "sg:phone":"+1 301 372 3663",
    "sg:postcode":"20613",
    "sg:province":"MD",
    "sg:tags":[
        "grocer"
    ],
    "sg:website":"www.topbananagroceries.org",
    "wof:name":"Top Banana Home Delivery Groc",
    "wof:placetype":"venue"
},
  "geometry": {"coordinates":[-76.855047,38.697244],"type":"Point"}
}