{
  "type": "Feature",
  "properties": {
    "iso:country":"US",
    "sg:address":"3802 Eastern Ave",
    "sg:city":"Baltimore",
    "sg:classifiers":[
        {
            "category":"Restaurant",
            "type":"Food & Drink"
        }
    ],
    "sg:phone":"+1 410 276 9422",
    "sg:postcode":"21224",
    "sg:province":"MD",
    "sg:tags":[
        "traditional",
        "style",
        "american",
        "family"
    ],
    "sg:website":"www.gandarestaurant.com/",
    "wof:name":"G & A Restaurant",
    "wof:placetype":"venue"
},
  "geometry": {"coordinates":[-76.564903,39.286598],"type":"Point"}
}