{
  "type": "Feature",
  "properties": {
    "addr:full":"2227 Bel Pre Rd Silver Spring MD 20906",
    "addr:housenumber":"2227",
    "addr:postcode":"20906",
    "addr:street":"Pre Rd",
    "iso:country":"US",
    "sg:address":"2227 Bel Pre Rd",
    "sg:city":"Silver Spring",
    "sg:classifiers":[
        {
            "category":"Shopping",
            "subcategory":"Gifts & Souvenirs",
            "type":"Retail Goods"
        }
    ],
    "sg:phone":"+1 301 603 0780",
    "sg:postcode":"20906",
    "sg:province":"MD",
    "sg:tags":[
        "collectible"
    ],
    "wof:name":"C & C Sports Cards & Comic",
    "wof:placetype":"venue"
},
  "geometry": {"coordinates":[-77.047149,39.090596],"type":"Point"}
}