{
  "type": "Feature",
  "properties": {
    "addr:full":"3989 Kump Station Rd Taneytown MD 21787",
    "addr:housenumber":"3989",
    "addr:postcode":"21787",
    "addr:street":"Kump Station Rd",
    "iso:country":"US",
    "sg:address":"3989 Kump Station Rd",
    "sg:city":"Taneytown",
    "sg:classifiers":[
        {
            "category":"Building & Trades",
            "subcategory":"Plumbing",
            "type":"Services"
        }
    ],
    "sg:phone":"+1 410 751 0990",
    "sg:postcode":"21787",
    "sg:province":"MD",
    "sg:tags":[
        "mechanical",
        "contractor"
    ],
    "wof:name":"Schaefer Mechanical Svc Inc",
    "wof:placetype":"venue"
},
  "geometry": {"coordinates":[-77.138943,39.689277],"type":"Point"}
}