{
  "type": "Feature",
  "properties": {
    "addr:full":"20 Grand Corner Ave Gaithersburg MD 20878",
    "addr:housenumber":"20",
    "addr:postcode":"20878",
    "addr:street":"Grand Corner Ave",
    "iso:country":"US",
    "sg:address":"20 Grand Corner Ave",
    "sg:city":"Gaithersburg",
    "sg:classifiers":[
        {
            "category":"Food & Beverages",
            "subcategory":"Specialty",
            "type":"Retail Goods"
        }
    ],
    "sg:phone":"+1 301 548 8831",
    "sg:postcode":"20878",
    "sg:province":"MD",
    "sg:tags":[
        "health",
        "diet"
    ],
    "wof:name":"General Nutrition Ctr",
    "wof:placetype":"venue"
},
  "geometry": {"coordinates":[-77.19228200000001,39.111772],"type":"Point"}
}