{
  "type": "Feature",
  "properties": {
    "addr:full":"1800 Selma Ave Halethorpe MD 21227",
    "addr:housenumber":"1800",
    "addr:postcode":"21227",
    "addr:street":"Selma Ave",
    "iso:country":"US",
    "sg:address":"1800 Selma Ave",
    "sg:city":"Halethorpe",
    "sg:classifiers":[
        {
            "category":"Real Estate",
            "subcategory":"Real Estate Agent",
            "type":"Services"
        }
    ],
    "sg:phone":"+1 410 247 8055",
    "sg:postcode":"21227",
    "sg:province":"MD",
    "wof:name":"Charlotte Ault",
    "wof:placetype":"venue"
},
  "geometry": {"coordinates":[-76.68727699999999,39.234601],"type":"Point"}
}