{
  "type": "Feature",
  "properties": {
    "addr:full":"11811 Cedarwood Dr Dunkirk MD 20754",
    "addr:housenumber":"11811",
    "addr:postcode":"20754",
    "addr:street":"Cedarwood Dr",
    "iso:country":"US",
    "sg:address":"11811 Cedarwood Dr",
    "sg:city":"Dunkirk",
    "sg:classifiers":[
        {
            "category":"Professional",
            "subcategory":"Computer Services",
            "type":"Services"
        }
    ],
    "sg:phone":"+1 301 855 4600",
    "sg:postcode":"20754",
    "sg:province":"MD",
    "sg:tags":[
        "consultant",
        "designer"
    ],
    "sg:website":"www.npcnetwork.com",
    "wof:name":"Network Performance",
    "wof:placetype":"venue"
},
  "geometry": {"coordinates":[-76.653768,38.743216],"type":"Point"}
}