{
  "type": "Feature",
  "properties": {
    "iso:country":"US",
    "sg:address":"1908 Cecil Ave",
    "sg:city":"Baltimore",
    "sg:classifiers":[
        {
            "category":"Organizations",
            "subcategory":"Religious Organization",
            "type":"Services"
        }
    ],
    "sg:phone":"+1 410 889 2335",
    "sg:postcode":"21218",
    "sg:province":"MD",
    "sg:tags":[
        "clergy"
    ],
    "wof:name":"Roy J Rev",
    "wof:placetype":"venue"
},
  "geometry": {"coordinates":[-76.605154,39.311774],"type":"Point"}
}