{
  "type": "Feature",
  "properties": {
    "iso:country":"US",
    "sg:address":"407 Marley Station Rd",
    "sg:city":"Glen Burnie",
    "sg:classifiers":[
        {
            "category":"Education",
            "subcategory":"School",
            "type":"Public Place"
        }
    ],
    "sg:phone":"+1 410 768 5306",
    "sg:postcode":"21060",
    "sg:province":"MD",
    "sg:tags":[
        "organization",
        "religious"
    ],
    "wof:name":"Calvary Baptist Church Academy",
    "wof:placetype":"venue"
},
  "geometry": {"coordinates":[-76.601088,39.142561],"type":"Point"}
}