{
  "type": "Feature",
  "properties": {
    "addr:full":"6185 Oxon Hill Rd Oxon Hill MD 20745",
    "addr:housenumber":"6185",
    "addr:postcode":"20745",
    "addr:street":"Oxon Hill Rd",
    "iso:country":"US",
    "sg:address":"6185 Oxon Hill Rd",
    "sg:city":"Oxon Hill",
    "sg:classifiers":[
        {
            "category":"Shopping",
            "subcategory":"Clothing, Apparel, & Fashions",
            "type":"Retail Goods"
        }
    ],
    "sg:phone":"+1 301 567 6105",
    "sg:postcode":"20745",
    "sg:province":"MD",
    "wof:name":"Last Stop Co",
    "wof:placetype":"venue"
},
  "geometry": {"coordinates":[-76.985176,38.803973],"type":"Point"}
}