{
  "type": "Feature",
  "properties": {
    "iso:country":"US",
    "sg:address":"14013 Big Branch Dr",
    "sg:city":"Dayton",
    "sg:classifiers":[
        {
            "category":"Professional",
            "subcategory":"Detective & Security Services",
            "type":"Services"
        }
    ],
    "sg:phone":"+1 410 531 7709",
    "sg:postcode":"21036",
    "sg:province":"MD",
    "sg:tags":[
        "information",
        "bureau"
    ],
    "wof:name":"Nina Cusanelli",
    "wof:placetype":"venue"
},
  "geometry": {"coordinates":[-77.00702200000001,39.247013],"type":"Point"}
}