{
  "type": "Feature",
  "properties": {
    "addr:full":"7004 Club House Cir New Market MD 21774",
    "addr:housenumber":"7004",
    "addr:postcode":"21774",
    "addr:street":"Club House Cir",
    "iso:country":"US",
    "sg:address":"7004 Club House Cir",
    "sg:city":"New Market",
    "sg:classifiers":[
        {
            "category":"Professional",
            "subcategory":"Management & Consulting",
            "type":"Services"
        }
    ],
    "sg:phone":"+1 301 831 9656",
    "sg:postcode":"21774",
    "sg:province":"MD",
    "sg:tags":[
        "consultant"
    ],
    "wof:name":"Gail H Treglia",
    "wof:placetype":"venue"
},
  "geometry": {"coordinates":[-77.272165,39.42545],"type":"Point"}
}