{
  "type": "Feature",
  "properties": {
    "iso:country":"US",
    "sg:address":"312 Park Row",
    "sg:city":"Chestertown",
    "sg:classifiers":[
        {
            "category":"Retail",
            "subcategory":"Repair Shop",
            "type":"Services"
        }
    ],
    "sg:phone":"+1 410 778 1113",
    "sg:postcode":"21620",
    "sg:province":"MD",
    "sg:tags":[
        "television",
        "radio"
    ],
    "wof:name":"Continental TV",
    "wof:placetype":"venue"
},
  "geometry": {"coordinates":[-76.066722,39.209985],"type":"Point"}
}