{
  "type": "Feature",
  "properties": {
    "addr:full":"7120 N Point Rd Baltimore MD 21219",
    "addr:housenumber":"7120",
    "addr:postcode":"21219",
    "addr:street":"N Point Rd",
    "iso:country":"US",
    "sg:address":"7120 N Point Rd",
    "sg:city":"Baltimore",
    "sg:classifiers":[
        {
            "category":"Restaurant",
            "type":"Food & Drink"
        }
    ],
    "sg:phone":"+1 410 388 2003",
    "sg:postcode":"21219",
    "sg:province":"MD",
    "sg:tags":[
        "eating"
    ],
    "wof:name":"Edgemere Wok",
    "wof:placetype":"venue"
},
  "geometry": {"coordinates":[-76.44642899999999,39.241091],"type":"Point"}
}