{
  "type": "Feature",
  "properties": {
    "iso:country":"US",
    "sg:address":"24422 Mervell Dean Rd",
    "sg:city":"Hollywood",
    "sg:classifiers":[
        {
            "category":"Organizations",
            "subcategory":"Religious Organization",
            "type":"Services"
        }
    ],
    "sg:phone":"+1 301 373 8738",
    "sg:postcode":"20636",
    "sg:province":"MD",
    "sg:tags":[
        "church"
    ],
    "wof:name":"Hollywood United Methodist",
    "wof:placetype":"venue"
},
  "geometry": {"coordinates":[-76.55987399999999,38.337827],"type":"Point"}
}