{
  "type": "Feature",
  "properties": {
    "addr:full":"1018 Edgewood Rd Edgewood MD 21040",
    "addr:housenumber":"1018",
    "addr:postcode":"21040",
    "addr:street":"Edgewood Rd",
    "iso:country":"US",
    "sg:address":"1018 Edgewood Rd",
    "sg:city":"Edgewood",
    "sg:classifiers":[
        {
            "category":"Shopping",
            "subcategory":"Florist",
            "type":"Retail Goods"
        }
    ],
    "sg:phone":"+1 410 679 1515",
    "sg:postcode":"21040",
    "sg:province":"MD",
    "wof:name":"Dodd's Edgewood Florist & Gift Shop",
    "wof:placetype":"venue"
},
  "geometry": {"coordinates":[-76.306702,39.435501],"type":"Point"}
}