{
  "type": "Feature",
  "properties": {
    "iso:country":"US",
    "sg:address":"5202 Minnick Rd",
    "sg:city":"Laurel",
    "sg:classifiers":[
        {
            "category":"Wholesale",
            "subcategory":"Construction Materials",
            "type":"Manufacturing & Wholesale Goods"
        }
    ],
    "sg:phone":"+1 301 497 8900",
    "sg:postcode":"20707",
    "sg:province":"MD",
    "sg:tags":[
        "concrete",
        "form"
    ],
    "wof:name":"Precise Forms Distribution Ctr",
    "wof:placetype":"venue"
},
  "geometry": {"coordinates":[-76.914935,39.090009],"type":"Point"}
}