{
  "type": "Feature",
  "properties": {
    "iso:country":"US",
    "sg:address":"66 Water St",
    "sg:city":"Smithsburg",
    "sg:classifiers":[
        {
            "category":"Education",
            "subcategory":"Library",
            "type":"Public Place"
        }
    ],
    "sg:phone":"+1 301 824 7722",
    "sg:postcode":"21783",
    "sg:province":"MD",
    "wof:name":"Smithsburg Library",
    "wof:placetype":"venue"
},
  "geometry": {"coordinates":[-77.56659399999999,39.657646],"type":"Point"}
}