{
  "type": "Feature",
  "properties": {
    "addr:full":"6610 Baltimore National Pike Ste 2 Catonsville MD 21228",
    "addr:housenumber":"6610",
    "addr:postcode":"21228",
    "addr:street":"Baltimore National Pike Ste 2",
    "iso:country":"US",
    "sg:address":"6610 Baltimore National Pike Ste 2",
    "sg:city":"Catonsville",
    "sg:classifiers":[
        {
            "category":"Retail",
            "subcategory":"Auto Rental",
            "type":"Services"
        }
    ],
    "sg:phone":"+1 410 744 1308",
    "sg:postcode":"21228",
    "sg:province":"MD",
    "sg:tags":[
        "car"
    ],
    "sg:website":"budget.com",
    "wof:name":"Budget Car Rental",
    "wof:placetype":"venue"
},
  "geometry": {"coordinates":[-76.76617,39.287326],"type":"Point"}
}