{
  "type": "Feature",
  "properties": {
    "addr:full":"2850 Dunleigh Dr Dunkirk MD 20754",
    "addr:housenumber":"2850",
    "addr:postcode":"20754",
    "addr:street":"Dunleigh Dr",
    "iso:country":"US",
    "sg:address":"2850 Dunleigh Dr",
    "sg:city":"Dunkirk",
    "sg:classifiers":[
        {
            "category":"Building & Trades",
            "subcategory":"Landscaping Services",
            "type":"Services"
        }
    ],
    "sg:phone":"+1 410 286 7207",
    "sg:postcode":"20754",
    "sg:province":"MD",
    "sg:tags":[
        "consultant",
        "designer",
        "landscape"
    ],
    "wof:name":"Donald Entzian",
    "wof:placetype":"venue"
},
  "geometry": {"coordinates":[-76.65969,38.749829],"type":"Point"}
}