{
  "type": "Feature",
  "properties": {
    "iso:country":"US",
    "sg:address":"16771 Oakmont Ave",
    "sg:city":"Gaithersburg",
    "sg:classifiers":[
        {
            "category":"Retail",
            "subcategory":"Auto Repair",
            "type":"Services"
        }
    ],
    "sg:phone":"+1 301 527 0885",
    "sg:postcode":"20877",
    "sg:province":"MD",
    "sg:tags":[
        "repairing",
        "automobile"
    ],
    "wof:name":"Los Angeles Auto & Truck Rpr",
    "wof:placetype":"venue"
},
  "geometry": {"coordinates":[-77.175151,39.132207],"type":"Point"}
}