{
  "type": "Feature",
  "properties": {
    "iso:country":"US",
    "sg:address":"800 W Baltimore St",
    "sg:city":"Baltimore",
    "sg:classifiers":[
        {
            "category":"Building & Trades",
            "subcategory":"Electrical",
            "type":"Services"
        }
    ],
    "sg:phone":"+1 410 539 2068",
    "sg:postcode":"21201",
    "sg:province":"MD",
    "sg:tags":[
        "electric",
        "contractor"
    ],
    "wof:name":"Primo Electric",
    "wof:placetype":"venue"
},
  "geometry": {"coordinates":[-76.631397,39.288877],"type":"Point"}
}