{
  "type": "Feature",
  "properties": {
    "addr:full":"13679 Baltimore Ave Laurel MD 20707",
    "addr:housenumber":"13679",
    "addr:postcode":"20707",
    "addr:street":"Baltimore Ave",
    "iso:country":"US",
    "sg:address":"13679 Baltimore Ave",
    "sg:city":"Laurel",
    "sg:classifiers":[
        {
            "category":"Real Estate",
            "subcategory":"Architect",
            "type":"Services"
        }
    ],
    "sg:phone":"+1 301 953 3400",
    "sg:postcode":"20707",
    "sg:province":"MD",
    "sg:tags":[
        "estimate",
        "construction"
    ],
    "wof:name":"Sierra Commercial Construction",
    "wof:placetype":"venue"
},
  "geometry": {"coordinates":[-76.867223,39.076982],"type":"Point"}
}