{
  "type": "Feature",
  "properties": {
    "addr:full":"207 Love Point Rd Stevensville MD 21666",
    "addr:housenumber":"207",
    "addr:postcode":"21666",
    "addr:street":"Love Point Rd",
    "iso:country":"US",
    "sg:address":"207 Love Point Rd",
    "sg:city":"Stevensville",
    "sg:classifiers":[
        {
            "category":"Retail",
            "subcategory":"Auto Repair",
            "type":"Services"
        }
    ],
    "sg:phone":"+1 410 643 6692",
    "sg:postcode":"21666",
    "sg:province":"MD",
    "sg:tags":[
        "body",
        "automobile",
        "painting",
        "repairing"
    ],
    "wof:name":"Kent Dutys Island Auto Body",
    "wof:placetype":"venue"
},
  "geometry": {"coordinates":[-76.319039,38.979381],"type":"Point"}
}