{
  "type": "Feature",
  "properties": {
    "iso:country":"US",
    "sg:address":"733 Deepdene Rd",
    "sg:city":"Baltimore",
    "sg:classifiers":[
        {
            "category":"Shopping",
            "subcategory":"Florist",
            "type":"Retail Goods"
        }
    ],
    "sg:phone":"+1 410 534 5459",
    "sg:postcode":"21210",
    "sg:province":"MD",
    "sg:website":"www.crimsonandcloverdesigns.com",
    "wof:name":"Crimson & Clover Floral Design, Inc.",
    "wof:placetype":"venue"
},
  "geometry": {"coordinates":[-76.633864,39.356507],"type":"Point"}
}