{
  "type": "Feature",
  "properties": {
    "addr:full":"545 Blue Ball Rd Elkton MD 21921",
    "addr:housenumber":"545",
    "addr:postcode":"21921",
    "addr:street":"Blue Ball Rd",
    "iso:country":"US",
    "sg:address":"545 Blue Ball Rd",
    "sg:city":"Elkton",
    "sg:classifiers":[
        {
            "category":"Freight",
            "type":"Transportation"
        }
    ],
    "sg:phone":"+1 410 392 0900",
    "sg:postcode":"21921",
    "sg:province":"MD",
    "sg:tags":[
        "mobile",
        "home"
    ],
    "wof:name":"Morgan Drive Away Inc",
    "wof:placetype":"venue"
},
  "geometry": {"coordinates":[-75.851738,39.621392],"type":"Point"}
}