{
  "type": "Feature",
  "properties": {
    "addr:full":"8 W 2nd St Frederick MD 21701",
    "addr:housenumber":"8",
    "addr:postcode":"21701",
    "addr:street":"W 2Nd St",
    "iso:country":"US",
    "sg:address":"8 W 2nd St",
    "sg:city":"Frederick",
    "sg:classifiers":[
        {
            "category":"Organizations",
            "subcategory":"Religious Organization",
            "type":"Services"
        }
    ],
    "sg:phone":"+1 301 663 5273",
    "sg:postcode":"21701",
    "sg:province":"MD",
    "sg:tags":[
        "church"
    ],
    "wof:name":"Centennial Memorial United Chr",
    "wof:placetype":"venue"
},
  "geometry": {"coordinates":[-77.41191999999999,39.416617],"type":"Point"}
}