{
  "type": "Feature",
  "properties": {
    "addr:full":"8000 Martin Luther King Jr Hwy Lanham MD 20706",
    "addr:housenumber":"8000",
    "addr:postcode":"20706",
    "addr:street":"Martin Luther King Jr Hwy",
    "iso:country":"US",
    "sg:address":"8000 Martin Luther King Jr Hwy",
    "sg:city":"Lanham",
    "sg:classifiers":[
        {
            "category":"Shopping",
            "subcategory":"Discount & Variety Stores",
            "type":"Retail Goods"
        }
    ],
    "sg:phone":"+1 301 386 5161",
    "sg:postcode":"20706",
    "sg:province":"MD",
    "wof:name":"Neighboorhood Dollar Plus",
    "wof:placetype":"venue"
},
  "geometry": {"coordinates":[-76.870818,38.929963],"type":"Point"}
}