{
  "type": "Feature",
  "properties": {
    "addr:full":"3250 Roscommon Dr Glenelg MD 21737",
    "addr:housenumber":"3250",
    "addr:postcode":"21737",
    "addr:street":"Roscommon Dr",
    "iso:country":"US",
    "sg:address":"3250 Roscommon Dr",
    "sg:city":"Glenelg",
    "sg:classifiers":[
        {
            "category":"Home & Garden",
            "subcategory":"Building Materials",
            "type":"Retail Goods"
        }
    ],
    "sg:phone":"+1 410 489 2296",
    "sg:postcode":"21737",
    "sg:province":"MD",
    "sg:tags":[
        "windows"
    ],
    "wof:name":"Window Connection",
    "wof:placetype":"venue"
},
  "geometry": {"coordinates":[-76.99706500000001,39.279802],"type":"Point"}
}