{
  "type": "Feature",
  "properties": {
    "iso:country":"US",
    "sg:address":"6501 Greenfield Ct",
    "sg:city":"Lanham",
    "sg:classifiers":[
        {
            "category":"Real Estate",
            "subcategory":"Real Estate Agent",
            "type":"Services"
        }
    ],
    "sg:phone":"+1 301 552 3222",
    "sg:postcode":"20706",
    "sg:province":"MD",
    "wof:name":"Cole & Assoc Realtors",
    "wof:placetype":"venue"
},
  "geometry": {"coordinates":[-76.867708,38.979279],"type":"Point"}
}