{
  "type": "Feature",
  "properties": {
    "iso:country":"US",
    "sg:address":"3725 Harbor Rd",
    "sg:city":"Chesapeake Beach",
    "sg:classifiers":[
        {
            "category":"Recreation",
            "subcategory":"Marina",
            "type":"Entertainment"
        }
    ],
    "sg:phone":"+1 301 855 6705",
    "sg:postcode":"20732",
    "sg:province":"MD",
    "wof:name":"Abners Crabhouse",
    "wof:placetype":"venue"
},
  "geometry": {"coordinates":[-76.540105,38.688642],"type":"Point"}
}