{
  "type": "Feature",
  "properties": {
    "iso:country":"US",
    "sg:address":"919 East St",
    "sg:city":"Frederick",
    "sg:classifiers":[
        {
            "category":"Home & Garden",
            "subcategory":"Building Materials",
            "type":"Retail Goods"
        }
    ],
    "sg:phone":"+1 301 631 5325",
    "sg:postcode":"21701",
    "sg:province":"MD",
    "sg:tags":[
        "stone"
    ],
    "wof:name":"Stone Accent",
    "wof:placetype":"venue"
},
  "geometry": {"coordinates":[-77.403544,39.426957],"type":"Point"}
}