{
  "type": "Feature",
  "properties": {
    "iso:country":"US",
    "sg:address":"900 E Patapsco Ave",
    "sg:city":"Brooklyn",
    "sg:classifiers":[
        {
            "category":"Retail",
            "subcategory":"Auto Repair",
            "type":"Services"
        }
    ],
    "sg:phone":"+1 410 355 0054",
    "sg:postcode":"21225",
    "sg:province":"MD",
    "sg:tags":[
        "repairing",
        "automobile"
    ],
    "wof:name":"Citco Garage",
    "wof:placetype":"venue"
},
  "geometry": {"coordinates":[-76.596565,39.23455],"type":"Point"}
}