{
  "type": "Feature",
  "properties": {
    "iso:country":"US",
    "sg:address":"10825 Marathon Dr",
    "sg:city":"Upper Marlboro",
    "sg:classifiers":[
        {
            "category":"Professional",
            "subcategory":"Business Services",
            "type":"Services"
        }
    ],
    "sg:phone":"+1 301 877 3908",
    "sg:postcode":"20772",
    "sg:province":"MD",
    "sg:tags":[
        "investigation",
        "background"
    ],
    "wof:name":"Dorothy J Franklin",
    "wof:placetype":"venue"
},
  "geometry": {"coordinates":[-76.823832,38.75503],"type":"Point"}
}