{
  "type": "Feature",
  "properties": {
    "addr:full":"102 E Bay Front Rd Deale MD 20751",
    "addr:housenumber":"102",
    "addr:postcode":"20751",
    "addr:street":"E Bay Front Rd",
    "iso:country":"US",
    "sg:address":"102 E Bay Front Rd",
    "sg:city":"Deale",
    "sg:classifiers":[
        {
            "category":"Wholesale",
            "subcategory":"Medical Equipment & Supplies",
            "type":"Manufacturing & Wholesale Goods"
        }
    ],
    "sg:phone":"+1 410 320 1455",
    "sg:postcode":"20751",
    "sg:province":"MD",
    "sg:tags":[
        "laboratory"
    ],
    "sg:website":"http://www.qualitycalibrationsinc.com",
    "wof:name":"Great Scapes by ESI, Inc.",
    "wof:placetype":"venue"
},
  "geometry": {"coordinates":[-76.587869,38.788406],"type":"Point"}
}