{
  "type": "Feature",
  "properties": {
    "iso:country":"US",
    "sg:address":"728 Glenwood St",
    "sg:city":"Annapolis",
    "sg:classifiers":[
        {
            "category":"Social Services",
            "subcategory":"Child Care",
            "type":"Services"
        }
    ],
    "sg:phone":"+1 410 626 0106",
    "sg:postcode":"21401",
    "sg:province":"MD",
    "sg:tags":[
        "day"
    ],
    "wof:name":"Pattys Little People Inc",
    "wof:placetype":"venue"
},
  "geometry": {"coordinates":[-76.505593,38.981497],"type":"Point"}
}