{
  "type": "Feature",
  "properties": {
    "addr:full":"1021 Johnsville Rd Sykesville MD 21784",
    "addr:housenumber":"1021",
    "addr:postcode":"21784",
    "addr:street":"Johnsville Rd",
    "iso:country":"US",
    "sg:address":"1021 Johnsville Rd",
    "sg:city":"Sykesville",
    "sg:classifiers":[
        {
            "category":"Education",
            "subcategory":"School",
            "type":"Public Place"
        }
    ],
    "sg:phone":"+1 410 751 3520",
    "sg:postcode":"21784",
    "sg:province":"MD",
    "wof:name":"Eldersburg Elementary School",
    "wof:placetype":"venue"
},
  "geometry": {"coordinates":[-76.96008,39.409175],"type":"Point"}
}