{
  "type": "Feature",
  "properties": {
    "addr:full":"7013 Deer Valley Rd Highland MD 20777",
    "addr:housenumber":"7013",
    "addr:postcode":"20777",
    "addr:street":"Deer Valley Rd",
    "iso:country":"US",
    "sg:address":"7013 Deer Valley Rd",
    "sg:city":"Highland",
    "sg:classifiers":[
        {
            "category":"Building & Trades",
            "subcategory":"Construction",
            "type":"Services"
        }
    ],
    "sg:phone":"+1 301 854 0410",
    "sg:postcode":"20777",
    "sg:province":"MD",
    "sg:tags":[
        "house",
        "contractor"
    ],
    "wof:name":"Urbas Plastering",
    "wof:placetype":"venue"
},
  "geometry": {"coordinates":[-76.977867,39.177903],"type":"Point"}
}