{
  "type": "Feature",
  "properties": {
    "iso:country":"US",
    "sg:address":"6826 Harford Rd",
    "sg:city":"Parkville",
    "sg:classifiers":[
        {
            "category":"Restaurant",
            "type":"Food & Drink"
        }
    ],
    "sg:phone":"+1 410 539 1114",
    "sg:postcode":"21234",
    "sg:province":"MD",
    "sg:tags":[
        "caterer"
    ],
    "wof:name":"Bay Leaf Caterers",
    "wof:placetype":"venue"
},
  "geometry": {"coordinates":[-76.550533,39.365051],"type":"Point"}
}