{
  "type": "Feature",
  "properties": {
    "iso:country":"US",
    "sg:address":"9891 Brokenland Pkwy",
    "sg:city":"Columbia",
    "sg:classifiers":[
        {
            "category":"Professional",
            "subcategory":"Management & Consulting",
            "type":"Services"
        }
    ],
    "sg:phone":"+1 410 290 8217",
    "sg:postcode":"21046",
    "sg:province":"MD",
    "sg:tags":[
        "consultant",
        "educational"
    ],
    "wof:name":"Pearson Professional Centers",
    "wof:placetype":"venue"
},
  "geometry": {"coordinates":[-76.85178399999999,39.191662],"type":"Point"}
}