{
  "type": "Feature",
  "properties": {
    "iso:country":"US",
    "sg:address":"9737 Washingtonian Blvd 10 Ste 100",
    "sg:city":"Gaithersburg",
    "sg:classifiers":[
        {
            "category":"Wholesale",
            "subcategory":"Books, Periodicals, & Newspapers",
            "type":"Manufacturing & Wholesale Goods"
        }
    ],
    "sg:phone":"+1 301 287 2700",
    "sg:postcode":"20878",
    "sg:province":"MD",
    "sg:tags":[
        "publisher",
        "book"
    ],
    "wof:name":"Sap Press",
    "wof:placetype":"venue"
},
  "geometry": {"coordinates":[-77.192831,39.113477],"type":"Point"}
}