{
  "type": "Feature",
  "properties": {
    "addr:full":"700 Nursery Rd Linthicum Hts MD 21090",
    "addr:housenumber":"700",
    "addr:postcode":"21090",
    "addr:street":"Nursery Rd",
    "iso:country":"US",
    "sg:address":"700 Nursery Rd",
    "sg:city":"Linthicum Hts",
    "sg:classifiers":[
        {
            "category":"Retail",
            "subcategory":"Auto Rental",
            "type":"Services"
        }
    ],
    "sg:phone":"+1 410 789 9499",
    "sg:postcode":"21090",
    "sg:province":"MD",
    "sg:tags":[
        "renting",
        "automobile"
    ],
    "wof:name":"Enterprise Rent-A-Car",
    "wof:placetype":"venue"
},
  "geometry": {"coordinates":[-76.657217,39.224285],"type":"Point"}
}