{
  "type": "Feature",
  "properties": {
    "addr:full":"7595 Greenbelt Rd Greenbelt MD 20770",
    "addr:housenumber":"7595",
    "addr:postcode":"20770",
    "addr:street":"Greenbelt Rd",
    "iso:country":"US",
    "sg:address":"7595 Greenbelt Rd",
    "sg:city":"Greenbelt",
    "sg:classifiers":[
        {
            "category":"Coffee & Tea",
            "type":"Food & Drink"
        }
    ],
    "sg:menulink":"http://www.allmenus.com/md/berwyn/119049-starbucks-coffee/menu/",
    "sg:phone":"+1 301 345 0150",
    "sg:postcode":"20770",
    "sg:province":"MD",
    "sg:tags":[
        "american"
    ],
    "wof:name":"Starbucks Coffee",
    "wof:placetype":"venue"
},
  "geometry": {"coordinates":[-76.872253,38.993462],"type":"Point"}
}