{
  "type": "Feature",
  "properties": {
    "iso:country":"US",
    "sg:address":"9101 51st Pl",
    "sg:city":"College Park",
    "sg:classifiers":[
        {
            "category":"Retail",
            "subcategory":"Auto Repair",
            "type":"Services"
        }
    ],
    "sg:phone":"+1 301 345 7727",
    "sg:postcode":"20740",
    "sg:province":"MD",
    "sg:tags":[
        "body",
        "automobile",
        "painting"
    ],
    "wof:name":"MAACO Auto Painting & Bodywork",
    "wof:placetype":"venue"
},
  "geometry": {"coordinates":[-76.920344,39.000207],"type":"Point"}
}