{
  "type": "Feature",
  "properties": {
    "iso:country":"US",
    "sg:address":"595 Main St",
    "sg:city":"Laurel",
    "sg:classifiers":[
        {
            "category":"Professional",
            "subcategory":"Lawyer & Legal Services",
            "type":"Services"
        }
    ],
    "sg:phone":"+1 301 317 6300",
    "sg:postcode":"20707",
    "sg:province":"MD",
    "sg:tags":[
        "attorney"
    ],
    "wof:name":"Gale & Walthall",
    "wof:placetype":"venue"
},
  "geometry": {"coordinates":[-76.851239,39.107397],"type":"Point"}
}