{
  "type": "Feature",
  "properties": {
    "addr:full":"7908 Red Jacket Way Jessup MD 20794",
    "addr:housenumber":"7908",
    "addr:postcode":"20794",
    "addr:street":"Red Jacket Way",
    "iso:country":"US",
    "sg:address":"7908 Red Jacket Way",
    "sg:city":"Jessup",
    "sg:classifiers":[
        {
            "category":"Banks & Credit Unions",
            "subcategory":"Financial Services",
            "type":"Services"
        },
        {
            "category":"Professional",
            "subcategory":"Business Services",
            "type":"Services"
        }
    ],
    "sg:phone":"+1 301 725 7567",
    "sg:postcode":"20794",
    "sg:province":"MD",
    "sg:tags":[
        "management"
    ],
    "wof:name":"Richard Sullivan",
    "wof:placetype":"venue"
},
  "geometry": {"coordinates":[-76.8276,39.153188],"type":"Point"}
}