{
  "type": "Feature",
  "properties": {
    "addr:full":"309 Frederick St Cumberland MD 21502",
    "addr:housenumber":"309",
    "addr:postcode":"21502",
    "addr:street":"Frederick St",
    "iso:country":"US",
    "sg:address":"309 Frederick St",
    "sg:city":"Cumberland",
    "sg:classifiers":[
        {
            "category":"Organizations",
            "subcategory":"Religious Organization",
            "type":"Services"
        }
    ],
    "sg:phone":"+1 301 759 6398",
    "sg:postcode":"21502",
    "sg:province":"MD",
    "sg:tags":[
        "church"
    ],
    "wof:name":"Metropolitan AME Church",
    "wof:placetype":"venue"
},
  "geometry": {"coordinates":[-78.760316,39.656127],"type":"Point"}
}