{
  "type": "Feature",
  "properties": {
    "addr:full":"9216 Liberty Rd Randallstown MD 21133",
    "addr:housenumber":"9216",
    "addr:postcode":"21133",
    "addr:street":"Liberty Rd",
    "iso:country":"US",
    "sg:address":"9216 Liberty Rd",
    "sg:city":"Randallstown",
    "sg:classifiers":[
        {
            "category":"Organizations",
            "subcategory":"Religious Organization",
            "type":"Services"
        }
    ],
    "sg:phone":"+1 410 521 5802",
    "sg:postcode":"21133",
    "sg:province":"MD",
    "sg:tags":[
        "church"
    ],
    "wof:name":"Victory In Jesus Baptist Chr",
    "wof:placetype":"venue"
},
  "geometry": {"coordinates":[-76.799685,39.369423],"type":"Point"}
}