{
  "type": "Feature",
  "properties": {
    "addr:full":"14 White Oak Ct Severna Park MD 21146",
    "addr:housenumber":"14",
    "addr:postcode":"21146",
    "addr:street":"White Oak Ct",
    "iso:country":"US",
    "sg:address":"14 White Oak Ct",
    "sg:city":"Severna Park",
    "sg:classifiers":[
        {
            "category":"Building & Trades",
            "subcategory":"Construction",
            "type":"Services"
        }
    ],
    "sg:phone":"+1 410 647 6325",
    "sg:postcode":"21146",
    "sg:province":"MD",
    "sg:tags":[
        "residential"
    ],
    "wof:name":"Nmv Ltd",
    "wof:placetype":"venue"
},
  "geometry": {"coordinates":[-76.559648,39.071556],"type":"Point"}
}