{
  "type": "Feature",
  "properties": {
    "addr:full":"10 N Calvert St Ste 142 Baltimore MD 21202",
    "addr:housenumber":"10",
    "addr:postcode":"21202",
    "addr:street":"N Calvert St Ste 142",
    "iso:country":"US",
    "sg:address":"10 N Calvert St Ste 142",
    "sg:city":"Baltimore",
    "sg:classifiers":[
        {
            "category":"Professional",
            "subcategory":"Lawyer & Legal Services",
            "type":"Services"
        }
    ],
    "sg:phone":"+1 410 244 0850",
    "sg:postcode":"21202",
    "sg:province":"MD",
    "wof:name":"Melissa Phinn At Law",
    "wof:placetype":"venue"
},
  "geometry": {"coordinates":[-76.612467,39.290039],"type":"Point"}
}