{
  "type": "Feature",
  "properties": {
    "iso:country":"US",
    "sg:address":"900 Seton Dr",
    "sg:city":"Cumberland",
    "sg:classifiers":[
        {
            "category":"Health Services",
            "subcategory":"Clinic",
            "type":"Services"
        },
        {
            "category":"Health Services",
            "subcategory":"Nursing And Care Facility",
            "type":"Services"
        },
        {
            "category":"Health Services",
            "subcategory":"Health Practitioner",
            "type":"Services"
        },
        {
            "category":"Health Services",
            "subcategory":"Hospice",
            "type":"Services"
        },
        {
            "category":"Community Center",
            "type":"Public Place"
        }
    ],
    "sg:phone":"+1 301 723 6570",
    "sg:postcode":"21502",
    "sg:province":"MD",
    "sg:tags":[
        "home",
        "medical",
        "eldercare-home"
    ],
    "wof:name":"Western Maryland Health System",
    "wof:placetype":"venue"
},
  "geometry": {"coordinates":[-78.79724899999999,39.654518],"type":"Point"}
}