{
  "type": "Feature",
  "properties": {
    "addr:full":"47 Main St Reisterstown MD 21136",
    "addr:housenumber":"47",
    "addr:postcode":"21136",
    "addr:street":"Main St",
    "iso:country":"US",
    "sg:address":"47 Main St",
    "sg:city":"Reisterstown",
    "sg:classifiers":[
        {
            "category":"Shopping",
            "type":"Retail Goods"
        }
    ],
    "sg:phone":"+1 410 517 0880",
    "sg:postcode":"21136",
    "sg:province":"MD",
    "sg:tags":[
        "picture",
        "frame"
    ],
    "wof:name":"Reisterstown Custom Picture",
    "wof:placetype":"venue"
},
  "geometry": {"coordinates":[-76.82935000000001,39.46697],"type":"Point"}
}