{
  "type": "Feature",
  "properties": {
    "iso:country":"US",
    "sg:address":"1210 Guadelupe Ct",
    "sg:city":"Westminster",
    "sg:classifiers":[
        {
            "category":"Professional",
            "type":"Services"
        }
    ],
    "sg:phone":"+1 410 857 4262",
    "sg:postcode":"21157",
    "sg:province":"MD",
    "wof:name":"Dave S World",
    "wof:placetype":"venue"
},
  "geometry": {"coordinates":[-76.95072500000001,39.603765],"type":"Point"}
}