{
  "type": "Feature",
  "properties": {
    "addr:full":"8021 Harford Rd Parkville MD 21234",
    "addr:housenumber":"8021",
    "addr:postcode":"21234",
    "addr:street":"Harford Rd",
    "iso:country":"US",
    "sg:address":"8021 Harford Rd",
    "sg:city":"Parkville",
    "sg:classifiers":[
        {
            "category":"Professional",
            "type":"Services"
        }
    ],
    "sg:phone":"+1 410 665 1311",
    "sg:postcode":"21234",
    "sg:province":"MD",
    "sg:tags":[
        "establishment"
    ],
    "wof:name":"Cedar Chest Shop",
    "wof:placetype":"venue"
},
  "geometry": {"coordinates":[-76.540761,39.375959],"type":"Point"}
}