{
  "type": "Feature",
  "properties": {
    "iso:country":"US",
    "sg:address":"6904 Decatur St",
    "sg:city":"Hyattsville",
    "sg:classifiers":[
        {
            "category":"Social Services",
            "subcategory":"Child Care",
            "type":"Services"
        }
    ],
    "sg:phone":"+1 301 505 0062",
    "sg:postcode":"20784",
    "sg:province":"MD",
    "wof:name":"TLC Child Development Center",
    "wof:placetype":"venue"
},
  "geometry": {"coordinates":[-76.89666099999999,38.949119],"type":"Point"}
}