{
  "type": "Feature",
  "properties": {
    "addr:full":"8602 Lonicera Ct Brandywine MD 20613",
    "addr:housenumber":"8602",
    "addr:postcode":"20613",
    "addr:street":"Lonicera Ct",
    "iso:country":"US",
    "sg:address":"8602 Lonicera Ct",
    "sg:city":"Brandywine",
    "sg:classifiers":[
        {
            "category":"Transit Center",
            "subcategory":"Freight",
            "type":"Transportation"
        }
    ],
    "sg:phone":"+1 301 782 2844",
    "sg:postcode":"20613",
    "sg:province":"MD",
    "sg:tags":[
        "trucking-motor"
    ],
    "wof:name":"Covenant Trucking",
    "wof:placetype":"venue"
},
  "geometry": {"coordinates":[-76.85616400000001,38.692914],"type":"Point"}
}