{
  "type": "Feature",
  "properties": {
    "iso:country":"US",
    "sg:address":"9400 Snowden River Pkwy Columbia Marketplace - Suite 111",
    "sg:city":"Columbia",
    "sg:classifiers":[
        {
            "category":"Restaurant",
            "type":"Food & Drink"
        }
    ],
    "sg:phone":"+1 410 381 6111",
    "sg:postcode":"21045",
    "sg:province":"MD",
    "sg:tags":[
        "greek"
    ],
    "sg:website":"www.royalpizzamd.com",
    "wof:name":"Royal Pizza",
    "wof:placetype":"venue"
},
  "geometry": {"coordinates":[-76.835658,39.176102],"type":"Point"}
}