{
  "type": "Feature",
  "properties": {
    "addr:full":"1428 Annapolis Rd Odenton MD 21113",
    "addr:housenumber":"1428",
    "addr:postcode":"21113",
    "addr:street":"Annapolis Rd",
    "iso:country":"US",
    "sg:address":"1428 Annapolis Rd",
    "sg:city":"Odenton",
    "sg:classifiers":[
        {
            "category":"Real Estate",
            "subcategory":"Real Estate Services",
            "type":"Services"
        },
        {
            "category":"Real Estate",
            "subcategory":"Real Estate Agent",
            "type":"Services"
        }
    ],
    "sg:phone":"+1 410 672 2888",
    "sg:postcode":"21113",
    "sg:province":"MD",
    "sg:tags":[
        "management",
        "commercial"
    ],
    "sg:website":"http://towncenterrealty.net",
    "wof:name":"Town Center Realty",
    "wof:placetype":"venue"
},
  "geometry": {"coordinates":[-76.711218,39.090824],"type":"Point"}
}