{
  "type": "Feature",
  "properties": {
    "addr:full":"2849 Woodbrook Ave Baltimore MD 21217",
    "addr:housenumber":"2849",
    "addr:postcode":"21217",
    "addr:street":"Woodbrook Ave",
    "iso:country":"US",
    "sg:address":"2849 Woodbrook Ave",
    "sg:city":"Baltimore",
    "sg:classifiers":[
        {
            "category":"Professional",
            "subcategory":"Computer Services",
            "type":"Services"
        }
    ],
    "sg:phone":"+1 410 523 6735",
    "sg:postcode":"21217",
    "sg:province":"MD",
    "sg:tags":[
        "repair",
        "equipment-service"
    ],
    "sg:website":"theboxdr.com/",
    "wof:name":"TheBoxDr.com",
    "wof:placetype":"venue"
},
  "geometry": {"coordinates":[-76.646534,39.314886],"type":"Point"}
}