{
  "type": "Feature",
  "properties": {
    "addr:full":"9603 Jacqueline Dr Fort Washington MD 20744",
    "addr:housenumber":"9603",
    "addr:postcode":"20744",
    "addr:street":"Jacqueline Dr",
    "iso:country":"US",
    "sg:address":"9603 Jacqueline Dr",
    "sg:city":"Fort Washington",
    "sg:classifiers":[
        {
            "category":"Education",
            "subcategory":"Special Training",
            "type":"Public Place"
        }
    ],
    "sg:phone":"+1 301 801 2650",
    "sg:postcode":"20744",
    "sg:province":"MD",
    "sg:tags":[
        "development",
        "community"
    ],
    "wof:name":"Touch - Teaching Our Urban Com",
    "wof:placetype":"venue"
},
  "geometry": {"coordinates":[-76.960403,38.756861],"type":"Point"}
}