{
  "type": "Feature",
  "properties": {
    "iso:country":"US",
    "sg:address":"5625 Harbor Valley Dr",
    "sg:city":"Brooklyn",
    "sg:classifiers":[
        {
            "category":"Personal",
            "type":"Services"
        }
    ],
    "sg:phone":"+1 410 636 1569",
    "sg:postcode":"21225",
    "sg:province":"MD",
    "sg:tags":[
        "butlers'",
        "maids'"
    ],
    "wof:name":"Molly Maid",
    "wof:placetype":"venue"
},
  "geometry": {"coordinates":[-76.62275699999999,39.22102],"type":"Point"}
}