{
  "type": "Feature",
  "properties": {
    "addr:full":"20953 Great Mills Rd Lexington Park MD 20653",
    "addr:housenumber":"20953",
    "addr:postcode":"20653",
    "addr:street":"Great Mills Rd",
    "iso:country":"US",
    "sg:address":"20953 Great Mills Rd",
    "sg:city":"Lexington Park",
    "sg:classifiers":[
        {
            "category":"Insurance",
            "subcategory":"Insurance Agent",
            "type":"Services"
        }
    ],
    "sg:phone":"+1 301 862 4844",
    "sg:postcode":"20653",
    "sg:province":"MD",
    "wof:name":"Allstate Insurance",
    "wof:placetype":"venue"
},
  "geometry": {"coordinates":[-76.49127799999999,38.244236],"type":"Point"}
}