{
  "type": "Feature",
  "properties": {
    "iso:country":"US",
    "sg:address":"11005 Waycroft Way",
    "sg:city":"Rockville",
    "sg:classifiers":[
        {
            "category":"Professional",
            "subcategory":"Research",
            "type":"Services"
        }
    ],
    "sg:phone":"+1 301 792 8126",
    "sg:postcode":"20852",
    "sg:province":"MD",
    "sg:tags":[
        "educational"
    ],
    "sg:website":"http://www.viraldefense.org",
    "wof:name":"Viral Defense Foundation Inc",
    "wof:placetype":"venue"
},
  "geometry": {"coordinates":[-77.111659,39.036368],"type":"Point"}
}