{
  "type": "Feature",
  "properties": {
    "addr:full":"2258 Commissary Cir Odenton MD 21113",
    "addr:housenumber":"2258",
    "addr:postcode":"21113",
    "addr:street":"Commissary Cir",
    "iso:country":"US",
    "sg:address":"2258 Commissary Cir",
    "sg:city":"Odenton",
    "sg:classifiers":[
        {
            "category":"Professional",
            "subcategory":"Art Services",
            "type":"Services"
        }
    ],
    "sg:phone":"+1 410 672 2258",
    "sg:postcode":"21113",
    "sg:province":"MD",
    "sg:tags":[
        "graphic",
        "designer"
    ],
    "wof:name":"Yak Studios",
    "wof:placetype":"venue"
},
  "geometry": {"coordinates":[-76.720744,39.108865],"type":"Point"}
}