{
  "type": "Feature",
  "properties": {
    "iso:country":"US",
    "sg:address":"3998 Roland Ave",
    "sg:city":"Baltimore",
    "sg:classifiers":[
        {
            "category":"Restaurant",
            "type":"Food & Drink"
        }
    ],
    "sg:phone":"+1 410 235 1688",
    "sg:postcode":"21211",
    "sg:province":"MD",
    "sg:tags":[
        "sushi",
        "bar",
        "chinese"
    ],
    "sg:website":"no1chinesekitchen.com/",
    "wof:name":"Number One Chinese Kitchen",
    "wof:placetype":"venue"
},
  "geometry": {"coordinates":[-76.633252,39.337118],"type":"Point"}
}