{
  "type": "Feature",
  "properties": {
    "iso:country":"US",
    "sg:address":"11121 York Rd Ste E",
    "sg:city":"Cockeysville",
    "sg:classifiers":[
        {
            "category":"Personal",
            "subcategory":"Tanning Parlor",
            "type":"Services"
        }
    ],
    "sg:phone":"+1 410 771 1772",
    "sg:postcode":"21030",
    "sg:province":"MD",
    "wof:name":"The Tan Stand",
    "wof:placetype":"venue"
},
  "geometry": {"coordinates":[-76.647634,39.490233],"type":"Point"}
}