{
  "type": "Feature",
  "properties": {
    "iso:country":"US",
    "sg:address":"4100 Franklin St",
    "sg:city":"Kensington",
    "sg:classifiers":[
        {
            "category":"Professional",
            "subcategory":"Management & Consulting",
            "type":"Services"
        }
    ],
    "sg:phone":"+1 301 942 5690",
    "sg:postcode":"20895",
    "sg:province":"MD",
    "sg:tags":[
        "consultant",
        "business"
    ],
    "wof:name":"Prosource Systems",
    "wof:placetype":"venue"
},
  "geometry": {"coordinates":[-77.081107,39.018514],"type":"Point"}
}