{
  "type": "Feature",
  "properties": {
    "iso:country":"US",
    "sg:address":"891 Rockville Pike",
    "sg:city":"Rockville",
    "sg:classifiers":[
        {
            "category":"Personal",
            "subcategory":"Shoe Repair & Shine",
            "type":"Services"
        }
    ],
    "sg:phone":"+1 301 424 0908",
    "sg:postcode":"20852",
    "sg:province":"MD",
    "sg:tags":[
        "repairing",
        "boot"
    ],
    "wof:name":"Nick's Shoe Repair",
    "wof:placetype":"venue"
},
  "geometry": {"coordinates":[-77.13902899999999,39.076814],"type":"Point"}
}