{
  "type": "Feature",
  "properties": {
    "addr:full":"9116 Fall River Ln Potomac MD 20854",
    "addr:housenumber":"9116",
    "addr:postcode":"20854",
    "addr:street":"Fall River Ln",
    "iso:country":"US",
    "sg:address":"9116 Fall River Ln",
    "sg:city":"Potomac",
    "sg:classifiers":[
        {
            "category":"Professional",
            "subcategory":"Business Services",
            "type":"Services"
        }
    ],
    "sg:phone":"+1 301 299 2707",
    "sg:postcode":"20854",
    "sg:province":"MD",
    "sg:tags":[
        "convention",
        "meeting",
        "facility"
    ],
    "wof:name":"Event Productions Inc",
    "wof:placetype":"venue"
},
  "geometry": {"coordinates":[-77.18648399999999,39.039163],"type":"Point"}
}