{
  "type": "Feature",
  "properties": {
    "iso:country":"US",
    "sg:address":"5335 Wisconsin Ave NW",
    "sg:city":"Washington",
    "sg:classifiers":[
        {
            "category":"Communications",
            "type":"Services"
        }
    ],
    "sg:phone":"+1 202 478 9651",
    "sg:postcode":"20015",
    "sg:province":"MD",
    "wof:name":"Axiom Communications Group",
    "wof:placetype":"venue"
},
  "geometry": {"coordinates":[-77.084846,38.959041],"type":"Point"}
}