{
  "type": "Feature",
  "properties": {
    "iso:country":"US",
    "sg:address":"11917 Falls Rd",
    "sg:city":"Potomac",
    "sg:classifiers":[
        {
            "category":"Social Services",
            "type":"Services"
        }
    ],
    "sg:phone":"+1 301 738 9268",
    "sg:postcode":"20854",
    "sg:province":"MD",
    "wof:name":"Ltp Challenge",
    "wof:placetype":"venue"
},
  "geometry": {"coordinates":[-77.185751,39.051931],"type":"Point"}
}