{
  "type": "Feature",
  "properties": {
    "iso:country":"US",
    "sg:address":"9007 Seneca Ln",
    "sg:city":"Bethesda",
    "sg:classifiers":[
        {
            "category":"Restaurant",
            "type":"Food & Drink"
        }
    ],
    "sg:phone":"+1 301 564 1642",
    "sg:postcode":"20817",
    "sg:province":"MD",
    "wof:name":"House Grill",
    "wof:placetype":"venue"
},
  "geometry": {"coordinates":[-77.111216,39.002932],"type":"Point"}
}