{
  "type": "Feature",
  "properties": {
    "iso:country":"US",
    "sg:address":"6080 Falls Rd",
    "sg:city":"Baltimore",
    "sg:classifiers":[
        {
            "category":"Personal",
            "subcategory":"Beauty Salon",
            "type":"Services"
        }
    ],
    "sg:phone":"+1 410 377 4300",
    "sg:postcode":"21209",
    "sg:province":"MD",
    "wof:name":"D K Salon & Day Spa",
    "wof:placetype":"venue"
},
  "geometry": {"coordinates":[-76.650717,39.375104],"type":"Point"}
}