{
  "type": "Feature",
  "properties": {
    "iso:country":"US",
    "sg:address":"711 W 40th St Ste 202",
    "sg:city":"Baltimore",
    "sg:classifiers":[
        {
            "category":"Health Services",
            "subcategory":"Clinic",
            "type":"Services"
        }
    ],
    "sg:phone":"+1 410 235 3255",
    "sg:postcode":"21211",
    "sg:province":"MD",
    "sg:tags":[
        "welfare"
    ],
    "wof:name":"Integrative Health Wellness Center",
    "wof:placetype":"venue"
},
  "geometry": {"coordinates":[-76.628646,39.337208],"type":"Point"}
}