{
  "type": "Feature",
  "properties": {
    "addr:full":"515 S Camp Meade Rd Linthicum Hts MD 21090",
    "addr:housenumber":"515",
    "addr:postcode":"21090",
    "addr:street":"S Camp Meade Rd",
    "iso:country":"US",
    "sg:address":"515 S Camp Meade Rd",
    "sg:city":"Linthicum Hts",
    "sg:classifiers":[
        {
            "category":"Government",
            "subcategory":"Post Office",
            "type":"Public Place"
        }
    ],
    "sg:phone":"+1 410 859 0227",
    "sg:postcode":"21090",
    "sg:province":"MD",
    "wof:name":"US Post Office",
    "wof:placetype":"venue"
},
  "geometry": {"coordinates":[-76.656023,39.199341],"type":"Point"}
}