{
  "type": "Feature",
  "properties": {
    "iso:country":"US",
    "sg:address":"6006 Greenbelt Rd",
    "sg:city":"Greenbelt",
    "sg:classifiers":[
        {
            "category":"Organizations",
            "subcategory":"Religious Organization",
            "type":"Services"
        }
    ],
    "sg:phone":"+1 301 773 8007",
    "sg:postcode":"20770",
    "sg:province":"MD",
    "sg:tags":[
        "church"
    ],
    "wof:name":"Friends In Christ",
    "wof:placetype":"venue"
},
  "geometry": {"coordinates":[-76.911911,38.998073],"type":"Point"}
}