{
  "type": "Feature",
  "properties": {
    "iso:country":"US",
    "sg:address":"5022 Avoca Ave",
    "sg:city":"Ellicott City",
    "sg:classifiers":[
        {
            "category":"Organizations",
            "subcategory":"Religious Organization",
            "type":"Services"
        }
    ],
    "sg:phone":"+1 410 465 0206",
    "sg:postcode":"21043",
    "sg:province":"MD",
    "sg:tags":[
        "church"
    ],
    "wof:name":"First Mennonite Church",
    "wof:placetype":"venue"
},
  "geometry": {"coordinates":[-76.807722,39.235919],"type":"Point"}
}