{
  "type": "Feature",
  "properties": {
    "iso:country":"US",
    "sg:address":"7290 Cradlerock Way",
    "sg:city":"Columbia",
    "sg:classifiers":[
        {
            "category":"Shopping",
            "subcategory":"Computers & Home Electronics",
            "type":"Retail Goods"
        }
    ],
    "sg:phone":"+1 410 309 9898",
    "sg:postcode":"21045",
    "sg:province":"MD",
    "sg:tags":[
        "software"
    ],
    "wof:name":"W Z Technologies LLC",
    "wof:placetype":"venue"
},
  "geometry": {"coordinates":[-76.84939,39.185831],"type":"Point"}
}