{
  "type": "Feature",
  "properties": {
    "addr:full":"7 Carroll St Westminster MD 21157",
    "addr:housenumber":"7",
    "addr:postcode":"21157",
    "addr:street":"Carroll St",
    "iso:country":"US",
    "sg:address":"7 Carroll St",
    "sg:city":"Westminster",
    "sg:classifiers":[
        {
            "category":"Home & Garden",
            "subcategory":"Building Materials",
            "type":"Retail Goods"
        }
    ],
    "sg:phone":"+1 410 876 8383",
    "sg:postcode":"21157",
    "sg:province":"MD",
    "sg:tags":[
        "paint"
    ],
    "wof:name":"Duron Paints & Wallcoverings",
    "wof:placetype":"venue"
},
  "geometry": {"coordinates":[-76.997781,39.57742],"type":"Point"}
}