{
  "type": "Feature",
  "properties": {
    "iso:country":"US",
    "sg:address":"7729 Finns Ln",
    "sg:city":"Lanham",
    "sg:classifiers":[
        {
            "category":"Social Services",
            "subcategory":"Child Care",
            "type":"Services"
        }
    ],
    "sg:phone":"+1 301 429 0008",
    "sg:postcode":"20706",
    "sg:province":"MD",
    "sg:tags":[
        "day"
    ],
    "wof:name":"Kids N Kids",
    "wof:placetype":"venue"
},
  "geometry": {"coordinates":[-76.878601,38.953201],"type":"Point"}
}