{
  "type": "Feature",
  "properties": {
    "iso:country":"US",
    "sg:address":"8260 Patuxent Range Rd",
    "sg:city":"Jessup",
    "sg:classifiers":[
        {
            "category":"Wholesale",
            "subcategory":"Electrical",
            "type":"Manufacturing & Wholesale Goods"
        }
    ],
    "sg:phone":"+1 301 490 1844",
    "sg:postcode":"20794",
    "sg:province":"MD",
    "sg:tags":[
        "supply",
        "sign"
    ],
    "wof:name":"Grimco",
    "wof:placetype":"venue"
},
  "geometry": {"coordinates":[-76.796329,39.146913],"type":"Point"}
}