{
  "type": "Feature",
  "properties": {
    "iso:country":"US",
    "sg:address":"9950 Business Pkwy Ste 240",
    "sg:city":"Lanham",
    "sg:classifiers":[
        {
            "category":"Shopping",
            "subcategory":"Stationery & Office Supplies",
            "type":"Retail Goods"
        },
        {
            "category":"Home & Garden",
            "subcategory":"Furniture",
            "type":"Retail Goods"
        }
    ],
    "sg:phone":"+1 301 577 1890",
    "sg:postcode":"20706",
    "sg:province":"MD",
    "sg:tags":[
        "equipment",
        "store"
    ],
    "sg:website":"www.bfr.com",
    "wof:name":"Brook Furniture Rental",
    "wof:placetype":"venue"
},
  "geometry": {"coordinates":[-76.831029,38.95866],"type":"Point"}
}