{
  "type": "Feature",
  "properties": {
    "iso:country":"US",
    "sg:address":"2030 E Baltimore St",
    "sg:city":"Baltimore",
    "sg:classifiers":[
        {
            "category":"Building & Trades",
            "subcategory":"Construction",
            "type":"Services"
        }
    ],
    "sg:phone":"+1 410 925 7207",
    "sg:postcode":"21231",
    "sg:province":"MD",
    "sg:tags":[
        "wallcoverings-installation",
        "wallpaper",
        "painting",
        "contractor"
    ],
    "wof:name":"Kiwi Painting And Renovation",
    "wof:placetype":"venue"
},
  "geometry": {"coordinates":[-76.588112,39.291754],"type":"Point"}
}