{
  "type": "Feature",
  "properties": {
    "addr:full":"5407 Loch Raven Blvd Baltimore MD 21239",
    "addr:housenumber":"5407",
    "addr:postcode":"21239",
    "addr:street":"Loch Raven Blvd",
    "iso:country":"US",
    "sg:address":"5407 Loch Raven Blvd",
    "sg:city":"Baltimore",
    "sg:classifiers":[
        {
            "category":"Education",
            "subcategory":"School",
            "type":"Public Place"
        }
    ],
    "sg:phone":"+1 410 433 2775",
    "sg:postcode":"21239",
    "sg:province":"MD",
    "sg:tags":[
        "high",
        "middle",
        "elementary"
    ],
    "sg:website":"www.cardinalshehanschool.org",
    "wof:name":"Cardinal Shehan School",
    "wof:placetype":"venue"
},
  "geometry": {"coordinates":[-76.589401,39.355598],"type":"Point"}
}