{
  "type": "Feature",
  "properties": {
    "iso:country":"US",
    "sg:address":"7085 Samuel Morse Dr",
    "sg:city":"Columbia",
    "sg:classifiers":[
        {
            "category":"Health Services",
            "subcategory":"Doctor",
            "type":"Services"
        },
        {
            "category":"Health Services",
            "subcategory":"Hospital",
            "type":"Services"
        }
    ],
    "sg:phone":"+1 301 621 8500",
    "sg:postcode":"21046",
    "sg:province":"MD",
    "sg:tags":[
        "nursing",
        "consultant",
        "medical",
        "practice",
        "home"
    ],
    "sg:website":"http://www.mcbeeassociates.com",
    "wof:name":"Mcbee Associates Inc.",
    "wof:placetype":"venue"
},
  "geometry": {"coordinates":[-76.80842800000001,39.170218],"type":"Point"}
}