{
  "type": "Feature",
  "properties": {
    "iso:country":"US",
    "sg:address":"105 Federal St",
    "sg:city":"Easton",
    "sg:classifiers":[
        {
            "category":"Professional",
            "subcategory":"Lawyer & Legal Services",
            "type":"Services"
        }
    ],
    "sg:phone":"+1 410 820 5733",
    "sg:postcode":"21601",
    "sg:province":"MD",
    "sg:tags":[
        "attorney"
    ],
    "wof:name":"Richard G Garrett",
    "wof:placetype":"venue"
},
  "geometry": {"coordinates":[-76.077562,38.775276],"type":"Point"}
}