{
  "type": "Feature",
  "properties": {
    "iso:country":"US",
    "sg:address":"7 Southfield Pl",
    "sg:city":"Baltimore",
    "sg:classifiers":[
        {
            "category":"Banks & Credit Unions",
            "subcategory":"Financial Services",
            "type":"Services"
        }
    ],
    "sg:phone":"+1 410 323 1834",
    "sg:postcode":"21212",
    "sg:province":"MD",
    "sg:tags":[
        "company",
        "holding"
    ],
    "wof:name":"Agerton Holding Co Inc",
    "wof:placetype":"venue"
},
  "geometry": {"coordinates":[-76.612729,39.354507],"type":"Point"}
}