{
  "type": "Feature",
  "properties": {
    "iso:country":"US",
    "sg:address":"8700 Groffs Mill Dr",
    "sg:city":"Owings Mills",
    "sg:classifiers":[
        {
            "category":"Real Estate",
            "subcategory":"Real Estate Operator",
            "type":"Services"
        }
    ],
    "sg:phone":"+1 410 654 6798",
    "sg:postcode":"21117",
    "sg:province":"MD",
    "sg:tags":[
        "condominium"
    ],
    "wof:name":"Spring Mill Condominiums",
    "wof:placetype":"venue"
},
  "geometry": {"coordinates":[-76.81014999999999,39.405001],"type":"Point"}
}