{
  "type": "Feature",
  "properties": {
    "iso:country":"US",
    "sg:address":"4641 Montgomery Ave",
    "sg:city":"Bethesda",
    "sg:classifiers":[
        {
            "category":"Shopping",
            "subcategory":"Computers & Home Electronics",
            "type":"Retail Goods"
        }
    ],
    "sg:phone":"+1 301 718 8880",
    "sg:postcode":"20814",
    "sg:province":"MD",
    "sg:tags":[
        "software"
    ],
    "wof:name":"NDG",
    "wof:placetype":"venue"
},
  "geometry": {"coordinates":[-77.093312,38.983823],"type":"Point"}
}