{
  "type": "Feature",
  "properties": {
    "iso:country":"US",
    "sg:address":"4 Bishops Rd",
    "sg:city":"Baltimore",
    "sg:classifiers":[
        {
            "category":"Professional",
            "subcategory":"Management & Consulting",
            "type":"Services"
        }
    ],
    "sg:phone":"+1 410 889 5010",
    "sg:postcode":"21218",
    "sg:province":"MD",
    "sg:tags":[
        "consultant",
        "business"
    ],
    "wof:name":"Sage Dining Svc Inc",
    "wof:placetype":"venue"
},
  "geometry": {"coordinates":[-76.615798,39.333885],"type":"Point"}
}