{
  "type": "Feature",
  "properties": {
    "addr:full":"8618 Loch Raven Blvd Towson MD 21286",
    "addr:housenumber":"8618",
    "addr:postcode":"21286",
    "addr:street":"Loch Raven Blvd",
    "iso:country":"US",
    "sg:address":"8618 Loch Raven Blvd",
    "sg:city":"Towson",
    "sg:classifiers":[
        {
            "category":"Retail",
            "subcategory":"Auto Rental",
            "type":"Services"
        }
    ],
    "sg:phone":"+1 410 825 2104",
    "sg:postcode":"21286",
    "sg:province":"MD",
    "sg:tags":[
        "renting",
        "truck",
        "leasing"
    ],
    "wof:name":"U-Haul Co",
    "wof:placetype":"venue"
},
  "geometry": {"coordinates":[-76.563225,39.395254],"type":"Point"}
}