{
  "type": "Feature",
  "properties": {
    "iso:country":"US",
    "sg:address":"5203 Lansing Dr",
    "sg:city":"Temple Hills",
    "sg:classifiers":[
        {
            "category":"Personal",
            "subcategory":"Beauty Salon",
            "type":"Services"
        }
    ],
    "sg:phone":"+1 301 449 6052",
    "sg:postcode":"20748",
    "sg:province":"MD",
    "sg:tags":[
        "shop"
    ],
    "wof:name":"CLD Hair Salon",
    "wof:placetype":"venue"
},
  "geometry": {"coordinates":[-76.917613,38.787779],"type":"Point"}
}