{
  "type": "Feature",
  "properties": {
    "addr:full":"208 Taylor Ave Annapolis MD 21401",
    "addr:housenumber":"208",
    "addr:postcode":"21401",
    "addr:street":"Taylor Ave",
    "iso:country":"US",
    "sg:address":"208 Taylor Ave",
    "sg:city":"Annapolis",
    "sg:classifiers":[
        {
            "category":"Building & Trades",
            "subcategory":"Plumbing",
            "type":"Services"
        }
    ],
    "sg:phone":"+1 410 268 7191",
    "sg:postcode":"21401",
    "sg:province":"MD",
    "sg:tags":[
        "plumbing",
        "contractor"
    ],
    "sg:website":"www.heidlerplumbing.com",
    "wof:name":"Heidler Inc",
    "wof:placetype":"venue"
},
  "geometry": {"coordinates":[-76.50594700000001,38.980558],"type":"Point"}
}