{
  "type": "Feature",
  "properties": {
    "iso:country":"US",
    "sg:address":"17 E 21st St",
    "sg:city":"Baltimore",
    "sg:classifiers":[
        {
            "category":"Personal",
            "subcategory":"Beauty Salon",
            "type":"Services"
        }
    ],
    "sg:phone":"+1 410 783 9914",
    "sg:postcode":"21218",
    "sg:province":"MD",
    "sg:tags":[
        "shop"
    ],
    "wof:name":"A Touch From Above Hair Salon",
    "wof:placetype":"venue"
},
  "geometry": {"coordinates":[-76.615132,39.313279],"type":"Point"}
}