{
  "type": "Feature",
  "properties": {
    "iso:country":"US",
    "sg:address":"1903 Research Blvd",
    "sg:city":"Rockville",
    "sg:classifiers":[
        {
            "category":"Banks & Credit Unions",
            "subcategory":"Bank",
            "type":"Services"
        }
    ],
    "sg:phone":"+1 301 309 1771",
    "sg:postcode":"20850",
    "sg:province":"MD",
    "wof:name":"Columbia Bank",
    "wof:placetype":"venue"
},
  "geometry": {"coordinates":[-77.181376,39.099318],"type":"Point"}
}