{
  "type": "Feature",
  "properties": {
    "iso:country":"US",
    "sg:address":"49 S Carroll St",
    "sg:city":"Frederick",
    "sg:classifiers":[
        {
            "category":"Real Estate",
            "subcategory":"Real Estate Agent",
            "type":"Services"
        }
    ],
    "sg:phone":"+1 301 662 8987",
    "sg:postcode":"21701",
    "sg:province":"MD",
    "wof:name":"Carroll Creek Realty",
    "wof:placetype":"venue"
},
  "geometry": {"coordinates":[-77.408005,39.412462],"type":"Point"}
}