{
  "type": "Feature",
  "properties": {
    "iso:country":"US",
    "sg:address":"53 Eastford Ct",
    "sg:city":"Parkville",
    "sg:classifiers":[
        {
            "category":"Retail",
            "subcategory":"Animal Services",
            "type":"Services"
        }
    ],
    "sg:phone":"+1 410 882 0424",
    "sg:postcode":"21234",
    "sg:province":"MD",
    "sg:tags":[
        "pet",
        "boarding",
        "sitting"
    ],
    "wof:name":"Jimmie's Petsitting Svc",
    "wof:placetype":"venue"
},
  "geometry": {"coordinates":[-76.533486,39.413618],"type":"Point"}
}