{
  "type": "Feature",
  "properties": {
    "iso:country":"US",
    "sg:address":"7909 Airy Hill Rd",
    "sg:city":"Chestertown",
    "sg:phone":"+1 410 778 2258",
    "sg:postcode":"21620",
    "sg:province":"MD",
    "sg:tags":[
        "farm",
        "corn",
        "soybean"
    ],
    "wof:name":"James Berna",
    "wof:placetype":"venue"
},
  "geometry": {"coordinates":[-76.097633,39.193305],"type":"Point"}
}