{
  "type": "Feature",
  "properties": {
    "addr:full":"11891 Knollcrest Ln La Plata MD 20646",
    "addr:housenumber":"11891",
    "addr:postcode":"20646",
    "addr:street":"Knollcrest Ln",
    "iso:country":"US",
    "sg:address":"11891 Knollcrest Ln",
    "sg:city":"La Plata",
    "sg:classifiers":[
        {
            "category":"Personal",
            "type":"Services"
        }
    ],
    "sg:phone":"+1 301 934 8584",
    "sg:postcode":"20646",
    "sg:province":"MD",
    "sg:tags":[
        "housing",
        "referral",
        "network"
    ],
    "wof:name":"Housing Network",
    "wof:placetype":"venue"
},
  "geometry": {"coordinates":[-76.901551,38.456229],"type":"Point"}
}