{
  "type": "Feature",
  "properties": {
    "addr:full":"15120 Turkey Foot Rd Gaithersburg MD 20878",
    "addr:housenumber":"15120",
    "addr:postcode":"20878",
    "addr:street":"Turkey Foot Rd",
    "iso:country":"US",
    "sg:address":"15120 Turkey Foot Rd",
    "sg:city":"Gaithersburg",
    "sg:classifiers":[
        {
            "category":"Organizations",
            "subcategory":"Religious Organization",
            "type":"Services"
        }
    ],
    "sg:phone":"+1 301 948 9127",
    "sg:postcode":"20878",
    "sg:province":"MD",
    "sg:tags":[
        "church"
    ],
    "wof:name":"Darnestown Presbyterian Church",
    "wof:placetype":"venue"
},
  "geometry": {"coordinates":[-77.28425799999999,39.103316],"type":"Point"}
}