{
  "type": "Feature",
  "properties": {
    "addr:full":"3737 Branch Ave Ste 4 Temple Hills MD 20748",
    "addr:housenumber":"3737",
    "addr:postcode":"20748",
    "addr:street":"Branch Ave Ste 4 Temple",
    "iso:country":"US",
    "sg:address":"3737 Branch Ave Ste 4",
    "sg:city":"Temple Hills",
    "sg:classifiers":[
        {
            "category":"Shopping",
            "subcategory":"Jewelry",
            "type":"Retail Goods"
        }
    ],
    "sg:phone":"+1 301 423 7001",
    "sg:postcode":"20748",
    "sg:province":"MD",
    "wof:name":"Gold Plaza",
    "wof:placetype":"venue"
},
  "geometry": {"coordinates":[-76.94740299999999,38.840401],"type":"Point"}
}