{
  "type": "Feature",
  "properties": {
    "iso:country":"US",
    "sg:address":"9000 Iron Horse Ln",
    "sg:city":"Pikesville",
    "sg:classifiers":[
        {
            "category":"Real Estate",
            "subcategory":"Real Estate Operator",
            "type":"Services"
        }
    ],
    "sg:phone":"+1 410 580 0102",
    "sg:postcode":"21208",
    "sg:province":"MD",
    "sg:tags":[
        "apartment"
    ],
    "wof:name":"Avalon Apartments",
    "wof:placetype":"venue"
},
  "geometry": {"coordinates":[-76.750721,39.395737],"type":"Point"}
}