{
  "type": "Feature",
  "properties": {
    "addr:full":"14532 Peddicord Rd Mount Airy MD 21771",
    "addr:postcode":"14532;21771",
    "addr:street":"Peddicord Rd",
    "iso:country":"US",
    "sg:address":"14532 Peddicord Rd",
    "sg:city":"Mount Airy",
    "sg:classifiers":[
        {
            "category":"Retail",
            "subcategory":"Repair Shop",
            "type":"Services"
        }
    ],
    "sg:phone":"+1 301 829 0929",
    "sg:postcode":"21771",
    "sg:province":"MD",
    "wof:name":"Hanans Mobile Lock Service",
    "wof:placetype":"venue"
},
  "geometry": {"coordinates":[-77.155565,39.443072],"type":"Point"}
}