{
  "type": "Feature",
  "properties": {
    "iso:country":"US",
    "sg:address":"9505 Deereco Rd",
    "sg:city":"Timonium",
    "sg:classifiers":[
        {
            "category":"Organizations",
            "subcategory":"Religious Organization",
            "type":"Services"
        }
    ],
    "sg:phone":"+1 410 494 7797",
    "sg:postcode":"21093",
    "sg:province":"MD",
    "sg:tags":[
        "church"
    ],
    "sg:website":"www.gfc.org",
    "wof:name":"Grace Fellowship Church",
    "wof:placetype":"venue"
},
  "geometry": {"coordinates":[-76.63838,39.452151],"type":"Point"}
}