{
  "type": "Feature",
  "properties": {
    "iso:country":"US",
    "sg:address":"5804 Tanglewood Dr",
    "sg:city":"Bethesda",
    "sg:classifiers":[
        {
            "category":"Real Estate",
            "subcategory":"Architect",
            "type":"Services"
        }
    ],
    "sg:phone":"+1 301 320 1680",
    "sg:postcode":"20817",
    "sg:province":"MD",
    "sg:tags":[
        "architects'",
        "specification",
        "construction",
        "builders'",
        "architectural"
    ],
    "sg:website":"http://www.hainsarch.com",
    "wof:name":"Hains Architects Inc",
    "wof:placetype":"venue"
},
  "geometry": {"coordinates":[-77.11672,38.979044],"type":"Point"}
}