{
  "type": "Feature",
  "properties": {
    "addr:full":"4015 Penhurst Ave Baltimore MD 21215",
    "addr:housenumber":"4015",
    "addr:postcode":"21215",
    "addr:street":"Penhurst Ave",
    "iso:country":"US",
    "sg:address":"4015 Penhurst Ave",
    "sg:city":"Baltimore",
    "sg:classifiers":[
        {
            "category":"Organizations",
            "subcategory":"Religious Organization",
            "type":"Services"
        }
    ],
    "sg:phone":"+1 410 664 1700",
    "sg:postcode":"21215",
    "sg:province":"MD",
    "wof:name":"New Commandment Baptist Chruch",
    "wof:placetype":"venue"
},
  "geometry": {"coordinates":[-76.6866,39.3386],"type":"Point"}
}