{
  "type": "Feature",
  "properties": {
    "addr:full":"7804 Livingston Rd Oxon Hill MD 20745",
    "addr:housenumber":"7804",
    "addr:postcode":"20745",
    "addr:street":"Livingston Rd",
    "iso:country":"US",
    "sg:address":"7804 Livingston Rd",
    "sg:city":"Oxon Hill",
    "sg:classifiers":[
        {
            "category":"Organizations",
            "subcategory":"Religious Organization",
            "type":"Services"
        }
    ],
    "sg:phone":"+1 301 567 5506",
    "sg:postcode":"20745",
    "sg:province":"MD",
    "sg:tags":[
        "church"
    ],
    "wof:name":"St Columba RC Rectory",
    "wof:placetype":"venue"
},
  "geometry": {"coordinates":[-76.99265800000001,38.781889],"type":"Point"}
}