{
  "type": "Feature",
  "properties": {
    "addr:full":"7701 Heatherton Ln Potomac MD 20854",
    "addr:housenumber":"7701",
    "addr:postcode":"20854",
    "addr:street":"Heatherton Ln",
    "iso:country":"US",
    "sg:address":"7701 Heatherton Ln",
    "sg:city":"Potomac",
    "sg:classifiers":[
        {
            "category":"Professional",
            "type":"Services"
        }
    ],
    "sg:phone":"+1 301 299 1866",
    "sg:postcode":"20854",
    "sg:province":"MD",
    "sg:tags":[
        "scientist",
        "social"
    ],
    "wof:name":"Pei Dr Minxin",
    "wof:placetype":"venue"
},
  "geometry": {"coordinates":[-77.158103,39.044222],"type":"Point"}
}