{
  "type": "Feature",
  "properties": {
    "addr:full":"8426 Stephen Decatur Hwy Berlin MD 21811",
    "addr:housenumber":"8426",
    "addr:postcode":"21811",
    "addr:street":"Stephen Decatur Hwy",
    "iso:country":"US",
    "sg:address":"8426 Stephen Decatur Hwy",
    "sg:city":"Berlin",
    "sg:classifiers":[
        {
            "category":"Shopping",
            "subcategory":"Gifts & Souvenirs",
            "type":"Retail Goods"
        }
    ],
    "sg:phone":"+1 410 629 1141",
    "sg:postcode":"21811",
    "sg:province":"MD",
    "sg:tags":[
        "shop"
    ],
    "wof:name":"Pony Island Gifts",
    "wof:placetype":"venue"
},
  "geometry": {"coordinates":[-75.15041100000001,38.291845],"type":"Point"}
}