{
  "type": "Feature",
  "properties": {
    "iso:country":"US",
    "sg:address":"15 E Churchville Rd",
    "sg:city":"Bel Air",
    "sg:classifiers":[
        {
            "category":"Professional",
            "subcategory":"Computer Services",
            "type":"Services"
        }
    ],
    "sg:phone":"+1 410 766 8274",
    "sg:postcode":"21014",
    "sg:province":"MD",
    "sg:tags":[
        "design",
        "system"
    ],
    "wof:name":"TCSI",
    "wof:placetype":"venue"
},
  "geometry": {"coordinates":[-76.346244,39.535605],"type":"Point"}
}