{
  "type": "Feature",
  "properties": {
    "iso:country":"US",
    "sg:address":"2909 Boarman Ave",
    "sg:city":"Baltimore",
    "sg:classifiers":[
        {
            "category":"Social Services",
            "subcategory":"Job Training",
            "type":"Services"
        }
    ],
    "sg:phone":"+1 410 367 8440",
    "sg:postcode":"21215",
    "sg:province":"MD",
    "sg:tags":[
        "employment"
    ],
    "wof:name":"Ray Of Hope House, Inc.",
    "wof:placetype":"venue"
},
  "geometry": {"coordinates":[-76.669534,39.337215],"type":"Point"}
}