{
  "type": "Feature",
  "properties": {
    "iso:country":"US",
    "sg:address":"115 Record St",
    "sg:city":"Frederick",
    "sg:classifiers":[
        {
            "category":"Social Services",
            "subcategory":"Retirement Home",
            "type":"Services"
        }
    ],
    "sg:phone":"+1 301 663 6822",
    "sg:postcode":"21701",
    "sg:province":"MD",
    "sg:tags":[
        "apartment",
        "hotel",
        "community"
    ],
    "wof:name":"Record Street Home",
    "wof:placetype":"venue"
},
  "geometry": {"coordinates":[-77.41298500000001,39.416103],"type":"Point"}
}