{
  "type": "Feature",
  "properties": {
    "iso:country":"US",
    "sg:address":"6001 Montrose Rd Ste 804",
    "sg:city":"Rockville",
    "sg:classifiers":[
        {
            "category":"Professional",
            "subcategory":"Accounting & Tax Preparation",
            "type":"Services"
        }
    ],
    "sg:phone":"+1 301 770 3330",
    "sg:postcode":"20852",
    "sg:province":"MD",
    "sg:tags":[
        "accountant"
    ],
    "wof:name":"Hollrah Bernstein Funkhouser",
    "wof:placetype":"venue"
},
  "geometry": {"coordinates":[-77.121002,39.052898],"type":"Point"}
}