{
  "type": "Feature",
  "properties": {
    "addr:full":"5410 Klee Mill Rd S Sykesville MD 21784",
    "addr:postcode":"5410;21784",
    "addr:street":"Klee Mill Rd",
    "iso:country":"US",
    "sg:address":"5410 Klee Mill Rd S",
    "sg:city":"Sykesville",
    "sg:classifiers":[
        {
            "category":"Home & Garden",
            "subcategory":"Carpets & Floor Coverings",
            "type":"Retail Goods"
        }
    ],
    "sg:phone":"+1 410 795 3541",
    "sg:postcode":"21784",
    "sg:province":"MD",
    "sg:tags":[
        "vinyl"
    ],
    "wof:name":"Bfc Vinyl Products",
    "wof:placetype":"venue"
},
  "geometry": {"coordinates":[-76.996734,39.424131],"type":"Point"}
}