{
  "type": "Feature",
  "properties": {
    "iso:country":"US",
    "sg:address":"6160 Springhill Ter",
    "sg:city":"Greenbelt",
    "sg:classifiers":[
        {
            "category":"Manufacturing",
            "subcategory":"Chemicals & Compounds",
            "type":"Manufacturing & Wholesale Goods"
        }
    ],
    "sg:phone":"+1 301 537 4037",
    "sg:postcode":"20770",
    "sg:province":"MD",
    "sg:tags":[
        "preparation",
        "toilet",
        "mfg"
    ],
    "wof:name":"Natures Bare Essentials",
    "wof:placetype":"venue"
},
  "geometry": {"coordinates":[-76.900571,39.005776],"type":"Point"}
}