{
  "type": "Feature",
  "properties": {
    "addr:full":"4915 Wilkens Ave Catonsville MD 21228",
    "addr:housenumber":"4915",
    "addr:postcode":"21228",
    "addr:street":"Wilkens Ave",
    "iso:country":"US",
    "sg:address":"4915 Wilkens Ave",
    "sg:city":"Catonsville",
    "sg:classifiers":[
        {
            "category":"Travel",
            "subcategory":"Hotels & Motels",
            "type":"Entertainment"
        },
        {
            "category":"Travel",
            "subcategory":"Bed & Breakfast",
            "type":"Entertainment"
        }
    ],
    "sg:phone":"+1 410 675 7375",
    "sg:postcode":"21228",
    "sg:province":"MD",
    "sg:tags":[
        "inn"
    ],
    "wof:name":"Prp Enterprises Inc",
    "wof:placetype":"venue"
},
  "geometry": {"coordinates":[-76.702769,39.263377],"type":"Point"}
}