{
  "type": "Feature",
  "properties": {
    "addr:full":"2436 Greenmount Ave Baltimore MD 21218",
    "addr:housenumber":"2436",
    "addr:postcode":"21218",
    "addr:street":"Greenmount Ave",
    "iso:country":"US",
    "sg:address":"2436 Greenmount Ave",
    "sg:city":"Baltimore",
    "sg:classifiers":[
        {
            "category":"Food & Beverages",
            "subcategory":"Groceries & Convenience Stores",
            "type":"Retail Goods"
        }
    ],
    "sg:phone":"+1 410 235 1405",
    "sg:postcode":"21218",
    "sg:province":"MD",
    "sg:tags":[
        "product"
    ],
    "wof:name":"Quality Food Shop",
    "wof:placetype":"venue"
},
  "geometry": {"coordinates":[-76.609559,39.316797],"type":"Point"}
}