{
  "type": "Feature",
  "properties": {
    "iso:country":"US",
    "sg:address":"501 N Baltimore Ave",
    "sg:city":"Ocean City",
    "sg:classifiers":[
        {
            "category":"Travel",
            "subcategory":"Hotels & Motels",
            "type":"Entertainment"
        }
    ],
    "sg:phone":"+1 410 289 2333",
    "sg:postcode":"21842",
    "sg:province":"MD",
    "sg:tags":[
        "breakfast",
        "accommodation",
        "bed"
    ],
    "sg:website":"www.atlantichouse.com",
    "wof:name":"Atlantic House Bed & Breakfast",
    "wof:placetype":"venue"
},
  "geometry": {"coordinates":[-75.08319,38.337205],"type":"Point"}
}