{
  "type": "Feature",
  "properties": {
    "addr:full":"500 N Calvert St Baltimore MD 21202",
    "addr:housenumber":"500",
    "addr:postcode":"21202",
    "addr:street":"N Calvert St",
    "iso:country":"US",
    "sg:address":"500 N Calvert St",
    "sg:city":"Baltimore",
    "sg:classifiers":[
        {
            "category":"Government",
            "subcategory":"Office",
            "type":"Public Place"
        }
    ],
    "sg:phone":"+1 410 230 6229",
    "sg:postcode":"21202",
    "sg:province":"MD",
    "wof:name":"Cemetery Oversight",
    "wof:placetype":"venue"
},
  "geometry": {"coordinates":[-76.61284499999999,39.296454],"type":"Point"}
}