{
  "type": "Feature",
  "properties": {
    "iso:country":"US",
    "sg:address":"14516 Mac Clintock Ct",
    "sg:city":"Glenwood",
    "sg:classifiers":[
        {
            "category":"Retail",
            "subcategory":"Repair Shop",
            "type":"Services"
        }
    ],
    "sg:phone":"+1 301 854 6006",
    "sg:postcode":"21738",
    "sg:province":"MD",
    "sg:tags":[
        "lock",
        "locksmith"
    ],
    "wof:name":"Capitol Lock Co",
    "wof:placetype":"venue"
},
  "geometry": {"coordinates":[-77.020218,39.27875],"type":"Point"}
}