{
  "type": "Feature",
  "properties": {
    "iso:country":"US",
    "sg:address":"8125 Wisconsin Ave Ste 1",
    "sg:city":"Bethesda",
    "sg:classifiers":[
        {
            "category":"Deli",
            "type":"Food & Drink"
        },
        {
            "category":"Food & Beverages",
            "subcategory":"Bakery",
            "type":"Retail Goods"
        },
        {
            "category":"Food & Beverages",
            "subcategory":"Groceries & Convenience Stores",
            "type":"Retail Goods"
        }
    ],
    "sg:phone":"+1 301 654 4880",
    "sg:postcode":"20814",
    "sg:province":"MD",
    "sg:tags":[
        "sandwich"
    ],
    "sg:website":"www.worldmarket.com",
    "wof:name":"World Market",
    "wof:placetype":"venue"
},
  "geometry": {"coordinates":[-77.09546,38.991417],"type":"Point"}
}