{
  "type": "Feature",
  "properties": {
    "addr:full":"2 S Rolling Rd Catonsville MD 21228",
    "addr:housenumber":"2",
    "addr:postcode":"21228",
    "addr:street":"S Rolling Rd",
    "iso:country":"US",
    "sg:address":"2 S Rolling Rd",
    "sg:city":"Catonsville",
    "sg:classifiers":[
        {
            "category":"Social Services",
            "subcategory":"Child Care",
            "type":"Services"
        }
    ],
    "sg:phone":"+1 410 744 8225",
    "sg:postcode":"21228",
    "sg:province":"MD",
    "sg:tags":[
        "day"
    ],
    "wof:name":"Rob N Ness Adult Medical Daycare Center Inc",
    "wof:placetype":"venue"
},
  "geometry": {"coordinates":[-76.74604600000001,39.268615],"type":"Point"}
}