{
  "type": "Feature",
  "properties": {
    "iso:country":"US",
    "sg:address":"873 New London Harbour",
    "sg:city":"Pasadena",
    "sg:classifiers":[
        {
            "category":"Wholesale",
            "subcategory":"Groceries",
            "type":"Manufacturing & Wholesale Goods"
        }
    ],
    "sg:phone":"+1 410 437 1769",
    "sg:postcode":"21122",
    "sg:province":"MD",
    "sg:tags":[
        "confectionery",
        "candy"
    ],
    "wof:name":"Burdette Beckmann Co",
    "wof:placetype":"venue"
},
  "geometry": {"coordinates":[-76.529271,39.156121],"type":"Point"}
}