{
  "type": "Feature",
  "properties": {
    "iso:country":"US",
    "sg:address":"1179 Wright Ave",
    "sg:city":"Arnold",
    "sg:classifiers":[
        {
            "category":"Professional",
            "subcategory":"Employment Agencies",
            "type":"Services"
        }
    ],
    "sg:phone":"+1 410 647 5979",
    "sg:postcode":"21012",
    "sg:province":"MD",
    "sg:tags":[
        "teachers'"
    ],
    "wof:name":"Kauffman",
    "wof:placetype":"venue"
},
  "geometry": {"coordinates":[-76.509314,39.04397],"type":"Point"}
}