{
  "type": "Feature",
  "properties": {
    "addr:full":"215 Ritchie Ln Glen Burnie MD 21061",
    "addr:housenumber":"215",
    "addr:postcode":"21061",
    "addr:street":"Ritchie Ln",
    "iso:country":"US",
    "sg:address":"215 Ritchie Ln",
    "sg:city":"Glen Burnie",
    "sg:classifiers":[
        {
            "category":"Professional",
            "type":"Services"
        }
    ],
    "sg:phone":"+1 410 761 9079",
    "sg:postcode":"21061",
    "sg:province":"MD",
    "sg:tags":[
        "establishment"
    ],
    "wof:name":"Anzitech Inc",
    "wof:placetype":"venue"
},
  "geometry": {"coordinates":[-76.623203,39.166418],"type":"Point"}
}