{
  "type": "Feature",
  "properties": {
    "addr:full":"1400 Phoenix Rd W Phoenix MD 21131",
    "addr:housenumber":"1400",
    "addr:postcode":"21131",
    "addr:street":"Phoenix Rd W",
    "iso:country":"US",
    "sg:address":"1400 Phoenix Rd W",
    "sg:city":"Phoenix",
    "sg:classifiers":[
        {
            "category":"Wholesale",
            "subcategory":"Durable Goods & Equipment",
            "type":"Manufacturing & Wholesale Goods"
        }
    ],
    "sg:phone":"+1 410 472 0977",
    "sg:postcode":"21131",
    "sg:province":"MD",
    "sg:tags":[
        "importer"
    ],
    "wof:name":"Bellehaven Specialties",
    "wof:placetype":"venue"
},
  "geometry": {"coordinates":[-76.631745,39.519564],"type":"Point"}
}