{
  "type": "Feature",
  "properties": {
    "iso:country":"US",
    "sg:address":"3312 Dodge Park Rd",
    "sg:city":"Hyattsville",
    "sg:classifiers":[
        {
            "category":"Government",
            "subcategory":"Post Office",
            "type":"Public Place"
        }
    ],
    "sg:phone":"+1 301 322 5050",
    "sg:postcode":"20785",
    "sg:province":"MD",
    "wof:name":"US Post Office",
    "wof:placetype":"venue"
},
  "geometry": {"coordinates":[-76.88205000000001,38.929302],"type":"Point"}
}