{
  "type": "Feature",
  "properties": {
    "iso:country":"US",
    "sg:address":"8211 Annapolis Rd",
    "sg:city":"New Carrollton",
    "sg:classifiers":[
        {
            "category":"Banks & Credit Unions",
            "subcategory":"Bank",
            "type":"Services"
        },
        {
            "category":"Banks & Credit Unions",
            "subcategory":"Financial Services",
            "type":"Services"
        }
    ],
    "sg:phone":"+1 888 751 9000",
    "sg:postcode":"20784",
    "sg:province":"MD",
    "sg:tags":[
        "broker",
        "mortgage"
    ],
    "sg:website":"www.commerceonline.com",
    "wof:name":"Commerce Bank",
    "wof:placetype":"venue"
},
  "geometry": {"coordinates":[-76.872332,38.956349],"type":"Point"}
}