{
  "type": "Feature",
  "properties": {
    "iso:country":"US",
    "sg:address":"7754 Mayfair Cir",
    "sg:city":"Ellicott City",
    "sg:classifiers":[
        {
            "category":"Social Services",
            "type":"Services"
        }
    ],
    "sg:phone":"+1 410 750 7957",
    "sg:postcode":"21043",
    "sg:province":"MD",
    "sg:tags":[
        "organization",
        "welfare"
    ],
    "wof:name":"Huntington's Disease Society",
    "wof:placetype":"venue"
},
  "geometry": {"coordinates":[-76.784498,39.202039],"type":"Point"}
}