{
  "type": "Feature",
  "properties": {
    "iso:country":"US",
    "sg:address":"101 Sandsbury Ave",
    "sg:city":"Glen Burnie",
    "sg:classifiers":[
        {
            "category":"Health Services",
            "subcategory":"Nursing And Care Facility",
            "type":"Services"
        }
    ],
    "sg:phone":"+1 410 768 7759",
    "sg:postcode":"21060",
    "sg:province":"MD",
    "wof:name":"Homeplace Estate Inc",
    "wof:placetype":"venue"
},
  "geometry": {"coordinates":[-76.60245399999999,39.142976],"type":"Point"}
}