{
  "type": "Feature",
  "properties": {
    "addr:full":"6335 Crain Hwy La Plata MD 20646",
    "addr:housenumber":"6335",
    "addr:postcode":"20646",
    "addr:street":"Crain Hwy",
    "iso:country":"US",
    "sg:address":"6335 Crain Hwy",
    "sg:city":"La Plata",
    "sg:classifiers":[
        {
            "category":"Real Estate",
            "subcategory":"Real Estate Agent",
            "type":"Services"
        }
    ],
    "sg:phone":"+1 301 934 4411",
    "sg:postcode":"20646",
    "sg:province":"MD",
    "sg:tags":[
        "appraiser"
    ],
    "wof:name":"County Services Inc",
    "wof:placetype":"venue"
},
  "geometry": {"coordinates":[-76.984245,38.538852],"type":"Point"}
}