{
  "type": "Feature",
  "properties": {
    "addr:full":"4810 Saint Barnabas Rd Frnt Temple Hills MD 20748",
    "addr:housenumber":"4810",
    "addr:postcode":"20748",
    "addr:street":"Saint Barnabas Rd;Hills",
    "iso:country":"US",
    "sg:address":"4810 Saint Barnabas Rd Frnt",
    "sg:city":"Temple Hills",
    "sg:classifiers":[
        {
            "category":"Home & Garden",
            "subcategory":"Carpets & Floor Coverings",
            "type":"Retail Goods"
        }
    ],
    "sg:phone":"+1 301 899 8000",
    "sg:postcode":"20748",
    "sg:province":"MD",
    "sg:tags":[
        "carpeting"
    ],
    "sg:website":"www.carpetqueenandfloors.com",
    "wof:name":"Carpet Queen and Floors",
    "wof:placetype":"venue"
},
  "geometry": {"coordinates":[-76.94909699999999,38.823399],"type":"Point"}
}