{
  "type": "Feature",
  "properties": {
    "iso:country":"US",
    "sg:address":"615 Twin Brook Ln",
    "sg:city":"Joppa",
    "sg:classifiers":[
        {
            "category":"Banks & Credit Unions",
            "subcategory":"Investment Brokerage",
            "type":"Services"
        }
    ],
    "sg:phone":"+1 410 638 1350",
    "sg:postcode":"21085",
    "sg:province":"MD",
    "sg:tags":[
        "stock",
        "bond"
    ],
    "wof:name":"Shaw Group",
    "wof:placetype":"venue"
},
  "geometry": {"coordinates":[-76.36928399999999,39.496662],"type":"Point"}
}