{
  "type": "Feature",
  "properties": {
    "addr:full":"3912 Ironwood Pl Hyattsville MD 20785",
    "addr:housenumber":"3912",
    "addr:postcode":"20785",
    "addr:street":"Ironwood Pl",
    "iso:country":"US",
    "sg:address":"3912 Ironwood Pl",
    "sg:city":"Hyattsville",
    "sg:classifiers":[
        {
            "category":"Autos & Motor Vehicles",
            "subcategory":"Auto Supplies",
            "type":"Retail Goods"
        },
        {
            "category":"Wholesale",
            "subcategory":"Auto Parts",
            "type":"Manufacturing & Wholesale Goods"
        }
    ],
    "sg:phone":"+1 301 341 3499",
    "sg:postcode":"20785",
    "sg:province":"MD",
    "sg:tags":[
        "automobile"
    ],
    "wof:name":"Parts Central Inc",
    "wof:placetype":"venue"
},
  "geometry": {"coordinates":[-76.859663,38.941779],"type":"Point"}
}