{
  "type": "Feature",
  "properties": {
    "addr:full":"3508 Roland Ave Baltimore MD 21211",
    "addr:housenumber":"3508",
    "addr:postcode":"21211",
    "addr:street":"Roland Ave",
    "iso:country":"US",
    "sg:address":"3508 Roland Ave",
    "sg:city":"Baltimore",
    "sg:classifiers":[
        {
            "category":"Building & Trades",
            "subcategory":"Landscaping Services",
            "type":"Services"
        }
    ],
    "sg:phone":"+1 410 557 9750",
    "sg:postcode":"21211",
    "sg:province":"MD",
    "sg:tags":[
        "landscape",
        "contractor"
    ],
    "wof:name":"Rich Landscaping & Design",
    "wof:placetype":"venue"
},
  "geometry": {"coordinates":[-76.63251099999999,39.328585],"type":"Point"}
}