{
  "type": "Feature",
  "properties": {
    "addr:full":"8303 Liberty Rd Baltimore MD 21244",
    "addr:housenumber":"8303",
    "addr:postcode":"21244",
    "addr:street":"Liberty Rd",
    "iso:country":"US",
    "sg:address":"8303 Liberty Rd",
    "sg:city":"Baltimore",
    "sg:classifiers":[
        {
            "category":"Social Services",
            "type":"Services"
        }
    ],
    "sg:phone":"+1 410 521 3800",
    "sg:postcode":"21244",
    "sg:province":"MD",
    "sg:tags":[
        "counselor",
        "marriage",
        "family"
    ],
    "sg:website":"www.firststepmd.com",
    "wof:name":"First Step Hotline",
    "wof:placetype":"venue"
},
  "geometry": {"coordinates":[-76.766873,39.356679],"type":"Point"}
}