{
  "type": "Feature",
  "properties": {
    "addr:full":"109 Lindsay Rd Millington MD 21651",
    "addr:housenumber":"109",
    "addr:postcode":"21651",
    "addr:street":"Lindsay Rd",
    "iso:country":"US",
    "sg:address":"109 Lindsay Rd",
    "sg:city":"Millington",
    "sg:classifiers":[
        {
            "category":"Internet Cafe",
            "subcategory":"None",
            "type":"Food & Drink"
        },
        {
            "category":"Professional",
            "subcategory":"Computer Services",
            "type":"Services"
        }
    ],
    "sg:phone":"+1 410 778 6510",
    "sg:postcode":"21651",
    "sg:province":"MD",
    "sg:tags":[
        "product",
        "designer",
        "network",
        "consultant",
        "system",
        "design",
        "software"
    ],
    "wof:name":"Silo Technologies Inc",
    "wof:placetype":"venue"
},
  "geometry": {"coordinates":[-75.87786699999999,39.236034],"type":"Point"}
}