{
  "type": "Feature",
  "properties": {
    "iso:country":"US",
    "sg:address":"6503 York Rd",
    "sg:city":"Baltimore",
    "sg:classifiers":[
        {
            "category":"Building & Trades",
            "subcategory":"Construction",
            "type":"Services"
        }
    ],
    "sg:phone":"+1 410 377 4420",
    "sg:postcode":"21212",
    "sg:province":"MD",
    "sg:tags":[
        "equipment",
        "foundation"
    ],
    "sg:website":"http://www.atlanticcaisson.com",
    "wof:name":"Atlantic Caisson Corp.",
    "wof:placetype":"venue"
},
  "geometry": {"coordinates":[-76.60939,39.375351],"type":"Point"}
}