{
  "type": "Feature",
  "properties": {
    "addr:full":"7112 25th Ave Adelphi MD 20783",
    "addr:housenumber":"7112",
    "addr:postcode":"20783",
    "addr:street":"25Th Ave",
    "iso:country":"US",
    "sg:address":"7112 25th Ave",
    "sg:city":"Adelphi",
    "sg:classifiers":[
        {
            "category":"Education",
            "subcategory":"Special Training",
            "type":"Public Place"
        }
    ],
    "sg:phone":"+1 301 422 9334",
    "sg:postcode":"20783",
    "sg:province":"MD",
    "sg:tags":[
        "instruction",
        "speaking"
    ],
    "wof:name":"Johnson, Kennita",
    "wof:placetype":"venue"
},
  "geometry": {"coordinates":[-76.967832,38.975651],"type":"Point"}
}