{
  "type": "Feature",
  "properties": {
    "addr:full":"605 Reisterstown Rd Pikesville MD 21208",
    "addr:housenumber":"605",
    "addr:postcode":"21208",
    "addr:street":"Reisterstown Rd",
    "iso:country":"US",
    "sg:address":"605 Reisterstown Rd",
    "sg:city":"Pikesville",
    "sg:phone":"+1 410 653 2448",
    "sg:postcode":"21208",
    "sg:province":"MD",
    "sg:tags":[
        "equipment",
        "supply"
    ],
    "wof:name":"Maryland Equipment Co",
    "wof:placetype":"venue"
},
  "geometry": {"coordinates":[-76.71762699999999,39.369029],"type":"Point"}
}