{
  "type": "Feature",
  "properties": {
    "addr:full":"12816 Beck Rd Hagerstown MD 21742",
    "addr:housenumber":"12816",
    "addr:postcode":"21742",
    "addr:street":"Beck Rd",
    "iso:country":"US",
    "sg:address":"12816 Beck Rd",
    "sg:city":"Hagerstown",
    "sg:classifiers":[
        {
            "category":"Building & Trades",
            "subcategory":"Landscaping Services",
            "type":"Services"
        }
    ],
    "sg:phone":"+1 301 733 6331",
    "sg:postcode":"21742",
    "sg:province":"MD",
    "sg:tags":[
        "landscape",
        "contractor"
    ],
    "wof:name":"Good's Garden & Greenhouse",
    "wof:placetype":"venue"
},
  "geometry": {"coordinates":[-77.62002200000001,39.665133],"type":"Point"}
}