{
  "type": "Feature",
  "properties": {
    "iso:country":"US",
    "sg:address":"13851 Hopkins Rd",
    "sg:city":"Germantown",
    "sg:classifiers":[
        {
            "category":"Farming",
            "subcategory":"Farm",
            "type":"Manufacturing & Wholesale Goods"
        }
    ],
    "sg:phone":"+1 301 601 9130",
    "sg:postcode":"20874",
    "sg:province":"MD",
    "wof:name":"Manchester Farm",
    "wof:placetype":"venue"
},
  "geometry": {"coordinates":[-77.287322,39.168884],"type":"Point"}
}