{
  "type": "Feature",
  "properties": {
    "addr:full":"1823 Division Rd Pasadena MD 21122",
    "addr:housenumber":"1823",
    "addr:postcode":"21122",
    "addr:street":"Division Rd",
    "iso:country":"US",
    "sg:address":"1823 Division Rd",
    "sg:city":"Pasadena",
    "sg:classifiers":[
        {
            "category":"Building & Trades",
            "subcategory":"Plumbing",
            "type":"Services"
        }
    ],
    "sg:phone":"+1 410 646 9039",
    "sg:postcode":"21122",
    "sg:province":"MD",
    "sg:tags":[
        "plumber",
        "industrial",
        "contractors-commercial"
    ],
    "wof:name":"A Complete Plumbing Servi",
    "wof:placetype":"venue"
},
  "geometry": {"coordinates":[-76.48242,39.158734],"type":"Point"}
}