{
  "type": "Feature",
  "properties": {
    "addr:full":"5260 Fairlawn Ave Baltimore MD 21215",
    "addr:housenumber":"5260",
    "addr:postcode":"21215",
    "addr:street":"Fairlawn Ave",
    "iso:country":"US",
    "sg:address":"5260 Fairlawn Ave",
    "sg:city":"Baltimore",
    "sg:classifiers":[
        {
            "category":"Retail",
            "subcategory":"Auto Repair",
            "type":"Services"
        }
    ],
    "sg:phone":"+1 410 466 8410",
    "sg:postcode":"21215",
    "sg:province":"MD",
    "wof:name":"S & S Auto",
    "wof:placetype":"venue"
},
  "geometry": {"coordinates":[-76.685799,39.343201],"type":"Point"}
}