{
  "type": "Feature",
  "properties": {
    "iso:country":"US",
    "sg:address":"86 Ritchie Rd",
    "sg:city":"Capitol Heights",
    "sg:classifiers":[
        {
            "category":"Retail",
            "subcategory":"Auto Repair",
            "type":"Services"
        }
    ],
    "sg:phone":"+1 301 324 1783",
    "sg:postcode":"20743",
    "sg:province":"MD",
    "sg:tags":[
        "automotive"
    ],
    "wof:name":"Urban Audio Installations",
    "wof:placetype":"venue"
},
  "geometry": {"coordinates":[-76.861704,38.887795],"type":"Point"}
}