{
  "type": "Feature",
  "properties": {
    "addr:full":"9610 Martingham Cir St Michaels MD 21663",
    "addr:housenumber":"9610",
    "addr:postcode":"21663",
    "addr:street":"Martingham Cir",
    "iso:country":"US",
    "sg:address":"9610 Martingham Cir",
    "sg:city":"St Michaels",
    "sg:classifiers":[
        {
            "category":"Retail",
            "subcategory":"Repair Shop",
            "type":"Services"
        }
    ],
    "sg:phone":"+1 410 745 6303",
    "sg:postcode":"21663",
    "sg:province":"MD",
    "sg:tags":[
        "refinishing",
        "furniture"
    ],
    "wof:name":"Furniture Medic",
    "wof:placetype":"venue"
},
  "geometry": {"coordinates":[-76.23563300000001,38.818923],"type":"Point"}
}