{
  "type": "Feature",
  "properties": {
    "iso:country":"US",
    "sg:address":"15408 Old Columbia Pike",
    "sg:city":"Burtonsville",
    "sg:classifiers":[
        {
            "category":"Manufacturing",
            "subcategory":"Tools & Machinery",
            "type":"Manufacturing & Wholesale Goods"
        },
        {
            "category":"Home & Garden",
            "subcategory":"Garden Supply",
            "type":"Retail Goods"
        }
    ],
    "sg:phone":"+1 301 421 1288",
    "sg:postcode":"20866",
    "sg:province":"MD",
    "sg:tags":[
        "mowers-sharpening",
        "repairing",
        "lawn",
        "mower"
    ],
    "wof:name":"Pat's Lawn Mower Svc",
    "wof:placetype":"venue"
},
  "geometry": {"coordinates":[-76.937005,39.108207],"type":"Point"}
}