{
  "type": "Feature",
  "properties": {
    "addr:full":"3615 Ivory Rd Glenelg MD 21737",
    "addr:housenumber":"3615",
    "addr:postcode":"21737",
    "addr:street":"Ivory Rd",
    "iso:country":"US",
    "sg:address":"3615 Ivory Rd",
    "sg:city":"Glenelg",
    "sg:classifiers":[
        {
            "category":"Building & Trades",
            "subcategory":"Landscaping Services",
            "type":"Services"
        }
    ],
    "sg:phone":"+1 301 854 6801",
    "sg:postcode":"21737",
    "sg:province":"MD",
    "sg:tags":[
        "landscape",
        "contractor"
    ],
    "wof:name":"Geoffrey I Clark Landscaping",
    "wof:placetype":"venue"
},
  "geometry": {"coordinates":[-76.99014099999999,39.26755],"type":"Point"}
}