{
  "type": "Feature",
  "properties": {
    "addr:full":"1826 Crocheron Rd Toddville MD 21672",
    "addr:housenumber":"1826",
    "addr:postcode":"21672",
    "addr:street":"Crocheron Rd",
    "iso:country":"US",
    "sg:address":"1826 Crocheron Rd",
    "sg:city":"Toddville",
    "sg:classifiers":[
        {
            "category":"Building & Trades",
            "subcategory":"Construction",
            "type":"Services"
        }
    ],
    "sg:phone":"+1 410 397 8789",
    "sg:postcode":"21672",
    "sg:province":"MD",
    "sg:tags":[
        "excavating",
        "contractor"
    ],
    "wof:name":"Jeff Bramble Contractor",
    "wof:placetype":"venue"
},
  "geometry": {"coordinates":[-76.066429,38.258571],"type":"Point"}
}