{
  "type": "Feature",
  "properties": {
    "iso:country":"US",
    "sg:address":"5 Hawthorn Dr",
    "sg:city":"Port Deposit",
    "sg:classifiers":[
        {
            "category":"Building & Trades",
            "subcategory":"Construction",
            "type":"Services"
        }
    ],
    "sg:phone":"+1 410 658 1600",
    "sg:postcode":"21904",
    "sg:province":"MD",
    "sg:tags":[
        "general",
        "contractor"
    ],
    "wof:name":"Ragan Contractors",
    "wof:placetype":"venue"
},
  "geometry": {"coordinates":[-76.066154,39.667866],"type":"Point"}
}