{
  "type": "Feature",
  "properties": {
    "addr:full":"1405 Odenton Rd Odenton MD 21113",
    "addr:housenumber":"1405",
    "addr:postcode":"21113",
    "addr:street":"Odenton Rd",
    "iso:country":"US",
    "sg:address":"1405 Odenton Rd",
    "sg:city":"Odenton",
    "sg:classifiers":[
        {
            "category":"Bus Charters",
            "type":"Transportation"
        },
        {
            "category":"Local Transit",
            "type":"Transportation"
        }
    ],
    "sg:phone":"+1 410 551 4131",
    "sg:postcode":"21113",
    "sg:province":"MD",
    "sg:tags":[
        "line"
    ],
    "wof:name":"Robert A Gaug Bus Enterprises",
    "wof:placetype":"venue"
},
  "geometry": {"coordinates":[-76.708321,39.087196],"type":"Point"}
}