{
  "type": "Feature",
  "properties": {
    "addr:full":"301 Saint Paul St Baltimore MD 21202",
    "addr:housenumber":"301",
    "addr:postcode":"21202",
    "addr:street":"Saint Paul St",
    "iso:country":"US",
    "sg:address":"301 Saint Paul St",
    "sg:city":"Baltimore",
    "sg:classifiers":[
        {
            "category":"Health Services",
            "subcategory":"Doctor",
            "type":"Services"
        }
    ],
    "sg:phone":"+1 410 332 9200",
    "sg:postcode":"21202",
    "sg:province":"MD",
    "sg:tags":[
        "physician",
        "surgeon"
    ],
    "wof:name":"Gynecology Center Of Mercy",
    "wof:placetype":"venue"
},
  "geometry": {"coordinates":[-76.614217,39.293637],"type":"Point"}
}