{
  "type": "Feature",
  "properties": {
    "iso:country":"US",
    "sg:address":"8700 Central Ave Ste 105",
    "sg:city":"Hyattsville",
    "sg:classifiers":[
        {
            "category":"Health Services",
            "subcategory":"Doctor",
            "type":"Services"
        }
    ],
    "sg:phone":"+1 301 499 3338",
    "sg:postcode":"20785",
    "sg:province":"MD",
    "sg:tags":[
        "podiatrist"
    ],
    "wof:name":"Capital Foot & Ankle Care Center",
    "wof:placetype":"venue"
},
  "geometry": {"coordinates":[-76.854797,38.890598],"type":"Point"}
}