{
  "type": "Feature",
  "properties": {
    "iso:country":"US",
    "sg:address":"9751 Washington Blvd N",
    "sg:city":"Laurel",
    "sg:classifiers":[
        {
            "category":"Retail",
            "subcategory":"Auto Repair",
            "type":"Services"
        }
    ],
    "sg:phone":"+1 301 317 1437",
    "sg:postcode":"20723",
    "sg:province":"MD",
    "wof:name":"Amauri Auto Body",
    "wof:placetype":"venue"
},
  "geometry": {"coordinates":[-76.829803,39.118],"type":"Point"}
}