{
  "type": "Feature",
  "properties": {
    "iso:country":"US",
    "sg:address":"11758 S Laurel Dr",
    "sg:city":"Laurel",
    "sg:classifiers":[
        {
            "category":"Professional",
            "subcategory":"Business Services",
            "type":"Services"
        }
    ],
    "sg:phone":"+1 301 725 1743",
    "sg:postcode":"20708",
    "sg:province":"MD",
    "sg:tags":[
        "technology",
        "it"
    ],
    "wof:name":"Certified Professionals",
    "wof:placetype":"venue"
},
  "geometry": {"coordinates":[-76.836547,39.051614],"type":"Point"}
}