{
  "type": "Feature",
  "properties": {
    "iso:country":"US",
    "sg:address":"10102 Country Club Rd",
    "sg:city":"Cumberland",
    "sg:classifiers":[
        {
            "category":"Government",
            "subcategory":"Office",
            "type":"Public Place"
        }
    ],
    "sg:phone":"+1 301 777 2285",
    "sg:postcode":"21502",
    "sg:province":"MD",
    "wof:name":"Joseph S Massie Unit",
    "wof:placetype":"venue"
},
  "geometry": {"coordinates":[-78.739007,39.65735],"type":"Point"}
}