{
  "type": "Feature",
  "properties": {
    "addr:full":"6303 Ivy Ln Greenbelt MD 20770",
    "addr:housenumber":"6303",
    "addr:postcode":"20770",
    "addr:street":"Ivy Ln",
    "iso:country":"US",
    "sg:address":"6303 Ivy Ln",
    "sg:city":"Greenbelt",
    "sg:classifiers":[
        {
            "category":"Professional",
            "subcategory":"Lawyer & Legal Services",
            "type":"Services"
        }
    ],
    "sg:phone":"+1 301 474 8831",
    "sg:postcode":"20770",
    "sg:province":"MD",
    "sg:tags":[
        "attorney"
    ],
    "wof:name":"Bud Stephen Tayman",
    "wof:placetype":"venue"
},
  "geometry": {"coordinates":[-76.89698300000001,39.008216],"type":"Point"}
}