{
  "type": "Feature",
  "properties": {
    "addr:full":"7925 Glenbrook Rd Bethesda MD 20814",
    "addr:housenumber":"7925",
    "addr:postcode":"20814",
    "addr:street":"Glenbrook Rd",
    "iso:country":"US",
    "sg:address":"7925 Glenbrook Rd",
    "sg:city":"Bethesda",
    "sg:classifiers":[
        {
            "category":"Real Estate",
            "subcategory":"Architect",
            "type":"Services"
        }
    ],
    "sg:phone":"+1 301 951 7933",
    "sg:postcode":"20814",
    "sg:province":"MD",
    "wof:name":"NOA Architecture Planning",
    "wof:placetype":"venue"
},
  "geometry": {"coordinates":[-77.101833,38.989191],"type":"Point"}
}