{
  "type": "Feature",
  "properties": {
    "addr:full":"9455 Hickory View Way Montgomery Vlg MD 20886",
    "addr:housenumber":"9455",
    "addr:postcode":"20886",
    "addr:street":"Hickory View Way",
    "iso:country":"US",
    "sg:address":"9455 Hickory View Way",
    "sg:city":"Montgomery Vlg",
    "sg:classifiers":[
        {
            "category":"Professional",
            "subcategory":"Management & Consulting",
            "type":"Services"
        }
    ],
    "sg:phone":"+1 301 869 0456",
    "sg:postcode":"20886",
    "sg:province":"MD",
    "sg:tags":[
        "consultant",
        "business"
    ],
    "wof:name":"Evans Consulting LLC",
    "wof:placetype":"venue"
},
  "geometry": {"coordinates":[-77.194107,39.181114],"type":"Point"}
}