{
  "type": "Feature",
  "properties": {
    "iso:country":"US",
    "sg:address":"11808 Silent Valley Ln",
    "sg:city":"North Potomac",
    "sg:classifiers":[
        {
            "category":"Professional",
            "type":"Services"
        }
    ],
    "sg:phone":"+1 301 279 7046",
    "sg:postcode":"20878",
    "sg:province":"MD",
    "sg:tags":[
        "establishment"
    ],
    "wof:name":"London Brass Rubbing Ctr",
    "wof:placetype":"venue"
},
  "geometry": {"coordinates":[-77.245254,39.10137],"type":"Point"}
}