{
  "type": "Feature",
  "properties": {
    "addr:full":"954 Highpoint Dr Annapolis MD 21409",
    "addr:housenumber":"954",
    "addr:postcode":"21409",
    "addr:street":"Highpoint Dr",
    "iso:country":"US",
    "sg:address":"954 Highpoint Dr",
    "sg:city":"Annapolis",
    "sg:classifiers":[
        {
            "category":"Building & Trades",
            "subcategory":"Plumbing",
            "type":"Services"
        }
    ],
    "sg:phone":"+1 410 757 6061",
    "sg:postcode":"21409",
    "sg:province":"MD",
    "sg:tags":[
        "plumbing",
        "contractor"
    ],
    "wof:name":"Elsey Plumbing & Heating Inc",
    "wof:placetype":"venue"
},
  "geometry": {"coordinates":[-76.45152899999999,39.044152],"type":"Point"}
}