{
  "type": "Feature",
  "properties": {
    "addr:full":"11701 Central Ave Waldorf MD 20601",
    "addr:housenumber":"11701",
    "addr:postcode":"20601",
    "addr:street":"Central Ave",
    "iso:country":"US",
    "sg:address":"11701 Central Ave",
    "sg:city":"Waldorf",
    "sg:classifiers":[
        {
            "category":"Personal",
            "subcategory":"Beauty Salon",
            "type":"Services"
        }
    ],
    "sg:phone":"+1 301 870 1900",
    "sg:postcode":"20601",
    "sg:province":"MD",
    "wof:name":"Nu Concepts Hair Studio",
    "wof:placetype":"venue"
},
  "geometry": {"coordinates":[-76.90241899999999,38.634288],"type":"Point"}
}