{
  "type": "Feature",
  "properties": {
    "iso:country":"US",
    "sg:address":"12164 Central Ave",
    "sg:city":"Mitchellville",
    "sg:classifiers":[
        {
            "category":"Real Estate",
            "subcategory":"Real Estate Services",
            "type":"Services"
        }
    ],
    "sg:phone":"+1 301 390 0577",
    "sg:postcode":"20721",
    "sg:province":"MD",
    "sg:tags":[
        "company",
        "title"
    ],
    "wof:name":"Title Associates Inc",
    "wof:placetype":"venue"
},
  "geometry": {"coordinates":[-76.794038,38.899938],"type":"Point"}
}