{
  "type": "Feature",
  "properties": {
    "iso:country":"US",
    "sg:address":"10815 Beaver Dam Rd",
    "sg:city":"Cockysvl Hnt Vly",
    "sg:classifiers":[
        {
            "category":"Wholesale",
            "subcategory":"Home Furnishings",
            "type":"Manufacturing & Wholesale Goods"
        }
    ],
    "sg:phone":"+1 410 771 3865",
    "sg:postcode":"21030",
    "sg:province":"MD",
    "sg:tags":[
        "closet",
        "accessory"
    ],
    "wof:name":"Closet Creation LLC",
    "wof:placetype":"venue"
},
  "geometry": {"coordinates":[-76.654756,39.479669],"type":"Point"}
}