{
  "type": "Feature",
  "properties": {
    "addr:full":"514 Dogwood Dr Salisbury MD 21801",
    "addr:housenumber":"514",
    "addr:postcode":"21801",
    "addr:street":"Dogwood Dr",
    "iso:country":"US",
    "sg:address":"514 Dogwood Dr",
    "sg:city":"Salisbury",
    "sg:classifiers":[
        {
            "category":"Retail",
            "subcategory":"Repair Shop",
            "type":"Services"
        }
    ],
    "sg:phone":"+1 410 742 8986",
    "sg:postcode":"21801",
    "sg:province":"MD",
    "sg:tags":[
        "clocks",
        "parts"
    ],
    "wof:name":"About Time",
    "wof:placetype":"venue"
},
  "geometry": {"coordinates":[-75.614935,38.342203],"type":"Point"}
}