{
  "type": "Feature",
  "properties": {
    "iso:country":"US",
    "sg:address":"2425 Annapolis Rd",
    "sg:city":"Baltimore",
    "sg:classifiers":[
        {
            "category":"Government",
            "subcategory":"Fire Station",
            "type":"Public Place"
        }
    ],
    "sg:phone":"+1 410 396 1258",
    "sg:postcode":"21230",
    "sg:province":"MD",
    "sg:tags":[
        "consultant",
        "protection"
    ],
    "sg:website":"http://www.bccenter.org",
    "wof:name":"Fire Department Station 58",
    "wof:placetype":"venue"
},
  "geometry": {"coordinates":[-76.63495899999999,39.261425],"type":"Point"}
}