{
  "type": "Feature",
  "properties": {
    "addr:full":"4035 Broadbill Cir Waldorf MD 20603",
    "addr:housenumber":"4035",
    "addr:postcode":"20603",
    "addr:street":"Broadbill Cir",
    "iso:country":"US",
    "sg:address":"4035 Broadbill Cir",
    "sg:city":"Waldorf",
    "sg:classifiers":[
        {
            "category":"Banks & Credit Unions",
            "subcategory":"Investment Brokerage",
            "type":"Services"
        }
    ],
    "sg:phone":"+1 301 638 0904",
    "sg:postcode":"20603",
    "sg:province":"MD",
    "sg:tags":[
        "advisory"
    ],
    "wof:name":"Holder & Assoc Financial Svcs",
    "wof:placetype":"venue"
},
  "geometry": {"coordinates":[-76.935486,38.622894],"type":"Point"}
}