{
  "type": "Feature",
  "properties": {
    "addr:full":"160 Somerset Rd Stevensville MD 21666",
    "addr:housenumber":"160",
    "addr:postcode":"21666",
    "addr:street":"Somerset Rd",
    "iso:country":"US",
    "sg:address":"160 Somerset Rd",
    "sg:city":"Stevensville",
    "sg:classifiers":[
        {
            "category":"Professional",
            "subcategory":"Management & Consulting",
            "type":"Services"
        }
    ],
    "sg:phone":"+1 410 643 1461",
    "sg:postcode":"21666",
    "sg:province":"MD",
    "sg:tags":[
        "statistics",
        "evaluation"
    ],
    "wof:name":"Lissitz & Associates",
    "wof:placetype":"venue"
},
  "geometry": {"coordinates":[-76.344686,38.893886],"type":"Point"}
}