{
  "type": "Feature",
  "properties": {
    "addr:full":"11 Public Sq Hagerstown MD 21740",
    "addr:housenumber":"11",
    "addr:postcode":"21740",
    "addr:street":"Public Sq",
    "iso:country":"US",
    "sg:address":"11 Public Sq",
    "sg:city":"Hagerstown",
    "sg:classifiers":[
        {
            "category":"Professional",
            "subcategory":"Art Services",
            "type":"Services"
        }
    ],
    "sg:phone":"+1 301 791 2080",
    "sg:postcode":"21740",
    "sg:province":"MD",
    "sg:tags":[
        "graphic",
        "designer"
    ],
    "sg:website":"www.icongraphics.com",
    "wof:name":"Icon Graphics",
    "wof:placetype":"venue"
},
  "geometry": {"coordinates":[-77.720433,39.64184],"type":"Point"}
}