{
  "type": "Feature",
  "properties": {
    "addr:full":"520 Ridgely Ave Annapolis MD 21401",
    "addr:housenumber":"520",
    "addr:postcode":"21401",
    "addr:street":"Ridgely Ave",
    "iso:country":"US",
    "sg:address":"520 Ridgely Ave",
    "sg:city":"Annapolis",
    "sg:classifiers":[
        {
            "category":"Autos & Motor Vehicles",
            "subcategory":"Boat Sales",
            "type":"Retail Goods"
        }
    ],
    "sg:phone":"+1 410 266 6616",
    "sg:postcode":"21401",
    "sg:province":"MD",
    "sg:tags":[
        "dealer",
        "sales"
    ],
    "wof:name":"Sail America",
    "wof:placetype":"venue"
},
  "geometry": {"coordinates":[-76.511264,38.994317],"type":"Point"}
}