{
  "type": "Feature",
  "properties": {
    "addr:full":"4232 Main St Manchester MD 21102",
    "addr:housenumber":"4232",
    "addr:postcode":"21102",
    "addr:street":"Main St",
    "iso:country":"US",
    "sg:address":"4232 Main St",
    "sg:city":"Manchester",
    "sg:classifiers":[
        {
            "category":"Bars & Pubs",
            "type":"Food & Drink"
        }
    ],
    "sg:phone":"+1 410 239 7082",
    "sg:postcode":"21102",
    "sg:province":"MD",
    "wof:name":"Village Inn",
    "wof:placetype":"venue"
},
  "geometry": {"coordinates":[-76.846047,39.717589],"type":"Point"}
}