{
  "type": "Feature",
  "properties": {
    "addr:full":"3814 Mary Ave Baltimore MD 21206",
    "addr:housenumber":"3814",
    "addr:postcode":"21206",
    "addr:street":"Mary Ave",
    "iso:country":"US",
    "sg:address":"3814 Mary Ave",
    "sg:city":"Baltimore",
    "sg:classifiers":[
        {
            "category":"Professional",
            "type":"Services"
        }
    ],
    "sg:phone":"+1 410 426 8568",
    "sg:postcode":"21206",
    "sg:province":"MD",
    "sg:tags":[
        "establishment"
    ],
    "wof:name":"Titanium Express",
    "wof:placetype":"venue"
},
  "geometry": {"coordinates":[-76.54561,39.347729],"type":"Point"}
}