{
  "type": "Feature",
  "properties": {
    "iso:country":"US",
    "sg:address":"1318 E Fort Ave",
    "sg:city":"Baltimore",
    "sg:classifiers":[
        {
            "category":"Building & Trades",
            "subcategory":"Construction",
            "type":"Services"
        }
    ],
    "sg:phone":"+1 410 332 4134",
    "sg:postcode":"21230",
    "sg:province":"MD",
    "sg:tags":[
        "management",
        "industrial",
        "contractors-commercial",
        "contractor"
    ],
    "sg:website":"http://www.southwaybuilders.com",
    "wof:name":"Southway Builders",
    "wof:placetype":"venue"
},
  "geometry": {"coordinates":[-76.59580200000001,39.2696],"type":"Point"}
}