{
  "type": "Feature",
  "properties": {
    "iso:country":"US",
    "sg:address":"7927 Mandan Rd",
    "sg:city":"Greenbelt",
    "sg:classifiers":[
        {
            "category":"Shopping",
            "subcategory":"Discount & Variety Stores",
            "type":"Retail Goods"
        }
    ],
    "sg:phone":"+1 301 343 0027",
    "sg:postcode":"20770",
    "sg:province":"MD",
    "sg:tags":[
        "merchandise",
        "general"
    ],
    "wof:name":"Wholesale Designer",
    "wof:placetype":"venue"
},
  "geometry": {"coordinates":[-76.865954,38.999085],"type":"Point"}
}