{
  "type": "Feature",
  "properties": {
    "addr:full":"44 E Sudbrook Ln Pikesville MD 21208",
    "addr:housenumber":"44",
    "addr:postcode":"21208",
    "addr:street":"E Sudbrook Ln",
    "iso:country":"US",
    "sg:address":"44 E Sudbrook Ln",
    "sg:city":"Pikesville",
    "sg:classifiers":[
        {
            "category":"Banks & Credit Unions",
            "subcategory":"Bank",
            "type":"Services"
        },
        {
            "category":"Banks & Credit Unions",
            "subcategory":"Financial Services",
            "type":"Services"
        }
    ],
    "sg:phone":"+1 410 602 2200",
    "sg:postcode":"21208",
    "sg:province":"MD",
    "sg:tags":[
        "commercial",
        "financing",
        "saving",
        "loan"
    ],
    "sg:website":"http://www.bbt.com",
    "wof:name":"BB & T",
    "wof:placetype":"venue"
},
  "geometry": {"coordinates":[-76.71971499999999,39.377128],"type":"Point"}
}