{
  "type": "Feature",
  "properties": {
    "addr:full":"2440 Dixie Ln Forest Hill MD 21050",
    "addr:housenumber":"2440",
    "addr:postcode":"21050",
    "addr:street":"Dixie Ln",
    "iso:country":"US",
    "sg:address":"2440 Dixie Ln",
    "sg:city":"Forest Hill",
    "sg:classifiers":[
        {
            "category":"Building & Trades",
            "subcategory":"Construction",
            "type":"Services"
        }
    ],
    "sg:phone":"+1 410 879 8507",
    "sg:postcode":"21050",
    "sg:province":"MD",
    "sg:tags":[
        "house"
    ],
    "wof:name":"Heritage Custom Builders Inc",
    "wof:placetype":"venue"
},
  "geometry": {"coordinates":[-76.359459,39.577896],"type":"Point"}
}