{
  "type": "Feature",
  "properties": {
    "iso:country":"US",
    "sg:address":"12016 Great Elm Dr",
    "sg:city":"Potomac",
    "sg:classifiers":[
        {
            "category":"Real Estate",
            "subcategory":"Developer",
            "type":"Services"
        }
    ],
    "sg:phone":"+1 301 983 6317",
    "sg:postcode":"20854",
    "sg:province":"MD",
    "wof:name":"Swiftwater Development LLC",
    "wof:placetype":"venue"
},
  "geometry": {"coordinates":[-77.243575,39.049079],"type":"Point"}
}