{
  "type": "Feature",
  "properties": {
    "iso:country":"US",
    "sg:address":"2 Burnham Woods Ct",
    "sg:city":"Annapolis",
    "sg:classifiers":[
        {
            "category":"Health Services",
            "subcategory":"Health Practitioner",
            "type":"Services"
        }
    ],
    "sg:phone":"+1 410 626 0361",
    "sg:postcode":"21403",
    "sg:province":"MD",
    "sg:tags":[
        "psychologist"
    ],
    "wof:name":"Joanne B Mendelman PHD",
    "wof:placetype":"venue"
},
  "geometry": {"coordinates":[-76.508364,38.951782],"type":"Point"}
}