{
  "type": "Feature",
  "properties": {
    "iso:country":"US",
    "sg:address":"5817 Jamestown Rd",
    "sg:city":"Hyattsville",
    "sg:classifiers":[
        {
            "category":"Professional",
            "subcategory":"Management & Consulting",
            "type":"Services"
        }
    ],
    "sg:phone":"+1 610 558 9994",
    "sg:postcode":"20782",
    "sg:province":"MD",
    "sg:tags":[
        "engineering",
        "system"
    ],
    "wof:name":"Belk",
    "wof:placetype":"venue"
},
  "geometry": {"coordinates":[-76.958882,38.961176],"type":"Point"}
}