{
  "type": "Feature",
  "properties": {
    "iso:country":"US",
    "sg:address":"12302 Collins Rd",
    "sg:city":"Bishopville",
    "sg:classifiers":[
        {
            "category":"Building & Trades",
            "subcategory":"Landscaping Services",
            "type":"Services"
        }
    ],
    "sg:phone":"+1 410 352 5623",
    "sg:postcode":"21813",
    "sg:province":"MD",
    "sg:tags":[
        "consultant",
        "designer",
        "landscape"
    ],
    "sg:website":"http://www.rdhand.com",
    "wof:name":"R D Hand & Associates Inc",
    "wof:placetype":"venue"
},
  "geometry": {"coordinates":[-75.189071,38.41597],"type":"Point"}
}