{
  "type": "Feature",
  "properties": {
    "iso:country":"US",
    "sg:address":"401 Sunburst Hwy",
    "sg:city":"Cambridge",
    "sg:classifiers":[
        {
            "category":"Autos & Motor Vehicles",
            "subcategory":"Auto Supplies",
            "type":"Retail Goods"
        }
    ],
    "sg:phone":"+1 410 901 2418",
    "sg:postcode":"21613",
    "sg:province":"MD",
    "sg:tags":[
        "tire"
    ],
    "wof:name":"Admiral Tire & Auto Ctr",
    "wof:placetype":"venue"
},
  "geometry": {"coordinates":[-76.065913,38.563908],"type":"Point"}
}