{
  "type": "Feature",
  "properties": {
    "addr:full":"15815 Glacier Ct Gaithersburg MD 20878",
    "addr:housenumber":"15815",
    "addr:postcode":"20878",
    "addr:street":"Glacier Ct",
    "iso:country":"US",
    "sg:address":"15815 Glacier Ct",
    "sg:city":"Gaithersburg",
    "sg:classifiers":[
        {
            "category":"Professional",
            "type":"Services"
        }
    ],
    "sg:phone":"+1 301 869 7350",
    "sg:postcode":"20878",
    "sg:province":"MD",
    "wof:name":"Martin Sr Joseph A",
    "wof:placetype":"venue"
},
  "geometry": {"coordinates":[-77.259888,39.117096],"type":"Point"}
}