{
  "type": "Feature",
  "properties": {
    "addr:full":"7400 Commerce Ln Clinton MD 20735",
    "addr:housenumber":"7400",
    "addr:postcode":"20735",
    "addr:street":"Commerce Ln",
    "iso:country":"US",
    "sg:address":"7400 Commerce Ln",
    "sg:city":"Clinton",
    "sg:classifiers":[
        {
            "category":"Utilities",
            "subcategory":"Telephone",
            "type":"Services"
        }
    ],
    "sg:phone":"+1 301 297 7451",
    "sg:postcode":"20735",
    "sg:province":"MD",
    "sg:tags":[
        "communications"
    ],
    "wof:name":"Verizon",
    "wof:placetype":"venue"
},
  "geometry": {"coordinates":[-76.906155,38.785483],"type":"Point"}
}