{
  "type": "Feature",
  "properties": {
    "iso:country":"US",
    "sg:address":"15 Crafton Rd",
    "sg:city":"Essex",
    "sg:classifiers":[
        {
            "category":"Structure",
            "subcategory":"Warehouse",
            "type":"Public Place"
        },
        {
            "category":"Retail",
            "subcategory":"Storage",
            "type":"Services"
        }
    ],
    "sg:phone":"+1 410 633 9690",
    "sg:postcode":"21221",
    "sg:province":"MD",
    "sg:tags":[
        "self",
        "warehouses-public-commercial"
    ],
    "wof:name":"Just 4 Inc",
    "wof:placetype":"venue"
},
  "geometry": {"coordinates":[-76.48491199999999,39.306009],"type":"Point"}
}