{
  "type": "Feature",
  "properties": {
    "addr:full":"401 N Atlantic Ave Ocean City MD 21842",
    "addr:housenumber":"401",
    "addr:postcode":"21842",
    "addr:street":"N Atlantic Ave",
    "iso:country":"US",
    "sg:address":"401 N Atlantic Ave",
    "sg:city":"Ocean City",
    "sg:classifiers":[
        {
            "category":"Shopping",
            "subcategory":"Jewelry",
            "type":"Retail Goods"
        }
    ],
    "sg:phone":"+1 410 289 5002",
    "sg:postcode":"21842",
    "sg:province":"MD",
    "sg:tags":[
        "jeweler"
    ],
    "wof:name":"Free As A Bird",
    "wof:placetype":"venue"
},
  "geometry": {"coordinates":[-75.08249499999999,38.335909],"type":"Point"}
}