{
  "type": "Feature",
  "properties": {
    "addr:full":"611 Central Ave Baltimore MD 21204",
    "addr:housenumber":"611",
    "addr:postcode":"21204",
    "addr:street":"Central Ave",
    "iso:country":"US",
    "sg:address":"611 Central Ave",
    "sg:city":"Baltimore",
    "sg:classifiers":[
        {
            "category":"Government",
            "subcategory":"Office",
            "type":"Public Place"
        }
    ],
    "sg:phone":"+1 410 887 2080",
    "sg:postcode":"21204",
    "sg:province":"MD",
    "wof:name":"Countyride",
    "wof:placetype":"venue"
},
  "geometry": {"coordinates":[-76.609556,39.402618],"type":"Point"}
}