{
  "type": "Feature",
  "properties": {
    "addr:full":"1003 Old Philadelphia Rd Aberdeen MD 21001",
    "addr:housenumber":"1003",
    "addr:postcode":"21001",
    "addr:street":"Old Philadelphia Rd",
    "iso:country":"US",
    "sg:address":"1003 Old Philadelphia Rd",
    "sg:city":"Aberdeen",
    "sg:classifiers":[
        {
            "category":"Professional",
            "subcategory":"Business Services",
            "type":"Services"
        }
    ],
    "sg:phone":"+1 410 575 7517",
    "sg:postcode":"21001",
    "sg:province":"MD",
    "sg:tags":[
        "water",
        "treatment"
    ],
    "sg:website":"www.waterchem.com",
    "wof:name":"Waterchem",
    "wof:placetype":"venue"
},
  "geometry": {"coordinates":[-76.187219,39.488761],"type":"Point"}
}