{
  "type": "Feature",
  "properties": {
    "addr:full":"4800 Lawrence St Hyattsville MD 20781",
    "addr:housenumber":"4800",
    "addr:postcode":"20781",
    "addr:street":"Lawrence St",
    "iso:country":"US",
    "sg:address":"4800 Lawrence St",
    "sg:city":"Hyattsville",
    "sg:classifiers":[
        {
            "category":"Freight",
            "type":"Transportation"
        }
    ],
    "sg:phone":"+1 301 773 4800",
    "sg:postcode":"20781",
    "sg:province":"MD",
    "sg:tags":[
        "trucking"
    ],
    "wof:name":"Hawk Enterprises Inc",
    "wof:placetype":"venue"
},
  "geometry": {"coordinates":[-76.933948,38.932024],"type":"Point"}
}