{
  "type": "Feature",
  "properties": {
    "iso:country":"US",
    "sg:address":"12511 Hillmeade Station Dr",
    "sg:city":"Bowie",
    "sg:classifiers":[
        {
            "category":"Social Services",
            "subcategory":"Child Care",
            "type":"Services"
        }
    ],
    "sg:phone":"+1 301 860 0577",
    "sg:postcode":"20720",
    "sg:province":"MD",
    "sg:tags":[
        "day"
    ],
    "wof:name":"Heavenly Kids Family Day Care",
    "wof:placetype":"venue"
},
  "geometry": {"coordinates":[-76.78639,38.982878],"type":"Point"}
}