{
  "type": "Feature",
  "properties": {
    "iso:country":"US",
    "sg:address":"10401 Old Georgetown Rd Ste 304",
    "sg:city":"Bethesda",
    "sg:classifiers":[
        {
            "category":"Health Services",
            "subcategory":"Doctor",
            "type":"Services"
        }
    ],
    "sg:phone":"+1 301 530 7700",
    "sg:postcode":"20814",
    "sg:province":"MD",
    "wof:name":"Joy Chen, MD",
    "wof:placetype":"venue"
},
  "geometry": {"coordinates":[-77.125311,39.026502],"type":"Point"}
}