{
  "type": "Feature",
  "properties": {
    "addr:full":"2453 Maryland Ave Baltimore MD 21218",
    "addr:housenumber":"2453",
    "addr:postcode":"21218",
    "addr:street":"Maryland Ave",
    "iso:country":"US",
    "sg:address":"2453 Maryland Ave",
    "sg:city":"Baltimore",
    "sg:classifiers":[
        {
            "category":"Professional",
            "subcategory":"Business Services",
            "type":"Services"
        }
    ],
    "sg:phone":"+1 443 447 6228",
    "sg:postcode":"21218",
    "sg:province":"MD",
    "sg:tags":[
        "consultant",
        "coach"
    ],
    "sg:website":"http://www.bilingualsecretary.com",
    "wof:name":"Bilingual Secretary Services LLC",
    "wof:placetype":"venue"
},
  "geometry": {"coordinates":[-76.618351,39.317863],"type":"Point"}
}