{
  "type": "Feature",
  "properties": {
    "iso:country":"US",
    "sg:address":"4532 Bennion Rd",
    "sg:city":"Silver Spring",
    "sg:classifiers":[
        {
            "category":"Professional",
            "subcategory":"Research",
            "type":"Services"
        }
    ],
    "sg:phone":"+1 301 942 6100",
    "sg:postcode":"20906",
    "sg:province":"MD",
    "sg:tags":[
        "laboratory"
    ],
    "wof:name":"Collins Dental Laboratory",
    "wof:placetype":"venue"
},
  "geometry": {"coordinates":[-77.08937,39.051662],"type":"Point"}
}