{
  "type": "Feature",
  "properties": {
    "iso:country":"US",
    "sg:address":"3638 Jarrettsville Pike",
    "sg:city":"Monkton",
    "sg:classifiers":[
        {
            "category":"Retail",
            "subcategory":"Repair Shop",
            "type":"Services"
        }
    ],
    "sg:phone":"+1 410 557 7418",
    "sg:postcode":"21111",
    "sg:province":"MD",
    "sg:tags":[
        "machine",
        "sewing"
    ],
    "wof:name":"Saturn Sewing",
    "wof:placetype":"venue"
},
  "geometry": {"coordinates":[-76.509885,39.591395],"type":"Point"}
}