{
  "type": "Feature",
  "properties": {
    "addr:full":"7927 Grant Dr Lanham MD 20706",
    "addr:housenumber":"7927",
    "addr:postcode":"20706",
    "addr:street":"Grant Dr",
    "iso:country":"US",
    "sg:address":"7927 Grant Dr",
    "sg:city":"Lanham",
    "sg:classifiers":[
        {
            "category":"Professional",
            "subcategory":"Business Services",
            "type":"Services"
        }
    ],
    "sg:phone":"+1 301 772 7976",
    "sg:postcode":"20706",
    "sg:province":"MD",
    "wof:name":"AF Diversified Services",
    "wof:placetype":"venue"
},
  "geometry": {"coordinates":[-76.870344,38.932781],"type":"Point"}
}