{
  "type": "Feature",
  "properties": {
    "iso:country":"US",
    "sg:address":"8629 Leslie Ave",
    "sg:city":"Lanham",
    "sg:classifiers":[
        {
            "category":"Professional",
            "subcategory":"Engineering",
            "type":"Services"
        }
    ],
    "sg:phone":"+1 301 322 5233",
    "sg:postcode":"20706",
    "sg:province":"MD",
    "sg:tags":[
        "track",
        "railway"
    ],
    "wof:name":"Zicha Engineering Corporation",
    "wof:placetype":"venue"
},
  "geometry": {"coordinates":[-76.86461,38.932846],"type":"Point"}
}