{
  "type": "Feature",
  "properties": {
    "iso:country":"US",
    "sg:address":"201 Milford St",
    "sg:city":"Salisbury",
    "sg:classifiers":[
        {
            "category":"Personal",
            "type":"Services"
        }
    ],
    "sg:phone":"+1 410 749 7198",
    "sg:postcode":"21804",
    "sg:province":"MD",
    "sg:tags":[
        "program",
        "physical",
        "exercise",
        "fitness"
    ],
    "wof:name":"Merritt Athletic Club",
    "wof:placetype":"venue"
},
  "geometry": {"coordinates":[-75.602749,38.338814],"type":"Point"}
}