{
  "type": "Feature",
  "properties": {
    "addr:full":"5517 Urbana Pike Frederick MD 21704",
    "addr:housenumber":"5517",
    "addr:postcode":"21704",
    "addr:street":"Urbana Pike",
    "iso:country":"US",
    "sg:address":"5517 Urbana Pike",
    "sg:city":"Frederick",
    "sg:classifiers":[
        {
            "category":"Wholesale",
            "subcategory":"Painting Supplies",
            "type":"Manufacturing & Wholesale Goods"
        },
        {
            "category":"Home & Garden",
            "subcategory":"Hardware",
            "type":"Retail Goods"
        },
        {
            "category":"Home & Garden",
            "subcategory":"Building Materials",
            "type":"Retail Goods"
        },
        {
            "category":"Manufacturing",
            "subcategory":"Tools & Machinery",
            "type":"Manufacturing & Wholesale Goods"
        }
    ],
    "sg:phone":"+1 301 620 0571",
    "sg:postcode":"21704",
    "sg:province":"MD",
    "sg:tags":[
        "paint",
        "store",
        "improvement"
    ],
    "sg:website":"http://www.homedepot.com",
    "wof:name":"The Home Depot",
    "wof:placetype":"venue"
},
  "geometry": {"coordinates":[-77.400988,39.382852],"type":"Point"}
}