{
  "type": "Feature",
  "properties": {
    "iso:country":"US",
    "sg:address":"21404 Manor View Cir",
    "sg:city":"Germantown",
    "sg:classifiers":[
        {
            "category":"Shopping",
            "subcategory":"Gifts & Souvenirs",
            "type":"Retail Goods"
        }
    ],
    "sg:phone":"+1 301 601 9589",
    "sg:postcode":"20876",
    "sg:province":"MD",
    "wof:name":"Gifts To Remember",
    "wof:placetype":"venue"
},
  "geometry": {"coordinates":[-77.250523,39.207895],"type":"Point"}
}