{
  "type": "Feature",
  "properties": {
    "iso:country":"US",
    "sg:address":"1458 Pinch Valley Rd",
    "sg:city":"Westminster",
    "sg:classifiers":[
        {
            "category":"Professional",
            "subcategory":"Accounting & Tax Preparation",
            "type":"Services"
        }
    ],
    "sg:phone":"+1 410 875 2021",
    "sg:postcode":"21158",
    "sg:province":"MD",
    "sg:tags":[
        "return",
        "filing"
    ],
    "wof:name":"Charles Miller Tax Svc",
    "wof:placetype":"venue"
},
  "geometry": {"coordinates":[-77.014957,39.618149],"type":"Point"}
}