{
  "type": "Feature",
  "properties": {
    "addr:full":"598 Cynwood Dr Easton MD 21601",
    "addr:housenumber":"598",
    "addr:postcode":"21601",
    "addr:street":"Cynwood Dr",
    "iso:country":"US",
    "sg:address":"598 Cynwood Dr",
    "sg:city":"Easton",
    "sg:classifiers":[
        {
            "category":"Health Services",
            "subcategory":"Doctor",
            "type":"Services"
        }
    ],
    "sg:phone":"+1 410 820 7040",
    "sg:postcode":"21601",
    "sg:province":"MD",
    "sg:tags":[
        "physician",
        "surgeon"
    ],
    "wof:name":"Cheryl Ortel MD",
    "wof:placetype":"venue"
},
  "geometry": {"coordinates":[-76.061939,38.754063],"type":"Point"}
}