{
  "type": "Feature",
  "properties": {
    "addr:full":"17 Rolling Green Ct Lutherville MD 21093",
    "addr:housenumber":"17",
    "addr:postcode":"21093",
    "addr:street":"Rolling Green Ct",
    "iso:country":"US",
    "sg:address":"17 Rolling Green Ct",
    "sg:city":"Lutherville",
    "sg:classifiers":[
        {
            "category":"Real Estate",
            "subcategory":"Architect",
            "type":"Services"
        }
    ],
    "sg:phone":"+1 410 494 1956",
    "sg:postcode":"21093",
    "sg:province":"MD",
    "sg:tags":[
        "home",
        "planning",
        "design"
    ],
    "wof:name":"Southern Cross Homes",
    "wof:placetype":"venue"
},
  "geometry": {"coordinates":[-76.642387,39.42984],"type":"Point"}
}