{
  "type": "Feature",
  "properties": {
    "addr:full":"378 Mc Arthur Blvd California MD 20619",
    "addr:housenumber":"378",
    "addr:postcode":"20619",
    "addr:street":"Mc Arthur Blvd",
    "iso:country":"US",
    "sg:address":"378 Mc Arthur Blvd",
    "sg:city":"California",
    "sg:classifiers":[
        {
            "category":"Restaurant",
            "type":"Food & Drink"
        }
    ],
    "sg:phone":"+1 301 863 6876",
    "sg:postcode":"20619",
    "sg:province":"MD",
    "wof:name":"Subway Sandwiches & Salad",
    "wof:placetype":"venue"
},
  "geometry": {"coordinates":[-76.5159,38.293499],"type":"Point"}
}