{
  "type": "Feature",
  "properties": {
    "iso:country":"US",
    "sg:address":"3411 N High St",
    "sg:city":"Olney",
    "sg:classifiers":[
        {
            "category":"Autos & Motor Vehicles",
            "subcategory":"Auto Supplies",
            "type":"Retail Goods"
        },
        {
            "category":"Retail",
            "subcategory":"Auto Repair",
            "type":"Services"
        }
    ],
    "sg:phone":"+1 301 924 8473",
    "sg:postcode":"20832",
    "sg:province":"MD",
    "sg:tags":[
        "automobile",
        "part",
        "truck"
    ],
    "sg:website":"http://clickserve.dartsearch.net/link/click?lid=43000000313870888&ds_s_kwgid=58000000006820725&ds_e_matchtype={MatchType}&ds_e_kwdid={OrderItemId}&ds_e_adid={AdId}&ds_url_v=2",
    "wof:name":"Graeves Auto & Appliance",
    "wof:placetype":"venue"
},
  "geometry": {"coordinates":[-77.067014,39.15132],"type":"Point"}
}