{
  "type": "Feature",
  "properties": {
    "iso:country":"US",
    "sg:address":"2022 W Lafayette Ave",
    "sg:city":"Baltimore",
    "sg:classifiers":[
        {
            "category":"Food & Beverages",
            "subcategory":"Groceries & Convenience Stores",
            "type":"Retail Goods"
        }
    ],
    "sg:phone":"+1 410 669 6500",
    "sg:postcode":"21217",
    "sg:province":"MD",
    "sg:tags":[
        "grocer"
    ],
    "wof:name":"Food City",
    "wof:placetype":"venue"
},
  "geometry": {"coordinates":[-76.650243,39.298673],"type":"Point"}
}