{
  "type": "Feature",
  "properties": {
    "iso:country":"US",
    "sg:address":"6007 Corewood Ln",
    "sg:city":"Bethesda",
    "sg:classifiers":[
        {
            "category":"Health Services",
            "subcategory":"Doctor",
            "type":"Services"
        }
    ],
    "sg:phone":"+1 301 229 3550",
    "sg:postcode":"20816",
    "sg:province":"MD",
    "wof:name":"Bellanti Joseph A MD",
    "wof:placetype":"venue"
},
  "geometry": {"coordinates":[-77.1203,38.954601],"type":"Point"}
}