{
  "type": "Feature",
  "properties": {
    "iso:country":"US",
    "sg:address":"2 Ivory Crest Ct",
    "sg:city":"Baltimore",
    "sg:classifiers":[
        {
            "category":"Professional",
            "subcategory":"Management & Consulting",
            "type":"Services"
        }
    ],
    "sg:phone":"+1 410 484 7996",
    "sg:postcode":"21209",
    "sg:province":"MD",
    "wof:name":"Aleph Group Inc",
    "wof:placetype":"venue"
},
  "geometry": {"coordinates":[-76.677576,39.383508],"type":"Point"}
}