{
  "type": "Feature",
  "properties": {
    "iso:country":"US",
    "sg:address":"5018A Old National Pike",
    "sg:city":"Frederick",
    "sg:classifiers":[
        {
            "category":"Shopping",
            "subcategory":"Antiques",
            "type":"Retail Goods"
        }
    ],
    "sg:phone":"+1 301 371 5591",
    "sg:postcode":"21702",
    "sg:province":"MD",
    "wof:name":"Mark Mc Connell",
    "wof:placetype":"venue"
},
  "geometry": {"coordinates":[-77.497337,39.421967],"type":"Point"}
}