{
  "type": "Feature",
  "properties": {
    "iso:country":"US",
    "sg:address":"414 Doe Meadow Dr",
    "sg:city":"Owings Mills",
    "sg:classifiers":[
        {
            "category":"Social Services",
            "type":"Services"
        }
    ],
    "sg:phone":"+1 410 356 0142",
    "sg:postcode":"21117",
    "sg:province":"MD",
    "sg:tags":[
        "youth",
        "organization",
        "center"
    ],
    "wof:name":"Diamonds Baseball Club",
    "wof:placetype":"venue"
},
  "geometry": {"coordinates":[-76.789626,39.449672],"type":"Point"}
}