{
  "type": "Feature",
  "properties": {
    "iso:country":"US",
    "sg:address":"4 Mellor Ave",
    "sg:city":"Catonsville",
    "sg:classifiers":[
        {
            "category":"Personal",
            "type":"Services"
        }
    ],
    "sg:phone":"+1 410 598 7893",
    "sg:postcode":"21228",
    "sg:province":"MD",
    "sg:tags":[
        "local"
    ],
    "sg:website":"www.fixmyaxe.com",
    "wof:name":"Anthony Instrument Repair",
    "wof:placetype":"venue"
},
  "geometry": {"coordinates":[-76.733954,39.271432],"type":"Point"}
}