{
  "type": "Feature",
  "properties": {
    "addr:full":"1024 Grandview Ave Sykesville MD 21784",
    "addr:housenumber":"1024",
    "addr:postcode":"21784",
    "addr:street":"Grandview Ave",
    "iso:country":"US",
    "sg:address":"1024 Grandview Ave",
    "sg:city":"Sykesville",
    "sg:classifiers":[
        {
            "category":"Professional",
            "subcategory":"Computer Services",
            "type":"Services"
        }
    ],
    "sg:phone":"+1 410 795 3830",
    "sg:postcode":"21784",
    "sg:province":"MD",
    "wof:name":"Drawn By Kim",
    "wof:placetype":"venue"
},
  "geometry": {"coordinates":[-76.957778,39.395937],"type":"Point"}
}