{
  "type": "Feature",
  "properties": {
    "addr:full":"515 W Patrick St Frederick MD 21701",
    "addr:housenumber":"515",
    "addr:postcode":"21701",
    "addr:street":"W Patrick St",
    "iso:country":"US",
    "sg:address":"515 W Patrick St",
    "sg:city":"Frederick",
    "sg:classifiers":[
        {
            "category":"Education",
            "subcategory":"School",
            "type":"Public Place"
        }
    ],
    "sg:phone":"+1 240 236 4000",
    "sg:postcode":"21701",
    "sg:province":"MD",
    "sg:tags":[
        "executive"
    ],
    "wof:name":"West Frederick Middle School",
    "wof:placetype":"venue"
},
  "geometry": {"coordinates":[-77.428201,39.4141],"type":"Point"}
}