{
  "type": "Feature",
  "properties": {
    "iso:country":"US",
    "sg:address":"7437 Sharpsburg Pike",
    "sg:city":"Boonsboro",
    "sg:classifiers":[
        {
            "category":"Farming",
            "subcategory":"Nursery",
            "type":"Manufacturing & Wholesale Goods"
        }
    ],
    "sg:phone":"+1 301 432 2327",
    "sg:postcode":"21713",
    "sg:province":"MD",
    "sg:tags":[
        "greenhouse"
    ],
    "wof:name":"Sunny Meadows Greenhouse",
    "wof:placetype":"venue"
},
  "geometry": {"coordinates":[-77.743381,39.522189],"type":"Point"}
}