{
  "type": "Feature",
  "properties": {
    "iso:country":"US",
    "sg:address":"302 Cedar St",
    "sg:city":"Cambridge",
    "sg:classifiers":[
        {
            "category":"Shopping",
            "subcategory":"Florist",
            "type":"Retail Goods"
        }
    ],
    "sg:phone":"+1 410 228 6331",
    "sg:postcode":"21613",
    "sg:province":"MD",
    "wof:name":"Flowers 'n Things",
    "wof:placetype":"venue"
},
  "geometry": {"coordinates":[-76.076224,38.565365],"type":"Point"}
}