{
  "type": "Feature",
  "properties": {
    "iso:country":"US",
    "sg:address":"1309 Continental Dr",
    "sg:city":"Abingdon",
    "sg:classifiers":[
        {
            "category":"Retail",
            "subcategory":"Repair Shop",
            "type":"Services"
        }
    ],
    "sg:phone":"+1 410 679 3698",
    "sg:postcode":"21009",
    "sg:province":"MD",
    "sg:tags":[
        "plumbing",
        "drain",
        "cleaning",
        "sewer"
    ],
    "wof:name":"D & L Drains",
    "wof:placetype":"venue"
},
  "geometry": {"coordinates":[-76.29207700000001,39.447913],"type":"Point"}
}