{
  "type": "Feature",
  "properties": {
    "iso:country":"US",
    "sg:address":"1006 Joppa Farm Rd",
    "sg:city":"Joppa",
    "sg:classifiers":[
        {
            "category":"Restaurant",
            "type":"Food & Drink"
        }
    ],
    "sg:phone":"+1 410 538 4590",
    "sg:postcode":"21085",
    "sg:province":"MD",
    "wof:name":"Mariner Seafood & Subs",
    "wof:placetype":"venue"
},
  "geometry": {"coordinates":[-76.37064100000001,39.422521],"type":"Point"}
}