{
  "type": "Feature",
  "properties": {
    "addr:full":"293 Cross Creek Dr Glen Burnie MD 21061",
    "addr:housenumber":"293",
    "addr:postcode":"21061",
    "addr:street":"Cross Creek Dr",
    "iso:country":"US",
    "sg:address":"293 Cross Creek Dr",
    "sg:city":"Glen Burnie",
    "sg:classifiers":[
        {
            "category":"Retail",
            "subcategory":"Portrait Studio",
            "type":"Services"
        }
    ],
    "sg:phone":"+1 410 760 1208",
    "sg:postcode":"21061",
    "sg:province":"MD",
    "sg:tags":[
        "photo"
    ],
    "wof:name":"Picture Prfect Phtgrphy Lmosne",
    "wof:placetype":"venue"
},
  "geometry": {"coordinates":[-76.616404,39.134892],"type":"Point"}
}