{
  "type": "Feature",
  "properties": {
    "iso:country":"US",
    "sg:address":"205 Contee Ct",
    "sg:city":"Joppa",
    "sg:classifiers":[
        {
            "category":"Building & Trades",
            "subcategory":"Construction",
            "type":"Services"
        }
    ],
    "sg:phone":"+1 410 538 4736",
    "sg:postcode":"21085",
    "sg:province":"MD",
    "sg:tags":[
        "housing"
    ],
    "wof:name":"H & H Construction",
    "wof:placetype":"venue"
},
  "geometry": {"coordinates":[-76.36402200000001,39.415998],"type":"Point"}
}