{
  "type": "Feature",
  "properties": {
    "iso:country":"US",
    "sg:address":"510 McCormick Dr",
    "sg:city":"Glen Burnie",
    "sg:classifiers":[
        {
            "category":"Building & Trades",
            "subcategory":"Construction",
            "type":"Services"
        }
    ],
    "sg:phone":"+1 410 590 6023",
    "sg:postcode":"21061",
    "sg:province":"MD",
    "sg:tags":[
        "dry wall",
        "contractor"
    ],
    "wof:name":"American First Choice Drywall",
    "wof:placetype":"venue"
},
  "geometry": {"coordinates":[-76.67424800000001,39.157193],"type":"Point"}
}