{
  "type": "Feature",
  "properties": {
    "addr:full":"11753 Chesterville Rd Kennedyville MD 21645",
    "addr:postcode":"11753;21645",
    "addr:street":"Chesterville Rd",
    "iso:country":"US",
    "sg:address":"11753 Chesterville Rd",
    "sg:city":"Kennedyville",
    "sg:classifiers":[
        {
            "category":"Building & Trades",
            "subcategory":"Construction",
            "type":"Services"
        }
    ],
    "sg:phone":"+1 410 648 5579",
    "sg:postcode":"21645",
    "sg:province":"MD",
    "sg:tags":[
        "roofing",
        "contractor"
    ],
    "wof:name":"Commercial Roof Coating Inc",
    "wof:placetype":"venue"
},
  "geometry": {"coordinates":[-75.909571,39.287949],"type":"Point"}
}