{
  "type": "Feature",
  "properties": {
    "addr:full":"5283 Buckeystown Pike Frederick MD 21704",
    "addr:housenumber":"5283",
    "addr:postcode":"21704",
    "addr:street":"Buckeystown Pike",
    "iso:country":"US",
    "sg:address":"5283 Buckeystown Pike",
    "sg:city":"Frederick",
    "sg:classifiers":[
        {
            "category":"Coffee & Tea",
            "type":"Food & Drink"
        }
    ],
    "sg:menulink":"http://www.allmenus.com/md/frederick/119029-starbucks-coffee/menu/",
    "sg:phone":"+1 301 682 3330",
    "sg:postcode":"21704",
    "sg:province":"MD",
    "sg:tags":[
        "american"
    ],
    "wof:name":"Starbucks Coffee",
    "wof:placetype":"venue"
},
  "geometry": {"coordinates":[-77.40935899999999,39.376829],"type":"Point"}
}