{
  "type": "Feature",
  "properties": {
    "iso:country":"US",
    "sg:address":"5806 York Rd",
    "sg:city":"Baltimore",
    "sg:classifiers":[
        {
            "category":"Building & Trades",
            "subcategory":"Plumbing",
            "type":"Services"
        }
    ],
    "sg:phone":"+1 410 323 5400",
    "sg:postcode":"21212",
    "sg:province":"MD",
    "sg:tags":[
        "contractor"
    ],
    "sg:website":"www.calvertinc.com",
    "wof:name":"Calvert Plumbing & Heating",
    "wof:placetype":"venue"
},
  "geometry": {"coordinates":[-76.609802,39.361099],"type":"Point"}
}