{
  "type": "Feature",
  "properties": {
    "addr:full":"20700 Martinsburg Rd Dickerson MD 20842",
    "addr:postcode":"20700;20842",
    "addr:street":"Martinsburg Rd",
    "iso:country":"US",
    "sg:address":"20700 Martinsburg Rd",
    "sg:city":"Dickerson",
    "sg:classifiers":[
        {
            "category":"Government",
            "subcategory":"Office",
            "type":"Public Place"
        }
    ],
    "sg:phone":"+1 301 972 9396",
    "sg:postcode":"20842",
    "sg:province":"MD",
    "sg:tags":[
        "county"
    ],
    "wof:name":"Dickerson Conservation Park",
    "wof:placetype":"venue"
},
  "geometry": {"coordinates":[-77.458557,39.194934],"type":"Point"}
}