{
  "type": "Feature",
  "properties": {
    "iso:country":"US",
    "sg:address":"7904 Gilmore Ave",
    "sg:city":"Rosedale",
    "sg:classifiers":[
        {
            "category":"Personal",
            "type":"Services"
        },
        {
            "category":"Building & Trades",
            "subcategory":"Construction",
            "type":"Services"
        },
        {
            "category":"Manufacturing",
            "subcategory":"Building Materials",
            "type":"Manufacturing & Wholesale Goods"
        }
    ],
    "sg:phone":"+1 410 687 2039",
    "sg:postcode":"21237",
    "sg:province":"MD",
    "sg:tags":[
        "roofing",
        "industrial",
        "sheet",
        "work",
        "metal",
        "contractor",
        "siding",
        "contractors-commercial",
        "home",
        "local"
    ],
    "sg:website":"none",
    "wof:name":"Residential Roofing",
    "wof:placetype":"venue"
},
  "geometry": {"coordinates":[-76.51305499999999,39.31503],"type":"Point"}
}