{
  "type": "Feature",
  "properties": {
    "addr:full":"14740 Old York Rd Phoenix MD 21131",
    "addr:housenumber":"14740",
    "addr:postcode":"21131",
    "addr:street":"Old York Rd",
    "iso:country":"US",
    "sg:address":"14740 Old York Rd",
    "sg:city":"Phoenix",
    "sg:classifiers":[
        {
            "category":"Wholesale",
            "subcategory":"Construction Materials",
            "type":"Manufacturing & Wholesale Goods"
        }
    ],
    "sg:phone":"+1 410 771 4148",
    "sg:postcode":"21131",
    "sg:province":"MD",
    "sg:tags":[
        "marble"
    ],
    "wof:name":"Santo J Navarria Tile Co",
    "wof:placetype":"venue"
},
  "geometry": {"coordinates":[-76.572457,39.53126],"type":"Point"}
}