{
  "type": "Feature",
  "properties": {
    "addr:full":"8604 2nd Ave Silver Spring MD 20910",
    "addr:housenumber":"8604",
    "addr:postcode":"20910",
    "addr:street":"2Nd Ave",
    "iso:country":"US",
    "sg:address":"8604 2nd Ave",
    "sg:city":"Silver Spring",
    "sg:classifiers":[
        {
            "category":"Building & Trades",
            "subcategory":"Construction",
            "type":"Services"
        }
    ],
    "sg:phone":"+1 301 608 3960",
    "sg:postcode":"20910",
    "sg:province":"MD",
    "sg:tags":[
        "waterproofing",
        "contractor"
    ],
    "wof:name":"Diamond State Waterproofing",
    "wof:placetype":"venue"
},
  "geometry": {"coordinates":[-77.03337399999999,38.996784],"type":"Point"}
}