{
  "type": "Feature",
  "properties": {
    "addr:full":"1830 Billman Ln Silver Spring MD 20902",
    "addr:housenumber":"1830",
    "addr:postcode":"20902",
    "addr:street":"Billman Ln",
    "iso:country":"US",
    "sg:address":"1830 Billman Ln",
    "sg:city":"Silver Spring",
    "sg:classifiers":[
        {
            "category":"Building & Trades",
            "subcategory":"Construction",
            "type":"Services"
        }
    ],
    "sg:phone":"+1 301 946 6088",
    "sg:postcode":"20902",
    "sg:province":"MD",
    "sg:tags":[
        "hanging",
        "contractor"
    ],
    "wof:name":"Barsa Quality Painting SE",
    "wof:placetype":"venue"
},
  "geometry": {"coordinates":[-77.040575,39.062487],"type":"Point"}
}