{
  "type": "Feature",
  "properties": {
    "iso:country":"US",
    "sg:address":"4404 Holter Ct",
    "sg:city":"Jefferson",
    "sg:classifiers":[
        {
            "category":"Professional",
            "subcategory":"Detective & Security Services",
            "type":"Services"
        }
    ],
    "sg:phone":"+1 301 371 3584",
    "sg:postcode":"21755",
    "sg:province":"MD",
    "sg:tags":[
        "information",
        "bureau"
    ],
    "wof:name":"Remote Sensing Technology, Inc.",
    "wof:placetype":"venue"
},
  "geometry": {"coordinates":[-77.514787,39.398515],"type":"Point"}
}