{
  "type": "Feature",
  "properties": {
    "addr:full":"4831 del Ray Ave Bethesda MD 20814",
    "addr:housenumber":"4831",
    "addr:postcode":"20814",
    "addr:street":"Del Ray Ave",
    "iso:country":"US",
    "sg:address":"4831 del Ray Ave",
    "sg:city":"Bethesda",
    "sg:classifiers":[
        {
            "category":"Building & Trades",
            "subcategory":"Plumbing",
            "type":"Services"
        }
    ],
    "sg:phone":"+1 301 654 3224",
    "sg:postcode":"20814",
    "sg:province":"MD",
    "sg:tags":[
        "heating",
        "contractor"
    ],
    "wof:name":"Bethesda Refrigeration Svc",
    "wof:placetype":"venue"
},
  "geometry": {"coordinates":[-77.098574,38.990303],"type":"Point"}
}