{
  "type": "Feature",
  "properties": {
    "iso:country":"US",
    "sg:address":"11307 Baritone Ct",
    "sg:city":"Silver Spring",
    "sg:phone":"+1 301 681 7764",
    "sg:postcode":"20901",
    "sg:province":"MD",
    "sg:tags":[
        "farm",
        "soybean"
    ],
    "wof:name":"Lloyd Wright",
    "wof:placetype":"venue"
},
  "geometry": {"coordinates":[-76.99433500000001,39.042996],"type":"Point"}
}