{
  "type": "Feature",
  "properties": {
    "iso:country":"US",
    "sg:address":"109 Park Towne Dr",
    "sg:city":"Elkton",
    "sg:classifiers":[
        {
            "category":"Wholesale",
            "subcategory":"Vending Machines",
            "type":"Manufacturing & Wholesale Goods"
        }
    ],
    "sg:phone":"+1 410 398 8297",
    "sg:postcode":"21921",
    "sg:province":"MD",
    "wof:name":"J & R Vending",
    "wof:placetype":"venue"
},
  "geometry": {"coordinates":[-75.80971,39.604582],"type":"Point"}
}