{
  "type": "Feature",
  "properties": {
    "addr:full":"12503 Augustine Herman Hwy Kennedyville MD 21645",
    "addr:housenumber":"12503",
    "addr:postcode":"21645",
    "addr:street":"Augustine Herman Hwy",
    "iso:country":"US",
    "sg:address":"12503 Augustine Herman Hwy",
    "sg:city":"Kennedyville",
    "sg:classifiers":[
        {
            "category":"Food & Beverages",
            "subcategory":"Groceries & Convenience Stores",
            "type":"Retail Goods"
        }
    ],
    "sg:phone":"+1 410 778 5300",
    "sg:postcode":"21645",
    "sg:province":"MD",
    "sg:tags":[
        "grocer"
    ],
    "wof:name":"Stoltzfus Country Store",
    "wof:placetype":"venue"
},
  "geometry": {"coordinates":[-75.965951,39.322624],"type":"Point"}
}