{
  "type": "Feature",
  "properties": {
    "iso:country":"US",
    "sg:address":"253 N 3rd St",
    "sg:city":"Oakland",
    "sg:classifiers":[
        {
            "category":"Real Estate",
            "subcategory":"Real Estate Agent",
            "type":"Services"
        }
    ],
    "sg:phone":"+1 301 334 1500",
    "sg:postcode":"21550",
    "sg:province":"MD",
    "wof:name":"Railey Realty",
    "wof:placetype":"venue"
},
  "geometry": {"coordinates":[-79.403174,39.414625],"type":"Point"}
}