{
  "type": "Feature",
  "properties": {
    "addr:full":"534 Hampton Ln Baltimore MD 21286",
    "addr:housenumber":"534",
    "addr:postcode":"21286",
    "addr:street":"Hampton Ln",
    "iso:country":"US",
    "sg:address":"534 Hampton Ln",
    "sg:city":"Baltimore",
    "sg:classifiers":[
        {
            "category":"Professional",
            "subcategory":"Business Services",
            "type":"Services"
        }
    ],
    "sg:phone":"+1 410 321 1335",
    "sg:postcode":"21286",
    "sg:province":"MD",
    "wof:name":"Ambridge Interiors",
    "wof:placetype":"venue"
},
  "geometry": {"coordinates":[-76.59057,39.417953],"type":"Point"}
}