{
  "type": "Feature",
  "properties": {
    "addr:full":"7050 Old Waterloo Rd Elkridge MD 21075",
    "addr:housenumber":"7050",
    "addr:postcode":"21075",
    "addr:street":"Old Waterloo Rd",
    "iso:country":"US",
    "sg:address":"7050 Old Waterloo Rd",
    "sg:city":"Elkridge",
    "sg:classifiers":[
        {
            "category":"Freight",
            "type":"Transportation"
        }
    ],
    "sg:phone":"+1 877 258 8230",
    "sg:postcode":"21075",
    "sg:province":"MD",
    "sg:tags":[
        "commercial",
        "household",
        "storage"
    ],
    "sg:website":"http://www.publicstorage.com/?pid=ypcomCPCingenio",
    "wof:name":"Public Storage",
    "wof:placetype":"venue"
},
  "geometry": {"coordinates":[-76.785623,39.176937],"type":"Point"}
}