{
  "type": "Feature",
  "properties": {
    "iso:country":"US",
    "sg:address":"6053 Falls Rd",
    "sg:city":"Baltimore",
    "sg:classifiers":[
        {
            "category":"Insurance",
            "subcategory":"Insurance Agent",
            "type":"Services"
        }
    ],
    "sg:phone":"+1 410 372 0888",
    "sg:postcode":"21209",
    "sg:province":"MD",
    "wof:name":"State Farm Insurance",
    "wof:placetype":"venue"
},
  "geometry": {"coordinates":[-76.650384,39.374351],"type":"Point"}
}