{
  "type": "Feature",
  "properties": {
    "iso:country":"US",
    "sg:address":"3313 Hampton Point Dr",
    "sg:city":"Silver Spring",
    "sg:classifiers":[
        {
            "category":"Building & Trades",
            "subcategory":"Construction",
            "type":"Services"
        }
    ],
    "sg:phone":"+1 301 779 9078",
    "sg:postcode":"20904",
    "sg:province":"MD",
    "sg:tags":[
        "painting",
        "contractor"
    ],
    "wof:name":"Goodman Painting",
    "wof:placetype":"venue"
},
  "geometry": {"coordinates":[-76.941005,39.078103],"type":"Point"}
}