{
  "type": "Feature",
  "properties": {
    "addr:full":"309 N Charles St Baltimore MD 21201",
    "addr:housenumber":"309",
    "addr:postcode":"21201",
    "addr:street":"N Charles St",
    "iso:country":"US",
    "sg:address":"309 N Charles St",
    "sg:city":"Baltimore",
    "sg:classifiers":[
        {
            "category":"Professional",
            "subcategory":"Computer Services",
            "type":"Services"
        }
    ],
    "sg:phone":"+1 410 369 2404",
    "sg:postcode":"21201",
    "sg:province":"MD",
    "sg:tags":[
        "internet"
    ],
    "wof:name":"Technical Support",
    "wof:placetype":"venue"
},
  "geometry": {"coordinates":[-76.615376,39.293196],"type":"Point"}
}