{
  "type": "Feature",
  "properties": {
    "addr:full":"513 Liberty St Hagerstown MD 21740",
    "addr:housenumber":"513",
    "addr:postcode":"21740",
    "addr:street":"Liberty St",
    "iso:country":"US",
    "sg:address":"513 Liberty St",
    "sg:city":"Hagerstown",
    "sg:classifiers":[
        {
            "category":"Education",
            "subcategory":"Junior College",
            "type":"Public Place"
        },
        {
            "category":"Shopping",
            "subcategory":"Gifts & Souvenirs",
            "type":"Retail Goods"
        },
        {
            "category":"Shopping",
            "subcategory":"Hobbies, Toys, & Games",
            "type":"Retail Goods"
        }
    ],
    "sg:phone":"+1 301 739 0301",
    "sg:postcode":"21740",
    "sg:province":"MD",
    "sg:tags":[
        "shop",
        "house",
        "accessory",
        "doll"
    ],
    "wof:name":"Toys & Treasures",
    "wof:placetype":"venue"
},
  "geometry": {"coordinates":[-77.708603,39.640988],"type":"Point"}
}