{
  "type": "Feature",
  "properties": {
    "addr:full":"2083 West St Annapolis MD 21401",
    "addr:housenumber":"2083",
    "addr:postcode":"21401",
    "addr:street":"West St",
    "iso:country":"US",
    "sg:address":"2083 West St",
    "sg:city":"Annapolis",
    "sg:classifiers":[
        {
            "category":"Education",
            "subcategory":"Special Training",
            "type":"Public Place"
        }
    ],
    "sg:phone":"+1 410 266 8192",
    "sg:postcode":"21401",
    "sg:province":"MD",
    "sg:tags":[
        "instruction",
        "driving"
    ],
    "wof:name":"Alfredo's Driving School",
    "wof:placetype":"venue"
},
  "geometry": {"coordinates":[-76.538382,38.983538],"type":"Point"}
}