{
  "type": "Feature",
  "properties": {
    "addr:full":"183 Mayo Rd Edgewater MD 21037",
    "addr:housenumber":"183",
    "addr:postcode":"21037",
    "addr:street":"Mayo Rd",
    "iso:country":"US",
    "sg:address":"183 Mayo Rd",
    "sg:city":"Edgewater",
    "sg:classifiers":[
        {
            "category":"Retail",
            "subcategory":"Self-service Laundry",
            "type":"Services"
        }
    ],
    "sg:phone":"+1 410 956 4546",
    "sg:postcode":"21037",
    "sg:province":"MD",
    "sg:tags":[
        "coin"
    ],
    "wof:name":"Sweetish Laundromat",
    "wof:placetype":"venue"
},
  "geometry": {"coordinates":[-76.556496,38.930671],"type":"Point"}
}