{
  "type": "Feature",
  "properties": {
    "iso:country":"US",
    "sg:address":"11170 Mall Cir",
    "sg:city":"Waldorf",
    "sg:classifiers":[
        {
            "category":"Shopping",
            "subcategory":"Department Store",
            "type":"Retail Goods"
        }
    ],
    "sg:phone":"+1 301 870 6300",
    "sg:postcode":"20603",
    "sg:province":"MD",
    "wof:name":"Sears Roebuck & Co",
    "wof:placetype":"venue"
},
  "geometry": {"coordinates":[-76.916984,38.620581],"type":"Point"}
}