{
  "type": "Feature",
  "properties": {
    "iso:country":"US",
    "sg:address":"2433 Shirley Ave",
    "sg:city":"Baltimore",
    "sg:classifiers":[
        {
            "category":"Professional",
            "subcategory":"Business Services",
            "type":"Services"
        }
    ],
    "sg:phone":"+1 443 621 6121",
    "sg:postcode":"21215",
    "sg:province":"MD",
    "sg:tags":[
        "support"
    ],
    "wof:name":"s and b Solutions",
    "wof:placetype":"venue"
},
  "geometry": {"coordinates":[-76.658078,39.336038],"type":"Point"}
}