{
  "type": "Feature",
  "properties": {
    "addr:full":"9 Bratton Rd Elkton MD 21921",
    "addr:housenumber":"9",
    "addr:postcode":"21921",
    "addr:street":"Bratton Rd",
    "iso:country":"US",
    "sg:address":"9 Bratton Rd",
    "sg:city":"Elkton",
    "sg:classifiers":[
        {
            "category":"Organizations",
            "subcategory":"Religious Organization",
            "type":"Services"
        }
    ],
    "sg:phone":"+1 410 398 4498",
    "sg:postcode":"21921",
    "sg:province":"MD",
    "sg:tags":[
        "clergy"
    ],
    "wof:name":"Garney U Trivett",
    "wof:placetype":"venue"
},
  "geometry": {"coordinates":[-75.84087,39.608975],"type":"Point"}
}