{
  "type": "Feature",
  "properties": {
    "iso:country":"US",
    "sg:address":"4844 Bonnie Branch Rd",
    "sg:city":"Ellicott City",
    "sg:classifiers":[
        {
            "category":"Professional",
            "subcategory":"Computer Services",
            "type":"Services"
        }
    ],
    "sg:phone":"+1 410 788 1660",
    "sg:postcode":"21043",
    "sg:province":"MD",
    "sg:tags":[
        "technical",
        "solution"
    ],
    "wof:name":"Rwb Technical Solutions LLC",
    "wof:placetype":"venue"
},
  "geometry": {"coordinates":[-76.78224899999999,39.23469],"type":"Point"}
}