{
  "type": "Feature",
  "properties": {
    "addr:full":"801 N Salisbury Blvd Salisbury MD 21801",
    "addr:housenumber":"801",
    "addr:postcode":"21801",
    "addr:street":"N Salisbury Blvd",
    "iso:country":"US",
    "sg:address":"801 N Salisbury Blvd",
    "sg:city":"Salisbury",
    "sg:classifiers":[
        {
            "category":"Manufacturing",
            "subcategory":"Building Materials",
            "type":"Manufacturing & Wholesale Goods"
        }
    ],
    "sg:phone":"+1 410 749 7731",
    "sg:postcode":"21801",
    "sg:province":"MD",
    "wof:name":"E S Adkins & Co",
    "wof:placetype":"venue"
},
  "geometry": {"coordinates":[-75.593242,38.373252],"type":"Point"}
}