{
  "type": "Feature",
  "properties": {
    "addr:full":"11810 Pika Dr Waldorf MD 20602",
    "addr:postcode":"11810;20602",
    "addr:street":"Pika Dr",
    "iso:country":"US",
    "sg:address":"11810 Pika Dr",
    "sg:city":"Waldorf",
    "sg:classifiers":[
        {
            "category":"Recreation",
            "type":"Entertainment"
        }
    ],
    "sg:phone":"+1 301 705 7002",
    "sg:postcode":"20602",
    "sg:province":"MD",
    "sg:tags":[
        "karate",
        "judo",
        "instr"
    ],
    "wof:name":"Universal Martial Studies",
    "wof:placetype":"venue"
},
  "geometry": {"coordinates":[-76.905569,38.622807],"type":"Point"}
}