{
  "type": "Feature",
  "properties": {
    "addr:full":"7026 Friendship Rd Baltimore MD 21240",
    "addr:housenumber":"7026",
    "addr:postcode":"21240",
    "addr:street":"Friendship Rd",
    "iso:country":"US",
    "sg:address":"7026 Friendship Rd",
    "sg:city":"Baltimore",
    "sg:classifiers":[
        {
            "category":"Shopping",
            "subcategory":"Clothing, Apparel, & Fashions",
            "type":"Retail Goods"
        },
        {
            "category":"Manufacturing",
            "subcategory":"Leather Goods",
            "type":"Manufacturing & Wholesale Goods"
        },
        {
            "category":"Shopping",
            "subcategory":"Shoes",
            "type":"Retail Goods"
        }
    ],
    "sg:phone":"+1 410 684 6892",
    "sg:postcode":"21240",
    "sg:province":"MD",
    "sg:tags":[
        "men's",
        "clothing",
        "store"
    ],
    "sg:website":"http://www.johnstonmurphy.com",
    "wof:name":"Johnston & Murphy",
    "wof:placetype":"venue"
},
  "geometry": {"coordinates":[-76.674578,39.184132],"type":"Point"}
}