{
  "type": "Feature",
  "properties": {
    "addr:full":"823 Eastern Blvd Essex MD 21221",
    "addr:housenumber":"823",
    "addr:postcode":"21221",
    "addr:street":"Eastern Blvd",
    "iso:country":"US",
    "sg:address":"823 Eastern Blvd",
    "sg:city":"Essex",
    "sg:classifiers":[
        {
            "category":"Insurance",
            "subcategory":"Insurance Agent",
            "type":"Services"
        }
    ],
    "sg:phone":"+1 410 686 5400",
    "sg:postcode":"21221",
    "sg:province":"MD",
    "wof:name":"Erik L Anderson Insurance",
    "wof:placetype":"venue"
},
  "geometry": {"coordinates":[-76.466734,39.311933],"type":"Point"}
}