{
  "type": "Feature",
  "properties": {
    "addr:full":"3675 Park Ave Ellicott City MD 21043",
    "addr:housenumber":"3675",
    "addr:postcode":"21043",
    "addr:street":"Park Ave",
    "iso:country":"US",
    "sg:address":"3675 Park Ave",
    "sg:city":"Ellicott City",
    "sg:classifiers":[
        {
            "category":"Building & Trades",
            "subcategory":"Construction",
            "type":"Services"
        }
    ],
    "sg:phone":"+1 410 480 0023",
    "sg:postcode":"21043",
    "sg:province":"MD",
    "sg:tags":[
        "contractor"
    ],
    "wof:name":"Trinity Homes Main Office",
    "wof:placetype":"venue"
},
  "geometry": {"coordinates":[-76.797798,39.268902],"type":"Point"}
}