{
  "type": "Feature",
  "properties": {
    "addr:full":"8 Aquahart Rd Glen Burnie MD 21061",
    "addr:housenumber":"8",
    "addr:postcode":"21061",
    "addr:street":"Aquahart Rd",
    "iso:country":"US",
    "sg:address":"8 Aquahart Rd",
    "sg:city":"Glen Burnie",
    "sg:classifiers":[
        {
            "category":"Wholesale",
            "subcategory":"Electrical",
            "type":"Manufacturing & Wholesale Goods"
        }
    ],
    "sg:phone":"+1 410 760 0006",
    "sg:postcode":"21061",
    "sg:province":"MD",
    "sg:tags":[
        "control",
        "security",
        "system"
    ],
    "wof:name":"Door Access Controls",
    "wof:placetype":"venue"
},
  "geometry": {"coordinates":[-76.62889699999999,39.152057],"type":"Point"}
}