{
  "type": "Feature",
  "properties": {
    "iso:country":"US",
    "sg:address":"7941 Starburst Dr",
    "sg:city":"Pikesville",
    "sg:classifiers":[
        {
            "category":"Manufacturing",
            "subcategory":"Textiles",
            "type":"Manufacturing & Wholesale Goods"
        },
        {
            "category":"Wholesale",
            "subcategory":"Apparel",
            "type":"Manufacturing & Wholesale Goods"
        }
    ],
    "sg:phone":"+1 410 653 5858",
    "sg:postcode":"21208",
    "sg:province":"MD",
    "sg:tags":[
        "manufacturer",
        "shirts-wholesale",
        "t-shirts-wholesale"
    ],
    "wof:name":"Oriole Uniform",
    "wof:placetype":"venue"
},
  "geometry": {"coordinates":[-76.718433,39.389111],"type":"Point"}
}