{
  "type": "Feature",
  "properties": {
    "iso:country":"US",
    "sg:address":"7224 Carroll Ave",
    "sg:city":"Takoma Park",
    "sg:classifiers":[
        {
            "category":"Autos & Motor Vehicles",
            "subcategory":"Fuel & Gas Station",
            "type":"Retail Goods"
        }
    ],
    "sg:phone":"+1 301 270 1747",
    "sg:postcode":"20912",
    "sg:province":"MD",
    "sg:tags":[
        "oil"
    ],
    "wof:name":"Takoma Junction Citgo",
    "wof:placetype":"venue"
},
  "geometry": {"coordinates":[-77.00847400000001,38.976561],"type":"Point"}
}