{
  "type": "Feature",
  "properties": {
    "iso:country":"US",
    "sg:address":"9005 Red Branch Rd",
    "sg:city":"Columbia",
    "sg:classifiers":[
        {
            "category":"Organizations",
            "subcategory":"Professional Association",
            "type":"Services"
        }
    ],
    "sg:phone":"+1 410 964 1246",
    "sg:postcode":"21045",
    "sg:province":"MD",
    "wof:name":"Columbia Triathlon Assn",
    "wof:placetype":"venue"
},
  "geometry": {"coordinates":[-76.819855,39.227166],"type":"Point"}
}