{
  "type": "Feature",
  "properties": {
    "iso:country":"US",
    "sg:address":"1433 Bolton St",
    "sg:city":"Baltimore",
    "sg:classifiers":[
        {
            "category":"Insurance",
            "subcategory":"Hazard Insurance",
            "type":"Services"
        }
    ],
    "sg:phone":"+1 410 669 6636",
    "sg:postcode":"21217",
    "sg:province":"MD",
    "wof:name":"H Leimbachs Clu",
    "wof:placetype":"venue"
},
  "geometry": {"coordinates":[-76.625342,39.306399],"type":"Point"}
}