{
  "type": "Feature",
  "properties": {
    "iso:country":"US",
    "sg:address":"23 E North Ave",
    "sg:city":"Baltimore",
    "sg:classifiers":[
        {
            "category":"Shopping",
            "subcategory":"Books",
            "type":"Retail Goods"
        }
    ],
    "sg:phone":"+1 410 528 7777",
    "sg:postcode":"21202",
    "sg:province":"MD",
    "sg:tags":[
        "dealer"
    ],
    "wof:name":"S & S Casey Booksellers",
    "wof:placetype":"venue"
},
  "geometry": {"coordinates":[-76.614971,39.31112],"type":"Point"}
}