{
  "type": "Feature",
  "properties": {
    "addr:full":"7856 Foxfarm Ln Glen Burnie MD 21061",
    "addr:housenumber":"7856",
    "addr:postcode":"21061",
    "addr:street":"Foxfarm Ln",
    "iso:country":"US",
    "sg:address":"7856 Foxfarm Ln",
    "sg:city":"Glen Burnie",
    "sg:classifiers":[
        {
            "category":"Travel",
            "subcategory":"Travel Agent",
            "type":"Entertainment"
        }
    ],
    "sg:phone":"+1 410 798 0755",
    "sg:postcode":"21061",
    "sg:province":"MD",
    "sg:tags":[
        "agency",
        "bureau"
    ],
    "sg:website":"www.bobduckworth.com",
    "wof:name":"Travel Excursions",
    "wof:placetype":"venue"
},
  "geometry": {"coordinates":[-76.609218,39.135028],"type":"Point"}
}