{
  "type": "Feature",
  "properties": {
    "addr:full":"18 Partridge Ct La Plata MD 20646",
    "addr:housenumber":"18",
    "addr:postcode":"20646",
    "addr:street":"Partridge Ct",
    "iso:country":"US",
    "sg:address":"18 Partridge Ct",
    "sg:city":"La Plata",
    "sg:classifiers":[
        {
            "category":"Shopping",
            "subcategory":"Used Merchandise",
            "type":"Retail Goods"
        }
    ],
    "sg:phone":"+1 301 934 4212",
    "sg:postcode":"20646",
    "sg:province":"MD",
    "wof:name":"Antiques Etc",
    "wof:placetype":"venue"
},
  "geometry": {"coordinates":[-76.99197100000001,38.530207],"type":"Point"}
}