{
  "type": "Feature",
  "properties": {
    "addr:full":"1705 York Rd Lutherville MD 21093",
    "addr:housenumber":"1705",
    "addr:postcode":"21093",
    "addr:street":"York Rd",
    "iso:country":"US",
    "sg:address":"1705 York Rd",
    "sg:city":"Lutherville",
    "sg:classifiers":[
        {
            "category":"Retail",
            "subcategory":"Auto Repair",
            "type":"Services"
        }
    ],
    "sg:phone":"+1 410 828 9295",
    "sg:postcode":"21093",
    "sg:province":"MD",
    "sg:tags":[
        "repairing",
        "automobile"
    ],
    "sg:website":"www.ntb.com",
    "wof:name":"NTB",
    "wof:placetype":"venue"
},
  "geometry": {"coordinates":[-76.619501,39.426009],"type":"Point"}
}