{
  "type": "Feature",
  "properties": {
    "iso:country":"US",
    "sg:address":"13455 New Hampshire Ave",
    "sg:city":"Silver Spring",
    "sg:classifiers":[
        {
            "category":"Autos & Motor Vehicles",
            "subcategory":"Fuel & Gas Station",
            "type":"Retail Goods"
        }
    ],
    "sg:phone":"+1 301 989 1395",
    "sg:postcode":"20904",
    "sg:province":"MD",
    "wof:name":"Petroleum Holdings Inc",
    "wof:placetype":"venue"
},
  "geometry": {"coordinates":[-77.00160200000001,39.077301],"type":"Point"}
}