{
  "type": "Feature",
  "properties": {
    "addr:full":"1671 Monument Rd Middletown MD 21769",
    "addr:housenumber":"1671",
    "addr:postcode":"21769",
    "addr:street":"Monument Rd",
    "iso:country":"US",
    "sg:address":"1671 Monument Rd",
    "sg:city":"Middletown",
    "sg:classifiers":[
        {
            "category":"Education",
            "subcategory":"Dance Studio",
            "type":"Public Place"
        }
    ],
    "sg:phone":"+1 301 293 2821",
    "sg:postcode":"21769",
    "sg:province":"MD",
    "sg:tags":[
        "instruction",
        "dancing"
    ],
    "wof:name":"Dona Huffer School-Dance",
    "wof:placetype":"venue"
},
  "geometry": {"coordinates":[-77.614678,39.500639],"type":"Point"}
}