{
  "type": "Feature",
  "properties": {
    "addr:full":"6905 Rockledge Dr Bethesda MD 20817",
    "addr:housenumber":"6905",
    "addr:postcode":"20817",
    "addr:street":"Rockledge Dr",
    "iso:country":"US",
    "sg:address":"6905 Rockledge Dr",
    "sg:city":"Bethesda",
    "sg:classifiers":[
        {
            "category":"Professional",
            "subcategory":"Management & Consulting",
            "type":"Services"
        }
    ],
    "sg:phone":"+1 301 896 9715",
    "sg:postcode":"20817",
    "sg:province":"MD",
    "sg:tags":[
        "consultant",
        "business"
    ],
    "wof:name":"Audacy Consulting",
    "wof:placetype":"venue"
},
  "geometry": {"coordinates":[-77.134536,39.029972],"type":"Point"}
}