{
  "type": "Feature",
  "properties": {
    "iso:country":"US",
    "sg:address":"11 N Central Ave",
    "sg:city":"Ridgely",
    "sg:classifiers":[
        {
            "category":"Food & Beverages",
            "subcategory":"Groceries & Convenience Stores",
            "type":"Retail Goods"
        }
    ],
    "sg:phone":"+1 410 634 2366",
    "sg:postcode":"21660",
    "sg:province":"MD",
    "sg:tags":[
        "grocer"
    ],
    "wof:name":"Tri-Me Warehouse Foods",
    "wof:placetype":"venue"
},
  "geometry": {"coordinates":[-75.884276,38.947351],"type":"Point"}
}