{
  "type": "Feature",
  "properties": {
    "iso:country":"US",
    "sg:address":"12629 Manor Rd",
    "sg:city":"Glen Arm",
    "sg:classifiers":[
        {
            "category":"Professional",
            "type":"Services"
        }
    ],
    "sg:phone":"+1 410 592 3828",
    "sg:postcode":"21057",
    "sg:province":"MD",
    "sg:tags":[
        "establishment"
    ],
    "wof:name":"Mailer's Edge",
    "wof:placetype":"venue"
},
  "geometry": {"coordinates":[-76.524427,39.470164],"type":"Point"}
}