{
  "type": "Feature",
  "properties": {
    "iso:country":"US",
    "sg:address":"130 E Main St",
    "sg:city":"Rising Sun",
    "sg:classifiers":[
        {
            "category":"Real Estate",
            "subcategory":"Real Estate Agent",
            "type":"Services"
        }
    ],
    "sg:phone":"+1 410 658 7444",
    "sg:postcode":"21911",
    "sg:province":"MD",
    "wof:name":"Fisher Realty LTD Inc",
    "wof:placetype":"venue"
},
  "geometry": {"coordinates":[-76.057895,39.698166],"type":"Point"}
}