{
  "type": "Feature",
  "properties": {
    "addr:full":"1404 Stockton Rd Joppa MD 21085",
    "addr:housenumber":"1404",
    "addr:postcode":"21085",
    "addr:street":"Stockton Rd",
    "iso:country":"US",
    "sg:address":"1404 Stockton Rd",
    "sg:city":"Joppa",
    "sg:classifiers":[
        {
            "category":"Retail",
            "subcategory":"Repair Shop",
            "type":"Services"
        }
    ],
    "sg:phone":"+1 410 679 8495",
    "sg:postcode":"21085",
    "sg:province":"MD",
    "sg:tags":[
        "refrigerating"
    ],
    "wof:name":"Joppa Commercial Refrigeration",
    "wof:placetype":"venue"
},
  "geometry": {"coordinates":[-76.351029,39.478596],"type":"Point"}
}