{
  "type": "Feature",
  "properties": {
    "iso:country":"US",
    "sg:address":"5516 Berm Rd",
    "sg:city":"Hancock",
    "sg:classifiers":[
        {
            "category":"Professional",
            "type":"Services"
        }
    ],
    "sg:phone":"+1 301 678 7599",
    "sg:postcode":"21750",
    "sg:province":"MD",
    "sg:tags":[
        "establishment"
    ],
    "wof:name":"Supreme Council-House Of Jacob",
    "wof:placetype":"venue"
},
  "geometry": {"coordinates":[-78.183135,39.69807],"type":"Point"}
}