{
  "type": "Feature",
  "properties": {
    "iso:country":"US",
    "sg:address":"10440 Little Patuxent Pkwy",
    "sg:city":"Columbia",
    "sg:classifiers":[
        {
            "category":"Professional",
            "subcategory":"Lawyer & Legal Services",
            "type":"Services"
        }
    ],
    "sg:phone":"+1 301 953 1985",
    "sg:postcode":"21044",
    "sg:province":"MD",
    "sg:tags":[
        "attorney"
    ],
    "wof:name":"Stacy R Berger",
    "wof:placetype":"venue"
},
  "geometry": {"coordinates":[-76.86014400000001,39.211682],"type":"Point"}
}