{
  "type": "Feature",
  "properties": {
    "addr:full":"7238 Wapello Dr Derwood MD 20855",
    "addr:housenumber":"7238",
    "addr:postcode":"20855",
    "addr:street":"Wapello Dr",
    "iso:country":"US",
    "sg:address":"7238 Wapello Dr",
    "sg:city":"Derwood",
    "sg:classifiers":[
        {
            "category":"Professional",
            "subcategory":"Engineering",
            "type":"Services"
        }
    ],
    "sg:phone":"+1 301 340 9096",
    "sg:postcode":"20855",
    "sg:province":"MD",
    "sg:tags":[
        "consulting",
        "engineer"
    ],
    "wof:name":"Keene Ideas Inc",
    "wof:placetype":"venue"
},
  "geometry": {"coordinates":[-77.146074,39.111632],"type":"Point"}
}