{
  "type": "Feature",
  "properties": {
    "addr:full":"2900 Hanover Pike Manchester MD 21102",
    "addr:housenumber":"2900",
    "addr:postcode":"21102",
    "addr:street":"Hanover Pike",
    "iso:country":"US",
    "sg:address":"2900 Hanover Pike",
    "sg:city":"Manchester",
    "sg:classifiers":[
        {
            "category":"Retail",
            "subcategory":"Auto Repair",
            "type":"Services"
        }
    ],
    "sg:phone":"+1 410 239 3444",
    "sg:postcode":"21102",
    "sg:province":"MD",
    "sg:tags":[
        "repairing",
        "automobile"
    ],
    "wof:name":"Caltrider's Garage",
    "wof:placetype":"venue"
},
  "geometry": {"coordinates":[-76.88240399999999,39.656893],"type":"Point"}
}