{
  "type": "Feature",
  "properties": {
    "addr:full":"825 Dulaney Valley Rd Towson MD 21204",
    "addr:housenumber":"825",
    "addr:postcode":"21204",
    "addr:street":"Dulaney Valley Rd",
    "iso:country":"US",
    "sg:address":"825 Dulaney Valley Rd",
    "sg:city":"Towson",
    "sg:classifiers":[
        {
            "category":"Shopping",
            "subcategory":"Clothing, Apparel, & Fashions",
            "type":"Retail Goods"
        }
    ],
    "sg:phone":"+1 410 321 8012",
    "sg:postcode":"21204",
    "sg:province":"MD",
    "sg:tags":[
        "sportswear"
    ],
    "wof:name":"Pacific Sunwear",
    "wof:placetype":"venue"
},
  "geometry": {"coordinates":[-76.60154199999999,39.403782],"type":"Point"}
}