{
  "type": "Feature",
  "properties": {
    "addr:full":"6901 Security Blvd Windsor Mill MD 21244",
    "addr:housenumber":"6901",
    "addr:postcode":"21244",
    "addr:street":"Security Blvd",
    "iso:country":"US",
    "sg:address":"6901 Security Blvd",
    "sg:city":"Windsor Mill",
    "sg:classifiers":[
        {
            "category":"Restaurant",
            "type":"Food & Drink"
        }
    ],
    "sg:phone":"+1 410 265 0191",
    "sg:postcode":"21244",
    "sg:province":"MD",
    "wof:name":"Sj Security Square Food Dba Sarka Japan",
    "wof:placetype":"venue"
},
  "geometry": {"coordinates":[-76.74870300000001,39.312801],"type":"Point"}
}