{
  "type": "Feature",
  "properties": {
    "iso:country":"US",
    "sg:address":"5434 Harford Rd",
    "sg:city":"Baltimore",
    "sg:classifiers":[
        {
            "category":"Shopping",
            "subcategory":"Jewelry",
            "type":"Retail Goods"
        }
    ],
    "sg:phone":"+1 410 426 8696",
    "sg:postcode":"21214",
    "sg:province":"MD",
    "sg:tags":[
        "jeweler"
    ],
    "wof:name":"S & N KATZ",
    "wof:placetype":"venue"
},
  "geometry": {"coordinates":[-76.56235599999999,39.351304],"type":"Point"}
}