{
  "type": "Feature",
  "properties": {
    "iso:country":"US",
    "sg:address":"6450 Dobbin Rd Ste G",
    "sg:city":"Columbia",
    "sg:classifiers":[
        {
            "category":"Food & Beverages",
            "subcategory":"Liquor & Beverages",
            "type":"Retail Goods"
        }
    ],
    "sg:phone":"+1 410 884 9463",
    "sg:postcode":"21045",
    "sg:province":"MD",
    "sg:tags":[
        "beer",
        "spirit",
        "wine"
    ],
    "wof:name":"A V Classic Imports",
    "wof:placetype":"venue"
},
  "geometry": {"coordinates":[-76.820801,39.194901],"type":"Point"}
}