{
  "type": "Feature",
  "properties": {
    "iso:country":"US",
    "sg:address":"2929 Pennsy Dr",
    "sg:city":"Landover",
    "sg:classifiers":[
        {
            "category":"Retail",
            "subcategory":"Storage",
            "type":"Services"
        }
    ],
    "sg:phone":"+1 866 838 2192",
    "sg:postcode":"20785",
    "sg:province":"MD",
    "sg:tags":[
        "self"
    ],
    "sg:website":"www.unclebobs.com/",
    "wof:name":"Uncle Bob's Self Storage",
    "wof:placetype":"venue"
},
  "geometry": {"coordinates":[-76.891627,38.928064],"type":"Point"}
}