{
  "type": "Feature",
  "properties": {
    "addr:full":"1822 Webster St Baltimore MD 21230",
    "addr:housenumber":"1822",
    "addr:postcode":"21230",
    "addr:street":"Webster St",
    "iso:country":"US",
    "sg:address":"1822 Webster St",
    "sg:city":"Baltimore",
    "sg:classifiers":[
        {
            "category":"Banks & Credit Unions",
            "subcategory":"Financial Services",
            "type":"Services"
        }
    ],
    "sg:phone":"+1 410 528 9100",
    "sg:postcode":"21230",
    "sg:province":"MD",
    "sg:website":"http://www.modern-wealth.com",
    "wof:name":"Modern Wealth",
    "wof:placetype":"venue"
},
  "geometry": {"coordinates":[-76.604164,39.26963],"type":"Point"}
}