{
  "type": "Feature",
  "properties": {
    "addr:full":"517 E Main St Emmitsburg MD 21727",
    "addr:housenumber":"517",
    "addr:postcode":"21727",
    "addr:street":"E Main St",
    "iso:country":"US",
    "sg:address":"517 E Main St",
    "sg:city":"Emmitsburg",
    "sg:classifiers":[
        {
            "category":"Restaurant",
            "type":"Food & Drink"
        }
    ],
    "sg:menulink":"http://www.allmenus.com/md/emmitsburg/215613-mcdonalds/menu/",
    "sg:postcode":"21727",
    "sg:province":"MD",
    "sg:tags":[
        "burger",
        "american"
    ],
    "wof:name":"McDonald's",
    "wof:placetype":"venue"
},
  "geometry": {"coordinates":[-77.31698400000001,39.703119],"type":"Point"}
}