{
  "type": "Feature",
  "properties": {
    "addr:full":"4419 Muncaster Mill Rd Rockville MD 20853",
    "addr:housenumber":"4419",
    "addr:postcode":"20853",
    "addr:street":"Muncaster Mill Rd",
    "iso:country":"US",
    "sg:address":"4419 Muncaster Mill Rd",
    "sg:city":"Rockville",
    "sg:classifiers":[
        {
            "category":"Social Services",
            "subcategory":"Child Care",
            "type":"Services"
        }
    ],
    "sg:phone":"+1 301 924 0063",
    "sg:postcode":"20853",
    "sg:province":"MD",
    "wof:name":"Pathway Child Dev Ctr Inc",
    "wof:placetype":"venue"
},
  "geometry": {"coordinates":[-77.092491,39.113757],"type":"Point"}
}