{
  "type": "Feature",
  "properties": {
    "addr:full":"1952 Pulaski Hwy Edgewood MD 21040",
    "addr:housenumber":"1952",
    "addr:postcode":"21040",
    "addr:street":"Pulaski Hwy",
    "iso:country":"US",
    "sg:address":"1952 Pulaski Hwy",
    "sg:city":"Edgewood",
    "sg:classifiers":[
        {
            "category":"Health Services",
            "subcategory":"Doctor",
            "type":"Services"
        }
    ],
    "sg:phone":"+1 410 676 8108",
    "sg:postcode":"21040",
    "sg:province":"MD",
    "wof:name":"Ritu Bhambhani MD",
    "wof:placetype":"venue"
},
  "geometry": {"coordinates":[-76.313564,39.435655],"type":"Point"}
}