{
  "type": "Feature",
  "properties": {
    "iso:country":"US",
    "sg:address":"1818 York Rd",
    "sg:city":"Lutherville Timonium",
    "sg:classifiers":[
        {
            "category":"Restaurant",
            "type":"Food & Drink"
        }
    ],
    "sg:menulink":"http://www.allmenus.com/md/hunt-valley/70183-bertuccis/menu/",
    "sg:phone":"+1 410 561 7000",
    "sg:postcode":"21093",
    "sg:province":"MD",
    "sg:tags":[
        "american",
        "italian",
        "pizza"
    ],
    "wof:name":"Bertucci's",
    "wof:placetype":"venue"
},
  "geometry": {"coordinates":[-76.621708,39.430809],"type":"Point"}
}