{
  "type": "Feature",
  "properties": {
    "addr:full":"216 E Pulaski Hwy Elkton MD 21921",
    "addr:housenumber":"216",
    "addr:postcode":"21921",
    "addr:street":"E Pulaski Hwy",
    "iso:country":"US",
    "sg:address":"216 E Pulaski Hwy",
    "sg:city":"Elkton",
    "sg:classifiers":[
        {
            "category":"Professional",
            "subcategory":"Employment Agencies",
            "type":"Services"
        }
    ],
    "sg:phone":"+1 410 398 6704",
    "sg:postcode":"21921",
    "sg:province":"MD",
    "sg:tags":[
        "opportunity"
    ],
    "wof:name":"Adecco",
    "wof:placetype":"venue"
},
  "geometry": {"coordinates":[-75.824985,39.599051],"type":"Point"}
}