{
  "type": "Feature",
  "properties": {
    "iso:country":"US",
    "sg:address":"920 Damsontown Rd",
    "sg:city":"Queen Anne",
    "sg:classifiers":[
        {
            "category":"Building & Trades",
            "subcategory":"Construction",
            "type":"Services"
        }
    ],
    "sg:phone":"+1 410 364 9896",
    "sg:postcode":"21657",
    "sg:province":"MD",
    "sg:tags":[
        "excavating",
        "contractor"
    ],
    "wof:name":"Earthworks Excavating LLC",
    "wof:placetype":"venue"
},
  "geometry": {"coordinates":[-75.974048,38.969543],"type":"Point"}
}