{
  "type": "Feature",
  "properties": {
    "addr:full":"538 Edgewater Rd Pasadena MD 21122",
    "addr:housenumber":"538",
    "addr:postcode":"21122",
    "addr:street":"Edgewater Rd",
    "iso:country":"US",
    "sg:address":"538 Edgewater Rd",
    "sg:city":"Pasadena",
    "sg:classifiers":[
        {
            "category":"Retail",
            "subcategory":"Repair Shop",
            "type":"Services"
        }
    ],
    "sg:phone":"+1 410 255 5673",
    "sg:postcode":"21122",
    "sg:province":"MD",
    "wof:name":"Shoreline Marine Services Inc",
    "wof:placetype":"venue"
},
  "geometry": {"coordinates":[-76.471289,39.082561],"type":"Point"}
}