{
  "type": "Feature",
  "properties": {
    "iso:country":"US",
    "sg:address":"200 Saint Paul St",
    "sg:city":"Baltimore",
    "sg:classifiers":[
        {
            "category":"Parking",
            "type":"Transportation"
        }
    ],
    "sg:phone":"+1 410 539 2724",
    "sg:postcode":"21202",
    "sg:province":"MD",
    "sg:tags":[
        "garage"
    ],
    "wof:name":"Park-It of Maryland",
    "wof:placetype":"venue"
},
  "geometry": {"coordinates":[-76.613899,39.291199],"type":"Point"}
}