{
  "type": "Feature",
  "properties": {
    "addr:full":"5924 Falkirk Rd Baltimore MD 21239",
    "addr:housenumber":"5924",
    "addr:postcode":"21239",
    "addr:street":"Falkirk Rd",
    "iso:country":"US",
    "sg:address":"5924 Falkirk Rd",
    "sg:city":"Baltimore",
    "sg:classifiers":[
        {
            "category":"Personal",
            "subcategory":"Beauty Salon",
            "type":"Services"
        }
    ],
    "sg:phone":"+1 410 485 8386",
    "sg:postcode":"21239",
    "sg:province":"MD",
    "sg:tags":[
        "shop"
    ],
    "wof:name":"Toni Keene Salon Inc",
    "wof:placetype":"venue"
},
  "geometry": {"coordinates":[-76.588066,39.363848],"type":"Point"}
}