{
  "type": "Feature",
  "properties": {
    "addr:full":"9 Salt Grass Rd Berlin MD 21811",
    "addr:housenumber":"9",
    "addr:postcode":"21811",
    "addr:street":"Salt Grass Rd",
    "iso:country":"US",
    "sg:address":"9 Salt Grass Rd",
    "sg:city":"Berlin",
    "sg:classifiers":[
        {
            "category":"Communications",
            "type":"Services"
        }
    ],
    "sg:phone":"+1 410 208 0330",
    "sg:postcode":"21811",
    "sg:province":"MD",
    "wof:name":"Public Communications Cons",
    "wof:placetype":"venue"
},
  "geometry": {"coordinates":[-75.14653199999999,38.369529],"type":"Point"}
}