{
  "type": "Feature",
  "properties": {
    "iso:country":"US",
    "sg:address":"9632 Kanfer Ct",
    "sg:city":"Montgomery Village",
    "sg:classifiers":[
        {
            "category":"Health Services",
            "subcategory":"Clinic",
            "type":"Services"
        }
    ],
    "sg:phone":"+1 301 258 7673",
    "sg:postcode":"20886",
    "sg:province":"MD",
    "wof:name":"Kirtana Srinivasa Kalavpudi",
    "wof:placetype":"venue"
},
  "geometry": {"coordinates":[-77.198478,39.172606],"type":"Point"}
}