{
  "type": "Feature",
  "properties": {
    "iso:country":"US",
    "sg:address":"6000 Davis Blvd",
    "sg:city":"Suitland",
    "sg:classifiers":[
        {
            "category":"Organizations",
            "subcategory":"Religious Organization",
            "type":"Services"
        }
    ],
    "sg:phone":"+1 301 423 2320",
    "sg:postcode":"20746",
    "sg:province":"MD",
    "sg:tags":[
        "testament",
        "churches-church",
        "christ-new"
    ],
    "sg:website":"http://www.beltwaycoc.org",
    "wof:name":"Beltway Church Of Christ",
    "wof:placetype":"venue"
},
  "geometry": {"coordinates":[-76.902351,38.816368],"type":"Point"}
}