{
  "type": "Feature",
  "properties": {
    "addr:full":"4601 N Park Ave Chevy Chase MD 20815",
    "addr:housenumber":"4601",
    "addr:postcode":"20815",
    "addr:street":"N Park Ave",
    "iso:country":"US",
    "sg:address":"4601 N Park Ave",
    "sg:city":"Chevy Chase",
    "sg:classifiers":[
        {
            "category":"Real Estate",
            "subcategory":"Real Estate Agent",
            "type":"Services"
        }
    ],
    "sg:phone":"+1 301 654 1800",
    "sg:postcode":"20815",
    "sg:province":"MD",
    "wof:name":"Jeff Foster & Assoc Inc",
    "wof:placetype":"venue"
},
  "geometry": {"coordinates":[-77.09099399999999,38.963485],"type":"Point"}
}