{
  "type": "Feature",
  "properties": {
    "iso:country":"US",
    "sg:address":"1704 Lancaster St",
    "sg:city":"Baltimore",
    "sg:classifiers":[
        {
            "category":"Organizations",
            "subcategory":"Religious Organization",
            "type":"Services"
        }
    ],
    "sg:phone":"+1 410 276 6287",
    "sg:postcode":"21231",
    "sg:province":"MD",
    "sg:tags":[
        "clergy"
    ],
    "wof:name":"Trautwein John Rev",
    "wof:placetype":"venue"
},
  "geometry": {"coordinates":[-76.59274499999999,39.282574],"type":"Point"}
}