{
  "type": "Feature",
  "properties": {
    "iso:country":"US",
    "sg:address":"13505 Wisteria Dr",
    "sg:city":"Germantown",
    "sg:classifiers":[
        {
            "category":"Social Services",
            "subcategory":"Child Care",
            "type":"Services"
        }
    ],
    "sg:phone":"+1 301 972 1072",
    "sg:postcode":"20874",
    "sg:province":"MD",
    "wof:name":"Childrens House Of Germantown",
    "wof:placetype":"venue"
},
  "geometry": {"coordinates":[-77.281424,39.181092],"type":"Point"}
}