{
  "type": "Feature",
  "properties": {
    "addr:full":"10600 Bailey Dr Cheltenham MD 20623",
    "addr:housenumber":"10600",
    "addr:postcode":"20623",
    "addr:street":"Bailey Dr",
    "iso:country":"US",
    "sg:address":"10600 Bailey Dr",
    "sg:city":"Cheltenham",
    "sg:classifiers":[
        {
            "category":"Building & Trades",
            "subcategory":"Construction",
            "type":"Services"
        }
    ],
    "sg:phone":"+1 301 372 8255",
    "sg:postcode":"20623",
    "sg:province":"MD",
    "sg:tags":[
        "home",
        "builder"
    ],
    "wof:name":"Cheltenham Woods Home Owners",
    "wof:placetype":"venue"
},
  "geometry": {"coordinates":[-76.82276400000001,38.740913],"type":"Point"}
}