{
  "type": "Feature",
  "properties": {
    "addr:full":"8659 Baltimore Natinl Pke Ellicott City MD 21043",
    "addr:housenumber":"8659",
    "addr:postcode":"21043",
    "addr:street":"Baltimore Natinl Pke",
    "iso:country":"US",
    "sg:address":"8659 Baltimore Natinl Pke",
    "sg:city":"Ellicott City",
    "sg:classifiers":[
        {
            "category":"Health Services",
            "subcategory":"Doctor",
            "type":"Services"
        },
        {
            "category":"Retail",
            "subcategory":"Auto Rental",
            "type":"Services"
        }
    ],
    "sg:phone":"+1 410 750 0200",
    "sg:postcode":"21043",
    "sg:province":"MD",
    "sg:tags":[
        "car"
    ],
    "wof:name":"Reliable Rent-A-Car Inc",
    "wof:placetype":"venue"
},
  "geometry": {"coordinates":[-76.812798,39.2812],"type":"Point"}
}