{
  "type": "Feature",
  "properties": {
    "iso:country":"US",
    "sg:address":"28662 W Ridge Rd",
    "sg:city":"Princess Anne",
    "sg:classifiers":[
        {
            "category":"Professional",
            "subcategory":"Detective & Security Services",
            "type":"Services"
        }
    ],
    "sg:phone":"+1 410 651 4497",
    "sg:postcode":"21853",
    "sg:province":"MD",
    "sg:tags":[
        "investigator"
    ],
    "wof:name":"Robert Lankford Investigations",
    "wof:placetype":"venue"
},
  "geometry": {"coordinates":[-75.754392,38.231659],"type":"Point"}
}