{
  "type": "Feature",
  "properties": {
    "iso:country":"US",
    "sg:address":"2083 West St",
    "sg:city":"Annapolis",
    "sg:classifiers":[
        {
            "category":"Professional",
            "subcategory":"Business Services",
            "type":"Services"
        }
    ],
    "sg:phone":"+1 410 266 2525",
    "sg:postcode":"21401",
    "sg:province":"MD",
    "sg:tags":[
        "holding"
    ],
    "wof:name":"Ghp Holdings",
    "wof:placetype":"venue"
},
  "geometry": {"coordinates":[-76.540047,38.98381],"type":"Point"}
}