{
  "type": "Feature",
  "properties": {
    "addr:full":"11110 Mall Cir Waldorf MD 20603",
    "addr:housenumber":"11110",
    "addr:postcode":"20603",
    "addr:street":"Mall Cir",
    "iso:country":"US",
    "sg:address":"11110 Mall Cir",
    "sg:city":"Waldorf",
    "sg:classifiers":[
        {
            "category":"Shopping",
            "subcategory":"Clothing, Apparel, & Fashions",
            "type":"Retail Goods"
        }
    ],
    "sg:phone":"+1 301 705 9820",
    "sg:postcode":"20603",
    "sg:province":"MD",
    "wof:name":"Size 5-7-9 Shop",
    "wof:placetype":"venue"
},
  "geometry": {"coordinates":[-76.91711599999999,38.620635],"type":"Point"}
}