{
  "type": "Feature",
  "properties": {
    "addr:full":"3099 E Madison St Baltimore MD 21205",
    "addr:housenumber":"3099",
    "addr:postcode":"21205",
    "addr:street":"E Madison St",
    "iso:country":"US",
    "sg:address":"3099 E Madison St",
    "sg:city":"Baltimore",
    "sg:classifiers":[
        {
            "category":"Retail",
            "subcategory":"Auto Repair",
            "type":"Services"
        }
    ],
    "sg:phone":"+1 410 327 3088",
    "sg:postcode":"21205",
    "sg:province":"MD",
    "sg:tags":[
        "body",
        "shop"
    ],
    "wof:name":"Tim Murphy's Collision Center Inc",
    "wof:placetype":"venue"
},
  "geometry": {"coordinates":[-76.57440200000001,39.3004],"type":"Point"}
}