{
  "type": "Feature",
  "properties": {
    "iso:country":"US",
    "sg:address":"1220B E Joppa Rd Ste 310",
    "sg:city":"Towson",
    "sg:classifiers":[
        {
            "category":"Health Services",
            "subcategory":"Doctor",
            "type":"Services"
        }
    ],
    "sg:phone":"+1 410 494 1888",
    "sg:postcode":"21286",
    "sg:province":"MD",
    "sg:tags":[
        "physician",
        "surgeon"
    ],
    "wof:name":"Rheumatology Associates",
    "wof:placetype":"venue"
},
  "geometry": {"coordinates":[-76.57804899999999,39.39637],"type":"Point"}
}