{
  "type": "Feature",
  "properties": {
    "iso:country":"US",
    "sg:address":"10514 Marriottsville Rd",
    "sg:city":"Randallstown",
    "sg:classifiers":[
        {
            "category":"Shopping",
            "subcategory":"Used Merchandise",
            "type":"Retail Goods"
        }
    ],
    "sg:phone":"+1 410 465 9023",
    "sg:postcode":"21133",
    "sg:province":"MD",
    "sg:tags":[
        "book",
        "rare",
        "dealer"
    ],
    "wof:name":"John Gach Books",
    "wof:placetype":"venue"
},
  "geometry": {"coordinates":[-76.845079,39.375075],"type":"Point"}
}