{
  "type": "Feature",
  "properties": {
    "iso:country":"US",
    "sg:address":"221 Commerce Dr",
    "sg:city":"Upper Marlboro",
    "sg:classifiers":[
        {
            "category":"Building & Trades",
            "subcategory":"Equipment Rental",
            "type":"Services"
        }
    ],
    "sg:phone":"+1 301 390 3806",
    "sg:postcode":"20774",
    "sg:province":"MD",
    "sg:tags":[
        "contractor"
    ],
    "wof:name":"Godwin Pumps Of Maryland Inc",
    "wof:placetype":"venue"
},
  "geometry": {"coordinates":[-76.728779,38.885478],"type":"Point"}
}