{
  "type": "Feature",
  "properties": {
    "iso:country":"US",
    "sg:address":"6110 Old Silver Hill Rd",
    "sg:city":"District Heights",
    "sg:classifiers":[
        {
            "category":"Shopping",
            "subcategory":"Pharmacy",
            "type":"Retail Goods"
        }
    ],
    "sg:phone":"+1 301 735 7700",
    "sg:postcode":"20747",
    "sg:province":"MD",
    "sg:tags":[
        "drugstore"
    ],
    "sg:website":"www.kayceedrugs.com",
    "wof:name":"Kay Cee Drugs",
    "wof:placetype":"venue"
},
  "geometry": {"coordinates":[-76.90149700000001,38.855099],"type":"Point"}
}