{
  "type": "Feature",
  "properties": {
    "iso:country":"US",
    "sg:address":"301 Prince Georges Blvd",
    "sg:city":"Upper Marlboro",
    "sg:classifiers":[
        {
            "category":"Professional",
            "type":"Services"
        }
    ],
    "sg:phone":"+1 301 390 5500",
    "sg:postcode":"20774",
    "sg:province":"MD",
    "sg:tags":[
        "establishment"
    ],
    "wof:name":"Jcm Associates",
    "wof:placetype":"venue"
},
  "geometry": {"coordinates":[-76.72778599999999,38.886109],"type":"Point"}
}