{
  "type": "Feature",
  "properties": {
    "addr:full":"1301 W Patrick St Ste 408 Frederick MD 21702",
    "addr:housenumber":"1301",
    "addr:postcode":"21702",
    "addr:street":"W Patrick St Ste 408",
    "iso:country":"US",
    "sg:address":"1301 W Patrick St Ste 408",
    "sg:city":"Frederick",
    "sg:classifiers":[
        {
            "category":"Shopping",
            "subcategory":"Jewelry",
            "type":"Retail Goods"
        },
        {
            "category":"Manufacturing",
            "subcategory":"Jewelry",
            "type":"Manufacturing & Wholesale Goods"
        }
    ],
    "sg:phone":"+1 301 663 8480",
    "sg:postcode":"21702",
    "sg:province":"MD",
    "sg:tags":[
        "stone",
        "designer",
        "watch",
        "jeweler",
        "precious",
        "semi-precious"
    ],
    "sg:website":"http://www.kay.com",
    "wof:name":"Kay Jewelers",
    "wof:placetype":"venue"
},
  "geometry": {"coordinates":[-77.45343800000001,39.418789],"type":"Point"}
}