{
  "type": "Feature",
  "properties": {
    "addr:full":"14939 Athey Rd Burtonsville MD 20866",
    "addr:housenumber":"14939",
    "addr:postcode":"20866",
    "addr:street":"Athey Rd",
    "iso:country":"US",
    "sg:address":"14939 Athey Rd",
    "sg:city":"Burtonsville",
    "sg:classifiers":[
        {
            "category":"Building & Trades",
            "subcategory":"Electrical",
            "type":"Services"
        }
    ],
    "sg:phone":"+1 301 421 4135",
    "sg:postcode":"20866",
    "sg:province":"MD",
    "sg:tags":[
        "electrical",
        "contractor"
    ],
    "wof:name":"Aacr Inc",
    "wof:placetype":"venue"
},
  "geometry": {"coordinates":[-76.936716,39.09953],"type":"Point"}
}