{
  "type": "Feature",
  "properties": {
    "iso:country":"US",
    "sg:address":"8555 16th St",
    "sg:city":"Silver Spring",
    "sg:classifiers":[
        {
            "category":"Real Estate",
            "subcategory":"Real Estate Services",
            "type":"Services"
        }
    ],
    "sg:phone":"+1 301 587 7599",
    "sg:postcode":"20910",
    "sg:province":"MD",
    "sg:tags":[
        "company",
        "title"
    ],
    "sg:website":"www.fountainheadtitle.com",
    "wof:name":"Fountainhead Title Group",
    "wof:placetype":"venue"
},
  "geometry": {"coordinates":[-77.038517,38.998009],"type":"Point"}
}