{
  "type": "Feature",
  "properties": {
    "iso:country":"US",
    "sg:address":"971 Beards Hill Rd # G ",
    "sg:city":"Aberdeen",
    "sg:classifiers":[
        {
            "category":"Restaurant",
            "type":"Food & Drink"
        }
    ],
    "sg:menulink":"http://www.allmenus.com/md/halls-cross-roads/285729-lees-hunan-chinese-rstrnt/menu/",
    "sg:phone":"+1 410 272 6610",
    "sg:postcode":"21001",
    "sg:province":"MD",
    "sg:tags":[
        "asian",
        "chinese"
    ],
    "wof:name":"Lee's Hunan Chinese Rstrnt",
    "wof:placetype":"venue"
},
  "geometry": {"coordinates":[-76.18367600000001,39.524607],"type":"Point"}
}