{
  "type": "Feature",
  "properties": {
    "iso:country":"US",
    "sg:address":"726 Fayette St",
    "sg:city":"Cumberland",
    "sg:classifiers":[
        {
            "category":"Building & Trades",
            "subcategory":"Construction",
            "type":"Services"
        }
    ],
    "sg:phone":"+1 301 777 1248",
    "sg:postcode":"21502",
    "sg:province":"MD",
    "sg:tags":[
        "house"
    ],
    "wof:name":"Allcraft Improvement",
    "wof:placetype":"venue"
},
  "geometry": {"coordinates":[-78.781212,39.653449],"type":"Point"}
}