{
  "type": "Feature",
  "properties": {
    "addr:full":"4400 Viceroy Pl White Plains MD 20695",
    "addr:housenumber":"4400",
    "addr:postcode":"20695",
    "addr:street":"Viceroy Pl",
    "iso:country":"US",
    "sg:address":"4400 Viceroy Pl",
    "sg:city":"White Plains",
    "sg:classifiers":[
        {
            "category":"Building & Trades",
            "subcategory":"Cleaning & Sanitation",
            "type":"Services"
        }
    ],
    "sg:phone":"+1 301 870 4285",
    "sg:postcode":"20695",
    "sg:province":"MD",
    "sg:tags":[
        "janitor"
    ],
    "wof:name":"Carlitas Cleaning Concepts LLC",
    "wof:placetype":"venue"
},
  "geometry": {"coordinates":[-77.031874,38.611884],"type":"Point"}
}