{
  "type": "Feature",
  "properties": {
    "addr:full":"15480 Annapolis Rd Bowie MD 20715",
    "addr:housenumber":"15480",
    "addr:postcode":"20715",
    "addr:street":"Annapolis Rd",
    "iso:country":"US",
    "sg:address":"15480 Annapolis Rd",
    "sg:city":"Bowie",
    "sg:classifiers":[
        {
            "category":"Food & Beverages",
            "subcategory":"Groceries & Convenience Stores",
            "type":"Retail Goods"
        }
    ],
    "sg:phone":"+1 301 464 3461",
    "sg:postcode":"20715",
    "sg:province":"MD",
    "sg:tags":[
        "grocer"
    ],
    "wof:name":"Giant Food",
    "wof:placetype":"venue"
},
  "geometry": {"coordinates":[-76.736512,38.978809],"type":"Point"}
}