{
  "type": "Feature",
  "properties": {
    "iso:country":"US",
    "sg:address":"11345 Pembrooke Sq",
    "sg:city":"Waldorf",
    "sg:classifiers":[
        {
            "category":"Health Services",
            "subcategory":"Doctor",
            "type":"Services"
        }
    ],
    "sg:phone":"+1 301 645 4220",
    "sg:postcode":"20603",
    "sg:province":"MD",
    "sg:tags":[
        "physician",
        "surgeon"
    ],
    "wof:name":"Family Health Care Physicians",
    "wof:placetype":"venue"
},
  "geometry": {"coordinates":[-76.917337,38.619255],"type":"Point"}
}