{
  "type": "Feature",
  "properties": {
    "iso:country":"US",
    "sg:address":"14508 Sorrento Ct",
    "sg:city":"Burtonsville",
    "sg:classifiers":[
        {
            "category":"Real Estate",
            "subcategory":"Real Estate Agent",
            "type":"Services"
        }
    ],
    "sg:phone":"+1 301 890 2820",
    "sg:postcode":"20866",
    "sg:province":"MD",
    "sg:tags":[
        "consultant"
    ],
    "wof:name":"Land Realty & Appraisal Inc",
    "wof:placetype":"venue"
},
  "geometry": {"coordinates":[-76.932047,39.093833],"type":"Point"}
}