{
  "type": "Feature",
  "properties": {
    "iso:country":"US",
    "sg:address":"6025 10th Pl",
    "sg:city":"Hyattsville",
    "sg:classifiers":[
        {
            "category":"Building & Trades",
            "subcategory":"Construction",
            "type":"Services"
        }
    ],
    "sg:phone":"+1 301 559 1138",
    "sg:postcode":"20782",
    "sg:province":"MD",
    "sg:tags":[
        "roofing",
        "contractor"
    ],
    "wof:name":"R & C Roofing & Gutters Inc",
    "wof:placetype":"venue"
},
  "geometry": {"coordinates":[-76.989436,38.961403],"type":"Point"}
}