{
  "type": "Feature",
  "properties": {
    "addr:full":"398 Hungerford Dr Rockville MD 20850",
    "addr:housenumber":"398",
    "addr:postcode":"20850",
    "addr:street":"Hungerford Dr",
    "iso:country":"US",
    "sg:address":"398 Hungerford Dr",
    "sg:city":"Rockville",
    "sg:classifiers":[
        {
            "category":"Shopping",
            "subcategory":"Used Merchandise",
            "type":"Retail Goods"
        }
    ],
    "sg:phone":"+1 301 762 2242",
    "sg:postcode":"20850",
    "sg:province":"MD",
    "sg:tags":[
        "shop",
        "thrift"
    ],
    "wof:name":"Bargain Box",
    "wof:placetype":"venue"
},
  "geometry": {"coordinates":[-77.15320199999999,39.091659],"type":"Point"}
}