{
  "type": "Feature",
  "properties": {
    "iso:country":"US",
    "sg:address":"2310 Ridge Tree Ct",
    "sg:city":"Ellicott City",
    "sg:classifiers":[
        {
            "category":"Arts & Performance",
            "subcategory":"Theater",
            "type":"Entertainment"
        }
    ],
    "sg:phone":"+1 410 992 8244",
    "sg:postcode":"21042",
    "sg:province":"MD",
    "sg:tags":[
        "live",
        "music"
    ],
    "wof:name":"Bristol Sounds Inc",
    "wof:placetype":"venue"
},
  "geometry": {"coordinates":[-76.84493000000001,39.307244],"type":"Point"}
}