{
  "type": "Feature",
  "properties": {
    "iso:country":"US",
    "sg:address":"10241 Kensington Pkwy",
    "sg:city":"Kensington",
    "sg:classifiers":[
        {
            "category":"Local Transit",
            "type":"Transportation"
        }
    ],
    "sg:phone":"+1 301 933 4357",
    "sg:postcode":"20895",
    "sg:province":"MD",
    "sg:tags":[
        "ambulance"
    ],
    "wof:name":"All American Ambulance",
    "wof:placetype":"venue"
},
  "geometry": {"coordinates":[-77.072192,39.025982],"type":"Point"}
}