{
  "type": "Feature",
  "properties": {
    "addr:full":"16 Bel Air South Pkwy Bel Air MD 21015",
    "addr:housenumber":"16",
    "addr:postcode":"21015",
    "addr:street":"Bel Air South Pkwy",
    "iso:country":"US",
    "sg:address":"16 Bel Air South Pkwy",
    "sg:city":"Bel Air",
    "sg:classifiers":[
        {
            "category":"Shopping",
            "subcategory":"Clothing, Apparel, & Fashions",
            "type":"Retail Goods"
        }
    ],
    "sg:phone":"+1 410 569 6694",
    "sg:postcode":"21015",
    "sg:province":"MD",
    "sg:website":"www.talbots.com",
    "wof:name":"Talbots",
    "wof:placetype":"venue"
},
  "geometry": {"coordinates":[-76.325424,39.497972],"type":"Point"}
}