{
  "type": "Feature",
  "properties": {
    "addr:full":"101 Broad St Hurlock MD 21643",
    "addr:housenumber":"101",
    "addr:postcode":"21643",
    "addr:street":"Broad St",
    "iso:country":"US",
    "sg:address":"101 Broad St",
    "sg:city":"Hurlock",
    "sg:classifiers":[
        {
            "category":"Food & Beverages",
            "subcategory":"Groceries & Convenience Stores",
            "type":"Retail Goods"
        }
    ],
    "sg:phone":"+1 410 943 4000",
    "sg:postcode":"21643",
    "sg:province":"MD",
    "sg:tags":[
        "grocer"
    ],
    "wof:name":"Hurlock FOOD Rite",
    "wof:placetype":"venue"
},
  "geometry": {"coordinates":[-75.861503,38.636188],"type":"Point"}
}