{
  "type": "Feature",
  "properties": {
    "addr:full":"2003 W Pratt St Baltimore MD 21223",
    "addr:housenumber":"2003",
    "addr:postcode":"21223",
    "addr:street":"W Pratt St",
    "iso:country":"US",
    "sg:address":"2003 W Pratt St",
    "sg:city":"Baltimore",
    "sg:classifiers":[
        {
            "category":"Restaurant",
            "type":"Food & Drink"
        }
    ],
    "sg:phone":"+1 410 566 0110",
    "sg:postcode":"21223",
    "sg:province":"MD",
    "wof:name":"Pak Man Fried Chicken",
    "wof:placetype":"venue"
},
  "geometry": {"coordinates":[-76.64859800000001,39.285],"type":"Point"}
}