{
  "type": "Feature",
  "properties": {
    "iso:country":"US",
    "sg:address":"1504 Mount Hermon Rd",
    "sg:city":"Salisbury",
    "sg:classifiers":[
        {
            "category":"Shopping",
            "subcategory":"Hobbies, Toys, & Games",
            "type":"Retail Goods"
        }
    ],
    "sg:phone":"+1 443 260 4925",
    "sg:postcode":"21804",
    "sg:province":"MD",
    "wof:name":"Natures Creations Mfg",
    "wof:placetype":"venue"
},
  "geometry": {"coordinates":[-75.55950799999999,38.363371],"type":"Point"}
}