{
  "type": "Feature",
  "properties": {
    "iso:country":"US",
    "sg:address":"14415 Cuba Rd",
    "sg:city":"Cockeysville",
    "sg:classifiers":[
        {
            "category":"Professional",
            "subcategory":"Business Services",
            "type":"Services"
        }
    ],
    "sg:phone":"+1 443 621 0557",
    "sg:postcode":"21030",
    "sg:province":"MD",
    "wof:name":"Applied Solutions Inc",
    "wof:placetype":"venue"
},
  "geometry": {"coordinates":[-76.712903,39.522706],"type":"Point"}
}