{
  "type": "Feature",
  "properties": {
    "iso:country":"US",
    "sg:address":"18153 Village Mart Dr",
    "sg:city":"Olney",
    "sg:classifiers":[
        {
            "category":"Utilities",
            "subcategory":"Mobile Phone",
            "type":"Services"
        }
    ],
    "sg:phone":"+1 301 929 3476",
    "sg:postcode":"20832",
    "sg:province":"MD",
    "sg:tags":[
        "telephone",
        "cellular"
    ],
    "wof:name":"Nextel Retail",
    "wof:placetype":"venue"
},
  "geometry": {"coordinates":[-77.06359999999999,39.151864],"type":"Point"}
}