{
  "type": "Feature",
  "properties": {
    "addr:full":"3950 Ravine Dr White Plains MD 20695",
    "addr:housenumber":"3950",
    "addr:postcode":"20695",
    "addr:street":"Ravine Dr",
    "iso:country":"US",
    "sg:address":"3950 Ravine Dr",
    "sg:city":"White Plains",
    "sg:classifiers":[
        {
            "category":"Mining & Drilling",
            "type":"Manufacturing & Wholesale Goods"
        }
    ],
    "sg:phone":"+1 301 645 1484",
    "sg:postcode":"20695",
    "sg:province":"MD",
    "sg:tags":[
        "construction"
    ],
    "wof:name":"Jmc",
    "wof:placetype":"venue"
},
  "geometry": {"coordinates":[-77.02597400000001,38.605425],"type":"Point"}
}