{
  "type": "Feature",
  "properties": {
    "iso:country":"US",
    "sg:address":"7619 Penn Belt Dr",
    "sg:city":"District Heights",
    "sg:classifiers":[
        {
            "category":"Wholesale",
            "subcategory":"Electrical",
            "type":"Manufacturing & Wholesale Goods"
        }
    ],
    "sg:phone":"+1 301 736 5500",
    "sg:postcode":"20747",
    "sg:province":"MD",
    "sg:tags":[
        "armature"
    ],
    "sg:website":"www.certipro.com",
    "wof:name":"Precision Certi Pro Warehouse",
    "wof:placetype":"venue"
},
  "geometry": {"coordinates":[-76.875578,38.836332],"type":"Point"}
}