{
  "type": "Feature",
  "properties": {
    "addr:full":"401 Marvel Ct Easton MD 21601",
    "addr:housenumber":"401",
    "addr:postcode":"21601",
    "addr:street":"Marvel Ct",
    "iso:country":"US",
    "sg:address":"401 Marvel Ct",
    "sg:city":"Easton",
    "sg:classifiers":[
        {
            "category":"Health Services",
            "subcategory":"Health Practitioner",
            "type":"Services"
        }
    ],
    "sg:phone":"+1 410 820 4449",
    "sg:postcode":"21601",
    "sg:province":"MD",
    "sg:tags":[
        "therapist",
        "physical"
    ],
    "wof:name":"Easton Physical Thrpy & Sports",
    "wof:placetype":"venue"
},
  "geometry": {"coordinates":[-76.063655,38.76539],"type":"Point"}
}