{
  "type": "Feature",
  "properties": {
    "iso:country":"US",
    "sg:address":"2112 Emmorton Park Rd",
    "sg:city":"Edgewood",
    "sg:classifiers":[
        {
            "category":"Travel",
            "subcategory":"Hotels & Motels",
            "type":"Entertainment"
        }
    ],
    "sg:phone":"+1 410 670 6000",
    "sg:postcode":"21040",
    "sg:province":"MD",
    "sg:tags":[
        "corporate",
        "lodging"
    ],
    "sg:website":"http://www.baltimoreedgewood.hamptoninn.com",
    "wof:name":"Hampton Inn",
    "wof:placetype":"venue"
},
  "geometry": {"coordinates":[-76.310547,39.453129],"type":"Point"}
}