{
  "type": "Feature",
  "properties": {
    "addr:full":"3201 Saint Paul St Baltimore MD 21218",
    "addr:housenumber":"3201",
    "addr:postcode":"21218",
    "addr:street":"Saint Paul St",
    "iso:country":"US",
    "sg:address":"3201 Saint Paul St",
    "sg:city":"Baltimore",
    "sg:classifiers":[
        {
            "category":"Building & Trades",
            "subcategory":"Locksmith",
            "type":"Services"
        }
    ],
    "sg:phone":"+1 443 378 3067",
    "sg:postcode":"21218",
    "sg:province":"MD",
    "sg:tags":[
        "key"
    ],
    "wof:name":"Acl Baltimore Locksmith",
    "wof:placetype":"venue"
},
  "geometry": {"coordinates":[-76.61569299999999,39.32689],"type":"Point"}
}