{
  "type": "Feature",
  "properties": {
    "addr:full":"5625 Allentown Rd Suitland MD 20746",
    "addr:housenumber":"5625",
    "addr:postcode":"20746",
    "addr:street":"Allentown Rd",
    "iso:country":"US",
    "sg:address":"5625 Allentown Rd",
    "sg:city":"Suitland",
    "sg:classifiers":[
        {
            "category":"Utilities",
            "subcategory":"Electric",
            "type":"Services"
        }
    ],
    "sg:phone":"+1 301 505 0061",
    "sg:postcode":"20746",
    "sg:province":"MD",
    "sg:tags":[
        "company"
    ],
    "wof:name":"We Electric",
    "wof:placetype":"venue"
},
  "geometry": {"coordinates":[-76.89807,38.808371],"type":"Point"}
}