{
  "type": "Feature",
  "properties": {
    "addr:full":"140 W Lafayette Ave Baltimore MD 21217",
    "addr:housenumber":"140",
    "addr:postcode":"21217",
    "addr:street":"W Lafayette Ave",
    "iso:country":"US",
    "sg:address":"140 W Lafayette Ave",
    "sg:city":"Baltimore",
    "sg:classifiers":[
        {
            "category":"Coffee & Tea",
            "type":"Food & Drink"
        },
        {
            "category":"Restaurant",
            "type":"Food & Drink"
        }
    ],
    "sg:phone":"+1 410 383 6614",
    "sg:postcode":"21217",
    "sg:province":"MD",
    "sg:tags":[
        "espresso"
    ],
    "wof:name":"Mica Cafe Doris",
    "wof:placetype":"venue"
},
  "geometry": {"coordinates":[-76.62325300000001,39.307444],"type":"Point"}
}