{
  "type": "Feature",
  "properties": {
    "addr:full":"8402 Towne Crest Ct Gaithersburg MD 20877",
    "addr:housenumber":"8402",
    "addr:postcode":"20877",
    "addr:street":"Towne Crest Ct",
    "iso:country":"US",
    "sg:address":"8402 Towne Crest Ct",
    "sg:city":"Gaithersburg",
    "sg:classifiers":[
        {
            "category":"Banks & Credit Unions",
            "subcategory":"Financial Services",
            "type":"Services"
        }
    ],
    "sg:phone":"+1 240 506 7206",
    "sg:postcode":"20877",
    "sg:province":"MD",
    "sg:tags":[
        "company",
        "investment",
        "real estate"
    ],
    "wof:name":"Wilson Enterprises LLC",
    "wof:placetype":"venue"
},
  "geometry": {"coordinates":[-77.173742,39.145319],"type":"Point"}
}