{
  "type": "Feature",
  "properties": {
    "iso:country":"US",
    "sg:address":"2515 Bennett Point Rd",
    "sg:city":"Queenstown",
    "sg:classifiers":[
        {
            "category":"Food & Beverages",
            "subcategory":"Meat & Fish",
            "type":"Retail Goods"
        }
    ],
    "sg:phone":"+1 410 827 6535",
    "sg:postcode":"21658",
    "sg:province":"MD",
    "sg:tags":[
        "seafood"
    ],
    "wof:name":"Winchester Crab & Seafood Co",
    "wof:placetype":"venue"
},
  "geometry": {"coordinates":[-76.184439,38.899061],"type":"Point"}
}