{
  "type": "Feature",
  "properties": {
    "addr:full":"601 Lakeview Dr Westminster MD 21157",
    "addr:housenumber":"601",
    "addr:postcode":"21157",
    "addr:street":"Lakeview Dr",
    "iso:country":"US",
    "sg:address":"601 Lakeview Dr",
    "sg:city":"Westminster",
    "sg:classifiers":[
        {
            "category":"Local Transit",
            "type":"Transportation"
        }
    ],
    "sg:phone":"+1 410 840 3600",
    "sg:postcode":"21157",
    "sg:province":"MD",
    "sg:tags":[
        "limousine"
    ],
    "wof:name":"A Paradise Limousine Svc",
    "wof:placetype":"venue"
},
  "geometry": {"coordinates":[-76.96339999999999,39.592898],"type":"Point"}
}