{
  "type": "Feature",
  "properties": {
    "addr:full":"1139 Poplar Grove St Baltimore MD 21216",
    "addr:housenumber":"1139",
    "addr:postcode":"21216",
    "addr:street":"Poplar Grove St",
    "iso:country":"US",
    "sg:address":"1139 Poplar Grove St",
    "sg:city":"Baltimore",
    "sg:classifiers":[
        {
            "category":"Professional",
            "subcategory":"Detective & Security Services",
            "type":"Services"
        }
    ],
    "sg:phone":"+1 443 564 7612",
    "sg:postcode":"21216",
    "sg:province":"MD",
    "sg:tags":[
        "guard",
        "patrol"
    ],
    "wof:name":"In The Life Security",
    "wof:placetype":"venue"
},
  "geometry": {"coordinates":[-76.665279,39.300677],"type":"Point"}
}