{
  "type": "Feature",
  "properties": {
    "iso:country":"US",
    "sg:address":"1707 Frederick Rd",
    "sg:city":"Catonsville",
    "sg:classifiers":[
        {
            "category":"Retail",
            "subcategory":"Veterinary Services",
            "type":"Services"
        }
    ],
    "sg:phone":"+1 410 719 2445",
    "sg:postcode":"21228",
    "sg:province":"MD",
    "sg:tags":[
        "clinic",
        "hospital",
        "veterinarian",
        "specialty"
    ],
    "wof:name":"Catonsville Animal Hospital",
    "wof:placetype":"venue"
},
  "geometry": {"coordinates":[-76.751503,39.2682],"type":"Point"}
}