{
  "type": "Feature",
  "properties": {
    "iso:country":"US",
    "sg:address":"310 Argosy Dr",
    "sg:city":"Gaithersburg",
    "sg:classifiers":[
        {
            "category":"Professional",
            "subcategory":"Business Services",
            "type":"Services"
        }
    ],
    "sg:phone":"+1 301 670 0977",
    "sg:postcode":"20878",
    "sg:province":"MD",
    "wof:name":"Argosy Group Inc",
    "wof:placetype":"venue"
},
  "geometry": {"coordinates":[-77.221038,39.105236],"type":"Point"}
}