{
  "type": "Feature",
  "properties": {
    "iso:country":"US",
    "sg:address":"8661 Glenarden Pkwy",
    "sg:city":"Glenarden",
    "sg:classifiers":[
        {
            "category":"Shopping",
            "subcategory":"Clothing, Apparel, & Fashions",
            "type":"Retail Goods"
        }
    ],
    "sg:phone":"+1 301 736 8107",
    "sg:postcode":"20706",
    "sg:province":"MD",
    "sg:tags":[
        "clothing",
        "store"
    ],
    "wof:name":"Gallery Africa",
    "wof:placetype":"venue"
},
  "geometry": {"coordinates":[-76.862925,38.931362],"type":"Point"}
}