{
  "type": "Feature",
  "properties": {
    "iso:country":"US",
    "sg:address":"22340 Three Notch Rd",
    "sg:city":"Lexington Park",
    "sg:classifiers":[
        {
            "category":"Personal",
            "type":"Services"
        }
    ],
    "sg:phone":"+1 301 862 1665",
    "sg:postcode":"20653",
    "sg:province":"MD",
    "sg:tags":[
        "mover"
    ],
    "sg:website":"www.calvertselfstorage.com",
    "wof:name":"Potomac Self Storage",
    "wof:placetype":"venue"
},
  "geometry": {"coordinates":[-76.46933,38.281325],"type":"Point"}
}