{
  "type": "Feature",
  "properties": {
    "addr:full":"11801 Park Waldorf Ln Waldorf MD 20601",
    "addr:housenumber":"11801",
    "addr:postcode":"20601",
    "addr:street":"Park Waldorf Ln",
    "iso:country":"US",
    "sg:address":"11801 Park Waldorf Ln",
    "sg:city":"Waldorf",
    "sg:classifiers":[
        {
            "category":"Education",
            "subcategory":"Special Training",
            "type":"Public Place"
        }
    ],
    "sg:phone":"+1 301 632 5557",
    "sg:postcode":"20601",
    "sg:province":"MD",
    "sg:tags":[
        "instruction",
        "driving"
    ],
    "wof:name":"Top Dawg Driving School",
    "wof:placetype":"venue"
},
  "geometry": {"coordinates":[-76.900595,38.635282],"type":"Point"}
}