{
  "type": "Feature",
  "properties": {
    "addr:full":"7 Monmouth Rd Catonsville MD 21228",
    "addr:housenumber":"7",
    "addr:postcode":"21228",
    "addr:street":"Monmouth Rd",
    "iso:country":"US",
    "sg:address":"7 Monmouth Rd",
    "sg:city":"Catonsville",
    "sg:classifiers":[
        {
            "category":"Professional",
            "subcategory":"Management & Consulting",
            "type":"Services"
        },
        {
            "category":"Professional",
            "subcategory":"Advertising",
            "type":"Services"
        },
        {
            "category":"Internet Cafe",
            "subcategory":"None",
            "type":"Food & Drink"
        },
        {
            "category":"Professional",
            "subcategory":"Computer Services",
            "type":"Services"
        }
    ],
    "sg:phone":"+1 410 788 4516",
    "sg:postcode":"21228",
    "sg:province":"MD",
    "sg:tags":[
        "product",
        "marketing",
        "sale",
        "relation",
        "online",
        "promotion",
        "counselor",
        "public"
    ],
    "sg:website":"http://www.graphicseo.com",
    "wof:name":"Graphic SEO",
    "wof:placetype":"venue"
},
  "geometry": {"coordinates":[-76.76197999999999,39.266272],"type":"Point"}
}