{
  "type": "Feature",
  "properties": {
    "addr:full":"658 Kenilworth Dr Baltimore MD 21204",
    "addr:housenumber":"658",
    "addr:postcode":"21204",
    "addr:street":"Kenilworth Dr",
    "iso:country":"US",
    "sg:address":"658 Kenilworth Dr",
    "sg:city":"Baltimore",
    "sg:classifiers":[
        {
            "category":"Health Services",
            "subcategory":"Doctor",
            "type":"Services"
        }
    ],
    "sg:phone":"+1 410 828 0555",
    "sg:postcode":"21204",
    "sg:province":"MD",
    "sg:tags":[
        "physician",
        "surgeon"
    ],
    "wof:name":"D T Haciski MD",
    "wof:placetype":"venue"
},
  "geometry": {"coordinates":[-76.61585100000001,39.409932],"type":"Point"}
}