{
  "type": "Feature",
  "properties": {
    "addr:full":"1008 Primrose Rd Apt 302 Annapolis MD 21403",
    "addr:housenumber":"1008;302",
    "addr:postcode":"21403",
    "addr:street":"Primrose Rd Apt",
    "iso:country":"US",
    "sg:address":"1008 Primrose Rd Apt 302",
    "sg:city":"Annapolis",
    "sg:classifiers":[
        {
            "category":"Building & Trades",
            "subcategory":"Cleaning & Sanitation",
            "type":"Services"
        }
    ],
    "sg:phone":"+1 410 507 9092",
    "sg:postcode":"21403",
    "sg:province":"MD",
    "sg:tags":[
        "window"
    ],
    "wof:name":"Atlantic Window Cleaning",
    "wof:placetype":"venue"
},
  "geometry": {"coordinates":[-76.49973,38.966421],"type":"Point"}
}