{
  "type": "Feature",
  "properties": {
    "addr:full":"1317 E Gude Dr Rockville MD 20850",
    "addr:housenumber":"1317",
    "addr:postcode":"20850",
    "addr:street":"E Gude Dr",
    "iso:country":"US",
    "sg:address":"1317 E Gude Dr",
    "sg:city":"Rockville",
    "sg:classifiers":[
        {
            "category":"Home & Garden",
            "subcategory":"Furniture",
            "type":"Retail Goods"
        }
    ],
    "sg:phone":"+1 301 340 1737",
    "sg:postcode":"20850",
    "sg:province":"MD",
    "wof:name":"Wright's Furniture",
    "wof:placetype":"venue"
},
  "geometry": {"coordinates":[-77.136117,39.097383],"type":"Point"}
}