{
  "type": "Feature",
  "properties": {
    "addr:full":"3301 Belair Rd Baltimore MD 21213",
    "addr:housenumber":"3301",
    "addr:postcode":"21213",
    "addr:street":"Belair Rd",
    "iso:country":"US",
    "sg:address":"3301 Belair Rd",
    "sg:city":"Baltimore",
    "sg:classifiers":[
        {
            "category":"Banks & Credit Unions",
            "subcategory":"Bank",
            "type":"Services"
        }
    ],
    "sg:phone":"+1 410 342 5515",
    "sg:postcode":"21213",
    "sg:province":"MD",
    "sg:website":"www.susquehanna.net",
    "wof:name":"Susquehanna Bank",
    "wof:placetype":"venue"
},
  "geometry": {"coordinates":[-76.5737,39.321701],"type":"Point"}
}