{
  "type": "Feature",
  "properties": {
    "addr:full":"21605 Great Mills Rd Lexington Park MD 20653",
    "addr:housenumber":"21605",
    "addr:postcode":"20653",
    "addr:street":"Great Mills Rd",
    "iso:country":"US",
    "sg:address":"21605 Great Mills Rd",
    "sg:city":"Lexington Park",
    "sg:classifiers":[
        {
            "category":"Autos & Motor Vehicles",
            "subcategory":"Auto Supplies",
            "type":"Retail Goods"
        }
    ],
    "sg:phone":"+1 301 737 6072",
    "sg:postcode":"20653",
    "sg:province":"MD",
    "sg:tags":[
        "automobile",
        "parts"
    ],
    "wof:name":"Advance Auto Parts",
    "wof:placetype":"venue"
},
  "geometry": {"coordinates":[-76.46472,38.260863],"type":"Point"}
}