{
  "type": "Feature",
  "properties": {
    "addr:full":"3561 Fortuna Ct Huntingtown MD 20639",
    "addr:housenumber":"3561",
    "addr:postcode":"20639",
    "addr:street":"Fortuna Ct",
    "iso:country":"US",
    "sg:address":"3561 Fortuna Ct",
    "sg:city":"Huntingtown",
    "sg:classifiers":[
        {
            "category":"Insurance",
            "subcategory":"Hazard Insurance",
            "type":"Services"
        }
    ],
    "sg:phone":"+1 410 414 9155",
    "sg:postcode":"20639",
    "sg:province":"MD",
    "wof:name":"American Ins Mktg Corp",
    "wof:placetype":"venue"
},
  "geometry": {"coordinates":[-76.540904,38.61454],"type":"Point"}
}