{
  "type": "Feature",
  "properties": {
    "addr:full":"5570 Norbeck Rd Rockville MD 20853",
    "addr:housenumber":"5570",
    "addr:postcode":"20853",
    "addr:street":"Norbeck Rd",
    "iso:country":"US",
    "sg:address":"5570 Norbeck Rd",
    "sg:city":"Rockville",
    "sg:classifiers":[
        {
            "category":"Restaurant",
            "type":"Food & Drink"
        }
    ],
    "sg:phone":"+1 301 460 7591",
    "sg:postcode":"20853",
    "sg:province":"MD",
    "wof:name":"Pizza Hut",
    "wof:placetype":"venue"
},
  "geometry": {"coordinates":[-77.11426299999999,39.094773],"type":"Point"}
}