{
  "type": "Feature",
  "properties": {
    "addr:full":"8919 Double Hills Rd Denton MD 21629",
    "addr:housenumber":"8919",
    "addr:postcode":"21629",
    "addr:street":"Double Hills Rd",
    "iso:country":"US",
    "sg:address":"8919 Double Hills Rd",
    "sg:city":"Denton",
    "sg:classifiers":[
        {
            "category":"Autos & Motor Vehicles",
            "subcategory":"Auto Supplies",
            "type":"Retail Goods"
        }
    ],
    "sg:phone":"+1 410 479 0090",
    "sg:postcode":"21629",
    "sg:province":"MD",
    "sg:tags":[
        "tire"
    ],
    "wof:name":"Wayside Tire & Svc Ctr Inc",
    "wof:placetype":"venue"
},
  "geometry": {"coordinates":[-75.82238700000001,38.863919],"type":"Point"}
}