{
  "type": "Feature",
  "properties": {
    "iso:country":"US",
    "sg:address":"5435 Handley Rd",
    "sg:city":"Cambridge",
    "sg:classifiers":[
        {
            "category":"Building & Trades",
            "subcategory":"Construction",
            "type":"Services"
        }
    ],
    "sg:phone":"+1 410 228 2920",
    "sg:postcode":"21613",
    "sg:province":"MD",
    "sg:tags":[
        "grading",
        "contractor"
    ],
    "wof:name":"Dorchester County Highway Dept",
    "wof:placetype":"venue"
},
  "geometry": {"coordinates":[-76.033753,38.553359],"type":"Point"}
}