{
  "type": "Feature",
  "properties": {
    "iso:country":"US",
    "sg:address":"5880 Hubbard Dr",
    "sg:city":"Rockville",
    "sg:classifiers":[
        {
            "category":"Insurance",
            "subcategory":"Hazard Insurance",
            "type":"Services"
        },
        {
            "category":"Insurance",
            "subcategory":"Health Insurance",
            "type":"Services"
        }
    ],
    "sg:phone":"+1 301 984 1566",
    "sg:postcode":"20852",
    "sg:province":"MD",
    "sg:tags":[
        "maintenance"
    ],
    "wof:name":"Informedix Inc",
    "wof:placetype":"venue"
},
  "geometry": {"coordinates":[-77.11897,39.054947],"type":"Point"}
}