{
  "type": "Feature",
  "properties": {
    "addr:full":"150 Log Canoe Cir Stevensville MD 21666",
    "addr:housenumber":"150",
    "addr:postcode":"21666",
    "addr:street":"Log Canoe Cir",
    "iso:country":"US",
    "sg:address":"150 Log Canoe Cir",
    "sg:city":"Stevensville",
    "sg:classifiers":[
        {
            "category":"Shopping",
            "type":"Retail Goods"
        }
    ],
    "sg:phone":"+1 410 604 0770",
    "sg:postcode":"21666",
    "sg:province":"MD",
    "sg:tags":[
        "orthopedic",
        "appliance"
    ],
    "sg:website":"www.dynasplint.com",
    "wof:name":"Dynasplint Systems",
    "wof:placetype":"venue"
},
  "geometry": {"coordinates":[-76.31902100000001,38.989602],"type":"Point"}
}