{
  "type": "Feature",
  "properties": {
    "iso:country":"US",
    "sg:address":"7686 Belair Rd",
    "sg:city":"Baltimore",
    "sg:classifiers":[
        {
            "category":"Professional",
            "subcategory":"Employment Agencies",
            "type":"Services"
        }
    ],
    "sg:phone":"+1 410 663 5000",
    "sg:postcode":"21236",
    "sg:province":"MD",
    "sg:tags":[
        "opportunity"
    ],
    "sg:website":"www.aerotek.com",
    "wof:name":"Aerotek",
    "wof:placetype":"venue"
},
  "geometry": {"coordinates":[-76.517765,39.366239],"type":"Point"}
}