{
  "type": "Feature",
  "properties": {
    "iso:country":"US",
    "sg:address":"1603 Coopers Way",
    "sg:city":"Frederick",
    "sg:classifiers":[
        {
            "category":"Professional",
            "subcategory":"Detective & Security Services",
            "type":"Services"
        }
    ],
    "sg:phone":"+1 301 473 6110",
    "sg:postcode":"21701",
    "sg:province":"MD",
    "sg:tags":[
        "information",
        "bureau"
    ],
    "wof:name":"Air Quality Services",
    "wof:placetype":"venue"
},
  "geometry": {"coordinates":[-77.37602099999999,39.449089],"type":"Point"}
}