{
  "type": "Feature",
  "properties": {
    "iso:country":"US",
    "sg:address":"18223 Shawley Dr",
    "sg:city":"Hagerstown",
    "sg:classifiers":[
        {
            "category":"Manufacturing",
            "subcategory":"Paper Products",
            "type":"Manufacturing & Wholesale Goods"
        }
    ],
    "sg:phone":"+1 301 790 1660",
    "sg:postcode":"21740",
    "sg:province":"MD",
    "sg:tags":[
        "label"
    ],
    "sg:website":"www.hublabels.com",
    "wof:name":"Hub Labels Inc",
    "wof:placetype":"venue"
},
  "geometry": {"coordinates":[-77.735377,39.688158],"type":"Point"}
}