{
  "type": "Feature",
  "properties": {
    "iso:country":"US",
    "sg:address":"125 N Division St",
    "sg:city":"Salisbury",
    "sg:classifiers":[
        {
            "category":"Government",
            "subcategory":"Office",
            "type":"Public Place"
        }
    ],
    "sg:phone":"+1 410 548 3130",
    "sg:postcode":"21801",
    "sg:province":"MD",
    "sg:tags":[
        "village"
    ],
    "sg:website":"www.ci.salisbury.md.us",
    "wof:name":"Plumbing Inspection",
    "wof:placetype":"venue"
},
  "geometry": {"coordinates":[-75.600295,38.366178],"type":"Point"}
}