{
  "type": "Feature",
  "properties": {
    "iso:country":"US",
    "sg:address":"3302 Harford Rd",
    "sg:city":"Baltimore",
    "sg:classifiers":[
        {
            "category":"Professional",
            "subcategory":"Advertising",
            "type":"Services"
        }
    ],
    "sg:phone":"+1 410 889 2623",
    "sg:postcode":"21218",
    "sg:province":"MD",
    "sg:tags":[
        "agency"
    ],
    "sg:website":"www.szeman.com",
    "wof:name":"Szedesign",
    "wof:placetype":"venue"
},
  "geometry": {"coordinates":[-76.583185,39.328369],"type":"Point"}
}