{
  "type": "Feature",
  "properties": {
    "addr:full":"3801 Cottage Ter Brentwood MD 20722",
    "addr:housenumber":"3801",
    "addr:postcode":"20722",
    "addr:street":"Cottage Ter",
    "iso:country":"US",
    "sg:address":"3801 Cottage Ter",
    "sg:city":"Brentwood",
    "sg:classifiers":[
        {
            "category":"Building & Trades",
            "subcategory":"Cleaning & Sanitation",
            "type":"Services"
        }
    ],
    "sg:phone":"+1 301 277 1129",
    "sg:postcode":"20722",
    "sg:province":"MD",
    "sg:tags":[
        "polishing",
        "waxing",
        "floor"
    ],
    "wof:name":"Andy's General Floor Service",
    "wof:placetype":"venue"
},
  "geometry": {"coordinates":[-76.953033,38.937389],"type":"Point"}
}