{
  "type": "Feature",
  "properties": {
    "addr:full":"250 W Pratt St Baltimore MD 21201",
    "addr:housenumber":"250",
    "addr:postcode":"21201",
    "addr:street":"W Pratt St",
    "iso:country":"US",
    "sg:address":"250 W Pratt St",
    "sg:city":"Baltimore",
    "sg:classifiers":[
        {
            "category":"Professional",
            "subcategory":"Lawyer & Legal Services",
            "type":"Services"
        }
    ],
    "sg:phone":"+1 410 539 5040",
    "sg:postcode":"21201",
    "sg:province":"MD",
    "wof:name":"Gutman Edward J Atty",
    "wof:placetype":"venue"
},
  "geometry": {"coordinates":[-76.61840100000001,39.2864],"type":"Point"}
}