{
  "type": "Feature",
  "properties": {
    "addr:full":"3132 Briggs Chaney Rd Silver Spring MD 20904",
    "addr:housenumber":"3132",
    "addr:postcode":"20904",
    "addr:street":"Briggs Chaney Rd",
    "iso:country":"US",
    "sg:address":"3132 Briggs Chaney Rd",
    "sg:city":"Silver Spring",
    "sg:classifiers":[
        {
            "category":"Social Services",
            "subcategory":"Child Care",
            "type":"Services"
        }
    ],
    "sg:phone":"+1 301 847 1234",
    "sg:postcode":"20904",
    "sg:province":"MD",
    "wof:name":"Kids In Focus",
    "wof:placetype":"venue"
},
  "geometry": {"coordinates":[-76.94693100000001,39.081997],"type":"Point"}
}