{
  "type": "Feature",
  "properties": {
    "addr:full":"205 143rd St Ocean City MD 21842",
    "addr:housenumber":"205",
    "addr:postcode":"21842",
    "addr:street":"143Rd St",
    "iso:country":"US",
    "sg:address":"205 143rd St",
    "sg:city":"Ocean City",
    "sg:classifiers":[
        {
            "category":"Building & Trades",
            "subcategory":"Electrical",
            "type":"Services"
        }
    ],
    "sg:phone":"+1 410 250 2422",
    "sg:postcode":"21842",
    "sg:province":"MD",
    "sg:tags":[
        "electrical",
        "contractor"
    ],
    "wof:name":"R Hall Electric Co",
    "wof:placetype":"venue"
},
  "geometry": {"coordinates":[-75.055913,38.448461],"type":"Point"}
}