{
  "type": "Feature",
  "properties": {
    "addr:full":"8600 Brooks Dr Easton MD 21601",
    "addr:housenumber":"8600",
    "addr:postcode":"21601",
    "addr:street":"Brooks Dr",
    "iso:country":"US",
    "sg:address":"8600 Brooks Dr",
    "sg:city":"Easton",
    "sg:classifiers":[
        {
            "category":"Professional",
            "subcategory":"Engineering",
            "type":"Services"
        }
    ],
    "sg:phone":"+1 410 822 1441",
    "sg:postcode":"21601",
    "sg:province":"MD",
    "sg:tags":[
        "engineer"
    ],
    "sg:website":"www.axisgeospatial.com",
    "wof:name":"Axis Geospatial",
    "wof:placetype":"venue"
},
  "geometry": {"coordinates":[-76.083305,38.788245],"type":"Point"}
}