{
  "type": "Feature",
  "properties": {
    "addr:full":"1200 W Old Liberty Rd Sykesville MD 21784",
    "addr:housenumber":"1200",
    "addr:postcode":"21784",
    "addr:street":"W Old Liberty Rd",
    "iso:country":"US",
    "sg:address":"1200 W Old Liberty Rd",
    "sg:city":"Sykesville",
    "sg:classifiers":[
        {
            "category":"Health Services",
            "subcategory":"Doctor",
            "type":"Services"
        }
    ],
    "sg:phone":"+1 410 795 8833",
    "sg:postcode":"21784",
    "sg:province":"MD",
    "sg:tags":[
        "dentist"
    ],
    "wof:name":"Winfield Medical Ctr",
    "wof:placetype":"venue"
},
  "geometry": {"coordinates":[-77.044543,39.443053],"type":"Point"}
}