{
  "type": "Feature",
  "properties": {
    "addr:full":"6644 Security Blvd Gwynn Oak MD 21207",
    "addr:housenumber":"6644",
    "addr:postcode":"21207",
    "addr:street":"Security Blvd",
    "iso:country":"US",
    "sg:address":"6644 Security Blvd",
    "sg:city":"Gwynn Oak",
    "sg:classifiers":[
        {
            "category":"Shopping",
            "subcategory":"Department Store",
            "type":"Retail Goods"
        }
    ],
    "sg:phone":"+1 410 298 0180",
    "sg:postcode":"21207",
    "sg:province":"MD",
    "sg:tags":[
        "vintage",
        "used",
        "consignment"
    ],
    "sg:website":"www.aj-wright.com",
    "wof:name":"A J Wright",
    "wof:placetype":"venue"
},
  "geometry": {"coordinates":[-76.737602,39.312302],"type":"Point"}
}