{
  "type": "Feature",
  "properties": {
    "addr:full":"4260 Drake Ct Waldorf MD 20603",
    "addr:housenumber":"4260",
    "addr:postcode":"20603",
    "addr:street":"Drake Ct",
    "iso:country":"US",
    "sg:address":"4260 Drake Ct",
    "sg:city":"Waldorf",
    "sg:classifiers":[
        {
            "category":"Arts & Performance",
            "subcategory":"Theater",
            "type":"Entertainment"
        }
    ],
    "sg:phone":"+1 301 870 7776",
    "sg:postcode":"20603",
    "sg:province":"MD",
    "sg:tags":[
        "group"
    ],
    "wof:name":"H Ingles",
    "wof:placetype":"venue"
},
  "geometry": {"coordinates":[-76.930729,38.625352],"type":"Point"}
}