{
  "type": "Feature",
  "properties": {
    "iso:country":"US",
    "sg:address":"3436 Frederick Ave",
    "sg:city":"Baltimore",
    "sg:classifiers":[
        {
            "category":"Restaurant",
            "type":"Food & Drink"
        }
    ],
    "sg:phone":"+1 410 945 1011",
    "sg:postcode":"21229",
    "sg:province":"MD",
    "sg:website":"http://www.newduffysrestaurant.com/",
    "wof:name":"Duffy's Restaurant",
    "wof:placetype":"venue"
},
  "geometry": {"coordinates":[-76.674301,39.281399],"type":"Point"}
}