{
  "type": "Feature",
  "properties": {
    "iso:country":"US",
    "sg:address":"234 S Broadway",
    "sg:city":"Baltimore",
    "sg:classifiers":[
        {
            "category":"Health Services",
            "subcategory":"Nursing And Care Facility",
            "type":"Services"
        }
    ],
    "sg:phone":"+1 410 675 4704",
    "sg:postcode":"21231",
    "sg:province":"MD",
    "sg:tags":[
        "blind",
        "vision",
        "impaired"
    ],
    "wof:name":"Alliance, Incorporated",
    "wof:placetype":"venue"
},
  "geometry": {"coordinates":[-76.593762,39.288664],"type":"Point"}
}