{
  "type": "Feature",
  "properties": {
    "addr:full":"3090 Mayberry Ave Huntingtown MD 20639",
    "addr:housenumber":"3090",
    "addr:postcode":"20639",
    "addr:street":"Mayberry Ave",
    "iso:country":"US",
    "sg:address":"3090 Mayberry Ave",
    "sg:city":"Huntingtown",
    "sg:classifiers":[
        {
            "category":"Banks & Credit Unions",
            "subcategory":"Financial Services",
            "type":"Services"
        }
    ],
    "sg:phone":"+1 410 535 2746",
    "sg:postcode":"20639",
    "sg:province":"MD",
    "sg:tags":[
        "trust",
        "nonprofit",
        "management"
    ],
    "wof:name":"Doran Family Foundation Inc",
    "wof:placetype":"venue"
},
  "geometry": {"coordinates":[-76.60061399999999,38.609021],"type":"Point"}
}