{
  "type": "Feature",
  "properties": {
    "iso:country":"US",
    "sg:address":"413 Crain Hwy S",
    "sg:city":"Glen Burnie",
    "sg:classifiers":[
        {
            "category":"Building & Trades",
            "subcategory":"Construction",
            "type":"Services"
        }
    ],
    "sg:phone":"+1 410 590 0247",
    "sg:postcode":"21061",
    "sg:province":"MD",
    "sg:tags":[
        "general",
        "contractor"
    ],
    "wof:name":"Van Zant Group",
    "wof:placetype":"venue"
},
  "geometry": {"coordinates":[-76.629007,39.157643],"type":"Point"}
}