{
  "type": "Feature",
  "properties": {
    "iso:country":"US",
    "sg:address":"5501 Oakbrook Pl",
    "sg:city":"Lanham",
    "sg:classifiers":[
        {
            "category":"Retail",
            "subcategory":"Auto Repair",
            "type":"Services"
        }
    ],
    "sg:phone":"+1 301 459 2391",
    "sg:postcode":"20706",
    "sg:province":"MD",
    "wof:name":"Platinum Auto Care",
    "wof:placetype":"venue"
},
  "geometry": {"coordinates":[-76.836449,38.964722],"type":"Point"}
}