{
  "type": "Feature",
  "properties": {
    "iso:country":"US",
    "sg:address":"224 Washburn Ave",
    "sg:city":"Baltimore",
    "sg:classifiers":[
        {
            "category":"Organizations",
            "subcategory":"Religious Organization",
            "type":"Services"
        }
    ],
    "sg:phone":"+1 410 355 7295",
    "sg:postcode":"21225",
    "sg:province":"MD",
    "wof:name":"St Johns Lutheran Church",
    "wof:placetype":"venue"
},
  "geometry": {"coordinates":[-76.60822,39.236047],"type":"Point"}
}