{
  "type": "Feature",
  "properties": {
    "iso:country":"US",
    "sg:address":"16047 Comprint Cir",
    "sg:city":"Gaithersburg",
    "sg:classifiers":[
        {
            "category":"Banks & Credit Unions",
            "subcategory":"Investment Brokerage",
            "type":"Services"
        }
    ],
    "sg:phone":"+1 301 948 7872",
    "sg:postcode":"20877",
    "sg:province":"MD",
    "sg:tags":[
        "security"
    ],
    "wof:name":"Target Investment Svc Inc",
    "wof:placetype":"venue"
},
  "geometry": {"coordinates":[-77.184601,39.120153],"type":"Point"}
}