{
  "type": "Feature",
  "properties": {
    "addr:full":"5736 Spring St Clinton MD 20735",
    "addr:housenumber":"5736",
    "addr:postcode":"20735",
    "addr:street":"Spring St",
    "iso:country":"US",
    "sg:address":"5736 Spring St",
    "sg:city":"Clinton",
    "sg:classifiers":[
        {
            "category":"Building & Trades",
            "subcategory":"Construction",
            "type":"Services"
        }
    ],
    "sg:phone":"+1 301 297 4759",
    "sg:postcode":"20735",
    "sg:province":"MD",
    "sg:tags":[
        "home",
        "improvement"
    ],
    "wof:name":"Apollo Construction Inc",
    "wof:placetype":"venue"
},
  "geometry": {"coordinates":[-76.909646,38.784658],"type":"Point"}
}