{
  "type": "Feature",
  "properties": {
    "iso:country":"US",
    "sg:address":"19 Midway Ave",
    "sg:city":"Baltimore",
    "sg:classifiers":[
        {
            "category":"Building & Trades",
            "subcategory":"Construction",
            "type":"Services"
        }
    ],
    "sg:phone":"+1 410 285 1134",
    "sg:postcode":"21222",
    "sg:province":"MD",
    "sg:tags":[
        "roofing",
        "contractor"
    ],
    "wof:name":"A & B Roofing Co",
    "wof:placetype":"venue"
},
  "geometry": {"coordinates":[-76.481387,39.262046],"type":"Point"}
}