{
  "type": "Feature",
  "properties": {
    "iso:country":"US",
    "sg:address":"100 E Pennsylvania Ave",
    "sg:city":"Towson",
    "sg:classifiers":[
        {
            "category":"Health Services",
            "subcategory":"Health Practitioner",
            "type":"Services"
        },
        {
            "category":"Communications",
            "type":"Services"
        }
    ],
    "sg:phone":"+1 410 825 9445",
    "sg:postcode":"21286",
    "sg:province":"MD",
    "sg:tags":[
        "pathologist",
        "speech-language",
        "audiologists",
        "therapy",
        "myofunctional"
    ],
    "sg:website":"http://www.aslsinc.com",
    "wof:name":"Associated Speech And Language Services Inc",
    "wof:placetype":"venue"
},
  "geometry": {"coordinates":[-76.601158,39.40033],"type":"Point"}
}