{
  "type": "Feature",
  "properties": {
    "iso:country":"US",
    "sg:address":"6431 Washington Ave",
    "sg:city":"Glen Burnie",
    "sg:classifiers":[
        {
            "category":"Communications",
            "subcategory":"Film & Video Production",
            "type":"Services"
        }
    ],
    "sg:phone":"+1 410 789 2457",
    "sg:postcode":"21060",
    "sg:province":"MD",
    "sg:tags":[
        "motion"
    ],
    "wof:name":"Artistic Video Production",
    "wof:placetype":"venue"
},
  "geometry": {"coordinates":[-76.604648,39.200259],"type":"Point"}
}