{
  "type": "Feature",
  "properties": {
    "addr:full":"460 Garrison Forest Rd Owings Mills MD 21117",
    "addr:housenumber":"460",
    "addr:postcode":"21117",
    "addr:street":"Garrison Forest Rd",
    "iso:country":"US",
    "sg:address":"460 Garrison Forest Rd",
    "sg:city":"Owings Mills",
    "sg:classifiers":[
        {
            "category":"Insurance",
            "subcategory":"Insurance Agent",
            "type":"Services"
        }
    ],
    "sg:phone":"+1 410 363 1391",
    "sg:postcode":"21117",
    "sg:province":"MD",
    "wof:name":"Francis X Wells",
    "wof:placetype":"venue"
},
  "geometry": {"coordinates":[-76.757738,39.41476],"type":"Point"}
}