{
  "type": "Feature",
  "properties": {
    "addr:full":"9720 Greenside Dr Cockysvl Hnt Vly MD 21030",
    "addr:housenumber":"9720",
    "addr:postcode":"21030",
    "addr:street":"Greenside Dr;Hnt Vly",
    "iso:country":"US",
    "sg:address":"9720 Greenside Dr",
    "sg:city":"Cockysvl Hnt Vly",
    "sg:classifiers":[
        {
            "category":"Shopping",
            "subcategory":"Computers & Home Electronics",
            "type":"Retail Goods"
        }
    ],
    "sg:phone":"+1 410 667 1224",
    "sg:postcode":"21030",
    "sg:province":"MD",
    "sg:tags":[
        "software"
    ],
    "wof:name":"Innovative Computer Solutions",
    "wof:placetype":"venue"
},
  "geometry": {"coordinates":[-76.62991700000001,39.45776],"type":"Point"}
}