{
  "type": "Feature",
  "properties": {
    "addr:full":"9525 Durness Ln Laurel MD 20723",
    "addr:housenumber":"9525",
    "addr:postcode":"20723",
    "addr:street":"Durness Ln",
    "iso:country":"US",
    "sg:address":"9525 Durness Ln",
    "sg:city":"Laurel",
    "sg:classifiers":[
        {
            "category":"Education",
            "subcategory":"Library",
            "type":"Public Place"
        }
    ],
    "sg:phone":"+1 410 880 5980",
    "sg:postcode":"20723",
    "sg:province":"MD",
    "wof:name":"Howard County Libraries",
    "wof:placetype":"venue"
},
  "geometry": {"coordinates":[-76.83580000000001,39.132],"type":"Point"}
}