{
  "type": "Feature",
  "properties": {
    "iso:country":"US",
    "sg:address":"5202 Newton St",
    "sg:city":"Bladensburg",
    "sg:classifiers":[
        {
            "category":"Social Services",
            "subcategory":"Child Care",
            "type":"Services"
        }
    ],
    "sg:phone":"+1 301 927 1568",
    "sg:postcode":"20710",
    "sg:province":"MD",
    "sg:tags":[
        "day"
    ],
    "wof:name":"Iboko Patience",
    "wof:placetype":"venue"
},
  "geometry": {"coordinates":[-76.92949,38.936238],"type":"Point"}
}