{
  "type": "Feature",
  "properties": {
    "addr:full":"1412 York Rd Lutherville MD 21093",
    "addr:housenumber":"1412",
    "addr:postcode":"21093",
    "addr:street":"York Rd",
    "iso:country":"US",
    "sg:address":"1412 York Rd",
    "sg:city":"Lutherville",
    "sg:classifiers":[
        {
            "category":"Retail",
            "subcategory":"Auto Repair",
            "type":"Services"
        }
    ],
    "sg:phone":"+1 410 321 9140",
    "sg:postcode":"21093",
    "sg:province":"MD",
    "sg:tags":[
        "repairing",
        "automobile"
    ],
    "wof:name":"Lutherville Car Care",
    "wof:placetype":"venue"
},
  "geometry": {"coordinates":[-76.616687,39.420421],"type":"Point"}
}