{
  "type": "Feature",
  "properties": {
    "addr:full":"2107 Laurel Bush Rd Bel Air MD 21015",
    "addr:housenumber":"2107",
    "addr:postcode":"21015",
    "addr:street":"Laurel Bush Rd",
    "iso:country":"US",
    "sg:address":"2107 Laurel Bush Rd",
    "sg:city":"Bel Air",
    "sg:classifiers":[
        {
            "category":"Professional",
            "subcategory":"Business Services",
            "type":"Services"
        }
    ],
    "sg:phone":"+1 410 420 7152",
    "sg:postcode":"21015",
    "sg:province":"MD",
    "sg:tags":[
        "aerial",
        "photographic",
        "mapping"
    ],
    "wof:name":"Map Factory",
    "wof:placetype":"venue"
},
  "geometry": {"coordinates":[-76.324275,39.498069],"type":"Point"}
}