{
  "type": "Feature",
  "properties": {
    "addr:full":"785 Solomons Island Rd N Prince Frederick MD 20678",
    "addr:housenumber":"785",
    "addr:postcode":"20678",
    "addr:street":"Solomons Island Rd N",
    "iso:country":"US",
    "sg:address":"785 Solomons Island Rd N",
    "sg:city":"Prince Frederick",
    "sg:classifiers":[
        {
            "category":"Health Services",
            "subcategory":"Optometrist",
            "type":"Services"
        }
    ],
    "sg:phone":"+1 410 535 6333",
    "sg:postcode":"20678",
    "sg:province":"MD",
    "wof:name":"Eye Care Ctr",
    "wof:placetype":"venue"
},
  "geometry": {"coordinates":[-76.595129,38.554268],"type":"Point"}
}