{
  "type": "Feature",
  "properties": {
    "iso:country":"US",
    "sg:address":"11606 Bonaventure Dr",
    "sg:city":"Upper Marlboro",
    "sg:classifiers":[
        {
            "category":"Building & Trades",
            "subcategory":"Construction",
            "type":"Services"
        }
    ],
    "sg:phone":"+1 301 390 7061",
    "sg:postcode":"20774",
    "sg:province":"MD",
    "sg:tags":[
        "house"
    ],
    "wof:name":"Gdm Construction",
    "wof:placetype":"venue"
},
  "geometry": {"coordinates":[-76.716371,38.889839],"type":"Point"}
}