{
  "type": "Feature",
  "properties": {
    "iso:country":"US",
    "sg:address":"33 E Patrick St",
    "sg:city":"Frederick",
    "sg:classifiers":[
        {
            "category":"Retail",
            "subcategory":"Repair Shop",
            "type":"Services"
        }
    ],
    "sg:phone":"+1 301 695 6110",
    "sg:postcode":"21701",
    "sg:province":"MD",
    "sg:tags":[
        "lock",
        "locksmith"
    ],
    "wof:name":"D & D Safe & Locks",
    "wof:placetype":"venue"
},
  "geometry": {"coordinates":[-77.410421,39.414226],"type":"Point"}
}