{
  "type": "Feature",
  "properties": {
    "iso:country":"US",
    "sg:address":"678 Lofstrand Ln",
    "sg:city":"Rockville",
    "sg:classifiers":[
        {
            "category":"Manufacturing",
            "subcategory":"Rubber & Plastics",
            "type":"Manufacturing & Wholesale Goods"
        }
    ],
    "sg:phone":"+1 301 762 9261",
    "sg:postcode":"20850",
    "sg:province":"MD",
    "sg:tags":[
        "forming"
    ],
    "sg:website":"www.unipec.net",
    "wof:name":"Universal Plastics Engineering",
    "wof:placetype":"venue"
},
  "geometry": {"coordinates":[-77.137984,39.096559],"type":"Point"}
}