{
  "type": "Feature",
  "properties": {
    "addr:full":"14656 Peddicord Rd Mount Airy MD 21771",
    "addr:postcode":"14656;21771",
    "addr:street":"Peddicord Rd",
    "iso:country":"US",
    "sg:address":"14656 Peddicord Rd",
    "sg:city":"Mount Airy",
    "sg:classifiers":[
        {
            "category":"Building & Trades",
            "subcategory":"Construction",
            "type":"Services"
        }
    ],
    "sg:phone":"+1 301 831 7026",
    "sg:postcode":"21771",
    "sg:province":"MD",
    "sg:tags":[
        "house",
        "hanging"
    ],
    "wof:name":"Robert Elam",
    "wof:placetype":"venue"
},
  "geometry": {"coordinates":[-77.148635,39.437052],"type":"Point"}
}