{
  "type": "Feature",
  "properties": {
    "addr:full":"1911 Haverhill Rd Parkville MD 21234",
    "addr:housenumber":"1911",
    "addr:postcode":"21234",
    "addr:street":"Haverhill Rd",
    "iso:country":"US",
    "sg:address":"1911 Haverhill Rd",
    "sg:city":"Parkville",
    "sg:classifiers":[
        {
            "category":"Professional",
            "subcategory":"Advertising",
            "type":"Services"
        }
    ],
    "sg:phone":"+1 410 665 0653",
    "sg:postcode":"21234",
    "sg:province":"MD",
    "sg:tags":[
        "promotion",
        "sale"
    ],
    "wof:name":"B & B Promotions Inc",
    "wof:placetype":"venue"
},
  "geometry": {"coordinates":[-76.554883,39.405599],"type":"Point"}
}