{
  "type": "Feature",
  "properties": {
    "iso:country":"US",
    "sg:address":"4951 Prince Georges Ave",
    "sg:city":"Beltsville",
    "sg:classifiers":[
        {
            "category":"Personal",
            "subcategory":"Barber",
            "type":"Services"
        }
    ],
    "sg:phone":"+1 301 937 8771",
    "sg:postcode":"20705",
    "sg:province":"MD",
    "wof:name":"Sam's Barber Shop",
    "wof:placetype":"venue"
},
  "geometry": {"coordinates":[-76.906097,39.0368],"type":"Point"}
}