{
  "type": "Feature",
  "properties": {
    "iso:country":"US",
    "sg:address":"11326 Donner Ct",
    "sg:city":"Lusby",
    "sg:classifiers":[
        {
            "category":"Professional",
            "subcategory":"Business Services",
            "type":"Services"
        }
    ],
    "sg:phone":"+1 410 326 9388",
    "sg:postcode":"20657",
    "sg:province":"MD",
    "sg:tags":[
        "inspection"
    ],
    "wof:name":"Statewide Inspection Inc",
    "wof:placetype":"venue"
},
  "geometry": {"coordinates":[-76.406711,38.38165],"type":"Point"}
}