{
  "type": "Feature",
  "properties": {
    "addr:full":"9 N Point Ter Baltimore MD 21222",
    "addr:housenumber":"9",
    "addr:postcode":"21222",
    "addr:street":"N Point Ter",
    "iso:country":"US",
    "sg:address":"9 N Point Ter",
    "sg:city":"Baltimore",
    "sg:classifiers":[
        {
            "category":"Retail",
            "subcategory":"Auto Repair",
            "type":"Services"
        }
    ],
    "sg:phone":"+1 410 284 1005",
    "sg:postcode":"21222",
    "sg:province":"MD",
    "sg:tags":[
        "transmission"
    ],
    "wof:name":"Rose's Transmissions",
    "wof:placetype":"venue"
},
  "geometry": {"coordinates":[-76.488446,39.280341],"type":"Point"}
}