{
  "type": "Feature",
  "properties": {
    "addr:full":"125 W Washington St Hagerstown MD 21740",
    "addr:housenumber":"125",
    "addr:postcode":"21740",
    "addr:street":"W Washington St",
    "iso:country":"US",
    "sg:address":"125 W Washington St",
    "sg:city":"Hagerstown",
    "sg:classifiers":[
        {
            "category":"Professional",
            "type":"Services"
        }
    ],
    "sg:phone":"+1 301 733 6676",
    "sg:postcode":"21740",
    "sg:province":"MD",
    "sg:tags":[
        "establishment"
    ],
    "wof:name":"Soul Haven",
    "wof:placetype":"venue"
},
  "geometry": {"coordinates":[-77.72396500000001,39.643683],"type":"Point"}
}