{
  "type": "Feature",
  "properties": {
    "iso:country":"US",
    "sg:address":"664 Pine Dr",
    "sg:city":"Pasadena",
    "sg:classifiers":[
        {
            "category":"Manufacturing",
            "subcategory":"Food",
            "type":"Manufacturing & Wholesale Goods"
        }
    ],
    "sg:phone":"+1 410 317 5434",
    "sg:postcode":"21122",
    "sg:province":"MD",
    "sg:tags":[
        "product"
    ],
    "wof:name":"Timothy & Denise L Estell",
    "wof:placetype":"venue"
},
  "geometry": {"coordinates":[-76.519552,39.103133],"type":"Point"}
}