{
  "type": "Feature",
  "properties": {
    "iso:country":"US",
    "sg:address":"6100 Pimlico Rd",
    "sg:city":"Baltimore",
    "sg:classifiers":[
        {
            "category":"Health Services",
            "subcategory":"Health Practitioner",
            "type":"Services"
        }
    ],
    "sg:phone":"+1 410 358 0287",
    "sg:postcode":"21209",
    "sg:province":"MD",
    "sg:tags":[
        "therapy",
        "physical"
    ],
    "wof:name":"People Encouraging",
    "wof:placetype":"venue"
},
  "geometry": {"coordinates":[-76.67600299999999,39.367591],"type":"Point"}
}