{
  "type": "Feature",
  "properties": {
    "addr:full":"130 Hearne Rd Annapolis MD 21401",
    "addr:housenumber":"130",
    "addr:postcode":"21401",
    "addr:street":"Hearne Rd",
    "iso:country":"US",
    "sg:address":"130 Hearne Rd",
    "sg:city":"Annapolis",
    "sg:classifiers":[
        {
            "category":"Real Estate",
            "subcategory":"Real Estate Operator",
            "type":"Services"
        }
    ],
    "sg:phone":"+1 410 266 5730",
    "sg:postcode":"21401",
    "sg:province":"MD",
    "sg:tags":[
        "apartment"
    ],
    "wof:name":"Claiborne Place Apartments",
    "wof:placetype":"venue"
},
  "geometry": {"coordinates":[-76.545982,38.979676],"type":"Point"}
}