{
  "type": "Feature",
  "properties": {
    "addr:full":"6506 41st Ave Hyattsville MD 20782",
    "addr:housenumber":"6506",
    "addr:postcode":"20782",
    "addr:street":"41St Ave",
    "iso:country":"US",
    "sg:address":"6506 41st Ave",
    "sg:city":"Hyattsville",
    "sg:classifiers":[
        {
            "category":"Communications",
            "subcategory":"Film & Video Production",
            "type":"Services"
        }
    ],
    "sg:phone":"+1 301 927 7788",
    "sg:postcode":"20782",
    "sg:province":"MD",
    "sg:tags":[
        "motion",
        "picture"
    ],
    "wof:name":"Media Northeast Location Sound",
    "wof:placetype":"venue"
},
  "geometry": {"coordinates":[-76.948436,38.965681],"type":"Point"}
}