{
  "type": "Feature",
  "properties": {
    "addr:full":"8057 Cryden Way Forestville MD 20747",
    "addr:housenumber":"8057",
    "addr:postcode":"20747",
    "addr:street":"Cryden Way",
    "iso:country":"US",
    "sg:address":"8057 Cryden Way",
    "sg:city":"Forestville",
    "sg:classifiers":[
        {
            "category":"Building & Trades",
            "subcategory":"Pest Control",
            "type":"Services"
        }
    ],
    "sg:phone":"+1 301 967 2127",
    "sg:postcode":"20747",
    "sg:province":"MD",
    "wof:name":"R & T Pest Control Svc",
    "wof:placetype":"venue"
},
  "geometry": {"coordinates":[-76.86921700000001,38.84772],"type":"Point"}
}