{
  "type": "Feature",
  "properties": {
    "addr:full":"1524 Puffin Ct Pasadena MD 21122",
    "addr:housenumber":"1524",
    "addr:postcode":"21122",
    "addr:street":"Puffin Ct",
    "iso:country":"US",
    "sg:address":"1524 Puffin Ct",
    "sg:city":"Pasadena",
    "sg:classifiers":[
        {
            "category":"Manufacturing",
            "subcategory":"Printing",
            "type":"Manufacturing & Wholesale Goods"
        }
    ],
    "sg:phone":"+1 410 437 2500",
    "sg:postcode":"21122",
    "sg:province":"MD",
    "sg:tags":[
        "printer"
    ],
    "wof:name":"KNT Printing",
    "wof:placetype":"venue"
},
  "geometry": {"coordinates":[-76.458105,39.102474],"type":"Point"}
}