{
  "type": "Feature",
  "properties": {
    "iso:country":"US",
    "sg:address":"4173 Patterson Ave",
    "sg:city":"Baltimore",
    "sg:classifiers":[
        {
            "category":"Health Services",
            "subcategory":"Dentist",
            "type":"Services"
        }
    ],
    "sg:phone":"+1 443 743 2100",
    "sg:postcode":"21215",
    "sg:province":"MD",
    "sg:tags":[
        "pediatric"
    ],
    "wof:name":"Kool Smiles",
    "wof:placetype":"venue"
},
  "geometry": {"coordinates":[-76.704972,39.353826],"type":"Point"}
}