{
  "type": "Feature",
  "properties": {
    "iso:country":"US",
    "sg:address":"5905 Rose Ct",
    "sg:city":"St Leonard",
    "sg:classifiers":[
        {
            "category":"Building & Trades",
            "subcategory":"Construction",
            "type":"Services"
        }
    ],
    "sg:phone":"+1 410 414 8273",
    "sg:postcode":"20685",
    "sg:province":"MD",
    "sg:tags":[
        "home",
        "builder"
    ],
    "wof:name":"David Gilbert Construction Inc",
    "wof:placetype":"venue"
},
  "geometry": {"coordinates":[-76.550093,38.455358],"type":"Point"}
}