{
  "type": "Feature",
  "properties": {
    "addr:full":"2305 Foster Ave Baltimore MD 21224",
    "addr:housenumber":"2305",
    "addr:postcode":"21224",
    "addr:street":"Foster Ave",
    "iso:country":"US",
    "sg:address":"2305 Foster Ave",
    "sg:city":"Baltimore",
    "sg:classifiers":[
        {
            "category":"Health Services",
            "subcategory":"Hospital",
            "type":"Services"
        }
    ],
    "sg:phone":"+1 443 725 4059",
    "sg:postcode":"21224",
    "sg:province":"MD",
    "wof:name":"Critical Care Professionals Inc.",
    "wof:placetype":"venue"
},
  "geometry": {"coordinates":[-76.583412,39.283803],"type":"Point"}
}