{
  "type": "Feature",
  "properties": {
    "addr:full":"11145 Veirs Mill Rd Silver Spring MD 20902",
    "addr:housenumber":"11145",
    "addr:postcode":"20902",
    "addr:street":"Veirs Mill Rd",
    "iso:country":"US",
    "sg:address":"11145 Veirs Mill Rd",
    "sg:city":"Silver Spring",
    "sg:classifiers":[
        {
            "category":"Retail",
            "subcategory":"Repair Shop",
            "type":"Services"
        }
    ],
    "sg:phone":"+1 301 929 2490",
    "sg:postcode":"20902",
    "sg:province":"MD",
    "sg:tags":[
        "instrument",
        "musical"
    ],
    "wof:name":"Protech",
    "wof:placetype":"venue"
},
  "geometry": {"coordinates":[-77.053163,39.038749],"type":"Point"}
}