{
  "type": "Feature",
  "properties": {
    "addr:full":"11419 Cronridge Dr Owings Mills MD 21117",
    "addr:housenumber":"11419",
    "addr:postcode":"21117",
    "addr:street":"Cronridge Dr",
    "iso:country":"US",
    "sg:address":"11419 Cronridge Dr",
    "sg:city":"Owings Mills",
    "sg:classifiers":[
        {
            "category":"Retail",
            "subcategory":"Portrait Studio",
            "type":"Services"
        }
    ],
    "sg:phone":"+1 410 902 5779",
    "sg:postcode":"21117",
    "sg:province":"MD",
    "sg:tags":[
        "photographer",
        "imaging"
    ],
    "wof:name":"Events In A Flash",
    "wof:placetype":"venue"
},
  "geometry": {"coordinates":[-76.776033,39.440444],"type":"Point"}
}