{
  "type": "Feature",
  "properties": {
    "iso:country":"US",
    "sg:address":"4715 Erdman Ave",
    "sg:city":"Baltimore",
    "sg:classifiers":[
        {
            "category":"Autos & Motor Vehicles",
            "subcategory":"Auto Supplies",
            "type":"Retail Goods"
        }
    ],
    "sg:phone":"+1 410 276 9458",
    "sg:postcode":"21205",
    "sg:province":"MD",
    "sg:tags":[
        "automobile",
        "parts"
    ],
    "wof:name":"Nationwide Auto Parts Co",
    "wof:placetype":"venue"
},
  "geometry": {"coordinates":[-76.56060100000001,39.307812],"type":"Point"}
}