{
  "type": "Feature",
  "properties": {
    "addr:full":"701 Wilson Point Rd Baltimore MD 21220",
    "addr:housenumber":"701",
    "addr:postcode":"21220",
    "addr:street":"Wilson Point Rd",
    "iso:country":"US",
    "sg:address":"701 Wilson Point Rd",
    "sg:city":"Baltimore",
    "sg:classifiers":[
        {
            "category":"Manufacturing",
            "subcategory":"Rubber & Plastics",
            "type":"Manufacturing & Wholesale Goods"
        }
    ],
    "sg:phone":"+1 410 574 5500",
    "sg:postcode":"21220",
    "sg:province":"MD",
    "wof:name":"C & J Decorative Plastics Inc",
    "wof:placetype":"venue"
},
  "geometry": {"coordinates":[-76.427471,39.331697],"type":"Point"}
}