{
  "type": "Feature",
  "properties": {
    "iso:country":"US",
    "sg:address":"1637 N Washington St",
    "sg:city":"Baltimore",
    "sg:classifiers":[
        {
            "category":"Wholesale",
            "subcategory":"Office Equipment",
            "type":"Manufacturing & Wholesale Goods"
        }
    ],
    "sg:phone":"+1 410 710 9728",
    "sg:postcode":"21213",
    "sg:province":"MD",
    "sg:tags":[
        "equipment-installation",
        "furniture"
    ],
    "wof:name":"Steve Leonard Martin",
    "wof:placetype":"venue"
},
  "geometry": {"coordinates":[-76.590225,39.309098],"type":"Point"}
}