{
  "type": "Feature",
  "properties": {
    "iso:country":"US",
    "sg:address":"1801 Long Corner Rd",
    "sg:city":"Mount Airy",
    "sg:classifiers":[
        {
            "category":"Professional",
            "subcategory":"Business Services",
            "type":"Services"
        }
    ],
    "sg:phone":"+1 301 831 5963",
    "sg:postcode":"21771",
    "sg:province":"MD",
    "wof:name":"Stone Assoc",
    "wof:placetype":"venue"
},
  "geometry": {"coordinates":[-77.156907,39.322279],"type":"Point"}
}