{
  "type": "Feature",
  "properties": {
    "addr:full":"818 Appleton St Baltimore MD 21217",
    "addr:housenumber":"818",
    "addr:postcode":"21217",
    "addr:street":"Appleton St",
    "iso:country":"US",
    "sg:address":"818 Appleton St",
    "sg:city":"Baltimore",
    "sg:classifiers":[
        {
            "category":"Social Services",
            "subcategory":"Child Care",
            "type":"Services"
        }
    ],
    "sg:phone":"+1 410 728 0050",
    "sg:postcode":"21217",
    "sg:province":"MD",
    "sg:tags":[
        "nursery",
        "day"
    ],
    "wof:name":"Tiny Angels",
    "wof:placetype":"venue"
},
  "geometry": {"coordinates":[-76.64830499999999,39.297736],"type":"Point"}
}