{
  "type": "Feature",
  "properties": {
    "addr:full":"4739 Bucktown Rd Cambridge MD 21613",
    "addr:postcode":"4739;21613",
    "addr:street":"Bucktown Rd",
    "iso:country":"US",
    "sg:address":"4739 Bucktown Rd",
    "sg:city":"Cambridge",
    "sg:classifiers":[
        {
            "category":"Home & Garden",
            "subcategory":"Household Appliances",
            "type":"Retail Goods"
        }
    ],
    "sg:phone":"+1 410 822 5059",
    "sg:postcode":"21613",
    "sg:province":"MD",
    "sg:tags":[
        "machine",
        "major",
        "dishwashing"
    ],
    "wof:name":"Reliable Appliance",
    "wof:placetype":"venue"
},
  "geometry": {"coordinates":[-76.014236,38.500401],"type":"Point"}
}