{
  "type": "Feature",
  "properties": {
    "addr:full":"14100 Darnestown Rd Germantown MD 20874",
    "addr:housenumber":"14100",
    "addr:postcode":"20874",
    "addr:street":"Darnestown Rd",
    "iso:country":"US",
    "sg:address":"14100 Darnestown Rd",
    "sg:city":"Germantown",
    "sg:classifiers":[
        {
            "category":"Real Estate",
            "subcategory":"Real Estate Agent",
            "type":"Services"
        }
    ],
    "sg:phone":"+1 301 417 1051",
    "sg:postcode":"20874",
    "sg:province":"MD",
    "wof:name":"Michael Fox Realty",
    "wof:placetype":"venue"
},
  "geometry": {"coordinates":[-77.29177,39.103263],"type":"Point"}
}