{
  "type": "Feature",
  "properties": {
    "iso:country":"US",
    "sg:address":"7705 Harford Rd",
    "sg:city":"Parkville",
    "sg:classifiers":[
        {
            "category":"Food & Beverages",
            "subcategory":"Liquor & Beverages",
            "type":"Retail Goods"
        }
    ],
    "sg:phone":"+1 410 661 7922",
    "sg:postcode":"21234",
    "sg:province":"MD",
    "sg:tags":[
        "lounge",
        "cocktail"
    ],
    "sg:website":"http://www.beveragedepot.com",
    "wof:name":"Beverage Depot",
    "wof:placetype":"venue"
},
  "geometry": {"coordinates":[-76.54383300000001,39.372611],"type":"Point"}
}