{
  "type": "Feature",
  "properties": {
    "addr:full":"7938 Eastern Ave Baltimore MD 21224",
    "addr:housenumber":"7938",
    "addr:postcode":"21224",
    "addr:street":"Eastern Ave",
    "iso:country":"US",
    "sg:address":"7938 Eastern Ave",
    "sg:city":"Baltimore",
    "sg:classifiers":[
        {
            "category":"Cinema",
            "subcategory":"Movie Theater",
            "type":"Entertainment"
        }
    ],
    "sg:phone":"+1 410 284 3106",
    "sg:postcode":"21224",
    "sg:province":"MD",
    "sg:website":"http://boxoffice.printtixusa.com",
    "wof:name":"East Point Movies 10",
    "wof:placetype":"venue"
},
  "geometry": {"coordinates":[-76.507986,39.296038],"type":"Point"}
}