{
  "type": "Feature",
  "properties": {
    "addr:full":"10712 Tuckahoe Way Gaithersburg MD 20878",
    "addr:housenumber":"10712",
    "addr:postcode":"20878",
    "addr:street":"Tuckahoe Way",
    "iso:country":"US",
    "sg:address":"10712 Tuckahoe Way",
    "sg:city":"Gaithersburg",
    "sg:classifiers":[
        {
            "category":"Manufacturing",
            "subcategory":"Printing",
            "type":"Manufacturing & Wholesale Goods"
        }
    ],
    "sg:phone":"+1 301 340 1735",
    "sg:postcode":"20878",
    "sg:province":"MD",
    "sg:tags":[
        "lithographic",
        "commercial"
    ],
    "wof:name":"Leflar Kim",
    "wof:placetype":"venue"
},
  "geometry": {"coordinates":[-77.220423,39.096097],"type":"Point"}
}