{
  "type": "Feature",
  "properties": {
    "addr:full":"1606 Junius Ct Bel Air MD 21015",
    "addr:housenumber":"1606",
    "addr:postcode":"21015",
    "addr:street":"Junius Ct",
    "iso:country":"US",
    "sg:address":"1606 Junius Ct",
    "sg:city":"Bel Air",
    "sg:classifiers":[
        {
            "category":"Home & Garden",
            "subcategory":"Building Materials",
            "type":"Retail Goods"
        }
    ],
    "sg:phone":"+1 410 638 7611",
    "sg:postcode":"21015",
    "sg:province":"MD",
    "wof:name":"Clear Lake Lumber Inc",
    "wof:placetype":"venue"
},
  "geometry": {"coordinates":[-76.323469,39.554775],"type":"Point"}
}