{
  "type": "Feature",
  "properties": {
    "iso:country":"US",
    "sg:address":"2355 Davidsonville Rd",
    "sg:city":"Gambrills",
    "sg:classifiers":[
        {
            "category":"Health Services",
            "subcategory":"Health Practitioner",
            "type":"Services"
        }
    ],
    "sg:phone":"+1 410 721 4356",
    "sg:postcode":"21054",
    "sg:province":"MD",
    "sg:tags":[
        "acupuncture"
    ],
    "wof:name":"Acupuncture & Qi Gong Ctr",
    "wof:placetype":"venue"
},
  "geometry": {"coordinates":[-76.67016099999999,38.991519],"type":"Point"}
}