{
  "type": "Feature",
  "properties": {
    "iso:country":"US",
    "sg:address":"925 Fairlawn Ave",
    "sg:city":"Laurel",
    "sg:classifiers":[
        {
            "category":"Personal",
            "subcategory":"Beauty Salon",
            "type":"Services"
        }
    ],
    "sg:phone":"+1 301 317 6667",
    "sg:postcode":"20707",
    "sg:province":"MD",
    "wof:name":"Hair Fix",
    "wof:placetype":"venue"
},
  "geometry": {"coordinates":[-76.855172,39.097105],"type":"Point"}
}