{
  "type": "Feature",
  "properties": {
    "iso:country":"US",
    "sg:address":"4600 Patterson Ave",
    "sg:city":"Baltimore",
    "sg:classifiers":[
        {
            "category":"Utilities",
            "subcategory":"Refuse",
            "type":"Services"
        }
    ],
    "sg:phone":"+1 410 764 1649",
    "sg:postcode":"21215",
    "sg:province":"MD",
    "sg:tags":[
        "system"
    ],
    "wof:name":"C A Recyclers",
    "wof:placetype":"venue"
},
  "geometry": {"coordinates":[-76.7096,39.350746],"type":"Point"}
}