{
  "type": "Feature",
  "properties": {
    "addr:full":"5801 Ivy League Dr Baltimore MD 21228",
    "addr:housenumber":"5801",
    "addr:postcode":"21228",
    "addr:street":"Ivy League Dr",
    "iso:country":"US",
    "sg:address":"5801 Ivy League Dr",
    "sg:city":"Baltimore",
    "sg:classifiers":[
        {
            "category":"Real Estate",
            "subcategory":"Real Estate Agent",
            "type":"Services"
        }
    ],
    "sg:phone":"+1 410 455 9105",
    "sg:postcode":"21228",
    "sg:province":"MD",
    "wof:name":"Ryland Group Inc",
    "wof:placetype":"venue"
},
  "geometry": {"coordinates":[-76.731807,39.252062],"type":"Point"}
}