{
  "type": "Feature",
  "properties": {
    "addr:full":"3401 Erdman Ave Baltimore MD 21213",
    "addr:housenumber":"3401",
    "addr:postcode":"21213",
    "addr:street":"Erdman Ave",
    "iso:country":"US",
    "sg:address":"3401 Erdman Ave",
    "sg:city":"Baltimore",
    "sg:classifiers":[
        {
            "category":"Community Center",
            "type":"Public Place"
        }
    ],
    "sg:phone":"+1 410 276 9222",
    "sg:postcode":"21213",
    "sg:province":"MD",
    "sg:tags":[
        "medical"
    ],
    "wof:name":"Erdman Medical Center",
    "wof:placetype":"venue"
},
  "geometry": {"coordinates":[-76.57089999999999,39.319599],"type":"Point"}
}