{
  "type": "Feature",
  "properties": {
    "iso:country":"US",
    "sg:address":"3939 Reisterstown Rd",
    "sg:city":"Baltimore",
    "sg:classifiers":[
        {
            "category":"Health Services",
            "subcategory":"Hospital",
            "type":"Services"
        }
    ],
    "sg:phone":"+1 410 367 7821",
    "sg:postcode":"21215",
    "sg:province":"MD",
    "sg:tags":[
        "mental"
    ],
    "wof:name":"ABA Health Svc",
    "wof:placetype":"venue"
},
  "geometry": {"coordinates":[-76.663694,39.333444],"type":"Point"}
}