{
  "type": "Feature",
  "properties": {
    "addr:full":"9210 Vermilion Ct La Plata MD 20646",
    "addr:housenumber":"9210",
    "addr:postcode":"20646",
    "addr:street":"Vermilion Ct",
    "iso:country":"US",
    "sg:address":"9210 Vermilion Ct",
    "sg:city":"La Plata",
    "sg:classifiers":[
        {
            "category":"Building & Trades",
            "subcategory":"Landscaping Services",
            "type":"Services"
        }
    ],
    "sg:phone":"+1 301 753 1316",
    "sg:postcode":"20646",
    "sg:province":"MD",
    "sg:tags":[
        "maintenance"
    ],
    "wof:name":"Fennell Services",
    "wof:placetype":"venue"
},
  "geometry": {"coordinates":[-76.991568,38.580361],"type":"Point"}
}