{
  "type": "Feature",
  "properties": {
    "iso:country":"US",
    "sg:address":"7060 Oakland Mills Road",
    "sg:city":"Columbia",
    "sg:classifiers":[
        {
            "category":"Health Services",
            "subcategory":"Dentist",
            "type":"Services"
        }
    ],
    "sg:phone":"+1 301 908 5304",
    "sg:postcode":"21046",
    "sg:province":"MD",
    "sg:website":"columbiafamilydental.com",
    "wof:name":"Columbia Family Dental",
    "wof:placetype":"venue"
},
  "geometry": {"coordinates":[-76.829482,39.176017],"type":"Point"}
}