{
  "type": "Feature",
  "properties": {
    "iso:country":"US",
    "sg:address":"2252 Crain Hwy",
    "sg:city":"Waldorf",
    "sg:classifiers":[
        {
            "category":"Home & Garden",
            "subcategory":"Building Materials",
            "type":"Retail Goods"
        }
    ],
    "sg:phone":"+1 301 645 9606",
    "sg:postcode":"20601",
    "sg:province":"MD",
    "sg:tags":[
        "paint"
    ],
    "wof:name":"Sherwin-Williams Paints",
    "wof:placetype":"venue"
},
  "geometry": {"coordinates":[-76.88586599999999,38.648966],"type":"Point"}
}