{
  "type": "Feature",
  "properties": {
    "iso:country":"US",
    "sg:address":"5851 Riggs Rd",
    "sg:city":"Hyattsville",
    "sg:classifiers":[
        {
            "category":"Wholesale",
            "subcategory":"Furniture",
            "type":"Manufacturing & Wholesale Goods"
        }
    ],
    "sg:phone":"+1 301 364 1769",
    "sg:postcode":"20783",
    "sg:province":"MD",
    "sg:tags":[
        "beds-wholesale",
        "manufacturer"
    ],
    "wof:name":"Bob's Bed Bug Removal",
    "wof:placetype":"venue"
},
  "geometry": {"coordinates":[-76.995728,38.961817],"type":"Point"}
}