{
  "type": "Feature",
  "properties": {
    "iso:country":"US",
    "sg:address":"217 E Churchville Rd",
    "sg:city":"Bel Air",
    "sg:classifiers":[
        {
            "category":"Professional",
            "subcategory":"Lawyer & Legal Services",
            "type":"Services"
        }
    ],
    "sg:phone":"+1 410 838 1955",
    "sg:postcode":"21014",
    "sg:province":"MD",
    "sg:tags":[
        "attorney"
    ],
    "wof:name":"Theresa Boutchyard",
    "wof:placetype":"venue"
},
  "geometry": {"coordinates":[-76.344925,39.536283],"type":"Point"}
}