{
  "type": "Feature",
  "properties": {
    "iso:country":"US",
    "sg:address":"7315 Wisconsin Ave",
    "sg:city":"Bethesda",
    "sg:classifiers":[
        {
            "category":"Professional",
            "subcategory":"Management & Consulting",
            "type":"Services"
        }
    ],
    "sg:phone":"+1 301 469 3388",
    "sg:postcode":"20814",
    "sg:province":"MD",
    "sg:tags":[
        "fuel"
    ],
    "wof:name":"Information Managemnt Intl Inc",
    "wof:placetype":"venue"
},
  "geometry": {"coordinates":[-77.093582,38.983062],"type":"Point"}
}