{
  "type": "Feature",
  "properties": {
    "iso:country":"US",
    "sg:address":"1602 Frederick Rd",
    "sg:city":"Catonsville",
    "sg:classifiers":[
        {
            "category":"Home & Garden",
            "subcategory":"Building Materials",
            "type":"Retail Goods"
        }
    ],
    "sg:phone":"+1 410 835 4101",
    "sg:postcode":"21228",
    "sg:province":"MD",
    "wof:name":"Catonsville Express Locksmith",
    "wof:placetype":"venue"
},
  "geometry": {"coordinates":[-76.74862400000001,39.268441],"type":"Point"}
}