{
  "type": "Feature",
  "properties": {
    "addr:full":"6601 Amberton Dr Elkridge MD 21075",
    "addr:housenumber":"6601",
    "addr:postcode":"21075",
    "addr:street":"Amberton Dr",
    "iso:country":"US",
    "sg:address":"6601 Amberton Dr",
    "sg:city":"Elkridge",
    "sg:phone":"+1 410 796 6400",
    "sg:postcode":"21075",
    "sg:province":"MD",
    "sg:tags":[
        "fixture",
        "display"
    ],
    "sg:website":"www.agam.com",
    "wof:name":"Agam Group LTD",
    "wof:placetype":"venue"
},
  "geometry": {"coordinates":[-76.750123,39.18837],"type":"Point"}
}