{
  "type": "Feature",
  "properties": {
    "addr:full":"7527 Belair Rd Nottingham MD 21236",
    "addr:housenumber":"7527",
    "addr:postcode":"21236",
    "addr:street":"Belair Rd",
    "iso:country":"US",
    "sg:address":"7527 Belair Rd",
    "sg:city":"Nottingham",
    "sg:classifiers":[
        {
            "category":"Freight",
            "type":"Transportation"
        }
    ],
    "sg:phone":"+1 410 668 8777",
    "sg:postcode":"21236",
    "sg:province":"MD",
    "wof:name":"D B Delivery Inc",
    "wof:placetype":"venue"
},
  "geometry": {"coordinates":[-76.520456,39.363628],"type":"Point"}
}