{
  "type": "Feature",
  "properties": {
    "iso:country":"US",
    "sg:address":"1624 Lynch Rd",
    "sg:city":"Dundalk",
    "sg:classifiers":[
        {
            "category":"Organizations",
            "subcategory":"Religious Organization",
            "type":"Services"
        }
    ],
    "sg:phone":"+1 410 282 1376",
    "sg:postcode":"21222",
    "sg:province":"MD",
    "sg:tags":[
        "church"
    ],
    "wof:name":"Church Of The Nazarene",
    "wof:placetype":"venue"
},
  "geometry": {"coordinates":[-76.494247,39.27176],"type":"Point"}
}