{
  "type": "Feature",
  "properties": {
    "addr:full":"605 Davol Rd Stevensville MD 21666",
    "addr:housenumber":"605",
    "addr:postcode":"21666",
    "addr:street":"Davol Rd",
    "iso:country":"US",
    "sg:address":"605 Davol Rd",
    "sg:city":"Stevensville",
    "sg:classifiers":[
        {
            "category":"Health Services",
            "subcategory":"Hospital",
            "type":"Services"
        }
    ],
    "sg:phone":"+1 410 924 2488",
    "sg:postcode":"21666",
    "sg:province":"MD",
    "sg:tags":[
        "sleep",
        "treatment",
        "disorders-information"
    ],
    "wof:name":"Infectious Diseases Pharmacy Associates, Inc.",
    "wof:placetype":"venue"
},
  "geometry": {"coordinates":[-76.304693,38.990449],"type":"Point"}
}