{
  "type": "Feature",
  "properties": {
    "iso:country":"US",
    "sg:address":"4101 Tulare Dr",
    "sg:city":"Silver Spring",
    "sg:classifiers":[
        {
            "category":"Manufacturing",
            "subcategory":"Motor Vehicles & Parts",
            "type":"Manufacturing & Wholesale Goods"
        }
    ],
    "sg:phone":"+1 301 946 1724",
    "sg:postcode":"20906",
    "sg:province":"MD",
    "sg:tags":[
        "c",
        "mfg",
        "automotive",
        "powered",
        "accessory",
        "solar"
    ],
    "wof:name":"Flaxsun Power Co",
    "wof:placetype":"venue"
},
  "geometry": {"coordinates":[-77.081459,39.051548],"type":"Point"}
}