{
  "type": "Feature",
  "properties": {
    "addr:full":"7115 Standard Dr Hanover MD 21076",
    "addr:housenumber":"7115",
    "addr:postcode":"21076",
    "addr:street":"Standard Dr",
    "iso:country":"US",
    "sg:address":"7115 Standard Dr",
    "sg:city":"Hanover",
    "sg:classifiers":[
        {
            "category":"Utilities",
            "subcategory":"Mobile Phone",
            "type":"Services"
        }
    ],
    "sg:phone":"+1 410 712 4765",
    "sg:postcode":"21076",
    "sg:province":"MD",
    "sg:tags":[
        "telephone",
        "cellular"
    ],
    "wof:name":"Nextwave Wireless",
    "wof:placetype":"venue"
},
  "geometry": {"coordinates":[-76.72901899999999,39.177697],"type":"Point"}
}