{
  "type": "Feature",
  "properties": {
    "addr:full":"9191 Baltimore National Pike Ellicott City MD 21042",
    "addr:housenumber":"9191",
    "addr:postcode":"21042",
    "addr:street":"Baltimore National Pike",
    "iso:country":"US",
    "sg:address":"9191 Baltimore National Pike",
    "sg:city":"Ellicott City",
    "sg:classifiers":[
        {
            "category":"Autos & Motor Vehicles",
            "subcategory":"Auto Supplies",
            "type":"Retail Goods"
        }
    ],
    "sg:phone":"+1 410 465 7711",
    "sg:postcode":"21042",
    "sg:province":"MD",
    "sg:tags":[
        "glass"
    ],
    "sg:website":"www.safelite.com",
    "wof:name":"Safelite Auto Glass",
    "wof:placetype":"venue"
},
  "geometry": {"coordinates":[-76.828298,39.277032],"type":"Point"}
}