{
  "type": "Feature",
  "properties": {
    "addr:full":"13724 Village Mill Dr Maugansville MD 21767",
    "addr:housenumber":"13724",
    "addr:postcode":"21767",
    "addr:street":"Village Mill Dr",
    "iso:country":"US",
    "sg:address":"13724 Village Mill Dr",
    "sg:city":"Maugansville",
    "sg:classifiers":[
        {
            "category":"Manufacturing",
            "subcategory":"Pet Food",
            "type":"Manufacturing & Wholesale Goods"
        }
    ],
    "sg:phone":"+1 301 791 5288",
    "sg:postcode":"21767",
    "sg:province":"MD",
    "sg:tags":[
        "feed"
    ],
    "wof:name":"Maugansville Feed Svc Inc",
    "wof:placetype":"venue"
},
  "geometry": {"coordinates":[-77.74657000000001,39.690496],"type":"Point"}
}