{
  "type": "Feature",
  "properties": {
    "addr:full":"244 Pearl St Baltimore MD 21201",
    "addr:housenumber":"244",
    "addr:postcode":"21201",
    "addr:street":"Pearl St",
    "iso:country":"US",
    "sg:address":"244 Pearl St",
    "sg:city":"Baltimore",
    "sg:classifiers":[
        {
            "category":"Food & Beverages",
            "subcategory":"Bakery",
            "type":"Retail Goods"
        }
    ],
    "sg:phone":"+1 410 625 1591",
    "sg:postcode":"21201",
    "sg:province":"MD",
    "sg:tags":[
        "bakers-wholesale"
    ],
    "wof:name":"F. & S. Maranto",
    "wof:placetype":"venue"
},
  "geometry": {"coordinates":[-76.624647,39.292096],"type":"Point"}
}