{
  "type": "Feature",
  "properties": {
    "iso:country":"US",
    "sg:address":"203 N Market St",
    "sg:city":"Frederick",
    "sg:classifiers":[
        {
            "category":"Professional",
            "type":"Services"
        }
    ],
    "sg:phone":"+1 301 418 6000",
    "sg:postcode":"21701",
    "sg:province":"MD",
    "sg:tags":[
        "establishment"
    ],
    "wof:name":"Wong Eng Assoc",
    "wof:placetype":"venue"
},
  "geometry": {"coordinates":[-77.41058,39.417819],"type":"Point"}
}