{
  "type": "Feature",
  "properties": {
    "addr:full":"222 Crestmoor Cir Silver Spring MD 20901",
    "addr:housenumber":"222",
    "addr:postcode":"20901",
    "addr:street":"Crestmoor Cir",
    "iso:country":"US",
    "sg:address":"222 Crestmoor Cir",
    "sg:city":"Silver Spring",
    "sg:classifiers":[
        {
            "category":"Organizations",
            "subcategory":"Membership Organization",
            "type":"Services"
        }
    ],
    "sg:phone":"+1 301 593 7075",
    "sg:postcode":"20901",
    "sg:province":"MD",
    "wof:name":"Unidentified Flying Opera Co",
    "wof:placetype":"venue"
},
  "geometry": {"coordinates":[-77.00488900000001,39.024864],"type":"Point"}
}