{
  "type": "Feature",
  "properties": {
    "addr:full":"8840 Orchard Tree Ln Towson MD 21286",
    "addr:housenumber":"8840",
    "addr:postcode":"21286",
    "addr:street":"Orchard Tree Ln",
    "iso:country":"US",
    "sg:address":"8840 Orchard Tree Ln",
    "sg:city":"Towson",
    "sg:classifiers":[
        {
            "category":"Professional",
            "subcategory":"Advertising",
            "type":"Services"
        }
    ],
    "sg:phone":"+1 410 769 8989",
    "sg:postcode":"21286",
    "sg:province":"MD",
    "sg:tags":[
        "distribution"
    ],
    "wof:name":"S Pi Distribution Inc",
    "wof:placetype":"venue"
},
  "geometry": {"coordinates":[-76.568719,39.39811],"type":"Point"}
}