{
  "type": "Feature",
  "properties": {
    "addr:full":"4543 Dallas Pl Temple Hills MD 20748",
    "addr:housenumber":"4543",
    "addr:postcode":"20748",
    "addr:street":"Dallas Pl",
    "iso:country":"US",
    "sg:address":"4543 Dallas Pl",
    "sg:city":"Temple Hills",
    "sg:classifiers":[
        {
            "category":"Personal",
            "subcategory":"Beauty Salon",
            "type":"Services"
        }
    ],
    "sg:phone":"+1 202 561 4073",
    "sg:postcode":"20748",
    "sg:province":"MD",
    "sg:tags":[
        "hair"
    ],
    "wof:name":"Porcher Beauty Salon",
    "wof:placetype":"venue"
},
  "geometry": {"coordinates":[-76.948708,38.825229],"type":"Point"}
}