{
  "type": "Feature",
  "properties": {
    "addr:full":"15311 Diamond Cove Ter Rockville MD 20850",
    "addr:housenumber":"15311",
    "addr:postcode":"20850",
    "addr:street":"Diamond Cove Ter",
    "iso:country":"US",
    "sg:address":"15311 Diamond Cove Ter",
    "sg:city":"Rockville",
    "sg:classifiers":[
        {
            "category":"Manufacturing",
            "subcategory":"Electronics",
            "type":"Manufacturing & Wholesale Goods"
        }
    ],
    "sg:phone":"+1 301 523 9225",
    "sg:postcode":"20850",
    "sg:province":"MD",
    "sg:tags":[
        "prerecorded",
        "mfg"
    ],
    "wof:name":"Blue Elephant Music Publishing",
    "wof:placetype":"venue"
},
  "geometry": {"coordinates":[-77.206366,39.109654],"type":"Point"}
}