{
  "type": "Feature",
  "properties": {
    "addr:full":"3449 Wilkens Ave Ste 100 Baltimore MD 21229",
    "addr:housenumber":"3449",
    "addr:postcode":"21229",
    "addr:street":"Wilkens Ave Ste 100",
    "iso:country":"US",
    "sg:address":"3449 Wilkens Ave Ste 100",
    "sg:city":"Baltimore",
    "sg:classifiers":[
        {
            "category":"Health Services",
            "subcategory":"Doctor",
            "type":"Services"
        },
        {
            "category":"Professional",
            "subcategory":"Lawyer & Legal Services",
            "type":"Services"
        }
    ],
    "sg:phone":"+1 410 644 7077",
    "sg:postcode":"21229",
    "sg:province":"MD",
    "wof:name":"Gordon Roger L PA",
    "wof:placetype":"venue"
},
  "geometry": {"coordinates":[-76.67572800000001,39.272323],"type":"Point"}
}