{
  "type": "Feature",
  "properties": {
    "iso:country":"US",
    "sg:address":"7429 Taylor St",
    "sg:city":"Hyattsville",
    "sg:phone":"+1 202 321 2275",
    "sg:postcode":"20784",
    "sg:province":"MD",
    "wof:name":"Sturge Sewer Drain & Plumbing",
    "wof:placetype":"venue"
},
  "geometry": {"coordinates":[-76.88454900000001,38.942405],"type":"Point"}
}