{
  "type": "Feature",
  "properties": {
    "iso:country":"US",
    "sg:address":"5534 Old Middletown Rd",
    "sg:city":"Jefferson",
    "sg:classifiers":[
        {
            "category":"Professional",
            "subcategory":"Business Services",
            "type":"Services"
        }
    ],
    "sg:phone":"+1 301 473 8100",
    "sg:postcode":"21755",
    "sg:province":"MD",
    "sg:tags":[
        "auctioneer"
    ],
    "wof:name":"Willowdale Auction Co",
    "wof:placetype":"venue"
},
  "geometry": {"coordinates":[-77.53839499999999,39.385878],"type":"Point"}
}