{
  "type": "Feature",
  "properties": {
    "iso:country":"US",
    "sg:address":"4891 Telsa Dr",
    "sg:city":"Bowie",
    "sg:classifiers":[
        {
            "category":"Building & Trades",
            "subcategory":"Construction",
            "type":"Services"
        }
    ],
    "sg:phone":"+1 301 262 7880",
    "sg:postcode":"20715",
    "sg:province":"MD",
    "sg:tags":[
        "waterproofing",
        "contractor"
    ],
    "wof:name":"Valcourt Exterior Building Svc",
    "wof:placetype":"venue"
},
  "geometry": {"coordinates":[-76.710117,38.957211],"type":"Point"}
}