{
  "type": "Feature",
  "properties": {
    "iso:country":"US",
    "sg:address":"3615 B and O Rd",
    "sg:city":"Abingdon",
    "sg:classifiers":[
        {
            "category":"Retail",
            "subcategory":"Auto Repair",
            "type":"Services"
        }
    ],
    "sg:phone":"+1 410 676 6200",
    "sg:postcode":"21009",
    "sg:province":"MD",
    "sg:tags":[
        "repairing",
        "automobile"
    ],
    "wof:name":"American Car Care Ctr",
    "wof:placetype":"venue"
},
  "geometry": {"coordinates":[-76.263486,39.456619],"type":"Point"}
}