{
  "type": "Feature",
  "properties": {
    "addr:city":"Baltimore",
    "addr:full":"600 N Charles St Baltimore, Md 21201",
    "addr:house_number":"600",
    "addr:housenumber":"600",
    "addr:phone":"+1 410-547-9000",
    "addr:postcode":"21201",
    "addr:road":"N Charles St",
    "addr:state":"MD",
    "addr:street":"N Charles St",
    "iso:country":"US",
    "sg:address":"600 N Charles St",
    "sg:city":"Baltimore",
    "sg:classifiers":[
        {
            "category":"Museum",
            "type":"Entertainment"
        }
    ],
    "sg:phone":"+1 410 547 9000",
    "sg:postcode":"21201",
    "sg:province":"MD",
    "sg:website":"thewalters.org/",
    "wof:airports":[
        102527121,
        102532047
    ],
    "wof:name":"Walters Art Museum",
    "wof:placetype":"venue"
},
  "geometry": {"coordinates":[-76.61566999999999,39.29588],"type":"Point"}
}