{
  "type": "Feature",
  "properties": {
    "iso:country":"US",
    "sg:address":"600 N Charles St",
    "sg:city":"Baltimore",
    "sg:classifiers":[
        {
            "category":"Museum",
            "type":"Entertainment"
        }
    ],
    "sg:phone":"+1 410 547 9000",
    "sg:postcode":"21201",
    "sg:province":"MD",
    "sg:website":"thewalters.org/",
    "wof:name":"Walters Art Museum",
    "wof:placetype":"venue"
},
  "geometry": {"coordinates":[-76.61660000000001,39.297298],"type":"Point"}
}