{
  "type": "Feature",
  "properties": {
    "iso:country":"US",
    "sg:address":"21 W Baltimore Ste 4",
    "sg:city":"Baltimore",
    "sg:classifiers":[
        {
            "category":"Professional",
            "subcategory":"Detective & Security Services",
            "type":"Services"
        }
    ],
    "sg:phone":"+1 443 692 9362",
    "sg:postcode":"21201",
    "sg:province":"MD",
    "sg:tags":[
        "system"
    ],
    "sg:website":"www.adt.com",
    "wof:name":"ADT",
    "wof:placetype":"venue"
},
  "geometry": {"coordinates":[-76.61508600000001,39.275457],"type":"Point"}
}