{
  "type": "Feature",
  "properties": {
    "iso:country":"US",
    "sg:address":"143 Saint Patricks Dr",
    "sg:city":"Waldorf",
    "sg:classifiers":[
        {
            "category":"Retail",
            "subcategory":"Auto Repair",
            "type":"Services"
        }
    ],
    "sg:phone":"+1 301 638 9800",
    "sg:postcode":"20603",
    "sg:province":"MD",
    "sg:tags":[
        "automobile",
        "lubrication"
    ],
    "wof:name":"Chesapeake Lubrication",
    "wof:placetype":"venue"
},
  "geometry": {"coordinates":[-76.927893,38.621018],"type":"Point"}
}