{
  "type": "Feature",
  "properties": {
    "addr:full":"11724 Roby Ave Beltsville MD 20705",
    "addr:housenumber":"11724",
    "addr:postcode":"20705",
    "addr:street":"Roby Ave",
    "iso:country":"US",
    "sg:address":"11724 Roby Ave",
    "sg:city":"Beltsville",
    "sg:classifiers":[
        {
            "category":"Personal",
            "subcategory":"Beauty Salon",
            "type":"Services"
        }
    ],
    "sg:phone":"+1 301 937 0669",
    "sg:postcode":"20705",
    "sg:province":"MD",
    "wof:name":"Who's Hair",
    "wof:placetype":"venue"
},
  "geometry": {"coordinates":[-76.915796,39.051206],"type":"Point"}
}