{
  "type": "Feature",
  "properties": {
    "iso:country":"US",
    "sg:address":"1215 Annapolis Rd",
    "sg:city":"Odenton",
    "sg:classifiers":[
        {
            "category":"Restaurant",
            "type":"Food & Drink"
        }
    ],
    "sg:menulink":"http://www.allmenus.com/md/odenton/67404-dominos-pizza/menu/",
    "sg:phone":"+1 410 672 3232",
    "sg:postcode":"21113",
    "sg:province":"MD",
    "sg:tags":[
        "american",
        "wing",
        "pizza"
    ],
    "wof:name":"Domino's Pizza",
    "wof:placetype":"venue"
},
  "geometry": {"coordinates":[-76.692744,39.083544],"type":"Point"}
}