{
  "type": "Feature",
  "properties": {
    "iso:country":"US",
    "sg:address":"706 Orchard Way",
    "sg:city":"Silver Spring",
    "sg:classifiers":[
        {
            "category":"Building & Trades",
            "subcategory":"Landscaping Services",
            "type":"Services"
        }
    ],
    "sg:phone":"+1 301 590 1280",
    "sg:postcode":"20904",
    "sg:province":"MD",
    "sg:tags":[
        "sod",
        "sodding"
    ],
    "wof:name":"Maryland Seed & Environmental",
    "wof:placetype":"venue"
},
  "geometry": {"coordinates":[-76.99233099999999,39.08304],"type":"Point"}
}