{
  "type": "Feature",
  "properties": {
    "iso:country":"US",
    "sg:address":"4617 Benson Ave",
    "sg:city":"Halethorpe",
    "sg:classifiers":[
        {
            "category":"Building & Trades",
            "subcategory":"Locksmith",
            "type":"Services"
        }
    ],
    "sg:phone":"+1 443 297 2068",
    "sg:postcode":"21227",
    "sg:province":"MD",
    "sg:tags":[
        "key"
    ],
    "wof:name":"Available Benson Ave Emergency Locksmith",
    "wof:placetype":"venue"
},
  "geometry": {"coordinates":[-76.68365300000001,39.257921],"type":"Point"}
}