{
  "type": "Feature",
  "properties": {
    "iso:country":"US",
    "sg:address":"4175 Henson Ln",
    "sg:city":"Bowie",
    "sg:classifiers":[
        {
            "category":"Health Services",
            "subcategory":"Doctor",
            "type":"Services"
        }
    ],
    "sg:phone":"+1 301 809 6880",
    "sg:postcode":"20748",
    "sg:province":"MD",
    "sg:tags":[
        "physician",
        "surgeon"
    ],
    "wof:name":"Cardiology Associates",
    "wof:placetype":"venue"
},
  "geometry": {"coordinates":[-76.936224,38.803565],"type":"Point"}
}