{
  "type": "Feature",
  "properties": {
    "iso:country":"US",
    "sg:address":"15709 Crabbs Branch Way",
    "sg:city":"Derwood",
    "sg:classifiers":[
        {
            "category":"Shopping",
            "subcategory":"Clothing, Apparel, & Fashions",
            "type":"Retail Goods"
        }
    ],
    "sg:phone":"+1 301 948 1833",
    "sg:postcode":"20855",
    "sg:province":"MD",
    "sg:tags":[
        "shop",
        "bridal"
    ],
    "wof:name":"Distinctive Designs Bridal",
    "wof:placetype":"venue"
},
  "geometry": {"coordinates":[-77.154813,39.110793],"type":"Point"}
}