{
  "type": "Feature",
  "properties": {
    "addr:full":"7312 Kerry Hill Ct Columbia MD 21045",
    "addr:housenumber":"7312",
    "addr:postcode":"21045",
    "addr:street":"Kerry Hill Ct",
    "iso:country":"US",
    "sg:address":"7312 Kerry Hill Ct",
    "sg:city":"Columbia",
    "sg:classifiers":[
        {
            "category":"Shopping",
            "subcategory":"Clothing, Apparel, & Fashions",
            "type":"Retail Goods"
        }
    ],
    "sg:phone":"+1 410 381 2226",
    "sg:postcode":"21045",
    "sg:province":"MD",
    "sg:tags":[
        "designer"
    ],
    "wof:name":"Fashion Studio",
    "wof:placetype":"venue"
},
  "geometry": {"coordinates":[-76.847199,39.186118],"type":"Point"}
}