{
  "type": "Feature",
  "properties": {
    "iso:country":"US",
    "sg:address":"2400 Boston St",
    "sg:city":"Baltimore",
    "sg:classifiers":[
        {
            "category":"Professional",
            "subcategory":"Advertising",
            "type":"Services"
        },
        {
            "category":"Professional",
            "subcategory":"Secretarial Services",
            "type":"Services"
        }
    ],
    "sg:phone":"+1 410 327 9148",
    "sg:postcode":"21224",
    "sg:province":"MD",
    "sg:tags":[
        "fax",
        "answering",
        "telephone",
        "advertising-telephone",
        "telemarketing"
    ],
    "sg:website":"http://www.etcbaltimore.com",
    "wof:name":"Greater Baltimore Tech Cncl",
    "wof:placetype":"venue"
},
  "geometry": {"coordinates":[-76.582626,39.28199],"type":"Point"}
}