{
  "type": "Feature",
  "properties": {
    "iso:country":"US",
    "sg:address":"45 Westminster Rd",
    "sg:city":"Reisterstown",
    "sg:classifiers":[
        {
            "category":"Organizations",
            "subcategory":"Community Association",
            "type":"Services"
        }
    ],
    "sg:phone":"+1 410 517 8111",
    "sg:postcode":"21136",
    "sg:province":"MD",
    "sg:tags":[
        "club"
    ],
    "wof:name":"Tracys Comedy Club Hotline",
    "wof:placetype":"venue"
},
  "geometry": {"coordinates":[-76.83099799999999,39.47029],"type":"Point"}
}