{
  "type": "Feature",
  "properties": {
    "iso:country":"US",
    "sg:address":"9801 York Rd",
    "sg:city":"Cockeysville",
    "sg:classifiers":[
        {
            "category":"Restaurant",
            "type":"Food & Drink"
        }
    ],
    "sg:phone":"+1 410 666 2600",
    "sg:postcode":"21030",
    "sg:province":"MD",
    "sg:tags":[
        "pizza",
        "italian"
    ],
    "wof:name":"Pizza Palace",
    "wof:placetype":"venue"
},
  "geometry": {"coordinates":[-76.633678,39.458366],"type":"Point"}
}