{
  "type": "Feature",
  "properties": {
    "iso:country":"US",
    "sg:address":"128 Main St",
    "sg:city":"Annapolis",
    "sg:classifiers":[
        {
            "category":"Restaurant",
            "type":"Food & Drink"
        }
    ],
    "sg:phone":"+1 410 269 7686",
    "sg:postcode":"21401",
    "sg:province":"MD",
    "sg:tags":[
        "parlor",
        "ice",
        "cream"
    ],
    "wof:name":"Greentree's",
    "wof:placetype":"venue"
},
  "geometry": {"coordinates":[-76.48814,38.977226],"type":"Point"}
}