{
  "type": "Feature",
  "properties": {
    "iso:country":"US",
    "sg:address":"16060 Three Notch Rd",
    "sg:city":"California",
    "sg:classifiers":[
        {
            "category":"Restaurant",
            "type":"Food & Drink"
        }
    ],
    "sg:phone":"+1 301 862 1398",
    "sg:postcode":"20619",
    "sg:province":"MD",
    "wof:name":"Hong Kong Restaurant III",
    "wof:placetype":"venue"
},
  "geometry": {"coordinates":[-76.50584000000001,38.296639],"type":"Point"}
}