{
  "type": "Feature",
  "properties": {
    "iso:country":"US",
    "sg:address":"5300 East Dr Ste F",
    "sg:city":"Halethorpe",
    "sg:classifiers":[
        {
            "category":"Retail",
            "subcategory":"Laundry & Dry Cleaning",
            "type":"Services"
        },
        {
            "category":"Building & Trades",
            "subcategory":"Cleaning & Sanitation",
            "type":"Services"
        },
        {
            "category":"Home & Garden",
            "subcategory":"Carpets & Floor Coverings",
            "type":"Retail Goods"
        }
    ],
    "sg:phone":"+1 410 242 6010",
    "sg:postcode":"21227",
    "sg:province":"MD",
    "sg:tags":[
        "cleaner",
        "installation",
        "rug",
        "carpeting"
    ],
    "sg:website":"www.reliablecarpetservice.com",
    "wof:name":"Reliable Carpet Service",
    "wof:placetype":"venue"
},
  "geometry": {"coordinates":[-76.69344700000001,39.250591],"type":"Point"}
}