{
  "type": "Feature",
  "properties": {
    "addr:full":"31 Old Solomons Island Rd Annapolis MD 21401",
    "addr:housenumber":"31",
    "addr:postcode":"21401",
    "addr:street":"Old Solomons Island Rd",
    "iso:country":"US",
    "sg:address":"31 Old Solomons Island Rd",
    "sg:city":"Annapolis",
    "sg:classifiers":[
        {
            "category":"Organizations",
            "subcategory":"Non-profit Organization",
            "type":"Services"
        }
    ],
    "sg:phone":"+1 410 841 6920",
    "sg:postcode":"21401",
    "sg:province":"MD",
    "sg:tags":[
        "charity",
        "foundations-educational",
        "philanthropic",
        "research"
    ],
    "sg:website":"http://www.kintehaley.org",
    "wof:name":"Kunta Kinte Alex Haley Foundation Inc",
    "wof:placetype":"venue"
},
  "geometry": {"coordinates":[-76.535133,38.980228],"type":"Point"}
}