{
  "type": "Feature",
  "properties": {
    "iso:country":"US",
    "sg:address":"4203 Harcourt Rd",
    "sg:city":"Baltimore",
    "sg:classifiers":[
        {
            "category":"Professional",
            "subcategory":"Management & Consulting",
            "type":"Services"
        },
        {
            "category":"Professional",
            "subcategory":"Engineering",
            "type":"Services"
        }
    ],
    "sg:phone":"+1 410 444 6146",
    "sg:postcode":"21214",
    "sg:province":"MD",
    "sg:tags":[
        "consultant",
        "ecological",
        "engineer",
        "environmental"
    ],
    "wof:name":"Susan Markowitz",
    "wof:placetype":"venue"
},
  "geometry": {"coordinates":[-76.569738,39.332764],"type":"Point"}
}