{
  "type": "Feature",
  "properties": {
    "addr:full":"201 Water St Severna Park MD 21146",
    "addr:housenumber":"201",
    "addr:postcode":"21146",
    "addr:street":"Water St",
    "iso:country":"US",
    "sg:address":"201 Water St",
    "sg:city":"Severna Park",
    "sg:classifiers":[
        {
            "category":"Education",
            "subcategory":"School",
            "type":"Public Place"
        }
    ],
    "sg:phone":"+1 410 647 7700",
    "sg:postcode":"21146",
    "sg:province":"MD",
    "sg:website":"www.severnschool.com",
    "wof:name":"Severn School Inc",
    "wof:placetype":"venue"
},
  "geometry": {"coordinates":[-76.549283,39.069475],"type":"Point"}
}