{
  "type": "Feature",
  "properties": {
    "addr:full":"5428 Silver Hill Rd District Heights MD 20747",
    "addr:housenumber":"5428",
    "addr:postcode":"20747",
    "addr:street":"Silver Hill Rd",
    "iso:country":"US",
    "sg:address":"5428 Silver Hill Rd",
    "sg:city":"District Heights",
    "sg:classifiers":[
        {
            "category":"Shopping",
            "subcategory":"Beauty & Cosmetics",
            "type":"Retail Goods"
        }
    ],
    "sg:phone":"+1 301 568 1190",
    "sg:postcode":"20747",
    "sg:province":"MD",
    "sg:tags":[
        "supply"
    ],
    "wof:name":"Gold Beauty Supply",
    "wof:placetype":"venue"
},
  "geometry": {"coordinates":[-76.91404300000001,38.852473],"type":"Point"}
}