{
  "type": "Feature",
  "properties": {
    "iso:country":"US",
    "sg:address":"357 Main St Suite East",
    "sg:city":"Laurel",
    "sg:classifiers":[
        {
            "category":"Professional",
            "subcategory":"Printing & Photocopies",
            "type":"Services"
        }
    ],
    "sg:phone":"+1 301 256 7125",
    "sg:postcode":"20707",
    "sg:province":"MD",
    "wof:name":"Asha Prints LLC",
    "wof:placetype":"venue"
},
  "geometry": {"coordinates":[-76.846287,39.105208],"type":"Point"}
}