{
  "type": "Feature",
  "properties": {
    "addr:full":"11404 Reisterstown Rd Owings Mills MD 21117",
    "addr:housenumber":"11404",
    "addr:postcode":"21117",
    "addr:street":"Reisterstown Rd",
    "iso:country":"US",
    "sg:address":"11404 Reisterstown Rd",
    "sg:city":"Owings Mills",
    "sg:classifiers":[
        {
            "category":"Retail",
            "subcategory":"Auto Rental",
            "type":"Services"
        }
    ],
    "sg:phone":"+1 443 394 3840",
    "sg:postcode":"21117",
    "sg:province":"MD",
    "sg:tags":[
        "renting",
        "automobile"
    ],
    "wof:name":"Enterprise Rent-A-Car",
    "wof:placetype":"venue"
},
  "geometry": {"coordinates":[-76.80501099999999,39.439521],"type":"Point"}
}