{
  "type": "Feature",
  "properties": {
    "iso:country":"US",
    "sg:address":"9185 Central Ave Ste C",
    "sg:city":"Capitol Heights",
    "sg:classifiers":[
        {
            "category":"Shopping",
            "subcategory":"Beauty & Cosmetics",
            "type":"Retail Goods"
        }
    ],
    "sg:phone":"+1 301 808 1317",
    "sg:postcode":"20743",
    "sg:province":"MD",
    "sg:tags":[
        "supply"
    ],
    "wof:name":"Beauty",
    "wof:placetype":"venue"
},
  "geometry": {"coordinates":[-76.85080000000001,38.890999],"type":"Point"}
}