{
  "type": "Feature",
  "properties": {
    "iso:country":"US",
    "sg:address":"9402 Pennsylvania Ave",
    "sg:city":"Upper Marlboro",
    "sg:classifiers":[
        {
            "category":"Retail",
            "subcategory":"Portrait Studio",
            "type":"Services"
        }
    ],
    "sg:phone":"+1 301 599 8340",
    "sg:postcode":"20772",
    "sg:province":"MD",
    "sg:tags":[
        "photographer"
    ],
    "wof:name":"Photogenic Studios",
    "wof:placetype":"venue"
},
  "geometry": {"coordinates":[-76.844516,38.819394],"type":"Point"}
}