{
  "type": "Feature",
  "properties": {
    "iso:country":"US",
    "sg:address":"3 Brinker Ct",
    "sg:city":"Rising Sun",
    "sg:classifiers":[
        {
            "category":"Insurance",
            "subcategory":"Insurance Agent",
            "type":"Services"
        }
    ],
    "sg:phone":"+1 410 658 4969",
    "sg:postcode":"21911",
    "sg:province":"MD",
    "wof:name":"Sun Insurance Assoc",
    "wof:placetype":"venue"
},
  "geometry": {"coordinates":[-76.064963,39.701762],"type":"Point"}
}