{
  "type": "Feature",
  "properties": {
    "addr:full":"3 Brinker Ct Rising Sun MD 21911",
    "addr:housenumber":"3",
    "addr:postcode":"21911",
    "addr:street":"Brinker Ct",
    "iso:country":"US",
    "sg:address":"3 Brinker Ct",
    "sg:city":"Rising Sun",
    "sg:classifiers":[
        {
            "category":"Insurance",
            "subcategory":"Insurance Agent",
            "type":"Services"
        }
    ],
    "sg:phone":"+1 410 658 4969",
    "sg:postcode":"21911",
    "sg:province":"MD",
    "wof:name":"Sun Insurance Assoc",
    "wof:placetype":"venue"
},
  "geometry": {"coordinates":[-76.06496300000001,39.701762],"type":"Point"}
}