{
  "type": "Feature",
  "properties": {
    "addr:full":"19414 Leitersburg Pike Hagerstown MD 21742",
    "addr:housenumber":"19414",
    "addr:postcode":"21742",
    "addr:street":"Leitersburg Pike",
    "iso:country":"US",
    "sg:address":"19414 Leitersburg Pike",
    "sg:city":"Hagerstown",
    "sg:classifiers":[
        {
            "category":"Health Services",
            "subcategory":"Doctor",
            "type":"Services"
        }
    ],
    "sg:phone":"+1 301 791 2510",
    "sg:postcode":"21742",
    "sg:province":"MD",
    "sg:tags":[
        "physician",
        "surgeon"
    ],
    "wof:name":"Allegany Medical",
    "wof:placetype":"venue"
},
  "geometry": {"coordinates":[-77.699825,39.667923],"type":"Point"}
}