{
  "type": "Feature",
  "properties": {
    "addr:full":"9421 Largo Dr W Upper Marlboro MD 20774",
    "addr:housenumber":"9421",
    "addr:postcode":"20774",
    "addr:street":"Largo Dr W",
    "iso:country":"US",
    "sg:address":"9421 Largo Dr W",
    "sg:city":"Upper Marlboro",
    "sg:classifiers":[
        {
            "category":"Travel",
            "subcategory":"Hotels & Motels",
            "type":"Entertainment"
        }
    ],
    "sg:phone":"+1 301 499 4600",
    "sg:postcode":"20774",
    "sg:province":"MD",
    "wof:name":"Hampton Inn",
    "wof:placetype":"venue"
},
  "geometry": {"coordinates":[-76.842608,38.895343],"type":"Point"}
}