{
  "type": "Feature",
  "properties": {
    "addr:full":"7677 Canton Center Dr Baltimore MD 21224",
    "addr:housenumber":"7677",
    "addr:postcode":"21224",
    "addr:street":"Canton Center Dr",
    "iso:country":"US",
    "sg:address":"7677 Canton Center Dr",
    "sg:city":"Baltimore",
    "sg:classifiers":[
        {
            "category":"Manufacturing",
            "subcategory":"Tools & Machinery",
            "type":"Manufacturing & Wholesale Goods"
        }
    ],
    "sg:phone":"+1 410 285 7475",
    "sg:postcode":"21224",
    "sg:province":"MD",
    "sg:tags":[
        "control",
        "electronic"
    ],
    "wof:name":"Electronic Control Corp",
    "wof:placetype":"venue"
},
  "geometry": {"coordinates":[-76.52225,39.29725],"type":"Point"}
}