{
  "type": "Feature",
  "properties": {
    "addr:full":"5309 38th Ave Hyattsville MD 20781",
    "addr:housenumber":"5309",
    "addr:postcode":"20781",
    "addr:street":"38Th Ave",
    "iso:country":"US",
    "sg:address":"5309 38th Ave",
    "sg:city":"Hyattsville",
    "sg:classifiers":[
        {
            "category":"Professional",
            "subcategory":"Art Services",
            "type":"Services"
        }
    ],
    "sg:phone":"+1 301 728 3314",
    "sg:postcode":"20781",
    "sg:province":"MD",
    "sg:tags":[
        "commercial",
        "design"
    ],
    "wof:name":"I Am Designs",
    "wof:placetype":"venue"
},
  "geometry": {"coordinates":[-76.954542,38.953473],"type":"Point"}
}