{
  "type": "Feature",
  "properties": {
    "iso:country":"US",
    "sg:address":"3599 E Northern Pkwy",
    "sg:city":"Baltimore",
    "sg:classifiers":[
        {
            "category":"Organizations",
            "subcategory":"Religious Organization",
            "type":"Services"
        }
    ],
    "sg:phone":"+1 410 254 7641",
    "sg:postcode":"21206",
    "sg:province":"MD",
    "sg:tags":[
        "church"
    ],
    "wof:name":"Evangelical Presbyterian Chr",
    "wof:placetype":"venue"
},
  "geometry": {"coordinates":[-76.540027,39.358961],"type":"Point"}
}