{
  "type": "Feature",
  "properties": {
    "iso:country":"US",
    "sg:address":"17608 Livingston Rd",
    "sg:city":"Accokeek",
    "sg:classifiers":[
        {
            "category":"Bus Charters",
            "type":"Transportation"
        }
    ],
    "sg:phone":"+1 301 283 3108",
    "sg:postcode":"20607",
    "sg:province":"MD",
    "sg:tags":[
        "rental"
    ],
    "wof:name":"Acco Bus Svc",
    "wof:placetype":"venue"
},
  "geometry": {"coordinates":[-77.04132799999999,38.650338],"type":"Point"}
}