{
  "type": "Feature",
  "properties": {
    "addr:full":"718 E Gude Dr Rockville MD 20850",
    "addr:housenumber":"718",
    "addr:postcode":"20850",
    "addr:street":"E Gude Dr",
    "iso:country":"US",
    "sg:address":"718 E Gude Dr",
    "sg:city":"Rockville",
    "sg:classifiers":[
        {
            "category":"Shopping",
            "subcategory":"Hobbies, Toys, & Games",
            "type":"Retail Goods"
        }
    ],
    "sg:phone":"+1 301 279 2966",
    "sg:postcode":"20850",
    "sg:province":"MD",
    "sg:tags":[
        "equipment",
        "ceramic",
        "supply"
    ],
    "sg:website":"www.suziegoose.com",
    "wof:name":"Suzie Goose Hobbies",
    "wof:placetype":"venue"
},
  "geometry": {"coordinates":[-77.14009799999999,39.100357],"type":"Point"}
}