{
  "type": "Feature",
  "properties": {
    "iso:country":"US",
    "sg:address":"1222 Hull St",
    "sg:city":"Baltimore",
    "sg:classifiers":[
        {
            "category":"Building & Trades",
            "subcategory":"Locksmith",
            "type":"Services"
        }
    ],
    "sg:phone":"+1 443 378 3823",
    "sg:postcode":"21230",
    "sg:province":"MD",
    "sg:tags":[
        "key"
    ],
    "wof:name":"Emergency 24 Hour 7 Day Locksmith",
    "wof:placetype":"venue"
},
  "geometry": {"coordinates":[-76.591995,39.272305],"type":"Point"}
}