{
  "type": "Feature",
  "properties": {
    "addr:full":"9470 Annapolis Rd Lanham MD 20706",
    "addr:housenumber":"9470",
    "addr:postcode":"20706",
    "addr:street":"Annapolis Rd",
    "iso:country":"US",
    "sg:address":"9470 Annapolis Rd",
    "sg:city":"Lanham",
    "sg:classifiers":[
        {
            "category":"Health Services",
            "subcategory":"Doctor",
            "type":"Services"
        }
    ],
    "sg:phone":"+1 301 731 4522",
    "sg:postcode":"20706",
    "sg:province":"MD",
    "sg:tags":[
        "dentist"
    ],
    "wof:name":"Enterprise Dental Specialists",
    "wof:placetype":"venue"
},
  "geometry": {"coordinates":[-76.841284,38.964931],"type":"Point"}
}