{
  "type": "Feature",
  "properties": {
    "iso:country":"US",
    "sg:address":"3275 SOLOMONS ISLAND RD",
    "sg:city":"EDGEWATER",
    "sg:classifiers":[
        {
            "category":"Restaurant",
            "type":"Food & Drink"
        },
        {
            "category":"Food & Beverages",
            "subcategory":"Groceries & Convenience Stores",
            "type":"Retail Goods"
        }
    ],
    "sg:phone":"+1 410 956 4420",
    "sg:postcode":"21037",
    "sg:province":"MD",
    "sg:tags":[
        "shop",
        "house",
        "steak",
        "sandwich"
    ],
    "sg:website":"http://JakesSteaksMaryland.com",
    "wof:name":"Jakes Steaks South River Colony Shopping Center",
    "wof:placetype":"venue"
},
  "geometry": {"coordinates":[-76.56825499999999,38.927701],"type":"Point"}
}