{
  "type": "Feature",
  "properties": {
    "iso:country":"US",
    "sg:address":"3202 Southern Ave",
    "sg:city":"Baltimore",
    "sg:classifiers":[
        {
            "category":"Government",
            "subcategory":"Office",
            "type":"Public Place"
        }
    ],
    "sg:phone":"+1 410 333 7729",
    "sg:postcode":"21214",
    "sg:province":"MD",
    "sg:tags":[
        "state",
        "program"
    ],
    "wof:name":"Transportation Dept",
    "wof:placetype":"venue"
},
  "geometry": {"coordinates":[-76.563427,39.342513],"type":"Point"}
}