{
  "type": "Feature",
  "properties": {
    "iso:country":"US",
    "sg:address":"223 W Saratoga St",
    "sg:city":"Baltimore",
    "sg:classifiers":[
        {
            "category":"Personal",
            "subcategory":"Barber",
            "type":"Services"
        }
    ],
    "sg:phone":"+1 410 234 0411",
    "sg:postcode":"21201",
    "sg:province":"MD",
    "wof:name":"My Barber Shop",
    "wof:placetype":"venue"
},
  "geometry": {"coordinates":[-76.61889600000001,39.292801],"type":"Point"}
}