{
  "type": "Feature",
  "properties": {
    "iso:country":"US",
    "sg:address":"819 Bennett Point Rd",
    "sg:city":"Queenstown",
    "sg:classifiers":[
        {
            "category":"Building & Trades",
            "subcategory":"Plumbing",
            "type":"Services"
        }
    ],
    "sg:phone":"+1 410 643 4555",
    "sg:postcode":"21658",
    "sg:province":"MD",
    "sg:tags":[
        "heat",
        "pump"
    ],
    "wof:name":"W Scott Jones Mechanical Contr",
    "wof:placetype":"venue"
},
  "geometry": {"coordinates":[-76.170872,38.954441],"type":"Point"}
}