{
  "type": "Feature",
  "properties": {
    "iso:country":"US",
    "sg:address":"419 Cedarcroft Rd",
    "sg:city":"Baltimore",
    "sg:classifiers":[
        {
            "category":"Organizations",
            "subcategory":"Religious Organization",
            "type":"Services"
        }
    ],
    "sg:phone":"+1 410 433 4811",
    "sg:postcode":"21212",
    "sg:province":"MD",
    "sg:tags":[
        "church"
    ],
    "sg:website":"www.nativitycedarcroft.ang-md.org",
    "wof:name":"Church Of The Nativity",
    "wof:placetype":"venue"
},
  "geometry": {"coordinates":[-76.610359,39.368175],"type":"Point"}
}