{
  "type": "Feature",
  "properties": {
    "iso:country":"US",
    "sg:address":"12601 Carrington Hill Dr",
    "sg:city":"Gaithersburg",
    "sg:classifiers":[
        {
            "category":"Professional",
            "subcategory":"Research",
            "type":"Services"
        }
    ],
    "sg:phone":"+1 301 977 8564",
    "sg:postcode":"20878",
    "sg:province":"MD",
    "sg:tags":[
        "consultant",
        "scientific"
    ],
    "wof:name":"Gary L Kreps",
    "wof:placetype":"venue"
},
  "geometry": {"coordinates":[-77.261987,39.118632],"type":"Point"}
}