{
  "type": "Feature",
  "properties": {
    "iso:country":"US",
    "sg:address":"6201 Riverdale Rd Ste 320",
    "sg:city":"Riverdale",
    "sg:classifiers":[
        {
            "category":"Building & Trades",
            "subcategory":"Construction",
            "type":"Services"
        }
    ],
    "sg:phone":"+1 301 277 9200",
    "sg:postcode":"20737",
    "sg:province":"MD",
    "sg:tags":[
        "interior",
        "design"
    ],
    "wof:name":"Summers Company",
    "wof:placetype":"venue"
},
  "geometry": {"coordinates":[-76.91267499999999,38.960234],"type":"Point"}
}