{
  "type": "Feature",
  "properties": {
    "addr:full":"9 Lochwell Ct Parkville MD 21234",
    "addr:housenumber":"9",
    "addr:postcode":"21234",
    "addr:street":"Lochwell Ct",
    "iso:country":"US",
    "sg:address":"9 Lochwell Ct",
    "sg:city":"Parkville",
    "sg:classifiers":[
        {
            "category":"Real Estate",
            "subcategory":"Real Estate Agent",
            "type":"Services"
        }
    ],
    "sg:phone":"+1 410 583 7300",
    "sg:postcode":"21234",
    "sg:province":"MD",
    "wof:name":"Horizon Development",
    "wof:placetype":"venue"
},
  "geometry": {"coordinates":[-76.539264,39.417238],"type":"Point"}
}