{
  "type": "Feature",
  "properties": {
    "iso:country":"US",
    "sg:address":"4905 Carroll Ct",
    "sg:city":"Baldwin",
    "sg:classifiers":[
        {
            "category":"Building & Trades",
            "subcategory":"Construction",
            "type":"Services"
        }
    ],
    "sg:phone":"+1 410 592 2431",
    "sg:postcode":"21013",
    "sg:province":"MD",
    "sg:tags":[
        "altering",
        "remodeling",
        "contractor"
    ],
    "wof:name":"Major Contracting",
    "wof:placetype":"venue"
},
  "geometry": {"coordinates":[-76.505312,39.511589],"type":"Point"}
}