{
  "type": "Feature",
  "properties": {
    "iso:country":"US",
    "sg:address":"4952 Churchey Rd",
    "sg:city":"Keedysville",
    "sg:classifiers":[
        {
            "category":"Personal",
            "type":"Services"
        }
    ],
    "sg:phone":"+1 301 432 4993",
    "sg:postcode":"21756",
    "sg:province":"MD",
    "wof:name":"Lewis Valeta Lic Makup Artist",
    "wof:placetype":"venue"
},
  "geometry": {"coordinates":[-77.710473,39.450052],"type":"Point"}
}