{
  "type": "Feature",
  "properties": {
    "iso:country":"US",
    "sg:address":"7979 Old Georgetown Rd",
    "sg:city":"Bethesda",
    "sg:classifiers":[
        {
            "category":"Shopping",
            "subcategory":"Computers & Home Electronics",
            "type":"Retail Goods"
        }
    ],
    "sg:phone":"+1 301 656 5501",
    "sg:postcode":"20814",
    "sg:province":"MD",
    "sg:tags":[
        "software"
    ],
    "sg:website":"www.lokitech.com",
    "wof:name":"Loki Technologies",
    "wof:placetype":"venue"
},
  "geometry": {"coordinates":[-77.101345,38.989038],"type":"Point"}
}