{
  "type": "Feature",
  "properties": {
    "addr:full":"3050 Crain Hwy Waldorf MD 20601",
    "addr:housenumber":"3050",
    "addr:postcode":"20601",
    "addr:street":"Crain Hwy",
    "iso:country":"US",
    "sg:address":"3050 Crain Hwy",
    "sg:city":"Waldorf",
    "sg:classifiers":[
        {
            "category":"Retail",
            "subcategory":"Auto Rental",
            "type":"Services"
        }
    ],
    "sg:phone":"+1 301 843 5091",
    "sg:postcode":"20601",
    "sg:province":"MD",
    "sg:tags":[
        "renting",
        "automobile"
    ],
    "wof:name":"Total Car Rental Inc",
    "wof:placetype":"venue"
},
  "geometry": {"coordinates":[-76.90902199999999,38.627534],"type":"Point"}
}