{
  "type": "Feature",
  "properties": {
    "iso:country":"US",
    "sg:address":"4715 Pilgrim Rd",
    "sg:city":"Baltimore",
    "sg:classifiers":[
        {
            "category":"Wholesale",
            "subcategory":"Construction Materials",
            "type":"Manufacturing & Wholesale Goods"
        },
        {
            "category":"Building & Trades",
            "subcategory":"Construction",
            "type":"Services"
        }
    ],
    "sg:phone":"+1 410 319 9355",
    "sg:postcode":"21214",
    "sg:province":"MD",
    "sg:tags":[
        "cars-refinishing",
        "elevator"
    ],
    "wof:name":"Hydro",
    "wof:placetype":"venue"
},
  "geometry": {"coordinates":[-76.575603,39.345643],"type":"Point"}
}