{
  "type": "Feature",
  "properties": {
    "addr:full":"7545 Montevideo Rd Jessup MD 20794",
    "addr:housenumber":"7545",
    "addr:postcode":"20794",
    "addr:street":"Montevideo Rd",
    "iso:country":"US",
    "sg:address":"7545 Montevideo Rd",
    "sg:city":"Jessup",
    "sg:classifiers":[
        {
            "category":"Building & Trades",
            "subcategory":"Construction",
            "type":"Services"
        }
    ],
    "sg:phone":"+1 410 799 4495",
    "sg:postcode":"20794",
    "sg:province":"MD",
    "sg:tags":[
        "mason",
        "masonry",
        "industrial",
        "contractors-commercial",
        "contractor"
    ],
    "sg:website":"http://www.cfmasonry.com",
    "wof:name":"C.F. Masonry Specialists, Inc.",
    "wof:placetype":"venue"
},
  "geometry": {"coordinates":[-76.769706,39.163785],"type":"Point"}
}