{
  "type": "Feature",
  "properties": {
    "iso:country":"US",
    "sg:address":"12680 Hg Trueman Rd",
    "sg:city":"Lusby",
    "sg:classifiers":[
        {
            "category":"Education",
            "subcategory":"School",
            "type":"Public Place"
        }
    ],
    "sg:phone":"+1 410 535 7802",
    "sg:postcode":"20657",
    "sg:province":"MD",
    "wof:name":"Dowell Elementary School",
    "wof:placetype":"venue"
},
  "geometry": {"coordinates":[-76.449478,38.363194],"type":"Point"}
}