{
  "type": "Feature",
  "properties": {
    "iso:country":"US",
    "sg:address":"3428 Elmley Ave",
    "sg:city":"Baltimore",
    "sg:classifiers":[
        {
            "category":"Organizations",
            "subcategory":"Religious Organization",
            "type":"Services"
        }
    ],
    "sg:phone":"+1 410 558 0950",
    "sg:postcode":"21213",
    "sg:province":"MD",
    "sg:tags":[
        "church"
    ],
    "wof:name":"New Zion Hill Baptist Church",
    "wof:placetype":"venue"
},
  "geometry": {"coordinates":[-76.57510600000001,39.317163],"type":"Point"}
}