{
  "type": "Feature",
  "properties": {
    "addr:full":"15215 Shady Grove Rd Rockville MD 20850",
    "addr:housenumber":"15215",
    "addr:postcode":"20850",
    "addr:street":"Shady Grove Rd",
    "iso:country":"US",
    "sg:address":"15215 Shady Grove Rd",
    "sg:city":"Rockville",
    "sg:classifiers":[
        {
            "category":"Health Services",
            "subcategory":"Doctor",
            "type":"Services"
        }
    ],
    "sg:phone":"+1 301 869 1800",
    "sg:postcode":"20850",
    "sg:province":"MD",
    "sg:tags":[
        "physician",
        "surgeon"
    ],
    "wof:name":"ENT Specialists-Shady Grove",
    "wof:placetype":"venue"
},
  "geometry": {"coordinates":[-77.190494,39.104006],"type":"Point"}
}