{
  "type": "Feature",
  "properties": {
    "iso:country":"US",
    "sg:address":"10850 Hanna St",
    "sg:city":"Beltsville",
    "sg:classifiers":[
        {
            "category":"Retail",
            "subcategory":"Repair Shop",
            "type":"Services"
        }
    ],
    "sg:phone":"+1 301 595 0030",
    "sg:postcode":"20705",
    "sg:province":"MD",
    "sg:tags":[
        "upholsterer"
    ],
    "wof:name":"Hamilton Upholstery Co",
    "wof:placetype":"venue"
},
  "geometry": {"coordinates":[-76.90898900000001,39.028617],"type":"Point"}
}