{
  "type": "Feature",
  "properties": {
    "addr:full":"1628 N Salisbury Blvd Salisbury MD 21801",
    "addr:housenumber":"1628",
    "addr:postcode":"21801",
    "addr:street":"N Salisbury Blvd",
    "iso:country":"US",
    "sg:address":"1628 N Salisbury Blvd",
    "sg:city":"Salisbury",
    "sg:classifiers":[
        {
            "category":"Autos & Motor Vehicles",
            "subcategory":"Auto Supplies",
            "type":"Retail Goods"
        }
    ],
    "sg:phone":"+1 410 548 9291",
    "sg:postcode":"21801",
    "sg:province":"MD",
    "sg:tags":[
        "automobile",
        "parts"
    ],
    "wof:name":"Pep Boys Supercenter",
    "wof:placetype":"venue"
},
  "geometry": {"coordinates":[-75.58487100000001,38.382919],"type":"Point"}
}