{
  "type": "Feature",
  "properties": {
    "addr:full":"5400 Broadwater Ct Temple Hills MD 20748",
    "addr:housenumber":"5400",
    "addr:postcode":"20748",
    "addr:street":"Broadwater Ct",
    "iso:country":"US",
    "sg:address":"5400 Broadwater Ct",
    "sg:city":"Temple Hills",
    "sg:classifiers":[
        {
            "category":"Wholesale",
            "subcategory":"Computers",
            "type":"Manufacturing & Wholesale Goods"
        }
    ],
    "sg:phone":"+1 301 899 2244",
    "sg:postcode":"20748",
    "sg:province":"MD",
    "wof:name":"I C S",
    "wof:placetype":"venue"
},
  "geometry": {"coordinates":[-76.95765,38.815838],"type":"Point"}
}