{
  "type": "Feature",
  "properties": {
    "addr:full":"10810 Liberty Rd Frederick MD 21701",
    "addr:housenumber":"10810",
    "addr:postcode":"21701",
    "addr:street":"Liberty Rd",
    "iso:country":"US",
    "sg:address":"10810 Liberty Rd",
    "sg:city":"Frederick",
    "sg:classifiers":[
        {
            "category":"Sports & Exercise",
            "subcategory":"Golf",
            "type":"Entertainment"
        }
    ],
    "sg:phone":"+1 301 898 3035",
    "sg:postcode":"21701",
    "sg:province":"MD",
    "sg:tags":[
        "range",
        "practice"
    ],
    "wof:name":"Liberty Road Golf Center",
    "wof:placetype":"venue"
},
  "geometry": {"coordinates":[-77.288624,39.463927],"type":"Point"}
}