{
  "type": "Feature",
  "properties": {
    "iso:country":"US",
    "sg:address":"389 Grinstead Rd",
    "sg:city":"Severna Park",
    "sg:classifiers":[
        {
            "category":"Professional",
            "subcategory":"Computer Services",
            "type":"Services"
        }
    ],
    "sg:phone":"+1 410 544 3227",
    "sg:postcode":"21146",
    "sg:province":"MD",
    "sg:tags":[
        "consultant",
        "designer"
    ],
    "wof:name":"Infogroup",
    "wof:placetype":"venue"
},
  "geometry": {"coordinates":[-76.589598,39.089345],"type":"Point"}
}