{
  "type": "Feature",
  "properties": {
    "addr:full":"610A 4H Park Rd Queenstown MD 21658",
    "addr:housenumber":"610a 4h",
    "addr:postcode":"21658",
    "addr:street":"Park Rd",
    "iso:country":"US",
    "sg:address":"610A 4H Park Rd",
    "sg:city":"Queenstown",
    "sg:classifiers":[
        {
            "category":"Manufacturing",
            "subcategory":"Buildings",
            "type":"Manufacturing & Wholesale Goods"
        },
        {
            "category":"Building & Trades",
            "subcategory":"Construction",
            "type":"Services"
        }
    ],
    "sg:phone":"+1 410 827 4900",
    "sg:postcode":"21658",
    "sg:province":"MD",
    "sg:tags":[
        "home",
        "builder",
        "contractor"
    ],
    "wof:name":"Creative Countertops",
    "wof:placetype":"venue"
},
  "geometry": {"coordinates":[-76.130773,39.007702],"type":"Point"}
}