{
  "type": "Feature",
  "properties": {
    "iso:country":"US",
    "sg:address":"1126 Bay Ridge Rd",
    "sg:city":"Annapolis",
    "sg:classifiers":[
        {
            "category":"Professional",
            "subcategory":"Management & Consulting",
            "type":"Services"
        }
    ],
    "sg:phone":"+1 410 626 1413",
    "sg:postcode":"21403",
    "sg:province":"MD",
    "sg:tags":[
        "business"
    ],
    "wof:name":"J Cater Economic Consultants",
    "wof:placetype":"venue"
},
  "geometry": {"coordinates":[-76.475568,38.94206],"type":"Point"}
}