{
  "type": "Feature",
  "properties": {
    "addr:full":"4713 Leeds Ave Halethorpe MD 21227",
    "addr:housenumber":"4713",
    "addr:postcode":"21227",
    "addr:street":"Leeds Ave",
    "iso:country":"US",
    "sg:address":"4713 Leeds Ave",
    "sg:city":"Halethorpe",
    "sg:classifiers":[
        {
            "category":"Health Services",
            "subcategory":"Doctor",
            "type":"Services"
        }
    ],
    "sg:phone":"+1 410 247 4740",
    "sg:postcode":"21227",
    "sg:province":"MD",
    "wof:name":"Universal Surgical Associates",
    "wof:placetype":"venue"
},
  "geometry": {"coordinates":[-76.690697,39.257801],"type":"Point"}
}