{
  "type": "Feature",
  "properties": {
    "iso:country":"US",
    "sg:address":"3600 Clipper Mill Rd",
    "sg:city":"Baltimore",
    "sg:classifiers":[
        {
            "category":"Professional",
            "subcategory":"Art Services",
            "type":"Services"
        }
    ],
    "sg:phone":"+1 410 235 3250",
    "sg:postcode":"21211",
    "sg:province":"MD",
    "sg:tags":[
        "interior",
        "designer",
        "decorator"
    ],
    "wof:name":"The Austin Group",
    "wof:placetype":"venue"
},
  "geometry": {"coordinates":[-76.64052,39.328622],"type":"Point"}
}