{
  "type": "Feature",
  "properties": {
    "addr:full":"597 Brightwood Rd Millersville MD 21108",
    "addr:housenumber":"597",
    "addr:postcode":"21108",
    "addr:street":"Brightwood Rd",
    "iso:country":"US",
    "sg:address":"597 Brightwood Rd",
    "sg:city":"Millersville",
    "sg:classifiers":[
        {
            "category":"Personal",
            "type":"Services"
        }
    ],
    "sg:phone":"+1 410 987 0727",
    "sg:postcode":"21108",
    "sg:province":"MD",
    "sg:tags":[
        "therapist",
        "massage"
    ],
    "wof:name":"Caring Strokes Therapeutic",
    "wof:placetype":"venue"
},
  "geometry": {"coordinates":[-76.618612,39.108367],"type":"Point"}
}