{
  "type": "Feature",
  "properties": {
    "addr:full":"1409 Berwick Rd Towson MD 21204",
    "addr:housenumber":"1409",
    "addr:postcode":"21204",
    "addr:street":"Berwick Rd",
    "iso:country":"US",
    "sg:address":"1409 Berwick Rd",
    "sg:city":"Towson",
    "sg:classifiers":[
        {
            "category":"Real Estate",
            "subcategory":"Real Estate Services",
            "type":"Services"
        }
    ],
    "sg:phone":"+1 410 276 6444",
    "sg:postcode":"21204",
    "sg:province":"MD",
    "sg:tags":[
        "inspection"
    ],
    "wof:name":"Jack Reilly Associates Inc",
    "wof:placetype":"venue"
},
  "geometry": {"coordinates":[-76.642034,39.399364],"type":"Point"}
}