{
  "type": "Feature",
  "properties": {
    "addr:full":"1104 Clendenin St Baltimore MD 21217",
    "addr:housenumber":"1104",
    "addr:postcode":"21217",
    "addr:street":"Clendenin St",
    "iso:country":"US",
    "sg:address":"1104 Clendenin St",
    "sg:city":"Baltimore",
    "sg:classifiers":[
        {
            "category":"Professional",
            "subcategory":"Management & Consulting",
            "type":"Services"
        }
    ],
    "sg:phone":"+1 410 746 5201",
    "sg:postcode":"21217",
    "sg:province":"MD",
    "sg:tags":[
        "consultant"
    ],
    "wof:name":"Brighton Enterprises",
    "wof:placetype":"venue"
},
  "geometry": {"coordinates":[-76.63629299999999,39.310987],"type":"Point"}
}