{
  "type": "Feature",
  "properties": {
    "addr:full":"115 N Harrison St Easton MD 21601",
    "addr:housenumber":"115",
    "addr:postcode":"21601",
    "addr:street":"N Harrison St",
    "iso:country":"US",
    "sg:address":"115 N Harrison St",
    "sg:city":"Easton",
    "sg:classifiers":[
        {
            "category":"Real Estate",
            "subcategory":"Developer",
            "type":"Services"
        }
    ],
    "sg:phone":"+1 410 822 6123",
    "sg:postcode":"21601",
    "sg:province":"MD",
    "sg:tags":[
        "property",
        "subdivider"
    ],
    "wof:name":"Claiborne Resources Inc",
    "wof:placetype":"venue"
},
  "geometry": {"coordinates":[-76.07512199999999,38.776768],"type":"Point"}
}