{
  "type": "Feature",
  "properties": {
    "iso:country":"US",
    "sg:address":"115 N Harrison St",
    "sg:city":"Easton",
    "sg:classifiers":[
        {
            "category":"Real Estate",
            "subcategory":"Developer",
            "type":"Services"
        }
    ],
    "sg:phone":"+1 410 822 6123",
    "sg:postcode":"21601",
    "sg:province":"MD",
    "sg:tags":[
        "property",
        "subdivider"
    ],
    "wof:name":"Claiborne Resources Inc",
    "wof:placetype":"venue"
},
  "geometry": {"coordinates":[-76.075122,38.776768],"type":"Point"}
}