{
  "type": "Feature",
  "properties": {
    "addr:full":"2712 Thornbrook Ct Odenton MD 21113",
    "addr:housenumber":"2712",
    "addr:postcode":"21113",
    "addr:street":"Thornbrook Ct",
    "iso:country":"US",
    "sg:address":"2712 Thornbrook Ct",
    "sg:city":"Odenton",
    "sg:classifiers":[
        {
            "category":"Professional",
            "subcategory":"Advertising",
            "type":"Services"
        }
    ],
    "sg:phone":"+1 301 912 3912",
    "sg:postcode":"21113",
    "sg:province":"MD",
    "sg:tags":[
        "agency"
    ],
    "wof:name":"Taylor Wilson Advertising",
    "wof:placetype":"venue"
},
  "geometry": {"coordinates":[-76.727553,39.065059],"type":"Point"}
}