{
  "type": "Feature",
  "properties": {
    "addr:full":"11611 Silvergate Ln Bowie MD 20720",
    "addr:housenumber":"11611",
    "addr:postcode":"20720",
    "addr:street":"Silvergate Ln",
    "iso:country":"US",
    "sg:address":"11611 Silvergate Ln",
    "sg:city":"Bowie",
    "sg:classifiers":[
        {
            "category":"Building & Trades",
            "subcategory":"Construction",
            "type":"Services"
        }
    ],
    "sg:phone":"+1 301 464 3066",
    "sg:postcode":"20720",
    "sg:province":"MD",
    "sg:tags":[
        "home",
        "improvement"
    ],
    "wof:name":"ATR & Assoc",
    "wof:placetype":"venue"
},
  "geometry": {"coordinates":[-76.80372,38.956915],"type":"Point"}
}