{
  "type": "Feature",
  "properties": {
    "iso:country":"US",
    "sg:address":"12509 Monterey Cir",
    "sg:city":"Fort Washington",
    "sg:classifiers":[
        {
            "category":"Freight",
            "type":"Transportation"
        }
    ],
    "sg:phone":"+1 301 567 7326",
    "sg:postcode":"20744",
    "sg:province":"MD",
    "sg:tags":[
        "trucking"
    ],
    "wof:name":"C & M Trucking",
    "wof:placetype":"venue"
},
  "geometry": {"coordinates":[-77.018657,38.721075],"type":"Point"}
}