{
  "type": "Feature",
  "properties": {
    "addr:full":"13439 New Hampshire Ave Silver Spring MD 20904",
    "addr:housenumber":"13439",
    "addr:postcode":"20904",
    "addr:street":"New Hampshire Ave",
    "iso:country":"US",
    "sg:address":"13439 New Hampshire Ave",
    "sg:city":"Silver Spring",
    "sg:classifiers":[
        {
            "category":"Real Estate",
            "subcategory":"Real Estate Agent",
            "type":"Services"
        }
    ],
    "sg:phone":"+1 301 681 0540",
    "sg:postcode":"20904",
    "sg:province":"MD",
    "wof:name":"Weichert Realtors",
    "wof:placetype":"venue"
},
  "geometry": {"coordinates":[-77.00159600000001,39.07684],"type":"Point"}
}