{
  "type": "Feature",
  "properties": {
    "addr:full":"5210 Auth Rd Ste 401 Suitland MD 20746",
    "addr:postcode":"5210;20746",
    "addr:street":"Auth Rd Ste 401",
    "iso:country":"US",
    "sg:address":"5210 Auth Rd Ste 401",
    "sg:city":"Suitland",
    "sg:classifiers":[
        {
            "category":"Professional",
            "subcategory":"Engineering",
            "type":"Services"
        },
        {
            "category":"Professional",
            "subcategory":"Computer Services",
            "type":"Services"
        }
    ],
    "sg:phone":"+1 301 423 1042",
    "sg:postcode":"20746",
    "sg:province":"MD",
    "sg:tags":[
        "engineer",
        "consultant",
        "designer",
        "integration",
        "system"
    ],
    "sg:website":"http://www.chronos1.com",
    "wof:name":"United Air Temp Inc",
    "wof:placetype":"venue"
},
  "geometry": {"coordinates":[-76.917091,38.822899],"type":"Point"}
}