{
  "type": "Feature",
  "properties": {
    "addr:full":"7212 Carroll Ave Takoma Park MD 20912",
    "addr:housenumber":"7212",
    "addr:postcode":"20912",
    "addr:street":"Carroll Ave",
    "iso:country":"US",
    "sg:address":"7212 Carroll Ave",
    "sg:city":"Takoma Park",
    "sg:classifiers":[
        {
            "category":"Manufacturing",
            "subcategory":"Printing",
            "type":"Manufacturing & Wholesale Goods"
        }
    ],
    "sg:phone":"+1 301 270 8100",
    "sg:postcode":"20912",
    "sg:province":"MD",
    "sg:tags":[
        "commercial"
    ],
    "wof:name":"Takoma Letter Shop",
    "wof:placetype":"venue"
},
  "geometry": {"coordinates":[-77.008394,38.976689],"type":"Point"}
}