{
  "type": "Feature",
  "properties": {
    "addr:full":"146 E Main St Elkton MD 21921",
    "addr:housenumber":"146",
    "addr:postcode":"21921",
    "addr:street":"E Main St",
    "iso:country":"US",
    "sg:address":"146 E Main St",
    "sg:city":"Elkton",
    "sg:classifiers":[
        {
            "category":"Professional",
            "subcategory":"Lawyer & Legal Services",
            "type":"Services"
        }
    ],
    "sg:phone":"+1 410 398 1700",
    "sg:postcode":"21921",
    "sg:province":"MD",
    "sg:tags":[
        "attorney"
    ],
    "wof:name":"Bathon & Bathon",
    "wof:placetype":"venue"
},
  "geometry": {"coordinates":[-75.827594,39.608623],"type":"Point"}
}