{
  "type": "Feature",
  "properties": {
    "addr:full":"1094 Magothy Cir Annapolis MD 21409",
    "addr:housenumber":"1094",
    "addr:postcode":"21409",
    "addr:street":"Magothy Cir",
    "iso:country":"US",
    "sg:address":"1094 Magothy Cir",
    "sg:city":"Annapolis",
    "sg:classifiers":[
        {
            "category":"Banks & Credit Unions",
            "subcategory":"Investment Brokerage",
            "type":"Services"
        },
        {
            "category":"Banks & Credit Unions",
            "subcategory":"Financial Services",
            "type":"Services"
        }
    ],
    "sg:phone":"+1 410 349 0988",
    "sg:postcode":"21409",
    "sg:province":"MD",
    "sg:tags":[
        "advisory",
        "planner"
    ],
    "wof:name":"Shaker Financial Services",
    "wof:placetype":"venue"
},
  "geometry": {"coordinates":[-76.433823,39.038717],"type":"Point"}
}