{
  "type": "Feature",
  "properties": {
    "iso:country":"US",
    "sg:address":"111 Versailles Cir",
    "sg:city":"Baltimore",
    "sg:classifiers":[
        {
            "category":"Real Estate",
            "subcategory":"Real Estate Operator",
            "type":"Services"
        }
    ],
    "sg:phone":"+1 410 821 8811",
    "sg:postcode":"21204",
    "sg:province":"MD",
    "sg:tags":[
        "building",
        "apartment"
    ],
    "wof:name":"Town and Country Trust",
    "wof:placetype":"venue"
},
  "geometry": {"coordinates":[-76.62188,39.397591],"type":"Point"}
}