{
  "type": "Feature",
  "properties": {
    "addr:full":"1604 Valley Dr Westminster MD 21157",
    "addr:housenumber":"1604",
    "addr:postcode":"21157",
    "addr:street":"Valley Dr",
    "iso:country":"US",
    "sg:address":"1604 Valley Dr",
    "sg:city":"Westminster",
    "sg:classifiers":[
        {
            "category":"Building & Trades",
            "subcategory":"Construction",
            "type":"Services"
        }
    ],
    "sg:phone":"+1 410 875 5739",
    "sg:postcode":"21157",
    "sg:province":"MD",
    "sg:tags":[
        "concrete",
        "contractor"
    ],
    "wof:name":"Elite Concrete Construction",
    "wof:placetype":"venue"
},
  "geometry": {"coordinates":[-77.05336,39.461862],"type":"Point"}
}