{
  "type": "Feature",
  "properties": {
    "iso:country":"US",
    "sg:address":"600 Sprite Way",
    "sg:city":"Glen Burnie",
    "sg:classifiers":[
        {
            "category":"Building & Trades",
            "subcategory":"Construction",
            "type":"Services"
        }
    ],
    "sg:phone":"+1 443 623 6900",
    "sg:postcode":"21061",
    "sg:province":"MD",
    "sg:tags":[
        "contractor"
    ],
    "wof:name":"Sanford Contracting",
    "wof:placetype":"venue"
},
  "geometry": {"coordinates":[-76.63724999999999,39.124151],"type":"Point"}
}