{
  "type": "Feature",
  "properties": {
    "addr:full":"5405 Columbia Rd Columbia MD 21044",
    "addr:housenumber":"5405",
    "addr:postcode":"21044",
    "addr:street":"Columbia Rd",
    "iso:country":"US",
    "sg:address":"5405 Columbia Rd",
    "sg:city":"Columbia",
    "sg:classifiers":[
        {
            "category":"Professional",
            "subcategory":"Computer Services",
            "type":"Services"
        }
    ],
    "sg:phone":"+1 240 620 1974",
    "sg:postcode":"21044",
    "sg:province":"MD",
    "sg:tags":[
        "website",
        "design"
    ],
    "wof:name":"Onyx Web Design Inc",
    "wof:placetype":"venue"
},
  "geometry": {"coordinates":[-76.846974,39.232421],"type":"Point"}
}