{
  "type": "Feature",
  "properties": {
    "addr:full":"32 West St Annapolis MD 21401",
    "addr:housenumber":"32",
    "addr:postcode":"21401",
    "addr:street":"West St",
    "iso:country":"US",
    "sg:address":"32 West St",
    "sg:city":"Annapolis",
    "sg:classifiers":[
        {
            "category":"Shopping",
            "subcategory":"Clothing, Apparel, & Fashions",
            "type":"Retail Goods"
        }
    ],
    "sg:phone":"+1 410 280 9771",
    "sg:postcode":"21401",
    "sg:province":"MD",
    "sg:tags":[
        "lingerie"
    ],
    "wof:name":"A LA Mode",
    "wof:placetype":"venue"
},
  "geometry": {"coordinates":[-76.49629400000001,38.978267],"type":"Point"}
}