{
  "type": "Feature",
  "properties": {
    "addr:full":"845 Dora Pl Bel Air MD 21014",
    "addr:housenumber":"845",
    "addr:postcode":"21014",
    "addr:street":"Dora Pl",
    "iso:country":"US",
    "sg:address":"845 Dora Pl",
    "sg:city":"Bel Air",
    "sg:classifiers":[
        {
            "category":"Building & Trades",
            "subcategory":"Construction",
            "type":"Services"
        }
    ],
    "sg:phone":"+1 410 638 0732",
    "sg:postcode":"21014",
    "sg:province":"MD",
    "sg:tags":[
        "house"
    ],
    "wof:name":"P M Construction",
    "wof:placetype":"venue"
},
  "geometry": {"coordinates":[-76.344105,39.548417],"type":"Point"}
}