{
  "type": "Feature",
  "properties": {
    "addr:full":"6492 Landover Rd Hyattsville MD 20785",
    "addr:housenumber":"6492",
    "addr:postcode":"20785",
    "addr:street":"Landover Rd",
    "iso:country":"US",
    "sg:address":"6492 Landover Rd",
    "sg:city":"Hyattsville",
    "sg:classifiers":[
        {
            "category":"Health Services",
            "subcategory":"Clinic",
            "type":"Services"
        }
    ],
    "sg:phone":"+1 301 322 2630",
    "sg:postcode":"20785",
    "sg:province":"MD",
    "sg:tags":[
        "specialty",
        "outpatient"
    ],
    "wof:name":"Donna Liu & Associates",
    "wof:placetype":"venue"
},
  "geometry": {"coordinates":[-76.90230200000001,38.932141],"type":"Point"}
}