{
  "type": "Feature",
  "properties": {
    "iso:country":"US",
    "sg:address":"955 Bonifant St",
    "sg:city":"Silver Spring",
    "sg:classifiers":[
        {
            "category":"Shopping",
            "subcategory":"Used Merchandise",
            "type":"Retail Goods"
        }
    ],
    "sg:phone":"+1 301 587 6242",
    "sg:postcode":"20910",
    "sg:province":"MD",
    "wof:name":"Pennyworth Shop",
    "wof:placetype":"venue"
},
  "geometry": {"coordinates":[-77.025338,38.993956],"type":"Point"}
}