{
  "type": "Feature",
  "properties": {
    "addr:full":"8425 Shears Ct Laurel MD 20723",
    "addr:housenumber":"8425",
    "addr:postcode":"20723",
    "addr:street":"Shears Ct",
    "iso:country":"US",
    "sg:address":"8425 Shears Ct",
    "sg:city":"Laurel",
    "sg:classifiers":[
        {
            "category":"Professional",
            "subcategory":"Accounting & Tax Preparation",
            "type":"Services"
        }
    ],
    "sg:phone":"+1 301 490 1488",
    "sg:postcode":"20723",
    "sg:province":"MD",
    "sg:tags":[
        "accountant"
    ],
    "wof:name":"Paul K Verburg CPA PA",
    "wof:placetype":"venue"
},
  "geometry": {"coordinates":[-76.88578099999999,39.142126],"type":"Point"}
}