{
  "type": "Feature",
  "properties": {
    "iso:country":"US",
    "sg:address":"1532 Hollins St",
    "sg:city":"Baltimore",
    "sg:classifiers":[
        {
            "category":"Professional",
            "subcategory":"Business Services",
            "type":"Services"
        }
    ],
    "sg:phone":"+1 410 362 0002",
    "sg:postcode":"21223",
    "sg:province":"MD",
    "sg:tags":[
        "interior",
        "designer",
        "decorator"
    ],
    "wof:name":"Anthony Prado Iii",
    "wof:placetype":"venue"
},
  "geometry": {"coordinates":[-76.641366,39.287414],"type":"Point"}
}