{
  "type": "Feature",
  "properties": {
    "iso:country":"US",
    "sg:address":"1912 Forest Dr",
    "sg:city":"Annapolis",
    "sg:classifiers":[
        {
            "category":"Restaurant",
            "type":"Food & Drink"
        }
    ],
    "sg:phone":"+1 410 263 1011",
    "sg:postcode":"21401",
    "sg:province":"MD",
    "sg:tags":[
        "pizza"
    ],
    "wof:name":"Olives Mediterranean Market",
    "wof:placetype":"venue"
},
  "geometry": {"coordinates":[-76.526428,38.974585],"type":"Point"}
}