{
  "type": "Feature",
  "properties": {
    "iso:country":"US",
    "sg:address":"6 Berrymans Ln",
    "sg:city":"Reisterstown",
    "sg:classifiers":[
        {
            "category":"Retail",
            "subcategory":"Repair Shop",
            "type":"Services"
        }
    ],
    "sg:phone":"+1 410 833 8797",
    "sg:postcode":"21136",
    "sg:province":"MD",
    "wof:name":"Howard Lock & Key",
    "wof:placetype":"venue"
},
  "geometry": {"coordinates":[-76.825007,39.454208],"type":"Point"}
}