{
  "type": "Feature",
  "properties": {
    "addr:full":"17222 Spates Hill Rd Poolesville MD 20837",
    "addr:postcode":"17222;20837",
    "addr:street":"Spates Hill Rd",
    "iso:country":"US",
    "sg:address":"17222 Spates Hill Rd",
    "sg:city":"Poolesville",
    "sg:classifiers":[
        {
            "category":"Shopping",
            "subcategory":"Computers & Home Electronics",
            "type":"Retail Goods"
        }
    ],
    "sg:phone":"+1 301 785 3092",
    "sg:postcode":"20837",
    "sg:province":"MD",
    "sg:tags":[
        "audio"
    ],
    "wof:name":"A Bare Moose",
    "wof:placetype":"venue"
},
  "geometry": {"coordinates":[-77.393902,39.139377],"type":"Point"}
}