{
  "type": "Feature",
  "properties": {
    "iso:country":"US",
    "sg:address":"9009 Baltimore Rd",
    "sg:city":"Frederick",
    "sg:classifiers":[
        {
            "category":"Restaurant",
            "type":"Food & Drink"
        },
        {
            "category":"Food & Beverages",
            "subcategory":"Meat & Fish",
            "type":"Retail Goods"
        }
    ],
    "sg:phone":"+1 301 228 2722",
    "sg:postcode":"21704",
    "sg:province":"MD",
    "sg:tags":[
        "seafood",
        "market"
    ],
    "wof:name":"Jug Bridge Seafood",
    "wof:placetype":"venue"
},
  "geometry": {"coordinates":[-77.353216,39.396422],"type":"Point"}
}