{
  "type": "Feature",
  "properties": {
    "iso:country":"US",
    "sg:address":"6931 Arlington Rd Suite T-200",
    "sg:city":"Bethesda",
    "sg:classifiers":[
        {
            "category":"Professional",
            "type":"Services"
        }
    ],
    "sg:phone":"+1 240 333 7324",
    "sg:postcode":"20814",
    "sg:province":"MD",
    "sg:website":"www.citypl.com/menu.htm",
    "wof:name":"City Express Courier Service",
    "wof:placetype":"venue"
},
  "geometry": {"coordinates":[-77.098328,38.978803],"type":"Point"}
}