{
  "type": "Feature",
  "properties": {
    "addr:full":"7720 Wisconsin Ave Bethesda MD 20814",
    "addr:housenumber":"7720",
    "addr:postcode":"20814",
    "addr:street":"Wisconsin Ave",
    "iso:country":"US",
    "sg:address":"7720 Wisconsin Ave",
    "sg:city":"Bethesda",
    "sg:classifiers":[
        {
            "category":"Banks & Credit Unions",
            "subcategory":"Bank",
            "type":"Services"
        }
    ],
    "sg:phone":"+1 301 951 4288",
    "sg:postcode":"20814",
    "sg:province":"MD",
    "sg:tags":[
        "financing"
    ],
    "wof:name":"Security Financial & Invstmnt",
    "wof:placetype":"venue"
},
  "geometry": {"coordinates":[-77.09467600000001,38.986049],"type":"Point"}
}