{
  "type": "Feature",
  "properties": {
    "addr:full":"2801 Wilkens Ave Baltimore MD 21223",
    "addr:housenumber":"2801",
    "addr:postcode":"21223",
    "addr:street":"Wilkens Ave",
    "iso:country":"US",
    "sg:address":"2801 Wilkens Ave",
    "sg:city":"Baltimore",
    "sg:classifiers":[
        {
            "category":"Restaurant",
            "type":"Food & Drink"
        }
    ],
    "sg:phone":"+1 410 233 7550",
    "sg:postcode":"21223",
    "sg:province":"MD",
    "sg:tags":[
        "eating"
    ],
    "wof:name":"Andre's Pit Beef & Deli",
    "wof:placetype":"venue"
},
  "geometry": {"coordinates":[-76.662691,39.276734],"type":"Point"}
}