{
  "type": "Feature",
  "properties": {
    "addr:full":"12025 Bronzegate Pl Silver Spring MD 20904",
    "addr:housenumber":"12025",
    "addr:postcode":"20904",
    "addr:street":"Bronzegate Pl",
    "iso:country":"US",
    "sg:address":"12025 Bronzegate Pl",
    "sg:city":"Silver Spring",
    "sg:classifiers":[
        {
            "category":"Real Estate",
            "subcategory":"Architect",
            "type":"Services"
        }
    ],
    "sg:phone":"+1 301 680 3631",
    "sg:postcode":"20904",
    "sg:province":"MD",
    "wof:name":"A & N Architectural",
    "wof:placetype":"venue"
},
  "geometry": {"coordinates":[-76.972848,39.052952],"type":"Point"}
}