{
  "type": "Feature",
  "properties": {
    "addr:full":"3730 Rhode Island Ave Brentwood MD 20722",
    "addr:housenumber":"3730",
    "addr:postcode":"20722",
    "addr:street":"Rhode Island Ave",
    "iso:country":"US",
    "sg:address":"3730 Rhode Island Ave",
    "sg:city":"Brentwood",
    "sg:classifiers":[
        {
            "category":"Autos & Motor Vehicles",
            "subcategory":"Fuel & Gas Station",
            "type":"Retail Goods"
        }
    ],
    "sg:phone":"+1 301 277 2376",
    "sg:postcode":"20722",
    "sg:province":"MD",
    "wof:name":"Brentwood Sunoco",
    "wof:placetype":"venue"
},
  "geometry": {"coordinates":[-76.95740000000001,38.938169],"type":"Point"}
}