{
  "type": "Feature",
  "properties": {
    "iso:country":"US",
    "sg:address":"12620 Crain Hwy",
    "sg:city":"Newburg",
    "sg:classifiers":[
        {
            "category":"Railroad",
            "type":"Transportation"
        },
        {
            "category":"Train Station",
            "subcategory":"Rail",
            "type":"Transportation"
        }
    ],
    "sg:phone":"+1 301 259 0643",
    "sg:postcode":"20664",
    "sg:province":"MD",
    "sg:tags":[
        "contractor"
    ],
    "wof:name":"Csx Technology",
    "wof:placetype":"venue"
},
  "geometry": {"coordinates":[-76.970082,38.365149],"type":"Point"}
}