{
  "type": "Feature",
  "properties": {
    "addr:full":"8 Sudbrook Ln Pikesville MD 21208",
    "addr:housenumber":"8",
    "addr:postcode":"21208",
    "addr:street":"Sudbrook Ln",
    "iso:country":"US",
    "sg:address":"8 Sudbrook Ln",
    "sg:city":"Pikesville",
    "sg:classifiers":[
        {
            "category":"Health Services",
            "subcategory":"Medical Lab",
            "type":"Services"
        }
    ],
    "sg:phone":"+1 410 653 0413",
    "sg:postcode":"21208",
    "sg:province":"MD",
    "sg:tags":[
        "laboratory"
    ],
    "wof:name":"Joseph Benamor & Dental Lab",
    "wof:placetype":"venue"
},
  "geometry": {"coordinates":[-76.723449,39.374023],"type":"Point"}
}