{
  "type": "Feature",
  "properties": {
    "iso:country":"US",
    "sg:address":"11 E Mount Royal Ave",
    "sg:city":"Baltimore",
    "sg:classifiers":[
        {
            "category":"Wholesale",
            "subcategory":"Office Equipment",
            "type":"Manufacturing & Wholesale Goods"
        }
    ],
    "sg:phone":"+1 410 247 7533",
    "sg:postcode":"21202",
    "sg:province":"MD",
    "sg:tags":[
        "machine",
        "duplicating",
        "copying"
    ],
    "wof:name":"Reliable Office Technologies",
    "wof:placetype":"venue"
},
  "geometry": {"coordinates":[-76.614617,39.305513],"type":"Point"}
}