{
  "type": "Feature",
  "properties": {
    "iso:country":"US",
    "sg:address":"18 Franklin Blvd",
    "sg:city":"Reisterstown",
    "sg:classifiers":[
        {
            "category":"Restaurant",
            "type":"Food & Drink"
        }
    ],
    "sg:phone":"+1 410 833 5008",
    "sg:postcode":"21136",
    "sg:province":"MD",
    "sg:tags":[
        "pizza"
    ],
    "sg:website":"http://www.lucascompaniesinc.com",
    "wof:name":"Luca's Pizza",
    "wof:placetype":"venue"
},
  "geometry": {"coordinates":[-76.81504099999999,39.446671],"type":"Point"}
}