{
  "type": "Feature",
  "properties": {
    "iso:country":"US",
    "sg:address":"700 Wildwood Pkwy",
    "sg:city":"Baltimore",
    "sg:classifiers":[
        {
            "category":"Social Services",
            "subcategory":"Child Care",
            "type":"Services"
        }
    ],
    "sg:phone":"+1 410 947 6880",
    "sg:postcode":"21229",
    "sg:province":"MD",
    "wof:name":"Wee Care Learning Ctr",
    "wof:placetype":"venue"
},
  "geometry": {"coordinates":[-76.68399,39.296319],"type":"Point"}
}