{
  "type": "Feature",
  "properties": {
    "iso:country":"US",
    "sg:address":"40 National Hwy",
    "sg:city":"Cumberland",
    "sg:classifiers":[
        {
            "category":"Food & Beverages",
            "subcategory":"Specialty",
            "type":"Retail Goods"
        }
    ],
    "sg:phone":"+1 301 722 6673",
    "sg:postcode":"21502",
    "sg:province":"MD",
    "sg:tags":[
        "health",
        "diet"
    ],
    "wof:name":"Four Tree Herb Shoppe",
    "wof:placetype":"venue"
},
  "geometry": {"coordinates":[-78.793341,39.669167],"type":"Point"}
}