{
  "type": "Feature",
  "properties": {
    "addr:full":"21712 Great Mills Rd Lexington Park MD 20653",
    "addr:housenumber":"21712",
    "addr:postcode":"20653",
    "addr:street":"Great Mills Rd",
    "iso:country":"US",
    "sg:address":"21712 Great Mills Rd",
    "sg:city":"Lexington Park",
    "sg:classifiers":[
        {
            "category":"Home & Garden",
            "subcategory":"Household Appliances",
            "type":"Retail Goods"
        }
    ],
    "sg:phone":"+1 301 862 4310",
    "sg:postcode":"20653",
    "sg:province":"MD",
    "sg:tags":[
        "machine",
        "sewing"
    ],
    "wof:name":"Southern Maryland Vacuum Ctr",
    "wof:placetype":"venue"
},
  "geometry": {"coordinates":[-76.455135,38.264653],"type":"Point"}
}