{
  "type": "Feature",
  "properties": {
    "iso:country":"US",
    "sg:address":"8626 Liberty Rd",
    "sg:city":"Randallstown",
    "sg:classifiers":[
        {
            "category":"Professional",
            "subcategory":"Accounting & Tax Preparation",
            "type":"Services"
        }
    ],
    "sg:phone":"+1 410 496 4428",
    "sg:postcode":"21133",
    "sg:province":"MD",
    "sg:tags":[
        "return",
        "filing"
    ],
    "wof:name":"Amity Tax & Financial Inc",
    "wof:placetype":"venue"
},
  "geometry": {"coordinates":[-76.781092,39.362403],"type":"Point"}
}