{
  "type": "Feature",
  "properties": {
    "addr:full":"513 E 36th St Baltimore MD 21218",
    "addr:housenumber":"513",
    "addr:postcode":"21218",
    "addr:street":"E 36Th St",
    "iso:country":"US",
    "sg:address":"513 E 36th St",
    "sg:city":"Baltimore",
    "sg:classifiers":[
        {
            "category":"Organizations",
            "subcategory":"Religious Organization",
            "type":"Services"
        }
    ],
    "sg:phone":"+1 410 235 4788",
    "sg:postcode":"21218",
    "sg:province":"MD",
    "sg:tags":[
        "church"
    ],
    "wof:name":"Mt Oliver Missionary Baptist",
    "wof:placetype":"venue"
},
  "geometry": {"coordinates":[-76.609494,39.332545],"type":"Point"}
}