{
  "type": "Feature",
  "properties": {
    "addr:full":"21511 Flintstone Dr NE Flintstone MD 21530",
    "addr:housenumber":"21511",
    "addr:postcode":"21530",
    "addr:street":"Flintstone Dr Ne",
    "iso:country":"US",
    "sg:address":"21511 Flintstone Dr NE",
    "sg:city":"Flintstone",
    "sg:classifiers":[
        {
            "category":"Restaurant",
            "type":"Food & Drink"
        },
        {
            "category":"Bakery",
            "type":"Food & Drink"
        }
    ],
    "sg:phone":"+1 301 478 3696",
    "sg:postcode":"21530",
    "sg:province":"MD",
    "wof:name":"Alpine Pantry & Bakery",
    "wof:placetype":"venue"
},
  "geometry": {"coordinates":[-78.57363100000001,39.708279],"type":"Point"}
}