{
  "type": "Feature",
  "properties": {
    "addr:full":"801 S Dallas St Baltimore MD 21231",
    "addr:housenumber":"801",
    "addr:postcode":"21231",
    "addr:street":"S Dallas St",
    "iso:country":"US",
    "sg:address":"801 S Dallas St",
    "sg:city":"Baltimore",
    "sg:classifiers":[
        {
            "category":"Professional",
            "type":"Services"
        }
    ],
    "sg:phone":"+1 410 563 4038",
    "sg:postcode":"21231",
    "sg:province":"MD",
    "wof:name":"Maureen Haines",
    "wof:placetype":"venue"
},
  "geometry": {"coordinates":[-76.59582399999999,39.281386],"type":"Point"}
}