{
  "type": "Feature",
  "properties": {
    "iso:country":"US",
    "sg:address":"2424 Hunting Ln",
    "sg:city":"Waldorf",
    "sg:classifiers":[
        {
            "category":"Professional",
            "subcategory":"Engineering",
            "type":"Services"
        }
    ],
    "sg:phone":"+1 301 870 5270",
    "sg:postcode":"20601",
    "sg:province":"MD",
    "sg:tags":[
        "business"
    ],
    "wof:name":"Meuchel Richard G",
    "wof:placetype":"venue"
},
  "geometry": {"coordinates":[-76.906588,38.644013],"type":"Point"}
}