{
  "type": "Feature",
  "properties": {
    "addr:full":"505 W Lexington St Baltimore MD 21201",
    "addr:housenumber":"505",
    "addr:postcode":"21201",
    "addr:street":"W Lexington St",
    "iso:country":"US",
    "sg:address":"505 W Lexington St",
    "sg:city":"Baltimore",
    "sg:classifiers":[
        {
            "category":"Shopping",
            "subcategory":"Department Store",
            "type":"Retail Goods"
        },
        {
            "category":"Food & Beverages",
            "subcategory":"Groceries & Convenience Stores",
            "type":"Retail Goods"
        }
    ],
    "sg:phone":"+1 410 837 4352",
    "sg:postcode":"21201",
    "sg:province":"MD",
    "sg:tags":[
        "variety"
    ],
    "wof:name":"Young Mart",
    "wof:placetype":"venue"
},
  "geometry": {"coordinates":[-76.62311200000001,39.29141],"type":"Point"}
}