{
  "type": "Feature",
  "properties": {
    "addr:full":"1777 Reisterstown Rd Ste A12 Pikesville MD 21208",
    "addr:housenumber":"1777",
    "addr:postcode":"21208",
    "addr:street":"Reisterstown Rd Ste A12",
    "iso:country":"US",
    "sg:address":"1777 Reisterstown Rd Ste A12",
    "sg:city":"Pikesville",
    "sg:classifiers":[
        {
            "category":"Real Estate",
            "subcategory":"Real Estate Services",
            "type":"Services"
        },
        {
            "category":"Real Estate",
            "subcategory":"Real Estate Agent",
            "type":"Services"
        }
    ],
    "sg:phone":"+1 410 653 7666",
    "sg:postcode":"21208",
    "sg:province":"MD",
    "sg:tags":[
        "buyer",
        "broker"
    ],
    "sg:website":"http://www.century21.com",
    "wof:name":"Century 21",
    "wof:placetype":"venue"
},
  "geometry": {"coordinates":[-76.73484000000001,39.385511],"type":"Point"}
}