{
  "type": "Feature",
  "properties": {
    "addr:full":"3029 Cluster Pines Ct Ellicott City MD 21042",
    "addr:housenumber":"3029",
    "addr:postcode":"21042",
    "addr:street":"Cluster Pines Ct",
    "iso:country":"US",
    "sg:address":"3029 Cluster Pines Ct",
    "sg:city":"Ellicott City",
    "sg:classifiers":[
        {
            "category":"Building & Trades",
            "subcategory":"Landscaping Services",
            "type":"Services"
        }
    ],
    "sg:phone":"+1 410 418 5616",
    "sg:postcode":"21042",
    "sg:province":"MD",
    "wof:name":"Starrs Lawncare",
    "wof:placetype":"venue"
},
  "geometry": {"coordinates":[-76.877728,39.286913],"type":"Point"}
}