{
  "type": "Feature",
  "properties": {
    "iso:country":"US",
    "sg:address":"32 Oak Shade Rd",
    "sg:city":"Gaithersburg",
    "sg:classifiers":[
        {
            "category":"Shopping",
            "subcategory":"Catalog Store",
            "type":"Retail Goods"
        }
    ],
    "sg:phone":"+1 877 424 1138",
    "sg:postcode":"20878",
    "sg:province":"MD",
    "sg:tags":[
        "mail",
        "order",
        "online"
    ],
    "wof:name":"Fuller Brush Co A Customer Service Number Nationwide Toll Free",
    "wof:placetype":"venue"
},
  "geometry": {"coordinates":[-77.235366,39.149071],"type":"Point"}
}