{
  "type": "Feature",
  "properties": {
    "iso:country":"US",
    "sg:address":"960 W Pulaski Hwy",
    "sg:city":"Elkton",
    "sg:classifiers":[
        {
            "category":"Real Estate",
            "subcategory":"Real Estate Agent",
            "type":"Services"
        }
    ],
    "sg:phone":"+1 410 398 5005",
    "sg:postcode":"21921",
    "sg:province":"MD",
    "sg:website":"www.selcon.com",
    "wof:name":"Seller's Connection",
    "wof:placetype":"venue"
},
  "geometry": {"coordinates":[-75.88874199999999,39.609105],"type":"Point"}
}