{
  "type": "Feature",
  "properties": {
    "addr:full":"2509 Pennsylvania Ave Baltimore MD 21217",
    "addr:housenumber":"2509",
    "addr:postcode":"21217",
    "addr:street":"Pennsylvania Ave",
    "iso:country":"US",
    "sg:address":"2509 Pennsylvania Ave",
    "sg:city":"Baltimore",
    "sg:classifiers":[
        {
            "category":"Shopping",
            "subcategory":"Pharmacy",
            "type":"Retail Goods"
        }
    ],
    "sg:phone":"+1 410 225 2091",
    "sg:postcode":"21217",
    "sg:province":"MD",
    "sg:tags":[
        "drugstore"
    ],
    "sg:website":"www.cvs.com",
    "wof:name":"CVS Pharmacy",
    "wof:placetype":"venue"
},
  "geometry": {"coordinates":[-76.6427,39.310101],"type":"Point"}
}