{
  "type": "Feature",
  "properties": {
    "addr:full":"10001 Pulaski Hwy Baltimore MD 21220",
    "addr:housenumber":"10001",
    "addr:postcode":"21220",
    "addr:street":"Pulaski Hwy",
    "iso:country":"US",
    "sg:address":"10001 Pulaski Hwy",
    "sg:city":"Baltimore",
    "sg:classifiers":[
        {
            "category":"Autos & Motor Vehicles",
            "subcategory":"Automobile Sales",
            "type":"Retail Goods"
        }
    ],
    "sg:phone":"+1 410 687 0504",
    "sg:postcode":"21220",
    "sg:province":"MD",
    "sg:tags":[
        "car",
        "dealer"
    ],
    "wof:name":"B & L Motors",
    "wof:placetype":"venue"
},
  "geometry": {"coordinates":[-76.444312,39.361805],"type":"Point"}
}