{
  "type": "Feature",
  "properties": {
    "iso:country":"US",
    "sg:address":"4114 Mitscher Ct",
    "sg:city":"Kensington",
    "sg:classifiers":[
        {
            "category":"Professional",
            "subcategory":"Computer Services",
            "type":"Services"
        }
    ],
    "sg:phone":"+1 301 204 3716",
    "sg:postcode":"20895",
    "sg:province":"MD",
    "sg:tags":[
        "iphone-apps",
        "customized",
        "microsites",
        "web-sites",
        "css",
        "xml",
        "xhtml",
        "javascript",
        "api--jquery",
        "maps"
    ],
    "sg:website":"http://got-apps.com",
    "wof:name":"Got Apps?",
    "wof:placetype":"venue"
},
  "geometry": {"coordinates":[-77.082112,39.037888],"type":"Point"}
}