{
  "type": "Feature",
  "properties": {
    "addr:full":"20010 Century Blvd Gaithersburg MD 20874",
    "addr:housenumber":"20010",
    "addr:postcode":"20874",
    "addr:street":"Century Blvd",
    "iso:country":"US",
    "sg:address":"20010 Century Blvd",
    "sg:city":"Gaithersburg",
    "sg:classifiers":[
        {
            "category":"Insurance",
            "subcategory":"Insurance Agent",
            "type":"Services"
        }
    ],
    "sg:phone":"+1 301 417 1377",
    "sg:postcode":"20874",
    "sg:province":"MD",
    "wof:name":"Allstate",
    "wof:placetype":"venue"
},
  "geometry": {"coordinates":[-77.261605,39.184104],"type":"Point"}
}