{
  "type": "Feature",
  "properties": {
    "iso:country":"US",
    "sg:address":"3100 Wyman Park Dr",
    "sg:city":"Baltimore",
    "sg:classifiers":[
        {
            "category":"Health Services",
            "subcategory":"Doctor",
            "type":"Services"
        },
        {
            "category":"Health Services",
            "subcategory":"Health Practitioner",
            "type":"Services"
        }
    ],
    "sg:phone":"+1 410 338 3169",
    "sg:postcode":"21211",
    "sg:province":"MD",
    "sg:tags":[
        "physician",
        "ophthalmology",
        "surgeons",
        "surgeon"
    ],
    "wof:name":"Wilmer Eye Institute At Wyman Park",
    "wof:placetype":"venue"
},
  "geometry": {"coordinates":[-76.622528,39.325809],"type":"Point"}
}