{
  "type": "Feature",
  "properties": {
    "addr:full":"7721 Barlowe Rd Hyattsville MD 20785",
    "addr:housenumber":"7721",
    "addr:postcode":"20785",
    "addr:street":"Barlowe Rd",
    "iso:country":"US",
    "sg:address":"7721 Barlowe Rd",
    "sg:city":"Hyattsville",
    "sg:classifiers":[
        {
            "category":"Organizations",
            "subcategory":"Membership Organization",
            "type":"Services"
        }
    ],
    "sg:phone":"+1 301 341 1119",
    "sg:postcode":"20785",
    "sg:province":"MD",
    "sg:tags":[
        "athletic"
    ],
    "wof:name":"Palmer Park Boys & Girls Club",
    "wof:placetype":"venue"
},
  "geometry": {"coordinates":[-76.873515,38.918229],"type":"Point"}
}