{
  "type": "Feature",
  "properties": {
    "addr:full":"200 Caraway Rd Apt. 2A Reisterstown MD 21136",
    "addr:housenumber":"200;2a",
    "addr:postcode":"21136",
    "addr:street":"Caraway Rd",
    "iso:country":"US",
    "sg:address":"200 Caraway Rd Apt. 2A",
    "sg:city":"Reisterstown",
    "sg:classifiers":[
        {
            "category":"Building & Trades",
            "subcategory":"Construction",
            "type":"Services"
        }
    ],
    "sg:phone":"+1 410 858 1857",
    "sg:postcode":"21136",
    "sg:province":"MD",
    "sg:tags":[
        "altering",
        "remodeling",
        "contractor"
    ],
    "sg:website":"http://jdcarpetandtile.com",
    "wof:name":"JD's Carpet Tile/Installation",
    "wof:placetype":"venue"
},
  "geometry": {"coordinates":[-76.82343299999999,39.444031],"type":"Point"}
}