{
  "type": "Feature",
  "properties": {
    "iso:country":"US",
    "sg:address":"3642 Castle Ter",
    "sg:city":"Silver Spring",
    "sg:classifiers":[
        {
            "category":"Wholesale",
            "subcategory":"Medical Equipment & Supplies",
            "type":"Manufacturing & Wholesale Goods"
        }
    ],
    "sg:phone":"+1 301 890 7216",
    "sg:postcode":"20904",
    "sg:province":"MD",
    "sg:tags":[
        "physician",
        "surgeon"
    ],
    "wof:name":"Pro Cure Medical Equipment",
    "wof:placetype":"venue"
},
  "geometry": {"coordinates":[-76.94319,39.084997],"type":"Point"}
}