{
  "type": "Feature",
  "properties": {
    "addr:full":"3512 Old Silver Hill Rd Suitland MD 20746",
    "addr:housenumber":"3512",
    "addr:postcode":"20746",
    "addr:street":"Old Silver Hill Rd",
    "iso:country":"US",
    "sg:address":"3512 Old Silver Hill Rd",
    "sg:city":"Suitland",
    "sg:classifiers":[
        {
            "category":"Organizations",
            "subcategory":"Religious Organization",
            "type":"Services"
        }
    ],
    "sg:phone":"+1 301 423 7094",
    "sg:postcode":"20746",
    "sg:province":"MD",
    "wof:name":"Delivrnce Frwill Baptst Church",
    "wof:placetype":"venue"
},
  "geometry": {"coordinates":[-76.949381,38.843908],"type":"Point"}
}