{
  "type": "Feature",
  "properties": {
    "addr:full":"1255 E Randolph Rd Silver Spring MD 20904",
    "addr:housenumber":"1255",
    "addr:postcode":"20904",
    "addr:street":"E Randolph Rd",
    "iso:country":"US",
    "sg:address":"1255 E Randolph Rd",
    "sg:city":"Silver Spring",
    "sg:classifiers":[
        {
            "category":"Banks & Credit Unions",
            "subcategory":"Investment Brokerage",
            "type":"Services"
        }
    ],
    "sg:phone":"+1 301 236 5710",
    "sg:postcode":"20904",
    "sg:province":"MD",
    "wof:name":"Pfp Corp",
    "wof:placetype":"venue"
},
  "geometry": {"coordinates":[-76.986707,39.06869],"type":"Point"}
}