{
  "type": "Feature",
  "properties": {
    "addr:full":"8300 Guilford Rd Columbia MD 21046",
    "addr:housenumber":"8300",
    "addr:postcode":"21046",
    "addr:street":"Guilford Rd",
    "iso:country":"US",
    "sg:address":"8300 Guilford Rd",
    "sg:city":"Columbia",
    "sg:classifiers":[
        {
            "category":"Personal",
            "subcategory":"Barber",
            "type":"Services"
        }
    ],
    "sg:phone":"+1 410 290 5983",
    "sg:postcode":"21046",
    "sg:province":"MD",
    "wof:name":"Robert Barber",
    "wof:placetype":"venue"
},
  "geometry": {"coordinates":[-76.869916,39.175897],"type":"Point"}
}