{
  "type": "Feature",
  "properties": {
    "addr:full":"900 Reisterstown Road Pikesville MD 21208",
    "addr:housenumber":"900",
    "addr:postcode":"21208",
    "addr:street":"Reisterstown Road",
    "iso:country":"US",
    "sg:address":"900 Reisterstown Road",
    "sg:city":"Pikesville",
    "sg:classifiers":[
        {
            "category":"Professional",
            "subcategory":"Lawyer & Legal Services",
            "type":"Services"
        }
    ],
    "sg:phone":"+1 516 816 1816",
    "sg:postcode":"21208",
    "sg:province":"MD",
    "sg:tags":[
        "attorney",
        "law",
        "immigration"
    ],
    "wof:name":"Angela Nwadiogbu, Esq.",
    "wof:placetype":"venue"
},
  "geometry": {"coordinates":[-76.72081,39.37212],"type":"Point"}
}