{
  "type": "Feature",
  "properties": {
    "iso:country":"US",
    "sg:address":"8737 Colesville Rd",
    "sg:city":"Silver Spring",
    "sg:classifiers":[
        {
            "category":"Health Services",
            "subcategory":"Clinic",
            "type":"Services"
        }
    ],
    "sg:phone":"+1 301 608 3764",
    "sg:postcode":"20910",
    "sg:province":"MD",
    "sg:tags":[
        "specialty",
        "outpatient"
    ],
    "wof:name":"Dennis OBrien",
    "wof:placetype":"venue"
},
  "geometry": {"coordinates":[-77.02636,38.998458],"type":"Point"}
}