{
  "type": "Feature",
  "properties": {
    "addr:full":"1710 Aliceanna St Baltimore MD 21231",
    "addr:housenumber":"1710",
    "addr:postcode":"21231",
    "addr:street":"Aliceanna St",
    "iso:country":"US",
    "sg:address":"1710 Aliceanna St",
    "sg:city":"Baltimore",
    "sg:classifiers":[
        {
            "category":"Bars & Pubs",
            "type":"Food & Drink"
        }
    ],
    "sg:phone":"+1 410 276 6388",
    "sg:postcode":"21231",
    "sg:province":"MD",
    "sg:tags":[
        "club",
        "night"
    ],
    "sg:website":"www.fullmoon-saloon.com",
    "wof:name":"Full Moon Saloon-Blues",
    "wof:placetype":"venue"
},
  "geometry": {"coordinates":[-76.59321799999999,39.283543],"type":"Point"}
}