{
  "type": "Feature",
  "properties": {
    "iso:country":"US",
    "sg:address":"4111 Old Washington Rd",
    "sg:city":"Waldorf",
    "sg:classifiers":[
        {
            "category":"Building & Trades",
            "subcategory":"Construction",
            "type":"Services"
        },
        {
            "category":"Home & Garden",
            "subcategory":"Furniture",
            "type":"Retail Goods"
        }
    ],
    "sg:phone":"+1 240 607 2878",
    "sg:postcode":"20602",
    "sg:province":"MD",
    "sg:tags":[
        "maker",
        "cabinet"
    ],
    "wof:name":"Michael Mowrey",
    "wof:placetype":"venue"
},
  "geometry": {"coordinates":[-76.933414,38.60002],"type":"Point"}
}