{
  "type": "Feature",
  "properties": {
    "addr:full":"10805 Nantucket Ter Potomac MD 20854",
    "addr:housenumber":"10805",
    "addr:postcode":"20854",
    "addr:street":"Nantucket Ter",
    "iso:country":"US",
    "sg:address":"10805 Nantucket Ter",
    "sg:city":"Potomac",
    "sg:classifiers":[
        {
            "category":"Health Services",
            "subcategory":"Doctor",
            "type":"Services"
        }
    ],
    "sg:phone":"+1 301 299 5000",
    "sg:postcode":"20854",
    "sg:province":"MD",
    "wof:name":"Dr Suresh C Gupta MD",
    "wof:placetype":"venue"
},
  "geometry": {"coordinates":[-77.194979,39.032214],"type":"Point"}
}