{
  "type": "Feature",
  "properties": {
    "iso:country":"US",
    "sg:address":"1206 York Rd",
    "sg:city":"Lutherville",
    "sg:classifiers":[
        {
            "category":"Health Services",
            "subcategory":"Health Practitioner",
            "type":"Services"
        }
    ],
    "sg:phone":"+1 410 583 9980",
    "sg:postcode":"21093",
    "sg:province":"MD",
    "sg:tags":[
        "therapist",
        "physical"
    ],
    "wof:name":"Baitch Physical Therapy",
    "wof:placetype":"venue"
},
  "geometry": {"coordinates":[-76.614338,39.416201],"type":"Point"}
}