{
  "type": "Feature",
  "properties": {
    "addr:full":"8004 Marlboro Pike Forestville MD 20747",
    "addr:housenumber":"8004",
    "addr:postcode":"20747",
    "addr:street":"Marlboro Pike",
    "iso:country":"US",
    "sg:address":"8004 Marlboro Pike",
    "sg:city":"Forestville",
    "sg:classifiers":[
        {
            "category":"Wholesale",
            "subcategory":"Vending Machines",
            "type":"Manufacturing & Wholesale Goods"
        }
    ],
    "sg:phone":"+1 301 735 6366",
    "sg:postcode":"20747",
    "sg:province":"MD",
    "wof:name":"Vend Lease Co Inc",
    "wof:placetype":"venue"
},
  "geometry": {"coordinates":[-76.866317,38.841805],"type":"Point"}
}