{
  "type": "Feature",
  "properties": {
    "iso:country":"US",
    "sg:address":"9601 Marathon Ter",
    "sg:city":"Gaithersburg",
    "sg:classifiers":[
        {
            "category":"Professional",
            "subcategory":"Management & Consulting",
            "type":"Services"
        }
    ],
    "sg:phone":"+1 301 990 2481",
    "sg:postcode":"20878",
    "sg:province":"MD",
    "wof:name":"A Center For Self-Development",
    "wof:placetype":"venue"
},
  "geometry": {"coordinates":[-77.195411,39.113067],"type":"Point"}
}