{
  "type": "Feature",
  "properties": {
    "iso:country":"US",
    "sg:address":"100 E Pratt St",
    "sg:city":"Baltimore",
    "sg:classifiers":[
        {
            "category":"Professional",
            "subcategory":"Advertising",
            "type":"Services"
        }
    ],
    "sg:phone":"+1 410 576 9181",
    "sg:postcode":"21202",
    "sg:province":"MD",
    "sg:tags":[
        "mail"
    ],
    "wof:name":"OLWEN Intl Direct Mail Inc",
    "wof:placetype":"venue"
},
  "geometry": {"coordinates":[-76.612128,39.286603],"type":"Point"}
}