{
  "type": "Feature",
  "properties": {
    "addr:full":"4215 Knox Rd College Park MD 20740",
    "addr:housenumber":"4215",
    "addr:postcode":"20740",
    "addr:street":"Knox Rd",
    "iso:country":"US",
    "sg:address":"4215 Knox Rd",
    "sg:city":"College Park",
    "sg:classifiers":[
        {
            "category":"Professional",
            "subcategory":"Computer Services",
            "type":"Services"
        }
    ],
    "sg:phone":"+1 301 277 3110",
    "sg:postcode":"20740",
    "sg:province":"MD",
    "sg:tags":[
        "design",
        "system"
    ],
    "wof:name":"Buddy Turner Graphic Designer",
    "wof:placetype":"venue"
},
  "geometry": {"coordinates":[-76.94242199999999,38.981132],"type":"Point"}
}