{
  "type": "Feature",
  "properties": {
    "iso:country":"US",
    "sg:address":"2709 Ocean Gtwy",
    "sg:city":"Cambridge",
    "sg:classifiers":[
        {
            "category":"Freight",
            "type":"Transportation"
        }
    ],
    "sg:phone":"+1 410 221 0441",
    "sg:postcode":"21613",
    "sg:province":"MD",
    "sg:tags":[
        "general"
    ],
    "wof:name":"Basic Storage Co",
    "wof:placetype":"venue"
},
  "geometry": {"coordinates":[-76.058198,38.557035],"type":"Point"}
}