{
  "type": "Feature",
  "properties": {
    "addr:full":"657 Broadneck Rd Annapolis MD 21401",
    "addr:housenumber":"657",
    "addr:postcode":"21401",
    "addr:street":"Broadneck Rd",
    "iso:country":"US",
    "sg:address":"657 Broadneck Rd",
    "sg:city":"Annapolis",
    "sg:classifiers":[
        {
            "category":"Organizations",
            "subcategory":"Religious Organization",
            "type":"Services"
        }
    ],
    "sg:phone":"+1 410 757 2995",
    "sg:postcode":"21401",
    "sg:province":"MD",
    "sg:tags":[
        "church"
    ],
    "wof:name":"Broadneck United Methodist Chr",
    "wof:placetype":"venue"
},
  "geometry": {"coordinates":[-76.45055000000001,39.028087],"type":"Point"}
}