{
  "type": "Feature",
  "properties": {
    "iso:country":"US",
    "sg:address":"706 E 30th St",
    "sg:city":"Baltimore",
    "sg:classifiers":[
        {
            "category":"Government",
            "subcategory":"Post Office",
            "type":"Public Place"
        }
    ],
    "sg:phone":"+1 410 235 9838",
    "sg:postcode":"21218",
    "sg:province":"MD",
    "sg:tags":[
        "delivery",
        "courier"
    ],
    "wof:name":"Lee Enterprises Inc.",
    "wof:placetype":"venue"
},
  "geometry": {"coordinates":[-76.60697399999999,39.324047],"type":"Point"}
}