{
  "type": "Feature",
  "properties": {
    "addr:full":"17433 Evangeline Ln Olney MD 20832",
    "addr:housenumber":"17433",
    "addr:postcode":"20832",
    "addr:street":"Evangeline Ln",
    "iso:country":"US",
    "sg:address":"17433 Evangeline Ln",
    "sg:city":"Olney",
    "sg:classifiers":[
        {
            "category":"Professional",
            "subcategory":"Business Services",
            "type":"Services"
        }
    ],
    "sg:phone":"+1 301 774 1481",
    "sg:postcode":"20832",
    "sg:province":"MD",
    "wof:name":"Creative Management System",
    "wof:placetype":"venue"
},
  "geometry": {"coordinates":[-77.08056500000001,39.141941],"type":"Point"}
}