{
  "type": "Feature",
  "properties": {
    "addr:full":"3832 New Section Rd Baltimore MD 21220",
    "addr:housenumber":"3832",
    "addr:postcode":"21220",
    "addr:street":"New Section Rd",
    "iso:country":"US",
    "sg:address":"3832 New Section Rd",
    "sg:city":"Baltimore",
    "sg:classifiers":[
        {
            "category":"Shopping",
            "subcategory":"Computers & Home Electronics",
            "type":"Retail Goods"
        }
    ],
    "sg:phone":"+1 410 686 0023",
    "sg:postcode":"21220",
    "sg:province":"MD",
    "sg:tags":[
        "repair",
        "satellite",
        "system",
        "equipment"
    ],
    "wof:name":"Rosedale TV Sales & Service",
    "wof:placetype":"venue"
},
  "geometry": {"coordinates":[-76.37182,39.317367],"type":"Point"}
}