{
  "type": "Feature",
  "properties": {
    "addr:full":"1407 Wesley Dr Salisbury MD 21801",
    "addr:housenumber":"1407",
    "addr:postcode":"21801",
    "addr:street":"Wesley Dr",
    "iso:country":"US",
    "sg:address":"1407 Wesley Dr",
    "sg:city":"Salisbury",
    "sg:classifiers":[
        {
            "category":"Professional",
            "subcategory":"Computer Services",
            "type":"Services"
        }
    ],
    "sg:phone":"+1 410 548 3901",
    "sg:postcode":"21801",
    "sg:province":"MD",
    "sg:tags":[
        "consultant",
        "designer"
    ],
    "sg:website":"www.ideas-net.com",
    "wof:name":"Interface Design Engineering",
    "wof:placetype":"venue"
},
  "geometry": {"coordinates":[-75.607169,38.341648],"type":"Point"}
}