{
  "type": "Feature",
  "properties": {
    "iso:country":"US",
    "sg:address":"1179 Hall Ct",
    "sg:city":"Andrews Afb",
    "sg:classifiers":[
        {
            "category":"Real Estate",
            "subcategory":"Real Estate Agent",
            "type":"Services"
        }
    ],
    "sg:phone":"+1 301 599 6383",
    "sg:postcode":"20762",
    "sg:province":"MD",
    "sg:tags":[
        "authorities",
        "housing"
    ],
    "wof:name":"Andrews Airforce Base Housing",
    "wof:placetype":"venue"
},
  "geometry": {"coordinates":[-76.89102699999999,38.806303],"type":"Point"}
}