{
  "type": "Feature",
  "properties": {
    "iso:country":"US",
    "sg:address":"9687 Gerwig Ln",
    "sg:city":"Columbia",
    "sg:classifiers":[
        {
            "category":"Home & Garden",
            "subcategory":"Furniture",
            "type":"Retail Goods"
        }
    ],
    "sg:phone":"+1 410 381 3110",
    "sg:postcode":"21046",
    "sg:province":"MD",
    "sg:tags":[
        "bed"
    ],
    "wof:name":"Craftmatic Of Maryland",
    "wof:placetype":"venue"
},
  "geometry": {"coordinates":[-76.846321,39.175241],"type":"Point"}
}