{
  "type": "Feature",
  "properties": {
    "addr:full":"7126 E Furnace Branch Rd Glen Burnie MD 21060",
    "addr:housenumber":"7126",
    "addr:postcode":"21060",
    "addr:street":"E Furnace Branch Rd",
    "iso:country":"US",
    "sg:address":"7126 E Furnace Branch Rd",
    "sg:city":"Glen Burnie",
    "sg:classifiers":[
        {
            "category":"Retail",
            "subcategory":"Auto Repair",
            "type":"Services"
        }
    ],
    "sg:phone":"+1 410 761 3992",
    "sg:postcode":"21060",
    "sg:province":"MD",
    "sg:tags":[
        "body",
        "automobile",
        "painting"
    ],
    "wof:name":"A & R Body Frame",
    "wof:placetype":"venue"
},
  "geometry": {"coordinates":[-76.609706,39.180569],"type":"Point"}
}