{
  "type": "Feature",
  "properties": {
    "iso:country":"US",
    "sg:address":"4704 Eastern Ave",
    "sg:city":"Baltimore",
    "sg:classifiers":[
        {
            "category":"Shopping",
            "subcategory":"Musical Instruments",
            "type":"Retail Goods"
        }
    ],
    "sg:phone":"+1 410 563 0200",
    "sg:postcode":"21224",
    "sg:province":"MD",
    "wof:name":"Nitsa Morekas",
    "wof:placetype":"venue"
},
  "geometry": {"coordinates":[-76.555837,39.287124],"type":"Point"}
}