{
  "type": "Feature",
  "properties": {
    "addr:full":"5837 Timberview Dr Elkridge MD 21075",
    "addr:housenumber":"5837",
    "addr:postcode":"21075",
    "addr:street":"Timberview Dr",
    "iso:country":"US",
    "sg:address":"5837 Timberview Dr",
    "sg:city":"Elkridge",
    "sg:classifiers":[
        {
            "category":"Building & Trades",
            "subcategory":"Construction",
            "type":"Services"
        }
    ],
    "sg:phone":"+1 443 790 6355",
    "sg:postcode":"21075",
    "sg:province":"MD",
    "sg:tags":[
        "painting",
        "contractor"
    ],
    "wof:name":"Dorsey & Sons Painting",
    "wof:placetype":"venue"
},
  "geometry": {"coordinates":[-76.748751,39.208625],"type":"Point"}
}