{
  "type": "Feature",
  "properties": {
    "iso:country":"US",
    "sg:address":"7513 Landover Rd",
    "sg:city":"Hyattsville",
    "sg:classifiers":[
        {
            "category":"Wholesale",
            "subcategory":"Machinery & Supplies",
            "type":"Manufacturing & Wholesale Goods"
        }
    ],
    "sg:phone":"+1 301 772 2733",
    "sg:postcode":"20785",
    "sg:province":"MD",
    "sg:tags":[
        "salon",
        "cosmetic",
        "beauty"
    ],
    "wof:name":"Action Beauty Supply",
    "wof:placetype":"venue"
},
  "geometry": {"coordinates":[-76.88649700000001,38.926601],"type":"Point"}
}