{
  "type": "Feature",
  "properties": {
    "addr:full":"1985 Corporal Frank Scott Dr College Park MD 20740",
    "addr:housenumber":"1985",
    "addr:postcode":"20740",
    "addr:street":"Corporal Frank Scott Dr",
    "iso:country":"US",
    "sg:address":"1985 Corporal Frank Scott Dr",
    "sg:city":"College Park",
    "sg:classifiers":[
        {
            "category":"Museum",
            "type":"Entertainment"
        }
    ],
    "sg:phone":"+1 301 864 6029",
    "sg:postcode":"20740",
    "sg:province":"MD",
    "wof:name":"College Park Aviation Museum",
    "wof:placetype":"venue"
},
  "geometry": {"coordinates":[-76.92424099999999,38.979799],"type":"Point"}
}