{
  "type": "Feature",
  "properties": {
    "addr:full":"7346 Hidden Cv Columbia MD 21046",
    "addr:housenumber":"7346",
    "addr:postcode":"21046",
    "addr:street":"Hidden Cv",
    "iso:country":"US",
    "sg:address":"7346 Hidden Cv",
    "sg:city":"Columbia",
    "sg:classifiers":[
        {
            "category":"Shopping",
            "type":"Retail Goods"
        }
    ],
    "sg:phone":"+1 443 691 1704",
    "sg:postcode":"21046",
    "sg:province":"MD",
    "sg:tags":[
        "merchandise"
    ],
    "wof:name":"The Upgrade Shoppe",
    "wof:placetype":"venue"
},
  "geometry": {"coordinates":[-76.83157799999999,39.170488],"type":"Point"}
}