{
  "type": "Feature",
  "properties": {
    "iso:country":"US",
    "sg:address":"204 1/2 Arundel Rd W",
    "sg:city":"Baltimore",
    "sg:classifiers":[
        {
            "category":"Building & Trades",
            "subcategory":"Plumbing",
            "type":"Services"
        }
    ],
    "sg:phone":"+1 410 636 6019",
    "sg:postcode":"21225",
    "sg:province":"MD",
    "wof:name":"Mpb Plumbing Services",
    "wof:placetype":"venue"
},
  "geometry": {"coordinates":[-76.61546800000001,39.23274],"type":"Point"}
}