{
  "type": "Feature",
  "properties": {
    "addr:full":"3140 Leonardtown Rd Waldorf MD 20601",
    "addr:housenumber":"3140",
    "addr:postcode":"20601",
    "addr:street":"Leonardtown Rd",
    "iso:country":"US",
    "sg:address":"3140 Leonardtown Rd",
    "sg:city":"Waldorf",
    "sg:classifiers":[
        {
            "category":"Insurance",
            "subcategory":"Insurance Agent",
            "type":"Services"
        }
    ],
    "sg:phone":"+1 301 870 5200",
    "sg:postcode":"20601",
    "sg:province":"MD",
    "wof:name":"Parsons & Assoc",
    "wof:placetype":"venue"
},
  "geometry": {"coordinates":[-76.908908,38.625178],"type":"Point"}
}