{
  "type": "Feature",
  "properties": {
    "iso:country":"US",
    "sg:address":"2450 Riva Rd",
    "sg:city":"Annapolis",
    "sg:classifiers":[
        {
            "category":"Banks & Credit Unions",
            "subcategory":"Bank",
            "type":"Services"
        }
    ],
    "sg:phone":"+1 301 970 2344",
    "sg:postcode":"21401",
    "sg:province":"MD",
    "sg:tags":[
        "financing"
    ],
    "wof:name":"Allied Home Mortgage",
    "wof:placetype":"venue"
},
  "geometry": {"coordinates":[-76.54146299999999,38.983162],"type":"Point"}
}