{
  "type": "Feature",
  "properties": {
    "iso:country":"US",
    "sg:address":"623 Pulaski Hwy",
    "sg:city":"Joppa",
    "sg:classifiers":[
        {
            "category":"Health Services",
            "subcategory":"Clinic",
            "type":"Services"
        }
    ],
    "sg:phone":"+1 410 538 5809",
    "sg:postcode":"21085",
    "sg:province":"MD",
    "sg:tags":[
        "home"
    ],
    "wof:name":"Joppa Health Svc",
    "wof:placetype":"venue"
},
  "geometry": {"coordinates":[-76.352902,39.429345],"type":"Point"}
}