{
  "type": "Feature",
  "properties": {
    "addr:full":"10851 Lanham Severn Rd Glenn Dale MD 20769",
    "addr:housenumber":"10851",
    "addr:postcode":"20769",
    "addr:street":"Severn Rd",
    "iso:country":"US",
    "sg:address":"10851 Lanham Severn Rd",
    "sg:city":"Glenn Dale",
    "sg:classifiers":[
        {
            "category":"Real Estate",
            "subcategory":"Real Estate Agent",
            "type":"Services"
        }
    ],
    "sg:phone":"+1 301 262 9311",
    "sg:postcode":"20769",
    "sg:province":"MD",
    "sg:tags":[
        "management"
    ],
    "wof:name":"Glenn Dale Plaza Condo Assoc",
    "wof:placetype":"venue"
},
  "geometry": {"coordinates":[-76.82293900000001,38.985109],"type":"Point"}
}