{
  "type": "Feature",
  "properties": {
    "iso:country":"US",
    "sg:address":"2820 Glen Isle Rd",
    "sg:city":"Riva",
    "sg:classifiers":[
        {
            "category":"Utilities",
            "subcategory":"Mobile Phone",
            "type":"Services"
        }
    ],
    "sg:phone":"+1 301 205 0013",
    "sg:postcode":"21140",
    "sg:province":"MD",
    "sg:tags":[
        "communication",
        "radiotelephone"
    ],
    "wof:name":"G C Paging",
    "wof:placetype":"venue"
},
  "geometry": {"coordinates":[-76.593609,38.95289],"type":"Point"}
}