{
  "type": "Feature",
  "properties": {
    "addr:full":"1907 Lansdowne Rd Halethorpe MD 21227",
    "addr:housenumber":"1907",
    "addr:postcode":"21227",
    "addr:street":"Lansdowne Rd",
    "iso:country":"US",
    "sg:address":"1907 Lansdowne Rd",
    "sg:city":"Halethorpe",
    "sg:classifiers":[
        {
            "category":"Wholesale",
            "subcategory":"Machinery & Supplies",
            "type":"Manufacturing & Wholesale Goods"
        }
    ],
    "sg:phone":"+1 410 737 9280",
    "sg:postcode":"21227",
    "sg:province":"MD",
    "sg:tags":[
        "equipment",
        "material",
        "handling"
    ],
    "sg:website":"www.bayindustrialgroup.com",
    "wof:name":"Bay Design Inc",
    "wof:placetype":"venue"
},
  "geometry": {"coordinates":[-76.668029,39.253166],"type":"Point"}
}