{
  "type": "Feature",
  "properties": {
    "addr:full":"10974 Millbank Row Columbia MD 21044",
    "addr:housenumber":"10974",
    "addr:postcode":"21044",
    "addr:street":"Millbank Row",
    "iso:country":"US",
    "sg:address":"10974 Millbank Row",
    "sg:city":"Columbia",
    "sg:classifiers":[
        {
            "category":"Organizations",
            "subcategory":"Religious Organization",
            "type":"Services"
        }
    ],
    "sg:phone":"+1 410 884 5190",
    "sg:postcode":"21044",
    "sg:province":"MD",
    "wof:name":"4 H Hope Ministries Inc",
    "wof:placetype":"venue"
},
  "geometry": {"coordinates":[-76.890675,39.216837],"type":"Point"}
}