{
  "type": "Feature",
  "properties": {
    "addr:full":"11902 Gold Needle Way Columbia MD 21044",
    "addr:housenumber":"11902",
    "addr:postcode":"21044",
    "addr:street":"Gold Needle Way",
    "iso:country":"US",
    "sg:address":"11902 Gold Needle Way",
    "sg:city":"Columbia",
    "sg:classifiers":[
        {
            "category":"Freight",
            "type":"Transportation"
        }
    ],
    "sg:phone":"+1 410 772 0158",
    "sg:postcode":"21044",
    "sg:province":"MD",
    "sg:tags":[
        "trucking"
    ],
    "wof:name":"KB Trucking Systems  LLC",
    "wof:placetype":"venue"
},
  "geometry": {"coordinates":[-76.902854,39.212954],"type":"Point"}
}