{
  "type": "Feature",
  "properties": {
    "addr:full":"116 Stonewall Rd Catonsville MD 21228",
    "addr:housenumber":"116",
    "addr:postcode":"21228",
    "addr:street":"Stonewall Rd",
    "iso:country":"US",
    "sg:address":"116 Stonewall Rd",
    "sg:city":"Catonsville",
    "sg:classifiers":[
        {
            "category":"Building & Trades",
            "subcategory":"Construction",
            "type":"Services"
        }
    ],
    "sg:phone":"+1 410 788 2683",
    "sg:postcode":"21228",
    "sg:province":"MD",
    "sg:tags":[
        "concrete",
        "contractor"
    ],
    "wof:name":"Tri-State Construction Inc",
    "wof:placetype":"venue"
},
  "geometry": {"coordinates":[-76.769086,39.267873],"type":"Point"}
}