{
  "type": "Feature",
  "properties": {
    "iso:country":"US",
    "sg:address":"420 Colonial Dr",
    "sg:city":"Denton",
    "sg:classifiers":[
        {
            "category":"Social Services",
            "subcategory":"Job Training",
            "type":"Services"
        }
    ],
    "sg:phone":"+1 410 479 4400",
    "sg:postcode":"21629",
    "sg:province":"MD",
    "sg:tags":[
        "rehabilitation"
    ],
    "wof:name":"Ruxton Health Care",
    "wof:placetype":"venue"
},
  "geometry": {"coordinates":[-75.80693100000001,38.89099],"type":"Point"}
}