{
  "type": "Feature",
  "properties": {
    "iso:country":"US",
    "sg:address":"10 E Baltimore St",
    "sg:city":"Baltimore",
    "sg:classifiers":[
        {
            "category":"Professional",
            "subcategory":"Lawyer & Legal Services",
            "type":"Services"
        }
    ],
    "sg:phone":"+1 410 685 1111",
    "sg:postcode":"21202",
    "sg:province":"MD",
    "sg:tags":[
        "attorney"
    ],
    "wof:name":"Marvin I Singer",
    "wof:placetype":"venue"
},
  "geometry": {"coordinates":[-76.613857,39.289675],"type":"Point"}
}