{
  "type": "Feature",
  "properties": {
    "addr:full":"6200 Days Cove Rd Ste 3 White Marsh MD 21162",
    "addr:housenumber":"6200",
    "addr:postcode":"21162",
    "addr:street":"Days Cove Rd Ste 3",
    "iso:country":"US",
    "sg:address":"6200 Days Cove Rd Ste 3",
    "sg:city":"White Marsh",
    "sg:classifiers":[
        {
            "category":"Personal",
            "type":"Services"
        }
    ],
    "sg:phone":"+1 410 344 0050",
    "sg:postcode":"21162",
    "sg:province":"MD",
    "sg:tags":[
        "party",
        "planning",
        "event"
    ],
    "sg:website":"www.trimbolistents.com",
    "wof:name":"Trimbolis Tents & Events",
    "wof:placetype":"venue"
},
  "geometry": {"coordinates":[-76.401521,39.399482],"type":"Point"}
}