{
  "type": "Feature",
  "properties": {
    "iso:country":"US",
    "sg:address":"7750 Deforest Dr",
    "sg:city":"Chesapeake Beach",
    "sg:classifiers":[
        {
            "category":"Building & Trades",
            "subcategory":"Plumbing",
            "type":"Services"
        }
    ],
    "sg:phone":"+1 301 855 5257",
    "sg:postcode":"20732",
    "sg:province":"MD",
    "sg:tags":[
        "air",
        "heating",
        "conditioning",
        "contractor"
    ],
    "wof:name":"Air Doctor",
    "wof:placetype":"venue"
},
  "geometry": {"coordinates":[-76.537109,38.687495],"type":"Point"}
}