{
  "type": "Feature",
  "properties": {
    "addr:full":"6312 Kenwood Ave Rosedale MD 21237",
    "addr:housenumber":"6312",
    "addr:postcode":"21237",
    "addr:street":"Kenwood Ave",
    "iso:country":"US",
    "sg:address":"6312 Kenwood Ave",
    "sg:city":"Rosedale",
    "sg:classifiers":[
        {
            "category":"Insurance",
            "subcategory":"Insurance Agent",
            "type":"Services"
        },
        {
            "category":"Insurance",
            "subcategory":"Hazard Insurance",
            "type":"Services"
        },
        {
            "category":"Insurance",
            "subcategory":"Title Insurance",
            "type":"Services"
        },
        {
            "category":"Insurance",
            "subcategory":"Life Insurance",
            "type":"Services"
        }
    ],
    "sg:phone":"+1 410 866 4600",
    "sg:postcode":"21237",
    "sg:province":"MD",
    "sg:tags":[
        "business",
        "auto",
        "commercial",
        "homeowner",
        "motorcycle",
        "renter"
    ],
    "wof:name":"Allstate Insurance Company - Edgardo Nieves",
    "wof:placetype":"venue"
},
  "geometry": {"coordinates":[-76.505341,39.339439],"type":"Point"}
}