{
  "type": "Feature",
  "properties": {
    "addr:full":"7523 Catone Ct Oxon Hill MD 20745",
    "addr:housenumber":"7523",
    "addr:postcode":"20745",
    "addr:street":"Catone Ct",
    "iso:country":"US",
    "sg:address":"7523 Catone Ct",
    "sg:city":"Oxon Hill",
    "sg:classifiers":[
        {
            "category":"Professional",
            "subcategory":"Accounting & Tax Preparation",
            "type":"Services"
        }
    ],
    "sg:phone":"+1 301 839 0747",
    "sg:postcode":"20745",
    "sg:province":"MD",
    "sg:tags":[
        "return",
        "filing"
    ],
    "wof:name":"Larry Baucum Income Tax Svc",
    "wof:placetype":"venue"
},
  "geometry": {"coordinates":[-76.997445,38.785901],"type":"Point"}
}