{
  "type": "Feature",
  "properties": {
    "addr:full":"7081 Arundel Mills Cir Hanover MD 21076",
    "addr:housenumber":"7081",
    "addr:postcode":"21076",
    "addr:street":"Arundel Mills Cir",
    "iso:country":"US",
    "sg:address":"7081 Arundel Mills Cir",
    "sg:city":"Hanover",
    "sg:classifiers":[
        {
            "category":"Fast Food",
            "type":"Food & Drink"
        },
        {
            "category":"Restaurant",
            "type":"Food & Drink"
        }
    ],
    "sg:phone":"+1 410 379 1306",
    "sg:postcode":"21076",
    "sg:province":"MD",
    "sg:tags":[
        "hamburger",
        "hot",
        "dog",
        "american",
        "take",
        "chicken"
    ],
    "sg:website":"http://www.mcdonalds.com",
    "wof:name":"McDonald's",
    "wof:placetype":"venue"
},
  "geometry": {"coordinates":[-76.730324,39.154388],"type":"Point"}
}