{
  "type": "Feature",
  "properties": {
    "iso:country":"US",
    "sg:address":"7920 Norfolk Ave Ste 200",
    "sg:city":"Bethesda",
    "sg:classifiers":[
        {
            "category":"Health Services",
            "subcategory":"Clinic",
            "type":"Services"
        }
    ],
    "sg:phone":"+1 301 718 3588",
    "sg:postcode":"20814",
    "sg:province":"MD",
    "sg:tags":[
        "counseling",
        "mental"
    ],
    "wof:name":"Aad Psychological Services",
    "wof:placetype":"venue"
},
  "geometry": {"coordinates":[-77.097827,38.989231],"type":"Point"}
}