{
  "type": "Feature",
  "properties": {
    "iso:country":"US",
    "sg:address":"1011 Decesaris Dr",
    "sg:city":"Lothian",
    "sg:classifiers":[
        {
            "category":"Food & Beverages",
            "subcategory":"Groceries & Convenience Stores",
            "type":"Retail Goods"
        }
    ],
    "sg:phone":"+1 410 741 1447",
    "sg:postcode":"20711",
    "sg:province":"MD",
    "wof:name":"James Stanley Development Inc",
    "wof:placetype":"venue"
},
  "geometry": {"coordinates":[-76.673162,38.824606],"type":"Point"}
}