{
  "type": "Feature",
  "properties": {
    "addr:full":"5212 McCormick Ave Baltimore MD 21206",
    "addr:housenumber":"5212",
    "addr:postcode":"21206",
    "addr:street":"Mccormick Ave",
    "iso:country":"US",
    "sg:address":"5212 McCormick Ave",
    "sg:city":"Baltimore",
    "sg:classifiers":[
        {
            "category":"Organizations",
            "subcategory":"Religious Organization",
            "type":"Services"
        }
    ],
    "sg:phone":"+1 410 866 4020",
    "sg:postcode":"21206",
    "sg:province":"MD",
    "wof:name":"Church of The Enunciation",
    "wof:placetype":"venue"
},
  "geometry": {"coordinates":[-76.522651,39.335424],"type":"Point"}
}