{
  "type": "Feature",
  "properties": {
    "iso:country":"US",
    "sg:address":"1201 E Preston St",
    "sg:city":"Baltimore",
    "sg:classifiers":[
        {
            "category":"Food & Beverages",
            "subcategory":"Groceries & Convenience Stores",
            "type":"Retail Goods"
        }
    ],
    "sg:phone":"+1 410 332 0723",
    "sg:postcode":"21202",
    "sg:province":"MD",
    "sg:tags":[
        "grocer"
    ],
    "wof:name":"Crown Food Market",
    "wof:placetype":"venue"
},
  "geometry": {"coordinates":[-76.60182399999999,39.305064],"type":"Point"}
}