{
  "type": "Feature",
  "properties": {
    "addr:full":"6105 Plum Way Clinton MD 20735",
    "addr:housenumber":"6105",
    "addr:postcode":"20735",
    "addr:street":"Plum Way",
    "iso:country":"US",
    "sg:address":"6105 Plum Way",
    "sg:city":"Clinton",
    "sg:classifiers":[
        {
            "category":"Professional",
            "type":"Services"
        }
    ],
    "sg:phone":"+1 301 868 2111",
    "sg:postcode":"20735",
    "sg:province":"MD",
    "sg:tags":[
        "establishment"
    ],
    "wof:name":"Bankhead Landscapings & Assoc",
    "wof:placetype":"venue"
},
  "geometry": {"coordinates":[-76.901612,38.738579],"type":"Point"}
}