{
  "type": "Feature",
  "properties": {
    "addr:full":"601 Chelsea Rd Aberdeen MD 21001",
    "addr:housenumber":"601",
    "addr:postcode":"21001",
    "addr:street":"Chelsea Rd",
    "iso:country":"US",
    "sg:address":"601 Chelsea Rd",
    "sg:city":"Aberdeen",
    "sg:classifiers":[
        {
            "category":"Local Transit",
            "type":"Transportation"
        }
    ],
    "sg:phone":"+1 410 273 7222",
    "sg:postcode":"21001",
    "sg:province":"MD",
    "wof:name":"J G Assoc",
    "wof:placetype":"venue"
},
  "geometry": {"coordinates":[-76.217716,39.429828],"type":"Point"}
}