{
  "type": "Feature",
  "properties": {
    "addr:full":"888 Bestgate Rd Annapolis MD 21401",
    "addr:housenumber":"888",
    "addr:postcode":"21401",
    "addr:street":"Bestgate Rd",
    "iso:country":"US",
    "sg:address":"888 Bestgate Rd",
    "sg:city":"Annapolis",
    "sg:classifiers":[
        {
            "category":"Banks & Credit Unions",
            "subcategory":"Financial Services",
            "type":"Services"
        }
    ],
    "sg:phone":"+1 410 224 9700",
    "sg:postcode":"21401",
    "sg:province":"MD",
    "sg:tags":[
        "company",
        "holding"
    ],
    "wof:name":"Sofitel Holdings Inc",
    "wof:placetype":"venue"
},
  "geometry": {"coordinates":[-76.54445699999999,38.992635],"type":"Point"}
}