{
  "type": "Feature",
  "properties": {
    "iso:country":"US",
    "sg:address":"5518 Muddy Creek Rd",
    "sg:city":"West River",
    "sg:classifiers":[
        {
            "category":"Building & Trades",
            "subcategory":"Plumbing",
            "type":"Services"
        }
    ],
    "sg:phone":"+1 301 261 9079",
    "sg:postcode":"20778",
    "sg:province":"MD",
    "sg:tags":[
        "conditioning",
        "air",
        "system",
        "contractor"
    ],
    "sg:website":"www.bobfoxservices.com",
    "wof:name":"Bob Fox Svc",
    "wof:placetype":"venue"
},
  "geometry": {"coordinates":[-76.538983,38.815085],"type":"Point"}
}