{
  "type": "Feature",
  "properties": {
    "iso:country":"US",
    "sg:address":"51 N McCain Dr",
    "sg:city":"Frederick",
    "sg:classifiers":[
        {
            "category":"Manufacturing",
            "subcategory":"Electronics",
            "type":"Manufacturing & Wholesale Goods"
        }
    ],
    "sg:phone":"+1 301 663 5777",
    "sg:postcode":"21702",
    "sg:province":"MD",
    "sg:tags":[
        "modem",
        "set"
    ],
    "wof:name":"Behr Modem",
    "wof:placetype":"venue"
},
  "geometry": {"coordinates":[-77.453555,39.419323],"type":"Point"}
}