{
  "type": "Feature",
  "properties": {
    "addr:full":"815 Hatherleigh Rd Baltimore MD 21212",
    "addr:housenumber":"815",
    "addr:postcode":"21212",
    "addr:street":"Hatherleigh Rd",
    "iso:country":"US",
    "sg:address":"815 Hatherleigh Rd",
    "sg:city":"Baltimore",
    "sg:classifiers":[
        {
            "category":"Professional",
            "type":"Services"
        }
    ],
    "sg:phone":"+1 410 938 2677",
    "sg:postcode":"21212",
    "sg:province":"MD",
    "sg:tags":[
        "establishment"
    ],
    "wof:name":"Stoneleigh COP Substation",
    "wof:placetype":"venue"
},
  "geometry": {"coordinates":[-76.601004,39.382992],"type":"Point"}
}