{
  "type": "Feature",
  "properties": {
    "addr:full":"7655 New Hampshire Ave Takoma Park MD 20912",
    "addr:housenumber":"7655",
    "addr:postcode":"20912",
    "addr:street":"New Hampshire Ave",
    "iso:country":"US",
    "sg:address":"7655 New Hampshire Ave",
    "sg:city":"Takoma Park",
    "sg:classifiers":[
        {
            "category":"Personal",
            "subcategory":"Beauty Salon",
            "type":"Services"
        }
    ],
    "sg:phone":"+1 301 422 1944",
    "sg:postcode":"20912",
    "sg:province":"MD",
    "wof:name":"Sheila's Unisex",
    "wof:placetype":"venue"
},
  "geometry": {"coordinates":[-76.987934,38.98653],"type":"Point"}
}