{
  "type": "Feature",
  "properties": {
    "addr:full":"251 Kentlands Blvd Gaithersburg MD 20878",
    "addr:housenumber":"251",
    "addr:postcode":"20878",
    "addr:street":"Kentlands Blvd",
    "iso:country":"US",
    "sg:address":"251 Kentlands Blvd",
    "sg:city":"Gaithersburg",
    "sg:classifiers":[
        {
            "category":"Food & Beverages",
            "subcategory":"Specialty",
            "type":"Retail Goods"
        }
    ],
    "sg:phone":"+1 301 948 0129",
    "sg:postcode":"20878",
    "sg:province":"MD",
    "sg:tags":[
        "health",
        "diet"
    ],
    "wof:name":"General Nutrition Ctr",
    "wof:placetype":"venue"
},
  "geometry": {"coordinates":[-77.241702,39.124725],"type":"Point"}
}