{
  "type": "Feature",
  "properties": {
    "addr:full":"21308 China Aster Ct Germantown MD 20876",
    "addr:housenumber":"21308",
    "addr:postcode":"20876",
    "addr:street":"China Aster Ct",
    "iso:country":"US",
    "sg:address":"21308 China Aster Ct",
    "sg:city":"Germantown",
    "sg:classifiers":[
        {
            "category":"Professional",
            "subcategory":"Business Services",
            "type":"Services"
        }
    ],
    "sg:phone":"+1 301 916 7919",
    "sg:postcode":"20876",
    "sg:province":"MD",
    "sg:tags":[
        "broadcasting"
    ],
    "wof:name":"Anutosh R Saha",
    "wof:placetype":"venue"
},
  "geometry": {"coordinates":[-77.253049,39.205814],"type":"Point"}
}