{
  "type": "Feature",
  "properties": {
    "iso:country":"US",
    "sg:address":"217 Tyler Ave",
    "sg:city":"Saint Michaels",
    "sg:classifiers":[
        {
            "category":"Professional",
            "subcategory":"Business Services",
            "type":"Services"
        }
    ],
    "sg:phone":"+1 410 745 2732",
    "sg:postcode":"21663",
    "sg:province":"MD",
    "sg:tags":[
        "radiology"
    ],
    "wof:name":"Frank Brennan MD",
    "wof:placetype":"venue"
},
  "geometry": {"coordinates":[-76.20953299999999,38.778684],"type":"Point"}
}