{
  "type": "Feature",
  "properties": {
    "addr:full":"900 Cathedral St Ste 4 Baltimore MD 21201",
    "addr:housenumber":"900",
    "addr:postcode":"21201",
    "addr:street":"Cathedral St Ste 4",
    "iso:country":"US",
    "sg:address":"900 Cathedral St Ste 4",
    "sg:city":"Baltimore",
    "sg:classifiers":[
        {
            "category":"Real Estate",
            "subcategory":"Real Estate Services",
            "type":"Services"
        },
        {
            "category":"Real Estate",
            "subcategory":"Real Estate Operator",
            "type":"Services"
        }
    ],
    "sg:phone":"+1 410 539 6565",
    "sg:postcode":"21201",
    "sg:province":"MD",
    "sg:tags":[
        "apartment",
        "vacancy",
        "listing",
        "rental",
        "finder"
    ],
    "sg:website":"http://www.cathedralcourt.com",
    "wof:name":"Cathedral Court Llc",
    "wof:placetype":"venue"
},
  "geometry": {"coordinates":[-76.617104,39.299599],"type":"Point"}
}