{
  "type": "Feature",
  "properties": {
    "addr:full":"135 Slade Ave Pikesville MD 21208",
    "addr:housenumber":"135",
    "addr:postcode":"21208",
    "addr:street":"Slade Ave",
    "iso:country":"US",
    "sg:address":"135 Slade Ave",
    "sg:city":"Pikesville",
    "sg:classifiers":[
        {
            "category":"Recreation",
            "type":"Entertainment"
        }
    ],
    "sg:phone":"+1 410 484 9728",
    "sg:postcode":"21208",
    "sg:province":"MD",
    "sg:tags":[
        "pool",
        "swimming"
    ],
    "wof:name":"Warren Park Pool",
    "wof:placetype":"venue"
},
  "geometry": {"coordinates":[-76.717918,39.36867],"type":"Point"}
}