{
  "type": "Feature",
  "properties": {
    "iso:country":"US",
    "sg:address":"1208 Southbreeze Ln",
    "sg:city":"Annapolis",
    "sg:classifiers":[
        {
            "category":"Professional",
            "subcategory":"Management & Consulting",
            "type":"Services"
        }
    ],
    "sg:phone":"+1 410 280 2527",
    "sg:postcode":"21403",
    "sg:province":"MD",
    "sg:tags":[
        "consultant"
    ],
    "wof:name":"Mc C Consulting Inc",
    "wof:placetype":"venue"
},
  "geometry": {"coordinates":[-76.476967,38.917507],"type":"Point"}
}