{
  "type": "Feature",
  "properties": {
    "addr:full":"650 Alpine Ln Westminster MD 21157",
    "addr:housenumber":"650",
    "addr:postcode":"21157",
    "addr:street":"Alpine Ln",
    "iso:country":"US",
    "sg:address":"650 Alpine Ln",
    "sg:city":"Westminster",
    "sg:classifiers":[
        {
            "category":"Professional",
            "subcategory":"Advertising",
            "type":"Services"
        }
    ],
    "sg:phone":"+1 410 857 1986",
    "sg:postcode":"21157",
    "sg:province":"MD",
    "sg:tags":[
        "distribution"
    ],
    "wof:name":"Direct Distributing",
    "wof:placetype":"venue"
},
  "geometry": {"coordinates":[-76.973007,39.541624],"type":"Point"}
}