{
  "type": "Feature",
  "properties": {
    "iso:country":"US",
    "sg:address":"1734 Fleet St",
    "sg:city":"Baltimore",
    "sg:classifiers":[
        {
            "category":"Shopping",
            "subcategory":"Used Merchandise",
            "type":"Retail Goods"
        }
    ],
    "sg:phone":"+1 410 675 7174",
    "sg:postcode":"21231",
    "sg:province":"MD",
    "sg:tags":[
        "antique"
    ],
    "wof:name":"In the Groove",
    "wof:placetype":"venue"
},
  "geometry": {"coordinates":[-76.591797,39.284599],"type":"Point"}
}