{
  "type": "Feature",
  "properties": {
    "addr:full":"2215 Neville Ct Waldorf MD 20602",
    "addr:housenumber":"2215",
    "addr:postcode":"20602",
    "addr:street":"Neville Ct",
    "iso:country":"US",
    "sg:address":"2215 Neville Ct",
    "sg:city":"Waldorf",
    "sg:classifiers":[
        {
            "category":"Manufacturing",
            "subcategory":"Retail Goods",
            "type":"Manufacturing & Wholesale Goods"
        }
    ],
    "sg:phone":"+1 301 932 5157",
    "sg:postcode":"20602",
    "sg:province":"MD",
    "sg:tags":[
        "product",
        "mfg"
    ],
    "wof:name":"Barbaras Designs",
    "wof:placetype":"venue"
},
  "geometry": {"coordinates":[-76.886455,38.597947],"type":"Point"}
}