{
  "type": "Feature",
  "properties": {
    "addr:full":"920 Adelina Rd Prince Frederick MD 20678",
    "addr:housenumber":"920",
    "addr:postcode":"20678",
    "addr:street":"Adelina Rd",
    "iso:country":"US",
    "sg:address":"920 Adelina Rd",
    "sg:city":"Prince Frederick",
    "sg:classifiers":[
        {
            "category":"Building & Trades",
            "subcategory":"Plumbing",
            "type":"Services"
        }
    ],
    "sg:phone":"+1 410 535 3100",
    "sg:postcode":"20678",
    "sg:province":"MD",
    "sg:tags":[
        "tank",
        "septic"
    ],
    "wof:name":"Griffin Backhoe Svc",
    "wof:placetype":"venue"
},
  "geometry": {"coordinates":[-76.62302,38.498419],"type":"Point"}
}