{
  "type": "Feature",
  "properties": {
    "iso:country":"US",
    "sg:address":"1325 Mount Hermon Rd",
    "sg:city":"Salisbury",
    "sg:classifiers":[
        {
            "category":"Building & Trades",
            "subcategory":"Cleaning & Sanitation",
            "type":"Services"
        }
    ],
    "sg:phone":"+1 410 860 1400",
    "sg:postcode":"21804",
    "sg:province":"MD",
    "sg:tags":[
        "janitor"
    ],
    "wof:name":"Mr Meticulous Cleaning Svc",
    "wof:placetype":"venue"
},
  "geometry": {"coordinates":[-75.56629599999999,38.366479],"type":"Point"}
}