{
  "type": "Feature",
  "properties": {
    "iso:country":"US",
    "sg:address":"5530 Wisconsin Ave",
    "sg:city":"Chevy Chase",
    "sg:classifiers":[
        {
            "category":"Health Services",
            "subcategory":"Clinic",
            "type":"Services"
        }
    ],
    "sg:phone":"+1 301 951 3668",
    "sg:postcode":"20815",
    "sg:province":"MD",
    "sg:tags":[
        "counseling",
        "mental"
    ],
    "wof:name":"Panic Attack Therapy",
    "wof:placetype":"venue"
},
  "geometry": {"coordinates":[-77.087502,38.964298],"type":"Point"}
}