{
  "type": "Feature",
  "properties": {
    "iso:country":"US",
    "sg:address":"14711 Main St",
    "sg:city":"Upper Marlboro",
    "sg:classifiers":[
        {
            "category":"Personal",
            "subcategory":"Beauty Salon",
            "type":"Services"
        }
    ],
    "sg:phone":"+1 301 574 1726",
    "sg:postcode":"20772",
    "sg:province":"MD",
    "wof:name":"Euphoria Spalon",
    "wof:placetype":"venue"
},
  "geometry": {"coordinates":[-76.750979,38.81646],"type":"Point"}
}