{
  "type": "Feature",
  "properties": {
    "addr:full":"764 Spruce St Hagerstown MD 21740",
    "addr:housenumber":"764",
    "addr:postcode":"21740",
    "addr:street":"Spruce St",
    "iso:country":"US",
    "sg:address":"764 Spruce St",
    "sg:city":"Hagerstown",
    "sg:classifiers":[
        {
            "category":"Organizations",
            "subcategory":"Religious Organization",
            "type":"Services"
        }
    ],
    "sg:phone":"+1 301 223 8908",
    "sg:postcode":"21740",
    "sg:province":"MD",
    "wof:name":"Hagerstown Evangelistic Temple",
    "wof:placetype":"venue"
},
  "geometry": {"coordinates":[-77.726798,39.628698],"type":"Point"}
}