{
  "type": "Feature",
  "properties": {
    "addr:full":"1550 Caton Center Dr Halethorpe MD 21227",
    "addr:housenumber":"1550",
    "addr:postcode":"21227",
    "addr:street":"Caton Center Dr",
    "iso:country":"US",
    "sg:address":"1550 Caton Center Dr",
    "sg:city":"Halethorpe",
    "sg:classifiers":[
        {
            "category":"Wholesale",
            "subcategory":"Electrical",
            "type":"Manufacturing & Wholesale Goods"
        }
    ],
    "sg:phone":"+1 410 644 3400",
    "sg:postcode":"21227",
    "sg:province":"MD",
    "sg:tags":[
        "control"
    ],
    "wof:name":"Control Corp Of America Inc",
    "wof:placetype":"venue"
},
  "geometry": {"coordinates":[-76.68218400000001,39.256313],"type":"Point"}
}