{
  "type": "Feature",
  "properties": {
    "iso:country":"US",
    "sg:address":"6501 Erdman Ave",
    "sg:city":"Baltimore",
    "sg:classifiers":[
        {
            "category":"Manufacturing",
            "subcategory":"Building Materials",
            "type":"Manufacturing & Wholesale Goods"
        }
    ],
    "sg:phone":"+1 410 483 5600",
    "sg:postcode":"21205",
    "sg:province":"MD",
    "sg:tags":[
        "metal",
        "work",
        "sheet"
    ],
    "wof:name":"Pritchard Brown",
    "wof:placetype":"venue"
},
  "geometry": {"coordinates":[-76.539419,39.301869],"type":"Point"}
}