{
  "type": "Feature",
  "properties": {
    "iso:country":"US",
    "sg:address":"1101 Camden Ave",
    "sg:city":"Salisbury",
    "sg:classifiers":[
        {
            "category":"Professional",
            "subcategory":"Research",
            "type":"Services"
        }
    ],
    "sg:phone":"+1 410 543 6312",
    "sg:postcode":"21801",
    "sg:province":"MD",
    "wof:name":"Edward H Nabb Research Ctr",
    "wof:placetype":"venue"
},
  "geometry": {"coordinates":[-75.607719,38.349188],"type":"Point"}
}