{
  "type": "Feature",
  "properties": {
    "addr:city":"Salisbury",
    "addr:full":"1101 Camden Avenue Salisbury, Md 21801",
    "addr:house_number":"1101",
    "addr:housenumber":"1101",
    "addr:phone":"+1 410-543-6312",
    "addr:postcode":"21801",
    "addr:road":"Camden Avenue",
    "addr:state":"MD",
    "addr:street":"Camden Ave",
    "iso:country":"US",
    "sg:address":"1101 Camden Ave",
    "sg:city":"Salisbury",
    "sg:classifiers":[
        {
            "category":"Professional",
            "subcategory":"Research",
            "type":"Services"
        }
    ],
    "sg:phone":"+1 410 543 6312",
    "sg:postcode":"21801",
    "sg:province":"MD",
    "wof:airports":[
        102527383
    ],
    "wof:name":"Edward H Nabb Research Center For Delmarva History",
    "wof:placetype":"venue"
},
  "geometry": {"coordinates":[-75.60738000000001,38.34977],"type":"Point"}
}