{
  "type": "Feature",
  "properties": {
    "iso:country":"US",
    "sg:address":"15 First Light Ct",
    "sg:city":"Baltimore",
    "sg:classifiers":[
        {
            "category":"Banks & Credit Unions",
            "subcategory":"Financial Services",
            "type":"Services"
        }
    ],
    "sg:phone":"+1 410 866 4229",
    "sg:postcode":"21237",
    "sg:province":"MD",
    "sg:tags":[
        "investor"
    ],
    "wof:name":"Powell Investments Inc",
    "wof:placetype":"venue"
},
  "geometry": {"coordinates":[-76.498662,39.340715],"type":"Point"}
}