{
  "type": "Feature",
  "properties": {
    "iso:country":"US",
    "sg:address":"4017 Annellen Rd",
    "sg:city":"Baltimore",
    "sg:classifiers":[
        {
            "category":"Professional",
            "subcategory":"Management & Consulting",
            "type":"Services"
        }
    ],
    "sg:phone":"+1 410 484 3050",
    "sg:postcode":"21215",
    "sg:province":"MD",
    "sg:tags":[
        "business"
    ],
    "wof:name":"Goodridge Roy Roger Winston",
    "wof:placetype":"venue"
},
  "geometry": {"coordinates":[-76.66806699999999,39.333616],"type":"Point"}
}