{
  "type": "Feature",
  "properties": {
    "addr:full":"21216 Chewsville Rd Smithsburg MD 21783",
    "addr:postcode":"21216;21783",
    "addr:street":"Chewsville Rd",
    "iso:country":"US",
    "sg:address":"21216 Chewsville Rd",
    "sg:city":"Smithsburg",
    "sg:classifiers":[
        {
            "category":"Real Estate",
            "subcategory":"Real Estate Agent",
            "type":"Services"
        }
    ],
    "sg:phone":"+1 301 739 0537",
    "sg:postcode":"21783",
    "sg:province":"MD",
    "wof:name":"Constance Grimm",
    "wof:placetype":"venue"
},
  "geometry": {"coordinates":[-77.630137,39.634489],"type":"Point"}
}