{
  "type": "Feature",
  "properties": {
    "iso:country":"US",
    "sg:address":"26741 Siloam Rd",
    "sg:city":"Salisbury",
    "sg:classifiers":[
        {
            "category":"Building & Trades",
            "subcategory":"Construction",
            "type":"Services"
        }
    ],
    "sg:phone":"+1 410 334 3708",
    "sg:postcode":"21801",
    "sg:province":"MD",
    "sg:tags":[
        "home",
        "improvement"
    ],
    "wof:name":"Salisbury Renovations",
    "wof:placetype":"venue"
},
  "geometry": {"coordinates":[-75.685861,38.325878],"type":"Point"}
}