{
  "type": "Feature",
  "properties": {
    "iso:country":"US",
    "sg:address":"8019 Belair Rd",
    "sg:city":"Baltimore",
    "sg:classifiers":[
        {
            "category":"Wholesale",
            "subcategory":"Vending Machines",
            "type":"Manufacturing & Wholesale Goods"
        }
    ],
    "sg:phone":"+1 410 661 0973",
    "sg:postcode":"21236",
    "sg:province":"MD",
    "wof:name":"Salisbury Vending",
    "wof:placetype":"venue"
},
  "geometry": {"coordinates":[-76.506867,39.375778],"type":"Point"}
}