{
  "type": "Feature",
  "properties": {
    "iso:country":"US",
    "sg:address":"1610 West St",
    "sg:city":"Annapolis",
    "sg:classifiers":[
        {
            "category":"Personal",
            "subcategory":"Beauty Salon",
            "type":"Services"
        }
    ],
    "sg:phone":"+1 410 268 3344",
    "sg:postcode":"21401",
    "sg:province":"MD",
    "wof:name":"Wills, Tara Le Cce",
    "wof:placetype":"venue"
},
  "geometry": {"coordinates":[-76.51870700000001,38.979328],"type":"Point"}
}