{
  "type": "Feature",
  "properties": {
    "addr:full":"9624 Belair Rd Perry Hall MD 21236",
    "addr:housenumber":"9624",
    "addr:postcode":"21236",
    "addr:street":"Belair Rd",
    "iso:country":"US",
    "sg:address":"9624 Belair Rd",
    "sg:city":"Perry Hall",
    "sg:classifiers":[
        {
            "category":"Insurance",
            "subcategory":"Hazard Insurance",
            "type":"Services"
        }
    ],
    "sg:phone":"+1 410 256 5600",
    "sg:postcode":"21236",
    "sg:province":"MD",
    "wof:name":"Frank Insley - State Farm Insurance",
    "wof:placetype":"venue"
},
  "geometry": {"coordinates":[-76.463116,39.413494],"type":"Point"}
}