{
  "type": "Feature",
  "properties": {
    "addr:full":"18 Bel Air South Pkwy Bel Air MD 21015",
    "addr:housenumber":"18",
    "addr:postcode":"21015",
    "addr:street":"Bel Air South Pkwy",
    "iso:country":"US",
    "sg:address":"18 Bel Air South Pkwy",
    "sg:city":"Bel Air",
    "sg:classifiers":[
        {
            "category":"Retail",
            "subcategory":"Laundry & Dry Cleaning",
            "type":"Services"
        }
    ],
    "sg:phone":"+1 410 569 1362",
    "sg:postcode":"21015",
    "sg:province":"MD",
    "sg:tags":[
        "cleaners"
    ],
    "wof:name":"South Cleaners",
    "wof:placetype":"venue"
},
  "geometry": {"coordinates":[-76.325185,39.497996],"type":"Point"}
}