{
  "type": "Feature",
  "properties": {
    "addr:full":"Old Three Notch Rd Hollywood MD 20636",
    "addr:postcode":"20636",
    "addr:street":"Old Three Notch Rd",
    "iso:country":"US",
    "sg:address":"Old Three Notch Rd",
    "sg:city":"Hollywood",
    "sg:classifiers":[
        {
            "category":"Government",
            "subcategory":"Post Office",
            "type":"Public Place"
        }
    ],
    "sg:phone":"+1 301 373 5215",
    "sg:postcode":"20636",
    "sg:province":"MD",
    "wof:name":"United States Government",
    "wof:placetype":"venue"
},
  "geometry": {"coordinates":[-76.562302,38.3405],"type":"Point"}
}