{
  "type": "Feature",
  "properties": {
    "addr:full":"209 E Joppa Rd Towson MD 21286",
    "addr:housenumber":"209",
    "addr:postcode":"21286",
    "addr:street":"E Joppa Rd",
    "iso:country":"US",
    "sg:address":"209 E Joppa Rd",
    "sg:city":"Towson",
    "sg:classifiers":[
        {
            "category":"Manufacturing",
            "subcategory":"Printing",
            "type":"Manufacturing & Wholesale Goods"
        }
    ],
    "sg:phone":"+1 410 337 8644",
    "sg:postcode":"21286",
    "sg:province":"MD",
    "sg:tags":[
        "publisher"
    ],
    "wof:name":"Doubleclick'd Publications",
    "wof:placetype":"venue"
},
  "geometry": {"coordinates":[-76.59634699999999,39.401792],"type":"Point"}
}