{
  "type": "Feature",
  "properties": {
    "addr:full":"809 Eastern Blvd Essex MD 21221",
    "addr:housenumber":"809",
    "addr:postcode":"21221",
    "addr:street":"Eastern Blvd",
    "iso:country":"US",
    "sg:address":"809 Eastern Blvd",
    "sg:city":"Essex",
    "sg:classifiers":[
        {
            "category":"Banks & Credit Unions",
            "subcategory":"Bank",
            "type":"Services"
        }
    ],
    "sg:phone":"+1 410 686 8822",
    "sg:postcode":"21221",
    "sg:province":"MD",
    "wof:name":"First National Bank of Maryland 347-6000",
    "wof:placetype":"venue"
},
  "geometry": {"coordinates":[-76.467344,39.31155],"type":"Point"}
}