{
  "type": "Feature",
  "properties": {
    "iso:country":"US",
    "sg:address":"2185 Fawn Ct",
    "sg:city":"Waldorf",
    "sg:classifiers":[
        {
            "category":"Professional",
            "subcategory":"Accounting & Tax Preparation",
            "type":"Services"
        }
    ],
    "sg:phone":"+1 301 705 8866",
    "sg:postcode":"20602",
    "sg:province":"MD",
    "sg:tags":[
        "payroll"
    ],
    "wof:name":"Metropolitan Payroll",
    "wof:placetype":"venue"
},
  "geometry": {"coordinates":[-76.88913100000001,38.601859],"type":"Point"}
}