{
  "type": "Feature",
  "properties": {
    "iso:country":"US",
    "sg:address":"5027 Forge Haven Dr",
    "sg:city":"Perry Hall",
    "sg:classifiers":[
        {
            "category":"Autos & Motor Vehicles",
            "subcategory":"Automobile Sales",
            "type":"Retail Goods"
        }
    ],
    "sg:phone":"+1 410 529 5006",
    "sg:postcode":"21128",
    "sg:province":"MD",
    "sg:tags":[
        "limo"
    ],
    "wof:name":"Affordable Luxury Limousine Service",
    "wof:placetype":"venue"
},
  "geometry": {"coordinates":[-76.43090100000001,39.4053],"type":"Point"}
}