{
  "type": "Feature",
  "properties": {
    "iso:country":"US",
    "sg:address":"4711 Montgomery Lane",
    "sg:city":"Bethesda",
    "sg:classifiers":[
        {
            "category":"Personal",
            "subcategory":"Beauty Salon",
            "type":"Services"
        }
    ],
    "sg:phone":"+1 301 907 6810",
    "sg:postcode":"20814",
    "sg:province":"MD",
    "sg:tags":[
        "hair"
    ],
    "sg:website":"www.yourlux.com",
    "wof:name":"Lux Studios",
    "wof:placetype":"venue"
},
  "geometry": {"coordinates":[-77.094031,38.983562],"type":"Point"}
}