{
  "type": "Feature",
  "properties": {
    "iso:country":"US",
    "sg:address":"7283 Cooper Dr",
    "sg:city":"Sykesville",
    "sg:classifiers":[
        {
            "category":"Museum",
            "type":"Entertainment"
        }
    ],
    "sg:phone":"+1 410 549 5150",
    "sg:postcode":"21784",
    "sg:province":"MD",
    "wof:name":"Sykesville Gate House Museum",
    "wof:placetype":"venue"
},
  "geometry": {"coordinates":[-76.96529700000001,39.375577],"type":"Point"}
}