{
  "type": "Feature",
  "properties": {
    "iso:country":"US",
    "sg:address":"10315 Westlake Dr",
    "sg:city":"Bethesda",
    "sg:classifiers":[
        {
            "category":"Cafe",
            "type":"Food & Drink"
        }
    ],
    "sg:menulink":"http://www.allmenus.com/md/potomac/29699-fu-shing-cafe/menu/",
    "sg:phone":"+1 301 469 8878",
    "sg:postcode":"20817",
    "sg:province":"MD",
    "sg:tags":[
        "asian",
        "chinese"
    ],
    "wof:name":"Fu Shing Cafe",
    "wof:placetype":"venue"
},
  "geometry": {"coordinates":[-77.148248,39.026076],"type":"Point"}
}