{
  "type": "Feature",
  "properties": {
    "iso:country":"US",
    "sg:address":"200 Civic Ave",
    "sg:city":"Salisbury",
    "sg:classifiers":[
        {
            "category":"Health Services",
            "subcategory":"Nursing And Care Facility",
            "type":"Services"
        }
    ],
    "sg:phone":"+1 410 749 1466",
    "sg:postcode":"21804",
    "sg:province":"MD",
    "sg:tags":[
        "home",
        "convalescent"
    ],
    "wof:name":"Salisbury Center Genesis",
    "wof:placetype":"venue"
},
  "geometry": {"coordinates":[-75.573109,38.370028],"type":"Point"}
}