{
  "type": "Feature",
  "properties": {
    "iso:country":"US",
    "sg:address":"5205 Nuth Ave",
    "sg:city":"Baltimore",
    "sg:classifiers":[
        {
            "category":"Education",
            "subcategory":"Special Training",
            "type":"Public Place"
        }
    ],
    "sg:phone":"+1 410 485 0095",
    "sg:postcode":"21206",
    "sg:province":"MD",
    "wof:name":"Polyglots In Action",
    "wof:placetype":"venue"
},
  "geometry": {"coordinates":[-76.55223700000001,39.335974],"type":"Point"}
}