{
  "type": "Feature",
  "properties": {
    "iso:country":"US",
    "sg:address":"4822 Wright Ave",
    "sg:city":"Baltimore",
    "sg:classifiers":[
        {
            "category":"Insurance",
            "subcategory":"Hazard Insurance",
            "type":"Services"
        }
    ],
    "sg:phone":"+1 410 483 4625",
    "sg:postcode":"21205",
    "sg:province":"MD",
    "sg:tags":[
        "commercial",
        "business"
    ],
    "wof:name":"Vetri Insurance Services",
    "wof:placetype":"venue"
},
  "geometry": {"coordinates":[-76.559178,39.307931],"type":"Point"}
}