{
  "type": "Feature",
  "properties": {
    "addr:full":"18256 Smoke House Ct Germantown MD 20874",
    "addr:housenumber":"18256",
    "addr:postcode":"20874",
    "addr:street":"Smoke House Ct",
    "iso:country":"US",
    "sg:address":"18256 Smoke House Ct",
    "sg:city":"Germantown",
    "sg:classifiers":[
        {
            "category":"Personal",
            "subcategory":"Nail Salon",
            "type":"Services"
        }
    ],
    "sg:phone":"+1 301 916 6080",
    "sg:postcode":"20874",
    "sg:province":"MD",
    "wof:name":"Belle Nails Ltd",
    "wof:placetype":"venue"
},
  "geometry": {"coordinates":[-77.267786,39.153657],"type":"Point"}
}