{
  "type": "Feature",
  "properties": {
    "iso:country":"US",
    "sg:address":"6 E Main St",
    "sg:city":"Thurmont",
    "sg:classifiers":[
        {
            "category":"Bars & Pubs",
            "type":"Food & Drink"
        },
        {
            "category":"Restaurant",
            "type":"Food & Drink"
        }
    ],
    "sg:phone":"+1 301 271 4171",
    "sg:postcode":"21788",
    "sg:province":"MD",
    "sg:tags":[
        "tavern"
    ],
    "wof:name":"Tommy's Tavern",
    "wof:placetype":"venue"
},
  "geometry": {"coordinates":[-77.411446,39.623696],"type":"Point"}
}