{
  "type": "Feature",
  "properties": {
    "addr:full":"7917 Cessna Ave Gaithersburg MD 20879",
    "addr:housenumber":"7917",
    "addr:postcode":"20879",
    "addr:street":"Cessna Ave",
    "iso:country":"US",
    "sg:address":"7917 Cessna Ave",
    "sg:city":"Gaithersburg",
    "sg:classifiers":[
        {
            "category":"Building & Trades",
            "subcategory":"Construction",
            "type":"Services"
        }
    ],
    "sg:phone":"+1 301 253 3106",
    "sg:postcode":"20879",
    "sg:province":"MD",
    "sg:tags":[
        "general",
        "contractor"
    ],
    "wof:name":"Laytonsville Contractors",
    "wof:placetype":"venue"
},
  "geometry": {"coordinates":[-77.160461,39.171447],"type":"Point"}
}