{
  "type": "Feature",
  "properties": {
    "iso:country":"US",
    "sg:address":"3604 Belair Rd",
    "sg:city":"Baltimore",
    "sg:classifiers":[
        {
            "category":"Wholesale",
            "subcategory":"Apparel",
            "type":"Manufacturing & Wholesale Goods"
        }
    ],
    "sg:phone":"+1 410 325 5454",
    "sg:postcode":"21213",
    "sg:province":"MD",
    "wof:name":"Revolver",
    "wof:placetype":"venue"
},
  "geometry": {"coordinates":[-76.56998400000001,39.324491],"type":"Point"}
}