{
  "type": "Feature",
  "properties": {
    "addr:full":"118 Walnut St Friendsville MD 21531",
    "addr:housenumber":"118",
    "addr:postcode":"21531",
    "addr:street":"Walnut St",
    "iso:country":"US",
    "sg:address":"118 Walnut St",
    "sg:city":"Friendsville",
    "sg:classifiers":[
        {
            "category":"Utilities",
            "subcategory":"Refuse",
            "type":"Services"
        }
    ],
    "sg:phone":"+1 301 746 5620",
    "sg:postcode":"21531",
    "sg:province":"MD",
    "sg:tags":[
        "garbage",
        "collection"
    ],
    "wof:name":"Deep Creek Refuse Svc",
    "wof:placetype":"venue"
},
  "geometry": {"coordinates":[-79.401748,39.664008],"type":"Point"}
}