{
  "type": "Feature",
  "properties": {
    "iso:country":"US",
    "sg:address":"5108 Roland Ave",
    "sg:city":"Baltimore",
    "sg:classifiers":[
        {
            "category":"Education",
            "subcategory":"Library",
            "type":"Public Place"
        }
    ],
    "sg:phone":"+1 410 396 6099",
    "sg:postcode":"21210",
    "sg:province":"MD",
    "sg:tags":[
        "educational",
        "program",
        "administrative"
    ],
    "wof:name":"Enoch Pratt Free Library",
    "wof:placetype":"venue"
},
  "geometry": {"coordinates":[-76.634487,39.354788],"type":"Point"}
}