{
  "type": "Feature",
  "properties": {
    "addr:full":"11501 Fingerboard Rd Monrovia MD 21770",
    "addr:housenumber":"11501",
    "addr:postcode":"21770",
    "addr:street":"Fingerboard Rd",
    "iso:country":"US",
    "sg:address":"11501 Fingerboard Rd",
    "sg:city":"Monrovia",
    "sg:classifiers":[
        {
            "category":"Education",
            "subcategory":"School",
            "type":"Public Place"
        }
    ],
    "sg:phone":"+1 240 236 3400",
    "sg:postcode":"21770",
    "sg:province":"MD",
    "wof:name":"Green Valley Elementary School",
    "wof:placetype":"venue"
},
  "geometry": {"coordinates":[-77.262337,39.344556],"type":"Point"}
}