{
  "type": "Feature",
  "properties": {
    "iso:country":"US",
    "sg:address":"14630 Solomons Island Rd",
    "sg:city":"Solomons",
    "sg:classifiers":[
        {
            "category":"Travel",
            "subcategory":"Hotels & Motels",
            "type":"Entertainment"
        }
    ],
    "sg:phone":"+1 410 326 6790",
    "sg:postcode":"20688",
    "sg:province":"MD",
    "wof:name":"Bowen's Inn",
    "wof:placetype":"venue"
},
  "geometry": {"coordinates":[-76.458062,38.320441],"type":"Point"}
}