{
  "type": "Feature",
  "properties": {
    "addr:full":"25 S Charles St Baltimore MD 21201",
    "addr:housenumber":"25",
    "addr:postcode":"21201",
    "addr:street":"S Charles St",
    "iso:country":"US",
    "sg:address":"25 S Charles St",
    "sg:city":"Baltimore",
    "sg:classifiers":[
        {
            "category":"Professional",
            "subcategory":"Computer Services",
            "type":"Services"
        }
    ],
    "sg:phone":"+1 410 649 0285",
    "sg:postcode":"21201",
    "sg:province":"MD",
    "sg:tags":[
        "telecommunication"
    ],
    "wof:name":"American Telephone & Telegraph",
    "wof:placetype":"venue"
},
  "geometry": {"coordinates":[-76.615065,39.288566],"type":"Point"}
}