{
  "type": "Feature",
  "properties": {
    "addr:full":"123 W 24th St Baltimore MD 21218",
    "addr:housenumber":"123",
    "addr:postcode":"21218",
    "addr:street":"W 24Th St",
    "iso:country":"US",
    "sg:address":"123 W 24th St",
    "sg:city":"Baltimore",
    "sg:classifiers":[
        {
            "category":"Organizations",
            "subcategory":"Religious Organization",
            "type":"Services"
        }
    ],
    "sg:phone":"+1 410 235 6908",
    "sg:postcode":"21218",
    "sg:province":"MD",
    "sg:tags":[
        "church"
    ],
    "wof:name":"Oak St AME Church",
    "wof:placetype":"venue"
},
  "geometry": {"coordinates":[-76.619587,39.316182],"type":"Point"}
}