{
  "type": "Feature",
  "properties": {
    "addr:full":"4414 Pennwood Rd Brentwood MD 20722",
    "addr:housenumber":"4414",
    "addr:postcode":"20722",
    "addr:street":"Pennwood Rd",
    "iso:country":"US",
    "sg:address":"4414 Pennwood Rd",
    "sg:city":"Brentwood",
    "sg:classifiers":[
        {
            "category":"Building & Trades",
            "subcategory":"Construction",
            "type":"Services"
        }
    ],
    "sg:phone":"+1 301 699 7773",
    "sg:postcode":"20722",
    "sg:province":"MD",
    "sg:tags":[
        "house"
    ],
    "wof:name":"C & M Builders Inc",
    "wof:placetype":"venue"
},
  "geometry": {"coordinates":[-76.94934499999999,38.94209],"type":"Point"}
}