{
  "type": "Feature",
  "properties": {
    "addr:full":"11711 Parklawn Dr Rockville MD 20852",
    "addr:housenumber":"11711",
    "addr:postcode":"20852",
    "addr:street":"Parklawn Dr",
    "iso:country":"US",
    "sg:address":"11711 Parklawn Dr",
    "sg:city":"Rockville",
    "sg:classifiers":[
        {
            "category":"Government",
            "subcategory":"Post Office",
            "type":"Public Place"
        }
    ],
    "sg:phone":"+1 301 231 6331",
    "sg:postcode":"20852",
    "sg:province":"MD",
    "wof:name":"US Post Office",
    "wof:placetype":"venue"
},
  "geometry": {"coordinates":[-77.101912,39.048745],"type":"Point"}
}