{
  "type": "Feature",
  "properties": {
    "addr:full":"13625 Annapolis Rd Bowie MD 20720",
    "addr:housenumber":"13625",
    "addr:postcode":"20720",
    "addr:street":"Annapolis Rd",
    "iso:country":"US",
    "sg:address":"13625 Annapolis Rd",
    "sg:city":"Bowie",
    "sg:classifiers":[
        {
            "category":"Retail",
            "subcategory":"Laundry & Dry Cleaning",
            "type":"Services"
        }
    ],
    "sg:phone":"+1 301 805 9807",
    "sg:postcode":"20720",
    "sg:province":"MD",
    "sg:tags":[
        "cleaners"
    ],
    "wof:name":"Colonial Dry Cleaners",
    "wof:placetype":"venue"
},
  "geometry": {"coordinates":[-76.769155,38.971436],"type":"Point"}
}