{
  "type": "Feature",
  "properties": {
    "addr:full":"85 Thomas Johnson Ct Frederick MD 21702",
    "addr:housenumber":"85",
    "addr:postcode":"21702",
    "addr:street":"Thomas Johnson Ct",
    "iso:country":"US",
    "sg:address":"85 Thomas Johnson Ct",
    "sg:city":"Frederick",
    "sg:classifiers":[
        {
            "category":"Health Services",
            "subcategory":"Doctor",
            "type":"Services"
        }
    ],
    "sg:phone":"+1 301 663 0052",
    "sg:postcode":"21702",
    "sg:province":"MD",
    "sg:tags":[
        "dentist"
    ],
    "wof:name":"Koch & Parsons",
    "wof:placetype":"venue"
},
  "geometry": {"coordinates":[-77.40459199999999,39.448953],"type":"Point"}
}