{
  "type": "Feature",
  "properties": {
    "addr:full":"15107 Candy Hill Rd Upper Marlboro MD 20772",
    "addr:housenumber":"15107",
    "addr:postcode":"20772",
    "addr:street":"Candy Hill Rd",
    "iso:country":"US",
    "sg:address":"15107 Candy Hill Rd",
    "sg:city":"Upper Marlboro",
    "sg:classifiers":[
        {
            "category":"Real Estate",
            "subcategory":"Surveying",
            "type":"Services"
        }
    ],
    "sg:phone":"+1 301 888 2990",
    "sg:postcode":"20772",
    "sg:province":"MD",
    "sg:tags":[
        "surveyor"
    ],
    "wof:name":"Design Tech Assoc",
    "wof:placetype":"venue"
},
  "geometry": {"coordinates":[-76.742402,38.712264],"type":"Point"}
}