{
  "type": "Feature",
  "properties": {
    "addr:full":"11345 Pembrooke Sq Waldorf MD 20603",
    "addr:housenumber":"11345",
    "addr:postcode":"20603",
    "addr:street":"Pembrooke Sq",
    "iso:country":"US",
    "sg:address":"11345 Pembrooke Sq",
    "sg:city":"Waldorf",
    "sg:classifiers":[
        {
            "category":"Health Services",
            "subcategory":"Doctor",
            "type":"Services"
        }
    ],
    "sg:phone":"+1 301 645 8120",
    "sg:postcode":"20603",
    "sg:province":"MD",
    "sg:tags":[
        "physician",
        "surgeon"
    ],
    "wof:name":"F J Sauerburger Inc",
    "wof:placetype":"venue"
},
  "geometry": {"coordinates":[-76.917337,38.619255],"type":"Point"}
}