{
  "type": "Feature",
  "properties": {
    "addr:full":"2421 Crofton Ln Crofton MD 21114",
    "addr:housenumber":"2421",
    "addr:postcode":"21114",
    "addr:street":"Crofton Ln",
    "iso:country":"US",
    "sg:address":"2421 Crofton Ln",
    "sg:city":"Crofton",
    "sg:classifiers":[
        {
            "category":"Autos & Motor Vehicles",
            "subcategory":"Auto Supplies",
            "type":"Retail Goods"
        }
    ],
    "sg:phone":"+1 410 451 0202",
    "sg:postcode":"21114",
    "sg:province":"MD",
    "sg:tags":[
        "equipment",
        "racing",
        "car",
        "automobile"
    ],
    "wof:name":"ELD Performance Power Store",
    "wof:placetype":"venue"
},
  "geometry": {"coordinates":[-76.698539,39.014056],"type":"Point"}
}