{
  "type": "Feature",
  "properties": {
    "iso:country":"US",
    "sg:address":"1710 Bloomsberry Ct",
    "sg:city":"Crofton",
    "sg:classifiers":[
        {
            "category":"Social Services",
            "type":"Services"
        },
        {
            "category":"Organizations",
            "subcategory":"Community Association",
            "type":"Services"
        }
    ],
    "sg:phone":"+1 410 451 3998",
    "sg:postcode":"21114",
    "sg:province":"MD",
    "sg:website":"http://www.pnwkiwanis.org",
    "wof:name":"Kiwanis International Inc",
    "wof:placetype":"venue"
},
  "geometry": {"coordinates":[-76.68313999999999,39.015511],"type":"Point"}
}