{
  "type": "Feature",
  "properties": {
    "iso:country":"US",
    "sg:address":"2 N Wickham Rd",
    "sg:city":"Baltimore",
    "sg:classifiers":[
        {
            "category":"Education",
            "subcategory":"Library",
            "type":"Public Place"
        }
    ],
    "sg:phone":"+1 410 644 7341",
    "sg:postcode":"21229",
    "sg:province":"MD",
    "sg:tags":[
        "reading",
        "instruction"
    ],
    "sg:website":"http://www.kumon.com",
    "wof:name":"Kumon Math & Reading Center Of West Baltimore - Sankofa",
    "wof:placetype":"venue"
},
  "geometry": {"coordinates":[-76.69579299999999,39.28347],"type":"Point"}
}