{
  "type": "Feature",
  "properties": {
    "addr:full":"10110 Greenbelt Rd Lanham MD 20706",
    "addr:housenumber":"10110",
    "addr:postcode":"20706",
    "addr:street":"Greenbelt Rd",
    "iso:country":"US",
    "sg:address":"10110 Greenbelt Rd",
    "sg:city":"Lanham",
    "sg:classifiers":[
        {
            "category":"Organizations",
            "subcategory":"Religious Organization",
            "type":"Services"
        }
    ],
    "sg:phone":"+1 301 794 7300",
    "sg:postcode":"20706",
    "sg:province":"MD",
    "sg:tags":[
        "church"
    ],
    "sg:website":"www.goodsamaritan.us.net",
    "wof:name":"Good Samaritan Lutheran Church",
    "wof:placetype":"venue"
},
  "geometry": {"coordinates":[-76.82982699999999,38.991051],"type":"Point"}
}