{
  "type": "Feature",
  "properties": {
    "iso:country":"US",
    "sg:address":"4465 Mountain Rd",
    "sg:city":"Pasadena",
    "sg:classifiers":[
        {
            "category":"Restaurant",
            "type":"Food & Drink"
        }
    ],
    "sg:menulink":"http://www.allmenus.com/md/lake-shore/10580-texas-roadhouse/menu/",
    "sg:phone":"+1 410 439 0233",
    "sg:postcode":"21122",
    "sg:province":"MD",
    "sg:tags":[
        "american",
        "steakhouse"
    ],
    "wof:name":"Texas Roadhouse",
    "wof:placetype":"venue"
},
  "geometry": {"coordinates":[-76.497849,39.109746],"type":"Point"}
}