{
  "type": "Feature",
  "properties": {
    "iso:country":"US",
    "sg:address":"6200 Goldsboro Rd",
    "sg:city":"Bethesda",
    "sg:classifiers":[
        {
            "category":"Wholesale",
            "subcategory":"Computers",
            "type":"Manufacturing & Wholesale Goods"
        }
    ],
    "sg:phone":"+1 301 320 0812",
    "sg:postcode":"20817",
    "sg:province":"MD",
    "sg:tags":[
        "computer-wholesale",
        "manufacturer"
    ],
    "wof:name":"Teltime Inc",
    "wof:placetype":"venue"
},
  "geometry": {"coordinates":[-77.12576300000001,38.971111],"type":"Point"}
}