{
  "type": "Feature",
  "properties": {
    "iso:country":"US",
    "sg:address":"8401 Colesville Rd",
    "sg:city":"Silver Spring",
    "sg:classifiers":[
        {
            "category":"Social Services",
            "type":"Services"
        }
    ],
    "sg:phone":"+1 301 562 1920",
    "sg:postcode":"20910",
    "sg:province":"MD",
    "sg:tags":[
        "organization",
        "welfare"
    ],
    "sg:website":"www.mcd.org",
    "wof:name":"Medical Care Dev Intl Inc",
    "wof:placetype":"venue"
},
  "geometry": {"coordinates":[-77.031623,38.993904],"type":"Point"}
}