{
  "type": "Feature",
  "properties": {
    "addr:full":"105 Bland Dr Indian Head MD 20640",
    "addr:housenumber":"105",
    "addr:postcode":"20640",
    "addr:street":"Bland Dr",
    "iso:country":"US",
    "sg:address":"105 Bland Dr",
    "sg:city":"Indian Head",
    "sg:classifiers":[
        {
            "category":"Recreation",
            "type":"Entertainment"
        }
    ],
    "sg:phone":"+1 301 753 5644",
    "sg:postcode":"20640",
    "sg:province":"MD",
    "wof:name":"Indian Head Martial Arts Ctr",
    "wof:placetype":"venue"
},
  "geometry": {"coordinates":[-77.161413,38.595546],"type":"Point"}
}