{
  "type": "Feature",
  "properties": {
    "iso:country":"US",
    "sg:address":"1838 Greene Tree Rd",
    "sg:city":"Pikesville",
    "sg:classifiers":[
        {
            "category":"Shopping",
            "subcategory":"Optical Goods",
            "type":"Retail Goods"
        }
    ],
    "sg:phone":"+1 410 602 3937",
    "sg:postcode":"21208",
    "sg:province":"MD",
    "wof:name":"Onsite Optical",
    "wof:placetype":"venue"
},
  "geometry": {"coordinates":[-76.735069,39.387809],"type":"Point"}
}