{
  "type": "Feature",
  "properties": {
    "addr:full":"1661 Rockville Pike Rockville MD 20852",
    "addr:housenumber":"1661",
    "addr:postcode":"20852",
    "addr:street":"Rockville Pike",
    "iso:country":"US",
    "sg:address":"1661 Rockville Pike",
    "sg:city":"Rockville",
    "sg:classifiers":[
        {
            "category":"Shopping",
            "subcategory":"Clothing, Apparel, & Fashions",
            "type":"Retail Goods"
        }
    ],
    "sg:phone":"+1 301 770 5275",
    "sg:postcode":"20852",
    "sg:province":"MD",
    "sg:tags":[
        "infant",
        "wear"
    ],
    "sg:website":"www.oshkoshbgosh.com",
    "wof:name":"Osh Kosh B'Gosh",
    "wof:placetype":"venue"
},
  "geometry": {"coordinates":[-77.125809,39.06399],"type":"Point"}
}