{
  "type": "Feature",
  "properties": {
    "iso:country":"US",
    "sg:address":"6568 Macbeth Way",
    "sg:city":"Sykesville",
    "sg:classifiers":[
        {
            "category":"Personal",
            "type":"Services"
        }
    ],
    "sg:phone":"+1 410 549 7385",
    "sg:postcode":"21784",
    "sg:province":"MD",
    "wof:name":"Mark A Livesay Jr",
    "wof:placetype":"venue"
},
  "geometry": {"coordinates":[-76.93558299999999,39.392918],"type":"Point"}
}