{
  "type": "Feature",
  "properties": {
    "addr:full":"4230 Tabler Rd Frederick MD 21704",
    "addr:postcode":"4230;21704",
    "addr:street":"Tabler Rd",
    "iso:country":"US",
    "sg:address":"4230 Tabler Rd",
    "sg:city":"Frederick",
    "sg:classifiers":[
        {
            "category":"Education",
            "subcategory":"Special Training",
            "type":"Public Place"
        }
    ],
    "sg:phone":"+1 301 662 4521",
    "sg:postcode":"21704",
    "sg:province":"MD",
    "sg:tags":[
        "program"
    ],
    "wof:name":"Professional Education & Trng",
    "wof:placetype":"venue"
},
  "geometry": {"coordinates":[-77.362876,39.342199],"type":"Point"}
}