{
  "type": "Feature",
  "properties": {
    "addr:full":"60 Summerhill Trailer Park Crownsville MD 21032",
    "addr:housenumber":"60",
    "addr:postcode":"21032",
    "addr:street":"Summerhill Trailer",
    "iso:country":"US",
    "sg:address":"60 Summerhill Trailer Park",
    "sg:city":"Crownsville",
    "sg:classifiers":[
        {
            "category":"Social Services",
            "subcategory":"Child Care",
            "type":"Services"
        }
    ],
    "sg:phone":"+1 410 849 3138",
    "sg:postcode":"21032",
    "sg:province":"MD",
    "sg:tags":[
        "day"
    ],
    "wof:name":"Miss Janet Pleyo",
    "wof:placetype":"venue"
},
  "geometry": {"coordinates":[-76.58887300000001,39.007152],"type":"Point"}
}