{
  "type": "Feature",
  "properties": {
    "iso:country":"US",
    "sg:address":"20528 Boland Farm Rd",
    "sg:city":"Germantown",
    "sg:classifiers":[
        {
            "category":"Health Services",
            "subcategory":"Medical Lab",
            "type":"Services"
        }
    ],
    "sg:phone":"+1 301 253 6498",
    "sg:postcode":"20876",
    "sg:province":"MD",
    "sg:tags":[
        "laboratory"
    ],
    "wof:name":"Quest Diagnostics",
    "wof:placetype":"venue"
},
  "geometry": {"coordinates":[-77.249899,39.192112],"type":"Point"}
}