{
  "type": "Feature",
  "properties": {
    "iso:country":"US",
    "sg:address":"1018 Bernoudy Rd",
    "sg:city":"White Hall",
    "sg:classifiers":[
        {
            "category":"Professional",
            "subcategory":"Business Services",
            "type":"Services"
        }
    ],
    "sg:phone":"+1 410 357 8000",
    "sg:postcode":"21161",
    "sg:province":"MD",
    "sg:tags":[
        "statistical"
    ],
    "wof:name":"Research Assessment & Msrmnt",
    "wof:placetype":"venue"
},
  "geometry": {"coordinates":[-76.641471,39.621568],"type":"Point"}
}