{
  "type": "Feature",
  "properties": {
    "iso:country":"US",
    "sg:address":"4134 E Joppa Rd Ste 101",
    "sg:city":"Nottingham",
    "sg:classifiers":[
        {
            "category":"Health Services",
            "subcategory":"Chiropractor",
            "type":"Services"
        }
    ],
    "sg:phone":"+1 410 529 5003",
    "sg:postcode":"21236",
    "sg:province":"MD",
    "sg:tags":[
        "chiropractic"
    ],
    "wof:name":"Heil Chiropractic",
    "wof:placetype":"venue"
},
  "geometry": {"coordinates":[-76.48403500000001,39.398037],"type":"Point"}
}