{
  "type": "Feature",
  "properties": {
    "iso:country":"US",
    "sg:address":"150 Penrod Ct",
    "sg:city":"Glen Burnie",
    "sg:classifiers":[
        {
            "category":"Home & Garden",
            "subcategory":"Furniture",
            "type":"Retail Goods"
        }
    ],
    "sg:phone":"+1 410 787 9806",
    "sg:postcode":"21061",
    "sg:province":"MD",
    "sg:tags":[
        "builder",
        "custom"
    ],
    "wof:name":"Banks Woodworking",
    "wof:placetype":"venue"
},
  "geometry": {"coordinates":[-76.623268,39.17792],"type":"Point"}
}