{
  "type": "Feature",
  "properties": {
    "iso:country":"US",
    "sg:address":"1930 Lincoln Dr",
    "sg:city":"Annapolis",
    "sg:classifiers":[
        {
            "category":"Autos & Motor Vehicles",
            "subcategory":"Motorcycle Sales",
            "type":"Retail Goods"
        }
    ],
    "sg:phone":"+1 410 267 9090",
    "sg:postcode":"21401",
    "sg:province":"MD",
    "sg:tags":[
        "scooter"
    ],
    "wof:name":"Annapolis Atv's Scooters",
    "wof:placetype":"venue"
},
  "geometry": {"coordinates":[-76.521423,38.97344],"type":"Point"}
}