{
  "type": "Feature",
  "properties": {
    "iso:country":"US",
    "sg:address":"700 Gaither Rd",
    "sg:city":"Rockville",
    "sg:classifiers":[
        {
            "category":"Bakery",
            "type":"Food & Drink"
        },
        {
            "category":"Coffee & Tea",
            "type":"Food & Drink"
        },
        {
            "category":"Bagels",
            "type":"Food & Drink"
        },
        {
            "category":"Donuts",
            "type":"Food & Drink"
        }
    ],
    "sg:menulink":"http://www.allmenus.com/md/rockville/148831-dunkin-donuts/menu/",
    "sg:phone":"+1 301 330 5471",
    "sg:postcode":"20850",
    "sg:province":"MD",
    "sg:tags":[
        "wrap",
        "american",
        "sandwich",
        "pastry"
    ],
    "wof:name":"Dunkin' Donuts",
    "wof:placetype":"venue"
},
  "geometry": {"coordinates":[-77.173737,39.109142],"type":"Point"}
}