{
  "type": "Feature",
  "properties": {
    "iso:country":"US",
    "sg:address":"6 E Eager St",
    "sg:city":"Baltimore",
    "sg:classifiers":[
        {
            "category":"Freight",
            "type":"Transportation"
        }
    ],
    "sg:phone":"+1 410 385 9000",
    "sg:postcode":"21202",
    "sg:province":"MD",
    "sg:tags":[
        "delivery"
    ],
    "sg:website":"www.qms-md.com",
    "wof:name":"Quick Messenger Svc",
    "wof:placetype":"venue"
},
  "geometry": {"coordinates":[-76.615536,39.30111],"type":"Point"}
}