{
  "type": "Feature",
  "properties": {
    "addr:full":"8900 Cheltenham Ave Clinton MD 20735",
    "addr:housenumber":"8900",
    "addr:postcode":"20735",
    "addr:street":"Cheltenham Ave",
    "iso:country":"US",
    "sg:address":"8900 Cheltenham Ave",
    "sg:city":"Clinton",
    "sg:classifiers":[
        {
            "category":"Professional",
            "subcategory":"Management & Consulting",
            "type":"Services"
        }
    ],
    "sg:phone":"+1 301 856 3137",
    "sg:postcode":"20735",
    "sg:province":"MD",
    "wof:name":"Dmk Marketing",
    "wof:placetype":"venue"
},
  "geometry": {"coordinates":[-76.85840399999999,38.765777],"type":"Point"}
}