{
  "type": "Feature",
  "properties": {
    "addr:full":"9615 Horsham Dr Laurel MD 20723",
    "addr:housenumber":"9615",
    "addr:postcode":"20723",
    "addr:street":"Horsham Dr",
    "iso:country":"US",
    "sg:address":"9615 Horsham Dr",
    "sg:city":"Laurel",
    "sg:classifiers":[
        {
            "category":"Professional",
            "subcategory":"Secretarial Services",
            "type":"Services"
        }
    ],
    "sg:phone":"+1 301 362 4369",
    "sg:postcode":"20723",
    "sg:province":"MD",
    "sg:tags":[
        "reporting"
    ],
    "wof:name":"Tracy I Obering",
    "wof:placetype":"venue"
},
  "geometry": {"coordinates":[-76.837762,39.131392],"type":"Point"}
}