{
  "type": "Feature",
  "properties": {
    "iso:country":"US",
    "sg:address":"1538 York Rd",
    "sg:city":"Lutherville",
    "sg:classifiers":[
        {
            "category":"Food & Beverages",
            "subcategory":"Groceries & Convenience Stores",
            "type":"Retail Goods"
        }
    ],
    "sg:phone":"+1 410 296 5171",
    "sg:postcode":"21093",
    "sg:province":"MD",
    "wof:name":"7-Eleven",
    "wof:placetype":"venue"
},
  "geometry": {"coordinates":[-76.617868,39.422554],"type":"Point"}
}