{
  "type": "Feature",
  "properties": {
    "iso:country":"US",
    "sg:address":"3734 Cross Bow Ct",
    "sg:city":"Ellicott City",
    "sg:classifiers":[
        {
            "category":"Professional",
            "subcategory":"Business Services",
            "type":"Services"
        }
    ],
    "sg:phone":"+1 301 972 1680",
    "sg:postcode":"21042",
    "sg:province":"MD",
    "sg:tags":[
        "design",
        "facility"
    ],
    "wof:name":"Culinary Design LLC",
    "wof:placetype":"venue"
},
  "geometry": {"coordinates":[-76.87026,39.267915],"type":"Point"}
}