{
  "type": "Feature",
  "properties": {
    "addr:full":"9308 Allentown Rd Fort Washington MD 20744",
    "addr:housenumber":"9308",
    "addr:postcode":"20744",
    "addr:street":"Allentown Rd",
    "iso:country":"US",
    "sg:address":"9308 Allentown Rd",
    "sg:city":"Fort Washington",
    "sg:classifiers":[
        {
            "category":"Organizations",
            "subcategory":"Religious Organization",
            "type":"Services"
        }
    ],
    "sg:phone":"+1 301 449 6210",
    "sg:postcode":"20744",
    "sg:province":"MD",
    "sg:tags":[
        "church"
    ],
    "wof:name":"Victory Church Intnl",
    "wof:placetype":"venue"
},
  "geometry": {"coordinates":[-76.961596,38.7605],"type":"Point"}
}