{
  "type": "Feature",
  "properties": {
    "iso:country":"US",
    "sg:address":"4260 Port Tobacco Rd",
    "sg:city":"Nanjemoy",
    "sg:classifiers":[
        {
            "category":"Government",
            "subcategory":"Fire Station",
            "type":"Public Place"
        }
    ],
    "sg:phone":"+1 301 246 4322",
    "sg:postcode":"20662",
    "sg:province":"MD",
    "sg:tags":[
        "department"
    ],
    "wof:name":"Nanjemoy Volunteer Fire Department Inc",
    "wof:placetype":"venue"
},
  "geometry": {"coordinates":[-77.21466100000001,38.455429],"type":"Point"}
}