{
  "type": "Feature",
  "properties": {
    "addr:full":"800 Falls Lake Dr Bowie MD 20721",
    "addr:housenumber":"800",
    "addr:postcode":"20721",
    "addr:street":"Falls Lake Dr",
    "iso:country":"US",
    "sg:address":"800 Falls Lake Dr",
    "sg:city":"Bowie",
    "sg:classifiers":[
        {
            "category":"Health Services",
            "subcategory":"Doctor",
            "type":"Services"
        }
    ],
    "sg:phone":"+1 301 793 3771",
    "sg:postcode":"20721",
    "sg:province":"MD",
    "sg:tags":[
        "physician",
        "surgeon"
    ],
    "sg:website":"http://www.loismailoujones.com",
    "wof:name":"Chapman Pharmaceutical Health Foundation, Inc.",
    "wof:placetype":"venue"
},
  "geometry": {"coordinates":[-76.829002,38.901501],"type":"Point"}
}