{
  "type": "Feature",
  "properties": {
    "addr:full":"9043 Shady Grove Ct Gaithersburg MD 20877",
    "addr:housenumber":"9043",
    "addr:postcode":"20877",
    "addr:street":"Shady Grove Ct",
    "iso:country":"US",
    "sg:address":"9043 Shady Grove Ct",
    "sg:city":"Gaithersburg",
    "sg:classifiers":[
        {
            "category":"Social Services",
            "type":"Services"
        }
    ],
    "sg:phone":"+1 301 670 6866",
    "sg:postcode":"20877",
    "sg:province":"MD",
    "sg:tags":[
        "professional",
        "counselors-licensed"
    ],
    "wof:name":"Cathleen A Glass Lcsw-C Bcd",
    "wof:placetype":"venue"
},
  "geometry": {"coordinates":[-77.183914,39.119468],"type":"Point"}
}