{
  "type": "Feature",
  "properties": {
    "addr:full":"12513 Holdridge Rd Silver Spring MD 20906",
    "addr:postcode":"12513;20906",
    "addr:street":"Holdridge Rd",
    "iso:country":"US",
    "sg:address":"12513 Holdridge Rd",
    "sg:city":"Silver Spring",
    "sg:classifiers":[
        {
            "category":"Building & Trades",
            "subcategory":"Construction",
            "type":"Services"
        }
    ],
    "sg:phone":"+1 301 942 7476",
    "sg:postcode":"20906",
    "sg:province":"MD",
    "sg:tags":[
        "painter"
    ],
    "wof:name":"Stephens Decorators",
    "wof:placetype":"venue"
},
  "geometry": {"coordinates":[-77.05785299999999,39.062491],"type":"Point"}
}