{
  "type": "Feature",
  "properties": {
    "addr:full":"4131 Belt Rd Capitol Heights MD 20743",
    "addr:housenumber":"4131",
    "addr:postcode":"20743",
    "addr:street":"Belt Rd",
    "iso:country":"US",
    "sg:address":"4131 Belt Rd",
    "sg:city":"Capitol Heights",
    "sg:classifiers":[
        {
            "category":"Organizations",
            "subcategory":"Religious Organization",
            "type":"Services"
        }
    ],
    "sg:phone":"+1 301 735 1020",
    "sg:postcode":"20743",
    "sg:province":"MD",
    "sg:tags":[
        "church"
    ],
    "sg:website":"www.msbbcs.edu",
    "wof:name":"Maple Springs Baptist Church",
    "wof:placetype":"venue"
},
  "geometry": {"coordinates":[-76.942858,38.86374],"type":"Point"}
}