{
  "type": "Feature",
  "properties": {
    "iso:country":"US",
    "sg:address":"8722 Postoak Rd",
    "sg:city":"Potomac",
    "sg:classifiers":[
        {
            "category":"Personal",
            "type":"Services"
        }
    ],
    "sg:phone":"+1 301 765 9647",
    "sg:postcode":"20854",
    "sg:province":"MD",
    "sg:tags":[
        "therapist",
        "massage"
    ],
    "wof:name":"Hands That Heal",
    "wof:placetype":"venue"
},
  "geometry": {"coordinates":[-77.178414,39.047846],"type":"Point"}
}