{
  "type": "Feature",
  "properties": {
    "iso:country":"US",
    "sg:address":"7381 Washington Blvd",
    "sg:city":"Elkridge",
    "sg:classifiers":[
        {
            "category":"Shopping",
            "subcategory":"Computers & Home Electronics",
            "type":"Retail Goods"
        }
    ],
    "sg:phone":"+1 410 796 5999",
    "sg:postcode":"21075",
    "sg:province":"MD",
    "sg:tags":[
        "equipment",
        "electronic",
        "supply"
    ],
    "wof:name":"C F Marketing",
    "wof:placetype":"venue"
},
  "geometry": {"coordinates":[-76.768583,39.18068],"type":"Point"}
}