{
  "type": "Feature",
  "properties": {
    "addr:full":"7381 Washington Blvd Elkridge MD 21075",
    "addr:housenumber":"7381",
    "addr:postcode":"21075",
    "addr:street":"Washington Blvd",
    "iso:country":"US",
    "sg:address":"7381 Washington Blvd",
    "sg:city":"Elkridge",
    "sg:classifiers":[
        {
            "category":"Shopping",
            "subcategory":"Computers & Home Electronics",
            "type":"Retail Goods"
        }
    ],
    "sg:phone":"+1 410 796 5999",
    "sg:postcode":"21075",
    "sg:province":"MD",
    "sg:tags":[
        "equipment",
        "electronic",
        "supply"
    ],
    "wof:name":"C F Marketing",
    "wof:placetype":"venue"
},
  "geometry": {"coordinates":[-76.76858300000001,39.18068],"type":"Point"}
}