{
  "type": "Feature",
  "properties": {
    "iso:country":"US",
    "sg:address":"821 Fieldcrest Rd",
    "sg:city":"Cambridge",
    "sg:classifiers":[
        {
            "category":"Health Services",
            "subcategory":"Hospital",
            "type":"Services"
        }
    ],
    "sg:phone":"+1 410 221 0288",
    "sg:postcode":"21613",
    "sg:province":"MD",
    "sg:tags":[
        "mental"
    ],
    "wof:name":"Chesapeake Youth Ctr",
    "wof:placetype":"venue"
},
  "geometry": {"coordinates":[-76.059738,38.547841],"type":"Point"}
}