{
  "type": "Feature",
  "properties": {
    "addr:full":"11836 Belair Rd Kingsville MD 21087",
    "addr:housenumber":"11836",
    "addr:postcode":"21087",
    "addr:street":"Belair Rd",
    "iso:country":"US",
    "sg:address":"11836 Belair Rd",
    "sg:city":"Kingsville",
    "sg:classifiers":[
        {
            "category":"Professional",
            "subcategory":"Accounting & Tax Preparation",
            "type":"Services"
        }
    ],
    "sg:phone":"+1 410 817 9779",
    "sg:postcode":"21087",
    "sg:province":"MD",
    "sg:tags":[
        "accountant"
    ],
    "wof:name":"Baltimore Accounting Group LLC",
    "wof:placetype":"venue"
},
  "geometry": {"coordinates":[-76.418306,39.448831],"type":"Point"}
}