{
  "type": "Feature",
  "properties": {
    "addr:full":"5418 White Mane Columbia MD 21045",
    "addr:housenumber":"5418",
    "addr:postcode":"21045",
    "addr:street":"White Mane",
    "iso:country":"US",
    "sg:address":"5418 White Mane",
    "sg:city":"Columbia",
    "sg:classifiers":[
        {
            "category":"Professional",
            "subcategory":"Secretarial Services",
            "type":"Services"
        }
    ],
    "sg:phone":"+1 410 992 7626",
    "sg:postcode":"21045",
    "sg:province":"MD",
    "sg:tags":[
        "reporting"
    ],
    "wof:name":"Diane Gordon Reidmann",
    "wof:placetype":"venue"
},
  "geometry": {"coordinates":[-76.82075399999999,39.222767],"type":"Point"}
}