{
  "type": "Feature",
  "properties": {
    "addr:full":"1919 Pulaski Hwy Edgewood MD 21040",
    "addr:housenumber":"1919",
    "addr:postcode":"21040",
    "addr:street":"Pulaski Hwy",
    "iso:country":"US",
    "sg:address":"1919 Pulaski Hwy",
    "sg:city":"Edgewood",
    "sg:classifiers":[
        {
            "category":"Autos & Motor Vehicles",
            "subcategory":"Auto Supplies",
            "type":"Retail Goods"
        }
    ],
    "sg:phone":"+1 410 679 6800",
    "sg:postcode":"21040",
    "sg:province":"MD",
    "sg:tags":[
        "tire"
    ],
    "sg:website":"www.firestonecompleteautocare.com",
    "wof:name":"Firestone Tire & Service Centers",
    "wof:placetype":"venue"
},
  "geometry": {"coordinates":[-76.314903,39.435299],"type":"Point"}
}