{
  "type": "Feature",
  "properties": {
    "addr:full":"33524 Wango Rd Parsonsburg MD 21849",
    "addr:postcode":"33524;21849",
    "addr:street":"Wango Rd",
    "iso:country":"US",
    "sg:address":"33524 Wango Rd",
    "sg:city":"Parsonsburg",
    "sg:classifiers":[
        {
            "category":"Organizations",
            "subcategory":"Religious Organization",
            "type":"Services"
        }
    ],
    "sg:phone":"+1 410 835 2616",
    "sg:postcode":"21849",
    "sg:province":"MD",
    "sg:tags":[
        "church"
    ],
    "wof:name":"Jesus Christ Of Nazareth Chr",
    "wof:placetype":"venue"
},
  "geometry": {"coordinates":[-75.449714,38.321588],"type":"Point"}
}