{
  "type": "Feature",
  "properties": {
    "addr:full":"7658 Belair Rd Nottingham MD 21236",
    "addr:housenumber":"7658",
    "addr:postcode":"21236",
    "addr:street":"Belair Rd",
    "iso:country":"US",
    "sg:address":"7658 Belair Rd",
    "sg:city":"Nottingham",
    "sg:classifiers":[
        {
            "category":"Health Services",
            "subcategory":"Doctor",
            "type":"Services"
        }
    ],
    "sg:phone":"+1 410 882 6841",
    "sg:postcode":"21236",
    "sg:province":"MD",
    "wof:name":"Abdur-Rahman Najla MD",
    "wof:placetype":"venue"
},
  "geometry": {"coordinates":[-76.517781,39.366388],"type":"Point"}
}