{
  "type": "Feature",
  "properties": {
    "iso:country":"US",
    "sg:address":"1519 Ringe Dr",
    "sg:city":"Severn",
    "sg:classifiers":[
        {
            "category":"Shopping",
            "subcategory":"Hobbies, Toys, & Games",
            "type":"Retail Goods"
        }
    ],
    "sg:phone":"+1 410 519 6107",
    "sg:postcode":"21144",
    "sg:province":"MD",
    "sg:tags":[
        "basket"
    ],
    "wof:name":"Touch Of Baskets",
    "wof:placetype":"venue"
},
  "geometry": {"coordinates":[-76.68431699999999,39.093694],"type":"Point"}
}