{
  "type": "Feature",
  "properties": {
    "addr:full":"31120 Ward Rd Salisbury MD 21804",
    "addr:housenumber":"31120",
    "addr:postcode":"21804",
    "addr:street":"Ward Rd",
    "iso:country":"US",
    "sg:address":"31120 Ward Rd",
    "sg:city":"Salisbury",
    "sg:classifiers":[
        {
            "category":"Retail",
            "subcategory":"Repair Shop",
            "type":"Services"
        }
    ],
    "sg:phone":"+1 410 546 0644",
    "sg:postcode":"21804",
    "sg:province":"MD",
    "wof:name":"Upholstery Shoppe",
    "wof:placetype":"venue"
},
  "geometry": {"coordinates":[-75.534752,38.337596],"type":"Point"}
}