{
  "type": "Feature",
  "properties": {
    "addr:full":"32209 Park Ave Queen Anne MD 21657",
    "addr:housenumber":"32209",
    "addr:postcode":"21657",
    "addr:street":"Park Ave",
    "iso:country":"US",
    "sg:address":"32209 Park Ave",
    "sg:city":"Queen Anne",
    "sg:classifiers":[
        {
            "category":"Government",
            "subcategory":"Post Office",
            "type":"Public Place"
        }
    ],
    "sg:phone":"+1 410 820 2939",
    "sg:postcode":"21657",
    "sg:province":"MD",
    "wof:name":"US Post Office",
    "wof:placetype":"venue"
},
  "geometry": {"coordinates":[-75.954145,38.919104],"type":"Point"}
}