{
  "type": "Feature",
  "properties": {
    "addr:full":"4602 Brava Ct Fort Washington MD 20744",
    "addr:housenumber":"4602",
    "addr:postcode":"20744",
    "addr:street":"Brava Ct",
    "iso:country":"US",
    "sg:address":"4602 Brava Ct",
    "sg:city":"Fort Washington",
    "sg:classifiers":[
        {
            "category":"Building & Trades",
            "subcategory":"Construction",
            "type":"Services"
        }
    ],
    "sg:phone":"+1 301 449 1801",
    "sg:postcode":"20744",
    "sg:province":"MD",
    "sg:tags":[
        "remodeling",
        "dwelling",
        "family"
    ],
    "wof:name":"Specialized Service & Assoc",
    "wof:placetype":"venue"
},
  "geometry": {"coordinates":[-76.92909400000001,38.789209],"type":"Point"}
}