{
  "type": "Feature",
  "properties": {
    "iso:country":"US",
    "sg:address":"3829 Mount Airy Dr",
    "sg:city":"Mt Airy",
    "sg:classifiers":[
        {
            "category":"Building & Trades",
            "subcategory":"Construction",
            "type":"Services"
        }
    ],
    "sg:phone":"+1 301 831 7909",
    "sg:postcode":"21771",
    "sg:province":"MD",
    "sg:tags":[
        "woodworker"
    ],
    "wof:name":"Big Timber Woodworks",
    "wof:placetype":"venue"
},
  "geometry": {"coordinates":[-77.13885999999999,39.409669],"type":"Point"}
}