{
  "type": "Feature",
  "properties": {
    "addr:full":"13836 Blair Stone Ln Silver Spring MD 20906",
    "addr:housenumber":"13836",
    "addr:postcode":"20906",
    "addr:street":"Blair Stone Ln",
    "iso:country":"US",
    "sg:address":"13836 Blair Stone Ln",
    "sg:city":"Silver Spring",
    "sg:classifiers":[
        {
            "category":"Professional",
            "subcategory":"Management & Consulting",
            "type":"Services"
        }
    ],
    "sg:phone":"+1 301 871 1752",
    "sg:postcode":"20906",
    "sg:province":"MD",
    "sg:tags":[
        "construction"
    ],
    "wof:name":"North South Construction",
    "wof:placetype":"venue"
},
  "geometry": {"coordinates":[-77.056667,39.084706],"type":"Point"}
}