{
  "type": "Feature",
  "properties": {
    "iso:country":"US",
    "sg:address":"26505 Mechanicsville Rd",
    "sg:city":"Mechanicsville",
    "sg:classifiers":[
        {
            "category":"Building & Trades",
            "subcategory":"Plumbing",
            "type":"Services"
        }
    ],
    "sg:phone":"+1 301 884 5592",
    "sg:postcode":"20659",
    "sg:province":"MD",
    "sg:tags":[
        "tank",
        "septic"
    ],
    "wof:name":"Wayne's Drains Backhoe & Sptc",
    "wof:placetype":"venue"
},
  "geometry": {"coordinates":[-76.770617,38.398335],"type":"Point"}
}