{
  "type": "Feature",
  "properties": {
    "addr:full":"8316 Gibbons Dr Fort Washington MD 20744",
    "addr:housenumber":"8316",
    "addr:postcode":"20744",
    "addr:street":"Gibbons Dr",
    "iso:country":"US",
    "sg:address":"8316 Gibbons Dr",
    "sg:city":"Fort Washington",
    "sg:classifiers":[
        {
            "category":"Social Services",
            "subcategory":"Child Care",
            "type":"Services"
        }
    ],
    "sg:phone":"+1 301 248 6220",
    "sg:postcode":"20744",
    "sg:province":"MD",
    "wof:name":"Fundamental Early Learning Ctr",
    "wof:placetype":"venue"
},
  "geometry": {"coordinates":[-76.941104,38.776054],"type":"Point"}
}