{
  "type": "Feature",
  "properties": {
    "iso:country":"US",
    "sg:address":"1427 Lowman St",
    "sg:city":"Baltimore",
    "sg:classifiers":[
        {
            "category":"Building & Trades",
            "subcategory":"Construction",
            "type":"Services"
        }
    ],
    "sg:phone":"+1 410 528 0086",
    "sg:postcode":"21230",
    "sg:province":"MD",
    "sg:tags":[
        "home",
        "improvement"
    ],
    "wof:name":"Old World Home Improvements",
    "wof:placetype":"venue"
},
  "geometry": {"coordinates":[-76.595455,39.270003],"type":"Point"}
}