{
  "type": "Feature",
  "properties": {
    "iso:country":"US",
    "sg:address":"233 E Redwood St",
    "sg:city":"Baltimore",
    "sg:classifiers":[
        {
            "category":"Professional",
            "subcategory":"Lawyer & Legal Services",
            "type":"Services"
        }
    ],
    "sg:phone":"+1 410 576 4047",
    "sg:postcode":"21202",
    "sg:province":"MD",
    "sg:tags":[
        "attorney"
    ],
    "wof:name":"Matthew P Mellin",
    "wof:placetype":"venue"
},
  "geometry": {"coordinates":[-76.611198,39.288905],"type":"Point"}
}