{
  "type": "Feature",
  "properties": {
    "iso:country":"US",
    "sg:address":"7480 Conowingo Ave",
    "sg:city":"Jessup",
    "sg:classifiers":[
        {
            "category":"Transit Center",
            "subcategory":"Freight",
            "type":"Transportation"
        }
    ],
    "sg:phone":"+1 410 799 4035",
    "sg:postcode":"20794",
    "sg:province":"MD",
    "sg:tags":[
        "container",
        "broker"
    ],
    "wof:name":"Lombardi Transfer",
    "wof:placetype":"venue"
},
  "geometry": {"coordinates":[-76.78357,39.165481],"type":"Point"}
}