{
  "type": "Feature",
  "properties": {
    "iso:country":"US",
    "sg:address":"833 Russell Ave",
    "sg:city":"Gaithersburg",
    "sg:classifiers":[
        {
            "category":"Food & Beverages",
            "subcategory":"Supermarket",
            "type":"Retail Goods"
        },
        {
            "category":"Food & Beverages",
            "subcategory":"Groceries & Convenience Stores",
            "type":"Retail Goods"
        }
    ],
    "sg:phone":"+1 301 963 9775",
    "sg:postcode":"20879",
    "sg:province":"MD",
    "sg:tags":[
        "super"
    ],
    "wof:name":"Bloom",
    "wof:placetype":"venue"
},
  "geometry": {"coordinates":[-77.21019800000001,39.155219],"type":"Point"}
}