{
  "type": "Feature",
  "properties": {
    "addr:full":"10211 Wincopin Cir Columbia MD 21044",
    "addr:housenumber":"10211",
    "addr:postcode":"21044",
    "addr:street":"Wincopin Cir",
    "iso:country":"US",
    "sg:address":"10211 Wincopin Cir",
    "sg:city":"Columbia",
    "sg:classifiers":[
        {
            "category":"Organizations",
            "subcategory":"Non-profit Organization",
            "type":"Services"
        }
    ],
    "sg:phone":"+1 443 276 0580",
    "sg:postcode":"21044",
    "sg:province":"MD",
    "sg:tags":[
        "charity",
        "foundations-educational",
        "philanthropic",
        "research"
    ],
    "wof:name":"Viragh Family Foundation",
    "wof:placetype":"venue"
},
  "geometry": {"coordinates":[-76.854912,39.216703],"type":"Point"}
}