{
  "type": "Feature",
  "properties": {
    "addr:full":"1514 Woodlawn Dr Baltimore MD 21207",
    "addr:housenumber":"1514",
    "addr:postcode":"21207",
    "addr:street":"Woodlawn Dr",
    "iso:country":"US",
    "sg:address":"1514 Woodlawn Dr",
    "sg:city":"Baltimore",
    "sg:classifiers":[
        {
            "category":"Banks & Credit Unions",
            "subcategory":"Bank",
            "type":"Services"
        }
    ],
    "sg:phone":"+1 410 448 3170",
    "sg:postcode":"21207",
    "sg:province":"MD",
    "sg:tags":[
        "personal",
        "institution"
    ],
    "wof:name":"Regional Acceptance Corp",
    "wof:placetype":"venue"
},
  "geometry": {"coordinates":[-76.734206,39.306399],"type":"Point"}
}