{
  "type": "Feature",
  "properties": {
    "addr:full":"25510 Warren Ave Cascade MD 21719",
    "addr:housenumber":"25510",
    "addr:postcode":"21719",
    "addr:street":"Warren Ave",
    "iso:country":"US",
    "sg:address":"25510 Warren Ave",
    "sg:city":"Cascade",
    "sg:classifiers":[
        {
            "category":"Professional",
            "subcategory":"Business Services",
            "type":"Services"
        }
    ],
    "sg:phone":"+1 301 241 3124",
    "sg:postcode":"21719",
    "sg:province":"MD",
    "sg:tags":[
        "auctioneer"
    ],
    "wof:name":"Highland Auction & Glass",
    "wof:placetype":"venue"
},
  "geometry": {"coordinates":[-77.476814,39.719967],"type":"Point"}
}