{
  "type": "Feature",
  "properties": {
    "addr:city":"Piney Point",
    "addr:full":"44701 Lighthouse Rd Piney Point, Md 20674",
    "addr:house_number":"44701",
    "addr:housenumber":"44701",
    "addr:phone":"+1 301-994-1471",
    "addr:postcode":"20674",
    "addr:road":"Lighthouse Rd",
    "addr:state":"MD",
    "addr:street":"Lighthouse Rd",
    "iso:country":"US",
    "sg:address":"44701 Lighthouse Rd",
    "sg:city":"Piney Point",
    "sg:classifiers":[
        {
            "category":"Museum",
            "type":"Entertainment"
        }
    ],
    "sg:phone":"+1 301 994 1471",
    "sg:postcode":"20674",
    "sg:province":"MD",
    "wof:name":"Piney Point Light House",
    "wof:placetype":"venue"
},
  "geometry": {"coordinates":[-76.52757,38.13643],"type":"Point"}
}