{
  "type": "Feature",
  "properties": {
    "iso:country":"US",
    "sg:address":"11333 Owings Mills Blvd",
    "sg:city":"Owings Mills",
    "sg:classifiers":[
        {
            "category":"Freight",
            "type":"Transportation"
        }
    ],
    "sg:phone":"+1 410 363 8080",
    "sg:postcode":"21117",
    "sg:province":"MD",
    "sg:tags":[
        "commercial",
        "storage"
    ],
    "wof:name":"E-Z Storage",
    "wof:placetype":"venue"
},
  "geometry": {"coordinates":[-76.780537,39.433383],"type":"Point"}
}