{
  "type": "Feature",
  "properties": {
    "iso:country":"US",
    "sg:address":"618 Boulton St",
    "sg:city":"Bel Air",
    "sg:classifiers":[
        {
            "category":"Home & Garden",
            "subcategory":"Furniture",
            "type":"Retail Goods"
        }
    ],
    "sg:phone":"+1 410 879 3980",
    "sg:postcode":"21014",
    "sg:province":"MD",
    "sg:website":"www.gardiners.com",
    "wof:name":"Gardiner's Furniture",
    "wof:placetype":"venue"
},
  "geometry": {"coordinates":[-76.359734,39.526636],"type":"Point"}
}