{
  "type": "Feature",
  "properties": {
    "iso:country":"US",
    "sg:address":"16 E Lombard St",
    "sg:city":"Baltimore",
    "sg:classifiers":[
        {
            "category":"Professional",
            "subcategory":"Management & Consulting",
            "type":"Services"
        },
        {
            "category":"Banks & Credit Unions",
            "subcategory":"Financial Services",
            "type":"Services"
        }
    ],
    "sg:phone":"+1 443 524 0370",
    "sg:postcode":"21202",
    "sg:province":"MD",
    "sg:tags":[
        "consultant",
        "financing",
        "planning"
    ],
    "wof:name":"E L W Financial Group",
    "wof:placetype":"venue"
},
  "geometry": {"coordinates":[-76.614784,39.287738],"type":"Point"}
}