{
  "type": "Feature",
  "properties": {
    "addr:full":"6836 New Hampshire Ave Takoma Park MD 20912",
    "addr:housenumber":"6836",
    "addr:postcode":"20912",
    "addr:street":"New Hampshire Ave",
    "iso:country":"US",
    "sg:address":"6836 New Hampshire Ave",
    "sg:city":"Takoma Park",
    "sg:classifiers":[
        {
            "category":"Shopping",
            "subcategory":"Used Merchandise",
            "type":"Retail Goods"
        }
    ],
    "sg:phone":"+1 301 270 6106",
    "sg:postcode":"20912",
    "sg:province":"MD",
    "sg:tags":[
        "shop",
        "consignment"
    ],
    "wof:name":"Hanna's Consignment Shop Inc",
    "wof:placetype":"venue"
},
  "geometry": {"coordinates":[-76.995589,38.974054],"type":"Point"}
}