{
  "type": "Feature",
  "properties": {
    "iso:country":"US",
    "sg:address":"2523 E Biddle St",
    "sg:city":"Baltimore",
    "sg:classifiers":[
        {
            "category":"Place Of Worship",
            "subcategory":"Church",
            "type":"Public Place"
        },
        {
            "category":"Place Of Worship",
            "type":"Public Place"
        }
    ],
    "sg:phone":"+1 410 522 7655",
    "sg:postcode":"21213",
    "sg:province":"MD",
    "sg:tags":[
        "churches-baptist-general",
        "churches-baptist"
    ],
    "wof:name":"Prayer House Baptist Church",
    "wof:placetype":"venue"
},
  "geometry": {"coordinates":[-76.58206,39.304795],"type":"Point"}
}