{
  "type": "Feature",
  "properties": {
    "iso:country":"US",
    "sg:address":"142 Longfellow Dr",
    "sg:city":"Chestertown",
    "sg:classifiers":[
        {
            "category":"Building & Trades",
            "subcategory":"Construction",
            "type":"Services"
        }
    ],
    "sg:phone":"+1 410 778 4564",
    "sg:postcode":"21620",
    "sg:province":"MD",
    "sg:tags":[
        "home",
        "improvement"
    ],
    "wof:name":"Jones & Savage Home Imprvmnts",
    "wof:placetype":"venue"
},
  "geometry": {"coordinates":[-76.03569,39.209149],"type":"Point"}
}