{
  "type": "Feature",
  "properties": {
    "addr:full":"437 Century Vista Dr Arnold MD 21012",
    "addr:housenumber":"437",
    "addr:postcode":"21012",
    "addr:street":"Century Vista Dr",
    "iso:country":"US",
    "sg:address":"437 Century Vista Dr",
    "sg:city":"Arnold",
    "sg:classifiers":[
        {
            "category":"Retail",
            "subcategory":"Repair Shop",
            "type":"Services"
        }
    ],
    "sg:phone":"+1 410 544 0642",
    "sg:postcode":"21012",
    "sg:province":"MD",
    "wof:name":"Linas Cleaning",
    "wof:placetype":"venue"
},
  "geometry": {"coordinates":[-76.500652,39.063694],"type":"Point"}
}