{
  "type": "Feature",
  "properties": {
    "iso:country":"US",
    "sg:address":"8818 Waltham Woods Rd",
    "sg:city":"Baltimore",
    "sg:classifiers":[
        {
            "category":"Shopping",
            "subcategory":"Optical Goods",
            "type":"Retail Goods"
        }
    ],
    "sg:phone":"+1 410 882 2020",
    "sg:postcode":"21234",
    "sg:province":"MD",
    "wof:name":"Lens 'n Eye",
    "wof:placetype":"venue"
},
  "geometry": {"coordinates":[-76.541442,39.400147],"type":"Point"}
}