{
  "type": "Feature",
  "properties": {
    "iso:country":"US",
    "sg:address":"10610 Lakespring Way",
    "sg:city":"Cockysvl Hnt Vly",
    "sg:classifiers":[
        {
            "category":"Wholesale",
            "subcategory":"Vending Machines",
            "type":"Manufacturing & Wholesale Goods"
        }
    ],
    "sg:phone":"+1 410 667 1018",
    "sg:postcode":"21030",
    "sg:province":"MD",
    "wof:name":"Variety Vending Co",
    "wof:placetype":"venue"
},
  "geometry": {"coordinates":[-76.60821799999999,39.477344],"type":"Point"}
}