{
  "type": "Feature",
  "properties": {
    "addr:full":"5466 Phelps Luck Dr Columbia MD 21045",
    "addr:housenumber":"5466",
    "addr:postcode":"21045",
    "addr:street":"Phelps Luck Dr",
    "iso:country":"US",
    "sg:address":"5466 Phelps Luck Dr",
    "sg:city":"Columbia",
    "sg:classifiers":[
        {
            "category":"Professional",
            "subcategory":"Management & Consulting",
            "type":"Services"
        }
    ],
    "sg:phone":"+1 443 812 0886",
    "sg:postcode":"21045",
    "sg:province":"MD",
    "sg:tags":[
        "business"
    ],
    "wof:name":"Enterprising Systems Inc",
    "wof:placetype":"venue"
},
  "geometry": {"coordinates":[-76.82210499999999,39.223259],"type":"Point"}
}