{
  "type": "Feature",
  "properties": {
    "addr:full":"15223 Hanover Pike Upperco MD 21155",
    "addr:housenumber":"15223",
    "addr:postcode":"21155",
    "addr:street":"Hanover Pike",
    "iso:country":"US",
    "sg:address":"15223 Hanover Pike",
    "sg:city":"Upperco",
    "sg:classifiers":[
        {
            "category":"Retail",
            "subcategory":"Auto Repair",
            "type":"Services"
        }
    ],
    "sg:phone":"+1 410 833 5801",
    "sg:postcode":"21155",
    "sg:province":"MD",
    "sg:tags":[
        "body",
        "automobile",
        "painting"
    ],
    "wof:name":"Owings Collision Specialists",
    "wof:placetype":"venue"
},
  "geometry": {"coordinates":[-76.83774200000001,39.543077],"type":"Point"}
}