{
  "type": "Feature",
  "properties": {
    "iso:country":"US",
    "sg:address":"4400 Stamp Rd Ste 101",
    "sg:city":"Temple Hills",
    "sg:classifiers":[
        {
            "category":"Food & Beverages",
            "subcategory":"Groceries & Convenience Stores",
            "type":"Retail Goods"
        }
    ],
    "sg:phone":"+1 301 899 0079",
    "sg:postcode":"20748",
    "sg:province":"MD",
    "wof:name":"Ghion Market",
    "wof:placetype":"venue"
},
  "geometry": {"coordinates":[-76.94376200000001,38.827704],"type":"Point"}
}