{
  "type": "Feature",
  "properties": {
    "iso:country":"US",
    "sg:address":"705 Mace Ave",
    "sg:city":"Essex",
    "sg:classifiers":[
        {
            "category":"Personal",
            "subcategory":"Beauty Salon",
            "type":"Services"
        }
    ],
    "sg:phone":"+1 410 687 1505",
    "sg:postcode":"21221",
    "sg:province":"MD",
    "wof:name":"Sha Vic's Hair Studio",
    "wof:placetype":"venue"
},
  "geometry": {"coordinates":[-76.475274,39.316589],"type":"Point"}
}