{
  "type": "Feature",
  "properties": {
    "addr:full":"7909 Cessna Ave Gaithersburg MD 20879",
    "addr:housenumber":"7909",
    "addr:postcode":"20879",
    "addr:street":"Cessna Ave",
    "iso:country":"US",
    "sg:address":"7909 Cessna Ave",
    "sg:city":"Gaithersburg",
    "sg:classifiers":[
        {
            "category":"Wholesale",
            "subcategory":"Machinery & Supplies",
            "type":"Manufacturing & Wholesale Goods"
        }
    ],
    "sg:phone":"+1 301 926 7850",
    "sg:postcode":"20879",
    "sg:province":"MD",
    "sg:tags":[
        "equipment",
        "irrigation",
        "system"
    ],
    "wof:name":"John Deere Landscapes",
    "wof:placetype":"venue"
},
  "geometry": {"coordinates":[-77.16053599999999,39.17151],"type":"Point"}
}