{
  "type": "Feature",
  "properties": {
    "addr:full":"12503 Laurel Grove Pl Germantown MD 20874",
    "addr:housenumber":"12503",
    "addr:postcode":"20874",
    "addr:street":"Laurel Grove Pl",
    "iso:country":"US",
    "sg:address":"12503 Laurel Grove Pl",
    "sg:city":"Germantown",
    "sg:classifiers":[
        {
            "category":"Taxi",
            "type":"Transportation"
        }
    ],
    "sg:phone":"+1 301 825 3400",
    "sg:postcode":"20874",
    "sg:province":"MD",
    "sg:tags":[
        "delivery"
    ],
    "wof:name":"Jnick Delivery Services",
    "wof:placetype":"venue"
},
  "geometry": {"coordinates":[-77.259935,39.168613],"type":"Point"}
}