{
  "type": "Feature",
  "properties": {
    "addr:full":"17120 Butler Rd Poolesville MD 20837",
    "addr:housenumber":"17120",
    "addr:postcode":"20837",
    "addr:street":"Butler Rd",
    "iso:country":"US",
    "sg:address":"17120 Butler Rd",
    "sg:city":"Poolesville",
    "sg:classifiers":[
        {
            "category":"Wholesale",
            "subcategory":"Non-durable Goods",
            "type":"Manufacturing & Wholesale Goods"
        }
    ],
    "sg:phone":"+1 301 972 7544",
    "sg:postcode":"20837",
    "sg:province":"MD",
    "sg:tags":[
        "advertising"
    ],
    "sg:website":"www.dstchest.com",
    "wof:name":"D & S Treasure Chest",
    "wof:placetype":"venue"
},
  "geometry": {"coordinates":[-77.41605800000001,39.13695],"type":"Point"}
}