{
  "type": "Feature",
  "properties": {
    "iso:country":"US",
    "sg:address":"Dr Pier Side",
    "sg:city":"Baltimore",
    "sg:classifiers":[
        {
            "category":"Landmark",
            "subcategory":"Tourist Information",
            "type":"Public Place"
        }
    ],
    "sg:phone":"+1 410 347 3283",
    "sg:postcode":"21201",
    "sg:province":"MD",
    "sg:tags":[
        "tour"
    ],
    "wof:name":"After 5 23",
    "wof:placetype":"venue"
},
  "geometry": {"coordinates":[-76.622597,39.2957],"type":"Point"}
}