{
  "type": "Feature",
  "properties": {
    "iso:country":"US",
    "sg:address":"49043 Trapp Rd",
    "sg:city":"Saint Inigoes",
    "sg:phone":"+1 301 872 5343",
    "sg:postcode":"20684",
    "sg:province":"MD",
    "sg:tags":[
        "farm",
        "field",
        "crop"
    ],
    "wof:name":"Yellow Bank Farm",
    "wof:placetype":"venue"
},
  "geometry": {"coordinates":[-76.37805299999999,38.152229],"type":"Point"}
}