{
  "type": "Feature",
  "properties": {
    "iso:country":"US",
    "sg:address":"6002 Radecke Ave",
    "sg:city":"Baltimore",
    "sg:classifiers":[
        {
            "category":"Home & Garden",
            "subcategory":"Building Materials",
            "type":"Retail Goods"
        }
    ],
    "sg:phone":"+1 443 295 5110",
    "sg:postcode":"21206",
    "sg:province":"MD",
    "wof:name":"Baltimore Locksmiths",
    "wof:placetype":"venue"
},
  "geometry": {"coordinates":[-76.52925999999999,39.331253],"type":"Point"}
}