{
  "type": "Feature",
  "properties": {
    "iso:country":"US",
    "sg:address":"3319 Garrison Blvd",
    "sg:city":"Baltimore",
    "sg:classifiers":[
        {
            "category":"Shopping",
            "subcategory":"Clothing, Apparel, & Fashions",
            "type":"Retail Goods"
        },
        {
            "category":"Retail",
            "subcategory":"Laundry & Dry Cleaning",
            "type":"Services"
        }
    ],
    "sg:phone":"+1 410 542 1709",
    "sg:postcode":"21216",
    "sg:province":"MD",
    "sg:tags":[
        "cleaner",
        "tailor",
        "commercial"
    ],
    "wof:name":"Forest Park Cleaners",
    "wof:placetype":"venue"
},
  "geometry": {"coordinates":[-76.68261200000001,39.326455],"type":"Point"}
}