{
  "type": "Feature",
  "properties": {
    "iso:country":"US",
    "sg:address":"38 Timber Rock Rd",
    "sg:city":"Gaithersburg",
    "sg:classifiers":[
        {
            "category":"Professional",
            "subcategory":"Computer Services",
            "type":"Services"
        }
    ],
    "sg:phone":"+1 240 683 6045",
    "sg:postcode":"20878",
    "sg:province":"MD",
    "sg:tags":[
        "consulting",
        "it"
    ],
    "wof:name":"Tichennet LLC",
    "wof:placetype":"venue"
},
  "geometry": {"coordinates":[-77.248834,39.121252],"type":"Point"}
}