{
  "type": "Feature",
  "properties": {
    "iso:country":"US",
    "sg:address":"1810 Bel Air Rd",
    "sg:city":"Fallston",
    "sg:classifiers":[
        {
            "category":"Insurance",
            "subcategory":"Insurance Agent",
            "type":"Services"
        },
        {
            "category":"Insurance",
            "subcategory":"Hazard Insurance",
            "type":"Services"
        },
        {
            "category":"Insurance",
            "subcategory":"Title Insurance",
            "type":"Services"
        },
        {
            "category":"Insurance",
            "subcategory":"Life Insurance",
            "type":"Services"
        }
    ],
    "sg:phone":"+1 410 803 2886",
    "sg:postcode":"21047",
    "sg:province":"MD",
    "sg:tags":[
        "business",
        "auto",
        "commercial",
        "homeowner",
        "motorcycle",
        "renter"
    ],
    "wof:name":"Allstate Insurance Company - William Ewers",
    "wof:placetype":"venue"
},
  "geometry": {"coordinates":[-76.38606799999999,39.50001],"type":"Point"}
}