{
  "type": "Feature",
  "properties": {
    "addr:full":"521 N Division St Fruitland MD 21826",
    "addr:housenumber":"521",
    "addr:postcode":"21826",
    "addr:street":"N Division St",
    "iso:country":"US",
    "sg:address":"521 N Division St",
    "sg:city":"Fruitland",
    "sg:classifiers":[
        {
            "category":"Government",
            "subcategory":"Office",
            "type":"Public Place"
        }
    ],
    "sg:phone":"+1 410 548 2805",
    "sg:postcode":"21826",
    "sg:province":"MD",
    "sg:tags":[
        "village"
    ],
    "wof:name":"Fruitland Water Plant",
    "wof:placetype":"venue"
},
  "geometry": {"coordinates":[-75.607218,38.322383],"type":"Point"}
}