{
  "type": "Feature",
  "properties": {
    "addr:full":"2813 Bel Air Rd Fallston MD 21047",
    "addr:housenumber":"2813",
    "addr:postcode":"21047",
    "addr:street":"Bel Air Rd",
    "iso:country":"US",
    "sg:address":"2813 Bel Air Rd",
    "sg:city":"Fallston",
    "sg:classifiers":[
        {
            "category":"Building & Trades",
            "subcategory":"Plumbing",
            "type":"Services"
        }
    ],
    "sg:phone":"+1 410 877 1616",
    "sg:postcode":"21047",
    "sg:province":"MD",
    "sg:tags":[
        "plumbing",
        "air",
        "conditioning",
        "heating"
    ],
    "wof:name":"Positive Home Svc LLC",
    "wof:placetype":"venue"
},
  "geometry": {"coordinates":[-76.402508,39.483066],"type":"Point"}
}