{
  "type": "Feature",
  "properties": {
    "addr:full":"5 Longlea Ct Kingsville MD 21087",
    "addr:housenumber":"5",
    "addr:postcode":"21087",
    "addr:street":"Longlea Ct",
    "iso:country":"US",
    "sg:address":"5 Longlea Ct",
    "sg:city":"Kingsville",
    "sg:classifiers":[
        {
            "category":"Professional",
            "subcategory":"Employment Agencies",
            "type":"Services"
        }
    ],
    "sg:phone":"+1 410 593 9922",
    "sg:postcode":"21087",
    "sg:province":"MD",
    "sg:tags":[
        "consultant",
        "search",
        "executive"
    ],
    "wof:name":"Diamond Recruiting",
    "wof:placetype":"venue"
},
  "geometry": {"coordinates":[-76.425783,39.453249],"type":"Point"}
}