{
  "type": "Feature",
  "properties": {
    "iso:country":"US",
    "sg:address":"502 S Philadelphia Blvd",
    "sg:city":"Aberdeen",
    "sg:classifiers":[
        {
            "category":"Retail",
            "subcategory":"Car Wash",
            "type":"Services"
        }
    ],
    "sg:phone":"+1 410 272 8170",
    "sg:postcode":"21001",
    "sg:province":"MD",
    "sg:tags":[
        "polishing",
        "washing"
    ],
    "wof:name":"Astro Auto Wash",
    "wof:placetype":"venue"
},
  "geometry": {"coordinates":[-76.168027,39.502343],"type":"Point"}
}