{
  "type": "Feature",
  "properties": {
    "iso:country":"US",
    "sg:address":"7617 Standish Pl",
    "sg:city":"Derwood",
    "sg:classifiers":[
        {
            "category":"Shopping",
            "type":"Retail Goods"
        }
    ],
    "sg:phone":"+1 301 315 2001",
    "sg:postcode":"20855",
    "sg:province":"MD",
    "sg:tags":[
        "pet",
        "shop"
    ],
    "wof:name":"Naviscan Pet Systems Inc",
    "wof:placetype":"venue"
},
  "geometry": {"coordinates":[-77.15484499999999,39.108172],"type":"Point"}
}