{
  "type": "Feature",
  "properties": {
    "addr:full":"3342 Elmora Ave Baltimore MD 21213",
    "addr:housenumber":"3342",
    "addr:postcode":"21213",
    "addr:street":"Elmora Ave",
    "iso:country":"US",
    "sg:address":"3342 Elmora Ave",
    "sg:city":"Baltimore",
    "sg:classifiers":[
        {
            "category":"Food & Beverages",
            "subcategory":"Groceries & Convenience Stores",
            "type":"Retail Goods"
        }
    ],
    "sg:phone":"+1 410 732 1641",
    "sg:postcode":"21213",
    "sg:province":"MD",
    "sg:tags":[
        "deli",
        "restaurant"
    ],
    "wof:name":"Elmora Delicatessen",
    "wof:placetype":"venue"
},
  "geometry": {"coordinates":[-76.576599,39.3158],"type":"Point"}
}