{
  "type": "Feature",
  "properties": {
    "addr:full":"6349 Genoa Rd Tracys Landing MD 20779",
    "addr:housenumber":"6349",
    "addr:postcode":"20779",
    "addr:street":"Genoa Rd",
    "iso:country":"US",
    "sg:address":"6349 Genoa Rd",
    "sg:city":"Tracys Landing",
    "sg:classifiers":[
        {
            "category":"Real Estate",
            "subcategory":"Developer",
            "type":"Services"
        }
    ],
    "sg:phone":"+1 301 855 7215",
    "sg:postcode":"20779",
    "sg:province":"MD",
    "wof:name":"Netpost Services LLC",
    "wof:placetype":"venue"
},
  "geometry": {"coordinates":[-76.558989,38.757408],"type":"Point"}
}