{
  "type": "Feature",
  "properties": {
    "addr:full":"2202 Arden Dr Fallston MD 21047",
    "addr:housenumber":"2202",
    "addr:postcode":"21047",
    "addr:street":"Arden Dr",
    "iso:country":"US",
    "sg:address":"2202 Arden Dr",
    "sg:city":"Fallston",
    "sg:classifiers":[
        {
            "category":"Restaurant",
            "type":"Food & Drink"
        }
    ],
    "sg:phone":"+1 410 879 2452",
    "sg:postcode":"21047",
    "sg:province":"MD",
    "wof:name":"Olympic Flame",
    "wof:placetype":"venue"
},
  "geometry": {"coordinates":[-76.438427,39.53495],"type":"Point"}
}