{
  "type": "Feature",
  "properties": {
    "iso:country":"US",
    "sg:address":"629 Sligo Ave",
    "sg:city":"Silver Spring",
    "sg:classifiers":[
        {
            "category":"Shopping",
            "subcategory":"Florist",
            "type":"Retail Goods"
        }
    ],
    "sg:phone":"+1 301 588 8484",
    "sg:postcode":"20910",
    "sg:province":"MD",
    "wof:name":"Agnes Flower Shop",
    "wof:placetype":"venue"
},
  "geometry": {"coordinates":[-77.01634,38.990888],"type":"Point"}
}