{
  "type": "Feature",
  "properties": {
    "addr:full":"17434 Falls Rd Upperco MD 21155",
    "addr:housenumber":"17434",
    "addr:postcode":"21155",
    "addr:street":"Falls Rd",
    "iso:country":"US",
    "sg:address":"17434 Falls Rd",
    "sg:city":"Upperco",
    "sg:phone":"+1 410 374 2415",
    "sg:postcode":"21155",
    "sg:province":"MD",
    "sg:tags":[
        "farm",
        "corn"
    ],
    "wof:name":"Kenneth Hare",
    "wof:placetype":"venue"
},
  "geometry": {"coordinates":[-76.774733,39.603211],"type":"Point"}
}