{
  "type": "Feature",
  "properties": {
    "iso:country":"US",
    "sg:address":"9900 Medical Center Dr",
    "sg:city":"Rockville",
    "sg:classifiers":[
        {
            "category":"Professional",
            "subcategory":"Research",
            "type":"Services"
        }
    ],
    "sg:phone":"+1 301 417 0900",
    "sg:postcode":"20850",
    "sg:province":"MD",
    "sg:tags":[
        "information",
        "medical"
    ],
    "wof:name":"Otsuka Md Medicinal Labs",
    "wof:placetype":"venue"
},
  "geometry": {"coordinates":[-77.20075199999999,39.097672],"type":"Point"}
}