{
  "type": "Feature",
  "properties": {
    "addr:full":"940 W North Ave Baltimore MD 21217",
    "addr:housenumber":"940",
    "addr:postcode":"21217",
    "addr:street":"W North Ave",
    "iso:country":"US",
    "sg:address":"940 W North Ave",
    "sg:city":"Baltimore",
    "sg:classifiers":[
        {
            "category":"Education",
            "subcategory":"Vocational School",
            "type":"Public Place"
        }
    ],
    "sg:phone":"+1 410 225 3117",
    "sg:postcode":"21217",
    "sg:province":"MD",
    "sg:tags":[
        "training",
        "computer"
    ],
    "wof:name":"Icetech Inc",
    "wof:placetype":"venue"
},
  "geometry": {"coordinates":[-76.63337199999999,39.310594],"type":"Point"}
}