{
  "type": "Feature",
  "properties": {
    "iso:country":"US",
    "sg:address":"1101-B S Hanover St",
    "sg:city":"Baltimore",
    "sg:classifiers":[
        {
            "category":"Real Estate",
            "subcategory":"Real Estate Services",
            "type":"Services"
        }
    ],
    "sg:phone":"+1 410 332 0662",
    "sg:postcode":"21230",
    "sg:province":"MD",
    "sg:tags":[
        "management",
        "property"
    ],
    "sg:website":"www.elitepropertiesofmd.com",
    "wof:name":"Elite Properties of Maryland",
    "wof:placetype":"venue"
},
  "geometry": {"coordinates":[-76.61541,39.276651],"type":"Point"}
}