{
  "type": "Feature",
  "properties": {
    "iso:country":"US",
    "sg:address":"615 W Montgomery Ave",
    "sg:city":"Rockville",
    "sg:classifiers":[
        {
            "category":"Health Services",
            "subcategory":"Doctor",
            "type":"Services"
        }
    ],
    "sg:phone":"+1 301 762 6148",
    "sg:postcode":"20850",
    "sg:province":"MD",
    "sg:tags":[
        "physician",
        "surgeon"
    ],
    "wof:name":"Internal Medicine",
    "wof:placetype":"venue"
},
  "geometry": {"coordinates":[-77.167501,39.085643],"type":"Point"}
}