{
  "type": "Feature",
  "properties": {
    "iso:country":"US",
    "sg:address":"4615 N Park Ave",
    "sg:city":"Chevy Chase",
    "sg:classifiers":[
        {
            "category":"Professional",
            "subcategory":"Lawyer & Legal Services",
            "type":"Services"
        }
    ],
    "sg:phone":"+1 301 718 6549",
    "sg:postcode":"20815",
    "sg:province":"MD",
    "wof:name":"Young James P Atty",
    "wof:placetype":"venue"
},
  "geometry": {"coordinates":[-77.09098,38.963627],"type":"Point"}
}