{
  "type": "Feature",
  "properties": {
    "iso:country":"US",
    "sg:address":"2126 Edmondson Ave",
    "sg:city":"Baltimore",
    "sg:classifiers":[
        {
            "category":"Home & Garden",
            "subcategory":"Household Appliances",
            "type":"Retail Goods"
        }
    ],
    "sg:phone":"+1 410 362 4250",
    "sg:postcode":"21223",
    "sg:province":"MD",
    "wof:name":"Gibb Transfer",
    "wof:placetype":"venue"
},
  "geometry": {"coordinates":[-76.650803,39.295061],"type":"Point"}
}