{
  "type": "Feature",
  "properties": {
    "addr:full":"7425 Old Alexandria Ferry Rd Clinton MD 20735",
    "addr:housenumber":"7425",
    "addr:postcode":"20735",
    "addr:street":"Old Alexandria Ferry Rd",
    "iso:country":"US",
    "sg:address":"7425 Old Alexandria Ferry Rd",
    "sg:city":"Clinton",
    "sg:classifiers":[
        {
            "category":"Retail",
            "subcategory":"Auto Repair",
            "type":"Services"
        }
    ],
    "sg:phone":"+1 301 877 1004",
    "sg:postcode":"20735",
    "sg:province":"MD",
    "sg:tags":[
        "repairing",
        "automobile"
    ],
    "wof:name":"Teleport MD",
    "wof:placetype":"venue"
},
  "geometry": {"coordinates":[-76.87997,38.782717],"type":"Point"}
}