{
  "type": "Feature",
  "properties": {
    "iso:country":"US",
    "sg:address":"1805 George Ave",
    "sg:city":"Annapolis",
    "sg:classifiers":[
        {
            "category":"Autos & Motor Vehicles",
            "subcategory":"Boat Sales",
            "type":"Retail Goods"
        }
    ],
    "sg:phone":"+1 410 267 0137",
    "sg:postcode":"21401",
    "sg:province":"MD",
    "sg:tags":[
        "canoe"
    ],
    "sg:website":"www.clcinc.com",
    "wof:name":"Chesapeake Light Craft LLC",
    "wof:placetype":"venue"
},
  "geometry": {"coordinates":[-76.52243799999999,38.975816],"type":"Point"}
}