{
  "type": "Feature",
  "properties": {
    "iso:country":"US",
    "sg:address":"9142 Edgeworth Dr",
    "sg:city":"Capitol Heights",
    "sg:classifiers":[
        {
            "category":"Retail",
            "subcategory":"Auto Repair",
            "type":"Services"
        }
    ],
    "sg:phone":"+1 301 350 4040",
    "sg:postcode":"20743",
    "sg:province":"MD",
    "wof:name":"Free-State Auto & Truck Svcs Inc",
    "wof:placetype":"venue"
},
  "geometry": {"coordinates":[-76.8489,38.881302],"type":"Point"}
}