{
  "type": "Feature",
  "properties": {
    "addr:full":"7916 Honeygo Blvd Nottingham MD 21236",
    "addr:housenumber":"7916",
    "addr:postcode":"21236",
    "addr:street":"Honeygo Blvd",
    "iso:country":"US",
    "sg:address":"7916 Honeygo Blvd",
    "sg:city":"Nottingham",
    "sg:classifiers":[
        {
            "category":"Restaurant",
            "type":"Food & Drink"
        }
    ],
    "sg:phone":"+1 410 931 3586",
    "sg:postcode":"21236",
    "sg:province":"MD",
    "sg:tags":[
        "chinese"
    ],
    "sg:website":"www.chinawok.com",
    "wof:name":"China Wok",
    "wof:placetype":"venue"
},
  "geometry": {"coordinates":[-76.472504,39.373001],"type":"Point"}
}