{
  "type": "Feature",
  "properties": {
    "iso:country":"US",
    "sg:address":"8359 Tamar Dr Apt 425",
    "sg:city":"Columbia",
    "sg:classifiers":[
        {
            "category":"Professional",
            "subcategory":"Computer Services",
            "type":"Services"
        }
    ],
    "sg:phone":"+1 301 773 1143",
    "sg:postcode":"21045",
    "sg:province":"MD",
    "sg:tags":[
        "graphic"
    ],
    "wof:name":"Shannon Thomas-Fong",
    "wof:placetype":"venue"
},
  "geometry": {"coordinates":[-76.803754,39.205295],"type":"Point"}
}