{
  "type": "Feature",
  "properties": {
    "iso:country":"US",
    "sg:address":"4102 Webster St",
    "sg:city":"Brentwood",
    "sg:classifiers":[
        {
            "category":"Professional",
            "subcategory":"Management & Consulting",
            "type":"Services"
        }
    ],
    "sg:phone":"+1 301 864 3860",
    "sg:postcode":"20722",
    "sg:province":"MD",
    "sg:tags":[
        "town",
        "city",
        "regional",
        "planner"
    ],
    "wof:name":"Gateway Municipalities Cmmnty",
    "wof:placetype":"venue"
},
  "geometry": {"coordinates":[-76.950717,38.942919],"type":"Point"}
}