{
  "type": "Feature",
  "properties": {
    "addr:full":"2307 Haddon Pl Bowie MD 20716",
    "addr:housenumber":"2307",
    "addr:postcode":"20716",
    "addr:street":"Haddon Pl",
    "iso:country":"US",
    "sg:address":"2307 Haddon Pl",
    "sg:city":"Bowie",
    "sg:classifiers":[
        {
            "category":"Professional",
            "subcategory":"Business Services",
            "type":"Services"
        }
    ],
    "sg:phone":"+1 301 262 0956",
    "sg:postcode":"20716",
    "sg:province":"MD",
    "sg:tags":[
        "editing",
        "history"
    ],
    "wof:name":"Jack Shulimson",
    "wof:placetype":"venue"
},
  "geometry": {"coordinates":[-76.73038099999999,38.95252],"type":"Point"}
}