{
  "type": "Feature",
  "properties": {
    "iso:country":"US",
    "sg:address":"443 W Side Dr",
    "sg:city":"Gaithersburg",
    "sg:classifiers":[
        {
            "category":"Professional",
            "subcategory":"Computer Services",
            "type":"Services"
        }
    ],
    "sg:phone":"+1 301 977 3498",
    "sg:postcode":"20878",
    "sg:province":"MD",
    "sg:tags":[
        "datum"
    ],
    "wof:name":"Ionel Popa",
    "wof:placetype":"venue"
},
  "geometry": {"coordinates":[-77.20425899999999,39.125685],"type":"Point"}
}