{
  "type": "Feature",
  "properties": {
    "addr:full":"9 Equestrian Ct Derwood MD 20855",
    "addr:housenumber":"9",
    "addr:postcode":"20855",
    "addr:street":"Equestrian Ct",
    "iso:country":"US",
    "sg:address":"9 Equestrian Ct",
    "sg:city":"Derwood",
    "sg:classifiers":[
        {
            "category":"Professional",
            "subcategory":"Computer Services",
            "type":"Services"
        }
    ],
    "sg:phone":"+1 301 258 9470",
    "sg:postcode":"20855",
    "sg:province":"MD",
    "sg:tags":[
        "consultant",
        "designer"
    ],
    "sg:website":"www.augustschell.com",
    "wof:name":"August Schell Enterprises Inc",
    "wof:placetype":"venue"
},
  "geometry": {"coordinates":[-77.136341,39.125858],"type":"Point"}
}