{
  "type": "Feature",
  "properties": {
    "addr:full":"2229 Mcelderry St Baltimore MD 21205",
    "addr:housenumber":"2229",
    "addr:postcode":"21205",
    "addr:street":"Mcelderry St",
    "iso:country":"US",
    "sg:address":"2229 Mcelderry St",
    "sg:city":"Baltimore",
    "sg:classifiers":[
        {
            "category":"Building & Trades",
            "subcategory":"Plumbing",
            "type":"Services"
        },
        {
            "category":"Building & Trades",
            "subcategory":"Construction",
            "type":"Services"
        },
        {
            "category":"Building & Trades",
            "subcategory":"Electrical",
            "type":"Services"
        }
    ],
    "sg:phone":"+1 443 615 4039",
    "sg:postcode":"21205",
    "sg:province":"MD",
    "sg:tags":[
        "plumber",
        "electrician",
        "carpenter",
        "system",
        "specialty",
        "heating",
        "contractor",
        "air conditioning"
    ],
    "wof:name":"Keeling Construction",
    "wof:placetype":"venue"
},
  "geometry": {"coordinates":[-76.585823,39.297588],"type":"Point"}
}