{
  "type": "Feature",
  "properties": {
    "iso:country":"US",
    "sg:address":"6525 Beechwood Dr",
    "sg:city":"Temple Hills",
    "sg:classifiers":[
        {
            "category":"Food & Beverages",
            "subcategory":"Specialty",
            "type":"Retail Goods"
        }
    ],
    "sg:phone":"+1 301 449 0388",
    "sg:postcode":"20748",
    "sg:province":"MD",
    "wof:name":"Seed Of Life",
    "wof:placetype":"venue"
},
  "geometry": {"coordinates":[-76.90527899999999,38.799104],"type":"Point"}
}