{
  "type": "Feature",
  "properties": {
    "addr:full":"7930 Queenair Dr Gaithersburg MD 20879",
    "addr:housenumber":"7930",
    "addr:postcode":"20879",
    "addr:street":"Queenair Dr",
    "iso:country":"US",
    "sg:address":"7930 Queenair Dr",
    "sg:city":"Gaithersburg",
    "sg:classifiers":[
        {
            "category":"Building & Trades",
            "subcategory":"Construction",
            "type":"Services"
        }
    ],
    "sg:phone":"+1 301 570 0111",
    "sg:postcode":"20879",
    "sg:province":"MD",
    "sg:tags":[
        "fire",
        "restoration",
        "damage"
    ],
    "wof:name":"A-Plus Cleaning & Restoration",
    "wof:placetype":"venue"
},
  "geometry": {"coordinates":[-77.161816,39.169823],"type":"Point"}
}