{
  "type": "Feature",
  "properties": {
    "iso:country":"US",
    "sg:address":"1122 Kenilworth Dr",
    "sg:city":"Towson",
    "sg:classifiers":[
        {
            "category":"Health Services",
            "subcategory":"Doctor",
            "type":"Services"
        }
    ],
    "sg:phone":"+1 410 821 7066",
    "sg:postcode":"21204",
    "sg:province":"MD",
    "sg:tags":[
        "physician",
        "surgeon"
    ],
    "wof:name":"Alcoholic Beverage Medical",
    "wof:placetype":"venue"
},
  "geometry": {"coordinates":[-76.630234,39.41357],"type":"Point"}
}