{
  "type": "Feature",
  "properties": {
    "iso:country":"US",
    "sg:address":"12224 Central Ave",
    "sg:city":"Mitchellville",
    "sg:classifiers":[
        {
            "category":"Autos & Motor Vehicles",
            "subcategory":"Fuel & Gas Station",
            "type":"Retail Goods"
        }
    ],
    "sg:phone":"+1 301 249 7587",
    "sg:postcode":"20785",
    "sg:province":"MD",
    "sg:tags":[
        "oil"
    ],
    "wof:name":"Enterprise Mobil",
    "wof:placetype":"venue"
},
  "geometry": {"coordinates":[-76.795975,38.899437],"type":"Point"}
}