{
  "type": "Feature",
  "properties": {
    "iso:country":"US",
    "sg:address":"5816 Baltimore Natinl Pke",
    "sg:city":"Catonsville",
    "sg:classifiers":[
        {
            "category":"Shopping",
            "subcategory":"Department Store",
            "type":"Retail Goods"
        },
        {
            "category":"Shopping",
            "subcategory":"Clothing, Apparel, & Fashions",
            "type":"Retail Goods"
        }
    ],
    "sg:phone":"+1 410 719 6959",
    "sg:postcode":"21228",
    "sg:province":"MD",
    "sg:tags":[
        "accessory",
        "clothing",
        "women's"
    ],
    "wof:name":"Rainbow",
    "wof:placetype":"venue"
},
  "geometry": {"coordinates":[-76.741699,39.285702],"type":"Point"}
}