{
  "type": "Feature",
  "properties": {
    "addr:full":"282 N Main St Port Deposit MD 21904",
    "addr:housenumber":"282",
    "addr:postcode":"21904",
    "addr:street":"N Main St",
    "iso:country":"US",
    "sg:address":"282 N Main St",
    "sg:city":"Port Deposit",
    "sg:classifiers":[
        {
            "category":"Organizations",
            "subcategory":"Religious Organization",
            "type":"Services"
        }
    ],
    "sg:phone":"+1 410 378 4886",
    "sg:postcode":"21904",
    "sg:province":"MD",
    "wof:name":"First Bptst Chrch Port Deposit",
    "wof:placetype":"venue"
},
  "geometry": {"coordinates":[-76.124934,39.61274],"type":"Point"}
}