{
  "type": "Feature",
  "properties": {
    "iso:country":"US",
    "sg:address":"8767 Satyr Hill Rd",
    "sg:city":"Parkville",
    "sg:classifiers":[
        {
            "category":"Wholesale",
            "subcategory":"Electrical",
            "type":"Manufacturing & Wholesale Goods"
        }
    ],
    "sg:phone":"+1 410 663 4580",
    "sg:postcode":"21234",
    "sg:province":"MD",
    "sg:tags":[
        "equipment",
        "electric",
        "supply"
    ],
    "wof:name":"Eaton Corp",
    "wof:placetype":"venue"
},
  "geometry": {"coordinates":[-76.54456999999999,39.399111],"type":"Point"}
}