{
  "type": "Feature",
  "properties": {
    "iso:country":"US",
    "sg:address":"4705 Wyaconda Rd",
    "sg:city":"Rockville",
    "sg:classifiers":[
        {
            "category":"Social Services",
            "subcategory":"Child Care",
            "type":"Services"
        }
    ],
    "sg:phone":"+1 301 984 2155",
    "sg:postcode":"20852",
    "sg:province":"MD",
    "sg:tags":[
        "day"
    ],
    "wof:name":"Happy Faces Family Day Care",
    "wof:placetype":"venue"
},
  "geometry": {"coordinates":[-77.09229999999999,39.045101],"type":"Point"}
}