{
  "type": "Feature",
  "properties": {
    "addr:full":"404 Winters Ln Catonsville MD 21228",
    "addr:housenumber":"404",
    "addr:postcode":"21228",
    "addr:street":"Winters Ln",
    "iso:country":"US",
    "sg:address":"404 Winters Ln",
    "sg:city":"Catonsville",
    "sg:classifiers":[
        {
            "category":"Personal",
            "subcategory":"Barber",
            "type":"Services"
        }
    ],
    "sg:phone":"+1 410 747 7470",
    "sg:postcode":"21228",
    "sg:province":"MD",
    "wof:name":"Unisex Hair Center",
    "wof:placetype":"venue"
},
  "geometry": {"coordinates":[-76.74340100000001,39.284401],"type":"Point"}
}