{
  "type": "Feature",
  "properties": {
    "iso:country":"US",
    "sg:address":"585 Ritchie Rd",
    "sg:city":"Capitol Heights",
    "sg:classifiers":[
        {
            "category":"Retail",
            "subcategory":"Auto Repair",
            "type":"Services"
        }
    ],
    "sg:phone":"+1 301 333 4722",
    "sg:postcode":"20743",
    "sg:province":"MD",
    "wof:name":"Ray's Auto Repair",
    "wof:placetype":"venue"
},
  "geometry": {"coordinates":[-76.85900100000001,38.8811],"type":"Point"}
}