{
  "type": "Feature",
  "properties": {
    "addr:full":"1 Science Park Frostburg MD 21532",
    "addr:postcode":"21532",
    "iso:country":"US",
    "sg:address":"1 Science Park",
    "sg:city":"Frostburg",
    "sg:classifiers":[
        {
            "category":"Communications",
            "type":"Services"
        }
    ],
    "sg:phone":"+1 301 689 5194",
    "sg:postcode":"21532",
    "sg:province":"MD",
    "sg:website":"http://www.hamilton.net",
    "wof:name":"Hamilton Relay Service",
    "wof:placetype":"venue"
},
  "geometry": {"coordinates":[-78.909058,39.643551],"type":"Point"}
}