{
  "type": "Feature",
  "properties": {
    "addr:full":"2403 McCormick Rd Rockville MD 20850",
    "addr:housenumber":"2403",
    "addr:postcode":"20850",
    "addr:street":"Mccormick Rd",
    "iso:country":"US",
    "sg:address":"2403 McCormick Rd",
    "sg:city":"Rockville",
    "sg:classifiers":[
        {
            "category":"Professional",
            "subcategory":"Management & Consulting",
            "type":"Services"
        }
    ],
    "sg:phone":"+1 301 424 5443",
    "sg:postcode":"20850",
    "sg:province":"MD",
    "sg:tags":[
        "consultant"
    ],
    "wof:name":"Zigler",
    "wof:placetype":"venue"
},
  "geometry": {"coordinates":[-77.186829,39.085598],"type":"Point"}
}