{
  "type": "Feature",
  "properties": {
    "addr:full":"6410 Rockledge Dr Ste 400 Bethesda MD 20817",
    "addr:housenumber":"6410",
    "addr:postcode":"20817",
    "addr:street":"Rockledge Dr Ste 400",
    "iso:country":"US",
    "sg:address":"6410 Rockledge Dr Ste 400",
    "sg:city":"Bethesda",
    "sg:classifiers":[
        {
            "category":"Health Services",
            "subcategory":"Optometrist",
            "type":"Services"
        }
    ],
    "sg:phone":"+1 301 530 5200",
    "sg:postcode":"20817",
    "sg:province":"MD",
    "sg:tags":[
        "ophthalmologist"
    ],
    "sg:website":"www.retinaconsultants.net",
    "wof:name":"Palestine Alan G MD",
    "wof:placetype":"venue"
},
  "geometry": {"coordinates":[-77.13249999999999,39.023399],"type":"Point"}
}