{
  "type": "Feature",
  "properties": {
    "iso:country":"US",
    "sg:address":"5928 Falls Rd",
    "sg:city":"Baltimore",
    "sg:classifiers":[
        {
            "category":"Place Of Worship",
            "subcategory":"Church",
            "type":"Public Place"
        },
        {
            "category":"Place Of Worship",
            "type":"Public Place"
        }
    ],
    "sg:phone":"+1 410 435 6121",
    "sg:postcode":"21209",
    "sg:province":"MD",
    "sg:tags":[
        "churches-non-denominational"
    ],
    "wof:name":"Divine Life Church",
    "wof:placetype":"venue"
},
  "geometry": {"coordinates":[-76.64917800000001,39.370178],"type":"Point"}
}