{
  "type": "Feature",
  "properties": {
    "addr:full":"8151 Mission Rd Jessup MD 20794",
    "addr:housenumber":"8151",
    "addr:postcode":"20794",
    "addr:street":"Mission Rd",
    "iso:country":"US",
    "sg:address":"8151 Mission Rd",
    "sg:city":"Jessup",
    "sg:classifiers":[
        {
            "category":"Freight",
            "type":"Transportation"
        }
    ],
    "sg:phone":"+1 410 799 2122",
    "sg:postcode":"20794",
    "sg:province":"MD",
    "sg:tags":[
        "trucking"
    ],
    "sg:website":"www.conway.com",
    "wof:name":"Con-Way Central Express",
    "wof:placetype":"venue"
},
  "geometry": {"coordinates":[-76.79589300000001,39.162617],"type":"Point"}
}