{
  "type": "Feature",
  "properties": {
    "addr:full":"1735 Carpenters Dr Marriottsville MD 21104",
    "addr:housenumber":"1735",
    "addr:postcode":"21104",
    "addr:street":"Carpenters Dr",
    "iso:country":"US",
    "sg:address":"1735 Carpenters Dr",
    "sg:city":"Marriottsville",
    "sg:classifiers":[
        {
            "category":"Professional",
            "subcategory":"Computer Services",
            "type":"Services"
        }
    ],
    "sg:phone":"+1 410 549 5242",
    "sg:postcode":"21104",
    "sg:province":"MD",
    "sg:tags":[
        "repair"
    ],
    "wof:name":"Computer & Network Consultants",
    "wof:placetype":"venue"
},
  "geometry": {"coordinates":[-76.93602799999999,39.371344],"type":"Point"}
}