{
  "type": "Feature",
  "properties": {
    "iso:country":"US",
    "sg:address":"516 Washington Ave",
    "sg:city":"Chestertown",
    "sg:classifiers":[
        {
            "category":"Health Services",
            "subcategory":"Hospital",
            "type":"Services"
        },
        {
            "category":"Social Services",
            "type":"Services"
        }
    ],
    "sg:phone":"+1 410 778 5147",
    "sg:postcode":"21620",
    "sg:province":"MD",
    "sg:tags":[
        "center",
        "mental",
        "crisis"
    ],
    "wof:name":"For All Seasons Inc",
    "wof:placetype":"venue"
},
  "geometry": {"coordinates":[-76.068913,39.221814],"type":"Point"}
}