{
  "type": "Feature",
  "properties": {
    "addr:full":"2411 Berry Thicket Ct Waldorf MD 20603",
    "addr:housenumber":"2411",
    "addr:postcode":"20603",
    "addr:street":"Berry Thicket Ct",
    "iso:country":"US",
    "sg:address":"2411 Berry Thicket Ct",
    "sg:city":"Waldorf",
    "sg:classifiers":[
        {
            "category":"Professional",
            "subcategory":"Detective & Security Services",
            "type":"Services"
        }
    ],
    "sg:phone":"+1 301 893 2788",
    "sg:postcode":"20603",
    "sg:province":"MD",
    "sg:tags":[
        "contract",
        "investigator"
    ],
    "wof:name":"Reeves Investigations",
    "wof:placetype":"venue"
},
  "geometry": {"coordinates":[-76.99018599999999,38.642385],"type":"Point"}
}