{
  "type": "Feature",
  "properties": {
    "iso:country":"US",
    "sg:address":"11801 Reisterstown Rd",
    "sg:city":"Reisterstown",
    "sg:classifiers":[
        {
            "category":"Shopping",
            "type":"Retail Goods"
        }
    ],
    "sg:phone":"+1 410 833 7788",
    "sg:postcode":"21136",
    "sg:province":"MD",
    "sg:tags":[
        "wedding",
        "supply"
    ],
    "sg:website":"www.flowersbypennylane.com",
    "wof:name":"Penny Lane Florist",
    "wof:placetype":"venue"
},
  "geometry": {"coordinates":[-76.812287,39.445564],"type":"Point"}
}