{
  "type": "Feature",
  "properties": {
    "iso:country":"US",
    "sg:address":"1012 Dartford Ln",
    "sg:city":"Bowie",
    "sg:classifiers":[
        {
            "category":"Shopping",
            "subcategory":"Clothing, Apparel, & Fashions",
            "type":"Retail Goods"
        }
    ],
    "sg:phone":"+1 301 218 1832",
    "sg:postcode":"20721",
    "sg:province":"MD",
    "wof:name":"Mzuri Fashion & Gifts",
    "wof:placetype":"venue"
},
  "geometry": {"coordinates":[-76.752402,38.905311],"type":"Point"}
}