{
  "type": "Feature",
  "properties": {
    "addr:full":"1659 W North Ave Baltimore MD 21217",
    "addr:housenumber":"1659",
    "addr:postcode":"21217",
    "addr:street":"W North Ave",
    "iso:country":"US",
    "sg:address":"1659 W North Ave",
    "sg:city":"Baltimore",
    "sg:classifiers":[
        {
            "category":"Building & Trades",
            "subcategory":"Construction",
            "type":"Services"
        }
    ],
    "sg:phone":"+1 410 383 9900",
    "sg:postcode":"21217",
    "sg:province":"MD",
    "sg:tags":[
        "maintenance",
        "contractor"
    ],
    "wof:name":"L & B Maintenance",
    "wof:placetype":"venue"
},
  "geometry": {"coordinates":[-76.644271,39.309921],"type":"Point"}
}