{
  "type": "Feature",
  "properties": {
    "addr:full":"8200 Perry Hall Blvd Baltimore MD 21236",
    "addr:housenumber":"8200",
    "addr:postcode":"21236",
    "addr:street":"Perry Hall Blvd",
    "iso:country":"US",
    "sg:address":"8200 Perry Hall Blvd",
    "sg:city":"Baltimore",
    "sg:classifiers":[
        {
            "category":"Utilities",
            "subcategory":"Mobile Phone",
            "type":"Services"
        }
    ],
    "sg:phone":"+1 410 931 6980",
    "sg:postcode":"21236",
    "sg:province":"MD",
    "sg:tags":[
        "telephone",
        "cellular"
    ],
    "wof:name":"T-Mobile",
    "wof:placetype":"venue"
},
  "geometry": {"coordinates":[-76.47514,39.371244],"type":"Point"}
}