{
  "type": "Feature",
  "properties": {
    "iso:country":"US",
    "sg:address":"286 Wroxeter Dr",
    "sg:city":"Arnold",
    "sg:classifiers":[
        {
            "category":"Real Estate",
            "subcategory":"Real Estate Services",
            "type":"Services"
        },
        {
            "category":"Real Estate",
            "subcategory":"Real Estate Agent",
            "type":"Services"
        }
    ],
    "sg:phone":"+1 410 315 9395",
    "sg:postcode":"21012",
    "sg:province":"MD",
    "sg:tags":[
        "buyer",
        "broker"
    ],
    "wof:name":"Ashton Real Estate",
    "wof:placetype":"venue"
},
  "geometry": {"coordinates":[-76.53442800000001,39.040802],"type":"Point"}
}