{
  "type": "Feature",
  "properties": {
    "addr:full":"1 Nicodemus Rd Reisterstown MD 21136",
    "addr:housenumber":"1",
    "addr:postcode":"21136",
    "addr:street":"Nicodemus Rd",
    "iso:country":"US",
    "sg:address":"1 Nicodemus Rd",
    "sg:city":"Reisterstown",
    "sg:classifiers":[
        {
            "category":"Banks & Credit Unions",
            "subcategory":"Bank",
            "type":"Services"
        }
    ],
    "sg:phone":"+1 410 833 3939",
    "sg:postcode":"21136",
    "sg:province":"MD",
    "sg:tags":[
        "loan",
        "real estate"
    ],
    "wof:name":"Mortgage & Loan Place",
    "wof:placetype":"venue"
},
  "geometry": {"coordinates":[-76.808145,39.440107],"type":"Point"}
}