{
  "type": "Feature",
  "properties": {
    "addr:full":"210 6th Ave Brooklyn MD 21225",
    "addr:housenumber":"210",
    "addr:postcode":"21225",
    "addr:street":"6Th Ave",
    "iso:country":"US",
    "sg:address":"210 6th Ave",
    "sg:city":"Brooklyn",
    "sg:classifiers":[
        {
            "category":"Shopping",
            "subcategory":"Antiques",
            "type":"Retail Goods"
        }
    ],
    "sg:phone":"+1 410 789 8836",
    "sg:postcode":"21225",
    "sg:province":"MD",
    "wof:name":"A Absolute Limousine",
    "wof:placetype":"venue"
},
  "geometry": {"coordinates":[-76.61750000000001,39.228802],"type":"Point"}
}