{
  "type": "Feature",
  "properties": {
    "iso:country":"US",
    "sg:address":"3117 Edgewood Rd",
    "sg:city":"Ellicott City",
    "sg:classifiers":[
        {
            "category":"Health Services",
            "subcategory":"Doctor",
            "type":"Services"
        }
    ],
    "sg:phone":"+1 410 465 2999",
    "sg:postcode":"21043",
    "sg:province":"MD",
    "wof:name":"Baykaler Ali I MD",
    "wof:placetype":"venue"
},
  "geometry": {"coordinates":[-76.796097,39.287998],"type":"Point"}
}