{
  "type": "Feature",
  "properties": {
    "addr:full":"4625 Falls Rd Baltimore MD 21209",
    "addr:housenumber":"4625",
    "addr:postcode":"21209",
    "addr:street":"Falls Rd",
    "iso:country":"US",
    "sg:address":"4625 Falls Rd",
    "sg:city":"Baltimore",
    "sg:classifiers":[
        {
            "category":"Shopping",
            "subcategory":"Pharmacy",
            "type":"Retail Goods"
        }
    ],
    "sg:phone":"+1 410 662 1670",
    "sg:postcode":"21209",
    "sg:province":"MD",
    "sg:tags":[
        "drugstore"
    ],
    "sg:website":"www.cvs.com",
    "wof:name":"Cvs/Pharmacy",
    "wof:placetype":"venue"
},
  "geometry": {"coordinates":[-76.64099899999999,39.345501],"type":"Point"}
}