{
  "type": "Feature",
  "properties": {
    "iso:country":"US",
    "sg:address":"4501 Shaff Ln",
    "sg:city":"Frederick",
    "sg:classifiers":[
        {
            "category":"Professional",
            "subcategory":"Business Services",
            "type":"Services"
        }
    ],
    "sg:phone":"+1 301 371 7885",
    "sg:postcode":"21703",
    "sg:province":"MD",
    "wof:name":"Skyline Capital Group LLC",
    "wof:placetype":"venue"
},
  "geometry": {"coordinates":[-77.50912,39.38808],"type":"Point"}
}