{
  "type": "Feature",
  "properties": {
    "addr:full":"3495 Laurel Fort Meade Rd Laurel MD 20724",
    "addr:housenumber":"3495",
    "addr:postcode":"20724",
    "addr:street":"Laurel Fort Meade Rd",
    "iso:country":"US",
    "sg:address":"3495 Laurel Fort Meade Rd",
    "sg:city":"Laurel",
    "sg:classifiers":[
        {
            "category":"Food & Beverages",
            "subcategory":"Specialty",
            "type":"Retail Goods"
        },
        {
            "category":"Food & Beverages",
            "subcategory":"Fruits & Vegetables",
            "type":"Retail Goods"
        },
        {
            "category":"Shopping",
            "subcategory":"Pharmacy",
            "type":"Retail Goods"
        }
    ],
    "sg:phone":"+1 301 776 7061",
    "sg:postcode":"20724",
    "sg:province":"MD",
    "sg:tags":[
        "product",
        "wellness",
        "vitamin",
        "diet",
        "supplement",
        "health",
        "herb"
    ],
    "sg:website":"http://www.gnc.com",
    "wof:name":"GNC",
    "wof:placetype":"venue"
},
  "geometry": {"coordinates":[-76.816231,39.10014],"type":"Point"}
}