{
  "type": "Feature",
  "properties": {
    "addr:full":"18939 Bonanza Way Gaithersburg MD 20879",
    "addr:housenumber":"18939",
    "addr:postcode":"20879",
    "addr:street":"Bonanza Way",
    "iso:country":"US",
    "sg:address":"18939 Bonanza Way",
    "sg:city":"Gaithersburg",
    "sg:classifiers":[
        {
            "category":"Building & Trades",
            "subcategory":"Construction",
            "type":"Services"
        }
    ],
    "sg:phone":"+1 301 948 0800",
    "sg:postcode":"20879",
    "sg:province":"MD",
    "sg:tags":[
        "installs",
        "home",
        "retail",
        "furnishing"
    ],
    "wof:name":"Towne & Country Tiles",
    "wof:placetype":"venue"
},
  "geometry": {"coordinates":[-77.170635,39.166592],"type":"Point"}
}