{
  "type": "Feature",
  "properties": {
    "iso:country":"US",
    "sg:address":"11518 Cosca Park Pl",
    "sg:city":"Clinton",
    "sg:classifiers":[
        {
            "category":"Social Services",
            "subcategory":"Child Care",
            "type":"Services"
        }
    ],
    "sg:phone":"+1 301 856 5140",
    "sg:postcode":"20735",
    "sg:province":"MD",
    "sg:tags":[
        "day"
    ],
    "wof:name":"Maries Day Care",
    "wof:placetype":"venue"
},
  "geometry": {"coordinates":[-76.91048000000001,38.732269],"type":"Point"}
}