{
  "type": "Feature",
  "properties": {
    "addr:full":"24908 Silver Crest Dr Gaithersburg MD 20882",
    "addr:housenumber":"24908",
    "addr:postcode":"20882",
    "addr:street":"Silver Crest Dr",
    "iso:country":"US",
    "sg:address":"24908 Silver Crest Dr",
    "sg:city":"Gaithersburg",
    "sg:classifiers":[
        {
            "category":"Banks & Credit Unions",
            "subcategory":"Investment Brokerage",
            "type":"Services"
        },
        {
            "category":"Professional",
            "subcategory":"Business Services",
            "type":"Services"
        }
    ],
    "sg:phone":"+1 301 253 0600",
    "sg:postcode":"20882",
    "sg:province":"MD",
    "sg:tags":[
        "advisory",
        "planning",
        "financial",
        "consultant"
    ],
    "wof:name":"Cornerstone Financial Planning",
    "wof:placetype":"venue"
},
  "geometry": {"coordinates":[-77.17062799999999,39.267479],"type":"Point"}
}