{
  "type": "Feature",
  "properties": {
    "iso:country":"US",
    "sg:address":"1111 Park Ave",
    "sg:city":"Baltimore",
    "sg:classifiers":[
        {
            "category":"Building & Trades",
            "subcategory":"Locksmith",
            "type":"Services"
        }
    ],
    "sg:phone":"+1 443 378 3703",
    "sg:postcode":"21201",
    "sg:province":"MD",
    "sg:tags":[
        "key"
    ],
    "wof:name":"24 Emergency Locksmith",
    "wof:placetype":"venue"
},
  "geometry": {"coordinates":[-76.62173300000001,39.305547],"type":"Point"}
}