{
  "type": "Feature",
  "properties": {
    "addr:full":"806 Old English Ct Bel Air MD 21014",
    "addr:housenumber":"806",
    "addr:postcode":"21014",
    "addr:street":"Old English Ct",
    "iso:country":"US",
    "sg:address":"806 Old English Ct",
    "sg:city":"Bel Air",
    "sg:classifiers":[
        {
            "category":"Retail",
            "subcategory":"Laundry & Dry Cleaning",
            "type":"Services"
        }
    ],
    "sg:phone":"+1 410 838 2958",
    "sg:postcode":"21014",
    "sg:province":"MD",
    "sg:tags":[
        "cleaners",
        "rug",
        "carpet"
    ],
    "wof:name":"Carl's Carpet Care",
    "wof:placetype":"venue"
},
  "geometry": {"coordinates":[-76.352889,39.548784],"type":"Point"}
}