{
  "type": "Feature",
  "properties": {
    "addr:full":"808 Reservoir St Baltimore MD 21217",
    "addr:housenumber":"808",
    "addr:postcode":"21217",
    "addr:street":"Reservoir St",
    "iso:country":"US",
    "sg:address":"808 Reservoir St",
    "sg:city":"Baltimore",
    "sg:classifiers":[
        {
            "category":"Manufacturing",
            "subcategory":"Printing",
            "type":"Manufacturing & Wholesale Goods"
        }
    ],
    "sg:phone":"+1 410 523 7742",
    "sg:postcode":"21217",
    "sg:province":"MD",
    "sg:tags":[
        "printer"
    ],
    "wof:name":"Dubbs Printers",
    "wof:placetype":"venue"
},
  "geometry": {"coordinates":[-76.632639,39.312744],"type":"Point"}
}