{
  "type": "Feature",
  "properties": {
    "addr:full":"230 Park Ave Baltimore MD 21201",
    "addr:housenumber":"230",
    "addr:postcode":"21201",
    "addr:street":"Park Ave",
    "iso:country":"US",
    "sg:address":"230 Park Ave",
    "sg:city":"Baltimore",
    "sg:classifiers":[
        {
            "category":"Banks & Credit Unions",
            "subcategory":"Bank",
            "type":"Services"
        }
    ],
    "sg:phone":"+1 410 752 7451",
    "sg:postcode":"21201",
    "sg:province":"MD",
    "sg:tags":[
        "broker",
        "foreign",
        "dealer",
        "exchange"
    ],
    "wof:name":"Ace Currency Exchange",
    "wof:placetype":"venue"
},
  "geometry": {"coordinates":[-76.618224,39.292823],"type":"Point"}
}