{
  "type": "Feature",
  "properties": {
    "addr:full":"240 Fairground Rd Prince Frederick MD 20678",
    "addr:housenumber":"240",
    "addr:postcode":"20678",
    "addr:street":"Fairground Rd",
    "iso:country":"US",
    "sg:address":"240 Fairground Rd",
    "sg:city":"Prince Frederick",
    "sg:classifiers":[
        {
            "category":"Real Estate",
            "subcategory":"Real Estate Agent",
            "type":"Services"
        }
    ],
    "sg:phone":"+1 410 535 7670",
    "sg:postcode":"20678",
    "sg:province":"MD",
    "wof:name":"Premier MGT & Consulting",
    "wof:placetype":"venue"
},
  "geometry": {"coordinates":[-76.583877,38.54654],"type":"Point"}
}