{
  "type": "Feature",
  "properties": {
    "iso:country":"US",
    "sg:address":"1800 N Market St",
    "sg:city":"Frederick",
    "sg:classifiers":[
        {
            "category":"Utilities",
            "subcategory":"Natural Gas",
            "type":"Services"
        }
    ],
    "sg:phone":"+1 301 662 2151",
    "sg:postcode":"21701",
    "sg:province":"MD",
    "wof:name":"Frederick Gas A Div Wash Gas",
    "wof:placetype":"venue"
},
  "geometry": {"coordinates":[-77.397346,39.441219],"type":"Point"}
}