{
  "type": "Feature",
  "properties": {
    "addr:full":"12801 Stone Hill Rd Phoenix MD 21131",
    "addr:housenumber":"12801",
    "addr:postcode":"21131",
    "addr:street":"Stone Hill Rd",
    "iso:country":"US",
    "sg:address":"12801 Stone Hill Rd",
    "sg:city":"Phoenix",
    "sg:classifiers":[
        {
            "category":"Social Services",
            "type":"Services"
        },
        {
            "category":"Professional",
            "subcategory":"Employment Agencies",
            "type":"Services"
        },
        {
            "category":"Organizations",
            "subcategory":"Membership Organization",
            "type":"Services"
        }
    ],
    "sg:phone":"+1 410 252 8484",
    "sg:postcode":"21131",
    "sg:province":"MD",
    "sg:tags":[
        "placement",
        "workers'",
        "private",
        "club",
        "volunteer"
    ],
    "wof:name":"Towson Golf & Country Club",
    "wof:placetype":"venue"
},
  "geometry": {"coordinates":[-76.560417,39.466942],"type":"Point"}
}