{
  "type": "Feature",
  "properties": {
    "iso:country":"US",
    "sg:address":"16 Scott Adam Rd",
    "sg:city":"Cockeysville",
    "sg:classifiers":[
        {
            "category":"Personal",
            "subcategory":"Beauty Salon",
            "type":"Services"
        }
    ],
    "sg:phone":"+1 410 666 0717",
    "sg:postcode":"21030",
    "sg:province":"MD",
    "sg:tags":[
        "nail",
        "manicuring"
    ],
    "wof:name":"Timonium Nail Care Inc",
    "wof:placetype":"venue"
},
  "geometry": {"coordinates":[-76.639099,39.4716],"type":"Point"}
}