{
  "type": "Feature",
  "properties": {
    "addr:full":"6908 40th Ave University Park MD 20782",
    "addr:housenumber":"6908",
    "addr:postcode":"20782",
    "addr:street":"40Th Ave",
    "iso:country":"US",
    "sg:address":"6908 40th Ave",
    "sg:city":"University Park",
    "sg:classifiers":[
        {
            "category":"Real Estate",
            "subcategory":"Real Estate Agent",
            "type":"Services"
        }
    ],
    "sg:phone":"+1 301 864 8050",
    "sg:postcode":"20782",
    "sg:province":"MD",
    "wof:name":"Happy Homebuyers LLC",
    "wof:placetype":"venue"
},
  "geometry": {"coordinates":[-76.95092099999999,38.975658],"type":"Point"}
}