{
  "type": "Feature",
  "properties": {
    "iso:country":"US",
    "sg:address":"6500 Capitol Dr",
    "sg:city":"Greenbelt",
    "sg:classifiers":[
        {
            "category":"Autos & Motor Vehicles",
            "subcategory":"Automobile Sales",
            "type":"Retail Goods"
        },
        {
            "category":"Autos & Motor Vehicles",
            "subcategory":"Auto Supplies",
            "type":"Retail Goods"
        },
        {
            "category":"Retail",
            "subcategory":"Auto Repair",
            "type":"Services"
        }
    ],
    "sg:phone":"+1 240 297 1579",
    "sg:postcode":"20770",
    "sg:province":"MD",
    "sg:tags":[
        "used",
        "tire",
        "car",
        "accessory",
        "part",
        "new"
    ],
    "sg:website":"http://washingtondc.citysearch.com/profile/external/4872780/greenbelt_md/capitol_cadillac.html?publisher=yellowpages&reference_id=15&placement=ypwebsitemip",
    "wof:name":"Capitol Cadillac",
    "wof:placetype":"venue"
},
  "geometry": {"coordinates":[-76.89299099999999,38.996483],"type":"Point"}
}