{
  "type": "Feature",
  "properties": {
    "iso:country":"US",
    "sg:address":"9101 Franklin Square Dr",
    "sg:city":"Baltimore",
    "sg:classifiers":[
        {
            "category":"Health Services",
            "subcategory":"Doctor",
            "type":"Services"
        }
    ],
    "sg:phone":"+1 410 574 3100",
    "sg:postcode":"21237",
    "sg:province":"MD",
    "sg:tags":[
        "physician",
        "surgeon"
    ],
    "wof:name":"Drs Poutton & Acr",
    "wof:placetype":"venue"
},
  "geometry": {"coordinates":[-76.478078,39.350634],"type":"Point"}
}