{
  "type": "Feature",
  "properties": {
    "iso:country":"US",
    "sg:address":"11910 Whistler Ct",
    "sg:city":"Potomac",
    "sg:classifiers":[
        {
            "category":"Professional",
            "subcategory":"Computer Services",
            "type":"Services"
        }
    ],
    "sg:phone":"+1 301 424 7068",
    "sg:postcode":"20854",
    "sg:province":"MD",
    "sg:tags":[
        "programing",
        "custom"
    ],
    "wof:name":"Cedars Software",
    "wof:placetype":"venue"
},
  "geometry": {"coordinates":[-77.158648,39.051526],"type":"Point"}
}