{
  "type": "Feature",
  "properties": {
    "iso:country":"US",
    "sg:address":"11836 Kittys Corner Rd",
    "sg:city":"Cordova",
    "sg:classifiers":[
        {
            "category":"Government",
            "subcategory":"Post Office",
            "type":"Public Place"
        }
    ],
    "sg:phone":"+1 410 820 2964",
    "sg:postcode":"21625",
    "sg:province":"MD",
    "wof:name":"US Post Office",
    "wof:placetype":"venue"
},
  "geometry": {"coordinates":[-75.994315,38.872206],"type":"Point"}
}