{
  "type": "Feature",
  "properties": {
    "addr:full":"3397 York St Manchester MD 21102",
    "addr:housenumber":"3397",
    "addr:postcode":"21102",
    "addr:street":"York St",
    "iso:country":"US",
    "sg:address":"3397 York St",
    "sg:city":"Manchester",
    "sg:classifiers":[
        {
            "category":"Retail",
            "subcategory":"Auto Repair",
            "type":"Services"
        }
    ],
    "sg:phone":"+1 410 374 6926",
    "sg:postcode":"21102",
    "sg:province":"MD",
    "sg:tags":[
        "repairing",
        "automobile"
    ],
    "wof:name":"Lewy's Garage",
    "wof:placetype":"venue"
},
  "geometry": {"coordinates":[-76.878139,39.667518],"type":"Point"}
}