{
  "type": "Feature",
  "properties": {
    "iso:country":"US",
    "sg:address":"13524 Glen Mill Rd",
    "sg:city":"Rockville",
    "sg:classifiers":[
        {
            "category":"Government",
            "subcategory":"Office",
            "type":"Public Place"
        }
    ],
    "sg:phone":"+1 240 393 2442",
    "sg:postcode":"20850",
    "sg:province":"MD",
    "sg:tags":[
        "advises",
        "on",
        "regulation",
        "biologic",
        "drug"
    ],
    "wof:name":"Sharon T Risso",
    "wof:placetype":"venue"
},
  "geometry": {"coordinates":[-77.204869,39.077214],"type":"Point"}
}