{
  "type": "Feature",
  "properties": {
    "iso:country":"US",
    "sg:address":"6435 Dobbin Rd",
    "sg:city":"Columbia",
    "sg:classifiers":[
        {
            "category":"Autos & Motor Vehicles",
            "subcategory":"Auto Supplies",
            "type":"Retail Goods"
        }
    ],
    "sg:phone":"+1 410 730 6903",
    "sg:postcode":"21045",
    "sg:province":"MD",
    "sg:tags":[
        "automobile",
        "part",
        "batteries-storage"
    ],
    "sg:website":"http://www.advanceautoparts.com",
    "wof:name":"Advance Auto Parts",
    "wof:placetype":"venue"
},
  "geometry": {"coordinates":[-76.820965,39.195252],"type":"Point"}
}