{
  "type": "Feature",
  "properties": {
    "iso:country":"US",
    "sg:address":"1720 N Salisbury Blvd",
    "sg:city":"Salisbury",
    "sg:classifiers":[
        {
            "category":"Personal",
            "subcategory":"Beauty Salon",
            "type":"Services"
        }
    ],
    "sg:phone":"+1 443 944 8870",
    "sg:postcode":"21801",
    "sg:province":"MD",
    "sg:tags":[
        "hair",
        "stylist"
    ],
    "wof:name":"Daisy's Healthy Hair Salon",
    "wof:placetype":"venue"
},
  "geometry": {"coordinates":[-75.582291,38.384941],"type":"Point"}
}