{
  "type": "Feature",
  "properties": {
    "addr:full":"6523 78th St Cabin John MD 20818",
    "addr:housenumber":"6523",
    "addr:postcode":"md 20818",
    "addr:street":"78Th St",
    "iso:country":"US",
    "sg:address":"6523 78th St",
    "sg:city":"Cabin John",
    "sg:classifiers":[
        {
            "category":"Professional",
            "subcategory":"Lawyer & Legal Services",
            "type":"Services"
        }
    ],
    "sg:phone":"+1 301 229 5054",
    "sg:postcode":"20818",
    "sg:province":"MD",
    "sg:tags":[
        "attorney"
    ],
    "wof:name":"Ag-Riverside Cpc",
    "wof:placetype":"venue"
},
  "geometry": {"coordinates":[-77.159775,38.975931],"type":"Point"}
}