{
  "type": "Feature",
  "properties": {
    "addr:full":"521 E Joppa Rd Baltimore MD 21286",
    "addr:housenumber":"521",
    "addr:postcode":"21286",
    "addr:street":"E Joppa Rd",
    "iso:country":"US",
    "sg:address":"521 E Joppa Rd",
    "sg:city":"Baltimore",
    "sg:classifiers":[
        {
            "category":"Social Services",
            "type":"Services"
        }
    ],
    "sg:phone":"+1 410 583 2318",
    "sg:postcode":"21286",
    "sg:province":"MD",
    "sg:tags":[
        "organization",
        "welfare"
    ],
    "wof:name":"Mary W Horky",
    "wof:placetype":"venue"
},
  "geometry": {"coordinates":[-76.595088,39.401626],"type":"Point"}
}