{
  "type": "Feature",
  "properties": {
    "addr:full":"6478 Barchink Pl Columbia MD 21045",
    "addr:housenumber":"6478",
    "addr:postcode":"21045",
    "addr:street":"Barchink Pl",
    "iso:country":"US",
    "sg:address":"6478 Barchink Pl",
    "sg:city":"Columbia",
    "sg:classifiers":[
        {
            "category":"Professional",
            "type":"Services"
        },
        {
            "category":"Professional",
            "subcategory":"Business Services",
            "type":"Services"
        }
    ],
    "sg:phone":"+1 410 312 7885",
    "sg:postcode":"21045",
    "sg:province":"MD",
    "sg:tags":[
        "establishment"
    ],
    "wof:name":"Accessable Data Solutions LLC",
    "wof:placetype":"venue"
},
  "geometry": {"coordinates":[-76.832577,39.19368],"type":"Point"}
}