{
  "type": "Feature",
  "properties": {
    "addr:full":"11800 Baltimore Ave Beltsville MD 20705",
    "addr:housenumber":"11800",
    "addr:postcode":"20705",
    "addr:street":"Baltimore Ave",
    "iso:country":"US",
    "sg:address":"11800 Baltimore Ave",
    "sg:city":"Beltsville",
    "sg:classifiers":[
        {
            "category":"Professional",
            "subcategory":"Management & Consulting",
            "type":"Services"
        }
    ],
    "sg:phone":"+1 301 206 2214",
    "sg:postcode":"20705",
    "sg:province":"MD",
    "sg:tags":[
        "consultant",
        "business"
    ],
    "sg:website":"www.bioreg.com",
    "wof:name":"Bio-Reg Assoc",
    "wof:placetype":"venue"
},
  "geometry": {"coordinates":[-76.89814200000001,39.050035],"type":"Point"}
}