{
  "type": "Feature",
  "properties": {
    "addr:full":"6315 Freedom Ave Sykesville MD 21784",
    "addr:housenumber":"6315",
    "addr:postcode":"21784",
    "addr:street":"Freedom Ave",
    "iso:country":"US",
    "sg:address":"6315 Freedom Ave",
    "sg:city":"Sykesville",
    "sg:classifiers":[
        {
            "category":"Social Services",
            "subcategory":"Child Care",
            "type":"Services"
        }
    ],
    "sg:phone":"+1 410 795 0731",
    "sg:postcode":"21784",
    "sg:province":"MD",
    "wof:name":"ABC Care Inc",
    "wof:placetype":"venue"
},
  "geometry": {"coordinates":[-76.96537499999999,39.406012],"type":"Point"}
}