{
  "type": "Feature",
  "properties": {
    "iso:country":"US",
    "sg:address":"5113 King Henry Way",
    "sg:city":"Upper Marlboro",
    "sg:classifiers":[
        {
            "category":"Professional",
            "subcategory":"Secretarial Services",
            "type":"Services"
        }
    ],
    "sg:phone":"+1 301 780 5550",
    "sg:postcode":"20772",
    "sg:province":"MD",
    "sg:tags":[
        "convention",
        "court",
        "reporter"
    ],
    "wof:name":"Phoenix Reporters",
    "wof:placetype":"venue"
},
  "geometry": {"coordinates":[-76.764843,38.82403],"type":"Point"}
}