{
  "type": "Feature",
  "properties": {
    "iso:country":"US",
    "sg:address":"1527 Mitchell Ln",
    "sg:city":"Aberdeen",
    "sg:classifiers":[
        {
            "category":"Organizations",
            "subcategory":"Religious Organization",
            "type":"Services"
        }
    ],
    "sg:phone":"+1 410 272 4848",
    "sg:postcode":"21001",
    "sg:province":"MD",
    "wof:name":"Kingdom Hall of Jehovah",
    "wof:placetype":"venue"
},
  "geometry": {"coordinates":[-76.216172,39.480216],"type":"Point"}
}