{
  "type": "Feature",
  "properties": {
    "iso:country":"US",
    "sg:address":"1238 Greenmount Ave",
    "sg:city":"Baltimore",
    "sg:classifiers":[
        {
            "category":"Food & Beverages",
            "subcategory":"Liquor & Beverages",
            "type":"Retail Goods"
        }
    ],
    "sg:phone":"+1 410 752 7261",
    "sg:postcode":"21202",
    "sg:province":"MD",
    "sg:tags":[
        "beer",
        "spirit",
        "wine"
    ],
    "wof:name":"Avenue Bar",
    "wof:placetype":"venue"
},
  "geometry": {"coordinates":[-76.608002,39.304501],"type":"Point"}
}