{
  "type": "Feature",
  "properties": {
    "iso:country":"US",
    "sg:address":"712 Park Ave",
    "sg:city":"Baltimore",
    "sg:classifiers":[
        {
            "category":"Professional",
            "subcategory":"Lawyer & Legal Services",
            "type":"Services"
        }
    ],
    "sg:phone":"+1 410 669 9300",
    "sg:postcode":"21201",
    "sg:province":"MD",
    "sg:tags":[
        "attorney"
    ],
    "sg:website":"www.stflawyers.com",
    "wof:name":"Seigel Tully & Furrer",
    "wof:placetype":"venue"
},
  "geometry": {"coordinates":[-76.618301,39.298302],"type":"Point"}
}