{
  "type": "Feature",
  "properties": {
    "addr:full":"5603 N Charles St Baltimore MD 21210",
    "addr:housenumber":"5603",
    "addr:postcode":"21210",
    "addr:street":"N Charles St",
    "iso:country":"US",
    "sg:address":"5603 N Charles St",
    "sg:city":"Baltimore",
    "sg:classifiers":[
        {
            "category":"Education",
            "subcategory":"Preschool",
            "type":"Public Place"
        },
        {
            "category":"Education",
            "subcategory":"School",
            "type":"Public Place"
        }
    ],
    "sg:phone":"+1 410 435 9510",
    "sg:postcode":"21210",
    "sg:province":"MD",
    "sg:tags":[
        "elementary"
    ],
    "wof:name":"Church of the Redeemer Parish Day School",
    "wof:placetype":"venue"
},
  "geometry": {"coordinates":[-76.625298,39.365101],"type":"Point"}
}