{
  "type": "Feature",
  "properties": {
    "iso:country":"US",
    "sg:address":"1301 Avondale Rd",
    "sg:city":"New Windsor",
    "sg:classifiers":[
        {
            "category":"Manufacturing",
            "subcategory":"Building Materials",
            "type":"Manufacturing & Wholesale Goods"
        }
    ],
    "sg:phone":"+1 410 876 9966",
    "sg:postcode":"21776",
    "sg:province":"MD",
    "sg:tags":[
        "cabinet"
    ],
    "sg:website":"www.vartta.com",
    "wof:name":"Vartta Industries",
    "wof:placetype":"venue"
},
  "geometry": {"coordinates":[-77.045672,39.551524],"type":"Point"}
}