{
  "type": "Feature",
  "properties": {
    "addr:full":"8226 Tall Trees Court Ellicott City MD 21043",
    "addr:housenumber":"8226",
    "addr:postcode":"21043",
    "addr:street":"Tall Trees Court",
    "iso:country":"US",
    "sg:address":"8226 Tall Trees Court",
    "sg:city":"Ellicott City",
    "sg:classifiers":[
        {
            "category":"Building & Trades",
            "subcategory":"Cleaning & Sanitation",
            "type":"Services"
        }
    ],
    "sg:phone":"+1 443 277 7265",
    "sg:postcode":"21043",
    "sg:province":"MD",
    "sg:tags":[
        "carpet"
    ],
    "sg:website":"superiorsteamcleaners.com/",
    "wof:name":"Superior Steam Cleaners",
    "wof:placetype":"venue"
},
  "geometry": {"coordinates":[-76.79323599999999,39.202244],"type":"Point"}
}