{
  "type": "Feature",
  "properties": {
    "iso:country":"US",
    "sg:address":"12106 Nebel St",
    "sg:city":"Rockville",
    "sg:classifiers":[
        {
            "category":"Health Services",
            "subcategory":"Doctor",
            "type":"Services"
        }
    ],
    "sg:phone":"+1 301 984 5791",
    "sg:postcode":"20852",
    "sg:province":"MD",
    "wof:name":"Cvca",
    "wof:placetype":"venue"
},
  "geometry": {"coordinates":[-77.110248,39.051727],"type":"Point"}
}