{
  "type": "Feature",
  "properties": {
    "addr:full":"7501 Pulaski Hwy Rosedale MD 21237",
    "addr:housenumber":"7501",
    "addr:postcode":"21237",
    "addr:street":"Pulaski Hwy",
    "iso:country":"US",
    "sg:address":"7501 Pulaski Hwy",
    "sg:city":"Rosedale",
    "sg:classifiers":[
        {
            "category":"Health Services",
            "subcategory":"Health Practitioner",
            "type":"Services"
        }
    ],
    "sg:phone":"+1 410 866 3855",
    "sg:postcode":"21237",
    "sg:province":"MD",
    "sg:tags":[
        "therapist",
        "therapy",
        "physical"
    ],
    "wof:name":"Rehab At Work Inc",
    "wof:placetype":"venue"
},
  "geometry": {"coordinates":[-76.524597,39.313],"type":"Point"}
}