{
  "type": "Feature",
  "properties": {
    "iso:country":"US",
    "sg:address":"120 S Frederick Ave",
    "sg:city":"Gaithersburg",
    "sg:classifiers":[
        {
            "category":"Social Services",
            "type":"Services"
        },
        {
            "category":"Personal",
            "type":"Services"
        }
    ],
    "sg:phone":"+1 301 840 9664",
    "sg:postcode":"20877",
    "sg:province":"MD",
    "sg:tags":[
        "family",
        "counselors-licensed",
        "individual",
        "marriage",
        "child",
        "professional",
        "counselor"
    ],
    "wof:name":"Waldman Robert J Mediation Ser",
    "wof:placetype":"venue"
},
  "geometry": {"coordinates":[-77.19617,39.13954],"type":"Point"}
}