{
  "type": "Feature",
  "properties": {
    "addr:full":"17705 Smokewood Dr Germantown MD 20874",
    "addr:housenumber":"17705",
    "addr:postcode":"20874",
    "addr:street":"Smokewood Dr",
    "iso:country":"US",
    "sg:address":"17705 Smokewood Dr",
    "sg:city":"Germantown",
    "sg:classifiers":[
        {
            "category":"Professional",
            "subcategory":"Business Services",
            "type":"Services"
        }
    ],
    "sg:phone":"+1 301 353 9160",
    "sg:postcode":"20874",
    "sg:province":"MD",
    "sg:tags":[
        "interior",
        "decorating"
    ],
    "wof:name":"Evening Interiors LLC",
    "wof:placetype":"venue"
},
  "geometry": {"coordinates":[-77.278847,39.147421],"type":"Point"}
}