{
  "type": "Feature",
  "properties": {
    "iso:country":"US",
    "sg:address":"6004 Norman Ave",
    "sg:city":"Riverdale",
    "sg:classifiers":[
        {
            "category":"Manufacturing",
            "subcategory":"Motor Vehicles & Parts",
            "type":"Manufacturing & Wholesale Goods"
        }
    ],
    "sg:phone":"+1 301 927 8945",
    "sg:postcode":"20737",
    "sg:province":"MD",
    "sg:tags":[
        "equipment",
        "manufacturer",
        "automobile",
        "supply"
    ],
    "wof:name":"Tech Heng",
    "wof:placetype":"venue"
},
  "geometry": {"coordinates":[-76.91359300000001,38.968346],"type":"Point"}
}