{
  "type": "Feature",
  "properties": {
    "iso:country":"US",
    "sg:address":"8001 Cryden Way",
    "sg:city":"District Heights",
    "sg:classifiers":[
        {
            "category":"Organizations",
            "subcategory":"Professional Association",
            "type":"Services"
        }
    ],
    "sg:phone":"+1 301 967 8800",
    "sg:postcode":"20747",
    "sg:province":"MD",
    "wof:name":"Prince George's County Board",
    "wof:placetype":"venue"
},
  "geometry": {"coordinates":[-76.868409,38.848194],"type":"Point"}
}