{
  "type": "Feature",
  "properties": {
    "iso:country":"US",
    "sg:address":"1120 Benfield Blvd",
    "sg:city":"Millersville",
    "sg:classifiers":[
        {
            "category":"Shopping",
            "subcategory":"Computers & Home Electronics",
            "type":"Retail Goods"
        }
    ],
    "sg:phone":"+1 410 729 8781",
    "sg:postcode":"21108",
    "sg:province":"MD",
    "sg:tags":[
        "software"
    ],
    "wof:name":"Synplicity Inc",
    "wof:placetype":"venue"
},
  "geometry": {"coordinates":[-76.632047,39.094465],"type":"Point"}
}