{
  "type": "Feature",
  "properties": {
    "addr:full":"21513 Great Mills Rd Lexington Park MD 20653",
    "addr:housenumber":"21513",
    "addr:postcode":"20653",
    "addr:street":"Great Mills Rd",
    "iso:country":"US",
    "sg:address":"21513 Great Mills Rd",
    "sg:city":"Lexington Park",
    "sg:classifiers":[
        {
            "category":"Professional",
            "subcategory":"Management & Consulting",
            "type":"Services"
        }
    ],
    "sg:phone":"+1 301 866 6600",
    "sg:postcode":"20653",
    "sg:province":"MD",
    "sg:tags":[
        "datum"
    ],
    "wof:name":"Lockheed Martin",
    "wof:placetype":"venue"
},
  "geometry": {"coordinates":[-76.474812,38.256869],"type":"Point"}
}