{
  "type": "Feature",
  "properties": {
    "addr:full":"2025 Hudson Rd Cambridge MD 21613",
    "addr:housenumber":"2025",
    "addr:postcode":"21613",
    "addr:street":"Hudson Rd",
    "iso:country":"US",
    "sg:address":"2025 Hudson Rd",
    "sg:city":"Cambridge",
    "sg:classifiers":[
        {
            "category":"Freight",
            "type":"Transportation"
        }
    ],
    "sg:phone":"+1 410 228 1092",
    "sg:postcode":"21613",
    "sg:province":"MD",
    "wof:name":"C E Dunnock Trans Inc",
    "wof:placetype":"venue"
},
  "geometry": {"coordinates":[-76.13677800000001,38.572992],"type":"Point"}
}