{
  "type": "Feature",
  "properties": {
    "iso:country":"US",
    "sg:address":"75 Brownfield Loop",
    "sg:city":"Elkton",
    "sg:classifiers":[
        {
            "category":"Building & Trades",
            "subcategory":"Construction",
            "type":"Services"
        }
    ],
    "sg:phone":"+1 410 885 2229",
    "sg:postcode":"21921",
    "sg:province":"MD",
    "sg:tags":[
        "residential",
        "renovation",
        "contractor"
    ],
    "wof:name":"Sp Construction Co",
    "wof:placetype":"venue"
},
  "geometry": {"coordinates":[-75.846419,39.538352],"type":"Point"}
}