{
  "type": "Feature",
  "properties": {
    "addr:full":"8704 Wandering Trail Dr Potomac MD 20854",
    "addr:housenumber":"8704",
    "addr:postcode":"20854",
    "addr:street":"Wandering Trail Dr",
    "iso:country":"US",
    "sg:address":"8704 Wandering Trail Dr",
    "sg:city":"Potomac",
    "sg:classifiers":[
        {
            "category":"Organizations",
            "subcategory":"Religious Organization",
            "type":"Services"
        }
    ],
    "sg:phone":"+1 301 340 6034",
    "sg:postcode":"20854",
    "sg:province":"MD",
    "wof:name":"Rockville Evangelical Mission",
    "wof:placetype":"venue"
},
  "geometry": {"coordinates":[-77.181123,39.066406],"type":"Point"}
}