{
  "type": "Feature",
  "properties": {
    "iso:country":"US",
    "sg:address":"1448 S Rolling Rd",
    "sg:city":"Halethorpe",
    "sg:classifiers":[
        {
            "category":"Science Facility",
            "type":"Public Place"
        }
    ],
    "sg:phone":"+1 410 262 3971",
    "sg:postcode":"21227",
    "sg:province":"MD",
    "sg:tags":[
        "development",
        "laboratories-research"
    ],
    "wof:name":"Cgc",
    "wof:placetype":"venue"
},
  "geometry": {"coordinates":[-76.713442,39.237086],"type":"Point"}
}