{
  "type": "Feature",
  "properties": {
    "iso:country":"US",
    "sg:address":"23201 Gilpin Point Rd",
    "sg:city":"Preston",
    "sg:classifiers":[
        {
            "category":"Bars & Pubs",
            "subcategory":"Lounge",
            "type":"Food & Drink"
        },
        {
            "category":"Restaurant",
            "type":"Food & Drink"
        }
    ],
    "sg:phone":"+1 410 479 9833",
    "sg:postcode":"21655",
    "sg:province":"MD",
    "sg:tags":[
        "style",
        "cocktail",
        "family"
    ],
    "wof:name":"404 Bar Grill",
    "wof:placetype":"venue"
},
  "geometry": {"coordinates":[-75.902615,38.800702],"type":"Point"}
}