{
  "type": "Feature",
  "properties": {
    "addr:full":"800 E Lombard St Baltimore MD 21202",
    "addr:housenumber":"800",
    "addr:postcode":"21202",
    "addr:street":"E Lombard St",
    "iso:country":"US",
    "sg:address":"800 E Lombard St",
    "sg:city":"Baltimore",
    "sg:classifiers":[
        {
            "category":"Museum",
            "type":"Entertainment"
        }
    ],
    "sg:phone":"+1 410 605 2964",
    "sg:postcode":"21202",
    "sg:province":"MD",
    "wof:name":"Carroll Mansion & Shot Tower",
    "wof:placetype":"venue"
},
  "geometry": {"coordinates":[-76.6045,39.2883],"type":"Point"}
}