{
  "type": "Feature",
  "properties": {
    "iso:country":"US",
    "sg:address":"308 Springdale St",
    "sg:city":"Cumberland",
    "sg:classifiers":[
        {
            "category":"Freight",
            "type":"Transportation"
        }
    ],
    "sg:phone":"+1 301 724 1322",
    "sg:postcode":"21502",
    "sg:province":"MD",
    "sg:tags":[
        "local",
        "trucking"
    ],
    "wof:name":"B Burn Trucking Inc",
    "wof:placetype":"venue"
},
  "geometry": {"coordinates":[-78.764337,39.635246],"type":"Point"}
}