{
  "type": "Feature",
  "properties": {
    "iso:country":"US",
    "sg:address":"21 Oskaloosa Ct",
    "sg:city":"Derwood",
    "sg:classifiers":[
        {
            "category":"Utilities",
            "subcategory":"Telephone",
            "type":"Services"
        }
    ],
    "sg:phone":"+1 301 840 9488",
    "sg:postcode":"20855",
    "sg:province":"MD",
    "sg:tags":[
        "development",
        "web",
        "sell",
        "site",
        "used"
    ],
    "wof:name":"Hairston Enterprises LLC",
    "wof:placetype":"venue"
},
  "geometry": {"coordinates":[-77.144708,39.113975],"type":"Point"}
}