{
  "type": "Feature",
  "properties": {
    "addr:full":"12300 Kemmerton Ln Bowie MD 20715",
    "addr:housenumber":"12300",
    "addr:postcode":"20715",
    "addr:street":"Kemmerton Ln",
    "iso:country":"US",
    "sg:address":"12300 Kemmerton Ln",
    "sg:city":"Bowie",
    "sg:classifiers":[
        {
            "category":"Health Services",
            "subcategory":"Doctor",
            "type":"Services"
        }
    ],
    "sg:phone":"+1 301 352 5250",
    "sg:postcode":"20715",
    "sg:province":"MD",
    "sg:tags":[
        "dentist"
    ],
    "wof:name":"James P Chorbajian DDS",
    "wof:placetype":"venue"
},
  "geometry": {"coordinates":[-76.743354,38.957152],"type":"Point"}
}