{
  "type": "Feature",
  "properties": {
    "addr:full":"11248 Triangle Ln Silver Spring MD 20902",
    "addr:housenumber":"11248",
    "addr:postcode":"20902",
    "addr:street":"Triangle Ln",
    "iso:country":"US",
    "sg:address":"11248 Triangle Ln",
    "sg:city":"Silver Spring",
    "sg:classifiers":[
        {
            "category":"Shopping",
            "subcategory":"Music",
            "type":"Retail Goods"
        }
    ],
    "sg:phone":"+1 301 946 7520",
    "sg:postcode":"20902",
    "sg:province":"MD",
    "sg:tags":[
        "record",
        "american",
        "latin",
        "tape"
    ],
    "wof:name":"Discocentro Zodiac",
    "wof:placetype":"venue"
},
  "geometry": {"coordinates":[-77.052008,39.039641],"type":"Point"}
}