{
  "type": "Feature",
  "properties": {
    "iso:country":"US",
    "sg:address":"1583 Sulphur Spring Rd",
    "sg:city":"Halethorpe",
    "sg:classifiers":[
        {
            "category":"Sports & Exercise",
            "subcategory":"Sports Center",
            "type":"Entertainment"
        }
    ],
    "sg:phone":"+1 410 536 5766",
    "sg:postcode":"21227",
    "sg:province":"MD",
    "sg:tags":[
        "amateur",
        "team"
    ],
    "wof:name":"Sgi USA",
    "wof:placetype":"venue"
},
  "geometry": {"coordinates":[-76.68589799999999,39.2486],"type":"Point"}
}