{
  "type": "Feature",
  "properties": {
    "addr:full":"14623 Maugansville Rd Hagerstown MD 21740",
    "addr:postcode":"14623;21740",
    "addr:street":"Maugansville Rd",
    "iso:country":"US",
    "sg:address":"14623 Maugansville Rd",
    "sg:city":"Hagerstown",
    "sg:classifiers":[
        {
            "category":"Home & Garden",
            "subcategory":"Garden Supply",
            "type":"Retail Goods"
        }
    ],
    "sg:phone":"+1 301 733 6011",
    "sg:postcode":"21740",
    "sg:province":"MD",
    "sg:tags":[
        "engine",
        "lawn",
        "gasoline",
        "mower"
    ],
    "wof:name":"Jim's Small Engine Repair",
    "wof:placetype":"venue"
},
  "geometry": {"coordinates":[-77.742057,39.714704],"type":"Point"}
}