{
  "type": "Feature",
  "properties": {
    "addr:full":"429 Fawcett St Baltimore MD 21211",
    "addr:housenumber":"429",
    "addr:postcode":"21211",
    "addr:street":"Fawcett St",
    "iso:country":"US",
    "sg:address":"429 Fawcett St",
    "sg:city":"Baltimore",
    "sg:classifiers":[
        {
            "category":"Retail",
            "subcategory":"Repair Shop",
            "type":"Services"
        }
    ],
    "sg:phone":"+1 410 243 1163",
    "sg:postcode":"21211",
    "sg:province":"MD",
    "sg:tags":[
        "reupholstery",
        "upholsterer",
        "furniture"
    ],
    "wof:name":"Ibello & Co",
    "wof:placetype":"venue"
},
  "geometry": {"coordinates":[-76.623199,39.315201],"type":"Point"}
}