{
  "type": "Feature",
  "properties": {
    "iso:country":"US",
    "sg:address":"176 Main St",
    "sg:city":"Annapolis",
    "sg:classifiers":[
        {
            "category":"Organizations",
            "subcategory":"Professional Association",
            "type":"Services"
        }
    ],
    "sg:phone":"+1 410 990 9502",
    "sg:postcode":"21401",
    "sg:province":"MD",
    "wof:name":"Maryland Delaware District",
    "wof:placetype":"venue"
},
  "geometry": {"coordinates":[-76.49231399999999,38.978342],"type":"Point"}
}