{
  "type": "Feature",
  "properties": {
    "iso:country":"US",
    "sg:address":"3701 Duncanwood Ln",
    "sg:city":"Baltimore",
    "sg:classifiers":[
        {
            "category":"Real Estate",
            "subcategory":"Real Estate Services",
            "type":"Services"
        },
        {
            "category":"Building & Trades",
            "subcategory":"Cleaning & Sanitation",
            "type":"Services"
        }
    ],
    "sg:phone":"+1 443 984 1774",
    "sg:postcode":"21213",
    "sg:province":"MD",
    "sg:tags":[
        "maintenance",
        "cleaners-interior"
    ],
    "wof:name":"B C H A Maintenance Opera",
    "wof:placetype":"venue"
},
  "geometry": {"coordinates":[-76.56832199999999,39.308884],"type":"Point"}
}