{
  "type": "Feature",
  "properties": {
    "iso:country":"US",
    "sg:address":"1329 Pennsylvania Ave",
    "sg:city":"Hagerstown",
    "sg:classifiers":[
        {
            "category":"Retail",
            "subcategory":"Portrait Studio",
            "type":"Services"
        }
    ],
    "sg:phone":"+1 301 733 2320",
    "sg:postcode":"21742",
    "sg:province":"MD",
    "sg:tags":[
        "photographer"
    ],
    "wof:name":"Photography By Dale",
    "wof:placetype":"venue"
},
  "geometry": {"coordinates":[-77.71894399999999,39.663634],"type":"Point"}
}