{
  "type": "Feature",
  "properties": {
    "iso:country":"US",
    "sg:address":"4715 Trident Ct",
    "sg:city":"Halethorpe",
    "sg:classifiers":[
        {
            "category":"Professional",
            "type":"Services"
        },
        {
            "category":"Personal",
            "type":"Services"
        },
        {
            "category":"Retail",
            "subcategory":"Event Space",
            "type":"Services"
        }
    ],
    "sg:phone":"+1 866 652 7044",
    "sg:postcode":"21227",
    "sg:province":"MD",
    "sg:tags":[
        "box",
        "full",
        "material",
        "storage",
        "moving",
        "services-labor",
        "mover"
    ],
    "sg:website":"http://www.alliedvanlines.com/",
    "wof:name":"Allied Van Lines",
    "wof:placetype":"venue"
},
  "geometry": {"coordinates":[-76.680448,39.227598],"type":"Point"}
}