{
  "type": "Feature",
  "properties": {
    "iso:country":"US",
    "sg:address":"11611 Old Georgetown Rd",
    "sg:city":"Rockville",
    "sg:classifiers":[
        {
            "category":"Building & Trades",
            "subcategory":"Construction",
            "type":"Services"
        }
    ],
    "sg:phone":"+1 301 231 0009",
    "sg:postcode":"20852",
    "sg:province":"MD",
    "sg:tags":[
        "contractor"
    ],
    "wof:name":"Mid-Atlantic Companies Inc",
    "wof:placetype":"venue"
},
  "geometry": {"coordinates":[-77.112396,39.046001],"type":"Point"}
}