{
  "type": "Feature",
  "properties": {
    "addr:full":"1801 Research Blvd Rockville MD 20850",
    "addr:housenumber":"1801",
    "addr:postcode":"20850",
    "addr:street":"Research Blvd",
    "iso:country":"US",
    "sg:address":"1801 Research Blvd",
    "sg:city":"Rockville",
    "sg:classifiers":[
        {
            "category":"Building & Trades",
            "subcategory":"Construction",
            "type":"Services"
        }
    ],
    "sg:phone":"+1 301 738 0087",
    "sg:postcode":"20850",
    "sg:province":"MD",
    "sg:tags":[
        "contractor"
    ],
    "wof:name":"Skanska USA Building Inc",
    "wof:placetype":"venue"
},
  "geometry": {"coordinates":[-77.181079,39.098362],"type":"Point"}
}