{
  "type": "Feature",
  "properties": {
    "iso:country":"US",
    "sg:address":"109 S 3rd St",
    "sg:city":"Oakland",
    "sg:classifiers":[
        {
            "category":"Organizations",
            "subcategory":"Non-profit Organization",
            "type":"Services"
        }
    ],
    "sg:phone":"+1 301 533 4470",
    "sg:postcode":"21550",
    "sg:province":"MD",
    "wof:name":"Oakland Oakland Main St",
    "wof:placetype":"venue"
},
  "geometry": {"coordinates":[-79.406829,39.408422],"type":"Point"}
}