{
  "type": "Feature",
  "properties": {
    "addr:full":"8791 Piney Orchard Pkwy Odenton MD 21113",
    "addr:housenumber":"8791",
    "addr:postcode":"21113",
    "addr:street":"Piney Orchard Pkwy",
    "iso:country":"US",
    "sg:address":"8791 Piney Orchard Pkwy",
    "sg:city":"Odenton",
    "sg:classifiers":[
        {
            "category":"Professional",
            "subcategory":"Engineering",
            "type":"Services"
        }
    ],
    "sg:phone":"+1 410 551 9850",
    "sg:postcode":"21113",
    "sg:province":"MD",
    "sg:tags":[
        "water",
        "treatment",
        "engineer"
    ],
    "wof:name":"Waste Water Treatment Plant",
    "wof:placetype":"venue"
},
  "geometry": {"coordinates":[-76.71560599999999,39.068493],"type":"Point"}
}