{
  "type": "Feature",
  "properties": {
    "addr:full":"1589 Sulphur Spring Rd Baltimore MD 21227",
    "addr:housenumber":"1589",
    "addr:postcode":"21227",
    "addr:street":"Sulphur Spring Rd",
    "iso:country":"US",
    "sg:address":"1589 Sulphur Spring Rd",
    "sg:city":"Baltimore",
    "sg:classifiers":[
        {
            "category":"Wholesale",
            "subcategory":"Chemicals & Plastics",
            "type":"Manufacturing & Wholesale Goods"
        }
    ],
    "sg:phone":"+1 410 247 7676",
    "sg:postcode":"21227",
    "sg:province":"MD",
    "sg:tags":[
        "oxygen"
    ],
    "wof:name":"Lincare",
    "wof:placetype":"venue"
},
  "geometry": {"coordinates":[-76.686543,39.248865],"type":"Point"}
}