{
  "type": "Feature",
  "properties": {
    "iso:country":"US",
    "sg:address":"5018 Dorsey Hall Dr",
    "sg:city":"Ellicott City",
    "sg:classifiers":[
        {
            "category":"Manufacturing",
            "subcategory":"Printing",
            "type":"Manufacturing & Wholesale Goods"
        }
    ],
    "sg:phone":"+1 410 740 0065",
    "sg:postcode":"21042",
    "sg:province":"MD",
    "sg:tags":[
        "publisher"
    ],
    "sg:website":"www.chevronpublishing.com",
    "wof:name":"Chevron Publishing Corp",
    "wof:placetype":"venue"
},
  "geometry": {"coordinates":[-76.83834,39.242962],"type":"Point"}
}