{
  "type": "Feature",
  "properties": {
    "addr:full":"812 Hayward Ave Takoma Park MD 20912",
    "addr:housenumber":"812",
    "addr:postcode":"20912",
    "addr:street":"Hayward Ave",
    "iso:country":"US",
    "sg:address":"812 Hayward Ave",
    "sg:city":"Takoma Park",
    "sg:classifiers":[
        {
            "category":"Sports & Exercise",
            "subcategory":"Gym",
            "type":"Entertainment"
        }
    ],
    "sg:phone":"+1 301 270 2658",
    "sg:postcode":"20912",
    "sg:province":"MD",
    "sg:tags":[
        "instructor",
        "fitness"
    ],
    "wof:name":"Longino Frenchie",
    "wof:placetype":"venue"
},
  "geometry": {"coordinates":[-76.996219,38.977612],"type":"Point"}
}