{
  "type": "Feature",
  "properties": {
    "addr:full":"8646 LIBERTY RD RANDALLSTOWN MD 21133",
    "addr:housenumber":"8646",
    "addr:postcode":"21133",
    "addr:street":"Liberty Rd",
    "iso:country":"US",
    "sg:address":"8646 LIBERTY RD",
    "sg:city":"RANDALLSTOWN",
    "sg:phone":"+1 410 521 8696",
    "sg:postcode":"21133",
    "sg:province":"MD",
    "sg:website":"http://www.rentacenter.com/",
    "wof:name":"Rent-A-Center",
    "wof:placetype":"venue"
},
  "geometry": {"coordinates":[-76.780995,39.362223],"type":"Point"}
}