{
  "type": "Feature",
  "properties": {
    "iso:country":"US",
    "sg:address":"4545 Finney Ave",
    "sg:city":"Baltimore",
    "sg:classifiers":[
        {
            "category":"Real Estate",
            "subcategory":"Real Estate Services",
            "type":"Services"
        },
        {
            "category":"Banks & Credit Unions",
            "subcategory":"Financial Services",
            "type":"Services"
        }
    ],
    "sg:phone":"+1 410 542 0182",
    "sg:postcode":"21215",
    "sg:province":"MD",
    "sg:tags":[
        "loan",
        "processing"
    ],
    "wof:name":"Customer First Mortgage",
    "wof:placetype":"venue"
},
  "geometry": {"coordinates":[-76.66103099999999,39.3434],"type":"Point"}
}