{
  "type": "Feature",
  "properties": {
    "addr:full":"906 Pine Avenue Frederick MD 21701",
    "addr:housenumber":"906",
    "addr:postcode":"21701",
    "addr:street":"Pine Avenue",
    "iso:country":"US",
    "sg:address":"906 Pine Avenue",
    "sg:city":"Frederick",
    "sg:classifiers":[
        {
            "category":"Professional",
            "subcategory":"Engineering",
            "type":"Services"
        }
    ],
    "sg:phone":"+1 301 698 8207",
    "sg:postcode":"21701",
    "sg:province":"MD",
    "sg:tags":[
        "consulting",
        "structural",
        "engineer"
    ],
    "wof:name":"Houchins Specialty Engineering, LLC",
    "wof:placetype":"venue"
},
  "geometry": {"coordinates":[-77.401117,39.425954],"type":"Point"}
}