{
  "type": "Feature",
  "properties": {
    "addr:full":"6323 Rhode Island Ave # D Riverdale MD 20737",
    "addr:housenumber":"6323",
    "addr:postcode":"20737",
    "addr:street":"Rhode Island Ave # D",
    "iso:country":"US",
    "sg:address":"6323 Rhode Island Ave # D",
    "sg:city":"Riverdale",
    "sg:classifiers":[
        {
            "category":"Retail",
            "subcategory":"Auto Repair",
            "type":"Services"
        }
    ],
    "sg:phone":"+1 301 277 1997",
    "sg:postcode":"20737",
    "sg:province":"MD",
    "wof:name":"Romero Auto Service",
    "wof:placetype":"venue"
},
  "geometry": {"coordinates":[-76.93450199999999,38.964901],"type":"Point"}
}