{
  "type": "Feature",
  "properties": {
    "addr:full":"1940 Mitchellville Rd Bowie MD 20716",
    "addr:housenumber":"1940",
    "addr:postcode":"20716",
    "addr:street":"Mitchellville Rd",
    "iso:country":"US",
    "sg:address":"1940 Mitchellville Rd",
    "sg:city":"Bowie",
    "sg:classifiers":[
        {
            "category":"Organizations",
            "subcategory":"Religious Organization",
            "type":"Services"
        }
    ],
    "sg:phone":"+1 301 249 9599",
    "sg:postcode":"20716",
    "sg:province":"MD",
    "sg:tags":[
        "church"
    ],
    "wof:name":"Saint Edwards Catholic Church",
    "wof:placetype":"venue"
},
  "geometry": {"coordinates":[-76.727463,38.915972],"type":"Point"}
}