{
  "type": "Feature",
  "properties": {
    "iso:country":"US",
    "sg:address":"3137 Eastern Ave",
    "sg:city":"Baltimore",
    "sg:classifiers":[
        {
            "category":"Bars & Pubs",
            "type":"Food & Drink"
        }
    ],
    "sg:phone":"+1 410 675 3191",
    "sg:postcode":"21224",
    "sg:province":"MD",
    "wof:name":"Chuck's Place",
    "wof:placetype":"venue"
},
  "geometry": {"coordinates":[-76.57168,39.286372],"type":"Point"}
}