{
  "type": "Feature",
  "properties": {
    "addr:full":"38 Leatherwood Pl Baltimore MD 21237",
    "addr:housenumber":"38",
    "addr:postcode":"21237",
    "addr:street":"Leatherwood Pl",
    "iso:country":"US",
    "sg:address":"38 Leatherwood Pl",
    "sg:city":"Baltimore",
    "sg:classifiers":[
        {
            "category":"Professional",
            "type":"Services"
        }
    ],
    "sg:phone":"+1 410 882 4977",
    "sg:postcode":"21237",
    "sg:province":"MD",
    "wof:name":"Leonard J Manzella",
    "wof:placetype":"venue"
},
  "geometry": {"coordinates":[-76.50087000000001,39.360075],"type":"Point"}
}