{
  "type": "Feature",
  "properties": {
    "iso:country":"US",
    "sg:address":"6701 Democracy Blvd",
    "sg:city":"Bethesda",
    "sg:classifiers":[
        {
            "category":"Manufacturing",
            "subcategory":"Printing",
            "type":"Manufacturing & Wholesale Goods"
        }
    ],
    "sg:phone":"+1 301 493 0300",
    "sg:postcode":"20817",
    "sg:province":"MD",
    "sg:tags":[
        "printer",
        "form"
    ],
    "wof:name":"Atlantic Forms Corp",
    "wof:placetype":"venue"
},
  "geometry": {"coordinates":[-77.13637199999999,39.021812],"type":"Point"}
}