{
  "type": "Feature",
  "properties": {
    "addr:full":"10807 Pearson St Kensington MD 20895",
    "addr:housenumber":"10807",
    "addr:postcode":"20895",
    "addr:street":"Pearson St",
    "iso:country":"US",
    "sg:address":"10807 Pearson St",
    "sg:city":"Kensington",
    "sg:classifiers":[
        {
            "category":"Professional",
            "subcategory":"Computer Services",
            "type":"Services"
        }
    ],
    "sg:phone":"+1 301 929 8591",
    "sg:postcode":"20895",
    "sg:province":"MD",
    "sg:tags":[
        "datum"
    ],
    "wof:name":"Mark Wenner",
    "wof:placetype":"venue"
},
  "geometry": {"coordinates":[-77.065641,39.034293],"type":"Point"}
}