{
  "type": "Feature",
  "properties": {
    "addr:full":"17204 Longleaf Dr Bowie MD 20716",
    "addr:housenumber":"17204",
    "addr:postcode":"20716",
    "addr:street":"Longleaf Dr",
    "iso:country":"US",
    "sg:address":"17204 Longleaf Dr",
    "sg:city":"Bowie",
    "sg:classifiers":[
        {
            "category":"Professional",
            "subcategory":"Management & Consulting",
            "type":"Services"
        }
    ],
    "sg:phone":"+1 301 805 6125",
    "sg:postcode":"20716",
    "sg:province":"MD",
    "wof:name":"Joh Enterprises Inc",
    "wof:placetype":"venue"
},
  "geometry": {"coordinates":[-76.706363,38.952057],"type":"Point"}
}