{
  "type": "Feature",
  "properties": {
    "iso:country":"US",
    "sg:address":"5030 Brown Station Rd",
    "sg:city":"Upper Marlboro",
    "sg:classifiers":[
        {
            "category":"Food & Beverages",
            "subcategory":"Groceries & Convenience Stores",
            "type":"Retail Goods"
        }
    ],
    "sg:phone":"+1 301 952 8222",
    "sg:postcode":"20772",
    "sg:province":"MD",
    "sg:tags":[
        "grocer"
    ],
    "wof:name":"Lauers Iga",
    "wof:placetype":"venue"
},
  "geometry": {"coordinates":[-76.764212,38.819782],"type":"Point"}
}