{
  "type": "Feature",
  "properties": {
    "addr:full":"18928 Premiere Ct Gaithersburg MD 20879",
    "addr:postcode":"18928;20879",
    "addr:street":"Premiere Ct",
    "iso:country":"US",
    "sg:address":"18928 Premiere Ct",
    "sg:city":"Gaithersburg",
    "sg:classifiers":[
        {
            "category":"Organizations",
            "subcategory":"Non-profit Organization",
            "type":"Services"
        }
    ],
    "sg:phone":"+1 301 670 0604",
    "sg:postcode":"20879",
    "sg:province":"MD",
    "wof:name":"Composite Panel Assn",
    "wof:placetype":"venue"
},
  "geometry": {"coordinates":[-77.16681699999999,39.166961],"type":"Point"}
}