{
  "type": "Feature",
  "properties": {
    "iso:country":"US",
    "sg:address":"857 E Fort Ave",
    "sg:city":"Baltimore",
    "sg:classifiers":[
        {
            "category":"Food & Beverages",
            "subcategory":"Groceries & Convenience Stores",
            "type":"Retail Goods"
        }
    ],
    "sg:phone":"+1 410 727 1246",
    "sg:postcode":"21230",
    "sg:province":"MD",
    "sg:tags":[
        "grocer"
    ],
    "sg:website":"www.shoppersfood.com",
    "wof:name":"Shoppers Food Warehouse",
    "wof:placetype":"venue"
},
  "geometry": {"coordinates":[-76.60190900000001,39.271851],"type":"Point"}
}