{
  "type": "Feature",
  "properties": {
    "addr:full":"7972 Belair Rd Nottingham MD 21236",
    "addr:housenumber":"7972",
    "addr:postcode":"21236",
    "addr:street":"Belair Rd",
    "iso:country":"US",
    "sg:address":"7972 Belair Rd",
    "sg:city":"Nottingham",
    "sg:classifiers":[
        {
            "category":"Shopping",
            "subcategory":"Hobbies, Toys, & Games",
            "type":"Retail Goods"
        }
    ],
    "sg:phone":"+1 410 663 6963",
    "sg:postcode":"21236",
    "sg:province":"MD",
    "sg:tags":[
        "video",
        "supply"
    ],
    "sg:website":"http://www.gamestop.com/",
    "wof:name":"Gamestop",
    "wof:placetype":"venue"
},
  "geometry": {"coordinates":[-76.50779,39.375134],"type":"Point"}
}