{
  "type": "Feature",
  "properties": {
    "iso:country":"US",
    "sg:address":"3031 Blackland Ct",
    "sg:city":"Waldorf",
    "sg:classifiers":[
        {
            "category":"Building & Trades",
            "subcategory":"Construction",
            "type":"Services"
        }
    ],
    "sg:phone":"+1 301 801 3325",
    "sg:postcode":"20602",
    "sg:province":"MD",
    "sg:tags":[
        "wallcoverings-installation",
        "wallpaper",
        "painting",
        "contractor"
    ],
    "wof:name":"Bens Painting",
    "wof:placetype":"venue"
},
  "geometry": {"coordinates":[-76.900291,38.610249],"type":"Point"}
}