{
  "type": "Feature",
  "properties": {
    "iso:country":"US",
    "sg:address":"3005 Tyson Ln",
    "sg:city":"Bowie",
    "sg:classifiers":[
        {
            "category":"Farming",
            "subcategory":"Fish & Marine Products",
            "type":"Manufacturing & Wholesale Goods"
        }
    ],
    "sg:phone":"+1 301 262 8417",
    "sg:postcode":"20715",
    "sg:province":"MD",
    "sg:tags":[
        "shellfish",
        "fishing"
    ],
    "wof:name":"Dales Capn Seafood",
    "wof:placetype":"venue"
},
  "geometry": {"coordinates":[-76.749365,38.971651],"type":"Point"}
}