{
  "type": "Feature",
  "properties": {
    "addr:full":"8427 Pleasant Plains Rd Baltimore MD 21286",
    "addr:housenumber":"8427",
    "addr:postcode":"21286",
    "addr:street":"Pleasant Plains Rd",
    "iso:country":"US",
    "sg:address":"8427 Pleasant Plains Rd",
    "sg:city":"Baltimore",
    "sg:classifiers":[
        {
            "category":"Retail",
            "subcategory":"Portrait Studio",
            "type":"Services"
        }
    ],
    "sg:phone":"+1 410 828 1561",
    "sg:postcode":"21286",
    "sg:province":"MD",
    "sg:tags":[
        "photo"
    ],
    "wof:name":"Nancy L Held Photographer An",
    "wof:placetype":"venue"
},
  "geometry": {"coordinates":[-76.570455,39.39242],"type":"Point"}
}