{
  "type": "Feature",
  "properties": {
    "iso:country":"US",
    "sg:address":"3501 Benson Ave",
    "sg:city":"Halethorpe",
    "sg:classifiers":[
        {
            "category":"Shopping",
            "subcategory":"Tobacco",
            "type":"Retail Goods"
        },
        {
            "category":"Manufacturing",
            "subcategory":"Food",
            "type":"Manufacturing & Wholesale Goods"
        },
        {
            "category":"Food & Beverages",
            "subcategory":"Candy",
            "type":"Retail Goods"
        },
        {
            "category":"Organizations",
            "subcategory":"Non-profit Organization",
            "type":"Services"
        }
    ],
    "sg:phone":"+1 410 644 6414",
    "sg:postcode":"21227",
    "sg:province":"MD",
    "sg:tags":[
        "shop",
        "confectionery",
        "fund",
        "confectionery-wholesale",
        "store",
        "raising",
        "manufacturer"
    ],
    "sg:website":"http://www.georgejfalter.com",
    "wof:name":"Falter Geo J Co Inc Candy & Tobacco",
    "wof:placetype":"venue"
},
  "geometry": {"coordinates":[-76.672997,39.2659],"type":"Point"}
}