{
  "type": "Feature",
  "properties": {
    "addr:full":"101 S Baltimore Ave Ocean City MD 21842",
    "addr:housenumber":"101",
    "addr:postcode":"21842",
    "addr:street":"S Baltimore Ave",
    "iso:country":"US",
    "sg:address":"101 S Baltimore Ave",
    "sg:city":"Ocean City",
    "sg:classifiers":[
        {
            "category":"Shopping",
            "subcategory":"Clothing, Apparel, & Fashions",
            "type":"Retail Goods"
        }
    ],
    "sg:phone":"+1 410 289 1926",
    "sg:postcode":"21842",
    "sg:province":"MD",
    "wof:name":"Horizan Beach Wear",
    "wof:placetype":"venue"
},
  "geometry": {"coordinates":[-75.08641799999999,38.331109],"type":"Point"}
}