{
  "type": "Feature",
  "properties": {
    "iso:country":"US",
    "sg:address":"2400 Boston St",
    "sg:city":"Baltimore",
    "sg:classifiers":[
        {
            "category":"Restaurant",
            "type":"Food & Drink"
        }
    ],
    "sg:phone":"+1 410 534 0606",
    "sg:postcode":"21224",
    "sg:province":"MD",
    "sg:tags":[
        "grill",
        "bar"
    ],
    "sg:website":"http://www.austingrill.com",
    "wof:name":"Austin Grill",
    "wof:placetype":"venue"
},
  "geometry": {"coordinates":[-76.582397,39.281898],"type":"Point"}
}