{
  "type": "Feature",
  "properties": {
    "iso:country":"US",
    "sg:address":"200 E Lexington St",
    "sg:city":"Baltimore",
    "sg:classifiers":[
        {
            "category":"Professional",
            "subcategory":"Lawyer & Legal Services",
            "type":"Services"
        }
    ],
    "sg:phone":"+1 410 244 1456",
    "sg:postcode":"21202",
    "sg:province":"MD",
    "sg:tags":[
        "divorce",
        "law",
        "family"
    ],
    "wof:name":"Kirwan Susan G",
    "wof:placetype":"venue"
},
  "geometry": {"coordinates":[-76.612396,39.291199],"type":"Point"}
}