{
  "type": "Feature",
  "properties": {
    "iso:country":"US",
    "sg:address":"10015 Raynor Rd",
    "sg:city":"Silver Spring",
    "sg:classifiers":[
        {
            "category":"Professional",
            "subcategory":"Business Services",
            "type":"Services"
        }
    ],
    "sg:phone":"+1 301 592 0078",
    "sg:postcode":"20901",
    "sg:province":"MD",
    "sg:tags":[
        "language",
        "contractor"
    ],
    "wof:name":"Jill Werwinski",
    "wof:placetype":"venue"
},
  "geometry": {"coordinates":[-77.029712,39.020892],"type":"Point"}
}