{
  "type": "Feature",
  "properties": {
    "iso:country":"US",
    "sg:address":"10046 Cotton Mill Ln",
    "sg:city":"Columbia",
    "sg:classifiers":[
        {
            "category":"Professional",
            "subcategory":"Management & Consulting",
            "type":"Services"
        }
    ],
    "sg:phone":"+1 301 596 0533",
    "sg:postcode":"21046",
    "sg:province":"MD",
    "sg:tags":[
        "business"
    ],
    "wof:name":"Reagle Associates",
    "wof:placetype":"venue"
},
  "geometry": {"coordinates":[-76.859016,39.183744],"type":"Point"}
}