{
  "type": "Feature",
  "properties": {
    "addr:full":"2100 Merritt Blvd Dundalk MD 21222",
    "addr:housenumber":"2100",
    "addr:postcode":"21222",
    "addr:street":"Merritt Blvd",
    "iso:country":"US",
    "sg:address":"2100 Merritt Blvd",
    "sg:city":"Dundalk",
    "sg:classifiers":[
        {
            "category":"Personal",
            "type":"Services"
        },
        {
            "category":"Retail",
            "subcategory":"Auto Rental",
            "type":"Services"
        },
        {
            "category":"Retail",
            "subcategory":"Storage",
            "type":"Services"
        }
    ],
    "sg:phone":"+1 410 238 7630",
    "sg:postcode":"21222",
    "sg:province":"MD",
    "sg:tags":[
        "renting",
        "moving-self",
        "leasing",
        "truck",
        "mover",
        "trailer"
    ],
    "wof:name":"U-Haul Co",
    "wof:placetype":"venue"
},
  "geometry": {"coordinates":[-76.511139,39.258091],"type":"Point"}
}