{
  "type": "Feature",
  "properties": {
    "addr:full":"8043 Penn Randall Pl Upper Marlboro MD 20772",
    "addr:housenumber":"8043",
    "addr:postcode":"20772",
    "addr:street":"Penn Randall Pl",
    "iso:country":"US",
    "sg:address":"8043 Penn Randall Pl",
    "sg:city":"Upper Marlboro",
    "sg:classifiers":[
        {
            "category":"Recreation",
            "type":"Entertainment"
        }
    ],
    "sg:phone":"+1 301 736 2004",
    "sg:postcode":"20772",
    "sg:province":"MD",
    "sg:tags":[
        "instruction",
        "gymnastic"
    ],
    "wof:name":"Maryland Cheer Explosion",
    "wof:placetype":"venue"
},
  "geometry": {"coordinates":[-76.86729200000001,38.835604],"type":"Point"}
}