{
  "type": "Feature",
  "properties": {
    "addr:full":"10386 Southard Dr Beltsville MD 20705",
    "addr:housenumber":"10386",
    "addr:postcode":"20705",
    "addr:street":"Southard Dr",
    "iso:country":"US",
    "sg:address":"10386 Southard Dr",
    "sg:city":"Beltsville",
    "sg:classifiers":[
        {
            "category":"Building & Trades",
            "subcategory":"Electrical",
            "type":"Services"
        }
    ],
    "sg:phone":"+1 301 595 1933",
    "sg:postcode":"20705",
    "sg:province":"MD",
    "wof:name":"Cabling Systems Inc",
    "wof:placetype":"venue"
},
  "geometry": {"coordinates":[-76.90965,39.030928],"type":"Point"}
}