{
  "type": "Feature",
  "properties": {
    "addr:full":"7208 Main St Queenstown MD 21658",
    "addr:housenumber":"7208",
    "addr:postcode":"21658",
    "addr:street":"Main St",
    "iso:country":"US",
    "sg:address":"7208 Main St",
    "sg:city":"Queenstown",
    "sg:classifiers":[
        {
            "category":"Organizations",
            "subcategory":"Religious Organization",
            "type":"Services"
        }
    ],
    "sg:phone":"+1 410 827 8484",
    "sg:postcode":"21658",
    "sg:province":"MD",
    "sg:tags":[
        "church"
    ],
    "sg:website":"www.wyeparish.org",
    "wof:name":"St Lukes Chapel",
    "wof:placetype":"venue"
},
  "geometry": {"coordinates":[-76.15504,38.990885],"type":"Point"}
}