{
  "type": "Feature",
  "properties": {
    "addr:full":"8907 Ardwick Ardmore Rd Springdale MD 20774",
    "addr:postcode":"8907;20774",
    "addr:street":"Ardmore Rd",
    "iso:country":"US",
    "sg:address":"8907 Ardwick Ardmore Rd",
    "sg:city":"Springdale",
    "sg:classifiers":[
        {
            "category":"Communications",
            "type":"Services"
        }
    ],
    "sg:phone":"+1 240 501 0251",
    "sg:postcode":"20774",
    "sg:province":"MD",
    "wof:name":"So &T Communications",
    "wof:placetype":"venue"
},
  "geometry": {"coordinates":[-76.854705,38.936533],"type":"Point"}
}