{
  "type": "Feature",
  "properties": {
    "iso:country":"US",
    "sg:address":"5933 Belair Rd",
    "sg:city":"Baltimore",
    "sg:classifiers":[
        {
            "category":"Banks & Credit Unions",
            "subcategory":"Bank",
            "type":"Services"
        }
    ],
    "sg:phone":"+1 410 325 7576",
    "sg:postcode":"21206",
    "sg:province":"MD",
    "sg:tags":[
        "loan"
    ],
    "wof:name":"Student Loan Relief Orgnztn",
    "wof:placetype":"venue"
},
  "geometry": {"coordinates":[-76.53985400000001,39.346508],"type":"Point"}
}