{
  "type": "Feature",
  "properties": {
    "addr:full":"3103 Edgewood Rd Kensington MD 20895",
    "addr:housenumber":"3103",
    "addr:postcode":"20895",
    "addr:street":"Edgewood Rd",
    "iso:country":"US",
    "sg:address":"3103 Edgewood Rd",
    "sg:city":"Kensington",
    "sg:classifiers":[
        {
            "category":"Professional",
            "subcategory":"Computer Services",
            "type":"Services"
        }
    ],
    "sg:phone":"+1 301 942 3453",
    "sg:postcode":"20895",
    "sg:province":"MD",
    "sg:tags":[
        "consultant",
        "designer"
    ],
    "wof:name":"Systems & Management Assoc",
    "wof:placetype":"venue"
},
  "geometry": {"coordinates":[-77.061881,39.0261],"type":"Point"}
}