{
  "type": "Feature",
  "properties": {
    "addr:full":"10712 Anglo Hill Rd Cockeysville MD 21030",
    "addr:housenumber":"10712",
    "addr:postcode":"21030",
    "addr:street":"Anglo Hill Rd",
    "iso:country":"US",
    "sg:address":"10712 Anglo Hill Rd",
    "sg:city":"Cockeysville",
    "sg:classifiers":[
        {
            "category":"Insurance",
            "subcategory":"Insurance Agent",
            "type":"Services"
        }
    ],
    "sg:phone":"+1 410 667 4654",
    "sg:postcode":"21030",
    "sg:province":"MD",
    "wof:name":"Employease Inc",
    "wof:placetype":"venue"
},
  "geometry": {"coordinates":[-76.604574,39.479093],"type":"Point"}
}