{
  "type": "Feature",
  "properties": {
    "addr:full":"222 S Main St Hurlock MD 21643",
    "addr:housenumber":"222",
    "addr:postcode":"21643",
    "addr:street":"S Main St",
    "iso:country":"US",
    "sg:address":"222 S Main St",
    "sg:city":"Hurlock",
    "sg:classifiers":[
        {
            "category":"Education",
            "subcategory":"Library",
            "type":"Public Place"
        }
    ],
    "sg:phone":"+1 410 943 4331",
    "sg:postcode":"21643",
    "sg:province":"MD",
    "wof:name":"Hurlock Library",
    "wof:placetype":"venue"
},
  "geometry": {"coordinates":[-75.86230500000001,38.631625],"type":"Point"}
}