{
  "type": "Feature",
  "properties": {
    "iso:country":"US",
    "sg:address":"1560 Caton Center Dr",
    "sg:city":"Halethorpe",
    "sg:classifiers":[
        {
            "category":"Manufacturing",
            "subcategory":"Printing",
            "type":"Manufacturing & Wholesale Goods"
        }
    ],
    "sg:phone":"+1 410 242 8300",
    "sg:postcode":"21227",
    "sg:province":"MD",
    "sg:tags":[
        "printer"
    ],
    "wof:name":"Creative Print Group",
    "wof:placetype":"venue"
},
  "geometry": {"coordinates":[-76.680491,39.256691],"type":"Point"}
}