{
  "type": "Feature",
  "properties": {
    "addr:full":"1356 Dorsey Rd Hanover MD 21076",
    "addr:housenumber":"1356",
    "addr:postcode":"21076",
    "addr:street":"Dorsey Rd",
    "iso:country":"US",
    "sg:address":"1356 Dorsey Rd",
    "sg:city":"Hanover",
    "sg:classifiers":[
        {
            "category":"Autos & Motor Vehicles",
            "subcategory":"Fuel & Gas Station",
            "type":"Retail Goods"
        }
    ],
    "sg:phone":"+1 410 850 5759",
    "sg:postcode":"21076",
    "sg:province":"MD",
    "sg:tags":[
        "oil"
    ],
    "wof:name":"Shell",
    "wof:placetype":"venue"
},
  "geometry": {"coordinates":[-76.708347,39.158492],"type":"Point"}
}