{
  "type": "Feature",
  "properties": {
    "addr:full":"3611 Branch Ave Ste 309 Temple Hills MD 20748",
    "addr:housenumber":"3611",
    "addr:postcode":"20748",
    "addr:street":"Branch Ave Ste 309 Temple",
    "iso:country":"US",
    "sg:address":"3611 Branch Ave Ste 309",
    "sg:city":"Temple Hills",
    "sg:classifiers":[
        {
            "category":"Health Services",
            "subcategory":"Doctor",
            "type":"Services"
        }
    ],
    "sg:phone":"+1 301 899 7900",
    "sg:postcode":"20748",
    "sg:province":"MD",
    "wof:name":"Ignacio Daniel R MD",
    "wof:placetype":"venue"
},
  "geometry": {"coordinates":[-76.948402,38.841801],"type":"Point"}
}