{
  "type": "Feature",
  "properties": {
    "addr:full":"415 S Bond St Baltimore MD 21231",
    "addr:housenumber":"415",
    "addr:postcode":"21231",
    "addr:street":"S Bond St",
    "iso:country":"US",
    "sg:address":"415 S Bond St",
    "sg:city":"Baltimore",
    "sg:classifiers":[
        {
            "category":"Building & Trades",
            "subcategory":"Construction",
            "type":"Services"
        }
    ],
    "sg:phone":"+1 410 522 1165",
    "sg:postcode":"21231",
    "sg:province":"MD",
    "sg:tags":[
        "contractor"
    ],
    "wof:name":"E Pikounis",
    "wof:placetype":"venue"
},
  "geometry": {"coordinates":[-76.59522200000001,39.286387],"type":"Point"}
}