{
  "type": "Feature",
  "properties": {
    "addr:full":"41655 Fenwick St Leonardtown MD 20650",
    "addr:housenumber":"41655",
    "addr:postcode":"20650",
    "addr:street":"Fenwick St",
    "iso:country":"US",
    "sg:address":"41655 Fenwick St",
    "sg:city":"Leonardtown",
    "sg:classifiers":[
        {
            "category":"Restaurant",
            "type":"Food & Drink"
        }
    ],
    "sg:phone":"+1 301 997 0500",
    "sg:postcode":"20650",
    "sg:province":"MD",
    "sg:website":"www.cafedesartistes.ws",
    "wof:name":"Cafe Des Artistes",
    "wof:placetype":"venue"
},
  "geometry": {"coordinates":[-76.633067,38.290948],"type":"Point"}
}