{
  "type": "Feature",
  "properties": {
    "iso:country":"US",
    "sg:address":"300 Carroll Ave",
    "sg:city":"Laurel",
    "sg:classifiers":[
        {
            "category":"Arts & Performance",
            "subcategory":"Music",
            "type":"Entertainment"
        }
    ],
    "sg:phone":"+1 301 498 5656",
    "sg:postcode":"20707",
    "sg:province":"MD",
    "sg:tags":[
        "jockey",
        "disc"
    ],
    "wof:name":"Djs Plus",
    "wof:placetype":"venue"
},
  "geometry": {"coordinates":[-76.84761,39.10025],"type":"Point"}
}