{
  "type": "Feature",
  "properties": {
    "addr:full":"821 N Eutaw St Ste 102 Baltimore MD 21201",
    "addr:housenumber":"821",
    "addr:postcode":"21201",
    "addr:street":"N Eutaw St Ste 102",
    "iso:country":"US",
    "sg:address":"821 N Eutaw St Ste 102",
    "sg:city":"Baltimore",
    "sg:classifiers":[
        {
            "category":"Health Services",
            "subcategory":"Doctor",
            "type":"Services"
        }
    ],
    "sg:phone":"+1 410 523 3800",
    "sg:postcode":"21201",
    "sg:province":"MD",
    "sg:tags":[
        "obstetrician",
        "gynecologist"
    ],
    "wof:name":"Diener Ronald L MD",
    "wof:placetype":"venue"
},
  "geometry": {"coordinates":[-76.621498,39.299198],"type":"Point"}
}