{
  "type": "Feature",
  "properties": {
    "addr:full":"4307 Beaman Pl Temple Hills MD 20748",
    "addr:housenumber":"4307",
    "addr:postcode":"20748",
    "addr:street":"Beaman Pl",
    "iso:country":"US",
    "sg:address":"4307 Beaman Pl",
    "sg:city":"Temple Hills",
    "sg:classifiers":[
        {
            "category":"Organizations",
            "subcategory":"Religious Organization",
            "type":"Services"
        }
    ],
    "sg:phone":"+1 301 894 6111",
    "sg:postcode":"20748",
    "sg:province":"MD",
    "sg:tags":[
        "clergy"
    ],
    "wof:name":"Allen Chapel AME Chr Parsonage",
    "wof:placetype":"venue"
},
  "geometry": {"coordinates":[-76.97062099999999,38.830881],"type":"Point"}
}