{
  "type": "Feature",
  "properties": {
    "iso:country":"US",
    "sg:address":"301 Colesville Manor Dr",
    "sg:city":"Silver Spring",
    "sg:classifiers":[
        {
            "category":"Professional",
            "subcategory":"Lawyer & Legal Services",
            "type":"Services"
        }
    ],
    "sg:phone":"+1 301 384 2452",
    "sg:postcode":"20904",
    "sg:province":"MD",
    "wof:name":"Phelan Brian",
    "wof:placetype":"venue"
},
  "geometry": {"coordinates":[-77.002899,39.086201],"type":"Point"}
}