{
  "type": "Feature",
  "properties": {
    "addr:full":"20 Howard St Aberdeen MD 21001",
    "addr:housenumber":"20",
    "addr:postcode":"21001",
    "addr:street":"Howard St",
    "iso:country":"US",
    "sg:address":"20 Howard St",
    "sg:city":"Aberdeen",
    "sg:classifiers":[
        {
            "category":"Social Services",
            "type":"Services"
        },
        {
            "category":"Professional",
            "subcategory":"Employment Agencies",
            "type":"Services"
        },
        {
            "category":"Organizations",
            "subcategory":"Membership Organization",
            "type":"Services"
        }
    ],
    "sg:phone":"+1 410 272 3788",
    "sg:postcode":"21001",
    "sg:province":"MD",
    "sg:tags":[
        "workers'",
        "placement",
        "fraternal",
        "volunteer"
    ],
    "wof:name":"Aberdeen Masonic Lodge",
    "wof:placetype":"venue"
},
  "geometry": {"coordinates":[-76.16364299999999,39.510761],"type":"Point"}
}