{
  "type": "Feature",
  "properties": {
    "addr:full":"6012 Shiloh Church Hurlock Rd Hurlock MD 21643",
    "addr:housenumber":"6012",
    "addr:postcode":"21643",
    "addr:street":"Shiloh;Hurlock Rd",
    "iso:country":"US",
    "sg:address":"6012 Shiloh Church Hurlock Rd",
    "sg:city":"Hurlock",
    "sg:classifiers":[
        {
            "category":"Autos & Motor Vehicles",
            "subcategory":"Automobile Sales",
            "type":"Retail Goods"
        },
        {
            "category":"Wholesale",
            "subcategory":"Scrap",
            "type":"Manufacturing & Wholesale Goods"
        },
        {
            "category":"Utilities",
            "subcategory":"Recycling",
            "type":"Services"
        }
    ],
    "sg:phone":"+1 410 943 3089",
    "sg:postcode":"21643",
    "sg:province":"MD",
    "sg:tags":[
        "salvage",
        "junk",
        "metals-wholesale",
        "metal"
    ],
    "wof:name":"Midshore Recyclers , Inc.",
    "wof:placetype":"venue"
},
  "geometry": {"coordinates":[-75.861137,38.605381],"type":"Point"}
}