{
  "type": "Feature",
  "properties": {
    "addr:full":"7705 Old Georgetown Rd Bethesda MD 20814",
    "addr:housenumber":"7705",
    "addr:postcode":"20814",
    "addr:street":"Old Georgetown Rd",
    "iso:country":"US",
    "sg:address":"7705 Old Georgetown Rd",
    "sg:city":"Bethesda",
    "sg:classifiers":[
        {
            "category":"Real Estate",
            "subcategory":"Architect",
            "type":"Services"
        }
    ],
    "sg:phone":"+1 301 654 9300",
    "sg:postcode":"20814",
    "sg:province":"MD",
    "sg:tags":[
        "builder"
    ],
    "wof:name":"SKG Architects & Planners",
    "wof:placetype":"venue"
},
  "geometry": {"coordinates":[-77.097852,38.986987],"type":"Point"}
}