{
  "type": "Feature",
  "properties": {
    "iso:country":"US",
    "sg:address":"809 Montclaire Ave",
    "sg:city":"Frederick",
    "sg:classifiers":[
        {
            "category":"Building & Trades",
            "subcategory":"Construction",
            "type":"Services"
        }
    ],
    "sg:phone":"+1 301 228 3908",
    "sg:postcode":"21701",
    "sg:province":"MD",
    "sg:tags":[
        "home",
        "improvement"
    ],
    "wof:name":"T A Keller",
    "wof:placetype":"venue"
},
  "geometry": {"coordinates":[-77.412963,39.426013],"type":"Point"}
}