{
  "type": "Feature",
  "properties": {
    "addr:full":"3015 Hamilton Ave Baltimore MD 21214",
    "addr:housenumber":"3015",
    "addr:postcode":"21214",
    "addr:street":"Hamilton Ave",
    "iso:country":"US",
    "sg:address":"3015 Hamilton Ave",
    "sg:city":"Baltimore",
    "sg:classifiers":[
        {
            "category":"Personal",
            "subcategory":"Beauty Salon",
            "type":"Services"
        }
    ],
    "sg:phone":"+1 410 254 1310",
    "sg:postcode":"21214",
    "sg:province":"MD",
    "sg:tags":[
        "shop"
    ],
    "wof:name":"Rose's Beauty Salon",
    "wof:placetype":"venue"
},
  "geometry": {"coordinates":[-76.560281,39.351028],"type":"Point"}
}