{
  "type": "Feature",
  "properties": {
    "iso:country":"US",
    "sg:address":"1301 Main St",
    "sg:city":"Hampstead",
    "sg:classifiers":[
        {
            "category":"Restaurant",
            "type":"Food & Drink"
        }
    ],
    "sg:phone":"+1 410 374 6969",
    "sg:postcode":"21074",
    "sg:province":"MD",
    "wof:name":"Hill Street Pub",
    "wof:placetype":"venue"
},
  "geometry": {"coordinates":[-76.852088,39.609723],"type":"Point"}
}