{
  "type": "Feature",
  "properties": {
    "addr:full":"2582 Twin Landing Cv Annapolis MD 21401",
    "addr:housenumber":"2582",
    "addr:postcode":"21401",
    "addr:street":"Twin Landing Cv",
    "iso:country":"US",
    "sg:address":"2582 Twin Landing Cv",
    "sg:city":"Annapolis",
    "sg:classifiers":[
        {
            "category":"Place Of Worship",
            "type":"Public Place"
        }
    ],
    "sg:phone":"+1 410 573 5555",
    "sg:postcode":"21401",
    "sg:province":"MD",
    "sg:tags":[
        "church"
    ],
    "wof:name":"Eastern Shore Shrine Club",
    "wof:placetype":"venue"
},
  "geometry": {"coordinates":[-76.599073,38.978026],"type":"Point"}
}