{
  "type": "Feature",
  "properties": {
    "addr:full":"103 S Main St Federalsburg MD 21632",
    "addr:housenumber":"103",
    "addr:postcode":"21632",
    "addr:street":"S Main St",
    "iso:country":"US",
    "sg:address":"103 S Main St",
    "sg:city":"Federalsburg",
    "sg:classifiers":[
        {
            "category":"Real Estate",
            "subcategory":"Real Estate Agent",
            "type":"Services"
        }
    ],
    "sg:phone":"+1 410 754 8003",
    "sg:postcode":"21632",
    "sg:province":"MD",
    "wof:name":"Charles C Powell Realtors Inc",
    "wof:placetype":"venue"
},
  "geometry": {"coordinates":[-75.773704,38.694209],"type":"Point"}
}