{
  "type": "Feature",
  "properties": {
    "iso:country":"US",
    "sg:address":"22931 Dover Bridge Rd",
    "sg:city":"Preston",
    "sg:classifiers":[
        {
            "category":"Wholesale",
            "subcategory":"Scrap",
            "type":"Manufacturing & Wholesale Goods"
        }
    ],
    "sg:phone":"+1 410 673 1470",
    "sg:postcode":"21655",
    "sg:province":"MD",
    "sg:tags":[
        "recycling",
        "center"
    ],
    "wof:name":"Crown Cork & Seal Co",
    "wof:placetype":"venue"
},
  "geometry": {"coordinates":[-75.912734,38.723614],"type":"Point"}
}