{
  "type": "Feature",
  "properties": {
    "iso:country":"US",
    "sg:address":"3121 Ashwood Dr",
    "sg:city":"Dunkirk",
    "sg:classifiers":[
        {
            "category":"Building & Trades",
            "subcategory":"Electrical",
            "type":"Services"
        }
    ],
    "sg:phone":"+1 410 257 9405",
    "sg:postcode":"20754",
    "sg:province":"MD",
    "sg:tags":[
        "electric",
        "contractor"
    ],
    "wof:name":"Chesapeake Electrical Svc",
    "wof:placetype":"venue"
},
  "geometry": {"coordinates":[-76.66821299999999,38.740635],"type":"Point"}
}