{
  "type": "Feature",
  "properties": {
    "addr:full":"12006 Old Baltimore Pike Beltsville MD 20705",
    "addr:housenumber":"12006",
    "addr:postcode":"20705",
    "addr:street":"Old Baltimore Pike",
    "iso:country":"US",
    "sg:address":"12006 Old Baltimore Pike",
    "sg:city":"Beltsville",
    "sg:classifiers":[
        {
            "category":"Professional",
            "subcategory":"Advertising",
            "type":"Services"
        }
    ],
    "sg:phone":"+1 301 937 1011",
    "sg:postcode":"20705",
    "sg:province":"MD",
    "sg:tags":[
        "mailing",
        "shipping"
    ],
    "wof:name":"CHS Mailing Inc",
    "wof:placetype":"venue"
},
  "geometry": {"coordinates":[-76.88644600000001,39.053902],"type":"Point"}
}