{
  "type": "Feature",
  "properties": {
    "iso:country":"US",
    "sg:address":"7144 Ambassador Rd",
    "sg:city":"Baltimore",
    "sg:classifiers":[
        {
            "category":"Building & Trades",
            "subcategory":"Cleaning & Sanitation",
            "type":"Services"
        }
    ],
    "sg:phone":"+1 410 277 8821",
    "sg:postcode":"21244",
    "sg:province":"MD",
    "sg:tags":[
        "carpet"
    ],
    "wof:name":"Floor Works Inc",
    "wof:placetype":"venue"
},
  "geometry": {"coordinates":[-76.74552199999999,39.324717],"type":"Point"}
}