{
  "type": "Feature",
  "properties": {
    "iso:country":"US",
    "sg:address":"1000 Franklin Ave",
    "sg:city":"Essex",
    "sg:classifiers":[
        {
            "category":"Personal",
            "subcategory":"Beauty Salon",
            "type":"Services"
        }
    ],
    "sg:phone":"+1 410 391 1244",
    "sg:postcode":"21221",
    "sg:province":"MD",
    "wof:name":"Jo Ann Hair Salon",
    "wof:placetype":"venue"
},
  "geometry": {"coordinates":[-76.464203,39.314658],"type":"Point"}
}