{
  "type": "Feature",
  "properties": {
    "addr:full":"1325 Mount Hermon Rd Salisbury MD 21804",
    "addr:housenumber":"1325",
    "addr:postcode":"21804",
    "addr:street":"Mount Hermon Rd",
    "iso:country":"US",
    "sg:address":"1325 Mount Hermon Rd",
    "sg:city":"Salisbury",
    "sg:classifiers":[
        {
            "category":"Banks & Credit Unions",
            "subcategory":"Investment Brokerage",
            "type":"Services"
        }
    ],
    "sg:phone":"+1 410 742 4443",
    "sg:postcode":"21804",
    "sg:province":"MD",
    "sg:tags":[
        "security"
    ],
    "wof:name":"Pheasant & Associates",
    "wof:placetype":"venue"
},
  "geometry": {"coordinates":[-75.56629599999999,38.366479],"type":"Point"}
}