{
  "type": "Feature",
  "properties": {
    "addr:full":"5485 Harpers Farm Rd Columbia MD 21044",
    "addr:housenumber":"5485",
    "addr:postcode":"21044",
    "addr:street":"Harpers Farm Rd",
    "iso:country":"US",
    "sg:address":"5485 Harpers Farm Rd",
    "sg:city":"Columbia",
    "sg:classifiers":[
        {
            "category":"Health Services",
            "subcategory":"Hospital",
            "type":"Services"
        }
    ],
    "sg:phone":"+1 410 740 2452",
    "sg:postcode":"21044",
    "sg:province":"MD",
    "sg:tags":[
        "mental"
    ],
    "wof:name":"New Pathways Counseling Assoc",
    "wof:placetype":"venue"
},
  "geometry": {"coordinates":[-76.884979,39.221854],"type":"Point"}
}