{
  "type": "Feature",
  "properties": {
    "addr:full":"4915 Elm St Bethesda MD 20814",
    "addr:housenumber":"4915",
    "addr:postcode":"20814",
    "addr:street":"Elm St",
    "iso:country":"US",
    "sg:address":"4915 Elm St",
    "sg:city":"Bethesda",
    "sg:classifiers":[
        {
            "category":"Professional",
            "subcategory":"Accounting & Tax Preparation",
            "type":"Services"
        }
    ],
    "sg:phone":"+1 301 652 1120",
    "sg:postcode":"20814",
    "sg:province":"MD",
    "sg:tags":[
        "accountant"
    ],
    "wof:name":"Sachs & Figurelli LLC",
    "wof:placetype":"venue"
},
  "geometry": {"coordinates":[-77.098224,38.98215],"type":"Point"}
}