{
  "type": "Feature",
  "properties": {
    "iso:country":"US",
    "sg:address":"113 Sandyhook Rd",
    "sg:city":"Berlin",
    "sg:classifiers":[
        {
            "category":"Wholesale",
            "subcategory":"Non-durable Goods",
            "type":"Manufacturing & Wholesale Goods"
        }
    ],
    "sg:phone":"+1 410 641 6470",
    "sg:postcode":"21811",
    "sg:province":"MD",
    "wof:name":"Browsers Delite",
    "wof:placetype":"venue"
},
  "geometry": {"coordinates":[-75.170613,38.394387],"type":"Point"}
}