{
  "type": "Feature",
  "properties": {
    "iso:country":"US",
    "sg:address":"2201 Link Rd",
    "sg:city":"Silver Spring",
    "sg:classifiers":[
        {
            "category":"Professional",
            "subcategory":"Accounting & Tax Preparation",
            "type":"Services"
        }
    ],
    "sg:phone":"+1 301 384 6220",
    "sg:postcode":"20905",
    "sg:province":"MD",
    "wof:name":"Jon A Wegznek",
    "wof:placetype":"venue"
},
  "geometry": {"coordinates":[-76.959815,39.141226],"type":"Point"}
}