{
  "type": "Feature",
  "properties": {
    "addr:full":"2201 Link Rd Silver Spring MD 20905",
    "addr:housenumber":"2201",
    "addr:postcode":"20905",
    "addr:street":"Link Rd",
    "iso:country":"US",
    "sg:address":"2201 Link Rd",
    "sg:city":"Silver Spring",
    "sg:classifiers":[
        {
            "category":"Professional",
            "subcategory":"Accounting & Tax Preparation",
            "type":"Services"
        }
    ],
    "sg:phone":"+1 301 384 6220",
    "sg:postcode":"20905",
    "sg:province":"MD",
    "wof:name":"Jon A Wegznek",
    "wof:placetype":"venue"
},
  "geometry": {"coordinates":[-76.95981500000001,39.141226],"type":"Point"}
}