{
  "type": "Feature",
  "properties": {
    "addr:full":"11602 Reisterstown Rd Reisterstown MD 21136",
    "addr:housenumber":"11602",
    "addr:postcode":"21136",
    "addr:street":"Reisterstown Rd",
    "iso:country":"US",
    "sg:address":"11602 Reisterstown Rd",
    "sg:city":"Reisterstown",
    "sg:classifiers":[
        {
            "category":"Retail",
            "subcategory":"Auto Repair",
            "type":"Services"
        }
    ],
    "sg:phone":"+1 410 833 2271",
    "sg:postcode":"21136",
    "sg:province":"MD",
    "sg:tags":[
        "body",
        "automobile",
        "painting"
    ],
    "wof:name":"Reisterstown Auto Body",
    "wof:placetype":"venue"
},
  "geometry": {"coordinates":[-76.809566,39.443131],"type":"Point"}
}