{
  "type": "Feature",
  "properties": {
    "iso:country":"US",
    "sg:address":"17601 Olney Ln",
    "sg:city":"Rockville",
    "sg:classifiers":[
        {
            "category":"Professional",
            "subcategory":"Employment Agencies",
            "type":"Services"
        }
    ],
    "sg:phone":"+1 301 570 6820",
    "sg:postcode":"20853",
    "sg:province":"MD",
    "wof:name":"Peace of Mind Care Services",
    "wof:placetype":"venue"
},
  "geometry": {"coordinates":[-77.097777,39.145858],"type":"Point"}
}