{
  "type": "Feature",
  "properties": {
    "addr:full":"100 Gibbs St Unit H Rockville MD 20850",
    "addr:housenumber":"100",
    "addr:postcode":"20850",
    "addr:street":"Gibbs St Unit H",
    "iso:country":"US",
    "sg:address":"100 Gibbs St Unit H",
    "sg:city":"Rockville",
    "sg:classifiers":[
        {
            "category":"Personal",
            "subcategory":"Nail Salon",
            "type":"Services"
        }
    ],
    "sg:phone":"+1 301 838 8599",
    "sg:postcode":"20850",
    "sg:province":"MD",
    "wof:name":"Acqua Nails Inc",
    "wof:placetype":"venue"
},
  "geometry": {"coordinates":[-77.151917,39.085018],"type":"Point"}
}