{
  "type": "Feature",
  "properties": {
    "addr:full":"206 E Churchville Rd Bel Air MD 21014",
    "addr:housenumber":"206",
    "addr:postcode":"21014",
    "addr:street":"E Churchville Rd",
    "iso:country":"US",
    "sg:address":"206 E Churchville Rd",
    "sg:city":"Bel Air",
    "sg:classifiers":[
        {
            "category":"Professional",
            "subcategory":"Accounting & Tax Preparation",
            "type":"Services"
        }
    ],
    "sg:phone":"+1 410 893 9706",
    "sg:postcode":"21014",
    "sg:province":"MD",
    "sg:tags":[
        "payroll"
    ],
    "sg:website":"www.accupayonline.com",
    "wof:name":"Accu-Pay Inc",
    "wof:placetype":"venue"
},
  "geometry": {"coordinates":[-76.34281300000001,39.537277],"type":"Point"}
}