{
  "type": "Feature",
  "properties": {
    "addr:full":"3801 Hamilton St Hyattsville MD 20781",
    "addr:housenumber":"3801",
    "addr:postcode":"20781",
    "addr:street":"Hamilton St",
    "iso:country":"US",
    "sg:address":"3801 Hamilton St",
    "sg:city":"Hyattsville",
    "sg:classifiers":[
        {
            "category":"Retail",
            "subcategory":"Laundry & Dry Cleaning",
            "type":"Services"
        }
    ],
    "sg:phone":"+1 301 779 3657",
    "sg:postcode":"20781",
    "sg:province":"MD",
    "wof:name":"Mc Wash Laundromat",
    "wof:placetype":"venue"
},
  "geometry": {"coordinates":[-76.953878,38.953063],"type":"Point"}
}