{
  "type": "Feature",
  "properties": {
    "iso:country":"US",
    "sg:address":"8499 Lucerne Rd",
    "sg:city":"Randallstown",
    "sg:classifiers":[
        {
            "category":"Building & Trades",
            "subcategory":"Construction",
            "type":"Services"
        }
    ],
    "sg:phone":"+1 301 570 6640",
    "sg:postcode":"21133",
    "sg:province":"MD",
    "sg:tags":[
        "home",
        "builder"
    ],
    "wof:name":"Portrait Homes",
    "wof:placetype":"venue"
},
  "geometry": {"coordinates":[-76.77251699999999,39.372111],"type":"Point"}
}