{
  "type": "Feature",
  "properties": {
    "addr:full":"629 Main St Laurel MD 20707",
    "addr:housenumber":"629",
    "addr:postcode":"20707",
    "addr:street":"Main St",
    "iso:country":"US",
    "sg:address":"629 Main St",
    "sg:city":"Laurel",
    "sg:classifiers":[
        {
            "category":"Health Services",
            "subcategory":"Chiropractor",
            "type":"Services"
        }
    ],
    "sg:phone":"+1 301 776 8666",
    "sg:postcode":"20707",
    "sg:province":"MD",
    "wof:name":"Back Pain & Headache Centers Llc",
    "wof:placetype":"venue"
},
  "geometry": {"coordinates":[-76.854401,39.1087],"type":"Point"}
}