{
  "type": "Feature",
  "properties": {
    "iso:country":"US",
    "sg:address":"6476 Dobbin Center Way",
    "sg:city":"Columbia",
    "sg:classifiers":[
        {
            "category":"Insurance",
            "subcategory":"Health Insurance",
            "type":"Services"
        }
    ],
    "sg:phone":"+1 443 542 9885",
    "sg:postcode":"21045",
    "sg:province":"MD",
    "sg:tags":[
        "market"
    ],
    "sg:website":"www.maxmuscle.com/",
    "wof:name":"Max Muscle Sports Nutrition",
    "wof:placetype":"venue"
},
  "geometry": {"coordinates":[-76.821601,39.197789],"type":"Point"}
}