{
  "type": "Feature",
  "properties": {
    "addr:full":"2033 Liberty Rd Eldersburg MD 21784",
    "addr:housenumber":"2033",
    "addr:postcode":"21784",
    "addr:street":"Liberty Rd",
    "iso:country":"US",
    "sg:address":"2033 Liberty Rd",
    "sg:city":"Eldersburg",
    "sg:classifiers":[
        {
            "category":"Food & Beverages",
            "subcategory":"Groceries & Convenience Stores",
            "type":"Retail Goods"
        }
    ],
    "sg:phone":"+1 410 781 6240",
    "sg:postcode":"21784",
    "sg:province":"MD",
    "wof:name":"7-Eleven",
    "wof:placetype":"venue"
},
  "geometry": {"coordinates":[-76.924325,39.396883],"type":"Point"}
}