{
  "type": "Feature",
  "properties": {
    "addr:full":"9021 Legion Rd Denton MD 21629",
    "addr:housenumber":"9021",
    "addr:postcode":"21629",
    "addr:street":"Legion Rd",
    "iso:country":"US",
    "sg:address":"9021 Legion Rd",
    "sg:city":"Denton",
    "sg:classifiers":[
        {
            "category":"Farming",
            "subcategory":"Farm",
            "type":"Manufacturing & Wholesale Goods"
        }
    ],
    "sg:phone":"+1 410 479 0594",
    "sg:postcode":"21629",
    "sg:province":"MD",
    "sg:tags":[
        "crop",
        "general"
    ],
    "wof:name":"Crosshaven Farm",
    "wof:placetype":"venue"
},
  "geometry": {"coordinates":[-75.799699,38.85651],"type":"Point"}
}