{
  "type": "Feature",
  "properties": {
    "addr:full":"108 Cranbrook Rd Cockeysville MD 21030",
    "addr:housenumber":"108",
    "addr:postcode":"21030",
    "addr:street":"Cranbrook Rd",
    "iso:country":"US",
    "sg:address":"108 Cranbrook Rd",
    "sg:city":"Cockeysville",
    "sg:classifiers":[
        {
            "category":"Retail",
            "subcategory":"Laundry & Dry Cleaning",
            "type":"Services"
        }
    ],
    "sg:phone":"+1 410 683 8440",
    "sg:postcode":"21030",
    "sg:province":"MD",
    "wof:name":"Eddie's Cleaners",
    "wof:placetype":"venue"
},
  "geometry": {"coordinates":[-76.63412,39.464412],"type":"Point"}
}