{
  "type": "Feature",
  "properties": {
    "iso:country":"US",
    "sg:address":"4428 Park Heights Ave",
    "sg:city":"Baltimore",
    "sg:classifiers":[
        {
            "category":"Restaurant",
            "type":"Food & Drink"
        }
    ],
    "sg:phone":"+1 410 367 5283",
    "sg:postcode":"21215",
    "sg:province":"MD",
    "sg:tags":[
        "deli",
        "delicatessen"
    ],
    "wof:name":"Duke & Lou's Delicatessen",
    "wof:placetype":"venue"
},
  "geometry": {"coordinates":[-76.667198,39.341],"type":"Point"}
}