{
  "type": "Feature",
  "properties": {
    "iso:country":"US",
    "sg:address":"13025 11th St",
    "sg:city":"Bowie",
    "sg:classifiers":[
        {
            "category":"Retail",
            "subcategory":"Auto Repair",
            "type":"Services"
        }
    ],
    "sg:phone":"+1 301 262 9200",
    "sg:postcode":"20715",
    "sg:province":"MD",
    "sg:tags":[
        "transmission"
    ],
    "wof:name":"Bowie Transmission Svc",
    "wof:placetype":"venue"
},
  "geometry": {"coordinates":[-76.77892799999999,39.006526],"type":"Point"}
}