{
  "type": "Feature",
  "properties": {
    "iso:country":"US",
    "sg:address":"859 Spriggs Ct",
    "sg:city":"Arnold",
    "sg:classifiers":[
        {
            "category":"Building & Trades",
            "subcategory":"Construction",
            "type":"Services"
        }
    ],
    "sg:phone":"+1 410 975 9325",
    "sg:postcode":"21012",
    "sg:province":"MD",
    "sg:tags":[
        "home",
        "improvement"
    ],
    "wof:name":"Veterans Home Svc",
    "wof:placetype":"venue"
},
  "geometry": {"coordinates":[-76.50064,39.064061],"type":"Point"}
}