{
  "type": "Feature",
  "properties": {
    "addr:full":"12904 Buccaneer Rd Silver Spring MD 20904",
    "addr:housenumber":"12904",
    "addr:postcode":"20904",
    "addr:street":"Buccaneer Rd",
    "iso:country":"US",
    "sg:address":"12904 Buccaneer Rd",
    "sg:city":"Silver Spring",
    "sg:classifiers":[
        {
            "category":"Professional",
            "subcategory":"Computer Services",
            "type":"Services"
        }
    ],
    "sg:phone":"+1 301 384 1998",
    "sg:postcode":"20904",
    "sg:province":"MD",
    "sg:tags":[
        "related"
    ],
    "wof:name":"Computer Analysts Ltd",
    "wof:placetype":"venue"
},
  "geometry": {"coordinates":[-76.995406,39.06885],"type":"Point"}
}