{
  "type": "Feature",
  "properties": {
    "iso:country":"US",
    "sg:address":"4701 Queensbury Rd",
    "sg:city":"Riverdale",
    "sg:classifiers":[
        {
            "category":"Shopping",
            "subcategory":"Used Merchandise",
            "type":"Retail Goods"
        }
    ],
    "sg:phone":"+1 301 277 8141",
    "sg:postcode":"20737",
    "sg:province":"MD",
    "sg:tags":[
        "book",
        "rare",
        "dealer"
    ],
    "wof:name":"Riverdale Bookshop",
    "wof:placetype":"venue"
},
  "geometry": {"coordinates":[-76.934209,38.962478],"type":"Point"}
}