{
  "type": "Feature",
  "properties": {
    "addr:full":"3838 Falls Rd Baltimore MD 21211",
    "addr:housenumber":"3838",
    "addr:postcode":"21211",
    "addr:street":"Falls Rd",
    "iso:country":"US",
    "sg:address":"3838 Falls Rd",
    "sg:city":"Baltimore",
    "sg:classifiers":[
        {
            "category":"Shopping",
            "subcategory":"Photographic Equipment",
            "type":"Retail Goods"
        }
    ],
    "sg:phone":"+1 410 235 6200",
    "sg:postcode":"21211",
    "sg:province":"MD",
    "sg:tags":[
        "photography",
        "manufacturer",
        "supplies-wholesale",
        "store",
        "supply"
    ],
    "sg:website":"www.servicephoto.com",
    "wof:name":"Service Photo Supply",
    "wof:placetype":"venue"
},
  "geometry": {"coordinates":[-76.636032,39.334674],"type":"Point"}
}