{
  "type": "Feature",
  "properties": {
    "addr:full":"4420 Band Hall Hill Rd Westminster MD 21158",
    "addr:postcode":"4420;21158",
    "addr:street":"Hall Hill Rd",
    "iso:country":"US",
    "sg:address":"4420 Band Hall Hill Rd",
    "sg:city":"Westminster",
    "sg:classifiers":[
        {
            "category":"Farming",
            "subcategory":"Farm",
            "type":"Manufacturing & Wholesale Goods"
        }
    ],
    "sg:phone":"+1 410 346 7577",
    "sg:postcode":"21158",
    "sg:province":"MD",
    "sg:tags":[
        "crop",
        "general"
    ],
    "wof:name":"Ray Holland",
    "wof:placetype":"venue"
},
  "geometry": {"coordinates":[-76.96115899999999,39.695367],"type":"Point"}
}