{
  "type": "Feature",
  "properties": {
    "iso:country":"US",
    "sg:address":"1815 B York Rd",
    "sg:city":"Timonium",
    "sg:classifiers":[
        {
            "category":"Restaurant",
            "type":"Food & Drink"
        }
    ],
    "sg:menulink":"http://www.allmenus.com/md/hunt-valley/260893-bruce-lee-chinese-restaurant/menu/",
    "sg:phone":"+1 410 252 8866",
    "sg:postcode":"21093",
    "sg:province":"MD",
    "sg:tags":[
        "asian",
        "chinese"
    ],
    "wof:name":"Bruce Lee Chinese Restaurant",
    "wof:placetype":"venue"
},
  "geometry": {"coordinates":[-76.621951,39.431596],"type":"Point"}
}