{
  "type": "Feature",
  "properties": {
    "iso:country":"US",
    "sg:address":"8615 Commerce Dr",
    "sg:city":"Easton",
    "sg:classifiers":[
        {
            "category":"Real Estate",
            "subcategory":"Real Estate Services",
            "type":"Services"
        }
    ],
    "sg:phone":"+1 410 822 7676",
    "sg:postcode":"21601",
    "sg:province":"MD",
    "sg:tags":[
        "company",
        "title"
    ],
    "wof:name":"Colonial Title Co",
    "wof:placetype":"venue"
},
  "geometry": {"coordinates":[-76.08086400000001,38.787206],"type":"Point"}
}