{
  "type": "Feature",
  "properties": {
    "iso:country":"US",
    "sg:address":"8161 Teal Dr",
    "sg:city":"Easton",
    "sg:classifiers":[
        {
            "category":"Building & Trades",
            "subcategory":"Pest Control",
            "type":"Services"
        }
    ],
    "sg:phone":"+1 410 822 8777",
    "sg:postcode":"21601",
    "sg:province":"MD",
    "wof:name":"En Garde Inc",
    "wof:placetype":"venue"
},
  "geometry": {"coordinates":[-76.053184,38.772565],"type":"Point"}
}