{
  "type": "Feature",
  "properties": {
    "addr:full":"2 Magnolia Pl Berlin MD 21811",
    "addr:housenumber":"2",
    "addr:postcode":"21811",
    "addr:street":"Magnolia Pl",
    "iso:country":"US",
    "sg:address":"2 Magnolia Pl",
    "sg:city":"Berlin",
    "sg:classifiers":[
        {
            "category":"Building & Trades",
            "subcategory":"Plumbing",
            "type":"Services"
        },
        {
            "category":"Home & Garden",
            "subcategory":"Building Materials",
            "type":"Retail Goods"
        },
        {
            "category":"Building & Trades",
            "subcategory":"Construction",
            "type":"Services"
        }
    ],
    "sg:phone":"+1 410 726 0064",
    "sg:postcode":"21811",
    "sg:province":"MD",
    "sg:tags":[
        "heater",
        "plumber",
        "industrial",
        "repair",
        "bathroom",
        "water",
        "sewer",
        "cleaning",
        "plumbing-drain",
        "remodeling",
        "contractors-commercial"
    ],
    "wof:name":"Lynch Plumbing",
    "wof:placetype":"venue"
},
  "geometry": {"coordinates":[-75.146362,38.367531],"type":"Point"}
}