{
  "type": "Feature",
  "properties": {
    "addr:full":"3193 High Timber Ct Waldorf MD 20602",
    "addr:housenumber":"3193",
    "addr:postcode":"20602",
    "addr:street":"High Timber Ct",
    "iso:country":"US",
    "sg:address":"3193 High Timber Ct",
    "sg:city":"Waldorf",
    "sg:classifiers":[
        {
            "category":"Wholesale",
            "subcategory":"Electrical",
            "type":"Manufacturing & Wholesale Goods"
        }
    ],
    "sg:phone":"+1 301 638 2924",
    "sg:postcode":"20602",
    "sg:province":"MD",
    "sg:tags":[
        "control",
        "security",
        "system"
    ],
    "wof:name":"Insight Security",
    "wof:placetype":"venue"
},
  "geometry": {"coordinates":[-76.89510900000001,38.609325],"type":"Point"}
}