{
  "type": "Feature",
  "properties": {
    "addr:full":"5 N Main St Bel Air MD 21014",
    "addr:housenumber":"5",
    "addr:postcode":"21014",
    "addr:street":"N Main St",
    "iso:country":"US",
    "sg:address":"5 N Main St",
    "sg:city":"Bel Air",
    "sg:classifiers":[
        {
            "category":"Government",
            "subcategory":"Office",
            "type":"Public Place"
        },
        {
            "category":"Social Services",
            "subcategory":"Job Training",
            "type":"Services"
        }
    ],
    "sg:phone":"+1 410 638 3076",
    "sg:postcode":"21014",
    "sg:province":"MD",
    "sg:tags":[
        "county",
        "program",
        "health",
        "rehabilitation"
    ],
    "wof:name":"Harford County Health Dept",
    "wof:placetype":"venue"
},
  "geometry": {"coordinates":[-76.350692,39.537671],"type":"Point"}
}