{
  "type": "Feature",
  "properties": {
    "addr:full":"2029 E Joppa Rd Parkville MD 21234",
    "addr:housenumber":"2029 e",
    "addr:postcode":"21234",
    "addr:street":"Joppa Rd",
    "iso:country":"US",
    "sg:address":"2029 E Joppa Rd",
    "sg:city":"Parkville",
    "sg:classifiers":[
        {
            "category":"Bars & Pubs",
            "subcategory":"Sports Bar",
            "type":"Food & Drink"
        }
    ],
    "sg:phone":"+1 410 882 5933",
    "sg:postcode":"21234",
    "sg:province":"MD",
    "sg:tags":[
        "hall",
        "pool"
    ],
    "wof:name":"Satyr Hill Cue Club",
    "wof:placetype":"venue"
},
  "geometry": {"coordinates":[-76.542528,39.398585],"type":"Point"}
}