{
  "type": "Feature",
  "properties": {
    "iso:country":"US",
    "sg:address":"1814 Severn Rd",
    "sg:city":"Severn",
    "sg:classifiers":[
        {
            "category":"Building & Trades",
            "subcategory":"Construction",
            "type":"Services"
        }
    ],
    "sg:phone":"+1 410 551 4037",
    "sg:postcode":"21144",
    "sg:province":"MD",
    "sg:tags":[
        "house"
    ],
    "wof:name":"Bennanzar Construction",
    "wof:placetype":"venue"
},
  "geometry": {"coordinates":[-76.72568800000001,39.140943],"type":"Point"}
}