{
  "type": "Feature",
  "properties": {
    "addr:full":"202 W Main St Elkton MD 21921",
    "addr:housenumber":"202",
    "addr:postcode":"21921",
    "addr:street":"W Main St",
    "iso:country":"US",
    "sg:address":"202 W Main St",
    "sg:city":"Elkton",
    "sg:classifiers":[
        {
            "category":"Home & Garden",
            "subcategory":"Hardware",
            "type":"Retail Goods"
        }
    ],
    "sg:phone":"+1 410 398 1900",
    "sg:postcode":"21921",
    "sg:province":"MD",
    "sg:website":"www.amerhome.doitbest.com",
    "wof:name":"American Home & Hardware",
    "wof:placetype":"venue"
},
  "geometry": {"coordinates":[-75.83309800000001,39.606504],"type":"Point"}
}