{
  "type": "Feature",
  "properties": {
    "addr:full":"52 N Main St Bel Air MD 21014",
    "addr:housenumber":"52",
    "addr:postcode":"21014",
    "addr:street":"N Main St",
    "iso:country":"US",
    "sg:address":"52 N Main St",
    "sg:city":"Bel Air",
    "sg:classifiers":[
        {
            "category":"Shopping",
            "subcategory":"Clothing, Apparel, & Fashions",
            "type":"Retail Goods"
        }
    ],
    "sg:phone":"+1 410 420 9784",
    "sg:postcode":"21014",
    "sg:province":"MD",
    "sg:tags":[
        "item",
        "boutique"
    ],
    "wof:name":"Tiger Lily",
    "wof:placetype":"venue"
},
  "geometry": {"coordinates":[-76.35019699999999,39.537105],"type":"Point"}
}