{
  "type": "Feature",
  "properties": {
    "addr:full":"5272 River Rd Ste 630 Bethesda MD 20816",
    "addr:housenumber":"5272",
    "addr:postcode":"20816",
    "addr:street":"River Rd Ste 630",
    "iso:country":"US",
    "sg:address":"5272 River Rd Ste 630",
    "sg:city":"Bethesda",
    "sg:classifiers":[
        {
            "category":"Health Services",
            "subcategory":"Hospital",
            "type":"Services"
        }
    ],
    "sg:phone":"+1 301 718 6515",
    "sg:postcode":"20816",
    "sg:province":"MD",
    "wof:name":"American College Of Radiation Oncology",
    "wof:placetype":"venue"
},
  "geometry": {"coordinates":[-77.105277,38.96584],"type":"Point"}
}