{
  "type": "Feature",
  "properties": {
    "addr:full":"2800 University Blvd W Silver Spring MD 20902",
    "addr:housenumber":"2800",
    "addr:postcode":"20902",
    "addr:street":"University Blvd W",
    "iso:country":"US",
    "sg:address":"2800 University Blvd W",
    "sg:city":"Silver Spring",
    "sg:classifiers":[
        {
            "category":"Coffee & Tea",
            "type":"Food & Drink"
        }
    ],
    "sg:menulink":"http://www.allmenus.com/md/silver-spring/119112-starbucks-coffee/menu/",
    "sg:phone":"+1 301 933 9093",
    "sg:postcode":"20902",
    "sg:province":"MD",
    "sg:tags":[
        "american"
    ],
    "wof:name":"Starbucks Coffee",
    "wof:placetype":"venue"
},
  "geometry": {"coordinates":[-77.057,39.039038],"type":"Point"}
}