{
  "type": "Feature",
  "properties": {
    "addr:full":"5806 N Charles St Baltimore MD 21210",
    "addr:housenumber":"5806",
    "addr:postcode":"21210",
    "addr:street":"N Charles St",
    "iso:country":"US",
    "sg:address":"5806 N Charles St",
    "sg:city":"Baltimore",
    "sg:classifiers":[
        {
            "category":"Education",
            "subcategory":"Special Training",
            "type":"Public Place"
        }
    ],
    "sg:phone":"+1 301 379 3986",
    "sg:postcode":"21210",
    "sg:province":"MD",
    "sg:tags":[
        "center"
    ],
    "wof:name":"Compass Learning",
    "wof:placetype":"venue"
},
  "geometry": {"coordinates":[-76.625839,39.369335],"type":"Point"}
}