{
  "type": "Feature",
  "properties": {
    "addr:full":"1124 South Charles Street Baltimore MD 21230",
    "addr:housenumber":"1124",
    "addr:postcode":"21230",
    "addr:street":"South Charles Street",
    "iso:country":"US",
    "sg:address":"1124 South Charles Street",
    "sg:city":"Baltimore",
    "sg:classifiers":[
        {
            "category":"Personal",
            "subcategory":"Beauty Salon",
            "type":"Services"
        }
    ],
    "sg:phone":"+1 443 600 4329",
    "sg:postcode":"21230",
    "sg:province":"MD",
    "sg:tags":[
        "spa"
    ],
    "sg:website":"federalhillmassage.com",
    "wof:name":"Shiatsu Jen @ Federal Hill Massage and Wellness",
    "wof:placetype":"venue"
},
  "geometry": {"coordinates":[-76.614442,39.276135],"type":"Point"}
}