{
  "type": "Feature",
  "properties": {
    "iso:country":"US",
    "sg:address":"10516 Vista Gardens Dr",
    "sg:city":"Bowie",
    "sg:classifiers":[
        {
            "category":"Real Estate",
            "subcategory":"Real Estate Operator",
            "type":"Services"
        }
    ],
    "sg:phone":"+1 301 577 6356",
    "sg:postcode":"20720",
    "sg:province":"MD",
    "sg:tags":[
        "apartment"
    ],
    "wof:name":"The Frugal Investor",
    "wof:placetype":"venue"
},
  "geometry": {"coordinates":[-76.824642,38.950565],"type":"Point"}
}