{
  "type": "Feature",
  "properties": {
    "iso:country":"US",
    "sg:address":"2200 Edmondson Ave",
    "sg:city":"Baltimore",
    "sg:classifiers":[
        {
            "category":"Retail",
            "subcategory":"Self-service Laundry",
            "type":"Services"
        }
    ],
    "sg:phone":"+1 410 566 5370",
    "sg:postcode":"21223",
    "sg:province":"MD",
    "wof:name":"Spincycle Coin Laundry",
    "wof:placetype":"venue"
},
  "geometry": {"coordinates":[-76.653285,39.294838],"type":"Point"}
}