{
  "type": "Feature",
  "properties": {
    "addr:full":"400 Maloney Rd Elkton MD 21921",
    "addr:housenumber":"400",
    "addr:postcode":"21921",
    "addr:street":"Maloney Rd",
    "iso:country":"US",
    "sg:address":"400 Maloney Rd",
    "sg:city":"Elkton",
    "sg:classifiers":[
        {
            "category":"Wholesale",
            "subcategory":"Beer",
            "type":"Manufacturing & Wholesale Goods"
        }
    ],
    "sg:phone":"+1 410 398 2770",
    "sg:postcode":"21921",
    "sg:province":"MD",
    "sg:tags":[
        "distributor",
        "ale"
    ],
    "wof:name":"Sentman Distributors Inc",
    "wof:placetype":"venue"
},
  "geometry": {"coordinates":[-75.801185,39.600686],"type":"Point"}
}