{
  "type": "Feature",
  "properties": {
    "addr:full":"9900 Georgia Ave Silver Spring MD 20902",
    "addr:housenumber":"9900",
    "addr:postcode":"20902",
    "addr:street":"Georgia Ave",
    "iso:country":"US",
    "sg:address":"9900 Georgia Ave",
    "sg:city":"Silver Spring",
    "sg:classifiers":[
        {
            "category":"Manufacturing",
            "subcategory":"Printing",
            "type":"Manufacturing & Wholesale Goods"
        }
    ],
    "sg:phone":"+1 301 946 0900",
    "sg:postcode":"20902",
    "sg:province":"MD",
    "sg:tags":[
        "broker"
    ],
    "sg:website":"www.psa-byergroup.com",
    "wof:name":"Printing Service Assoc Inc",
    "wof:placetype":"venue"
},
  "geometry": {"coordinates":[-77.043678,39.018383],"type":"Point"}
}