{
  "type": "Feature",
  "properties": {
    "iso:country":"US",
    "sg:address":"2111 Crain Hwy",
    "sg:city":"Waldorf",
    "sg:classifiers":[
        {
            "category":"Restaurant",
            "type":"Food & Drink"
        },
        {
            "category":"Food & Beverages",
            "subcategory":"Meat & Fish",
            "type":"Retail Goods"
        }
    ],
    "sg:phone":"+1 301 885 0397",
    "sg:postcode":"20601",
    "sg:province":"MD",
    "sg:tags":[
        "seafood",
        "seafood-wholesale",
        "market"
    ],
    "wof:name":"The Fat Crab Seafood Shoppe",
    "wof:placetype":"venue"
},
  "geometry": {"coordinates":[-76.87944,38.653519],"type":"Point"}
}