{
  "type": "Feature",
  "properties": {
    "iso:country":"US",
    "sg:address":"5710 Newbury St",
    "sg:city":"Baltimore",
    "sg:classifiers":[
        {
            "category":"Personal",
            "subcategory":"Massage",
            "type":"Services"
        }
    ],
    "sg:phone":"+1 410 542 9100",
    "sg:postcode":"21209",
    "sg:province":"MD",
    "sg:tags":[
        "therapist"
    ],
    "wof:name":"Mt Washington Massage & Asian",
    "wof:placetype":"venue"
},
  "geometry": {"coordinates":[-76.652123,39.367447],"type":"Point"}
}