{
  "type": "Feature",
  "properties": {
    "addr:full":"2 Foxfield Ct Reisterstown MD 21136",
    "addr:housenumber":"2",
    "addr:postcode":"21136",
    "addr:street":"Foxfield Ct",
    "iso:country":"US",
    "sg:address":"2 Foxfield Ct",
    "sg:city":"Reisterstown",
    "sg:classifiers":[
        {
            "category":"Local Transit",
            "type":"Transportation"
        },
        {
            "category":"Retail",
            "subcategory":"Auto Rental",
            "type":"Services"
        }
    ],
    "sg:phone":"+1 410 833 1060",
    "sg:postcode":"21136",
    "sg:province":"MD",
    "sg:tags":[
        "passenger",
        "general",
        "limousine",
        "car",
        "repair"
    ],
    "wof:name":"American Sedan Service Inc",
    "wof:placetype":"venue"
},
  "geometry": {"coordinates":[-76.867324,39.435361],"type":"Point"}
}