{
  "type": "Feature",
  "properties": {
    "iso:country":"US",
    "sg:address":"4431 23rd Pkwy",
    "sg:city":"Temple Hills",
    "sg:classifiers":[
        {
            "category":"Real Estate",
            "subcategory":"Real Estate Operator",
            "type":"Services"
        }
    ],
    "sg:phone":"+1 301 894 1777",
    "sg:postcode":"20748",
    "sg:province":"MD",
    "sg:tags":[
        "apartment"
    ],
    "sg:website":"www.raleighcourtapartments.com",
    "wof:name":"Raleigh Court Apartments",
    "wof:placetype":"venue"
},
  "geometry": {"coordinates":[-76.956703,38.829601],"type":"Point"}
}