{
  "type": "Feature",
  "properties": {
    "addr:full":"9400 Surratts Rd Cheltenham MD 20623",
    "addr:postcode":"9400;20623",
    "addr:street":"Surratts Rd",
    "iso:country":"US",
    "sg:address":"9400 Surratts Rd",
    "sg:city":"Cheltenham",
    "sg:classifiers":[
        {
            "category":"Health Services",
            "subcategory":"Clinic",
            "type":"Services"
        }
    ],
    "sg:phone":"+1 301 372 1800",
    "sg:postcode":"20623",
    "sg:province":"MD",
    "sg:tags":[
        "psychiatric"
    ],
    "sg:website":"http://www.pgcts.org",
    "wof:name":"RICA Southern Maryland",
    "wof:placetype":"venue"
},
  "geometry": {"coordinates":[-76.843423,38.734127],"type":"Point"}
}