{
  "type": "Feature",
  "properties": {
    "iso:country":"US",
    "sg:address":"520 Corbin Pkwy",
    "sg:city":"Annapolis",
    "sg:classifiers":[
        {
            "category":"Professional",
            "subcategory":"Management & Consulting",
            "type":"Services"
        }
    ],
    "sg:phone":"+1 410 571 9766",
    "sg:postcode":"21401",
    "sg:province":"MD",
    "sg:tags":[
        "marketing",
        "consultant"
    ],
    "wof:name":"BAYSYS Inc",
    "wof:placetype":"venue"
},
  "geometry": {"coordinates":[-76.56017199999999,39.005883],"type":"Point"}
}