{
  "type": "Feature",
  "properties": {
    "iso:country":"US",
    "sg:address":"27 Meadow Ln",
    "sg:city":"Thurmont",
    "sg:classifiers":[
        {
            "category":"Education",
            "subcategory":"School",
            "type":"Public Place"
        }
    ],
    "sg:phone":"+1 301 271 7269",
    "sg:postcode":"21788",
    "sg:province":"MD",
    "wof:name":"Maryland Music Educators Assn",
    "wof:placetype":"venue"
},
  "geometry": {"coordinates":[-77.400706,39.619092],"type":"Point"}
}