{
  "type": "Feature",
  "properties": {
    "addr:full":"1806 Virginia Ave Annapolis MD 21401",
    "addr:housenumber":"1806",
    "addr:postcode":"21401",
    "addr:street":"Virginia Ave",
    "iso:country":"US",
    "sg:address":"1806 Virginia Ave",
    "sg:city":"Annapolis",
    "sg:classifiers":[
        {
            "category":"Building & Trades",
            "subcategory":"Construction",
            "type":"Services"
        }
    ],
    "sg:phone":"+1 301 858 6767",
    "sg:postcode":"21401",
    "sg:province":"MD",
    "sg:tags":[
        "contractor"
    ],
    "wof:name":"Third Coast Contractors",
    "wof:placetype":"venue"
},
  "geometry": {"coordinates":[-76.52400799999999,38.978276],"type":"Point"}
}