{
  "type": "Feature",
  "properties": {
    "iso:country":"US",
    "sg:address":"8000 Sagramore Rd",
    "sg:city":"Rosedale",
    "sg:classifiers":[
        {
            "category":"Organizations",
            "subcategory":"Professional Association",
            "type":"Services"
        }
    ],
    "sg:phone":"+1 410 866 5600",
    "sg:postcode":"21237",
    "sg:province":"MD",
    "wof:name":"National Guard Assn Of MD",
    "wof:placetype":"venue"
},
  "geometry": {"coordinates":[-76.516694,39.327099],"type":"Point"}
}