{
  "type": "Feature",
  "properties": {
    "addr:full":"916 Eldridge Dr Hagerstown MD 21740",
    "addr:housenumber":"916",
    "addr:postcode":"21740",
    "addr:street":"Eldridge Dr",
    "iso:country":"US",
    "sg:address":"916 Eldridge Dr",
    "sg:city":"Hagerstown",
    "sg:classifiers":[
        {
            "category":"Professional",
            "type":"Services"
        }
    ],
    "sg:phone":"+1 301 416 7212",
    "sg:postcode":"21740",
    "sg:province":"MD",
    "sg:tags":[
        "establishment"
    ],
    "wof:name":"Lanier World Wide",
    "wof:placetype":"venue"
},
  "geometry": {"coordinates":[-77.708195,39.627534],"type":"Point"}
}