{
  "type": "Feature",
  "properties": {
    "iso:country":"US",
    "sg:address":"414 Hungerford Dr",
    "sg:city":"Rockville",
    "sg:classifiers":[
        {
            "category":"Health Services",
            "subcategory":"Health Practitioner",
            "type":"Services"
        },
        {
            "category":"Communications",
            "type":"Services"
        }
    ],
    "sg:phone":"+1 301 309 1291",
    "sg:postcode":"20850",
    "sg:province":"MD",
    "sg:tags":[
        "pathologist",
        "speech-language",
        "myofunctional",
        "therapy"
    ],
    "wof:name":"Katherine J Fleming",
    "wof:placetype":"venue"
},
  "geometry": {"coordinates":[-77.150648,39.087997],"type":"Point"}
}