{
  "type": "Feature",
  "properties": {
    "iso:country":"US",
    "sg:address":"222 Washington Heights Med Ctr Med",
    "sg:city":"Westminster",
    "sg:phone":"+1 410 876 1918",
    "sg:postcode":"21157",
    "sg:province":"MD",
    "sg:website":"http://www.questdiagnostics.com",
    "wof:name":"Quest Diagnostics",
    "wof:placetype":"venue"
},
  "geometry": {"coordinates":[-76.986419,39.56327],"type":"Point"}
}