{
  "type": "Feature",
  "properties": {
    "iso:country":"US",
    "sg:address":"313 E Potomac St",
    "sg:city":"Williamsport",
    "sg:classifiers":[
        {
            "category":"Restaurant",
            "type":"Food & Drink"
        }
    ],
    "sg:menulink":"http://www.allmenus.com/md/williamsport/215761-mcdonalds/menu/",
    "sg:postcode":"21795",
    "sg:province":"MD",
    "sg:tags":[
        "burger",
        "american"
    ],
    "wof:name":"McDonald's",
    "wof:placetype":"venue"
},
  "geometry": {"coordinates":[-77.809755,39.603504],"type":"Point"}
}