{
  "type": "Feature",
  "properties": {
    "iso:country":"US",
    "sg:address":"4740 Chevy Chase Dr Ste 200",
    "sg:city":"Chevy Chase",
    "sg:classifiers":[
        {
            "category":"Arena",
            "subcategory":"Sports Club",
            "type":"Entertainment"
        }
    ],
    "sg:phone":"+1 301 654 0880",
    "sg:postcode":"20815",
    "sg:province":"MD",
    "sg:tags":[
        "martial art"
    ],
    "wof:name":"Efc Black Belt School",
    "wof:placetype":"venue"
},
  "geometry": {"coordinates":[-77.092697,38.976799],"type":"Point"}
}