{
  "type": "Feature",
  "properties": {
    "iso:country":"US",
    "sg:address":"31664 Old Ocean City Rd",
    "sg:city":"Salisbury",
    "sg:classifiers":[
        {
            "category":"Health Services",
            "subcategory":"Doctor",
            "type":"Services"
        }
    ],
    "sg:phone":"+1 410 334 3805",
    "sg:postcode":"21804",
    "sg:province":"MD",
    "sg:tags":[
        "physician",
        "surgeon"
    ],
    "wof:name":"Joan Smith DO",
    "wof:placetype":"venue"
},
  "geometry": {"coordinates":[-75.515115,38.380613],"type":"Point"}
}