{
  "type": "Feature",
  "properties": {
    "addr:full":"11820 Danville Dr Rockville MD 20852",
    "addr:housenumber":"11820",
    "addr:postcode":"20852",
    "addr:street":"Danville Dr",
    "iso:country":"US",
    "sg:address":"11820 Danville Dr",
    "sg:city":"Rockville",
    "sg:classifiers":[
        {
            "category":"Professional",
            "type":"Services"
        }
    ],
    "sg:phone":"+1 301 770 1135",
    "sg:postcode":"20852",
    "sg:province":"MD",
    "sg:tags":[
        "establishment"
    ],
    "wof:name":"Sellica Corp",
    "wof:placetype":"venue"
},
  "geometry": {"coordinates":[-77.130129,39.05018],"type":"Point"}
}