{
  "type": "Feature",
  "properties": {
    "iso:country":"US",
    "sg:address":"7100 Oxon Hill Rd",
    "sg:city":"Oxon Hill",
    "sg:classifiers":[
        {
            "category":"Professional",
            "subcategory":"Management & Consulting",
            "type":"Services"
        }
    ],
    "sg:phone":"+1 301 839 8788",
    "sg:postcode":"20745",
    "sg:province":"MD",
    "wof:name":"Qvinta Inc",
    "wof:placetype":"venue"
},
  "geometry": {"coordinates":[-76.999154,38.801542],"type":"Point"}
}