{
  "type": "Feature",
  "properties": {
    "addr:full":"501 E Pratt St Baltimore MD 21202",
    "addr:housenumber":"501",
    "addr:postcode":"21202",
    "addr:street":"E Pratt St",
    "iso:country":"US",
    "sg:address":"501 E Pratt St",
    "sg:city":"Baltimore",
    "sg:classifiers":[
        {
            "category":"Ice Cream",
            "type":"Food & Drink"
        }
    ],
    "sg:menulink":"http://www.allmenus.com/md/baltimore/227964-dippin-dots/menu/",
    "sg:postcode":"21202",
    "sg:province":"MD",
    "sg:tags":[
        "american"
    ],
    "wof:name":"Dippin' Dots",
    "wof:placetype":"venue"
},
  "geometry": {"coordinates":[-76.60865200000001,39.286636],"type":"Point"}
}