{
  "type": "Feature",
  "properties": {
    "iso:country":"US",
    "sg:address":"52 Broadway",
    "sg:city":"Hagerstown",
    "sg:classifiers":[
        {
            "category":"Professional",
            "subcategory":"Art Services",
            "type":"Services"
        }
    ],
    "sg:phone":"+1 301 739 7250",
    "sg:postcode":"21740",
    "sg:province":"MD",
    "sg:tags":[
        "photo",
        "photography",
        "commercial",
        "studio",
        "portrait"
    ],
    "wof:name":"Youngblood Studios",
    "wof:placetype":"venue"
},
  "geometry": {"coordinates":[-77.71335999999999,39.647486],"type":"Point"}
}