{
  "type": "Feature",
  "properties": {
    "addr:full":"11825 Ramble Dr Owings MD 20736",
    "addr:housenumber":"11825",
    "addr:postcode":"20736",
    "addr:street":"Ramble Dr",
    "iso:country":"US",
    "sg:address":"11825 Ramble Dr",
    "sg:city":"Owings",
    "sg:classifiers":[
        {
            "category":"Government",
            "subcategory":"Office",
            "type":"Public Place"
        }
    ],
    "sg:phone":"+1 301 855 8754",
    "sg:postcode":"20736",
    "sg:province":"MD",
    "sg:tags":[
        "consultant",
        "grant"
    ],
    "wof:name":"Catherine S Deluca",
    "wof:placetype":"venue"
},
  "geometry": {"coordinates":[-76.625444,38.744347],"type":"Point"}
}