{
  "type": "Feature",
  "properties": {
    "addr:full":"11408 Cronridge Dr Owings Mills MD 21117",
    "addr:housenumber":"11408",
    "addr:postcode":"21117",
    "addr:street":"Cronridge Dr",
    "iso:country":"US",
    "sg:address":"11408 Cronridge Dr",
    "sg:city":"Owings Mills",
    "sg:classifiers":[
        {
            "category":"Wholesale",
            "subcategory":"Sporting Goods",
            "type":"Manufacturing & Wholesale Goods"
        }
    ],
    "sg:phone":"+1 410 363 9919",
    "sg:postcode":"21117",
    "sg:province":"MD",
    "sg:tags":[
        "equipment",
        "pool",
        "swimming"
    ],
    "wof:name":"Sweetwater Pool & Spa Ctr",
    "wof:placetype":"venue"
},
  "geometry": {"coordinates":[-76.775988,39.440763],"type":"Point"}
}