{
  "type": "Feature",
  "properties": {
    "iso:country":"US",
    "sg:address":"2016 Maryland Ave Ste 2",
    "sg:city":"Baltimore",
    "sg:classifiers":[
        {
            "category":"Coffee & Tea",
            "type":"Food & Drink"
        },
        {
            "category":"Donuts",
            "subcategory":"None",
            "type":"Food & Drink"
        }
    ],
    "sg:phone":"+1 410 244 1830",
    "sg:postcode":"21218",
    "sg:province":"MD",
    "sg:tags":[
        "shop",
        "espresso",
        "restaurant"
    ],
    "sg:website":"http://www.dunkindonuts.com",
    "wof:name":"Dunkin' Donuts",
    "wof:placetype":"venue"
},
  "geometry": {"coordinates":[-76.617982,39.312317],"type":"Point"}
}