{
  "type": "Feature",
  "properties": {
    "addr:full":"7620 York Rd Baltimore MD 21204",
    "addr:housenumber":"7620",
    "addr:postcode":"21204",
    "addr:street":"York Rd",
    "iso:country":"US",
    "sg:address":"7620 York Rd",
    "sg:city":"Baltimore",
    "sg:classifiers":[
        {
            "category":"Health Services",
            "subcategory":"Hospital",
            "type":"Services"
        }
    ],
    "sg:phone":"+1 410 337 1053",
    "sg:postcode":"21204",
    "sg:province":"MD",
    "wof:name":"Ambulatory Surgery Ctr",
    "wof:placetype":"venue"
},
  "geometry": {"coordinates":[-76.606154,39.387314],"type":"Point"}
}