{
  "type": "Feature",
  "properties": {
    "addr:full":"7709 Fitch Ln Nottingham MD 21236",
    "addr:housenumber":"7709",
    "addr:postcode":"21236",
    "addr:street":"Fitch Ln",
    "iso:country":"US",
    "sg:address":"7709 Fitch Ln",
    "sg:city":"Nottingham",
    "sg:classifiers":[
        {
            "category":"Building & Trades",
            "subcategory":"Construction",
            "type":"Services"
        }
    ],
    "sg:phone":"+1 410 592 2558",
    "sg:postcode":"21236",
    "sg:province":"MD",
    "sg:tags":[
        "general",
        "contractor"
    ],
    "wof:name":"East Coast Contracting Inc",
    "wof:placetype":"venue"
},
  "geometry": {"coordinates":[-76.50743300000001,39.365598],"type":"Point"}
}