{
  "type": "Feature",
  "properties": {
    "iso:country":"US",
    "sg:address":"9891 Brokenland Pkwy",
    "sg:city":"Columbia",
    "sg:classifiers":[
        {
            "category":"Building & Trades",
            "subcategory":"Cleaning & Sanitation",
            "type":"Services"
        }
    ],
    "sg:phone":"+1 410 290 7027",
    "sg:postcode":"21046",
    "sg:province":"MD",
    "sg:tags":[
        "operations",
        "maintenance"
    ],
    "wof:name":"Kentucky Facilities",
    "wof:placetype":"venue"
},
  "geometry": {"coordinates":[-76.848314,39.18192],"type":"Point"}
}