{
  "type": "Feature",
  "properties": {
    "addr:full":"116 Defense Hwy Annapolis MD 21401",
    "addr:housenumber":"116",
    "addr:postcode":"21401",
    "addr:street":"Defense Hwy",
    "iso:country":"US",
    "sg:address":"116 Defense Hwy",
    "sg:city":"Annapolis",
    "sg:classifiers":[
        {
            "category":"Health Services",
            "subcategory":"Health Practitioner",
            "type":"Services"
        }
    ],
    "sg:phone":"+1 410 897 0120",
    "sg:postcode":"21401",
    "sg:province":"MD",
    "sg:tags":[
        "therapist",
        "physical"
    ],
    "wof:name":"Novacare Rehabilitation",
    "wof:placetype":"venue"
},
  "geometry": {"coordinates":[-76.549829,38.985897],"type":"Point"}
}