{
  "type": "Feature",
  "properties": {
    "iso:country":"US",
    "sg:address":"778 Old Crellin Rd",
    "sg:city":"Oakland",
    "sg:classifiers":[
        {
            "category":"Building & Trades",
            "subcategory":"Construction",
            "type":"Services"
        }
    ],
    "sg:phone":"+1 301 334 9536",
    "sg:postcode":"21550",
    "sg:province":"MD",
    "sg:tags":[
        "contractor"
    ],
    "wof:name":"Joe S Little Contracting",
    "wof:placetype":"venue"
},
  "geometry": {"coordinates":[-79.444905,39.377193],"type":"Point"}
}