{
  "type": "Feature",
  "properties": {
    "addr:full":"2023 Penderbrooke Dr Crownsville MD 21032",
    "addr:housenumber":"2023",
    "addr:postcode":"21032",
    "addr:street":"Penderbrooke Dr",
    "iso:country":"US",
    "sg:address":"2023 Penderbrooke Dr",
    "sg:city":"Crownsville",
    "sg:classifiers":[
        {
            "category":"Professional",
            "subcategory":"Management & Consulting",
            "type":"Services"
        }
    ],
    "sg:phone":"+1 410 451 5611",
    "sg:postcode":"21032",
    "sg:province":"MD",
    "wof:name":"Millennium Contrs & Cons LLC",
    "wof:placetype":"venue"
},
  "geometry": {"coordinates":[-76.63390099999999,39.020372],"type":"Point"}
}