{
  "type": "Feature",
  "properties": {
    "iso:country":"US",
    "sg:address":"16404 Elliott Pkwy",
    "sg:city":"Williamsport",
    "sg:classifiers":[
        {
            "category":"Manufacturing",
            "subcategory":"Rubber & Plastics",
            "type":"Manufacturing & Wholesale Goods"
        }
    ],
    "sg:phone":"+1 301 223 6933",
    "sg:postcode":"21795",
    "sg:province":"MD",
    "sg:tags":[
        "product"
    ],
    "sg:website":"www.xerxescorp.com",
    "wof:name":"Xerxes Corp",
    "wof:placetype":"venue"
},
  "geometry": {"coordinates":[-77.796897,39.621368],"type":"Point"}
}