{
  "type": "Feature",
  "properties": {
    "addr:full":"1 Kane St Baltimore MD 21224",
    "addr:housenumber":"1",
    "addr:postcode":"21224",
    "addr:street":"Kane St",
    "iso:country":"US",
    "sg:address":"1 Kane St",
    "sg:city":"Baltimore",
    "sg:classifiers":[
        {
            "category":"Autos & Motor Vehicles",
            "subcategory":"Automobile Sales",
            "type":"Retail Goods"
        },
        {
            "category":"Retail",
            "subcategory":"Auto Repair",
            "type":"Services"
        }
    ],
    "sg:phone":"+1 410 633 9000",
    "sg:postcode":"21224",
    "sg:province":"MD",
    "sg:tags":[
        "body",
        "shop",
        "car"
    ],
    "wof:name":"Penn Pontiac GMC",
    "wof:placetype":"venue"
},
  "geometry": {"coordinates":[-76.530575,39.29581],"type":"Point"}
}