{
  "type": "Feature",
  "properties": {
    "iso:country":"US",
    "sg:address":"11900 Mcmullen Hwy SW",
    "sg:city":"Cumberland",
    "sg:classifiers":[
        {
            "category":"Wholesale",
            "subcategory":"Home Furnishings",
            "type":"Manufacturing & Wholesale Goods"
        }
    ],
    "sg:phone":"+1 301 729 2800",
    "sg:postcode":"21502",
    "sg:province":"MD",
    "sg:tags":[
        "plumbing",
        "supplies-wholesale",
        "part",
        "fixture",
        "manufacturer"
    ],
    "sg:website":"http://www.hisersupplycompany.com",
    "wof:name":"Hiser Supply Company",
    "wof:placetype":"venue"
},
  "geometry": {"coordinates":[-78.800667,39.634226],"type":"Point"}
}