{
  "type": "Feature",
  "properties": {
    "iso:country":"US",
    "sg:address":"9012 Satyr Hill Rd",
    "sg:city":"Parkville",
    "sg:classifiers":[
        {
            "category":"Banks & Credit Unions",
            "subcategory":"Financial Services",
            "type":"Services"
        }
    ],
    "sg:phone":"+1 410 668 6901",
    "sg:postcode":"21234",
    "sg:province":"MD",
    "sg:tags":[
        "program",
        "scholarship"
    ],
    "wof:name":"High School & College Football",
    "wof:placetype":"venue"
},
  "geometry": {"coordinates":[-76.543233,39.406881],"type":"Point"}
}