{
  "type": "Feature",
  "properties": {
    "iso:country":"US",
    "sg:address":"9930 Moyer Rd",
    "sg:city":"Damascus",
    "sg:classifiers":[
        {
            "category":"Education",
            "subcategory":"School",
            "type":"Public Place"
        }
    ],
    "sg:phone":"+1 301 253 7004",
    "sg:postcode":"20872",
    "sg:province":"MD",
    "wof:name":"Clearspring Elementary School",
    "wof:placetype":"venue"
},
  "geometry": {"coordinates":[-77.205047,39.267086],"type":"Point"}
}