{
  "type": "Feature",
  "properties": {
    "addr:full":"2107 Bel Air Rd Fallston MD 21047",
    "addr:housenumber":"2107",
    "addr:postcode":"21047",
    "addr:street":"Bel Air Rd",
    "iso:country":"US",
    "sg:address":"2107 Bel Air Rd",
    "sg:city":"Fallston",
    "sg:classifiers":[
        {
            "category":"Wholesale",
            "subcategory":"Machinery & Supplies",
            "type":"Manufacturing & Wholesale Goods"
        }
    ],
    "sg:phone":"+1 410 877 0070",
    "sg:postcode":"21047",
    "sg:province":"MD",
    "sg:tags":[
        "contractor"
    ],
    "wof:name":"Volvo Rents",
    "wof:placetype":"venue"
},
  "geometry": {"coordinates":[-76.390553,39.495403],"type":"Point"}
}