{
  "type": "Feature",
  "properties": {
    "addr:full":"1317 Reisterstown Rd Pikesville MD 21208",
    "addr:housenumber":"1317",
    "addr:postcode":"21208",
    "addr:street":"Reisterstown Rd",
    "iso:country":"US",
    "sg:address":"1317 Reisterstown Rd",
    "sg:city":"Pikesville",
    "sg:classifiers":[
        {
            "category":"Retail",
            "subcategory":"Auto Repair",
            "type":"Services"
        }
    ],
    "sg:phone":"+1 410 484 7080",
    "sg:postcode":"21208",
    "sg:province":"MD",
    "sg:tags":[
        "repairing",
        "automobile"
    ],
    "wof:name":"C & C Motors",
    "wof:placetype":"venue"
},
  "geometry": {"coordinates":[-76.72427,39.376084],"type":"Point"}
}