{
  "type": "Feature",
  "properties": {
    "addr:full":"10110 Galsworthy Pl Bethesda MD 20817",
    "addr:postcode":"10110;20817",
    "addr:street":"Galsworthy Pl",
    "iso:country":"US",
    "sg:address":"10110 Galsworthy Pl",
    "sg:city":"Bethesda",
    "sg:classifiers":[
        {
            "category":"Professional",
            "type":"Services"
        }
    ],
    "sg:phone":"+1 301 469 0336",
    "sg:postcode":"20817",
    "sg:province":"MD",
    "wof:name":"Michael Schall",
    "wof:placetype":"venue"
},
  "geometry": {"coordinates":[-77.15074,39.021209],"type":"Point"}
}