{
  "type": "Feature",
  "properties": {
    "addr:full":"7204 Greenbank Rd Baltimore MD 21220",
    "addr:housenumber":"7204",
    "addr:postcode":"21220",
    "addr:street":"Greenbank Rd",
    "iso:country":"US",
    "sg:address":"7204 Greenbank Rd",
    "sg:city":"Baltimore",
    "sg:classifiers":[
        {
            "category":"Building & Trades",
            "subcategory":"Construction",
            "type":"Services"
        }
    ],
    "sg:phone":"+1 410 335 5595",
    "sg:postcode":"21220",
    "sg:province":"MD",
    "sg:tags":[
        "general",
        "contractor"
    ],
    "wof:name":"Jordan Brothers Builders",
    "wof:placetype":"venue"
},
  "geometry": {"coordinates":[-76.34664100000001,39.374303],"type":"Point"}
}