{
  "type": "Feature",
  "properties": {
    "addr:full":"2519 Wilkens Ave Baltimore MD 21223",
    "addr:housenumber":"2519",
    "addr:postcode":"21223",
    "addr:street":"Wilkens Ave",
    "iso:country":"US",
    "sg:address":"2519 Wilkens Ave",
    "sg:city":"Baltimore",
    "sg:classifiers":[
        {
            "category":"Transit Center",
            "subcategory":"Freight",
            "type":"Transportation"
        },
        {
            "category":"Freight",
            "type":"Transportation"
        },
        {
            "category":"Local Transit",
            "type":"Transportation"
        }
    ],
    "sg:phone":"+1 410 947 2905",
    "sg:postcode":"21223",
    "sg:province":"MD",
    "sg:tags":[
        "provider",
        "trucking",
        "trucking-motor",
        "broker"
    ],
    "wof:name":"M-Scrap Transportation Svc",
    "wof:placetype":"venue"
},
  "geometry": {"coordinates":[-76.654996,39.279251],"type":"Point"}
}