{
  "type": "Feature",
  "properties": {
    "addr:full":"500 Roslyn Ave Cambridge MD 21613",
    "addr:housenumber":"500",
    "addr:postcode":"21613",
    "addr:street":"Roslyn Ave",
    "iso:country":"US",
    "sg:address":"500 Roslyn Ave",
    "sg:city":"Cambridge",
    "sg:classifiers":[
        {
            "category":"Wholesale",
            "subcategory":"Auto Parts",
            "type":"Manufacturing & Wholesale Goods"
        }
    ],
    "sg:phone":"+1 410 228 7800",
    "sg:postcode":"21613",
    "sg:province":"MD",
    "sg:tags":[
        "automobile",
        "supply"
    ],
    "wof:name":"Parts Wholesale Inc",
    "wof:placetype":"venue"
},
  "geometry": {"coordinates":[-76.06678599999999,38.566913],"type":"Point"}
}