{
  "type": "Feature",
  "properties": {
    "iso:country":"US",
    "sg:address":"529 W Lexington St",
    "sg:city":"Baltimore",
    "sg:classifiers":[
        {
            "category":"Shopping",
            "type":"Retail Goods"
        }
    ],
    "sg:phone":"+1 410 539 2456",
    "sg:postcode":"21201",
    "sg:province":"MD",
    "sg:tags":[
        "candle"
    ],
    "wof:name":"Jerico Candle & Herb Co Inc",
    "wof:placetype":"venue"
},
  "geometry": {"coordinates":[-76.623769,39.291306],"type":"Point"}
}