{
  "type": "Feature",
  "properties": {
    "iso:country":"US",
    "sg:address":"887 Rockville Pike",
    "sg:city":"Rockville",
    "sg:classifiers":[
        {
            "category":"Restaurant",
            "type":"Food & Drink"
        }
    ],
    "sg:phone":"+1 301 294 0553",
    "sg:postcode":"20852",
    "sg:province":"MD",
    "sg:tags":[
        "caterer"
    ],
    "wof:name":"Niwano Hana Japanese Rstrnt",
    "wof:placetype":"venue"
},
  "geometry": {"coordinates":[-77.138896,39.076697],"type":"Point"}
}