{
  "type": "Feature",
  "properties": {
    "iso:country":"US",
    "sg:address":"626 N Market St",
    "sg:city":"Frederick",
    "sg:classifiers":[
        {
            "category":"Personal",
            "subcategory":"Beauty Salon",
            "type":"Services"
        }
    ],
    "sg:phone":"+1 301 682 3988",
    "sg:postcode":"21701",
    "sg:province":"MD",
    "wof:name":"Honey Comb Salon",
    "wof:placetype":"venue"
},
  "geometry": {"coordinates":[-77.40996699999999,39.421738],"type":"Point"}
}