{
  "type": "Feature",
  "properties": {
    "addr:full":"29890 Three Notch Rd Charlotte Hall MD 20622",
    "addr:housenumber":"29890",
    "addr:postcode":"20622",
    "addr:street":"Three Notch Rd",
    "iso:country":"US",
    "sg:address":"29890 Three Notch Rd",
    "sg:city":"Charlotte Hall",
    "sg:classifiers":[
        {
            "category":"Shopping",
            "subcategory":"Used Merchandise",
            "type":"Retail Goods"
        }
    ],
    "sg:phone":"+1 301 884 5400",
    "sg:postcode":"20622",
    "sg:province":"MD",
    "sg:tags":[
        "flea",
        "market"
    ],
    "wof:name":"Second Chance LLC",
    "wof:placetype":"venue"
},
  "geometry": {"coordinates":[-76.77496600000001,38.492776],"type":"Point"}
}