{
  "type": "Feature",
  "properties": {
    "iso:country":"US",
    "sg:address":"593 O'Brien Rd",
    "sg:city":"Swanton",
    "sg:classifiers":[
        {
            "category":"Organizations",
            "subcategory":"Religious Organization",
            "type":"Services"
        }
    ],
    "sg:phone":"+1 301 387 4380",
    "sg:postcode":"21561",
    "sg:province":"MD",
    "sg:tags":[
        "school"
    ],
    "wof:name":"Swanton Mennonite School",
    "wof:placetype":"venue"
},
  "geometry": {"coordinates":[-78.784871,39.645136],"type":"Point"}
}