{
  "type": "Feature",
  "properties": {
    "iso:country":"US",
    "sg:address":"502 Crain Hwy N",
    "sg:city":"Glen Burnie",
    "sg:classifiers":[
        {
            "category":"Autos & Motor Vehicles",
            "subcategory":"Automobile Sales",
            "type":"Retail Goods"
        }
    ],
    "sg:phone":"+1 410 760 3195",
    "sg:postcode":"21061",
    "sg:province":"MD",
    "sg:tags":[
        "car",
        "dealer"
    ],
    "wof:name":"Enterprise Car Sales",
    "wof:placetype":"venue"
},
  "geometry": {"coordinates":[-76.620677,39.172109],"type":"Point"}
}