{
  "type": "Feature",
  "properties": {
    "addr:full":"11734 Rousby Hall Rd Lusby MD 20657",
    "addr:housenumber":"11734",
    "addr:postcode":"20657",
    "addr:street":"Rousby Hall Rd",
    "iso:country":"US",
    "sg:address":"11734 Rousby Hall Rd",
    "sg:city":"Lusby",
    "sg:classifiers":[
        {
            "category":"Retail",
            "subcategory":"Repair Shop",
            "type":"Services"
        },
        {
            "category":"Building & Trades",
            "subcategory":"Construction",
            "type":"Services"
        }
    ],
    "sg:phone":"+1 443 404 5686",
    "sg:postcode":"20657",
    "sg:province":"MD",
    "sg:tags":[
        "interior",
        "reupholstery",
        "design",
        "furniture"
    ],
    "wof:name":"SKD Studios",
    "wof:placetype":"venue"
},
  "geometry": {"coordinates":[-76.43502599999999,38.3654],"type":"Point"}
}