{
  "type": "Feature",
  "properties": {
    "addr:full":"8601 Heathermill Rd Nottingham MD 21236",
    "addr:housenumber":"8601",
    "addr:postcode":"21236",
    "addr:street":"Heathermill Rd",
    "iso:country":"US",
    "sg:address":"8601 Heathermill Rd",
    "sg:city":"Nottingham",
    "sg:classifiers":[
        {
            "category":"Building & Trades",
            "subcategory":"Construction",
            "type":"Services"
        }
    ],
    "sg:phone":"+1 410 256 7171",
    "sg:postcode":"21236",
    "sg:province":"MD",
    "sg:tags":[
        "contractor"
    ],
    "wof:name":"Chesapeake Homes Inc",
    "wof:placetype":"venue"
},
  "geometry": {"coordinates":[-76.474036,39.385037],"type":"Point"}
}