{
  "type": "Feature",
  "properties": {
    "addr:full":"618 Wells St Cambridge MD 21613",
    "addr:housenumber":"618",
    "addr:postcode":"21613",
    "addr:street":"Wells St",
    "iso:country":"US",
    "sg:address":"618 Wells St",
    "sg:city":"Cambridge",
    "sg:classifiers":[
        {
            "category":"Education",
            "subcategory":"Preschool",
            "type":"Public Place"
        }
    ],
    "sg:phone":"+1 410 228 2664",
    "sg:postcode":"21613",
    "sg:province":"MD",
    "sg:tags":[
        "kindergarten"
    ],
    "wof:name":"Teddy Karen's Bear Daycar",
    "wof:placetype":"venue"
},
  "geometry": {"coordinates":[-76.080826,38.565025],"type":"Point"}
}