{
  "type": "Feature",
  "properties": {
    "addr:full":"9 Barclay Ct Rockville MD 20850",
    "addr:housenumber":"9",
    "addr:postcode":"20850",
    "addr:street":"Barclay Ct",
    "iso:country":"US",
    "sg:address":"9 Barclay Ct",
    "sg:city":"Rockville",
    "sg:classifiers":[
        {
            "category":"Building & Trades",
            "subcategory":"Landscaping Services",
            "type":"Services"
        }
    ],
    "sg:phone":"+1 301 252 7205",
    "sg:postcode":"20850",
    "sg:province":"MD",
    "sg:tags":[
        "lawn",
        "maintenance",
        "grounds"
    ],
    "wof:name":"Lawn Master & Landscape Co",
    "wof:placetype":"venue"
},
  "geometry": {"coordinates":[-77.17774799999999,39.08181],"type":"Point"}
}