{
  "type": "Feature",
  "properties": {
    "iso:country":"US",
    "sg:address":"5502 Burling Ct",
    "sg:city":"Bethesda",
    "sg:classifiers":[
        {
            "category":"Professional",
            "subcategory":"Business Services",
            "type":"Services"
        }
    ],
    "sg:phone":"+1 301 951 6374",
    "sg:postcode":"20817",
    "sg:province":"MD",
    "sg:tags":[
        "consultant",
        "coach"
    ],
    "wof:name":"Jlr Pharmaceutical Consulting",
    "wof:placetype":"venue"
},
  "geometry": {"coordinates":[-77.111638,38.979238],"type":"Point"}
}