{
  "type": "Feature",
  "properties": {
    "addr:full":"731 Chessie Crossing Way Woodbine MD 21797",
    "addr:housenumber":"731",
    "addr:postcode":"21797",
    "addr:street":"Chessie Crossing Way",
    "iso:country":"US",
    "sg:address":"731 Chessie Crossing Way",
    "sg:city":"Woodbine",
    "sg:classifiers":[
        {
            "category":"Retail",
            "subcategory":"Animal Services",
            "type":"Services"
        }
    ],
    "sg:phone":"+1 410 442 2461",
    "sg:postcode":"21797",
    "sg:province":"MD",
    "wof:name":"Kim Williams Inc",
    "wof:placetype":"venue"
},
  "geometry": {"coordinates":[-77.054368,39.353184],"type":"Point"}
}