{
  "type": "Feature",
  "properties": {
    "iso:country":"US",
    "sg:address":"2034 Lord Baltimore Dr",
    "sg:city":"Baltimore",
    "sg:classifiers":[
        {
            "category":"Professional",
            "subcategory":"Business Services",
            "type":"Services"
        }
    ],
    "sg:phone":"+1 410 298 8000",
    "sg:postcode":"21244",
    "sg:province":"MD",
    "sg:tags":[
        "messenger"
    ],
    "wof:name":"Mid-Atlantic Messenger Svc",
    "wof:placetype":"venue"
},
  "geometry": {"coordinates":[-76.751997,39.311424],"type":"Point"}
}