{
  "type": "Feature",
  "properties": {
    "addr:full":"2802 Orchard Summit Ct Hyattsville MD 20785",
    "addr:housenumber":"2802",
    "addr:postcode":"20785",
    "addr:street":"Orchard Summit Ct",
    "iso:country":"US",
    "sg:address":"2802 Orchard Summit Ct",
    "sg:city":"Hyattsville",
    "sg:classifiers":[
        {
            "category":"Freight",
            "type":"Transportation"
        }
    ],
    "sg:phone":"+1 301 341 6656",
    "sg:postcode":"20785",
    "sg:province":"MD",
    "sg:tags":[
        "operator",
        "local",
        "trucking"
    ],
    "wof:name":"Earthauler Trucking Inc",
    "wof:placetype":"venue"
},
  "geometry": {"coordinates":[-76.878052,38.925914],"type":"Point"}
}