{
  "type": "Feature",
  "properties": {
    "addr:full":"8815 Columbia 100 Pkwy Columbia MD 21045",
    "addr:housenumber":"8815",
    "addr:postcode":"21045",
    "addr:street":"Columbia 100 Pkwy",
    "iso:country":"US",
    "sg:address":"8815 Columbia 100 Pkwy",
    "sg:city":"Columbia",
    "sg:classifiers":[
        {
            "category":"Professional",
            "subcategory":"Employment Agencies",
            "type":"Services"
        }
    ],
    "sg:phone":"+1 410 884 3800",
    "sg:postcode":"21045",
    "sg:province":"MD",
    "sg:tags":[
        "opportunity"
    ],
    "wof:name":"Premier Placement Inc",
    "wof:placetype":"venue"
},
  "geometry": {"coordinates":[-76.814061,39.22915],"type":"Point"}
}