{
  "type": "Feature",
  "properties": {
    "addr:full":"9317 Livingston Rd Fort Washington MD 20744",
    "addr:housenumber":"9317",
    "addr:postcode":"20744",
    "addr:street":"Livingston Rd",
    "iso:country":"US",
    "sg:address":"9317 Livingston Rd",
    "sg:city":"Fort Washington",
    "sg:classifiers":[
        {
            "category":"Food & Beverages",
            "subcategory":"Groceries & Convenience Stores",
            "type":"Retail Goods"
        }
    ],
    "sg:phone":"+1 301 248 9346",
    "sg:postcode":"20744",
    "sg:province":"MD",
    "wof:name":"Oxen Hill",
    "wof:placetype":"venue"
},
  "geometry": {"coordinates":[-76.995616,38.763094],"type":"Point"}
}