{
  "type": "Feature",
  "properties": {
    "addr:full":"670 Old Mill Rd Millersville MD 21108",
    "addr:housenumber":"670",
    "addr:postcode":"21108",
    "addr:street":"Old Mill Rd",
    "iso:country":"US",
    "sg:address":"670 Old Mill Rd",
    "sg:city":"Millersville",
    "sg:classifiers":[
        {
            "category":"Banks & Credit Unions",
            "subcategory":"Bank",
            "type":"Services"
        }
    ],
    "sg:phone":"+1 410 281 7458",
    "sg:postcode":"21108",
    "sg:province":"MD",
    "wof:name":"Provident Bank",
    "wof:placetype":"venue"
},
  "geometry": {"coordinates":[-76.632322,39.11772],"type":"Point"}
}