{
  "type": "Feature",
  "properties": {
    "iso:country":"US",
    "sg:address":"6934 Pindell School Rd",
    "sg:city":"Fulton",
    "sg:classifiers":[
        {
            "category":"Building & Trades",
            "subcategory":"Construction",
            "type":"Services"
        }
    ],
    "sg:phone":"+1 410 531 6655",
    "sg:postcode":"20759",
    "sg:province":"MD",
    "sg:tags":[
        "contractor"
    ],
    "wof:name":"Aaro Construction Inc",
    "wof:placetype":"venue"
},
  "geometry": {"coordinates":[-76.902648,39.18124],"type":"Point"}
}