{
  "type": "Feature",
  "properties": {
    "iso:country":"US",
    "sg:address":"659 S Salisbury Blvd # 4",
    "sg:city":"Salisbury",
    "sg:classifiers":[
        {
            "category":"Health Services",
            "subcategory":"Clinic",
            "type":"Services"
        },
        {
            "category":"Community Center",
            "type":"Public Place"
        }
    ],
    "sg:phone":"+1 410 543 9111",
    "sg:postcode":"21801",
    "sg:province":"MD",
    "sg:tags":[
        "medical"
    ],
    "wof:name":"Center For Womens Health Of Salisbury",
    "wof:placetype":"venue"
},
  "geometry": {"coordinates":[-75.59967,38.358311],"type":"Point"}
}