{
  "type": "Feature",
  "properties": {
    "iso:country":"US",
    "sg:address":"510 Saybrooke View Dr",
    "sg:city":"Gaithersburg",
    "sg:classifiers":[
        {
            "category":"Building & Trades",
            "subcategory":"Plumbing",
            "type":"Services"
        }
    ],
    "sg:phone":"+1 301 948 6614",
    "sg:postcode":"20877",
    "sg:province":"MD",
    "sg:tags":[
        "contractor"
    ],
    "wof:name":"Joseph Engineering Services",
    "wof:placetype":"venue"
},
  "geometry": {"coordinates":[-77.179158,39.148477],"type":"Point"}
}