{
  "type": "Feature",
  "properties": {
    "iso:country":"US",
    "sg:address":"1225 Eastern Blvd",
    "sg:city":"Essex",
    "sg:phone":"+1 410 391 8350",
    "sg:postcode":"21221",
    "sg:province":"MD",
    "sg:website":"http://www.haircuttery.com/",
    "wof:name":"Hair Cuttery",
    "wof:placetype":"venue"
},
  "geometry": {"coordinates":[-76.46185699999999,39.314554],"type":"Point"}
}