{
  "type": "Feature",
  "properties": {
    "addr:full":"302 Barn View Ct Forest Hill MD 21050",
    "addr:housenumber":"302",
    "addr:postcode":"21050",
    "addr:street":"Barn View Ct",
    "iso:country":"US",
    "sg:address":"302 Barn View Ct",
    "sg:city":"Forest Hill",
    "sg:classifiers":[
        {
            "category":"Retail",
            "subcategory":"Laundry & Dry Cleaning",
            "type":"Services"
        }
    ],
    "sg:phone":"+1 410 420 7901",
    "sg:postcode":"21050",
    "sg:province":"MD",
    "wof:name":"Chesapeake Diaper Co",
    "wof:placetype":"venue"
},
  "geometry": {"coordinates":[-76.36745000000001,39.563437],"type":"Point"}
}