{
  "type": "Feature",
  "properties": {
    "iso:country":"US",
    "sg:address":"9708 Monroe St Ste 102",
    "sg:city":"Cockeysville",
    "sg:classifiers":[
        {
            "category":"Manufacturing",
            "subcategory":"Pet Food",
            "type":"Manufacturing & Wholesale Goods"
        },
        {
            "category":"Food & Beverages",
            "subcategory":"Supermarket",
            "type":"Retail Goods"
        }
    ],
    "sg:phone":"+1 410 667 1600",
    "sg:postcode":"21030",
    "sg:province":"MD",
    "sg:tags":[
        "manufacturer",
        "foods-wholesale",
        "super",
        "store",
        "supply"
    ],
    "sg:website":"http://www.regalpetfoods.com",
    "wof:name":"Regal Pet Foods",
    "wof:placetype":"venue"
},
  "geometry": {"coordinates":[-76.632423,39.457581],"type":"Point"}
}