{
  "type": "Feature",
  "properties": {
    "addr:full":"107 Woodwind Rd Catonsville MD 21228",
    "addr:housenumber":"107",
    "addr:postcode":"21228",
    "addr:street":"Woodwind Rd",
    "iso:country":"US",
    "sg:address":"107 Woodwind Rd",
    "sg:city":"Catonsville",
    "sg:classifiers":[
        {
            "category":"Social Services",
            "subcategory":"Child Care",
            "type":"Services"
        }
    ],
    "sg:phone":"+1 410 788 2439",
    "sg:postcode":"21228",
    "sg:province":"MD",
    "sg:tags":[
        "nursery",
        "day"
    ],
    "wof:name":"Birrane Child Care",
    "wof:placetype":"venue"
},
  "geometry": {"coordinates":[-76.759531,39.262093],"type":"Point"}
}