{
  "type": "Feature",
  "properties": {
    "iso:country":"US",
    "sg:address":"2516 N Charles St Apt 1",
    "sg:city":"Baltimore",
    "sg:classifiers":[
        {
            "category":"Organizations",
            "subcategory":"Political Organization",
            "type":"Services"
        }
    ],
    "sg:phone":"+1 410 467 2722",
    "sg:postcode":"21218",
    "sg:province":"MD",
    "wof:name":"Republican Party Of Baltimore City",
    "wof:placetype":"venue"
},
  "geometry": {"coordinates":[-76.617031,39.318496],"type":"Point"}
}