{
  "type": "Feature",
  "properties": {
    "iso:country":"US",
    "sg:address":"4100 Falls Rd",
    "sg:city":"Baltimore",
    "sg:classifiers":[
        {
            "category":"Restaurant",
            "type":"Food & Drink"
        }
    ],
    "sg:menulink":"http://www.allmenus.com/md/baltimore/18092-falls-road-carry-out/menu/",
    "sg:phone":"+1 410 243 5939",
    "sg:postcode":"21211",
    "sg:province":"MD",
    "sg:tags":[
        "italian",
        "american",
        "sandwich",
        "pizza"
    ],
    "wof:name":"Falls Road Carry Out",
    "wof:placetype":"venue"
},
  "geometry": {"coordinates":[-76.637458,39.337746],"type":"Point"}
}