{
  "type": "Feature",
  "properties": {
    "addr:full":"2792 Crain Hwy Waldorf MD 20601",
    "addr:housenumber":"2792",
    "addr:postcode":"20601",
    "addr:street":"Crain Hwy",
    "iso:country":"US",
    "sg:address":"2792 Crain Hwy",
    "sg:city":"Waldorf",
    "sg:classifiers":[
        {
            "category":"Restaurant",
            "type":"Food & Drink"
        }
    ],
    "sg:phone":"+1 301 374 9955",
    "sg:postcode":"20601",
    "sg:province":"MD",
    "sg:tags":[
        "eating"
    ],
    "wof:name":"Yummy Yummy Carry Out",
    "wof:placetype":"venue"
},
  "geometry": {"coordinates":[-76.902106,38.634557],"type":"Point"}
}