{
  "type": "Feature",
  "properties": {
    "iso:country":"US",
    "sg:address":"337 Civic Ave",
    "sg:city":"Salisbury",
    "sg:classifiers":[
        {
            "category":"Health Services",
            "subcategory":"Health Practitioner",
            "type":"Services"
        }
    ],
    "sg:phone":"+1 410 742 2844",
    "sg:postcode":"21804",
    "sg:province":"MD",
    "sg:tags":[
        "psychologist"
    ],
    "wof:name":"Transform Yourself",
    "wof:placetype":"venue"
},
  "geometry": {"coordinates":[-75.574758,38.365112],"type":"Point"}
}