{
  "type": "Feature",
  "properties": {
    "addr:full":"6 W Madison St Baltimore MD 21201",
    "addr:housenumber":"6",
    "addr:postcode":"21201",
    "addr:street":"W Madison St",
    "iso:country":"US",
    "sg:address":"6 W Madison St",
    "sg:city":"Baltimore",
    "sg:classifiers":[
        {
            "category":"Professional",
            "subcategory":"Management & Consulting",
            "type":"Services"
        }
    ],
    "sg:phone":"+1 410 332 4562",
    "sg:postcode":"21201",
    "sg:province":"MD",
    "sg:tags":[
        "consultant",
        "business"
    ],
    "wof:name":"Global Lead Management Consult",
    "wof:placetype":"venue"
},
  "geometry": {"coordinates":[-76.61582799999999,39.298683],"type":"Point"}
}