{
  "type": "Feature",
  "properties": {
    "iso:country":"US",
    "sg:address":"2712 Crain Hwy",
    "sg:city":"Waldorf",
    "sg:classifiers":[
        {
            "category":"Personal",
            "subcategory":"Nail Salon",
            "type":"Services"
        }
    ],
    "sg:phone":"+1 301 705 9872",
    "sg:postcode":"20601",
    "sg:province":"MD",
    "wof:name":"Us Nail",
    "wof:placetype":"venue"
},
  "geometry": {"coordinates":[-76.900346,38.636302],"type":"Point"}
}