{
  "type": "Feature",
  "properties": {
    "iso:country":"US",
    "sg:address":"4400 Stamp Rd",
    "sg:city":"Temple Hills",
    "sg:classifiers":[
        {
            "category":"Real Estate",
            "subcategory":"Architect",
            "type":"Services"
        }
    ],
    "sg:phone":"+1 301 316 0500",
    "sg:postcode":"20748",
    "sg:province":"MD",
    "sg:tags":[
        "estimate",
        "construction"
    ],
    "wof:name":"W & D Svc",
    "wof:placetype":"venue"
},
  "geometry": {"coordinates":[-76.943216,38.826674],"type":"Point"}
}