{
  "type": "Feature",
  "properties": {
    "iso:country":"US",
    "sg:address":"2402 Chestnut Terrace Ct",
    "sg:city":"Odenton",
    "sg:classifiers":[
        {
            "category":"Professional",
            "type":"Services"
        }
    ],
    "sg:phone":"+1 410 672 3929",
    "sg:postcode":"21113",
    "sg:province":"MD",
    "sg:tags":[
        "writer"
    ],
    "wof:name":"Practical Parenting Concepts",
    "wof:placetype":"venue"
},
  "geometry": {"coordinates":[-76.72184799999999,39.064331],"type":"Point"}
}