{
  "type": "Feature",
  "properties": {
    "iso:country":"US",
    "sg:address":"401 E Jefferson St Ste 101",
    "sg:city":"Rockville",
    "sg:classifiers":[
        {
            "category":"Health Services",
            "subcategory":"Clinic",
            "type":"Services"
        },
        {
            "category":"Health Services",
            "subcategory":"Chiropractor",
            "type":"Services"
        }
    ],
    "sg:phone":"+1 301 762 7494",
    "sg:postcode":"20850",
    "sg:province":"MD",
    "sg:tags":[
        "chiropractic"
    ],
    "wof:name":"Chiropractic Centre",
    "wof:placetype":"venue"
},
  "geometry": {"coordinates":[-77.148188,39.081583],"type":"Point"}
}