{
  "type": "Feature",
  "properties": {
    "addr:full":"7304 Parkway Dr Hanover MD 21076",
    "addr:housenumber":"7304",
    "addr:postcode":"21076",
    "addr:street":"Parkway Dr",
    "iso:country":"US",
    "sg:address":"7304 Parkway Dr",
    "sg:city":"Hanover",
    "sg:classifiers":[
        {
            "category":"Restaurant",
            "type":"Food & Drink"
        }
    ],
    "sg:phone":"+1 410 712 9404",
    "sg:postcode":"21076",
    "sg:province":"MD",
    "sg:tags":[
        "lounge",
        "cocktail"
    ],
    "wof:name":"Gunning's Seafood Restaurant",
    "wof:placetype":"venue"
},
  "geometry": {"coordinates":[-76.733817,39.173379],"type":"Point"}
}