{
  "type": "Feature",
  "properties": {
    "iso:country":"US",
    "sg:address":"8418 Peters Rd",
    "sg:city":"Frederick",
    "sg:classifiers":[
        {
            "category":"Building & Trades",
            "subcategory":"Construction",
            "type":"Services"
        }
    ],
    "sg:phone":"+1 301 874 3692",
    "sg:postcode":"21704",
    "sg:province":"MD",
    "sg:tags":[
        "hanging",
        "contractor"
    ],
    "wof:name":"Mom For Daughters Painting & W",
    "wof:placetype":"venue"
},
  "geometry": {"coordinates":[-77.375404,39.300294],"type":"Point"}
}