{
  "type": "Feature",
  "properties": {
    "iso:country":"US",
    "sg:address":"5 Carter Ct",
    "sg:city":"Rockville",
    "sg:classifiers":[
        {
            "category":"Professional",
            "subcategory":"Computer Services",
            "type":"Services"
        }
    ],
    "sg:phone":"+1 301 762 6261",
    "sg:postcode":"20852",
    "sg:province":"MD",
    "sg:tags":[
        "consulting"
    ],
    "wof:name":"Elliott D Fein Associates",
    "wof:placetype":"venue"
},
  "geometry": {"coordinates":[-77.148393,39.070302],"type":"Point"}
}