{
  "type": "Feature",
  "properties": {
    "addr:full":"274 N Frederick Ave Gaithersburg MD 20877",
    "addr:housenumber":"274",
    "addr:postcode":"20877",
    "addr:street":"N Frederick Ave",
    "iso:country":"US",
    "sg:address":"274 N Frederick Ave",
    "sg:city":"Gaithersburg",
    "sg:classifiers":[
        {
            "category":"Restaurant",
            "type":"Food & Drink"
        }
    ],
    "sg:menulink":"http://www.allmenus.com/md/gaithersburg/67383-dominos-pizza/menu/",
    "sg:phone":"+1 301 990 2400",
    "sg:postcode":"20877",
    "sg:province":"MD",
    "sg:tags":[
        "american",
        "wing",
        "pizza"
    ],
    "wof:name":"Domino's Pizza",
    "wof:placetype":"venue"
},
  "geometry": {"coordinates":[-77.202736,39.144808],"type":"Point"}
}