{
  "type": "Feature",
  "properties": {
    "iso:country":"US",
    "sg:address":"12308 Rockledge Dr",
    "sg:city":"Bowie",
    "sg:classifiers":[
        {
            "category":"Personal",
            "type":"Services"
        }
    ],
    "sg:phone":"+1 301 464 7326",
    "sg:postcode":"20715",
    "sg:province":"MD",
    "wof:name":"Negron Co",
    "wof:placetype":"venue"
},
  "geometry": {"coordinates":[-76.750451,38.996477],"type":"Point"}
}