{
  "type": "Feature",
  "properties": {
    "addr:full":"19506 Brassie Pl Montgomery Village MD 20886",
    "addr:housenumber":"19506",
    "addr:postcode":"20886",
    "addr:street":"Brassie Pl",
    "iso:country":"US",
    "sg:address":"19506 Brassie Pl",
    "sg:city":"Montgomery Village",
    "sg:classifiers":[
        {
            "category":"Professional",
            "type":"Services"
        }
    ],
    "sg:phone":"+1 301 926 4571",
    "sg:postcode":"20886",
    "sg:province":"MD",
    "wof:name":"Jorge Luis Somarriba",
    "wof:placetype":"venue"
},
  "geometry": {"coordinates":[-77.20263300000001,39.177109],"type":"Point"}
}