{
  "type": "Feature",
  "properties": {
    "addr:full":"345 Warren Ave Baltimore MD 21230",
    "addr:housenumber":"345",
    "addr:postcode":"21230",
    "addr:street":"Warren Ave",
    "iso:country":"US",
    "sg:address":"345 Warren Ave",
    "sg:city":"Baltimore",
    "sg:classifiers":[
        {
            "category":"Building & Trades",
            "subcategory":"Equipment Rental",
            "type":"Services"
        }
    ],
    "sg:phone":"+1 410 528 9272",
    "sg:postcode":"21230",
    "sg:province":"MD",
    "sg:tags":[
        "yard",
        "leasing",
        "store"
    ],
    "wof:name":"Federal Hill Rentals",
    "wof:placetype":"venue"
},
  "geometry": {"coordinates":[-76.60883200000001,39.279016],"type":"Point"}
}