{
  "type": "Feature",
  "properties": {
    "iso:country":"US",
    "sg:address":"517 Sudbrook Ln",
    "sg:city":"Pikesville",
    "sg:classifiers":[
        {
            "category":"Professional",
            "subcategory":"Art Services",
            "type":"Services"
        }
    ],
    "sg:phone":"+1 410 484 9110",
    "sg:postcode":"21208",
    "sg:province":"MD",
    "sg:tags":[
        "graphic",
        "designer"
    ],
    "wof:name":"EKZ & Co",
    "wof:placetype":"venue"
},
  "geometry": {"coordinates":[-76.732483,39.364848],"type":"Point"}
}