{
  "type": "Feature",
  "properties": {
    "addr:full":"100 E Carroll St Salisbury MD 21801",
    "addr:housenumber":"100",
    "addr:postcode":"21801",
    "addr:street":"E Carroll St",
    "iso:country":"US",
    "sg:address":"100 E Carroll St",
    "sg:city":"Salisbury",
    "sg:classifiers":[
        {
            "category":"Health Services",
            "subcategory":"Doctor",
            "type":"Services"
        }
    ],
    "sg:phone":"+1 410 742 0567",
    "sg:postcode":"21801",
    "sg:province":"MD",
    "sg:tags":[
        "physician",
        "surgeon"
    ],
    "wof:name":"Ability Rehab Assoc",
    "wof:placetype":"venue"
},
  "geometry": {"coordinates":[-75.596221,38.363184],"type":"Point"}
}