{
  "type": "Feature",
  "properties": {
    "addr:full":"19321 Jerusalem Rd Poolesville MD 20837",
    "addr:housenumber":"19321",
    "addr:postcode":"20837",
    "addr:street":"Jerusalem Rd",
    "iso:country":"US",
    "sg:address":"19321 Jerusalem Rd",
    "sg:city":"Poolesville",
    "sg:classifiers":[
        {
            "category":"Autos & Motor Vehicles",
            "subcategory":"Automobile Sales",
            "type":"Retail Goods"
        }
    ],
    "sg:phone":"+1 301 428 8288",
    "sg:postcode":"20837",
    "sg:province":"MD",
    "sg:tags":[
        "car",
        "dealer"
    ],
    "wof:name":"ASO Co Inc",
    "wof:placetype":"venue"
},
  "geometry": {"coordinates":[-77.403341,39.162293],"type":"Point"}
}