{
  "type": "Feature",
  "properties": {
    "iso:country":"US",
    "sg:address":"10022 Dallas Ave",
    "sg:city":"Silver Spring",
    "sg:classifiers":[
        {
            "category":"Personal",
            "type":"Services"
        }
    ],
    "sg:phone":"+1 301 754 0350",
    "sg:postcode":"20901",
    "sg:province":"MD",
    "wof:name":"Crystal Song",
    "wof:placetype":"venue"
},
  "geometry": {"coordinates":[-77.02282200000001,39.020732],"type":"Point"}
}