{
  "type": "Feature",
  "properties": {
    "iso:country":"US",
    "sg:address":"109 S Augusta Ave",
    "sg:city":"Baltimore",
    "sg:classifiers":[
        {
            "category":"Professional",
            "subcategory":"Management & Consulting",
            "type":"Services"
        }
    ],
    "sg:phone":"+1 410 644 6399",
    "sg:postcode":"21229",
    "sg:province":"MD",
    "sg:tags":[
        "counselor",
        "public",
        "relations"
    ],
    "wof:name":"Napata Consulting Svc",
    "wof:placetype":"venue"
},
  "geometry": {"coordinates":[-76.684757,39.285727],"type":"Point"}
}