{
  "type": "Feature",
  "properties": {
    "addr:full":"5004 Hydes Rd Hydes MD 21082",
    "addr:housenumber":"5004",
    "addr:postcode":"21082",
    "addr:street":"Hydes Rd",
    "iso:country":"US",
    "sg:address":"5004 Hydes Rd",
    "sg:city":"Hydes",
    "sg:classifiers":[
        {
            "category":"Parking",
            "type":"Transportation"
        }
    ],
    "sg:phone":"+1 410 593 9990",
    "sg:postcode":"21082",
    "sg:province":"MD",
    "sg:tags":[
        "attendant"
    ],
    "wof:name":"Courtesy Parking Svc",
    "wof:placetype":"venue"
},
  "geometry": {"coordinates":[-76.49333900000001,39.484285],"type":"Point"}
}