{
  "type": "Feature",
  "properties": {
    "addr:full":"8637 Zetts Ave Gaithersburg MD 20877",
    "addr:housenumber":"8637",
    "addr:postcode":"20877",
    "addr:street":"Zetts Ave",
    "iso:country":"US",
    "sg:address":"8637 Zetts Ave",
    "sg:city":"Gaithersburg",
    "sg:classifiers":[
        {
            "category":"Personal",
            "subcategory":"Tattoo Parlor",
            "type":"Services"
        }
    ],
    "sg:phone":"+1 301 990 2650",
    "sg:postcode":"20877",
    "sg:province":"MD",
    "sg:tags":[
        "tattooing"
    ],
    "wof:name":"Adrenaline Tattoos & Art Ink",
    "wof:placetype":"venue"
},
  "geometry": {"coordinates":[-77.178436,39.121259],"type":"Point"}
}