{
  "type": "Feature",
  "properties": {
    "addr:full":"2827 Smith Ave Baltimore MD 21209",
    "addr:housenumber":"2827",
    "addr:postcode":"21209",
    "addr:street":"Smith Ave",
    "iso:country":"US",
    "sg:address":"2827 Smith Ave",
    "sg:city":"Baltimore",
    "sg:classifiers":[
        {
            "category":"Banks & Credit Unions",
            "subcategory":"Bank",
            "type":"Services"
        }
    ],
    "sg:phone":"+1 410 484 1288",
    "sg:postcode":"21209",
    "sg:province":"MD",
    "wof:name":"Bank Of America",
    "wof:placetype":"venue"
},
  "geometry": {"coordinates":[-76.693787,39.375747],"type":"Point"}
}