{
  "type": "Feature",
  "properties": {
    "iso:country":"US",
    "sg:address":"1160 Spa Rd",
    "sg:city":"Annapolis",
    "sg:classifiers":[
        {
            "category":"Professional",
            "subcategory":"Lawyer & Legal Services",
            "type":"Services"
        }
    ],
    "sg:phone":"+1 410 280 6608",
    "sg:postcode":"21403",
    "sg:province":"MD",
    "sg:tags":[
        "attorney"
    ],
    "sg:website":"www.laubscherlaw.com",
    "wof:name":"Laubscher Steverson",
    "wof:placetype":"venue"
},
  "geometry": {"coordinates":[-76.51275099999999,38.961906],"type":"Point"}
}