{
  "type": "Feature",
  "properties": {
    "iso:country":"US",
    "sg:address":"19411 White Ground Rd",
    "sg:city":"Boyds",
    "sg:classifiers":[
        {
            "category":"Freight",
            "type":"Transportation"
        }
    ],
    "sg:phone":"+1 301 972 9000",
    "sg:postcode":"20841",
    "sg:province":"MD",
    "sg:tags":[
        "mover"
    ],
    "wof:name":"AAA Moving & Storage",
    "wof:placetype":"venue"
},
  "geometry": {"coordinates":[-77.34016800000001,39.163844],"type":"Point"}
}