{
  "type": "Feature",
  "properties": {
    "iso:country":"US",
    "sg:address":"1729 Trotting Ct",
    "sg:city":"Jarrettsville",
    "sg:classifiers":[
        {
            "category":"Building & Trades",
            "subcategory":"Construction",
            "type":"Services"
        }
    ],
    "sg:phone":"+1 410 557 7035",
    "sg:postcode":"21084",
    "sg:province":"MD",
    "sg:tags":[
        "home",
        "builder"
    ],
    "wof:name":"Quality Construction Co",
    "wof:placetype":"venue"
},
  "geometry": {"coordinates":[-76.461144,39.580221],"type":"Point"}
}