{
  "type": "Feature",
  "properties": {
    "iso:country":"US",
    "sg:address":"7 S 7th St",
    "sg:city":"Berlin",
    "sg:classifiers":[
        {
            "category":"Real Estate",
            "subcategory":"Real Estate Agent",
            "type":"Services"
        }
    ],
    "sg:phone":"+1 410 208 6050",
    "sg:postcode":"21817",
    "sg:province":"MD",
    "wof:name":"Centex Homes At Ocean Pines",
    "wof:placetype":"venue"
},
  "geometry": {"coordinates":[-75.857868,37.980699],"type":"Point"}
}