{
  "type": "Feature",
  "properties": {
    "addr:full":"6400 Baltimore Natl Pike Suite 170 B Catonsville MD 21228",
    "addr:housenumber":"6400",
    "addr:postcode":"21228",
    "addr:street":"Baltimore Natl Pike Suite 170 B",
    "iso:country":"US",
    "sg:address":"6400 Baltimore Natl Pike Suite 170 B",
    "sg:city":"Catonsville",
    "sg:classifiers":[
        {
            "category":"Restaurant",
            "type":"Food & Drink"
        }
    ],
    "sg:phone":"+1 410 747 0080",
    "sg:postcode":"21228",
    "sg:province":"MD",
    "sg:tags":[
        "indian"
    ],
    "sg:website":"www.thespicygarden.com/",
    "wof:name":"The Spicy Garden",
    "wof:placetype":"venue"
},
  "geometry": {"coordinates":[-76.731567,39.261144],"type":"Point"}
}