{
  "type": "Feature",
  "properties": {
    "iso:country":"US",
    "sg:address":"11708 Old Baltimore Pike",
    "sg:city":"Beltsville",
    "sg:classifiers":[
        {
            "category":"Building & Trades",
            "subcategory":"Equipment Rental",
            "type":"Services"
        }
    ],
    "sg:phone":"+1 301 937 5888",
    "sg:postcode":"20705",
    "sg:province":"MD",
    "sg:tags":[
        "crane"
    ],
    "wof:name":"Johnson Crane Svc",
    "wof:placetype":"venue"
},
  "geometry": {"coordinates":[-76.89197299999999,39.047289],"type":"Point"}
}