{
  "type": "Feature",
  "properties": {
    "iso:country":"US",
    "sg:address":"510 Bonifant St",
    "sg:city":"Silver Spring",
    "sg:classifiers":[
        {
            "category":"Professional",
            "subcategory":"Management & Consulting",
            "type":"Services"
        }
    ],
    "sg:phone":"+1 301 585 4592",
    "sg:postcode":"20910",
    "sg:province":"MD",
    "sg:tags":[
        "project",
        "co"
    ],
    "wof:name":"John A Ogulnik",
    "wof:placetype":"venue"
},
  "geometry": {"coordinates":[-77.017056,38.998004],"type":"Point"}
}