{
  "type": "Feature",
  "properties": {
    "iso:country":"US",
    "sg:address":"5509 Taylor Rd",
    "sg:city":"Riverdale",
    "sg:classifiers":[
        {
            "category":"Professional",
            "subcategory":"Computer Services",
            "type":"Services"
        }
    ],
    "sg:phone":"+1 301 520 2984",
    "sg:postcode":"20737",
    "sg:province":"MD",
    "sg:tags":[
        "related"
    ],
    "wof:name":"Innovative Concepts",
    "wof:placetype":"venue"
},
  "geometry": {"coordinates":[-76.93348899999999,38.952624],"type":"Point"}
}