{
  "type": "Feature",
  "properties": {
    "iso:country":"US",
    "sg:address":"1720 Basil Way",
    "sg:city":"Gambrills",
    "sg:classifiers":[
        {
            "category":"Home & Garden",
            "subcategory":"Hardware",
            "type":"Retail Goods"
        }
    ],
    "sg:phone":"+1 410 793 3909",
    "sg:postcode":"21054",
    "sg:province":"MD",
    "wof:name":"Standard Tool Inc",
    "wof:placetype":"venue"
},
  "geometry": {"coordinates":[-76.661349,39.001636],"type":"Point"}
}