{
  "type": "Feature",
  "properties": {
    "addr:full":"1667 Knecht Ave Halethorpe MD 21227",
    "addr:housenumber":"1667",
    "addr:postcode":"21227",
    "addr:street":"Knecht Ave",
    "iso:country":"US",
    "sg:address":"1667 Knecht Ave",
    "sg:city":"Halethorpe",
    "sg:classifiers":[
        {
            "category":"Building & Trades",
            "subcategory":"Plumbing",
            "type":"Services"
        }
    ],
    "sg:phone":"+1 410 247 0682",
    "sg:postcode":"21227",
    "sg:province":"MD",
    "wof:name":"Caton Plumbing Hvac",
    "wof:placetype":"venue"
},
  "geometry": {"coordinates":[-76.67974,39.257637],"type":"Point"}
}