{
  "type": "Feature",
  "properties": {
    "iso:country":"US",
    "sg:address":"10461 Mill Run Cir",
    "sg:city":"Owings Mills",
    "sg:classifiers":[
        {
            "category":"Banks & Credit Unions",
            "subcategory":"Bank",
            "type":"Services"
        }
    ],
    "sg:phone":"+1 410 902 1527",
    "sg:postcode":"21117",
    "sg:province":"MD",
    "sg:tags":[
        "loan",
        "real estate"
    ],
    "sg:website":"www.ameriquest.com",
    "wof:name":"Ameriquest Mortgage Co",
    "wof:placetype":"venue"
},
  "geometry": {"coordinates":[-76.790649,39.408755],"type":"Point"}
}