{
  "type": "Feature",
  "properties": {
    "addr:full":"3610 Old Silver Hill Rd Suitland MD 20746",
    "addr:housenumber":"3610",
    "addr:postcode":"20746",
    "addr:street":"Old Silver Hill Rd",
    "iso:country":"US",
    "sg:address":"3610 Old Silver Hill Rd",
    "sg:city":"Suitland",
    "sg:classifiers":[
        {
            "category":"Autos & Motor Vehicles",
            "subcategory":"Auto Supplies",
            "type":"Retail Goods"
        },
        {
            "category":"Retail",
            "subcategory":"Auto Repair",
            "type":"Services"
        }
    ],
    "sg:phone":"+1 301 702 0606",
    "sg:postcode":"20746",
    "sg:province":"MD",
    "sg:tags":[
        "wheel",
        "tire"
    ],
    "wof:name":"Dl Thomas Enterprises Inc",
    "wof:placetype":"venue"
},
  "geometry": {"coordinates":[-76.947751,38.842782],"type":"Point"}
}