{
  "type": "Feature",
  "properties": {
    "iso:country":"US",
    "sg:address":"802 Linwood Rd",
    "sg:city":"Hagerstown",
    "sg:classifiers":[
        {
            "category":"Health Services",
            "subcategory":"Doctor",
            "type":"Services"
        }
    ],
    "sg:phone":"+1 301 797 6571",
    "sg:postcode":"21740",
    "sg:province":"MD",
    "sg:tags":[
        "dentist"
    ],
    "wof:name":"John W Garrott DDS",
    "wof:placetype":"venue"
},
  "geometry": {"coordinates":[-77.749325,39.623557],"type":"Point"}
}