{
  "type": "Feature",
  "properties": {
    "iso:country":"US",
    "sg:address":"6196 Oxon Hill Rd",
    "sg:city":"Oxon Hill",
    "sg:classifiers":[
        {
            "category":"Health Services",
            "subcategory":"Doctor",
            "type":"Services"
        }
    ],
    "sg:phone":"+1 301 567 3772",
    "sg:postcode":"20745",
    "sg:province":"MD",
    "sg:tags":[
        "physician",
        "surgeon"
    ],
    "wof:name":"A H Pourhamidi MD",
    "wof:placetype":"venue"
},
  "geometry": {"coordinates":[-76.984196,38.803904],"type":"Point"}
}