{
  "type": "Feature",
  "properties": {
    "addr:full":"12247 Baugher Rd Thurmont MD 21788",
    "addr:postcode":"12247;21788",
    "addr:street":"Baugher Rd",
    "iso:country":"US",
    "sg:address":"12247 Baugher Rd",
    "sg:city":"Thurmont",
    "sg:classifiers":[
        {
            "category":"Wholesale",
            "subcategory":"Meat",
            "type":"Manufacturing & Wholesale Goods"
        }
    ],
    "sg:phone":"+1 301 271 2231",
    "sg:postcode":"21788",
    "sg:province":"MD",
    "wof:name":"Shuff's Meat Market",
    "wof:placetype":"venue"
},
  "geometry": {"coordinates":[-77.438873,39.568725],"type":"Point"}
}