{
  "type": "Feature",
  "properties": {
    "addr:full":"1405 Riverside Dr Salisbury MD 21801",
    "addr:housenumber":"1405",
    "addr:postcode":"21801",
    "addr:street":"Riverside Dr",
    "iso:country":"US",
    "sg:address":"1405 Riverside Dr",
    "sg:city":"Salisbury",
    "sg:classifiers":[
        {
            "category":"Building & Trades",
            "subcategory":"Landscaping Services",
            "type":"Services"
        }
    ],
    "sg:phone":"+1 410 548 1111",
    "sg:postcode":"21801",
    "sg:province":"MD",
    "sg:tags":[
        "landscape",
        "contractor"
    ],
    "wof:name":"Johnson Landscape Co",
    "wof:placetype":"venue"
},
  "geometry": {"coordinates":[-75.623529,38.344303],"type":"Point"}
}