{
  "type": "Feature",
  "properties": {
    "addr:full":"101 John St Westminster MD 21157",
    "addr:housenumber":"101",
    "addr:postcode":"21157",
    "addr:street":"John St",
    "iso:country":"US",
    "sg:address":"101 John St",
    "sg:city":"Westminster",
    "sg:classifiers":[
        {
            "category":"Arena",
            "subcategory":"Sports Club",
            "type":"Entertainment"
        }
    ],
    "sg:phone":"+1 410 751 3892",
    "sg:postcode":"21157",
    "sg:province":"MD",
    "wof:name":"Upholstery & Sew On",
    "wof:placetype":"venue"
},
  "geometry": {"coordinates":[-76.991753,39.581236],"type":"Point"}
}