{
  "type": "Feature",
  "properties": {
    "addr:full":"8078 Green Bud Ln Glen Burnie MD 21061",
    "addr:housenumber":"8078",
    "addr:postcode":"21061",
    "addr:street":"Green Bud Ln",
    "iso:country":"US",
    "sg:address":"8078 Green Bud Ln",
    "sg:city":"Glen Burnie",
    "sg:classifiers":[
        {
            "category":"Building & Trades",
            "subcategory":"Cleaning & Sanitation",
            "type":"Services"
        }
    ],
    "sg:phone":"+1 410 813 4050",
    "sg:postcode":"21061",
    "sg:province":"MD",
    "sg:tags":[
        "maintenance"
    ],
    "wof:name":"Colonial Driveway Service",
    "wof:placetype":"venue"
},
  "geometry": {"coordinates":[-76.638277,39.127968],"type":"Point"}
}