{
  "type": "Feature",
  "properties": {
    "iso:country":"US",
    "sg:address":"2253 Kirk Ave",
    "sg:city":"Baltimore",
    "sg:classifiers":[
        {
            "category":"Retail",
            "subcategory":"Auto Rental",
            "type":"Services"
        }
    ],
    "sg:phone":"+1 410 243 0068",
    "sg:postcode":"21218",
    "sg:province":"MD",
    "sg:tags":[
        "truck"
    ],
    "sg:website":"http://www.uhaul.com/Locations/Rentals-near-Baltimore-MD-21218/003041",
    "wof:name":"U-Haul R&R Towing Service",
    "wof:placetype":"venue"
},
  "geometry": {"coordinates":[-76.604871,39.315444],"type":"Point"}
}