{
  "type": "Feature",
  "properties": {
    "addr:full":"14013 Barnhart Rd Clear Spring MD 21722",
    "addr:housenumber":"14013",
    "addr:postcode":"21722",
    "addr:street":"Barnhart Rd",
    "iso:country":"US",
    "sg:address":"14013 Barnhart Rd",
    "sg:city":"Clear Spring",
    "sg:classifiers":[
        {
            "category":"Building & Trades",
            "subcategory":"Construction",
            "type":"Services"
        }
    ],
    "sg:phone":"+1 301 842 1216",
    "sg:postcode":"21722",
    "sg:province":"MD",
    "sg:tags":[
        "concrete",
        "contractor"
    ],
    "wof:name":"Bywaters Construction Inc",
    "wof:placetype":"venue"
},
  "geometry": {"coordinates":[-77.884713,39.692348],"type":"Point"}
}