{
  "type": "Feature",
  "properties": {
    "iso:country":"US",
    "sg:address":"16820A Hampton Rd",
    "sg:city":"Williamsport",
    "sg:classifiers":[
        {
            "category":"Wholesale",
            "subcategory":"Groceries",
            "type":"Manufacturing & Wholesale Goods"
        },
        {
            "category":"Food & Beverages",
            "subcategory":"Groceries & Convenience Stores",
            "type":"Retail Goods"
        }
    ],
    "sg:phone":"+1 301 223 9464",
    "sg:postcode":"21795",
    "sg:province":"MD",
    "sg:tags":[
        "products-wholesale"
    ],
    "sg:website":"http://www.oharasonline.com",
    "wof:name":"O'hara Specialties",
    "wof:placetype":"venue"
},
  "geometry": {"coordinates":[-77.787282,39.612281],"type":"Point"}
}