{
  "type": "Feature",
  "properties": {
    "addr:full":"4733 Bethesda Ave 2nd Fl Bethesda MD 20814",
    "addr:housenumber":"4733",
    "addr:postcode":"20814",
    "addr:street":"Bethesda Ave 2Nd",
    "iso:country":"US",
    "sg:address":"4733 Bethesda Ave 2nd Fl",
    "sg:city":"Bethesda",
    "sg:classifiers":[
        {
            "category":"Real Estate",
            "subcategory":"Real Estate Agent",
            "type":"Services"
        }
    ],
    "sg:phone":"+1 301 792 7351",
    "sg:postcode":"20814",
    "sg:province":"MD",
    "sg:website":"www.ValerieBrownRealtor.com",
    "wof:name":"Valerie Brown, Long & Foster Realtors",
    "wof:placetype":"venue"
},
  "geometry": {"coordinates":[-77.094278,38.981288],"type":"Point"}
}