{
  "type": "Feature",
  "properties": {
    "iso:country":"US",
    "sg:address":"11202 Rock Rd",
    "sg:city":"Rockville",
    "sg:classifiers":[
        {
            "category":"Retail",
            "subcategory":"Auto Repair",
            "type":"Services"
        }
    ],
    "sg:phone":"+1 240 430 0363",
    "sg:postcode":"20852",
    "sg:province":"MD",
    "wof:name":"Shine Cleaning Services",
    "wof:placetype":"venue"
},
  "geometry": {"coordinates":[-77.08975100000001,39.037595],"type":"Point"}
}