{
  "type": "Feature",
  "properties": {
    "addr:full":"6821 Riverdale Rd Riverdale MD 20737",
    "addr:housenumber":"6821",
    "addr:postcode":"20737",
    "addr:street":"Riverdale Rd",
    "iso:country":"US",
    "sg:address":"6821 Riverdale Rd",
    "sg:city":"Riverdale",
    "sg:classifiers":[
        {
            "category":"Real Estate",
            "subcategory":"Real Estate Operator",
            "type":"Services"
        }
    ],
    "sg:phone":"+1 301 577 7733",
    "sg:postcode":"20737",
    "sg:province":"MD",
    "sg:tags":[
        "apartment"
    ],
    "wof:name":"Auburn Manor Apartments",
    "wof:placetype":"venue"
},
  "geometry": {"coordinates":[-76.900966,38.962745],"type":"Point"}
}