{
  "type": "Feature",
  "properties": {
    "iso:country":"US",
    "sg:address":"5129 Reisterstown Rd",
    "sg:city":"Baltimore",
    "sg:classifiers":[
        {
            "category":"Food & Beverages",
            "subcategory":"Groceries & Convenience Stores",
            "type":"Retail Goods"
        }
    ],
    "sg:phone":"+1 410 367 6711",
    "sg:postcode":"21215",
    "sg:province":"MD",
    "wof:name":"7-Eleven",
    "wof:placetype":"venue"
},
  "geometry": {"coordinates":[-76.682334,39.342217],"type":"Point"}
}