{
  "type": "Feature",
  "properties": {
    "iso:country":"US",
    "sg:address":"313 W Main St",
    "sg:city":"Emmitsburg",
    "sg:classifiers":[
        {
            "category":"Mining & Drilling",
            "type":"Manufacturing & Wholesale Goods"
        }
    ],
    "sg:phone":"+1 301 447 3730",
    "sg:postcode":"21727",
    "sg:province":"MD",
    "sg:tags":[
        "stone"
    ],
    "sg:website":"www.bellstoneco.com",
    "wof:name":"Bell Stone Co",
    "wof:placetype":"venue"
},
  "geometry": {"coordinates":[-77.329778,39.705274],"type":"Point"}
}