{
  "type": "Feature",
  "properties": {
    "iso:country":"US",
    "sg:address":"19724 Germantown Rd",
    "sg:city":"Germantown",
    "sg:classifiers":[
        {
            "category":"Coffee & Tea",
            "type":"Food & Drink"
        }
    ],
    "sg:menulink":"http://www.allmenus.com/md/clarksburg/119040-starbucks-coffee/menu/",
    "sg:phone":"+1 240 686 0471",
    "sg:postcode":"20874",
    "sg:province":"MD",
    "sg:tags":[
        "american"
    ],
    "wof:name":"Starbucks Coffee",
    "wof:placetype":"venue"
},
  "geometry": {"coordinates":[-77.26419,39.180437],"type":"Point"}
}