{
  "type": "Feature",
  "properties": {
    "addr:full":"250 S Monastery Ave Baltimore MD 21229",
    "addr:housenumber":"250",
    "addr:postcode":"21229",
    "addr:street":"S Monastery Ave",
    "iso:country":"US",
    "sg:address":"250 S Monastery Ave",
    "sg:city":"Baltimore",
    "sg:classifiers":[
        {
            "category":"Banks & Credit Unions",
            "subcategory":"Investment Brokerage",
            "type":"Services"
        },
        {
            "category":"Real Estate",
            "subcategory":"Developer",
            "type":"Services"
        }
    ],
    "sg:phone":"+1 410 368 3692",
    "sg:postcode":"21229",
    "sg:province":"MD",
    "sg:tags":[
        "investing"
    ],
    "wof:name":"Associates In Property Investments",
    "wof:placetype":"venue"
},
  "geometry": {"coordinates":[-76.68102399999999,39.282983],"type":"Point"}
}