{
  "type": "Feature",
  "properties": {
    "iso:country":"US",
    "sg:address":"2401 Liberty Heights Ave",
    "sg:city":"Baltimore",
    "sg:classifiers":[
        {
            "category":"Shopping",
            "subcategory":"Jewelry",
            "type":"Retail Goods"
        },
        {
            "category":"Manufacturing",
            "subcategory":"Jewelry",
            "type":"Manufacturing & Wholesale Goods"
        }
    ],
    "sg:phone":"+1 410 462 1710",
    "sg:postcode":"21215",
    "sg:province":"MD",
    "sg:tags":[
        "manufacturer",
        "watch",
        "jewelers-wholesale",
        "jeweler"
    ],
    "wof:name":"Mara Jewelry",
    "wof:placetype":"venue"
},
  "geometry": {"coordinates":[-76.65463699999999,39.318915],"type":"Point"}
}