{
  "type": "Feature",
  "properties": {
    "addr:full":"2112 Pulaski Hwy Havre De Grace MD 21078",
    "addr:housenumber":"2112",
    "addr:postcode":"21078",
    "addr:street":"Pulaski Hwy",
    "iso:country":"US",
    "sg:address":"2112 Pulaski Hwy",
    "sg:city":"Havre De Grace",
    "sg:classifiers":[
        {
            "category":"Wholesale",
            "subcategory":"Durable Goods & Equipment",
            "type":"Manufacturing & Wholesale Goods"
        }
    ],
    "sg:phone":"+1 410 272 8002",
    "sg:postcode":"21078",
    "sg:province":"MD",
    "sg:tags":[
        "importer"
    ],
    "wof:name":"Delta Auto Imports",
    "wof:placetype":"venue"
},
  "geometry": {"coordinates":[-76.137227,39.524825],"type":"Point"}
}