{
  "type": "Feature",
  "properties": {
    "addr:full":"12340 Owings Mills Blvd Reisterstown MD 21136",
    "addr:housenumber":"12340",
    "addr:postcode":"21136",
    "addr:street":"Owings Mills Blvd",
    "iso:country":"US",
    "sg:address":"12340 Owings Mills Blvd",
    "sg:city":"Reisterstown",
    "sg:classifiers":[
        {
            "category":"Manufacturing",
            "subcategory":"Building Materials",
            "type":"Manufacturing & Wholesale Goods"
        }
    ],
    "sg:phone":"+1 410 526 5510",
    "sg:postcode":"21136",
    "sg:province":"MD",
    "wof:name":"Rolf Sorg Inc",
    "wof:placetype":"venue"
},
  "geometry": {"coordinates":[-76.804052,39.46219],"type":"Point"}
}