{
  "type": "Feature",
  "properties": {
    "addr:full":"6009 Sweetwater Ct Frederick MD 21703",
    "addr:housenumber":"6009",
    "addr:postcode":"21703",
    "addr:street":"Sweetwater Ct",
    "iso:country":"US",
    "sg:address":"6009 Sweetwater Ct",
    "sg:city":"Frederick",
    "sg:classifiers":[
        {
            "category":"Professional",
            "subcategory":"Management & Consulting",
            "type":"Services"
        }
    ],
    "sg:phone":"+1 301 473 5202",
    "sg:postcode":"21703",
    "sg:province":"MD",
    "sg:tags":[
        "consultant"
    ],
    "wof:name":"Etiquette Consultants",
    "wof:placetype":"venue"
},
  "geometry": {"coordinates":[-77.501081,39.398557],"type":"Point"}
}