{
  "type": "Feature",
  "properties": {
    "addr:full":"4130 Home Dale Rd Sykesville MD 21784",
    "addr:housenumber":"4130",
    "addr:postcode":"21784",
    "addr:street":"Home Dale Rd",
    "iso:country":"US",
    "sg:address":"4130 Home Dale Rd",
    "sg:city":"Sykesville",
    "sg:classifiers":[
        {
            "category":"Building & Trades",
            "subcategory":"Construction",
            "type":"Services"
        }
    ],
    "sg:phone":"+1 410 795 2227",
    "sg:postcode":"21784",
    "sg:province":"MD",
    "sg:tags":[
        "contractor"
    ],
    "wof:name":"Highlight Construction Co Inc",
    "wof:placetype":"venue"
},
  "geometry": {"coordinates":[-76.975708,39.46273],"type":"Point"}
}