{
  "type": "Feature",
  "properties": {
    "addr:full":"6 Woodland Ct Laurel MD 20707",
    "addr:housenumber":"6",
    "addr:postcode":"20707",
    "addr:street":"Woodland Ct",
    "iso:country":"US",
    "sg:address":"6 Woodland Ct",
    "sg:city":"Laurel",
    "sg:classifiers":[
        {
            "category":"Manufacturing",
            "subcategory":"Apparel",
            "type":"Manufacturing & Wholesale Goods"
        }
    ],
    "sg:phone":"+1 301 377 2475",
    "sg:postcode":"20707",
    "sg:province":"MD",
    "sg:tags":[
        "mfg"
    ],
    "wof:name":"Beleava",
    "wof:placetype":"venue"
},
  "geometry": {"coordinates":[-76.844521,39.095547],"type":"Point"}
}