{
  "type": "Feature",
  "properties": {
    "iso:country":"US",
    "sg:address":"3314 Meadowlark Rd",
    "sg:city":"White Hall",
    "sg:classifiers":[
        {
            "category":"Professional",
            "subcategory":"Business Services",
            "type":"Services"
        }
    ],
    "sg:phone":"+1 410 557 4313",
    "sg:postcode":"21161",
    "sg:province":"MD",
    "wof:name":"Meadowlark Enterprises Lt",
    "wof:placetype":"venue"
},
  "geometry": {"coordinates":[-76.56785000000001,39.692247],"type":"Point"}
}