{
  "type": "Feature",
  "properties": {
    "iso:country":"US",
    "sg:address":"5706 Hemlock Tree Ln",
    "sg:city":"Fairmount Hts",
    "sg:classifiers":[
        {
            "category":"Real Estate",
            "subcategory":"Real Estate Agent",
            "type":"Services"
        }
    ],
    "sg:phone":"+1 301 925 7820",
    "sg:postcode":"20743",
    "sg:province":"MD",
    "wof:name":"Mercedes Realty",
    "wof:placetype":"venue"
},
  "geometry": {"coordinates":[-76.906632,38.903696],"type":"Point"}
}