{
  "type": "Feature",
  "properties": {
    "addr:full":"10805 Hickory Ridge Rd Ste 201 Columbia MD 21044",
    "addr:housenumber":"10805",
    "addr:postcode":"21044",
    "addr:street":"Hickory Ridge Rd Ste 201",
    "iso:country":"US",
    "sg:address":"10805 Hickory Ridge Rd Ste 201",
    "sg:city":"Columbia",
    "sg:classifiers":[
        {
            "category":"Health Services",
            "subcategory":"Doctor",
            "type":"Services"
        }
    ],
    "sg:phone":"+1 410 715 9990",
    "sg:postcode":"21044",
    "sg:province":"MD",
    "sg:tags":[
        "physician",
        "family",
        "practice",
        "surgeons",
        "medicine",
        "surgeon"
    ],
    "wof:name":"Dennis, J Elizabeth, Md - J Elizabeth Dennis Pa",
    "wof:placetype":"venue"
},
  "geometry": {"coordinates":[-76.885485,39.210959],"type":"Point"}
}