{
  "type": "Feature",
  "properties": {
    "iso:country":"US",
    "sg:address":"1511 S Highland Ave Ste A",
    "sg:city":"Baltimore",
    "sg:classifiers":[
        {
            "category":"Banks & Credit Unions",
            "subcategory":"Bank",
            "type":"Services"
        }
    ],
    "sg:phone":"+1 410 534 7911",
    "sg:postcode":"21224",
    "sg:province":"MD",
    "wof:name":"1st Mariner Bank",
    "wof:placetype":"venue"
},
  "geometry": {"coordinates":[-76.568063,39.274679],"type":"Point"}
}