{
  "type": "Feature",
  "properties": {
    "addr:full":"6620 Reisterstown Rd Baltimore MD 21215",
    "addr:housenumber":"6620",
    "addr:postcode":"21215",
    "addr:street":"Reisterstown Rd",
    "iso:country":"US",
    "sg:address":"6620 Reisterstown Rd",
    "sg:city":"Baltimore",
    "sg:classifiers":[
        {
            "category":"Banks & Credit Unions",
            "subcategory":"Bank",
            "type":"Services"
        }
    ],
    "sg:phone":"+1 410 764 8725",
    "sg:postcode":"21215",
    "sg:province":"MD",
    "sg:website":"www.pnc.com",
    "wof:name":"Pnc Bank",
    "wof:placetype":"venue"
},
  "geometry": {"coordinates":[-76.70542399999999,39.358183],"type":"Point"}
}