{
  "type": "Feature",
  "properties": {
    "iso:country":"US",
    "sg:address":"1200 E 20th St",
    "sg:city":"Baltimore",
    "sg:classifiers":[
        {
            "category":"Retail",
            "subcategory":"Auto Repair",
            "type":"Services"
        }
    ],
    "sg:phone":"+1 410 235 1531",
    "sg:postcode":"21218",
    "sg:province":"MD",
    "sg:tags":[
        "body",
        "repairing",
        "painting",
        "automobile"
    ],
    "wof:name":"Leroy Mcneil",
    "wof:placetype":"venue"
},
  "geometry": {"coordinates":[-76.60266900000001,39.312851],"type":"Point"}
}