{
  "type": "Feature",
  "properties": {
    "iso:country":"US",
    "sg:address":"1015 N Charles St",
    "sg:city":"Baltimore",
    "sg:classifiers":[
        {
            "category":"Organizations",
            "subcategory":"Religious Organization",
            "type":"Services"
        }
    ],
    "sg:phone":"+1 443 869 4920",
    "sg:postcode":"21201",
    "sg:province":"MD",
    "wof:name":"Light Church the",
    "wof:placetype":"venue"
},
  "geometry": {"coordinates":[-76.615735,39.301211],"type":"Point"}
}