{
  "type": "Feature",
  "properties": {
    "addr:full":"401 Eastern Blvd Essex MD 21221",
    "addr:housenumber":"401",
    "addr:postcode":"21221",
    "addr:street":"Eastern Blvd",
    "iso:country":"US",
    "sg:address":"401 Eastern Blvd",
    "sg:city":"Essex",
    "sg:classifiers":[
        {
            "category":"Health Services",
            "subcategory":"Chiropractor",
            "type":"Services"
        }
    ],
    "sg:phone":"+1 410 780 4434",
    "sg:postcode":"21221",
    "sg:province":"MD",
    "wof:name":"Stripes Family Chiropractic",
    "wof:placetype":"venue"
},
  "geometry": {"coordinates":[-76.479502,39.306919],"type":"Point"}
}