{
  "type": "Feature",
  "properties": {
    "iso:country":"US",
    "sg:address":"602 Fallston Rd",
    "sg:city":"Fallston",
    "sg:classifiers":[
        {
            "category":"Retail",
            "subcategory":"Auto Repair",
            "type":"Services"
        }
    ],
    "sg:phone":"+1 410 893 9524",
    "sg:postcode":"21047",
    "sg:province":"MD",
    "sg:tags":[
        "wrecker"
    ],
    "wof:name":"Almony's Towing & Svc",
    "wof:placetype":"venue"
},
  "geometry": {"coordinates":[-76.400804,39.50281],"type":"Point"}
}