{
  "type": "Feature",
  "properties": {
    "iso:country":"US",
    "sg:address":"2640 N Salisbury Blvd",
    "sg:city":"Salisbury",
    "sg:classifiers":[
        {
            "category":"Shopping",
            "subcategory":"Computers & Home Electronics",
            "type":"Retail Goods"
        }
    ],
    "sg:phone":"+1 410 749 9457",
    "sg:postcode":"21801",
    "sg:province":"MD",
    "sg:tags":[
        "equipment",
        "electronic",
        "supply"
    ],
    "wof:name":"Circuit City",
    "wof:placetype":"venue"
},
  "geometry": {"coordinates":[-75.567589,38.412063],"type":"Point"}
}