{
  "type": "Feature",
  "properties": {
    "addr:full":"10611 Laurel Hill Dr Frostburg MD 21532",
    "addr:housenumber":"10611",
    "addr:postcode":"21532",
    "addr:street":"Laurel Hill Dr",
    "iso:country":"US",
    "sg:address":"10611 Laurel Hill Dr",
    "sg:city":"Frostburg",
    "sg:classifiers":[
        {
            "category":"Freight",
            "type":"Transportation"
        }
    ],
    "sg:phone":"+1 301 689 3436",
    "sg:postcode":"21532",
    "sg:province":"MD",
    "sg:tags":[
        "trucking"
    ],
    "wof:name":"Double R Trucking",
    "wof:placetype":"venue"
},
  "geometry": {"coordinates":[-78.906856,39.648137],"type":"Point"}
}