{
  "type": "Feature",
  "properties": {
    "addr:full":"658 Lucabaugh Mill Rd Westminster MD 21157",
    "addr:housenumber":"658",
    "addr:postcode":"21157",
    "addr:street":"Lucabaugh Mill Rd",
    "iso:country":"US",
    "sg:address":"658 Lucabaugh Mill Rd",
    "sg:city":"Westminster",
    "sg:classifiers":[
        {
            "category":"Organizations",
            "subcategory":"Religious Organization",
            "type":"Services"
        }
    ],
    "sg:phone":"+1 410 848 2222",
    "sg:postcode":"21157",
    "sg:province":"MD",
    "wof:name":"Westminster Rescue Mission",
    "wof:placetype":"venue"
},
  "geometry": {"coordinates":[-76.968784,39.592175],"type":"Point"}
}