{
  "type": "Feature",
  "properties": {
    "addr:full":"2661 Riva Rd Ste 300 Annapolis MD 21401",
    "addr:housenumber":"2661",
    "addr:postcode":"21401",
    "addr:street":"Riva Rd Ste 300",
    "iso:country":"US",
    "sg:address":"2661 Riva Rd Ste 300",
    "sg:city":"Annapolis",
    "sg:classifiers":[
        {
            "category":"Real Estate",
            "subcategory":"Real Estate Services",
            "type":"Services"
        },
        {
            "category":"Real Estate",
            "subcategory":"Real Estate Agent",
            "type":"Services"
        }
    ],
    "sg:phone":"+1 410 266 8444",
    "sg:postcode":"21401",
    "sg:province":"MD",
    "sg:tags":[
        "buyer",
        "management",
        "broker"
    ],
    "wof:name":"Murphy Hogan Commercial Real Estate",
    "wof:placetype":"venue"
},
  "geometry": {"coordinates":[-76.55924,38.974984],"type":"Point"}
}