{
  "type": "Feature",
  "properties": {
    "iso:country":"US",
    "sg:address":"16211 Penn Manor Ln",
    "sg:city":"Bowie",
    "sg:classifiers":[
        {
            "category":"Professional",
            "subcategory":"Business Services",
            "type":"Services"
        }
    ],
    "sg:phone":"+1 301 390 5188",
    "sg:postcode":"20716",
    "sg:province":"MD",
    "wof:name":"KS Enterprise",
    "wof:placetype":"venue"
},
  "geometry": {"coordinates":[-76.72426400000001,38.905297],"type":"Point"}
}