{
  "type": "Feature",
  "properties": {
    "iso:country":"US",
    "sg:address":"6411 Oxon Hill Rd",
    "sg:city":"Oxon Hill",
    "sg:classifiers":[
        {
            "category":"Government",
            "subcategory":"Office",
            "type":"Public Place"
        }
    ],
    "sg:phone":"+1 301 839 1177",
    "sg:postcode":"20745",
    "sg:province":"MD",
    "wof:name":"Oxon Hill Farm",
    "wof:placetype":"venue"
},
  "geometry": {"coordinates":[-77.001789,38.800753],"type":"Point"}
}