{
  "type": "Feature",
  "properties": {
    "iso:country":"US",
    "sg:address":"1340 Smith Ave",
    "sg:city":"Baltimore",
    "sg:classifiers":[
        {
            "category":"Home & Garden",
            "subcategory":"Garden Supply",
            "type":"Retail Goods"
        }
    ],
    "sg:phone":"+1 410 433 0119",
    "sg:postcode":"21209",
    "sg:province":"MD",
    "sg:tags":[
        "lawn",
        "gardener"
    ],
    "sg:website":"www.smithandhawken.com",
    "wof:name":"Smith and Hawken",
    "wof:placetype":"venue"
},
  "geometry": {"coordinates":[-76.64919999999999,39.367802],"type":"Point"}
}