{
  "type": "Feature",
  "properties": {
    "addr:full":"8 Platzer Ln Glen Burnie MD 21061",
    "addr:housenumber":"8",
    "addr:postcode":"21061",
    "addr:street":"Platzer Ln",
    "iso:country":"US",
    "sg:address":"8 Platzer Ln",
    "sg:city":"Glen Burnie",
    "sg:classifiers":[
        {
            "category":"Wholesale",
            "subcategory":"Non-durable Goods",
            "type":"Manufacturing & Wholesale Goods"
        }
    ],
    "sg:phone":"+1 410 760 9480",
    "sg:postcode":"21061",
    "sg:province":"MD",
    "sg:tags":[
        "advertising"
    ],
    "wof:name":"O P Henschel Inc",
    "wof:placetype":"venue"
},
  "geometry": {"coordinates":[-76.62601600000001,39.164576],"type":"Point"}
}