{
  "type": "Feature",
  "properties": {
    "iso:country":"US",
    "sg:address":"108 Metispa Dr",
    "sg:city":"Severna Park",
    "sg:classifiers":[
        {
            "category":"Shopping",
            "subcategory":"Computers & Home Electronics",
            "type":"Retail Goods"
        }
    ],
    "sg:phone":"+1 410 315 7753",
    "sg:postcode":"21146",
    "sg:province":"MD",
    "sg:tags":[
        "equipment",
        "electronic",
        "supply"
    ],
    "wof:name":"Richardson Electronics",
    "wof:placetype":"venue"
},
  "geometry": {"coordinates":[-76.56319,39.101752],"type":"Point"}
}