{
  "type": "Feature",
  "properties": {
    "addr:full":"24 E Pennsylvania Ave Bel Air MD 21014",
    "addr:housenumber":"24",
    "addr:postcode":"21014",
    "addr:street":"E Pennsylvania Ave",
    "iso:country":"US",
    "sg:address":"24 E Pennsylvania Ave",
    "sg:city":"Bel Air",
    "sg:classifiers":[
        {
            "category":"Personal",
            "subcategory":"Beauty Salon",
            "type":"Services"
        }
    ],
    "sg:phone":"+1 410 838 4030",
    "sg:postcode":"21014",
    "sg:province":"MD",
    "wof:name":"Hair Force I",
    "wof:placetype":"venue"
},
  "geometry": {"coordinates":[-76.34919499999999,39.536924],"type":"Point"}
}