{
  "type": "Feature",
  "properties": {
    "iso:country":"US",
    "sg:address":"3114 Royston Ave",
    "sg:city":"Baltimore",
    "sg:classifiers":[
        {
            "category":"Utilities",
            "subcategory":"Refuse",
            "type":"Services"
        },
        {
            "category":"Retail",
            "subcategory":"Animal Services",
            "type":"Services"
        }
    ],
    "sg:phone":"+1 410 319 6630",
    "sg:postcode":"21214",
    "sg:province":"MD",
    "sg:tags":[
        "container",
        "garbage",
        "pet",
        "collection",
        "removal",
        "rubbish"
    ],
    "sg:website":"www.scooperhero.com",
    "wof:name":"Scooperhero",
    "wof:placetype":"venue"
},
  "geometry": {"coordinates":[-76.55296,39.357857],"type":"Point"}
}