{
  "type": "Feature",
  "properties": {
    "addr:full":"13300 Parkland Dr Rockville MD 20853",
    "addr:housenumber":"13300",
    "addr:postcode":"20853",
    "addr:street":"Parkland Dr",
    "iso:country":"US",
    "sg:address":"13300 Parkland Dr",
    "sg:city":"Rockville",
    "sg:classifiers":[
        {
            "category":"Professional",
            "subcategory":"Management & Consulting",
            "type":"Services"
        }
    ],
    "sg:phone":"+1 301 946 3737",
    "sg:postcode":"20853",
    "sg:province":"MD",
    "sg:tags":[
        "consultant",
        "resource",
        "human"
    ],
    "wof:name":"Sylvia Matthews",
    "wof:placetype":"venue"
},
  "geometry": {"coordinates":[-77.086708,39.07479],"type":"Point"}
}