{
  "type": "Feature",
  "properties": {
    "addr:full":"3400 Annapolis Rd Baltimore MD 21227",
    "addr:housenumber":"3400",
    "addr:postcode":"21227",
    "addr:street":"Annapolis Rd",
    "iso:country":"US",
    "sg:address":"3400 Annapolis Rd",
    "sg:city":"Baltimore",
    "sg:classifiers":[
        {
            "category":"Shopping",
            "subcategory":"Shoes",
            "type":"Retail Goods"
        }
    ],
    "sg:phone":"+1 410 355 7700",
    "sg:postcode":"21227",
    "sg:province":"MD",
    "wof:name":"A & B Check Cashing Svc",
    "wof:placetype":"venue"
},
  "geometry": {"coordinates":[-76.640458,39.246514],"type":"Point"}
}