{
  "type": "Feature",
  "properties": {
    "addr:full":"2525 Riva Rd Annapolis MD 21401",
    "addr:housenumber":"2525",
    "addr:postcode":"21401",
    "addr:street":"Riva Rd",
    "iso:country":"US",
    "sg:address":"2525 Riva Rd",
    "sg:city":"Annapolis",
    "sg:classifiers":[
        {
            "category":"Professional",
            "subcategory":"Research",
            "type":"Services"
        }
    ],
    "sg:phone":"+1 410 266 8836",
    "sg:postcode":"21401",
    "sg:province":"MD",
    "sg:tags":[
        "foundation",
        "philanthropic"
    ],
    "wof:name":"Community Foundation",
    "wof:placetype":"venue"
},
  "geometry": {"coordinates":[-76.54942699999999,38.978907],"type":"Point"}
}