{
  "type": "Feature",
  "properties": {
    "addr:full":"800 S Broadway Baltimore MD 21231",
    "addr:housenumber":"800",
    "addr:postcode":"21231",
    "addr:street":"S Broadway",
    "iso:country":"US",
    "sg:address":"800 S Broadway",
    "sg:city":"Baltimore",
    "sg:classifiers":[
        {
            "category":"Professional",
            "subcategory":"Lawyer & Legal Services",
            "type":"Services"
        }
    ],
    "sg:phone":"+1 410 342 2002",
    "sg:postcode":"21231",
    "sg:province":"MD",
    "wof:name":"Liset Bollazo-Dingle",
    "wof:placetype":"venue"
},
  "geometry": {"coordinates":[-76.593637,39.282554],"type":"Point"}
}