{
  "type": "Feature",
  "properties": {
    "addr:full":"2251 Wilkens Ave Baltimore MD 21223",
    "addr:housenumber":"2251",
    "addr:postcode":"21223",
    "addr:street":"Wilkens Ave",
    "iso:country":"US",
    "sg:address":"2251 Wilkens Ave",
    "sg:city":"Baltimore",
    "sg:classifiers":[
        {
            "category":"Restaurant",
            "type":"Food & Drink"
        }
    ],
    "sg:phone":"+1 410 624 0026",
    "sg:postcode":"21223",
    "sg:province":"MD",
    "wof:name":"B J Restaurant & Carry Out",
    "wof:placetype":"venue"
},
  "geometry": {"coordinates":[-76.651703,39.280201],"type":"Point"}
}