{
  "type": "Feature",
  "properties": {
    "iso:country":"US",
    "sg:address":"2802 Solomons Island Rd",
    "sg:city":"Edgewater",
    "sg:classifiers":[
        {
            "category":"Recreation",
            "subcategory":"Marina",
            "type":"Entertainment"
        }
    ],
    "sg:phone":"+1 410 263 8980",
    "sg:postcode":"21037",
    "sg:province":"MD",
    "sg:tags":[
        "repairing",
        "boat"
    ],
    "wof:name":"Annapolis Gelcoat & Fiberglass",
    "wof:placetype":"venue"
},
  "geometry": {"coordinates":[-76.551881,38.956125],"type":"Point"}
}