{
  "type": "Feature",
  "properties": {
    "iso:country":"US",
    "sg:address":"5908 Ritchie Hwy",
    "sg:city":"Baltimore",
    "sg:classifiers":[
        {
            "category":"Retail",
            "subcategory":"Car Wash",
            "type":"Services"
        }
    ],
    "sg:phone":"+1 410 636 5365",
    "sg:postcode":"21225",
    "sg:province":"MD",
    "wof:name":"Dr Car Wash",
    "wof:placetype":"venue"
},
  "geometry": {"coordinates":[-76.616032,39.211161],"type":"Point"}
}