{
  "type": "Feature",
  "properties": {
    "iso:country":"US",
    "sg:address":"229 S Bridge St",
    "sg:city":"Elkton",
    "sg:classifiers":[
        {
            "category":"Building & Trades",
            "subcategory":"Construction",
            "type":"Services"
        }
    ],
    "sg:phone":"+1 410 398 7017",
    "sg:postcode":"21921",
    "sg:province":"MD",
    "sg:tags":[
        "remodeling",
        "altering",
        "wallcoverings-installation",
        "wallpaper",
        "contractor",
        "acoustical",
        "painting"
    ],
    "wof:name":"Big D Painting",
    "wof:placetype":"venue"
},
  "geometry": {"coordinates":[-75.830026,39.603908],"type":"Point"}
}