{
  "type": "Feature",
  "properties": {
    "iso:country":"US",
    "sg:address":"400 W Lexington St Ste 40",
    "sg:city":"Baltimore",
    "sg:classifiers":[
        {
            "category":"Deli",
            "type":"Food & Drink"
        },
        {
            "category":"Food & Beverages",
            "subcategory":"Bakery",
            "type":"Retail Goods"
        }
    ],
    "sg:phone":"+1 410 752 1397",
    "sg:postcode":"21201",
    "sg:province":"MD",
    "sg:tags":[
        "sandwich"
    ],
    "wof:name":"Mary Mervis Delicatessen",
    "wof:placetype":"venue"
},
  "geometry": {"coordinates":[-76.620701,39.291632],"type":"Point"}
}