{
  "type": "Feature",
  "properties": {
    "addr:full":"2399 Jones Ln Wheaton MD 20902",
    "addr:housenumber":"2399",
    "addr:postcode":"20902",
    "addr:street":"Jones Ln",
    "iso:country":"US",
    "sg:address":"2399 Jones Ln",
    "sg:city":"Wheaton",
    "sg:classifiers":[
        {
            "category":"Real Estate",
            "subcategory":"Real Estate Operator",
            "type":"Services"
        }
    ],
    "sg:phone":"+1 301 929 2828",
    "sg:postcode":"20902",
    "sg:province":"MD",
    "sg:tags":[
        "apartment"
    ],
    "wof:name":"Glen",
    "wof:placetype":"venue"
},
  "geometry": {"coordinates":[-77.04864000000001,39.054048],"type":"Point"}
}