{
  "type": "Feature",
  "properties": {
    "iso:country":"US",
    "sg:address":"600 Baltimore Annapolis Blvd",
    "sg:city":"Severna Park",
    "sg:classifiers":[
        {
            "category":"Shopping",
            "subcategory":"Gifts & Souvenirs",
            "type":"Retail Goods"
        }
    ],
    "sg:phone":"+1 410 544 6600",
    "sg:postcode":"21146",
    "sg:province":"MD",
    "sg:tags":[
        "shop"
    ],
    "wof:name":"Accents",
    "wof:placetype":"venue"
},
  "geometry": {"coordinates":[-76.54603299999999,39.071183],"type":"Point"}
}