{
  "type": "Feature",
  "properties": {
    "addr:full":"206 Patuxent Rd Laurel MD 20707",
    "addr:housenumber":"206",
    "addr:postcode":"20707",
    "addr:street":"Patuxent Rd",
    "iso:country":"US",
    "sg:address":"206 Patuxent Rd",
    "sg:city":"Laurel",
    "sg:classifiers":[
        {
            "category":"Professional",
            "subcategory":"Business Services",
            "type":"Services"
        }
    ],
    "sg:phone":"+1 301 725 3357",
    "sg:postcode":"20707",
    "sg:province":"MD",
    "sg:tags":[
        "interior",
        "designer"
    ],
    "sg:website":"www.kittrellinteriors.com",
    "wof:name":"Kittrell Interiors",
    "wof:placetype":"venue"
},
  "geometry": {"coordinates":[-76.86336300000001,39.108844],"type":"Point"}
}