{
  "type": "Feature",
  "properties": {
    "addr:full":"1001 Pine Heights Ave Baltimore MD 21229",
    "addr:housenumber":"1001",
    "addr:postcode":"21229",
    "addr:street":"Pine Heights Ave",
    "iso:country":"US",
    "sg:address":"1001 Pine Heights Ave",
    "sg:city":"Baltimore",
    "sg:classifiers":[
        {
            "category":"Health Services",
            "subcategory":"Doctor",
            "type":"Services"
        }
    ],
    "sg:phone":"+1 410 525 1515",
    "sg:postcode":"21229",
    "sg:province":"MD",
    "sg:tags":[
        "physician",
        "surgeon"
    ],
    "sg:website":"www.yourhealthyskin.com",
    "wof:name":"Carolyn J Pass MD",
    "wof:placetype":"venue"
},
  "geometry": {"coordinates":[-76.675679,39.26982],"type":"Point"}
}