{
  "type": "Feature",
  "properties": {
    "iso:country":"US",
    "sg:address":"6611 Sulky Ln",
    "sg:city":"Rockville",
    "sg:classifiers":[
        {
            "category":"Manufacturing",
            "subcategory":"Printing",
            "type":"Manufacturing & Wholesale Goods"
        }
    ],
    "sg:phone":"+1 301 984 4441",
    "sg:postcode":"20852",
    "sg:province":"MD",
    "sg:tags":[
        "publishing"
    ],
    "wof:name":"Lisa Simpson & Associates",
    "wof:placetype":"venue"
},
  "geometry": {"coordinates":[-77.137508,39.05104],"type":"Point"}
}