{
  "type": "Feature",
  "properties": {
    "iso:country":"US",
    "sg:address":"5291 Corporate Dr",
    "sg:city":"Frederick",
    "sg:classifiers":[
        {
            "category":"Organizations",
            "subcategory":"Professional Association",
            "type":"Services"
        }
    ],
    "sg:phone":"+1 301 668 7230",
    "sg:postcode":"21703",
    "sg:province":"MD",
    "wof:name":"Diesel Technology Forum",
    "wof:placetype":"venue"
},
  "geometry": {"coordinates":[-77.419412,39.37813],"type":"Point"}
}