{
  "type": "Feature",
  "properties": {
    "iso:country":"US",
    "sg:address":"6620 Napoli Rd",
    "sg:city":"Temple Hills",
    "sg:classifiers":[
        {
            "category":"Wholesale",
            "subcategory":"Auto Parts",
            "type":"Manufacturing & Wholesale Goods"
        }
    ],
    "sg:phone":"+1 301 433 0036",
    "sg:postcode":"20748",
    "sg:province":"MD",
    "sg:tags":[
        "equipment",
        "towing"
    ],
    "wof:name":"L W Towing",
    "wof:placetype":"venue"
},
  "geometry": {"coordinates":[-76.911013,38.79865],"type":"Point"}
}