{
  "type": "Feature",
  "properties": {
    "addr:full":"1980 N Market St Frederick MD 21701",
    "addr:housenumber":"1980",
    "addr:postcode":"21701",
    "addr:street":"N Market St",
    "iso:country":"US",
    "sg:address":"1980 N Market St",
    "sg:city":"Frederick",
    "sg:classifiers":[
        {
            "category":"Government",
            "subcategory":"Office",
            "type":"Public Place"
        }
    ],
    "sg:phone":"+1 301 694 1754",
    "sg:postcode":"21701",
    "sg:province":"MD",
    "sg:tags":[
        "govt",
        "city"
    ],
    "wof:name":"Water Treatment Facilities",
    "wof:placetype":"venue"
},
  "geometry": {"coordinates":[-77.392673,39.445131],"type":"Point"}
}