{
  "type": "Feature",
  "properties": {
    "addr:full":"7713 Bellona Ave Baltimore MD 21204",
    "addr:housenumber":"7713",
    "addr:postcode":"21204",
    "addr:street":"Bellona Ave",
    "iso:country":"US",
    "sg:address":"7713 Bellona Ave",
    "sg:city":"Baltimore",
    "sg:classifiers":[
        {
            "category":"Food & Beverages",
            "subcategory":"Bakery",
            "type":"Retail Goods"
        }
    ],
    "sg:phone":"+1 410 823 6077",
    "sg:postcode":"21204",
    "sg:province":"MD",
    "sg:tags":[
        "baker"
    ],
    "wof:name":"Graul's Market Inc",
    "wof:placetype":"venue"
},
  "geometry": {"coordinates":[-76.64509,39.398985],"type":"Point"}
}