{
  "type": "Feature",
  "properties": {
    "iso:country":"US",
    "sg:address":"505 Quince Orchard Rd",
    "sg:city":"Gaithersburg",
    "sg:classifiers":[
        {
            "category":"Utilities",
            "subcategory":"Mobile Phone",
            "type":"Services"
        },
        {
            "category":"Coffee & Tea",
            "type":"Food & Drink"
        }
    ],
    "sg:phone":"+1 301 987 2250",
    "sg:postcode":"20878",
    "sg:province":"MD",
    "sg:tags":[
        "shop",
        "wi-fi",
        "espresso",
        "hotspot",
        "restaurant"
    ],
    "sg:website":"http://www.starbuckscoffee.com",
    "wof:name":"Starbucks Coffee",
    "wof:placetype":"venue"
},
  "geometry": {"coordinates":[-77.220078,39.145119],"type":"Point"}
}