{
  "type": "Feature",
  "properties": {
    "addr:full":"2205 Bel Pre Rd Silver Spring MD 20906",
    "addr:postcode":"2205;20906",
    "addr:street":"Pre Rd",
    "iso:country":"US",
    "sg:address":"2205 Bel Pre Rd",
    "sg:city":"Silver Spring",
    "sg:classifiers":[
        {
            "category":"Coffee & Tea",
            "type":"Food & Drink"
        }
    ],
    "sg:menulink":"http://www.allmenus.com/md/silver-spring/119094-starbucks-coffee/menu/",
    "sg:phone":"+1 301 460 0409",
    "sg:postcode":"20906",
    "sg:province":"MD",
    "sg:tags":[
        "american"
    ],
    "wof:name":"Starbucks Coffee",
    "wof:placetype":"venue"
},
  "geometry": {"coordinates":[-77.046812,39.090528],"type":"Point"}
}