{
  "type": "Feature",
  "properties": {
    "iso:country":"US",
    "sg:address":"410 Highmeadow Ct",
    "sg:city":"Reisterstown",
    "sg:classifiers":[
        {
            "category":"Building & Trades",
            "subcategory":"Construction",
            "type":"Services"
        }
    ],
    "sg:phone":"+1 410 526 5563",
    "sg:postcode":"21136",
    "sg:province":"MD",
    "sg:tags":[
        "restoration",
        "preservation"
    ],
    "wof:name":"Acoustical Restoration Systems",
    "wof:placetype":"venue"
},
  "geometry": {"coordinates":[-76.81395500000001,39.458716],"type":"Point"}
}