{
  "type": "Feature",
  "properties": {
    "iso:country":"US",
    "sg:address":"11125 Rockville Pike",
    "sg:city":"Rockville",
    "sg:classifiers":[
        {
            "category":"Health Services",
            "subcategory":"Health Practitioner",
            "type":"Services"
        }
    ],
    "sg:phone":"+1 301 984 4099",
    "sg:postcode":"20852",
    "sg:province":"MD",
    "sg:tags":[
        "therapist",
        "physical"
    ],
    "wof:name":"Advance Physical Therapy Sport",
    "wof:placetype":"venue"
},
  "geometry": {"coordinates":[-77.10920900000001,39.039428],"type":"Point"}
}