{
  "type": "Feature",
  "properties": {
    "iso:country":"US",
    "sg:address":"43 N Philadelphia Blvd",
    "sg:city":"Aberdeen",
    "sg:classifiers":[
        {
            "category":"Restaurant",
            "type":"Food & Drink"
        }
    ],
    "sg:phone":"+1 410 272 6030",
    "sg:postcode":"21001",
    "sg:province":"MD",
    "wof:name":"Toscani's Pancake & Pasta",
    "wof:placetype":"venue"
},
  "geometry": {"coordinates":[-76.16258,39.510527],"type":"Point"}
}