{
  "type": "Feature",
  "properties": {
    "iso:country":"US",
    "sg:address":"505 Rollins Ave",
    "sg:city":"Capitol Heights",
    "sg:classifiers":[
        {
            "category":"Professional",
            "subcategory":"Business Services",
            "type":"Services"
        }
    ],
    "sg:phone":"+1 301 440 5343",
    "sg:postcode":"20743",
    "sg:province":"MD",
    "wof:name":"Andersn-Associates Trnspt Mgmt",
    "wof:placetype":"venue"
},
  "geometry": {"coordinates":[-76.90313999999999,38.883173],"type":"Point"}
}