{
  "type": "Feature",
  "properties": {
    "addr:full":"435 Prime Outlets Blvd Hagerstown MD 21740",
    "addr:housenumber":"435",
    "addr:postcode":"21740",
    "addr:street":"Outlets Blvd",
    "iso:country":"US",
    "sg:address":"435 Prime Outlets Blvd",
    "sg:city":"Hagerstown",
    "sg:classifiers":[
        {
            "category":"Shopping",
            "subcategory":"Clothing, Apparel, & Fashions",
            "type":"Retail Goods"
        }
    ],
    "sg:phone":"+1 301 739 5864",
    "sg:postcode":"21740",
    "sg:province":"MD",
    "wof:name":"Dress Barn",
    "wof:placetype":"venue"
},
  "geometry": {"coordinates":[-77.731286,39.609333],"type":"Point"}
}