{
  "type": "Feature",
  "properties": {
    "iso:country":"US",
    "sg:address":"6311 Pennsylvania Ave",
    "sg:city":"District Heights",
    "sg:classifiers":[
        {
            "category":"Real Estate",
            "subcategory":"Real Estate Operator",
            "type":"Services"
        }
    ],
    "sg:phone":"+1 301 735 3200",
    "sg:postcode":"20747",
    "sg:province":"MD",
    "sg:tags":[
        "apartment"
    ],
    "wof:name":"Park Berkshire Apts",
    "wof:placetype":"venue"
},
  "geometry": {"coordinates":[-76.8955,38.846802],"type":"Point"}
}