{
  "type": "Feature",
  "properties": {
    "iso:country":"US",
    "sg:address":"3166 New St",
    "sg:city":"Manchester",
    "sg:classifiers":[
        {
            "category":"Building & Trades",
            "subcategory":"Construction",
            "type":"Services"
        }
    ],
    "sg:phone":"+1 410 239 7915",
    "sg:postcode":"21102",
    "sg:province":"MD",
    "sg:tags":[
        "house"
    ],
    "wof:name":"Bachman Valley Builders",
    "wof:placetype":"venue"
},
  "geometry": {"coordinates":[-76.884117,39.656395],"type":"Point"}
}