{
  "type": "Feature",
  "properties": {
    "addr:full":"3803 Branch Ave Temple Hills MD 20748",
    "addr:housenumber":"3803",
    "addr:postcode":"20748",
    "addr:street":"Branch Ave",
    "iso:country":"US",
    "sg:address":"3803 Branch Ave",
    "sg:city":"Temple Hills",
    "sg:classifiers":[
        {
            "category":"Bakery",
            "type":"Food & Drink"
        }
    ],
    "sg:phone":"+1 301 423 2692",
    "sg:postcode":"20748",
    "sg:province":"MD",
    "sg:website":"www.tiffanysbakery.com",
    "wof:name":"Tiffany's Bakery",
    "wof:placetype":"venue"
},
  "geometry": {"coordinates":[-76.945773,38.838323],"type":"Point"}
}