{
  "type": "Feature",
  "properties": {
    "iso:country":"US",
    "sg:address":"9207 Harvest Rush Rd",
    "sg:city":"Owings Mills",
    "sg:classifiers":[
        {
            "category":"Professional",
            "subcategory":"Management & Consulting",
            "type":"Services"
        }
    ],
    "sg:phone":"+1 410 654 5413",
    "sg:postcode":"21117",
    "sg:province":"MD",
    "sg:tags":[
        "public",
        "relations"
    ],
    "wof:name":"Signature Promotions",
    "wof:placetype":"venue"
},
  "geometry": {"coordinates":[-76.744928,39.399203],"type":"Point"}
}