{
  "type": "Feature",
  "properties": {
    "iso:country":"US",
    "sg:address":"2112 Cross Trails Rd",
    "sg:city":"Baltimore",
    "sg:classifiers":[
        {
            "category":"Professional",
            "subcategory":"Computer Services",
            "type":"Services"
        }
    ],
    "sg:phone":"+1 410 265 1700",
    "sg:postcode":"21244",
    "sg:province":"MD",
    "sg:tags":[
        "internet"
    ],
    "wof:name":"Advanced Intelligent Network",
    "wof:placetype":"venue"
},
  "geometry": {"coordinates":[-76.781235,39.308824],"type":"Point"}
}