{
  "type": "Feature",
  "properties": {
    "addr:full":"4912 del Ray Ave Bethesda MD 20814",
    "addr:housenumber":"4912",
    "addr:postcode":"20814",
    "addr:street":"Del Ray Ave",
    "iso:country":"US",
    "sg:address":"4912 del Ray Ave",
    "sg:city":"Bethesda",
    "sg:classifiers":[
        {
            "category":"Real Estate",
            "subcategory":"Developer",
            "type":"Services"
        }
    ],
    "sg:phone":"+1 301 657 9900",
    "sg:postcode":"20814",
    "sg:province":"MD",
    "wof:name":"Quantum Co",
    "wof:placetype":"venue"
},
  "geometry": {"coordinates":[-77.10006799999999,38.988514],"type":"Point"}
}