{
  "type": "Feature",
  "properties": {
    "addr:full":"3115 Herbert St Baltimore MD 21216",
    "addr:housenumber":"3115",
    "addr:postcode":"21216",
    "addr:street":"Herbert St",
    "iso:country":"US",
    "sg:address":"3115 Herbert St",
    "sg:city":"Baltimore",
    "sg:classifiers":[
        {
            "category":"Retail",
            "subcategory":"Auto Repair",
            "type":"Services"
        }
    ],
    "sg:phone":"+1 410 462 3097",
    "sg:postcode":"21216",
    "sg:province":"MD",
    "sg:tags":[
        "repairing",
        "automobile"
    ],
    "wof:name":"Shorty's Garage",
    "wof:placetype":"venue"
},
  "geometry": {"coordinates":[-76.667603,39.309669],"type":"Point"}
}