{
  "type": "Feature",
  "properties": {
    "iso:country":"US",
    "sg:address":"101 W 22nd St",
    "sg:city":"Baltimore",
    "sg:classifiers":[
        {
            "category":"Health Services",
            "subcategory":"Hospital",
            "type":"Services"
        },
        {
            "category":"Health Services",
            "subcategory":"Nursing And Care Facility",
            "type":"Services"
        }
    ],
    "sg:phone":"+1 410 528 7200",
    "sg:postcode":"21218",
    "sg:province":"MD",
    "sg:tags":[
        "nurse",
        "registry"
    ],
    "wof:name":"A Ray Of Hope Inc Private Duty",
    "wof:placetype":"venue"
},
  "geometry": {"coordinates":[-76.618103,39.314152],"type":"Point"}
}