{
  "type": "Feature",
  "properties": {
    "addr:full":"14665 Rothgeb Dr Rockville MD 20850",
    "addr:housenumber":"14665",
    "addr:postcode":"20850",
    "addr:street":"Rothgeb Dr",
    "iso:country":"US",
    "sg:address":"14665 Rothgeb Dr",
    "sg:city":"Rockville",
    "sg:classifiers":[
        {
            "category":"Professional",
            "subcategory":"Research",
            "type":"Services"
        }
    ],
    "sg:phone":"+1 301 315 8460",
    "sg:postcode":"20850",
    "sg:province":"MD",
    "sg:tags":[
        "development",
        "laboratory"
    ],
    "sg:website":"www.mckessonbio.com",
    "wof:name":"Mc Kesson Corp",
    "wof:placetype":"venue"
},
  "geometry": {"coordinates":[-77.13328,39.09886],"type":"Point"}
}