{
  "type": "Feature",
  "properties": {
    "addr:full":"500 Frederick St Hagerstown MD 21740",
    "addr:housenumber":"500",
    "addr:postcode":"21740",
    "addr:street":"Frederick St",
    "iso:country":"US",
    "sg:address":"500 Frederick St",
    "sg:city":"Hagerstown",
    "sg:classifiers":[
        {
            "category":"Retail",
            "subcategory":"Auto Repair",
            "type":"Services"
        }
    ],
    "sg:phone":"+1 301 714 0202",
    "sg:postcode":"21740",
    "sg:province":"MD",
    "sg:tags":[
        "wrecker"
    ],
    "wof:name":"Blue Ridge Towing Inc",
    "wof:placetype":"venue"
},
  "geometry": {"coordinates":[-77.71638,39.63071],"type":"Point"}
}