{
  "type": "Feature",
  "properties": {
    "addr:full":"6902 Lachlan Cir Baltimore MD 21239",
    "addr:housenumber":"6902",
    "addr:postcode":"21239",
    "addr:street":"Lachlan Cir",
    "iso:country":"US",
    "sg:address":"6902 Lachlan Cir",
    "sg:city":"Baltimore",
    "sg:classifiers":[
        {
            "category":"Health Services",
            "subcategory":"Doctor",
            "type":"Services"
        }
    ],
    "sg:phone":"+1 410 821 1896",
    "sg:postcode":"21239",
    "sg:province":"MD",
    "sg:tags":[
        "physician",
        "surgeon"
    ],
    "wof:name":"Lourdes S Ramirez MD",
    "wof:placetype":"venue"
},
  "geometry": {"coordinates":[-76.58153799999999,39.385395],"type":"Point"}
}