{
  "type": "Feature",
  "properties": {
    "iso:country":"US",
    "sg:address":"10085 Red Run Blvd",
    "sg:city":"Owings Mills",
    "sg:classifiers":[
        {
            "category":"Health Services",
            "subcategory":"Doctor",
            "type":"Services"
        }
    ],
    "sg:phone":"+1 410 363 0777",
    "sg:postcode":"21117",
    "sg:province":"MD",
    "sg:tags":[
        "physician",
        "surgeon"
    ],
    "wof:name":"Maryland Orthopedics",
    "wof:placetype":"venue"
},
  "geometry": {"coordinates":[-76.78218699999999,39.400997],"type":"Point"}
}