{
  "type": "Feature",
  "properties": {
    "iso:country":"US",
    "sg:address":"7263 Dockside Ln",
    "sg:city":"Columbia",
    "sg:classifiers":[
        {
            "category":"Professional",
            "subcategory":"Management & Consulting",
            "type":"Services"
        }
    ],
    "sg:phone":"+1 410 995 6267",
    "sg:postcode":"21045",
    "sg:province":"MD",
    "wof:name":"Dennis G Saunders",
    "wof:placetype":"venue"
},
  "geometry": {"coordinates":[-76.846375,39.184745],"type":"Point"}
}