{
  "type": "Feature",
  "properties": {
    "addr:full":"3608 Milford Mill Rd Baltimore MD 21244",
    "addr:housenumber":"3608",
    "addr:postcode":"21244",
    "addr:street":"Milford Mill Rd",
    "iso:country":"US",
    "sg:address":"3608 Milford Mill Rd",
    "sg:city":"Baltimore",
    "sg:classifiers":[
        {
            "category":"Banks & Credit Unions",
            "subcategory":"Bank",
            "type":"Services"
        }
    ],
    "sg:phone":"+1 410 496 0918",
    "sg:postcode":"21244",
    "sg:province":"MD",
    "wof:name":"Wachovia Bank",
    "wof:placetype":"venue"
},
  "geometry": {"coordinates":[-76.75739799999999,39.356415],"type":"Point"}
}