{
  "type": "Feature",
  "properties": {
    "iso:country":"US",
    "sg:address":"213 E Main St",
    "sg:city":"Westminster",
    "sg:classifiers":[
        {
            "category":"Retail",
            "subcategory":"Repair Shop",
            "type":"Services"
        }
    ],
    "sg:phone":"+1 410 876 2453",
    "sg:postcode":"21157",
    "sg:province":"MD",
    "sg:tags":[
        "electrical"
    ],
    "wof:name":"Rainbow Vacuum",
    "wof:placetype":"venue"
},
  "geometry": {"coordinates":[-76.989773,39.569226],"type":"Point"}
}