{
  "type": "Feature",
  "properties": {
    "addr:full":"4523 Keswick Rd Baltimore MD 21210",
    "addr:housenumber":"4523",
    "addr:postcode":"21210",
    "addr:street":"Keswick Rd",
    "iso:country":"US",
    "sg:address":"4523 Keswick Rd",
    "sg:city":"Baltimore",
    "sg:classifiers":[
        {
            "category":"Retail",
            "subcategory":"Repair Shop",
            "type":"Services"
        },
        {
            "category":"Wholesale",
            "subcategory":"Construction Materials",
            "type":"Manufacturing & Wholesale Goods"
        }
    ],
    "sg:phone":"+1 410 558 2658",
    "sg:postcode":"21210",
    "sg:province":"MD",
    "sg:tags":[
        "refinish",
        "furniture",
        "caning",
        "supply"
    ],
    "wof:name":"Zizileuskas Furniture Restoration Inc",
    "wof:placetype":"venue"
},
  "geometry": {"coordinates":[-76.629879,39.344707],"type":"Point"}
}