{
  "type": "Feature",
  "properties": {
    "addr:full":"863 Whisper Dr Millersville MD 21108",
    "addr:housenumber":"863",
    "addr:postcode":"21108",
    "addr:street":"Whisper Dr",
    "iso:country":"US",
    "sg:address":"863 Whisper Dr",
    "sg:city":"Millersville",
    "sg:classifiers":[
        {
            "category":"Home & Garden",
            "subcategory":"Home Furnishings",
            "type":"Retail Goods"
        }
    ],
    "sg:phone":"+1 240 882 2020",
    "sg:postcode":"21108",
    "sg:province":"MD",
    "sg:tags":[
        "refinish",
        "bathtub",
        "sinks-repair"
    ],
    "wof:name":"Amazin Reglazin",
    "wof:placetype":"venue"
},
  "geometry": {"coordinates":[-76.644153,39.06186],"type":"Point"}
}