{
  "type": "Feature",
  "properties": {
    "iso:country":"US",
    "sg:address":"8515 Pelham Rd",
    "sg:city":"Bethesda",
    "sg:classifiers":[
        {
            "category":"Professional",
            "subcategory":"Computer Services",
            "type":"Services"
        }
    ],
    "sg:phone":"+1 301 564 5967",
    "sg:postcode":"20817",
    "sg:province":"MD",
    "sg:tags":[
        "consultant",
        "designer"
    ],
    "wof:name":"Advmath Systems Inc",
    "wof:placetype":"venue"
},
  "geometry": {"coordinates":[-77.121725,38.996268],"type":"Point"}
}