{
  "type": "Feature",
  "properties": {
    "addr:full":"5210 York Rd Baltimore MD 21212",
    "addr:housenumber":"5210",
    "addr:postcode":"21212",
    "addr:street":"York Rd",
    "iso:country":"US",
    "sg:address":"5210 York Rd",
    "sg:city":"Baltimore",
    "sg:classifiers":[
        {
            "category":"Organizations",
            "subcategory":"Religious Organization",
            "type":"Services"
        }
    ],
    "sg:phone":"+1 410 435 1550",
    "sg:postcode":"21212",
    "sg:province":"MD",
    "sg:tags":[
        "church"
    ],
    "wof:name":"Govans-Boundary PARISH Umc",
    "wof:placetype":"venue"
},
  "geometry": {"coordinates":[-76.609994,39.353923],"type":"Point"}
}