{
  "type": "Feature",
  "properties": {
    "iso:country":"US",
    "sg:address":"5820 Washington Blvd",
    "sg:city":"Elkridge",
    "sg:classifiers":[
        {
            "category":"Professional",
            "subcategory":"Management & Consulting",
            "type":"Services"
        },
        {
            "category":"Banks & Credit Unions",
            "subcategory":"Financial Services",
            "type":"Services"
        }
    ],
    "sg:phone":"+1 410 379 2005",
    "sg:postcode":"21075",
    "sg:province":"MD",
    "sg:tags":[
        "consultant",
        "financing",
        "planning"
    ],
    "wof:name":"Northstar Wealth Management",
    "wof:placetype":"venue"
},
  "geometry": {"coordinates":[-76.71051300000001,39.216306],"type":"Point"}
}