{
  "type": "Feature",
  "properties": {
    "iso:country":"US",
    "sg:address":"2205 Shorefield Rd",
    "sg:city":"Silver Spring",
    "sg:classifiers":[
        {
            "category":"Freight",
            "type":"Transportation"
        }
    ],
    "sg:phone":"+1 301 933 1008",
    "sg:postcode":"20902",
    "sg:province":"MD",
    "sg:tags":[
        "hauling",
        "trucking"
    ],
    "wof:name":"Anything Hauled",
    "wof:placetype":"venue"
},
  "geometry": {"coordinates":[-77.04721,39.053047],"type":"Point"}
}