{
  "type": "Feature",
  "properties": {
    "addr:full":"5906 Baltic St Capitol Heights MD 20743",
    "addr:housenumber":"5906",
    "addr:postcode":"20743",
    "addr:street":"Baltic St",
    "iso:country":"US",
    "sg:address":"5906 Baltic St",
    "sg:city":"Capitol Heights",
    "sg:classifiers":[
        {
            "category":"Shopping",
            "subcategory":"Gifts & Souvenirs",
            "type":"Retail Goods"
        }
    ],
    "sg:phone":"+1 301 350 8709",
    "sg:postcode":"20743",
    "sg:province":"MD",
    "wof:name":"Shanthi Annaleiah Unique Shop",
    "wof:placetype":"venue"
},
  "geometry": {"coordinates":[-76.905687,38.888075],"type":"Point"}
}