{
  "type": "Feature",
  "properties": {
    "iso:country":"US",
    "sg:address":"2415 Musgrove Rd Suite 203",
    "sg:city":"Silver Spring",
    "sg:classifiers":[
        {
            "category":"Health Services",
            "subcategory":"Doctor",
            "type":"Services"
        }
    ],
    "sg:phone":"+1 301 989 2300",
    "sg:postcode":"20904",
    "sg:province":"MD",
    "sg:tags":[
        "throat",
        "ear",
        "nose"
    ],
    "sg:website":"www.otoheadandneck.com",
    "wof:name":"Brian P Driscoll",
    "wof:placetype":"venue"
},
  "geometry": {"coordinates":[-76.96069300000001,39.067443],"type":"Point"}
}