{
  "type": "Feature",
  "properties": {
    "iso:country":"US",
    "sg:address":"8605 Wiles Ct",
    "sg:city":"Middletown",
    "sg:classifiers":[
        {
            "category":"Building & Trades",
            "subcategory":"Construction",
            "type":"Services"
        }
    ],
    "sg:phone":"+1 301 473 7233",
    "sg:postcode":"21769",
    "sg:province":"MD",
    "sg:tags":[
        "contractor"
    ],
    "wof:name":"Sherrard Design & Build",
    "wof:placetype":"venue"
},
  "geometry": {"coordinates":[-77.52057,39.470072],"type":"Point"}
}