{
  "type": "Feature",
  "properties": {
    "iso:country":"US",
    "sg:address":"207 Melvin Ave",
    "sg:city":"Grasonville",
    "sg:classifiers":[
        {
            "category":"Building & Trades",
            "subcategory":"Construction",
            "type":"Services"
        }
    ],
    "sg:phone":"+1 410 827 5617",
    "sg:postcode":"21638",
    "sg:province":"MD",
    "sg:tags":[
        "excavating",
        "contractor"
    ],
    "wof:name":"Pat's Excavation",
    "wof:placetype":"venue"
},
  "geometry": {"coordinates":[-76.204495,38.957195],"type":"Point"}
}