{
  "type": "Feature",
  "properties": {
    "iso:country":"US",
    "sg:address":"1330 Sulphur Spring Rd",
    "sg:city":"Halethorpe",
    "sg:classifiers":[
        {
            "category":"Building & Trades",
            "subcategory":"Construction",
            "type":"Services"
        }
    ],
    "sg:phone":"+1 410 737 4417",
    "sg:postcode":"21227",
    "sg:province":"MD",
    "sg:tags":[
        "plastering",
        "contractor"
    ],
    "wof:name":"M & N Plastering Inc",
    "wof:placetype":"venue"
},
  "geometry": {"coordinates":[-76.694089,39.247279],"type":"Point"}
}