{
  "type": "Feature",
  "properties": {
    "addr:full":"19825 Executive Park Cir Germantown MD 20874",
    "addr:housenumber":"19825",
    "addr:postcode":"20874",
    "addr:street":"Executive Park Cir",
    "iso:country":"US",
    "sg:address":"19825 Executive Park Cir",
    "sg:city":"Germantown",
    "sg:classifiers":[
        {
            "category":"Banks & Credit Unions",
            "subcategory":"Financial Services",
            "type":"Services"
        }
    ],
    "sg:phone":"+1 240 387 5702",
    "sg:postcode":"20874",
    "sg:province":"MD",
    "sg:tags":[
        "financing"
    ],
    "wof:name":"Landmark Funding",
    "wof:placetype":"venue"
},
  "geometry": {"coordinates":[-77.274064,39.181209],"type":"Point"}
}