{
  "type": "Feature",
  "properties": {
    "iso:country":"US",
    "sg:address":"3235 Magnolia Ave",
    "sg:city":"Halethorpe",
    "sg:classifiers":[
        {
            "category":"Restaurant",
            "type":"Food & Drink"
        }
    ],
    "sg:phone":"+1 410 789 8126",
    "sg:postcode":"21227",
    "sg:province":"MD",
    "wof:name":"Tokyo Sushi",
    "wof:placetype":"venue"
},
  "geometry": {"coordinates":[-76.638402,39.245278],"type":"Point"}
}