{
  "type": "Feature",
  "properties": {
    "iso:country":"US",
    "sg:address":"5 S Wisner St",
    "sg:city":"Frederick",
    "sg:classifiers":[
        {
            "category":"Food & Beverages",
            "subcategory":"Meat & Fish",
            "type":"Retail Goods"
        }
    ],
    "sg:phone":"+1 301 662 1392",
    "sg:postcode":"21701",
    "sg:province":"MD",
    "wof:name":"W & W Meat Poultry & Seafood",
    "wof:placetype":"venue"
},
  "geometry": {"coordinates":[-77.403584,39.41341],"type":"Point"}
}