{
  "type": "Feature",
  "properties": {
    "addr:full":"14757 Main St Upper Marlboro MD 20772",
    "addr:housenumber":"14757",
    "addr:postcode":"20772",
    "addr:street":"Main St",
    "iso:country":"US",
    "sg:address":"14757 Main St",
    "sg:city":"Upper Marlboro",
    "sg:classifiers":[
        {
            "category":"Real Estate",
            "subcategory":"Real Estate Services",
            "type":"Services"
        }
    ],
    "sg:phone":"+1 301 627 3555",
    "sg:postcode":"20772",
    "sg:province":"MD",
    "sg:tags":[
        "company",
        "title"
    ],
    "wof:name":"Title Abstract Svc",
    "wof:placetype":"venue"
},
  "geometry": {"coordinates":[-76.751454,38.816431],"type":"Point"}
}