{
  "type": "Feature",
  "properties": {
    "iso:country":"US",
    "sg:address":"15 McKinsey Rd",
    "sg:city":"Severna Park",
    "sg:classifiers":[
        {
            "category":"Professional",
            "subcategory":"Business Services",
            "type":"Services"
        }
    ],
    "sg:phone":"+1 410 544 7752",
    "sg:postcode":"21146",
    "sg:province":"MD",
    "wof:name":"Ecaped Artist Studio Inc",
    "wof:placetype":"venue"
},
  "geometry": {"coordinates":[-76.54189700000001,39.075242],"type":"Point"}
}