{
  "type": "Feature",
  "properties": {
    "iso:country":"US",
    "sg:address":"7502 Race Rd",
    "sg:city":"Hanover",
    "sg:classifiers":[
        {
            "category":"Professional",
            "subcategory":"Engineering",
            "type":"Services"
        }
    ],
    "sg:phone":"+1 410 799 3055",
    "sg:postcode":"21076",
    "sg:province":"MD",
    "sg:tags":[
        "electrical",
        "electronic",
        "engineer"
    ],
    "sg:website":"http://www.gardettoengineering.com",
    "wof:name":"Gardetto Engineering",
    "wof:placetype":"venue"
},
  "geometry": {"coordinates":[-76.742858,39.16169],"type":"Point"}
}