{
  "type": "Feature",
  "properties": {
    "addr:full":"5603 38th Ave Hyattsville MD 20782",
    "addr:housenumber":"5603",
    "addr:postcode":"20782",
    "addr:street":"38Th Ave",
    "iso:country":"US",
    "sg:address":"5603 38th Ave",
    "sg:city":"Hyattsville",
    "sg:classifiers":[
        {
            "category":"Wholesale",
            "subcategory":"Vending Machines",
            "type":"Manufacturing & Wholesale Goods"
        }
    ],
    "sg:phone":"+1 301 699 5883",
    "sg:postcode":"20782",
    "sg:province":"MD",
    "sg:tags":[
        "machines-parts",
        "machines-wholesale",
        "manufacturer",
        "supply"
    ],
    "wof:name":"B & A Associates",
    "wof:placetype":"venue"
},
  "geometry": {"coordinates":[-76.95363399999999,38.954348],"type":"Point"}
}