{
  "type": "Feature",
  "properties": {
    "iso:country":"US",
    "sg:address":"3901 Martin Luther King Jr Ave SW",
    "sg:city":"Washington",
    "sg:classifiers":[
        {
            "category":"Restaurant",
            "type":"Food & Drink"
        }
    ],
    "sg:phone":"+1 202 563 5849",
    "sg:postcode":"20032",
    "sg:province":"MD",
    "sg:tags":[
        "delicatessen"
    ],
    "wof:name":"Yip Chak Pui",
    "wof:placetype":"venue"
},
  "geometry": {"coordinates":[-77.008805,38.832871],"type":"Point"}
}