{
  "type": "Feature",
  "properties": {
    "addr:full":"6801 Moravia Park Dr Baltimore MD 21206",
    "addr:housenumber":"6801",
    "addr:postcode":"21206",
    "addr:street":"Moravia Park Dr",
    "iso:country":"US",
    "sg:address":"6801 Moravia Park Dr",
    "sg:city":"Baltimore",
    "sg:classifiers":[
        {
            "category":"Professional",
            "subcategory":"Engineering",
            "type":"Services"
        }
    ],
    "sg:phone":"+1 410 325 4090",
    "sg:postcode":"21206",
    "sg:province":"MD",
    "sg:tags":[
        "engineer"
    ],
    "sg:website":"www.reidrayco.com",
    "wof:name":"Rei DSSI",
    "wof:placetype":"venue"
},
  "geometry": {"coordinates":[-76.53234500000001,39.308668],"type":"Point"}
}