{
  "type": "Feature",
  "properties": {
    "addr:full":"313 W Main St Emmitsburg MD 21727",
    "addr:housenumber":"313",
    "addr:postcode":"21727",
    "addr:street":"W Main St",
    "iso:country":"US",
    "sg:address":"313 W Main St",
    "sg:city":"Emmitsburg",
    "sg:classifiers":[
        {
            "category":"Organizations",
            "subcategory":"Religious Organization",
            "type":"Services"
        }
    ],
    "sg:phone":"+1 301 447 3740",
    "sg:postcode":"21727",
    "sg:province":"MD",
    "sg:tags":[
        "church"
    ],
    "wof:name":"Trinity United Methodist",
    "wof:placetype":"venue"
},
  "geometry": {"coordinates":[-77.329778,39.705274],"type":"Point"}
}