{
  "type": "Feature",
  "properties": {
    "addr:full":"5511 York Rd Baltimore MD 21212",
    "addr:housenumber":"5511",
    "addr:postcode":"21212",
    "addr:street":"York Rd",
    "iso:country":"US",
    "sg:address":"5511 York Rd",
    "sg:city":"Baltimore",
    "sg:classifiers":[
        {
            "category":"Wholesale",
            "subcategory":"Durable Goods & Equipment",
            "type":"Manufacturing & Wholesale Goods"
        }
    ],
    "sg:phone":"+1 410 323 0208",
    "sg:postcode":"21212",
    "sg:province":"MD",
    "sg:tags":[
        "exporter"
    ],
    "wof:name":"S & D Intl Inc",
    "wof:placetype":"venue"
},
  "geometry": {"coordinates":[-76.60990200000001,39.357405],"type":"Point"}
}