{
  "type": "Feature",
  "properties": {
    "iso:country":"US",
    "sg:address":"2002 Indian Head Rd",
    "sg:city":"Towson",
    "sg:classifiers":[
        {
            "category":"Education",
            "subcategory":"Special Training",
            "type":"Public Place"
        }
    ],
    "sg:phone":"+1 410 583 7954",
    "sg:postcode":"21204",
    "sg:province":"MD",
    "sg:tags":[
        "aid",
        "instruction",
        "safety",
        "first"
    ],
    "wof:name":"John F Rekus & Associates Ltd",
    "wof:placetype":"venue"
},
  "geometry": {"coordinates":[-76.65677100000001,39.39392],"type":"Point"}
}