{
  "type": "Feature",
  "properties": {
    "iso:country":"US",
    "sg:address":"5550 Nicholson Ln",
    "sg:city":"Rockville",
    "sg:classifiers":[
        {
            "category":"Retail",
            "subcategory":"Repair Shop",
            "type":"Services"
        }
    ],
    "sg:phone":"+1 301 816 0076",
    "sg:postcode":"20852",
    "sg:province":"MD",
    "sg:tags":[
        "television",
        "radio"
    ],
    "wof:name":"Video & Audio Svc Co",
    "wof:placetype":"venue"
},
  "geometry": {"coordinates":[-77.110715,39.044803],"type":"Point"}
}