{
  "type": "Feature",
  "properties": {
    "addr:full":"2954 Sunderland Ct Abingdon MD 21009",
    "addr:housenumber":"2954",
    "addr:postcode":"21009",
    "addr:street":"Sunderland Ct",
    "iso:country":"US",
    "sg:address":"2954 Sunderland Ct",
    "sg:city":"Abingdon",
    "sg:classifiers":[
        {
            "category":"Building & Trades",
            "subcategory":"Construction",
            "type":"Services"
        }
    ],
    "sg:phone":"+1 410 515 6130",
    "sg:postcode":"21009",
    "sg:province":"MD",
    "sg:tags":[
        "wallcoverings-installation",
        "wallpaper",
        "painting",
        "contractor"
    ],
    "wof:name":"O'malley Painting Inc",
    "wof:placetype":"venue"
},
  "geometry": {"coordinates":[-76.29902300000001,39.48072],"type":"Point"}
}