{
  "type": "Feature",
  "properties": {
    "iso:country":"US",
    "sg:address":"505 Blue Ball Rd",
    "sg:city":"Elkton",
    "sg:classifiers":[
        {
            "category":"Wholesale",
            "subcategory":"Machinery & Supplies",
            "type":"Manufacturing & Wholesale Goods"
        }
    ],
    "sg:phone":"+1 410 398 4142",
    "sg:postcode":"21921",
    "sg:province":"MD",
    "sg:tags":[
        "farm",
        "equipment"
    ],
    "wof:name":"Mid-Atlantic Svc",
    "wof:placetype":"venue"
},
  "geometry": {"coordinates":[-75.851688,39.621287],"type":"Point"}
}