{
  "type": "Feature",
  "properties": {
    "addr:full":"409 Washington Ave Ste 1000 Towson MD 21204",
    "addr:housenumber":"409",
    "addr:postcode":"21204",
    "addr:street":"Washington Ave Ste 1000",
    "iso:country":"US",
    "sg:address":"409 Washington Ave Ste 1000",
    "sg:city":"Towson",
    "sg:classifiers":[
        {
            "category":"Professional",
            "subcategory":"Lawyer & Legal Services",
            "type":"Services"
        }
    ],
    "sg:phone":"+1 410 823 5003",
    "sg:postcode":"21204",
    "sg:province":"MD",
    "sg:tags":[
        "litigation",
        "attorney",
        "practice",
        "tort",
        "appellate"
    ],
    "wof:name":"Buckler, Patrick R. - The Law Offices of Spence & Buckler, P.C.",
    "wof:placetype":"venue"
},
  "geometry": {"coordinates":[-76.605394,39.399713],"type":"Point"}
}