{
  "type": "Feature",
  "properties": {
    "addr:full":"13236 Bellevue St Silver Spring MD 20904",
    "addr:housenumber":"13236",
    "addr:postcode":"20904",
    "addr:street":"Bellevue St",
    "iso:country":"US",
    "sg:address":"13236 Bellevue St",
    "sg:city":"Silver Spring",
    "sg:classifiers":[
        {
            "category":"Personal",
            "subcategory":"Beauty Salon",
            "type":"Services"
        }
    ],
    "sg:phone":"+1 301 572 3965",
    "sg:postcode":"20904",
    "sg:province":"MD",
    "wof:name":"Nail Salon",
    "wof:placetype":"venue"
},
  "geometry": {"coordinates":[-76.94399199999999,39.061712],"type":"Point"}
}