{
  "type": "Feature",
  "properties": {
    "iso:country":"US",
    "sg:address":"1335 Rockville Pike",
    "sg:city":"Rockville",
    "sg:classifiers":[
        {
            "category":"Real Estate",
            "subcategory":"Real Estate Agent",
            "type":"Services"
        }
    ],
    "sg:phone":"+1 301 309 3868",
    "sg:postcode":"20852",
    "sg:province":"MD",
    "sg:tags":[
        "investment"
    ],
    "wof:name":"K & Y Amer Invstmnt Properties",
    "wof:placetype":"venue"
},
  "geometry": {"coordinates":[-77.129356,39.068171],"type":"Point"}
}