{
  "type": "Feature",
  "properties": {
    "addr:full":"1041 Maryland Ave Hagerstown MD 21740",
    "addr:housenumber":"1041",
    "addr:postcode":"21740",
    "addr:street":"Maryland Ave",
    "iso:country":"US",
    "sg:address":"1041 Maryland Ave",
    "sg:city":"Hagerstown",
    "sg:classifiers":[
        {
            "category":"Restaurant",
            "type":"Food & Drink"
        }
    ],
    "sg:phone":"+1 240 420 5955",
    "sg:postcode":"21740",
    "sg:province":"MD",
    "wof:name":"China Buffet",
    "wof:placetype":"venue"
},
  "geometry": {"coordinates":[-77.732562,39.623553],"type":"Point"}
}