{
  "type": "Feature",
  "properties": {
    "addr:full":"709 Morgnec Rd Chestertown MD 21620",
    "addr:housenumber":"709",
    "addr:postcode":"21620",
    "addr:street":"Morgnec Rd",
    "iso:country":"US",
    "sg:address":"709 Morgnec Rd",
    "sg:city":"Chestertown",
    "sg:classifiers":[
        {
            "category":"Government",
            "subcategory":"Office",
            "type":"Public Place"
        }
    ],
    "sg:phone":"+1 410 778 7439",
    "sg:postcode":"21620",
    "sg:province":"MD",
    "sg:tags":[
        "program",
        "administrative"
    ],
    "wof:name":"Public Works",
    "wof:placetype":"venue"
},
  "geometry": {"coordinates":[-76.053169,39.228075],"type":"Point"}
}