{
  "type": "Feature",
  "properties": {
    "addr:full":"12520 Heurich Rd Silver Spring MD 20902",
    "addr:housenumber":"12520",
    "addr:postcode":"20902",
    "addr:street":"Heurich Rd",
    "iso:country":"US",
    "sg:address":"12520 Heurich Rd",
    "sg:city":"Silver Spring",
    "sg:classifiers":[
        {
            "category":"Social Services",
            "subcategory":"Child Care",
            "type":"Services"
        }
    ],
    "sg:phone":"+1 301 949 2455",
    "sg:postcode":"20902",
    "sg:province":"MD",
    "wof:name":"Kids After Hours Inc",
    "wof:placetype":"venue"
},
  "geometry": {"coordinates":[-77.039939,39.061293],"type":"Point"}
}