{
  "type": "Feature",
  "properties": {
    "iso:country":"US",
    "sg:address":"3812 Charred Oak Dr",
    "sg:city":"Fort Washington",
    "sg:classifiers":[
        {
            "category":"Building & Trades",
            "subcategory":"Construction",
            "type":"Services"
        }
    ],
    "sg:phone":"+1 301 248 7442",
    "sg:postcode":"20744",
    "sg:province":"MD",
    "sg:tags":[
        "concrete",
        "contractor"
    ],
    "wof:name":"George Ryans Construction Co",
    "wof:placetype":"venue"
},
  "geometry": {"coordinates":[-76.941005,38.76619],"type":"Point"}
}