{
  "type": "Feature",
  "properties": {
    "addr:full":"5522 Cordona St Lanham MD 20706",
    "addr:housenumber":"5522",
    "addr:postcode":"20706",
    "addr:street":"Cordona St",
    "iso:country":"US",
    "sg:address":"5522 Cordona St",
    "sg:city":"Lanham",
    "sg:classifiers":[
        {
            "category":"Building & Trades",
            "subcategory":"Cleaning & Sanitation",
            "type":"Services"
        }
    ],
    "sg:phone":"+1 301 459 4368",
    "sg:postcode":"20706",
    "sg:province":"MD",
    "sg:tags":[
        "maintenance"
    ],
    "wof:name":"Diezcanseco Glady S In Es",
    "wof:placetype":"venue"
},
  "geometry": {"coordinates":[-76.85357999999999,38.959396],"type":"Point"}
}