{
  "type": "Feature",
  "properties": {
    "iso:country":"US",
    "sg:address":"5001 Wilson Ln 2nd Fl",
    "sg:city":"Bethesda",
    "sg:classifiers":[
        {
            "category":"Education",
            "subcategory":"Special Training",
            "type":"Public Place"
        }
    ],
    "sg:phone":"+1 301 718 0809",
    "sg:postcode":"20814",
    "sg:province":"MD",
    "sg:tags":[
        "school",
        "art"
    ],
    "sg:website":"www.studioneptune.com",
    "wof:name":"Studio Neptune",
    "wof:placetype":"venue"
},
  "geometry": {"coordinates":[-77.099172,38.987413],"type":"Point"}
}