{
  "type": "Feature",
  "properties": {
    "iso:country":"US",
    "sg:address":"7901 Wisconsin Ave",
    "sg:city":"Bethesda",
    "sg:classifiers":[
        {
            "category":"Banks & Credit Unions",
            "subcategory":"Financial Services",
            "type":"Services"
        }
    ],
    "sg:phone":"+1 301 907 2000",
    "sg:postcode":"20814",
    "sg:province":"MD",
    "sg:tags":[
        "broker",
        "mortgage"
    ],
    "wof:name":"Wachovia Mortgage Corporation",
    "wof:placetype":"venue"
},
  "geometry": {"coordinates":[-77.095398,38.9897],"type":"Point"}
}