{
  "type": "Feature",
  "properties": {
    "iso:country":"US",
    "sg:address":"12401 Kiln Ct",
    "sg:city":"Beltsville",
    "sg:classifiers":[
        {
            "category":"Professional",
            "type":"Services"
        }
    ],
    "sg:phone":"+1 301 419 2970",
    "sg:postcode":"20705",
    "sg:province":"MD",
    "sg:tags":[
        "establishment"
    ],
    "sg:website":"www.criticalservices.com",
    "wof:name":"Critical Site Systems",
    "wof:placetype":"venue"
},
  "geometry": {"coordinates":[-76.888998,39.061593],"type":"Point"}
}