{
  "type": "Feature",
  "properties": {
    "addr:full":"319 W Lexington St Baltimore MD 21201",
    "addr:housenumber":"319",
    "addr:postcode":"21201",
    "addr:street":"W Lexington St",
    "iso:country":"US",
    "sg:address":"319 W Lexington St",
    "sg:city":"Baltimore",
    "sg:classifiers":[
        {
            "category":"Shopping",
            "subcategory":"Shoes",
            "type":"Retail Goods"
        }
    ],
    "sg:phone":"+1 410 234 8913",
    "sg:postcode":"21201",
    "sg:province":"MD",
    "sg:tags":[
        "store"
    ],
    "sg:website":"www.footlocker.com",
    "wof:name":"Foot Locker",
    "wof:placetype":"venue"
},
  "geometry": {"coordinates":[-76.62069700000001,39.291302],"type":"Point"}
}