{
  "type": "Feature",
  "properties": {
    "addr:full":"2101 Frederick Ave Baltimore MD 21223",
    "addr:housenumber":"2101",
    "addr:postcode":"21223",
    "addr:street":"Frederick Ave",
    "iso:country":"US",
    "sg:address":"2101 Frederick Ave",
    "sg:city":"Baltimore",
    "sg:classifiers":[
        {
            "category":"Organizations",
            "subcategory":"Religious Organization",
            "type":"Services"
        }
    ],
    "sg:phone":"+1 410 566 2620",
    "sg:postcode":"21223",
    "sg:province":"MD",
    "wof:name":"New Tabernacle Baptist Church",
    "wof:placetype":"venue"
},
  "geometry": {"coordinates":[-76.650305,39.285672],"type":"Point"}
}