{
  "type": "Feature",
  "properties": {
    "addr:full":"1501 Harris Mill Rd Parkton MD 21120",
    "addr:housenumber":"1501",
    "addr:postcode":"21120",
    "addr:street":"Harris Mill Rd",
    "iso:country":"US",
    "sg:address":"1501 Harris Mill Rd",
    "sg:city":"Parkton",
    "sg:classifiers":[
        {
            "category":"Travel",
            "subcategory":"Hotels & Motels",
            "type":"Entertainment"
        }
    ],
    "sg:phone":"+1 410 343 1089",
    "sg:postcode":"21120",
    "sg:province":"MD",
    "sg:tags":[
        "membership",
        "lodging"
    ],
    "wof:name":"North County Coalition Inc",
    "wof:placetype":"venue"
},
  "geometry": {"coordinates":[-76.62136099999999,39.7158],"type":"Point"}
}