{
  "type": "Feature",
  "properties": {
    "iso:country":"US",
    "sg:address":"200 Rollingfield Rd",
    "sg:city":"Baltimore",
    "sg:classifiers":[
        {
            "category":"Shopping",
            "subcategory":"Used Merchandise",
            "type":"Retail Goods"
        }
    ],
    "sg:phone":"+1 410 788 4499",
    "sg:postcode":"21228",
    "sg:province":"MD",
    "wof:name":"Cobblestone Antiques & Co",
    "wof:placetype":"venue"
},
  "geometry": {"coordinates":[-76.759885,39.269012],"type":"Point"}
}