{
  "type": "Feature",
  "properties": {
    "iso:country":"US",
    "sg:address":"5501 Roland Ave",
    "sg:city":"Baltimore",
    "sg:classifiers":[
        {
            "category":"Professional",
            "subcategory":"Business Services",
            "type":"Services"
        }
    ],
    "sg:phone":"+1 410 532 9320",
    "sg:postcode":"21210",
    "sg:province":"MD",
    "wof:name":"Swani Associates Inc",
    "wof:placetype":"venue"
},
  "geometry": {"coordinates":[-76.634515,39.362711],"type":"Point"}
}