{
  "type": "Feature",
  "properties": {
    "iso:country":"US",
    "sg:address":"2900 Dede Rd",
    "sg:city":"Finksburg",
    "sg:classifiers":[
        {
            "category":"Utilities",
            "subcategory":"Refuse",
            "type":"Services"
        }
    ],
    "sg:phone":"+1 410 526 3535",
    "sg:postcode":"21048",
    "sg:province":"MD",
    "sg:tags":[
        "garbage",
        "collection"
    ],
    "sg:website":"www.roll-offexpress.com",
    "wof:name":"Roll-Off Express",
    "wof:placetype":"venue"
},
  "geometry": {"coordinates":[-76.88311,39.494068],"type":"Point"}
}