{
  "type": "Feature",
  "properties": {
    "addr:full":"1309 Harding Ln Silver Spring MD 20905",
    "addr:housenumber":"1309",
    "addr:postcode":"20905",
    "addr:street":"Harding Ln",
    "iso:country":"US",
    "sg:address":"1309 Harding Ln",
    "sg:city":"Silver Spring",
    "sg:classifiers":[
        {
            "category":"Building & Trades",
            "subcategory":"Construction",
            "type":"Services"
        }
    ],
    "sg:phone":"+1 301 879 9810",
    "sg:postcode":"20905",
    "sg:province":"MD",
    "sg:tags":[
        "hanging",
        "contractor"
    ],
    "wof:name":"Falcon Painting",
    "wof:placetype":"venue"
},
  "geometry": {"coordinates":[-76.987982,39.116464],"type":"Point"}
}