{
  "type": "Feature",
  "properties": {
    "iso:country":"US",
    "sg:address":"2422 Sandymount Rd",
    "sg:city":"Finksburg",
    "sg:classifiers":[
        {
            "category":"Building & Trades",
            "subcategory":"Construction",
            "type":"Services"
        }
    ],
    "sg:phone":"+1 410 848 4771",
    "sg:postcode":"21048",
    "sg:province":"MD",
    "sg:tags":[
        "paving",
        "contractor"
    ],
    "wof:name":"Carroll Garland Paving Inc",
    "wof:placetype":"venue"
},
  "geometry": {"coordinates":[-76.911584,39.532674],"type":"Point"}
}