{
  "type": "Feature",
  "properties": {
    "iso:country":"US",
    "sg:address":"10 Center Dr",
    "sg:city":"Bethesda",
    "sg:classifiers":[
        {
            "category":"Health Services",
            "subcategory":"Doctor",
            "type":"Services"
        }
    ],
    "sg:phone":"+1 301 496 5610",
    "sg:postcode":"20892",
    "sg:province":"MD",
    "sg:tags":[
        "physician",
        "surgeon"
    ],
    "wof:name":"Nat'l Institute Of Health",
    "wof:placetype":"venue"
},
  "geometry": {"coordinates":[-77.10466,39.002544],"type":"Point"}
}