{
  "type": "Feature",
  "properties": {
    "addr:full":"1348 Division St Baltimore MD 21217",
    "addr:housenumber":"1348",
    "addr:postcode":"21217",
    "addr:street":"Division St",
    "iso:country":"US",
    "sg:address":"1348 Division St",
    "sg:city":"Baltimore",
    "sg:classifiers":[
        {
            "category":"Personal",
            "subcategory":"Beauty Salon",
            "type":"Services"
        }
    ],
    "sg:phone":"+1 410 523 9337",
    "sg:postcode":"21217",
    "sg:province":"MD",
    "wof:name":"First Class Unisex",
    "wof:placetype":"venue"
},
  "geometry": {"coordinates":[-76.63027599999999,39.301543],"type":"Point"}
}