{
  "type": "Feature",
  "properties": {
    "iso:country":"US",
    "sg:address":"123 Camden St",
    "sg:city":"Salisbury",
    "sg:classifiers":[
        {
            "category":"Professional",
            "type":"Services"
        }
    ],
    "sg:phone":"+1 410 749 5191",
    "sg:postcode":"21801",
    "sg:province":"MD",
    "sg:tags":[
        "establishment"
    ],
    "wof:name":"Schilling's",
    "wof:placetype":"venue"
},
  "geometry": {"coordinates":[-75.601159,38.364937],"type":"Point"}
}