{
  "type": "Feature",
  "properties": {
    "iso:country":"US",
    "sg:address":"1600 Havenwood Rd",
    "sg:city":"Baltimore",
    "sg:classifiers":[
        {
            "category":"Food & Beverages",
            "subcategory":"Groceries & Convenience Stores",
            "type":"Retail Goods"
        }
    ],
    "sg:phone":"+1 410 354 3417",
    "sg:postcode":"21218",
    "sg:province":"MD",
    "sg:tags":[
        "grocer"
    ],
    "wof:name":"J Best Enterprises Inc",
    "wof:placetype":"venue"
},
  "geometry": {"coordinates":[-76.58847299999999,39.340595],"type":"Point"}
}