{
  "type": "Feature",
  "properties": {
    "iso:country":"US",
    "sg:address":"1305 S Division St",
    "sg:city":"Salisbury",
    "sg:classifiers":[
        {
            "category":"Retail",
            "subcategory":"Animal Services",
            "type":"Services"
        }
    ],
    "sg:phone":"+1 410 548 2110",
    "sg:postcode":"21804",
    "sg:province":"MD",
    "sg:tags":[
        "pet",
        "boarding",
        "sitting"
    ],
    "wof:name":"Salisbury Maryland Kennel Club",
    "wof:placetype":"venue"
},
  "geometry": {"coordinates":[-75.59909,38.340045],"type":"Point"}
}