{
  "type": "Feature",
  "properties": {
    "iso:country":"US",
    "sg:address":"201 Ritchie Rd",
    "sg:city":"Capitol Heights",
    "sg:classifiers":[
        {
            "category":"Building & Trades",
            "subcategory":"Construction",
            "type":"Services"
        }
    ],
    "sg:phone":"+1 301 350 9137",
    "sg:postcode":"20743",
    "sg:province":"MD",
    "sg:tags":[
        "contractor"
    ],
    "wof:name":"Shirley Contracting",
    "wof:placetype":"venue"
},
  "geometry": {"coordinates":[-76.86129800000001,38.8867],"type":"Point"}
}