{
  "type": "Feature",
  "properties": {
    "iso:country":"US",
    "sg:address":"17213 Wellfleet Dr",
    "sg:city":"Olney",
    "sg:classifiers":[
        {
            "category":"Real Estate",
            "subcategory":"Architect",
            "type":"Services"
        }
    ],
    "sg:phone":"+1 301 774 2496",
    "sg:postcode":"20832",
    "sg:province":"MD",
    "sg:tags":[
        "architectural"
    ],
    "wof:name":"Peter Y Cheung Architect",
    "wof:placetype":"venue"
},
  "geometry": {"coordinates":[-77.07812800000001,39.138832],"type":"Point"}
}