{
  "type": "Feature",
  "properties": {
    "iso:country":"US",
    "sg:address":"439 Grindall St",
    "sg:city":"Baltimore",
    "sg:classifiers":[
        {
            "category":"Professional",
            "subcategory":"Engineering",
            "type":"Services"
        }
    ],
    "sg:phone":"+1 410 528 5960",
    "sg:postcode":"21230",
    "sg:province":"MD",
    "sg:tags":[
        "consulting",
        "engineer"
    ],
    "sg:website":"http://www.savengineers.com",
    "wof:name":"Savengineers Inc",
    "wof:placetype":"venue"
},
  "geometry": {"coordinates":[-76.608176,39.278012],"type":"Point"}
}