{
  "type": "Feature",
  "properties": {
    "iso:country":"US",
    "sg:address":"9527 Valleymede Ct",
    "sg:city":"Ellicott City",
    "sg:classifiers":[
        {
            "category":"Organizations",
            "subcategory":"Religious Organization",
            "type":"Services"
        }
    ],
    "sg:phone":"+1 410 418 9587",
    "sg:postcode":"21042",
    "sg:province":"MD",
    "sg:tags":[
        "clergy"
    ],
    "wof:name":"D Mitchell",
    "wof:placetype":"venue"
},
  "geometry": {"coordinates":[-76.842961,39.288765],"type":"Point"}
}