{
  "type": "Feature",
  "properties": {
    "iso:country":"US",
    "sg:address":"14633 Baltimore Ave",
    "sg:city":"Laurel",
    "sg:classifiers":[
        {
            "category":"Wholesale",
            "subcategory":"Stationery",
            "type":"Manufacturing & Wholesale Goods"
        }
    ],
    "sg:phone":"+1 301 362 9100",
    "sg:postcode":"20707",
    "sg:province":"MD",
    "sg:tags":[
        "mapping"
    ],
    "wof:name":"Convenant Food & Drug",
    "wof:placetype":"venue"
},
  "geometry": {"coordinates":[-76.857653,39.091066],"type":"Point"}
}