{
  "type": "Feature",
  "properties": {
    "addr:full":"224 W Washington St Hagerstown MD 21740",
    "addr:housenumber":"224",
    "addr:postcode":"21740",
    "addr:street":"W Washington St",
    "iso:country":"US",
    "sg:address":"224 W Washington St",
    "sg:city":"Hagerstown",
    "sg:classifiers":[
        {
            "category":"Place Of Worship",
            "subcategory":"Church",
            "type":"Public Place"
        },
        {
            "category":"Place Of Worship",
            "type":"Public Place"
        }
    ],
    "sg:phone":"+1 301 739 0390",
    "sg:postcode":"21740",
    "sg:province":"MD",
    "sg:tags":[
        "churches-catholic-traditional",
        "churches-catholic"
    ],
    "wof:name":"St Mary Catholic Church and Rectory",
    "wof:placetype":"venue"
},
  "geometry": {"coordinates":[-77.725342,39.644451],"type":"Point"}
}