{
  "type": "Feature",
  "properties": {
    "iso:country":"US",
    "sg:address":"13007 Old Stage Coach Rd",
    "sg:city":"Laurel",
    "sg:classifiers":[
        {
            "category":"Building & Trades",
            "subcategory":"Landscaping Services",
            "type":"Services"
        },
        {
            "category":"Health Services",
            "subcategory":"Nursing And Care Facility",
            "type":"Services"
        }
    ],
    "sg:phone":"+1 412 758 9331",
    "sg:postcode":"20708",
    "sg:province":"MD",
    "sg:tags":[
        "home",
        "aged",
        "homes-institutional",
        "rest"
    ],
    "wof:name":"House Of New Beginnings, Md",
    "wof:placetype":"venue"
},
  "geometry": {"coordinates":[-76.842758,39.071591],"type":"Point"}
}