{
  "type": "Feature",
  "properties": {
    "addr:full":"1203 S Philadelphia Blvd Aberdeen MD 21001",
    "addr:housenumber":"1203",
    "addr:postcode":"21001",
    "addr:street":"S Philadelphia Blvd",
    "iso:country":"US",
    "sg:address":"1203 S Philadelphia Blvd",
    "sg:city":"Aberdeen",
    "sg:classifiers":[
        {
            "category":"Autos & Motor Vehicles",
            "subcategory":"Automobile Sales",
            "type":"Retail Goods"
        }
    ],
    "sg:phone":"+1 410 272 8810",
    "sg:postcode":"21001",
    "sg:province":"MD",
    "sg:tags":[
        "car",
        "dealer"
    ],
    "wof:name":"Accent Auto Rental & Sales LLC",
    "wof:placetype":"venue"
},
  "geometry": {"coordinates":[-76.198926,39.487801],"type":"Point"}
}