{
  "type": "Feature",
  "properties": {
    "addr:full":"16 Alt Rd Cockysvl Hnt Vly MD 21030",
    "addr:housenumber":"16",
    "addr:postcode":"21030",
    "addr:street":"Alt Rd;Hnt Vly",
    "iso:country":"US",
    "sg:address":"16 Alt Rd",
    "sg:city":"Cockysvl Hnt Vly",
    "sg:classifiers":[
        {
            "category":"Building & Trades",
            "subcategory":"Construction",
            "type":"Services"
        }
    ],
    "sg:phone":"+1 410 771 9473",
    "sg:postcode":"21030",
    "sg:province":"MD",
    "sg:tags":[
        "resurfacing",
        "laying",
        "refinishing",
        "floor"
    ],
    "sg:website":"www.beynonsports.com",
    "wof:name":"Beynon Sports Surfaces Inc",
    "wof:placetype":"venue"
},
  "geometry": {"coordinates":[-76.645813,39.480017],"type":"Point"}
}