{
  "type": "Feature",
  "properties": {
    "iso:country":"US",
    "sg:address":"407 N Charles St Fl 1",
    "sg:city":"Baltimore",
    "sg:classifiers":[
        {
            "category":"Professional",
            "subcategory":"Employment Agencies",
            "type":"Services"
        },
        {
            "category":"Professional",
            "subcategory":"Business Services",
            "type":"Services"
        }
    ],
    "sg:phone":"+1 410 234 0600",
    "sg:postcode":"21201",
    "sg:province":"MD",
    "sg:tags":[
        "consultant",
        "coach",
        "opportunity"
    ],
    "sg:website":"http://www.engineperformance.com",
    "wof:name":"Engine Performance Inc",
    "wof:placetype":"venue"
},
  "geometry": {"coordinates":[-76.615143,39.294449],"type":"Point"}
}