{
  "type": "Feature",
  "properties": {
    "addr:full":"1305 S Salisbury Blvd Salisbury MD 21801",
    "addr:housenumber":"1305",
    "addr:postcode":"21801",
    "addr:street":"S Salisbury Blvd",
    "iso:country":"US",
    "sg:address":"1305 S Salisbury Blvd",
    "sg:city":"Salisbury",
    "sg:classifiers":[
        {
            "category":"Restaurant",
            "type":"Food & Drink"
        }
    ],
    "sg:phone":"+1 410 749 5888",
    "sg:postcode":"21801",
    "sg:province":"MD",
    "wof:name":"Mc Donald's",
    "wof:placetype":"venue"
},
  "geometry": {"coordinates":[-75.60370899999999,38.344364],"type":"Point"}
}