{
  "type": "Feature",
  "properties": {
    "addr:full":"4013 Frederick Ave Baltimore MD 21229",
    "addr:housenumber":"4013",
    "addr:postcode":"21229",
    "addr:street":"Frederick Ave",
    "iso:country":"US",
    "sg:address":"4013 Frederick Ave",
    "sg:city":"Baltimore",
    "sg:classifiers":[
        {
            "category":"Restaurant",
            "type":"Food & Drink"
        }
    ],
    "sg:phone":"+1 410 368 1555",
    "sg:postcode":"21229",
    "sg:province":"MD",
    "wof:name":"Chicken & Trout",
    "wof:placetype":"venue"
},
  "geometry": {"coordinates":[-76.68249299999999,39.281761],"type":"Point"}
}