{
  "type": "Feature",
  "properties": {
    "iso:country":"US",
    "sg:address":"3016 Mitchellville Rd",
    "sg:city":"Bowie",
    "sg:classifiers":[
        {
            "category":"Real Estate",
            "subcategory":"Real Estate Agent",
            "type":"Services"
        }
    ],
    "sg:phone":"+1 301 390 0370",
    "sg:postcode":"20716",
    "sg:province":"MD",
    "sg:tags":[
        "appraiser"
    ],
    "wof:name":"Renner Hansborough Reese Inc",
    "wof:placetype":"venue"
},
  "geometry": {"coordinates":[-76.734212,38.930988],"type":"Point"}
}