{
  "type": "Feature",
  "properties": {
    "iso:country":"US",
    "sg:address":"4409 Atwick Rd",
    "sg:city":"Baltimore",
    "sg:classifiers":[
        {
            "category":"Health Services",
            "subcategory":"Doctor",
            "type":"Services"
        },
        {
            "category":"Health Services",
            "subcategory":"Health Practitioner",
            "type":"Services"
        }
    ],
    "sg:phone":"+1 410 366 4409",
    "sg:postcode":"21210",
    "sg:province":"MD",
    "sg:tags":[
        "physician",
        "ophthalmology",
        "surgeons",
        "surgeon"
    ],
    "wof:name":"Welch Robert Bond MD",
    "wof:placetype":"venue"
},
  "geometry": {"coordinates":[-76.628998,39.344299],"type":"Point"}
}