{
  "type": "Feature",
  "properties": {
    "addr:full":"2001 Harbour Gates Dr Annapolis MD 21401",
    "addr:housenumber":"2001",
    "addr:postcode":"21401",
    "addr:street":"Harbour Gates Dr",
    "iso:country":"US",
    "sg:address":"2001 Harbour Gates Dr",
    "sg:city":"Annapolis",
    "sg:classifiers":[
        {
            "category":"Real Estate",
            "subcategory":"Real Estate Operator",
            "type":"Services"
        }
    ],
    "sg:phone":"+1 410 573 0900",
    "sg:postcode":"21401",
    "sg:province":"MD",
    "sg:tags":[
        "apartment"
    ],
    "wof:name":"Harbour Gates Apartments",
    "wof:placetype":"venue"
},
  "geometry": {"coordinates":[-76.53193899999999,38.993351],"type":"Point"}
}