{
  "type": "Feature",
  "properties": {
    "iso:country":"US",
    "sg:address":"5303 King Charles Way",
    "sg:city":"Bethesda",
    "sg:classifiers":[
        {
            "category":"Professional",
            "subcategory":"Management & Consulting",
            "type":"Services"
        }
    ],
    "sg:phone":"+1 301 897 2950",
    "sg:postcode":"20814",
    "sg:province":"MD",
    "sg:tags":[
        "it"
    ],
    "wof:name":"Infosmyth",
    "wof:placetype":"venue"
},
  "geometry": {"coordinates":[-77.10463300000001,39.021431],"type":"Point"}
}