{
  "type": "Feature",
  "properties": {
    "addr:full":"215 E North Ave Baltimore MD 21202",
    "addr:housenumber":"215",
    "addr:postcode":"21202",
    "addr:street":"E North Ave",
    "iso:country":"US",
    "sg:address":"215 E North Ave",
    "sg:city":"Baltimore",
    "sg:classifiers":[
        {
            "category":"Professional",
            "subcategory":"Computer Services",
            "type":"Services"
        }
    ],
    "sg:phone":"+1 410 727 3278",
    "sg:postcode":"21202",
    "sg:province":"MD",
    "sg:tags":[
        "design",
        "network",
        "system"
    ],
    "wof:name":"Between Bruthaz",
    "wof:placetype":"venue"
},
  "geometry": {"coordinates":[-76.61358199999999,39.311144],"type":"Point"}
}