{
  "type": "Feature",
  "properties": {
    "iso:country":"US",
    "sg:address":"1 Ansted Ct",
    "sg:city":"Silver Spring",
    "sg:classifiers":[
        {
            "category":"Professional",
            "subcategory":"Computer Services",
            "type":"Services"
        }
    ],
    "sg:phone":"+1 301 879 9845",
    "sg:postcode":"20905",
    "sg:province":"MD",
    "sg:tags":[
        "programing",
        "custom"
    ],
    "wof:name":"Novasoft Corp",
    "wof:placetype":"venue"
},
  "geometry": {"coordinates":[-76.97406,39.091505],"type":"Point"}
}