{
  "type": "Feature",
  "properties": {
    "addr:full":"6010 Eurith Ave Baltimore MD 21206",
    "addr:housenumber":"6010",
    "addr:postcode":"21206",
    "addr:street":"Eurith Ave",
    "iso:country":"US",
    "sg:address":"6010 Eurith Ave",
    "sg:city":"Baltimore",
    "sg:classifiers":[
        {
            "category":"Professional",
            "subcategory":"Management & Consulting",
            "type":"Services"
        },
        {
            "category":"Professional",
            "subcategory":"Advertising",
            "type":"Services"
        },
        {
            "category":"Communications",
            "type":"Services"
        },
        {
            "category":"Professional",
            "subcategory":"Computer Services",
            "type":"Services"
        }
    ],
    "sg:phone":"+1 410 325 3911",
    "sg:postcode":"21206",
    "sg:province":"MD",
    "sg:tags":[
        "web",
        "consultant",
        "program",
        "design",
        "marketing",
        "software"
    ],
    "wof:name":"World Fire Business Services and Marketing",
    "wof:placetype":"venue"
},
  "geometry": {"coordinates":[-76.531178,39.347256],"type":"Point"}
}