{
  "type": "Feature",
  "properties": {
    "addr:full":"101 S Main St Greensboro MD 21639",
    "addr:housenumber":"101",
    "addr:postcode":"21639",
    "addr:street":"S Main St",
    "iso:country":"US",
    "sg:address":"101 S Main St",
    "sg:city":"Greensboro",
    "sg:classifiers":[
        {
            "category":"Restaurant",
            "type":"Food & Drink"
        }
    ],
    "sg:phone":"+1 410 482 8633",
    "sg:postcode":"21639",
    "sg:province":"MD",
    "wof:name":"Greensboro Restaurant",
    "wof:placetype":"venue"
},
  "geometry": {"coordinates":[-75.80506099999999,38.974478],"type":"Point"}
}