{
  "type": "Feature",
  "properties": {
    "iso:country":"US",
    "sg:address":"6670 Oakwood Cir",
    "sg:city":"Indian Head",
    "sg:classifiers":[
        {
            "category":"Professional",
            "subcategory":"Business Services",
            "type":"Services"
        }
    ],
    "sg:phone":"+1 301 375 9600",
    "sg:postcode":"20640",
    "sg:province":"MD",
    "wof:name":"Building Permit Drawings",
    "wof:placetype":"venue"
},
  "geometry": {"coordinates":[-77.082606,38.614254],"type":"Point"}
}