{
  "type": "Feature",
  "properties": {
    "addr:full":"1209 Cowpens Ave Baltimore MD 21286",
    "addr:housenumber":"1209",
    "addr:postcode":"21286",
    "addr:street":"Cowpens Ave",
    "iso:country":"US",
    "sg:address":"1209 Cowpens Ave",
    "sg:city":"Baltimore",
    "sg:classifiers":[
        {
            "category":"Organizations",
            "subcategory":"Religious Organization",
            "type":"Services"
        }
    ],
    "sg:phone":"+1 410 828 6448",
    "sg:postcode":"21286",
    "sg:province":"MD",
    "wof:name":"New Wine Family Worship Center",
    "wof:placetype":"venue"
},
  "geometry": {"coordinates":[-76.567471,39.405134],"type":"Point"}
}