{
  "type": "Feature",
  "properties": {
    "addr:full":"4606 Weston Pl Olney MD 20832",
    "addr:housenumber":"4606",
    "addr:postcode":"20832",
    "addr:street":"Weston Pl",
    "iso:country":"US",
    "sg:address":"4606 Weston Pl",
    "sg:city":"Olney",
    "sg:classifiers":[
        {
            "category":"Education",
            "subcategory":"Special Training",
            "type":"Public Place"
        }
    ],
    "sg:phone":"+1 301 570 2027",
    "sg:postcode":"20832",
    "sg:province":"MD",
    "sg:tags":[
        "educational"
    ],
    "wof:name":"Mohammed P Farshori",
    "wof:placetype":"venue"
},
  "geometry": {"coordinates":[-77.09137,39.160615],"type":"Point"}
}