{
  "type": "Feature",
  "properties": {
    "addr:full":"1752 Merritt Blvd Baltimore MD 21222",
    "addr:housenumber":"1752",
    "addr:postcode":"21222",
    "addr:street":"Merritt Blvd",
    "iso:country":"US",
    "sg:address":"1752 Merritt Blvd",
    "sg:city":"Baltimore",
    "sg:classifiers":[
        {
            "category":"Health Services",
            "subcategory":"Doctor",
            "type":"Services"
        }
    ],
    "sg:phone":"+1 410 284 4100",
    "sg:postcode":"21222",
    "sg:province":"MD",
    "sg:tags":[
        "physician",
        "surgeon"
    ],
    "wof:name":"Charles Walder MD",
    "wof:placetype":"venue"
},
  "geometry": {"coordinates":[-76.503502,39.269973],"type":"Point"}
}