{
  "type": "Feature",
  "properties": {
    "addr:full":"2031 Hanover Pike Hampstead MD 21074",
    "addr:housenumber":"2031",
    "addr:postcode":"21074",
    "addr:street":"Hanover Pike",
    "iso:country":"US",
    "sg:address":"2031 Hanover Pike",
    "sg:city":"Hampstead",
    "sg:classifiers":[
        {
            "category":"Retail",
            "subcategory":"Auto Repair",
            "type":"Services"
        }
    ],
    "sg:phone":"+1 410 239 7680",
    "sg:postcode":"21074",
    "sg:province":"MD",
    "sg:tags":[
        "body"
    ],
    "wof:name":"Autos Unlimited",
    "wof:placetype":"venue"
},
  "geometry": {"coordinates":[-76.862172,39.630425],"type":"Point"}
}