{
  "type": "Feature",
  "properties": {
    "addr:full":"17213 Virginia Ave Hagerstown MD 21740",
    "addr:housenumber":"17213",
    "addr:postcode":"21740",
    "addr:street":"Virginia Ave",
    "iso:country":"US",
    "sg:address":"17213 Virginia Ave",
    "sg:city":"Hagerstown",
    "sg:classifiers":[
        {
            "category":"Retail",
            "subcategory":"Auto Repair",
            "type":"Services"
        }
    ],
    "sg:phone":"+1 301 582 3028",
    "sg:postcode":"21740",
    "sg:province":"MD",
    "sg:tags":[
        "machine",
        "automobile",
        "shop"
    ],
    "wof:name":"A & C Auto Machine Inc",
    "wof:placetype":"venue"
},
  "geometry": {"coordinates":[-77.77117200000001,39.616308],"type":"Point"}
}