{
  "type": "Feature",
  "properties": {
    "addr:full":"King Shopping Ctr Landover MD 20785",
    "addr:postcode":"20785",
    "iso:country":"US",
    "sg:address":"King Shopping Ctr",
    "sg:city":"Landover",
    "sg:classifiers":[
        {
            "category":"Shopping",
            "subcategory":"Mobile Phones",
            "type":"Retail Goods"
        },
        {
            "category":"Wholesale",
            "subcategory":"Computers",
            "type":"Manufacturing & Wholesale Goods"
        }
    ],
    "sg:phone":"+1 301 772 0010",
    "sg:postcode":"20785",
    "sg:province":"MD",
    "sg:website":"www.radioshack.com",
    "wof:name":"Radioshack",
    "wof:placetype":"venue"
},
  "geometry": {"coordinates":[-76.88368699999999,38.915013],"type":"Point"}
}