{
  "type": "Feature",
  "properties": {
    "iso:country":"US",
    "sg:address":"201 E Pratt St",
    "sg:city":"Baltimore",
    "sg:classifiers":[
        {
            "category":"Restaurant",
            "type":"Food & Drink"
        }
    ],
    "sg:menulink":"http://www.allmenus.com/md/baltimore/69152-california-pizza-kitchen/menu/",
    "sg:phone":"+1 410 783 9339",
    "sg:postcode":"21202",
    "sg:province":"MD",
    "sg:tags":[
        "sandwich",
        "salad",
        "soup",
        "american",
        "pasta",
        "californian",
        "pizza"
    ],
    "wof:name":"California Pizza Kitchen",
    "wof:placetype":"venue"
},
  "geometry": {"coordinates":[-76.611397,39.286598],"type":"Point"}
}