{
  "type": "Feature",
  "properties": {
    "addr:full":"4409 Holter Ct Jefferson MD 21755",
    "addr:postcode":"4409;21755",
    "addr:street":"Holter Ct",
    "iso:country":"US",
    "sg:address":"4409 Holter Ct",
    "sg:city":"Jefferson",
    "sg:classifiers":[
        {
            "category":"Home & Garden",
            "subcategory":"Building Materials",
            "type":"Retail Goods"
        }
    ],
    "sg:phone":"+1 301 371 0502",
    "sg:postcode":"21755",
    "sg:province":"MD",
    "sg:tags":[
        "shutter"
    ],
    "wof:name":"Louver Shop Of Maryland LLC",
    "wof:placetype":"venue"
},
  "geometry": {"coordinates":[-77.514094,39.398859],"type":"Point"}
}