{
  "type": "Feature",
  "properties": {
    "addr:full":"2402 Chelmsford Dr Crofton MD 21114",
    "addr:housenumber":"2402",
    "addr:postcode":"21114",
    "addr:street":"Chelmsford Dr",
    "iso:country":"US",
    "sg:address":"2402 Chelmsford Dr",
    "sg:city":"Crofton",
    "sg:classifiers":[
        {
            "category":"Social Services",
            "subcategory":"Job Training",
            "type":"Services"
        }
    ],
    "sg:phone":"+1 410 451 2198",
    "sg:postcode":"21114",
    "sg:province":"MD",
    "sg:tags":[
        "business"
    ],
    "wof:name":"Dynamic Destiny L L C",
    "wof:placetype":"venue"
},
  "geometry": {"coordinates":[-76.659863,39.018819],"type":"Point"}
}