{
  "type": "Feature",
  "properties": {
    "addr:full":"11000 Owings Mills Blvd Owings Mills MD 21117",
    "addr:housenumber":"11000",
    "addr:postcode":"21117",
    "addr:street":"Owings Mills Blvd",
    "iso:country":"US",
    "sg:address":"11000 Owings Mills Blvd",
    "sg:city":"Owings Mills",
    "sg:classifiers":[
        {
            "category":"Health Services",
            "subcategory":"Chiropractor",
            "type":"Services"
        }
    ],
    "sg:phone":"+1 410 356 0820",
    "sg:postcode":"21117",
    "sg:province":"MD",
    "wof:name":"Weiner Chiropractic",
    "wof:placetype":"venue"
},
  "geometry": {"coordinates":[-76.779983,39.424426],"type":"Point"}
}