{
  "type": "Feature",
  "properties": {
    "addr:full":"507 Commerce Dr Upper Marlboro MD 20774",
    "addr:housenumber":"507",
    "addr:postcode":"20774",
    "addr:street":"Commerce Dr",
    "iso:country":"US",
    "sg:address":"507 Commerce Dr",
    "sg:city":"Upper Marlboro",
    "sg:classifiers":[
        {
            "category":"Education",
            "subcategory":"Dance Studio",
            "type":"Public Place"
        }
    ],
    "sg:phone":"+1 301 249 7430",
    "sg:postcode":"20774",
    "sg:province":"MD",
    "sg:tags":[
        "instruction",
        "dancing"
    ],
    "wof:name":"Dance Expressions Inc",
    "wof:placetype":"venue"
},
  "geometry": {"coordinates":[-76.730439,38.878297],"type":"Point"}
}