{
  "type": "Feature",
  "properties": {
    "iso:country":"US",
    "sg:address":"12421 Arrow Park Dr",
    "sg:city":"Fort Washington",
    "sg:classifiers":[
        {
            "category":"Health Services",
            "subcategory":"Doctor",
            "type":"Services"
        }
    ],
    "sg:phone":"+1 301 292 9650",
    "sg:postcode":"20744",
    "sg:province":"MD",
    "sg:tags":[
        "dentist"
    ],
    "wof:name":"N Moradi DDS",
    "wof:placetype":"venue"
},
  "geometry": {"coordinates":[-77.01211000000001,38.722272],"type":"Point"}
}