{
  "type": "Feature",
  "properties": {
    "iso:country":"US",
    "sg:address":"7350 Westlake Ter",
    "sg:city":"Bethesda",
    "sg:classifiers":[
        {
            "category":"Education",
            "subcategory":"Special Training",
            "type":"Public Place"
        }
    ],
    "sg:phone":"+1 301 469 8323",
    "sg:postcode":"20817",
    "sg:province":"MD",
    "sg:tags":[
        "school",
        "language"
    ],
    "wof:name":"Sadigh-Mostowfi, Farima",
    "wof:placetype":"venue"
},
  "geometry": {"coordinates":[-77.14982500000001,39.027513],"type":"Point"}
}