{
  "type": "Feature",
  "properties": {
    "iso:country":"US",
    "sg:address":"8137 Main St",
    "sg:city":"Ellicott City",
    "sg:classifiers":[
        {
            "category":"Banks & Credit Unions",
            "subcategory":"Bank",
            "type":"Services"
        }
    ],
    "sg:phone":"+1 410 203 1105",
    "sg:postcode":"21043",
    "sg:province":"MD",
    "wof:name":"Farmers & Mechanics National Bank",
    "wof:placetype":"venue"
},
  "geometry": {"coordinates":[-76.796547,39.267169],"type":"Point"}
}