{
  "type": "Feature",
  "properties": {
    "iso:country":"US",
    "sg:address":"11529 February Cir",
    "sg:city":"Silver Spring",
    "sg:classifiers":[
        {
            "category":"Professional",
            "subcategory":"Business Services",
            "type":"Services"
        }
    ],
    "sg:phone":"+1 301 625 2322",
    "sg:postcode":"20904",
    "sg:province":"MD",
    "wof:name":"Brenda Hermann",
    "wof:placetype":"venue"
},
  "geometry": {"coordinates":[-76.97815199999999,39.046373],"type":"Point"}
}