{
  "type": "Feature",
  "properties": {
    "addr:full":"120 Hospital Rd Prince Frederick MD 20678",
    "addr:housenumber":"120",
    "addr:postcode":"20678",
    "addr:street":"Hospital Rd",
    "iso:country":"US",
    "sg:address":"120 Hospital Rd",
    "sg:city":"Prince Frederick",
    "sg:classifiers":[
        {
            "category":"Social Services",
            "subcategory":"Job Training",
            "type":"Services"
        }
    ],
    "sg:phone":"+1 410 257 7106",
    "sg:postcode":"20678",
    "sg:province":"MD",
    "sg:tags":[
        "rehabilitation"
    ],
    "wof:name":"Chesapeake Physical Medicine",
    "wof:placetype":"venue"
},
  "geometry": {"coordinates":[-76.595741,38.56056],"type":"Point"}
}