{
  "type": "Feature",
  "properties": {
    "iso:country":"US",
    "sg:address":"5435B Bartonsville Rd",
    "sg:city":"Frederick",
    "sg:classifiers":[
        {
            "category":"Retail",
            "subcategory":"Animal Services",
            "type":"Services"
        }
    ],
    "sg:phone":"+1 301 694 9506",
    "sg:postcode":"21704",
    "sg:province":"MD",
    "sg:tags":[
        "pet",
        "exercising",
        "sitting"
    ],
    "wof:name":"Dan Simmons",
    "wof:placetype":"venue"
},
  "geometry": {"coordinates":[-77.339343,39.382895],"type":"Point"}
}