{
  "type": "Feature",
  "properties": {
    "iso:country":"US",
    "sg:address":"22 Sebastiani Blvd",
    "sg:city":"Gaithersburg",
    "sg:classifiers":[
        {
            "category":"Communications",
            "subcategory":"Film & Video Production",
            "type":"Services"
        },
        {
            "category":"Communications",
            "subcategory":"Television Station",
            "type":"Services"
        }
    ],
    "sg:phone":"+1 240 401 6439",
    "sg:postcode":"20878",
    "sg:province":"MD",
    "sg:tags":[
        "companies-film",
        "producer",
        "tv",
        "program",
        "radio",
        "distributor"
    ],
    "wof:name":"Karimian, Mehrnoush",
    "wof:placetype":"venue"
},
  "geometry": {"coordinates":[-77.227814,39.136041],"type":"Point"}
}