{
  "type": "Feature",
  "properties": {
    "addr:full":"450 Man O War Ct Ste A Annapolis MD 21409",
    "addr:housenumber":"450",
    "addr:postcode":"21409",
    "addr:street":"Man O War Ct Ste A",
    "iso:country":"US",
    "sg:address":"450 Man O War Ct Ste A",
    "sg:city":"Annapolis",
    "sg:classifiers":[
        {
            "category":"Wholesale",
            "subcategory":"Construction Materials",
            "type":"Manufacturing & Wholesale Goods"
        }
    ],
    "sg:phone":"+1 410 974 0559",
    "sg:postcode":"21409",
    "sg:province":"MD",
    "sg:tags":[
        "control",
        "manufacturer",
        "system",
        "controls",
        "regulators-wholesale"
    ],
    "wof:name":"Kor-Ko, Ltd",
    "wof:placetype":"venue"
},
  "geometry": {"coordinates":[-76.435951,39.030331],"type":"Point"}
}