{
  "type": "Feature",
  "properties": {
    "addr:full":"1445 N Bend Rd Jarrettsville MD 21084",
    "addr:housenumber":"1445",
    "addr:postcode":"21084",
    "addr:street":"N Bend Rd",
    "iso:country":"US",
    "sg:address":"1445 N Bend Rd",
    "sg:city":"Jarrettsville",
    "sg:classifiers":[
        {
            "category":"Travel",
            "subcategory":"Campground",
            "type":"Entertainment"
        }
    ],
    "sg:phone":"+1 410 692 7820",
    "sg:postcode":"21084",
    "sg:province":"MD",
    "sg:tags":[
        "executive",
        "trailer"
    ],
    "wof:name":"Jarrettsville Recreation",
    "wof:placetype":"venue"
},
  "geometry": {"coordinates":[-76.45910600000001,39.633891],"type":"Point"}
}