{
  "type": "Feature",
  "properties": {
    "addr:full":"9 N 8th St Denton MD 21629",
    "addr:housenumber":"9",
    "addr:postcode":"21629",
    "addr:street":"N 8Th St",
    "iso:country":"US",
    "sg:address":"9 N 8th St",
    "sg:city":"Denton",
    "sg:classifiers":[
        {
            "category":"Retail",
            "subcategory":"Car Wash",
            "type":"Services"
        }
    ],
    "sg:phone":"+1 410 822 7239",
    "sg:postcode":"21629",
    "sg:province":"MD",
    "sg:tags":[
        "automobile",
        "detail",
        "clean"
    ],
    "wof:name":"Color Finishes Of Maryland",
    "wof:placetype":"venue"
},
  "geometry": {"coordinates":[-75.823886,38.884725],"type":"Point"}
}