{
  "type": "Feature",
  "properties": {
    "addr:full":"528 Meadow Hall Dr Rockville MD 20851",
    "addr:housenumber":"528",
    "addr:postcode":"20851",
    "addr:street":"Meadow Hall Dr",
    "iso:country":"US",
    "sg:address":"528 Meadow Hall Dr",
    "sg:city":"Rockville",
    "sg:classifiers":[
        {
            "category":"Professional",
            "subcategory":"Management & Consulting",
            "type":"Services"
        }
    ],
    "sg:phone":"+1 301 315 9479",
    "sg:postcode":"20851",
    "sg:province":"MD",
    "wof:name":"Blockbuster",
    "wof:placetype":"venue"
},
  "geometry": {"coordinates":[-77.10979500000001,39.075862],"type":"Point"}
}