{
  "type": "Feature",
  "properties": {
    "iso:country":"US",
    "sg:address":"1650 Robin Cir",
    "sg:city":"Forest Hill",
    "sg:classifiers":[
        {
            "category":"Building & Trades",
            "subcategory":"Cleaning & Sanitation",
            "type":"Services"
        }
    ],
    "sg:phone":"+1 410 638 8800",
    "sg:postcode":"21050",
    "sg:province":"MD",
    "sg:tags":[
        "fireplace",
        "chimney"
    ],
    "wof:name":"Flanagans Chimney Sweep",
    "wof:placetype":"venue"
},
  "geometry": {"coordinates":[-76.363394,39.567547],"type":"Point"}
}