{
  "type": "Feature",
  "properties": {
    "addr:full":"13815 Jarrettsville Pike Phoenix MD 21131",
    "addr:housenumber":"13815",
    "addr:postcode":"21131",
    "addr:street":"Jarrettsville Pike",
    "iso:country":"US",
    "sg:address":"13815 Jarrettsville Pike",
    "sg:city":"Phoenix",
    "sg:classifiers":[
        {
            "category":"Professional",
            "subcategory":"Computer Services",
            "type":"Services"
        }
    ],
    "sg:phone":"+1 410 667 2001",
    "sg:postcode":"21131",
    "sg:province":"MD",
    "sg:tags":[
        "consultant",
        "engineering",
        "or",
        "system",
        "ex"
    ],
    "wof:name":"Phoenix Group LLC",
    "wof:placetype":"venue"
},
  "geometry": {"coordinates":[-76.570736,39.500725],"type":"Point"}
}