{
  "type": "Feature",
  "properties": {
    "iso:country":"US",
    "sg:address":"12147 Park Heights Ave",
    "sg:city":"Owings Mills",
    "sg:classifiers":[
        {
            "category":"Retail",
            "subcategory":"Laundry & Dry Cleaning",
            "type":"Services"
        }
    ],
    "sg:phone":"+1 410 654 5511",
    "sg:postcode":"21117",
    "sg:province":"MD",
    "sg:tags":[
        "drycleaning",
        "plant",
        "except",
        "rug"
    ],
    "wof:name":"B & B Cleaners",
    "wof:placetype":"venue"
},
  "geometry": {"coordinates":[-76.75479900000001,39.458],"type":"Point"}
}