{
  "type": "Feature",
  "properties": {
    "iso:country":"US",
    "sg:address":"14225 Cherry Lane Ct",
    "sg:city":"Laurel",
    "sg:classifiers":[
        {
            "category":"Building & Trades",
            "subcategory":"Plumbing",
            "type":"Services"
        }
    ],
    "sg:phone":"+1 301 470 2224",
    "sg:postcode":"20707",
    "sg:province":"MD",
    "wof:name":"Associates Plumbing",
    "wof:placetype":"venue"
},
  "geometry": {"coordinates":[-76.855797,39.087898],"type":"Point"}
}