{
  "type": "Feature",
  "properties": {
    "iso:country":"US",
    "sg:address":"2415 Bear Run Rd",
    "sg:city":"Taneytown",
    "sg:classifiers":[
        {
            "category":"Retail",
            "subcategory":"Laundry & Dry Cleaning",
            "type":"Services"
        }
    ],
    "sg:phone":"+1 410 751 0343",
    "sg:postcode":"21787",
    "sg:province":"MD",
    "sg:tags":[
        "cleaners",
        "rug",
        "carpet"
    ],
    "wof:name":"Chem-Dry By Carpet Magic",
    "wof:placetype":"venue"
},
  "geometry": {"coordinates":[-77.113539,39.639308],"type":"Point"}
}