{
  "type": "Feature",
  "properties": {
    "addr:full":"7600 Rickenbacker Dr Gaithersburg MD 20879",
    "addr:housenumber":"7600",
    "addr:postcode":"20879",
    "addr:street":"Rickenbacker Dr",
    "iso:country":"US",
    "sg:address":"7600 Rickenbacker Dr",
    "sg:city":"Gaithersburg",
    "sg:classifiers":[
        {
            "category":"Professional",
            "subcategory":"Engineering",
            "type":"Services"
        }
    ],
    "sg:phone":"+1 301 948 6730",
    "sg:postcode":"20879",
    "sg:province":"MD",
    "sg:tags":[
        "engineer"
    ],
    "wof:name":"Danac Corp",
    "wof:placetype":"venue"
},
  "geometry": {"coordinates":[-77.15757000000001,39.173354],"type":"Point"}
}