{
  "type": "Feature",
  "properties": {
    "addr:full":"271 Mackintosh Dr Glen Burnie MD 21061",
    "addr:housenumber":"271",
    "addr:postcode":"21061",
    "addr:street":"Mackintosh Dr",
    "iso:country":"US",
    "sg:address":"271 Mackintosh Dr",
    "sg:city":"Glen Burnie",
    "sg:classifiers":[
        {
            "category":"Social Services",
            "subcategory":"Child Care",
            "type":"Services"
        }
    ],
    "sg:phone":"+1 410 766 3126",
    "sg:postcode":"21061",
    "sg:province":"MD",
    "wof:name":"Southgate In Home Daycare",
    "wof:placetype":"venue"
},
  "geometry": {"coordinates":[-76.615848,39.131716],"type":"Point"}
}