{
  "type": "Feature",
  "properties": {
    "iso:country":"US",
    "sg:address":"8736 Belair Rd",
    "sg:city":"Nottingham",
    "sg:classifiers":[
        {
            "category":"Personal",
            "subcategory":"Beauty Salon",
            "type":"Services"
        }
    ],
    "sg:phone":"+1 410 248 9220",
    "sg:postcode":"21236",
    "sg:province":"MD",
    "wof:name":"Salon 8736",
    "wof:placetype":"venue"
},
  "geometry": {"coordinates":[-76.487571,39.39266],"type":"Point"}
}