{
  "type": "Feature",
  "properties": {
    "iso:country":"US",
    "sg:address":"2930 Industrial Park Dr",
    "sg:city":"Finksburg",
    "sg:classifiers":[
        {
            "category":"Building & Trades",
            "subcategory":"Construction",
            "type":"Services"
        }
    ],
    "sg:phone":"+1 410 833 4300",
    "sg:postcode":"21048",
    "sg:province":"MD",
    "sg:tags":[
        "water",
        "control",
        "pollution"
    ],
    "wof:name":"Hugh Supply",
    "wof:placetype":"venue"
},
  "geometry": {"coordinates":[-76.886968,39.499127],"type":"Point"}
}