{
  "type": "Feature",
  "properties": {
    "iso:country":"US",
    "sg:address":"2505 N Salisbury Blvd",
    "sg:city":"Salisbury",
    "sg:classifiers":[
        {
            "category":"Government",
            "subcategory":"Post Office",
            "type":"Public Place"
        }
    ],
    "sg:phone":"+1 410 548 7103",
    "sg:postcode":"21801",
    "sg:province":"MD",
    "wof:name":"US Post Office",
    "wof:placetype":"venue"
},
  "geometry": {"coordinates":[-75.567489,38.407134],"type":"Point"}
}