{
  "type": "Feature",
  "properties": {
    "iso:country":"US",
    "sg:address":"1011 Cedar Ridge Ct",
    "sg:city":"Annapolis",
    "sg:classifiers":[
        {
            "category":"Professional",
            "subcategory":"Computer Services",
            "type":"Services"
        }
    ],
    "sg:phone":"+1 410 263 2987",
    "sg:postcode":"21403",
    "sg:province":"MD",
    "sg:tags":[
        "programming",
        "custom"
    ],
    "wof:name":"S D D I",
    "wof:placetype":"venue"
},
  "geometry": {"coordinates":[-76.492809,38.957935],"type":"Point"}
}