{
  "type": "Feature",
  "properties": {
    "addr:full":"12320 Greenspring Ave Owings Mills MD 21117",
    "addr:housenumber":"12320",
    "addr:postcode":"21117",
    "addr:street":"Greenspring Ave",
    "iso:country":"US",
    "sg:address":"12320 Greenspring Ave",
    "sg:city":"Owings Mills",
    "sg:classifiers":[
        {
            "category":"Wholesale",
            "subcategory":"Electrical",
            "type":"Manufacturing & Wholesale Goods"
        }
    ],
    "sg:phone":"+1 410 453 9164",
    "sg:postcode":"21117",
    "sg:province":"MD",
    "sg:tags":[
        "alarm",
        "burglar",
        "system"
    ],
    "wof:name":"Intertech Electronic Systems",
    "wof:placetype":"venue"
},
  "geometry": {"coordinates":[-76.73679199999999,39.460253],"type":"Point"}
}