{
  "type": "Feature",
  "properties": {
    "iso:country":"US",
    "sg:address":"21009 Great Mills Rd",
    "sg:city":"Lexington Park",
    "sg:classifiers":[
        {
            "category":"Restaurant",
            "type":"Food & Drink"
        }
    ],
    "sg:phone":"+1 301 737 5232",
    "sg:postcode":"20653",
    "sg:province":"MD",
    "wof:name":"Emily's Oriental Express",
    "wof:placetype":"venue"
},
  "geometry": {"coordinates":[-76.477997,38.255001],"type":"Point"}
}