{
  "type": "Feature",
  "properties": {
    "addr:full":"7901 Queenair Dr Gaithersburg MD 20879",
    "addr:housenumber":"7901",
    "addr:postcode":"20879",
    "addr:street":"Queenair Dr",
    "iso:country":"US",
    "sg:address":"7901 Queenair Dr",
    "sg:city":"Gaithersburg",
    "sg:classifiers":[
        {
            "category":"Home & Garden",
            "subcategory":"Household Appliances",
            "type":"Retail Goods"
        }
    ],
    "sg:phone":"+1 301 963 8939",
    "sg:postcode":"20879",
    "sg:province":"MD",
    "sg:tags":[
        "machine",
        "washing"
    ],
    "wof:name":"Air Park Appliance",
    "wof:placetype":"venue"
},
  "geometry": {"coordinates":[-77.16127,39.169498],"type":"Point"}
}