{
  "type": "Feature",
  "properties": {
    "addr:full":"1201 Brantford Ave Silver Spring MD 20904",
    "addr:housenumber":"1201",
    "addr:postcode":"20904",
    "addr:street":"Brantford Ave",
    "iso:country":"US",
    "sg:address":"1201 Brantford Ave",
    "sg:city":"Silver Spring",
    "sg:classifiers":[
        {
            "category":"Building & Trades",
            "subcategory":"Locksmith",
            "type":"Services"
        }
    ],
    "sg:phone":"+1 240 388 9117",
    "sg:postcode":"20904",
    "sg:province":"MD",
    "sg:tags":[
        "key"
    ],
    "wof:name":"Always Available Emergency Locksmith",
    "wof:placetype":"venue"
},
  "geometry": {"coordinates":[-76.987921,39.058163],"type":"Point"}
}