{
  "type": "Feature",
  "properties": {
    "iso:country":"US",
    "sg:address":"7753 Edgewood Church Rd",
    "sg:city":"Frederick",
    "sg:classifiers":[
        {
            "category":"Education",
            "subcategory":"Vocational School",
            "type":"Public Place"
        }
    ],
    "sg:phone":"+1 301 473 7848",
    "sg:postcode":"21702",
    "sg:province":"MD",
    "sg:tags":[
        "instruction",
        "taxidermy"
    ],
    "wof:name":"D R Taxidermy",
    "wof:placetype":"venue"
},
  "geometry": {"coordinates":[-77.474359,39.444573],"type":"Point"}
}