{
  "type": "Feature",
  "properties": {
    "addr:full":"7753 Edgewood Church Rd Frederick MD 21702",
    "addr:housenumber":"7753",
    "addr:postcode":"21702",
    "addr:street":"Edgewood Church Rd",
    "iso:country":"US",
    "sg:address":"7753 Edgewood Church Rd",
    "sg:city":"Frederick",
    "sg:classifiers":[
        {
            "category":"Education",
            "subcategory":"Vocational School",
            "type":"Public Place"
        }
    ],
    "sg:phone":"+1 301 473 7848",
    "sg:postcode":"21702",
    "sg:province":"MD",
    "sg:tags":[
        "instruction",
        "taxidermy"
    ],
    "wof:name":"D R Taxidermy",
    "wof:placetype":"venue"
},
  "geometry": {"coordinates":[-77.47435900000001,39.444573],"type":"Point"}
}