{
  "type": "Feature",
  "properties": {
    "iso:country":"US",
    "sg:address":"5601 Loch Raven Blvd # 101",
    "sg:city":"Baltimore",
    "sg:classifiers":[
        {
            "category":"Health Services",
            "subcategory":"Doctor",
            "type":"Services"
        }
    ],
    "sg:phone":"+1 410 433 4300",
    "sg:postcode":"21239",
    "sg:province":"MD",
    "sg:tags":[
        "physician",
        "reconstructive",
        "surgery-general",
        "surgeons",
        "cosmetic",
        "plastic",
        "surgery",
        "surgeon"
    ],
    "wof:name":"Plastic & Cosmetic Surgeons Pa",
    "wof:placetype":"venue"
},
  "geometry": {"coordinates":[-76.588887,39.358921],"type":"Point"}
}