{
  "type": "Feature",
  "properties": {
    "addr:full":"1055 S Charles St Baltimore MD 21230",
    "addr:housenumber":"1055",
    "addr:postcode":"21230",
    "addr:street":"S Charles St",
    "iso:country":"US",
    "sg:address":"1055 S Charles St",
    "sg:city":"Baltimore",
    "sg:classifiers":[
        {
            "category":"Banks & Credit Unions",
            "subcategory":"Financial Services",
            "type":"Services"
        }
    ],
    "sg:phone":"+1 410 385 2968",
    "sg:postcode":"21230",
    "sg:province":"MD",
    "sg:tags":[
        "cashing",
        "check"
    ],
    "wof:name":"Check-It-Out",
    "wof:placetype":"venue"
},
  "geometry": {"coordinates":[-76.61438200000001,39.276984],"type":"Point"}
}