{
  "type": "Feature",
  "properties": {
    "addr:full":"6405 Pennell Ct Elkridge MD 21075",
    "addr:housenumber":"6405",
    "addr:postcode":"21075",
    "addr:street":"Pennell Ct",
    "iso:country":"US",
    "sg:address":"6405 Pennell Ct",
    "sg:city":"Elkridge",
    "sg:classifiers":[
        {
            "category":"Professional",
            "subcategory":"Business Services",
            "type":"Services"
        }
    ],
    "sg:phone":"+1 410 796 6765",
    "sg:postcode":"21075",
    "sg:province":"MD",
    "wof:name":"Kupferman & Assoc",
    "wof:placetype":"venue"
},
  "geometry": {"coordinates":[-76.775795,39.20344],"type":"Point"}
}