{
  "type": "Feature",
  "properties": {
    "iso:country":"US",
    "sg:address":"10535 York Rd Ste 1",
    "sg:city":"Cockeysville",
    "sg:classifiers":[
        {
            "category":"Real Estate",
            "subcategory":"Real Estate Operator",
            "type":"Services"
        }
    ],
    "sg:phone":"+1 410 666 1030",
    "sg:postcode":"21030",
    "sg:province":"MD",
    "sg:tags":[
        "apartment"
    ],
    "wof:name":"Warren Place",
    "wof:placetype":"venue"
},
  "geometry": {"coordinates":[-76.641727,39.476379],"type":"Point"}
}