{
  "type": "Feature",
  "properties": {
    "addr:full":"27 N Main St Berlin MD 21811",
    "addr:housenumber":"27",
    "addr:postcode":"21811",
    "addr:street":"N Main St",
    "iso:country":"US",
    "sg:address":"27 N Main St",
    "sg:city":"Berlin",
    "sg:classifiers":[
        {
            "category":"Shopping",
            "subcategory":"Gifts & Souvenirs",
            "type":"Retail Goods"
        }
    ],
    "sg:phone":"+1 410 629 1984",
    "sg:postcode":"21811",
    "sg:province":"MD",
    "sg:tags":[
        "shop"
    ],
    "wof:name":"Just A Taste",
    "wof:placetype":"venue"
},
  "geometry": {"coordinates":[-75.21922499999999,38.325165],"type":"Point"}
}