{
  "type": "Feature",
  "properties": {
    "addr:full":"3875 Jarrettsville Pike Jarrettsville MD 21084",
    "addr:housenumber":"3875",
    "addr:postcode":"21084",
    "addr:street":"Jarrettsville Pike",
    "iso:country":"US",
    "sg:address":"3875 Jarrettsville Pike",
    "sg:city":"Jarrettsville",
    "sg:classifiers":[
        {
            "category":"Professional",
            "subcategory":"Computer Services",
            "type":"Services"
        }
    ],
    "sg:phone":"+1 410 692 2675",
    "sg:postcode":"21084",
    "sg:province":"MD",
    "sg:tags":[
        "datum"
    ],
    "wof:name":"James Rush",
    "wof:placetype":"venue"
},
  "geometry": {"coordinates":[-76.515421,39.610626],"type":"Point"}
}