{
  "type": "Feature",
  "properties": {
    "iso:country":"US",
    "sg:address":"20126 Leitersburg Pike",
    "sg:city":"Hagerstown",
    "sg:classifiers":[
        {
            "category":"Retail",
            "subcategory":"Car Wash",
            "type":"Services"
        }
    ],
    "sg:phone":"+1 301 733 3300",
    "sg:postcode":"21742",
    "sg:province":"MD",
    "sg:tags":[
        "automobile",
        "detail",
        "clean"
    ],
    "wof:name":"Crocar Auto Detailing",
    "wof:placetype":"venue"
},
  "geometry": {"coordinates":[-77.664185,39.686203],"type":"Point"}
}