{
  "type": "Feature",
  "properties": {
    "addr:full":"6 Seneca Forest Ct Germantown MD 20876",
    "addr:housenumber":"6",
    "addr:postcode":"20876",
    "addr:street":"Seneca Forest Ct",
    "iso:country":"US",
    "sg:address":"6 Seneca Forest Ct",
    "sg:city":"Germantown",
    "sg:classifiers":[
        {
            "category":"Social Services",
            "type":"Services"
        },
        {
            "category":"Professional",
            "subcategory":"Employment Agencies",
            "type":"Services"
        }
    ],
    "sg:phone":"+1 301 592 0325",
    "sg:postcode":"20876",
    "sg:province":"MD",
    "sg:tags":[
        "workers'",
        "placement",
        "volunteer"
    ],
    "wof:name":"Life In Yoga Foundation",
    "wof:placetype":"venue"
},
  "geometry": {"coordinates":[-77.23430999999999,39.206319],"type":"Point"}
}