{
  "type": "Feature",
  "properties": {
    "iso:country":"US",
    "sg:address":"9856 Brookridge Ct",
    "sg:city":"Gaithersburg",
    "sg:classifiers":[
        {
            "category":"Professional",
            "subcategory":"Computer Services",
            "type":"Services"
        }
    ],
    "sg:phone":"+1 301 417 9160",
    "sg:postcode":"20886",
    "sg:province":"MD",
    "sg:tags":[
        "consultant",
        "designer"
    ],
    "wof:name":"Jordan Computer Specialists",
    "wof:placetype":"venue"
},
  "geometry": {"coordinates":[-77.20249099999999,39.189021],"type":"Point"}
}