{
  "type": "Feature",
  "properties": {
    "iso:country":"US",
    "sg:address":"9712 Belair Rd",
    "sg:city":"Baltimore",
    "sg:classifiers":[
        {
            "category":"Health Services",
            "subcategory":"Podiatrist",
            "type":"Services"
        }
    ],
    "sg:phone":"+1 410 256 6060",
    "sg:postcode":"21236",
    "sg:province":"MD",
    "wof:name":"Podiatry Associates",
    "wof:placetype":"venue"
},
  "geometry": {"coordinates":[-76.459598,39.416341],"type":"Point"}
}