{
  "type": "Feature",
  "properties": {
    "iso:country":"US",
    "sg:address":"6345 Executive Blvd",
    "sg:city":"Rockville",
    "sg:classifiers":[
        {
            "category":"Building & Trades",
            "subcategory":"Construction",
            "type":"Services"
        }
    ],
    "sg:phone":"+1 301 881 2900",
    "sg:postcode":"20852",
    "sg:province":"MD",
    "sg:tags":[
        "home",
        "builder"
    ],
    "wof:name":"Senate Construction Corp",
    "wof:placetype":"venue"
},
  "geometry": {"coordinates":[-77.125398,39.048796],"type":"Point"}
}