{
  "type": "Feature",
  "properties": {
    "addr:full":"224 N Washington St Havre De Grace MD 21078",
    "addr:housenumber":"224",
    "addr:postcode":"21078",
    "addr:street":"N Washington St",
    "iso:country":"US",
    "sg:address":"224 N Washington St",
    "sg:city":"Havre De Grace",
    "sg:classifiers":[
        {
            "category":"Shopping",
            "subcategory":"Computers & Home Electronics",
            "type":"Retail Goods"
        }
    ],
    "sg:phone":"+1 410 939 5900",
    "sg:postcode":"21078",
    "sg:province":"MD",
    "sg:tags":[
        "software"
    ],
    "wof:name":"Dayspring Software",
    "wof:placetype":"venue"
},
  "geometry": {"coordinates":[-76.08985800000001,39.548687],"type":"Point"}
}