{
  "type": "Feature",
  "properties": {
    "addr:full":"7496 Merrymaker Way Elkridge MD 21075",
    "addr:housenumber":"7496",
    "addr:postcode":"21075",
    "addr:street":"Merrymaker Way",
    "iso:country":"US",
    "sg:address":"7496 Merrymaker Way",
    "sg:city":"Elkridge",
    "sg:classifiers":[
        {
            "category":"Professional",
            "subcategory":"Management & Consulting",
            "type":"Services"
        }
    ],
    "sg:phone":"+1 410 379 6941",
    "sg:postcode":"21075",
    "sg:province":"MD",
    "wof:name":"Gumerov Nail",
    "wof:placetype":"venue"
},
  "geometry": {"coordinates":[-76.774089,39.198323],"type":"Point"}
}