{
  "type": "Feature",
  "properties": {
    "iso:country":"US",
    "sg:address":"6895 Washington Blvd",
    "sg:city":"Elkridge",
    "sg:classifiers":[
        {
            "category":"Professional",
            "subcategory":"Management & Consulting",
            "type":"Services"
        }
    ],
    "sg:phone":"+1 410 579 6670",
    "sg:postcode":"21075",
    "sg:province":"MD",
    "sg:tags":[
        "business"
    ],
    "wof:name":"Star Business Management Inc",
    "wof:placetype":"venue"
},
  "geometry": {"coordinates":[-76.74609599999999,39.195063],"type":"Point"}
}