{
  "type": "Feature",
  "properties": {
    "iso:country":"US",
    "sg:address":"19941 Brownsville Rd",
    "sg:city":"Knoxville",
    "sg:classifiers":[
        {
            "category":"Shopping",
            "subcategory":"Bicycles & Sporting Goods",
            "type":"Retail Goods"
        }
    ],
    "sg:phone":"+1 301 432 0189",
    "sg:postcode":"21758",
    "sg:province":"MD",
    "sg:tags":[
        "saddlery",
        "harness"
    ],
    "wof:name":"Saddle Shed",
    "wof:placetype":"venue"
},
  "geometry": {"coordinates":[-77.67497299999999,39.385172],"type":"Point"}
}