{
  "type": "Feature",
  "properties": {
    "iso:country":"US",
    "sg:address":"9831 Greenbelt Rd",
    "sg:city":"Lanham",
    "sg:classifiers":[
        {
            "category":"Health Services",
            "subcategory":"Doctor",
            "type":"Services"
        }
    ],
    "sg:phone":"+1 301 552 4100",
    "sg:postcode":"20706",
    "sg:province":"MD",
    "sg:tags":[
        "physician",
        "surgeon"
    ],
    "wof:name":"Asthma & Allergic Disease Clnc",
    "wof:placetype":"venue"
},
  "geometry": {"coordinates":[-76.839319,38.991152],"type":"Point"}
}