{
  "type": "Feature",
  "properties": {
    "addr:full":"9890 Main St Damascus MD 20872",
    "addr:housenumber":"9890",
    "addr:postcode":"20872",
    "addr:street":"Main St",
    "iso:country":"US",
    "sg:address":"9890 Main St",
    "sg:city":"Damascus",
    "sg:classifiers":[
        {
            "category":"Health Services",
            "subcategory":"Doctor",
            "type":"Services"
        }
    ],
    "sg:phone":"+1 301 253 6977",
    "sg:postcode":"20872",
    "sg:province":"MD",
    "sg:tags":[
        "physician",
        "surgeon"
    ],
    "wof:name":"Kenneth J Weiss MD",
    "wof:placetype":"venue"
},
  "geometry": {"coordinates":[-77.20256500000001,39.287931],"type":"Point"}
}