{
  "type": "Feature",
  "properties": {
    "iso:country":"US",
    "sg:address":"11414 Tulip Poplar Ter",
    "sg:city":"Germantown",
    "sg:classifiers":[
        {
            "category":"Health Services",
            "subcategory":"Clinic",
            "type":"Services"
        }
    ],
    "sg:phone":"+1 301 972 3012",
    "sg:postcode":"20876",
    "sg:province":"MD",
    "sg:tags":[
        "welfare"
    ],
    "wof:name":"Tabaku Center Of Healthcare Ed",
    "wof:placetype":"venue"
},
  "geometry": {"coordinates":[-77.23626400000001,39.203153],"type":"Point"}
}