{
  "type": "Feature",
  "properties": {
    "iso:country":"US",
    "sg:address":"5730 Deale Churchton Rd",
    "sg:city":"Deale",
    "sg:classifiers":[
        {
            "category":"Wholesale",
            "subcategory":"Sporting Goods",
            "type":"Manufacturing & Wholesale Goods"
        }
    ],
    "sg:phone":"+1 410 867 7665",
    "sg:postcode":"20751",
    "sg:province":"MD",
    "sg:tags":[
        "equipment",
        "pool",
        "swimming"
    ],
    "wof:name":"Pool Perfect Inc",
    "wof:placetype":"venue"
},
  "geometry": {"coordinates":[-76.545696,38.793507],"type":"Point"}
}