{
  "type": "Feature",
  "properties": {
    "addr:full":"10750 Demarr Rd White Plains MD 20695",
    "addr:housenumber":"10750",
    "addr:postcode":"20695",
    "addr:street":"Demarr Rd",
    "iso:country":"US",
    "sg:address":"10750 Demarr Rd",
    "sg:city":"White Plains",
    "sg:classifiers":[
        {
            "category":"Utilities",
            "subcategory":"Natural Gas",
            "type":"Services"
        }
    ],
    "sg:phone":"+1 301 283 0549",
    "sg:postcode":"20695",
    "sg:province":"MD",
    "sg:tags":[
        "company"
    ],
    "sg:website":"www.vngas.com",
    "wof:name":"Valley National Gases Inc",
    "wof:placetype":"venue"
},
  "geometry": {"coordinates":[-76.93938300000001,38.589923],"type":"Point"}
}