{
  "type": "Feature",
  "properties": {
    "addr:full":"320 Romancoke Rd Stevensville MD 21666",
    "addr:housenumber":"320",
    "addr:postcode":"21666",
    "addr:street":"Romancoke Rd",
    "iso:country":"US",
    "sg:address":"320 Romancoke Rd",
    "sg:city":"Stevensville",
    "sg:classifiers":[
        {
            "category":"Food & Beverages",
            "subcategory":"Groceries & Convenience Stores",
            "type":"Retail Goods"
        }
    ],
    "sg:phone":"+1 410 604 3000",
    "sg:postcode":"21666",
    "sg:province":"MD",
    "sg:website":"www.kidepot.com",
    "wof:name":"Kent Island Depot",
    "wof:placetype":"venue"
},
  "geometry": {"coordinates":[-76.325992,38.973459],"type":"Point"}
}