{
  "type": "Feature",
  "properties": {
    "iso:country":"US",
    "sg:address":"8952 Deal Island Rd",
    "sg:city":"Deal Island",
    "sg:classifiers":[
        {
            "category":"Food & Beverages",
            "subcategory":"Groceries & Convenience Stores",
            "type":"Retail Goods"
        }
    ],
    "sg:phone":"+1 410 784 2749",
    "sg:postcode":"21821",
    "sg:province":"MD",
    "wof:name":"Arby & Deb Sea Rations",
    "wof:placetype":"venue"
},
  "geometry": {"coordinates":[-75.94969399999999,38.129448],"type":"Point"}
}