{
  "type": "Feature",
  "properties": {
    "addr:full":"1550 Country Ridge Ln Essex MD 21221",
    "addr:housenumber":"1550",
    "addr:postcode":"21221",
    "addr:street":"Country Ridge Ln",
    "iso:country":"US",
    "sg:address":"1550 Country Ridge Ln",
    "sg:city":"Essex",
    "sg:classifiers":[
        {
            "category":"Personal",
            "subcategory":"Shoe Repair & Shine",
            "type":"Services"
        }
    ],
    "sg:phone":"+1 410 686 0192",
    "sg:postcode":"21221",
    "sg:province":"MD",
    "sg:tags":[
        "dry",
        "repairing",
        "laundry",
        "boot",
        "commercial",
        "cleaning"
    ],
    "wof:name":"Martin One Hour Dry Cleaners & Laundry",
    "wof:placetype":"venue"
},
  "geometry": {"coordinates":[-76.446602,39.310501],"type":"Point"}
}