{
  "type": "Feature",
  "properties": {
    "addr:full":"638 Glynlee Ct Reisterstown MD 21136",
    "addr:housenumber":"638",
    "addr:postcode":"21136",
    "addr:street":"Glynlee Ct",
    "iso:country":"US",
    "sg:address":"638 Glynlee Ct",
    "sg:city":"Reisterstown",
    "sg:classifiers":[
        {
            "category":"Building & Trades",
            "subcategory":"Construction",
            "type":"Services"
        }
    ],
    "sg:phone":"+1 410 526 7432",
    "sg:postcode":"21136",
    "sg:province":"MD",
    "sg:tags":[
        "house"
    ],
    "wof:name":"JD Home Imp",
    "wof:placetype":"venue"
},
  "geometry": {"coordinates":[-76.800957,39.462649],"type":"Point"}
}