{
  "type": "Feature",
  "properties": {
    "addr:full":"2116 N Charles St Baltimore MD 21218",
    "addr:housenumber":"2116",
    "addr:postcode":"21218",
    "addr:street":"N Charles St",
    "iso:country":"US",
    "sg:address":"2116 N Charles St",
    "sg:city":"Baltimore",
    "sg:classifiers":[
        {
            "category":"Shopping",
            "subcategory":"Party Supplies",
            "type":"Retail Goods"
        },
        {
            "category":"Personal",
            "type":"Services"
        }
    ],
    "sg:phone":"+1 410 377 9090",
    "sg:postcode":"21218",
    "sg:province":"MD",
    "sg:tags":[
        "favors",
        "planning",
        "event"
    ],
    "wof:name":"Balloon Bouquets",
    "wof:placetype":"venue"
},
  "geometry": {"coordinates":[-76.616702,39.313391],"type":"Point"}
}