{
  "type": "Feature",
  "properties": {
    "addr:full":"831 Forest Dr Ste B Annapolis MD 21403",
    "addr:housenumber":"831",
    "addr:postcode":"21403",
    "addr:street":"Forest Dr Ste B",
    "iso:country":"US",
    "sg:address":"831 Forest Dr Ste B",
    "sg:city":"Annapolis",
    "sg:classifiers":[
        {
            "category":"Health Services",
            "subcategory":"Health Practitioner",
            "type":"Services"
        },
        {
            "category":"Communications",
            "type":"Services"
        }
    ],
    "sg:phone":"+1 410 280 9788",
    "sg:postcode":"21403",
    "sg:province":"MD",
    "sg:tags":[
        "pathologist",
        "speech-language",
        "myofunctional",
        "therapy"
    ],
    "wof:name":"Chesapeake Speech Language Associates",
    "wof:placetype":"venue"
},
  "geometry": {"coordinates":[-76.499329,38.95199],"type":"Point"}
}