{
  "type": "Feature",
  "properties": {
    "addr:full":"1645 Marley Ave Glen Burnie MD 21060",
    "addr:housenumber":"1645",
    "addr:postcode":"21060",
    "addr:street":"Marley Ave",
    "iso:country":"US",
    "sg:address":"1645 Marley Ave",
    "sg:city":"Glen Burnie",
    "sg:classifiers":[
        {
            "category":"Recreation",
            "subcategory":"Marina",
            "type":"Entertainment"
        }
    ],
    "sg:phone":"+1 410 766 8809",
    "sg:postcode":"21060",
    "sg:province":"MD",
    "wof:name":"Captains Cove Marina",
    "wof:placetype":"venue"
},
  "geometry": {"coordinates":[-76.584367,39.180621],"type":"Point"}
}