{
  "type": "Feature",
  "properties": {
    "addr:full":"4622 Wilkens Ave Baltimore MD 21229",
    "addr:housenumber":"4622",
    "addr:postcode":"21229",
    "addr:street":"Wilkens Ave",
    "iso:country":"US",
    "sg:address":"4622 Wilkens Ave",
    "sg:city":"Baltimore",
    "sg:classifiers":[
        {
            "category":"Banks & Credit Unions",
            "subcategory":"Bank",
            "type":"Services"
        }
    ],
    "sg:phone":"+1 410 737 6670",
    "sg:postcode":"21229",
    "sg:province":"MD",
    "sg:tags":[
        "federal",
        "saving",
        "institution"
    ],
    "wof:name":"Chevy Chase Bank",
    "wof:placetype":"venue"
},
  "geometry": {"coordinates":[-76.697701,39.265301],"type":"Point"}
}