{
  "type": "Feature",
  "properties": {
    "addr:full":"962 W Central Ave Davidsonville MD 21035",
    "addr:housenumber":"962",
    "addr:postcode":"21035",
    "addr:street":"W Central Ave",
    "iso:country":"US",
    "sg:address":"962 W Central Ave",
    "sg:city":"Davidsonville",
    "sg:classifiers":[
        {
            "category":"Education",
            "subcategory":"School",
            "type":"Public Place"
        }
    ],
    "sg:phone":"+1 410 222 1655",
    "sg:postcode":"21035",
    "sg:province":"MD",
    "sg:website":"www.aacps.org",
    "wof:name":"Davidsonville Elementary Schl",
    "wof:placetype":"venue"
},
  "geometry": {"coordinates":[-76.63957000000001,38.917695],"type":"Point"}
}