{
  "type": "Feature",
  "properties": {
    "addr:full":"11710 Reisterstown Rd Reisterstown MD 21136",
    "addr:housenumber":"11710",
    "addr:postcode":"21136",
    "addr:street":"Reisterstown Rd",
    "iso:country":"US",
    "sg:address":"11710 Reisterstown Rd",
    "sg:city":"Reisterstown",
    "sg:classifiers":[
        {
            "category":"Health Services",
            "subcategory":"Podiatrist",
            "type":"Services"
        }
    ],
    "sg:phone":"+1 410 833 0040",
    "sg:postcode":"21136",
    "sg:province":"MD",
    "wof:name":"Le Bow Podiatry",
    "wof:placetype":"venue"
},
  "geometry": {"coordinates":[-76.811671,39.444804],"type":"Point"}
}