{
  "type": "Feature",
  "properties": {
    "addr:full":"15971 Meandering Dr Brandywine MD 20613",
    "addr:housenumber":"15971",
    "addr:postcode":"20613",
    "addr:street":"Meandering Dr",
    "iso:country":"US",
    "sg:address":"15971 Meandering Dr",
    "sg:city":"Brandywine",
    "sg:classifiers":[
        {
            "category":"Building & Trades",
            "subcategory":"Construction",
            "type":"Services"
        }
    ],
    "sg:phone":"+1 301 888 1404",
    "sg:postcode":"20613",
    "sg:province":"MD",
    "sg:tags":[
        "contractor"
    ],
    "wof:name":"MIH Builders",
    "wof:placetype":"venue"
},
  "geometry": {"coordinates":[-76.75779,38.595794],"type":"Point"}
}