{
  "type": "Feature",
  "properties": {
    "addr:full":"350 N Aurora St Easton MD 21601",
    "addr:housenumber":"350",
    "addr:postcode":"21601",
    "addr:street":"N Aurora St",
    "iso:country":"US",
    "sg:address":"350 N Aurora St",
    "sg:city":"Easton",
    "sg:classifiers":[
        {
            "category":"Real Estate",
            "subcategory":"Real Estate Agent",
            "type":"Services"
        }
    ],
    "sg:phone":"+1 410 822 7620",
    "sg:postcode":"21601",
    "sg:province":"MD",
    "sg:tags":[
        "management"
    ],
    "wof:name":"Dietz Property Management",
    "wof:placetype":"venue"
},
  "geometry": {"coordinates":[-76.071941,38.782727],"type":"Point"}
}