{
  "type": "Feature",
  "properties": {
    "iso:country":"US",
    "sg:address":"6503 Park Heights Ave",
    "sg:city":"Baltimore",
    "sg:classifiers":[
        {
            "category":"Real Estate",
            "subcategory":"Real Estate Operator",
            "type":"Services"
        }
    ],
    "sg:phone":"+1 410 358 4185",
    "sg:postcode":"21215",
    "sg:province":"MD",
    "sg:tags":[
        "apartment"
    ],
    "wof:name":"Windsor House Apartments of Pikesville",
    "wof:placetype":"venue"
},
  "geometry": {"coordinates":[-76.69760100000001,39.360699],"type":"Point"}
}