{
  "type": "Feature",
  "properties": {
    "iso:country":"US",
    "sg:address":"240 E Washington St",
    "sg:city":"Hagerstown",
    "sg:classifiers":[
        {
            "category":"Home & Garden",
            "subcategory":"Furniture",
            "type":"Retail Goods"
        }
    ],
    "sg:phone":"+1 301 797 0030",
    "sg:postcode":"21740",
    "sg:province":"MD",
    "wof:name":"Barber's Daughter",
    "wof:placetype":"venue"
},
  "geometry": {"coordinates":[-77.71527399999999,39.639737],"type":"Point"}
}