{
  "type": "Feature",
  "properties": {
    "addr:full":"5830 Flannery Ln Baltimore MD 21207",
    "addr:housenumber":"5830",
    "addr:postcode":"21207",
    "addr:street":"Flannery Ln",
    "iso:country":"US",
    "sg:address":"5830 Flannery Ln",
    "sg:city":"Baltimore",
    "sg:classifiers":[
        {
            "category":"Building & Trades",
            "subcategory":"Construction",
            "type":"Services"
        }
    ],
    "sg:phone":"+1 410 944 8685",
    "sg:postcode":"21207",
    "sg:province":"MD",
    "sg:tags":[
        "resurfacing",
        "laying",
        "refinishing",
        "floor"
    ],
    "wof:name":"Young's Floor Svc",
    "wof:placetype":"venue"
},
  "geometry": {"coordinates":[-76.719185,39.330646],"type":"Point"}
}