{
  "type": "Feature",
  "properties": {
    "iso:country":"US",
    "sg:address":"580 Frederick Rd",
    "sg:city":"Catonsville",
    "sg:classifiers":[
        {
            "category":"Bagels",
            "type":"Food & Drink"
        },
        {
            "category":"Coffee & Tea",
            "type":"Food & Drink"
        },
        {
            "category":"Food & Beverages",
            "subcategory":"Bakery",
            "type":"Retail Goods"
        },
        {
            "category":"Bakery",
            "type":"Food & Drink"
        },
        {
            "category":"Donuts",
            "type":"Food & Drink"
        }
    ],
    "sg:menulink":"http://www.allmenus.com/md/catonsville/148958-dunkin-donuts/menu/",
    "sg:phone":"+1 410 788 7001",
    "sg:postcode":"21228",
    "sg:province":"MD",
    "sg:tags":[
        "coffee",
        "sandwich",
        "tea",
        "american",
        "bagel",
        "bakery",
        "pastry",
        "wrap"
    ],
    "wof:name":"Dunkin' Donuts",
    "wof:placetype":"venue"
},
  "geometry": {"coordinates":[-76.728515,39.272725],"type":"Point"}
}