{
  "type": "Feature",
  "properties": {
    "iso:country":"US",
    "sg:address":"3072 Waldorf Market Pl",
    "sg:city":"Waldorf",
    "sg:classifiers":[
        {
            "category":"Restaurant",
            "type":"Food & Drink"
        }
    ],
    "sg:menulink":"http://www.allmenus.com/md/waldorf/8650-red-robin/menu/",
    "sg:phone":"+1 301 374 2290",
    "sg:postcode":"20603",
    "sg:province":"MD",
    "sg:tags":[
        "american"
    ],
    "wof:name":"Red Robin",
    "wof:placetype":"venue"
},
  "geometry": {"coordinates":[-76.91870900000001,38.62691],"type":"Point"}
}