{
  "type": "Feature",
  "properties": {
    "addr:full":"6655 Detrick Rd Mount Airy MD 21771",
    "addr:housenumber":"6655",
    "addr:postcode":"21771",
    "addr:street":"Detrick Rd",
    "iso:country":"US",
    "sg:address":"6655 Detrick Rd",
    "sg:city":"Mount Airy",
    "sg:classifiers":[
        {
            "category":"Building & Trades",
            "subcategory":"Construction",
            "type":"Services"
        }
    ],
    "sg:phone":"+1 301 831 5030",
    "sg:postcode":"21771",
    "sg:province":"MD",
    "sg:tags":[
        "builder",
        "operative"
    ],
    "wof:name":"Strayer Building Company",
    "wof:placetype":"venue"
},
  "geometry": {"coordinates":[-77.213312,39.41581],"type":"Point"}
}