{
  "type": "Feature",
  "properties": {
    "addr:full":"1617 Davinda Dr Finksburg MD 21048",
    "addr:housenumber":"1617",
    "addr:postcode":"21048",
    "addr:street":"Davinda Dr",
    "iso:country":"US",
    "sg:address":"1617 Davinda Dr",
    "sg:city":"Finksburg",
    "sg:classifiers":[
        {
            "category":"Professional",
            "subcategory":"Management & Consulting",
            "type":"Services"
        }
    ],
    "sg:phone":"+1 410 857 4774",
    "sg:postcode":"21048",
    "sg:province":"MD",
    "sg:tags":[
        "business"
    ],
    "wof:name":"Custom Work Consultants",
    "wof:placetype":"venue"
},
  "geometry": {"coordinates":[-76.93619,39.50059],"type":"Point"}
}