{
  "type": "Feature",
  "properties": {
    "addr:full":"1013 Boyce Ave Baltimore MD 21204",
    "addr:housenumber":"1013",
    "addr:postcode":"21204",
    "addr:street":"Boyce Ave",
    "iso:country":"US",
    "sg:address":"1013 Boyce Ave",
    "sg:city":"Baltimore",
    "sg:classifiers":[
        {
            "category":"Health Services",
            "subcategory":"Doctor",
            "type":"Services"
        }
    ],
    "sg:phone":"+1 410 494 8840",
    "sg:postcode":"21204",
    "sg:province":"MD",
    "sg:tags":[
        "medical"
    ],
    "wof:name":"Maryland Health Associate",
    "wof:placetype":"venue"
},
  "geometry": {"coordinates":[-76.630945,39.402253],"type":"Point"}
}