{
  "type": "Feature",
  "properties": {
    "addr:full":"8229 Bodkin Ave Pasadena MD 21122",
    "addr:housenumber":"8229",
    "addr:postcode":"21122",
    "addr:street":"Bodkin Ave",
    "iso:country":"US",
    "sg:address":"8229 Bodkin Ave",
    "sg:city":"Pasadena",
    "sg:classifiers":[
        {
            "category":"Manufacturing",
            "subcategory":"Tools & Machinery",
            "type":"Manufacturing & Wholesale Goods"
        }
    ],
    "sg:phone":"+1 410 437 0174",
    "sg:postcode":"21122",
    "sg:province":"MD",
    "sg:tags":[
        "electronic",
        "assembly"
    ],
    "wof:name":"Mattox Enterprises",
    "wof:placetype":"venue"
},
  "geometry": {"coordinates":[-76.478213,39.118331],"type":"Point"}
}