{
  "type": "Feature",
  "properties": {
    "iso:country":"US",
    "sg:address":"17656 Garland Groh Blvd",
    "sg:city":"Hagerstown",
    "sg:classifiers":[
        {
            "category":"Shopping",
            "subcategory":"Hobbies, Toys, & Games",
            "type":"Retail Goods"
        }
    ],
    "sg:phone":"+1 301 739 4888",
    "sg:postcode":"21740",
    "sg:province":"MD",
    "sg:tags":[
        "craft",
        "supply"
    ],
    "sg:website":"www.acmoore.com",
    "wof:name":"A C Moore",
    "wof:placetype":"venue"
},
  "geometry": {"coordinates":[-77.753978,39.653809],"type":"Point"}
}