{
  "type": "Feature",
  "properties": {
    "iso:country":"US",
    "sg:address":"200 E 33rd St",
    "sg:city":"Baltimore",
    "sg:classifiers":[
        {
            "category":"Health Services",
            "subcategory":"Doctor",
            "type":"Services"
        }
    ],
    "sg:phone":"+1 410 554 2729",
    "sg:postcode":"21218",
    "sg:province":"MD",
    "sg:tags":[
        "physician",
        "surgeon",
        "surgeons",
        "surgery-general"
    ],
    "wof:name":"Steven Lauzon Md",
    "wof:placetype":"venue"
},
  "geometry": {"coordinates":[-76.614906,39.32827],"type":"Point"}
}