{
  "type": "Feature",
  "properties": {
    "addr:full":"5832 Kirby Rd Clinton MD 20735",
    "addr:housenumber":"5832",
    "addr:postcode":"20735",
    "addr:street":"Kirby Rd",
    "iso:country":"US",
    "sg:address":"5832 Kirby Rd",
    "sg:city":"Clinton",
    "sg:classifiers":[
        {
            "category":"Retail",
            "subcategory":"Laundry & Dry Cleaning",
            "type":"Services"
        }
    ],
    "sg:phone":"+1 301 856 0700",
    "sg:postcode":"20735",
    "sg:province":"MD",
    "sg:tags":[
        "cleaners",
        "rug",
        "carpet"
    ],
    "wof:name":"Affordable Carpet",
    "wof:placetype":"venue"
},
  "geometry": {"coordinates":[-76.905564,38.784817],"type":"Point"}
}