{
  "type": "Feature",
  "properties": {
    "addr:full":"334 Lees Mill Rd Hampstead MD 21074",
    "addr:housenumber":"334",
    "addr:postcode":"21074",
    "addr:street":"Lees Mill Rd",
    "iso:country":"US",
    "sg:address":"334 Lees Mill Rd",
    "sg:city":"Hampstead",
    "sg:classifiers":[
        {
            "category":"Wholesale",
            "subcategory":"Farm Supplies",
            "type":"Manufacturing & Wholesale Goods"
        }
    ],
    "sg:phone":"+1 410 374 4333",
    "sg:postcode":"21074",
    "sg:province":"MD",
    "sg:tags":[
        "grain",
        "elevator"
    ],
    "wof:name":"Donald Lippy",
    "wof:placetype":"venue"
},
  "geometry": {"coordinates":[-76.854561,39.566872],"type":"Point"}
}