{
  "type": "Feature",
  "properties": {
    "addr:full":"926 Gallatin St NW Washington MD 20011",
    "addr:housenumber":"926",
    "addr:postcode":"20011",
    "addr:street":"Gallatin St Nw",
    "iso:country":"US",
    "sg:address":"926 Gallatin St NW",
    "sg:city":"Washington",
    "sg:classifiers":[
        {
            "category":"Real Estate",
            "subcategory":"Architect",
            "type":"Services"
        }
    ],
    "sg:phone":"+1 202 722 4200",
    "sg:postcode":"20011",
    "sg:province":"MD",
    "sg:tags":[
        "estimate",
        "construction"
    ],
    "wof:name":"Dag Construction Corp",
    "wof:placetype":"venue"
},
  "geometry": {"coordinates":[-77.025116,38.951854],"type":"Point"}
}