{
  "type": "Feature",
  "properties": {
    "addr:full":"5500 Baltimore Ave Hyattsville MD 20781",
    "addr:housenumber":"5500",
    "addr:postcode":"20781",
    "addr:street":"Baltimore Ave",
    "iso:country":"US",
    "sg:address":"5500 Baltimore Ave",
    "sg:city":"Hyattsville",
    "sg:classifiers":[
        {
            "category":"Professional",
            "subcategory":"Lawyer & Legal Services",
            "type":"Services"
        }
    ],
    "sg:phone":"+1 301 209 0037",
    "sg:postcode":"20781",
    "sg:province":"MD",
    "sg:website":"www.law.help.com",
    "wof:name":"Cohen & Dwin PA",
    "wof:placetype":"venue"
},
  "geometry": {"coordinates":[-76.940415,38.955345],"type":"Point"}
}