{
  "type": "Feature",
  "properties": {
    "iso:country":"US",
    "sg:address":"8735 Bollman Pl",
    "sg:city":"Savage",
    "sg:classifiers":[
        {
            "category":"Wholesale",
            "subcategory":"Machinery & Supplies",
            "type":"Manufacturing & Wholesale Goods"
        }
    ],
    "sg:phone":"+1 301 776 0408",
    "sg:postcode":"20763",
    "sg:province":"MD",
    "sg:tags":[
        "equipment",
        "baker"
    ],
    "wof:name":"Charles Pyle Bakery Machinery",
    "wof:placetype":"venue"
},
  "geometry": {"coordinates":[-76.805757,39.130267],"type":"Point"}
}