{
  "type": "Feature",
  "properties": {
    "iso:country":"US",
    "sg:address":"8146 Quarterfield Rd",
    "sg:city":"Severn",
    "sg:classifiers":[
        {
            "category":"Restaurant",
            "type":"Food & Drink"
        }
    ],
    "sg:phone":"+1 410 551 0445",
    "sg:postcode":"21144",
    "sg:province":"MD",
    "sg:tags":[
        "caterer"
    ],
    "wof:name":"Quarterfield Catering & Cafe",
    "wof:placetype":"venue"
},
  "geometry": {"coordinates":[-76.67010000000001,39.120925],"type":"Point"}
}