{
  "type": "Feature",
  "properties": {
    "addr:full":"8146 Quarterfield Rd Severn MD 21144",
    "addr:housenumber":"8146",
    "addr:postcode":"21144",
    "addr:street":"Quarterfield Rd",
    "iso:country":"US",
    "sg:address":"8146 Quarterfield Rd",
    "sg:city":"Severn",
    "sg:classifiers":[
        {
            "category":"Restaurant",
            "type":"Food & Drink"
        }
    ],
    "sg:phone":"+1 410 551 0445",
    "sg:postcode":"21144",
    "sg:province":"MD",
    "sg:tags":[
        "caterer"
    ],
    "wof:name":"Quarterfield Catering & Cafe",
    "wof:placetype":"venue"
},
  "geometry": {"coordinates":[-76.67010000000001,39.120925],"type":"Point"}
}