{
  "type": "Feature",
  "properties": {
    "iso:country":"US",
    "sg:address":"13221 Rippling Brook Dr",
    "sg:city":"Silver Spring",
    "sg:classifiers":[
        {
            "category":"Professional",
            "subcategory":"Research",
            "type":"Services"
        }
    ],
    "sg:phone":"+1 301 871 1095",
    "sg:postcode":"20906",
    "sg:province":"MD",
    "sg:tags":[
        "development",
        "electronic"
    ],
    "wof:name":"Chronometrics",
    "wof:placetype":"venue"
},
  "geometry": {"coordinates":[-77.06364000000001,39.072822],"type":"Point"}
}