{
  "type": "Feature",
  "properties": {
    "iso:country":"US",
    "sg:address":"13975 Connecticut Ave",
    "sg:city":"Aspen Hill",
    "sg:phone":"+1 301 603 0052",
    "sg:postcode":"20906",
    "sg:province":"MD",
    "sg:tags":[
        "shelving"
    ],
    "wof:name":"Interior Metal Equip Erection",
    "wof:placetype":"venue"
},
  "geometry": {"coordinates":[-77.07843800000001,39.083463],"type":"Point"}
}