{
  "type": "Feature",
  "properties": {
    "iso:country":"US",
    "sg:address":"2308 Eutaw Pl",
    "sg:city":"Baltimore",
    "sg:classifiers":[
        {
            "category":"Shopping",
            "subcategory":"Clothing, Apparel, & Fashions",
            "type":"Retail Goods"
        }
    ],
    "sg:phone":"+1 410 234 0053",
    "sg:postcode":"21217",
    "sg:province":"MD",
    "sg:tags":[
        "accessory",
        "clothing",
        "women's"
    ],
    "wof:name":"Accessories Plus",
    "wof:placetype":"venue"
},
  "geometry": {"coordinates":[-76.63584400000001,39.311862],"type":"Point"}
}