{
  "type": "Feature",
  "properties": {
    "iso:country":"US",
    "sg:address":"7600 Energy Pkwy",
    "sg:city":"Baltimore",
    "sg:classifiers":[
        {
            "category":"Manufacturing",
            "subcategory":"Chemicals & Compounds",
            "type":"Manufacturing & Wholesale Goods"
        }
    ],
    "sg:phone":"+1 410 437 7725",
    "sg:postcode":"21226",
    "sg:province":"MD",
    "sg:tags":[
        "cosmetic"
    ],
    "wof:name":"Arcade Marketing",
    "wof:placetype":"venue"
},
  "geometry": {"coordinates":[-76.551578,39.177102],"type":"Point"}
}