{
  "type": "Feature",
  "properties": {
    "iso:country":"US",
    "sg:address":"2984 Main St",
    "sg:city":"Manchester",
    "sg:classifiers":[
        {
            "category":"Autos & Motor Vehicles",
            "subcategory":"Automobile Sales",
            "type":"Retail Goods"
        }
    ],
    "sg:phone":"+1 410 239 3699",
    "sg:postcode":"21102",
    "sg:province":"MD",
    "sg:tags":[
        "car",
        "dealer"
    ],
    "wof:name":"Manchester Motor Co",
    "wof:placetype":"venue"
},
  "geometry": {"coordinates":[-76.88162,39.655442],"type":"Point"}
}