{
  "type": "Feature",
  "properties": {
    "addr:full":"1016 Double Gate Rd Davidsonville MD 21035",
    "addr:housenumber":"1016",
    "addr:postcode":"21035",
    "addr:street":"Double Gate Rd",
    "iso:country":"US",
    "sg:address":"1016 Double Gate Rd",
    "sg:city":"Davidsonville",
    "sg:classifiers":[
        {
            "category":"Real Estate",
            "subcategory":"Real Estate Agent",
            "type":"Services"
        }
    ],
    "sg:phone":"+1 410 854 4832",
    "sg:postcode":"21035",
    "sg:province":"MD",
    "wof:name":"William Wood",
    "wof:placetype":"venue"
},
  "geometry": {"coordinates":[-76.643501,38.938229],"type":"Point"}
}