{
  "type": "Feature",
  "properties": {
    "iso:country":"US",
    "sg:address":"15751 Columbia Pike",
    "sg:city":"Burtonsville",
    "sg:classifiers":[
        {
            "category":"Shopping",
            "subcategory":"Crafts & Fabrics",
            "type":"Retail Goods"
        }
    ],
    "sg:phone":"+1 301 421 5977",
    "sg:postcode":"20866",
    "sg:province":"MD",
    "sg:tags":[
        "art",
        "supply"
    ],
    "wof:name":"Hobby City",
    "wof:placetype":"venue"
},
  "geometry": {"coordinates":[-76.923401,39.12624],"type":"Point"}
}