{
  "type": "Feature",
  "properties": {
    "iso:country":"US",
    "sg:address":"7404 Executive Pl",
    "sg:city":"Lanham",
    "sg:classifiers":[
        {
            "category":"Manufacturing",
            "subcategory":"Tools & Machinery",
            "type":"Manufacturing & Wholesale Goods"
        }
    ],
    "sg:phone":"+1 301 464 4700",
    "sg:postcode":"20706",
    "sg:province":"MD",
    "sg:tags":[
        "industry",
        "aerospace"
    ],
    "wof:name":"Ball Aerospace & Technologies",
    "wof:placetype":"venue"
},
  "geometry": {"coordinates":[-76.82874,38.991348],"type":"Point"}
}