{
  "type": "Feature",
  "properties": {
    "iso:country":"US",
    "sg:address":"103 Sunset Dr",
    "sg:city":"Annapolis",
    "sg:classifiers":[
        {
            "category":"Professional",
            "subcategory":"Management & Consulting",
            "type":"Services"
        }
    ],
    "sg:phone":"+1 410 263 1998",
    "sg:postcode":"21403",
    "sg:province":"MD",
    "sg:tags":[
        "environmental",
        "ecological",
        "consultant"
    ],
    "wof:name":"Chesapeake Wildlife And Wetlands Foundat",
    "wof:placetype":"venue"
},
  "geometry": {"coordinates":[-76.494032,38.928323],"type":"Point"}
}