{
  "type": "Feature",
  "properties": {
    "addr:full":"320 Cinnabar Ln Bel Air MD 21015",
    "addr:housenumber":"320",
    "addr:postcode":"21015",
    "addr:street":"Cinnabar Ln",
    "iso:country":"US",
    "sg:address":"320 Cinnabar Ln",
    "sg:city":"Bel Air",
    "sg:classifiers":[
        {
            "category":"Building & Trades",
            "subcategory":"Construction",
            "type":"Services"
        }
    ],
    "sg:phone":"+1 410 515 0755",
    "sg:postcode":"21015",
    "sg:province":"MD",
    "sg:tags":[
        "painting",
        "contractor"
    ],
    "wof:name":"Associate Craftsman",
    "wof:placetype":"venue"
},
  "geometry": {"coordinates":[-76.333167,39.489473],"type":"Point"}
}