{
  "type": "Feature",
  "properties": {
    "iso:country":"US",
    "sg:address":"4806 Bethesda Ave",
    "sg:city":"Bethesda",
    "sg:classifiers":[
        {
            "category":"Home & Garden",
            "subcategory":"Home Furnishings",
            "type":"Retail Goods"
        }
    ],
    "sg:phone":"+1 301 913 0002",
    "sg:postcode":"20814",
    "sg:province":"MD",
    "sg:tags":[
        "linen"
    ],
    "wof:name":"Wallpoles",
    "wof:placetype":"venue"
},
  "geometry": {"coordinates":[-77.094878,38.980874],"type":"Point"}
}