{
  "type": "Feature",
  "properties": {
    "addr:full":"15910 Indianola Dr Rockville MD 20855",
    "addr:housenumber":"15910",
    "addr:postcode":"20855",
    "addr:street":"Indianola Dr",
    "iso:country":"US",
    "sg:address":"15910 Indianola Dr",
    "sg:city":"Rockville",
    "sg:classifiers":[
        {
            "category":"Manufacturing",
            "subcategory":"Glass & Minerals",
            "type":"Manufacturing & Wholesale Goods"
        }
    ],
    "sg:phone":"+1 301 670 2794",
    "sg:postcode":"20855",
    "sg:province":"MD",
    "sg:tags":[
        "product",
        "marble"
    ],
    "wof:name":"Fernando's Marble Shop Inc",
    "wof:placetype":"venue"
},
  "geometry": {"coordinates":[-77.159994,39.114063],"type":"Point"}
}