{
  "type": "Feature",
  "properties": {
    "addr:full":"17740 Muncaster Rd Derwood MD 20855",
    "addr:housenumber":"17740",
    "addr:postcode":"20855",
    "addr:street":"Muncaster Rd",
    "iso:country":"US",
    "sg:address":"17740 Muncaster Rd",
    "sg:city":"Derwood",
    "sg:classifiers":[
        {
            "category":"Organizations",
            "subcategory":"Religious Organization",
            "type":"Services"
        }
    ],
    "sg:phone":"+1 301 926 1220",
    "sg:postcode":"20855",
    "sg:province":"MD",
    "sg:tags":[
        "church"
    ],
    "sg:website":"www.stlukesderwood.org",
    "wof:name":"St Luke Lutheran Church",
    "wof:placetype":"venue"
},
  "geometry": {"coordinates":[-77.143156,39.14699],"type":"Point"}
}