{
  "type": "Feature",
  "properties": {
    "addr:full":"1301 Iron Forge Rd Forestville MD 20747",
    "addr:housenumber":"1301",
    "addr:postcode":"20747",
    "addr:street":"Iron Forge Rd",
    "iso:country":"US",
    "sg:address":"1301 Iron Forge Rd",
    "sg:city":"Forestville",
    "sg:classifiers":[
        {
            "category":"Shopping",
            "subcategory":"Clothing, Apparel, & Fashions",
            "type":"Retail Goods"
        }
    ],
    "sg:phone":"+1 301 324 3786",
    "sg:postcode":"20747",
    "sg:province":"MD",
    "sg:tags":[
        "dressmaker"
    ],
    "wof:name":"Marcel Fashions",
    "wof:placetype":"venue"
},
  "geometry": {"coordinates":[-76.878558,38.870456],"type":"Point"}
}