{
  "type": "Feature",
  "properties": {
    "iso:country":"US",
    "sg:address":"12745 Triadelphia Rd",
    "sg:city":"Ellicott City",
    "sg:classifiers":[
        {
            "category":"Health Services",
            "subcategory":"Health Practitioner",
            "type":"Services"
        }
    ],
    "sg:phone":"+1 410 531 9958",
    "sg:postcode":"21042",
    "sg:province":"MD",
    "sg:tags":[
        "nurse",
        "registry"
    ],
    "wof:name":"Glenda M Hull Rn Nurse Cnslnt",
    "wof:placetype":"venue"
},
  "geometry": {"coordinates":[-76.95018399999999,39.277757],"type":"Point"}
}