{
  "type": "Feature",
  "properties": {
    "addr:full":"801 S Carey St Baltimore MD 21223",
    "addr:housenumber":"801",
    "addr:postcode":"21223",
    "addr:street":"S Carey St",
    "iso:country":"US",
    "sg:address":"801 S Carey St",
    "sg:city":"Baltimore",
    "sg:classifiers":[
        {
            "category":"Personal",
            "type":"Services"
        }
    ],
    "sg:phone":"+1 410 547 7758",
    "sg:postcode":"21223",
    "sg:province":"MD",
    "sg:tags":[
        "towing"
    ],
    "wof:name":"Kerns Motors",
    "wof:placetype":"venue"
},
  "geometry": {"coordinates":[-76.63688,39.282677],"type":"Point"}
}