{
  "type": "Feature",
  "properties": {
    "addr:full":"12289 Tech Rd Silver Spring MD 20904",
    "addr:housenumber":"12289",
    "addr:postcode":"20904",
    "addr:street":"Tech Rd",
    "iso:country":"US",
    "sg:address":"12289 Tech Rd",
    "sg:city":"Silver Spring",
    "sg:classifiers":[
        {
            "category":"Fast Food",
            "type":"Food & Drink"
        }
    ],
    "sg:phone":"+1 301 622 2353",
    "sg:postcode":"20904",
    "sg:province":"MD",
    "sg:website":"www.chick-fil-a.com/",
    "wof:name":"Chick-fil-A",
    "wof:placetype":"venue"
},
  "geometry": {"coordinates":[-76.966464,39.055763],"type":"Point"}
}