{
  "type": "Feature",
  "properties": {
    "addr:full":"610 Bosley Ave Baltimore MD 21204",
    "addr:housenumber":"610",
    "addr:postcode":"21204",
    "addr:street":"Bosley Ave",
    "iso:country":"US",
    "sg:address":"610 Bosley Ave",
    "sg:city":"Baltimore",
    "sg:classifiers":[
        {
            "category":"Professional",
            "subcategory":"Lawyer & Legal Services",
            "type":"Services"
        }
    ],
    "sg:phone":"+1 410 296 2600",
    "sg:postcode":"21204",
    "sg:province":"MD",
    "sg:tags":[
        "attorney"
    ],
    "wof:name":"Charles E Brooks",
    "wof:placetype":"venue"
},
  "geometry": {"coordinates":[-76.608437,39.402574],"type":"Point"}
}