{
  "type": "Feature",
  "properties": {
    "iso:country":"US",
    "sg:address":"11403 Cronridge Dr",
    "sg:city":"Owings Mills",
    "sg:classifiers":[
        {
            "category":"Professional",
            "subcategory":"Employment Agencies",
            "type":"Services"
        }
    ],
    "sg:phone":"+1 410 654 5665",
    "sg:postcode":"21117",
    "sg:province":"MD",
    "sg:tags":[
        "leasing"
    ],
    "wof:name":"Advanced Information Research",
    "wof:placetype":"venue"
},
  "geometry": {"coordinates":[-76.77577599999999,39.440841],"type":"Point"}
}