{
  "type": "Feature",
  "properties": {
    "addr:full":"2664 Riva Rd Ste 170 Annapolis MD 21401",
    "addr:housenumber":"2664",
    "addr:postcode":"21401",
    "addr:street":"Riva Rd Ste 170",
    "iso:country":"US",
    "sg:address":"2664 Riva Rd Ste 170",
    "sg:city":"Annapolis",
    "sg:classifiers":[
        {
            "category":"Banks & Credit Unions",
            "subcategory":"Investment Brokerage",
            "type":"Services"
        }
    ],
    "sg:phone":"+1 410 222 7441",
    "sg:postcode":"21401",
    "sg:province":"MD",
    "sg:tags":[
        "trust"
    ],
    "wof:name":"Anne Arundel County Trust For Preservation",
    "wof:placetype":"venue"
},
  "geometry": {"coordinates":[-76.559605,38.974765],"type":"Point"}
}