{
  "type": "Feature",
  "properties": {
    "addr:full":"703 Dorsey Ave Baltimore MD 21221",
    "addr:housenumber":"703",
    "addr:postcode":"21221",
    "addr:street":"Dorsey Ave",
    "iso:country":"US",
    "sg:address":"703 Dorsey Ave",
    "sg:city":"Baltimore",
    "sg:classifiers":[
        {
            "category":"Building & Trades",
            "subcategory":"Construction",
            "type":"Services"
        }
    ],
    "sg:phone":"+1 410 687 4136",
    "sg:postcode":"21221",
    "sg:province":"MD",
    "sg:tags":[
        "house"
    ],
    "wof:name":"FCA Construction Co",
    "wof:placetype":"venue"
},
  "geometry": {"coordinates":[-76.471575,39.311216],"type":"Point"}
}