{
  "type": "Feature",
  "properties": {
    "iso:country":"US",
    "sg:address":"1099 Taft St",
    "sg:city":"Rockville",
    "sg:classifiers":[
        {
            "category":"Retail",
            "subcategory":"Auto Repair",
            "type":"Services"
        }
    ],
    "sg:phone":"+1 301 424 0317",
    "sg:postcode":"20850",
    "sg:province":"MD",
    "sg:tags":[
        "repairing",
        "automobile"
    ],
    "wof:name":"Willy's Auto Repair",
    "wof:placetype":"venue"
},
  "geometry": {"coordinates":[-77.137237,39.093903],"type":"Point"}
}