{
  "type": "Feature",
  "properties": {
    "iso:country":"US",
    "sg:address":"2407 Sherwood Ave",
    "sg:city":"Baltimore",
    "sg:classifiers":[
        {
            "category":"Building & Trades",
            "subcategory":"Construction",
            "type":"Services"
        }
    ],
    "sg:phone":"+1 410 889 4115",
    "sg:postcode":"21218",
    "sg:province":"MD",
    "sg:tags":[
        "demolition",
        "contractor"
    ],
    "wof:name":"B & L Hauling",
    "wof:placetype":"venue"
},
  "geometry": {"coordinates":[-76.596446,39.31683],"type":"Point"}
}