{
  "type": "Feature",
  "properties": {
    "addr:full":"8511 Wild Game Ln Owings MD 20736",
    "addr:housenumber":"8511",
    "addr:postcode":"20736",
    "addr:street":"Wild Game Ln",
    "iso:country":"US",
    "sg:address":"8511 Wild Game Ln",
    "sg:city":"Owings",
    "sg:classifiers":[
        {
            "category":"Communications",
            "type":"Services"
        }
    ],
    "sg:phone":"+1 301 812 2600",
    "sg:postcode":"20736",
    "sg:province":"MD",
    "wof:name":"Calvert Communications Inc",
    "wof:placetype":"venue"
},
  "geometry": {"coordinates":[-76.664483,38.694556],"type":"Point"}
}