{
  "type": "Feature",
  "properties": {
    "iso:country":"US",
    "sg:address":"5602 Baltimore National Pike",
    "sg:city":"Catonsville",
    "sg:classifiers":[
        {
            "category":"Banks & Credit Unions",
            "subcategory":"Financial Services",
            "type":"Services"
        }
    ],
    "sg:phone":"+1 410 788 6933",
    "sg:postcode":"21228",
    "sg:province":"MD",
    "sg:tags":[
        "card-merchant",
        "card"
    ],
    "wof:name":"A & A International Group",
    "wof:placetype":"venue"
},
  "geometry": {"coordinates":[-76.727074,39.289299],"type":"Point"}
}