{
  "type": "Feature",
  "properties": {
    "iso:country":"US",
    "sg:address":"1911 Rosemary Hills Dr",
    "sg:city":"Silver Spring",
    "sg:classifiers":[
        {
            "category":"Education",
            "subcategory":"Dance Studio",
            "type":"Public Place"
        }
    ],
    "sg:phone":"+1 202 276 3222",
    "sg:postcode":"20910",
    "sg:province":"MD",
    "wof:name":"Pasew Mulu",
    "wof:placetype":"venue"
},
  "geometry": {"coordinates":[-77.042884,38.997657],"type":"Point"}
}