{
  "type": "Feature",
  "properties": {
    "addr:full":"8808 Centre Park Dr Ste 208 Columbia MD 21045",
    "addr:housenumber":"8808",
    "addr:postcode":"21045",
    "addr:street":"Centre Park Dr Ste 208",
    "iso:country":"US",
    "sg:address":"8808 Centre Park Dr Ste 208",
    "sg:city":"Columbia",
    "sg:classifiers":[
        {
            "category":"Professional",
            "subcategory":"Accounting & Tax Preparation",
            "type":"Services"
        },
        {
            "category":"Shopping",
            "subcategory":"Mobile Phones",
            "type":"Retail Goods"
        }
    ],
    "sg:phone":"+1 410 995 4000",
    "sg:postcode":"21045",
    "sg:province":"MD",
    "sg:tags":[
        "accountant"
    ],
    "wof:name":"Sturgill & Associates Llp Cpa's",
    "wof:placetype":"venue"
},
  "geometry": {"coordinates":[-76.816399,39.226601],"type":"Point"}
}