{
  "type": "Feature",
  "properties": {
    "iso:country":"US",
    "sg:address":"3330 Crain Hwy",
    "sg:city":"Bowie",
    "sg:classifiers":[
        {
            "category":"Shopping",
            "subcategory":"Department Store",
            "type":"Retail Goods"
        }
    ],
    "sg:phone":"+1 301 805 8238",
    "sg:postcode":"20716",
    "sg:province":"MD",
    "wof:name":"Wal-Mart",
    "wof:placetype":"venue"
},
  "geometry": {"coordinates":[-76.71781,38.933726],"type":"Point"}
}