{
  "type": "Feature",
  "properties": {
    "addr:full":"524 E Belvedere Ave Baltimore MD 21212",
    "addr:housenumber":"524",
    "addr:postcode":"21212",
    "addr:street":"E Belvedere Ave",
    "iso:country":"US",
    "sg:address":"524 E Belvedere Ave",
    "sg:city":"Baltimore",
    "sg:classifiers":[
        {
            "category":"Shopping",
            "subcategory":"Clothing, Apparel, & Fashions",
            "type":"Retail Goods"
        }
    ],
    "sg:phone":"+1 410 464 1240",
    "sg:postcode":"21212",
    "sg:province":"MD",
    "sg:tags":[
        "infant",
        "wear"
    ],
    "wof:name":"RAW Sugar",
    "wof:placetype":"venue"
},
  "geometry": {"coordinates":[-76.609905,39.364157],"type":"Point"}
}