{
  "type": "Feature",
  "properties": {
    "addr:full":"5114 Wright Ave Baltimore MD 21205",
    "addr:housenumber":"5114",
    "addr:postcode":"21205",
    "addr:street":"Wright Ave",
    "iso:country":"US",
    "sg:address":"5114 Wright Ave",
    "sg:city":"Baltimore",
    "sg:classifiers":[
        {
            "category":"Building & Trades",
            "subcategory":"Construction",
            "type":"Services"
        }
    ],
    "sg:phone":"+1 410 485 1409",
    "sg:postcode":"21205",
    "sg:province":"MD",
    "sg:tags":[
        "house"
    ],
    "wof:name":"Ryans Home Improvement",
    "wof:placetype":"venue"
},
  "geometry": {"coordinates":[-76.55638,39.307566],"type":"Point"}
}