{
  "type": "Feature",
  "properties": {
    "addr:full":"5900 Princess Garden Pkwy Lanham MD 20706",
    "addr:housenumber":"5900",
    "addr:postcode":"20706",
    "addr:street":"Princess Garden Pkwy",
    "iso:country":"US",
    "sg:address":"5900 Princess Garden Pkwy",
    "sg:city":"Lanham",
    "sg:classifiers":[
        {
            "category":"Health Services",
            "subcategory":"Dentist",
            "type":"Services"
        }
    ],
    "sg:phone":"+1 301 577 2962",
    "sg:postcode":"20706",
    "sg:province":"MD",
    "sg:tags":[
        "dental",
        "dentists-cosmetic",
        "clinic",
        "dentistry"
    ],
    "sg:website":"http://www.drdonchristopher.com",
    "wof:name":"Dr. Donald C Christopher",
    "wof:placetype":"venue"
},
  "geometry": {"coordinates":[-76.863319,38.961658],"type":"Point"}
}