{
  "type": "Feature",
  "properties": {
    "addr:full":"1119 Nelson St Rockville MD 20850",
    "addr:housenumber":"1119",
    "addr:postcode":"20850",
    "addr:street":"Nelson St",
    "iso:country":"US",
    "sg:address":"1119 Nelson St",
    "sg:city":"Rockville",
    "sg:classifiers":[
        {
            "category":"Building & Trades",
            "subcategory":"Construction",
            "type":"Services"
        }
    ],
    "sg:phone":"+1 301 294 0242",
    "sg:postcode":"20850",
    "sg:province":"MD",
    "sg:tags":[
        "contractor"
    ],
    "wof:name":"Mc Millian Contracting Inc",
    "wof:placetype":"venue"
},
  "geometry": {"coordinates":[-77.17385,39.091891],"type":"Point"}
}