{
  "type": "Feature",
  "properties": {
    "iso:country":"US",
    "sg:address":"9151 Hampton Overlook",
    "sg:city":"Capitol Heights",
    "sg:classifiers":[
        {
            "category":"Food & Beverages",
            "subcategory":"Meat & Fish",
            "type":"Retail Goods"
        }
    ],
    "sg:phone":"+1 301 333 2229",
    "sg:postcode":"20743",
    "sg:province":"MD",
    "sg:tags":[
        "hot",
        "dog"
    ],
    "wof:name":"Red Robin-Red Clover Cdc",
    "wof:placetype":"venue"
},
  "geometry": {"coordinates":[-76.84924700000001,38.885843],"type":"Point"}
}