{
  "type": "Feature",
  "properties": {
    "iso:country":"US",
    "sg:address":"2901 Druid Park Dr",
    "sg:city":"Baltimore",
    "sg:classifiers":[
        {
            "category":"Professional",
            "subcategory":"Detective & Security Services",
            "type":"Services"
        }
    ],
    "sg:phone":"+1 410 523 5080",
    "sg:postcode":"21215",
    "sg:province":"MD",
    "sg:tags":[
        "guard",
        "patrol"
    ],
    "wof:name":"Watkins Security Agency Inc",
    "wof:placetype":"venue"
},
  "geometry": {"coordinates":[-76.660352,39.323933],"type":"Point"}
}