{
  "type": "Feature",
  "properties": {
    "iso:country":"US",
    "sg:address":"7809 Ridge Rd",
    "sg:city":"Frederick",
    "sg:classifiers":[
        {
            "category":"Building & Trades",
            "subcategory":"Plumbing",
            "type":"Services"
        }
    ],
    "sg:phone":"+1 301 473 4015",
    "sg:postcode":"21702",
    "sg:province":"MD",
    "sg:tags":[
        "plumbing",
        "contractor"
    ],
    "wof:name":"Dennison Plumbing & Heating",
    "wof:placetype":"venue"
},
  "geometry": {"coordinates":[-77.50094300000001,39.454423],"type":"Point"}
}