{
  "type": "Feature",
  "properties": {
    "addr:full":"6208 District Heights Pkwy District Heights MD 20747",
    "addr:postcode":"6208;20747",
    "addr:street":"District Heights Pkwy",
    "iso:country":"US",
    "sg:address":"6208 District Heights Pkwy",
    "sg:city":"District Heights",
    "sg:classifiers":[
        {
            "category":"Organizations",
            "subcategory":"Non-profit Organization",
            "type":"Services"
        }
    ],
    "sg:phone":"+1 301 735 3399",
    "sg:postcode":"20747",
    "sg:province":"MD",
    "wof:name":"District Heights Fire Dept",
    "wof:placetype":"venue"
},
  "geometry": {"coordinates":[-76.89915499999999,38.857849],"type":"Point"}
}