{
  "type": "Feature",
  "properties": {
    "addr:full":"7524 Old Stage Rd Glen Burnie MD 21061",
    "addr:housenumber":"7524",
    "addr:postcode":"21061",
    "addr:street":"Old Stage Rd",
    "iso:country":"US",
    "sg:address":"7524 Old Stage Rd",
    "sg:city":"Glen Burnie",
    "sg:classifiers":[
        {
            "category":"Organizations",
            "subcategory":"Religious Organization",
            "type":"Services"
        }
    ],
    "sg:phone":"+1 410 766 2588",
    "sg:postcode":"21061",
    "sg:province":"MD",
    "sg:tags":[
        "church"
    ],
    "sg:website":"www.glenburniebaptist.org",
    "wof:name":"Glen Burnie Baptist Church",
    "wof:placetype":"venue"
},
  "geometry": {"coordinates":[-76.642782,39.157007],"type":"Point"}
}