{
  "type": "Feature",
  "properties": {
    "addr:full":"907 York Rd Towson MD 21204",
    "addr:housenumber":"907",
    "addr:postcode":"21204",
    "addr:street":"York Rd",
    "iso:country":"US",
    "sg:address":"907 York Rd",
    "sg:city":"Towson",
    "sg:classifiers":[
        {
            "category":"Professional",
            "type":"Services"
        }
    ],
    "sg:phone":"+1 410 337 2245",
    "sg:postcode":"21204",
    "sg:province":"MD",
    "sg:tags":[
        "establishment"
    ],
    "wof:name":"Statewide Bail Bonds",
    "wof:placetype":"venue"
},
  "geometry": {"coordinates":[-76.608188,39.408505],"type":"Point"}
}