{
  "type": "Feature",
  "properties": {
    "iso:country":"US",
    "sg:address":"9135 Piscataway Rd",
    "sg:city":"Clinton",
    "sg:classifiers":[
        {
            "category":"Health Services",
            "subcategory":"Doctor",
            "type":"Services"
        }
    ],
    "sg:phone":"+1 301 868 8291",
    "sg:postcode":"20735",
    "sg:province":"MD",
    "sg:tags":[
        "physician",
        "surgeon"
    ],
    "wof:name":"Wadeson Psychiatric Ctr",
    "wof:placetype":"venue"
},
  "geometry": {"coordinates":[-76.90229100000001,38.7647],"type":"Point"}
}