{
  "type": "Feature",
  "properties": {
    "addr:full":"3711 Ladova Way Springdale MD 20774",
    "addr:housenumber":"3711",
    "addr:postcode":"20774",
    "addr:street":"Ladova Way",
    "iso:country":"US",
    "sg:address":"3711 Ladova Way",
    "sg:city":"Springdale",
    "sg:classifiers":[
        {
            "category":"Organizations",
            "subcategory":"Non-profit Organization",
            "type":"Services"
        }
    ],
    "sg:phone":"+1 301 322 7613",
    "sg:postcode":"20774",
    "sg:province":"MD",
    "wof:name":"T T Thomas-Community Empwrmnt",
    "wof:placetype":"venue"
},
  "geometry": {"coordinates":[-76.844408,38.942341],"type":"Point"}
}