{
  "type": "Feature",
  "properties": {
    "addr:full":"7110 Lansdale St District Heights MD 20747",
    "addr:housenumber":"7110",
    "addr:postcode":"20747",
    "addr:street":"Lansdale St",
    "iso:country":"US",
    "sg:address":"7110 Lansdale St",
    "sg:city":"District Heights",
    "sg:classifiers":[
        {
            "category":"Organizations",
            "subcategory":"Membership Organization",
            "type":"Services"
        }
    ],
    "sg:phone":"+1 301 735 4253",
    "sg:postcode":"20747",
    "sg:province":"MD",
    "wof:name":"Urdc",
    "wof:placetype":"venue"
},
  "geometry": {"coordinates":[-76.882859,38.856254],"type":"Point"}
}