{
  "type": "Feature",
  "properties": {
    "iso:country":"US",
    "sg:address":"1545 Merritt Blvd",
    "sg:city":"Dundalk",
    "sg:classifiers":[
        {
            "category":"Utilities",
            "subcategory":"Telephone",
            "type":"Services"
        },
        {
            "category":"Communications",
            "type":"Services"
        }
    ],
    "sg:phone":"+1 410 284 8990",
    "sg:postcode":"21222",
    "sg:province":"MD",
    "sg:tags":[
        "system",
        "equipment",
        "carrier",
        "radiotelephone",
        "communications-common"
    ],
    "wof:name":"Eastern Cllular Communications",
    "wof:placetype":"venue"
},
  "geometry": {"coordinates":[-76.503124,39.274399],"type":"Point"}
}