{
  "type": "Feature",
  "properties": {
    "iso:country":"US",
    "sg:address":"8221 Preston Ct",
    "sg:city":"Jessup",
    "sg:classifiers":[
        {
            "category":"Building & Trades",
            "subcategory":"Equipment Rental",
            "type":"Services"
        }
    ],
    "sg:phone":"+1 301 776 7690",
    "sg:postcode":"20794",
    "sg:province":"MD",
    "sg:tags":[
        "leasing",
        "furniture"
    ],
    "wof:name":"Cort Trade Show Furnishings",
    "wof:placetype":"venue"
},
  "geometry": {"coordinates":[-76.79353399999999,39.147562],"type":"Point"}
}