{
  "type": "Feature",
  "properties": {
    "iso:country":"US",
    "sg:address":"7901 Butterfield Dr",
    "sg:city":"Elkridge",
    "sg:classifiers":[
        {
            "category":"Building & Trades",
            "subcategory":"Locksmith",
            "type":"Services"
        },
        {
            "category":"Manufacturing",
            "subcategory":"Soap",
            "type":"Manufacturing & Wholesale Goods"
        }
    ],
    "sg:phone":"+1 410 796 0183",
    "sg:postcode":"21075",
    "sg:province":"MD",
    "sg:tags":[
        "lock",
        "key",
        "locks-wholesale",
        "manufacturer"
    ],
    "wof:name":"All-State Lock & Key",
    "wof:placetype":"venue"
},
  "geometry": {"coordinates":[-76.785828,39.193988],"type":"Point"}
}