{
  "type": "Feature",
  "properties": {
    "addr:full":"600 Western Run Rd Cockeysville MD 21030",
    "addr:housenumber":"600",
    "addr:postcode":"21030",
    "addr:street":"Western Run Rd",
    "iso:country":"US",
    "sg:address":"600 Western Run Rd",
    "sg:city":"Cockeysville",
    "sg:classifiers":[
        {
            "category":"Personal",
            "subcategory":"Massage",
            "type":"Services"
        }
    ],
    "sg:phone":"+1 410 771 1249",
    "sg:postcode":"21030",
    "sg:province":"MD",
    "wof:name":"Dorothy Ryan",
    "wof:placetype":"venue"
},
  "geometry": {"coordinates":[-76.668961,39.50536],"type":"Point"}
}