{
  "type": "Feature",
  "properties": {
    "iso:country":"US",
    "sg:address":"5900 Old Branch Ave",
    "sg:city":"Temple Hills",
    "sg:classifiers":[
        {
            "category":"Organizations",
            "subcategory":"Religious Organization",
            "type":"Services"
        }
    ],
    "sg:phone":"+1 301 899 5940",
    "sg:postcode":"20748",
    "sg:province":"MD",
    "sg:tags":[
        "church"
    ],
    "wof:name":"Evangel Assembly Of God",
    "wof:placetype":"venue"
},
  "geometry": {"coordinates":[-76.910466,38.807164],"type":"Point"}
}