{
  "type": "Feature",
  "properties": {
    "addr:full":"1132 Maces Ln Cambridge MD 21613",
    "addr:housenumber":"1132",
    "addr:postcode":"21613",
    "addr:street":"Maces Ln",
    "iso:country":"US",
    "sg:address":"1132 Maces Ln",
    "sg:city":"Cambridge",
    "sg:classifiers":[
        {
            "category":"Organizations",
            "subcategory":"Religious Organization",
            "type":"Services"
        }
    ],
    "sg:phone":"+1 410 228 2230",
    "sg:postcode":"21613",
    "sg:province":"MD",
    "wof:name":"Leon B Hall Sr",
    "wof:placetype":"venue"
},
  "geometry": {"coordinates":[-76.089771,38.558646],"type":"Point"}
}