{
  "type": "Feature",
  "properties": {
    "iso:country":"US",
    "sg:address":"306 Burnt Mills Ave",
    "sg:city":"Silver Spring",
    "sg:classifiers":[
        {
            "category":"Professional",
            "subcategory":"Accounting & Tax Preparation",
            "type":"Services"
        }
    ],
    "sg:phone":"+1 301 593 0749",
    "sg:postcode":"20901",
    "sg:province":"MD",
    "wof:name":"Leon Taksel",
    "wof:placetype":"venue"
},
  "geometry": {"coordinates":[-77.003519,39.037137],"type":"Point"}
}