{
  "type": "Feature",
  "properties": {
    "addr:full":"5440 Marinelli Rd Rockville MD 20852",
    "addr:housenumber":"5440",
    "addr:postcode":"20852",
    "addr:street":"Marinelli Rd",
    "iso:country":"US",
    "sg:address":"5440 Marinelli Rd",
    "sg:city":"Rockville",
    "sg:classifiers":[
        {
            "category":"Real Estate",
            "subcategory":"Real Estate Operator",
            "type":"Services"
        }
    ],
    "sg:phone":"+1 301 230 5811",
    "sg:postcode":"20852",
    "sg:province":"MD",
    "sg:tags":[
        "apartment"
    ],
    "wof:name":"Strathmore Court",
    "wof:placetype":"venue"
},
  "geometry": {"coordinates":[-77.108867,39.047452],"type":"Point"}
}