{
  "type": "Feature",
  "properties": {
    "iso:country":"US",
    "sg:address":"10400 Old Georgetown Rd",
    "sg:city":"Bethesda",
    "sg:classifiers":[
        {
            "category":"Food & Beverages",
            "subcategory":"Bakery",
            "type":"Retail Goods"
        }
    ],
    "sg:phone":"+1 301 530 8822",
    "sg:postcode":"20814",
    "sg:province":"MD",
    "sg:tags":[
        "baker"
    ],
    "wof:name":"Boulevard Cafe",
    "wof:placetype":"venue"
},
  "geometry": {"coordinates":[-77.12621300000001,39.026962],"type":"Point"}
}