{
  "type": "Feature",
  "properties": {
    "iso:country":"US",
    "sg:address":"3205 Poffenberger Rd",
    "sg:city":"Jefferson",
    "sg:classifiers":[
        {
            "category":"Manufacturing",
            "subcategory":"Pottery",
            "type":"Manufacturing & Wholesale Goods"
        }
    ],
    "sg:phone":"+1 301 371 9172",
    "sg:postcode":"21755",
    "sg:province":"MD",
    "sg:tags":[
        "product"
    ],
    "sg:website":"www.nutricyclesystems.com",
    "wof:name":"Nutricycle Systems LLC",
    "wof:placetype":"venue"
},
  "geometry": {"coordinates":[-77.562704,39.376773],"type":"Point"}
}