{
  "type": "Feature",
  "properties": {
    "iso:country":"US",
    "sg:address":"7402 York Rd",
    "sg:city":"Baltimore",
    "sg:classifiers":[
        {
            "category":"Manufacturing",
            "subcategory":"Electronics",
            "type":"Manufacturing & Wholesale Goods"
        }
    ],
    "sg:phone":"+1 410 821 4000",
    "sg:postcode":"21204",
    "sg:province":"MD",
    "sg:tags":[
        "burglar",
        "alarm",
        "monitoring",
        "system"
    ],
    "wof:name":"Belmar Security",
    "wof:placetype":"venue"
},
  "geometry": {"coordinates":[-76.60686200000001,39.384765],"type":"Point"}
}