{
  "type": "Feature",
  "properties": {
    "iso:country":"US",
    "sg:address":"1800 Greenplace Ter",
    "sg:city":"Rockville",
    "sg:classifiers":[
        {
            "category":"Education",
            "subcategory":"School",
            "type":"Public Place"
        }
    ],
    "sg:phone":"+1 301 279 4984",
    "sg:postcode":"20850",
    "sg:province":"MD",
    "wof:name":"Fallsmead Elementary School",
    "wof:placetype":"venue"
},
  "geometry": {"coordinates":[-77.177436,39.078022],"type":"Point"}
}