{
  "type": "Feature",
  "properties": {
    "iso:country":"US",
    "sg:address":"9546 Belair Rd",
    "sg:city":"Nottingham",
    "sg:classifiers":[
        {
            "category":"Insurance",
            "subcategory":"Insurance Agent",
            "type":"Services"
        },
        {
            "category":"Insurance",
            "subcategory":"Hazard Insurance",
            "type":"Services"
        },
        {
            "category":"Insurance",
            "subcategory":"Title Insurance",
            "type":"Services"
        },
        {
            "category":"Insurance",
            "subcategory":"Life Insurance",
            "type":"Services"
        }
    ],
    "sg:phone":"+1 410 256 5500",
    "sg:postcode":"21236",
    "sg:province":"MD",
    "sg:tags":[
        "business",
        "auto",
        "commercial",
        "homeowner",
        "motorcycle",
        "renter"
    ],
    "wof:name":"Allstate Insurance Company - Donna Magsamen",
    "wof:placetype":"venue"
},
  "geometry": {"coordinates":[-76.46629900000001,39.410702],"type":"Point"}
}