{
  "type": "Feature",
  "properties": {
    "addr:full":"14 Marquis Dr Gaithersburg MD 20878",
    "addr:housenumber":"14",
    "addr:postcode":"20878",
    "addr:street":"Marquis Dr",
    "iso:country":"US",
    "sg:address":"14 Marquis Dr",
    "sg:city":"Gaithersburg",
    "sg:classifiers":[
        {
            "category":"Professional",
            "subcategory":"Business Services",
            "type":"Services"
        }
    ],
    "sg:phone":"+1 301 977 3169",
    "sg:postcode":"20878",
    "sg:province":"MD",
    "sg:tags":[
        "consultant",
        "proposal",
        "mapping"
    ],
    "wof:name":"Frey Wolfdieter Eric",
    "wof:placetype":"venue"
},
  "geometry": {"coordinates":[-77.23943800000001,39.134356],"type":"Point"}
}