{
  "type": "Feature",
  "properties": {
    "iso:country":"US",
    "sg:address":"5812 Clarksville Sq Dr",
    "sg:city":"Clarksville",
    "sg:classifiers":[
        {
            "category":"Retail",
            "subcategory":"Car Wash",
            "type":"Services"
        }
    ],
    "sg:phone":"+1 410 531 1457",
    "sg:postcode":"21029",
    "sg:province":"MD",
    "wof:name":"Clarksville Car Wash Llc",
    "wof:placetype":"venue"
},
  "geometry": {"coordinates":[-76.90679900000001,39.168499],"type":"Point"}
}