{
  "type": "Feature",
  "properties": {
    "iso:country":"US",
    "sg:address":"8306 Sunnyview Dr",
    "sg:city":"Millersville",
    "sg:classifiers":[
        {
            "category":"Building & Trades",
            "subcategory":"Electrical",
            "type":"Services"
        }
    ],
    "sg:phone":"+1 410 987 4324",
    "sg:postcode":"21108",
    "sg:province":"MD",
    "sg:tags":[
        "electrical",
        "contractor"
    ],
    "wof:name":"Konkus Marine Electronics",
    "wof:placetype":"venue"
},
  "geometry": {"coordinates":[-76.61432600000001,39.112181],"type":"Point"}
}