{
  "type": "Feature",
  "properties": {
    "iso:country":"US",
    "sg:address":"600 Sungold Rd",
    "sg:city":"Reisterstown",
    "sg:classifiers":[
        {
            "category":"Building & Trades",
            "subcategory":"Electrical",
            "type":"Services"
        }
    ],
    "sg:phone":"+1 410 833 7151",
    "sg:postcode":"21136",
    "sg:province":"MD",
    "sg:tags":[
        "industrial",
        "electrician",
        "contractors-commercial",
        "electric"
    ],
    "wof:name":"Benton Electric Co Inc",
    "wof:placetype":"venue"
},
  "geometry": {"coordinates":[-76.83168000000001,39.433472],"type":"Point"}
}