{
  "type": "Feature",
  "properties": {
    "iso:country":"US",
    "sg:address":"9122 Bridgewater St",
    "sg:city":"College Park",
    "sg:classifiers":[
        {
            "category":"Retail",
            "subcategory":"Repair Shop",
            "type":"Services"
        }
    ],
    "sg:phone":"+1 301 935 6918",
    "sg:postcode":"20740",
    "sg:province":"MD",
    "wof:name":"F T Strocchia",
    "wof:placetype":"venue"
},
  "geometry": {"coordinates":[-76.949267,39.004386],"type":"Point"}
}