{
  "type": "Feature",
  "properties": {
    "iso:country":"US",
    "sg:address":"2016 Quay Village Ct",
    "sg:city":"Annapolis",
    "sg:classifiers":[
        {
            "category":"Insurance",
            "subcategory":"Insurance Agent",
            "type":"Services"
        }
    ],
    "sg:phone":"+1 410 267 0015",
    "sg:postcode":"21403",
    "sg:province":"MD",
    "wof:name":"National Assn Of Self Employed",
    "wof:placetype":"venue"
},
  "geometry": {"coordinates":[-76.476038,38.961102],"type":"Point"}
}