{
  "type": "Feature",
  "properties": {
    "iso:country":"US",
    "sg:address":"200 E Lexington St",
    "sg:city":"Baltimore",
    "sg:classifiers":[
        {
            "category":"Professional",
            "subcategory":"Lawyer & Legal Services",
            "type":"Services"
        }
    ],
    "sg:phone":"+1 410 837 6686",
    "sg:postcode":"21202",
    "sg:province":"MD",
    "wof:name":"Sureff J Seymour",
    "wof:placetype":"venue"
},
  "geometry": {"coordinates":[-76.61218100000001,39.291373],"type":"Point"}
}