{
  "type": "Feature",
  "properties": {
    "addr:full":"640 Legion Rd Ste 3 Denton MD 21629",
    "addr:housenumber":"640",
    "addr:postcode":"21629",
    "addr:street":"Legion Rd Ste 3",
    "iso:country":"US",
    "sg:address":"640 Legion Rd Ste 3",
    "sg:city":"Denton",
    "sg:classifiers":[
        {
            "category":"Home & Garden",
            "subcategory":"Garden Supply",
            "type":"Retail Goods"
        }
    ],
    "sg:phone":"+1 410 479 1202",
    "sg:postcode":"21629",
    "sg:province":"MD",
    "sg:tags":[
        "soil",
        "conservation"
    ],
    "wof:name":"Natural Resources Conservation Service",
    "wof:placetype":"venue"
},
  "geometry": {"coordinates":[-75.821308,38.875993],"type":"Point"}
}