{
  "type": "Feature",
  "properties": {
    "iso:country":"US",
    "sg:address":"315 N Charles St",
    "sg:city":"Baltimore",
    "sg:classifiers":[
        {
            "category":"Professional",
            "subcategory":"Lawyer & Legal Services",
            "type":"Services"
        }
    ],
    "sg:phone":"+1 410 752 1169",
    "sg:postcode":"21201",
    "sg:province":"MD",
    "sg:tags":[
        "attorney"
    ],
    "wof:name":"Hecht & Chapper",
    "wof:placetype":"venue"
},
  "geometry": {"coordinates":[-76.615196,39.292999],"type":"Point"}
}