{
  "type": "Feature",
  "properties": {
    "iso:country":"US",
    "sg:address":"2657G Annapolis Rd # 476",
    "sg:city":"Hanover",
    "sg:classifiers":[
        {
            "category":"Real Estate",
            "subcategory":"Real Estate Services",
            "type":"Services"
        },
        {
            "category":"Real Estate",
            "subcategory":"Real Estate Agent",
            "type":"Services"
        }
    ],
    "sg:phone":"+1 410 672 4225",
    "sg:postcode":"21076",
    "sg:province":"MD",
    "sg:tags":[
        "management"
    ],
    "wof:name":"Just Accurate Acquisition Management",
    "wof:placetype":"venue"
},
  "geometry": {"coordinates":[-76.741495,39.132394],"type":"Point"}
}