{
  "type": "Feature",
  "properties": {
    "iso:country":"US",
    "sg:address":"201 W Preston St 417C",
    "sg:city":"Baltimore",
    "sg:classifiers":[
        {
            "category":"Organizations",
            "subcategory":"Membership Organization",
            "type":"Services"
        }
    ],
    "sg:phone":"+1 877 770 4801",
    "sg:postcode":"21201",
    "sg:province":"MD",
    "sg:tags":[
        "military",
        "veteran"
    ],
    "wof:name":"Marylnds Cmmitment To Veterans",
    "wof:placetype":"venue"
},
  "geometry": {"coordinates":[-76.62056,39.303291],"type":"Point"}
}