{
  "type": "Feature",
  "properties": {
    "iso:country":"US",
    "sg:address":"802 Champions Ct",
    "sg:city":"Reisterstown",
    "sg:classifiers":[
        {
            "category":"Professional",
            "subcategory":"Business Services",
            "type":"Services"
        }
    ],
    "sg:phone":"+1 410 833 2868",
    "sg:postcode":"21136",
    "sg:province":"MD",
    "sg:tags":[
        "holding"
    ],
    "wof:name":"Brijo Holdings",
    "wof:placetype":"venue"
},
  "geometry": {"coordinates":[-76.798332,39.4673],"type":"Point"}
}