{
  "type": "Feature",
  "properties": {
    "addr:full":"7009 Sulky Ln Rockville MD 20852",
    "addr:housenumber":"7009",
    "addr:postcode":"20852",
    "addr:street":"Sulky Ln",
    "iso:country":"US",
    "sg:address":"7009 Sulky Ln",
    "sg:city":"Rockville",
    "sg:classifiers":[
        {
            "category":"Professional",
            "subcategory":"Lawyer & Legal Services",
            "type":"Services"
        }
    ],
    "sg:phone":"+1 301 231 0013",
    "sg:postcode":"20852",
    "sg:province":"MD",
    "sg:tags":[
        "patent",
        "agent"
    ],
    "sg:website":"www.biotechpatent.net",
    "wof:name":"BIOTECHPATENT.NET",
    "wof:placetype":"venue"
},
  "geometry": {"coordinates":[-77.14545200000001,39.052622],"type":"Point"}
}