{
  "type": "Feature",
  "properties": {
    "iso:country":"US",
    "sg:address":"516 Grays Creek Rd",
    "sg:city":"Pasadena",
    "sg:classifiers":[
        {
            "category":"Professional",
            "subcategory":"Business Services",
            "type":"Services"
        }
    ],
    "sg:phone":"+1 410 255 5411",
    "sg:postcode":"21122",
    "sg:province":"MD",
    "sg:tags":[
        "management"
    ],
    "sg:website":"http://www.mergebds.com",
    "wof:name":"Merge Business Development Systems",
    "wof:placetype":"venue"
},
  "geometry": {"coordinates":[-76.465512,39.092284],"type":"Point"}
}