{
  "type": "Feature",
  "properties": {
    "addr:full":"302 Woodland Dr Oakland MD 21550",
    "addr:housenumber":"302",
    "addr:postcode":"21550",
    "addr:street":"Woodland Dr",
    "iso:country":"US",
    "sg:address":"302 Woodland Dr",
    "sg:city":"Oakland",
    "sg:classifiers":[
        {
            "category":"Retail",
            "subcategory":"Repair Shop",
            "type":"Services"
        }
    ],
    "sg:phone":"+1 301 334 4776",
    "sg:postcode":"21550",
    "sg:province":"MD",
    "wof:name":"Tech Cleaning Systems",
    "wof:placetype":"venue"
},
  "geometry": {"coordinates":[-79.414857,39.41788],"type":"Point"}
}