{
  "type": "Feature",
  "properties": {
    "addr:full":"402 Englar Rd Westminster MD 21157",
    "addr:housenumber":"402",
    "addr:postcode":"21157",
    "addr:street":"Englar Rd",
    "iso:country":"US",
    "sg:address":"402 Englar Rd",
    "sg:city":"Westminster",
    "sg:classifiers":[
        {
            "category":"Shopping",
            "subcategory":"Stationery & Office Supplies",
            "type":"Retail Goods"
        }
    ],
    "sg:phone":"+1 410 386 0070",
    "sg:postcode":"21157",
    "sg:province":"MD",
    "wof:name":"Office Depot",
    "wof:placetype":"venue"
},
  "geometry": {"coordinates":[-76.98078099999999,39.585082],"type":"Point"}
}