{
  "type": "Feature",
  "properties": {
    "iso:country":"US",
    "sg:address":"9500 Perry Hall Blvd # 303",
    "sg:city":"Nottingham",
    "sg:classifiers":[
        {
            "category":"Structure",
            "subcategory":"Warehouse",
            "type":"Public Place"
        }
    ],
    "sg:phone":"+1 443 204 4278",
    "sg:postcode":"21236",
    "sg:province":"MD",
    "sg:tags":[
        "warehouses-merchandise",
        "warehouses-public-commercial"
    ],
    "wof:name":"Master Construction Company",
    "wof:placetype":"venue"
},
  "geometry": {"coordinates":[-76.46244799999999,39.407799],"type":"Point"}
}