{
  "type": "Feature",
  "properties": {
    "iso:country":"US",
    "sg:address":"3546 Gentry Ridge Ct",
    "sg:city":"Silver Spring",
    "sg:classifiers":[
        {
            "category":"Professional",
            "subcategory":"Lawyer & Legal Services",
            "type":"Services"
        }
    ],
    "sg:phone":"+1 301 890 6990",
    "sg:postcode":"20904",
    "sg:province":"MD",
    "sg:tags":[
        "attorney"
    ],
    "wof:name":"Banks Theodore R III",
    "wof:placetype":"venue"
},
  "geometry": {"coordinates":[-76.939302,39.072405],"type":"Point"}
}