{
  "type": "Feature",
  "properties": {
    "addr:full":"346 Carey Ave Salisbury MD 21804",
    "addr:housenumber":"346",
    "addr:postcode":"21804",
    "addr:street":"Carey Ave",
    "iso:country":"US",
    "sg:address":"346 Carey Ave",
    "sg:city":"Salisbury",
    "sg:classifiers":[
        {
            "category":"Building & Trades",
            "subcategory":"Construction",
            "type":"Services"
        }
    ],
    "sg:phone":"+1 410 860 5587",
    "sg:postcode":"21804",
    "sg:province":"MD",
    "sg:tags":[
        "contractor"
    ],
    "wof:name":"Dennis Sigai Jr",
    "wof:placetype":"venue"
},
  "geometry": {"coordinates":[-75.56558699999999,38.362787],"type":"Point"}
}