{
  "type": "Feature",
  "properties": {
    "addr:full":"104 1st Ave Baltimore MD 21227",
    "addr:housenumber":"104",
    "addr:postcode":"21227",
    "addr:street":"1St Ave",
    "iso:country":"US",
    "sg:address":"104 1st Ave",
    "sg:city":"Baltimore",
    "sg:classifiers":[
        {
            "category":"Building & Trades",
            "subcategory":"Construction",
            "type":"Services"
        }
    ],
    "sg:phone":"+1 410 242 0545",
    "sg:postcode":"21227",
    "sg:province":"MD",
    "sg:tags":[
        "carpentry",
        "contractor"
    ],
    "wof:name":"Morningstar Window Company",
    "wof:placetype":"venue"
},
  "geometry": {"coordinates":[-76.661022,39.244567],"type":"Point"}
}