{
  "type": "Feature",
  "properties": {
    "iso:country":"US",
    "sg:address":"10837 Sherwood Hill Rd",
    "sg:city":"Owings Mills",
    "sg:classifiers":[
        {
            "category":"Professional",
            "subcategory":"Computer Services",
            "type":"Services"
        }
    ],
    "sg:phone":"+1 410 902 0838",
    "sg:postcode":"21117",
    "sg:province":"MD",
    "sg:tags":[
        "website",
        "design"
    ],
    "wof:name":"Fluid Web Solutions",
    "wof:placetype":"venue"
},
  "geometry": {"coordinates":[-76.816472,39.409436],"type":"Point"}
}