{
  "type": "Feature",
  "properties": {
    "addr:full":"18040 Cottage Garden Dr Germantown MD 20874",
    "addr:housenumber":"18040",
    "addr:postcode":"20874",
    "addr:street":"Cottage Garden Dr",
    "iso:country":"US",
    "sg:address":"18040 Cottage Garden Dr",
    "sg:city":"Germantown",
    "sg:classifiers":[
        {
            "category":"Professional",
            "subcategory":"Business Services",
            "type":"Services"
        }
    ],
    "sg:phone":"+1 301 515 8425",
    "sg:postcode":"20874",
    "sg:province":"MD",
    "sg:tags":[
        "research"
    ],
    "wof:name":"Clayton Yang Shuoche",
    "wof:placetype":"venue"
},
  "geometry": {"coordinates":[-77.27515200000001,39.152074],"type":"Point"}
}