{
  "type": "Feature",
  "properties": {
    "addr:full":"708 Glen Allen Dr Baltimore MD 21229",
    "addr:housenumber":"708",
    "addr:postcode":"21229",
    "addr:street":"Glen Allen Dr",
    "iso:country":"US",
    "sg:address":"708 Glen Allen Dr",
    "sg:city":"Baltimore",
    "sg:classifiers":[
        {
            "category":"Organizations",
            "subcategory":"Religious Organization",
            "type":"Services"
        }
    ],
    "sg:phone":"+1 410 945 3566",
    "sg:postcode":"21229",
    "sg:province":"MD",
    "wof:name":"Smith Horace Rev & Michele",
    "wof:placetype":"venue"
},
  "geometry": {"coordinates":[-76.696899,39.296101],"type":"Point"}
}