{
  "type": "Feature",
  "properties": {
    "addr:full":"7629 Water Oak Point Rd Pasadena MD 21122",
    "addr:housenumber":"7629",
    "addr:postcode":"21122",
    "addr:street":"Water Oak Point Rd",
    "iso:country":"US",
    "sg:address":"7629 Water Oak Point Rd",
    "sg:city":"Pasadena",
    "sg:classifiers":[
        {
            "category":"Professional",
            "type":"Services"
        }
    ],
    "sg:phone":"+1 410 255 2630",
    "sg:postcode":"21122",
    "sg:province":"MD",
    "wof:name":"Mikes Mobile Marine Services",
    "wof:placetype":"venue"
},
  "geometry": {"coordinates":[-76.510414,39.149718],"type":"Point"}
}