{
  "type": "Feature",
  "properties": {
    "iso:country":"US",
    "sg:address":"6717 Laurel Dr",
    "sg:city":"Baltimore",
    "sg:classifiers":[
        {
            "category":"Building & Trades",
            "subcategory":"Cleaning & Sanitation",
            "type":"Services"
        }
    ],
    "sg:phone":"+1 410 484 0157",
    "sg:postcode":"21207",
    "sg:province":"MD",
    "sg:tags":[
        "janitorial"
    ],
    "wof:name":"Office Cleaning By Murray",
    "wof:placetype":"venue"
},
  "geometry": {"coordinates":[-76.718878,39.348419],"type":"Point"}
}