{
  "type": "Feature",
  "properties": {
    "addr:full":"21656 Great Mills Rd Lexington Park MD 20653",
    "addr:housenumber":"21656",
    "addr:postcode":"20653",
    "addr:street":"Great Mills Rd",
    "iso:country":"US",
    "sg:address":"21656 Great Mills Rd",
    "sg:city":"Lexington Park",
    "sg:classifiers":[
        {
            "category":"Restaurant",
            "type":"Food & Drink"
        }
    ],
    "sg:menulink":"http://www.allmenus.com/md/bay/163025-rallys/menu/",
    "sg:phone":"+1 301 866 1888",
    "sg:postcode":"20653",
    "sg:province":"MD",
    "sg:tags":[
        "sandwich",
        "dog",
        "burger",
        "hot",
        "wrap",
        "american"
    ],
    "wof:name":"Rally's",
    "wof:placetype":"venue"
},
  "geometry": {"coordinates":[-76.46162099999999,38.262128],"type":"Point"}
}