{
  "type": "Feature",
  "properties": {
    "addr:full":"2916 Rockdale Rd Freeland MD 21053",
    "addr:housenumber":"2916",
    "addr:postcode":"21053",
    "addr:street":"Rockdale Rd",
    "iso:country":"US",
    "sg:address":"2916 Rockdale Rd",
    "sg:city":"Freeland",
    "sg:phone":"+1 410 357 5518",
    "sg:postcode":"21053",
    "sg:province":"MD",
    "sg:tags":[
        "farm",
        "corn"
    ],
    "wof:name":"Jake Swam",
    "wof:placetype":"venue"
},
  "geometry": {"coordinates":[-76.74806100000001,39.696091],"type":"Point"}
}