{
  "type": "Feature",
  "properties": {
    "addr:full":"6124 Landover Rd Hyattsville MD 20785",
    "addr:housenumber":"6124",
    "addr:postcode":"20785",
    "addr:street":"Landover Rd",
    "iso:country":"US",
    "sg:address":"6124 Landover Rd",
    "sg:city":"Hyattsville",
    "sg:classifiers":[
        {
            "category":"Health Services",
            "subcategory":"Doctor",
            "type":"Services"
        }
    ],
    "sg:phone":"+1 301 322 4500",
    "sg:postcode":"20785",
    "sg:province":"MD",
    "sg:tags":[
        "medical"
    ],
    "wof:name":"Anne Zevallos MD",
    "wof:placetype":"venue"
},
  "geometry": {"coordinates":[-76.91667,38.935228],"type":"Point"}
}