{
  "type": "Feature",
  "properties": {
    "iso:country":"US",
    "sg:address":"8504 Adelphi Rd",
    "sg:city":"Hyattsville",
    "sg:classifiers":[
        {
            "category":"Retail",
            "subcategory":"Repair Shop",
            "type":"Services"
        }
    ],
    "sg:phone":"+1 301 879 8505",
    "sg:postcode":"20783",
    "sg:province":"MD",
    "sg:tags":[
        "air",
        "system",
        "conditioning"
    ],
    "wof:name":"Aire Fresch C-O",
    "wof:placetype":"venue"
},
  "geometry": {"coordinates":[-76.962076,38.997561],"type":"Point"}
}