{
  "type": "Feature",
  "properties": {
    "iso:country":"US",
    "sg:address":"6011 E Capitol St",
    "sg:city":"Capitol Heights",
    "sg:classifiers":[
        {
            "category":"Professional",
            "subcategory":"Business Services",
            "type":"Services"
        }
    ],
    "sg:phone":"+1 301 925 4865",
    "sg:postcode":"20743",
    "sg:province":"MD",
    "wof:name":"Mtr Enterprise Inc",
    "wof:placetype":"venue"
},
  "geometry": {"coordinates":[-76.908535,38.889119],"type":"Point"}
}