{
  "type": "Feature",
  "properties": {
    "iso:country":"US",
    "sg:address":"6830 Hospital Dr",
    "sg:city":"Baltimore",
    "sg:classifiers":[
        {
            "category":"Health Services",
            "subcategory":"Doctor",
            "type":"Services"
        }
    ],
    "sg:phone":"+1 410 238 0057",
    "sg:postcode":"21237",
    "sg:province":"MD",
    "sg:tags":[
        "physician",
        "surgeon"
    ],
    "wof:name":"David J Hoyt MD LLC",
    "wof:placetype":"venue"
},
  "geometry": {"coordinates":[-76.476151,39.347879],"type":"Point"}
}