{
  "type": "Feature",
  "properties": {
    "addr:full":"9143 Sunset Ridge Rd Randallstown MD 21133",
    "addr:housenumber":"9143",
    "addr:postcode":"21133",
    "addr:street":"Sunset Ridge Rd",
    "iso:country":"US",
    "sg:address":"9143 Sunset Ridge Rd",
    "sg:city":"Randallstown",
    "sg:classifiers":[
        {
            "category":"Communications",
            "subcategory":"Film & Video Production",
            "type":"Services"
        }
    ],
    "sg:phone":"+1 410 922 2949",
    "sg:postcode":"21133",
    "sg:province":"MD",
    "sg:tags":[
        "services-commercial"
    ],
    "wof:name":"Jb Video Product",
    "wof:placetype":"venue"
},
  "geometry": {"coordinates":[-76.79484100000001,39.381281],"type":"Point"}
}