{
  "type": "Feature",
  "properties": {
    "iso:country":"US",
    "sg:address":"809 Eton Rd",
    "sg:city":"Baltimore",
    "sg:classifiers":[
        {
            "category":"Health Services",
            "subcategory":"Health Practitioner",
            "type":"Services"
        }
    ],
    "sg:phone":"+1 410 321 9719",
    "sg:postcode":"21204",
    "sg:province":"MD",
    "wof:name":"Louise Dorrett",
    "wof:placetype":"venue"
},
  "geometry": {"coordinates":[-76.620592,39.404047],"type":"Point"}
}