{
  "type": "Feature",
  "properties": {
    "addr:full":"322 E Antietam St Hagerstown MD 21740",
    "addr:housenumber":"322",
    "addr:postcode":"21740",
    "addr:street":"E Antietam St",
    "iso:country":"US",
    "sg:address":"322 E Antietam St",
    "sg:city":"Hagerstown",
    "sg:classifiers":[
        {
            "category":"Professional",
            "subcategory":"Lawyer & Legal Services",
            "type":"Services"
        }
    ],
    "sg:phone":"+1 301 739 4558",
    "sg:postcode":"21740",
    "sg:province":"MD",
    "sg:tags":[
        "attorney"
    ],
    "wof:name":"Semmes Bowen & Semmes",
    "wof:placetype":"venue"
},
  "geometry": {"coordinates":[-77.715019,39.637816],"type":"Point"}
}