{
  "type": "Feature",
  "properties": {
    "addr:full":"9737 Mount Pisgah Rd Silver Spring MD 20903",
    "addr:housenumber":"9737",
    "addr:postcode":"20903",
    "addr:street":"Mount Pisgah Rd",
    "iso:country":"US",
    "sg:address":"9737 Mount Pisgah Rd",
    "sg:city":"Silver Spring",
    "sg:classifiers":[
        {
            "category":"Arts & Performance",
            "subcategory":"Theater",
            "type":"Entertainment"
        }
    ],
    "sg:phone":"+1 301 434 6009",
    "sg:postcode":"20903",
    "sg:province":"MD",
    "sg:tags":[
        "musician"
    ],
    "wof:name":"Billy B Productions",
    "wof:placetype":"venue"
},
  "geometry": {"coordinates":[-76.97630100000001,39.016335],"type":"Point"}
}