{
  "type": "Feature",
  "properties": {
    "iso:country":"US",
    "sg:address":"9737 Mount Pisgah Rd",
    "sg:city":"Silver Spring",
    "sg:classifiers":[
        {
            "category":"Arts & Performance",
            "subcategory":"Theater",
            "type":"Entertainment"
        }
    ],
    "sg:phone":"+1 301 434 6009",
    "sg:postcode":"20903",
    "sg:province":"MD",
    "sg:tags":[
        "musician"
    ],
    "wof:name":"Billy B Productions",
    "wof:placetype":"venue"
},
  "geometry": {"coordinates":[-76.976301,39.016335],"type":"Point"}
}