{
  "type": "Feature",
  "properties": {
    "iso:country":"US",
    "sg:address":"5902 Franklin Ave",
    "sg:city":"Gwynn Oak",
    "sg:classifiers":[
        {
            "category":"Personal",
            "subcategory":"Tattoo Parlor",
            "type":"Services"
        }
    ],
    "sg:phone":"+1 410 719 7177",
    "sg:postcode":"21207",
    "sg:province":"MD",
    "sg:tags":[
        "tattooing"
    ],
    "wof:name":"Tamikas Tattoos",
    "wof:placetype":"venue"
},
  "geometry": {"coordinates":[-76.72018199999999,39.301459],"type":"Point"}
}