{
  "type": "Feature",
  "properties": {
    "iso:country":"US",
    "sg:address":"217 N Warwick Ave",
    "sg:city":"Baltimore",
    "sg:classifiers":[
        {
            "category":"Social Services",
            "type":"Services"
        },
        {
            "category":"Professional",
            "subcategory":"Employment Agencies",
            "type":"Services"
        }
    ],
    "sg:phone":"+1 410 566 4022",
    "sg:postcode":"21223",
    "sg:province":"MD",
    "sg:tags":[
        "workers'",
        "placement",
        "volunteer"
    ],
    "wof:name":"Free State Regional Service Center Of N.A., Inc.",
    "wof:placetype":"venue"
},
  "geometry": {"coordinates":[-76.655726,39.290286],"type":"Point"}
}