{
  "type": "Feature",
  "properties": {
    "iso:country":"US",
    "sg:address":"5110 Sinclair Ln",
    "sg:city":"Baltimore",
    "sg:classifiers":[
        {
            "category":"Food & Beverages",
            "subcategory":"Liquor & Beverages",
            "type":"Retail Goods"
        }
    ],
    "sg:phone":"+1 410 325 9200",
    "sg:postcode":"21206",
    "sg:province":"MD",
    "sg:tags":[
        "beer",
        "spirit",
        "wine"
    ],
    "wof:name":"Parkside Liquors",
    "wof:placetype":"venue"
},
  "geometry": {"coordinates":[-76.544601,39.322601],"type":"Point"}
}