{
  "type": "Feature",
  "properties": {
    "iso:country":"US",
    "sg:address":"4402 Eldone Rd",
    "sg:city":"Baltimore",
    "sg:classifiers":[
        {
            "category":"Building & Trades",
            "subcategory":"Construction",
            "type":"Services"
        }
    ],
    "sg:phone":"+1 410 644 6165",
    "sg:postcode":"21229",
    "sg:province":"MD",
    "sg:tags":[
        "home",
        "improvement"
    ],
    "wof:name":"C G & Z Painting Contractors",
    "wof:placetype":"venue"
},
  "geometry": {"coordinates":[-76.691164,39.277171],"type":"Point"}
}