{
  "type": "Feature",
  "properties": {
    "addr:full":"13218 Ingleside Dr Beltsville MD 20705",
    "addr:housenumber":"13218",
    "addr:postcode":"20705",
    "addr:street":"Ingleside Dr",
    "iso:country":"US",
    "sg:address":"13218 Ingleside Dr",
    "sg:city":"Beltsville",
    "sg:classifiers":[
        {
            "category":"Professional",
            "subcategory":"Computer Services",
            "type":"Services"
        }
    ],
    "sg:phone":"+1 301 572 4511",
    "sg:postcode":"20705",
    "sg:province":"MD",
    "sg:tags":[
        "information",
        "retrieval"
    ],
    "wof:name":"Lindell B Cole",
    "wof:placetype":"venue"
},
  "geometry": {"coordinates":[-76.938227,39.06108],"type":"Point"}
}