{
  "type": "Feature",
  "properties": {
    "iso:country":"US",
    "sg:address":"6219 Lone Oak Dr",
    "sg:city":"Bethesda",
    "sg:classifiers":[
        {
            "category":"Shopping",
            "subcategory":"Computers & Home Electronics",
            "type":"Retail Goods"
        }
    ],
    "sg:phone":"+1 301 530 9711",
    "sg:postcode":"20817",
    "sg:province":"MD",
    "sg:tags":[
        "software"
    ],
    "wof:name":"Sorgen Associates",
    "wof:placetype":"venue"
},
  "geometry": {"coordinates":[-77.126239,39.020266],"type":"Point"}
}