{
  "type": "Feature",
  "properties": {
    "addr:full":"9200 Rumsey Rd Ste 200 Columbia MD 21045",
    "addr:housenumber":"9200",
    "addr:postcode":"21045",
    "addr:street":"Rumsey Rd Ste 200",
    "iso:country":"US",
    "sg:address":"9200 Rumsey Rd Ste 200",
    "sg:city":"Columbia",
    "sg:classifiers":[
        {
            "category":"Shopping",
            "subcategory":"Stationery & Office Supplies",
            "type":"Retail Goods"
        }
    ],
    "sg:phone":"+1 410 995 0808",
    "sg:postcode":"21045",
    "sg:province":"MD",
    "sg:tags":[
        "equipment"
    ],
    "wof:name":"Modular Tech Inc",
    "wof:placetype":"venue"
},
  "geometry": {"coordinates":[-76.82105799999999,39.23347],"type":"Point"}
}