{
  "type": "Feature",
  "properties": {
    "addr:full":"80 Calvert St Annapolis MD 21401",
    "addr:housenumber":"80",
    "addr:postcode":"21401",
    "addr:street":"Calvert St",
    "iso:country":"US",
    "sg:address":"80 Calvert St",
    "sg:city":"Annapolis",
    "sg:classifiers":[
        {
            "category":"Government",
            "subcategory":"Office",
            "type":"Public Place"
        }
    ],
    "sg:phone":"+1 410 260 7314",
    "sg:postcode":"21401",
    "sg:province":"MD",
    "sg:tags":[
        "state",
        "taxation"
    ],
    "wof:name":"Alcohol & Tobacco Tax Div",
    "wof:placetype":"venue"
},
  "geometry": {"coordinates":[-76.495248,38.979783],"type":"Point"}
}