{
  "type": "Feature",
  "properties": {
    "addr:full":"6111 Bellinham Ct Baltimore MD 21210",
    "addr:housenumber":"6111",
    "addr:postcode":"21210",
    "addr:street":"Bellinham Ct",
    "iso:country":"US",
    "sg:address":"6111 Bellinham Ct",
    "sg:city":"Baltimore",
    "sg:classifiers":[
        {
            "category":"Banks & Credit Unions",
            "subcategory":"Investment Brokerage",
            "type":"Services"
        }
    ],
    "sg:phone":"+1 410 377 6112",
    "sg:postcode":"21210",
    "sg:province":"MD",
    "sg:tags":[
        "advisory",
        "financial",
        "counseling"
    ],
    "wof:name":"Nickerson Associates",
    "wof:placetype":"venue"
},
  "geometry": {"coordinates":[-76.632561,39.374888],"type":"Point"}
}