{
  "type": "Feature",
  "properties": {
    "addr:full":"3504 Jefferson St Hyattsville MD 20782",
    "addr:housenumber":"3504",
    "addr:postcode":"20782",
    "addr:street":"Jefferson St",
    "iso:country":"US",
    "sg:address":"3504 Jefferson St",
    "sg:city":"Hyattsville",
    "sg:classifiers":[
        {
            "category":"Shopping",
            "type":"Retail Goods"
        }
    ],
    "sg:phone":"+1 301 864 3948",
    "sg:postcode":"20782",
    "sg:province":"MD",
    "sg:tags":[
        "merchandise"
    ],
    "wof:name":"The Pottery Shoppe",
    "wof:placetype":"venue"
},
  "geometry": {"coordinates":[-76.959549,38.955577],"type":"Point"}
}