{
  "type": "Feature",
  "properties": {
    "iso:country":"US",
    "sg:address":"1721 Gwynns Falls Pkwy",
    "sg:city":"Baltimore",
    "sg:classifiers":[
        {
            "category":"Building & Trades",
            "subcategory":"Cleaning & Sanitation",
            "type":"Services"
        }
    ],
    "sg:phone":"+1 410 462 2060",
    "sg:postcode":"21217",
    "sg:province":"MD",
    "sg:tags":[
        "janitor"
    ],
    "wof:name":"Fresh & Clean LLC",
    "wof:placetype":"venue"
},
  "geometry": {"coordinates":[-76.650347,39.316734],"type":"Point"}
}