{
  "type": "Feature",
  "properties": {
    "iso:country":"US",
    "sg:address":"9800 Marting Luther King",
    "sg:city":"Hyattsville",
    "sg:classifiers":[
        {
            "category":"Personal",
            "type":"Services"
        }
    ],
    "sg:phone":"+1 301 577 1400",
    "sg:postcode":"20785",
    "sg:province":"MD",
    "sg:tags":[
        "mover"
    ],
    "wof:name":"Office Movers Inc A Kane Company",
    "wof:placetype":"venue"
},
  "geometry": {"coordinates":[-76.88009599999999,38.9128],"type":"Point"}
}