{
  "type": "Feature",
  "properties": {
    "iso:country":"US",
    "sg:address":"5009 Frankford Ave",
    "sg:city":"Baltimore",
    "sg:classifiers":[
        {
            "category":"Health Services",
            "subcategory":"Nursing And Care Facility",
            "type":"Services"
        }
    ],
    "sg:phone":"+1 410 325 4000",
    "sg:postcode":"21206",
    "sg:province":"MD",
    "sg:tags":[
        "home",
        "convalescent"
    ],
    "wof:name":"Lorien Frankford Nursing Ctr",
    "wof:placetype":"venue"
},
  "geometry": {"coordinates":[-76.541674,39.328909],"type":"Point"}
}