{
  "type": "Feature",
  "properties": {
    "iso:country":"US",
    "sg:address":"9218 Frederick Rd",
    "sg:city":"Ellicott City",
    "sg:classifiers":[
        {
            "category":"Health Services",
            "subcategory":"Health Practitioner",
            "type":"Services"
        }
    ],
    "sg:phone":"+1 410 461 8269",
    "sg:postcode":"21042",
    "sg:province":"MD",
    "sg:tags":[
        "acupuncture"
    ],
    "wof:name":"Jang's Acupunture",
    "wof:placetype":"venue"
},
  "geometry": {"coordinates":[-76.832331,39.272988],"type":"Point"}
}