{
  "type": "Feature",
  "properties": {
    "iso:country":"US",
    "sg:address":"5 Woodsyde Pl",
    "sg:city":"Owings Mills",
    "sg:classifiers":[
        {
            "category":"Shopping",
            "type":"Retail Goods"
        }
    ],
    "sg:phone":"+1 410 581 5035",
    "sg:postcode":"21117",
    "sg:province":"MD",
    "sg:tags":[
        "plant",
        "flower",
        "tree",
        "artificial"
    ],
    "wof:name":"Petals Of Perril",
    "wof:placetype":"venue"
},
  "geometry": {"coordinates":[-76.745046,39.453097],"type":"Point"}
}