{
  "type": "Feature",
  "properties": {
    "iso:country":"US",
    "sg:address":"4601 Forbes Blvd Ste 200",
    "sg:city":"Lanham",
    "sg:classifiers":[
        {
            "category":"Professional",
            "subcategory":"Computer Services",
            "type":"Services"
        }
    ],
    "sg:phone":"+1 301 577 3999",
    "sg:postcode":"20706",
    "sg:province":"MD",
    "sg:tags":[
        "information",
        "recovery",
        "processing",
        "system",
        "equipment",
        "data",
        "retrieval"
    ],
    "wof:name":"Nucore Visions Inc",
    "wof:placetype":"venue"
},
  "geometry": {"coordinates":[-76.83467899999999,38.952419],"type":"Point"}
}