{
  "type": "Feature",
  "properties": {
    "iso:country":"US",
    "sg:address":"28767 Ocean Gtwy",
    "sg:city":"Salisbury",
    "sg:classifiers":[
        {
            "category":"Professional",
            "subcategory":"Accounting & Tax Preparation",
            "type":"Services"
        },
        {
            "category":"Professional",
            "subcategory":"Business Services",
            "type":"Services"
        }
    ],
    "sg:phone":"+1 410 548 9666",
    "sg:postcode":"21801",
    "sg:province":"MD",
    "sg:tags":[
        "bookkeeping",
        "organizing",
        "services-household",
        "billing"
    ],
    "sg:website":"http://www.synapse-management.com",
    "wof:name":"Synapse Management Services",
    "wof:placetype":"venue"
},
  "geometry": {"coordinates":[-75.63126800000001,38.402506],"type":"Point"}
}