{
  "type": "Feature",
  "properties": {
    "iso:country":"US",
    "sg:address":"114 Baughmans Ln",
    "sg:city":"Frederick",
    "sg:classifiers":[
        {
            "category":"Retail",
            "subcategory":"Auto Rental",
            "type":"Services"
        },
        {
            "category":"Building & Trades",
            "subcategory":"Equipment Rental",
            "type":"Services"
        },
        {
            "category":"Retail",
            "subcategory":"Storage",
            "type":"Services"
        }
    ],
    "sg:phone":"+1 301 668 9955",
    "sg:postcode":"21702",
    "sg:province":"MD",
    "sg:tags":[
        "renting",
        "moving-self",
        "leasing",
        "car",
        "truck",
        "store",
        "yard",
        "trailer"
    ],
    "sg:website":"http://www.nextcar.com",
    "wof:name":"Nextcar Rental Leasing Sales",
    "wof:placetype":"venue"
},
  "geometry": {"coordinates":[-77.43750799999999,39.41925],"type":"Point"}
}