{
  "type": "Feature",
  "properties": {
    "iso:country":"US",
    "sg:address":"5742 Falls Rd",
    "sg:city":"Baltimore",
    "sg:classifiers":[
        {
            "category":"Retail",
            "subcategory":"Auto Repair",
            "type":"Services"
        }
    ],
    "sg:phone":"+1 410 532 8704",
    "sg:postcode":"21209",
    "sg:province":"MD",
    "sg:tags":[
        "repairing",
        "automobile"
    ],
    "wof:name":"Bob's Mt Washington Auto Service",
    "wof:placetype":"venue"
},
  "geometry": {"coordinates":[-76.647598,39.366402],"type":"Point"}
}