{
  "type": "Feature",
  "properties": {
    "iso:country":"US",
    "sg:address":"4 Howard St",
    "sg:city":"Aberdeen",
    "sg:classifiers":[
        {
            "category":"Professional",
            "subcategory":"Computer Services",
            "type":"Services"
        }
    ],
    "sg:phone":"+1 410 273 9414",
    "sg:postcode":"21001",
    "sg:province":"MD",
    "sg:tags":[
        "consultant",
        "designer"
    ],
    "sg:website":"www.tris.com",
    "wof:name":"Tri-S Inc",
    "wof:placetype":"venue"
},
  "geometry": {"coordinates":[-76.16410399999999,39.510014],"type":"Point"}
}