{
  "type": "Feature",
  "properties": {
    "iso:country":"US",
    "sg:address":"2926 Lakebrook Cir",
    "sg:city":"Halethorpe",
    "sg:classifiers":[
        {
            "category":"Real Estate",
            "subcategory":"Real Estate Operator",
            "type":"Services"
        }
    ],
    "sg:phone":"+1 410 242 4242",
    "sg:postcode":"21227",
    "sg:province":"MD",
    "sg:tags":[
        "apartment"
    ],
    "wof:name":"Circle Terrace Apartments",
    "wof:placetype":"venue"
},
  "geometry": {"coordinates":[-76.65679900000001,39.240898],"type":"Point"}
}