{
  "type": "Feature",
  "properties": {
    "addr:full":"401 Howard Ave Arnold MD 21012",
    "addr:housenumber":"401",
    "addr:postcode":"21012",
    "addr:street":"Howard Ave",
    "iso:country":"US",
    "sg:address":"401 Howard Ave",
    "sg:city":"Arnold",
    "sg:classifiers":[
        {
            "category":"Home & Garden",
            "subcategory":"Home Furnishings",
            "type":"Retail Goods"
        }
    ],
    "sg:phone":"+1 410 544 0074",
    "sg:postcode":"21012",
    "sg:province":"MD",
    "sg:tags":[
        "installation",
        "drapery"
    ],
    "wof:name":"Chesapeake Shutter & Awning",
    "wof:placetype":"venue"
},
  "geometry": {"coordinates":[-76.50749999999999,39.061629],"type":"Point"}
}