{
  "type": "Feature",
  "properties": {
    "iso:country":"US",
    "sg:address":"8370 Baltimore Annapolis Blvd",
    "sg:city":"Pasadena",
    "sg:classifiers":[
        {
            "category":"Personal",
            "subcategory":"Beauty Salon",
            "type":"Services"
        }
    ],
    "sg:phone":"+1 410 975 9222",
    "sg:postcode":"21122",
    "sg:province":"MD",
    "sg:tags":[
        "manicuring"
    ],
    "wof:name":"Get Nailed Salon Inc",
    "wof:placetype":"venue"
},
  "geometry": {"coordinates":[-76.55393,39.107786],"type":"Point"}
}