{
  "type": "Feature",
  "properties": {
    "iso:country":"US",
    "sg:address":"1507 Ritchie Hwy",
    "sg:city":"Arnold",
    "sg:classifiers":[
        {
            "category":"Health Services",
            "subcategory":"Health Practitioner",
            "type":"Services"
        },
        {
            "category":"Health Services",
            "subcategory":"Chiropractor",
            "type":"Services"
        }
    ],
    "sg:phone":"+1 410 349 0000",
    "sg:postcode":"21012",
    "sg:province":"MD",
    "sg:tags":[
        "sport",
        "chiropractic",
        "treatment",
        "medicine",
        "injury"
    ],
    "sg:website":"http://www.arnoldchiropracticcenter.com",
    "wof:name":"Arnold Chiropractic Center",
    "wof:placetype":"venue"
},
  "geometry": {"coordinates":[-76.502296,39.027215],"type":"Point"}
}