{
  "type": "Feature",
  "properties": {
    "iso:country":"US",
    "sg:address":"204 Bloomsbury Ave",
    "sg:city":"Catonsville",
    "sg:classifiers":[
        {
            "category":"Retail",
            "subcategory":"Pet Boarding",
            "type":"Services"
        }
    ],
    "sg:phone":"+1 410 719 0367",
    "sg:postcode":"21228",
    "sg:province":"MD",
    "sg:tags":[
        "boarding/pet",
        "sitting"
    ],
    "wof:name":"Critter Sitter",
    "wof:placetype":"venue"
},
  "geometry": {"coordinates":[-76.729748,39.266367],"type":"Point"}
}