{
  "type": "Feature",
  "properties": {
    "iso:country":"US",
    "sg:address":"1029 Ingleside Ave",
    "sg:city":"Catonsville",
    "sg:classifiers":[
        {
            "category":"Real Estate",
            "subcategory":"Real Estate Agent",
            "type":"Services"
        }
    ],
    "sg:phone":"+1 410 719 0500",
    "sg:postcode":"21228",
    "sg:province":"MD",
    "wof:name":"Merritt & Assoc Inc",
    "wof:placetype":"venue"
},
  "geometry": {"coordinates":[-76.73159099999999,39.292683],"type":"Point"}
}