{
  "type": "Feature",
  "properties": {
    "addr:full":"309 3rd St Annapolis MD 21403",
    "addr:housenumber":"309",
    "addr:postcode":"21403",
    "addr:street":"3Rd St",
    "iso:country":"US",
    "sg:address":"309 3rd St",
    "sg:city":"Annapolis",
    "sg:classifiers":[
        {
            "category":"Autos & Motor Vehicles",
            "subcategory":"Boat Sales",
            "type":"Retail Goods"
        }
    ],
    "sg:phone":"+1 410 268 0021",
    "sg:postcode":"21403",
    "sg:province":"MD",
    "sg:tags":[
        "yacht",
        "broker"
    ],
    "wof:name":"Authentic Yacht Brokerage",
    "wof:placetype":"venue"
},
  "geometry": {"coordinates":[-76.48147299999999,38.972307],"type":"Point"}
}