{
  "type": "Feature",
  "properties": {
    "addr:full":"109 Main St Myersville MD 21773",
    "addr:housenumber":"109",
    "addr:postcode":"21773",
    "addr:street":"Main St",
    "iso:country":"US",
    "sg:address":"109 Main St",
    "sg:city":"Myersville",
    "sg:classifiers":[
        {
            "category":"Home & Garden",
            "subcategory":"Furniture",
            "type":"Retail Goods"
        }
    ],
    "sg:phone":"+1 301 416 2222",
    "sg:postcode":"21773",
    "sg:province":"MD",
    "wof:name":"Bast Of Boonsboro",
    "wof:placetype":"venue"
},
  "geometry": {"coordinates":[-77.56661800000001,39.504241],"type":"Point"}
}