{
  "type": "Feature",
  "properties": {
    "addr:full":"2539 Veterans Dr Federalsburg MD 21632",
    "addr:housenumber":"2539",
    "addr:postcode":"21632",
    "addr:street":"Veterans Dr",
    "iso:country":"US",
    "sg:address":"2539 Veterans Dr",
    "sg:city":"Federalsburg",
    "sg:classifiers":[
        {
            "category":"Wholesale",
            "subcategory":"Construction Materials",
            "type":"Manufacturing & Wholesale Goods"
        },
        {
            "category":"Home & Garden",
            "subcategory":"Building Materials",
            "type":"Retail Goods"
        }
    ],
    "sg:phone":"+1 410 754 5595",
    "sg:postcode":"21632",
    "sg:province":"MD",
    "sg:tags":[
        "contractor",
        "sand",
        "gravel",
        "fill"
    ],
    "wof:name":"Marshy Hope Sand & Gravel",
    "wof:placetype":"venue"
},
  "geometry": {"coordinates":[-75.776633,38.676657],"type":"Point"}
}