{
  "type": "Feature",
  "properties": {
    "iso:country":"US",
    "sg:address":"11826 Rocking Horse Rd",
    "sg:city":"Rockville",
    "sg:classifiers":[
        {
            "category":"Professional",
            "subcategory":"Management & Consulting",
            "type":"Services"
        }
    ],
    "sg:phone":"+1 301 770 4737",
    "sg:postcode":"20852",
    "sg:province":"MD",
    "sg:tags":[
        "environmental",
        "consultant"
    ],
    "wof:name":"Paul T Hawes & Associates",
    "wof:placetype":"venue"
},
  "geometry": {"coordinates":[-77.096802,39.050842],"type":"Point"}
}