{
  "type": "Feature",
  "properties": {
    "addr:full":"2402 Shadywood Cir Crofton MD 21114",
    "addr:housenumber":"2402",
    "addr:postcode":"21114",
    "addr:street":"Shadywood Cir",
    "iso:country":"US",
    "sg:address":"2402 Shadywood Cir",
    "sg:city":"Crofton",
    "sg:classifiers":[
        {
            "category":"Shopping",
            "subcategory":"Bicycles & Sporting Goods",
            "type":"Retail Goods"
        }
    ],
    "sg:phone":"+1 410 451 3920",
    "sg:postcode":"21114",
    "sg:province":"MD",
    "wof:name":"Cool Stuff",
    "wof:placetype":"venue"
},
  "geometry": {"coordinates":[-76.676215,39.020952],"type":"Point"}
}