{
  "type": "Feature",
  "properties": {
    "addr:full":"3114 Evergreen Way Ellicott City MD 21042",
    "addr:housenumber":"3114",
    "addr:postcode":"21042",
    "addr:street":"Evergreen Way",
    "iso:country":"US",
    "sg:address":"3114 Evergreen Way",
    "sg:city":"Ellicott City",
    "sg:classifiers":[
        {
            "category":"Banks & Credit Unions",
            "subcategory":"Investment Brokerage",
            "type":"Services"
        }
    ],
    "sg:phone":"+1 410 531 7030",
    "sg:postcode":"21042",
    "sg:province":"MD",
    "sg:tags":[
        "consultant",
        "planning",
        "financial"
    ],
    "wof:name":"Black Rock",
    "wof:placetype":"venue"
},
  "geometry": {"coordinates":[-76.926483,39.283743],"type":"Point"}
}