{
  "type": "Feature",
  "properties": {
    "addr:full":"6032 Amberwood Rd Baltimore MD 21206",
    "addr:housenumber":"6032",
    "addr:postcode":"21206",
    "addr:street":"Amberwood Rd",
    "iso:country":"US",
    "sg:address":"6032 Amberwood Rd",
    "sg:city":"Baltimore",
    "sg:classifiers":[
        {
            "category":"Shopping",
            "subcategory":"Clothing, Apparel, & Fashions",
            "type":"Retail Goods"
        }
    ],
    "sg:phone":"+1 410 488 3221",
    "sg:postcode":"21206",
    "sg:province":"MD",
    "sg:tags":[
        "item",
        "boutique"
    ],
    "wof:name":"Leslie's Boutique",
    "wof:placetype":"venue"
},
  "geometry": {"coordinates":[-76.543357,39.316418],"type":"Point"}
}