{
  "type": "Feature",
  "properties": {
    "iso:country":"US",
    "sg:address":"3448 Ellicott Center Dr",
    "sg:city":"Ellicott City",
    "sg:classifiers":[
        {
            "category":"Professional",
            "subcategory":"Credit Reporting & Collection",
            "type":"Services"
        }
    ],
    "sg:phone":"+1 410 750 6017",
    "sg:postcode":"21043",
    "sg:province":"MD",
    "sg:tags":[
        "agency"
    ],
    "wof:name":"Account Balance Consultants",
    "wof:placetype":"venue"
},
  "geometry": {"coordinates":[-76.814652,39.277022],"type":"Point"}
}