{
  "type": "Feature",
  "properties": {
    "addr:full":"156 Foxchase Dr Glen Burnie MD 21061",
    "addr:housenumber":"156",
    "addr:postcode":"21061",
    "addr:street":"Foxchase Dr",
    "iso:country":"US",
    "sg:address":"156 Foxchase Dr",
    "sg:city":"Glen Burnie",
    "sg:classifiers":[
        {
            "category":"Wholesale",
            "subcategory":"Medical Equipment & Supplies",
            "type":"Manufacturing & Wholesale Goods"
        }
    ],
    "sg:phone":"+1 443 306 1424",
    "sg:postcode":"21061",
    "sg:province":"MD",
    "wof:name":"Core Trading Company",
    "wof:placetype":"venue"
},
  "geometry": {"coordinates":[-76.608588,39.136048],"type":"Point"}
}