{
  "type": "Feature",
  "properties": {
    "addr:full":"707 Winifred Rd Cumberland MD 21502",
    "addr:housenumber":"707",
    "addr:postcode":"21502",
    "addr:street":"Winifred Rd",
    "iso:country":"US",
    "sg:address":"707 Winifred Rd",
    "sg:city":"Cumberland",
    "sg:classifiers":[
        {
            "category":"Building & Trades",
            "subcategory":"Construction",
            "type":"Services"
        }
    ],
    "sg:phone":"+1 301 724 6789",
    "sg:postcode":"21502",
    "sg:province":"MD",
    "sg:tags":[
        "painter"
    ],
    "wof:name":"Fradiska & Sons",
    "wof:placetype":"venue"
},
  "geometry": {"coordinates":[-78.74444200000001,39.641461],"type":"Point"}
}