{
  "type": "Feature",
  "properties": {
    "iso:country":"US",
    "sg:address":"3 Rosemont Ct",
    "sg:city":"Rockville",
    "sg:classifiers":[
        {
            "category":"Health Services",
            "subcategory":"Dentist",
            "type":"Services"
        }
    ],
    "sg:phone":"+1 301 564 5900",
    "sg:postcode":"20852",
    "sg:province":"MD",
    "wof:name":"Scott Stuart DDS PA",
    "wof:placetype":"venue"
},
  "geometry": {"coordinates":[-77.127762,39.032784],"type":"Point"}
}