{
  "type": "Feature",
  "properties": {
    "addr:full":"10750 Little Patuxent Pkwy Columbia MD 21044",
    "addr:housenumber":"10750",
    "addr:postcode":"21044",
    "addr:street":"Little Patuxent Pkwy",
    "iso:country":"US",
    "sg:address":"10750 Little Patuxent Pkwy",
    "sg:city":"Columbia",
    "sg:classifiers":[
        {
            "category":"Professional",
            "subcategory":"Advertising",
            "type":"Services"
        }
    ],
    "sg:phone":"+1 410 995 0899",
    "sg:postcode":"21044",
    "sg:province":"MD",
    "sg:tags":[
        "agency",
        "specialty"
    ],
    "wof:name":"Ad Advertising Assoc",
    "wof:placetype":"venue"
},
  "geometry": {"coordinates":[-76.87485,39.214591],"type":"Point"}
}