{
  "type": "Feature",
  "properties": {
    "addr:full":"135 Delaware Ave Glen Burnie MD 21061",
    "addr:housenumber":"135",
    "addr:postcode":"21061",
    "addr:street":"Delaware Ave",
    "iso:country":"US",
    "sg:address":"135 Delaware Ave",
    "sg:city":"Glen Burnie",
    "sg:classifiers":[
        {
            "category":"Shopping",
            "subcategory":"Bicycles & Sporting Goods",
            "type":"Retail Goods"
        }
    ],
    "sg:phone":"+1 410 590 2833",
    "sg:postcode":"21061",
    "sg:province":"MD",
    "sg:tags":[
        "equipment",
        "skateboard"
    ],
    "wof:name":"Charm City Skateboard Shop",
    "wof:placetype":"venue"
},
  "geometry": {"coordinates":[-76.623458,39.164366],"type":"Point"}
}