{
  "type": "Feature",
  "properties": {
    "addr:full":"514 Foster Knoll Dr Joppa MD 21085",
    "addr:housenumber":"514",
    "addr:postcode":"21085",
    "addr:street":"Foster Knoll Dr",
    "iso:country":"US",
    "sg:address":"514 Foster Knoll Dr",
    "sg:city":"Joppa",
    "sg:classifiers":[
        {
            "category":"Freight",
            "type":"Transportation"
        }
    ],
    "sg:phone":"+1 410 679 6393",
    "sg:postcode":"21085",
    "sg:province":"MD",
    "sg:tags":[
        "operator",
        "local",
        "trucking"
    ],
    "wof:name":"Scotts Trucking",
    "wof:placetype":"venue"
},
  "geometry": {"coordinates":[-76.341908,39.409853],"type":"Point"}
}