{
  "type": "Feature",
  "properties": {
    "addr:full":"209 Front St Chestertown MD 21628",
    "addr:housenumber":"209",
    "addr:postcode":"21628",
    "addr:street":"Front St",
    "iso:country":"US",
    "sg:address":"209 Front St",
    "sg:city":"Chestertown",
    "sg:classifiers":[
        {
            "category":"Manufacturing",
            "subcategory":"Watercraft",
            "type":"Manufacturing & Wholesale Goods"
        }
    ],
    "sg:phone":"+1 410 778 5594",
    "sg:postcode":"21628",
    "sg:province":"MD",
    "sg:tags":[
        "boat"
    ],
    "wof:name":"Williams Marine & Cabinetry",
    "wof:placetype":"venue"
},
  "geometry": {"coordinates":[-75.924955,39.241494],"type":"Point"}
}