{
  "type": "Feature",
  "properties": {
    "addr:full":"11101 Indian Head Hwy Fort Washington MD 20744",
    "addr:housenumber":"11101",
    "addr:postcode":"20744",
    "addr:street":"Indian Head Hwy",
    "iso:country":"US",
    "sg:address":"11101 Indian Head Hwy",
    "sg:city":"Fort Washington",
    "sg:classifiers":[
        {
            "category":"Insurance",
            "subcategory":"Insurance Agent",
            "type":"Services"
        }
    ],
    "sg:phone":"+1 301 292 5700",
    "sg:postcode":"20744",
    "sg:province":"MD",
    "wof:name":"Nationwide Insurance",
    "wof:placetype":"venue"
},
  "geometry": {"coordinates":[-76.991744,38.740411],"type":"Point"}
}