{
  "type": "Feature",
  "properties": {
    "addr:full":"750 Dual Hwy Hagerstown MD 21740",
    "addr:housenumber":"750",
    "addr:postcode":"21740",
    "addr:street":"Dual Hwy",
    "iso:country":"US",
    "sg:address":"750 Dual Hwy",
    "sg:city":"Hagerstown",
    "sg:classifiers":[
        {
            "category":"Social Services",
            "subcategory":"Retirement Home",
            "type":"Services"
        }
    ],
    "sg:phone":"+1 301 797 4020",
    "sg:postcode":"21740",
    "sg:province":"MD",
    "sg:tags":[
        "living",
        "assisted",
        "facility"
    ],
    "wof:name":"Golden Living Ctr-Hagerstown",
    "wof:placetype":"venue"
},
  "geometry": {"coordinates":[-77.69229900000001,39.615929],"type":"Point"}
}