{
  "type": "Feature",
  "properties": {
    "addr:full":"5753 Main St Rock Hall MD 21661",
    "addr:housenumber":"5753",
    "addr:postcode":"21661",
    "addr:street":"Main St",
    "iso:country":"US",
    "sg:address":"5753 Main St",
    "sg:city":"Rock Hall",
    "sg:classifiers":[
        {
            "category":"Shopping",
            "subcategory":"Gifts & Souvenirs",
            "type":"Retail Goods"
        }
    ],
    "sg:phone":"+1 410 639 7991",
    "sg:postcode":"21661",
    "sg:province":"MD",
    "sg:tags":[
        "shop"
    ],
    "wof:name":"Sweet Annie's",
    "wof:placetype":"venue"
},
  "geometry": {"coordinates":[-76.234786,39.137404],"type":"Point"}
}