{
  "type": "Feature",
  "properties": {
    "iso:country":"US",
    "sg:address":"3321 Annapolis Rd",
    "sg:city":"Baltimore",
    "sg:classifiers":[
        {
            "category":"Bakery",
            "type":"Food & Drink"
        }
    ],
    "sg:phone":"+1 410 355 1524",
    "sg:postcode":"21230",
    "sg:province":"MD",
    "wof:name":"Tropical Treats",
    "wof:placetype":"venue"
},
  "geometry": {"coordinates":[-76.63955799999999,39.249684],"type":"Point"}
}