{
  "type": "Feature",
  "properties": {
    "addr:full":"1102 E Joppa Rd Baltimore MD 21286",
    "addr:housenumber":"1102 e",
    "addr:postcode":"21286",
    "addr:street":"Joppa Rd",
    "iso:country":"US",
    "sg:address":"1102 E Joppa Rd",
    "sg:city":"Baltimore",
    "sg:classifiers":[
        {
            "category":"Health Services",
            "subcategory":"Chiropractor",
            "type":"Services"
        }
    ],
    "sg:phone":"+1 410 321 7210",
    "sg:postcode":"21286",
    "sg:province":"MD",
    "wof:name":"Spector Chiropractic Offices",
    "wof:placetype":"venue"
},
  "geometry": {"coordinates":[-76.579314,39.39694],"type":"Point"}
}