{
  "type": "Feature",
  "properties": {
    "iso:country":"US",
    "sg:address":"200 Main St",
    "sg:city":"Laurel",
    "sg:classifiers":[
        {
            "category":"Professional",
            "subcategory":"Lawyer & Legal Services",
            "type":"Services"
        }
    ],
    "sg:phone":"+1 301 490 1455",
    "sg:postcode":"20707",
    "sg:province":"MD",
    "wof:name":"Barikor Law Offices",
    "wof:placetype":"venue"
},
  "geometry": {"coordinates":[-76.842865,39.10324],"type":"Point"}
}