{
  "type": "Feature",
  "properties": {
    "iso:country":"US",
    "sg:address":"1403 Edmondson Ave",
    "sg:city":"Baltimore",
    "sg:classifiers":[
        {
            "category":"Professional",
            "subcategory":"Secretarial Services",
            "type":"Services"
        }
    ],
    "sg:phone":"+1 410 744 7491",
    "sg:postcode":"21228",
    "sg:province":"MD",
    "sg:tags":[
        "reporting"
    ],
    "wof:name":"Reliant Data Services Inc",
    "wof:placetype":"venue"
},
  "geometry": {"coordinates":[-76.749952,39.274],"type":"Point"}
}