{
  "type": "Feature",
  "properties": {
    "addr:full":"6260 Columbia Xing Columbia MD 21045",
    "addr:housenumber":"6260",
    "addr:postcode":"21045",
    "addr:street":"Columbia Xing",
    "iso:country":"US",
    "sg:address":"6260 Columbia Xing",
    "sg:city":"Columbia",
    "sg:classifiers":[
        {
            "category":"Shopping",
            "subcategory":"Clothing, Apparel, & Fashions",
            "type":"Retail Goods"
        }
    ],
    "sg:phone":"+1 410 872 1170",
    "sg:postcode":"21045",
    "sg:province":"MD",
    "wof:name":"Old Navy",
    "wof:placetype":"venue"
},
  "geometry": {"coordinates":[-76.814526,39.198385],"type":"Point"}
}