{
  "type": "Feature",
  "properties": {
    "addr:full":"1680 E Gude Dr Rockville MD 20850",
    "addr:housenumber":"1680",
    "addr:postcode":"20850",
    "addr:street":"E Gude Dr",
    "iso:country":"US",
    "sg:address":"1680 E Gude Dr",
    "sg:city":"Rockville",
    "sg:classifiers":[
        {
            "category":"Real Estate",
            "subcategory":"Real Estate Operator",
            "type":"Services"
        }
    ],
    "sg:phone":"+1 301 294 2330",
    "sg:postcode":"20850",
    "sg:province":"MD",
    "sg:tags":[
        "building",
        "parks"
    ],
    "wof:name":"W M & F Gude One",
    "wof:placetype":"venue"
},
  "geometry": {"coordinates":[-77.131945,39.093779],"type":"Point"}
}