{
  "type": "Feature",
  "properties": {
    "addr:full":"1207 Northbrook Dr Hampstead MD 21074",
    "addr:housenumber":"1207",
    "addr:postcode":"21074",
    "addr:street":"Northbrook Dr",
    "iso:country":"US",
    "sg:address":"1207 Northbrook Dr",
    "sg:city":"Hampstead",
    "sg:classifiers":[
        {
            "category":"Landmark",
            "subcategory":"Tourist Information",
            "type":"Public Place"
        }
    ],
    "sg:phone":"+1 410 374 9059",
    "sg:postcode":"21074",
    "sg:province":"MD",
    "sg:tags":[
        "promoter",
        "tours-operators"
    ],
    "wof:name":"Class Acts On Tour",
    "wof:placetype":"venue"
},
  "geometry": {"coordinates":[-76.873429,39.605454],"type":"Point"}
}