{
  "type": "Feature",
  "properties": {
    "iso:country":"US",
    "sg:address":"700 Boxmere Ct",
    "sg:city":"West River",
    "sg:classifiers":[
        {
            "category":"Professional",
            "subcategory":"Management & Consulting",
            "type":"Services"
        }
    ],
    "sg:phone":"+1 410 867 7608",
    "sg:postcode":"20778",
    "sg:province":"MD",
    "sg:tags":[
        "financial"
    ],
    "wof:name":"Alberto J Di Pompo",
    "wof:placetype":"venue"
},
  "geometry": {"coordinates":[-76.544004,38.822739],"type":"Point"}
}