{
  "type": "Feature",
  "properties": {
    "addr:full":"8501 Snouffers School Rd Gaithersburg MD 20879",
    "addr:housenumber":"8501",
    "addr:postcode":"20879",
    "addr:street":"Snouffers School Rd",
    "iso:country":"US",
    "sg:address":"8501 Snouffers School Rd",
    "sg:city":"Gaithersburg",
    "sg:classifiers":[
        {
            "category":"Retail",
            "subcategory":"Auto Rental",
            "type":"Services"
        }
    ],
    "sg:phone":"+1 301 977 4130",
    "sg:postcode":"20879",
    "sg:province":"MD",
    "sg:tags":[
        "renting",
        "truck",
        "leasing"
    ],
    "wof:name":"U-Haul Co",
    "wof:placetype":"venue"
},
  "geometry": {"coordinates":[-77.175935,39.169071],"type":"Point"}
}