{
  "type": "Feature",
  "properties": {
    "iso:country":"US",
    "sg:address":"5732 Buckeystown Pike",
    "sg:city":"Frederick",
    "sg:classifiers":[
        {
            "category":"Personal",
            "subcategory":"Beauty Salon",
            "type":"Services"
        }
    ],
    "sg:phone":"+1 301 662 6621",
    "sg:postcode":"21704",
    "sg:province":"MD",
    "sg:tags":[
        "shop",
        "manicuring"
    ],
    "wof:name":"Just Nails",
    "wof:placetype":"venue"
},
  "geometry": {"coordinates":[-77.409494,39.391639],"type":"Point"}
}