{
  "type": "Feature",
  "properties": {
    "addr:full":"710 Brookridge Dr Boonsboro MD 21713",
    "addr:housenumber":"710",
    "addr:postcode":"21713",
    "addr:street":"Brookridge Dr",
    "iso:country":"US",
    "sg:address":"710 Brookridge Dr",
    "sg:city":"Boonsboro",
    "sg:classifiers":[
        {
            "category":"Shopping",
            "subcategory":"Bicycles & Sporting Goods",
            "type":"Retail Goods"
        }
    ],
    "sg:phone":"+1 301 432 8900",
    "sg:postcode":"21713",
    "sg:province":"MD",
    "sg:tags":[
        "equipment",
        "exercise"
    ],
    "wof:name":"East Coast Fitness Inc",
    "wof:placetype":"venue"
},
  "geometry": {"coordinates":[-77.66907999999999,39.499776],"type":"Point"}
}