{
  "type": "Feature",
  "properties": {
    "addr:full":"11050 Johns Hopkins Rd Laurel MD 20723",
    "addr:housenumber":"11050",
    "addr:postcode":"20723",
    "addr:street":"Johns Hopkins Rd",
    "iso:country":"US",
    "sg:address":"11050 Johns Hopkins Rd",
    "sg:city":"Laurel",
    "sg:classifiers":[
        {
            "category":"Banks & Credit Unions",
            "subcategory":"Bank",
            "type":"Services"
        }
    ],
    "sg:phone":"+1 443 778 5250",
    "sg:postcode":"20723",
    "sg:province":"MD",
    "wof:name":"A P L F C U",
    "wof:placetype":"venue"
},
  "geometry": {"coordinates":[-76.895544,39.160395],"type":"Point"}
}