{
  "type": "Feature",
  "properties": {
    "iso:country":"US",
    "sg:address":"7063 Friendship Rd",
    "sg:city":"Linthicum Heights",
    "sg:classifiers":[
        {
            "category":"Taxi",
            "type":"Transportation"
        },
        {
            "category":"Airline",
            "type":"Transportation"
        }
    ],
    "sg:phone":"+1 410 859 1103",
    "sg:postcode":"21090",
    "sg:province":"MD",
    "sg:tags":[
        "shuttle",
        "airport"
    ],
    "wof:name":"Bwi Airport Taxi",
    "wof:placetype":"venue"
},
  "geometry": {"coordinates":[-76.65619700000001,39.208698],"type":"Point"}
}