{
  "type": "Feature",
  "properties": {
    "addr:full":"13129 Memory Ln Hagerstown MD 21740",
    "addr:housenumber":"13129",
    "addr:postcode":"21740",
    "addr:street":"Memory Ln",
    "iso:country":"US",
    "sg:address":"13129 Memory Ln",
    "sg:city":"Hagerstown",
    "sg:classifiers":[
        {
            "category":"Building & Trades",
            "subcategory":"Construction",
            "type":"Services"
        }
    ],
    "sg:phone":"+1 301 766 0016",
    "sg:postcode":"21740",
    "sg:province":"MD",
    "sg:tags":[
        "contractor"
    ],
    "wof:name":"Mount Tabor Builders",
    "wof:placetype":"venue"
},
  "geometry": {"coordinates":[-77.81162,39.673091],"type":"Point"}
}