{
  "type": "Feature",
  "properties": {
    "iso:country":"US",
    "sg:address":"6236 Ranier Dr",
    "sg:city":"Frederick",
    "sg:classifiers":[
        {
            "category":"Retail",
            "subcategory":"Laundry & Dry Cleaning",
            "type":"Services"
        }
    ],
    "sg:phone":"+1 301 831 4963",
    "sg:postcode":"21703",
    "sg:province":"MD",
    "sg:tags":[
        "cleaners",
        "rug",
        "carpet"
    ],
    "wof:name":"J's Carpet Cleaning",
    "wof:placetype":"venue"
},
  "geometry": {"coordinates":[-77.451336,39.38773],"type":"Point"}
}