{
  "type": "Feature",
  "properties": {
    "iso:country":"US",
    "sg:address":"12 Pasture Brook Ct",
    "sg:city":"Potomac",
    "sg:classifiers":[
        {
            "category":"Social Services",
            "type":"Services"
        }
    ],
    "sg:phone":"+1 301 610 9620",
    "sg:postcode":"20854",
    "sg:province":"MD",
    "sg:tags":[
        "instruction",
        "health",
        "care"
    ],
    "sg:website":"www.intech-salud.org",
    "wof:name":"Intech Institute For Technical",
    "wof:placetype":"venue"
},
  "geometry": {"coordinates":[-77.165605,39.070626],"type":"Point"}
}