{
  "type": "Feature",
  "properties": {
    "addr:full":"8509 Timber Pine Ct Ellicott City MD 21043",
    "addr:housenumber":"8509",
    "addr:postcode":"21043",
    "addr:street":"Timber Pine Ct",
    "iso:country":"US",
    "sg:address":"8509 Timber Pine Ct",
    "sg:city":"Ellicott City",
    "sg:classifiers":[
        {
            "category":"Professional",
            "subcategory":"Business Services",
            "type":"Services"
        }
    ],
    "sg:phone":"+1 410 480 2722",
    "sg:postcode":"21043",
    "sg:province":"MD",
    "wof:name":"Star Styles",
    "wof:placetype":"venue"
},
  "geometry": {"coordinates":[-76.801845,39.256666],"type":"Point"}
}