{
  "type": "Feature",
  "properties": {
    "iso:country":"US",
    "sg:address":"23 Saddle Ct",
    "sg:city":"Pikesville",
    "sg:classifiers":[
        {
            "category":"Health Services",
            "subcategory":"Clinic",
            "type":"Services"
        }
    ],
    "sg:phone":"+1 410 486 5774",
    "sg:postcode":"21208",
    "sg:province":"MD",
    "sg:tags":[
        "organization",
        "medical",
        "surgical"
    ],
    "wof:name":"Aaron Friedmann & Assoc",
    "wof:placetype":"venue"
},
  "geometry": {"coordinates":[-76.725528,39.391875],"type":"Point"}
}