{
  "type": "Feature",
  "properties": {
    "iso:country":"US",
    "sg:address":"4331 Gallatin St",
    "sg:city":"Hyattsville",
    "sg:classifiers":[
        {
            "category":"Professional",
            "subcategory":"Lawyer & Legal Services",
            "type":"Services"
        }
    ],
    "sg:phone":"+1 301 277 5168",
    "sg:postcode":"20781",
    "sg:province":"MD",
    "sg:tags":[
        "attorney"
    ],
    "wof:name":"Rowland Law Firm",
    "wof:placetype":"venue"
},
  "geometry": {"coordinates":[-76.942707,38.952555],"type":"Point"}
}