{
  "type": "Feature",
  "properties": {
    "iso:country":"US",
    "sg:address":"10218 New Hampshire Ave",
    "sg:city":"Silver Spring",
    "sg:classifiers":[
        {
            "category":"Manufacturing",
            "subcategory":"Printing",
            "type":"Manufacturing & Wholesale Goods"
        }
    ],
    "sg:phone":"+1 301 431 0025",
    "sg:postcode":"20903",
    "sg:province":"MD",
    "sg:tags":[
        "commercial"
    ],
    "wof:name":"C & T Printing & Copy",
    "wof:placetype":"venue"
},
  "geometry": {"coordinates":[-76.979248,39.024042],"type":"Point"}
}