{
  "type": "Feature",
  "properties": {
    "iso:country":"US",
    "sg:address":"2734 Hess Rd",
    "sg:city":"Monkton",
    "sg:classifiers":[
        {
            "category":"Building & Trades",
            "subcategory":"Landscaping Services",
            "type":"Services"
        }
    ],
    "sg:phone":"+1 410 692 0050",
    "sg:postcode":"21111",
    "sg:province":"MD",
    "sg:tags":[
        "landscape",
        "contractor"
    ],
    "wof:name":"TDH Landscaping & Nurseries",
    "wof:placetype":"venue"
},
  "geometry": {"coordinates":[-76.524956,39.554901],"type":"Point"}
}