{
  "type": "Feature",
  "properties": {
    "addr:full":"8525 Baltimore National Pike Ellicott City MD 21043",
    "addr:housenumber":"8525",
    "addr:postcode":"21043",
    "addr:street":"Baltimore National Pike",
    "iso:country":"US",
    "sg:address":"8525 Baltimore National Pike",
    "sg:city":"Ellicott City",
    "sg:classifiers":[
        {
            "category":"Building & Trades",
            "subcategory":"Locksmith",
            "type":"Services"
        }
    ],
    "sg:phone":"+1 410 696 9002",
    "sg:postcode":"21043",
    "sg:province":"MD",
    "sg:tags":[
        "key"
    ],
    "wof:name":"Locksmith Al",
    "wof:placetype":"venue"
},
  "geometry": {"coordinates":[-76.807687,39.283999],"type":"Point"}
}