{
  "type": "Feature",
  "properties": {
    "addr:full":"11550-F Rockville Pike Rockville MD 20852",
    "addr:housenumber":"11550-f",
    "addr:postcode":"20852",
    "addr:street":"Rockville Pike",
    "iso:country":"US",
    "sg:address":"11550-F Rockville Pike",
    "sg:city":"Rockville",
    "sg:classifiers":[
        {
            "category":"Animal Shelter",
            "type":"Public Place"
        }
    ],
    "sg:phone":"+1 301 984 0020",
    "sg:postcode":"20852",
    "sg:province":"MD",
    "sg:tags":[
        "adult"
    ],
    "sg:website":"www.nightdreams.com/",
    "wof:name":"Night Dreams",
    "wof:placetype":"venue"
},
  "geometry": {"coordinates":[-77.112458,39.046119],"type":"Point"}
}