{
  "type": "Feature",
  "properties": {
    "addr:full":"3920 Falls Rd Baltimore MD 21211",
    "addr:housenumber":"3920",
    "addr:postcode":"21211",
    "addr:street":"Falls Rd",
    "iso:country":"US",
    "sg:address":"3920 Falls Rd",
    "sg:city":"Baltimore",
    "sg:classifiers":[
        {
            "category":"Restaurant",
            "type":"Food & Drink"
        }
    ],
    "sg:menulink":"http://www.allmenus.com/md/baltimore/215531-mcdonalds/menu/",
    "sg:postcode":"21211",
    "sg:province":"MD",
    "sg:tags":[
        "burger",
        "american"
    ],
    "wof:name":"McDonald's",
    "wof:placetype":"venue"
},
  "geometry": {"coordinates":[-76.63641699999999,39.335938],"type":"Point"}
}