{
  "type": "Feature",
  "properties": {
    "addr:full":"13022 8th St Bowie MD 20720",
    "addr:housenumber":"13022",
    "addr:postcode":"20720",
    "addr:street":"8Th St",
    "iso:country":"US",
    "sg:address":"13022 8th St",
    "sg:city":"Bowie",
    "sg:classifiers":[
        {
            "category":"Social Services",
            "type":"Services"
        }
    ],
    "sg:phone":"+1 301 464 3725",
    "sg:postcode":"20720",
    "sg:province":"MD",
    "sg:tags":[
        "youth",
        "organization",
        "center"
    ],
    "wof:name":"Huntington Community Ctr",
    "wof:placetype":"venue"
},
  "geometry": {"coordinates":[-76.779021,39.009246],"type":"Point"}
}