{
  "type": "Feature",
  "properties": {
    "iso:country":"US",
    "sg:address":"6600 Cradlerock Way",
    "sg:city":"Columbia",
    "sg:classifiers":[
        {
            "category":"Education",
            "subcategory":"Library",
            "type":"Public Place"
        }
    ],
    "sg:phone":"+1 410 313 7700",
    "sg:postcode":"21045",
    "sg:province":"MD",
    "sg:website":"www.hclibrary.org",
    "wof:name":"Howard County Libraries",
    "wof:placetype":"venue"
},
  "geometry": {"coordinates":[-76.846001,39.191002],"type":"Point"}
}