{
  "type": "Feature",
  "properties": {
    "addr:full":"4573 Kingscup Ct Ellicott City MD 21042",
    "addr:housenumber":"4573",
    "addr:postcode":"21042",
    "addr:street":"Kingscup Ct",
    "iso:country":"US",
    "sg:address":"4573 Kingscup Ct",
    "sg:city":"Ellicott City",
    "sg:classifiers":[
        {
            "category":"Communications",
            "subcategory":"Film & Video Production",
            "type":"Services"
        }
    ],
    "sg:phone":"+1 410 772 0010",
    "sg:postcode":"21042",
    "sg:province":"MD",
    "sg:tags":[
        "editor"
    ],
    "wof:name":"Maureen Leypoldt",
    "wof:placetype":"venue"
},
  "geometry": {"coordinates":[-76.83323900000001,39.248407],"type":"Point"}
}