{
  "type": "Feature",
  "properties": {
    "addr:full":"10440 Little Patuxent Pkwy Columbia MD 21044",
    "addr:housenumber":"10440",
    "addr:postcode":"21044",
    "addr:street":"Little Patuxent Pkwy",
    "iso:country":"US",
    "sg:address":"10440 Little Patuxent Pkwy",
    "sg:city":"Columbia",
    "sg:classifiers":[
        {
            "category":"Professional",
            "subcategory":"Research",
            "type":"Services"
        }
    ],
    "sg:phone":"+1 410 884 4009",
    "sg:postcode":"21044",
    "sg:province":"MD",
    "sg:tags":[
        "foundation",
        "philanthropic"
    ],
    "sg:website":"www.thehorizonfoundation.org",
    "wof:name":"Horizon Foundation Of Howard",
    "wof:placetype":"venue"
},
  "geometry": {"coordinates":[-76.86014400000001,39.211682],"type":"Point"}
}