{
  "type": "Feature",
  "properties": {
    "addr:full":"602 Deer Park Rd Westminster MD 21157",
    "addr:housenumber":"602",
    "addr:postcode":"21157",
    "addr:street":"Deer Park Rd",
    "iso:country":"US",
    "sg:address":"602 Deer Park Rd",
    "sg:city":"Westminster",
    "sg:classifiers":[
        {
            "category":"Food & Beverages",
            "subcategory":"Groceries & Convenience Stores",
            "type":"Retail Goods"
        }
    ],
    "sg:phone":"+1 410 876 7838",
    "sg:postcode":"21157",
    "sg:province":"MD",
    "wof:name":"George's Gas & Deli",
    "wof:placetype":"venue"
},
  "geometry": {"coordinates":[-76.97483099999999,39.513163],"type":"Point"}
}