{
  "type": "Feature",
  "properties": {
    "addr:full":"5113 Moorland Ln Bethesda MD 20814",
    "addr:housenumber":"5113",
    "addr:postcode":"20814",
    "addr:street":"Moorland Ln",
    "iso:country":"US",
    "sg:address":"5113 Moorland Ln",
    "sg:city":"Bethesda",
    "sg:classifiers":[
        {
            "category":"Real Estate",
            "subcategory":"Real Estate Agent",
            "type":"Services"
        }
    ],
    "sg:phone":"+1 301 654 3220",
    "sg:postcode":"20814",
    "sg:province":"MD",
    "wof:name":"Sherry L Davis",
    "wof:placetype":"venue"
},
  "geometry": {"coordinates":[-77.103065,38.985961],"type":"Point"}
}