{
  "type": "Feature",
  "properties": {
    "addr:full":"9800 Patuxent Woods Dr Columbia MD 21046",
    "addr:housenumber":"9800",
    "addr:postcode":"21046",
    "addr:street":"Patuxent Woods Dr",
    "iso:country":"US",
    "sg:address":"9800 Patuxent Woods Dr",
    "sg:city":"Columbia",
    "sg:classifiers":[
        {
            "category":"Restaurant",
            "type":"Food & Drink"
        }
    ],
    "sg:phone":"+1 410 309 3839",
    "sg:postcode":"21046",
    "sg:province":"MD",
    "sg:tags":[
        "eating"
    ],
    "wof:name":"Minute Maid Co",
    "wof:placetype":"venue"
},
  "geometry": {"coordinates":[-76.851517,39.177834],"type":"Point"}
}