{
  "type": "Feature",
  "properties": {
    "addr:full":"6013 Benalder Dr Bethesda MD 20816",
    "addr:postcode":"6013;20816",
    "addr:street":"Benalder Dr",
    "iso:country":"US",
    "sg:address":"6013 Benalder Dr",
    "sg:city":"Bethesda",
    "sg:classifiers":[
        {
            "category":"Social Services",
            "type":"Services"
        }
    ],
    "sg:phone":"+1 301 229 6764",
    "sg:postcode":"20816",
    "sg:province":"MD",
    "sg:tags":[
        "worker"
    ],
    "wof:name":"Ruth Simon",
    "wof:placetype":"venue"
},
  "geometry": {"coordinates":[-77.138043,38.970162],"type":"Point"}
}