{
  "type": "Feature",
  "properties": {
    "iso:country":"US",
    "sg:address":"18450 Showalter Rd # 104",
    "sg:city":"Hagerstown",
    "sg:classifiers":[
        {
            "category":"Professional",
            "subcategory":"Computer Services",
            "type":"Services"
        }
    ],
    "sg:phone":"+1 301 739 7205",
    "sg:postcode":"21742",
    "sg:province":"MD",
    "sg:tags":[
        "publisher",
        "developer",
        "software"
    ],
    "wof:name":"Compass Solutions",
    "wof:placetype":"venue"
},
  "geometry": {"coordinates":[-77.730176,39.702036],"type":"Point"}
}