{
  "type": "Feature",
  "properties": {
    "addr:full":"1301 Piccard Dr Rockville MD 20850",
    "addr:housenumber":"1301",
    "addr:postcode":"20850",
    "addr:street":"Piccard Dr",
    "iso:country":"US",
    "sg:address":"1301 Piccard Dr",
    "sg:city":"Rockville",
    "sg:classifiers":[
        {
            "category":"Government",
            "subcategory":"Office",
            "type":"Public Place"
        }
    ],
    "sg:phone":"+1 301 217 1425",
    "sg:postcode":"20850",
    "sg:province":"MD",
    "wof:name":"Victim Advocate Program",
    "wof:placetype":"venue"
},
  "geometry": {"coordinates":[-77.177696,39.102858],"type":"Point"}
}