{
  "type": "Feature",
  "properties": {
    "addr:full":"7914 Belair Rd PMB 53 Nottingham MD 21236",
    "addr:housenumber":"7914;53",
    "addr:postcode":"21236",
    "addr:street":"Belair Rd Pmb",
    "iso:country":"US",
    "sg:address":"7914 Belair Rd PMB 53",
    "sg:city":"Nottingham",
    "sg:classifiers":[
        {
            "category":"Professional",
            "subcategory":"Management & Consulting",
            "type":"Services"
        }
    ],
    "sg:phone":"+1 443 955 5772",
    "sg:postcode":"21236",
    "sg:province":"MD",
    "sg:tags":[
        "consultant"
    ],
    "wof:name":"My Utility Bill Savings",
    "wof:placetype":"venue"
},
  "geometry": {"coordinates":[-76.510396,39.372758],"type":"Point"}
}