{
  "type": "Feature",
  "properties": {
    "iso:country":"US",
    "sg:address":"1201 Dual Hwy",
    "sg:city":"Hagerstown",
    "sg:classifiers":[
        {
            "category":"Retail",
            "subcategory":"Auto Repair",
            "type":"Services"
        }
    ],
    "sg:phone":"+1 301 797 3100",
    "sg:postcode":"21740",
    "sg:province":"MD",
    "sg:tags":[
        "wrecker"
    ],
    "wof:name":"Pottery By Me & More",
    "wof:placetype":"venue"
},
  "geometry": {"coordinates":[-77.70083,39.63039],"type":"Point"}
}