{
  "type": "Feature",
  "properties": {
    "addr:full":"1710 Gwynn Oak Ave Gwynn Oak MD 21207",
    "addr:housenumber":"1710",
    "addr:postcode":"21207",
    "addr:street":"Gwynn Oak Ave",
    "iso:country":"US",
    "sg:address":"1710 Gwynn Oak Ave",
    "sg:city":"Gwynn Oak",
    "sg:classifiers":[
        {
            "category":"Social Services",
            "subcategory":"Child Care",
            "type":"Services"
        }
    ],
    "sg:phone":"+1 410 265 5435",
    "sg:postcode":"21207",
    "sg:province":"MD",
    "sg:tags":[
        "day"
    ],
    "wof:name":"Chelsea's Gentle Care of Woodlawn",
    "wof:placetype":"venue"
},
  "geometry": {"coordinates":[-76.729704,39.313011],"type":"Point"}
}