{
  "type": "Feature",
  "properties": {
    "addr:full":"625v Baltimore Blvd Westminster MD 21157",
    "addr:housenumber":"625v",
    "addr:postcode":"21157",
    "addr:street":"Baltimore Blvd",
    "iso:country":"US",
    "sg:address":"625v Baltimore Blvd",
    "sg:city":"Westminster",
    "sg:classifiers":[
        {
            "category":"Restaurant",
            "type":"Food & Drink"
        }
    ],
    "sg:menulink":"http://www.allmenus.com/md/westminster/207682-taco-bell/menu/",
    "sg:phone":"+1 410 876 1799",
    "sg:postcode":"21157",
    "sg:province":"MD",
    "sg:tags":[
        "mexican"
    ],
    "wof:name":"Taco Bell",
    "wof:placetype":"venue"
},
  "geometry": {"coordinates":[-76.972556,39.563375],"type":"Point"}
}