{
  "type": "Feature",
  "properties": {
    "addr:full":"37287 E Lakeland Dr Mechanicsville MD 20659",
    "addr:housenumber":"37287",
    "addr:postcode":"20659",
    "addr:street":"E Lakeland Dr",
    "iso:country":"US",
    "sg:address":"37287 E Lakeland Dr",
    "sg:city":"Mechanicsville",
    "sg:classifiers":[
        {
            "category":"Professional",
            "subcategory":"Accounting & Tax Preparation",
            "type":"Services"
        }
    ],
    "sg:phone":"+1 301 274 3870",
    "sg:postcode":"20659",
    "sg:province":"MD",
    "wof:name":"Fried Bruce S",
    "wof:placetype":"venue"
},
  "geometry": {"coordinates":[-76.786789,38.397433],"type":"Point"}
}