{
  "type": "Feature",
  "properties": {
    "addr:full":"3615 B And O Rd Abingdon MD 21009",
    "addr:housenumber":"3615",
    "addr:postcode":"21009",
    "addr:street":"B And O Rd",
    "iso:country":"US",
    "sg:address":"3615 B And O Rd",
    "sg:city":"Abingdon",
    "sg:classifiers":[
        {
            "category":"Autos & Motor Vehicles",
            "subcategory":"Fuel & Gas Station",
            "type":"Retail Goods"
        }
    ],
    "sg:phone":"+1 410 679 5290",
    "sg:postcode":"21009",
    "sg:province":"MD",
    "wof:name":"Citgo Quik Lube.",
    "wof:placetype":"venue"
},
  "geometry": {"coordinates":[-76.267365,39.456577],"type":"Point"}
}