{
  "type": "Feature",
  "properties": {
    "addr:full":"5135 Viaduct Ave Halethorpe MD 21227",
    "addr:housenumber":"5135",
    "addr:postcode":"21227",
    "addr:street":"Viaduct Ave",
    "iso:country":"US",
    "sg:address":"5135 Viaduct Ave",
    "sg:city":"Halethorpe",
    "sg:classifiers":[
        {
            "category":"Professional",
            "subcategory":"Lawyer & Legal Services",
            "type":"Services"
        }
    ],
    "sg:phone":"+1 410 247 0885",
    "sg:postcode":"21227",
    "sg:province":"MD",
    "sg:tags":[
        "living",
        "estate",
        "planning",
        "trust",
        "probate"
    ],
    "wof:name":"Relief Resources Inc",
    "wof:placetype":"venue"
},
  "geometry": {"coordinates":[-76.711838,39.227137],"type":"Point"}
}