{
  "type": "Feature",
  "properties": {
    "iso:country":"US",
    "sg:address":"298 Butler Rd",
    "sg:city":"Reisterstown",
    "sg:classifiers":[
        {
            "category":"Professional",
            "subcategory":"Lawyer & Legal Services",
            "type":"Services"
        }
    ],
    "sg:phone":"+1 410 902 9455",
    "sg:postcode":"21136",
    "sg:province":"MD",
    "wof:name":"Howard D Gregory Atty",
    "wof:placetype":"venue"
},
  "geometry": {"coordinates":[-76.824941,39.474266],"type":"Point"}
}