{
  "type": "Feature",
  "properties": {
    "addr:full":"1319 Woodbridge Station Way Edgewood MD 21040",
    "addr:housenumber":"1319",
    "addr:postcode":"21040",
    "addr:street":"Woodbridge Station Way",
    "iso:country":"US",
    "sg:address":"1319 Woodbridge Station Way",
    "sg:city":"Edgewood",
    "sg:classifiers":[
        {
            "category":"Professional",
            "subcategory":"Management & Consulting",
            "type":"Services"
        }
    ],
    "sg:phone":"+1 410 671 7104",
    "sg:postcode":"21040",
    "sg:province":"MD",
    "sg:tags":[
        "consultant",
        "business"
    ],
    "sg:website":"www.scitechinc.com",
    "wof:name":"Scitech Corp",
    "wof:placetype":"venue"
},
  "geometry": {"coordinates":[-76.328225,39.431831],"type":"Point"}
}