{
  "type": "Feature",
  "properties": {
    "addr:full":"13 Gay St Berlin MD 21811",
    "addr:housenumber":"13",
    "addr:postcode":"21811",
    "addr:street":"Gay St",
    "iso:country":"US",
    "sg:address":"13 Gay St",
    "sg:city":"Berlin",
    "sg:classifiers":[
        {
            "category":"Manufacturing",
            "subcategory":"Buildings",
            "type":"Manufacturing & Wholesale Goods"
        },
        {
            "category":"Building & Trades",
            "subcategory":"Construction",
            "type":"Services"
        }
    ],
    "sg:phone":"+1 410 641 4773",
    "sg:postcode":"21811",
    "sg:province":"MD",
    "sg:tags":[
        "home",
        "builder",
        "contractor"
    ],
    "wof:name":"Gem Builders Michael Vino",
    "wof:placetype":"venue"
},
  "geometry": {"coordinates":[-75.219931,38.324199],"type":"Point"}
}