{
  "type": "Feature",
  "properties": {
    "iso:country":"US",
    "sg:address":"9157 Whiskey Bottom Rd",
    "sg:city":"Laurel",
    "sg:classifiers":[
        {
            "category":"Wholesale",
            "subcategory":"Medical Equipment & Supplies",
            "type":"Manufacturing & Wholesale Goods"
        }
    ],
    "sg:phone":"+1 410 792 2907",
    "sg:postcode":"20723",
    "sg:province":"MD",
    "sg:tags":[
        "laboratory"
    ],
    "sg:website":"http://www.atrbiotech.com",
    "wof:name":"Atr",
    "wof:placetype":"venue"
},
  "geometry": {"coordinates":[-76.82986099999999,39.115244],"type":"Point"}
}