{
  "type": "Feature",
  "properties": {
    "addr:full":"2239 Bel Pre Rd Silver Spring MD 20906",
    "addr:housenumber":"2239",
    "addr:postcode":"20906",
    "addr:street":"Pre Rd",
    "iso:country":"US",
    "sg:address":"2239 Bel Pre Rd",
    "sg:city":"Silver Spring",
    "sg:classifiers":[
        {
            "category":"Personal",
            "subcategory":"Beauty Salon",
            "type":"Services"
        }
    ],
    "sg:phone":"+1 301 871 2800",
    "sg:postcode":"20906",
    "sg:province":"MD",
    "sg:tags":[
        "manicuring"
    ],
    "wof:name":"Nail Club",
    "wof:placetype":"venue"
},
  "geometry": {"coordinates":[-77.046848,39.090605],"type":"Point"}
}