{
  "type": "Feature",
  "properties": {
    "iso:country":"US",
    "sg:address":"3000 Lottsford Vista Rd",
    "sg:city":"Mitchellville",
    "sg:classifiers":[
        {
            "category":"Professional",
            "type":"Services"
        }
    ],
    "sg:phone":"+1 301 577 5496",
    "sg:postcode":"20721",
    "sg:province":"MD",
    "sg:tags":[
        "establishment"
    ],
    "wof:name":"Outreach Department",
    "wof:placetype":"venue"
},
  "geometry": {"coordinates":[-76.822047,38.931056],"type":"Point"}
}