{
  "type": "Feature",
  "properties": {
    "addr:full":"7474 Washington Blvd Elkridge MD 21075",
    "addr:housenumber":"7474",
    "addr:postcode":"21075",
    "addr:street":"Washington Blvd",
    "iso:country":"US",
    "sg:address":"7474 Washington Blvd",
    "sg:city":"Elkridge",
    "sg:classifiers":[
        {
            "category":"Organizations",
            "subcategory":"Religious Organization",
            "type":"Services"
        }
    ],
    "sg:phone":"+1 410 799 7974",
    "sg:postcode":"21075",
    "sg:province":"MD",
    "sg:tags":[
        "church"
    ],
    "sg:website":"www.trinity-waterloo.ang-md.org",
    "wof:name":"Trinity Episcopal Church",
    "wof:placetype":"venue"
},
  "geometry": {"coordinates":[-76.770146,39.179839],"type":"Point"}
}