{
  "type": "Feature",
  "properties": {
    "iso:country":"US",
    "sg:address":"1276 Bay Dale Dr",
    "sg:city":"Arnold",
    "sg:classifiers":[
        {
            "category":"Shopping",
            "subcategory":"Florist",
            "type":"Retail Goods"
        }
    ],
    "sg:phone":"+1 410 974 4220",
    "sg:postcode":"21012",
    "sg:province":"MD",
    "wof:name":"Severna Flowers & Gifts",
    "wof:placetype":"venue"
},
  "geometry": {"coordinates":[-76.47921700000001,39.03906],"type":"Point"}
}