{
  "type": "Feature",
  "properties": {
    "addr:full":"8553 Fort Smallwood Rd Riviera Beach MD 21122",
    "addr:housenumber":"8553",
    "addr:postcode":"21122",
    "addr:street":"Fort Smallwood Rd",
    "iso:country":"US",
    "sg:address":"8553 Fort Smallwood Rd",
    "sg:city":"Riviera Beach",
    "sg:classifiers":[
        {
            "category":"Banks & Credit Unions",
            "subcategory":"Bank",
            "type":"Services"
        }
    ],
    "sg:phone":"+1 410 437 1300",
    "sg:postcode":"21122",
    "sg:province":"MD",
    "sg:tags":[
        "savings",
        "loan",
        "association"
    ],
    "wof:name":"Provident Bank",
    "wof:placetype":"venue"
},
  "geometry": {"coordinates":[-76.522003,39.149915],"type":"Point"}
}