{
  "type": "Feature",
  "properties": {
    "iso:country":"US",
    "sg:address":"917 Snow Hill Rd",
    "sg:city":"Salisbury",
    "sg:classifiers":[
        {
            "category":"Personal",
            "subcategory":"Beauty Salon",
            "type":"Services"
        }
    ],
    "sg:phone":"+1 410 548 4522",
    "sg:postcode":"21804",
    "sg:province":"MD",
    "wof:name":"Classic Cut Salon",
    "wof:placetype":"venue"
},
  "geometry": {"coordinates":[-75.581854,38.347463],"type":"Point"}
}