{
  "type": "Feature",
  "properties": {
    "addr:full":"10407 Aubinoe Farm Dr Bethesda MD 20814",
    "addr:housenumber":"10407",
    "addr:postcode":"20814",
    "addr:street":"Aubinoe Farm Dr",
    "iso:country":"US",
    "sg:address":"10407 Aubinoe Farm Dr",
    "sg:city":"Bethesda",
    "sg:classifiers":[
        {
            "category":"Professional",
            "subcategory":"Management & Consulting",
            "type":"Services"
        },
        {
            "category":"Professional",
            "subcategory":"Engineering",
            "type":"Services"
        }
    ],
    "sg:phone":"+1 301 530 4712",
    "sg:postcode":"20814",
    "sg:province":"MD",
    "sg:tags":[
        "environmental",
        "ecological",
        "engineer",
        "consultant"
    ],
    "sg:website":"http://www.intowndenver.com",
    "wof:name":"In Town Consulting",
    "wof:placetype":"venue"
},
  "geometry": {"coordinates":[-77.125619,39.027403],"type":"Point"}
}