{
  "type": "Feature",
  "properties": {
    "iso:country":"US",
    "sg:address":"13 Tadcaster Cir",
    "sg:city":"Waldorf",
    "sg:classifiers":[
        {
            "category":"Health Services",
            "subcategory":"Clinic",
            "type":"Services"
        }
    ],
    "sg:phone":"+1 301 893 0956",
    "sg:postcode":"20602",
    "sg:province":"MD",
    "sg:tags":[
        "home",
        "care"
    ],
    "wof:name":"First In Quality Care",
    "wof:placetype":"venue"
},
  "geometry": {"coordinates":[-76.920385,38.591752],"type":"Point"}
}