{
  "type": "Feature",
  "properties": {
    "addr:full":"200 Greenland Beach Rd Curtis Bay MD 21226",
    "addr:housenumber":"200",
    "addr:postcode":"21226",
    "addr:street":"Greenland Beach Rd",
    "iso:country":"US",
    "sg:address":"200 Greenland Beach Rd",
    "sg:city":"Curtis Bay",
    "sg:classifiers":[
        {
            "category":"Building & Trades",
            "subcategory":"Plumbing",
            "type":"Services"
        }
    ],
    "sg:phone":"+1 410 647 3578",
    "sg:postcode":"21226",
    "sg:province":"MD",
    "sg:tags":[
        "conditioning",
        "air",
        "system",
        "contractor"
    ],
    "wof:name":"Supreme Heating & Air Cond",
    "wof:placetype":"venue"
},
  "geometry": {"coordinates":[-76.53062799999999,39.165447],"type":"Point"}
}