{
  "type": "Feature",
  "properties": {
    "iso:country":"US",
    "sg:address":"6653 Washington Blvd",
    "sg:city":"Elkridge",
    "sg:classifiers":[
        {
            "category":"Autos & Motor Vehicles",
            "subcategory":"Automobile Sales",
            "type":"Retail Goods"
        }
    ],
    "sg:phone":"+1 410 579 2444",
    "sg:postcode":"21075",
    "sg:province":"MD",
    "sg:tags":[
        "car",
        "dealer"
    ],
    "wof:name":"Elkridge Auto",
    "wof:placetype":"venue"
},
  "geometry": {"coordinates":[-76.73816,39.199455],"type":"Point"}
}