{
  "type": "Feature",
  "properties": {
    "iso:country":"US",
    "sg:address":"13129 Brushwood Way",
    "sg:city":"Potomac",
    "sg:classifiers":[
        {
            "category":"Professional",
            "type":"Services"
        }
    ],
    "sg:phone":"+1 301 519 2642",
    "sg:postcode":"20854",
    "sg:province":"MD",
    "wof:name":"Deirdre Saunder Artist",
    "wof:placetype":"venue"
},
  "geometry": {"coordinates":[-77.276357,39.068697],"type":"Point"}
}