{
  "type": "Feature",
  "properties": {
    "addr:full":"3408 Hamilton St Hyattsville MD 20782",
    "addr:housenumber":"3408",
    "addr:postcode":"20782",
    "addr:street":"Hamilton St",
    "iso:country":"US",
    "sg:address":"3408 Hamilton St",
    "sg:city":"Hyattsville",
    "sg:classifiers":[
        {
            "category":"Personal",
            "subcategory":"Barber",
            "type":"Services"
        }
    ],
    "sg:phone":"+1 301 927 7363",
    "sg:postcode":"20782",
    "sg:province":"MD",
    "wof:name":"Kut Klose",
    "wof:placetype":"venue"
},
  "geometry": {"coordinates":[-76.961304,38.9552],"type":"Point"}
}