{
  "type": "Feature",
  "properties": {
    "iso:country":"US",
    "sg:address":"9902 Rocky Ridge Rd",
    "sg:city":"Rocky Ridge",
    "sg:classifiers":[
        {
            "category":"Farming",
            "subcategory":"Farm",
            "type":"Manufacturing & Wholesale Goods"
        }
    ],
    "sg:phone":"+1 301 271 4154",
    "sg:postcode":"21778",
    "sg:province":"MD",
    "sg:tags":[
        "crop",
        "general"
    ],
    "wof:name":"Deer Hayen Farms",
    "wof:placetype":"venue"
},
  "geometry": {"coordinates":[-77.32650599999999,39.605316],"type":"Point"}
}