{
  "type": "Feature",
  "properties": {
    "addr:full":"215 Matapex Plantation Ln Stevensville MD 21666",
    "addr:housenumber":"215",
    "addr:postcode":"21666",
    "addr:street":"Matapex Plantation Ln",
    "iso:country":"US",
    "sg:address":"215 Matapex Plantation Ln",
    "sg:city":"Stevensville",
    "sg:classifiers":[
        {
            "category":"Professional",
            "subcategory":"Business Services",
            "type":"Services"
        }
    ],
    "sg:phone":"+1 443 249 0027",
    "sg:postcode":"21666",
    "sg:province":"MD",
    "wof:name":"Annapolis Interiors Inc",
    "wof:placetype":"venue"
},
  "geometry": {"coordinates":[-76.350409,38.911541],"type":"Point"}
}