{
  "type": "Feature",
  "properties": {
    "iso:country":"US",
    "sg:address":"503 Pinetree Dr",
    "sg:city":"Severna Park",
    "sg:classifiers":[
        {
            "category":"Professional",
            "subcategory":"Art Services",
            "type":"Services"
        }
    ],
    "sg:phone":"+1 410 647 1119",
    "sg:postcode":"21146",
    "sg:province":"MD",
    "sg:tags":[
        "commercial",
        "design"
    ],
    "wof:name":"Sally Chaney Lentzner",
    "wof:placetype":"venue"
},
  "geometry": {"coordinates":[-76.557746,39.073637],"type":"Point"}
}