{
  "type": "Feature",
  "properties": {
    "addr:full":"44736 Clarks Mill Rd Hollywood MD 20636",
    "addr:housenumber":"44736",
    "addr:postcode":"20636",
    "addr:street":"Clarks Mill Rd",
    "iso:country":"US",
    "sg:address":"44736 Clarks Mill Rd",
    "sg:city":"Hollywood",
    "sg:classifiers":[
        {
            "category":"Building & Trades",
            "subcategory":"Construction",
            "type":"Services"
        }
    ],
    "sg:phone":"+1 301 373 2738",
    "sg:postcode":"20636",
    "sg:province":"MD",
    "sg:tags":[
        "contractor"
    ],
    "wof:name":"Strong Arm Drywall",
    "wof:placetype":"venue"
},
  "geometry": {"coordinates":[-76.523977,38.324211],"type":"Point"}
}