{
  "type": "Feature",
  "properties": {
    "addr:full":"12504 Trelawn Ter Bowie MD 20721",
    "addr:housenumber":"12504",
    "addr:postcode":"20721",
    "addr:street":"Trelawn Ter",
    "iso:country":"US",
    "sg:address":"12504 Trelawn Ter",
    "sg:city":"Bowie",
    "sg:classifiers":[
        {
            "category":"Real Estate",
            "subcategory":"Developer",
            "type":"Services"
        }
    ],
    "sg:phone":"+1 301 249 9050",
    "sg:postcode":"20721",
    "sg:province":"MD",
    "wof:name":"Townsend Development Corporation Inc",
    "wof:placetype":"venue"
},
  "geometry": {"coordinates":[-76.788714,38.932861],"type":"Point"}
}