{
  "type": "Feature",
  "properties": {
    "addr:full":"7511 Leadenham Cove Rd Bozman MD 21612",
    "addr:housenumber":"7511",
    "addr:postcode":"21612",
    "addr:street":"Leadenham Cove Rd",
    "iso:country":"US",
    "sg:address":"7511 Leadenham Cove Rd",
    "sg:city":"Bozman",
    "sg:classifiers":[
        {
            "category":"Professional",
            "subcategory":"Lawyer & Legal Services",
            "type":"Services"
        }
    ],
    "sg:phone":"+1 410 745 0045",
    "sg:postcode":"21612",
    "sg:province":"MD",
    "sg:tags":[
        "attorney"
    ],
    "wof:name":"William G Hughes",
    "wof:placetype":"venue"
},
  "geometry": {"coordinates":[-76.28849700000001,38.759763],"type":"Point"}
}