{
  "type": "Feature",
  "properties": {
    "iso:country":"US",
    "sg:address":"6832 New Hampshire Ave",
    "sg:city":"Takoma Park",
    "sg:classifiers":[
        {
            "category":"Shopping",
            "subcategory":"Clothing, Apparel, & Fashions",
            "type":"Retail Goods"
        }
    ],
    "sg:phone":"+1 301 270 8201",
    "sg:postcode":"20912",
    "sg:province":"MD",
    "sg:tags":[
        "uniform"
    ],
    "wof:name":"American Uniform Center",
    "wof:placetype":"venue"
},
  "geometry": {"coordinates":[-76.995491,38.974173],"type":"Point"}
}