{
  "type": "Feature",
  "properties": {
    "iso:country":"US",
    "sg:address":"7 Slade Ave",
    "sg:city":"Pikesville",
    "sg:classifiers":[
        {
            "category":"Professional",
            "subcategory":"Business Services",
            "type":"Services"
        }
    ],
    "sg:phone":"+1 410 484 3640",
    "sg:postcode":"21208",
    "sg:province":"MD",
    "wof:name":"Mildred Mindell Foundation",
    "wof:placetype":"venue"
},
  "geometry": {"coordinates":[-76.71467699999999,39.370485],"type":"Point"}
}