{
  "type": "Feature",
  "properties": {
    "addr:full":"5504 Muddy Creek Rd West River MD 20778",
    "addr:housenumber":"5504",
    "addr:postcode":"20778",
    "addr:street":"Muddy Creek Rd",
    "iso:country":"US",
    "sg:address":"5504 Muddy Creek Rd",
    "sg:city":"West River",
    "sg:classifiers":[
        {
            "category":"Food & Beverages",
            "subcategory":"Specialty",
            "type":"Retail Goods"
        }
    ],
    "sg:phone":"+1 410 867 8505",
    "sg:postcode":"20778",
    "sg:province":"MD",
    "wof:name":"Early Birds Inc",
    "wof:placetype":"venue"
},
  "geometry": {"coordinates":[-76.548006,38.814864],"type":"Point"}
}