{
  "type": "Feature",
  "properties": {
    "addr:full":"202 Newton St Salisbury MD 21801",
    "addr:housenumber":"202",
    "addr:postcode":"21801",
    "addr:street":"Newton St",
    "iso:country":"US",
    "sg:address":"202 Newton St",
    "sg:city":"Salisbury",
    "sg:classifiers":[
        {
            "category":"Autos & Motor Vehicles",
            "subcategory":"Boat Sales",
            "type":"Retail Goods"
        }
    ],
    "sg:phone":"+1 410 749 9119",
    "sg:postcode":"21801",
    "sg:province":"MD",
    "sg:tags":[
        "dealer",
        "sales"
    ],
    "wof:name":"M & S Marine Inc",
    "wof:placetype":"venue"
},
  "geometry": {"coordinates":[-75.600686,38.359379],"type":"Point"}
}