{
  "type": "Feature",
  "properties": {
    "addr:full":"9128 Baltimore Ave College Park MD 20740",
    "addr:housenumber":"9128",
    "addr:postcode":"20740",
    "addr:street":"Baltimore Ave",
    "iso:country":"US",
    "sg:address":"9128 Baltimore Ave",
    "sg:city":"College Park",
    "sg:classifiers":[
        {
            "category":"Restaurant",
            "type":"Food & Drink"
        }
    ],
    "sg:phone":"+1 301 441 2040",
    "sg:postcode":"20740",
    "sg:province":"MD",
    "wof:name":"Lasick's College Inn",
    "wof:placetype":"venue"
},
  "geometry": {"coordinates":[-76.930268,39.005338],"type":"Point"}
}