{
  "type": "Feature",
  "properties": {
    "addr:full":"1532 Havnwd Rd Baltimore MD 21239",
    "addr:housenumber":"1532",
    "addr:postcode":"21239",
    "addr:street":"Havnwd Rd",
    "iso:country":"US",
    "sg:address":"1532 Havnwd Rd",
    "sg:city":"Baltimore",
    "sg:classifiers":[
        {
            "category":"Health Services",
            "subcategory":"Dentist",
            "type":"Services"
        }
    ],
    "sg:phone":"+1 410 243 7747",
    "sg:postcode":"21239",
    "sg:province":"MD",
    "wof:name":"Newman E H & Associates PA",
    "wof:placetype":"venue"
},
  "geometry": {"coordinates":[-76.586502,39.360802],"type":"Point"}
}