{
  "type": "Feature",
  "properties": {
    "iso:country":"US",
    "sg:address":"2785 Blue Ball Rd",
    "sg:city":"Elkton",
    "sg:classifiers":[
        {
            "category":"Restaurant",
            "type":"Food & Drink"
        }
    ],
    "sg:phone":"+1 410 620 0206",
    "sg:postcode":"21921",
    "sg:province":"MD",
    "sg:tags":[
        "delicatessen"
    ],
    "wof:name":"Kucukaydin Yusef",
    "wof:placetype":"venue"
},
  "geometry": {"coordinates":[-75.917833,39.682166],"type":"Point"}
}