{
  "type": "Feature",
  "properties": {
    "iso:country":"US",
    "sg:address":"152 River Run",
    "sg:city":"Queenstown",
    "sg:classifiers":[
        {
            "category":"Professional",
            "subcategory":"Management & Consulting",
            "type":"Services"
        }
    ],
    "sg:phone":"+1 410 827 4054",
    "sg:postcode":"21658",
    "sg:province":"MD",
    "sg:tags":[
        "consultant",
        "business"
    ],
    "wof:name":"North Star Maritime Inc",
    "wof:placetype":"venue"
},
  "geometry": {"coordinates":[-76.162205,38.943752],"type":"Point"}
}