{
  "type": "Feature",
  "properties": {
    "iso:country":"US",
    "sg:address":"11337 Elkin St",
    "sg:city":"Silver Spring",
    "sg:classifiers":[
        {
            "category":"Retail",
            "subcategory":"Auto Repair",
            "type":"Services"
        }
    ],
    "sg:phone":"+1 301 949 7850",
    "sg:postcode":"20902",
    "sg:province":"MD",
    "sg:tags":[
        "transmission"
    ],
    "wof:name":"Transpecialists",
    "wof:placetype":"venue"
},
  "geometry": {"coordinates":[-77.050307,39.041109],"type":"Point"}
}