{
  "type": "Feature",
  "properties": {
    "addr:full":"930 Port St Easton MD 21601",
    "addr:housenumber":"930",
    "addr:postcode":"21601",
    "addr:street":"Port St",
    "iso:country":"US",
    "sg:address":"930 Port St",
    "sg:city":"Easton",
    "sg:classifiers":[
        {
            "category":"Professional",
            "subcategory":"Advertising",
            "type":"Services"
        }
    ],
    "sg:phone":"+1 410 822 2000",
    "sg:postcode":"21601",
    "sg:province":"MD",
    "sg:tags":[
        "distribution"
    ],
    "wof:name":"Griffith Energy Svc",
    "wof:placetype":"venue"
},
  "geometry": {"coordinates":[-76.09304899999999,38.768451],"type":"Point"}
}