{
  "type": "Feature",
  "properties": {
    "addr:full":"1415 Lafayette Ave Baltimore MD 21207",
    "addr:housenumber":"1415",
    "addr:postcode":"21207",
    "addr:street":"Lafayette Ave",
    "iso:country":"US",
    "sg:address":"1415 Lafayette Ave",
    "sg:city":"Baltimore",
    "sg:classifiers":[
        {
            "category":"Education",
            "subcategory":"Special Training",
            "type":"Public Place"
        }
    ],
    "sg:phone":"+1 410 719 8828",
    "sg:postcode":"21207",
    "sg:province":"MD",
    "wof:name":"David Gorrie",
    "wof:placetype":"venue"
},
  "geometry": {"coordinates":[-76.72786499999999,39.302944],"type":"Point"}
}