{
  "type": "Feature",
  "properties": {
    "addr:full":"226 Washington Heights Medical Center Westminster MD 21157",
    "addr:housenumber":"226",
    "addr:postcode":"21157",
    "iso:country":"US",
    "sg:address":"226 Washington Heights Medical Center",
    "sg:city":"Westminster",
    "sg:classifiers":[
        {
            "category":"Health Services",
            "subcategory":"Doctor",
            "type":"Services"
        }
    ],
    "sg:phone":"+1 410 876 8650",
    "sg:postcode":"21157",
    "sg:province":"MD",
    "sg:tags":[
        "physician",
        "surgeon"
    ],
    "wof:name":"Pockun Penn MD",
    "wof:placetype":"venue"
},
  "geometry": {"coordinates":[-76.986588,39.563233],"type":"Point"}
}