{
  "type": "Feature",
  "properties": {
    "addr:full":"20321 Trolley Crossing Ct Montgomery Village MD 20886",
    "addr:housenumber":"20321",
    "addr:postcode":"20886",
    "addr:street":"Trolley Crossing Ct",
    "iso:country":"US",
    "sg:address":"20321 Trolley Crossing Ct",
    "sg:city":"Montgomery Village",
    "sg:classifiers":[
        {
            "category":"Health Services",
            "subcategory":"Clinic",
            "type":"Services"
        }
    ],
    "sg:phone":"+1 301 947 0855",
    "sg:postcode":"20886",
    "sg:province":"MD",
    "wof:name":"Manna Nurse Consultants",
    "wof:placetype":"venue"
},
  "geometry": {"coordinates":[-77.158483,39.188142],"type":"Point"}
}