{
  "type": "Feature",
  "properties": {
    "addr:full":"8 Poolside Ct Catonsville MD 21228",
    "addr:housenumber":"8",
    "addr:postcode":"21228",
    "addr:street":"Poolside Ct",
    "iso:country":"US",
    "sg:address":"8 Poolside Ct",
    "sg:city":"Catonsville",
    "sg:classifiers":[
        {
            "category":"Building & Trades",
            "subcategory":"Construction",
            "type":"Services"
        }
    ],
    "sg:phone":"+1 410 744 7838",
    "sg:postcode":"21228",
    "sg:province":"MD",
    "sg:tags":[
        "apartment",
        "contractor"
    ],
    "wof:name":"Westerlee Apartments",
    "wof:placetype":"venue"
},
  "geometry": {"coordinates":[-76.768204,39.290401],"type":"Point"}
}