{
  "type": "Feature",
  "properties": {
    "addr:full":"111 Brookletts Ave Easton MD 21601",
    "addr:housenumber":"111",
    "addr:postcode":"21601",
    "addr:street":"Brookletts Ave",
    "iso:country":"US",
    "sg:address":"111 Brookletts Ave",
    "sg:city":"Easton",
    "sg:classifiers":[
        {
            "category":"Organizations",
            "subcategory":"Religious Organization",
            "type":"Services"
        }
    ],
    "sg:phone":"+1 410 822 2904",
    "sg:postcode":"21601",
    "sg:province":"MD",
    "sg:tags":[
        "church"
    ],
    "wof:name":"Grace Lutheran Church",
    "wof:placetype":"venue"
},
  "geometry": {"coordinates":[-76.072958,38.770613],"type":"Point"}
}