{
  "type": "Feature",
  "properties": {
    "addr:full":"2337 N Rolling Rd Baltimore MD 21244",
    "addr:housenumber":"2337",
    "addr:postcode":"21244",
    "addr:street":"N Rolling Rd",
    "iso:country":"US",
    "sg:address":"2337 N Rolling Rd",
    "sg:city":"Baltimore",
    "sg:classifiers":[
        {
            "category":"Health Services",
            "subcategory":"Doctor",
            "type":"Services"
        }
    ],
    "sg:phone":"+1 410 944 6322",
    "sg:postcode":"21244",
    "sg:province":"MD",
    "sg:tags":[
        "physician",
        "surgeon"
    ],
    "wof:name":"Primary Family Health Clinic",
    "wof:placetype":"venue"
},
  "geometry": {"coordinates":[-76.758298,39.320737],"type":"Point"}
}