{
  "type": "Feature",
  "properties": {
    "iso:country":"US",
    "sg:address":"1601 E Lombard St",
    "sg:city":"Baltimore",
    "sg:classifiers":[
        {
            "category":"Education",
            "subcategory":"School",
            "type":"Public Place"
        },
        {
            "category":"Sports & Exercise",
            "subcategory":"Playing Field",
            "type":"Entertainment"
        }
    ],
    "sg:phone":"+1 410 396 1720",
    "sg:postcode":"21231",
    "sg:province":"MD",
    "sg:tags":[
        "personal",
        "development"
    ],
    "wof:name":"Alternative Learning Ctr 488",
    "wof:placetype":"venue"
},
  "geometry": {"coordinates":[-76.59638200000001,39.290272],"type":"Point"}
}