{
  "type": "Feature",
  "properties": {
    "addr:full":"1700 Alberti Dr Silver Spring MD 20902",
    "addr:housenumber":"1700",
    "addr:postcode":"20902",
    "addr:street":"Alberti Dr",
    "iso:country":"US",
    "sg:address":"1700 Alberti Dr",
    "sg:city":"Silver Spring",
    "sg:classifiers":[
        {
            "category":"Organizations",
            "subcategory":"Professional Association",
            "type":"Services"
        }
    ],
    "sg:phone":"+1 301 649 3628",
    "sg:postcode":"20902",
    "sg:province":"MD",
    "wof:name":"Maryland Perfusion Society",
    "wof:placetype":"venue"
},
  "geometry": {"coordinates":[-77.03828300000001,39.03467],"type":"Point"}
}