{
  "type": "Feature",
  "properties": {
    "addr:full":"137 Kent Oaks Way Gaithersburg MD 20878",
    "addr:housenumber":"137",
    "addr:postcode":"20878",
    "addr:street":"Kent Oaks Way",
    "iso:country":"US",
    "sg:address":"137 Kent Oaks Way",
    "sg:city":"Gaithersburg",
    "sg:classifiers":[
        {
            "category":"Communications",
            "subcategory":"Film & Video Production",
            "type":"Services"
        }
    ],
    "sg:phone":"+1 301 670 0252",
    "sg:postcode":"20878",
    "sg:province":"MD",
    "sg:tags":[
        "motion"
    ],
    "wof:name":"Visions Unlmted Prductions Inc",
    "wof:placetype":"venue"
},
  "geometry": {"coordinates":[-77.24174600000001,39.11446],"type":"Point"}
}