{
  "type": "Feature",
  "properties": {
    "iso:country":"US",
    "sg:address":"9821 Riverton Rd",
    "sg:city":"Mardela Springs",
    "sg:classifiers":[
        {
            "category":"Manufacturing",
            "subcategory":"Paper Products",
            "type":"Manufacturing & Wholesale Goods"
        }
    ],
    "sg:phone":"+1 410 749 7125",
    "sg:postcode":"21837",
    "sg:province":"MD",
    "sg:tags":[
        "box"
    ],
    "sg:website":"www.shorepaperbox.com",
    "wof:name":"Shore Paper Box Co",
    "wof:placetype":"venue"
},
  "geometry": {"coordinates":[-75.761566,38.463825],"type":"Point"}
}