{
  "type": "Feature",
  "properties": {
    "addr:full":"45808 Rose Ln Great Mills MD 20634",
    "addr:housenumber":"45808",
    "addr:postcode":"20634",
    "addr:street":"Rose Ln",
    "iso:country":"US",
    "sg:address":"45808 Rose Ln",
    "sg:city":"Great Mills",
    "sg:classifiers":[
        {
            "category":"Professional",
            "subcategory":"Computer Services",
            "type":"Services"
        }
    ],
    "sg:phone":"+1 301 862 1104",
    "sg:postcode":"20634",
    "sg:province":"MD",
    "sg:tags":[
        "consultant",
        "designer"
    ],
    "wof:name":"Creative Computer Consultants",
    "wof:placetype":"venue"
},
  "geometry": {"coordinates":[-76.493201,38.265707],"type":"Point"}
}