{
  "type": "Feature",
  "properties": {
    "addr:full":"7620 Maple Ave Takoma Park MD 20912",
    "addr:housenumber":"7620",
    "addr:postcode":"20912",
    "addr:street":"Maple Ave",
    "iso:country":"US",
    "sg:address":"7620 Maple Ave",
    "sg:city":"Takoma Park",
    "sg:classifiers":[
        {
            "category":"Real Estate",
            "subcategory":"Real Estate Operator",
            "type":"Services"
        }
    ],
    "sg:phone":"+1 301 270 5525",
    "sg:postcode":"20912",
    "sg:province":"MD",
    "sg:tags":[
        "apartment"
    ],
    "wof:name":"Franklin Apartments",
    "wof:placetype":"venue"
},
  "geometry": {"coordinates":[-77.005369,38.98401],"type":"Point"}
}