{
  "type": "Feature",
  "properties": {
    "iso:country":"US",
    "sg:address":"4710 Suitland Rd",
    "sg:city":"Suitland",
    "sg:classifiers":[
        {
            "category":"Retail",
            "subcategory":"Laundry & Dry Cleaning",
            "type":"Services"
        }
    ],
    "sg:phone":"+1 301 736 3366",
    "sg:postcode":"20746",
    "sg:province":"MD",
    "sg:tags":[
        "cleaner"
    ],
    "wof:name":"Ideal Cleaners Inc",
    "wof:placetype":"venue"
},
  "geometry": {"coordinates":[-76.9254,38.848999],"type":"Point"}
}