{
  "type": "Feature",
  "properties": {
    "iso:country":"US",
    "sg:address":"10304 Putman Rd",
    "sg:city":"Frederick",
    "sg:classifiers":[
        {
            "category":"Recreation",
            "type":"Entertainment"
        }
    ],
    "sg:phone":"+1 301 606 4153",
    "sg:postcode":"21702",
    "sg:province":"MD",
    "sg:tags":[
        "camps-recreational"
    ],
    "wof:name":"Wsi Camp Journey",
    "wof:placetype":"venue"
},
  "geometry": {"coordinates":[-77.448941,39.516173],"type":"Point"}
}