{
  "type": "Feature",
  "properties": {
    "iso:country":"US",
    "sg:address":"1010 Joppa Farm Rd",
    "sg:city":"Joppa",
    "sg:classifiers":[
        {
            "category":"Shopping",
            "subcategory":"Department Store",
            "type":"Retail Goods"
        },
        {
            "category":"Shopping",
            "subcategory":"Discount & Variety Stores",
            "type":"Retail Goods"
        },
        {
            "category":"Shopping",
            "type":"Retail Goods"
        }
    ],
    "sg:phone":"+1 410 538 5101",
    "sg:postcode":"21085",
    "sg:province":"MD",
    "sg:tags":[
        "merchandise"
    ],
    "sg:website":"http://www.dollartree.com/",
    "wof:name":"Dollar Tree",
    "wof:placetype":"venue"
},
  "geometry": {"coordinates":[-76.36971699999999,39.421735],"type":"Point"}
}