{
  "type": "Feature",
  "properties": {
    "iso:country":"US",
    "sg:address":"9660 Lottsford Ct",
    "sg:city":"Upper Marlboro",
    "sg:classifiers":[
        {
            "category":"Restaurant",
            "type":"Food & Drink"
        }
    ],
    "sg:phone":"+1 301 322 6444",
    "sg:postcode":"20774",
    "sg:province":"MD",
    "sg:tags":[
        "steakhouse"
    ],
    "sg:website":"www.outbacksteakhouse.com",
    "wof:name":"Outback Steakhouse",
    "wof:placetype":"venue"
},
  "geometry": {"coordinates":[-76.84079699999999,38.909],"type":"Point"}
}