{
  "type": "Feature",
  "properties": {
    "addr:full":"1300 Gateshead Rd Towson MD 21286",
    "addr:housenumber":"1300",
    "addr:postcode":"21286",
    "addr:street":"Gateshead Rd",
    "iso:country":"US",
    "sg:address":"1300 Gateshead Rd",
    "sg:city":"Towson",
    "sg:classifiers":[
        {
            "category":"Professional",
            "subcategory":"Business Services",
            "type":"Services"
        }
    ],
    "sg:phone":"+1 410 321 0449",
    "sg:postcode":"21286",
    "sg:province":"MD",
    "sg:tags":[
        "information",
        "referral"
    ],
    "wof:name":"R P Information Svc",
    "wof:placetype":"venue"
},
  "geometry": {"coordinates":[-76.585393,39.42623],"type":"Point"}
}