{
  "type": "Feature",
  "properties": {
    "iso:country":"US",
    "sg:address":"110 N Main St",
    "sg:city":"Greensboro",
    "sg:classifiers":[
        {
            "category":"Recreation",
            "type":"Entertainment"
        }
    ],
    "sg:phone":"+1 410 482 8444",
    "sg:postcode":"21639",
    "sg:province":"MD",
    "sg:tags":[
        "parlor",
        "billiard"
    ],
    "wof:name":"Doghouse Billiards",
    "wof:placetype":"venue"
},
  "geometry": {"coordinates":[-75.80457,38.975203],"type":"Point"}
}