{
  "type": "Feature",
  "properties": {
    "iso:country":"US",
    "sg:address":"3321 Toledo Ter Ste 102",
    "sg:city":"Hyattsville",
    "sg:classifiers":[
        {
            "category":"Health Services",
            "subcategory":"Doctor",
            "type":"Services"
        }
    ],
    "sg:phone":"+1 301 559 2400",
    "sg:postcode":"20782",
    "sg:province":"MD",
    "sg:tags":[
        "obstetrician",
        "gynecologist"
    ],
    "wof:name":"Dunmore Gwendolyn MD",
    "wof:placetype":"venue"
},
  "geometry": {"coordinates":[-76.96219600000001,38.967701],"type":"Point"}
}