{
  "type": "Feature",
  "properties": {
    "iso:country":"US",
    "sg:address":"9991 Pulaski Hwy",
    "sg:city":"Baltimore",
    "sg:classifiers":[
        {
            "category":"Autos & Motor Vehicles",
            "subcategory":"Boat Sales",
            "type":"Retail Goods"
        }
    ],
    "sg:phone":"+1 410 391 1994",
    "sg:postcode":"21220",
    "sg:province":"MD",
    "sg:tags":[
        "equipment",
        "supply"
    ],
    "wof:name":"Boater's World Marine Ctr",
    "wof:placetype":"venue"
},
  "geometry": {"coordinates":[-76.446377,39.359833],"type":"Point"}
}