{
  "type": "Feature",
  "properties": {
    "addr:full":"8110 Jumpers Hole Rd Pasadena MD 21122",
    "addr:housenumber":"8110",
    "addr:postcode":"21122",
    "addr:street":"Jumpers Hole Rd",
    "iso:country":"US",
    "sg:address":"8110 Jumpers Hole Rd",
    "sg:city":"Pasadena",
    "sg:classifiers":[
        {
            "category":"Restaurant",
            "type":"Food & Drink"
        }
    ],
    "sg:menulink":"http://www.allmenus.com/md/lake-shore/207698-taco-bell/menu/",
    "sg:phone":"+1 410 760 3800",
    "sg:postcode":"21122",
    "sg:province":"MD",
    "sg:tags":[
        "mexican"
    ],
    "wof:name":"Taco Bell",
    "wof:placetype":"venue"
},
  "geometry": {"coordinates":[-76.589797,39.125151],"type":"Point"}
}