{
  "type": "Feature",
  "properties": {
    "iso:country":"US",
    "sg:address":"1261 W Pratt St",
    "sg:city":"Baltimore",
    "sg:classifiers":[
        {
            "category":"Retail",
            "subcategory":"Auto Rental",
            "type":"Services"
        }
    ],
    "sg:phone":"+1 410 727 8080",
    "sg:postcode":"21223",
    "sg:province":"MD",
    "sg:tags":[
        "renting",
        "car",
        "automobile"
    ],
    "sg:website":"www.enterprise.com",
    "wof:name":"Enterprise Rent-A Car",
    "wof:placetype":"venue"
},
  "geometry": {"coordinates":[-76.637398,39.285599],"type":"Point"}
}