{
  "type": "Feature",
  "properties": {
    "iso:country":"US",
    "sg:address":"5908 Allentown Way",
    "sg:city":"Temple Hills",
    "sg:classifiers":[
        {
            "category":"Personal",
            "subcategory":"Barber",
            "type":"Services"
        }
    ],
    "sg:phone":"+1 301 449 5800",
    "sg:postcode":"20748",
    "sg:province":"MD",
    "wof:name":"Mc Gill's Barber Shop",
    "wof:placetype":"venue"
},
  "geometry": {"coordinates":[-76.907861,38.801224],"type":"Point"}
}