{
  "type": "Feature",
  "properties": {
    "addr:full":"10501 Tanager Ln Potomac MD 20854",
    "addr:housenumber":"10501",
    "addr:postcode":"20854",
    "addr:street":"Tanager Ln",
    "iso:country":"US",
    "sg:address":"10501 Tanager Ln",
    "sg:city":"Potomac",
    "sg:classifiers":[
        {
            "category":"Building & Trades",
            "subcategory":"Construction",
            "type":"Services"
        }
    ],
    "sg:phone":"+1 301 762 6335",
    "sg:postcode":"20854",
    "sg:province":"MD",
    "sg:tags":[
        "home",
        "improvement"
    ],
    "wof:name":"Associated Tile & Marble Inc",
    "wof:placetype":"venue"
},
  "geometry": {"coordinates":[-77.217947,39.067257],"type":"Point"}
}