{
  "type": "Feature",
  "properties": {
    "iso:country":"US",
    "sg:address":"1200 E Joppa Rd",
    "sg:city":"Baltimore",
    "sg:classifiers":[
        {
            "category":"Professional",
            "subcategory":"Accounting & Tax Preparation",
            "type":"Services"
        }
    ],
    "sg:phone":"+1 410 494 9300",
    "sg:postcode":"21286",
    "sg:province":"MD",
    "sg:tags":[
        "accountant"
    ],
    "wof:name":"Jay Naish CPA",
    "wof:placetype":"venue"
},
  "geometry": {"coordinates":[-76.578418,39.396564],"type":"Point"}
}