{
  "type": "Feature",
  "properties": {
    "iso:country":"US",
    "sg:address":"6413 Gallery St Ste B",
    "sg:city":"Bowie",
    "sg:classifiers":[
        {
            "category":"Professional",
            "subcategory":"Detective & Security Services",
            "type":"Services"
        }
    ],
    "sg:phone":"+1 301 490 6294",
    "sg:postcode":"20720",
    "sg:province":"MD",
    "sg:tags":[
        "car",
        "armored",
        "private",
        "investigator"
    ],
    "wof:name":"Metropolitan Security Management Inc.",
    "wof:placetype":"venue"
},
  "geometry": {"coordinates":[-76.77279299999999,38.978179],"type":"Point"}
}