{
  "type": "Feature",
  "properties": {
    "iso:country":"US",
    "sg:address":"11982 Frederick Rd",
    "sg:city":"Ellicott City",
    "sg:classifiers":[
        {
            "category":"Organizations",
            "subcategory":"Religious Organization",
            "type":"Services"
        }
    ],
    "sg:phone":"+1 410 531 2854",
    "sg:postcode":"21042",
    "sg:province":"MD",
    "sg:tags":[
        "church"
    ],
    "wof:name":"First Macedonia Baptist Church",
    "wof:placetype":"venue"
},
  "geometry": {"coordinates":[-76.93058499999999,39.29719],"type":"Point"}
}