{
  "type": "Feature",
  "properties": {
    "iso:country":"US",
    "sg:address":"5519 Uppingham St",
    "sg:city":"Chevy Chase",
    "sg:classifiers":[
        {
            "category":"Professional",
            "subcategory":"Lawyer & Legal Services",
            "type":"Services"
        }
    ],
    "sg:phone":"+1 301 656 9256",
    "sg:postcode":"20815",
    "sg:province":"MD",
    "wof:name":"Curzan Myron P Atty",
    "wof:placetype":"venue"
},
  "geometry": {"coordinates":[-77.097042,38.963367],"type":"Point"}
}