{
  "type": "Feature",
  "properties": {
    "addr:full":"8736 Flower Ave Silver Spring MD 20901",
    "addr:housenumber":"8736",
    "addr:postcode":"20901",
    "addr:street":"Flower Ave",
    "iso:country":"US",
    "sg:address":"8736 Flower Ave",
    "sg:city":"Silver Spring",
    "sg:classifiers":[
        {
            "category":"Retail",
            "subcategory":"Laundry & Dry Cleaning",
            "type":"Services"
        }
    ],
    "sg:phone":"+1 301 585 2220",
    "sg:postcode":"20901",
    "sg:province":"MD",
    "sg:tags":[
        "cleaners"
    ],
    "wof:name":"Reliable Cleaners",
    "wof:placetype":"venue"
},
  "geometry": {"coordinates":[-77.00384099999999,38.998936],"type":"Point"}
}