{
  "type": "Feature",
  "properties": {
    "iso:country":"US",
    "sg:address":"3350 Wilkens Ave",
    "sg:city":"Baltimore",
    "sg:classifiers":[
        {
            "category":"Health Services",
            "subcategory":"Doctor",
            "type":"Services"
        }
    ],
    "sg:phone":"+1 410 646 7111",
    "sg:postcode":"21229",
    "sg:province":"MD",
    "sg:tags":[
        "physician",
        "surgeon"
    ],
    "wof:name":"Salvador Papa MD",
    "wof:placetype":"venue"
},
  "geometry": {"coordinates":[-76.672641,39.273416],"type":"Point"}
}