{
  "type": "Feature",
  "properties": {
    "iso:country":"US",
    "sg:address":"1630 Bank St",
    "sg:city":"Baltimore",
    "sg:classifiers":[
        {
            "category":"Organizations",
            "subcategory":"Religious Organization",
            "type":"Services"
        }
    ],
    "sg:phone":"+1 410 276 1660",
    "sg:postcode":"21231",
    "sg:province":"MD",
    "wof:name":"Baltimore Hspanc Mnstry",
    "wof:placetype":"venue"
},
  "geometry": {"coordinates":[-76.59368600000001,39.286681],"type":"Point"}
}