{
  "type": "Feature",
  "properties": {
    "addr:full":"5623 Reisterstown Rd Baltimore MD 21215",
    "addr:housenumber":"5623",
    "addr:postcode":"21215",
    "addr:street":"Reisterstown Rd",
    "iso:country":"US",
    "sg:address":"5623 Reisterstown Rd",
    "sg:city":"Baltimore",
    "sg:classifiers":[
        {
            "category":"Personal",
            "subcategory":"Beauty Salon",
            "type":"Services"
        }
    ],
    "sg:phone":"+1 410 764 1611",
    "sg:postcode":"21215",
    "sg:province":"MD",
    "wof:name":"Quality Hair Braiding",
    "wof:placetype":"venue"
},
  "geometry": {"coordinates":[-76.69256300000001,39.349361],"type":"Point"}
}