{
  "type": "Feature",
  "properties": {
    "iso:country":"US",
    "sg:address":"12164 Tech Rd",
    "sg:city":"Silver Spring",
    "sg:classifiers":[
        {
            "category":"Banks & Credit Unions",
            "subcategory":"Bank",
            "type":"Services"
        }
    ],
    "sg:phone":"+1 301 755 2001",
    "sg:postcode":"20904",
    "sg:province":"MD",
    "wof:name":"Secu Credit Union",
    "wof:placetype":"venue"
},
  "geometry": {"coordinates":[-76.971129,39.050909],"type":"Point"}
}