{
  "type": "Feature",
  "properties": {
    "iso:country":"US",
    "sg:address":"3700 7 Mile Ln",
    "sg:city":"Pikesville",
    "sg:classifiers":[
        {
            "category":"Real Estate",
            "subcategory":"Real Estate Operator",
            "type":"Services"
        }
    ],
    "sg:phone":"+1 410 764 2500",
    "sg:postcode":"21208",
    "sg:province":"MD",
    "sg:tags":[
        "apartment"
    ],
    "wof:name":"Park Newport Mid-Rise Apts",
    "wof:placetype":"venue"
},
  "geometry": {"coordinates":[-76.709,39.366299],"type":"Point"}
}