{
  "type": "Feature",
  "properties": {
    "addr:full":"101 Chestnut St Gaithersburg MD 20877",
    "addr:housenumber":"101",
    "addr:postcode":"20877",
    "addr:street":"Chestnut St",
    "iso:country":"US",
    "sg:address":"101 Chestnut St",
    "sg:city":"Gaithersburg",
    "sg:classifiers":[
        {
            "category":"Real Estate",
            "subcategory":"Real Estate Agent",
            "type":"Services"
        }
    ],
    "sg:phone":"+1 301 948 2929",
    "sg:postcode":"20877",
    "sg:province":"MD",
    "sg:tags":[
        "management"
    ],
    "sg:website":"www.whetstonecompany.com",
    "wof:name":"Whetstone Co",
    "wof:placetype":"venue"
},
  "geometry": {"coordinates":[-77.204948,39.140102],"type":"Point"}
}