{
  "type": "Feature",
  "properties": {
    "iso:country":"US",
    "sg:address":"7742 Lake Shore Dr",
    "sg:city":"Owings",
    "sg:classifiers":[
        {
            "category":"Banks & Credit Unions",
            "subcategory":"Investment Brokerage",
            "type":"Services"
        }
    ],
    "sg:phone":"+1 410 286 9296",
    "sg:postcode":"20736",
    "sg:province":"MD",
    "sg:tags":[
        "security"
    ],
    "wof:name":"Raymond James Financial Svc",
    "wof:placetype":"venue"
},
  "geometry": {"coordinates":[-76.62394,38.688857],"type":"Point"}
}