{
  "type": "Feature",
  "properties": {
    "addr:full":"8131 Ritchie Hwy Ste K Pasadena MD 21122",
    "addr:housenumber":"8131",
    "addr:postcode":"21122",
    "addr:street":"Ritchie Hwy Ste K",
    "iso:country":"US",
    "sg:address":"8131 Ritchie Hwy Ste K",
    "sg:city":"Pasadena",
    "sg:classifiers":[
        {
            "category":"Personal",
            "subcategory":"Massage",
            "type":"Services"
        },
        {
            "category":"Health Services",
            "subcategory":"Hospital",
            "type":"Services"
        },
        {
            "category":"Health Services",
            "subcategory":"Health Practitioner",
            "type":"Services"
        },
        {
            "category":"Health Services",
            "subcategory":"Clinic",
            "type":"Services"
        }
    ],
    "sg:phone":"+1 410 647 2230",
    "sg:postcode":"21122",
    "sg:province":"MD",
    "sg:tags":[
        "therapist",
        "therapy",
        "treatment",
        "sleep",
        "disorders-information",
        "physical"
    ],
    "wof:name":"Massage Connection Therapy Center",
    "wof:placetype":"venue"
},
  "geometry": {"coordinates":[-76.58772999999999,39.124062],"type":"Point"}
}