{
  "type": "Feature",
  "properties": {
    "iso:country":"US",
    "sg:address":"18511 Darnestown Rd",
    "sg:city":"Poolesville",
    "sg:classifiers":[
        {
            "category":"Retail",
            "subcategory":"Animal Services",
            "type":"Services"
        }
    ],
    "sg:phone":"+1 301 972 7058",
    "sg:postcode":"20837",
    "sg:province":"MD",
    "wof:name":"Linda Wallaesa",
    "wof:placetype":"venue"
},
  "geometry": {"coordinates":[-77.388986,39.165501],"type":"Point"}
}