{
  "type": "Feature",
  "properties": {
    "addr:full":"20 E Frederick St Walkersville MD 21793",
    "addr:housenumber":"20",
    "addr:postcode":"21793",
    "addr:street":"E Frederick St",
    "iso:country":"US",
    "sg:address":"20 E Frederick St",
    "sg:city":"Walkersville",
    "sg:classifiers":[
        {
            "category":"Restaurant",
            "type":"Food & Drink"
        }
    ],
    "sg:phone":"+1 301 898 3514",
    "sg:postcode":"21793",
    "sg:province":"MD",
    "wof:name":"Mc Donald's",
    "wof:placetype":"venue"
},
  "geometry": {"coordinates":[-77.348299,39.482748],"type":"Point"}
}