{
  "type": "Feature",
  "properties": {
    "iso:country":"US",
    "sg:address":"3530 Southside Ave",
    "sg:city":"Phoenix",
    "sg:classifiers":[
        {
            "category":"Professional",
            "subcategory":"Management & Consulting",
            "type":"Services"
        }
    ],
    "sg:phone":"+1 410 683 4764",
    "sg:postcode":"21131",
    "sg:province":"MD",
    "sg:tags":[
        "business"
    ],
    "wof:name":"Bsr Consulting Inc",
    "wof:placetype":"venue"
},
  "geometry": {"coordinates":[-76.55814100000001,39.522445],"type":"Point"}
}