{
  "type": "Feature",
  "properties": {
    "addr:full":"11339 Columbia Pike Silver Spring MD 20904",
    "addr:housenumber":"11339",
    "addr:postcode":"20904",
    "addr:street":"Columbia Pike",
    "iso:country":"US",
    "sg:address":"11339 Columbia Pike",
    "sg:city":"Silver Spring",
    "sg:classifiers":[
        {
            "category":"Retail",
            "subcategory":"Laundry & Dry Cleaning",
            "type":"Services"
        }
    ],
    "sg:phone":"+1 301 593 2410",
    "sg:postcode":"20904",
    "sg:province":"MD",
    "sg:tags":[
        "cleaners",
        "upholstery"
    ],
    "wof:name":"B & B Furniture Cleaner",
    "wof:placetype":"venue"
},
  "geometry": {"coordinates":[-76.991587,39.04344],"type":"Point"}
}