{
  "type": "Feature",
  "properties": {
    "iso:country":"US",
    "sg:address":"2301 Eastern Ave",
    "sg:city":"Baltimore",
    "sg:classifiers":[
        {
            "category":"Social Services",
            "type":"Services"
        }
    ],
    "sg:phone":"+1 410 522 4296",
    "sg:postcode":"21224",
    "sg:province":"MD",
    "sg:tags":[
        "youth",
        "organization",
        "center"
    ],
    "wof:name":"Ukranian American Youth Assoc",
    "wof:placetype":"venue"
},
  "geometry": {"coordinates":[-76.583648,39.285965],"type":"Point"}
}