{
  "type": "Feature",
  "properties": {
    "addr:full":"57 W Timonium Rd Lutherville MD 21093",
    "addr:housenumber":"57",
    "addr:postcode":"21093",
    "addr:street":"W Timonium Rd",
    "iso:country":"US",
    "sg:address":"57 W Timonium Rd",
    "sg:city":"Lutherville",
    "sg:classifiers":[
        {
            "category":"Building & Trades",
            "subcategory":"Equipment Rental",
            "type":"Services"
        }
    ],
    "sg:phone":"+1 410 683 8963",
    "sg:postcode":"21093",
    "sg:province":"MD",
    "sg:tags":[
        "yard"
    ],
    "wof:name":"Color Tyme",
    "wof:placetype":"venue"
},
  "geometry": {"coordinates":[-76.630076,39.43957],"type":"Point"}
}