{
  "type": "Feature",
  "properties": {
    "iso:country":"US",
    "sg:address":"7195 Troy Hill Dr",
    "sg:city":"Elkridge",
    "sg:classifiers":[
        {
            "category":"Communications",
            "subcategory":"Television Station",
            "type":"Services"
        }
    ],
    "sg:phone":"+1 800 266 2278",
    "sg:postcode":"21075",
    "sg:province":"MD",
    "sg:tags":[
        "satellite",
        "cable"
    ],
    "sg:website":"http://www.comcast.com",
    "wof:name":"Comcast",
    "wof:placetype":"venue"
},
  "geometry": {"coordinates":[-76.75100399999999,39.194675],"type":"Point"}
}