{
  "type": "Feature",
  "properties": {
    "addr:full":"203 N Fruitland Blvd Fruitland MD 21826",
    "addr:housenumber":"203",
    "addr:postcode":"21826",
    "addr:street":"N Fruitland Blvd",
    "iso:country":"US",
    "sg:address":"203 N Fruitland Blvd",
    "sg:city":"Fruitland",
    "sg:classifiers":[
        {
            "category":"Professional",
            "subcategory":"Accounting & Tax Preparation",
            "type":"Services"
        }
    ],
    "sg:phone":"+1 410 742 4748",
    "sg:postcode":"21826",
    "sg:province":"MD",
    "sg:tags":[
        "return",
        "filing"
    ],
    "wof:name":"Truitts Tax Svc",
    "wof:placetype":"venue"
},
  "geometry": {"coordinates":[-75.61837300000001,38.323675],"type":"Point"}
}