{
  "type": "Feature",
  "properties": {
    "addr:full":"4 Autumn Ct Silver Spring MD 20904",
    "addr:housenumber":"4",
    "addr:postcode":"20904",
    "addr:street":"Autumn Ct",
    "iso:country":"US",
    "sg:address":"4 Autumn Ct",
    "sg:city":"Silver Spring",
    "sg:classifiers":[
        {
            "category":"Retail",
            "subcategory":"Repair Shop",
            "type":"Services"
        }
    ],
    "sg:phone":"+1 301 388 3848",
    "sg:postcode":"20904",
    "sg:province":"MD",
    "wof:name":"Buddy Curilla",
    "wof:placetype":"venue"
},
  "geometry": {"coordinates":[-76.998259,39.068231],"type":"Point"}
}