{
  "type": "Feature",
  "properties": {
    "iso:country":"US",
    "sg:address":"1500J Caton Center Dr J",
    "sg:city":"Halethorpe",
    "sg:classifiers":[
        {
            "category":"Real Estate",
            "subcategory":"Real Estate Services",
            "type":"Services"
        },
        {
            "category":"Real Estate",
            "subcategory":"Real Estate Agent",
            "type":"Services"
        }
    ],
    "sg:phone":"+1 410 737 4330",
    "sg:postcode":"21227",
    "sg:province":"MD",
    "sg:tags":[
        "buyer",
        "broker"
    ],
    "wof:name":"Ultra Graphics, Incorporated",
    "wof:placetype":"venue"
},
  "geometry": {"coordinates":[-76.67852000000001,39.257],"type":"Point"}
}