{
  "type": "Feature",
  "properties": {
    "iso:country":"US",
    "sg:address":"31 Hopkins Plz Ste 430B",
    "sg:city":"Baltimore",
    "sg:classifiers":[
        {
            "category":"Government",
            "subcategory":"Office",
            "type":"Public Place"
        }
    ],
    "sg:phone":"+1 410 962 2676",
    "sg:postcode":"21201",
    "sg:province":"MD",
    "sg:tags":[
        "government-united",
        "state"
    ],
    "sg:website":"http://www.stl.waldinger.com",
    "wof:name":"Apprenticeship And Training",
    "wof:placetype":"venue"
},
  "geometry": {"coordinates":[-76.61634100000001,39.289295],"type":"Point"}
}