{
  "type": "Feature",
  "properties": {
    "iso:country":"US",
    "sg:address":"2 Arnold Rd",
    "sg:city":"Arnold",
    "sg:classifiers":[
        {
            "category":"Banks & Credit Unions",
            "subcategory":"Bank",
            "type":"Services"
        }
    ],
    "sg:phone":"+1 410 757 5550",
    "sg:postcode":"21012",
    "sg:province":"MD",
    "wof:name":"B B & T",
    "wof:placetype":"venue"
},
  "geometry": {"coordinates":[-76.504042,39.029047],"type":"Point"}
}