{
  "type": "Feature",
  "properties": {
    "iso:country":"US",
    "sg:address":"301 Game Creek Dr",
    "sg:city":"Rockville",
    "sg:classifiers":[
        {
            "category":"Banks & Credit Unions",
            "subcategory":"Investment Brokerage",
            "type":"Services"
        }
    ],
    "sg:phone":"+1 301 515 7777",
    "sg:postcode":"20850",
    "sg:province":"MD",
    "sg:tags":[
        "consultant",
        "financing"
    ],
    "wof:name":"ACC Mortgage",
    "wof:placetype":"venue"
},
  "geometry": {"coordinates":[-77.169868,39.108165],"type":"Point"}
}