{
  "type": "Feature",
  "properties": {
    "addr:full":"18540 Woodfield Rd Gaithersburg MD 20879",
    "addr:housenumber":"18540",
    "addr:postcode":"20879",
    "addr:street":"Woodfield Rd",
    "iso:country":"US",
    "sg:address":"18540 Woodfield Rd",
    "sg:city":"Gaithersburg",
    "sg:classifiers":[
        {
            "category":"Retail",
            "subcategory":"Auto Rental",
            "type":"Services"
        }
    ],
    "sg:phone":"+1 301 948 8188",
    "sg:postcode":"20879",
    "sg:province":"MD",
    "sg:tags":[
        "renting",
        "automobile"
    ],
    "wof:name":"Enterprise Rent-A-Car",
    "wof:placetype":"venue"
},
  "geometry": {"coordinates":[-77.159661,39.160068],"type":"Point"}
}