{
  "type": "Feature",
  "properties": {
    "addr:full":"16211 Wishard Rd Hagerstown MD 21740",
    "addr:housenumber":"16211",
    "addr:postcode":"21740",
    "addr:street":"Wishard Rd",
    "iso:country":"US",
    "sg:address":"16211 Wishard Rd",
    "sg:city":"Hagerstown",
    "sg:classifiers":[
        {
            "category":"Professional",
            "subcategory":"Business Services",
            "type":"Services"
        }
    ],
    "sg:phone":"+1 301 992 3910",
    "sg:postcode":"21740",
    "sg:province":"MD",
    "sg:tags":[
        "organizing",
        "services-household"
    ],
    "wof:name":"Management Of Successful Teams, Most Company",
    "wof:placetype":"venue"
},
  "geometry": {"coordinates":[-77.80525900000001,39.718922],"type":"Point"}
}