{
  "type": "Feature",
  "properties": {
    "addr:full":"4210 47th St Bladensburg MD 20710",
    "addr:housenumber":"4210",
    "addr:postcode":"20710",
    "addr:street":"47Th St",
    "iso:country":"US",
    "sg:address":"4210 47th St",
    "sg:city":"Bladensburg",
    "sg:classifiers":[
        {
            "category":"Retail",
            "subcategory":"Auto Repair",
            "type":"Services"
        }
    ],
    "sg:phone":"+1 301 277 3066",
    "sg:postcode":"20710",
    "sg:province":"MD",
    "sg:tags":[
        "exchanging",
        "engine"
    ],
    "sg:website":"www.enginepro.com",
    "wof:name":"Engines & Components Inc",
    "wof:placetype":"venue"
},
  "geometry": {"coordinates":[-76.93813900000001,38.940008],"type":"Point"}
}