{
  "type": "Feature",
  "properties": {
    "iso:country":"US",
    "sg:address":"804 Mockingbird Ln",
    "sg:city":"Baltimore",
    "sg:classifiers":[
        {
            "category":"Real Estate",
            "subcategory":"Real Estate Operator",
            "type":"Services"
        }
    ],
    "sg:phone":"+1 410 828 4400",
    "sg:postcode":"21286",
    "sg:province":"MD",
    "sg:tags":[
        "building",
        "apartment"
    ],
    "wof:name":"Courthouse Square Apartments",
    "wof:placetype":"venue"
},
  "geometry": {"coordinates":[-76.58470199999999,39.395328],"type":"Point"}
}