{
  "type": "Feature",
  "properties": {
    "iso:country":"US",
    "sg:address":"3500 Dolfield Ave",
    "sg:city":"Baltimore",
    "sg:phone":"+1 410 542 3475",
    "sg:postcode":"21215",
    "sg:province":"MD",
    "sg:website":"http://www.usps.gov",
    "wof:name":"Us Post Office",
    "wof:placetype":"venue"
},
  "geometry": {"coordinates":[-76.673576,39.333961],"type":"Point"}
}