{
  "type": "Feature",
  "properties": {
    "addr:full":"1220 White Marsh Rd Centreville MD 21617",
    "addr:housenumber":"1220",
    "addr:postcode":"21617",
    "addr:street":"White Marsh Rd",
    "iso:country":"US",
    "sg:address":"1220 White Marsh Rd",
    "sg:city":"Centreville",
    "sg:classifiers":[
        {
            "category":"Manufacturing",
            "subcategory":"Buildings",
            "type":"Manufacturing & Wholesale Goods"
        },
        {
            "category":"Building & Trades",
            "subcategory":"Construction",
            "type":"Services"
        }
    ],
    "sg:phone":"+1 410 758 8224",
    "sg:postcode":"21617",
    "sg:province":"MD",
    "sg:tags":[
        "home",
        "builder",
        "contractor"
    ],
    "wof:name":"Walbert Const",
    "wof:placetype":"venue"
},
  "geometry": {"coordinates":[-75.98475500000001,39.07619],"type":"Point"}
}