{
  "type": "Feature",
  "properties": {
    "iso:country":"US",
    "sg:address":"9501 Georgia Ave",
    "sg:city":"Silver Spring",
    "sg:classifiers":[
        {
            "category":"Retail",
            "subcategory":"Auto Repair",
            "type":"Services"
        }
    ],
    "sg:phone":"+1 301 589 7878",
    "sg:postcode":"20910",
    "sg:province":"MD",
    "sg:tags":[
        "wrecker"
    ],
    "wof:name":"Silver Spring Towing",
    "wof:placetype":"venue"
},
  "geometry": {"coordinates":[-77.040949,39.010577],"type":"Point"}
}