{
  "type": "Feature",
  "properties": {
    "addr:full":"7801 York Rd Towson MD 21204",
    "addr:housenumber":"7801",
    "addr:postcode":"21204",
    "addr:street":"York Rd",
    "iso:country":"US",
    "sg:address":"7801 York Rd",
    "sg:city":"Towson",
    "sg:classifiers":[
        {
            "category":"Professional",
            "subcategory":"Management & Consulting",
            "type":"Services"
        }
    ],
    "sg:phone":"+1 410 825 0600",
    "sg:postcode":"21204",
    "sg:province":"MD",
    "sg:tags":[
        "fuel"
    ],
    "wof:name":"Triad Management & Consltng",
    "wof:placetype":"venue"
},
  "geometry": {"coordinates":[-76.61192699999999,39.41372],"type":"Point"}
}