{
  "type": "Feature",
  "properties": {
    "iso:country":"US",
    "sg:address":"14 State Cir",
    "sg:city":"Annapolis",
    "sg:classifiers":[
        {
            "category":"Manufacturing",
            "subcategory":"Printing",
            "type":"Manufacturing & Wholesale Goods"
        }
    ],
    "sg:phone":"+1 410 280 1414",
    "sg:postcode":"21401",
    "sg:province":"MD",
    "sg:tags":[
        "publisher"
    ],
    "sg:website":"www.annapolispublishing.com",
    "wof:name":"Annapolis Publishing Co",
    "wof:placetype":"venue"
},
  "geometry": {"coordinates":[-76.49072700000001,38.978194],"type":"Point"}
}