{
  "type": "Feature",
  "properties": {
    "iso:country":"US",
    "sg:address":"10830 Gilroy Rd",
    "sg:city":"Cockysvl Hnt Vly",
    "sg:classifiers":[
        {
            "category":"Manufacturing",
            "subcategory":"Printing",
            "type":"Manufacturing & Wholesale Goods"
        }
    ],
    "sg:phone":"+1 410 785 1111",
    "sg:postcode":"21031",
    "sg:province":"MD",
    "sg:tags":[
        "printer"
    ],
    "wof:name":"WEBB-Mason Inc",
    "wof:placetype":"venue"
},
  "geometry": {"coordinates":[-76.66257299999999,39.479393],"type":"Point"}
}