{
  "type": "Feature",
  "properties": {
    "addr:full":"6624 Vincent Ln Baltimore MD 21215",
    "addr:housenumber":"6624",
    "addr:postcode":"21215",
    "addr:street":"Vincent Ln",
    "iso:country":"US",
    "sg:address":"6624 Vincent Ln",
    "sg:city":"Baltimore",
    "sg:classifiers":[
        {
            "category":"Wholesale",
            "subcategory":"Painting Supplies",
            "type":"Manufacturing & Wholesale Goods"
        }
    ],
    "sg:phone":"+1 443 306 3595",
    "sg:postcode":"21215",
    "sg:province":"MD",
    "sg:tags":[
        "goods-wholesale",
        "art",
        "manufacturer"
    ],
    "wof:name":"Untohim Novalties",
    "wof:placetype":"venue"
},
  "geometry": {"coordinates":[-76.708027,39.354638],"type":"Point"}
}