{
  "type": "Feature",
  "properties": {
    "addr:full":"16155 Trade Zone Ave Upper Marlboro MD 20774",
    "addr:housenumber":"16155",
    "addr:postcode":"20774",
    "addr:street":"Trade Zone Ave",
    "iso:country":"US",
    "sg:address":"16155 Trade Zone Ave",
    "sg:city":"Upper Marlboro",
    "sg:classifiers":[
        {
            "category":"Wholesale",
            "subcategory":"Hardware",
            "type":"Manufacturing & Wholesale Goods"
        }
    ],
    "sg:phone":"+1 301 390 9575",
    "sg:postcode":"20774",
    "sg:province":"MD",
    "sg:tags":[
        "plumbing",
        "fixture",
        "supply"
    ],
    "wof:name":"Thomas Somerville Co",
    "wof:placetype":"venue"
},
  "geometry": {"coordinates":[-76.726035,38.880432],"type":"Point"}
}