{
  "type": "Feature",
  "properties": {
    "addr:full":"1927 Old Eastern Ave Essex MD 21221",
    "addr:housenumber":"1927",
    "addr:postcode":"21221",
    "addr:street":"Old Eastern Ave",
    "iso:country":"US",
    "sg:address":"1927 Old Eastern Ave",
    "sg:city":"Essex",
    "sg:classifiers":[
        {
            "category":"Professional",
            "subcategory":"Accounting & Tax Preparation",
            "type":"Services"
        }
    ],
    "sg:phone":"+1 410 687 8867",
    "sg:postcode":"21221",
    "sg:province":"MD",
    "sg:tags":[
        "return",
        "filing"
    ],
    "wof:name":"Davis Brothers Tax Svc",
    "wof:placetype":"venue"
},
  "geometry": {"coordinates":[-76.44524,39.324458],"type":"Point"}
}