{
  "type": "Feature",
  "properties": {
    "iso:country":"US",
    "sg:address":"8554 Edgeworth Dr",
    "sg:city":"Capitol Heights",
    "sg:classifiers":[
        {
            "category":"Retail",
            "subcategory":"Auto Repair",
            "type":"Services"
        }
    ],
    "sg:phone":"+1 301 350 0528",
    "sg:postcode":"20743",
    "sg:province":"MD",
    "wof:name":"Midnight Motors",
    "wof:placetype":"venue"
},
  "geometry": {"coordinates":[-76.857597,38.880199],"type":"Point"}
}