{
  "type": "Feature",
  "properties": {
    "addr:full":"3878 Salem Church Rd Jarrettsville MD 21084",
    "addr:housenumber":"3878",
    "addr:postcode":"21084",
    "addr:street":"Salem Church Rd",
    "iso:country":"US",
    "sg:address":"3878 Salem Church Rd",
    "sg:city":"Jarrettsville",
    "sg:classifiers":[
        {
            "category":"Organizations",
            "subcategory":"Non-profit Organization",
            "type":"Services"
        }
    ],
    "sg:phone":"+1 410 557 9994",
    "sg:postcode":"21084",
    "sg:province":"MD",
    "wof:name":"Opticians Association-Maryland",
    "wof:placetype":"venue"
},
  "geometry": {"coordinates":[-76.48668000000001,39.61869],"type":"Point"}
}