{
  "type": "Feature",
  "properties": {
    "addr:full":"405 Stemmers Run Rd Ste 2 Essex MD 21221",
    "addr:housenumber":"405",
    "addr:postcode":"21221",
    "addr:street":"Stemmers Run Rd Ste 2",
    "iso:country":"US",
    "sg:address":"405 Stemmers Run Rd Ste 2",
    "sg:city":"Essex",
    "sg:classifiers":[
        {
            "category":"Education",
            "subcategory":"Kindergarten",
            "type":"Public Place"
        }
    ],
    "sg:phone":"+1 410 918 0100",
    "sg:postcode":"21221",
    "sg:province":"MD",
    "sg:tags":[
        "school",
        "driving"
    ],
    "wof:name":"Eagle 1 Driving School",
    "wof:placetype":"venue"
},
  "geometry": {"coordinates":[-76.46019200000001,39.325088],"type":"Point"}
}