{
  "type": "Feature",
  "properties": {
    "addr:full":"540 Seven Trails Dr Aberdeen MD 21001",
    "addr:housenumber":"540",
    "addr:postcode":"21001",
    "addr:street":"Seven Trails Dr",
    "iso:country":"US",
    "sg:address":"540 Seven Trails Dr",
    "sg:city":"Aberdeen",
    "sg:classifiers":[
        {
            "category":"Wholesale",
            "subcategory":"Hardware",
            "type":"Manufacturing & Wholesale Goods"
        }
    ],
    "sg:phone":"+1 410 272 5326",
    "sg:postcode":"21001",
    "sg:province":"MD",
    "wof:name":"Hafele America",
    "wof:placetype":"venue"
},
  "geometry": {"coordinates":[-76.22103,39.490026],"type":"Point"}
}