{
  "type": "Feature",
  "properties": {
    "iso:country":"US",
    "sg:address":"1846 Pulaski Hwy",
    "sg:city":"Havre De Grace",
    "sg:classifiers":[
        {
            "category":"Wholesale",
            "subcategory":"Electrical",
            "type":"Manufacturing & Wholesale Goods"
        }
    ],
    "sg:phone":"+1 410 836 9222",
    "sg:postcode":"21078",
    "sg:province":"MD",
    "sg:tags":[
        "equipment",
        "electric",
        "supply"
    ],
    "wof:name":"Hagemeyer",
    "wof:placetype":"venue"
},
  "geometry": {"coordinates":[-76.12309999999999,39.531607],"type":"Point"}
}