{
  "type": "Feature",
  "properties": {
    "iso:country":"US",
    "sg:address":"300 W Preston St",
    "sg:city":"Baltimore",
    "sg:classifiers":[
        {
            "category":"Government",
            "subcategory":"Office",
            "type":"Public Place"
        }
    ],
    "sg:phone":"+1 410 333 4720",
    "sg:postcode":"21201",
    "sg:province":"MD",
    "sg:tags":[
        "state"
    ],
    "wof:name":"Real Estate Office",
    "wof:placetype":"venue"
},
  "geometry": {"coordinates":[-76.62161999999999,39.302562],"type":"Point"}
}