{
  "type": "Feature",
  "properties": {
    "addr:full":"5100 Norwood Rd Baltimore MD 21212",
    "addr:housenumber":"5100",
    "addr:postcode":"21212",
    "addr:street":"Norwood Rd",
    "iso:country":"US",
    "sg:address":"5100 Norwood Rd",
    "sg:city":"Baltimore",
    "sg:classifiers":[
        {
            "category":"Education",
            "subcategory":"Vocational School",
            "type":"Public Place"
        }
    ],
    "sg:phone":"+1 410 532 9142",
    "sg:postcode":"21212",
    "sg:province":"MD",
    "sg:tags":[
        "management",
        "business"
    ],
    "wof:name":"Tony Melanson",
    "wof:placetype":"venue"
},
  "geometry": {"coordinates":[-76.612801,39.349869],"type":"Point"}
}