{
  "type": "Feature",
  "properties": {
    "iso:country":"US",
    "sg:address":"7700 Landover Rd",
    "sg:city":"Hyattsville",
    "sg:classifiers":[
        {
            "category":"Banks & Credit Unions",
            "subcategory":"Bank",
            "type":"Services"
        }
    ],
    "sg:phone":"+1 301 650 1013",
    "sg:postcode":"20785",
    "sg:province":"MD",
    "sg:website":"www.wachovia.com",
    "wof:name":"Wachovia",
    "wof:placetype":"venue"
},
  "geometry": {"coordinates":[-76.882966,38.927191],"type":"Point"}
}