{
  "type": "Feature",
  "properties": {
    "addr:full":"19011 Noble Oak Dr Germantown MD 20874",
    "addr:housenumber":"19011",
    "addr:postcode":"20874",
    "addr:street":"Noble Oak Dr",
    "iso:country":"US",
    "sg:address":"19011 Noble Oak Dr",
    "sg:city":"Germantown",
    "sg:classifiers":[
        {
            "category":"Health Services",
            "subcategory":"Health Practitioner",
            "type":"Services"
        }
    ],
    "sg:phone":"+1 240 361 0497",
    "sg:postcode":"20874",
    "sg:province":"MD",
    "sg:tags":[
        "acupuncture"
    ],
    "wof:name":"Acupunture & Yoga Ctr",
    "wof:placetype":"venue"
},
  "geometry": {"coordinates":[-77.274295,39.165272],"type":"Point"}
}