{
  "type": "Feature",
  "properties": {
    "addr:full":"780 Sunny Chapel Rd Odenton MD 21113",
    "addr:housenumber":"780",
    "addr:postcode":"21113",
    "addr:street":"Sunny Chapel Rd",
    "iso:country":"US",
    "sg:address":"780 Sunny Chapel Rd",
    "sg:city":"Odenton",
    "sg:classifiers":[
        {
            "category":"Shopping",
            "type":"Retail Goods"
        }
    ],
    "sg:phone":"+1 443 623 6782",
    "sg:postcode":"21113",
    "sg:province":"MD",
    "sg:tags":[
        "merchandise"
    ],
    "wof:name":"Carribean Sno",
    "wof:placetype":"venue"
},
  "geometry": {"coordinates":[-76.699113,39.060169],"type":"Point"}
}