{
  "type": "Feature",
  "properties": {
    "addr:full":"4340 E West Hwy Bethesda MD 20814",
    "addr:housenumber":"4340 e",
    "addr:postcode":"20814",
    "addr:street":"West Hwy",
    "iso:country":"US",
    "sg:address":"4340 E West Hwy",
    "sg:city":"Bethesda",
    "sg:classifiers":[
        {
            "category":"Professional",
            "subcategory":"Research",
            "type":"Services"
        }
    ],
    "sg:phone":"+1 301 986 9800",
    "sg:postcode":"20814",
    "sg:province":"MD",
    "sg:tags":[
        "environmental",
        "ecological"
    ],
    "wof:name":"Environmental Restoration",
    "wof:placetype":"venue"
},
  "geometry": {"coordinates":[-77.088831,38.985281],"type":"Point"}
}