{
  "type": "Feature",
  "properties": {
    "iso:country":"US",
    "sg:address":"16004 Shady Grove Rd",
    "sg:city":"Gaithersburg",
    "sg:classifiers":[
        {
            "category":"Fast Food",
            "type":"Food & Drink"
        },
        {
            "category":"Restaurant",
            "type":"Food & Drink"
        }
    ],
    "sg:phone":"+1 301 840 0988",
    "sg:postcode":"20877",
    "sg:province":"MD",
    "sg:tags":[
        "american",
        "hot",
        "hamburger",
        "dog"
    ],
    "sg:website":"http://www.bk.com",
    "wof:name":"Burger King",
    "wof:placetype":"venue"
},
  "geometry": {"coordinates":[-77.182419,39.119266],"type":"Point"}
}