{
  "type": "Feature",
  "properties": {
    "addr:full":"1004 Ripley St Silver Spring MD 20910",
    "addr:housenumber":"1004",
    "addr:postcode":"20910",
    "addr:street":"Ripley St",
    "iso:country":"US",
    "sg:address":"1004 Ripley St",
    "sg:city":"Silver Spring",
    "sg:classifiers":[
        {
            "category":"Retail",
            "subcategory":"Auto Repair",
            "type":"Services"
        }
    ],
    "sg:phone":"+1 301 588 2942",
    "sg:postcode":"20910",
    "sg:province":"MD",
    "sg:tags":[
        "body"
    ],
    "wof:name":"Wilson Auto Body",
    "wof:placetype":"venue"
},
  "geometry": {"coordinates":[-77.02665500000001,38.992405],"type":"Point"}
}