{
  "type": "Feature",
  "properties": {
    "iso:country":"US",
    "sg:address":"19636 Club House Rd",
    "sg:city":"Montgomery Village",
    "sg:classifiers":[
        {
            "category":"Professional",
            "subcategory":"Computer Services",
            "type":"Services"
        }
    ],
    "sg:phone":"+1 301 948 1345",
    "sg:postcode":"20886",
    "sg:province":"MD",
    "sg:tags":[
        "development",
        "software"
    ],
    "wof:name":"Syngistix Inc",
    "wof:placetype":"venue"
},
  "geometry": {"coordinates":[-77.208079,39.174067],"type":"Point"}
}