{
  "type": "Feature",
  "properties": {
    "addr:full":"114 W Bel Air Ave Aberdeen MD 21001",
    "addr:housenumber":"114",
    "addr:postcode":"21001",
    "addr:street":"W Bel Air Ave",
    "iso:country":"US",
    "sg:address":"114 W Bel Air Ave",
    "sg:city":"Aberdeen",
    "sg:classifiers":[
        {
            "category":"Personal",
            "subcategory":"Beauty Salon",
            "type":"Services"
        }
    ],
    "sg:phone":"+1 410 273 9558",
    "sg:postcode":"21001",
    "sg:province":"MD",
    "wof:name":"Hair Central",
    "wof:placetype":"venue"
},
  "geometry": {"coordinates":[-76.16667200000001,39.510311],"type":"Point"}
}