{
  "type": "Feature",
  "properties": {
    "iso:country":"US",
    "sg:address":"5731 Bells Ln",
    "sg:city":"Frederick",
    "sg:classifiers":[
        {
            "category":"Building & Trades",
            "subcategory":"Cleaning & Sanitation",
            "type":"Services"
        }
    ],
    "sg:phone":"+1 301 694 0931",
    "sg:postcode":"21704",
    "sg:province":"MD",
    "sg:tags":[
        "janitor"
    ],
    "wof:name":"Crawford Building Maintenance",
    "wof:placetype":"venue"
},
  "geometry": {"coordinates":[-77.342253,39.393445],"type":"Point"}
}