{
  "type": "Feature",
  "properties": {
    "iso:country":"US",
    "sg:address":"6609 Warrens Way",
    "sg:city":"Elkridge",
    "sg:classifiers":[
        {
            "category":"Banks & Credit Unions",
            "subcategory":"Bank",
            "type":"Services"
        }
    ],
    "sg:phone":"+1 410 799 1070",
    "sg:postcode":"21075",
    "sg:province":"MD",
    "sg:tags":[
        "loan",
        "real estate"
    ],
    "wof:name":"Elkridge Mortgage Corp",
    "wof:placetype":"venue"
},
  "geometry": {"coordinates":[-76.74152100000001,39.203621],"type":"Point"}
}