{
  "type": "Feature",
  "properties": {
    "addr:full":"2846 Abbey Manor Cir Brookeville MD 20833",
    "addr:housenumber":"2846",
    "addr:postcode":"20833",
    "addr:street":"Abbey Manor Cir",
    "iso:country":"US",
    "sg:address":"2846 Abbey Manor Cir",
    "sg:city":"Brookeville",
    "sg:classifiers":[
        {
            "category":"Professional",
            "subcategory":"Management & Consulting",
            "type":"Services"
        }
    ],
    "sg:phone":"+1 301 260 0150",
    "sg:postcode":"20833",
    "sg:province":"MD",
    "sg:tags":[
        "public",
        "relations"
    ],
    "wof:name":"Approved Promotions",
    "wof:placetype":"venue"
},
  "geometry": {"coordinates":[-77.05887199999999,39.165109],"type":"Point"}
}