{
  "type": "Feature",
  "properties": {
    "iso:country":"US",
    "sg:address":"118 N Cross St",
    "sg:city":"Chestertown",
    "sg:classifiers":[
        {
            "category":"Government",
            "subcategory":"Office",
            "type":"Public Place"
        }
    ],
    "sg:phone":"+1 410 810 2673",
    "sg:postcode":"21620",
    "sg:province":"MD",
    "wof:name":"Local Management Board",
    "wof:placetype":"venue"
},
  "geometry": {"coordinates":[-76.06632999999999,39.209279],"type":"Point"}
}