{
  "type": "Feature",
  "properties": {
    "iso:country":"US",
    "sg:address":"106 N Talbot St",
    "sg:city":"St Michaels",
    "sg:classifiers":[
        {
            "category":"Restaurant",
            "type":"Food & Drink"
        }
    ],
    "sg:phone":"+1 410 745 5416",
    "sg:postcode":"21663",
    "sg:province":"MD",
    "sg:tags":[
        "shop",
        "fountain",
        "soda"
    ],
    "wof:name":"Justine's Ice Cream Parlor",
    "wof:placetype":"venue"
},
  "geometry": {"coordinates":[-76.224475,38.786723],"type":"Point"}
}