{
  "type": "Feature",
  "properties": {
    "iso:country":"US",
    "sg:address":"615 N Wolfe St",
    "sg:city":"Baltimore",
    "sg:classifiers":[
        {
            "category":"Professional",
            "subcategory":"Research",
            "type":"Services"
        }
    ],
    "sg:phone":"+1 410 955 8198",
    "sg:postcode":"21205",
    "sg:province":"MD",
    "sg:tags":[
        "trail",
        "clinical"
    ],
    "wof:name":"Curtis Meinert",
    "wof:placetype":"venue"
},
  "geometry": {"coordinates":[-76.590793,39.29837],"type":"Point"}
}