{
  "type": "Feature",
  "properties": {
    "addr:full":"35 N Centre St Cumberland MD 21502",
    "addr:housenumber":"35",
    "addr:postcode":"21502",
    "addr:street":"N Centre St",
    "iso:country":"US",
    "sg:address":"35 N Centre St",
    "sg:city":"Cumberland",
    "sg:classifiers":[
        {
            "category":"Fast Food",
            "type":"Food & Drink"
        },
        {
            "category":"Restaurant",
            "type":"Food & Drink"
        }
    ],
    "sg:phone":"+1 301 876 9244",
    "sg:postcode":"21502",
    "sg:province":"MD",
    "sg:tags":[
        "take"
    ],
    "wof:name":"El Canelo",
    "wof:placetype":"venue"
},
  "geometry": {"coordinates":[-78.761779,39.652475],"type":"Point"}
}