{
  "type": "Feature",
  "properties": {
    "iso:country":"US",
    "sg:address":"4827 Fairmont Ave",
    "sg:city":"Bethesda",
    "sg:classifiers":[
        {
            "category":"Fast Food",
            "type":"Food & Drink"
        },
        {
            "category":"Restaurant",
            "type":"Food & Drink"
        }
    ],
    "sg:phone":"+1 301 358 6137",
    "sg:postcode":"20814",
    "sg:province":"MD",
    "sg:tags":[
        "burger",
        "hot",
        "hamburger",
        "dog"
    ],
    "sg:website":"burgerjointdc.com",
    "wof:name":"The Burger Joint",
    "wof:placetype":"venue"
},
  "geometry": {"coordinates":[-77.096175,38.988859],"type":"Point"}
}