{
  "type": "Feature",
  "properties": {
    "addr:full":"5956 Turnabout Ln Columbia MD 21044",
    "addr:housenumber":"5956",
    "addr:postcode":"21044",
    "addr:street":"Turnabout Ln",
    "iso:country":"US",
    "sg:address":"5956 Turnabout Ln",
    "sg:city":"Columbia",
    "sg:classifiers":[
        {
            "category":"Professional",
            "type":"Services"
        }
    ],
    "sg:phone":"+1 410 884 9485",
    "sg:postcode":"21044",
    "sg:province":"MD",
    "wof:name":"Eco Trans",
    "wof:placetype":"venue"
},
  "geometry": {"coordinates":[-76.882008,39.217825],"type":"Point"}
}