{
  "type": "Feature",
  "properties": {
    "iso:country":"US",
    "sg:address":"7218 Huckleberry Ct",
    "sg:city":"Clinton",
    "sg:classifiers":[
        {
            "category":"Professional",
            "subcategory":"Management & Consulting",
            "type":"Services"
        }
    ],
    "sg:phone":"+1 301 221 0939",
    "sg:postcode":"20735",
    "sg:province":"MD",
    "sg:tags":[
        "admin",
        "financial"
    ],
    "wof:name":"SBS Services LLC",
    "wof:placetype":"venue"
},
  "geometry": {"coordinates":[-76.884272,38.749996],"type":"Point"}
}