{
  "type": "Feature",
  "properties": {
    "addr:full":"15790 Livingston Rd Ste B Accokeek MD 20607",
    "addr:housenumber":"15790",
    "addr:postcode":"20607",
    "addr:street":"Livingston Rd Ste B",
    "iso:country":"US",
    "sg:address":"15790 Livingston Rd Ste B",
    "sg:city":"Accokeek",
    "sg:classifiers":[
        {
            "category":"Retail",
            "subcategory":"Laundry & Dry Cleaning",
            "type":"Services"
        }
    ],
    "sg:phone":"+1 301 203 1188",
    "sg:postcode":"20607",
    "sg:province":"MD",
    "sg:tags":[
        "cleaner"
    ],
    "wof:name":"A Good Cleaners",
    "wof:placetype":"venue"
},
  "geometry": {"coordinates":[-77.009879,38.669931],"type":"Point"}
}