{
  "type": "Feature",
  "properties": {
    "iso:country":"US",
    "sg:address":"2145 Crain Hwy",
    "sg:city":"Waldorf",
    "sg:classifiers":[
        {
            "category":"Food & Beverages",
            "subcategory":"Groceries & Convenience Stores",
            "type":"Retail Goods"
        }
    ],
    "sg:phone":"+1 301 705 5258",
    "sg:postcode":"20601",
    "sg:province":"MD",
    "wof:name":"Xtramart Convenience",
    "wof:placetype":"venue"
},
  "geometry": {"coordinates":[-76.880105,38.653242],"type":"Point"}
}