{
  "type": "Feature",
  "properties": {
    "iso:country":"US",
    "sg:address":"1220 Caraway Ct",
    "sg:city":"Upper Marlboro",
    "sg:classifiers":[
        {
            "category":"Manufacturing",
            "subcategory":"Glass & Minerals",
            "type":"Manufacturing & Wholesale Goods"
        }
    ],
    "sg:phone":"+1 301 925 8444",
    "sg:postcode":"20774",
    "sg:province":"MD",
    "sg:tags":[
        "product",
        "marble"
    ],
    "wof:name":"Dal-Tile",
    "wof:placetype":"venue"
},
  "geometry": {"coordinates":[-76.845028,38.908304],"type":"Point"}
}