{
  "type": "Feature",
  "properties": {
    "iso:country":"US",
    "sg:address":"4815 Prince Georges Ave",
    "sg:city":"Beltsville",
    "sg:classifiers":[
        {
            "category":"Real Estate",
            "subcategory":"Architect",
            "type":"Services"
        }
    ],
    "sg:phone":"+1 301 937 7500",
    "sg:postcode":"20705",
    "sg:province":"MD",
    "wof:name":"Bethel Design Construct",
    "wof:placetype":"venue"
},
  "geometry": {"coordinates":[-76.909862,39.039807],"type":"Point"}
}