{
  "type": "Feature",
  "properties": {
    "addr:full":"13312 Laurel Bowie Rd Laurel MD 20708",
    "addr:housenumber":"13312",
    "addr:postcode":"20708",
    "addr:street":"Laurel Bowie Rd",
    "iso:country":"US",
    "sg:address":"13312 Laurel Bowie Rd",
    "sg:city":"Laurel",
    "sg:classifiers":[
        {
            "category":"Professional",
            "subcategory":"Employment Agencies",
            "type":"Services"
        }
    ],
    "sg:phone":"+1 301 483 8002",
    "sg:postcode":"20708",
    "sg:province":"MD",
    "sg:website":"www.laborready.com",
    "wof:name":"Labor Ready",
    "wof:placetype":"venue"
},
  "geometry": {"coordinates":[-76.84597100000001,39.071729],"type":"Point"}
}