{
  "type": "Feature",
  "properties": {
    "addr:full":"2303 Bel Air Rd Fallston MD 21047",
    "addr:housenumber":"2303",
    "addr:postcode":"21047",
    "addr:street":"Bel Air Rd",
    "iso:country":"US",
    "sg:address":"2303 Bel Air Rd",
    "sg:city":"Fallston",
    "sg:classifiers":[
        {
            "category":"Health Services",
            "subcategory":"Doctor",
            "type":"Services"
        },
        {
            "category":"Health Services",
            "subcategory":"Health Practitioner",
            "type":"Services"
        },
        {
            "category":"Health Services",
            "subcategory":"Podiatrist",
            "type":"Services"
        }
    ],
    "sg:phone":"+1 410 929 6997",
    "sg:postcode":"21047",
    "sg:province":"MD",
    "sg:tags":[
        "physician",
        "injury",
        "pediatrics",
        "surgeons",
        "medicine",
        "treatment",
        "pediatrics-orthopedics",
        "dermatology",
        "surgeon",
        "sport"
    ],
    "sg:website":"http://www.yext.com/p/superpages/honeygo-podiatry-dr-edward-orman-fallston-maryland.html",
    "wof:name":"Honeygo Podiatry Dr. Edward Orman",
    "wof:placetype":"venue"
},
  "geometry": {"coordinates":[-76.391952,39.493908],"type":"Point"}
}