{
  "type": "Feature",
  "properties": {
    "iso:country":"US",
    "sg:address":"20301 Benevola Church Rd",
    "sg:city":"Boonsboro",
    "sg:classifiers":[
        {
            "category":"Manufacturing",
            "subcategory":"Glass & Minerals",
            "type":"Manufacturing & Wholesale Goods"
        }
    ],
    "sg:phone":"+1 301 739 6406",
    "sg:postcode":"21713",
    "sg:province":"MD",
    "sg:tags":[
        "stone",
        "cut",
        "product"
    ],
    "wof:name":"Martin Marietta Aggregates",
    "wof:placetype":"venue"
},
  "geometry": {"coordinates":[-77.66033,39.55085],"type":"Point"}
}