{
  "type": "Feature",
  "properties": {
    "iso:country":"US",
    "sg:address":"4605 Belair Rd",
    "sg:city":"Baltimore",
    "sg:classifiers":[
        {
            "category":"Social Services",
            "subcategory":"Child Care",
            "type":"Services"
        }
    ],
    "sg:phone":"+1 410 246 1236",
    "sg:postcode":"21206",
    "sg:province":"MD",
    "sg:tags":[
        "nursery",
        "day"
    ],
    "wof:name":"Morgan State Headstart",
    "wof:placetype":"venue"
},
  "geometry": {"coordinates":[-76.5612,39.331408],"type":"Point"}
}