{
  "type": "Feature",
  "properties": {
    "iso:country":"US",
    "sg:address":"12401 Bedford Rd NE",
    "sg:city":"Cumberland",
    "sg:classifiers":[
        {
            "category":"Professional",
            "subcategory":"Lawyer & Legal Services",
            "type":"Services"
        }
    ],
    "sg:phone":"+1 301 724 0459",
    "sg:postcode":"21502",
    "sg:province":"MD",
    "sg:tags":[
        "plan"
    ],
    "wof:name":"Charles Mcelfish",
    "wof:placetype":"venue"
},
  "geometry": {"coordinates":[-78.72569300000001,39.69392],"type":"Point"}
}