{
  "type": "Feature",
  "properties": {
    "addr:full":"5403 East Dr Halethorpe MD 21227",
    "addr:housenumber":"5403",
    "addr:postcode":"21227",
    "addr:street":"East Dr",
    "iso:country":"US",
    "sg:address":"5403 East Dr",
    "sg:city":"Halethorpe",
    "sg:classifiers":[
        {
            "category":"Restaurant",
            "type":"Food & Drink"
        },
        {
            "category":"Ice Cream",
            "type":"Food & Drink"
        }
    ],
    "sg:phone":"+1 410 491 1624",
    "sg:postcode":"21227",
    "sg:province":"MD",
    "sg:tags":[
        "frozen",
        "dessert"
    ],
    "wof:name":"Brain Freeze One",
    "wof:placetype":"venue"
},
  "geometry": {"coordinates":[-76.69360500000001,39.2492],"type":"Point"}
}