{
  "type": "Feature",
  "properties": {
    "iso:country":"US",
    "sg:address":"301 Saint Paul St 421",
    "sg:city":"Baltimore",
    "sg:classifiers":[
        {
            "category":"Health Services",
            "subcategory":"Doctor",
            "type":"Services"
        }
    ],
    "sg:phone":"+1 410 332 9123",
    "sg:postcode":"21202",
    "sg:province":"MD",
    "sg:tags":[
        "physician",
        "surgeon"
    ],
    "wof:name":"Caren Craig",
    "wof:placetype":"venue"
},
  "geometry": {"coordinates":[-76.614059,39.292439],"type":"Point"}
}