{
  "type": "Feature",
  "properties": {
    "addr:full":"650 Marley Run Huntingtown MD 20639",
    "addr:housenumber":"650",
    "addr:postcode":"20639",
    "addr:street":"Marley Run",
    "iso:country":"US",
    "sg:address":"650 Marley Run",
    "sg:city":"Huntingtown",
    "sg:classifiers":[
        {
            "category":"Professional",
            "subcategory":"Management & Consulting",
            "type":"Services"
        }
    ],
    "sg:phone":"+1 410 414 7133",
    "sg:postcode":"20639",
    "sg:province":"MD",
    "sg:tags":[
        "consultant",
        "coach",
        "business"
    ],
    "wof:name":"Bittner Consulting",
    "wof:placetype":"venue"
},
  "geometry": {"coordinates":[-76.59495,38.608029],"type":"Point"}
}