{
  "type": "Feature",
  "properties": {
    "addr:full":"13975 Mill Creek Ln Galena MD 21635",
    "addr:housenumber":"13975",
    "addr:postcode":"21635",
    "addr:street":"Mill Creek Ln",
    "iso:country":"US",
    "sg:address":"13975 Mill Creek Ln",
    "sg:city":"Galena",
    "sg:classifiers":[
        {
            "category":"Restaurant",
            "type":"Food & Drink"
        }
    ],
    "sg:phone":"+1 410 648 6805",
    "sg:postcode":"21635",
    "sg:province":"MD",
    "sg:tags":[
        "caterer"
    ],
    "sg:website":"http://www.thegrillmeister.com",
    "wof:name":"Grill Meister",
    "wof:placetype":"venue"
},
  "geometry": {"coordinates":[-75.869759,39.35968],"type":"Point"}
}