{
  "type": "Feature",
  "properties": {
    "addr:full":"23 Stahls Point Rd Baltimore MD 21226",
    "addr:housenumber":"23",
    "addr:postcode":"21226",
    "addr:street":"Stahls Point Rd",
    "iso:country":"US",
    "sg:address":"23 Stahls Point Rd",
    "sg:city":"Baltimore",
    "sg:classifiers":[
        {
            "category":"Professional",
            "subcategory":"Research",
            "type":"Services"
        }
    ],
    "sg:phone":"+1 410 636 3800",
    "sg:postcode":"21226",
    "sg:province":"MD",
    "sg:tags":[
        "environmental",
        "ecological"
    ],
    "wof:name":"IMS Environmental Svc",
    "wof:placetype":"venue"
},
  "geometry": {"coordinates":[-76.581509,39.200606],"type":"Point"}
}