{
  "type": "Feature",
  "properties": {
    "iso:country":"US",
    "sg:address":"1301 N Monroe St",
    "sg:city":"Baltimore",
    "sg:classifiers":[
        {
            "category":"Retail",
            "subcategory":"Car Wash",
            "type":"Services"
        }
    ],
    "sg:phone":"+1 410 814 4707",
    "sg:postcode":"21217",
    "sg:province":"MD",
    "wof:name":"We Do It All",
    "wof:placetype":"venue"
},
  "geometry": {"coordinates":[-76.64778099999999,39.303028],"type":"Point"}
}