{
  "type": "Feature",
  "properties": {
    "iso:country":"US",
    "sg:address":"22840 Three Notch Rd",
    "sg:city":"California",
    "sg:classifiers":[
        {
            "category":"Social Services",
            "subcategory":"Child Care",
            "type":"Services"
        },
        {
            "category":"Education",
            "subcategory":"Preschool",
            "type":"Public Place"
        },
        {
            "category":"Education",
            "subcategory":"School",
            "type":"Public Place"
        }
    ],
    "sg:phone":"+1 301 863 2345",
    "sg:postcode":"20619",
    "sg:province":"MD",
    "sg:tags":[
        "elementary",
        "day"
    ],
    "sg:website":"www.cbchildcare.org",
    "wof:name":"Creative Beginnings Preschool & Daycare",
    "wof:placetype":"venue"
},
  "geometry": {"coordinates":[-76.534302,38.312401],"type":"Point"}
}