{
  "type": "Feature",
  "properties": {
    "iso:country":"US",
    "sg:address":"11744 Central Ave",
    "sg:city":"Waldorf",
    "sg:classifiers":[
        {
            "category":"Retail",
            "subcategory":"Auto Repair",
            "type":"Services"
        }
    ],
    "sg:phone":"+1 301 870 9885",
    "sg:postcode":"20601",
    "sg:province":"MD",
    "sg:tags":[
        "repairing",
        "automobile"
    ],
    "wof:name":"R & R Steering Column Repair",
    "wof:placetype":"venue"
},
  "geometry": {"coordinates":[-76.901488,38.633704],"type":"Point"}
}