{
  "type": "Feature",
  "properties": {
    "addr:full":"12803 Beaverdale Ln Bowie MD 20715",
    "addr:housenumber":"12803",
    "addr:postcode":"20715",
    "addr:street":"Beaverdale Ln",
    "iso:country":"US",
    "sg:address":"12803 Beaverdale Ln",
    "sg:city":"Bowie",
    "sg:classifiers":[
        {
            "category":"Building & Trades",
            "subcategory":"Plumbing",
            "type":"Services"
        }
    ],
    "sg:phone":"+1 301 464 3427",
    "sg:postcode":"20715",
    "sg:province":"MD",
    "sg:tags":[
        "plumbing",
        "contractor"
    ],
    "wof:name":"Diamond Properties",
    "wof:placetype":"venue"
},
  "geometry": {"coordinates":[-76.724379,38.964921],"type":"Point"}
}