{
  "type": "Feature",
  "properties": {
    "iso:country":"US",
    "sg:address":"7814 Telegraph Rd",
    "sg:city":"Severn",
    "sg:classifiers":[
        {
            "category":"Personal",
            "subcategory":"Beauty Salon",
            "type":"Services"
        }
    ],
    "sg:phone":"+1 410 969 6081",
    "sg:postcode":"21144",
    "sg:province":"MD",
    "sg:tags":[
        "shop"
    ],
    "wof:name":"Betty's Coiffeurs",
    "wof:placetype":"venue"
},
  "geometry": {"coordinates":[-76.68498700000001,39.139634],"type":"Point"}
}