{
  "type": "Feature",
  "properties": {
    "iso:country":"US",
    "sg:address":"15915 Indian Hills Ter",
    "sg:city":"Derwood",
    "sg:classifiers":[
        {
            "category":"Communications",
            "type":"Services"
        }
    ],
    "sg:phone":"+1 301 943 3883",
    "sg:postcode":"20855",
    "sg:province":"MD",
    "sg:tags":[
        "editing",
        "video"
    ],
    "wof:name":"Freeburn John",
    "wof:placetype":"venue"
},
  "geometry": {"coordinates":[-77.15331999999999,39.117152],"type":"Point"}
}