{
  "type": "Feature",
  "properties": {
    "iso:country":"US",
    "sg:address":"2 E West St Ste 10",
    "sg:city":"Baltimore",
    "sg:classifiers":[
        {
            "category":"Utilities",
            "subcategory":"Fuel Oil & Lpg",
            "type":"Services"
        }
    ],
    "sg:phone":"+1 410 455 6470",
    "sg:postcode":"21230",
    "sg:province":"MD",
    "sg:tags":[
        "development",
        "exploration",
        "gas"
    ],
    "sg:website":"http://www.hess.com",
    "wof:name":"Hess Corporation",
    "wof:placetype":"venue"
},
  "geometry": {"coordinates":[-76.614304,39.275761],"type":"Point"}
}