{
  "type": "Feature",
  "properties": {
    "addr:full":"9455 Washington Blvd N Laurel MD 20723",
    "addr:housenumber":"9455",
    "addr:postcode":"20723",
    "addr:street":"Washington Blvd N",
    "iso:country":"US",
    "sg:address":"9455 Washington Blvd N",
    "sg:city":"Laurel",
    "sg:classifiers":[
        {
            "category":"Professional",
            "subcategory":"Business Services",
            "type":"Services"
        }
    ],
    "sg:phone":"+1 301 490 1483",
    "sg:postcode":"20723",
    "sg:province":"MD",
    "sg:tags":[
        "record",
        "document"
    ],
    "wof:name":"Iron Mountain",
    "wof:placetype":"venue"
},
  "geometry": {"coordinates":[-76.822361,39.126655],"type":"Point"}
}