{
  "type": "Feature",
  "properties": {
    "iso:country":"US",
    "sg:address":"7401 Surratts Rd",
    "sg:city":"Clinton",
    "sg:classifiers":[
        {
            "category":"Travel",
            "subcategory":"Hotels & Motels",
            "type":"Entertainment"
        },
        {
            "category":"Restaurant",
            "type":"Food & Drink"
        },
        {
            "category":"Retail",
            "subcategory":"Event Space",
            "type":"Services"
        }
    ],
    "sg:phone":"+1 301 856 4500",
    "sg:postcode":"20735",
    "sg:province":"MD",
    "sg:tags":[
        "banquet",
        "hall",
        "reception",
        "facility"
    ],
    "sg:website":"http://www.colonysouth.com",
    "wof:name":"Colony South Hotel & Conference Center",
    "wof:placetype":"venue"
},
  "geometry": {"coordinates":[-76.87814299999999,38.750111],"type":"Point"}
}