{
  "type": "Feature",
  "properties": {
    "iso:country":"US",
    "sg:address":"14017 Notley Rd",
    "sg:city":"Silver Spring",
    "sg:classifiers":[
        {
            "category":"Professional",
            "subcategory":"Accounting & Tax Preparation",
            "type":"Services"
        }
    ],
    "sg:phone":"+1 301 384 0648",
    "sg:postcode":"20904",
    "sg:province":"MD",
    "sg:tags":[
        "return"
    ],
    "wof:name":"Leahy John & Adalia",
    "wof:placetype":"venue"
},
  "geometry": {"coordinates":[-77.013057,39.085916],"type":"Point"}
}