{
  "type": "Feature",
  "properties": {
    "iso:country":"US",
    "sg:address":"3817 Cooper Ln",
    "sg:city":"Hyattsville",
    "sg:classifiers":[
        {
            "category":"Education",
            "subcategory":"School",
            "type":"Public Place"
        }
    ],
    "sg:phone":"+1 301 925 1350",
    "sg:postcode":"20784",
    "sg:province":"MD",
    "sg:tags":[
        "high",
        "middle",
        "elementary"
    ],
    "wof:name":"Prince George's County School District",
    "wof:placetype":"venue"
},
  "geometry": {"coordinates":[-76.900486,38.938371],"type":"Point"}
}