{
  "type": "Feature",
  "properties": {
    "iso:country":"US",
    "sg:address":"248 S Broadway",
    "sg:city":"Baltimore",
    "sg:classifiers":[
        {
            "category":"Food & Beverages",
            "subcategory":"Groceries & Convenience Stores",
            "type":"Retail Goods"
        }
    ],
    "sg:phone":"+1 410 276 1151",
    "sg:postcode":"21231",
    "sg:province":"MD",
    "wof:name":"Broadway Mart",
    "wof:placetype":"venue"
},
  "geometry": {"coordinates":[-76.59393300000001,39.288429],"type":"Point"}
}