{
  "type": "Feature",
  "properties": {
    "addr:full":"10521 Vincent Farm Ln White Marsh MD 21162",
    "addr:housenumber":"10521",
    "addr:postcode":"21162",
    "addr:street":"Vincent Farm Ln",
    "iso:country":"US",
    "sg:address":"10521 Vincent Farm Ln",
    "sg:city":"White Marsh",
    "sg:classifiers":[
        {
            "category":"Building & Trades",
            "subcategory":"Landscaping Services",
            "type":"Services"
        }
    ],
    "sg:phone":"+1 410 335 3326",
    "sg:postcode":"21162",
    "sg:province":"MD",
    "sg:tags":[
        "landscape",
        "contractor"
    ],
    "wof:name":"Creative Containers",
    "wof:placetype":"venue"
},
  "geometry": {"coordinates":[-76.417107,39.37375],"type":"Point"}
}