{
  "type": "Feature",
  "properties": {
    "addr:full":"902 Cutler Ct Waldorf MD 20602",
    "addr:housenumber":"902",
    "addr:postcode":"20602",
    "addr:street":"Cutler Ct",
    "iso:country":"US",
    "sg:address":"902 Cutler Ct",
    "sg:city":"Waldorf",
    "sg:classifiers":[
        {
            "category":"Retail",
            "subcategory":"Repair Shop",
            "type":"Services"
        }
    ],
    "sg:phone":"+1 301 843 2800",
    "sg:postcode":"20602",
    "sg:province":"MD",
    "sg:tags":[
        "printers-equipment",
        "facsimile",
        "supply"
    ],
    "sg:website":"www.cpr-recharge.com",
    "wof:name":"Cpr Recharge",
    "wof:placetype":"venue"
},
  "geometry": {"coordinates":[-76.91122,38.605459],"type":"Point"}
}