{
  "type": "Feature",
  "properties": {
    "iso:country":"US",
    "sg:address":"8492 Baltimore National Pike",
    "sg:city":"Ellicott City",
    "sg:classifiers":[
        {
            "category":"Health Services",
            "subcategory":"Chiropractor",
            "type":"Services"
        }
    ],
    "sg:phone":"+1 410 505 4271",
    "sg:postcode":"21043",
    "sg:province":"MD",
    "sg:website":"www.drsilverston.com",
    "wof:name":"Silverston Family Chiropractic",
    "wof:placetype":"venue"
},
  "geometry": {"coordinates":[-76.806541,39.285204],"type":"Point"}
}