{
  "type": "Feature",
  "properties": {
    "addr:full":"903 Saxon Hill Dr Cockysvl Hnt Vly MD 21030",
    "addr:housenumber":"903",
    "addr:postcode":"21030",
    "addr:street":"Saxon Hill Dr;Hnt Vly",
    "iso:country":"US",
    "sg:address":"903 Saxon Hill Dr",
    "sg:city":"Cockysvl Hnt Vly",
    "sg:classifiers":[
        {
            "category":"Wholesale",
            "subcategory":"Electrical",
            "type":"Manufacturing & Wholesale Goods"
        }
    ],
    "sg:phone":"+1 410 666 1440",
    "sg:postcode":"21030",
    "sg:province":"MD",
    "sg:tags":[
        "control",
        "security",
        "system"
    ],
    "wof:name":"Olde Line Security Ctr",
    "wof:placetype":"venue"
},
  "geometry": {"coordinates":[-76.604865,39.47619],"type":"Point"}
}