{
  "type": "Feature",
  "properties": {
    "iso:country":"US",
    "sg:address":"6909 Coastal Hwy",
    "sg:city":"Ocean City",
    "sg:classifiers":[
        {
            "category":"Restaurant",
            "type":"Food & Drink"
        }
    ],
    "sg:phone":"+1 410 524 7981",
    "sg:postcode":"21842",
    "sg:province":"MD",
    "wof:name":"Dough Roller",
    "wof:placetype":"venue"
},
  "geometry": {"coordinates":[-75.06465799999999,38.390634],"type":"Point"}
}