{
  "type": "Feature",
  "properties": {
    "addr:full":"7105 Crain Hwy Upper Marlboro MD 20772",
    "addr:housenumber":"7105",
    "addr:postcode":"20772",
    "addr:street":"Crain Hwy",
    "iso:country":"US",
    "sg:address":"7105 Crain Hwy",
    "sg:city":"Upper Marlboro",
    "sg:classifiers":[
        {
            "category":"Manufacturing",
            "subcategory":"Printing",
            "type":"Manufacturing & Wholesale Goods"
        }
    ],
    "sg:phone":"+1 301 627 2892",
    "sg:postcode":"20772",
    "sg:province":"MD",
    "sg:tags":[
        "lithographic",
        "c",
        "commercial",
        "typesetting"
    ],
    "wof:name":"Utopia Typesetting",
    "wof:placetype":"venue"
},
  "geometry": {"coordinates":[-76.776837,38.792038],"type":"Point"}
}