{
  "type": "Feature",
  "properties": {
    "addr:full":"20809 Old York Rd Parkton MD 21120",
    "addr:housenumber":"20809",
    "addr:postcode":"21120",
    "addr:street":"Old York Rd",
    "iso:country":"US",
    "sg:address":"20809 Old York Rd",
    "sg:city":"Parkton",
    "sg:classifiers":[
        {
            "category":"Professional",
            "subcategory":"Business Services",
            "type":"Services"
        }
    ],
    "sg:phone":"+1 410 357 9500",
    "sg:postcode":"21120",
    "sg:province":"MD",
    "sg:tags":[
        "interior",
        "consultant",
        "design",
        "decorator"
    ],
    "wof:name":"Coppermine Terrace Interiors",
    "wof:placetype":"venue"
},
  "geometry": {"coordinates":[-76.623266,39.697374],"type":"Point"}
}