{
  "type": "Feature",
  "properties": {
    "addr:full":"8344 Belair Rd Nottingham MD 21236",
    "addr:housenumber":"8344",
    "addr:postcode":"21236",
    "addr:street":"Belair Rd",
    "iso:country":"US",
    "sg:address":"8344 Belair Rd",
    "sg:city":"Nottingham",
    "sg:classifiers":[
        {
            "category":"Insurance",
            "subcategory":"Insurance Agent",
            "type":"Services"
        }
    ],
    "sg:phone":"+1 410 256 5266",
    "sg:postcode":"21236",
    "sg:province":"MD",
    "wof:name":"Bodie & Assoc",
    "wof:placetype":"venue"
},
  "geometry": {"coordinates":[-76.49806,39.38422],"type":"Point"}
}