{
  "type": "Feature",
  "properties": {
    "addr:full":"5272 River Rd Ste 740 Bethesda MD 20816",
    "addr:housenumber":"5272",
    "addr:postcode":"20816",
    "addr:street":"River Rd Ste 740",
    "iso:country":"US",
    "sg:address":"5272 River Rd Ste 740",
    "sg:city":"Bethesda",
    "sg:classifiers":[
        {
            "category":"Real Estate",
            "subcategory":"Real Estate Services",
            "type":"Services"
        }
    ],
    "sg:phone":"+1 301 718 7744",
    "sg:postcode":"20816",
    "sg:province":"MD",
    "sg:tags":[
        "management"
    ],
    "wof:name":"Cpr Management Inc/ Renaissance Assets Inc Jv",
    "wof:placetype":"venue"
},
  "geometry": {"coordinates":[-77.105277,38.96584],"type":"Point"}
}