{
  "type": "Feature",
  "properties": {
    "iso:country":"US",
    "sg:address":"10312 Auto Pl",
    "sg:city":"Hagerstown",
    "sg:classifiers":[
        {
            "category":"Autos & Motor Vehicles",
            "subcategory":"Automobile Sales",
            "type":"Retail Goods"
        }
    ],
    "sg:phone":"+1 301 739 7777",
    "sg:postcode":"21740",
    "sg:province":"MD",
    "sg:tags":[
        "car",
        "dealer"
    ],
    "sg:website":"www.sharrett.com",
    "wof:name":"Sharrett Pontiac Buick GMC",
    "wof:placetype":"venue"
},
  "geometry": {"coordinates":[-77.67830600000001,39.597862],"type":"Point"}
}