{
  "type": "Feature",
  "properties": {
    "addr:full":"8600 Foundry St Savage MD 20763",
    "addr:housenumber":"8600",
    "addr:postcode":"20763",
    "addr:street":"Foundry St",
    "iso:country":"US",
    "sg:address":"8600 Foundry St",
    "sg:city":"Savage",
    "sg:classifiers":[
        {
            "category":"Shopping",
            "subcategory":"Gifts & Souvenirs",
            "type":"Retail Goods"
        }
    ],
    "sg:phone":"+1 301 604 6518",
    "sg:postcode":"20763",
    "sg:province":"MD",
    "sg:tags":[
        "collectible"
    ],
    "wof:name":"Art Craft Collections",
    "wof:placetype":"venue"
},
  "geometry": {"coordinates":[-76.824618,39.133805],"type":"Point"}
}