{
  "type": "Feature",
  "properties": {
    "iso:country":"US",
    "sg:address":"7456 Gumboro Rd",
    "sg:city":"Pittsville",
    "sg:classifiers":[
        {
            "category":"Restaurant",
            "type":"Food & Drink"
        }
    ],
    "sg:phone":"+1 410 835 3577",
    "sg:postcode":"21850",
    "sg:province":"MD",
    "sg:tags":[
        "style",
        "family"
    ],
    "wof:name":"Station 7 Restaurant Inc",
    "wof:placetype":"venue"
},
  "geometry": {"coordinates":[-75.413231,38.395248],"type":"Point"}
}