{
  "type": "Feature",
  "properties": {
    "addr:full":"520 S Conkling St Baltimore MD 21224",
    "addr:housenumber":"520",
    "addr:postcode":"21224",
    "addr:street":"S Conkling St",
    "iso:country":"US",
    "sg:address":"520 S Conkling St",
    "sg:city":"Baltimore",
    "sg:classifiers":[
        {
            "category":"Government",
            "subcategory":"Fire Station",
            "type":"Public Place"
        }
    ],
    "sg:phone":"+1 410 396 9241",
    "sg:postcode":"21224",
    "sg:province":"MD",
    "sg:tags":[
        "consultant",
        "protection"
    ],
    "sg:website":"http://www.bccenter.org",
    "wof:name":"Fire Dept Station 41",
    "wof:placetype":"venue"
},
  "geometry": {"coordinates":[-76.567132,39.286415],"type":"Point"}
}