{
  "type": "Feature",
  "properties": {
    "iso:country":"US",
    "sg:address":"685 W Baltimore St",
    "sg:city":"Baltimore",
    "sg:classifiers":[
        {
            "category":"Health Services",
            "subcategory":"Doctor",
            "type":"Services"
        }
    ],
    "sg:phone":"+1 410 706 5328",
    "sg:postcode":"21223",
    "sg:province":"MD",
    "sg:tags":[
        "physician",
        "surgeon"
    ],
    "wof:name":"University-MD Baltimore Ctr",
    "wof:placetype":"venue"
},
  "geometry": {"coordinates":[-76.624362,39.289125],"type":"Point"}
}