{
  "type": "Feature",
  "properties": {
    "iso:country":"US",
    "sg:address":"216 Dorchester Rd",
    "sg:city":"Stevensville",
    "sg:classifiers":[
        {
            "category":"Building & Trades",
            "subcategory":"Construction",
            "type":"Services"
        }
    ],
    "sg:phone":"+1 410 643 2702",
    "sg:postcode":"21666",
    "sg:province":"MD",
    "sg:tags":[
        "house"
    ],
    "wof:name":"Crutchley Building Larry Contr",
    "wof:placetype":"venue"
},
  "geometry": {"coordinates":[-76.339135,38.885217],"type":"Point"}
}