{
  "type": "Feature",
  "properties": {
    "addr:full":"6110 Executive Blvd Ste 800 Rockville MD 20852",
    "addr:housenumber":"6110",
    "addr:postcode":"20852",
    "addr:street":"Executive Blvd Ste 800",
    "iso:country":"US",
    "sg:address":"6110 Executive Blvd Ste 800",
    "sg:city":"Rockville",
    "sg:classifiers":[
        {
            "category":"Real Estate",
            "subcategory":"Real Estate Operator",
            "type":"Services"
        }
    ],
    "sg:phone":"+1 202 363 3800",
    "sg:postcode":"20852",
    "sg:province":"MD",
    "sg:tags":[
        "apartment"
    ],
    "wof:name":"Writ Building",
    "wof:placetype":"venue"
},
  "geometry": {"coordinates":[-77.12249799999999,39.048698],"type":"Point"}
}