{
  "type": "Feature",
  "properties": {
    "addr:full":"3561 Saint Johns Ln Ellicott City MD 21042",
    "addr:housenumber":"3561",
    "addr:postcode":"21042",
    "addr:street":"Saint Johns Ln",
    "iso:country":"US",
    "sg:address":"3561 Saint Johns Ln",
    "sg:city":"Ellicott City",
    "sg:classifiers":[
        {
            "category":"Education",
            "subcategory":"Vocational School",
            "type":"Public Place"
        }
    ],
    "sg:phone":"+1 410 997 1400",
    "sg:postcode":"21042",
    "sg:province":"MD",
    "sg:tags":[
        "training",
        "computer"
    ],
    "wof:name":"Futurekids",
    "wof:placetype":"venue"
},
  "geometry": {"coordinates":[-76.826373,39.272409],"type":"Point"}
}