{
  "type": "Feature",
  "properties": {
    "addr:full":"12203 Cedarville Rd Brandywine MD 20613",
    "addr:housenumber":"12203",
    "addr:postcode":"20613",
    "addr:street":"Cedarville Rd",
    "iso:country":"US",
    "sg:address":"12203 Cedarville Rd",
    "sg:city":"Brandywine",
    "sg:classifiers":[
        {
            "category":"Building & Trades",
            "subcategory":"Construction",
            "type":"Services"
        }
    ],
    "sg:phone":"+1 301 888 1729",
    "sg:postcode":"20613",
    "sg:province":"MD",
    "sg:tags":[
        "industrial",
        "painting",
        "contractors-commercial",
        "contractor"
    ],
    "wof:name":"J K S Painting",
    "wof:placetype":"venue"
},
  "geometry": {"coordinates":[-76.795329,38.663844],"type":"Point"}
}