{
  "type": "Feature",
  "properties": {
    "iso:country":"US",
    "sg:address":"22 Firstfield Rd",
    "sg:city":"Gaithersburg",
    "sg:classifiers":[
        {
            "category":"Banks & Credit Unions",
            "subcategory":"Bank",
            "type":"Services"
        }
    ],
    "sg:phone":"+1 301 208 8700",
    "sg:postcode":"20878",
    "sg:province":"MD",
    "wof:name":"Provident Bank Of Maryland",
    "wof:placetype":"venue"
},
  "geometry": {"coordinates":[-77.22594700000001,39.135408],"type":"Point"}
}