{
  "type": "Feature",
  "properties": {
    "iso:country":"US",
    "sg:address":"4414 Frankford Ave",
    "sg:city":"Baltimore",
    "sg:classifiers":[
        {
            "category":"Education",
            "subcategory":"School",
            "type":"Public Place"
        }
    ],
    "sg:phone":"+1 410 488 4848",
    "sg:postcode":"21206",
    "sg:province":"MD",
    "sg:tags":[
        "high",
        "middle",
        "elementary"
    ],
    "wof:name":"Mother Mary Lange Catholic School",
    "wof:placetype":"venue"
},
  "geometry": {"coordinates":[-76.549418,39.336133],"type":"Point"}
}