{
  "type": "Feature",
  "properties": {
    "addr:full":"6955 San Tomas Rd Elkridge MD 21075",
    "addr:housenumber":"6955",
    "addr:postcode":"21075",
    "addr:street":"San Tomas Rd",
    "iso:country":"US",
    "sg:address":"6955 San Tomas Rd",
    "sg:city":"Elkridge",
    "sg:classifiers":[
        {
            "category":"Building & Trades",
            "subcategory":"Construction",
            "type":"Services"
        }
    ],
    "sg:phone":"+1 410 796 5000",
    "sg:postcode":"21075",
    "sg:province":"MD",
    "sg:tags":[
        "driveway"
    ],
    "wof:name":"Structural Preservation",
    "wof:placetype":"venue"
},
  "geometry": {"coordinates":[-76.74723,39.186707],"type":"Point"}
}