{
  "type": "Feature",
  "properties": {
    "iso:country":"US",
    "sg:address":"900 Pulaski Hwy",
    "sg:city":"Havre De Grace",
    "sg:classifiers":[
        {
            "category":"Restaurant",
            "type":"Food & Drink"
        }
    ],
    "sg:phone":"+1 410 939 5000",
    "sg:postcode":"21078",
    "sg:province":"MD",
    "sg:tags":[
        "eating"
    ],
    "wof:name":"Domino's Pizza",
    "wof:placetype":"venue"
},
  "geometry": {"coordinates":[-76.10221,39.552127],"type":"Point"}
}