{
  "type": "Feature",
  "properties": {
    "iso:country":"US",
    "sg:address":"124 N Division St",
    "sg:city":"Salisbury",
    "sg:classifiers":[
        {
            "category":"Restaurant",
            "type":"Food & Drink"
        }
    ],
    "sg:phone":"+1 410 546 9991",
    "sg:postcode":"21801",
    "sg:province":"MD",
    "wof:name":"Frankie's Cafe & Grill",
    "wof:placetype":"venue"
},
  "geometry": {"coordinates":[-75.600442,38.366205],"type":"Point"}
}