{
  "type": "Feature",
  "properties": {
    "addr:full":"122 Defense Hwy Annapolis MD 21401",
    "addr:housenumber":"122",
    "addr:postcode":"21401",
    "addr:street":"Defense Hwy",
    "iso:country":"US",
    "sg:address":"122 Defense Hwy",
    "sg:city":"Annapolis",
    "sg:classifiers":[
        {
            "category":"Banks & Credit Unions",
            "subcategory":"Investment Brokerage",
            "type":"Services"
        }
    ],
    "sg:phone":"+1 410 224 9830",
    "sg:postcode":"21401",
    "sg:province":"MD",
    "sg:tags":[
        "consultant",
        "planning",
        "financial"
    ],
    "wof:name":"Walsh & Assoc",
    "wof:placetype":"venue"
},
  "geometry": {"coordinates":[-76.551097,38.985781],"type":"Point"}
}