{
  "type": "Feature",
  "properties": {
    "addr:full":"940 Seton Dr Cumberland MD 21502",
    "addr:housenumber":"940",
    "addr:postcode":"21502",
    "addr:street":"Seton Dr",
    "iso:country":"US",
    "sg:address":"940 Seton Dr",
    "sg:city":"Cumberland",
    "sg:classifiers":[
        {
            "category":"Health Services",
            "subcategory":"Doctor",
            "type":"Services"
        }
    ],
    "sg:phone":"+1 301 777 7420",
    "sg:postcode":"21502",
    "sg:province":"MD",
    "sg:tags":[
        "physician",
        "surgeon"
    ],
    "wof:name":"Robert D Cendo MD",
    "wof:placetype":"venue"
},
  "geometry": {"coordinates":[-78.79912299999999,39.64347],"type":"Point"}
}