{
  "type": "Feature",
  "properties": {
    "addr:full":"5738 Cedonia Ave Baltimore MD 21206",
    "addr:housenumber":"5738",
    "addr:postcode":"21206",
    "addr:street":"Cedonia Ave",
    "iso:country":"US",
    "sg:address":"5738 Cedonia Ave",
    "sg:city":"Baltimore",
    "sg:classifiers":[
        {
            "category":"Real Estate",
            "subcategory":"Real Estate Operator",
            "type":"Services"
        }
    ],
    "sg:phone":"+1 410 488 6000",
    "sg:postcode":"21206",
    "sg:province":"MD",
    "sg:tags":[
        "apartment"
    ],
    "wof:name":"Kenilworth At Hazelwood",
    "wof:placetype":"venue"
},
  "geometry": {"coordinates":[-76.53220399999999,39.338699],"type":"Point"}
}