{
  "type": "Feature",
  "properties": {
    "iso:country":"US",
    "sg:address":"1006 N Salisbury Blvd",
    "sg:city":"Salisbury",
    "sg:classifiers":[
        {
            "category":"Shopping",
            "subcategory":"Musical Instruments",
            "type":"Retail Goods"
        }
    ],
    "sg:phone":"+1 410 546 0304",
    "sg:postcode":"21801",
    "sg:province":"MD",
    "wof:name":"Pierce Music Inc",
    "wof:placetype":"venue"
},
  "geometry": {"coordinates":[-75.591786,38.376309],"type":"Point"}
}