{
  "type": "Feature",
  "properties": {
    "addr:full":"12215 Parkton Ct Fort Washington MD 20744",
    "addr:housenumber":"12215",
    "addr:postcode":"20744",
    "addr:street":"Parkton Ct",
    "iso:country":"US",
    "sg:address":"12215 Parkton Ct",
    "sg:city":"Fort Washington",
    "sg:classifiers":[
        {
            "category":"Building & Trades",
            "subcategory":"Landscaping Services",
            "type":"Services"
        }
    ],
    "sg:phone":"+1 301 292 8808",
    "sg:postcode":"20744",
    "sg:province":"MD",
    "sg:tags":[
        "designer",
        "landscape"
    ],
    "wof:name":"Cobb Lawn Svc & Landscaping",
    "wof:placetype":"venue"
},
  "geometry": {"coordinates":[-76.99894,38.721567],"type":"Point"}
}