{
  "type": "Feature",
  "properties": {
    "iso:country":"US",
    "sg:address":"3044 Mitchellville Rd",
    "sg:city":"Bowie",
    "sg:classifiers":[
        {
            "category":"Personal",
            "subcategory":"Beauty Salon",
            "type":"Services"
        }
    ],
    "sg:phone":"+1 301 390 5511",
    "sg:postcode":"20716",
    "sg:province":"MD",
    "sg:tags":[
        "hair",
        "stylist"
    ],
    "wof:name":"C & K Hair Design",
    "wof:placetype":"venue"
},
  "geometry": {"coordinates":[-76.733923,38.931364],"type":"Point"}
}