{
  "type": "Feature",
  "properties": {
    "iso:country":"US",
    "sg:address":"900 Silver Spring Ave",
    "sg:city":"Silver Spring",
    "sg:classifiers":[
        {
            "category":"Health Services",
            "subcategory":"Clinic",
            "type":"Services"
        }
    ],
    "sg:phone":"+1 301 588 9003",
    "sg:postcode":"20910",
    "sg:province":"MD",
    "sg:tags":[
        "holistic",
        "practitioner"
    ],
    "wof:name":"Wholistic Healthcare Ctr",
    "wof:placetype":"venue"
},
  "geometry": {"coordinates":[-77.02585500000001,38.991637],"type":"Point"}
}