{
  "type": "Feature",
  "properties": {
    "addr:full":"3 N Culver St Baltimore MD 21229",
    "addr:housenumber":"3",
    "addr:postcode":"21229",
    "addr:street":"N Culver St",
    "iso:country":"US",
    "sg:address":"3 N Culver St",
    "sg:city":"Baltimore",
    "sg:classifiers":[
        {
            "category":"Personal",
            "type":"Services"
        }
    ],
    "sg:phone":"+1 410 233 3011",
    "sg:postcode":"21229",
    "sg:province":"MD",
    "sg:tags":[
        "consultant",
        "planning",
        "wedding"
    ],
    "wof:name":"Premier Weddings & Events",
    "wof:placetype":"venue"
},
  "geometry": {"coordinates":[-76.67726399999999,39.286104],"type":"Point"}
}