{
  "type": "Feature",
  "properties": {
    "addr:full":"3015 Cornett Dr Finksburg MD 21048",
    "addr:housenumber":"3015",
    "addr:postcode":"21048",
    "addr:street":"Cornett Dr",
    "iso:country":"US",
    "sg:address":"3015 Cornett Dr",
    "sg:city":"Finksburg",
    "sg:classifiers":[
        {
            "category":"Wholesale",
            "subcategory":"Non-durable Goods",
            "type":"Manufacturing & Wholesale Goods"
        }
    ],
    "sg:phone":"+1 410 861 8333",
    "sg:postcode":"21048",
    "sg:province":"MD",
    "sg:tags":[
        "advertising"
    ],
    "wof:name":"LOGO Motion",
    "wof:placetype":"venue"
},
  "geometry": {"coordinates":[-76.921913,39.491808],"type":"Point"}
}