{
  "type": "Feature",
  "properties": {
    "addr:full":"1105 Spring St Silver Spring MD 20910",
    "addr:housenumber":"1105",
    "addr:postcode":"20910",
    "addr:street":"Spring St",
    "iso:country":"US",
    "sg:address":"1105 Spring St",
    "sg:city":"Silver Spring",
    "sg:classifiers":[
        {
            "category":"Wholesale",
            "subcategory":"Non-durable Goods",
            "type":"Manufacturing & Wholesale Goods"
        }
    ],
    "sg:phone":"+1 301 588 5010",
    "sg:postcode":"20910",
    "sg:province":"MD",
    "sg:tags":[
        "advertising",
        "specialty"
    ],
    "wof:name":"Bud Miller Associates Inc",
    "wof:placetype":"venue"
},
  "geometry": {"coordinates":[-77.02906900000001,39.000231],"type":"Point"}
}