{
  "type": "Feature",
  "properties": {
    "iso:country":"US",
    "sg:address":"4120 Hanson Oaks Dr",
    "sg:city":"Hyattsville",
    "sg:classifiers":[
        {
            "category":"Wholesale",
            "subcategory":"Machinery & Supplies",
            "type":"Manufacturing & Wholesale Goods"
        }
    ],
    "sg:phone":"+1 301 459 1557",
    "sg:postcode":"20784",
    "sg:province":"MD",
    "sg:tags":[
        "equipment",
        "industrial"
    ],
    "wof:name":"Baskets For All Occasions",
    "wof:placetype":"venue"
},
  "geometry": {"coordinates":[-76.874613,38.947175],"type":"Point"}
}