{
  "type": "Feature",
  "properties": {
    "addr:full":"11070 Cathell Rd Berlin MD 21811",
    "addr:housenumber":"11070",
    "addr:postcode":"21811",
    "addr:street":"Cathell Rd",
    "iso:country":"US",
    "sg:address":"11070 Cathell Rd",
    "sg:city":"Berlin",
    "sg:classifiers":[
        {
            "category":"Fast Food",
            "type":"Food & Drink"
        }
    ],
    "sg:phone":"+1 410 641 6333",
    "sg:postcode":"21811",
    "sg:province":"MD",
    "sg:tags":[
        "take",
        "restaurant"
    ],
    "sg:website":"http://www.jamrockco9.com",
    "wof:name":"JamRock Carryout",
    "wof:placetype":"venue"
},
  "geometry": {"coordinates":[-75.16949700000001,38.378669],"type":"Point"}
}