{
  "type": "Feature",
  "properties": {
    "iso:country":"US",
    "sg:address":"9000 Mendenhall Ct",
    "sg:city":"Columbia",
    "sg:classifiers":[
        {
            "category":"Professional",
            "subcategory":"Accounting & Tax Preparation",
            "type":"Services"
        }
    ],
    "sg:phone":"+1 410 381 3210",
    "sg:postcode":"21045",
    "sg:province":"MD",
    "sg:tags":[
        "accountant"
    ],
    "wof:name":"Rhee & Co",
    "wof:placetype":"venue"
},
  "geometry": {"coordinates":[-76.827129,39.186728],"type":"Point"}
}