{
  "type": "Feature",
  "properties": {
    "iso:country":"US",
    "sg:address":"10720 Gilroy Rd",
    "sg:city":"Cockysvl Hnt Vly",
    "sg:classifiers":[
        {
            "category":"Retail",
            "subcategory":"Auto Repair",
            "type":"Services"
        }
    ],
    "sg:phone":"+1 410 527 1703",
    "sg:postcode":"21031",
    "sg:province":"MD",
    "sg:tags":[
        "repairing",
        "automobile"
    ],
    "wof:name":"First Vehicle Svc Inc",
    "wof:placetype":"venue"
},
  "geometry": {"coordinates":[-76.662822,39.478448],"type":"Point"}
}