{
  "type": "Feature",
  "properties": {
    "addr:full":"1913 Applewood Dr Hagerstown MD 21740",
    "addr:housenumber":"1913",
    "addr:postcode":"21740",
    "addr:street":"Applewood Dr",
    "iso:country":"US",
    "sg:address":"1913 Applewood Dr",
    "sg:city":"Hagerstown",
    "sg:classifiers":[
        {
            "category":"Building & Trades",
            "subcategory":"Construction",
            "type":"Services"
        }
    ],
    "sg:phone":"+1 301 791 1148",
    "sg:postcode":"21740",
    "sg:province":"MD",
    "sg:tags":[
        "house",
        "contractor",
        "roofing"
    ],
    "wof:name":"Wingfield Construction Co",
    "wof:placetype":"venue"
},
  "geometry": {"coordinates":[-77.68089999999999,39.615819],"type":"Point"}
}