{
  "type": "Feature",
  "properties": {
    "iso:country":"US",
    "sg:address":"404 Snow Hill Rd",
    "sg:city":"Salisbury",
    "sg:classifiers":[
        {
            "category":"Retail",
            "subcategory":"Animal Services",
            "type":"Services"
        }
    ],
    "sg:phone":"+1 410 219 3647",
    "sg:postcode":"21804",
    "sg:province":"MD",
    "sg:tags":[
        "pet",
        "grooming",
        "washing"
    ],
    "wof:name":"Precious Pets",
    "wof:placetype":"venue"
},
  "geometry": {"coordinates":[-75.58980200000001,38.360158],"type":"Point"}
}