{
  "type": "Feature",
  "properties": {
    "addr:full":"8305 Old National Pike Boonsboro MD 21713",
    "addr:housenumber":"8305",
    "addr:postcode":"21713",
    "addr:street":"Old National Pike",
    "iso:country":"US",
    "sg:address":"8305 Old National Pike",
    "sg:city":"Boonsboro",
    "sg:classifiers":[
        {
            "category":"Government",
            "subcategory":"Office",
            "type":"Public Place"
        }
    ],
    "sg:phone":"+1 301 432 6200",
    "sg:postcode":"21713",
    "sg:province":"MD",
    "sg:tags":[
        "executive"
    ],
    "wof:name":"Christopher Shank",
    "wof:placetype":"venue"
},
  "geometry": {"coordinates":[-77.670709,39.537178],"type":"Point"}
}