{
  "type": "Feature",
  "properties": {
    "iso:country":"US",
    "sg:address":"800 E Pulaski Hwy",
    "sg:city":"Elkton",
    "sg:classifiers":[
        {
            "category":"Wholesale",
            "subcategory":"Auto Parts",
            "type":"Manufacturing & Wholesale Goods"
        }
    ],
    "sg:phone":"+1 410 398 1515",
    "sg:postcode":"21921",
    "sg:province":"MD",
    "sg:tags":[
        "equipment",
        "truck"
    ],
    "wof:name":"Keller Truck Parts Inc",
    "wof:placetype":"venue"
},
  "geometry": {"coordinates":[-75.802312,39.601337],"type":"Point"}
}