{
  "type": "Feature",
  "properties": {
    "iso:country":"US",
    "sg:address":"5610 Cedar Ln",
    "sg:city":"Columbia",
    "sg:classifiers":[
        {
            "category":"Education",
            "subcategory":"School",
            "type":"Public Place"
        }
    ],
    "sg:phone":"+1 410 313 6907",
    "sg:postcode":"21044",
    "sg:province":"MD",
    "sg:website":"www.hcpss.org",
    "wof:name":"Swansfield Elementary School",
    "wof:placetype":"venue"
},
  "geometry": {"coordinates":[-76.88799899999999,39.217825],"type":"Point"}
}