{
  "type": "Feature",
  "properties": {
    "addr:full":"1011 Saint Paul St Baltimore MD 21202",
    "addr:housenumber":"1011",
    "addr:postcode":"21202",
    "addr:street":"Saint Paul St",
    "iso:country":"US",
    "sg:address":"1011 Saint Paul St",
    "sg:city":"Baltimore",
    "sg:classifiers":[
        {
            "category":"Retail",
            "subcategory":"Laundry & Dry Cleaning",
            "type":"Services"
        }
    ],
    "sg:phone":"+1 410 332 1760",
    "sg:postcode":"21202",
    "sg:province":"MD",
    "sg:tags":[
        "cleaners"
    ],
    "wof:name":"Royal Cleaners",
    "wof:placetype":"venue"
},
  "geometry": {"coordinates":[-76.61432499999999,39.302324],"type":"Point"}
}