{
  "type": "Feature",
  "properties": {
    "iso:country":"US",
    "sg:address":"49 Frederick St",
    "sg:city":"Taneytown",
    "sg:classifiers":[
        {
            "category":"Health Services",
            "subcategory":"Doctor",
            "type":"Services"
        }
    ],
    "sg:phone":"+1 410 756 2121",
    "sg:postcode":"21787",
    "sg:province":"MD",
    "sg:tags":[
        "physician",
        "surgeon"
    ],
    "wof:name":"Wasim Fakhar MD",
    "wof:placetype":"venue"
},
  "geometry": {"coordinates":[-77.176655,39.659505],"type":"Point"}
}