{
  "type": "Feature",
  "properties": {
    "iso:country":"US",
    "sg:address":"13247 Executive Park Ter",
    "sg:city":"Germantown",
    "sg:classifiers":[
        {
            "category":"Health Services",
            "subcategory":"Health Practitioner",
            "type":"Services"
        }
    ],
    "sg:phone":"+1 301 601 2892",
    "sg:postcode":"20874",
    "sg:province":"MD",
    "sg:tags":[
        "therapist",
        "physical"
    ],
    "wof:name":"NRH Regional Rehab-Grmntwn",
    "wof:placetype":"venue"
},
  "geometry": {"coordinates":[-77.27493699999999,39.180998],"type":"Point"}
}