{
  "type": "Feature",
  "properties": {
    "addr:full":"500 Memorial Ave Cumberland MD 21502",
    "addr:housenumber":"500",
    "addr:postcode":"21502",
    "addr:street":"Memorial Ave",
    "iso:country":"US",
    "sg:address":"500 Memorial Ave",
    "sg:city":"Cumberland",
    "sg:classifiers":[
        {
            "category":"Health Services",
            "subcategory":"Doctor",
            "type":"Services"
        }
    ],
    "sg:phone":"+1 301 759 4544",
    "sg:postcode":"21502",
    "sg:province":"MD",
    "sg:tags":[
        "physician",
        "surgeon"
    ],
    "wof:name":"Allegany Internal Medicine",
    "wof:placetype":"venue"
},
  "geometry": {"coordinates":[-78.75216399999999,39.642804],"type":"Point"}
}