{
  "type": "Feature",
  "properties": {
    "iso:country":"US",
    "sg:address":"11816 Bedford Rd NE",
    "sg:city":"Cumberland",
    "sg:classifiers":[
        {
            "category":"Wholesale",
            "subcategory":"Medical Equipment & Supplies",
            "type":"Manufacturing & Wholesale Goods"
        }
    ],
    "sg:phone":"+1 301 722 0770",
    "sg:postcode":"21502",
    "sg:province":"MD",
    "sg:tags":[
        "hospital"
    ],
    "wof:name":"Chesapeake Rehab Equipment",
    "wof:placetype":"venue"
},
  "geometry": {"coordinates":[-78.732226,39.685687],"type":"Point"}
}