{
  "type": "Feature",
  "properties": {
    "addr:full":"150 Center St Frostburg MD 21532",
    "addr:housenumber":"150",
    "addr:postcode":"21532",
    "addr:street":"Center St",
    "iso:country":"US",
    "sg:address":"150 Center St",
    "sg:city":"Frostburg",
    "sg:classifiers":[
        {
            "category":"Organizations",
            "subcategory":"Religious Organization",
            "type":"Services"
        }
    ],
    "sg:phone":"+1 301 689 5146",
    "sg:postcode":"21532",
    "sg:province":"MD",
    "sg:tags":[
        "church"
    ],
    "wof:name":"Frostburg Church-Nazarene",
    "wof:placetype":"venue"
},
  "geometry": {"coordinates":[-78.92825499999999,39.651914],"type":"Point"}
}