{
  "type": "Feature",
  "properties": {
    "addr:full":"4379 Doctor Samuel Mudd Rd Waldorf MD 20601",
    "addr:housenumber":"4379",
    "addr:postcode":"20601",
    "addr:street":"Doctor Samuel Mudd Rd",
    "iso:country":"US",
    "sg:address":"4379 Doctor Samuel Mudd Rd",
    "sg:city":"Waldorf",
    "sg:classifiers":[
        {
            "category":"Professional",
            "subcategory":"Computer Services",
            "type":"Services"
        }
    ],
    "sg:phone":"+1 301 645 5353",
    "sg:postcode":"20601",
    "sg:province":"MD",
    "sg:tags":[
        "related"
    ],
    "wof:name":"H J Consulting Inc",
    "wof:placetype":"venue"
},
  "geometry": {"coordinates":[-76.81816499999999,38.590548],"type":"Point"}
}