{
  "type": "Feature",
  "properties": {
    "addr:full":"13 Dellwood Ct Cockeysville MD 21030",
    "addr:housenumber":"13",
    "addr:postcode":"21030",
    "addr:street":"Dellwood Ct",
    "iso:country":"US",
    "sg:address":"13 Dellwood Ct",
    "sg:city":"Cockeysville",
    "sg:classifiers":[
        {
            "category":"Banks & Credit Unions",
            "subcategory":"Financial Services",
            "type":"Services"
        }
    ],
    "sg:phone":"+1 410 308 8916",
    "sg:postcode":"21030",
    "sg:province":"MD",
    "sg:tags":[
        "broker",
        "mortgage"
    ],
    "wof:name":"J A S Finance Llc",
    "wof:placetype":"venue"
},
  "geometry": {"coordinates":[-76.70410200000001,39.476101],"type":"Point"}
}