{
  "type": "Feature",
  "properties": {
    "iso:country":"US",
    "sg:address":"3261 Old Washington Rd",
    "sg:city":"Waldorf",
    "sg:classifiers":[
        {
            "category":"Food & Beverages",
            "subcategory":"Groceries & Convenience Stores",
            "type":"Retail Goods"
        }
    ],
    "sg:phone":"+1 301 893 8150",
    "sg:postcode":"20602",
    "sg:province":"MD",
    "wof:name":"Youngs Snack Shop",
    "wof:placetype":"venue"
},
  "geometry": {"coordinates":[-76.91087,38.621907],"type":"Point"}
}