{
  "type": "Feature",
  "properties": {
    "iso:country":"US",
    "sg:address":"3009 Old Channel Rd",
    "sg:city":"Laurel",
    "sg:classifiers":[
        {
            "category":"Professional",
            "subcategory":"Business Services",
            "type":"Services"
        }
    ],
    "sg:phone":"+1 410 336 0944",
    "sg:postcode":"20724",
    "sg:province":"MD",
    "sg:tags":[
        "management"
    ],
    "sg:website":"http://www.fowgroup.com",
    "wof:name":"Fowgroup Inc.",
    "wof:placetype":"venue"
},
  "geometry": {"coordinates":[-76.803982,39.116333],"type":"Point"}
}