{
  "type": "Feature",
  "properties": {
    "iso:country":"US",
    "sg:address":"12800 Middlebrook Rd",
    "sg:city":"Germantown",
    "sg:classifiers":[
        {
            "category":"Banks & Credit Unions",
            "subcategory":"Investment Brokerage",
            "type":"Services"
        }
    ],
    "sg:phone":"+1 301 515 1500",
    "sg:postcode":"20874",
    "sg:province":"MD",
    "sg:tags":[
        "consultant",
        "planning",
        "financial"
    ],
    "wof:name":"Ameri Debt Inc",
    "wof:placetype":"venue"
},
  "geometry": {"coordinates":[-77.266637,39.178301],"type":"Point"}
}