{
  "type": "Feature",
  "properties": {
    "iso:country":"US",
    "sg:address":"6343 Old Branch Ave",
    "sg:city":"Temple Hills",
    "sg:classifiers":[
        {
            "category":"Shopping",
            "subcategory":"Clothing, Apparel, & Fashions",
            "type":"Retail Goods"
        }
    ],
    "sg:phone":"+1 301 449 6016",
    "sg:postcode":"20748",
    "sg:province":"MD",
    "wof:name":"Sister To Sister Boutique",
    "wof:placetype":"venue"
},
  "geometry": {"coordinates":[-76.906948,38.803675],"type":"Point"}
}