{
  "type": "Feature",
  "properties": {
    "iso:country":"US",
    "sg:address":"20409 Sawgrass Dr",
    "sg:city":"Montgomery Village",
    "sg:classifiers":[
        {
            "category":"Shopping",
            "subcategory":"Stationery & Office Supplies",
            "type":"Retail Goods"
        }
    ],
    "sg:phone":"+1 301 926 1795",
    "sg:postcode":"20886",
    "sg:province":"MD",
    "wof:name":"Yours Truly Stationery",
    "wof:placetype":"venue"
},
  "geometry": {"coordinates":[-77.153387,39.190577],"type":"Point"}
}