{
  "type": "Feature",
  "properties": {
    "addr:full":"8156 Solley Rd Pasadena MD 21122",
    "addr:housenumber":"8156",
    "addr:postcode":"21122",
    "addr:street":"Solley Rd",
    "iso:country":"US",
    "sg:address":"8156 Solley Rd",
    "sg:city":"Pasadena",
    "sg:classifiers":[
        {
            "category":"Utilities",
            "subcategory":"Water",
            "type":"Services"
        }
    ],
    "sg:phone":"+1 410 437 3386",
    "sg:postcode":"21122",
    "sg:province":"MD",
    "sg:tags":[
        "pump",
        "well",
        "drilling",
        "contractor"
    ],
    "sg:website":"http://www.awpservice.com",
    "wof:name":"Able Well and Pump Svc",
    "wof:placetype":"venue"
},
  "geometry": {"coordinates":[-76.563452,39.134396],"type":"Point"}
}