{
  "type": "Feature",
  "properties": {
    "addr:full":"1203 Windlass Dr Middle River MD 21220",
    "addr:housenumber":"1203",
    "addr:postcode":"21220",
    "addr:street":"Windlass Dr",
    "iso:country":"US",
    "sg:address":"1203 Windlass Dr",
    "sg:city":"Middle River",
    "sg:classifiers":[
        {
            "category":"Banks & Credit Unions",
            "subcategory":"Bank",
            "type":"Services"
        },
        {
            "category":"Banks & Credit Unions",
            "subcategory":"Financial Services",
            "type":"Services"
        }
    ],
    "sg:phone":"+1 410 686 7130",
    "sg:postcode":"21220",
    "sg:province":"MD",
    "sg:tags":[
        "broker",
        "mortgage"
    ],
    "sg:website":"www.bankofamerica.com",
    "wof:name":"Bank of America",
    "wof:placetype":"venue"
},
  "geometry": {"coordinates":[-76.450897,39.334202],"type":"Point"}
}