{
  "type": "Feature",
  "properties": {
    "iso:country":"US",
    "sg:address":"16 W Pennsylvania Ave",
    "sg:city":"Baltimore",
    "sg:classifiers":[
        {
            "category":"Shopping",
            "subcategory":"Photographic Equipment",
            "type":"Retail Goods"
        }
    ],
    "sg:phone":"+1 410 296 1717",
    "sg:postcode":"21204",
    "sg:province":"MD",
    "sg:tags":[
        "supply"
    ],
    "wof:name":"Towson Photo Supply Inc",
    "wof:placetype":"venue"
},
  "geometry": {"coordinates":[-76.604927,39.400799],"type":"Point"}
}