{
  "type": "Feature",
  "properties": {
    "iso:country":"US",
    "sg:address":"701 Russell Ave",
    "sg:city":"Gaithersburg",
    "sg:classifiers":[
        {
            "category":"Shopping",
            "subcategory":"Jewelry",
            "type":"Retail Goods"
        }
    ],
    "sg:phone":"+1 301 258 9070",
    "sg:postcode":"20877",
    "sg:province":"MD",
    "sg:tags":[
        "jeweler"
    ],
    "wof:name":"Shaw's Jewelers",
    "wof:placetype":"venue"
},
  "geometry": {"coordinates":[-77.20857100000001,39.152878],"type":"Point"}
}