{
  "type": "Feature",
  "properties": {
    "addr:full":"2288 Pulaski Hwy North East MD 21901",
    "addr:housenumber":"2288",
    "addr:postcode":"21901",
    "addr:street":"Pulaski Hwy North",
    "iso:country":"US",
    "sg:address":"2288 Pulaski Hwy",
    "sg:city":"North East",
    "sg:classifiers":[
        {
            "category":"Professional",
            "subcategory":"Computer Services",
            "type":"Services"
        }
    ],
    "sg:phone":"+1 410 287 5551",
    "sg:postcode":"21901",
    "sg:province":"MD",
    "sg:tags":[
        "repair"
    ],
    "wof:name":"Computer Doctor Of Northeast",
    "wof:placetype":"venue"
},
  "geometry": {"coordinates":[-75.94221899999999,39.610449],"type":"Point"}
}