{
  "type": "Feature",
  "properties": {
    "iso:country":"US",
    "sg:address":"9901 Greenbelt Rd",
    "sg:city":"Lanham",
    "sg:classifiers":[
        {
            "category":"Food & Beverages",
            "subcategory":"Liquor & Beverages",
            "type":"Retail Goods"
        }
    ],
    "sg:phone":"+1 301 794 4940",
    "sg:postcode":"20706",
    "sg:province":"MD",
    "wof:name":"Orbit Beer & Wine",
    "wof:placetype":"venue"
},
  "geometry": {"coordinates":[-76.834379,38.99084],"type":"Point"}
}