{
  "type": "Feature",
  "properties": {
    "addr:full":"2400 51st Pl Hyattsville MD 20781",
    "addr:housenumber":"2400",
    "addr:postcode":"20781",
    "addr:street":"51St Pl",
    "iso:country":"US",
    "sg:address":"2400 51st Pl",
    "sg:city":"Hyattsville",
    "sg:classifiers":[
        {
            "category":"Building & Trades",
            "subcategory":"Plumbing",
            "type":"Services"
        }
    ],
    "sg:phone":"+1 301 773 1300",
    "sg:postcode":"20781",
    "sg:province":"MD",
    "sg:tags":[
        "conditioning",
        "air",
        "system",
        "contractor"
    ],
    "sg:website":"www.wmschlosser.com",
    "wof:name":"W M Schlosser Co Inc",
    "wof:placetype":"venue"
},
  "geometry": {"coordinates":[-76.92702,38.920472],"type":"Point"}
}