{
  "type": "Feature",
  "properties": {
    "iso:country":"US",
    "sg:address":"7104 Carmae Rd",
    "sg:city":"Sykesville",
    "sg:classifiers":[
        {
            "category":"Travel",
            "subcategory":"Travel Agent",
            "type":"Entertainment"
        }
    ],
    "sg:phone":"+1 410 795 5320",
    "sg:postcode":"21784",
    "sg:province":"MD",
    "sg:tags":[
        "agency",
        "services-commercial"
    ],
    "wof:name":"A-Travel Essence, Inc.",
    "wof:placetype":"venue"
},
  "geometry": {"coordinates":[-76.997542,39.378039],"type":"Point"}
}