{
  "type": "Feature",
  "properties": {
    "addr:full":"12062 Long Lake Dr Owings Mills MD 21117",
    "addr:housenumber":"12062",
    "addr:postcode":"21117",
    "addr:street":"Long Lake Dr",
    "iso:country":"US",
    "sg:address":"12062 Long Lake Dr",
    "sg:city":"Owings Mills",
    "sg:classifiers":[
        {
            "category":"Professional",
            "subcategory":"Computer Services",
            "type":"Services"
        }
    ],
    "sg:phone":"+1 410 356 5121",
    "sg:postcode":"21117",
    "sg:province":"MD",
    "sg:tags":[
        "information",
        "technology"
    ],
    "wof:name":"Bdk Services Group",
    "wof:placetype":"venue"
},
  "geometry": {"coordinates":[-76.79142,39.458357],"type":"Point"}
}