{
  "type": "Feature",
  "properties": {
    "addr:full":"8950 State Route 108 Columbia MD 21045",
    "addr:housenumber":"8950",
    "addr:postcode":"21045",
    "addr:street":"State Route 108",
    "iso:country":"US",
    "sg:address":"8950 State Route 108",
    "sg:city":"Columbia",
    "sg:classifiers":[
        {
            "category":"Deli",
            "type":"Food & Drink"
        }
    ],
    "sg:phone":"+1 410 730 7257",
    "sg:postcode":"21045",
    "sg:province":"MD",
    "wof:name":"Gorman Plaza Deli",
    "wof:placetype":"venue"
},
  "geometry": {"coordinates":[-76.823402,39.227299],"type":"Point"}
}