{
  "type": "Feature",
  "properties": {
    "addr:full":"9055 Chevrolet Dr Ellicott City MD 21042",
    "addr:housenumber":"9055",
    "addr:postcode":"21042",
    "addr:street":"Chevrolet Dr",
    "iso:country":"US",
    "sg:address":"9055 Chevrolet Dr",
    "sg:city":"Ellicott City",
    "sg:classifiers":[
        {
            "category":"Health Services",
            "subcategory":"Doctor",
            "type":"Services"
        }
    ],
    "sg:phone":"+1 410 465 7533",
    "sg:postcode":"21042",
    "sg:province":"MD",
    "wof:name":"Mamo George MD",
    "wof:placetype":"venue"
},
  "geometry": {"coordinates":[-76.82399700000001,39.2752],"type":"Point"}
}