{
  "type": "Feature",
  "properties": {
    "iso:country":"US",
    "sg:address":"2509 E Monument St",
    "sg:city":"Baltimore",
    "sg:classifiers":[
        {
            "category":"Food & Beverages",
            "subcategory":"Groceries & Convenience Stores",
            "type":"Retail Goods"
        }
    ],
    "sg:phone":"+1 410 563 2525",
    "sg:postcode":"21205",
    "sg:province":"MD",
    "sg:tags":[
        "grocer"
    ],
    "wof:name":"Super A Farm",
    "wof:placetype":"venue"
},
  "geometry": {"coordinates":[-76.581924,39.298856],"type":"Point"}
}