{
  "type": "Feature",
  "properties": {
    "addr:full":"5505 York Rd Baltimore MD 21212",
    "addr:housenumber":"5505",
    "addr:postcode":"21212",
    "addr:street":"York Rd",
    "iso:country":"US",
    "sg:address":"5505 York Rd",
    "sg:city":"Baltimore",
    "sg:classifiers":[
        {
            "category":"Banks & Credit Unions",
            "subcategory":"Financial Services",
            "type":"Services"
        }
    ],
    "sg:phone":"+1 410 435 6115",
    "sg:postcode":"21212",
    "sg:province":"MD",
    "sg:tags":[
        "broker",
        "mortgage"
    ],
    "wof:name":"Ronald Rollins",
    "wof:placetype":"venue"
},
  "geometry": {"coordinates":[-76.610001,39.356701],"type":"Point"}
}