{
  "type": "Feature",
  "properties": {
    "iso:country":"US",
    "sg:address":"410 Oldham St",
    "sg:city":"Baltimore",
    "sg:classifiers":[
        {
            "category":"Building & Trades",
            "subcategory":"Construction",
            "type":"Services"
        }
    ],
    "sg:phone":"+1 410 342 4587",
    "sg:postcode":"21224",
    "sg:province":"MD",
    "sg:tags":[
        "heavy"
    ],
    "wof:name":"Karellas Construction",
    "wof:placetype":"venue"
},
  "geometry": {"coordinates":[-76.555891,39.287152],"type":"Point"}
}