{
  "type": "Feature",
  "properties": {
    "addr:full":"7139 Security Blvd Ste 106 Baltimore MD 21244",
    "addr:housenumber":"7139",
    "addr:postcode":"21244",
    "addr:street":"Security Blvd Ste 106",
    "iso:country":"US",
    "sg:address":"7139 Security Blvd Ste 106",
    "sg:city":"Baltimore",
    "sg:classifiers":[
        {
            "category":"Personal",
            "subcategory":"Day Spa",
            "type":"Services"
        },
        {
            "category":"Personal",
            "subcategory":"Nail Salon",
            "type":"Services"
        }
    ],
    "sg:phone":"+1 866 558 6181",
    "sg:postcode":"21244",
    "sg:province":"MD",
    "wof:name":"Beauty Creations",
    "wof:placetype":"venue"
},
  "geometry": {"coordinates":[-76.756987,39.313366],"type":"Point"}
}