{
  "type": "Feature",
  "properties": {
    "iso:country":"US",
    "sg:address":"2 Bentley Ct",
    "sg:city":"Rockville",
    "sg:classifiers":[
        {
            "category":"Professional",
            "subcategory":"Computer Services",
            "type":"Services"
        }
    ],
    "sg:phone":"+1 301 762 3677",
    "sg:postcode":"20850",
    "sg:province":"MD",
    "sg:tags":[
        "manager",
        "datum"
    ],
    "wof:name":"Tsao Li-Shih",
    "wof:placetype":"venue"
},
  "geometry": {"coordinates":[-77.17354400000001,39.079353],"type":"Point"}
}