{
  "type": "Feature",
  "properties": {
    "iso:country":"US",
    "sg:address":"15723 Haynes Rd",
    "sg:city":"Laurel",
    "sg:classifiers":[
        {
            "category":"Communications",
            "subcategory":"Film & Video Production",
            "type":"Services"
        }
    ],
    "sg:phone":"+1 866 718 8779",
    "sg:postcode":"20707",
    "sg:province":"MD",
    "wof:name":"Central Focus Video & Photography",
    "wof:placetype":"venue"
},
  "geometry": {"coordinates":[-76.86994900000001,39.106602],"type":"Point"}
}