{
  "type": "Feature",
  "properties": {
    "addr:full":"4508 Woodlea Ave Baltimore MD 21206",
    "addr:housenumber":"4508",
    "addr:postcode":"21206",
    "addr:street":"Woodlea Ave",
    "iso:country":"US",
    "sg:address":"4508 Woodlea Ave",
    "sg:city":"Baltimore",
    "sg:classifiers":[
        {
            "category":"Building & Trades",
            "subcategory":"Electrical",
            "type":"Services"
        }
    ],
    "sg:phone":"+1 410 325 2243",
    "sg:postcode":"21206",
    "sg:province":"MD",
    "sg:tags":[
        "electrician"
    ],
    "wof:name":"Harris Mullen Electric",
    "wof:placetype":"venue"
},
  "geometry": {"coordinates":[-76.553759,39.331642],"type":"Point"}
}