{
  "type": "Feature",
  "properties": {
    "addr:full":"12924 Center Dr Ocean City MD 21842",
    "addr:housenumber":"12924",
    "addr:postcode":"21842",
    "addr:street":"Center Dr",
    "iso:country":"US",
    "sg:address":"12924 Center Dr",
    "sg:city":"Ocean City",
    "sg:classifiers":[
        {
            "category":"Building & Trades",
            "subcategory":"Construction",
            "type":"Services"
        }
    ],
    "sg:phone":"+1 410 213 1991",
    "sg:postcode":"21842",
    "sg:province":"MD",
    "sg:tags":[
        "painter"
    ],
    "wof:name":"Barrett Contractors",
    "wof:placetype":"venue"
},
  "geometry": {"coordinates":[-75.10254500000001,38.346147],"type":"Point"}
}