{
  "type": "Feature",
  "properties": {
    "addr:full":"4805 Madison St Riverdale MD 20737",
    "addr:housenumber":"4805",
    "addr:postcode":"20737",
    "addr:street":"Madison St",
    "iso:country":"US",
    "sg:address":"4805 Madison St",
    "sg:city":"Riverdale",
    "sg:classifiers":[
        {
            "category":"Professional",
            "subcategory":"Accounting & Tax Preparation",
            "type":"Services"
        }
    ],
    "sg:phone":"+1 240 463 9019",
    "sg:postcode":"20737",
    "sg:province":"MD",
    "sg:tags":[
        "return",
        "public",
        "accountants-certified"
    ],
    "sg:website":"http://www.bernicehassancpa.com",
    "wof:name":"Bernice Hassan CPA Accounting & Tax Services",
    "wof:placetype":"venue"
},
  "geometry": {"coordinates":[-76.932348,38.957878],"type":"Point"}
}