{
  "type": "Feature",
  "properties": {
    "iso:country":"US",
    "sg:address":"203 Oakdale Rd",
    "sg:city":"Baltimore",
    "sg:classifiers":[
        {
            "category":"Professional",
            "subcategory":"Advertising",
            "type":"Services"
        }
    ],
    "sg:phone":"+1 410 889 7604",
    "sg:postcode":"21210",
    "sg:province":"MD",
    "sg:tags":[
        "agency",
        "specialty"
    ],
    "sg:website":"http://www.katycouch.com",
    "wof:name":"Katy Couch",
    "wof:placetype":"venue"
},
  "geometry": {"coordinates":[-76.63039999999999,39.348618],"type":"Point"}
}