{
  "type": "Feature",
  "properties": {
    "iso:country":"US",
    "sg:address":"53 E Baltimore St",
    "sg:city":"Hagerstown",
    "sg:classifiers":[
        {
            "category":"Organizations",
            "subcategory":"Religious Organization",
            "type":"Services"
        }
    ],
    "sg:phone":"+1 301 733 5039",
    "sg:postcode":"21740",
    "sg:province":"MD",
    "sg:tags":[
        "synagogue"
    ],
    "sg:website":"www.bnaiabraham.net",
    "wof:name":"Congregation B'Nai Abraham",
    "wof:placetype":"venue"
},
  "geometry": {"coordinates":[-77.720663,39.638258],"type":"Point"}
}