{
  "type": "Feature",
  "properties": {
    "iso:country":"US",
    "sg:address":"1739 Myles Dr",
    "sg:city":"Harwood",
    "sg:classifiers":[
        {
            "category":"Professional",
            "type":"Services"
        }
    ],
    "sg:phone":"+1 410 741 1768",
    "sg:postcode":"20776",
    "sg:province":"MD",
    "wof:name":"Myles Bobcat Service",
    "wof:placetype":"venue"
},
  "geometry": {"coordinates":[-76.663083,38.879512],"type":"Point"}
}