{
  "type": "Feature",
  "properties": {
    "iso:country":"US",
    "sg:address":"3989 Old Federal Hill Rd",
    "sg:city":"Jarrettsville",
    "sg:classifiers":[
        {
            "category":"Building & Trades",
            "subcategory":"Construction",
            "type":"Services"
        }
    ],
    "sg:phone":"+1 410 557 9305",
    "sg:postcode":"21084",
    "sg:province":"MD",
    "sg:tags":[
        "contractor"
    ],
    "wof:name":"Jarrettsville Builders Inc",
    "wof:placetype":"venue"
},
  "geometry": {"coordinates":[-76.459582,39.627021],"type":"Point"}
}