{
  "type": "Feature",
  "properties": {
    "addr:full":"2428 Corning Ave Fort Washington MD 20744",
    "addr:postcode":"2428;20744",
    "addr:street":"Corning Ave",
    "iso:country":"US",
    "sg:address":"2428 Corning Ave",
    "sg:city":"Fort Washington",
    "sg:classifiers":[
        {
            "category":"Real Estate",
            "subcategory":"Real Estate Operator",
            "type":"Services"
        }
    ],
    "sg:phone":"+1 301 630 1300",
    "sg:postcode":"20744",
    "sg:province":"MD",
    "sg:tags":[
        "apartment"
    ],
    "wof:name":"Rosecroft Mews Apartments",
    "wof:placetype":"venue"
},
  "geometry": {"coordinates":[-76.965897,38.807598],"type":"Point"}
}