{
  "type": "Feature",
  "properties": {
    "iso:country":"US",
    "sg:address":"1071 Rockville Pike",
    "sg:city":"Rockville",
    "sg:classifiers":[
        {
            "category":"Food & Beverages",
            "subcategory":"Groceries & Convenience Stores",
            "type":"Retail Goods"
        }
    ],
    "sg:phone":"+1 301 424 0099",
    "sg:postcode":"20852",
    "sg:province":"MD",
    "wof:name":"Seven Express",
    "wof:placetype":"venue"
},
  "geometry": {"coordinates":[-77.132688,39.07164],"type":"Point"}
}