{
  "type": "Feature",
  "properties": {
    "addr:full":"3836 Wayson Rd Davidsonville MD 21035",
    "addr:housenumber":"3836",
    "addr:postcode":"21035",
    "addr:street":"Wayson Rd",
    "iso:country":"US",
    "sg:address":"3836 Wayson Rd",
    "sg:city":"Davidsonville",
    "sg:classifiers":[
        {
            "category":"Building & Trades",
            "subcategory":"Plumbing",
            "type":"Services"
        }
    ],
    "sg:phone":"+1 301 261 7587",
    "sg:postcode":"21035",
    "sg:province":"MD",
    "sg:tags":[
        "sheet",
        "work",
        "metal",
        "contractor"
    ],
    "wof:name":"Champion Inc",
    "wof:placetype":"venue"
},
  "geometry": {"coordinates":[-76.650862,38.903195],"type":"Point"}
}