{
  "type": "Feature",
  "properties": {
    "iso:country":"US",
    "sg:address":"935 Solomons Island Rd N",
    "sg:city":"Prince Frederick",
    "sg:classifiers":[
        {
            "category":"Autos & Motor Vehicles",
            "subcategory":"Automobile Sales",
            "type":"Retail Goods"
        }
    ],
    "sg:phone":"+1 410 535 1200",
    "sg:postcode":"20678",
    "sg:province":"MD",
    "sg:tags":[
        "car",
        "dealer"
    ],
    "sg:website":"www.ralphsdodge.com",
    "wof:name":"Ralph's Dodge",
    "wof:placetype":"venue"
},
  "geometry": {"coordinates":[-76.59687599999999,38.556197],"type":"Point"}
}