{
  "type": "Feature",
  "properties": {
    "iso:country":"US",
    "sg:address":"1406 Martin Blvd",
    "sg:city":"Baltimore",
    "sg:classifiers":[
        {
            "category":"Shopping",
            "subcategory":"Tobacco",
            "type":"Retail Goods"
        }
    ],
    "sg:phone":"+1 410 646 3300",
    "sg:postcode":"21220",
    "sg:province":"MD",
    "sg:tags":[
        "cigarette",
        "cigar",
        "dealer"
    ],
    "wof:name":"Bargain Cigarettes",
    "wof:placetype":"venue"
},
  "geometry": {"coordinates":[-76.43612299999999,39.329502],"type":"Point"}
}