{
  "type": "Feature",
  "properties": {
    "addr:full":"22 E Padonia Rd Timonium MD 21093",
    "addr:housenumber":"22",
    "addr:postcode":"21093",
    "addr:street":"E Padonia Rd",
    "iso:country":"US",
    "sg:address":"22 E Padonia Rd",
    "sg:city":"Timonium",
    "sg:classifiers":[
        {
            "category":"Professional",
            "subcategory":"Management & Consulting",
            "type":"Services"
        }
    ],
    "sg:phone":"+1 410 329 6462",
    "sg:postcode":"21093",
    "sg:province":"MD",
    "sg:tags":[
        "fuel"
    ],
    "wof:name":"Griffith Management Svc Inc",
    "wof:placetype":"venue"
},
  "geometry": {"coordinates":[-76.63097399999999,39.456537],"type":"Point"}
}