{
  "type": "Feature",
  "properties": {
    "iso:country":"US",
    "sg:address":"10515 Summit Ave",
    "sg:city":"Kensington",
    "sg:classifiers":[
        {
            "category":"Retail",
            "subcategory":"Auto Repair",
            "type":"Services"
        }
    ],
    "sg:phone":"+1 301 897 8190",
    "sg:postcode":"20895",
    "sg:province":"MD",
    "sg:tags":[
        "body",
        "shop"
    ],
    "wof:name":"Duramax Auto Body",
    "wof:placetype":"venue"
},
  "geometry": {"coordinates":[-77.07910200000001,39.028702],"type":"Point"}
}