{
  "type": "Feature",
  "properties": {
    "addr:full":"3281 Main St Manchester MD 21102",
    "addr:housenumber":"3281",
    "addr:postcode":"21102",
    "addr:street":"Main St",
    "iso:country":"US",
    "sg:address":"3281 Main St",
    "sg:city":"Manchester",
    "sg:classifiers":[
        {
            "category":"Restaurant",
            "type":"Food & Drink"
        }
    ],
    "sg:menulink":"http://www.allmenus.com/md/manchester/279755-sheetz/menu/",
    "sg:phone":"+1 410 374 1454",
    "sg:postcode":"21102",
    "sg:province":"MD",
    "sg:tags":[
        "american"
    ],
    "wof:name":"Sheetz",
    "wof:placetype":"venue"
},
  "geometry": {"coordinates":[-76.88639000000001,39.664458],"type":"Point"}
}