{
  "type": "Feature",
  "properties": {
    "addr:full":"9422 Bentridge Ave Potomac MD 20854",
    "addr:housenumber":"9422",
    "addr:postcode":"20854",
    "addr:street":"Bentridge Ave",
    "iso:country":"US",
    "sg:address":"9422 Bentridge Ave",
    "sg:city":"Potomac",
    "sg:classifiers":[
        {
            "category":"Professional",
            "subcategory":"Engineering",
            "type":"Services"
        }
    ],
    "sg:phone":"+1 301 424 0954",
    "sg:postcode":"20854",
    "sg:province":"MD",
    "wof:name":"Water Systems International",
    "wof:placetype":"venue"
},
  "geometry": {"coordinates":[-77.193623,39.056807],"type":"Point"}
}