{
  "type": "Feature",
  "properties": {
    "addr:full":"2100 E North Ave Baltimore MD 21213",
    "addr:housenumber":"2100",
    "addr:postcode":"21213",
    "addr:street":"E North Ave",
    "iso:country":"US",
    "sg:address":"2100 E North Ave",
    "sg:city":"Baltimore",
    "sg:classifiers":[
        {
            "category":"Autos & Motor Vehicles",
            "subcategory":"Auto Supplies",
            "type":"Retail Goods"
        }
    ],
    "sg:phone":"+1 410 327 4510",
    "sg:postcode":"21213",
    "sg:province":"MD",
    "sg:tags":[
        "tire"
    ],
    "wof:name":"Tire Masters",
    "wof:placetype":"venue"
},
  "geometry": {"coordinates":[-76.58811300000001,39.312444],"type":"Point"}
}