{
  "type": "Feature",
  "properties": {
    "addr:full":"421 Nature Ln Rockville MD 20850",
    "addr:housenumber":"421",
    "addr:postcode":"20850",
    "addr:street":"Nature Ln",
    "iso:country":"US",
    "sg:address":"421 Nature Ln",
    "sg:city":"Rockville",
    "sg:classifiers":[
        {
            "category":"Utilities",
            "subcategory":"Electric",
            "type":"Services"
        }
    ],
    "sg:phone":"+1 301 762 8574",
    "sg:postcode":"20850",
    "sg:province":"MD",
    "sg:tags":[
        "equipment",
        "supplies-repair",
        "electronic",
        "equipment-repair"
    ],
    "wof:name":"Sunnet",
    "wof:placetype":"venue"
},
  "geometry": {"coordinates":[-77.185738,39.091862],"type":"Point"}
}