{
  "type": "Feature",
  "properties": {
    "addr:full":"9578 Deereco Rd Timonium MD 21093",
    "addr:housenumber":"9578",
    "addr:postcode":"21093",
    "addr:street":"Deereco Rd",
    "iso:country":"US",
    "sg:address":"9578 Deereco Rd",
    "sg:city":"Timonium",
    "sg:classifiers":[
        {
            "category":"Government",
            "subcategory":"Fire Station",
            "type":"Public Place"
        }
    ],
    "sg:phone":"+1 410 560 6750",
    "sg:postcode":"21093",
    "sg:province":"MD",
    "sg:tags":[
        "department"
    ],
    "wof:name":"Fire & Ice",
    "wof:placetype":"venue"
},
  "geometry": {"coordinates":[-76.641448,39.454276],"type":"Point"}
}