{
  "type": "Feature",
  "properties": {
    "addr:full":"728 Melrose St Annapolis MD 21401",
    "addr:housenumber":"728",
    "addr:postcode":"21401",
    "addr:street":"Melrose St",
    "iso:country":"US",
    "sg:address":"728 Melrose St",
    "sg:city":"Annapolis",
    "sg:classifiers":[
        {
            "category":"Manufacturing",
            "subcategory":"Printing",
            "type":"Manufacturing & Wholesale Goods"
        }
    ],
    "sg:phone":"+1 410 263 6043",
    "sg:postcode":"21401",
    "sg:province":"MD",
    "sg:tags":[
        "typesetting"
    ],
    "wof:name":"Annapolis Prepress",
    "wof:placetype":"venue"
},
  "geometry": {"coordinates":[-76.504926,38.983154],"type":"Point"}
}