{
  "type": "Feature",
  "properties": {
    "iso:country":"US",
    "sg:address":"882 Annapolis Rd",
    "sg:city":"Gambrills",
    "sg:classifiers":[
        {
            "category":"Real Estate",
            "subcategory":"Real Estate Agent",
            "type":"Services"
        }
    ],
    "sg:phone":"+1 410 987 4110",
    "sg:postcode":"21054",
    "sg:province":"MD",
    "wof:name":"Patterson Realtors",
    "wof:placetype":"venue"
},
  "geometry": {"coordinates":[-76.667953,39.067029],"type":"Point"}
}