{
  "type": "Feature",
  "properties": {
    "iso:country":"US",
    "sg:address":"8901 Potomac Station Ln",
    "sg:city":"Potomac",
    "sg:classifiers":[
        {
            "category":"Health Services",
            "subcategory":"Doctor",
            "type":"Services"
        }
    ],
    "sg:phone":"+1 301 299 5121",
    "sg:postcode":"20854",
    "sg:province":"MD",
    "wof:name":"Immergut Mark A MD",
    "wof:placetype":"venue"
},
  "geometry": {"coordinates":[-77.21060199999999,39.0014],"type":"Point"}
}