{
  "type": "Feature",
  "properties": {
    "addr:full":"4029 Chesapeake Dr Edgewater MD 21037",
    "addr:housenumber":"4029",
    "addr:postcode":"21037",
    "addr:street":"Chesapeake Dr",
    "iso:country":"US",
    "sg:address":"4029 Chesapeake Dr",
    "sg:city":"Edgewater",
    "sg:classifiers":[
        {
            "category":"Shopping",
            "subcategory":"Computers & Home Electronics",
            "type":"Retail Goods"
        }
    ],
    "sg:phone":"+1 410 798 9300",
    "sg:postcode":"21037",
    "sg:province":"MD",
    "sg:tags":[
        "software"
    ],
    "wof:name":"Tidgewell Associates Inc",
    "wof:placetype":"venue"
},
  "geometry": {"coordinates":[-76.49447499999999,38.899215],"type":"Point"}
}