{
  "type": "Feature",
  "properties": {
    "addr:full":"522 King Malcolm Ave Odenton MD 21113",
    "addr:housenumber":"522",
    "addr:postcode":"21113",
    "addr:street":"King Malcolm Ave",
    "iso:country":"US",
    "sg:address":"522 King Malcolm Ave",
    "sg:city":"Odenton",
    "sg:classifiers":[
        {
            "category":"Building & Trades",
            "subcategory":"Construction",
            "type":"Services"
        }
    ],
    "sg:phone":"+1 410 674 2877",
    "sg:postcode":"21113",
    "sg:province":"MD",
    "sg:tags":[
        "house"
    ],
    "wof:name":"Michael S Construction",
    "wof:placetype":"venue"
},
  "geometry": {"coordinates":[-76.695494,39.077463],"type":"Point"}
}