{
  "type": "Feature",
  "properties": {
    "addr:full":"4935 Nicholson Ct Kensington MD 20895",
    "addr:housenumber":"4935",
    "addr:postcode":"20895",
    "addr:street":"Nicholson Ct",
    "iso:country":"US",
    "sg:address":"4935 Nicholson Ct",
    "sg:city":"Kensington",
    "sg:classifiers":[
        {
            "category":"Autos & Motor Vehicles",
            "subcategory":"Automobile Sales",
            "type":"Retail Goods"
        }
    ],
    "sg:phone":"+1 301 230 2882",
    "sg:postcode":"20895",
    "sg:province":"MD",
    "sg:tags":[
        "car",
        "dealer"
    ],
    "wof:name":"Barnes Used Cars",
    "wof:placetype":"venue"
},
  "geometry": {"coordinates":[-77.10468299999999,39.045256],"type":"Point"}
}