{
  "type": "Feature",
  "properties": {
    "addr:full":"11405 Cosca Park Pl Clinton MD 20735",
    "addr:housenumber":"11405",
    "addr:postcode":"20735",
    "addr:street":"Cosca Park Pl",
    "iso:country":"US",
    "sg:address":"11405 Cosca Park Pl",
    "sg:city":"Clinton",
    "sg:classifiers":[
        {
            "category":"Retail",
            "subcategory":"Auto Repair",
            "type":"Services"
        }
    ],
    "sg:phone":"+1 301 856 7043",
    "sg:postcode":"20735",
    "sg:province":"MD",
    "sg:tags":[
        "body",
        "automobile",
        "painting"
    ],
    "wof:name":"Dave's Auto Body",
    "wof:placetype":"venue"
},
  "geometry": {"coordinates":[-76.909795,38.733161],"type":"Point"}
}