{
  "type": "Feature",
  "properties": {
    "addr:full":"4612 Woodfield Rd Bethesda MD 20814",
    "addr:housenumber":"4612",
    "addr:postcode":"20814",
    "addr:street":"Woodfield Rd",
    "iso:country":"US",
    "sg:address":"4612 Woodfield Rd",
    "sg:city":"Bethesda",
    "sg:classifiers":[
        {
            "category":"Real Estate",
            "subcategory":"Real Estate Agent",
            "type":"Services"
        }
    ],
    "sg:phone":"+1 301 530 5556",
    "sg:postcode":"20814",
    "sg:province":"MD",
    "sg:tags":[
        "appraiser"
    ],
    "wof:name":"Byars Appraisal Svc",
    "wof:placetype":"venue"
},
  "geometry": {"coordinates":[-77.094813,39.020152],"type":"Point"}
}