{
  "type": "Feature",
  "properties": {
    "iso:country":"US",
    "sg:address":"10820 Gilroy Rd",
    "sg:city":"Hunt Valley",
    "sg:classifiers":[
        {
            "category":"Professional",
            "subcategory":"Employment Agencies",
            "type":"Services"
        }
    ],
    "sg:phone":"+1 301 362 2250",
    "sg:postcode":"21031",
    "sg:province":"MD",
    "wof:name":"Think Big",
    "wof:placetype":"venue"
},
  "geometry": {"coordinates":[-76.66273200000001,39.479272],"type":"Point"}
}