{
  "type": "Feature",
  "properties": {
    "addr:full":"9711 Medical Center Dr Ste. 307 Rockville MD 20850",
    "addr:housenumber":"9711",
    "addr:postcode":"20850",
    "addr:street":"Medical Center Dr Ste. 307",
    "iso:country":"US",
    "sg:address":"9711 Medical Center Dr Ste. 307",
    "sg:city":"Rockville",
    "sg:classifiers":[
        {
            "category":"Health Services",
            "subcategory":"Doctor",
            "type":"Services"
        },
        {
            "category":"Personal",
            "subcategory":"Skin Care",
            "type":"Services"
        }
    ],
    "sg:phone":"+1 301 838 4303",
    "sg:postcode":"20850",
    "sg:province":"MD",
    "sg:tags":[
        "dermatology",
        "physician",
        "surgery",
        "laser",
        "surgeons"
    ],
    "sg:website":"http://liottaderm.com",
    "wof:name":"Elizabeth A. Liotta, MD",
    "wof:placetype":"venue"
},
  "geometry": {"coordinates":[-77.19508399999999,39.099499],"type":"Point"}
}