{
  "type": "Feature",
  "properties": {
    "iso:country":"US",
    "sg:address":"11466 Cherry Hill Rd",
    "sg:city":"Beltsville",
    "sg:classifiers":[
        {
            "category":"Wholesale",
            "subcategory":"Machinery & Supplies",
            "type":"Manufacturing & Wholesale Goods"
        }
    ],
    "sg:phone":"+1 301 595 1701",
    "sg:postcode":"20705",
    "sg:province":"MD",
    "sg:tags":[
        "salon",
        "cosmetic",
        "beauty"
    ],
    "wof:name":"Mama's Beauty Supply",
    "wof:placetype":"venue"
},
  "geometry": {"coordinates":[-76.951599,39.045502],"type":"Point"}
}