{
  "type": "Feature",
  "properties": {
    "addr:full":"422 S Taylor Ave Essex MD 21221",
    "addr:housenumber":"422",
    "addr:postcode":"21221",
    "addr:street":"S Taylor Ave",
    "iso:country":"US",
    "sg:address":"422 S Taylor Ave",
    "sg:city":"Essex",
    "sg:classifiers":[
        {
            "category":"Government",
            "subcategory":"Post Office",
            "type":"Public Place"
        }
    ],
    "sg:phone":"+1 410 780 2657",
    "sg:postcode":"21221",
    "sg:province":"MD",
    "sg:tags":[
        "delivery",
        "courier"
    ],
    "wof:name":"D And B White Deliveries",
    "wof:placetype":"venue"
},
  "geometry": {"coordinates":[-76.47219800000001,39.301912],"type":"Point"}
}