{
  "type": "Feature",
  "properties": {
    "addr:full":"915 Belgian Ave Baltimore MD 21218",
    "addr:housenumber":"915",
    "addr:postcode":"21218",
    "addr:street":"Belgian Ave",
    "iso:country":"US",
    "sg:address":"915 Belgian Ave",
    "sg:city":"Baltimore",
    "sg:classifiers":[
        {
            "category":"Wholesale",
            "subcategory":"Vending Machines",
            "type":"Manufacturing & Wholesale Goods"
        }
    ],
    "sg:phone":"+1 410 433 7562",
    "sg:postcode":"21218",
    "sg:province":"MD",
    "sg:tags":[
        "operator"
    ],
    "wof:name":"Tasty Treats Vending Dist",
    "wof:placetype":"venue"
},
  "geometry": {"coordinates":[-76.601247,39.340453],"type":"Point"}
}