{
  "type": "Feature",
  "properties": {
    "iso:country":"US",
    "sg:address":"12 W 3rd St",
    "sg:city":"Frederick",
    "sg:classifiers":[
        {
            "category":"Travel",
            "subcategory":"Hotels & Motels",
            "type":"Entertainment"
        }
    ],
    "sg:phone":"+1 301 682 4111",
    "sg:postcode":"21701",
    "sg:province":"MD",
    "sg:tags":[
        "breakfast",
        "accommodation",
        "bed"
    ],
    "wof:name":"Hill House Bed & Breakfast",
    "wof:placetype":"venue"
},
  "geometry": {"coordinates":[-77.411619,39.417844],"type":"Point"}
}