{
  "type": "Feature",
  "properties": {
    "addr:full":"6115 Central Ave Capitol Heights MD 20743",
    "addr:housenumber":"6115",
    "addr:postcode":"20743",
    "addr:street":"Central Ave",
    "iso:country":"US",
    "sg:address":"6115 Central Ave",
    "sg:city":"Capitol Heights",
    "sg:classifiers":[
        {
            "category":"Food & Beverages",
            "subcategory":"Liquor & Beverages",
            "type":"Retail Goods"
        }
    ],
    "sg:phone":"+1 301 333 1990",
    "sg:postcode":"20743",
    "sg:province":"MD",
    "wof:name":"Central Avenue Liquors",
    "wof:placetype":"venue"
},
  "geometry": {"coordinates":[-76.90879200000001,38.885253],"type":"Point"}
}