{
  "type": "Feature",
  "properties": {
    "iso:country":"US",
    "sg:address":"861 W 36th St",
    "sg:city":"Baltimore",
    "sg:classifiers":[
        {
            "category":"Personal",
            "subcategory":"Skin Care",
            "type":"Services"
        }
    ],
    "sg:phone":"+1 443 803 2563",
    "sg:postcode":"21211",
    "sg:province":"MD",
    "sg:website":"www.charmcityskin.com",
    "wof:name":"Charm City Skin",
    "wof:placetype":"venue"
},
  "geometry": {"coordinates":[-76.630979,39.330951],"type":"Point"}
}