{
  "type": "Feature",
  "properties": {
    "iso:country":"US",
    "sg:address":"138 E Lake Dr",
    "sg:city":"Annapolis",
    "sg:classifiers":[
        {
            "category":"Professional",
            "subcategory":"Computer Services",
            "type":"Services"
        }
    ],
    "sg:phone":"+1 301 858 5019",
    "sg:postcode":"21403",
    "sg:province":"MD",
    "sg:tags":[
        "related"
    ],
    "wof:name":"HP",
    "wof:placetype":"venue"
},
  "geometry": {"coordinates":[-76.459097,38.939654],"type":"Point"}
}