{
  "type": "Feature",
  "properties": {
    "iso:country":"US",
    "sg:address":"1009 Radiance Dr",
    "sg:city":"Cambridge",
    "sg:classifiers":[
        {
            "category":"Professional",
            "type":"Services"
        }
    ],
    "sg:phone":"+1 443 521 0969",
    "sg:postcode":"21613",
    "sg:province":"MD",
    "sg:tags":[
        "establishment"
    ],
    "wof:name":"Thomas & Thomas",
    "wof:placetype":"venue"
},
  "geometry": {"coordinates":[-76.057759,38.567885],"type":"Point"}
}