{
  "type": "Feature",
  "properties": {
    "addr:full":"404 W Saratoga St Baltimore MD 21201",
    "addr:housenumber":"404",
    "addr:postcode":"21201",
    "addr:street":"W Saratoga St",
    "iso:country":"US",
    "sg:address":"404 W Saratoga St",
    "sg:city":"Baltimore",
    "sg:classifiers":[
        {
            "category":"Building & Trades",
            "subcategory":"Locksmith",
            "type":"Services"
        }
    ],
    "sg:phone":"+1 443 378 3981",
    "sg:postcode":"21201",
    "sg:province":"MD",
    "sg:tags":[
        "key"
    ],
    "wof:name":"Acl Baltimore Locksmith",
    "wof:placetype":"venue"
},
  "geometry": {"coordinates":[-76.621379,39.292967],"type":"Point"}
}