{
  "type": "Feature",
  "properties": {
    "iso:country":"US",
    "sg:address":"1627 E Fort Ave",
    "sg:city":"Baltimore",
    "sg:classifiers":[
        {
            "category":"Recreation",
            "type":"Entertainment"
        }
    ],
    "sg:phone":"+1 410 837 4423",
    "sg:postcode":"21230",
    "sg:province":"MD",
    "sg:tags":[
        "sport",
        "amateur",
        "center",
        "team"
    ],
    "wof:name":"Locust Point Recreation",
    "wof:placetype":"venue"
},
  "geometry": {"coordinates":[-76.59169799999999,39.2682],"type":"Point"}
}