{
  "type": "Feature",
  "properties": {
    "iso:country":"US",
    "sg:address":"14470 Solomons Island Road",
    "sg:city":"Solomons",
    "sg:classifiers":[
        {
            "category":"Restaurant",
            "type":"Food & Drink"
        }
    ],
    "sg:menulink":"http://www.allmenus.com/md/solomons-island/270127-catamarans-restaurant/menu/",
    "sg:phone":"+1 410 326 8399",
    "sg:postcode":"20688",
    "sg:province":"MD",
    "sg:tags":[
        "seafood",
        "american"
    ],
    "wof:name":"Catamarans Restaurant",
    "wof:placetype":"venue"
},
  "geometry": {"coordinates":[-76.46033,38.323544],"type":"Point"}
}