{
  "type": "Feature",
  "properties": {
    "iso:country":"US",
    "sg:address":"45155 First Colony Way",
    "sg:city":"California",
    "sg:classifiers":[
        {
            "category":"Shopping",
            "subcategory":"Department Store",
            "type":"Retail Goods"
        }
    ],
    "sg:phone":"+1 301 862 5003",
    "sg:postcode":"20619",
    "sg:province":"MD",
    "wof:name":"Target Stores Store Information",
    "wof:placetype":"venue"
},
  "geometry": {"coordinates":[-76.5158,38.299702],"type":"Point"}
}