{
  "type": "Feature",
  "properties": {
    "addr:full":"7800 Penn Western Ct Upper Marlboro MD 20772",
    "addr:housenumber":"7800",
    "addr:postcode":"20772",
    "addr:street":"Penn Western Ct",
    "iso:country":"US",
    "sg:address":"7800 Penn Western Ct",
    "sg:city":"Upper Marlboro",
    "sg:classifiers":[
        {
            "category":"Building & Trades",
            "subcategory":"Construction",
            "type":"Services"
        }
    ],
    "sg:phone":"+1 301 516 1600",
    "sg:postcode":"20772",
    "sg:province":"MD",
    "sg:tags":[
        "concrete",
        "contractor"
    ],
    "wof:name":"Romano Concrete Construction",
    "wof:placetype":"venue"
},
  "geometry": {"coordinates":[-76.86842300000001,38.83423],"type":"Point"}
}