{
  "type": "Feature",
  "properties": {
    "iso:country":"US",
    "sg:address":"7839 Eastpoint Mall",
    "sg:city":"Baltimore",
    "sg:classifiers":[
        {
            "category":"Shopping",
            "subcategory":"Beauty & Cosmetics",
            "type":"Retail Goods"
        },
        {
            "category":"Food & Beverages",
            "subcategory":"Groceries & Convenience Stores",
            "type":"Retail Goods"
        }
    ],
    "sg:phone":"+1 410 285 7124",
    "sg:postcode":"21224",
    "sg:province":"MD",
    "sg:tags":[
        "perfume",
        "salons-equipment",
        "supply"
    ],
    "wof:name":"Perfumeri International",
    "wof:placetype":"venue"
},
  "geometry": {"coordinates":[-76.509697,39.291901],"type":"Point"}
}