{
  "type": "Feature",
  "properties": {
    "iso:country":"US",
    "sg:address":"108 Old Solomons Island Rd",
    "sg:city":"Annapolis",
    "sg:classifiers":[
        {
            "category":"Professional",
            "subcategory":"Accounting & Tax Preparation",
            "type":"Services"
        }
    ],
    "sg:phone":"+1 410 573 1521",
    "sg:postcode":"21401",
    "sg:province":"MD",
    "sg:tags":[
        "accountant"
    ],
    "wof:name":"Hansen & Hansen Pa TAX Svc",
    "wof:placetype":"venue"
},
  "geometry": {"coordinates":[-76.538311,38.976961],"type":"Point"}
}