{
  "type": "Feature",
  "properties": {
    "addr:full":"1413 Sharps Point Rd Annapolis MD 21401",
    "addr:housenumber":"1413",
    "addr:postcode":"21401",
    "addr:street":"Sharps Point Rd",
    "iso:country":"US",
    "sg:address":"1413 Sharps Point Rd",
    "sg:city":"Annapolis",
    "sg:classifiers":[
        {
            "category":"Professional",
            "subcategory":"Management & Consulting",
            "type":"Services"
        }
    ],
    "sg:phone":"+1 410 757 5040",
    "sg:postcode":"21401",
    "sg:province":"MD",
    "sg:tags":[
        "business"
    ],
    "wof:name":"H U W A International",
    "wof:placetype":"venue"
},
  "geometry": {"coordinates":[-76.437327,38.998036],"type":"Point"}
}