{
  "type": "Feature",
  "properties": {
    "addr:full":"530 N Pennsylvania Ave Hancock MD 21750",
    "addr:housenumber":"530",
    "addr:postcode":"21750",
    "addr:street":"N Pennsylvania Ave",
    "iso:country":"US",
    "sg:address":"530 N Pennsylvania Ave",
    "sg:city":"Hancock",
    "sg:classifiers":[
        {
            "category":"Place Of Worship",
            "type":"Public Place"
        }
    ],
    "sg:phone":"+1 301 678 5589",
    "sg:postcode":"21750",
    "sg:province":"MD",
    "sg:tags":[
        "church"
    ],
    "wof:name":"The Hancock Grace Church Of The Nazarene",
    "wof:placetype":"venue"
},
  "geometry": {"coordinates":[-78.171969,39.720936],"type":"Point"}
}