{
  "type": "Feature",
  "properties": {
    "iso:country":"US",
    "sg:address":"3511 Stark St",
    "sg:city":"Kensington",
    "sg:classifiers":[
        {
            "category":"Education",
            "subcategory":"Library",
            "type":"Public Place"
        }
    ],
    "sg:phone":"+1 301 962 3285",
    "sg:postcode":"20895",
    "sg:province":"MD",
    "sg:tags":[
        "reading",
        "instruction"
    ],
    "wof:name":"Sonja Reading Smith Specialist",
    "wof:placetype":"venue"
},
  "geometry": {"coordinates":[-77.070127,39.041678],"type":"Point"}
}