{
  "type": "Feature",
  "properties": {
    "addr:full":"6 Howard St Aberdeen MD 21001",
    "addr:housenumber":"6",
    "addr:postcode":"21001",
    "addr:street":"Howard St",
    "iso:country":"US",
    "sg:address":"6 Howard St",
    "sg:city":"Aberdeen",
    "sg:classifiers":[
        {
            "category":"Health Services",
            "subcategory":"Doctor",
            "type":"Services"
        }
    ],
    "sg:phone":"+1 410 272 2783",
    "sg:postcode":"21001",
    "sg:province":"MD",
    "sg:tags":[
        "dentist"
    ],
    "sg:website":"www.bayareadental.net",
    "wof:name":"Bay Area Dental Assoc",
    "wof:placetype":"venue"
},
  "geometry": {"coordinates":[-76.164177,39.509859],"type":"Point"}
}