{
  "type": "Feature",
  "properties": {
    "iso:country":"US",
    "sg:address":"10117 Treetop Ln",
    "sg:city":"Lanham",
    "sg:classifiers":[
        {
            "category":"Travel",
            "subcategory":"Travel Agent",
            "type":"Entertainment"
        }
    ],
    "sg:phone":"+1 301 794 3400",
    "sg:postcode":"20706",
    "sg:province":"MD",
    "sg:tags":[
        "agency",
        "bureau"
    ],
    "wof:name":"Volant World Travel",
    "wof:placetype":"venue"
},
  "geometry": {"coordinates":[-76.83142700000001,38.982671],"type":"Point"}
}