{
  "type": "Feature",
  "properties": {
    "iso:country":"US",
    "sg:address":"8633 Loch Raven Blvd",
    "sg:city":"Baltimore",
    "sg:classifiers":[
        {
            "category":"Professional",
            "type":"Services"
        }
    ],
    "sg:phone":"+1 410 661 1201",
    "sg:postcode":"21286",
    "sg:province":"MD",
    "sg:tags":[
        "establishment"
    ],
    "wof:name":"Cripson Enterprise",
    "wof:placetype":"venue"
},
  "geometry": {"coordinates":[-76.563301,39.397262],"type":"Point"}
}