{
  "type": "Feature",
  "properties": {
    "addr:full":"5602 Baltimore National Pike Catonsville MD 21228",
    "addr:housenumber":"5602",
    "addr:postcode":"21228",
    "addr:street":"Baltimore National Pike",
    "iso:country":"US",
    "sg:address":"5602 Baltimore National Pike",
    "sg:city":"Catonsville",
    "sg:classifiers":[
        {
            "category":"Health Services",
            "subcategory":"Hospital",
            "type":"Services"
        }
    ],
    "sg:phone":"+1 410 455 9967",
    "sg:postcode":"21228",
    "sg:province":"MD",
    "sg:tags":[
        "mental"
    ],
    "wof:name":"Child & Family Therapy Inc",
    "wof:placetype":"venue"
},
  "geometry": {"coordinates":[-76.725972,39.289655],"type":"Point"}
}