{
  "type": "Feature",
  "properties": {
    "iso:country":"US",
    "sg:address":"121 Peddlers Ln",
    "sg:city":"Earleville",
    "sg:classifiers":[
        {
            "category":"Professional",
            "subcategory":"Management & Consulting",
            "type":"Services"
        }
    ],
    "sg:phone":"+1 410 275 2329",
    "sg:postcode":"21919",
    "sg:province":"MD",
    "sg:tags":[
        "consultant",
        "business"
    ],
    "wof:name":"Boyer Management Svc",
    "wof:placetype":"venue"
},
  "geometry": {"coordinates":[-75.91758299999999,39.414658],"type":"Point"}
}