{
  "type": "Feature",
  "properties": {
    "addr:full":"525 Northern Ave Hagerstown MD 21742",
    "addr:housenumber":"525",
    "addr:postcode":"21742",
    "addr:street":"Northern Ave",
    "iso:country":"US",
    "sg:address":"525 Northern Ave",
    "sg:city":"Hagerstown",
    "sg:classifiers":[
        {
            "category":"Home & Garden",
            "subcategory":"Furniture",
            "type":"Retail Goods"
        }
    ],
    "sg:phone":"+1 301 739 8084",
    "sg:postcode":"21742",
    "sg:province":"MD",
    "sg:tags":[
        "equipment",
        "kitchen",
        "cabinet"
    ],
    "sg:website":"www.jdkitchen.com",
    "wof:name":"J & D Kitchen",
    "wof:placetype":"venue"
},
  "geometry": {"coordinates":[-77.709431,39.664494],"type":"Point"}
}