{
  "type": "Feature",
  "properties": {
    "addr:full":"6408 Arundel Cove Ave Baltimore MD 21226",
    "addr:housenumber":"6408",
    "addr:postcode":"21226",
    "addr:street":"Arundel Cove Ave",
    "iso:country":"US",
    "sg:address":"6408 Arundel Cove Ave",
    "sg:city":"Baltimore",
    "sg:classifiers":[
        {
            "category":"Freight",
            "type":"Transportation"
        }
    ],
    "sg:phone":"+1 410 354 1788",
    "sg:postcode":"21226",
    "sg:province":"MD",
    "wof:name":"Baltimore International Trnspt",
    "wof:placetype":"venue"
},
  "geometry": {"coordinates":[-76.56752400000001,39.202046],"type":"Point"}
}