{
  "type": "Feature",
  "properties": {
    "iso:country":"US",
    "sg:address":"311 Prospect Bay Dr W",
    "sg:city":"Grasonville",
    "sg:classifiers":[
        {
            "category":"Building & Trades",
            "subcategory":"Construction",
            "type":"Services"
        },
        {
            "category":"Manufacturing",
            "subcategory":"Building Materials",
            "type":"Manufacturing & Wholesale Goods"
        }
    ],
    "sg:phone":"+1 410 827 5525",
    "sg:postcode":"21638",
    "sg:province":"MD",
    "sg:tags":[
        "roofing",
        "sheet",
        "work",
        "metal",
        "contractor",
        "siding"
    ],
    "wof:name":"Willow Construction",
    "wof:placetype":"venue"
},
  "geometry": {"coordinates":[-76.19387500000001,38.915646],"type":"Point"}
}