{
  "type": "Feature",
  "properties": {
    "addr:full":"7100 Landover Rd Hyattsville MD 20781",
    "addr:housenumber":"7100",
    "addr:postcode":"20781",
    "addr:street":"Landover Rd",
    "iso:country":"US",
    "sg:address":"7100 Landover Rd",
    "sg:city":"Hyattsville",
    "sg:classifiers":[
        {
            "category":"Autos & Motor Vehicles",
            "subcategory":"Auto Supplies",
            "type":"Retail Goods"
        }
    ],
    "sg:phone":"+1 301 386 0813",
    "sg:postcode":"20781",
    "sg:province":"MD",
    "sg:tags":[
        "tire"
    ],
    "wof:name":"American Tire",
    "wof:placetype":"venue"
},
  "geometry": {"coordinates":[-76.89107799999999,38.927698],"type":"Point"}
}