{
  "type": "Feature",
  "properties": {
    "addr:full":"3135 Singerly Rd Elkton MD 21921",
    "addr:housenumber":"3135",
    "addr:postcode":"21921",
    "addr:street":"Singerly Rd",
    "iso:country":"US",
    "sg:address":"3135 Singerly Rd",
    "sg:city":"Elkton",
    "sg:classifiers":[
        {
            "category":"Food & Beverages",
            "subcategory":"Liquor & Beverages",
            "type":"Retail Goods"
        }
    ],
    "sg:phone":"+1 410 392 4169",
    "sg:postcode":"21921",
    "sg:province":"MD",
    "wof:name":"Fair Hill Discount Liquors",
    "wof:placetype":"venue"
},
  "geometry": {"coordinates":[-75.866928,39.692363],"type":"Point"}
}