{
  "type": "Feature",
  "properties": {
    "iso:country":"US",
    "sg:address":"4236 Elsa Ter",
    "sg:city":"Baltimore",
    "sg:classifiers":[
        {
            "category":"Professional",
            "subcategory":"Advertising",
            "type":"Services"
        }
    ],
    "sg:phone":"+1 410 878 2406",
    "sg:postcode":"21211",
    "sg:province":"MD",
    "sg:tags":[
        "agency",
        "specialty"
    ],
    "wof:name":"Faye Write Write",
    "wof:placetype":"venue"
},
  "geometry": {"coordinates":[-76.64054,39.339832],"type":"Point"}
}