{
  "type": "Feature",
  "properties": {
    "addr:full":"1500 Southview Dr Oxon Hill MD 20745",
    "addr:housenumber":"1500",
    "addr:postcode":"20745",
    "addr:street":"Southview Dr",
    "iso:country":"US",
    "sg:address":"1500 Southview Dr",
    "sg:city":"Oxon Hill",
    "sg:classifiers":[
        {
            "category":"Building & Trades",
            "subcategory":"Construction",
            "type":"Services"
        }
    ],
    "sg:phone":"+1 240 447 1531",
    "sg:postcode":"20745",
    "sg:province":"MD",
    "sg:tags":[
        "hanging",
        "contractor"
    ],
    "wof:name":"Ted Painting & Drywall Finish",
    "wof:placetype":"venue"
},
  "geometry": {"coordinates":[-76.98665699999999,38.826822],"type":"Point"}
}