{
  "type": "Feature",
  "properties": {
    "addr:full":"141 E Patrick St Frederick MD 21701",
    "addr:housenumber":"141",
    "addr:postcode":"21701",
    "addr:street":"E Patrick St",
    "iso:country":"US",
    "sg:address":"141 E Patrick St",
    "sg:city":"Frederick",
    "sg:classifiers":[
        {
            "category":"Wholesale",
            "subcategory":"Computers",
            "type":"Manufacturing & Wholesale Goods"
        }
    ],
    "sg:phone":"+1 301 682 3204",
    "sg:postcode":"21701",
    "sg:province":"MD",
    "wof:name":"Xtria",
    "wof:placetype":"venue"
},
  "geometry": {"coordinates":[-77.40856700000001,39.414102],"type":"Point"}
}