{
  "type": "Feature",
  "properties": {
    "addr:full":"1290 Smallwood Dr W Waldorf MD 20603",
    "addr:housenumber":"1290",
    "addr:postcode":"20603",
    "addr:street":"Smallwood Dr W",
    "iso:country":"US",
    "sg:address":"1290 Smallwood Dr W",
    "sg:city":"Waldorf",
    "sg:classifiers":[
        {
            "category":"Restaurant",
            "type":"Food & Drink"
        }
    ],
    "sg:phone":"+1 301 645 1534",
    "sg:postcode":"20603",
    "sg:province":"MD",
    "sg:website":"www.oldieslegends.net",
    "wof:name":"Legends Of Waldorf",
    "wof:placetype":"venue"
},
  "geometry": {"coordinates":[-76.926866,38.612598],"type":"Point"}
}