{
  "type": "Feature",
  "properties": {
    "addr:full":"9602 Martin Luther King Jr Hwy Lanham MD 20706",
    "addr:housenumber":"9602",
    "addr:postcode":"20706",
    "addr:street":"Martin Luther King Jr Hwy",
    "iso:country":"US",
    "sg:address":"9602 Martin Luther King Jr Hwy",
    "sg:city":"Lanham",
    "sg:classifiers":[
        {
            "category":"Professional",
            "type":"Services"
        }
    ],
    "sg:phone":"+1 301 731 6031",
    "sg:postcode":"20706",
    "sg:province":"MD",
    "sg:tags":[
        "establishment"
    ],
    "wof:name":"Primehealth Corp",
    "wof:placetype":"venue"
},
  "geometry": {"coordinates":[-76.838853,38.950235],"type":"Point"}
}