{
  "type": "Feature",
  "properties": {
    "addr:full":"5611 Glen Hill Ct Jefferson MD 21755",
    "addr:housenumber":"5611",
    "addr:postcode":"21755",
    "addr:street":"Glen Hill Ct",
    "iso:country":"US",
    "sg:address":"5611 Glen Hill Ct",
    "sg:city":"Jefferson",
    "sg:classifiers":[
        {
            "category":"Building & Trades",
            "subcategory":"Electrical",
            "type":"Services"
        }
    ],
    "sg:phone":"+1 301 371 5403",
    "sg:postcode":"21755",
    "sg:province":"MD",
    "sg:tags":[
        "electrical",
        "contractor"
    ],
    "wof:name":"Crone Electric Service",
    "wof:placetype":"venue"
},
  "geometry": {"coordinates":[-77.542451,39.389642],"type":"Point"}
}