{
  "type": "Feature",
  "properties": {
    "addr:full":"10316 Democracy Ln Potomac MD 20854",
    "addr:housenumber":"10316",
    "addr:postcode":"20854",
    "addr:street":"Democracy Ln",
    "iso:country":"US",
    "sg:address":"10316 Democracy Ln",
    "sg:city":"Potomac",
    "sg:classifiers":[
        {
            "category":"Professional",
            "subcategory":"Business Services",
            "type":"Services"
        }
    ],
    "sg:phone":"+1 301 365 5505",
    "sg:postcode":"20854",
    "sg:province":"MD",
    "wof:name":"Brob Enterprises Inc",
    "wof:placetype":"venue"
},
  "geometry": {"coordinates":[-77.16471799999999,39.023161],"type":"Point"}
}