{
  "type": "Feature",
  "properties": {
    "addr:full":"11116 Liberty Rd Randallstown MD 21133",
    "addr:housenumber":"11116",
    "addr:postcode":"21133",
    "addr:street":"Liberty Rd",
    "iso:country":"US",
    "sg:address":"11116 Liberty Rd",
    "sg:city":"Randallstown",
    "sg:classifiers":[
        {
            "category":"Real Estate",
            "subcategory":"Developer",
            "type":"Services"
        }
    ],
    "sg:phone":"+1 410 922 4441",
    "sg:postcode":"21133",
    "sg:province":"MD",
    "sg:tags":[
        "cemetery",
        "religious",
        "organization"
    ],
    "wof:name":"Wards Chapel Cemetery Assn",
    "wof:placetype":"venue"
},
  "geometry": {"coordinates":[-76.864777,39.395938],"type":"Point"}
}