{
  "type": "Feature",
  "properties": {
    "iso:country":"US",
    "sg:address":"567 Glendale Rd",
    "sg:city":"Oakland",
    "sg:classifiers":[
        {
            "category":"Restaurant",
            "type":"Food & Drink"
        }
    ],
    "sg:phone":"+1 301 387 5524",
    "sg:postcode":"21550",
    "sg:province":"MD",
    "wof:name":"Silver Tree Inn",
    "wof:placetype":"venue"
},
  "geometry": {"coordinates":[-79.317159,39.501957],"type":"Point"}
}