{
  "type": "Feature",
  "properties": {
    "iso:country":"US",
    "sg:address":"2300 N Salisbury Blvd",
    "sg:city":"Salisbury",
    "sg:classifiers":[
        {
            "category":"Manufacturing",
            "subcategory":"Apparel",
            "type":"Manufacturing & Wholesale Goods"
        }
    ],
    "sg:phone":"+1 410 334 2619",
    "sg:postcode":"21801",
    "sg:province":"MD",
    "wof:name":"Expressive Threads",
    "wof:placetype":"venue"
},
  "geometry": {"coordinates":[-75.571454,38.398448],"type":"Point"}
}