{
  "type": "Feature",
  "properties": {
    "iso:country":"US",
    "sg:address":"2109 Meghan Ct",
    "sg:city":"Crofton",
    "sg:classifiers":[
        {
            "category":"Professional",
            "subcategory":"Advertising",
            "type":"Services"
        }
    ],
    "sg:phone":"+1 301 858 0077",
    "sg:postcode":"21114",
    "sg:province":"MD",
    "sg:tags":[
        "counselor"
    ],
    "wof:name":"Ole Advertising",
    "wof:placetype":"venue"
},
  "geometry": {"coordinates":[-76.699416,38.994476],"type":"Point"}
}