{
  "type": "Feature",
  "properties": {
    "iso:country":"US",
    "sg:address":"4818 Drummond Ave",
    "sg:city":"Chevy Chase",
    "sg:classifiers":[
        {
            "category":"Professional",
            "subcategory":"Business Services",
            "type":"Services"
        }
    ],
    "sg:phone":"+1 301 657 1480",
    "sg:postcode":"20815",
    "sg:province":"MD",
    "wof:name":"Brandon Roberts + Associates",
    "wof:placetype":"venue"
},
  "geometry": {"coordinates":[-77.09567199999999,38.970163],"type":"Point"}
}