{
  "type": "Feature",
  "properties": {
    "addr:full":"2370 Solomons Island Rd Annapolis MD 21401",
    "addr:housenumber":"2370",
    "addr:postcode":"21401",
    "addr:street":"Solomons Island Rd",
    "iso:country":"US",
    "sg:address":"2370 Solomons Island Rd",
    "sg:city":"Annapolis",
    "sg:classifiers":[
        {
            "category":"Autos & Motor Vehicles",
            "subcategory":"Fuel & Gas Station",
            "type":"Retail Goods"
        }
    ],
    "sg:phone":"+1 410 224 3828",
    "sg:postcode":"21401",
    "sg:province":"MD",
    "sg:tags":[
        "oil"
    ],
    "wof:name":"Bowen's Parole Svc",
    "wof:placetype":"venue"
},
  "geometry": {"coordinates":[-76.537932,38.980379],"type":"Point"}
}