{
  "type": "Feature",
  "properties": {
    "addr:full":"11360 River Rd Ridgely MD 21660",
    "addr:housenumber":"11360",
    "addr:postcode":"21660",
    "addr:street":"River Rd",
    "iso:country":"US",
    "sg:address":"11360 River Rd",
    "sg:city":"Ridgely",
    "sg:classifiers":[
        {
            "category":"Professional",
            "type":"Services"
        }
    ],
    "sg:phone":"+1 410 479 0785",
    "sg:postcode":"21660",
    "sg:province":"MD",
    "sg:tags":[
        "transportation"
    ],
    "wof:name":"Werner Transport",
    "wof:placetype":"venue"
},
  "geometry": {"coordinates":[-75.837649,38.918459],"type":"Point"}
}