{
  "type": "Feature",
  "properties": {
    "addr:full":"9328 Alcona St Lanham MD 20706",
    "addr:housenumber":"9328",
    "addr:postcode":"20706",
    "addr:street":"Alcona St",
    "iso:country":"US",
    "sg:address":"9328 Alcona St",
    "sg:city":"Lanham",
    "sg:classifiers":[
        {
            "category":"Professional",
            "subcategory":"Management & Consulting",
            "type":"Services"
        }
    ],
    "sg:phone":"+1 301 429 3178",
    "sg:postcode":"20706",
    "sg:province":"MD",
    "sg:tags":[
        "logistics",
        "conference",
        "planning",
        "for"
    ],
    "wof:name":"Dream Weavers LLC",
    "wof:placetype":"venue"
},
  "geometry": {"coordinates":[-76.841846,38.959216],"type":"Point"}
}