{
  "type": "Feature",
  "properties": {
    "addr:full":"1350 Marshall St Hagerstown MD 21740",
    "addr:housenumber":"1350",
    "addr:postcode":"21740",
    "addr:street":"Marshall St",
    "iso:country":"US",
    "sg:address":"1350 Marshall St",
    "sg:city":"Hagerstown",
    "sg:classifiers":[
        {
            "category":"Education",
            "subcategory":"School",
            "type":"Public Place"
        }
    ],
    "sg:phone":"+1 301 766 8214",
    "sg:postcode":"21740",
    "sg:province":"MD",
    "wof:name":"Marshall Street School",
    "wof:placetype":"venue"
},
  "geometry": {"coordinates":[-77.732152,39.661493],"type":"Point"}
}