{
  "type": "Feature",
  "properties": {
    "addr:full":"5940 Frederick Crossing Ln Frederick MD 21704",
    "addr:housenumber":"5940",
    "addr:postcode":"21704",
    "addr:street":"Frederick Crossing Ln",
    "iso:country":"US",
    "sg:address":"5940 Frederick Crossing Ln",
    "sg:city":"Frederick",
    "sg:classifiers":[
        {
            "category":"Communications",
            "subcategory":"Radio Station",
            "type":"Services"
        }
    ],
    "sg:phone":"+1 301 668 0800",
    "sg:postcode":"21704",
    "sg:province":"MD",
    "sg:tags":[
        "company",
        "broadcasting"
    ],
    "wof:name":"Maryland Radio Inc",
    "wof:placetype":"venue"
},
  "geometry": {"coordinates":[-77.413096,39.395086],"type":"Point"}
}