{
  "type": "Feature",
  "properties": {
    "iso:country":"US",
    "sg:address":"138 N Hickory Ave",
    "sg:city":"Bel Air",
    "sg:classifiers":[
        {
            "category":"Health Services",
            "subcategory":"Health Practitioner",
            "type":"Services"
        }
    ],
    "sg:phone":"+1 410 879 6571",
    "sg:postcode":"21014",
    "sg:province":"MD",
    "sg:tags":[
        "nurse",
        "registry"
    ],
    "wof:name":"PRN Inc",
    "wof:placetype":"venue"
},
  "geometry": {"coordinates":[-76.349401,39.541649],"type":"Point"}
}