{
  "type": "Feature",
  "properties": {
    "iso:country":"US",
    "sg:address":"1053 Rockville Pike",
    "sg:city":"Rockville",
    "sg:classifiers":[
        {
            "category":"Government",
            "subcategory":"Office",
            "type":"Public Place"
        }
    ],
    "sg:phone":"+1 301 738 2383",
    "sg:postcode":"20852",
    "sg:province":"MD",
    "sg:tags":[
        "armed",
        "force",
        "recruiting"
    ],
    "wof:name":"Air Force Recruiting",
    "wof:placetype":"venue"
},
  "geometry": {"coordinates":[-77.132559,39.07147],"type":"Point"}
}