{
  "type": "Feature",
  "properties": {
    "iso:country":"US",
    "sg:address":"1107 Kenilworth Dr Ste 202",
    "sg:city":"Towson",
    "sg:classifiers":[
        {
            "category":"Organizations",
            "subcategory":"Non-profit Organization",
            "type":"Services"
        }
    ],
    "sg:phone":"+1 410 494 8545",
    "sg:postcode":"21204",
    "sg:province":"MD",
    "sg:tags":[
        "fund",
        "raising"
    ],
    "sg:website":"http://www.kidneymd.org",
    "wof:name":"Kidney Foundation Of Maryland",
    "wof:placetype":"venue"
},
  "geometry": {"coordinates":[-76.627999,39.413573],"type":"Point"}
}