{
  "type": "Feature",
  "properties": {
    "addr:full":"3882 Jefferson Pike Jefferson MD 21755",
    "addr:housenumber":"3882",
    "addr:postcode":"21755",
    "addr:street":"Jefferson Pike",
    "iso:country":"US",
    "sg:address":"3882 Jefferson Pike",
    "sg:city":"Jefferson",
    "sg:classifiers":[
        {
            "category":"Place Of Worship",
            "subcategory":"Church",
            "type":"Public Place"
        },
        {
            "category":"Place Of Worship",
            "type":"Public Place"
        }
    ],
    "sg:phone":"+1 301 473 4022",
    "sg:postcode":"21755",
    "sg:province":"MD",
    "sg:tags":[
        "churches-methodist"
    ],
    "wof:name":"Jefferson United Methodist Church",
    "wof:placetype":"venue"
},
  "geometry": {"coordinates":[-77.533276,39.361888],"type":"Point"}
}