{
  "type": "Feature",
  "properties": {
    "iso:country":"US",
    "sg:address":"9710 Sutherland Rd",
    "sg:city":"Silver Spring",
    "sg:classifiers":[
        {
            "category":"Insurance",
            "subcategory":"Insurance Agent",
            "type":"Services"
        }
    ],
    "sg:phone":"+1 301 588 9340",
    "sg:postcode":"20901",
    "sg:province":"MD",
    "sg:website":"www.dbgolf.com",
    "wof:name":"Rjm Assoc",
    "wof:placetype":"venue"
},
  "geometry": {"coordinates":[-77.01853300000001,39.015197],"type":"Point"}
}