{
  "type": "Feature",
  "properties": {
    "iso:country":"US",
    "sg:address":"1725 Elton Rd",
    "sg:city":"Silver Spring",
    "sg:classifiers":[
        {
            "category":"Real Estate",
            "subcategory":"Real Estate Agent",
            "type":"Services"
        }
    ],
    "sg:phone":"+1 301 439 9500",
    "sg:postcode":"20903",
    "sg:province":"MD",
    "sg:website":"www.fairfaxrealty.com",
    "wof:name":"Fairfax Realty Inc",
    "wof:placetype":"venue"
},
  "geometry": {"coordinates":[-76.974644,39.0199],"type":"Point"}
}