{
  "type": "Feature",
  "properties": {
    "addr:full":"531 Woodbine Ave Baltimore MD 21204",
    "addr:housenumber":"531",
    "addr:postcode":"21204",
    "addr:street":"Woodbine Ave",
    "iso:country":"US",
    "sg:address":"531 Woodbine Ave",
    "sg:city":"Baltimore",
    "sg:classifiers":[
        {
            "category":"Real Estate",
            "subcategory":"Real Estate Agent",
            "type":"Services"
        }
    ],
    "sg:phone":"+1 410 825 2713",
    "sg:postcode":"21204",
    "sg:province":"MD",
    "wof:name":"Jasinski Appraisals Inc",
    "wof:placetype":"venue"
},
  "geometry": {"coordinates":[-76.617491,39.401739],"type":"Point"}
}