{
  "type": "Feature",
  "properties": {
    "iso:country":"US",
    "sg:address":"81 Mellor Ave",
    "sg:city":"Catonsville",
    "sg:classifiers":[
        {
            "category":"Shopping",
            "subcategory":"Beauty & Cosmetics",
            "type":"Retail Goods"
        }
    ],
    "sg:phone":"+1 410 747 1200",
    "sg:postcode":"21228",
    "sg:province":"MD",
    "sg:tags":[
        "supply"
    ],
    "wof:name":"Avon Training Center",
    "wof:placetype":"venue"
},
  "geometry": {"coordinates":[-76.732101,39.2673],"type":"Point"}
}