{
  "type": "Feature",
  "properties": {
    "addr:full":"16623 Bethayres Rd Derwood MD 20855",
    "addr:housenumber":"16623",
    "addr:postcode":"20855",
    "addr:street":"Bethayres Rd",
    "iso:country":"US",
    "sg:address":"16623 Bethayres Rd",
    "sg:city":"Derwood",
    "sg:classifiers":[
        {
            "category":"Professional",
            "subcategory":"Testing Lab",
            "type":"Services"
        },
        {
            "category":"Professional",
            "subcategory":"Research",
            "type":"Services"
        }
    ],
    "sg:phone":"+1 301 963 6000",
    "sg:postcode":"20855",
    "sg:province":"MD",
    "sg:tags":[
        "environmental",
        "ecological",
        "laboratory"
    ],
    "wof:name":"Chirlin & Associates",
    "wof:placetype":"venue"
},
  "geometry": {"coordinates":[-77.157425,39.130336],"type":"Point"}
}