{
  "type": "Feature",
  "properties": {
    "addr:full":"25 Summer Fields Ct Timonium MD 21093",
    "addr:housenumber":"25",
    "addr:postcode":"21093",
    "addr:street":"Summer Fields Ct",
    "iso:country":"US",
    "sg:address":"25 Summer Fields Ct",
    "sg:city":"Timonium",
    "sg:classifiers":[
        {
            "category":"Building & Trades",
            "subcategory":"Construction",
            "type":"Services"
        }
    ],
    "sg:phone":"+1 410 666 2448",
    "sg:postcode":"21093",
    "sg:province":"MD",
    "sg:tags":[
        "masonry",
        "contractor"
    ],
    "wof:name":"Lavezza Contractors Inc",
    "wof:placetype":"venue"
},
  "geometry": {"coordinates":[-76.64975699999999,39.42208],"type":"Point"}
}