{
  "type": "Feature",
  "properties": {
    "addr:full":"612 E 36th St Baltimore MD 21218",
    "addr:housenumber":"612",
    "addr:postcode":"21218",
    "addr:street":"E 36Th St",
    "iso:country":"US",
    "sg:address":"612 E 36th St",
    "sg:city":"Baltimore",
    "sg:classifiers":[
        {
            "category":"Professional",
            "subcategory":"Detective & Security Services",
            "type":"Services"
        }
    ],
    "sg:phone":"+1 410 900 6318",
    "sg:postcode":"21218",
    "sg:province":"MD",
    "sg:tags":[
        "information",
        "bureau"
    ],
    "wof:name":"My Brother's Pressure Washing Services",
    "wof:placetype":"venue"
},
  "geometry": {"coordinates":[-76.607643,39.332321],"type":"Point"}
}