{
  "type": "Feature",
  "properties": {
    "addr:full":"22316 Three Notch Rd Lexington Park MD 20653",
    "addr:housenumber":"22316",
    "addr:postcode":"20653",
    "addr:street":"Three Notch Rd",
    "iso:country":"US",
    "sg:address":"22316 Three Notch Rd",
    "sg:city":"Lexington Park",
    "sg:classifiers":[
        {
            "category":"Real Estate",
            "subcategory":"Real Estate Agent",
            "type":"Services"
        }
    ],
    "sg:phone":"+1 301 863 7407",
    "sg:postcode":"20653",
    "sg:province":"MD",
    "wof:name":"Franzen Realtors Inc",
    "wof:placetype":"venue"
},
  "geometry": {"coordinates":[-76.468806,38.281105],"type":"Point"}
}