{
  "type": "Feature",
  "properties": {
    "addr:full":"7005 Blue Mountain Rd Thurmont MD 21788",
    "addr:housenumber":"7005",
    "addr:postcode":"21788",
    "addr:street":"Blue Mountain Rd",
    "iso:country":"US",
    "sg:address":"7005 Blue Mountain Rd",
    "sg:city":"Thurmont",
    "sg:classifiers":[
        {
            "category":"Food & Beverages",
            "subcategory":"Groceries & Convenience Stores",
            "type":"Retail Goods"
        }
    ],
    "sg:phone":"+1 301 271 2170",
    "sg:postcode":"21788",
    "sg:province":"MD",
    "sg:tags":[
        "grocer"
    ],
    "wof:name":"Market Basket",
    "wof:placetype":"venue"
},
  "geometry": {"coordinates":[-77.42495700000001,39.602656],"type":"Point"}
}