{
  "type": "Feature",
  "properties": {
    "addr:full":"1258 Maryland Ave Hagerstown MD 21740",
    "addr:housenumber":"1258",
    "addr:postcode":"21740",
    "addr:street":"Maryland Ave",
    "iso:country":"US",
    "sg:address":"1258 Maryland Ave",
    "sg:city":"Hagerstown",
    "sg:classifiers":[
        {
            "category":"Government",
            "subcategory":"Office",
            "type":"Public Place"
        }
    ],
    "sg:phone":"+1 301 797 1160",
    "sg:postcode":"21740",
    "sg:province":"MD",
    "sg:tags":[
        "federal",
        "human"
    ],
    "wof:name":"US Social Security Adm",
    "wof:placetype":"venue"
},
  "geometry": {"coordinates":[-77.739256,39.615607],"type":"Point"}
}