{
  "type": "Feature",
  "properties": {
    "iso:country":"US",
    "sg:address":"7735 Old Georgetown Rd",
    "sg:city":"Bethesda",
    "sg:classifiers":[
        {
            "category":"Professional",
            "subcategory":"Lawyer & Legal Services",
            "type":"Services"
        }
    ],
    "sg:phone":"+1 301 656 8850",
    "sg:postcode":"20814",
    "sg:province":"MD",
    "wof:name":"Viramontes-Lafree Vicki Atty",
    "wof:placetype":"venue"
},
  "geometry": {"coordinates":[-77.097927,38.987146],"type":"Point"}
}