{
  "type": "Feature",
  "properties": {
    "iso:country":"US",
    "sg:address":"1911 Aliceanna St",
    "sg:city":"Baltimore",
    "sg:classifiers":[
        {
            "category":"Restaurant",
            "type":"Food & Drink"
        }
    ],
    "sg:menulink":"http://www.allmenus.com/md/baltimore/245524-talay-thai-grille/menu/",
    "sg:phone":"+1 410 563 4004",
    "sg:postcode":"21231",
    "sg:province":"MD",
    "sg:tags":[
        "thai",
        "asian"
    ],
    "wof:name":"Talay Thai Grille",
    "wof:placetype":"venue"
},
  "geometry": {"coordinates":[-76.58955899999999,39.283694],"type":"Point"}
}