{
  "type": "Feature",
  "properties": {
    "addr:full":"3176 Rocks Chrome Hill Rd Jarrettsville MD 21084",
    "addr:housenumber":"3176",
    "addr:postcode":"21084",
    "addr:street":"Rocks Chrome Hill Rd",
    "iso:country":"US",
    "sg:address":"3176 Rocks Chrome Hill Rd",
    "sg:city":"Jarrettsville",
    "sg:classifiers":[
        {
            "category":"Building & Trades",
            "subcategory":"Cleaning & Sanitation",
            "type":"Services"
        }
    ],
    "sg:phone":"+1 410 836 6707",
    "sg:postcode":"21084",
    "sg:province":"MD",
    "sg:tags":[
        "janitor"
    ],
    "wof:name":"Eagle Cleaning Svc",
    "wof:placetype":"venue"
},
  "geometry": {"coordinates":[-76.419921,39.614237],"type":"Point"}
}