{
  "type": "Feature",
  "properties": {
    "iso:country":"US",
    "sg:address":"410 Severn Ave",
    "sg:city":"Annapolis",
    "sg:classifiers":[
        {
            "category":"Government",
            "subcategory":"Office",
            "type":"Public Place"
        }
    ],
    "sg:phone":"+1 410 267 5671",
    "sg:postcode":"21403",
    "sg:province":"MD",
    "sg:tags":[
        "policy",
        "political",
        "organ"
    ],
    "wof:name":"Noaa Nmfs Ncbo",
    "wof:placetype":"venue"
},
  "geometry": {"coordinates":[-76.483562,38.971082],"type":"Point"}
}