{
  "type": "Feature",
  "properties": {
    "iso:country":"US",
    "sg:address":"20306 Seabrook Dr",
    "sg:city":"Montgomery Village",
    "sg:classifiers":[
        {
            "category":"Shopping",
            "subcategory":"Beauty & Cosmetics",
            "type":"Retail Goods"
        }
    ],
    "sg:phone":"+1 301 330 0582",
    "sg:postcode":"20886",
    "sg:province":"MD",
    "sg:tags":[
        "merchandise"
    ],
    "wof:name":"Sjj Products",
    "wof:placetype":"venue"
},
  "geometry": {"coordinates":[-77.155295,39.18738],"type":"Point"}
}