{
  "type": "Feature",
  "properties": {
    "iso:country":"US",
    "sg:address":"11300 Rockville Pike # 710",
    "sg:city":"Rockville",
    "sg:classifiers":[
        {
            "category":"Communications",
            "subcategory":"Radio Station",
            "type":"Services"
        },
        {
            "category":"Professional",
            "subcategory":"Business Services",
            "type":"Services"
        }
    ],
    "sg:phone":"+1 240 221 0622",
    "sg:postcode":"20852",
    "sg:province":"MD",
    "sg:tags":[
        "medium",
        "publicity",
        "broker"
    ],
    "wof:name":"Rosenberg Media",
    "wof:placetype":"venue"
},
  "geometry": {"coordinates":[-77.110162,39.041213],"type":"Point"}
}