{
  "type": "Feature",
  "properties": {
    "addr:full":"735 Hanover Pike Hampstead MD 21074",
    "addr:housenumber":"735",
    "addr:postcode":"21074",
    "addr:street":"Hanover Pike",
    "iso:country":"US",
    "sg:address":"735 Hanover Pike",
    "sg:city":"Hampstead",
    "sg:classifiers":[
        {
            "category":"Banks & Credit Unions",
            "subcategory":"Bank",
            "type":"Services"
        }
    ],
    "sg:phone":"+1 410 374 4125",
    "sg:postcode":"21074",
    "sg:province":"MD",
    "sg:website":"www.farmersandmerchantsbk.com",
    "wof:name":"Susquehanna Bank",
    "wof:placetype":"venue"
},
  "geometry": {"coordinates":[-76.846406,39.595505],"type":"Point"}
}