{
  "type": "Feature",
  "properties": {
    "iso:country":"US",
    "sg:address":"13500 Baltimore Ave",
    "sg:city":"Laurel",
    "sg:classifiers":[
        {
            "category":"Home & Garden",
            "subcategory":"Carpets & Floor Coverings",
            "type":"Retail Goods"
        }
    ],
    "sg:phone":"+1 301 419 3500",
    "sg:postcode":"20707",
    "sg:province":"MD",
    "sg:tags":[
        "carpeting"
    ],
    "wof:name":"Kashmir Carpet & Floors",
    "wof:placetype":"venue"
},
  "geometry": {"coordinates":[-76.87020099999999,39.074299],"type":"Point"}
}