{
  "type": "Feature",
  "properties": {
    "addr:full":"6970 Security Blvd Windsor Mill MD 21244",
    "addr:housenumber":"6970",
    "addr:postcode":"21244",
    "addr:street":"Security Blvd",
    "iso:country":"US",
    "sg:address":"6970 Security Blvd",
    "sg:city":"Windsor Mill",
    "sg:classifiers":[
        {
            "category":"Autos & Motor Vehicles",
            "subcategory":"Automobile Sales",
            "type":"Retail Goods"
        }
    ],
    "sg:phone":"+1 301 621 5030",
    "sg:postcode":"21244",
    "sg:province":"MD",
    "sg:tags":[
        "car"
    ],
    "wof:name":"Koons Ford of Baltimore Inc",
    "wof:placetype":"venue"
},
  "geometry": {"coordinates":[-76.749802,39.313202],"type":"Point"}
}