{
  "type": "Feature",
  "properties": {
    "iso:country":"US",
    "sg:address":"11140 Rockville Pike",
    "sg:city":"Rockville",
    "sg:classifiers":[
        {
            "category":"Banks & Credit Unions",
            "subcategory":"Investment Brokerage",
            "type":"Services"
        }
    ],
    "sg:phone":"+1 240 506 1059",
    "sg:postcode":"20852",
    "sg:province":"MD",
    "sg:tags":[
        "advisory"
    ],
    "wof:name":"Regal Capital",
    "wof:placetype":"venue"
},
  "geometry": {"coordinates":[-77.109244,39.039338],"type":"Point"}
}