{
  "type": "Feature",
  "properties": {
    "addr:full":"14213 Bear Creek Dr Boyds MD 20841",
    "addr:housenumber":"14213",
    "addr:postcode":"20841",
    "addr:street":"Bear Creek Dr",
    "iso:country":"US",
    "sg:address":"14213 Bear Creek Dr",
    "sg:city":"Boyds",
    "sg:classifiers":[
        {
            "category":"Structure",
            "subcategory":"Office Building",
            "type":"Public Place"
        }
    ],
    "sg:phone":"+1 301 528 6033",
    "sg:postcode":"20841",
    "sg:province":"MD",
    "sg:tags":[
        "park"
    ],
    "wof:name":"Marquis Properties",
    "wof:placetype":"venue"
},
  "geometry": {"coordinates":[-77.293385,39.161871],"type":"Point"}
}