{
  "type": "Feature",
  "properties": {
    "iso:country":"US",
    "sg:address":"10010 Baltimore National Pike",
    "sg:city":"Ellicott City",
    "sg:classifiers":[
        {
            "category":"Food & Beverages",
            "subcategory":"Liquor & Beverages",
            "type":"Retail Goods"
        }
    ],
    "sg:phone":"+1 410 465 4262",
    "sg:postcode":"21042",
    "sg:province":"MD",
    "wof:name":"Normandy LLC",
    "wof:placetype":"venue"
},
  "geometry": {"coordinates":[-76.854665,39.279188],"type":"Point"}
}