{
  "type": "Feature",
  "properties": {
    "addr:full":"8 Hathaway Ct Silver Spring MD 20906",
    "addr:housenumber":"8",
    "addr:postcode":"20906",
    "addr:street":"Hathaway Ct",
    "iso:country":"US",
    "sg:address":"8 Hathaway Ct",
    "sg:city":"Silver Spring",
    "sg:classifiers":[
        {
            "category":"Professional",
            "subcategory":"Management & Consulting",
            "type":"Services"
        }
    ],
    "sg:phone":"+1 301 460 4222",
    "sg:postcode":"20906",
    "sg:province":"MD",
    "sg:tags":[
        "high",
        "aviation",
        "technology",
        "firm",
        "research"
    ],
    "wof:name":"Eagle Ventures Inc",
    "wof:placetype":"venue"
},
  "geometry": {"coordinates":[-77.05260199999999,39.07584],"type":"Point"}
}