{
  "type": "Feature",
  "properties": {
    "iso:country":"US",
    "sg:address":"8444 Braddock Way",
    "sg:city":"Columbia",
    "sg:classifiers":[
        {
            "category":"Personal",
            "subcategory":"Tanning Parlor",
            "type":"Services"
        }
    ],
    "sg:phone":"+1 410 730 6783",
    "sg:postcode":"21046",
    "sg:province":"MD",
    "wof:name":"Tantastic Corp",
    "wof:placetype":"venue"
},
  "geometry": {"coordinates":[-76.873199,39.174],"type":"Point"}
}