{
  "type": "Feature",
  "properties": {
    "iso:country":"US",
    "sg:address":"105 Centennial Street Suite F",
    "sg:city":"La Plata",
    "sg:classifiers":[
        {
            "category":"Professional",
            "subcategory":"Computer Services",
            "type":"Services"
        }
    ],
    "sg:phone":"+1 301 539 0200",
    "sg:postcode":"20646 ",
    "sg:province":"MD",
    "sg:website":"http://outsourceitcorp.com",
    "wof:name":"outsourceIT",
    "wof:placetype":"venue"
},
  "geometry": {"coordinates":[-76.98029699999999,38.527332],"type":"Point"}
}