{
  "type": "Feature",
  "properties": {
    "addr:full":"2103 Brickhouse Rd Dunkirk MD 20754",
    "addr:housenumber":"2103",
    "addr:postcode":"20754",
    "addr:street":"Brickhouse Rd",
    "iso:country":"US",
    "sg:address":"2103 Brickhouse Rd",
    "sg:city":"Dunkirk",
    "sg:classifiers":[
        {
            "category":"Manufacturing",
            "subcategory":"Furniture",
            "type":"Manufacturing & Wholesale Goods"
        }
    ],
    "sg:phone":"+1 301 855 8300",
    "sg:postcode":"20754",
    "sg:province":"MD",
    "sg:tags":[
        "bench"
    ],
    "wof:name":"Victor Stanley",
    "wof:placetype":"venue"
},
  "geometry": {"coordinates":[-76.64554800000001,38.740886],"type":"Point"}
}