{
  "type": "Feature",
  "properties": {
    "iso:country":"US",
    "sg:address":"12059 Tech Rd",
    "sg:city":"Silver Spring",
    "sg:classifiers":[
        {
            "category":"Building & Trades",
            "subcategory":"Plumbing",
            "type":"Services"
        }
    ],
    "sg:phone":"+1 301 434 3030",
    "sg:postcode":"20904",
    "sg:province":"MD",
    "sg:tags":[
        "conditioning",
        "air",
        "system",
        "contractor"
    ],
    "wof:name":"Mc Laughlin Heating & Air Cond",
    "wof:placetype":"venue"
},
  "geometry": {"coordinates":[-76.970222,39.051421],"type":"Point"}
}