{
  "type": "Feature",
  "properties": {
    "addr:full":"10911 New Hampshire Ave Silver Spring MD 20903",
    "addr:housenumber":"10911",
    "addr:postcode":"20903",
    "addr:street":"New Hampshire Ave",
    "iso:country":"US",
    "sg:address":"10911 New Hampshire Ave",
    "sg:city":"Silver Spring",
    "sg:classifiers":[
        {
            "category":"Sports & Exercise",
            "subcategory":"Golf",
            "type":"Entertainment"
        }
    ],
    "sg:phone":"+1 301 495 2530",
    "sg:postcode":"20903",
    "sg:province":"MD",
    "wof:name":"Maryland National Capital Park & Planning Commissn",
    "wof:placetype":"venue"
},
  "geometry": {"coordinates":[-76.986397,39.033901],"type":"Point"}
}