{
  "type": "Feature",
  "properties": {
    "iso:country":"US",
    "sg:address":"2662 Patapsco Rd",
    "sg:city":"Finksburg",
    "sg:classifiers":[
        {
            "category":"Building & Trades",
            "subcategory":"Construction",
            "type":"Services"
        }
    ],
    "sg:phone":"+1 410 876 7313",
    "sg:postcode":"21048",
    "sg:province":"MD",
    "sg:tags":[
        "paving",
        "contractor"
    ],
    "wof:name":"E Taylor & Sons Asphalt",
    "wof:placetype":"venue"
},
  "geometry": {"coordinates":[-76.90203099999999,39.542643],"type":"Point"}
}