{
  "type": "Feature",
  "properties": {
    "addr:full":"12227 Marne Ln Bowie MD 20715",
    "addr:housenumber":"12227",
    "addr:postcode":"20715",
    "addr:street":"Marne Ln",
    "iso:country":"US",
    "sg:address":"12227 Marne Ln",
    "sg:city":"Bowie",
    "sg:classifiers":[
        {
            "category":"Shopping",
            "subcategory":"Bicycles & Sporting Goods",
            "type":"Retail Goods"
        }
    ],
    "sg:phone":"+1 301 262 6138",
    "sg:postcode":"20715",
    "sg:province":"MD",
    "wof:name":"Lou's Sporting Goods & Elec",
    "wof:placetype":"venue"
},
  "geometry": {"coordinates":[-76.74725100000001,38.976549],"type":"Point"}
}