{
  "type": "Feature",
  "properties": {
    "iso:country":"US",
    "sg:address":"339 E Antietam St",
    "sg:city":"Hagerstown",
    "sg:classifiers":[
        {
            "category":"Insurance",
            "subcategory":"Hazard Insurance",
            "type":"Services"
        }
    ],
    "sg:phone":"+1 301 416 7133",
    "sg:postcode":"21740",
    "sg:province":"MD",
    "sg:tags":[
        "profit",
        "sharing",
        "pension",
        "plan"
    ],
    "wof:name":"BGS & G",
    "wof:placetype":"venue"
},
  "geometry": {"coordinates":[-77.710683,39.636323],"type":"Point"}
}