{
  "type": "Feature",
  "properties": {
    "iso:country":"US",
    "sg:address":"128 Springtowne Cir",
    "sg:city":"Parkville",
    "sg:classifiers":[
        {
            "category":"Real Estate",
            "subcategory":"Real Estate Agent",
            "type":"Services"
        }
    ],
    "sg:phone":"+1 410 248 0300",
    "sg:postcode":"21234",
    "sg:province":"MD",
    "sg:tags":[
        "appraiser"
    ],
    "wof:name":"Associated Appraisers-Maryland",
    "wof:placetype":"venue"
},
  "geometry": {"coordinates":[-76.492453,39.398982],"type":"Point"}
}