{
  "type": "Feature",
  "properties": {
    "addr:full":"1100 E Fayette St Baltimore MD 21231",
    "addr:housenumber":"1100",
    "addr:postcode":"21231",
    "addr:street":"E Fayette St",
    "iso:country":"US",
    "sg:address":"1100 E Fayette St",
    "sg:city":"Baltimore",
    "sg:classifiers":[
        {
            "category":"Social Services",
            "type":"Services"
        }
    ],
    "sg:phone":"+1 410 342 1153",
    "sg:postcode":"21231",
    "sg:province":"MD",
    "sg:tags":[
        "youth",
        "organization",
        "center"
    ],
    "wof:name":"Intel Computer Clubhouse",
    "wof:placetype":"venue"
},
  "geometry": {"coordinates":[-76.602779,39.291702],"type":"Point"}
}