{
  "type": "Feature",
  "properties": {
    "iso:country":"US",
    "sg:address":"66 Painters Mill Rd",
    "sg:city":"Owings Mills",
    "sg:classifiers":[
        {
            "category":"Health Services",
            "subcategory":"Doctor",
            "type":"Services"
        }
    ],
    "sg:phone":"+1 410 363 3780",
    "sg:postcode":"21117",
    "sg:province":"MD",
    "sg:tags":[
        "dentist"
    ],
    "wof:name":"Mandel & Keiser",
    "wof:placetype":"venue"
},
  "geometry": {"coordinates":[-76.777148,39.412922],"type":"Point"}
}