{
  "type": "Feature",
  "properties": {
    "iso:country":"US",
    "sg:address":"711 W 40th St",
    "sg:city":"Baltimore",
    "sg:classifiers":[
        {
            "category":"Health Services",
            "subcategory":"Health Practitioner",
            "type":"Services"
        }
    ],
    "sg:phone":"+1 410 243 6303",
    "sg:postcode":"21211",
    "sg:province":"MD",
    "sg:tags":[
        "therapy",
        "physical"
    ],
    "wof:name":"Means-Brunswick Physical Therapy Inc",
    "wof:placetype":"venue"
},
  "geometry": {"coordinates":[-76.6306,39.337101],"type":"Point"}
}