{
  "type": "Feature",
  "properties": {
    "iso:country":"US",
    "sg:address":"12307 Braxfield Ct",
    "sg:city":"Rockville",
    "sg:classifiers":[
        {
            "category":"Professional",
            "subcategory":"Computer Services",
            "type":"Services"
        }
    ],
    "sg:phone":"+1 301 230 9714",
    "sg:postcode":"20852",
    "sg:province":"MD",
    "sg:tags":[
        "consultant",
        "designer"
    ],
    "wof:name":"American Business Computer",
    "wof:placetype":"venue"
},
  "geometry": {"coordinates":[-77.10599000000001,39.056789],"type":"Point"}
}