{
  "type": "Feature",
  "properties": {
    "iso:country":"US",
    "sg:address":"4206 Flam St",
    "sg:city":"Fort Washington",
    "sg:classifiers":[
        {
            "category":"Building & Trades",
            "subcategory":"Cleaning & Sanitation",
            "type":"Services"
        }
    ],
    "sg:phone":"+1 301 449 4430",
    "sg:postcode":"20744",
    "sg:province":"MD",
    "sg:tags":[
        "window"
    ],
    "wof:name":"J L & S Building Svc",
    "wof:placetype":"venue"
},
  "geometry": {"coordinates":[-76.933286,38.785204],"type":"Point"}
}