{
  "type": "Feature",
  "properties": {
    "iso:country":"US",
    "sg:address":"10176 Baltimore National Pike",
    "sg:city":"Ellicott City",
    "sg:classifiers":[
        {
            "category":"Organizations",
            "subcategory":"Professional Association",
            "type":"Services"
        }
    ],
    "sg:phone":"+1 410 461 5977",
    "sg:postcode":"21042",
    "sg:province":"MD",
    "wof:name":"Maryland Plumbing & Heating",
    "wof:placetype":"venue"
},
  "geometry": {"coordinates":[-76.86298499999999,39.279817],"type":"Point"}
}