{
  "type": "Feature",
  "properties": {
    "iso:country":"US",
    "sg:address":"18100 Cashell Rd",
    "sg:city":"Rockville",
    "sg:classifiers":[
        {
            "category":"Professional",
            "subcategory":"Research",
            "type":"Services"
        }
    ],
    "sg:phone":"+1 301 570 2284",
    "sg:postcode":"20853",
    "sg:province":"MD",
    "wof:name":"International Research",
    "wof:placetype":"venue"
},
  "geometry": {"coordinates":[-77.094398,39.154106],"type":"Point"}
}