{
  "type": "Feature",
  "properties": {
    "addr:full":"6806 Upper Mills Cir Catonsville MD 21228",
    "addr:housenumber":"6806",
    "addr:postcode":"21228",
    "addr:street":"Upper Mills Cir",
    "iso:country":"US",
    "sg:address":"6806 Upper Mills Cir",
    "sg:city":"Catonsville",
    "sg:classifiers":[
        {
            "category":"Manufacturing",
            "subcategory":"Glass & Minerals",
            "type":"Manufacturing & Wholesale Goods"
        }
    ],
    "sg:phone":"+1 410 788 1794",
    "sg:postcode":"21228",
    "sg:province":"MD",
    "sg:tags":[
        "plate",
        "glass-auto",
        "glass-wholesale",
        "window",
        "manufacturer"
    ],
    "wof:name":"Royal Glass Co",
    "wof:placetype":"venue"
},
  "geometry": {"coordinates":[-76.764732,39.29974],"type":"Point"}
}