{
  "type": "Feature",
  "properties": {
    "addr:full":"21182 Marsh Creek Rd Preston MD 21655",
    "addr:housenumber":"21182",
    "addr:postcode":"21655",
    "addr:street":"Marsh Creek Rd",
    "iso:country":"US",
    "sg:address":"21182 Marsh Creek Rd",
    "sg:city":"Preston",
    "sg:classifiers":[
        {
            "category":"Manufacturing",
            "subcategory":"Buildings",
            "type":"Manufacturing & Wholesale Goods"
        },
        {
            "category":"Building & Trades",
            "subcategory":"Construction",
            "type":"Services"
        }
    ],
    "sg:phone":"+1 410 310 6358",
    "sg:postcode":"21655",
    "sg:province":"MD",
    "sg:tags":[
        "home",
        "builder",
        "contractor"
    ],
    "wof:name":"Meekins Builders",
    "wof:placetype":"venue"
},
  "geometry": {"coordinates":[-75.972236,38.742672],"type":"Point"}
}