{
  "type": "Feature",
  "properties": {
    "addr:full":"5051 Branchville Rd College Park MD 20740",
    "addr:housenumber":"5051",
    "addr:postcode":"20740",
    "addr:street":"Branchville Rd",
    "iso:country":"US",
    "sg:address":"5051 Branchville Rd",
    "sg:city":"College Park",
    "sg:classifiers":[
        {
            "category":"Organizations",
            "subcategory":"Community Association",
            "type":"Services"
        }
    ],
    "sg:phone":"+1 301 474 9642",
    "sg:postcode":"20740",
    "sg:province":"MD",
    "sg:tags":[
        "club"
    ],
    "wof:name":"Veterans Of Foreign Wars",
    "wof:placetype":"venue"
},
  "geometry": {"coordinates":[-76.92243499999999,38.99896],"type":"Point"}
}