{
  "type": "Feature",
  "properties": {
    "iso:country":"US",
    "sg:address":"10545 Friendship Rd",
    "sg:city":"Berlin",
    "sg:classifiers":[
        {
            "category":"Building & Trades",
            "subcategory":"Construction",
            "type":"Services"
        }
    ],
    "sg:phone":"+1 410 621 1553",
    "sg:postcode":"21811",
    "sg:province":"MD",
    "sg:tags":[
        "general",
        "contractor"
    ],
    "wof:name":"J J Reed Construction",
    "wof:placetype":"venue"
},
  "geometry": {"coordinates":[-75.200785,38.362593],"type":"Point"}
}