{
  "type": "Feature",
  "properties": {
    "iso:country":"US",
    "sg:address":"201A Broadway Street",
    "sg:city":"Frederick",
    "sg:classifiers":[
        {
            "category":"Professional",
            "subcategory":"Computer Services",
            "type":"Services"
        }
    ],
    "sg:phone":"+1 301 418 6180",
    "sg:postcode":"21701",
    "sg:province":"MD",
    "sg:website":"http://www.wideareasystems.com",
    "wof:name":"Widearea Systems",
    "wof:placetype":"venue"
},
  "geometry": {"coordinates":[-77.412668,39.410773],"type":"Point"}
}