{
  "type": "Feature",
  "properties": {
    "iso:country":"US",
    "sg:address":"1901 Sulphur Spring Rd",
    "sg:city":"Halethorpe",
    "sg:classifiers":[
        {
            "category":"Health Services",
            "subcategory":"Doctor",
            "type":"Services"
        }
    ],
    "sg:phone":"+1 410 242 6161",
    "sg:postcode":"21227",
    "sg:province":"MD",
    "sg:tags":[
        "podiatrist"
    ],
    "wof:name":"Podiatric Mycology Laboratory",
    "wof:placetype":"venue"
},
  "geometry": {"coordinates":[-76.67130299999999,39.246899],"type":"Point"}
}