{
  "type": "Feature",
  "properties": {
    "iso:country":"US",
    "sg:address":"3300 N Ridge Rd",
    "sg:city":"Ellicott City",
    "sg:classifiers":[
        {
            "category":"Professional",
            "subcategory":"Lawyer & Legal Services",
            "type":"Services"
        }
    ],
    "sg:phone":"+1 410 465 0473",
    "sg:postcode":"21043",
    "sg:province":"MD",
    "sg:tags":[
        "attorney"
    ],
    "wof:name":"Marc J Lipchin Law Offices",
    "wof:placetype":"venue"
},
  "geometry": {"coordinates":[-76.818426,39.28164],"type":"Point"}
}