{
  "type": "Feature",
  "properties": {
    "addr:full":"6925 Blair Rd NW Washington MD 20012",
    "addr:housenumber":"6925",
    "addr:postcode":"20012",
    "addr:street":"Blair Rd Nw",
    "iso:country":"US",
    "sg:address":"6925 Blair Rd NW",
    "sg:city":"Washington",
    "sg:classifiers":[
        {
            "category":"Organizations",
            "subcategory":"Labor Organization",
            "type":"Services"
        }
    ],
    "sg:phone":"+1 202 545 1789",
    "sg:postcode":"20012",
    "sg:province":"MD",
    "wof:name":"Parking & Svc Worker's Union",
    "wof:placetype":"venue"
},
  "geometry": {"coordinates":[-77.017725,38.974306],"type":"Point"}
}