{
  "type": "Feature",
  "properties": {
    "iso:country":"US",
    "sg:address":"7245 Hanover Pkwy Ste D",
    "sg:city":"Greenbelt",
    "sg:classifiers":[
        {
            "category":"Real Estate",
            "subcategory":"Real Estate Services",
            "type":"Services"
        },
        {
            "category":"Banks & Credit Unions",
            "subcategory":"Financial Services",
            "type":"Services"
        }
    ],
    "sg:phone":"+1 301 220 3885",
    "sg:postcode":"20770",
    "sg:province":"MD",
    "sg:tags":[
        "loan",
        "processing"
    ],
    "wof:name":"Point One Mortgage Group",
    "wof:placetype":"venue"
},
  "geometry": {"coordinates":[-76.87807599999999,38.98857],"type":"Point"}
}