{
  "type": "Feature",
  "properties": {
    "addr:full":"711 W 40th St Baltimore MD 21211",
    "addr:housenumber":"711",
    "addr:postcode":"21211",
    "addr:street":"W 40Th St",
    "iso:country":"US",
    "sg:address":"711 W 40th St",
    "sg:city":"Baltimore",
    "sg:classifiers":[
        {
            "category":"Bakery",
            "type":"Food & Drink"
        },
        {
            "category":"Shopping",
            "subcategory":"Florist",
            "type":"Retail Goods"
        }
    ],
    "sg:phone":"+1 410 467 0417",
    "sg:postcode":"21211",
    "sg:province":"MD",
    "wof:name":"Giant Food Inc",
    "wof:placetype":"venue"
},
  "geometry": {"coordinates":[-76.6306,39.337101],"type":"Point"}
}