{
  "type": "Feature",
  "properties": {
    "addr:full":"14804 Stonegate Ter Silver Spring MD 20905",
    "addr:housenumber":"14804",
    "addr:postcode":"20905",
    "addr:street":"Stonegate Ter",
    "iso:country":"US",
    "sg:address":"14804 Stonegate Ter",
    "sg:city":"Silver Spring",
    "sg:classifiers":[
        {
            "category":"Health Services",
            "subcategory":"Doctor",
            "type":"Services"
        }
    ],
    "sg:phone":"+1 301 384 1030",
    "sg:postcode":"20905",
    "sg:province":"MD",
    "wof:name":"Raiford Roger L MD",
    "wof:placetype":"venue"
},
  "geometry": {"coordinates":[-77.01190200000001,39.0993],"type":"Point"}
}