{
  "type": "Feature",
  "properties": {
    "iso:country":"US",
    "sg:address":"5010 Sunnyside Ave # 109",
    "sg:city":"Beltsville",
    "sg:classifiers":[
        {
            "category":"Insurance",
            "subcategory":"Hazard Insurance",
            "type":"Services"
        }
    ],
    "sg:phone":"+1 301 345 8855",
    "sg:postcode":"20705",
    "sg:province":"MD",
    "sg:tags":[
        "commercial",
        "business"
    ],
    "wof:name":"Lbj Insurance",
    "wof:placetype":"venue"
},
  "geometry": {"coordinates":[-76.919735,39.026229],"type":"Point"}
}