{
  "type": "Feature",
  "properties": {
    "addr:full":"1019 W Isabella St Salisbury MD 21801",
    "addr:housenumber":"1019",
    "addr:postcode":"21801",
    "addr:street":"W Isabella St",
    "iso:country":"US",
    "sg:address":"1019 W Isabella St",
    "sg:city":"Salisbury",
    "sg:classifiers":[
        {
            "category":"Banks & Credit Unions",
            "subcategory":"Bank",
            "type":"Services"
        }
    ],
    "sg:phone":"+1 410 543 1505",
    "sg:postcode":"21801",
    "sg:province":"MD",
    "wof:name":"Peninsula Bank",
    "wof:placetype":"venue"
},
  "geometry": {"coordinates":[-75.61326800000001,38.369929],"type":"Point"}
}