{
  "type": "Feature",
  "properties": {
    "iso:country":"US",
    "sg:address":"2339 N Point Blvd",
    "sg:city":"Baltimore",
    "sg:classifiers":[
        {
            "category":"Personal",
            "subcategory":"Tanning Parlor",
            "type":"Services"
        }
    ],
    "sg:phone":"+1 410 282 8192",
    "sg:postcode":"21222",
    "sg:province":"MD",
    "sg:tags":[
        "salon"
    ],
    "wof:name":"Nikki's Boutique",
    "wof:placetype":"venue"
},
  "geometry": {"coordinates":[-76.49643399999999,39.285873],"type":"Point"}
}