{
  "type": "Feature",
  "properties": {
    "iso:country":"US",
    "sg:address":"3914 Regency Pkwy",
    "sg:city":"Suitland",
    "sg:classifiers":[
        {
            "category":"Professional",
            "subcategory":"Management & Consulting",
            "type":"Services"
        }
    ],
    "sg:phone":"+1 301 568 6420",
    "sg:postcode":"20746",
    "sg:province":"MD",
    "sg:tags":[
        "business"
    ],
    "wof:name":"World Business Exchange",
    "wof:placetype":"venue"
},
  "geometry": {"coordinates":[-76.91362100000001,38.836388],"type":"Point"}
}