{
  "type": "Feature",
  "properties": {
    "addr:full":"9475 Gerwig Ln Ste P Columbia MD 21046",
    "addr:housenumber":"9475",
    "addr:postcode":"21046",
    "addr:street":"Gerwig Ln Ste P",
    "iso:country":"US",
    "sg:address":"9475 Gerwig Ln Ste P",
    "sg:city":"Columbia",
    "sg:classifiers":[
        {
            "category":"Manufacturing",
            "subcategory":"Metals",
            "type":"Manufacturing & Wholesale Goods"
        },
        {
            "category":"Manufacturing",
            "subcategory":"Printing",
            "type":"Manufacturing & Wholesale Goods"
        },
        {
            "category":"Utilities",
            "subcategory":"Recycling",
            "type":"Services"
        },
        {
            "category":"Shopping",
            "subcategory":"Discount & Variety Stores",
            "type":"Retail Goods"
        }
    ],
    "sg:phone":"+1 410 381 6363",
    "sg:postcode":"21046",
    "sg:province":"MD",
    "sg:tags":[
        "surplus",
        "aluminum",
        "disposal",
        "equipment",
        "paper",
        "waste",
        "salvage",
        "merchandise"
    ],
    "wof:name":"Kline Paper Mill Supplies Inc",
    "wof:placetype":"venue"
},
  "geometry": {"coordinates":[-76.837244,39.169335],"type":"Point"}
}