{
  "type": "Feature",
  "properties": {
    "iso:country":"US",
    "sg:address":"14720 Southlawn Ln",
    "sg:city":"Rockville",
    "sg:classifiers":[
        {
            "category":"Retail",
            "subcategory":"Auto Repair",
            "type":"Services"
        }
    ],
    "sg:phone":"+1 301 424 4474",
    "sg:postcode":"20850",
    "sg:province":"MD",
    "sg:tags":[
        "body",
        "automobile",
        "painting"
    ],
    "wof:name":"International Auto Body Repair",
    "wof:placetype":"venue"
},
  "geometry": {"coordinates":[-77.137474,39.096982],"type":"Point"}
}