{
  "type": "Feature",
  "properties": {
    "addr:full":"7895 Rockburn Dr Ellicott City MD 21043",
    "addr:housenumber":"7895",
    "addr:postcode":"21043",
    "addr:street":"Rockburn Dr",
    "iso:country":"US",
    "sg:address":"7895 Rockburn Dr",
    "sg:city":"Ellicott City",
    "sg:classifiers":[
        {
            "category":"Building & Trades",
            "subcategory":"Construction",
            "type":"Services"
        }
    ],
    "sg:phone":"+1 410 796 4422",
    "sg:postcode":"21043",
    "sg:province":"MD",
    "sg:tags":[
        "home",
        "builder"
    ],
    "wof:name":"Porten Sullivan Corp",
    "wof:placetype":"venue"
},
  "geometry": {"coordinates":[-76.786596,39.218098],"type":"Point"}
}