{
  "type": "Feature",
  "properties": {
    "iso:country":"US",
    "sg:address":"3940 Glenhurst Rd",
    "sg:city":"Baltimore",
    "sg:classifiers":[
        {
            "category":"Freight",
            "type":"Transportation"
        }
    ],
    "sg:phone":"+1 410 477 5100",
    "sg:postcode":"21222",
    "sg:province":"MD",
    "sg:tags":[
        "hauling",
        "trucking"
    ],
    "wof:name":"Besl Express",
    "wof:placetype":"venue"
},
  "geometry": {"coordinates":[-76.467529,39.281594],"type":"Point"}
}