{
  "type": "Feature",
  "properties": {
    "addr:full":"300 Moss Hill Ln Salisbury MD 21804",
    "addr:housenumber":"300",
    "addr:postcode":"21804",
    "addr:street":"Moss Hill Ln",
    "iso:country":"US",
    "sg:address":"300 Moss Hill Ln",
    "sg:city":"Salisbury",
    "sg:classifiers":[
        {
            "category":"Home & Garden",
            "subcategory":"Building Materials",
            "type":"Retail Goods"
        }
    ],
    "sg:phone":"+1 410 749 2269",
    "sg:postcode":"21804",
    "sg:province":"MD",
    "wof:name":"Bradco Supply Corp",
    "wof:placetype":"venue"
},
  "geometry": {"coordinates":[-75.57256700000001,38.378031],"type":"Point"}
}