{
  "type": "Feature",
  "properties": {
    "addr:full":"1403 Mountain Rd Joppa MD 21085",
    "addr:housenumber":"1403",
    "addr:postcode":"21085",
    "addr:street":"Mountain Rd",
    "iso:country":"US",
    "sg:address":"1403 Mountain Rd",
    "sg:city":"Joppa",
    "sg:classifiers":[
        {
            "category":"Government",
            "subcategory":"Fire Station",
            "type":"Public Place"
        }
    ],
    "sg:phone":"+1 410 676 4228",
    "sg:postcode":"21085",
    "sg:province":"MD",
    "sg:tags":[
        "department"
    ],
    "wof:name":"Joppa-Magnolia Volunteer Fire",
    "wof:placetype":"venue"
},
  "geometry": {"coordinates":[-76.345804,39.439481],"type":"Point"}
}