{
  "type": "Feature",
  "properties": {
    "iso:country":"US",
    "sg:address":"6824 Distribution Dr",
    "sg:city":"Beltsville",
    "sg:classifiers":[
        {
            "category":"Building & Trades",
            "subcategory":"Electrical",
            "type":"Services"
        }
    ],
    "sg:phone":"+1 301 937 0710",
    "sg:postcode":"20705",
    "sg:province":"MD",
    "sg:tags":[
        "contractors-commercial",
        "industrial",
        "electrician",
        "electric",
        "contractor"
    ],
    "wof:name":"Graphic Electric Inc",
    "wof:placetype":"venue"
},
  "geometry": {"coordinates":[-76.88829800000001,39.056099],"type":"Point"}
}