{
  "type": "Feature",
  "properties": {
    "addr:full":"10440 Little Patuxent Pkwy Columbia MD 21044",
    "addr:housenumber":"10440",
    "addr:postcode":"21044",
    "addr:street":"Little Patuxent Pkwy",
    "iso:country":"US",
    "sg:address":"10440 Little Patuxent Pkwy",
    "sg:city":"Columbia",
    "sg:classifiers":[
        {
            "category":"Health Services",
            "subcategory":"Doctor",
            "type":"Services"
        }
    ],
    "sg:phone":"+1 410 740 3240",
    "sg:postcode":"21044",
    "sg:province":"MD",
    "sg:tags":[
        "physician",
        "surgeon",
        "psychologist"
    ],
    "wof:name":"Silver Richard Dr",
    "wof:placetype":"venue"
},
  "geometry": {"coordinates":[-76.861115,39.212816],"type":"Point"}
}