{
  "type": "Feature",
  "properties": {
    "addr:full":"11235 York Rd Cockeysville MD 21030",
    "addr:housenumber":"11235",
    "addr:postcode":"21030",
    "addr:street":"York Rd",
    "iso:country":"US",
    "sg:address":"11235 York Rd",
    "sg:city":"Cockeysville",
    "sg:classifiers":[
        {
            "category":"Restaurant",
            "type":"Food & Drink"
        }
    ],
    "sg:menulink":"http://www.allmenus.com/md/hunt-valley/146774-subway/menu/",
    "sg:phone":"+1 410 771 1470",
    "sg:postcode":"21030",
    "sg:province":"MD",
    "sg:tags":[
        "american",
        "sandwich"
    ],
    "wof:name":"Subway",
    "wof:placetype":"venue"
},
  "geometry": {"coordinates":[-76.649534,39.493622],"type":"Point"}
}