{
  "type": "Feature",
  "properties": {
    "iso:country":"US",
    "sg:address":"4113 E Lombard St",
    "sg:city":"Baltimore",
    "sg:classifiers":[
        {
            "category":"Organizations",
            "subcategory":"Religious Organization",
            "type":"Services"
        }
    ],
    "sg:phone":"+1 410 342 7797",
    "sg:postcode":"21224",
    "sg:province":"MD",
    "sg:tags":[
        "church"
    ],
    "wof:name":"True Fellowship Of SM Chr",
    "wof:placetype":"venue"
},
  "geometry": {"coordinates":[-76.561767,39.291558],"type":"Point"}
}