{
  "type": "Feature",
  "properties": {
    "addr:full":"4576 Edmondson Ave Baltimore MD 21229",
    "addr:housenumber":"4576",
    "addr:postcode":"21229",
    "addr:street":"Edmondson Ave",
    "iso:country":"US",
    "sg:address":"4576 Edmondson Ave",
    "sg:city":"Baltimore",
    "sg:classifiers":[
        {
            "category":"Banks & Credit Unions",
            "subcategory":"Bank",
            "type":"Services"
        }
    ],
    "sg:phone":"+1 410 233 1725",
    "sg:postcode":"21229",
    "sg:province":"MD",
    "sg:tags":[
        "cashing",
        "check"
    ],
    "wof:name":"American Check Cashing",
    "wof:placetype":"venue"
},
  "geometry": {"coordinates":[-76.693712,39.293535],"type":"Point"}
}