{
  "type": "Feature",
  "properties": {
    "iso:country":"US",
    "sg:address":"2331 Broadbirch Dr",
    "sg:city":"Silver Spring",
    "sg:classifiers":[
        {
            "category":"Health Services",
            "subcategory":"Nursing And Care Facility",
            "type":"Services"
        }
    ],
    "sg:phone":"+1 301 680 7700",
    "sg:postcode":"20904",
    "sg:province":"MD",
    "wof:name":"Medstar Health",
    "wof:placetype":"venue"
},
  "geometry": {"coordinates":[-76.961489,39.055449],"type":"Point"}
}