{
  "type": "Feature",
  "properties": {
    "iso:country":"US",
    "sg:address":"120 E Baltimore St",
    "sg:city":"Baltimore",
    "sg:classifiers":[
        {
            "category":"Professional",
            "subcategory":"Lawyer & Legal Services",
            "type":"Services"
        }
    ],
    "sg:phone":"+1 301 783 3526",
    "sg:postcode":"21202",
    "sg:province":"MD",
    "wof:name":"Goldman Kathryn Atty",
    "wof:placetype":"venue"
},
  "geometry": {"coordinates":[-76.613035,39.289747],"type":"Point"}
}