{
  "type": "Feature",
  "properties": {
    "iso:country":"US",
    "sg:address":"10726 Hershey Dr",
    "sg:city":"Williamsport",
    "sg:classifiers":[
        {
            "category":"Building & Trades",
            "subcategory":"Plumbing",
            "type":"Services"
        }
    ],
    "sg:phone":"+1 301 797 0272",
    "sg:postcode":"21795",
    "sg:province":"MD",
    "sg:tags":[
        "contractor"
    ],
    "wof:name":"Shades Plumbing Heating",
    "wof:placetype":"venue"
},
  "geometry": {"coordinates":[-77.787593,39.608222],"type":"Point"}
}