{
  "type": "Feature",
  "properties": {
    "iso:country":"US",
    "sg:address":"23105 Three Notch Rd",
    "sg:city":"Lexington Park",
    "sg:classifiers":[
        {
            "category":"Shopping",
            "subcategory":"Mobile Phones",
            "type":"Retail Goods"
        }
    ],
    "sg:phone":"+1 301 863 9094",
    "sg:postcode":"20653",
    "sg:province":"MD",
    "wof:name":"Verizon Wireless",
    "wof:placetype":"venue"
},
  "geometry": {"coordinates":[-76.459999,38.257099],"type":"Point"}
}