{
  "type": "Feature",
  "properties": {
    "addr:full":"325 Steedman Point Rd Pasadena MD 21122",
    "addr:housenumber":"325",
    "addr:postcode":"21122",
    "addr:street":"Steedman Point Rd",
    "iso:country":"US",
    "sg:address":"325 Steedman Point Rd",
    "sg:city":"Pasadena",
    "sg:classifiers":[
        {
            "category":"Shopping",
            "subcategory":"Stationery & Office Supplies",
            "type":"Retail Goods"
        },
        {
            "category":"Retail",
            "subcategory":"Repair Shop",
            "type":"Services"
        },
        {
            "category":"Manufacturing",
            "subcategory":"Paper Products",
            "type":"Manufacturing & Wholesale Goods"
        }
    ],
    "sg:phone":"+1 410 255 2233",
    "sg:postcode":"21122",
    "sg:province":"MD",
    "sg:tags":[
        "machine",
        "equipment",
        "stationery-wholesale",
        "copy",
        "store",
        "manufacturer"
    ],
    "wof:name":"Equipment Dealers",
    "wof:placetype":"venue"
},
  "geometry": {"coordinates":[-76.51047199999999,39.089301],"type":"Point"}
}