{
  "type": "Feature",
  "properties": {
    "addr:full":"903 Dropleaf Ct Pikesville MD 21208",
    "addr:housenumber":"903",
    "addr:postcode":"21208",
    "addr:street":"Dropleaf Ct",
    "iso:country":"US",
    "sg:address":"903 Dropleaf Ct",
    "sg:city":"Pikesville",
    "sg:classifiers":[
        {
            "category":"Shopping",
            "subcategory":"Used Merchandise",
            "type":"Retail Goods"
        }
    ],
    "sg:phone":"+1 410 486 8813",
    "sg:postcode":"21208",
    "sg:province":"MD",
    "wof:name":"Carole S Antiques",
    "wof:placetype":"venue"
},
  "geometry": {"coordinates":[-76.744359,39.362555],"type":"Point"}
}