{
  "type": "Feature",
  "properties": {
    "addr:full":"4111 Harney Rd Taneytown MD 21787",
    "addr:housenumber":"4111",
    "addr:postcode":"21787",
    "addr:street":"Harney Rd",
    "iso:country":"US",
    "sg:address":"4111 Harney Rd",
    "sg:city":"Taneytown",
    "sg:classifiers":[
        {
            "category":"Professional",
            "type":"Services"
        }
    ],
    "sg:phone":"+1 301 471 3060",
    "sg:postcode":"21787",
    "sg:province":"MD",
    "wof:name":"Ah Technical Services",
    "wof:placetype":"venue"
},
  "geometry": {"coordinates":[-77.19416099999999,39.69503],"type":"Point"}
}