{
  "type": "Feature",
  "properties": {
    "addr:full":"1013 Wilso Dr Baltimore MD 21223",
    "addr:housenumber":"1013",
    "addr:postcode":"21223",
    "addr:street":"Wilso Dr",
    "iso:country":"US",
    "sg:address":"1013 Wilso Dr",
    "sg:city":"Baltimore",
    "sg:classifiers":[
        {
            "category":"Building & Trades",
            "subcategory":"Pest Control",
            "type":"Services"
        }
    ],
    "sg:phone":"+1 410 525 3400",
    "sg:postcode":"21223",
    "sg:province":"MD",
    "wof:name":"American Hearth Bakery LLC",
    "wof:placetype":"venue"
},
  "geometry": {"coordinates":[-76.665021,39.271658],"type":"Point"}
}