{
  "type": "Feature",
  "properties": {
    "addr:full":"405 W Franklin St Hagerstown MD 21740",
    "addr:housenumber":"405",
    "addr:postcode":"21740",
    "addr:street":"W Franklin St",
    "iso:country":"US",
    "sg:address":"405 W Franklin St",
    "sg:city":"Hagerstown",
    "sg:classifiers":[
        {
            "category":"Shopping",
            "subcategory":"Gifts & Souvenirs",
            "type":"Retail Goods"
        }
    ],
    "sg:phone":"+1 301 797 6965",
    "sg:postcode":"21740",
    "sg:province":"MD",
    "sg:tags":[
        "shop"
    ],
    "wof:name":"Country Peddler",
    "wof:placetype":"venue"
},
  "geometry": {"coordinates":[-77.727487,39.647155],"type":"Point"}
}