{
  "type": "Feature",
  "properties": {
    "addr:full":"15417 Merrifields Ln Silver Spring MD 20906",
    "addr:postcode":"15417;20906",
    "addr:street":"Merrifields Ln",
    "iso:country":"US",
    "sg:address":"15417 Merrifields Ln",
    "sg:city":"Silver Spring",
    "sg:classifiers":[
        {
            "category":"Professional",
            "type":"Services"
        }
    ],
    "sg:phone":"+1 301 438 7601",
    "sg:postcode":"20906",
    "sg:province":"MD",
    "sg:tags":[
        "new",
        "writer",
        "journalist"
    ],
    "wof:name":"Karen Leggett-Abouraya",
    "wof:placetype":"venue"
},
  "geometry": {"coordinates":[-77.04917500000001,39.110089],"type":"Point"}
}