{
  "type": "Feature",
  "properties": {
    "addr:full":"7459 Cedar Grove Ln Elkridge MD 21075",
    "addr:housenumber":"7459",
    "addr:postcode":"21075",
    "addr:street":"Cedar Grove Ln",
    "iso:country":"US",
    "sg:address":"7459 Cedar Grove Ln",
    "sg:city":"Elkridge",
    "sg:classifiers":[
        {
            "category":"Personal",
            "type":"Services"
        },
        {
            "category":"Professional",
            "subcategory":"Art Services",
            "type":"Services"
        }
    ],
    "sg:phone":"+1 443 629 8259",
    "sg:postcode":"21075",
    "sg:province":"MD",
    "sg:tags":[
        "photography",
        "videography",
        "wedding"
    ],
    "wof:name":"Digi Fotos By Lisa",
    "wof:placetype":"venue"
},
  "geometry": {"coordinates":[-76.778794,39.180135],"type":"Point"}
}