{
  "type": "Feature",
  "properties": {
    "addr:full":"7818 Bradshaw Rd Kingsville MD 21087",
    "addr:housenumber":"7818",
    "addr:postcode":"21087",
    "addr:street":"Bradshaw Rd",
    "iso:country":"US",
    "sg:address":"7818 Bradshaw Rd",
    "sg:city":"Kingsville",
    "sg:classifiers":[
        {
            "category":"Shopping",
            "subcategory":"Antiques",
            "type":"Retail Goods"
        }
    ],
    "sg:phone":"+1 410 592 6884",
    "sg:postcode":"21087",
    "sg:province":"MD",
    "wof:name":"Pete's Pickin's",
    "wof:placetype":"venue"
},
  "geometry": {"coordinates":[-76.4021,39.436798],"type":"Point"}
}