{
  "type": "Feature",
  "properties": {
    "iso:country":"US",
    "sg:address":"3901 Red Deer Cir",
    "sg:city":"Randallstown",
    "sg:classifiers":[
        {
            "category":"Building & Trades",
            "subcategory":"Construction",
            "type":"Services"
        }
    ],
    "sg:phone":"+1 301 350 0400",
    "sg:postcode":"21133",
    "sg:province":"MD",
    "sg:tags":[
        "home",
        "builder"
    ],
    "wof:name":"Robin Hood Homes",
    "wof:placetype":"venue"
},
  "geometry": {"coordinates":[-76.816317,39.378841],"type":"Point"}
}