{
  "type": "Feature",
  "properties": {
    "addr:full":"4700 Boston Way Ste D Lanham MD 20706",
    "addr:housenumber":"4700",
    "addr:postcode":"20706",
    "addr:street":"Boston Way Ste D",
    "iso:country":"US",
    "sg:address":"4700 Boston Way Ste D",
    "sg:city":"Lanham",
    "sg:classifiers":[
        {
            "category":"Building & Trades",
            "subcategory":"Construction",
            "type":"Services"
        }
    ],
    "sg:phone":"+1 301 420 0205",
    "sg:postcode":"20706",
    "sg:province":"MD",
    "sg:tags":[
        "wallcoverings-installation",
        "wallpaper",
        "painting",
        "contractor"
    ],
    "wof:name":"Painter's Local Union No 368",
    "wof:placetype":"venue"
},
  "geometry": {"coordinates":[-76.839027,38.954381],"type":"Point"}
}