{
  "type": "Feature",
  "properties": {
    "iso:country":"US",
    "sg:address":"11516 Darnestown Rd",
    "sg:city":"Gaithersburg",
    "sg:classifiers":[
        {
            "category":"Professional",
            "subcategory":"Management & Consulting",
            "type":"Services"
        }
    ],
    "sg:phone":"+1 301 926 0566",
    "sg:postcode":"20878",
    "sg:province":"MD",
    "sg:tags":[
        "science",
        "consultant",
        "academic"
    ],
    "wof:name":"Cancure Consulting",
    "wof:placetype":"venue"
},
  "geometry": {"coordinates":[-77.239993,39.111616],"type":"Point"}
}