{
  "type": "Feature",
  "properties": {
    "iso:country":"US",
    "sg:address":"15225 Rosecroft Rd",
    "sg:city":"Rockville",
    "sg:classifiers":[
        {
            "category":"Building & Trades",
            "subcategory":"Pest Control",
            "type":"Services"
        }
    ],
    "sg:phone":"+1 301 929 9007",
    "sg:postcode":"20853",
    "sg:province":"MD",
    "wof:name":"Bee Be Gone",
    "wof:placetype":"venue"
},
  "geometry": {"coordinates":[-77.078514,39.103215],"type":"Point"}
}