{
  "type": "Feature",
  "properties": {
    "addr:full":"8095 Edwin Raynor Blvd Pasadena MD 21122",
    "addr:housenumber":"8095",
    "addr:postcode":"21122",
    "addr:street":"Edwin Raynor Blvd",
    "iso:country":"US",
    "sg:address":"8095 Edwin Raynor Blvd",
    "sg:city":"Pasadena",
    "sg:classifiers":[
        {
            "category":"Restaurant",
            "type":"Food & Drink"
        }
    ],
    "sg:menulink":"http://www.allmenus.com/md/lake-shore/87524-little-caesars-pizza/menu/",
    "sg:phone":"+1 410 360 9500",
    "sg:postcode":"21122",
    "sg:province":"MD",
    "sg:tags":[
        "american",
        "pizza"
    ],
    "wof:name":"Little Caesar's Pizza",
    "wof:placetype":"venue"
},
  "geometry": {"coordinates":[-76.531149,39.126662],"type":"Point"}
}