{
  "type": "Feature",
  "properties": {
    "iso:country":"US",
    "sg:address":"1100 Wicomico St Ste 601",
    "sg:city":"Baltimore",
    "sg:classifiers":[
        {
            "category":"Food & Beverages",
            "subcategory":"Groceries & Convenience Stores",
            "type":"Retail Goods"
        }
    ],
    "sg:phone":"+1 410 783 1584",
    "sg:postcode":"21230",
    "sg:province":"MD",
    "wof:name":"Stop, Shop & Save, Inc.",
    "wof:placetype":"venue"
},
  "geometry": {"coordinates":[-76.628693,39.279758],"type":"Point"}
}