{
  "type": "Feature",
  "properties": {
    "iso:country":"US",
    "sg:address":"3 S 3rd St",
    "sg:city":"Oakland",
    "sg:classifiers":[
        {
            "category":"Professional",
            "subcategory":"Lawyer & Legal Services",
            "type":"Services"
        }
    ],
    "sg:phone":"+1 301 334 3522",
    "sg:postcode":"21550",
    "sg:province":"MD",
    "sg:tags":[
        "attorney"
    ],
    "wof:name":"Angela Blythe",
    "wof:placetype":"venue"
},
  "geometry": {"coordinates":[-79.40574700000001,39.410372],"type":"Point"}
}