{
  "type": "Feature",
  "properties": {
    "addr:full":"1414 Dilston Rd Silver Spring MD 20903",
    "addr:housenumber":"1414",
    "addr:postcode":"20903",
    "addr:street":"Dilston Rd",
    "iso:country":"US",
    "sg:address":"1414 Dilston Rd",
    "sg:city":"Silver Spring",
    "sg:classifiers":[
        {
            "category":"Professional",
            "subcategory":"Detective & Security Services",
            "type":"Services"
        }
    ],
    "sg:phone":"+1 301 445 6616",
    "sg:postcode":"20903",
    "sg:province":"MD",
    "sg:tags":[
        "agency"
    ],
    "wof:name":"Wiseguy Private Investigative",
    "wof:placetype":"venue"
},
  "geometry": {"coordinates":[-76.982584,39.013128],"type":"Point"}
}