{
  "type": "Feature",
  "properties": {
    "iso:country":"US",
    "sg:address":"3601 West St",
    "sg:city":"Hyattsville",
    "sg:classifiers":[
        {
            "category":"Restaurant",
            "type":"Food & Drink"
        }
    ],
    "sg:phone":"+1 301 386 9090",
    "sg:postcode":"20785",
    "sg:province":"MD",
    "sg:tags":[
        "mexican"
    ],
    "wof:name":"Moctec Enterprises",
    "wof:placetype":"venue"
},
  "geometry": {"coordinates":[-76.860703,38.939301],"type":"Point"}
}