{
  "type": "Feature",
  "properties": {
    "addr:full":"28929 Three Notch Rd Mechanicsville MD 20659",
    "addr:housenumber":"28929",
    "addr:postcode":"20659",
    "addr:street":"Three Notch Rd",
    "iso:country":"US",
    "sg:address":"28929 Three Notch Rd",
    "sg:city":"Mechanicsville",
    "sg:classifiers":[
        {
            "category":"Professional",
            "subcategory":"Accounting & Tax Preparation",
            "type":"Services"
        }
    ],
    "sg:phone":"+1 301 290 0070",
    "sg:postcode":"20659",
    "sg:province":"MD",
    "sg:tags":[
        "return",
        "filing"
    ],
    "wof:name":"Southern MD Tax Svc",
    "wof:placetype":"venue"
},
  "geometry": {"coordinates":[-76.76628100000001,38.463008],"type":"Point"}
}