{
  "type": "Feature",
  "properties": {
    "iso:country":"US",
    "sg:address":"10347 Champions Way",
    "sg:city":"Laurel",
    "sg:classifiers":[
        {
            "category":"Professional",
            "subcategory":"Engineering",
            "type":"Services"
        }
    ],
    "sg:phone":"+1 301 953 3040",
    "sg:postcode":"20723",
    "sg:province":"MD",
    "sg:tags":[
        "engineer"
    ],
    "wof:name":"Technical Representatives Inc",
    "wof:placetype":"venue"
},
  "geometry": {"coordinates":[-76.866455,39.152429],"type":"Point"}
}