{
  "type": "Feature",
  "properties": {
    "iso:country":"US",
    "sg:address":"1801 Rockville Pike",
    "sg:city":"Rockville",
    "sg:classifiers":[
        {
            "category":"Professional",
            "type":"Services"
        }
    ],
    "sg:phone":"+1 301 230 0030",
    "sg:postcode":"20852",
    "sg:province":"MD",
    "sg:tags":[
        "establishment"
    ],
    "wof:name":"1801 Rockville Pke Mgmt Ofc",
    "wof:placetype":"venue"
},
  "geometry": {"coordinates":[-77.121803,39.059303],"type":"Point"}
}