{
  "type": "Feature",
  "properties": {
    "iso:country":"US",
    "sg:address":"6999 Reisterstown Rd",
    "sg:city":"Baltimore",
    "sg:classifiers":[
        {
            "category":"Shopping",
            "subcategory":"Shoes",
            "type":"Retail Goods"
        }
    ],
    "sg:phone":"+1 410 318 6586",
    "sg:postcode":"21215",
    "sg:province":"MD",
    "wof:name":"Shoe Studio",
    "wof:placetype":"venue"
},
  "geometry": {"coordinates":[-76.709115,39.361345],"type":"Point"}
}