{
  "type": "Feature",
  "properties": {
    "addr:full":"3909 Jefferson St Hyattsville MD 20781",
    "addr:housenumber":"3909",
    "addr:postcode":"20781",
    "addr:street":"Jefferson St",
    "iso:country":"US",
    "sg:address":"3909 Jefferson St",
    "sg:city":"Hyattsville",
    "sg:classifiers":[
        {
            "category":"Manufacturing",
            "subcategory":"Metals",
            "type":"Manufacturing & Wholesale Goods"
        }
    ],
    "sg:phone":"+1 301 209 9452",
    "sg:postcode":"20781",
    "sg:province":"MD",
    "sg:tags":[
        "finisher"
    ],
    "wof:name":"CLD Metal & Painting",
    "wof:placetype":"venue"
},
  "geometry": {"coordinates":[-76.95003800000001,38.954637],"type":"Point"}
}