{
  "type": "Feature",
  "properties": {
    "addr:full":"30293 Mount Vernon Rd Princess Anne MD 21853",
    "addr:housenumber":"30293",
    "addr:postcode":"21853",
    "addr:street":"Mount Vernon Rd",
    "iso:country":"US",
    "sg:address":"30293 Mount Vernon Rd",
    "sg:city":"Princess Anne",
    "sg:classifiers":[
        {
            "category":"Restaurant",
            "type":"Food & Drink"
        }
    ],
    "sg:phone":"+1 410 621 0232",
    "sg:postcode":"21853",
    "sg:province":"MD",
    "wof:name":"Popeyes Chicken & Biscuits",
    "wof:placetype":"venue"
},
  "geometry": {"coordinates":[-75.70114,38.213575],"type":"Point"}
}