{
  "type": "Feature",
  "properties": {
    "iso:country":"US",
    "sg:address":"21736 Great Mills Rd",
    "sg:city":"Lexington Park",
    "sg:classifiers":[
        {
            "category":"Restaurant",
            "type":"Food & Drink"
        }
    ],
    "sg:phone":"+1 301 863 5051",
    "sg:postcode":"20653",
    "sg:province":"MD",
    "wof:name":"Roost",
    "wof:placetype":"venue"
},
  "geometry": {"coordinates":[-76.455404,38.264521],"type":"Point"}
}