{
  "type": "Feature",
  "properties": {
    "iso:country":"US",
    "sg:address":"7004 Kepner Ct",
    "sg:city":"Lanham",
    "sg:classifiers":[
        {
            "category":"Marine",
            "type":"Transportation"
        }
    ],
    "sg:phone":"+1 301 552 3450",
    "sg:postcode":"20706",
    "sg:province":"MD",
    "sg:tags":[
        "towing"
    ],
    "wof:name":"Menehune Marine Svc",
    "wof:placetype":"venue"
},
  "geometry": {"coordinates":[-76.882099,38.985855],"type":"Point"}
}