{
  "type": "Feature",
  "properties": {
    "iso:country":"US",
    "sg:address":"413 Kennedy St NW",
    "sg:city":"Washington",
    "sg:classifiers":[
        {
            "category":"Retail",
            "subcategory":"Laundry & Dry Cleaning",
            "type":"Services"
        }
    ],
    "sg:phone":"+1 202 726 7733",
    "sg:postcode":"20011",
    "sg:province":"MD",
    "sg:tags":[
        "cleaners"
    ],
    "wof:name":"E & G Cleaners",
    "wof:placetype":"venue"
},
  "geometry": {"coordinates":[-77.01969200000001,38.956532],"type":"Point"}
}