{
  "type": "Feature",
  "properties": {
    "addr:full":"2939 Olney Sandy Spring Rd Ste B Olney MD 20832",
    "addr:housenumber":"2939",
    "addr:postcode":"20832",
    "addr:street":"Olney Sandy Spring Rd Ste B",
    "iso:country":"US",
    "sg:address":"2939 Olney Sandy Spring Rd Ste B",
    "sg:city":"Olney",
    "sg:classifiers":[
        {
            "category":"Insurance",
            "subcategory":"Hazard Insurance",
            "type":"Services"
        }
    ],
    "sg:phone":"+1 301 774 7144",
    "sg:postcode":"20832",
    "sg:province":"MD",
    "sg:website":"http://statefarm.mqgroup.com/url.asp?usr=209471",
    "wof:name":"State Farm Insurance Agent-Tim Breidenstein",
    "wof:placetype":"venue"
},
  "geometry": {"coordinates":[-77.061173,39.15054],"type":"Point"}
}