{
  "type": "Feature",
  "properties": {
    "iso:country":"US",
    "sg:address":"5534 Randolph Rd",
    "sg:city":"Rockville",
    "sg:classifiers":[
        {
            "category":"Personal",
            "subcategory":"Beauty Salon",
            "type":"Services"
        }
    ],
    "sg:phone":"+1 301 881 5571",
    "sg:postcode":"20852",
    "sg:province":"MD",
    "wof:name":"Salon Gabor",
    "wof:placetype":"venue"
},
  "geometry": {"coordinates":[-77.113246,39.053173],"type":"Point"}
}