{
  "type": "Feature",
  "properties": {
    "iso:country":"US",
    "sg:address":"7105 MacArthur Blvd",
    "sg:city":"Bethesda",
    "sg:classifiers":[
        {
            "category":"Building & Trades",
            "subcategory":"Locksmith",
            "type":"Services"
        }
    ],
    "sg:phone":"+1 202 621 2138",
    "sg:postcode":"20816",
    "sg:province":"MD",
    "sg:tags":[
        "key"
    ],
    "wof:name":"Dancing Locksmith",
    "wof:placetype":"venue"
},
  "geometry": {"coordinates":[-77.137788,38.967447],"type":"Point"}
}