{
  "type": "Feature",
  "properties": {
    "iso:country":"US",
    "sg:address":"10 S Calvert St",
    "sg:city":"Baltimore",
    "sg:classifiers":[
        {
            "category":"Restaurant",
            "type":"Food & Drink"
        }
    ],
    "sg:phone":"+1 410 528 5110",
    "sg:postcode":"21202",
    "sg:province":"MD",
    "sg:tags":[
        "new",
        "american"
    ],
    "sg:website":"www.xanadubaltimore.com",
    "wof:name":"Xanadu",
    "wof:placetype":"venue"
},
  "geometry": {"coordinates":[-76.61225899999999,39.289253],"type":"Point"}
}