{
  "type": "Feature",
  "properties": {
    "addr:full":"4925 Bethesda Ave Bethesda MD 20814",
    "addr:housenumber":"4925",
    "addr:postcode":"20814",
    "addr:street":"Bethesda Ave",
    "iso:country":"US",
    "sg:address":"4925 Bethesda Ave",
    "sg:city":"Bethesda",
    "sg:classifiers":[
        {
            "category":"Autos & Motor Vehicles",
            "subcategory":"Auto Supplies",
            "type":"Retail Goods"
        }
    ],
    "sg:phone":"+1 301 986 1370",
    "sg:postcode":"20814",
    "sg:province":"MD",
    "sg:tags":[
        "automobile",
        "parts"
    ],
    "wof:name":"Bethesda Auto Parts",
    "wof:placetype":"venue"
},
  "geometry": {"coordinates":[-77.10031600000001,38.980857],"type":"Point"}
}