{
  "type": "Feature",
  "properties": {
    "addr:full":"12100 Woodford Dr Marriottsville MD 21104",
    "addr:housenumber":"12100",
    "addr:postcode":"21104",
    "addr:street":"Woodford Dr",
    "iso:country":"US",
    "sg:address":"12100 Woodford Dr",
    "sg:city":"Marriottsville",
    "sg:classifiers":[
        {
            "category":"Building & Trades",
            "subcategory":"Electrical",
            "type":"Services"
        }
    ],
    "sg:phone":"+1 410 442 5922",
    "sg:postcode":"21104",
    "sg:province":"MD",
    "sg:tags":[
        "electric",
        "contractor"
    ],
    "wof:name":"Crown Electric Co",
    "wof:placetype":"venue"
},
  "geometry": {"coordinates":[-76.935473,39.320886],"type":"Point"}
}