{
  "type": "Feature",
  "properties": {
    "iso:country":"US",
    "sg:address":"7717 Carroll Ave",
    "sg:city":"Takoma Park",
    "sg:classifiers":[
        {
            "category":"Building & Trades",
            "subcategory":"Plumbing",
            "type":"Services"
        }
    ],
    "sg:phone":"+1 301 891 3377",
    "sg:postcode":"20912",
    "sg:province":"MD",
    "sg:tags":[
        "plumbing",
        "heating",
        "contractor"
    ],
    "wof:name":"EDi Plumbing & Heating Svc",
    "wof:placetype":"venue"
},
  "geometry": {"coordinates":[-76.99640599999999,38.986083],"type":"Point"}
}