{
  "type": "Feature",
  "properties": {
    "iso:country":"US",
    "sg:address":"12605 Pentenville Rd",
    "sg:city":"Silver Spring",
    "sg:classifiers":[
        {
            "category":"Health Services",
            "subcategory":"Doctor",
            "type":"Services"
        }
    ],
    "sg:phone":"+1 301 622 2488",
    "sg:postcode":"20904",
    "sg:province":"MD",
    "wof:name":"Sweetbaum Harvey A PHD",
    "wof:placetype":"venue"
},
  "geometry": {"coordinates":[-77.014702,39.063202],"type":"Point"}
}