{
  "type": "Feature",
  "properties": {
    "addr:full":"518 S Marlyn Ave Essex MD 21221",
    "addr:housenumber":"518",
    "addr:postcode":"21221",
    "addr:street":"S Marlyn Ave",
    "iso:country":"US",
    "sg:address":"518 S Marlyn Ave",
    "sg:city":"Essex",
    "sg:classifiers":[
        {
            "category":"Personal",
            "subcategory":"Tanning Parlor",
            "type":"Services"
        }
    ],
    "sg:phone":"+1 410 238 0800",
    "sg:postcode":"21221",
    "sg:province":"MD",
    "sg:website":"www.shirleystantone.com",
    "wof:name":"Shirley's Tan & Tone",
    "wof:placetype":"venue"
},
  "geometry": {"coordinates":[-76.463402,39.305],"type":"Point"}
}