{
  "type": "Feature",
  "properties": {
    "addr:full":"5711 Odonnell St Baltimore MD 21224",
    "addr:housenumber":"5711",
    "addr:postcode":"21224",
    "addr:street":"Odonnell St",
    "iso:country":"US",
    "sg:address":"5711 Odonnell St",
    "sg:city":"Baltimore",
    "sg:classifiers":[
        {
            "category":"Professional",
            "subcategory":"Detective & Security Services",
            "type":"Services"
        }
    ],
    "sg:phone":"+1 410 488 1240",
    "sg:postcode":"21224",
    "sg:province":"MD",
    "sg:tags":[
        "information",
        "bureau"
    ],
    "wof:name":"Ogars Car Hire Service",
    "wof:placetype":"venue"
},
  "geometry": {"coordinates":[-76.54669199999999,39.281309],"type":"Point"}
}