{
  "type": "Feature",
  "properties": {
    "addr:full":"23188 Colton Point Rd Avenue MD 20609",
    "addr:postcode":"23188;20609",
    "addr:street":"Colton Point Rd Avenue",
    "iso:country":"US",
    "sg:address":"23188 Colton Point Rd",
    "sg:city":"Avenue",
    "sg:classifiers":[
        {
            "category":"Building & Trades",
            "subcategory":"Cleaning & Sanitation",
            "type":"Services"
        }
    ],
    "sg:phone":"+1 301 769 4778",
    "sg:postcode":"20609",
    "sg:province":"MD",
    "sg:tags":[
        "janitor"
    ],
    "wof:name":"Squeaky Clean",
    "wof:placetype":"venue"
},
  "geometry": {"coordinates":[-76.75882300000001,38.296203],"type":"Point"}
}