{
  "type": "Feature",
  "properties": {
    "addr:full":"217 Phillip Morris Dr Salisbury MD 21804",
    "addr:housenumber":"217",
    "addr:postcode":"21804",
    "addr:street":"Phillip Morris Dr",
    "iso:country":"US",
    "sg:address":"217 Phillip Morris Dr",
    "sg:city":"Salisbury",
    "sg:classifiers":[
        {
            "category":"Health Services",
            "subcategory":"Doctor",
            "type":"Services"
        }
    ],
    "sg:phone":"+1 410 546 3173",
    "sg:postcode":"21804",
    "sg:province":"MD",
    "sg:tags":[
        "physician",
        "surgeon"
    ],
    "wof:name":"Childrens Med Grp-Salisbury",
    "wof:placetype":"venue"
},
  "geometry": {"coordinates":[-75.554479,38.370521],"type":"Point"}
}