{
  "type": "Feature",
  "properties": {
    "addr:full":"1625 Ruxton Rd Edgewater MD 21037",
    "addr:housenumber":"1625",
    "addr:postcode":"21037",
    "addr:street":"Ruxton Rd",
    "iso:country":"US",
    "sg:address":"1625 Ruxton Rd",
    "sg:city":"Edgewater",
    "sg:classifiers":[
        {
            "category":"Recreation",
            "subcategory":"Marina",
            "type":"Entertainment"
        }
    ],
    "sg:phone":"+1 410 956 4732",
    "sg:postcode":"21037",
    "sg:province":"MD",
    "sg:tags":[
        "repairing",
        "boat"
    ],
    "wof:name":"Maritime Mobile Marine",
    "wof:placetype":"venue"
},
  "geometry": {"coordinates":[-76.54830800000001,38.935408],"type":"Point"}
}