{
  "type": "Feature",
  "properties": {
    "addr:full":"6907 Canyon Dr Capitol Heights MD 20743",
    "addr:housenumber":"6907",
    "addr:postcode":"20743",
    "addr:street":"Canyon Dr",
    "iso:country":"US",
    "sg:address":"6907 Canyon Dr",
    "sg:city":"Capitol Heights",
    "sg:classifiers":[
        {
            "category":"Building & Trades",
            "subcategory":"Landscaping Services",
            "type":"Services"
        }
    ],
    "sg:phone":"+1 301 336 1042",
    "sg:postcode":"20743",
    "sg:province":"MD",
    "sg:tags":[
        "lawn",
        "maintenance",
        "grounds"
    ],
    "wof:name":"Jordon Lawn & Maintenance",
    "wof:placetype":"venue"
},
  "geometry": {"coordinates":[-76.885835,38.890376],"type":"Point"}
}