{
  "type": "Feature",
  "properties": {
    "addr:full":"9103 Crosshill Rd Parkville MD 21234",
    "addr:housenumber":"9103",
    "addr:postcode":"21234",
    "addr:street":"Crosshill Rd",
    "iso:country":"US",
    "sg:address":"9103 Crosshill Rd",
    "sg:city":"Parkville",
    "sg:classifiers":[
        {
            "category":"Sports & Exercise",
            "subcategory":"Sports Center",
            "type":"Entertainment"
        }
    ],
    "sg:phone":"+1 410 882 9134",
    "sg:postcode":"21234",
    "sg:province":"MD",
    "sg:tags":[
        "manager",
        "promoter"
    ],
    "wof:name":"Universal Sports",
    "wof:placetype":"venue"
},
  "geometry": {"coordinates":[-76.51953899999999,39.385021],"type":"Point"}
}