{
  "type": "Feature",
  "properties": {
    "addr:full":"4025 Deepwood Rd Baltimore MD 21218",
    "addr:housenumber":"4025",
    "addr:postcode":"21218",
    "addr:street":"Deepwood Rd",
    "iso:country":"US",
    "sg:address":"4025 Deepwood Rd",
    "sg:city":"Baltimore",
    "sg:classifiers":[
        {
            "category":"Health Services",
            "subcategory":"Doctor",
            "type":"Services"
        }
    ],
    "sg:phone":"+1 410 235 2888",
    "sg:postcode":"21218",
    "sg:province":"MD",
    "wof:name":"Romanoski Alan J MD",
    "wof:placetype":"venue"
},
  "geometry": {"coordinates":[-76.59870100000001,39.339199],"type":"Point"}
}