{
  "type": "Feature",
  "properties": {
    "addr:full":"10900 Pump House Rd Annapolis Jct MD 20701",
    "addr:housenumber":"10900",
    "addr:postcode":"20701",
    "addr:street":"Pump House Rd",
    "iso:country":"US",
    "sg:address":"10900 Pump House Rd",
    "sg:city":"Annapolis Jct",
    "sg:classifiers":[
        {
            "category":"Professional",
            "subcategory":"Art Services",
            "type":"Services"
        }
    ],
    "sg:phone":"+1 301 725 8000",
    "sg:postcode":"20701",
    "sg:province":"MD",
    "sg:tags":[
        "graphic",
        "designer"
    ],
    "sg:website":"www.mm4solutions.com",
    "wof:name":"Millennium Printing & Graphics",
    "wof:placetype":"venue"
},
  "geometry": {"coordinates":[-76.791966,39.131347],"type":"Point"}
}