{
  "type": "Feature",
  "properties": {
    "iso:country":"US",
    "sg:address":"18 S Higgins St",
    "sg:city":"Easton",
    "sg:classifiers":[
        {
            "category":"Organizations",
            "subcategory":"Religious Organization",
            "type":"Services"
        }
    ],
    "sg:phone":"+1 410 822 3476",
    "sg:postcode":"21601",
    "sg:province":"MD",
    "sg:tags":[
        "church"
    ],
    "wof:name":"Asbury United Methodist Church",
    "wof:placetype":"venue"
},
  "geometry": {"coordinates":[-76.069976,38.773309],"type":"Point"}
}