{
  "type": "Feature",
  "properties": {
    "addr:full":"305 N Beaumont Ave Catonsville MD 21228",
    "addr:housenumber":"305",
    "addr:postcode":"21228",
    "addr:street":"N Beaumont Ave",
    "iso:country":"US",
    "sg:address":"305 N Beaumont Ave",
    "sg:city":"Catonsville",
    "sg:classifiers":[
        {
            "category":"Building & Trades",
            "subcategory":"Construction",
            "type":"Services"
        }
    ],
    "sg:phone":"+1 410 719 7489",
    "sg:postcode":"21228",
    "sg:province":"MD",
    "sg:tags":[
        "roofing",
        "contractor"
    ],
    "wof:name":"Westview Roofing Co",
    "wof:placetype":"venue"
},
  "geometry": {"coordinates":[-76.746242,39.278261],"type":"Point"}
}