{
  "type": "Feature",
  "properties": {
    "addr:full":"48 E Water St Smithsburg MD 21783",
    "addr:housenumber":"48",
    "addr:postcode":"21783",
    "addr:street":"E Water St",
    "iso:country":"US",
    "sg:address":"48 E Water St",
    "sg:city":"Smithsburg",
    "sg:classifiers":[
        {
            "category":"Insurance",
            "subcategory":"Hazard Insurance",
            "type":"Services"
        }
    ],
    "sg:phone":"+1 301 241 3989",
    "sg:postcode":"21783",
    "sg:province":"MD",
    "wof:name":"Abbott, Shaune",
    "wof:placetype":"venue"
},
  "geometry": {"coordinates":[-77.56909899999999,39.65657],"type":"Point"}
}