{
  "type": "Feature",
  "properties": {
    "addr:full":"7928 Allendale Dr Hyattsville MD 20785",
    "addr:housenumber":"7928",
    "addr:postcode":"20785",
    "addr:street":"Allendale Dr",
    "iso:country":"US",
    "sg:address":"7928 Allendale Dr",
    "sg:city":"Hyattsville",
    "sg:classifiers":[
        {
            "category":"Building & Trades",
            "subcategory":"Construction",
            "type":"Services"
        }
    ],
    "sg:phone":"+1 301 773 6901",
    "sg:postcode":"20785",
    "sg:province":"MD",
    "sg:tags":[
        "altering",
        "industrial",
        "remodeling",
        "contractors-commercial",
        "contractor"
    ],
    "wof:name":"Tolbert Construction",
    "wof:placetype":"venue"
},
  "geometry": {"coordinates":[-76.868156,38.91431],"type":"Point"}
}