{
  "type": "Feature",
  "properties": {
    "addr:full":"10611 Featherstone Dr Fort Washington MD 20744",
    "addr:housenumber":"10611",
    "addr:postcode":"20744",
    "addr:street":"Featherstone Dr",
    "iso:country":"US",
    "sg:address":"10611 Featherstone Dr",
    "sg:city":"Fort Washington",
    "sg:classifiers":[
        {
            "category":"Education",
            "subcategory":"Special Training",
            "type":"Public Place"
        }
    ],
    "sg:phone":"+1 301 203 0749",
    "sg:postcode":"20744",
    "sg:province":"MD",
    "wof:name":"Gospel Music Enterprises",
    "wof:placetype":"venue"
},
  "geometry": {"coordinates":[-76.962203,38.744454],"type":"Point"}
}