{
  "type": "Feature",
  "properties": {
    "iso:country":"US",
    "sg:address":"1938 Glenroths Dr",
    "sg:city":"Abingdon",
    "sg:classifiers":[
        {
            "category":"Freight",
            "type":"Transportation"
        }
    ],
    "sg:phone":"+1 443 512 0290",
    "sg:postcode":"21009",
    "sg:province":"MD",
    "wof:name":"Victors Transportation",
    "wof:placetype":"venue"
},
  "geometry": {"coordinates":[-76.329173,39.478599],"type":"Point"}
}