{
  "type": "Feature",
  "properties": {
    "iso:country":"US",
    "sg:address":"3600 Clipper Mill Rd Ste 201",
    "sg:city":"Baltimore",
    "sg:classifiers":[
        {
            "category":"Professional",
            "subcategory":"Lawyer & Legal Services",
            "type":"Services"
        }
    ],
    "sg:phone":"+1 410 662 5586",
    "sg:postcode":"21211",
    "sg:province":"MD",
    "wof:name":"Saunders Thomas J",
    "wof:placetype":"venue"
},
  "geometry": {"coordinates":[-76.641379,39.33062],"type":"Point"}
}