{
  "type": "Feature",
  "properties": {
    "addr:full":"3000 Festival Way Waldorf MD 20601",
    "addr:housenumber":"3000",
    "addr:postcode":"20601",
    "addr:street":"Festival Way",
    "iso:country":"US",
    "sg:address":"3000 Festival Way",
    "sg:city":"Waldorf",
    "sg:classifiers":[
        {
            "category":"Shopping",
            "subcategory":"Computers & Home Electronics",
            "type":"Retail Goods"
        }
    ],
    "sg:phone":"+1 301 932 9100",
    "sg:postcode":"20601",
    "sg:province":"MD",
    "sg:tags":[
        "equipment",
        "electronic",
        "supply"
    ],
    "sg:website":"www.circuitcity.com",
    "wof:name":"Circuit City",
    "wof:placetype":"venue"
},
  "geometry": {"coordinates":[-76.910921,38.627605],"type":"Point"}
}