{
  "type": "Feature",
  "properties": {
    "addr:full":"626 Piccadilly Rd Baltimore MD 21204",
    "addr:housenumber":"626",
    "addr:postcode":"21204",
    "addr:street":"Piccadilly Rd",
    "iso:country":"US",
    "sg:address":"626 Piccadilly Rd",
    "sg:city":"Baltimore",
    "sg:classifiers":[
        {
            "category":"Professional",
            "subcategory":"Art Services",
            "type":"Services"
        }
    ],
    "sg:phone":"+1 410 494 1795",
    "sg:postcode":"21204",
    "sg:province":"MD",
    "sg:tags":[
        "commercial",
        "design"
    ],
    "wof:name":"Js Graphics",
    "wof:placetype":"venue"
},
  "geometry": {"coordinates":[-76.61932,39.408042],"type":"Point"}
}