{
  "type": "Feature",
  "properties": {
    "iso:country":"US",
    "sg:address":"6520 Woodbridge Cir",
    "sg:city":"Catonsville",
    "sg:classifiers":[
        {
            "category":"Building & Trades",
            "subcategory":"Construction",
            "type":"Services"
        }
    ],
    "sg:phone":"+1 410 788 5577",
    "sg:postcode":"21228",
    "sg:province":"MD",
    "sg:tags":[
        "system",
        "contractor",
        "air conditioning"
    ],
    "wof:name":"Maryland Comfort Systems",
    "wof:placetype":"venue"
},
  "geometry": {"coordinates":[-76.744057,39.298031],"type":"Point"}
}