{
  "type": "Feature",
  "properties": {
    "addr:full":"5021 Cedar Ave Halethorpe MD 21227",
    "addr:housenumber":"5021",
    "addr:postcode":"21227",
    "addr:street":"Cedar Ave",
    "iso:country":"US",
    "sg:address":"5021 Cedar Ave",
    "sg:city":"Halethorpe",
    "sg:classifiers":[
        {
            "category":"Shopping",
            "subcategory":"Discount & Variety Stores",
            "type":"Retail Goods"
        }
    ],
    "sg:phone":"+1 410 242 3187",
    "sg:postcode":"21227",
    "sg:province":"MD",
    "sg:tags":[
        "liquidator"
    ],
    "wof:name":"Salvage Liquidators",
    "wof:placetype":"venue"
},
  "geometry": {"coordinates":[-76.705406,39.227569],"type":"Point"}
}