{
  "type": "Feature",
  "properties": {
    "addr:full":"6218 Sudlersville Rd Sudlersville MD 21668",
    "addr:housenumber":"6218",
    "addr:postcode":"21668",
    "addr:street":"Sudlersville Rd",
    "iso:country":"US",
    "sg:address":"6218 Sudlersville Rd",
    "sg:city":"Sudlersville",
    "sg:classifiers":[
        {
            "category":"Professional",
            "subcategory":"Management & Consulting",
            "type":"Services"
        },
        {
            "category":"Professional",
            "subcategory":"Advertising",
            "type":"Services"
        }
    ],
    "sg:phone":"+1 410 438 3265",
    "sg:postcode":"21668",
    "sg:province":"MD",
    "sg:tags":[
        "marketing",
        "program",
        "consultant"
    ],
    "wof:name":"Winborne Marketing",
    "wof:placetype":"venue"
},
  "geometry": {"coordinates":[-75.791612,39.195881],"type":"Point"}
}