{
  "type": "Feature",
  "properties": {
    "addr:full":"170 Airport Dr Westminster MD 21157",
    "addr:housenumber":"170",
    "addr:postcode":"21157",
    "addr:street":"Airport Dr",
    "iso:country":"US",
    "sg:address":"170 Airport Dr",
    "sg:city":"Westminster",
    "sg:classifiers":[
        {
            "category":"Manufacturing",
            "subcategory":"Glass & Minerals",
            "type":"Manufacturing & Wholesale Goods"
        }
    ],
    "sg:phone":"+1 410 876 6866",
    "sg:postcode":"21157",
    "sg:province":"MD",
    "sg:tags":[
        "prod",
        "made"
    ],
    "wof:name":"Manchester Services Inc",
    "wof:placetype":"venue"
},
  "geometry": {"coordinates":[-77.00295199999999,39.606405],"type":"Point"}
}