{
  "type": "Feature",
  "properties": {
    "addr:full":"408 Swale Ave Baltimore MD 21225",
    "addr:housenumber":"408",
    "addr:postcode":"21225",
    "addr:street":"Swale Ave",
    "iso:country":"US",
    "sg:address":"408 Swale Ave",
    "sg:city":"Baltimore",
    "sg:classifiers":[
        {
            "category":"Organizations",
            "subcategory":"Religious Organization",
            "type":"Services"
        }
    ],
    "sg:phone":"+1 410 903 9032",
    "sg:postcode":"21225",
    "sg:province":"MD",
    "wof:name":"Jesus Designs",
    "wof:placetype":"venue"
},
  "geometry": {"coordinates":[-76.619119,39.250072],"type":"Point"}
}