{
  "type": "Feature",
  "properties": {
    "iso:country":"US",
    "sg:address":"849 Bradhurst Rd",
    "sg:city":"Baltimore",
    "sg:classifiers":[
        {
            "category":"Personal",
            "type":"Services"
        }
    ],
    "sg:phone":"+1 443 829 1440",
    "sg:postcode":"21212",
    "sg:province":"MD",
    "sg:tags":[
        "mover"
    ],
    "wof:name":"Kevin's Moving & Hauling Company",
    "wof:placetype":"venue"
},
  "geometry": {"coordinates":[-76.603155,39.359082],"type":"Point"}
}