{
  "type": "Feature",
  "properties": {
    "addr:full":"8095 Edwin Raynor Blvd Pasadena MD 21122",
    "addr:housenumber":"8095",
    "addr:postcode":"21122",
    "addr:street":"Edwin Raynor Blvd",
    "iso:country":"US",
    "sg:address":"8095 Edwin Raynor Blvd",
    "sg:city":"Pasadena",
    "sg:classifiers":[
        {
            "category":"Retail",
            "subcategory":"Laundry & Dry Cleaning",
            "type":"Services"
        }
    ],
    "sg:phone":"+1 410 439 5673",
    "sg:postcode":"21122",
    "sg:province":"MD",
    "sg:tags":[
        "cleaners"
    ],
    "wof:name":"Chesterfield Cleaners",
    "wof:placetype":"venue"
},
  "geometry": {"coordinates":[-76.529894,39.131477],"type":"Point"}
}