{
  "type": "Feature",
  "properties": {
    "addr:full":"7063 Allentown Rd Temple Hills MD 20748",
    "addr:housenumber":"7063",
    "addr:postcode":"20748",
    "addr:street":"Allentown Rd",
    "iso:country":"US",
    "sg:address":"7063 Allentown Rd",
    "sg:city":"Temple Hills",
    "sg:classifiers":[
        {
            "category":"Health Services",
            "subcategory":"Doctor",
            "type":"Services"
        }
    ],
    "sg:phone":"+1 301 449 1088",
    "sg:postcode":"20748",
    "sg:province":"MD",
    "sg:tags":[
        "dentist"
    ],
    "wof:name":"Family Dental Care",
    "wof:placetype":"venue"
},
  "geometry": {"coordinates":[-76.92770899999999,38.793633],"type":"Point"}
}