{
  "type": "Feature",
  "properties": {
    "iso:country":"US",
    "sg:address":"307 E 2nd St",
    "sg:city":"Frederick",
    "sg:classifiers":[
        {
            "category":"Shopping",
            "subcategory":"Used Merchandise",
            "type":"Retail Goods"
        }
    ],
    "sg:phone":"+1 301 698 1791",
    "sg:postcode":"21701",
    "sg:province":"MD",
    "sg:tags":[
        "antique"
    ],
    "sg:website":"www.embassyantiques.com",
    "wof:name":"Embassy Antiques",
    "wof:placetype":"venue"
},
  "geometry": {"coordinates":[-77.40477799999999,39.416282],"type":"Point"}
}