{
  "type": "Feature",
  "properties": {
    "addr:full":"10601 New Georges Creek Rd SW Frostburg MD 21532",
    "addr:housenumber":"10601",
    "addr:postcode":"21532",
    "addr:street":"New Georges Creek Rd Sw",
    "iso:country":"US",
    "sg:address":"10601 New Georges Creek Rd SW",
    "sg:city":"Frostburg",
    "sg:classifiers":[
        {
            "category":"Shopping",
            "subcategory":"Pharmacy",
            "type":"Retail Goods"
        }
    ],
    "sg:phone":"+1 301 689 9961",
    "sg:postcode":"21532",
    "sg:province":"MD",
    "wof:name":"Medicine Shoppe Pharmacy",
    "wof:placetype":"venue"
},
  "geometry": {"coordinates":[-78.91559700000001,39.619698],"type":"Point"}
}