{
  "type": "Feature",
  "properties": {
    "addr:full":"1654 Solomons Island Rd S Prince Frederick MD 20678",
    "addr:housenumber":"1654",
    "addr:postcode":"20678",
    "addr:street":"Solomons Island Rd",
    "iso:country":"US",
    "sg:address":"1654 Solomons Island Rd S",
    "sg:city":"Prince Frederick",
    "sg:classifiers":[
        {
            "category":"Autos & Motor Vehicles",
            "subcategory":"Auto Supplies",
            "type":"Retail Goods"
        }
    ],
    "sg:phone":"+1 410 535 1091",
    "sg:postcode":"20678",
    "sg:province":"MD",
    "sg:tags":[
        "automobile",
        "parts"
    ],
    "wof:name":"Bee's Auto Supply Inc",
    "wof:placetype":"venue"
},
  "geometry": {"coordinates":[-76.570644,38.518657],"type":"Point"}
}