{
  "type": "Feature",
  "properties": {
    "addr:full":"935 S Charles St Baltimore MD 21230",
    "addr:housenumber":"935",
    "addr:postcode":"21230",
    "addr:street":"S Charles St",
    "iso:country":"US",
    "sg:address":"935 S Charles St",
    "sg:city":"Baltimore",
    "sg:classifiers":[
        {
            "category":"Retail",
            "subcategory":"Laundry & Dry Cleaning",
            "type":"Services"
        }
    ],
    "sg:phone":"+1 410 244 1255",
    "sg:postcode":"21230",
    "sg:province":"MD",
    "sg:tags":[
        "commercial"
    ],
    "wof:name":"Youngs Cleaners",
    "wof:placetype":"venue"
},
  "geometry": {"coordinates":[-76.61428100000001,39.278433],"type":"Point"}
}