{
  "type": "Feature",
  "properties": {
    "addr:full":"9708 Monroe St Cockysvl Hnt Vly MD 21030",
    "addr:housenumber":"9708",
    "addr:postcode":"21030",
    "addr:street":"Monroe St;Hnt Vly",
    "iso:country":"US",
    "sg:address":"9708 Monroe St",
    "sg:city":"Cockysvl Hnt Vly",
    "sg:classifiers":[
        {
            "category":"Professional",
            "subcategory":"Business Services",
            "type":"Services"
        }
    ],
    "sg:phone":"+1 410 628 7601",
    "sg:postcode":"21030",
    "sg:province":"MD",
    "sg:tags":[
        "foreground",
        "music"
    ],
    "wof:name":"Audiophile Imports",
    "wof:placetype":"venue"
},
  "geometry": {"coordinates":[-76.632385,39.457099],"type":"Point"}
}