{
  "type": "Feature",
  "properties": {
    "iso:country":"US",
    "sg:address":"1901 Edmondson Ave",
    "sg:city":"Baltimore",
    "sg:classifiers":[
        {
            "category":"Bars & Pubs",
            "type":"Food & Drink"
        }
    ],
    "sg:phone":"+1 410 566 8300",
    "sg:postcode":"21223",
    "sg:province":"MD",
    "wof:name":"Uptown Bar",
    "wof:placetype":"venue"
},
  "geometry": {"coordinates":[-76.648203,39.295134],"type":"Point"}
}