{
  "type": "Feature",
  "properties": {
    "iso:country":"US",
    "sg:address":"4901 Park Heights Ave",
    "sg:city":"Baltimore",
    "sg:classifiers":[
        {
            "category":"Organizations",
            "subcategory":"Religious Organization",
            "type":"Services"
        }
    ],
    "sg:phone":"+1 410 367 9771",
    "sg:postcode":"21215",
    "sg:province":"MD",
    "wof:name":"New Elizabeth Baptist Church",
    "wof:placetype":"venue"
},
  "geometry": {"coordinates":[-76.67289700000001,39.346901],"type":"Point"}
}