{
  "type": "Feature",
  "properties": {
    "iso:country":"US",
    "sg:address":"2900 Largo Rd",
    "sg:city":"Upper Marlboro",
    "sg:classifiers":[
        {
            "category":"Professional",
            "subcategory":"Management & Consulting",
            "type":"Services"
        }
    ],
    "sg:phone":"+1 301 627 1966",
    "sg:postcode":"20772",
    "sg:province":"MD",
    "sg:tags":[
        "business"
    ],
    "wof:name":"Jaysson & Jourdan Ltd",
    "wof:placetype":"venue"
},
  "geometry": {"coordinates":[-76.766047,38.847673],"type":"Point"}
}