{
  "type": "Feature",
  "properties": {
    "addr:full":"3 W Church St Frederick MD 21701",
    "addr:housenumber":"3",
    "addr:postcode":"21701",
    "addr:street":"W Church St",
    "iso:country":"US",
    "sg:address":"3 W Church St",
    "sg:city":"Frederick",
    "sg:classifiers":[
        {
            "category":"Social Services",
            "type":"Services"
        }
    ],
    "sg:phone":"+1 301 682 5025",
    "sg:postcode":"21701",
    "sg:province":"MD",
    "sg:tags":[
        "agency",
        "adoption"
    ],
    "sg:website":"www.fortheloveofachild.org",
    "wof:name":"Frank Adoption Ctr",
    "wof:placetype":"venue"
},
  "geometry": {"coordinates":[-77.41209499999999,39.415503],"type":"Point"}
}