{
  "type": "Feature",
  "properties": {
    "addr:full":"5530 Wisconsin Ave Ste 1235 Chevy Chase MD 20815",
    "addr:housenumber":"5530",
    "addr:postcode":"20815",
    "addr:street":"Wisconsin Ave Ste 1235",
    "iso:country":"US",
    "sg:address":"5530 Wisconsin Ave Ste 1235",
    "sg:city":"Chevy Chase",
    "sg:classifiers":[
        {
            "category":"Professional",
            "subcategory":"Lawyer & Legal Services",
            "type":"Services"
        }
    ],
    "sg:phone":"+1 301 951 0240",
    "sg:postcode":"20815",
    "sg:province":"MD",
    "wof:name":"Stahl Sherri M Lwyr",
    "wof:placetype":"venue"
},
  "geometry": {"coordinates":[-77.087502,38.964298],"type":"Point"}
}