{
  "type": "Feature",
  "properties": {
    "iso:country":"US",
    "sg:address":"16760 Oakmont Ave",
    "sg:city":"Gaithersburg",
    "sg:classifiers":[
        {
            "category":"Utilities",
            "subcategory":"Cable",
            "type":"Services"
        }
    ],
    "sg:phone":"+1 240 632 2828",
    "sg:postcode":"20877",
    "sg:province":"MD",
    "sg:tags":[
        "television"
    ],
    "wof:name":"Silver Bullet Cable Svc",
    "wof:placetype":"venue"
},
  "geometry": {"coordinates":[-77.175323,39.132304],"type":"Point"}
}