{
  "type": "Feature",
  "properties": {
    "iso:country":"US",
    "sg:address":"9407 Boulder Rd",
    "sg:city":"Frederick",
    "sg:classifiers":[
        {
            "category":"Shopping",
            "type":"Retail Goods"
        }
    ],
    "sg:phone":"+1 301 662 7160",
    "sg:postcode":"21702",
    "sg:province":"MD",
    "sg:tags":[
        "merchandise"
    ],
    "wof:name":"Pet Cabinet",
    "wof:placetype":"venue"
},
  "geometry": {"coordinates":[-77.456502,39.492681],"type":"Point"}
}