{
  "type": "Feature",
  "properties": {
    "iso:country":"US",
    "sg:address":"9606 Dundawan Road",
    "sg:city":"Baltimore",
    "sg:classifiers":[
        {
            "category":"Professional",
            "subcategory":"Management & Consulting",
            "type":"Services"
        }
    ],
    "sg:phone":"+1 410 256 0429",
    "sg:postcode":"21236",
    "sg:province":"MD",
    "sg:tags":[
        "graphic-design",
        "web-design",
        "illustration",
        "logo"
    ],
    "sg:website":"http://www.greenleegraphics.com",
    "wof:name":"Greenlee Graphics, LLC",
    "wof:placetype":"venue"
},
  "geometry": {"coordinates":[-76.47046,39.418032],"type":"Point"}
}