{
  "type": "Feature",
  "properties": {
    "addr:full":"4844 Cordell Ave Bethesda MD 20814",
    "addr:housenumber":"4844",
    "addr:postcode":"20814",
    "addr:street":"Cordell Ave",
    "iso:country":"US",
    "sg:address":"4844 Cordell Ave",
    "sg:city":"Bethesda",
    "sg:classifiers":[
        {
            "category":"Bars & Pubs",
            "type":"Food & Drink"
        },
        {
            "category":"Restaurant",
            "type":"Food & Drink"
        }
    ],
    "sg:phone":"+1 301 951 0115",
    "sg:postcode":"20814",
    "sg:province":"MD",
    "sg:tags":[
        "irish"
    ],
    "sg:website":"www.flanagansharpandfiddle.com",
    "wof:name":"Flanagan's Harp and Fiddle",
    "wof:placetype":"venue"
},
  "geometry": {"coordinates":[-77.097448,38.990084],"type":"Point"}
}