{
  "type": "Feature",
  "properties": {
    "addr:full":"3705 Chandler Dr Fort Washington MD 20744",
    "addr:housenumber":"3705",
    "addr:postcode":"20744",
    "addr:street":"Chandler Dr",
    "iso:country":"US",
    "sg:address":"3705 Chandler Dr",
    "sg:city":"Fort Washington",
    "sg:classifiers":[
        {
            "category":"Professional",
            "subcategory":"Management & Consulting",
            "type":"Services"
        }
    ],
    "sg:phone":"+1 301 248 8908",
    "sg:postcode":"20744",
    "sg:province":"MD",
    "sg:tags":[
        "consultant",
        "business"
    ],
    "wof:name":"Beacon Consulting & Marketing",
    "wof:placetype":"venue"
},
  "geometry": {"coordinates":[-76.94313699999999,38.776461],"type":"Point"}
}