{
  "type": "Feature",
  "properties": {
    "addr:full":"6201 Liberty Rd Ste A Gwynn Oak MD 21207",
    "addr:housenumber":"6201",
    "addr:postcode":"21207",
    "addr:street":"Liberty Rd Ste A",
    "iso:country":"US",
    "sg:address":"6201 Liberty Rd Ste A",
    "sg:city":"Gwynn Oak",
    "sg:classifiers":[
        {
            "category":"Professional",
            "subcategory":"Accounting & Tax Preparation",
            "type":"Services"
        }
    ],
    "sg:phone":"+1 410 944 6643",
    "sg:postcode":"21207",
    "sg:province":"MD",
    "sg:tags":[
        "accountant"
    ],
    "wof:name":"Drc & Associates Inc",
    "wof:placetype":"venue"
},
  "geometry": {"coordinates":[-76.714929,39.337721],"type":"Point"}
}