{
  "type": "Feature",
  "properties": {
    "addr:full":"889 Airport Park Rd Glen Burnie MD 21061",
    "addr:housenumber":"889",
    "addr:postcode":"21061",
    "addr:street":"Airport Park Rd",
    "iso:country":"US",
    "sg:address":"889 Airport Park Rd",
    "sg:city":"Glen Burnie",
    "sg:classifiers":[
        {
            "category":"Home & Garden",
            "subcategory":"Home Furnishings",
            "type":"Retail Goods"
        }
    ],
    "sg:phone":"+1 410 590 5701",
    "sg:postcode":"21061",
    "sg:province":"MD",
    "sg:tags":[
        "mirror"
    ],
    "wof:name":"Video Marketing Concepts LLC",
    "wof:placetype":"venue"
},
  "geometry": {"coordinates":[-76.644672,39.172767],"type":"Point"}
}