{
  "type": "Feature",
  "properties": {
    "addr:full":"650 Baltimore Pike Bel Air MD 21014",
    "addr:housenumber":"650",
    "addr:postcode":"21014",
    "addr:street":"Baltimore Pike",
    "iso:country":"US",
    "sg:address":"650 Baltimore Pike",
    "sg:city":"Bel Air",
    "sg:classifiers":[
        {
            "category":"Personal",
            "type":"Services"
        }
    ],
    "sg:phone":"+1 410 893 1005",
    "sg:postcode":"21014",
    "sg:province":"MD",
    "sg:tags":[
        "wear",
        "formal"
    ],
    "wof:name":"After Hours Formalwear",
    "wof:placetype":"venue"
},
  "geometry": {"coordinates":[-76.355762,39.524764],"type":"Point"}
}