{
  "type": "Feature",
  "properties": {
    "addr:full":"615 Eastern Shore Dr Salisbury MD 21804",
    "addr:housenumber":"615",
    "addr:postcode":"21804",
    "addr:street":"Eastern Shore Dr",
    "iso:country":"US",
    "sg:address":"615 Eastern Shore Dr",
    "sg:city":"Salisbury",
    "sg:classifiers":[
        {
            "category":"Professional",
            "subcategory":"Engineering",
            "type":"Services"
        },
        {
            "category":"Real Estate",
            "subcategory":"Surveying",
            "type":"Services"
        }
    ],
    "sg:phone":"+1 410 546 4215",
    "sg:postcode":"21804",
    "sg:province":"MD",
    "sg:tags":[
        "surveyor",
        "consulting",
        "land",
        "engineer"
    ],
    "wof:name":"John H Plummer & Associates",
    "wof:placetype":"venue"
},
  "geometry": {"coordinates":[-75.596327,38.357288],"type":"Point"}
}