{
  "type": "Feature",
  "properties": {
    "addr:full":"2017 Rock Spring Rd Forest Hill MD 21050",
    "addr:housenumber":"2017",
    "addr:postcode":"21050",
    "addr:street":"Rock Spring Rd",
    "iso:country":"US",
    "sg:address":"2017 Rock Spring Rd",
    "sg:city":"Forest Hill",
    "sg:classifiers":[
        {
            "category":"Restaurant",
            "type":"Food & Drink"
        }
    ],
    "sg:phone":"+1 410 893 1799",
    "sg:postcode":"21050",
    "sg:province":"MD",
    "wof:name":"Subway Sandwiches & Salads",
    "wof:placetype":"venue"
},
  "geometry": {"coordinates":[-76.384058,39.572706],"type":"Point"}
}