{
  "type": "Feature",
  "properties": {
    "iso:country":"US",
    "sg:address":"1408 Golf Course Dr",
    "sg:city":"Bowie",
    "sg:classifiers":[
        {
            "category":"Building & Trades",
            "subcategory":"Construction",
            "type":"Services"
        }
    ],
    "sg:phone":"+1 301 672 5883",
    "sg:postcode":"20721",
    "sg:province":"MD",
    "sg:tags":[
        "painter",
        "contractor"
    ],
    "wof:name":"GEG Contractor",
    "wof:placetype":"venue"
},
  "geometry": {"coordinates":[-76.81707400000001,38.909661],"type":"Point"}
}