{
  "type": "Feature",
  "properties": {
    "iso:country":"US",
    "sg:address":"622 Joppa Farm Rd",
    "sg:city":"Joppa",
    "sg:classifiers":[
        {
            "category":"Place Of Worship",
            "subcategory":"Church",
            "type":"Public Place"
        },
        {
            "category":"Social Services",
            "subcategory":"Child Care",
            "type":"Services"
        }
    ],
    "sg:phone":"+1 410 679 3322",
    "sg:postcode":"21085",
    "sg:province":"MD",
    "sg:tags":[
        "day"
    ],
    "sg:website":"www.goodshepherdpc.com/",
    "wof:name":"Good Shepherd Presbyterian Church",
    "wof:placetype":"venue"
},
  "geometry": {"coordinates":[-76.35558399999999,39.412255],"type":"Point"}
}