{
  "type": "Feature",
  "properties": {
    "iso:country":"US",
    "sg:address":"26 N Hickory Ave",
    "sg:city":"Bel Air",
    "sg:classifiers":[
        {
            "category":"Insurance",
            "subcategory":"Insurance Agent",
            "type":"Services"
        }
    ],
    "sg:phone":"+1 410 879 2773",
    "sg:postcode":"21014",
    "sg:province":"MD",
    "sg:website":"www.agkinsurance.com",
    "wof:name":"AGK Insurance Inc",
    "wof:placetype":"venue"
},
  "geometry": {"coordinates":[-76.34845799999999,39.538035],"type":"Point"}
}