{
  "type": "Feature",
  "properties": {
    "addr:full":"17220 Virginia Ave Hagerstown MD 21740",
    "addr:housenumber":"17220",
    "addr:postcode":"21740",
    "addr:street":"Virginia Ave",
    "iso:country":"US",
    "sg:address":"17220 Virginia Ave",
    "sg:city":"Hagerstown",
    "sg:classifiers":[
        {
            "category":"Home & Garden",
            "subcategory":"Home Furnishings",
            "type":"Retail Goods"
        }
    ],
    "sg:phone":"+1 301 582 2323",
    "sg:postcode":"21740",
    "sg:province":"MD",
    "sg:tags":[
        "curtain",
        "made",
        "drapery"
    ],
    "wof:name":"Windmill Shop",
    "wof:placetype":"venue"
},
  "geometry": {"coordinates":[-77.77016399999999,39.616797],"type":"Point"}
}