{
  "type": "Feature",
  "properties": {
    "addr:full":"1018 Carrs Wharf Rd Edgewater MD 21037",
    "addr:housenumber":"1018",
    "addr:postcode":"21037",
    "addr:street":"Carrs Wharf Rd",
    "iso:country":"US",
    "sg:address":"1018 Carrs Wharf Rd",
    "sg:city":"Edgewater",
    "sg:classifiers":[
        {
            "category":"Health Services",
            "subcategory":"Doctor",
            "type":"Services"
        }
    ],
    "sg:phone":"+1 410 353 5948",
    "sg:postcode":"21037",
    "sg:province":"MD",
    "sg:tags":[
        "medical"
    ],
    "wof:name":"American Tlrdiology Nighthawks",
    "wof:placetype":"venue"
},
  "geometry": {"coordinates":[-76.52287699999999,38.888953],"type":"Point"}
}