{
  "type": "Feature",
  "properties": {
    "iso:country":"US",
    "sg:address":"5046 Freter Rd",
    "sg:city":"Sykesville",
    "sg:classifiers":[
        {
            "category":"Retail",
            "subcategory":"Repair Shop",
            "type":"Services"
        }
    ],
    "sg:phone":"+1 410 795 0455",
    "sg:postcode":"21784",
    "sg:province":"MD",
    "wof:name":"Mouser Collectible Antique",
    "wof:placetype":"venue"
},
  "geometry": {"coordinates":[-77.02725100000001,39.43429],"type":"Point"}
}