{
  "type": "Feature",
  "properties": {
    "iso:country":"US",
    "sg:address":"4615 Hollins Ferry Rd Ste F",
    "sg:city":"Halethorpe",
    "sg:phone":"+1 443 701 4515",
    "sg:postcode":"21227",
    "sg:province":"MD",
    "sg:website":"http://baltimore.citysearch.com/profile/external/37290504/baltimore_md/movers_usa.html?publisher=yellowpages&reference_id=1&placement=ypwebsitemip",
    "wof:name":"Movers USA",
    "wof:placetype":"venue"
},
  "geometry": {"coordinates":[-76.67814799999999,39.230787],"type":"Point"}
}