{
  "type": "Feature",
  "properties": {
    "iso:country":"US",
    "sg:address":"825 Dulaney Valley Rd",
    "sg:city":"Baltimore",
    "sg:classifiers":[
        {
            "category":"Shopping",
            "subcategory":"Hobbies, Toys, & Games",
            "type":"Retail Goods"
        }
    ],
    "sg:phone":"+1 410 321 7225",
    "sg:postcode":"21204",
    "sg:province":"MD",
    "wof:name":"Power Gamer",
    "wof:placetype":"venue"
},
  "geometry": {"coordinates":[-76.601542,39.403782],"type":"Point"}
}