{
  "type": "Feature",
  "properties": {
    "addr:full":"48 Water Wheel Dr Port Deposit MD 21904",
    "addr:housenumber":"48",
    "addr:postcode":"21904",
    "addr:street":"Water Wheel Dr",
    "iso:country":"US",
    "sg:address":"48 Water Wheel Dr",
    "sg:city":"Port Deposit",
    "sg:classifiers":[
        {
            "category":"Taxi",
            "type":"Transportation"
        }
    ],
    "sg:phone":"+1 410 378 5589",
    "sg:postcode":"21904",
    "sg:province":"MD",
    "sg:tags":[
        "taxicab"
    ],
    "wof:name":"Highway Haulers Sedan Service",
    "wof:placetype":"venue"
},
  "geometry": {"coordinates":[-76.037885,39.630491],"type":"Point"}
}