{
  "type": "Feature",
  "properties": {
    "addr:full":"1121 S Philadelphia Blvd Aberdeen MD 21001",
    "addr:housenumber":"1121",
    "addr:postcode":"21001",
    "addr:street":"S Philadelphia Blvd",
    "iso:country":"US",
    "sg:address":"1121 S Philadelphia Blvd",
    "sg:city":"Aberdeen",
    "sg:classifiers":[
        {
            "category":"Autos & Motor Vehicles",
            "subcategory":"Automobile Sales",
            "type":"Retail Goods"
        }
    ],
    "sg:phone":"+1 410 273 2445",
    "sg:postcode":"21001",
    "sg:province":"MD",
    "sg:tags":[
        "car",
        "dealer"
    ],
    "wof:name":"R-Cars Inc",
    "wof:placetype":"venue"
},
  "geometry": {"coordinates":[-76.19364400000001,39.489905],"type":"Point"}
}