{
  "type": "Feature",
  "properties": {
    "addr:full":"8201 Bernard Dr Fort Washington MD 20744",
    "addr:housenumber":"8201",
    "addr:postcode":"20744",
    "addr:street":"Bernard Dr",
    "iso:country":"US",
    "sg:address":"8201 Bernard Dr",
    "sg:city":"Fort Washington",
    "sg:classifiers":[
        {
            "category":"Retail",
            "subcategory":"Portrait Studio",
            "type":"Services"
        }
    ],
    "sg:phone":"+1 301 265 9058",
    "sg:postcode":"20744",
    "sg:province":"MD",
    "sg:tags":[
        "photographer"
    ],
    "wof:name":"Roger Holmes Photography",
    "wof:placetype":"venue"
},
  "geometry": {"coordinates":[-76.94380099999999,38.776271],"type":"Point"}
}