{
  "type": "Feature",
  "properties": {
    "addr:full":"221 Duke of Gloucester St Annapolis MD 21401",
    "addr:housenumber":"221",
    "addr:postcode":"21401",
    "addr:street":"Duke Of Gloucester St",
    "iso:country":"US",
    "sg:address":"221 Duke of Gloucester St",
    "sg:city":"Annapolis",
    "sg:classifiers":[
        {
            "category":"Professional",
            "subcategory":"Lawyer & Legal Services",
            "type":"Services"
        }
    ],
    "sg:phone":"+1 410 263 3131",
    "sg:postcode":"21401",
    "sg:province":"MD",
    "sg:tags":[
        "attorney"
    ],
    "wof:name":"Hillman Brown & Darrow",
    "wof:placetype":"venue"
},
  "geometry": {"coordinates":[-76.492175,38.977985],"type":"Point"}
}