{
  "type": "Feature",
  "properties": {
    "addr:full":"11110 Medical Campus Rd Hagerstown MD 21742",
    "addr:housenumber":"11110",
    "addr:postcode":"21742",
    "addr:street":"Medical Campus Rd",
    "iso:country":"US",
    "sg:address":"11110 Medical Campus Rd",
    "sg:city":"Hagerstown",
    "sg:classifiers":[
        {
            "category":"Health Services",
            "subcategory":"Doctor",
            "type":"Services"
        }
    ],
    "sg:phone":"+1 301 714 4100",
    "sg:postcode":"21742",
    "sg:province":"MD",
    "sg:tags":[
        "physician",
        "surgeon"
    ],
    "wof:name":"Womens Health Ctr At Robinwood",
    "wof:placetype":"venue"
},
  "geometry": {"coordinates":[-77.68052,39.622415],"type":"Point"}
}