{
  "type": "Feature",
  "properties": {
    "iso:country":"US",
    "sg:address":"16431 Governor Bridge Rd",
    "sg:city":"Bowie",
    "sg:classifiers":[
        {
            "category":"Restaurant",
            "type":"Food & Drink"
        }
    ],
    "sg:menulink":"http://www.allmenus.com/md/queen-anne/98412-carrabbas/menu/",
    "sg:phone":"+1 301 809 0500",
    "sg:postcode":"20716",
    "sg:province":"MD",
    "sg:tags":[
        "italian"
    ],
    "wof:name":"Carrabba's",
    "wof:placetype":"venue"
},
  "geometry": {"coordinates":[-76.71653499999999,38.951209],"type":"Point"}
}