{
  "type": "Feature",
  "properties": {
    "iso:country":"US",
    "sg:address":"3200 Patuxent River Rd",
    "sg:city":"Davidsonville",
    "sg:classifiers":[
        {
            "category":"Home & Garden",
            "subcategory":"Building Materials",
            "type":"Retail Goods"
        },
        {
            "category":"Building & Trades",
            "subcategory":"Construction",
            "type":"Services"
        }
    ],
    "sg:phone":"+1 410 974 1105",
    "sg:postcode":"21035",
    "sg:province":"MD",
    "sg:tags":[
        "steel",
        "detailers",
        "reinforcement",
        "concrete",
        "shape",
        "block",
        "structural"
    ],
    "sg:website":"http://www.contractorsprecast.com",
    "wof:name":"Contractors Precast Corp.",
    "wof:placetype":"venue"
},
  "geometry": {"coordinates":[-76.673233,38.933529],"type":"Point"}
}