{
  "type": "Feature",
  "properties": {
    "iso:country":"US",
    "sg:address":"1909 Arcadia Ave",
    "sg:city":"Capitol Heights",
    "sg:classifiers":[
        {
            "category":"Social Services",
            "subcategory":"Child Care",
            "type":"Services"
        }
    ],
    "sg:phone":"+1 301 735 5654",
    "sg:postcode":"20743",
    "sg:province":"MD",
    "sg:tags":[
        "day"
    ],
    "wof:name":"God's Little People",
    "wof:placetype":"venue"
},
  "geometry": {"coordinates":[-76.94065500000001,38.864497],"type":"Point"}
}