{
  "type": "Feature",
  "properties": {
    "addr:full":"8220 Patuxent Range Rd A Jessup MD 20794",
    "addr:housenumber":"8220",
    "addr:postcode":"20794",
    "addr:street":"Patuxent Range Rd A",
    "iso:country":"US",
    "sg:address":"8220 Patuxent Range Rd A",
    "sg:city":"Jessup",
    "sg:classifiers":[
        {
            "category":"Health Services",
            "subcategory":"Doctor",
            "type":"Services"
        }
    ],
    "sg:phone":"+1 301 575 2390",
    "sg:postcode":"20794",
    "sg:province":"MD",
    "sg:tags":[
        "physician",
        "surgeon"
    ],
    "wof:name":"Doe & Ingalls Of Maryland Operating",
    "wof:placetype":"venue"
},
  "geometry": {"coordinates":[-76.789743,39.145032],"type":"Point"}
}