{
  "type": "Feature",
  "properties": {
    "iso:country":"US",
    "sg:address":"7548 Main St",
    "sg:city":"Sykesville",
    "sg:classifiers":[
        {
            "category":"Banks & Credit Unions",
            "subcategory":"Bank",
            "type":"Services"
        }
    ],
    "sg:phone":"+1 410 461 6200",
    "sg:postcode":"21784",
    "sg:province":"MD",
    "sg:tags":[
        "loan",
        "real estate"
    ],
    "sg:website":"www.americanidealmortgage.com",
    "wof:name":"American Ideal Mortgage",
    "wof:placetype":"venue"
},
  "geometry": {"coordinates":[-76.969432,39.366084],"type":"Point"}
}