{
  "type": "Feature",
  "properties": {
    "addr:full":"1622 Eastern Ave Baltimore MD 21231",
    "addr:housenumber":"1622",
    "addr:postcode":"21231",
    "addr:street":"Eastern Ave",
    "iso:country":"US",
    "sg:address":"1622 Eastern Ave",
    "sg:city":"Baltimore",
    "sg:classifiers":[
        {
            "category":"Restaurant",
            "type":"Food & Drink"
        }
    ],
    "sg:phone":"+1 410 537 5024",
    "sg:postcode":"21231",
    "sg:province":"MD",
    "sg:tags":[
        "mexican"
    ],
    "wof:name":"Las Palmas Mexican Restaurant",
    "wof:placetype":"venue"
},
  "geometry": {"coordinates":[-76.59446699999999,39.285561],"type":"Point"}
}