{
  "type": "Feature",
  "properties": {
    "iso:country":"US",
    "sg:address":"10240 York Rd",
    "sg:city":"Cockeysville",
    "sg:classifiers":[
        {
            "category":"Retail",
            "subcategory":"Auto Rental",
            "type":"Services"
        }
    ],
    "sg:phone":"+1 410 667 3571",
    "sg:postcode":"21030",
    "sg:province":"MD",
    "sg:tags":[
        "car"
    ],
    "sg:website":"www.enterprise.com",
    "wof:name":"Enterprise Rent-A-Car",
    "wof:placetype":"venue"
},
  "geometry": {"coordinates":[-76.639073,39.469846],"type":"Point"}
}