{
  "type": "Feature",
  "properties": {
    "iso:country":"US",
    "sg:address":"21 West Rd Ste 200",
    "sg:city":"Towson",
    "sg:classifiers":[
        {
            "category":"Organizations",
            "subcategory":"Labor Organization",
            "type":"Services"
        }
    ],
    "sg:phone":"+1 410 337 2700",
    "sg:postcode":"21204",
    "sg:province":"MD",
    "sg:website":"http://www.ufcw27.org",
    "wof:name":"Ufcw Local 27",
    "wof:placetype":"venue"
},
  "geometry": {"coordinates":[-76.613592,39.41169],"type":"Point"}
}