{
  "type": "Feature",
  "properties": {
    "addr:full":"205 Main St Preston MD 21655",
    "addr:housenumber":"205",
    "addr:postcode":"21655",
    "addr:street":"Main St",
    "iso:country":"US",
    "sg:address":"205 Main St",
    "sg:city":"Preston",
    "sg:classifiers":[
        {
            "category":"Professional",
            "subcategory":"Lawyer & Legal Services",
            "type":"Services"
        }
    ],
    "sg:phone":"+1 410 820 9724",
    "sg:postcode":"21655",
    "sg:province":"MD",
    "sg:tags":[
        "attorney"
    ],
    "wof:name":"Holmes Schwartz & Gordon",
    "wof:placetype":"venue"
},
  "geometry": {"coordinates":[-75.90813300000001,38.71212],"type":"Point"}
}