{
  "type": "Feature",
  "properties": {
    "iso:country":"US",
    "sg:address":"205 Pewter Ln",
    "sg:city":"Silver Spring",
    "sg:classifiers":[
        {
            "category":"Building & Trades",
            "subcategory":"Electrical",
            "type":"Services"
        }
    ],
    "sg:phone":"+1 301 384 8321",
    "sg:postcode":"20905",
    "sg:province":"MD",
    "sg:tags":[
        "electric",
        "contractor"
    ],
    "wof:name":"Ultimate Electric",
    "wof:placetype":"venue"
},
  "geometry": {"coordinates":[-77.0142,39.103371],"type":"Point"}
}