{
  "type": "Feature",
  "properties": {
    "addr:full":"12500 Kavanaugh Ln Bowie MD 20715",
    "addr:housenumber":"12500",
    "addr:postcode":"20715",
    "addr:street":"Kavanaugh Ln",
    "iso:country":"US",
    "sg:address":"12500 Kavanaugh Ln",
    "sg:city":"Bowie",
    "sg:classifiers":[
        {
            "category":"Professional",
            "subcategory":"Management & Consulting",
            "type":"Services"
        }
    ],
    "sg:phone":"+1 301 464 8112",
    "sg:postcode":"20715",
    "sg:province":"MD",
    "sg:tags":[
        "consultant",
        "elevator"
    ],
    "wof:name":"Robert L Seymour Assoc",
    "wof:placetype":"venue"
},
  "geometry": {"coordinates":[-76.73768699999999,38.956766],"type":"Point"}
}