{
  "type": "Feature",
  "properties": {
    "iso:country":"US",
    "sg:address":"8 Greene St",
    "sg:city":"Cumberland",
    "sg:classifiers":[
        {
            "category":"Professional",
            "subcategory":"Lawyer & Legal Services",
            "type":"Services"
        }
    ],
    "sg:phone":"+1 301 724 2061",
    "sg:postcode":"21502",
    "sg:province":"MD",
    "sg:tags":[
        "attorney"
    ],
    "wof:name":"Glenn J Robinette Law Office",
    "wof:placetype":"venue"
},
  "geometry": {"coordinates":[-78.76451900000001,39.650473],"type":"Point"}
}