{
  "type": "Feature",
  "properties": {
    "addr:full":"303 Winchester Creek Rd Grasonville MD 21638",
    "addr:housenumber":"303",
    "addr:postcode":"21638",
    "addr:street":"Winchester Creek Rd",
    "iso:country":"US",
    "sg:address":"303 Winchester Creek Rd",
    "sg:city":"Grasonville",
    "sg:classifiers":[
        {
            "category":"Shopping",
            "subcategory":"Bicycles & Sporting Goods",
            "type":"Retail Goods"
        }
    ],
    "sg:phone":"+1 410 827 7000",
    "sg:postcode":"21638",
    "sg:province":"MD",
    "sg:tags":[
        "tackle",
        "fishing"
    ],
    "sg:website":"www.winchestercreekoutfitters.com",
    "wof:name":"Winchester Creek Outfitters",
    "wof:placetype":"venue"
},
  "geometry": {"coordinates":[-76.200185,38.963048],"type":"Point"}
}