{
  "type": "Feature",
  "properties": {
    "addr:full":"2207 Bluebird Dr Westminster MD 21157",
    "addr:housenumber":"2207",
    "addr:postcode":"21157",
    "addr:street":"Bluebird Dr",
    "iso:country":"US",
    "sg:address":"2207 Bluebird Dr",
    "sg:city":"Westminster",
    "sg:classifiers":[
        {
            "category":"Building & Trades",
            "subcategory":"Electrical",
            "type":"Services"
        }
    ],
    "sg:phone":"+1 410 259 5394",
    "sg:postcode":"21157",
    "sg:province":"MD",
    "sg:tags":[
        "electrician"
    ],
    "wof:name":"Dave Bagrosky Electric",
    "wof:placetype":"venue"
},
  "geometry": {"coordinates":[-77.07824599999999,39.488805],"type":"Point"}
}