{
  "type": "Feature",
  "properties": {
    "addr:full":"14205 Castlemoor Ct Burtonsville MD 20866",
    "addr:housenumber":"14205",
    "addr:postcode":"20866",
    "addr:street":"Castlemoor Ct",
    "iso:country":"US",
    "sg:address":"14205 Castlemoor Ct",
    "sg:city":"Burtonsville",
    "sg:classifiers":[
        {
            "category":"Retail",
            "subcategory":"Laundry & Dry Cleaning",
            "type":"Services"
        }
    ],
    "sg:phone":"+1 240 423 8007",
    "sg:postcode":"20866",
    "sg:province":"MD",
    "sg:tags":[
        "cleaners",
        "rug",
        "carpet"
    ],
    "wof:name":"K G Carpet Cleaning",
    "wof:placetype":"venue"
},
  "geometry": {"coordinates":[-76.941166,39.089514],"type":"Point"}
}