{
  "type": "Feature",
  "properties": {
    "addr:full":"37837 Grand Ln Chaptico MD 20621",
    "addr:housenumber":"37837",
    "addr:postcode":"20621",
    "addr:street":"Grand Ln",
    "iso:country":"US",
    "sg:address":"37837 Grand Ln",
    "sg:city":"Chaptico",
    "sg:classifiers":[
        {
            "category":"Arena",
            "subcategory":"Auto Racetrack",
            "type":"Entertainment"
        },
        {
            "category":"Recreation",
            "subcategory":"Picnic Area",
            "type":"Entertainment"
        },
        {
            "category":"Sports & Exercise",
            "subcategory":"Race Track",
            "type":"Entertainment"
        }
    ],
    "sg:phone":"+1 301 884 4624",
    "sg:postcode":"20621",
    "sg:province":"MD",
    "sg:tags":[
        "arcade",
        "automobile",
        "place",
        "car",
        "racing",
        "amusement"
    ],
    "sg:website":"http://www.potomacspeedway.com/",
    "wof:name":"Potomac Speedway",
    "wof:placetype":"venue"
},
  "geometry": {"coordinates":[-76.768699,38.325505],"type":"Point"}
}