{
  "type": "Feature",
  "properties": {
    "iso:country":"US",
    "sg:address":"2225E Defense Hwy",
    "sg:city":"Crofton",
    "sg:classifiers":[
        {
            "category":"Health Services",
            "subcategory":"Doctor",
            "type":"Services"
        }
    ],
    "sg:phone":"+1 410 721 2273",
    "sg:postcode":"21114",
    "sg:province":"MD",
    "sg:tags":[
        "physician",
        "family",
        "practice",
        "surgeons",
        "medicine"
    ],
    "wof:name":"Kevin L Clark Md",
    "wof:placetype":"venue"
},
  "geometry": {"coordinates":[-76.701235,38.991807],"type":"Point"}
}