{
  "type": "Feature",
  "properties": {
    "addr:full":"5936 Belair Rd Baltimore MD 21206",
    "addr:housenumber":"5936",
    "addr:postcode":"21206",
    "addr:street":"Belair Rd",
    "iso:country":"US",
    "sg:address":"5936 Belair Rd",
    "sg:city":"Baltimore",
    "sg:classifiers":[
        {
            "category":"Retail",
            "subcategory":"Car Wash",
            "type":"Services"
        }
    ],
    "sg:phone":"+1 443 759 5919",
    "sg:postcode":"21206",
    "sg:province":"MD",
    "wof:name":"Crystal Clear Car Wash",
    "wof:placetype":"venue"
},
  "geometry": {"coordinates":[-76.540452,39.346252],"type":"Point"}
}