{
  "type": "Feature",
  "properties": {
    "addr:full":"1011 Mount Holly Dr Annapolis MD 21409",
    "addr:housenumber":"1011",
    "addr:postcode":"21409",
    "addr:street":"Mount Holly Dr",
    "iso:country":"US",
    "sg:address":"1011 Mount Holly Dr",
    "sg:city":"Annapolis",
    "sg:classifiers":[
        {
            "category":"Transit Center",
            "subcategory":"Freight",
            "type":"Transportation"
        }
    ],
    "sg:phone":"+1 443 957 1988",
    "sg:postcode":"21409",
    "sg:province":"MD",
    "sg:tags":[
        "container",
        "broker"
    ],
    "sg:website":"http://www.katoalogistics.com",
    "wof:name":"Katoa Logistics",
    "wof:placetype":"venue"
},
  "geometry": {"coordinates":[-76.443622,39.042466],"type":"Point"}
}