{
  "type": "Feature",
  "properties": {
    "iso:country":"US",
    "sg:address":"920 Providence Rd",
    "sg:city":"Towson",
    "sg:classifiers":[
        {
            "category":"Insurance",
            "subcategory":"Insurance Agent",
            "type":"Services"
        },
        {
            "category":"Insurance",
            "subcategory":"Hazard Insurance",
            "type":"Services"
        },
        {
            "category":"Insurance",
            "subcategory":"Title Insurance",
            "type":"Services"
        },
        {
            "category":"Insurance",
            "subcategory":"Life Insurance",
            "type":"Services"
        }
    ],
    "sg:phone":"+1 410 337 0015",
    "sg:postcode":"21286",
    "sg:province":"MD",
    "sg:tags":[
        "business",
        "auto",
        "commercial",
        "homeowner",
        "motorcycle",
        "renter"
    ],
    "wof:name":"Allstate Insurance Company - Edward Zink",
    "wof:placetype":"venue"
},
  "geometry": {"coordinates":[-76.581316,39.405922],"type":"Point"}
}