{
  "type": "Feature",
  "properties": {
    "addr:full":"3120 Belair Dr Bowie MD 20715",
    "addr:housenumber":"3120",
    "addr:postcode":"20715",
    "addr:street":"Belair Dr",
    "iso:country":"US",
    "sg:address":"3120 Belair Dr",
    "sg:city":"Bowie",
    "sg:classifiers":[
        {
            "category":"Social Services",
            "subcategory":"Child Care",
            "type":"Services"
        }
    ],
    "sg:phone":"+1 301 464 5782",
    "sg:postcode":"20715",
    "sg:province":"MD",
    "sg:tags":[
        "kindergarten",
        "academic",
        "school"
    ],
    "wof:name":"Belair Cooperative Nursery",
    "wof:placetype":"venue"
},
  "geometry": {"coordinates":[-76.74152100000001,38.975509],"type":"Point"}
}