{
  "type": "Feature",
  "properties": {
    "iso:country":"US",
    "sg:address":"20235 Jefferson Blvd",
    "sg:city":"Hagerstown",
    "sg:classifiers":[
        {
            "category":"Building & Trades",
            "subcategory":"Electrical",
            "type":"Services"
        }
    ],
    "sg:phone":"+1 301 733 6880",
    "sg:postcode":"21742",
    "sg:province":"MD",
    "sg:tags":[
        "electric",
        "contractor"
    ],
    "wof:name":"Warrior Electric & Control",
    "wof:placetype":"venue"
},
  "geometry": {"coordinates":[-77.667397,39.642506],"type":"Point"}
}