{
  "type": "Feature",
  "properties": {
    "addr:full":"18715 Hodges Ln Leonardtown MD 20650",
    "addr:housenumber":"18715",
    "addr:postcode":"20650",
    "addr:street":"Hodges Ln",
    "iso:country":"US",
    "sg:address":"18715 Hodges Ln",
    "sg:city":"Leonardtown",
    "sg:classifiers":[
        {
            "category":"Wholesale",
            "subcategory":"Construction Materials",
            "type":"Manufacturing & Wholesale Goods"
        }
    ],
    "sg:phone":"+1 301 994 2415",
    "sg:postcode":"20650",
    "sg:province":"MD",
    "sg:tags":[
        "sand",
        "gravel"
    ],
    "wof:name":"Hodges Trucking",
    "wof:placetype":"venue"
},
  "geometry": {"coordinates":[-76.540226,38.186026],"type":"Point"}
}