{
  "type": "Feature",
  "properties": {
    "addr:full":"7273 Cooper Dr Sykesville MD 21784",
    "addr:housenumber":"7273",
    "addr:postcode":"21784",
    "addr:street":"Cooper Dr",
    "iso:country":"US",
    "sg:address":"7273 Cooper Dr",
    "sg:city":"Sykesville",
    "sg:classifiers":[
        {
            "category":"Social Services",
            "subcategory":"Adult Care",
            "type":"Services"
        }
    ],
    "sg:phone":"+1 410 795 7361",
    "sg:postcode":"21784",
    "sg:province":"MD",
    "sg:tags":[
        "home"
    ],
    "wof:name":"Sykesville Group Shelter Home",
    "wof:placetype":"venue"
},
  "geometry": {"coordinates":[-76.965509,39.375371],"type":"Point"}
}