{
  "type": "Feature",
  "properties": {
    "iso:country":"US",
    "sg:address":"5900 Princess Garden Pkwy",
    "sg:city":"Lanham",
    "sg:classifiers":[
        {
            "category":"Real Estate",
            "subcategory":"Real Estate Services",
            "type":"Services"
        }
    ],
    "sg:phone":"+1 301 577 3956",
    "sg:postcode":"20706",
    "sg:province":"MD",
    "sg:tags":[
        "management",
        "property"
    ],
    "wof:name":"The Mark Winkler Company",
    "wof:placetype":"venue"
},
  "geometry": {"coordinates":[-76.862999,38.961399],"type":"Point"}
}