{
  "type": "Feature",
  "properties": {
    "iso:country":"US",
    "sg:address":"30 W Ridgely Rd",
    "sg:city":"Lutherville",
    "sg:classifiers":[
        {
            "category":"Shopping",
            "subcategory":"Hobbies, Toys, & Games",
            "type":"Retail Goods"
        }
    ],
    "sg:phone":"+1 443 279 0790",
    "sg:postcode":"21093",
    "sg:province":"MD",
    "sg:tags":[
        "craft",
        "supply"
    ],
    "wof:name":"Michaels Arts & Crafts Store",
    "wof:placetype":"venue"
},
  "geometry": {"coordinates":[-76.621769,39.43012],"type":"Point"}
}