{
  "type": "Feature",
  "properties": {
    "iso:country":"US",
    "sg:address":"211 S Jefferson St",
    "sg:city":"Frederick",
    "sg:classifiers":[
        {
            "category":"Banks & Credit Unions",
            "subcategory":"Bank",
            "type":"Services"
        }
    ],
    "sg:phone":"+1 301 620 1100",
    "sg:postcode":"21701",
    "sg:province":"MD",
    "sg:tags":[
        "loan",
        "real estate"
    ],
    "wof:name":"Founders Mortgage Co Inc",
    "wof:placetype":"venue"
},
  "geometry": {"coordinates":[-77.424366,39.41013],"type":"Point"}
}