{
  "type": "Feature",
  "properties": {
    "iso:country":"US",
    "sg:address":"13017 Chestnut Oak Dr",
    "sg:city":"Gaithersburg",
    "sg:classifiers":[
        {
            "category":"Professional",
            "subcategory":"Management & Consulting",
            "type":"Services"
        }
    ],
    "sg:phone":"+1 301 926 2837",
    "sg:postcode":"20878",
    "sg:province":"MD",
    "sg:tags":[
        "business"
    ],
    "wof:name":"McCom Comm & Consulting",
    "wof:placetype":"venue"
},
  "geometry": {"coordinates":[-77.274314,39.108118],"type":"Point"}
}