{
  "type": "Feature",
  "properties": {
    "iso:country":"US",
    "sg:address":"5340 Baltimore Ave",
    "sg:city":"Hyattsville",
    "sg:classifiers":[
        {
            "category":"Social Services",
            "subcategory":"Child Care",
            "type":"Services"
        }
    ],
    "sg:phone":"+1 301 699 0668",
    "sg:postcode":"20781",
    "sg:province":"MD",
    "wof:name":"Little Folks Early Learning",
    "wof:placetype":"venue"
},
  "geometry": {"coordinates":[-76.94041199999999,38.955068],"type":"Point"}
}