{
  "type": "Feature",
  "properties": {
    "addr:full":"22420 Frederick Rd Clarksburg MD 20871",
    "addr:housenumber":"22420",
    "addr:postcode":"20871",
    "addr:street":"Frederick Rd",
    "iso:country":"US",
    "sg:address":"22420 Frederick Rd",
    "sg:city":"Clarksburg",
    "sg:classifiers":[
        {
            "category":"Organizations",
            "subcategory":"Religious Organization",
            "type":"Services"
        }
    ],
    "sg:phone":"+1 301 972 5520",
    "sg:postcode":"20871",
    "sg:province":"MD",
    "wof:name":"John Wesley United Methodist",
    "wof:placetype":"venue"
},
  "geometry": {"coordinates":[-77.262079,39.224561],"type":"Point"}
}