{
  "type": "Feature",
  "properties": {
    "addr:full":"1509 Reisterstown Rd Pikesville MD 21208",
    "addr:housenumber":"1509",
    "addr:postcode":"21208",
    "addr:street":"Reisterstown Rd",
    "iso:country":"US",
    "sg:address":"1509 Reisterstown Rd",
    "sg:city":"Pikesville",
    "sg:classifiers":[
        {
            "category":"Autos & Motor Vehicles",
            "subcategory":"Fuel & Gas Station",
            "type":"Retail Goods"
        }
    ],
    "sg:phone":"+1 410 484 7816",
    "sg:postcode":"21208",
    "sg:province":"MD",
    "sg:tags":[
        "oil"
    ],
    "wof:name":"Pikesville Crown",
    "wof:placetype":"venue"
},
  "geometry": {"coordinates":[-76.72629499999999,39.37797],"type":"Point"}
}