{
  "type": "Feature",
  "properties": {
    "addr:full":"299 Frederick Rd Catonsville MD 21228",
    "addr:housenumber":"299",
    "addr:postcode":"21228",
    "addr:street":"Frederick Rd",
    "iso:country":"US",
    "sg:address":"299 Frederick Rd",
    "sg:city":"Catonsville",
    "sg:classifiers":[
        {
            "category":"Retail",
            "subcategory":"Funeral Services",
            "type":"Services"
        }
    ],
    "sg:phone":"+1 410 455 0100",
    "sg:postcode":"21228",
    "sg:province":"MD",
    "sg:tags":[
        "crematory"
    ],
    "wof:name":"Metro Crematory",
    "wof:placetype":"venue"
},
  "geometry": {"coordinates":[-76.725285,39.273396],"type":"Point"}
}