{
  "type": "Feature",
  "properties": {
    "addr:full":"12509 Mcmullen Hwy SW Cumberland MD 21502",
    "addr:housenumber":"12509",
    "addr:postcode":"21502",
    "addr:street":"Mcmullen Hwy Sw",
    "iso:country":"US",
    "sg:address":"12509 Mcmullen Hwy SW",
    "sg:city":"Cumberland",
    "sg:classifiers":[
        {
            "category":"Personal",
            "subcategory":"Beauty Salon",
            "type":"Services"
        }
    ],
    "sg:phone":"+1 301 729 2010",
    "sg:postcode":"21502",
    "sg:province":"MD",
    "wof:name":"Elite Design",
    "wof:placetype":"venue"
},
  "geometry": {"coordinates":[-78.805611,39.624048],"type":"Point"}
}