{
  "type": "Feature",
  "properties": {
    "iso:country":"US",
    "sg:address":"315 Howard Ave",
    "sg:city":"Rockville",
    "sg:classifiers":[
        {
            "category":"Manufacturing",
            "subcategory":"Tools & Machinery",
            "type":"Manufacturing & Wholesale Goods"
        }
    ],
    "sg:phone":"+1 301 251 9650",
    "sg:postcode":"20850",
    "sg:province":"MD",
    "sg:tags":[
        "machine",
        "shop"
    ],
    "wof:name":"Precision Engineering Co",
    "wof:placetype":"venue"
},
  "geometry": {"coordinates":[-77.144053,39.090677],"type":"Point"}
}