{
  "type": "Feature",
  "properties": {
    "addr:full":"7915 Old Branch Ave Clinton MD 20735",
    "addr:housenumber":"7915",
    "addr:postcode":"20735",
    "addr:street":"Old Branch Ave",
    "iso:country":"US",
    "sg:address":"7915 Old Branch Ave",
    "sg:city":"Clinton",
    "sg:classifiers":[
        {
            "category":"Professional",
            "subcategory":"Accounting & Tax Preparation",
            "type":"Services"
        }
    ],
    "sg:phone":"+1 301 868 3636",
    "sg:postcode":"20735",
    "sg:province":"MD",
    "sg:tags":[
        "accountant"
    ],
    "wof:name":"Denton Associates",
    "wof:placetype":"venue"
},
  "geometry": {"coordinates":[-76.89883399999999,38.782205],"type":"Point"}
}