{
  "type": "Feature",
  "properties": {
    "addr:full":"3703 Mountain Rd Pasadena MD 21122",
    "addr:housenumber":"3703",
    "addr:postcode":"21122",
    "addr:street":"Mountain Rd",
    "iso:country":"US",
    "sg:address":"3703 Mountain Rd",
    "sg:city":"Pasadena",
    "sg:classifiers":[
        {
            "category":"Shopping",
            "subcategory":"Used Merchandise",
            "type":"Retail Goods"
        }
    ],
    "sg:phone":"+1 410 437 3666",
    "sg:postcode":"21122",
    "sg:province":"MD",
    "sg:tags":[
        "second",
        "store",
        "hand"
    ],
    "wof:name":"Niftee Thriftee Shoppe",
    "wof:placetype":"venue"
},
  "geometry": {"coordinates":[-76.524824,39.123588],"type":"Point"}
}