{
  "type": "Feature",
  "properties": {
    "addr:full":"15 S 3rd St Oakland MD 21550",
    "addr:housenumber":"15",
    "addr:postcode":"21550",
    "addr:street":"S 3Rd St",
    "iso:country":"US",
    "sg:address":"15 S 3rd St",
    "sg:city":"Oakland",
    "sg:classifiers":[
        {
            "category":"Government",
            "subcategory":"Office",
            "type":"Public Place"
        }
    ],
    "sg:phone":"+1 301 334 2691",
    "sg:postcode":"21550",
    "sg:province":"MD",
    "sg:tags":[
        "city"
    ],
    "sg:website":"www.oaklandmd.com",
    "wof:name":"Oakland City Hall",
    "wof:placetype":"venue"
},
  "geometry": {"coordinates":[-79.405874,39.410146],"type":"Point"}
}