{
  "type": "Feature",
  "properties": {
    "addr:full":"204 E West St Fl 2 Baltimore MD 21230",
    "addr:housenumber":"204 e;2",
    "addr:postcode":"21230",
    "addr:street":"West St",
    "iso:country":"US",
    "sg:address":"204 E West St Fl 2",
    "sg:city":"Baltimore",
    "sg:classifiers":[
        {
            "category":"Restaurant",
            "type":"Food & Drink"
        }
    ],
    "sg:phone":"+1 410 244 7250",
    "sg:postcode":"21230",
    "sg:province":"MD",
    "sg:tags":[
        "italian"
    ],
    "wof:name":"Hot Mama",
    "wof:placetype":"venue"
},
  "geometry": {"coordinates":[-76.610365,39.276186],"type":"Point"}
}