{
  "type": "Feature",
  "properties": {
    "addr:full":"1335 Holton Ln Takoma Park MD 20912",
    "addr:housenumber":"1335",
    "addr:postcode":"20912",
    "addr:street":"Holton Ln",
    "iso:country":"US",
    "sg:address":"1335 Holton Ln",
    "sg:city":"Takoma Park",
    "sg:classifiers":[
        {
            "category":"Personal",
            "subcategory":"Shoe Repair & Shine",
            "type":"Services"
        }
    ],
    "sg:phone":"+1 301 439 6867",
    "sg:postcode":"20912",
    "sg:province":"MD",
    "sg:tags":[
        "repairing",
        "boot"
    ],
    "wof:name":"Joe's Shoe Repair",
    "wof:placetype":"venue"
},
  "geometry": {"coordinates":[-76.985854,38.985638],"type":"Point"}
}