{
  "type": "Feature",
  "properties": {
    "addr:full":"1 Mace Ave Essex MD 21221",
    "addr:housenumber":"1",
    "addr:postcode":"21221",
    "addr:street":"Mace Ave",
    "iso:country":"US",
    "sg:address":"1 Mace Ave",
    "sg:city":"Essex",
    "sg:classifiers":[
        {
            "category":"Shopping",
            "subcategory":"Books",
            "type":"Retail Goods"
        }
    ],
    "sg:phone":"+1 410 574 1496",
    "sg:postcode":"21221",
    "sg:province":"MD",
    "sg:tags":[
        "comic"
    ],
    "sg:website":"www.chuckscomics.com",
    "wof:name":"Chuck's Comics",
    "wof:placetype":"venue"
},
  "geometry": {"coordinates":[-76.47932299999999,39.307348],"type":"Point"}
}