{
  "type": "Feature",
  "properties": {
    "iso:country":"US",
    "sg:address":"1030 W 41st St",
    "sg:city":"Baltimore",
    "sg:classifiers":[
        {
            "category":"Shopping",
            "subcategory":"Shoes",
            "type":"Retail Goods"
        }
    ],
    "sg:phone":"+1 410 366 3718",
    "sg:postcode":"21211",
    "sg:province":"MD",
    "sg:tags":[
        "store"
    ],
    "sg:website":"www.payless.com",
    "wof:name":"Payless Shoesource",
    "wof:placetype":"venue"
},
  "geometry": {"coordinates":[-76.6353,39.337799],"type":"Point"}
}