{
  "type": "Feature",
  "properties": {
    "iso:country":"US",
    "sg:address":"2700 Sisson St",
    "sg:city":"Baltimore",
    "sg:classifiers":[
        {
            "category":"Wholesale",
            "subcategory":"Non-durable Goods",
            "type":"Manufacturing & Wholesale Goods"
        }
    ],
    "sg:phone":"+1 410 889 3000",
    "sg:postcode":"21211",
    "sg:province":"MD",
    "sg:tags":[
        "souvenir"
    ],
    "wof:name":"Traub Co",
    "wof:placetype":"venue"
},
  "geometry": {"coordinates":[-76.625224,39.319185],"type":"Point"}
}