{
  "type": "Feature",
  "properties": {
    "iso:country":"US",
    "sg:address":"300 E Lombard St",
    "sg:city":"Baltimore",
    "sg:classifiers":[
        {
            "category":"Shopping",
            "subcategory":"Florist",
            "type":"Retail Goods"
        }
    ],
    "sg:phone":"+1 410 347 0960",
    "sg:postcode":"21202",
    "sg:province":"MD",
    "wof:name":"Enchanted Petals Florist",
    "wof:placetype":"venue"
},
  "geometry": {"coordinates":[-76.61011499999999,39.287849],"type":"Point"}
}