{
  "type": "Feature",
  "properties": {
    "addr:full":"13200 Coastal Hwy Ocean City MD 21842",
    "addr:housenumber":"13200",
    "addr:postcode":"21842",
    "addr:street":"Coastal Hwy",
    "iso:country":"US",
    "sg:address":"13200 Coastal Hwy",
    "sg:city":"Ocean City",
    "sg:classifiers":[
        {
            "category":"Real Estate",
            "subcategory":"Real Estate Agent",
            "type":"Services"
        }
    ],
    "sg:phone":"+1 410 250 3668",
    "sg:postcode":"21842",
    "sg:province":"MD",
    "wof:name":"Excalibr Condo",
    "wof:placetype":"venue"
},
  "geometry": {"coordinates":[-75.053878,38.437422],"type":"Point"}
}