{
  "type": "Feature",
  "properties": {
    "iso:country":"US",
    "sg:address":"919 University Blvd W",
    "sg:city":"Silver Spring",
    "sg:classifiers":[
        {
            "category":"Education",
            "subcategory":"School",
            "type":"Public Place"
        }
    ],
    "sg:phone":"+1 301 279 8500",
    "sg:postcode":"20901",
    "sg:province":"MD",
    "sg:tags":[
        "high",
        "middle"
    ],
    "sg:website":"www.montgomeryschoolsmd.org/",
    "wof:name":"Montgomery County School District",
    "wof:placetype":"venue"
},
  "geometry": {"coordinates":[-77.023903,39.034],"type":"Point"}
}