{
  "type": "Feature",
  "properties": {
    "iso:country":"US",
    "sg:address":"165 N Potomac St",
    "sg:city":"Baltimore",
    "sg:classifiers":[
        {
            "category":"Shopping",
            "subcategory":"Jewelry",
            "type":"Retail Goods"
        }
    ],
    "sg:phone":"+1 410 327 8850",
    "sg:postcode":"21224",
    "sg:province":"MD",
    "wof:name":"Heng Da",
    "wof:placetype":"venue"
},
  "geometry": {"coordinates":[-76.574725,39.294223],"type":"Point"}
}