{
  "type": "Feature",
  "properties": {
    "addr:full":"14711 Mount Calvert Rd Upper Marlboro MD 20772",
    "addr:housenumber":"14711",
    "addr:postcode":"20772",
    "addr:street":"Mount Calvert Rd",
    "iso:country":"US",
    "sg:address":"14711 Mount Calvert Rd",
    "sg:city":"Upper Marlboro",
    "sg:classifiers":[
        {
            "category":"Manufacturing",
            "subcategory":"Printing",
            "type":"Manufacturing & Wholesale Goods"
        }
    ],
    "sg:phone":"+1 301 952 9008",
    "sg:postcode":"20772",
    "sg:province":"MD",
    "sg:tags":[
        "periodical"
    ],
    "wof:name":"Better Way Publications Inc",
    "wof:placetype":"venue"
},
  "geometry": {"coordinates":[-76.752793,38.771723],"type":"Point"}
}