{
  "type": "Feature",
  "properties": {
    "addr:full":"4922 Alice Ave Ellicott City MD 21043",
    "addr:housenumber":"4922",
    "addr:postcode":"21043",
    "addr:street":"Alice Ave",
    "iso:country":"US",
    "sg:address":"4922 Alice Ave",
    "sg:city":"Ellicott City",
    "sg:classifiers":[
        {
            "category":"Professional",
            "subcategory":"Computer Services",
            "type":"Services"
        }
    ],
    "sg:phone":"+1 410 461 2507",
    "sg:postcode":"21043",
    "sg:province":"MD",
    "sg:tags":[
        "repair"
    ],
    "wof:name":"21st Century Business Concepts",
    "wof:placetype":"venue"
},
  "geometry": {"coordinates":[-76.80669,39.234318],"type":"Point"}
}