{
  "type": "Feature",
  "properties": {
    "iso:country":"US",
    "sg:address":"7505 Democracy Blvd",
    "sg:city":"Bethesda",
    "sg:classifiers":[
        {
            "category":"Health Services",
            "subcategory":"Doctor",
            "type":"Services"
        }
    ],
    "sg:phone":"+1 301 365 0011",
    "sg:postcode":"20817",
    "sg:province":"MD",
    "sg:tags":[
        "physician",
        "surgeon"
    ],
    "wof:name":"Jere J Daum MD",
    "wof:placetype":"venue"
},
  "geometry": {"coordinates":[-77.152326,39.023002],"type":"Point"}
}