{
  "type": "Feature",
  "properties": {
    "iso:country":"US",
    "sg:address":"6410 Glydon Ct",
    "sg:city":"Bowie",
    "sg:classifiers":[
        {
            "category":"Shopping",
            "subcategory":"Hobbies, Toys, & Games",
            "type":"Retail Goods"
        }
    ],
    "sg:phone":"+1 240 793 4509",
    "sg:postcode":"20720",
    "sg:province":"MD",
    "sg:tags":[
        "toy",
        "store",
        "supply"
    ],
    "wof:name":"Color An Angel",
    "wof:placetype":"venue"
},
  "geometry": {"coordinates":[-76.770059,38.976768],"type":"Point"}
}