{
  "type": "Feature",
  "properties": {
    "addr:full":"4801 Elm St Bethesda MD 20814",
    "addr:housenumber":"4801",
    "addr:postcode":"20814",
    "addr:street":"Elm St",
    "iso:country":"US",
    "sg:address":"4801 Elm St",
    "sg:city":"Bethesda",
    "sg:classifiers":[
        {
            "category":"Shopping",
            "subcategory":"Used Merchandise",
            "type":"Retail Goods"
        }
    ],
    "sg:phone":"+1 301 656 3722",
    "sg:postcode":"20814",
    "sg:province":"MD",
    "wof:name":"Designer Rsale Consignment Btq",
    "wof:placetype":"venue"
},
  "geometry": {"coordinates":[-77.094476,38.982365],"type":"Point"}
}