{
  "type": "Feature",
  "properties": {
    "iso:country":"US",
    "sg:address":"218 E Lexington St",
    "sg:city":"Baltimore",
    "sg:classifiers":[
        {
            "category":"Professional",
            "subcategory":"Lawyer & Legal Services",
            "type":"Services"
        }
    ],
    "sg:phone":"+1 443 919 6331",
    "sg:postcode":"21202",
    "sg:province":"MD",
    "wof:name":"Bivens Jerome A",
    "wof:placetype":"venue"
},
  "geometry": {"coordinates":[-76.611839,39.291423],"type":"Point"}
}