{
  "type": "Feature",
  "properties": {
    "iso:country":"US",
    "sg:address":"40145 Little Woods Ln",
    "sg:city":"Compton",
    "sg:classifiers":[
        {
            "category":"Building & Trades",
            "subcategory":"Construction",
            "type":"Services"
        }
    ],
    "sg:phone":"+1 301 475 6618",
    "sg:postcode":"20650",
    "sg:province":"MD",
    "sg:tags":[
        "designer",
        "marine",
        "contractor"
    ],
    "wof:name":"Fish Tales Marine Consultants",
    "wof:placetype":"venue"
},
  "geometry": {"coordinates":[-76.685757,38.265069],"type":"Point"}
}