{
  "type": "Feature",
  "properties": {
    "iso:country":"US",
    "sg:address":"1335 Piccard Dr Fl 2",
    "sg:city":"Rockville",
    "sg:classifiers":[
        {
            "category":"Government",
            "subcategory":"Office",
            "type":"Public Place"
        }
    ],
    "sg:phone":"+1 301 977 5255",
    "sg:postcode":"20850",
    "sg:province":"MD",
    "sg:tags":[
        "parish",
        "government-county"
    ],
    "wof:name":"County Of Montgomery",
    "wof:placetype":"venue"
},
  "geometry": {"coordinates":[-77.17878399999999,39.104567],"type":"Point"}
}