{
  "type": "Feature",
  "properties": {
    "iso:country":"US",
    "sg:address":"11003 Schuylkill Rd",
    "sg:city":"Rockville",
    "sg:classifiers":[
        {
            "category":"Communications",
            "type":"Services"
        }
    ],
    "sg:phone":"+1 301 231 5885",
    "sg:postcode":"20852",
    "sg:province":"MD",
    "sg:tags":[
        "web",
        "design"
    ],
    "wof:name":"Cre8Ive Design",
    "wof:placetype":"venue"
},
  "geometry": {"coordinates":[-77.086707,39.035045],"type":"Point"}
}