{
  "type": "Feature",
  "properties": {
    "addr:full":"2003 Medical Pkwy Annapolis MD 21401",
    "addr:housenumber":"2003",
    "addr:postcode":"21401",
    "addr:street":"Medical Pkwy",
    "iso:country":"US",
    "sg:address":"2003 Medical Pkwy",
    "sg:city":"Annapolis",
    "sg:classifiers":[
        {
            "category":"Health Services",
            "subcategory":"Hospital",
            "type":"Services"
        }
    ],
    "sg:phone":"+1 410 573 1094",
    "sg:postcode":"21401",
    "sg:province":"MD",
    "sg:tags":[
        "center",
        "birth"
    ],
    "wof:name":"Bay Area Midwifery Ctr",
    "wof:placetype":"venue"
},
  "geometry": {"coordinates":[-76.53373000000001,38.989467],"type":"Point"}
}