{
  "type": "Feature",
  "properties": {
    "iso:country":"US",
    "sg:address":"6314 Windsor Mill Rd",
    "sg:city":"Gwynn Oak",
    "sg:classifiers":[
        {
            "category":"Freight",
            "type":"Transportation"
        }
    ],
    "sg:phone":"+1 410 298 5461",
    "sg:postcode":"21207",
    "sg:province":"MD",
    "sg:tags":[
        "mover"
    ],
    "wof:name":"Venable & Sons Moving Co",
    "wof:placetype":"venue"
},
  "geometry": {"coordinates":[-76.725526,39.321241],"type":"Point"}
}