{
  "type": "Feature",
  "properties": {
    "addr:full":"900 High St Easton MD 21601",
    "addr:housenumber":"900",
    "addr:postcode":"21601",
    "addr:street":"High St",
    "iso:country":"US",
    "sg:address":"900 High St",
    "sg:city":"Easton",
    "sg:classifiers":[
        {
            "category":"Education",
            "subcategory":"School",
            "type":"Public Place"
        }
    ],
    "sg:phone":"+1 410 822 2275",
    "sg:postcode":"21601",
    "sg:province":"MD",
    "sg:website":"www.ssppeaston.org",
    "wof:name":"St Peter & Paul Elementary Sch",
    "wof:placetype":"venue"
},
  "geometry": {"coordinates":[-76.062226,38.769622],"type":"Point"}
}