{
  "type": "Feature",
  "properties": {
    "iso:country":"US",
    "sg:address":"7427 Fire Tower Rd",
    "sg:city":"Hebron",
    "sg:classifiers":[
        {
            "category":"Food & Beverages",
            "subcategory":"Meat & Fish",
            "type":"Retail Goods"
        }
    ],
    "sg:phone":"+1 410 749 8933",
    "sg:postcode":"21830",
    "sg:province":"MD",
    "sg:tags":[
        "seafood",
        "market"
    ],
    "wof:name":"Stan Evans Seafood Inc",
    "wof:placetype":"venue"
},
  "geometry": {"coordinates":[-75.69716699999999,38.394443],"type":"Point"}
}