{
  "type": "Feature",
  "properties": {
    "addr:full":"311 E Alder St Oakland MD 21550",
    "addr:housenumber":"311",
    "addr:postcode":"21550",
    "addr:street":"E Alder St",
    "iso:country":"US",
    "sg:address":"311 E Alder St",
    "sg:city":"Oakland",
    "sg:classifiers":[
        {
            "category":"Government",
            "subcategory":"Jail",
            "type":"Public Place"
        }
    ],
    "sg:phone":"+1 301 334 5055",
    "sg:postcode":"21550",
    "sg:province":"MD",
    "sg:tags":[
        "county",
        "govt",
        "institution"
    ],
    "wof:name":"Garrett County Jail",
    "wof:placetype":"venue"
},
  "geometry": {"coordinates":[-79.406978,39.407781],"type":"Point"}
}