{
  "type": "Feature",
  "properties": {
    "addr:full":"832 Oregon Ave Linthicum Hts MD 21090",
    "addr:housenumber":"832",
    "addr:postcode":"21090",
    "addr:street":"Oregon Ave",
    "iso:country":"US",
    "sg:address":"832 Oregon Ave",
    "sg:city":"Linthicum Hts",
    "sg:classifiers":[
        {
            "category":"Home & Garden",
            "subcategory":"Building Materials",
            "type":"Retail Goods"
        }
    ],
    "sg:phone":"+1 410 636 5733",
    "sg:postcode":"21090",
    "sg:province":"MD",
    "sg:tags":[
        "windows"
    ],
    "wof:name":"United Window",
    "wof:placetype":"venue"
},
  "geometry": {"coordinates":[-76.661857,39.227114],"type":"Point"}
}