{
  "type": "Feature",
  "properties": {
    "iso:country":"US",
    "sg:address":"12103 Devilwood Dr",
    "sg:city":"Potomac",
    "sg:classifiers":[
        {
            "category":"Professional",
            "subcategory":"Management & Consulting",
            "type":"Services"
        }
    ],
    "sg:phone":"+1 410 676 3181",
    "sg:postcode":"20854",
    "sg:province":"MD",
    "sg:tags":[
        "business"
    ],
    "wof:name":"Hahm Information Systems",
    "wof:placetype":"venue"
},
  "geometry": {"coordinates":[-77.171612,39.055219],"type":"Point"}
}