{
  "type": "Feature",
  "properties": {
    "addr:full":"13318 Glissans Mill Rd Mount Airy MD 21771",
    "addr:housenumber":"13318",
    "addr:postcode":"21771",
    "addr:street":"Glissans Mill Rd",
    "iso:country":"US",
    "sg:address":"13318 Glissans Mill Rd",
    "sg:city":"Mount Airy",
    "sg:classifiers":[
        {
            "category":"Shopping",
            "subcategory":"Used Merchandise",
            "type":"Retail Goods"
        }
    ],
    "sg:phone":"+1 301 829 0561",
    "sg:postcode":"21771",
    "sg:province":"MD",
    "wof:name":"Trading Post Antiques",
    "wof:placetype":"venue"
},
  "geometry": {"coordinates":[-77.200187,39.43689],"type":"Point"}
}