{
  "type": "Feature",
  "properties": {
    "addr:full":"13017 Wisteria Dr Ste 452 Germantown MD 20874",
    "addr:housenumber":"13017",
    "addr:postcode":"20874",
    "addr:street":"Wisteria Dr Ste 452",
    "iso:country":"US",
    "sg:address":"13017 Wisteria Dr Ste 452",
    "sg:city":"Germantown",
    "sg:classifiers":[
        {
            "category":"Professional",
            "subcategory":"Business Services",
            "type":"Services"
        }
    ],
    "sg:phone":"+1 301 515 2800",
    "sg:postcode":"20874",
    "sg:province":"MD",
    "sg:tags":[
        "consultant",
        "coach"
    ],
    "wof:name":"Charlton Research Co",
    "wof:placetype":"venue"
},
  "geometry": {"coordinates":[-77.27083399999999,39.177335],"type":"Point"}
}