{
  "type": "Feature",
  "properties": {
    "addr:full":"12503 Bredon Ct Brandywine MD 20613",
    "addr:housenumber":"12503",
    "addr:postcode":"20613",
    "addr:street":"Bredon Ct",
    "iso:country":"US",
    "sg:address":"12503 Bredon Ct",
    "sg:city":"Brandywine",
    "sg:classifiers":[
        {
            "category":"Personal",
            "type":"Services"
        },
        {
            "category":"Professional",
            "subcategory":"Art Services",
            "type":"Services"
        }
    ],
    "sg:phone":"+1 301 372 8341",
    "sg:postcode":"20613",
    "sg:province":"MD",
    "sg:tags":[
        "photography",
        "videography",
        "wedding"
    ],
    "wof:name":"Lori Photo S",
    "wof:placetype":"venue"
},
  "geometry": {"coordinates":[-76.86363900000001,38.717746],"type":"Point"}
}