{
  "type": "Feature",
  "properties": {
    "iso:country":"US",
    "sg:address":"4435 Oakwood Overlook Ct",
    "sg:city":"Dayton",
    "sg:classifiers":[
        {
            "category":"Building & Trades",
            "subcategory":"Electrical",
            "type":"Services"
        }
    ],
    "sg:phone":"+1 301 854 1163",
    "sg:postcode":"21036",
    "sg:province":"MD",
    "sg:tags":[
        "electric",
        "contractor"
    ],
    "wof:name":"Dayton Electrical Contracting",
    "wof:placetype":"venue"
},
  "geometry": {"coordinates":[-76.984836,39.259017],"type":"Point"}
}