{
  "type": "Feature",
  "properties": {
    "addr:full":"15601 McMullen Hwy SW Cumberland MD 21502",
    "addr:housenumber":"15601",
    "addr:postcode":"21502",
    "addr:street":"Mcmullen Hwy Sw",
    "iso:country":"US",
    "sg:address":"15601 McMullen Hwy SW",
    "sg:city":"Cumberland",
    "sg:classifiers":[
        {
            "category":"Freight",
            "type":"Transportation"
        }
    ],
    "sg:phone":"+1 301 729 3141",
    "sg:postcode":"21502",
    "sg:province":"MD",
    "sg:tags":[
        "operator",
        "local",
        "trucking"
    ],
    "wof:name":"Fitzgeralds Moving and Storage",
    "wof:placetype":"venue"
},
  "geometry": {"coordinates":[-78.847033,39.581733],"type":"Point"}
}