{
  "type": "Feature",
  "properties": {
    "iso:country":"US",
    "sg:address":"906 S Wolfe St",
    "sg:city":"Baltimore",
    "sg:classifiers":[
        {
            "category":"Restaurant",
            "type":"Food & Drink"
        }
    ],
    "sg:phone":"+1 410 327 4416",
    "sg:postcode":"21231",
    "sg:province":"MD",
    "sg:tags":[
        "continental"
    ],
    "wof:name":"The Water's Edge",
    "wof:placetype":"venue"
},
  "geometry": {"coordinates":[-76.589764,39.281851],"type":"Point"}
}