{
  "type": "Feature",
  "properties": {
    "iso:country":"US",
    "sg:address":"14934 Schaeffer Rd",
    "sg:city":"Boyds",
    "sg:classifiers":[
        {
            "category":"Recreation",
            "type":"Entertainment"
        }
    ],
    "sg:phone":"+1 301 916 6500",
    "sg:postcode":"20841",
    "sg:province":"MD",
    "sg:tags":[
        "stable"
    ],
    "wof:name":"Gray Rock Ranch",
    "wof:placetype":"venue"
},
  "geometry": {"coordinates":[-77.312442,39.146171],"type":"Point"}
}