{
  "type": "Feature",
  "properties": {
    "addr:full":"914 Forest Dr Annapolis MD 21403",
    "addr:housenumber":"914",
    "addr:postcode":"21403",
    "addr:street":"Forest Dr",
    "iso:country":"US",
    "sg:address":"914 Forest Dr",
    "sg:city":"Annapolis",
    "sg:classifiers":[
        {
            "category":"Insurance",
            "subcategory":"Insurance Agent",
            "type":"Services"
        },
        {
            "category":"Insurance",
            "subcategory":"Hazard Insurance",
            "type":"Services"
        },
        {
            "category":"Insurance",
            "subcategory":"Title Insurance",
            "type":"Services"
        },
        {
            "category":"Insurance",
            "subcategory":"Life Insurance",
            "type":"Services"
        }
    ],
    "sg:phone":"+1 410 267 8850",
    "sg:postcode":"21403",
    "sg:province":"MD",
    "sg:tags":[
        "business",
        "auto",
        "commercial",
        "homeowner",
        "motorcycle",
        "renter"
    ],
    "wof:name":"Allstate Insurance Company - Roslynne Ross",
    "wof:placetype":"venue"
},
  "geometry": {"coordinates":[-76.492609,38.950156],"type":"Point"}
}