{
  "type": "Feature",
  "properties": {
    "addr:full":"100 Holliday St Ll8182 Baltimore MD 21202",
    "addr:housenumber":"100",
    "addr:postcode":"21202",
    "addr:street":"Holliday St",
    "iso:country":"US",
    "sg:address":"100 Holliday St Ll8182",
    "sg:city":"Baltimore",
    "sg:classifiers":[
        {
            "category":"Utilities",
            "subcategory":"Recycling",
            "type":"Services"
        }
    ],
    "sg:phone":"+1 410 396 1277",
    "sg:postcode":"21202",
    "sg:province":"MD",
    "sg:tags":[
        "reduction",
        "waste"
    ],
    "sg:website":"http://www.baltimorecitycouncil.com",
    "wof:name":"Public Works",
    "wof:placetype":"venue"
},
  "geometry": {"coordinates":[-76.61022199999999,39.290501],"type":"Point"}
}