{
  "type": "Feature",
  "properties": {
    "iso:country":"US",
    "sg:address":"5316 Midwood Ave",
    "sg:city":"Baltimore",
    "sg:classifiers":[
        {
            "category":"Wholesale",
            "subcategory":"Non-durable Goods",
            "type":"Manufacturing & Wholesale Goods"
        }
    ],
    "sg:phone":"+1 410 323 7111",
    "sg:postcode":"21212",
    "sg:province":"MD",
    "sg:tags":[
        "merchandise-wholesale"
    ],
    "wof:name":"Laparkan Trading Ltd",
    "wof:placetype":"venue"
},
  "geometry": {"coordinates":[-76.602572,39.353042],"type":"Point"}
}