{
  "type": "Feature",
  "properties": {
    "addr:full":"4380 Park Heights Ave Baltimore MD 21215",
    "addr:housenumber":"4380",
    "addr:postcode":"21215",
    "addr:street":"Park Heights Ave",
    "iso:country":"US",
    "sg:address":"4380 Park Heights Ave",
    "sg:city":"Baltimore",
    "sg:classifiers":[
        {
            "category":"Building & Trades",
            "subcategory":"Locksmith",
            "type":"Services"
        }
    ],
    "sg:phone":"+1 410 864 0113",
    "sg:postcode":"21215",
    "sg:province":"MD",
    "sg:tags":[
        "key"
    ],
    "wof:name":"7 Days Asap Locksmith",
    "wof:placetype":"venue"
},
  "geometry": {"coordinates":[-76.666808,39.339847],"type":"Point"}
}