{
  "type": "Feature",
  "properties": {
    "addr:full":"8620 Hampton Valley Rd Emmitsburg MD 21727",
    "addr:housenumber":"8620",
    "addr:postcode":"21727",
    "addr:street":"Hampton Valley Rd",
    "iso:country":"US",
    "sg:address":"8620 Hampton Valley Rd",
    "sg:city":"Emmitsburg",
    "sg:classifiers":[
        {
            "category":"Building & Trades",
            "subcategory":"Construction",
            "type":"Services"
        }
    ],
    "sg:phone":"+1 301 447 6373",
    "sg:postcode":"21727",
    "sg:province":"MD",
    "sg:tags":[
        "excavating",
        "contractor"
    ],
    "wof:name":"Andrew & Sons Excavating",
    "wof:placetype":"venue"
},
  "geometry": {"coordinates":[-77.368439,39.702743],"type":"Point"}
}