{
  "type": "Feature",
  "properties": {
    "addr:full":"1107 King Arthur Court Sykesville MD 21784",
    "addr:housenumber":"1107",
    "addr:postcode":"21784",
    "addr:street":"King Arthur Court",
    "iso:country":"US",
    "sg:address":"1107 King Arthur Court",
    "sg:city":"Sykesville",
    "sg:classifiers":[
        {
            "category":"Professional",
            "subcategory":"Accounting & Tax Preparation",
            "type":"Services"
        }
    ],
    "sg:phone":"+1 410 549 1075",
    "sg:postcode":"21784",
    "sg:province":"MD",
    "sg:tags":[
        "public",
        "accountants-certified"
    ],
    "sg:website":"http://welshfinacctg.com",
    "wof:name":"Welsh Fin. & Acctg. Serv., LLC",
    "wof:placetype":"venue"
},
  "geometry": {"coordinates":[-76.956965,39.460858],"type":"Point"}
}