{
  "type": "Feature",
  "properties": {
    "iso:country":"US",
    "sg:address":"1301 E 25th St",
    "sg:city":"Baltimore",
    "sg:classifiers":[
        {
            "category":"Autos & Motor Vehicles",
            "subcategory":"Fuel & Gas Station",
            "type":"Retail Goods"
        },
        {
            "category":"Retail",
            "subcategory":"Auto Repair",
            "type":"Services"
        }
    ],
    "sg:phone":"+1 410 366 5050",
    "sg:postcode":"21218",
    "sg:province":"MD",
    "wof:name":"A & A Autorama Inc",
    "wof:placetype":"venue"
},
  "geometry": {"coordinates":[-76.59610000000001,39.317001],"type":"Point"}
}