{
  "type": "Feature",
  "properties": {
    "iso:country":"US",
    "sg:address":"10207 Frederick Ave",
    "sg:city":"Kensington",
    "sg:classifiers":[
        {
            "category":"Health Services",
            "subcategory":"Doctor",
            "type":"Services"
        }
    ],
    "sg:phone":"+1 301 949 2016",
    "sg:postcode":"20895",
    "sg:province":"MD",
    "wof:name":"Heron William H MD",
    "wof:placetype":"venue"
},
  "geometry": {"coordinates":[-77.070396,39.022499],"type":"Point"}
}