{
  "type": "Feature",
  "properties": {
    "addr:full":"14225 Briarwood Ter Rockville MD 20853",
    "addr:housenumber":"14225",
    "addr:postcode":"20853",
    "addr:street":"Briarwood Ter",
    "iso:country":"US",
    "sg:address":"14225 Briarwood Ter",
    "sg:city":"Rockville",
    "sg:classifiers":[
        {
            "category":"Building & Trades",
            "subcategory":"Construction",
            "type":"Services"
        }
    ],
    "sg:phone":"+1 301 460 1240",
    "sg:postcode":"20853",
    "sg:province":"MD",
    "sg:tags":[
        "demolition",
        "contractor"
    ],
    "wof:name":"Princeton Recovery Inc",
    "wof:placetype":"venue"
},
  "geometry": {"coordinates":[-77.096266,39.088671],"type":"Point"}
}