{
  "type": "Feature",
  "properties": {
    "addr:full":"7930 Solley Rd Glen Burnie MD 21060",
    "addr:housenumber":"7930",
    "addr:postcode":"21060",
    "addr:street":"Solley Rd",
    "iso:country":"US",
    "sg:address":"7930 Solley Rd",
    "sg:city":"Glen Burnie",
    "sg:classifiers":[
        {
            "category":"Wholesale",
            "subcategory":"Auto Parts",
            "type":"Manufacturing & Wholesale Goods"
        }
    ],
    "sg:phone":"+1 410 255 2250",
    "sg:postcode":"21060",
    "sg:province":"MD",
    "sg:tags":[
        "automobile",
        "rebuilt"
    ],
    "wof:name":"Bill's Auto Parts",
    "wof:placetype":"venue"
},
  "geometry": {"coordinates":[-76.569855,39.152436],"type":"Point"}
}