{
  "type": "Feature",
  "properties": {
    "iso:country":"US",
    "sg:address":"507 Pennsylvania Ave",
    "sg:city":"Baltimore",
    "sg:classifiers":[
        {
            "category":"Fast Food",
            "type":"Food & Drink"
        },
        {
            "category":"Deli",
            "type":"Food & Drink"
        },
        {
            "category":"Restaurant",
            "type":"Food & Drink"
        }
    ],
    "sg:phone":"+1 410 728 0300",
    "sg:postcode":"21201",
    "sg:province":"MD",
    "sg:tags":[
        "delicatessen",
        "take"
    ],
    "wof:name":"Downtown Deli",
    "wof:placetype":"venue"
},
  "geometry": {"coordinates":[-76.62397900000001,39.294835],"type":"Point"}
}