{
  "type": "Feature",
  "properties": {
    "addr:full":"9021 Kahl Ave Perry Hall MD 21128",
    "addr:housenumber":"9021",
    "addr:postcode":"21128",
    "addr:street":"Kahl Ave",
    "iso:country":"US",
    "sg:address":"9021 Kahl Ave",
    "sg:city":"Perry Hall",
    "sg:classifiers":[
        {
            "category":"Retail",
            "subcategory":"Repair Shop",
            "type":"Services"
        }
    ],
    "sg:phone":"+1 410 256 4439",
    "sg:postcode":"21128",
    "sg:province":"MD",
    "wof:name":"Hilltop Sanitation Service",
    "wof:placetype":"venue"
},
  "geometry": {"coordinates":[-76.454075,39.396864],"type":"Point"}
}