{
  "type": "Feature",
  "properties": {
    "iso:country":"US",
    "sg:address":"241 E 4th St Ste 100",
    "sg:city":"Frederick",
    "sg:classifiers":[
        {
            "category":"Professional",
            "subcategory":"Business Services",
            "type":"Services"
        }
    ],
    "sg:phone":"+1 240 629 2164",
    "sg:postcode":"21701",
    "sg:province":"MD",
    "sg:tags":[
        "organizing",
        "services-household"
    ],
    "sg:website":"http://www.hindsiteinteractive.com",
    "wof:name":"R. Christopher Goodwin & Associates, Inc.",
    "wof:placetype":"venue"
},
  "geometry": {"coordinates":[-77.40607799999999,39.418804],"type":"Point"}
}