{
  "type": "Feature",
  "properties": {
    "iso:country":"US",
    "sg:address":"427 N Eutaw St",
    "sg:city":"Baltimore",
    "sg:classifiers":[
        {
            "category":"Shopping",
            "subcategory":"Clothing, Apparel, & Fashions",
            "type":"Retail Goods"
        }
    ],
    "sg:phone":"+1 410 539 2219",
    "sg:postcode":"21201",
    "sg:province":"MD",
    "sg:tags":[
        "tailor"
    ],
    "wof:name":"Shimba Inc",
    "wof:placetype":"venue"
},
  "geometry": {"coordinates":[-76.621225,39.294376],"type":"Point"}
}