{
  "type": "Feature",
  "properties": {
    "iso:country":"US",
    "sg:address":"1800 Washington Blvd Ste 420",
    "sg:city":"Baltimore",
    "sg:classifiers":[
        {
            "category":"Shopping",
            "subcategory":"Pharmacy",
            "type":"Retail Goods"
        }
    ],
    "sg:phone":"+1 410 223 1240",
    "sg:postcode":"21230",
    "sg:province":"MD",
    "sg:tags":[
        "drugstore"
    ],
    "wof:name":"Neighborcare",
    "wof:placetype":"venue"
},
  "geometry": {"coordinates":[-76.64220400000001,39.275411],"type":"Point"}
}