{
  "type": "Feature",
  "properties": {
    "addr:full":"1602 Main St Cardiff MD 21160",
    "addr:housenumber":"1602",
    "addr:postcode":"21160",
    "addr:street":"Main St",
    "iso:country":"US",
    "sg:address":"1602 Main St",
    "sg:city":"Cardiff",
    "sg:classifiers":[
        {
            "category":"Professional",
            "subcategory":"Computer Services",
            "type":"Services"
        }
    ],
    "sg:phone":"+1 410 452 5501",
    "sg:postcode":"21160",
    "sg:province":"MD",
    "sg:tags":[
        "internet"
    ],
    "wof:name":"Starix Internet Svc Inc",
    "wof:placetype":"venue"
},
  "geometry": {"coordinates":[-76.33712800000001,39.718956],"type":"Point"}
}