{
  "type": "Feature",
  "properties": {
    "iso:country":"US",
    "sg:address":"2100 Madison Ave Apt 202",
    "sg:city":"Baltimore",
    "sg:classifiers":[
        {
            "category":"Home & Garden",
            "subcategory":"Carpets & Floor Coverings",
            "type":"Retail Goods"
        }
    ],
    "sg:phone":"+1 443 603 5365",
    "sg:postcode":"21217",
    "sg:province":"MD",
    "sg:tags":[
        "distributor",
        "rug",
        "manufacturer"
    ],
    "wof:name":"C & G Carpet Cleaninginc",
    "wof:placetype":"venue"
},
  "geometry": {"coordinates":[-76.63475800000001,39.309502],"type":"Point"}
}