{
  "type": "Feature",
  "properties": {
    "iso:country":"US",
    "sg:address":"2703 Ocean Gtwy",
    "sg:city":"Cambridge",
    "sg:classifiers":[
        {
            "category":"Farming",
            "subcategory":"Farm",
            "type":"Manufacturing & Wholesale Goods"
        }
    ],
    "sg:phone":"+1 410 228 4473",
    "sg:postcode":"21613",
    "sg:province":"MD",
    "wof:name":"Royal Farms",
    "wof:placetype":"venue"
},
  "geometry": {"coordinates":[-76.059769,38.557894],"type":"Point"}
}