{
  "type": "Feature",
  "properties": {
    "iso:country":"US",
    "sg:address":"107 Main St",
    "sg:city":"Annapolis",
    "sg:classifiers":[
        {
            "category":"Shopping",
            "subcategory":"Clothing, Apparel, & Fashions",
            "type":"Retail Goods"
        }
    ],
    "sg:phone":"+1 410 267 0305",
    "sg:postcode":"21401",
    "sg:province":"MD",
    "sg:tags":[
        "apparel",
        "clothing",
        "store",
        "women's"
    ],
    "wof:name":"Naptown Clothing Co Inc",
    "wof:placetype":"venue"
},
  "geometry": {"coordinates":[-76.487841,38.977458],"type":"Point"}
}