{
  "type": "Feature",
  "properties": {
    "addr:full":"30 Marley Neck Rd Glen Burnie MD 21060",
    "addr:housenumber":"30",
    "addr:postcode":"21060",
    "addr:street":"Marley Neck Rd",
    "iso:country":"US",
    "sg:address":"30 Marley Neck Rd",
    "sg:city":"Glen Burnie",
    "sg:classifiers":[
        {
            "category":"Organizations",
            "subcategory":"Religious Organization",
            "type":"Services"
        }
    ],
    "sg:phone":"+1 410 760 4720",
    "sg:postcode":"21060",
    "sg:province":"MD",
    "sg:tags":[
        "church"
    ],
    "wof:name":"Marley United Methodist Church",
    "wof:placetype":"venue"
},
  "geometry": {"coordinates":[-76.59236900000001,39.154046],"type":"Point"}
}