{
  "type": "Feature",
  "properties": {
    "addr:full":"11009 Petersborough Dr Rockville MD 20852",
    "addr:housenumber":"11009",
    "addr:postcode":"20852",
    "addr:street":"Petersborough Dr",
    "iso:country":"US",
    "sg:address":"11009 Petersborough Dr",
    "sg:city":"Rockville",
    "sg:classifiers":[
        {
            "category":"Education",
            "subcategory":"Special Training",
            "type":"Public Place"
        }
    ],
    "sg:phone":"+1 301 468 0061",
    "sg:postcode":"20852",
    "sg:province":"MD",
    "wof:name":"Janki Ganju Eductl Foundation",
    "wof:placetype":"venue"
},
  "geometry": {"coordinates":[-77.114728,39.037638],"type":"Point"}
}