{
  "type": "Feature",
  "properties": {
    "iso:country":"US",
    "sg:address":"8821 River Rd",
    "sg:city":"Bethesda",
    "sg:classifiers":[
        {
            "category":"Education",
            "subcategory":"School",
            "type":"Public Place"
        }
    ],
    "sg:phone":"+1 301 365 2595",
    "sg:postcode":"20817",
    "sg:province":"MD",
    "sg:tags":[
        "high",
        "middle",
        "elementary"
    ],
    "wof:name":"The Norwood School Ofc",
    "wof:placetype":"venue"
},
  "geometry": {"coordinates":[-77.178802,39.001099],"type":"Point"}
}