{
  "type": "Feature",
  "properties": {
    "iso:country":"US",
    "sg:address":"3704 N Charles St",
    "sg:city":"Baltimore",
    "sg:classifiers":[
        {
            "category":"Professional",
            "subcategory":"Management & Consulting",
            "type":"Services"
        }
    ],
    "sg:phone":"+1 410 235 7105",
    "sg:postcode":"21218",
    "sg:province":"MD",
    "sg:tags":[
        "fuel"
    ],
    "wof:name":"Homewood Management Resources",
    "wof:placetype":"venue"
},
  "geometry": {"coordinates":[-76.618179,39.334745],"type":"Point"}
}