{
  "type": "Feature",
  "properties": {
    "iso:country":"US",
    "sg:address":"3017 W Belvedere Ave",
    "sg:city":"Baltimore",
    "sg:classifiers":[
        {
            "category":"Personal",
            "subcategory":"Beauty Salon",
            "type":"Services"
        }
    ],
    "sg:phone":"+1 410 466 7028",
    "sg:postcode":"21215",
    "sg:province":"MD",
    "wof:name":"Just Us",
    "wof:placetype":"venue"
},
  "geometry": {"coordinates":[-76.672607,39.350758],"type":"Point"}
}