{
  "type": "Feature",
  "properties": {
    "iso:country":"US",
    "sg:address":"14404 Lake Winds Way",
    "sg:city":"Gaithersburg",
    "sg:classifiers":[
        {
            "category":"Wholesale",
            "subcategory":"Vending Machines",
            "type":"Manufacturing & Wholesale Goods"
        }
    ],
    "sg:phone":"+1 301 762 4517",
    "sg:postcode":"20878",
    "sg:province":"MD",
    "sg:tags":[
        "operator"
    ],
    "wof:name":"Big B Vending Corporation",
    "wof:placetype":"venue"
},
  "geometry": {"coordinates":[-77.22818599999999,39.091595],"type":"Point"}
}