{
  "type": "Feature",
  "properties": {
    "iso:country":"US",
    "sg:address":"Laurel I & II",
    "sg:city":"Laurel",
    "sg:classifiers":[
        {
            "category":"Real Estate",
            "subcategory":"Real Estate Operator",
            "type":"Services"
        }
    ],
    "sg:phone":"+1 301 490 1526",
    "sg:postcode":"20707",
    "sg:province":"MD",
    "sg:tags":[
        "apartment"
    ],
    "wof:name":"Park View Communities",
    "wof:placetype":"venue"
},
  "geometry": {"coordinates":[-76.869202,39.098301],"type":"Point"}
}