{
  "type": "Feature",
  "properties": {
    "addr:full":"727 Druid Park Lake Dr D Baltimore MD 21217",
    "addr:housenumber":"727",
    "addr:postcode":"21217",
    "addr:street":"Druid Park Lake Dr D",
    "iso:country":"US",
    "sg:address":"727 Druid Park Lake Dr D",
    "sg:city":"Baltimore",
    "sg:classifiers":[
        {
            "category":"Social Services",
            "type":"Services"
        }
    ],
    "sg:phone":"+1 410 545 3305",
    "sg:postcode":"21217",
    "sg:province":"MD",
    "wof:name":"Lakeview Towers Tenant Council",
    "wof:placetype":"venue"
},
  "geometry": {"coordinates":[-76.632812,39.316973],"type":"Point"}
}