{
  "type": "Feature",
  "properties": {
    "addr:full":"7101 Wisconsin Ave Bethesda MD 20814",
    "addr:housenumber":"7101",
    "addr:postcode":"20814",
    "addr:street":"Wisconsin Ave",
    "iso:country":"US",
    "sg:address":"7101 Wisconsin Ave",
    "sg:city":"Bethesda",
    "sg:classifiers":[
        {
            "category":"Building & Trades",
            "subcategory":"Construction",
            "type":"Services"
        }
    ],
    "sg:phone":"+1 301 657 3370",
    "sg:postcode":"20814",
    "sg:province":"MD",
    "sg:tags":[
        "general",
        "contractor"
    ],
    "sg:website":"www.amec.com",
    "wof:name":"AMEC Construction Management",
    "wof:placetype":"venue"
},
  "geometry": {"coordinates":[-77.092422,38.980621],"type":"Point"}
}