{
  "type": "Feature",
  "properties": {
    "iso:country":"US",
    "sg:address":"2217 Stockton Rd",
    "sg:city":"Joppa",
    "sg:classifiers":[
        {
            "category":"Building & Trades",
            "subcategory":"Construction",
            "type":"Services"
        }
    ],
    "sg:phone":"+1 410 877 9716",
    "sg:postcode":"21085",
    "sg:province":"MD",
    "sg:tags":[
        "house"
    ],
    "wof:name":"Handyman Remodeling Inc",
    "wof:placetype":"venue"
},
  "geometry": {"coordinates":[-76.37020699999999,39.472132],"type":"Point"}
}