{
  "type": "Feature",
  "properties": {
    "addr:full":"12100 Baltimore Ave Beltsville MD 20705",
    "addr:housenumber":"12100",
    "addr:postcode":"20705",
    "addr:street":"Baltimore Ave",
    "iso:country":"US",
    "sg:address":"12100 Baltimore Ave",
    "sg:city":"Beltsville",
    "sg:classifiers":[
        {
            "category":"Building & Trades",
            "subcategory":"Construction",
            "type":"Services"
        }
    ],
    "sg:phone":"+1 301 419 3969",
    "sg:postcode":"20705",
    "sg:province":"MD",
    "sg:tags":[
        "contractor"
    ],
    "wof:name":"Pella Window Store",
    "wof:placetype":"venue"
},
  "geometry": {"coordinates":[-76.892595,39.055376],"type":"Point"}
}