{
  "type": "Feature",
  "properties": {
    "addr:full":"2015 E Lanvale St Baltimore MD 21213",
    "addr:housenumber":"2015",
    "addr:postcode":"21213",
    "addr:street":"E Lanvale St",
    "iso:country":"US",
    "sg:address":"2015 E Lanvale St",
    "sg:city":"Baltimore",
    "sg:classifiers":[
        {
            "category":"Organizations",
            "subcategory":"Religious Organization",
            "type":"Services"
        }
    ],
    "sg:phone":"+1 410 558 1193",
    "sg:postcode":"21213",
    "sg:province":"MD",
    "sg:tags":[
        "church"
    ],
    "wof:name":"Alpha & Omega Worship Center",
    "wof:placetype":"venue"
},
  "geometry": {"coordinates":[-76.5895,39.310001],"type":"Point"}
}