{
  "type": "Feature",
  "properties": {
    "addr:full":"3746 Howard Ave Kensington MD 20895",
    "addr:housenumber":"3746",
    "addr:postcode":"20895",
    "addr:street":"Howard Ave",
    "iso:country":"US",
    "sg:address":"3746 Howard Ave",
    "sg:city":"Kensington",
    "sg:classifiers":[
        {
            "category":"Shopping",
            "subcategory":"Antiques",
            "type":"Retail Goods"
        }
    ],
    "sg:phone":"+1 301 933 4460",
    "sg:postcode":"20895",
    "sg:province":"MD",
    "wof:name":"Goldsborough Glynn Antiques and Decorative Arts",
    "wof:placetype":"venue"
},
  "geometry": {"coordinates":[-77.07339899999999,39.027378],"type":"Point"}
}