{
  "type": "Feature",
  "properties": {
    "iso:country":"US",
    "sg:address":"11619 Greenlane Dr",
    "sg:city":"Potomac",
    "sg:classifiers":[
        {
            "category":"Shopping",
            "type":"Retail Goods"
        }
    ],
    "sg:phone":"+1 301 765 6247",
    "sg:postcode":"20854",
    "sg:province":"MD",
    "sg:tags":[
        "merchandise"
    ],
    "wof:name":"Honeybee In Garden",
    "wof:placetype":"venue"
},
  "geometry": {"coordinates":[-77.170581,39.047165],"type":"Point"}
}