{
  "type": "Feature",
  "properties": {
    "iso:country":"US",
    "sg:address":"12203 Linden Linthicum Ln",
    "sg:city":"Clarksville",
    "sg:classifiers":[
        {
            "category":"Professional",
            "subcategory":"Management & Consulting",
            "type":"Services"
        }
    ],
    "sg:phone":"+1 410 531 0465",
    "sg:postcode":"21029",
    "sg:province":"MD",
    "wof:name":"Law Offices of Jack Schwartz",
    "wof:placetype":"venue"
},
  "geometry": {"coordinates":[-76.930756,39.211788],"type":"Point"}
}