{
  "type": "Feature",
  "properties": {
    "iso:country":"US",
    "sg:address":"22790 Maple Rd",
    "sg:city":"Lexington Park",
    "sg:classifiers":[
        {
            "category":"Education",
            "subcategory":"School",
            "type":"Public Place"
        }
    ],
    "sg:phone":"+1 301 863 4014",
    "sg:postcode":"20653",
    "sg:province":"MD",
    "sg:tags":[
        "executive"
    ],
    "wof:name":"Esperanza Middle School",
    "wof:placetype":"venue"
},
  "geometry": {"coordinates":[-76.493359,38.291461],"type":"Point"}
}