{
  "type": "Feature",
  "properties": {
    "addr:full":"1737 Brodbeck Rd Hampstead MD 21074",
    "addr:housenumber":"1737",
    "addr:postcode":"21074",
    "addr:street":"Brodbeck Rd",
    "iso:country":"US",
    "sg:address":"1737 Brodbeck Rd",
    "sg:city":"Hampstead",
    "sg:classifiers":[
        {
            "category":"Building & Trades",
            "subcategory":"Construction",
            "type":"Services"
        }
    ],
    "sg:phone":"+1 410 374 9235",
    "sg:postcode":"21074",
    "sg:province":"MD",
    "sg:tags":[
        "excavation",
        "contractor"
    ],
    "wof:name":"George H Renfro Excavating",
    "wof:placetype":"venue"
},
  "geometry": {"coordinates":[-76.870239,39.626475],"type":"Point"}
}