{
  "type": "Feature",
  "properties": {
    "addr:full":"301 W Main St Middletown MD 21769",
    "addr:housenumber":"301",
    "addr:postcode":"21769",
    "addr:street":"W Main St",
    "iso:country":"US",
    "sg:address":"301 W Main St",
    "sg:city":"Middletown",
    "sg:classifiers":[
        {
            "category":"Government",
            "subcategory":"Office",
            "type":"Public Place"
        }
    ],
    "sg:phone":"+1 301 371 4480",
    "sg:postcode":"21769",
    "sg:province":"MD",
    "sg:tags":[
        "village"
    ],
    "wof:name":"Middletown Waste Water",
    "wof:placetype":"venue"
},
  "geometry": {"coordinates":[-77.548794,39.443979],"type":"Point"}
}