{
  "type": "Feature",
  "properties": {
    "iso:country":"US",
    "sg:address":"815 Thayer Ave",
    "sg:city":"Silver Spring",
    "sg:classifiers":[
        {
            "category":"Professional",
            "subcategory":"Management & Consulting",
            "type":"Services"
        }
    ],
    "sg:phone":"+1 301 585 8051",
    "sg:postcode":"20910",
    "sg:province":"MD",
    "wof:name":"Alfred Msw Brenda",
    "wof:placetype":"venue"
},
  "geometry": {"coordinates":[-77.023858,38.993126],"type":"Point"}
}