{
  "type": "Feature",
  "properties": {
    "addr:full":"6022 Pleasant Dr Frederick MD 21703",
    "addr:housenumber":"6022",
    "addr:postcode":"21703",
    "addr:street":"Pleasant Dr",
    "iso:country":"US",
    "sg:address":"6022 Pleasant Dr",
    "sg:city":"Frederick",
    "sg:classifiers":[
        {
            "category":"Wholesale",
            "subcategory":"Toys & Hobbies",
            "type":"Manufacturing & Wholesale Goods"
        }
    ],
    "sg:phone":"+1 301 668 0292",
    "sg:postcode":"21703",
    "sg:province":"MD",
    "wof:name":"Truequestproducts",
    "wof:placetype":"venue"
},
  "geometry": {"coordinates":[-77.459399,39.396815],"type":"Point"}
}