{
  "type": "Feature",
  "properties": {
    "addr:full":"600 Washington Ave Baltimore MD 21204",
    "addr:housenumber":"600",
    "addr:postcode":"21204",
    "addr:street":"Washington Ave",
    "iso:country":"US",
    "sg:address":"600 Washington Ave",
    "sg:city":"Baltimore",
    "sg:classifiers":[
        {
            "category":"Banks & Credit Unions",
            "subcategory":"Investment Brokerage",
            "type":"Services"
        }
    ],
    "sg:phone":"+1 410 821 7700",
    "sg:postcode":"21204",
    "sg:province":"MD",
    "sg:tags":[
        "stock",
        "bond"
    ],
    "sg:website":"www.leggmason.com",
    "wof:name":"Legg Mason Wood Walker Inc",
    "wof:placetype":"venue"
},
  "geometry": {"coordinates":[-76.604877,39.402543],"type":"Point"}
}