{
  "type": "Feature",
  "properties": {
    "addr:full":"2901 Crestview Ct Waldorf MD 20603",
    "addr:housenumber":"2901",
    "addr:postcode":"20603",
    "addr:street":"Crestview Ct",
    "iso:country":"US",
    "sg:address":"2901 Crestview Ct",
    "sg:city":"Waldorf",
    "sg:classifiers":[
        {
            "category":"Professional",
            "type":"Services"
        }
    ],
    "sg:phone":"+1 301 645 5981",
    "sg:postcode":"20603",
    "sg:province":"MD",
    "wof:name":"Creative Stained Glass",
    "wof:placetype":"venue"
},
  "geometry": {"coordinates":[-77.00536,38.63442],"type":"Point"}
}