{
  "type": "Feature",
  "properties": {
    "iso:country":"US",
    "sg:address":"8315 Benson Dr",
    "sg:city":"Columbia",
    "sg:classifiers":[
        {
            "category":"Restaurant",
            "type":"Food & Drink"
        }
    ],
    "sg:menulink":"http://www.allmenus.com/md/savage/13815-olive-garden-italian-restaurant/menu/",
    "sg:phone":"+1 410 290 0040",
    "sg:postcode":"21045",
    "sg:province":"MD",
    "sg:tags":[
        "italian"
    ],
    "wof:name":"Olive Garden Italian Restaurant",
    "wof:placetype":"venue"
},
  "geometry": {"coordinates":[-76.798832,39.187581],"type":"Point"}
}