{
  "type": "Feature",
  "properties": {
    "iso:country":"US",
    "sg:address":"7001 Quad Ave",
    "sg:city":"Rosedale",
    "sg:classifiers":[
        {
            "category":"Wholesale",
            "subcategory":"Wine & Distilled Alcoholic Beverages",
            "type":"Manufacturing & Wholesale Goods"
        }
    ],
    "sg:phone":"+1 410 284 1838",
    "sg:postcode":"21237",
    "sg:province":"MD",
    "sg:tags":[
        "liquors-wholesale"
    ],
    "wof:name":"F P Winner Ltd",
    "wof:placetype":"venue"
},
  "geometry": {"coordinates":[-76.526718,39.301541],"type":"Point"}
}