{
  "type": "Feature",
  "properties": {
    "iso:country":"US",
    "sg:address":"3600 Brightseat Rd",
    "sg:city":"Hyattsville",
    "sg:classifiers":[
        {
            "category":"Education",
            "subcategory":"Special Training",
            "type":"Public Place"
        },
        {
            "category":"Social Services",
            "subcategory":"Child Care",
            "type":"Services"
        }
    ],
    "sg:phone":"+1 301 386 8234",
    "sg:postcode":"20785",
    "sg:province":"MD",
    "sg:tags":[
        "educational",
        "nursery",
        "day"
    ],
    "wof:name":"Shabach Ministries, Inc.",
    "wof:placetype":"venue"
},
  "geometry": {"coordinates":[-76.857826,38.935076],"type":"Point"}
}