{
  "type": "Feature",
  "properties": {
    "iso:country":"US",
    "sg:address":"2809 Boston St",
    "sg:city":"Baltimore",
    "sg:classifiers":[
        {
            "category":"Professional",
            "type":"Services"
        }
    ],
    "sg:phone":"+1 410 276 7797",
    "sg:postcode":"21224",
    "sg:province":"MD",
    "wof:name":"Wtec Service Corp",
    "wof:placetype":"venue"
},
  "geometry": {"coordinates":[-76.575457,39.278178],"type":"Point"}
}