{
  "type": "Feature",
  "properties": {
    "addr:full":"20819 Shamrock Glen Cir Germantown MD 20874",
    "addr:housenumber":"20819",
    "addr:postcode":"20874",
    "addr:street":"Shamrock Glen Cir",
    "iso:country":"US",
    "sg:address":"20819 Shamrock Glen Cir",
    "sg:city":"Germantown",
    "sg:classifiers":[
        {
            "category":"Professional",
            "subcategory":"Management & Consulting",
            "type":"Services"
        }
    ],
    "sg:phone":"+1 301 528 0877",
    "sg:postcode":"20874",
    "sg:province":"MD",
    "sg:tags":[
        "business"
    ],
    "wof:name":"Oxford Analytical Ltd",
    "wof:placetype":"venue"
},
  "geometry": {"coordinates":[-77.268781,39.197115],"type":"Point"}
}