{
  "type": "Feature",
  "properties": {
    "addr:full":"2817 Bel Air Rd Fallston MD 21047",
    "addr:postcode":"2817;21047",
    "addr:street":"Bel Air Rd",
    "iso:country":"US",
    "sg:address":"2817 Bel Air Rd",
    "sg:city":"Fallston",
    "sg:classifiers":[
        {
            "category":"Retail",
            "subcategory":"Auto Repair",
            "type":"Services"
        }
    ],
    "sg:phone":"+1 410 879 0100",
    "sg:postcode":"21047",
    "sg:province":"MD",
    "sg:tags":[
        "repairing",
        "automobile"
    ],
    "wof:name":"Dietz Auto Repair Svc",
    "wof:placetype":"venue"
},
  "geometry": {"coordinates":[-76.402377,39.483129],"type":"Point"}
}