{
  "type": "Feature",
  "properties": {
    "iso:country":"US",
    "sg:address":"957 Rosedale Ave",
    "sg:city":"Rosedale",
    "sg:classifiers":[
        {
            "category":"Building & Trades",
            "subcategory":"Construction",
            "type":"Services"
        }
    ],
    "sg:phone":"+1 443 278 3411",
    "sg:postcode":"21237",
    "sg:province":"MD",
    "sg:tags":[
        "contractor"
    ],
    "sg:website":"www.alashekgeneralcontracting.com",
    "wof:name":"Alashek Contracting",
    "wof:placetype":"venue"
},
  "geometry": {"coordinates":[-76.510572,39.310891],"type":"Point"}
}