{
  "type": "Feature",
  "properties": {
    "iso:country":"US",
    "sg:address":"4206 Warner St",
    "sg:city":"Kensington",
    "sg:classifiers":[
        {
            "category":"Building & Trades",
            "subcategory":"Construction",
            "type":"Services"
        }
    ],
    "sg:phone":"+1 301 897 8773",
    "sg:postcode":"20895",
    "sg:province":"MD",
    "sg:tags":[
        "contractor"
    ],
    "wof:name":"Whitcomb Carroccio Construction",
    "wof:placetype":"venue"
},
  "geometry": {"coordinates":[-77.08237200000001,39.028021],"type":"Point"}
}