{
  "type": "Feature",
  "properties": {
    "iso:country":"US",
    "sg:address":"10305 Guilford Rd",
    "sg:city":"Jessup",
    "sg:classifiers":[
        {
            "category":"Freight",
            "type":"Transportation"
        }
    ],
    "sg:phone":"+1 301 604 2147",
    "sg:postcode":"20794",
    "sg:province":"MD",
    "sg:tags":[
        "mover"
    ],
    "sg:website":"www.certifiedpackaging.com",
    "wof:name":"Certified Packaging & Trnsprt",
    "wof:placetype":"venue"
},
  "geometry": {"coordinates":[-76.808807,39.143151],"type":"Point"}
}