{
  "type": "Feature",
  "properties": {
    "addr:full":"4500 Black Rock Rd Hampstead MD 21074",
    "addr:housenumber":"4500",
    "addr:postcode":"21074",
    "addr:street":"Black Rock Rd",
    "iso:country":"US",
    "sg:address":"4500 Black Rock Rd",
    "sg:city":"Hampstead",
    "sg:classifiers":[
        {
            "category":"Health Services",
            "subcategory":"Doctor",
            "type":"Services"
        }
    ],
    "sg:phone":"+1 410 239 0406",
    "sg:postcode":"21074",
    "sg:province":"MD",
    "sg:tags":[
        "physician",
        "surgeon"
    ],
    "wof:name":"Carroll Family Medicine",
    "wof:placetype":"venue"
},
  "geometry": {"coordinates":[-76.83600199999999,39.604217],"type":"Point"}
}