{
  "type": "Feature",
  "properties": {
    "iso:country":"US",
    "sg:address":"1612 Orlando Rd",
    "sg:city":"Baltimore",
    "sg:classifiers":[
        {
            "category":"Professional",
            "subcategory":"Business Services",
            "type":"Services"
        }
    ],
    "sg:phone":"+1 410 661 2573",
    "sg:postcode":"21234",
    "sg:province":"MD",
    "wof:name":"Kr Brown & Associates Inc",
    "wof:placetype":"venue"
},
  "geometry": {"coordinates":[-76.560678,39.383696],"type":"Point"}
}