{
  "type": "Feature",
  "properties": {
    "iso:country":"US",
    "sg:address":"6216 Montrose Rd",
    "sg:city":"Rockville",
    "sg:classifiers":[
        {
            "category":"Health Services",
            "subcategory":"Health Practitioner",
            "type":"Services"
        }
    ],
    "sg:phone":"+1 301 230 9155",
    "sg:postcode":"20852",
    "sg:province":"MD",
    "sg:tags":[
        "acupuncture"
    ],
    "wof:name":"A Center For Acupuncture & Herbs",
    "wof:placetype":"venue"
},
  "geometry": {"coordinates":[-77.12690000000001,39.052898],"type":"Point"}
}