{
  "type": "Feature",
  "properties": {
    "iso:country":"US",
    "sg:address":"3235 E Baltimore St",
    "sg:city":"Baltimore",
    "sg:classifiers":[
        {
            "category":"Personal",
            "type":"Services"
        }
    ],
    "sg:phone":"+1 410 327 7711",
    "sg:postcode":"21224",
    "sg:province":"MD",
    "sg:tags":[
        "sewing",
        "alteration"
    ],
    "wof:name":"Ricardo Custom Tailor Services",
    "wof:placetype":"venue"
},
  "geometry": {"coordinates":[-76.57086,39.292273],"type":"Point"}
}