{
  "type": "Feature",
  "properties": {
    "iso:country":"US",
    "sg:address":"8039 Liberty Rd",
    "sg:city":"Baltimore",
    "sg:classifiers":[
        {
            "category":"Utilities",
            "subcategory":"Mobile Phone",
            "type":"Services"
        }
    ],
    "sg:phone":"+1 410 655 4955",
    "sg:postcode":"21244",
    "sg:province":"MD",
    "sg:tags":[
        "telephone",
        "cellular"
    ],
    "wof:name":"Hook Me Up Communications",
    "wof:placetype":"venue"
},
  "geometry": {"coordinates":[-76.757357,39.353313],"type":"Point"}
}