{
  "type": "Feature",
  "properties": {
    "addr:full":"19706 Germantown Rd Germantown MD 20874",
    "addr:housenumber":"19706",
    "addr:postcode":"20874",
    "addr:street":"Germantown Rd",
    "iso:country":"US",
    "sg:address":"19706 Germantown Rd",
    "sg:city":"Germantown",
    "sg:classifiers":[
        {
            "category":"Shopping",
            "type":"Retail Goods"
        }
    ],
    "sg:phone":"+1 301 540 9663",
    "sg:postcode":"20874",
    "sg:province":"MD",
    "sg:tags":[
        "telephone",
        "cellular"
    ],
    "wof:name":"Wireless Zone",
    "wof:placetype":"venue"
},
  "geometry": {"coordinates":[-77.265523,39.179795],"type":"Point"}
}