{
  "type": "Feature",
  "properties": {
    "iso:country":"US",
    "sg:address":"800 Muddy Branch Rd",
    "sg:city":"Gaithersburg",
    "sg:classifiers":[
        {
            "category":"Banks & Credit Unions",
            "subcategory":"Bank",
            "type":"Services"
        }
    ],
    "sg:phone":"+1 301 230 8040",
    "sg:postcode":"20878",
    "sg:province":"MD",
    "wof:name":"Sun Trust Bank",
    "wof:placetype":"venue"
},
  "geometry": {"coordinates":[-77.21753099999999,39.109701],"type":"Point"}
}