{
  "type": "Feature",
  "properties": {
    "iso:country":"US",
    "sg:address":"14213 Jarrettsville Pike",
    "sg:city":"Phoenix",
    "sg:classifiers":[
        {
            "category":"Banks & Credit Unions",
            "subcategory":"Bank",
            "type":"Services"
        }
    ],
    "sg:phone":"+1 410 666 8510",
    "sg:postcode":"21131",
    "sg:province":"MD",
    "wof:name":"Bank Of America",
    "wof:placetype":"venue"
},
  "geometry": {"coordinates":[-76.56026,39.515001],"type":"Point"}
}