{
  "type": "Feature",
  "properties": {
    "iso:country":"US",
    "sg:address":"2140 McCulloh St",
    "sg:city":"Baltimore",
    "sg:classifiers":[
        {
            "category":"Social Services",
            "subcategory":"Child Care",
            "type":"Services"
        }
    ],
    "sg:phone":"+1 410 669 2480",
    "sg:postcode":"21217",
    "sg:province":"MD",
    "sg:tags":[
        "day"
    ],
    "wof:name":"Little Bears Den",
    "wof:placetype":"venue"
},
  "geometry": {"coordinates":[-76.636025,39.308985],"type":"Point"}
}