{
  "type": "Feature",
  "properties": {
    "addr:full":"175 Klee Mill Rd Sykesville MD 21784",
    "addr:housenumber":"175",
    "addr:postcode":"21784",
    "addr:street":"Klee Mill Rd",
    "iso:country":"US",
    "sg:address":"175 Klee Mill Rd",
    "sg:city":"Sykesville",
    "sg:classifiers":[
        {
            "category":"Social Services",
            "subcategory":"Child Care",
            "type":"Services"
        }
    ],
    "sg:phone":"+1 410 549 0844",
    "sg:postcode":"21784",
    "sg:province":"MD",
    "sg:tags":[
        "nursery",
        "day"
    ],
    "wof:name":"Sunshine Kids' Club",
    "wof:placetype":"venue"
},
  "geometry": {"coordinates":[-76.989858,39.449684],"type":"Point"}
}