{
  "type": "Feature",
  "properties": {
    "addr:full":"11140 Lake Breeze Dr Gaithersburg MD 20878",
    "addr:housenumber":"11140",
    "addr:postcode":"20878",
    "addr:street":"Lake Breeze Dr",
    "iso:country":"US",
    "sg:address":"11140 Lake Breeze Dr",
    "sg:city":"Gaithersburg",
    "sg:classifiers":[
        {
            "category":"Professional",
            "subcategory":"Art Services",
            "type":"Services"
        }
    ],
    "sg:phone":"+1 301 279 8789",
    "sg:postcode":"20878",
    "sg:province":"MD",
    "sg:tags":[
        "commercial",
        "design"
    ],
    "wof:name":"Potomac Graphics Incorporation",
    "wof:placetype":"venue"
},
  "geometry": {"coordinates":[-77.226721,39.095206],"type":"Point"}
}