{
  "type": "Feature",
  "properties": {
    "iso:country":"US",
    "sg:address":"10800 Rhode Island Ave",
    "sg:city":"Beltsville",
    "sg:classifiers":[
        {
            "category":"Shopping",
            "subcategory":"Books",
            "type":"Retail Goods"
        }
    ],
    "sg:phone":"+1 301 937 0971",
    "sg:postcode":"20705",
    "sg:province":"MD",
    "sg:tags":[
        "dealer"
    ],
    "wof:name":"Candelero De Oro",
    "wof:placetype":"venue"
},
  "geometry": {"coordinates":[-76.913703,39.033072],"type":"Point"}
}