{
  "type": "Feature",
  "properties": {
    "iso:country":"US",
    "sg:address":"41 W Kanawha Dr",
    "sg:city":"Rising Sun",
    "sg:classifiers":[
        {
            "category":"Wholesale",
            "subcategory":"Farm Supplies",
            "type":"Manufacturing & Wholesale Goods"
        }
    ],
    "sg:phone":"+1 410 658 6319",
    "sg:postcode":"21911",
    "sg:province":"MD",
    "wof:name":"Mid Atlantic Poly Store Inc",
    "wof:placetype":"venue"
},
  "geometry": {"coordinates":[-76.12689399999999,39.703472],"type":"Point"}
}