{
  "type": "Feature",
  "properties": {
    "iso:country":"US",
    "sg:address":"5 Cumberland Ct",
    "sg:city":"Annapolis",
    "sg:classifiers":[
        {
            "category":"Organizations",
            "subcategory":"Professional Association",
            "type":"Services"
        }
    ],
    "sg:phone":"+1 410 263 6378",
    "sg:postcode":"21401",
    "sg:province":"MD",
    "wof:name":"Cumberland Court Association",
    "wof:placetype":"venue"
},
  "geometry": {"coordinates":[-76.488128,38.980525],"type":"Point"}
}