{
  "type": "Feature",
  "properties": {
    "addr:full":"2101 Debra Lynn Way Accokeek MD 20607",
    "addr:housenumber":"2101",
    "addr:postcode":"20607",
    "addr:street":"Debra Lynn Way",
    "iso:country":"US",
    "sg:address":"2101 Debra Lynn Way",
    "sg:city":"Accokeek",
    "sg:classifiers":[
        {
            "category":"Professional",
            "subcategory":"Management & Consulting",
            "type":"Services"
        }
    ],
    "sg:phone":"+1 301 283 4155",
    "sg:postcode":"20607",
    "sg:province":"MD",
    "sg:tags":[
        "retail",
        "direct",
        "sales"
    ],
    "wof:name":"Quick Star",
    "wof:placetype":"venue"
},
  "geometry": {"coordinates":[-77.046857,38.639468],"type":"Point"}
}