{
  "type": "Feature",
  "properties": {
    "addr:full":"12 Woodgait Ct Reisterstown MD 21136",
    "addr:housenumber":"12",
    "addr:postcode":"21136",
    "addr:street":"Woodgait Ct",
    "iso:country":"US",
    "sg:address":"12 Woodgait Ct",
    "sg:city":"Reisterstown",
    "sg:classifiers":[
        {
            "category":"Professional",
            "subcategory":"Management & Consulting",
            "type":"Services"
        }
    ],
    "sg:phone":"+1 410 833 6468",
    "sg:postcode":"21136",
    "sg:province":"MD",
    "sg:tags":[
        "consultant"
    ],
    "sg:website":"www.woodgatepartners.com",
    "wof:name":"Woodgate Partners",
    "wof:placetype":"venue"
},
  "geometry": {"coordinates":[-76.86919399999999,39.433917],"type":"Point"}
}