{
  "type": "Feature",
  "properties": {
    "addr:full":"412 W 28th St Baltimore MD 21211",
    "addr:housenumber":"412",
    "addr:postcode":"21211",
    "addr:street":"W 28Th St",
    "iso:country":"US",
    "sg:address":"412 W 28th St",
    "sg:city":"Baltimore",
    "sg:classifiers":[
        {
            "category":"Organizations",
            "subcategory":"Community Association",
            "type":"Services"
        }
    ],
    "sg:phone":"+1 443 983 4654",
    "sg:postcode":"21211",
    "sg:province":"MD",
    "wof:name":"Rosetta's Family Unification Services Incorporation",
    "wof:placetype":"venue"
},
  "geometry": {"coordinates":[-76.6234,39.320305],"type":"Point"}
}