{
  "type": "Feature",
  "properties": {
    "addr:full":"4401 Salem Bottom Rd Westminster MD 21157",
    "addr:housenumber":"4401",
    "addr:postcode":"21157",
    "addr:street":"Salem Bottom Rd",
    "iso:country":"US",
    "sg:address":"4401 Salem Bottom Rd",
    "sg:city":"Westminster",
    "sg:classifiers":[
        {
            "category":"Social Services",
            "subcategory":"Child Care",
            "type":"Services"
        }
    ],
    "sg:phone":"+1 410 635 6985",
    "sg:postcode":"21157",
    "sg:province":"MD",
    "wof:name":"Tender Learning Care Inc",
    "wof:placetype":"venue"
},
  "geometry": {"coordinates":[-77.053985,39.456107],"type":"Point"}
}