{
  "type": "Feature",
  "properties": {
    "addr:full":"10203 Reisterstown Rd Owings Mills MD 21117",
    "addr:housenumber":"10203",
    "addr:postcode":"21117",
    "addr:street":"Reisterstown Rd",
    "iso:country":"US",
    "sg:address":"10203 Reisterstown Rd",
    "sg:city":"Owings Mills",
    "sg:classifiers":[
        {
            "category":"Health Services",
            "subcategory":"Optometrist",
            "type":"Services"
        }
    ],
    "sg:phone":"+1 410 356 3000",
    "sg:postcode":"21117",
    "sg:province":"MD",
    "wof:name":"Contact Lens Ctr",
    "wof:placetype":"venue"
},
  "geometry": {"coordinates":[-76.77437999999999,39.415587],"type":"Point"}
}