{
  "type": "Feature",
  "properties": {
    "iso:country":"US",
    "sg:address":"518 E 25th St",
    "sg:city":"Baltimore",
    "sg:classifiers":[
        {
            "category":"Autos & Motor Vehicles",
            "subcategory":"Auto Supplies",
            "type":"Retail Goods"
        }
    ],
    "sg:phone":"+1 410 554 9872",
    "sg:postcode":"21218",
    "sg:province":"MD",
    "sg:tags":[
        "wheel",
        "tire"
    ],
    "wof:name":"Diamond Tires",
    "wof:placetype":"venue"
},
  "geometry": {"coordinates":[-76.608521,39.318155],"type":"Point"}
}