{
  "type": "Feature",
  "properties": {
    "addr:full":"225 N Center St Westminster MD 21157",
    "addr:housenumber":"225",
    "addr:postcode":"21157",
    "addr:street":"N Center St",
    "iso:country":"US",
    "sg:address":"225 N Center St",
    "sg:city":"Westminster",
    "sg:classifiers":[
        {
            "category":"Government",
            "subcategory":"Office",
            "type":"Public Place"
        }
    ],
    "sg:phone":"+1 410 386 2980",
    "sg:postcode":"21157",
    "sg:province":"MD",
    "sg:tags":[
        "county",
        "planning",
        "dev"
    ],
    "wof:name":"Carroll County Zoning Office",
    "wof:placetype":"venue"
},
  "geometry": {"coordinates":[-76.986924,39.573569],"type":"Point"}
}