{
  "type": "Feature",
  "properties": {
    "addr:full":"5605 Kallan Ct Baltimore MD 21227",
    "addr:housenumber":"5605",
    "addr:postcode":"21227",
    "addr:street":"Kallan Ct",
    "iso:country":"US",
    "sg:address":"5605 Kallan Ct",
    "sg:city":"Baltimore",
    "sg:classifiers":[
        {
            "category":"Banks & Credit Unions",
            "subcategory":"Financial Services",
            "type":"Services"
        }
    ],
    "sg:phone":"+1 410 247 4320",
    "sg:postcode":"21227",
    "sg:province":"MD",
    "sg:tags":[
        "broker",
        "mortgage"
    ],
    "wof:name":"First National Mortgage",
    "wof:placetype":"venue"
},
  "geometry": {"coordinates":[-76.70518800000001,39.235949],"type":"Point"}
}