{
  "type": "Feature",
  "properties": {
    "iso:country":"US",
    "sg:address":"19520 Club House Rd",
    "sg:city":"Gaithersburg",
    "sg:classifiers":[
        {
            "category":"Insurance",
            "subcategory":"Insurance Agent",
            "type":"Services"
        }
    ],
    "sg:phone":"+1 301 948 6061",
    "sg:postcode":"20886",
    "sg:province":"MD",
    "wof:name":"State Farm Insurance",
    "wof:placetype":"venue"
},
  "geometry": {"coordinates":[-77.206968,39.17422],"type":"Point"}
}