{
  "type": "Feature",
  "properties": {
    "addr:full":"11279 New Hampshire Ave Silver Spring MD 20904",
    "addr:housenumber":"11279",
    "addr:postcode":"20904",
    "addr:street":"New Hampshire Ave",
    "iso:country":"US",
    "sg:address":"11279 New Hampshire Ave",
    "sg:city":"Silver Spring",
    "sg:classifiers":[
        {
            "category":"Restaurant",
            "type":"Food & Drink"
        }
    ],
    "sg:phone":"+1 301 592 8684",
    "sg:postcode":"20904",
    "sg:province":"MD",
    "wof:name":"Pansa Llena Mexican Grill",
    "wof:placetype":"venue"
},
  "geometry": {"coordinates":[-76.991759,39.043221],"type":"Point"}
}