{
  "type": "Feature",
  "properties": {
    "iso:country":"US",
    "sg:address":"1307 Noyes Dr",
    "sg:city":"Silver Spring",
    "sg:classifiers":[
        {
            "category":"Shopping",
            "subcategory":"Crafts & Fabrics",
            "type":"Retail Goods"
        }
    ],
    "sg:phone":"+1 301 585 7111",
    "sg:postcode":"20910",
    "sg:province":"MD",
    "sg:tags":[
        "sewing"
    ],
    "wof:name":"E V KIRK",
    "wof:placetype":"venue"
},
  "geometry": {"coordinates":[-77.034944,39.002504],"type":"Point"}
}