{
  "type": "Feature",
  "properties": {
    "addr:full":"801 Oaklawn Dr Forest Hill MD 21050",
    "addr:housenumber":"801",
    "addr:postcode":"21050",
    "addr:street":"Oaklawn Dr",
    "iso:country":"US",
    "sg:address":"801 Oaklawn Dr",
    "sg:city":"Forest Hill",
    "sg:classifiers":[
        {
            "category":"Personal",
            "type":"Services"
        }
    ],
    "sg:phone":"+1 410 879 1701",
    "sg:postcode":"21050",
    "sg:province":"MD",
    "sg:tags":[
        "help",
        "supply"
    ],
    "wof:name":"Synaptech Resources",
    "wof:placetype":"venue"
},
  "geometry": {"coordinates":[-76.38309,39.564733],"type":"Point"}
}