{
  "type": "Feature",
  "properties": {
    "addr:full":"725 N Wolfe St Baltimore MD 21205",
    "addr:housenumber":"725",
    "addr:postcode":"21205",
    "addr:street":"N Wolfe St",
    "iso:country":"US",
    "sg:address":"725 N Wolfe St",
    "sg:city":"Baltimore",
    "sg:classifiers":[
        {
            "category":"Professional",
            "subcategory":"Management & Consulting",
            "type":"Services"
        }
    ],
    "sg:phone":"+1 410 662 5770",
    "sg:postcode":"21205",
    "sg:province":"MD",
    "sg:tags":[
        "scientist"
    ],
    "wof:name":"Erika L Matunis",
    "wof:placetype":"venue"
},
  "geometry": {"coordinates":[-76.590853,39.299372],"type":"Point"}
}