{
  "type": "Feature",
  "properties": {
    "addr:full":"8555 Brad Ct Pasadena MD 21122",
    "addr:housenumber":"8555",
    "addr:postcode":"21122",
    "addr:street":"Brad Ct",
    "iso:country":"US",
    "sg:address":"8555 Brad Ct",
    "sg:city":"Pasadena",
    "sg:classifiers":[
        {
            "category":"Building & Trades",
            "subcategory":"Plumbing",
            "type":"Services"
        },
        {
            "category":"Building & Trades",
            "subcategory":"Cleaning & Sanitation",
            "type":"Services"
        }
    ],
    "sg:phone":"+1 410 437 9742",
    "sg:postcode":"21122",
    "sg:province":"MD",
    "sg:tags":[
        "plumber",
        "industrial",
        "septic",
        "supply",
        "tanks-treatment",
        "contractors-commercial"
    ],
    "wof:name":"Ace Septic Service",
    "wof:placetype":"venue"
},
  "geometry": {"coordinates":[-76.51416399999999,39.151503],"type":"Point"}
}