{
  "type": "Feature",
  "properties": {
    "addr:full":"4800 Seton Dr Baltimore MD 21215",
    "addr:housenumber":"4800",
    "addr:postcode":"21215",
    "addr:street":"Seton Dr",
    "iso:country":"US",
    "sg:address":"4800 Seton Dr",
    "sg:city":"Baltimore",
    "sg:classifiers":[
        {
            "category":"Health Services",
            "subcategory":"Nursing And Care Facility",
            "type":"Services"
        }
    ],
    "sg:phone":"+1 410 358 3410",
    "sg:postcode":"21215",
    "sg:province":"MD",
    "sg:tags":[
        "home",
        "convalescent"
    ],
    "wof:name":"Villa St Michael Nursing Ctr",
    "wof:placetype":"venue"
},
  "geometry": {"coordinates":[-76.706779,39.344071],"type":"Point"}
}