{
  "type": "Feature",
  "properties": {
    "addr:full":"1001 Riverside Dr Salisbury MD 21801",
    "addr:housenumber":"1001",
    "addr:postcode":"21801",
    "addr:street":"Riverside Dr",
    "iso:country":"US",
    "sg:address":"1001 Riverside Dr",
    "sg:city":"Salisbury",
    "sg:classifiers":[
        {
            "category":"Autos & Motor Vehicles",
            "subcategory":"Auto Supplies",
            "type":"Retail Goods"
        }
    ],
    "sg:phone":"+1 410 334 6145",
    "sg:postcode":"21801",
    "sg:province":"MD",
    "sg:tags":[
        "automobile",
        "part"
    ],
    "wof:name":"International Automotive",
    "wof:placetype":"venue"
},
  "geometry": {"coordinates":[-75.615578,38.352489],"type":"Point"}
}