{
  "type": "Feature",
  "properties": {
    "addr:full":"145 Main St Preston MD 21655",
    "addr:housenumber":"145",
    "addr:postcode":"21655",
    "addr:street":"Main St",
    "iso:country":"US",
    "sg:address":"145 Main St",
    "sg:city":"Preston",
    "sg:classifiers":[
        {
            "category":"Professional",
            "subcategory":"Accounting & Tax Preparation",
            "type":"Services"
        }
    ],
    "sg:phone":"+1 410 673 1384",
    "sg:postcode":"21655",
    "sg:province":"MD",
    "sg:tags":[
        "return",
        "preparation-business",
        "accountants-certified",
        "payroll",
        "bookkeeping",
        "public"
    ],
    "wof:name":"Accounting Strategies Group Llc",
    "wof:placetype":"venue"
},
  "geometry": {"coordinates":[-75.90973700000001,38.714161],"type":"Point"}
}