{
  "type": "Feature",
  "properties": {
    "iso:country":"US",
    "sg:address":"7943 Brock Bridge Rd",
    "sg:city":"Jessup",
    "sg:classifiers":[
        {
            "category":"Health Services",
            "subcategory":"Dentist",
            "type":"Services"
        }
    ],
    "sg:phone":"+1 410 799 5180",
    "sg:postcode":"20794",
    "sg:province":"MD",
    "sg:tags":[
        "dental",
        "clinic"
    ],
    "wof:name":"Mumby & Simmons Dental Consultants P C",
    "wof:placetype":"venue"
},
  "geometry": {"coordinates":[-76.775139,39.133369],"type":"Point"}
}