{
  "type": "Feature",
  "properties": {
    "addr:full":"5902 York Rd Baltimore MD 21212",
    "addr:housenumber":"5902",
    "addr:postcode":"21212",
    "addr:street":"York Rd",
    "iso:country":"US",
    "sg:address":"5902 York Rd",
    "sg:city":"Baltimore",
    "sg:classifiers":[
        {
            "category":"Shopping",
            "subcategory":"Thrift Store",
            "type":"Retail Goods"
        },
        {
            "category":"Banks & Credit Unions",
            "subcategory":"Bank",
            "type":"Services"
        },
        {
            "category":"Shopping",
            "subcategory":"Used Merchandise",
            "type":"Retail Goods"
        }
    ],
    "sg:phone":"+1 410 435 3244",
    "sg:postcode":"21212",
    "sg:province":"MD",
    "sg:tags":[
        "shop",
        "second",
        "resale",
        "hand"
    ],
    "sg:website":"http://www.jlbalt.org",
    "wof:name":"Wise Penny",
    "wof:placetype":"venue"
},
  "geometry": {"coordinates":[-76.60992299999999,39.364004],"type":"Point"}
}