{
  "type": "Feature",
  "properties": {
    "iso:country":"US",
    "sg:address":"6471 District Heights Pkwy",
    "sg:city":"District Heights",
    "sg:classifiers":[
        {
            "category":"Cinema",
            "subcategory":"Movie Rental",
            "type":"Entertainment"
        }
    ],
    "sg:phone":"+1 301 735 9878",
    "sg:postcode":"20747",
    "sg:province":"MD",
    "sg:tags":[
        "leasing",
        "video",
        "disc",
        "tape"
    ],
    "wof:name":"Video Warehouse",
    "wof:placetype":"venue"
},
  "geometry": {"coordinates":[-76.895332,38.858845],"type":"Point"}
}