{
  "type": "Feature",
  "properties": {
    "iso:country":"US",
    "sg:address":"728 Baltimore Pike",
    "sg:city":"Bel Air",
    "sg:classifiers":[
        {
            "category":"Retail",
            "subcategory":"Repair Shop",
            "type":"Services"
        }
    ],
    "sg:phone":"+1 410 893 8448",
    "sg:postcode":"21014",
    "sg:province":"MD",
    "sg:tags":[
        "player",
        "recorder",
        "video"
    ],
    "wof:name":"Video Tech Ctr",
    "wof:placetype":"venue"
},
  "geometry": {"coordinates":[-76.35847699999999,39.522447],"type":"Point"}
}