{
  "type": "Feature",
  "properties": {
    "addr:full":"5454 Wisconsin Ave Bethesda MD 20815",
    "addr:housenumber":"5454",
    "addr:postcode":"20815",
    "addr:street":"Wisconsin Ave",
    "iso:country":"US",
    "sg:address":"5454 Wisconsin Ave",
    "sg:city":"Bethesda",
    "sg:classifiers":[
        {
            "category":"Health Services",
            "subcategory":"Dentist",
            "type":"Services"
        }
    ],
    "sg:phone":"+1 301 654 1818",
    "sg:postcode":"20815",
    "sg:province":"MD",
    "sg:website":"www.advancedendo.com",
    "wof:name":"Menhinick Kim A",
    "wof:placetype":"venue"
},
  "geometry": {"coordinates":[-77.086912,38.962704],"type":"Point"}
}