{
  "type": "Feature",
  "properties": {
    "addr:full":"13007 Coastal Hwy Ocean City MD 21842",
    "addr:housenumber":"13007",
    "addr:postcode":"21842",
    "addr:street":"Coastal Hwy",
    "iso:country":"US",
    "sg:address":"13007 Coastal Hwy",
    "sg:city":"Ocean City",
    "sg:classifiers":[
        {
            "category":"Health Services",
            "subcategory":"Doctor",
            "type":"Services"
        }
    ],
    "sg:phone":"+1 410 250 9949",
    "sg:postcode":"21842",
    "sg:province":"MD",
    "sg:tags":[
        "clinic"
    ],
    "wof:name":"Bayside Medical 1",
    "wof:placetype":"venue"
},
  "geometry": {"coordinates":[-75.05429599999999,38.436382],"type":"Point"}
}