{
  "type": "Feature",
  "properties": {
    "addr:full":"2103 Greenspring Dr Lutherville MD 21093",
    "addr:housenumber":"2103",
    "addr:postcode":"21093",
    "addr:street":"Greenspring Dr",
    "iso:country":"US",
    "sg:address":"2103 Greenspring Dr",
    "sg:city":"Lutherville",
    "sg:classifiers":[
        {
            "category":"Manufacturing",
            "subcategory":"Signs",
            "type":"Manufacturing & Wholesale Goods"
        }
    ],
    "sg:phone":"+1 410 252 8235",
    "sg:postcode":"21093",
    "sg:province":"MD",
    "wof:name":"Signs By Tomorrow",
    "wof:placetype":"venue"
},
  "geometry": {"coordinates":[-76.63217899999999,39.440528],"type":"Point"}
}