{
  "type": "Feature",
  "properties": {
    "iso:country":"US",
    "sg:address":"3070 Leonardtown Rd",
    "sg:city":"Waldorf",
    "sg:classifiers":[
        {
            "category":"Banks & Credit Unions",
            "subcategory":"Bank",
            "type":"Services"
        },
        {
            "category":"Banks & Credit Unions",
            "subcategory":"Financial Services",
            "type":"Services"
        }
    ],
    "sg:phone":"+1 301 638 1201",
    "sg:postcode":"20601",
    "sg:province":"MD",
    "sg:tags":[
        "loan",
        "financing"
    ],
    "sg:website":"http://www.SunTrust.com",
    "wof:name":"SunTrust Bank - Waldorf",
    "wof:placetype":"venue"
},
  "geometry": {"coordinates":[-76.90939,38.625423],"type":"Point"}
}