{
  "type": "Feature",
  "properties": {
    "addr:full":"12100 Hidden Brook Ter Gaithersburg MD 20878",
    "addr:housenumber":"12100",
    "addr:postcode":"20878",
    "addr:street":"Hidden Brook Ter",
    "iso:country":"US",
    "sg:address":"12100 Hidden Brook Ter",
    "sg:city":"Gaithersburg",
    "sg:classifiers":[
        {
            "category":"Shopping",
            "subcategory":"Computers & Home Electronics",
            "type":"Retail Goods"
        }
    ],
    "sg:phone":"+1 301 869 6302",
    "sg:postcode":"20878",
    "sg:province":"MD",
    "wof:name":"Keith Gibby",
    "wof:placetype":"venue"
},
  "geometry": {"coordinates":[-77.25020499999999,39.099258],"type":"Point"}
}