{
  "type": "Feature",
  "properties": {
    "addr:full":"3601 Erma Ter Bowie MD 20716",
    "addr:housenumber":"3601",
    "addr:postcode":"20716",
    "addr:street":"Erma Ter",
    "iso:country":"US",
    "sg:address":"3601 Erma Ter",
    "sg:city":"Bowie",
    "sg:classifiers":[
        {
            "category":"Real Estate",
            "subcategory":"Real Estate Agent",
            "type":"Services"
        }
    ],
    "sg:phone":"+1 301 352 8908",
    "sg:postcode":"20716",
    "sg:province":"MD",
    "sg:tags":[
        "investor"
    ],
    "wof:name":"Mfiiv Unlimited LLC",
    "wof:placetype":"venue"
},
  "geometry": {"coordinates":[-76.72023,38.939201],"type":"Point"}
}