{
  "type": "Feature",
  "properties": {
    "iso:country":"US",
    "sg:address":"7315 Wisconsin Ave",
    "sg:city":"Bethesda",
    "sg:classifiers":[
        {
            "category":"Real Estate",
            "subcategory":"Real Estate Services",
            "type":"Services"
        }
    ],
    "sg:phone":"+1 301 968 2090",
    "sg:postcode":"20814",
    "sg:province":"MD",
    "sg:tags":[
        "management",
        "property"
    ],
    "sg:website":"www.hagner.com",
    "wof:name":"Hrj",
    "wof:placetype":"venue"
},
  "geometry": {"coordinates":[-77.093081,38.98262],"type":"Point"}
}