{
  "type": "Feature",
  "properties": {
    "iso:country":"US",
    "sg:address":"9301 Ardwick Ardmore Rd",
    "sg:city":"Springdale",
    "sg:classifiers":[
        {
            "category":"Education",
            "subcategory":"School",
            "type":"Public Place"
        }
    ],
    "sg:phone":"+1 301 925 1311",
    "sg:postcode":"20774",
    "sg:province":"MD",
    "wof:name":"Ardmore Elementary School",
    "wof:placetype":"venue"
},
  "geometry": {"coordinates":[-76.845584,38.93638],"type":"Point"}
}