{
  "type": "Feature",
  "properties": {
    "addr:full":"10 N Carroll St Thurmont MD 21788",
    "addr:housenumber":"10",
    "addr:postcode":"21788",
    "addr:street":"N Carroll St",
    "iso:country":"US",
    "sg:address":"10 N Carroll St",
    "sg:city":"Thurmont",
    "sg:classifiers":[
        {
            "category":"Wholesale",
            "subcategory":"Machinery & Supplies",
            "type":"Manufacturing & Wholesale Goods"
        }
    ],
    "sg:phone":"+1 301 271 7224",
    "sg:postcode":"21788",
    "sg:province":"MD",
    "sg:tags":[
        "valve"
    ],
    "wof:name":"Parker-Hannifin Corp",
    "wof:placetype":"venue"
},
  "geometry": {"coordinates":[-77.404623,39.625277],"type":"Point"}
}