{
  "type": "Feature",
  "properties": {
    "addr:full":"316 Crusader Rd Cambridge MD 21613",
    "addr:housenumber":"316",
    "addr:postcode":"21613",
    "addr:street":"Crusader Rd",
    "iso:country":"US",
    "sg:address":"316 Crusader Rd",
    "sg:city":"Cambridge",
    "sg:classifiers":[
        {
            "category":"Building & Trades",
            "subcategory":"Cleaning & Sanitation",
            "type":"Services"
        }
    ],
    "sg:phone":"+1 410 228 1074",
    "sg:postcode":"21613",
    "sg:province":"MD",
    "sg:tags":[
        "property",
        "maintenance"
    ],
    "wof:name":"Insignia Financial Group Inc",
    "wof:placetype":"venue"
},
  "geometry": {"coordinates":[-76.062252,38.565016],"type":"Point"}
}