{
  "type": "Feature",
  "properties": {
    "addr:full":"20 E Timonium Rd Lutherville MD 21093",
    "addr:housenumber":"20",
    "addr:postcode":"21093",
    "addr:street":"E Timonium Rd",
    "iso:country":"US",
    "sg:address":"20 E Timonium Rd",
    "sg:city":"Lutherville",
    "sg:classifiers":[
        {
            "category":"Banks & Credit Unions",
            "subcategory":"Investment Brokerage",
            "type":"Services"
        }
    ],
    "sg:phone":"+1 410 560 7170",
    "sg:postcode":"21093",
    "sg:province":"MD",
    "sg:tags":[
        "consultant",
        "planning",
        "financial"
    ],
    "wof:name":"Winer & Jones LLC",
    "wof:placetype":"venue"
},
  "geometry": {"coordinates":[-76.62446799999999,39.441691],"type":"Point"}
}