{
  "type": "Feature",
  "properties": {
    "iso:country":"US",
    "sg:address":"438 Snow Hill Rd",
    "sg:city":"Salisbury",
    "sg:classifiers":[
        {
            "category":"Wholesale",
            "subcategory":"Electrical",
            "type":"Manufacturing & Wholesale Goods"
        }
    ],
    "sg:phone":"+1 410 742 1185",
    "sg:postcode":"21804",
    "sg:province":"MD",
    "sg:tags":[
        "communication",
        "radio",
        "system"
    ],
    "sg:website":"www.caldabaugh.com",
    "wof:name":"Caldabaugh Communications Inc",
    "wof:placetype":"venue"
},
  "geometry": {"coordinates":[-75.588425,38.358475],"type":"Point"}
}