{
  "type": "Feature",
  "properties": {
    "iso:country":"US",
    "sg:address":"7434 Holabird Ave",
    "sg:city":"Dundalk",
    "sg:classifiers":[
        {
            "category":"Health Services",
            "subcategory":"Optometrist",
            "type":"Services"
        }
    ],
    "sg:phone":"+1 410 284 2273",
    "sg:postcode":"21222",
    "sg:province":"MD",
    "sg:tags":[
        "ophthalmologist"
    ],
    "wof:name":"Lerner Renee A MD",
    "wof:placetype":"venue"
},
  "geometry": {"coordinates":[-76.50949900000001,39.2715],"type":"Point"}
}