{
  "type": "Feature",
  "properties": {
    "iso:country":"US",
    "sg:address":"15 Minte Dr",
    "sg:city":"Nottingham",
    "sg:classifiers":[
        {
            "category":"Health Services",
            "subcategory":"Chiropractor",
            "type":"Services"
        }
    ],
    "sg:phone":"+1 410 529 1866",
    "sg:postcode":"21236",
    "sg:province":"MD",
    "sg:tags":[
        "chiropractic"
    ],
    "wof:name":"Nassirpour Chiropractic Pa",
    "wof:placetype":"venue"
},
  "geometry": {"coordinates":[-76.478874,39.401663],"type":"Point"}
}