{
  "type": "Feature",
  "properties": {
    "addr:full":"406 Hermleigh Rd Silver Spring MD 20902",
    "addr:housenumber":"406",
    "addr:postcode":"20902",
    "addr:street":"Hermleigh Rd",
    "iso:country":"US",
    "sg:address":"406 Hermleigh Rd",
    "sg:city":"Silver Spring",
    "sg:classifiers":[
        {
            "category":"Professional",
            "subcategory":"Management & Consulting",
            "type":"Services"
        }
    ],
    "sg:phone":"+1 301 681 3444",
    "sg:postcode":"20902",
    "sg:province":"MD",
    "sg:tags":[
        "construction"
    ],
    "wof:name":"Whitehead Associates Inc",
    "wof:placetype":"venue"
},
  "geometry": {"coordinates":[-77.01981600000001,39.050805],"type":"Point"}
}