{
  "type": "Feature",
  "properties": {
    "addr:full":"1107 N Point Blvd Ste 224 Baltimore MD 21224",
    "addr:housenumber":"1107",
    "addr:postcode":"21224",
    "addr:street":"N Point Blvd Ste 224",
    "iso:country":"US",
    "sg:address":"1107 N Point Blvd Ste 224",
    "sg:city":"Baltimore",
    "sg:classifiers":[
        {
            "category":"Health Services",
            "subcategory":"Doctor",
            "type":"Services"
        },
        {
            "category":"Health Services",
            "subcategory":"Dentist",
            "type":"Services"
        }
    ],
    "sg:phone":"+1 410 288 1900",
    "sg:postcode":"21224",
    "sg:province":"MD",
    "sg:tags":[
        "physician",
        "surgery",
        "surgeons",
        "oral"
    ],
    "wof:name":"Mitcherling Mitcherling",
    "wof:placetype":"venue"
},
  "geometry": {"coordinates":[-76.50732000000001,39.29061],"type":"Point"}
}