{
  "type": "Feature",
  "properties": {
    "addr:full":"2015 Rocky Point Rd Essex MD 21221",
    "addr:housenumber":"2015",
    "addr:postcode":"21221",
    "addr:street":"Rocky Point Rd",
    "iso:country":"US",
    "sg:address":"2015 Rocky Point Rd",
    "sg:city":"Essex",
    "sg:classifiers":[
        {
            "category":"Communications",
            "subcategory":"Film & Video Production",
            "type":"Services"
        }
    ],
    "sg:phone":"+1 410 686 0867",
    "sg:postcode":"21221",
    "sg:province":"MD",
    "sg:tags":[
        "companies-film",
        "tv",
        "dvd",
        "services-commercial",
        "duplicating",
        "cd",
        "radio",
        "cassette"
    ],
    "sg:website":"http://www.esm1941.com",
    "wof:name":"First Class Video Products Inc",
    "wof:placetype":"venue"
},
  "geometry": {"coordinates":[-76.407599,39.257008],"type":"Point"}
}