{
  "type": "Feature",
  "properties": {
    "addr:city":"Frederick",
    "addr:full":"1110 Rosemont Ave Frederick, Md 21701-4127",
    "addr:house_number":"1110",
    "addr:housenumber":"1110",
    "addr:phone":"+1 301-663-3885",
    "addr:postcode":"21701-4127",
    "addr:road":"Rosemont Ave",
    "addr:state":"MD",
    "addr:street":"Rosemont Ave",
    "iso:country":"US",
    "sg:address":"1110 Rosemont Ave",
    "sg:city":"Frederick",
    "sg:classifiers":[
        {
            "category":"Professional",
            "type":"Services"
        }
    ],
    "sg:phone":"+1 301 668 6088",
    "sg:postcode":"21701",
    "sg:province":"MD",
    "sg:tags":[
        "writer"
    ],
    "wof:airports":[
        102530753
    ],
    "wof:name":"Frederick County Landmarks Foundation",
    "wof:placetype":"venue"
},
  "geometry": {"coordinates":[-77.42645,39.42381],"type":"Point"}
}