{
  "type": "Feature",
  "properties": {
    "addr:full":"1110 Rosemont Ave Frederick MD 21701",
    "addr:housenumber":"1110",
    "addr:postcode":"21701",
    "addr:street":"Rosemont Ave",
    "iso:country":"US",
    "sg:address":"1110 Rosemont Ave",
    "sg:city":"Frederick",
    "sg:classifiers":[
        {
            "category":"Professional",
            "type":"Services"
        }
    ],
    "sg:phone":"+1 301 668 6088",
    "sg:postcode":"21701",
    "sg:province":"MD",
    "sg:tags":[
        "writer"
    ],
    "wof:name":"Frederick County Landmark",
    "wof:placetype":"venue"
},
  "geometry": {"coordinates":[-77.426655,39.423961],"type":"Point"}
}