{
  "type": "Feature",
  "properties": {
    "addr:full":"5911 14th Pl Hyattsville MD 20782",
    "addr:housenumber":"5911",
    "addr:postcode":"20782",
    "addr:street":"14Th Pl",
    "iso:country":"US",
    "sg:address":"5911 14th Pl",
    "sg:city":"Hyattsville",
    "sg:classifiers":[
        {
            "category":"Professional",
            "subcategory":"Secretarial Services",
            "type":"Services"
        }
    ],
    "sg:phone":"+1 301 559 3911",
    "sg:postcode":"20782",
    "sg:province":"MD",
    "sg:tags":[
        "reporting"
    ],
    "wof:name":"Theresa Wilcox",
    "wof:placetype":"venue"
},
  "geometry": {"coordinates":[-76.983833,38.962276],"type":"Point"}
}