{
  "type": "Feature",
  "properties": {
    "iso:country":"US",
    "sg:address":"2110 Herring Way",
    "sg:city":"Saint Leonard",
    "sg:classifiers":[
        {
            "category":"Autos & Motor Vehicles",
            "subcategory":"Boat Sales",
            "type":"Retail Goods"
        }
    ],
    "sg:phone":"+1 410 586 1076",
    "sg:postcode":"20685",
    "sg:province":"MD",
    "wof:name":"Saint Leonard Yacht Sales",
    "wof:placetype":"venue"
},
  "geometry": {"coordinates":[-76.4948,38.40248],"type":"Point"}
}