{
  "type": "Feature",
  "properties": {
    "addr:full":"13135 Hidden Acres Ln Bishopville MD 21813",
    "addr:housenumber":"13135",
    "addr:postcode":"21813",
    "addr:street":"Hidden Acres Ln",
    "iso:country":"US",
    "sg:address":"13135 Hidden Acres Ln",
    "sg:city":"Bishopville",
    "sg:classifiers":[
        {
            "category":"Farming",
            "subcategory":"Farm",
            "type":"Manufacturing & Wholesale Goods"
        }
    ],
    "sg:phone":"+1 410 352 3602",
    "sg:postcode":"21813",
    "sg:province":"MD",
    "wof:name":"Jacobs Farm, Inc.",
    "wof:placetype":"venue"
},
  "geometry": {"coordinates":[-75.241792,38.446472],"type":"Point"}
}