{
  "type": "Feature",
  "properties": {
    "addr:full":"2314 Bel Air Rd Fallston MD 21047",
    "addr:housenumber":"2314",
    "addr:postcode":"21047",
    "addr:street":"Bel Air Rd",
    "iso:country":"US",
    "sg:address":"2314 Bel Air Rd",
    "sg:city":"Fallston",
    "sg:phone":"+1 410 877 8334",
    "sg:postcode":"21047",
    "sg:province":"MD",
    "wof:name":"Fallston Diner",
    "wof:placetype":"venue"
},
  "geometry": {"coordinates":[-76.392163,39.493825],"type":"Point"}
}