{
  "type": "Feature",
  "properties": {
    "iso:country":"US",
    "sg:address":"11409 Woodington Ter",
    "sg:city":"Potomac",
    "sg:classifiers":[
        {
            "category":"Health Services",
            "subcategory":"Doctor",
            "type":"Services"
        }
    ],
    "sg:phone":"+1 301 897 8979",
    "sg:postcode":"20854",
    "sg:province":"MD",
    "sg:tags":[
        "physician",
        "surgeon"
    ],
    "wof:name":"Kathryn S Kirwin MD",
    "wof:placetype":"venue"
},
  "geometry": {"coordinates":[-77.194271,39.042308],"type":"Point"}
}