{
  "type": "Feature",
  "properties": {
    "iso:country":"US",
    "sg:address":"111 Craigtown Rd",
    "sg:city":"Port Deposit",
    "sg:classifiers":[
        {
            "category":"Building & Trades",
            "subcategory":"Construction",
            "type":"Services"
        }
    ],
    "sg:phone":"+1 410 378 2442",
    "sg:postcode":"21904",
    "sg:province":"MD",
    "sg:tags":[
        "home",
        "improvement"
    ],
    "wof:name":"Grove Bros Roofing & Siding",
    "wof:placetype":"venue"
},
  "geometry": {"coordinates":[-76.071945,39.602758],"type":"Point"}
}