{
  "type": "Feature",
  "properties": {
    "iso:country":"US",
    "sg:address":"424 E Wesley Cir",
    "sg:city":"Denton",
    "sg:classifiers":[
        {
            "category":"Travel",
            "subcategory":"Campground",
            "type":"Entertainment"
        }
    ],
    "sg:phone":"+1 410 479 3361",
    "sg:postcode":"21629",
    "sg:province":"MD",
    "sg:tags":[
        "camp",
        "trailer"
    ],
    "wof:name":"Denton Wesleyan Camp",
    "wof:placetype":"venue"
},
  "geometry": {"coordinates":[-75.81027400000001,38.890262],"type":"Point"}
}