{
  "type": "Feature",
  "properties": {
    "iso:country":"US",
    "sg:address":"8716 Little Patuxent Ct",
    "sg:city":"Odenton",
    "sg:classifiers":[
        {
            "category":"Freight",
            "type":"Transportation"
        }
    ],
    "sg:phone":"+1 301 912 5000",
    "sg:postcode":"21113",
    "sg:province":"MD",
    "sg:tags":[
        "hauling",
        "trucking"
    ],
    "wof:name":"Dallas Mavis",
    "wof:placetype":"venue"
},
  "geometry": {"coordinates":[-76.72794,39.058668],"type":"Point"}
}