{
  "type": "Feature",
  "properties": {
    "iso:country":"US",
    "sg:address":"203 N Commerce St",
    "sg:city":"Centreville",
    "sg:classifiers":[
        {
            "category":"Professional",
            "subcategory":"Lawyer & Legal Services",
            "type":"Services"
        }
    ],
    "sg:phone":"+1 410 758 9841",
    "sg:postcode":"21617",
    "sg:province":"MD",
    "sg:tags":[
        "attorney"
    ],
    "wof:name":"Lynn Putman Law Office",
    "wof:placetype":"venue"
},
  "geometry": {"coordinates":[-76.063984,39.046097],"type":"Point"}
}