{
  "type": "Feature",
  "properties": {
    "iso:country":"US",
    "sg:address":"13501 Baltimore Ave",
    "sg:city":"Laurel",
    "sg:classifiers":[
        {
            "category":"Restaurant",
            "type":"Food & Drink"
        }
    ],
    "sg:phone":"+1 301 210 3642",
    "sg:postcode":"20707",
    "sg:province":"MD",
    "wof:name":"Contee Station",
    "wof:placetype":"venue"
},
  "geometry": {"coordinates":[-76.870598,39.074299],"type":"Point"}
}