{
  "type": "Feature",
  "properties": {
    "addr:full":"2918 Burtonhill Dr Kensington MD 20895",
    "addr:housenumber":"2918",
    "addr:postcode":"20895",
    "addr:street":"Burtonhill Dr",
    "iso:country":"US",
    "sg:address":"2918 Burtonhill Dr",
    "sg:city":"Kensington",
    "sg:classifiers":[
        {
            "category":"Communications",
            "subcategory":"Film & Video Production",
            "type":"Services"
        }
    ],
    "sg:phone":"+1 301 942 0517",
    "sg:postcode":"20895",
    "sg:province":"MD",
    "sg:tags":[
        "motion",
        "picture",
        "studio",
        "producer"
    ],
    "wof:name":"Rosenberg Productions Inc",
    "wof:placetype":"venue"
},
  "geometry": {"coordinates":[-77.06016700000001,39.034333],"type":"Point"}
}