{
  "type": "Feature",
  "properties": {
    "addr:full":"2806 Maryland Hwy Oakland MD 21550",
    "addr:housenumber":"2806",
    "addr:postcode":"21550",
    "addr:street":"Maryland Hwy",
    "iso:country":"US",
    "sg:address":"2806 Maryland Hwy",
    "sg:city":"Oakland",
    "sg:classifiers":[
        {
            "category":"Bars & Pubs",
            "type":"Food & Drink"
        }
    ],
    "sg:phone":"+1 301 334 3678",
    "sg:postcode":"21550",
    "sg:province":"MD",
    "wof:name":"Tillerman's Pub",
    "wof:placetype":"venue"
},
  "geometry": {"coordinates":[-79.353416,39.407739],"type":"Point"}
}