{
  "type": "Feature",
  "properties": {
    "addr:full":"555 Quince Orchard Rd Gaithersburg MD 20878",
    "addr:housenumber":"555",
    "addr:postcode":"20878",
    "addr:street":"Quince Orchard Rd",
    "iso:country":"US",
    "sg:address":"555 Quince Orchard Rd",
    "sg:city":"Gaithersburg",
    "sg:classifiers":[
        {
            "category":"Banks & Credit Unions",
            "subcategory":"Bank",
            "type":"Services"
        }
    ],
    "sg:phone":"+1 301 921 3500",
    "sg:postcode":"20878",
    "sg:province":"MD",
    "wof:name":"Mid-Atlantic FEDERAL Cu",
    "wof:placetype":"venue"
},
  "geometry": {"coordinates":[-77.220274,39.144514],"type":"Point"}
}