{
  "type": "Feature",
  "properties": {
    "addr:full":"3 Walker Ave Gaithersburg MD 20877",
    "addr:housenumber":"3",
    "addr:postcode":"20877",
    "addr:street":"Walker Ave",
    "iso:country":"US",
    "sg:address":"3 Walker Ave",
    "sg:city":"Gaithersburg",
    "sg:classifiers":[
        {
            "category":"Social Services",
            "type":"Services"
        }
    ],
    "sg:phone":"+1 301 869 8428",
    "sg:postcode":"20877",
    "sg:province":"MD",
    "sg:tags":[
        "counselor",
        "marriage",
        "family"
    ],
    "wof:name":"Interfaith Counseling Svc",
    "wof:placetype":"venue"
},
  "geometry": {"coordinates":[-77.19808,39.145936],"type":"Point"}
}