{
  "type": "Feature",
  "properties": {
    "addr:full":"788 Inclination Dr Westminster MD 21157",
    "addr:housenumber":"788",
    "addr:postcode":"21157",
    "addr:street":"Inclination Dr",
    "iso:country":"US",
    "sg:address":"788 Inclination Dr",
    "sg:city":"Westminster",
    "sg:classifiers":[
        {
            "category":"Shopping",
            "subcategory":"Discount & Variety Stores",
            "type":"Retail Goods"
        }
    ],
    "sg:phone":"+1 410 871 1730",
    "sg:postcode":"21157",
    "sg:province":"MD",
    "sg:tags":[
        "merchandise",
        "general"
    ],
    "wof:name":"Sharper Image",
    "wof:placetype":"venue"
},
  "geometry": {"coordinates":[-77.022026,39.5541],"type":"Point"}
}