{
  "type": "Feature",
  "properties": {
    "addr:full":"2007 Campbell Dr Suitland MD 20746",
    "addr:housenumber":"2007",
    "addr:postcode":"20746",
    "addr:street":"Campbell Dr",
    "iso:country":"US",
    "sg:address":"2007 Campbell Dr",
    "sg:city":"Suitland",
    "sg:classifiers":[
        {
            "category":"Personal",
            "subcategory":"Barber",
            "type":"Services"
        }
    ],
    "sg:phone":"+1 301 856 5949",
    "sg:postcode":"20746",
    "sg:province":"MD",
    "wof:name":"Ivan's Barber & Beauty Salon",
    "wof:placetype":"venue"
},
  "geometry": {"coordinates":[-76.924845,38.861066],"type":"Point"}
}