{
  "type": "Feature",
  "properties": {
    "iso:country":"US",
    "sg:address":"3301 Boston St, Ste 200",
    "sg:city":"Baltimore",
    "sg:classifiers":[
        {
            "category":"Real Estate",
            "subcategory":"Real Estate Services",
            "type":"Services"
        }
    ],
    "sg:phone":"+1 410 342 4444",
    "sg:postcode":"21224",
    "sg:province":"MD",
    "sg:website":"timhodgin.com",
    "wof:name":"Keller Williams",
    "wof:placetype":"venue"
},
  "geometry": {"coordinates":[-76.568839,39.276828],"type":"Point"}
}