{
  "type": "Feature",
  "properties": {
    "iso:country":"US",
    "sg:address":"6113 Elaine Dr",
    "sg:city":"Jefferson",
    "sg:classifiers":[
        {
            "category":"Shopping",
            "subcategory":"Used Merchandise",
            "type":"Retail Goods"
        }
    ],
    "sg:phone":"+1 301 371 4437",
    "sg:postcode":"21755",
    "sg:province":"MD",
    "wof:name":"Springhouse Antiques",
    "wof:placetype":"venue"
},
  "geometry": {"coordinates":[-77.512566,39.402516],"type":"Point"}
}