{
  "type": "Feature",
  "properties": {
    "iso:country":"US",
    "sg:address":"7665 Investment Ct",
    "sg:city":"Owings",
    "sg:classifiers":[
        {
            "category":"Building & Trades",
            "subcategory":"Construction",
            "type":"Services"
        }
    ],
    "sg:phone":"+1 410 257 9077",
    "sg:postcode":"20736",
    "sg:province":"MD",
    "sg:tags":[
        "tile",
        "dealer"
    ],
    "wof:name":"Designs By Golden",
    "wof:placetype":"venue"
},
  "geometry": {"coordinates":[-76.612284,38.68572],"type":"Point"}
}