{
  "type": "Feature",
  "properties": {
    "addr:full":"2300 N Salisbury Blvd C109 Salisbury MD 21801",
    "addr:housenumber":"2300;c109",
    "addr:postcode":"21801",
    "addr:street":"N Salisbury Blvd",
    "iso:country":"US",
    "sg:address":"2300 N Salisbury Blvd C109",
    "sg:city":"Salisbury",
    "sg:classifiers":[
        {
            "category":"Retail",
            "subcategory":"Portrait Studio",
            "type":"Services"
        },
        {
            "category":"Professional",
            "subcategory":"Art Services",
            "type":"Services"
        }
    ],
    "sg:phone":"+1 410 546 9220",
    "sg:postcode":"21801",
    "sg:province":"MD",
    "sg:tags":[
        "rental",
        "photographers-portrait",
        "photographic",
        "darkroom"
    ],
    "sg:website":"http://www.picturepeople.com",
    "wof:name":"The Picture People Inc",
    "wof:placetype":"venue"
},
  "geometry": {"coordinates":[-75.56420900000001,38.40086],"type":"Point"}
}