{
  "type": "Feature",
  "properties": {
    "iso:country":"US",
    "sg:address":"10123 Hammond Rd",
    "sg:city":"Bishopville",
    "sg:classifiers":[
        {
            "category":"Home & Garden",
            "subcategory":"Building Materials",
            "type":"Retail Goods"
        },
        {
            "category":"Building & Trades",
            "subcategory":"Construction",
            "type":"Services"
        }
    ],
    "sg:phone":"+1 410 352 3882",
    "sg:postcode":"21813",
    "sg:province":"MD",
    "sg:tags":[
        "industrial",
        "specialty",
        "altering",
        "improvement",
        "heating",
        "system",
        "contractors-commercial",
        "contractor",
        "remodeling",
        "air conditioning"
    ],
    "wof:name":"Artistic Renovations",
    "wof:placetype":"venue"
},
  "geometry": {"coordinates":[-75.216217,38.442339],"type":"Point"}
}