{
  "type": "Feature",
  "properties": {
    "addr:full":"1038 W Chesapeake Beach Rd Owings MD 20736",
    "addr:housenumber":"1038",
    "addr:postcode":"20736",
    "addr:street":"W Chesapeake Beach Rd",
    "iso:country":"US",
    "sg:address":"1038 W Chesapeake Beach Rd",
    "sg:city":"Owings",
    "sg:classifiers":[
        {
            "category":"Manufacturing",
            "subcategory":"Building Materials",
            "type":"Manufacturing & Wholesale Goods"
        }
    ],
    "sg:phone":"+1 410 257 3400",
    "sg:postcode":"20736",
    "sg:province":"MD",
    "sg:tags":[
        "truss"
    ],
    "sg:website":"www.dunkirksupply.com",
    "wof:name":"Dunkirk Truss & Supply Inc",
    "wof:placetype":"venue"
},
  "geometry": {"coordinates":[-76.628013,38.739018],"type":"Point"}
}