{
  "type": "Feature",
  "properties": {
    "addr:full":"447 Chartley Park Rd Reisterstown MD 21136",
    "addr:housenumber":"447",
    "addr:postcode":"21136",
    "addr:street":"Chartley Park Rd",
    "iso:country":"US",
    "sg:address":"447 Chartley Park Rd",
    "sg:city":"Reisterstown",
    "sg:classifiers":[
        {
            "category":"Building & Trades",
            "subcategory":"Construction",
            "type":"Services"
        }
    ],
    "sg:phone":"+1 410 517 2143",
    "sg:postcode":"21136",
    "sg:province":"MD",
    "sg:tags":[
        "painter"
    ],
    "wof:name":"A B Painting Co",
    "wof:placetype":"venue"
},
  "geometry": {"coordinates":[-76.824361,39.459788],"type":"Point"}
}