{
  "type": "Feature",
  "properties": {
    "addr:full":"1204 Rosedale Ct Hyattsville MD 20782",
    "addr:housenumber":"1204",
    "addr:postcode":"20782",
    "addr:street":"Rosedale Ct",
    "iso:country":"US",
    "sg:address":"1204 Rosedale Ct",
    "sg:city":"Hyattsville",
    "sg:classifiers":[
        {
            "category":"Professional",
            "subcategory":"Business Services",
            "type":"Services"
        }
    ],
    "sg:phone":"+1 301 853 2465",
    "sg:postcode":"20782",
    "sg:province":"MD",
    "sg:tags":[
        "lecture",
        "bureau",
        "seminar"
    ],
    "wof:name":"Institute Of Karmic Guidance",
    "wof:placetype":"venue"
},
  "geometry": {"coordinates":[-76.98849,38.964028],"type":"Point"}
}