{
  "type": "Feature",
  "properties": {
    "iso:country":"US",
    "sg:address":"9117 Belair Rd",
    "sg:city":"Baltimore",
    "sg:classifiers":[
        {
            "category":"Restaurant",
            "type":"Food & Drink"
        }
    ],
    "sg:phone":"+1 410 256 3100",
    "sg:postcode":"21236",
    "sg:province":"MD",
    "wof:name":"Giorgio's Restaurant-Carryout",
    "wof:placetype":"venue"
},
  "geometry": {"coordinates":[-76.47831499999999,39.40031],"type":"Point"}
}