{
  "type": "Feature",
  "properties": {
    "iso:country":"US",
    "sg:address":"3548 Chiswick Ct",
    "sg:city":"Silver Spring",
    "sg:classifiers":[
        {
            "category":"Building & Trades",
            "subcategory":"Construction",
            "type":"Services"
        }
    ],
    "sg:phone":"+1 301 598 4079",
    "sg:postcode":"20906",
    "sg:province":"MD",
    "sg:tags":[
        "contractor"
    ],
    "wof:name":"Edward J Kennedy",
    "wof:placetype":"venue"
},
  "geometry": {"coordinates":[-77.068816,39.09807],"type":"Point"}
}