{
  "type": "Feature",
  "properties": {
    "iso:country":"US",
    "sg:address":"4795 Huron Ave",
    "sg:city":"Suitland",
    "sg:classifiers":[
        {
            "category":"Health Services",
            "subcategory":"Hospital",
            "type":"Services"
        }
    ],
    "sg:phone":"+1 301 735 6450",
    "sg:postcode":"20746",
    "sg:province":"MD",
    "sg:tags":[
        "mental"
    ],
    "wof:name":"Vesta Three",
    "wof:placetype":"venue"
},
  "geometry": {"coordinates":[-76.923338,38.85163],"type":"Point"}
}