{
  "type": "Feature",
  "properties": {
    "iso:country":"US",
    "sg:address":"50 W Deer Park Rd 303",
    "sg:city":"Gaithersburg",
    "sg:classifiers":[
        {
            "category":"Building & Trades",
            "subcategory":"Landscaping Services",
            "type":"Services"
        }
    ],
    "sg:phone":"+1 301 977 7476",
    "sg:postcode":"20877",
    "sg:province":"MD",
    "sg:tags":[
        "landscape",
        "contractor"
    ],
    "wof:name":"Montoya Green Landscape",
    "wof:placetype":"venue"
},
  "geometry": {"coordinates":[-77.192261,39.12907],"type":"Point"}
}