{
  "type": "Feature",
  "properties": {
    "iso:country":"US",
    "sg:address":"8109 Ritchie Hwy",
    "sg:city":"Pasadena",
    "sg:classifiers":[
        {
            "category":"Health Services",
            "subcategory":"Podiatrist",
            "type":"Services"
        }
    ],
    "sg:phone":"+1 410 590 8811",
    "sg:postcode":"21122",
    "sg:province":"MD",
    "sg:tags":[
        "physician",
        "surgeons"
    ],
    "wof:name":"Larry M Bernhard",
    "wof:placetype":"venue"
},
  "geometry": {"coordinates":[-76.589022,39.125538],"type":"Point"}
}