{
  "type": "Feature",
  "properties": {
    "addr:full":"7910 Woodmont Ave Bethesda MD 20814",
    "addr:housenumber":"7910",
    "addr:postcode":"20814",
    "addr:street":"Woodmont Ave",
    "iso:country":"US",
    "sg:address":"7910 Woodmont Ave",
    "sg:city":"Bethesda",
    "sg:classifiers":[
        {
            "category":"Professional",
            "subcategory":"Management & Consulting",
            "type":"Services"
        }
    ],
    "sg:phone":"+1 301 657 1441",
    "sg:postcode":"20814",
    "sg:province":"MD",
    "sg:tags":[
        "consultant"
    ],
    "wof:name":"Imi Svc USA",
    "wof:placetype":"venue"
},
  "geometry": {"coordinates":[-77.096469,38.989745],"type":"Point"}
}