{
  "type": "Feature",
  "properties": {
    "iso:country":"US",
    "sg:address":"7532 Westlake Ter",
    "sg:city":"Bethesda",
    "sg:classifiers":[
        {
            "category":"Professional",
            "subcategory":"Lawyer & Legal Services",
            "type":"Services"
        }
    ],
    "sg:phone":"+1 301 469 6546",
    "sg:postcode":"20817",
    "sg:province":"MD",
    "wof:name":"Laplaca M Michael",
    "wof:placetype":"venue"
},
  "geometry": {"coordinates":[-77.150597,39.027199],"type":"Point"}
}