{
  "type": "Feature",
  "properties": {
    "iso:country":"US",
    "sg:address":"10957 Crystal Falls Dr",
    "sg:city":"Hagerstown",
    "sg:classifiers":[
        {
            "category":"Building & Trades",
            "subcategory":"Landscaping Services",
            "type":"Services"
        }
    ],
    "sg:phone":"+1 301 797 7184",
    "sg:postcode":"21742",
    "sg:province":"MD",
    "wof:name":"Gold Leaf Lawn Service",
    "wof:placetype":"venue"
},
  "geometry": {"coordinates":[-77.59268,39.6143],"type":"Point"}
}