{
  "type": "Feature",
  "properties": {
    "iso:country":"US",
    "sg:address":"10801 Lockwood Dr",
    "sg:city":"Silver Spring",
    "sg:classifiers":[
        {
            "category":"Health Services",
            "subcategory":"Doctor",
            "type":"Services"
        }
    ],
    "sg:phone":"+1 301 593 5200",
    "sg:postcode":"20901",
    "sg:province":"MD",
    "sg:tags":[
        "throat",
        "ear",
        "nose"
    ],
    "wof:name":"Arenstein Michael H",
    "wof:placetype":"venue"
},
  "geometry": {"coordinates":[-77.00160200000001,39.033501],"type":"Point"}
}