{
  "type": "Feature",
  "properties": {
    "iso:country":"US",
    "sg:address":"2959 Kaycee Ln",
    "sg:city":"Windsor Mill",
    "sg:classifiers":[
        {
            "category":"Professional",
            "subcategory":"Employment Agencies",
            "type":"Services"
        }
    ],
    "sg:phone":"+1 410 265 5036",
    "sg:postcode":"21244",
    "sg:province":"MD",
    "wof:name":"Creative Options Inc",
    "wof:placetype":"venue"
},
  "geometry": {"coordinates":[-76.765462,39.333847],"type":"Point"}
}