{
  "type": "Feature",
  "properties": {
    "iso:country":"US",
    "sg:address":"7311 Brangles Rd",
    "sg:city":"Marriottsville",
    "sg:classifiers":[
        {
            "category":"Freight",
            "type":"Transportation"
        }
    ],
    "sg:phone":"+1 410 795 6006",
    "sg:postcode":"21104",
    "sg:province":"MD",
    "sg:tags":[
        "sand",
        "gravel",
        "hauling"
    ],
    "wof:name":"W E Craig Trucking",
    "wof:placetype":"venue"
},
  "geometry": {"coordinates":[-76.93198599999999,39.374038],"type":"Point"}
}