{
  "type": "Feature",
  "properties": {
    "addr:full":"3608 Roland Ave Baltimore MD 21211",
    "addr:housenumber":"3608",
    "addr:postcode":"21211",
    "addr:street":"Roland Ave",
    "iso:country":"US",
    "sg:address":"3608 Roland Ave",
    "sg:city":"Baltimore",
    "sg:classifiers":[
        {
            "category":"Building & Trades",
            "subcategory":"Landscaping Services",
            "type":"Services"
        }
    ],
    "sg:phone":"+1 410 338 0681",
    "sg:postcode":"21211",
    "sg:province":"MD",
    "sg:tags":[
        "landscape",
        "contractor"
    ],
    "wof:name":"Rich Landscaping & Design Inc",
    "wof:placetype":"venue"
},
  "geometry": {"coordinates":[-76.632859,39.332606],"type":"Point"}
}