{
  "type": "Feature",
  "properties": {
    "iso:country":"US",
    "sg:address":"8827 Columbia 100 Pkwy Ste 1A",
    "sg:city":"Columbia",
    "sg:classifiers":[
        {
            "category":"Social Services",
            "subcategory":"Child Care",
            "type":"Services"
        }
    ],
    "sg:phone":"+1 410 730 2229",
    "sg:postcode":"21045",
    "sg:province":"MD",
    "sg:tags":[
        "day"
    ],
    "wof:name":"A Choice Nanny",
    "wof:placetype":"venue"
},
  "geometry": {"coordinates":[-76.81529999999999,39.231098],"type":"Point"}
}