{
  "type": "Feature",
  "properties": {
    "addr:full":"2807 Armacost Ave Finksburg MD 21048",
    "addr:housenumber":"2807",
    "addr:postcode":"21048",
    "addr:street":"Armacost Ave",
    "iso:country":"US",
    "sg:address":"2807 Armacost Ave",
    "sg:city":"Finksburg",
    "sg:classifiers":[
        {
            "category":"Retail",
            "subcategory":"Portrait Studio",
            "type":"Services"
        },
        {
            "category":"Professional",
            "subcategory":"Art Services",
            "type":"Services"
        }
    ],
    "sg:phone":"+1 410 861 8025",
    "sg:postcode":"21048",
    "sg:province":"MD",
    "sg:tags":[
        "rental",
        "photographers-portrait",
        "photographic",
        "darkroom"
    ],
    "wof:name":"Doehrer Photography Inc",
    "wof:placetype":"venue"
},
  "geometry": {"coordinates":[-76.89724,39.50425],"type":"Point"}
}