{
  "type": "Feature",
  "properties": {
    "addr:full":"3544 Crain Hwy Bowie MD 20716",
    "addr:housenumber":"3544",
    "addr:postcode":"20716",
    "addr:street":"Crain Hwy",
    "iso:country":"US",
    "sg:address":"3544 Crain Hwy",
    "sg:city":"Bowie",
    "sg:classifiers":[
        {
            "category":"Restaurant",
            "type":"Food & Drink"
        }
    ],
    "sg:phone":"+1 301 352 4061",
    "sg:postcode":"20716",
    "sg:province":"MD",
    "wof:name":"New China Restaurant",
    "wof:placetype":"venue"
},
  "geometry": {"coordinates":[-76.718053,38.938584],"type":"Point"}
}