{
  "type": "Feature",
  "properties": {
    "iso:country":"US",
    "sg:address":"11220 Heron Pl",
    "sg:city":"Waldorf",
    "sg:classifiers":[
        {
            "category":"Utilities",
            "subcategory":"Telephone",
            "type":"Services"
        },
        {
            "category":"Building & Trades",
            "subcategory":"Construction",
            "type":"Services"
        }
    ],
    "sg:phone":"+1 301 705 5158",
    "sg:postcode":"20603",
    "sg:province":"MD",
    "sg:tags":[
        "communication",
        "line",
        "telecommunication"
    ],
    "wof:name":"Gap Communications Inc",
    "wof:placetype":"venue"
},
  "geometry": {"coordinates":[-76.923805,38.624857],"type":"Point"}
}