{
  "type": "Feature",
  "properties": {
    "addr:full":"23 Phillips Industrial Park Dr Cambridge MD 21613",
    "addr:housenumber":"23",
    "addr:postcode":"21613",
    "addr:street":"Phillips Industrial Park Dr",
    "iso:country":"US",
    "sg:address":"23 Phillips Industrial Park Dr",
    "sg:city":"Cambridge",
    "sg:classifiers":[
        {
            "category":"Building & Trades",
            "subcategory":"Construction",
            "type":"Services"
        },
        {
            "category":"Home & Garden",
            "subcategory":"Carpets & Floor Coverings",
            "type":"Retail Goods"
        }
    ],
    "sg:phone":"+1 410 228 8040",
    "sg:postcode":"21613",
    "sg:province":"MD",
    "sg:tags":[
        "marking",
        "asphalt",
        "contractor",
        "pavement",
        "paving",
        "sealcoating"
    ],
    "sg:website":"http://russellpavingco.com",
    "wof:name":"Russell Paving CO",
    "wof:placetype":"venue"
},
  "geometry": {"coordinates":[-76.06812600000001,38.558046],"type":"Point"}
}