{
  "type": "Feature",
  "properties": {
    "iso:country":"US",
    "sg:address":"400 N Bridge St",
    "sg:city":"Elkton",
    "sg:classifiers":[
        {
            "category":"Bars & Pubs",
            "type":"Food & Drink"
        }
    ],
    "sg:phone":"+1 410 392 0904",
    "sg:postcode":"21921",
    "sg:province":"MD",
    "wof:name":"4 Corners Tavern",
    "wof:placetype":"venue"
},
  "geometry": {"coordinates":[-75.836916,39.612493],"type":"Point"}
}