{
  "type": "Feature",
  "properties": {
    "addr:full":"1824 Clearwood Rd Baltimore MD 21234",
    "addr:housenumber":"1824",
    "addr:postcode":"21234",
    "addr:street":"Clearwood Rd",
    "iso:country":"US",
    "sg:address":"1824 Clearwood Rd",
    "sg:city":"Baltimore",
    "sg:classifiers":[
        {
            "category":"Building & Trades",
            "subcategory":"Construction",
            "type":"Services"
        }
    ],
    "sg:phone":"+1 410 663 9974",
    "sg:postcode":"21234",
    "sg:province":"MD",
    "sg:tags":[
        "carpentry",
        "contractor"
    ],
    "wof:name":"Kurowski Carpentry",
    "wof:placetype":"venue"
},
  "geometry": {"coordinates":[-76.553371,39.388135],"type":"Point"}
}