{
  "type": "Feature",
  "properties": {
    "iso:country":"US",
    "sg:address":"10015 Old Columbia Rd Ste E-245",
    "sg:city":"Columbia",
    "sg:classifiers":[
        {
            "category":"Health Services",
            "subcategory":"Chiropractor",
            "type":"Services"
        }
    ],
    "sg:phone":"+1 410 381 7246",
    "sg:postcode":"21046",
    "sg:province":"MD",
    "sg:website":"www.drcolquittchiro.com",
    "wof:name":"Chesapeake Family Wellness Center",
    "wof:placetype":"venue"
},
  "geometry": {"coordinates":[-76.86812399999999,39.176793],"type":"Point"}
}