{
  "type": "Feature",
  "properties": {
    "iso:country":"US",
    "sg:address":"1317 Market St",
    "sg:city":"Pocomoke City",
    "sg:classifiers":[
        {
            "category":"Restaurant",
            "type":"Food & Drink"
        }
    ],
    "sg:phone":"+1 410 957 9558",
    "sg:postcode":"21851",
    "sg:province":"MD",
    "wof:name":"Cafe LA Bella",
    "wof:placetype":"venue"
},
  "geometry": {"coordinates":[-75.554815,38.065851],"type":"Point"}
}