{
  "type": "Feature",
  "properties": {
    "iso:country":"US",
    "sg:address":"317 S Broadway",
    "sg:city":"Baltimore",
    "sg:classifiers":[
        {
            "category":"Place Of Worship",
            "subcategory":"Church",
            "type":"Public Place"
        },
        {
            "category":"Place Of Worship",
            "type":"Public Place"
        }
    ],
    "sg:phone":"+1 410 675 0640",
    "sg:postcode":"21231",
    "sg:province":"MD",
    "sg:tags":[
        "churches-catholic-traditional",
        "churches-catholic"
    ],
    "wof:name":"St Patricks Rectory",
    "wof:placetype":"venue"
},
  "geometry": {"coordinates":[-76.593507,39.287459],"type":"Point"}
}