{
  "type": "Feature",
  "properties": {
    "addr:full":"610 Professional Dr Gaithersburg MD 20879",
    "addr:housenumber":"610",
    "addr:postcode":"20879",
    "addr:street":"Professional Dr",
    "iso:country":"US",
    "sg:address":"610 Professional Dr",
    "sg:city":"Gaithersburg",
    "sg:classifiers":[
        {
            "category":"Professional",
            "subcategory":"Research",
            "type":"Services"
        }
    ],
    "sg:phone":"+1 240 364 6428",
    "sg:postcode":"20879",
    "sg:province":"MD",
    "sg:tags":[
        "information",
        "medical"
    ],
    "sg:website":"http://www.bridgecro.com",
    "wof:name":"Bridge Global Pharmaceutical Services, Inc.",
    "wof:placetype":"venue"
},
  "geometry": {"coordinates":[-77.228615,39.161931],"type":"Point"}
}