{
  "type": "Feature",
  "properties": {
    "addr:full":"5125 Cedgate Rd Baltimore MD 21206",
    "addr:housenumber":"5125",
    "addr:postcode":"21206",
    "addr:street":"Cedgate Rd",
    "iso:country":"US",
    "sg:address":"5125 Cedgate Rd",
    "sg:city":"Baltimore",
    "sg:classifiers":[
        {
            "category":"Manufacturing",
            "subcategory":"Glass & Minerals",
            "type":"Manufacturing & Wholesale Goods"
        }
    ],
    "sg:phone":"+1 410 483 7196",
    "sg:postcode":"21206",
    "sg:province":"MD",
    "wof:name":"Essential Elements Unisex Hair",
    "wof:placetype":"venue"
},
  "geometry": {"coordinates":[-76.531948,39.324117],"type":"Point"}
}