{
  "type": "Feature",
  "properties": {
    "iso:country":"US",
    "sg:address":"9603 Deereco Rd",
    "sg:city":"Timonium",
    "sg:classifiers":[
        {
            "category":"Wholesale",
            "subcategory":"Stationery",
            "type":"Manufacturing & Wholesale Goods"
        }
    ],
    "sg:phone":"+1 410 308 1437",
    "sg:postcode":"21093",
    "sg:province":"MD",
    "sg:tags":[
        "business",
        "form",
        "system"
    ],
    "wof:name":"Reynolds & Reynolds Co",
    "wof:placetype":"venue"
},
  "geometry": {"coordinates":[-76.640947,39.45404],"type":"Point"}
}