{
  "type": "Feature",
  "properties": {
    "iso:country":"US",
    "sg:address":"116 Cathedral St Suite B",
    "sg:city":"Annapolis",
    "sg:classifiers":[
        {
            "category":"Government",
            "subcategory":"Police Station",
            "type":"Public Place"
        },
        {
            "category":"Professional",
            "subcategory":"Lawyer & Legal Services",
            "type":"Services"
        }
    ],
    "sg:phone":"+1 888 268 5515",
    "sg:postcode":"21401",
    "sg:province":"MD",
    "sg:tags":[
        "attorney",
        "criminal",
        "duo",
        "damage",
        "accident",
        "traffic",
        "property",
        "dwi",
        "law"
    ],
    "sg:website":"http://www.dwi-law.com/",
    "wof:name":"The Law Office of Gill Cochran",
    "wof:placetype":"venue"
},
  "geometry": {"coordinates":[-76.49493,38.977722],"type":"Point"}
}