{
  "type": "Feature",
  "properties": {
    "addr:full":"214 S Morris St Oxford MD 21654",
    "addr:housenumber":"214",
    "addr:postcode":"21654",
    "addr:street":"S Morris St",
    "iso:country":"US",
    "sg:address":"214 S Morris St",
    "sg:city":"Oxford",
    "sg:classifiers":[
        {
            "category":"Banks & Credit Unions",
            "subcategory":"Investment Brokerage",
            "type":"Services"
        }
    ],
    "sg:phone":"+1 410 226 0505",
    "sg:postcode":"21654",
    "sg:province":"MD",
    "sg:tags":[
        "advisory",
        "financial"
    ],
    "wof:name":"Financial Strategy Group",
    "wof:placetype":"venue"
},
  "geometry": {"coordinates":[-76.17258,38.688427],"type":"Point"}
}