{
  "type": "Feature",
  "properties": {
    "iso:country":"US",
    "sg:address":"10715 Little Patuxent Pkwy",
    "sg:city":"Columbia",
    "sg:classifiers":[
        {
            "category":"Building & Trades",
            "subcategory":"Construction",
            "type":"Services"
        }
    ],
    "sg:phone":"+1 410 730 7020",
    "sg:postcode":"21044",
    "sg:province":"MD",
    "sg:tags":[
        "home",
        "builder"
    ],
    "wof:name":"Columbia Builders Inc",
    "wof:placetype":"venue"
},
  "geometry": {"coordinates":[-76.87928599999999,39.215974],"type":"Point"}
}