{
  "type": "Feature",
  "properties": {
    "addr:full":"1913 Lansdowne Rd Baltimore MD 21227",
    "addr:housenumber":"1913",
    "addr:postcode":"21227",
    "addr:street":"Lansdowne Rd",
    "iso:country":"US",
    "sg:address":"1913 Lansdowne Rd",
    "sg:city":"Baltimore",
    "sg:classifiers":[
        {
            "category":"Real Estate",
            "subcategory":"Real Estate Agent",
            "type":"Services"
        }
    ],
    "sg:phone":"+1 410 737 4900",
    "sg:postcode":"21227",
    "sg:province":"MD",
    "wof:name":"Millennium Realty",
    "wof:placetype":"venue"
},
  "geometry": {"coordinates":[-76.668318,39.253321],"type":"Point"}
}