{
  "type": "Feature",
  "properties": {
    "addr:full":"8811 60th Ave Berwyn Heights MD 20740",
    "addr:housenumber":"8811",
    "addr:postcode":"20740",
    "addr:street":"60Th Ave",
    "iso:country":"US",
    "sg:address":"8811 60th Ave",
    "sg:city":"Berwyn Heights",
    "sg:classifiers":[
        {
            "category":"Government",
            "subcategory":"Fire Station",
            "type":"Public Place"
        }
    ],
    "sg:phone":"+1 301 474 7866",
    "sg:postcode":"20740",
    "sg:province":"MD",
    "sg:tags":[
        "department",
        "protection"
    ],
    "sg:website":"www.bhvfd14.org",
    "wof:name":"Berwyn Heights Fire Dept",
    "wof:placetype":"venue"
},
  "geometry": {"coordinates":[-76.91161,38.995916],"type":"Point"}
}