{
  "type": "Feature",
  "properties": {
    "addr:full":"6201 Pulaski Hwy Baltimore MD 21224",
    "addr:housenumber":"6201",
    "addr:postcode":"21224",
    "addr:street":"Pulaski Hwy",
    "iso:country":"US",
    "sg:address":"6201 Pulaski Hwy",
    "sg:city":"Baltimore",
    "sg:classifiers":[
        {
            "category":"Manufacturing",
            "subcategory":"Wood Products",
            "type":"Manufacturing & Wholesale Goods"
        }
    ],
    "sg:phone":"+1 410 631 7199",
    "sg:postcode":"21224",
    "sg:province":"MD",
    "sg:tags":[
        "pallet",
        "skid"
    ],
    "sg:website":"www.frankspallets.com",
    "wof:name":"Frank's Pallet Svc",
    "wof:placetype":"venue"
},
  "geometry": {"coordinates":[-76.541877,39.303826],"type":"Point"}
}