{
  "type": "Feature",
  "properties": {
    "iso:country":"US",
    "sg:address":"3207 W Strathmore Ave",
    "sg:city":"Baltimore",
    "sg:classifiers":[
        {
            "category":"Professional",
            "type":"Services"
        }
    ],
    "sg:phone":"+1 410 358 5807",
    "sg:postcode":"21215",
    "sg:province":"MD",
    "sg:tags":[
        "establishment"
    ],
    "wof:name":"Keels Bernard",
    "wof:placetype":"venue"
},
  "geometry": {"coordinates":[-76.690956,39.362618],"type":"Point"}
}