{
  "type": "Feature",
  "properties": {
    "iso:country":"US",
    "sg:address":"120 N Potomac St",
    "sg:city":"Hagerstown",
    "sg:classifiers":[
        {
            "category":"Professional",
            "subcategory":"Lawyer & Legal Services",
            "type":"Services"
        }
    ],
    "sg:phone":"+1 301 739 4700",
    "sg:postcode":"21740",
    "sg:province":"MD",
    "sg:tags":[
        "attorney"
    ],
    "wof:name":"Miller & Stone",
    "wof:placetype":"venue"
},
  "geometry": {"coordinates":[-77.718413,39.64428],"type":"Point"}
}