{
  "type": "Feature",
  "properties": {
    "iso:country":"US",
    "sg:address":"4808 Hamilton Ave Apt 2D",
    "sg:city":"Baltimore",
    "sg:classifiers":[
        {
            "category":"Real Estate",
            "subcategory":"Real Estate Operator",
            "type":"Services"
        }
    ],
    "sg:phone":"+1 410 325 1242",
    "sg:postcode":"21206",
    "sg:province":"MD",
    "sg:tags":[
        "apartment"
    ],
    "wof:name":"Hamilton Springs Apts",
    "wof:placetype":"venue"
},
  "geometry": {"coordinates":[-76.5364,39.336899],"type":"Point"}
}