{
  "type": "Feature",
  "properties": {
    "iso:country":"US",
    "sg:address":"7810 Philadelphia Rd",
    "sg:city":"Rosedale",
    "sg:classifiers":[
        {
            "category":"Real Estate",
            "subcategory":"Real Estate Services",
            "type":"Services"
        },
        {
            "category":"Banks & Credit Unions",
            "subcategory":"Bank",
            "type":"Services"
        },
        {
            "category":"Banks & Credit Unions",
            "subcategory":"Financial Services",
            "type":"Services"
        }
    ],
    "sg:phone":"+1 410 866 3000",
    "sg:postcode":"21237",
    "sg:province":"MD",
    "sg:tags":[
        "loan",
        "processing",
        "broker",
        "mortgage"
    ],
    "sg:website":"www.rosedalefederal.com",
    "wof:name":"Rosedale Federal Savings & Loan Association",
    "wof:placetype":"venue"
},
  "geometry": {"coordinates":[-76.52010300000001,39.3172],"type":"Point"}
}