{
  "type": "Feature",
  "properties": {
    "addr:full":"307 Cedarcroft Rd Baltimore MD 21212",
    "addr:housenumber":"307",
    "addr:postcode":"21212",
    "addr:street":"Cedarcroft Rd",
    "iso:country":"US",
    "sg:address":"307 Cedarcroft Rd",
    "sg:city":"Baltimore",
    "sg:classifiers":[
        {
            "category":"Building & Trades",
            "subcategory":"Landscaping Services",
            "type":"Services"
        }
    ],
    "sg:phone":"+1 410 532 8650",
    "sg:postcode":"21212",
    "sg:province":"MD",
    "sg:tags":[
        "consultant",
        "designer",
        "landscape"
    ],
    "wof:name":"Zolna Environmental Design",
    "wof:placetype":"venue"
},
  "geometry": {"coordinates":[-76.61406700000001,39.368992],"type":"Point"}
}