{
  "type": "Feature",
  "properties": {
    "addr:full":"604 Gearing Ct E Millersville MD 21108",
    "addr:housenumber":"604",
    "addr:postcode":"21108",
    "addr:street":"Gearing Ct E",
    "iso:country":"US",
    "sg:address":"604 Gearing Ct E",
    "sg:city":"Millersville",
    "sg:classifiers":[
        {
            "category":"Restaurant",
            "type":"Food & Drink"
        }
    ],
    "sg:phone":"+1 410 987 8827",
    "sg:postcode":"21108",
    "sg:province":"MD",
    "sg:tags":[
        "eating"
    ],
    "wof:name":"Djs Hot Dogs",
    "wof:placetype":"venue"
},
  "geometry": {"coordinates":[-76.629068,39.112389],"type":"Point"}
}