{
  "type": "Feature",
  "properties": {
    "iso:country":"US",
    "sg:address":"17608 Bittinger Rd",
    "sg:city":"Grantsville",
    "sg:classifiers":[
        {
            "category":"Home & Garden",
            "subcategory":"Furniture",
            "type":"Retail Goods"
        }
    ],
    "sg:phone":"+1 301 895 3271",
    "sg:postcode":"21536",
    "sg:province":"MD",
    "sg:tags":[
        "equipment",
        "kitchen",
        "cabinet"
    ],
    "wof:name":"Casselman Lumber Do It Ctr",
    "wof:placetype":"venue"
},
  "geometry": {"coordinates":[-79.173001,39.674267],"type":"Point"}
}