{
  "type": "Feature",
  "properties": {
    "addr:full":"8850 Columbia 100 Pkwy # 204 Columbia MD 21045",
    "addr:housenumber":"8850",
    "addr:postcode":"21045",
    "addr:street":"Columbia 100 Pkwy # 204",
    "iso:country":"US",
    "sg:address":"8850 Columbia 100 Pkwy # 204",
    "sg:city":"Columbia",
    "sg:classifiers":[
        {
            "category":"Professional",
            "subcategory":"Management & Consulting",
            "type":"Services"
        },
        {
            "category":"Banks & Credit Unions",
            "subcategory":"Investment Brokerage",
            "type":"Services"
        },
        {
            "category":"Professional",
            "subcategory":"Lawyer & Legal Services",
            "type":"Services"
        },
        {
            "category":"Banks & Credit Unions",
            "subcategory":"Financial Services",
            "type":"Services"
        }
    ],
    "sg:phone":"+1 410 740 0220",
    "sg:postcode":"21045",
    "sg:province":"MD",
    "sg:tags":[
        "advisory",
        "financing",
        "planner",
        "estate",
        "consultant",
        "wills",
        "attorney",
        "planning",
        "trust"
    ],
    "wof:name":"Asset Williams Management",
    "wof:placetype":"venue"
},
  "geometry": {"coordinates":[-76.815336,39.23138],"type":"Point"}
}