{
  "type": "Feature",
  "properties": {
    "iso:country":"US",
    "sg:address":"7420 Village Rd",
    "sg:city":"Sykesville",
    "sg:classifiers":[
        {
            "category":"Real Estate",
            "subcategory":"Real Estate Operator",
            "type":"Services"
        }
    ],
    "sg:phone":"+1 410 781 6300",
    "sg:postcode":"21784",
    "sg:province":"MD",
    "sg:tags":[
        "apartment"
    ],
    "wof:name":"Sykesville Apartments",
    "wof:placetype":"venue"
},
  "geometry": {"coordinates":[-76.965359,39.368156],"type":"Point"}
}