{
  "type": "Feature",
  "properties": {
    "addr:full":"13005 Foxden Dr Rockville MD 20850",
    "addr:postcode":"13005;20850",
    "addr:street":"Foxden Dr",
    "iso:country":"US",
    "sg:address":"13005 Foxden Dr",
    "sg:city":"Rockville",
    "sg:classifiers":[
        {
            "category":"Real Estate",
            "subcategory":"Developer",
            "type":"Services"
        }
    ],
    "sg:phone":"+1 301 610 7400",
    "sg:postcode":"20850",
    "sg:province":"MD",
    "wof:name":"Med Inn Ctr Of America",
    "wof:placetype":"venue"
},
  "geometry": {"coordinates":[-77.190298,39.070388],"type":"Point"}
}