{
  "type": "Feature",
  "properties": {
    "addr:full":"11995 Frederick Rd Ellicott City MD 21042",
    "addr:housenumber":"11995",
    "addr:postcode":"21042",
    "addr:street":"Frederick Rd",
    "iso:country":"US",
    "sg:address":"11995 Frederick Rd",
    "sg:city":"Ellicott City",
    "sg:classifiers":[
        {
            "category":"Building & Trades",
            "subcategory":"Landscaping Services",
            "type":"Services"
        }
    ],
    "sg:phone":"+1 410 531 5101",
    "sg:postcode":"21042",
    "sg:province":"MD",
    "sg:tags":[
        "landscape"
    ],
    "wof:name":"Birches Ltd",
    "wof:placetype":"venue"
},
  "geometry": {"coordinates":[-76.92888600000001,39.296585],"type":"Point"}
}