{
  "type": "Feature",
  "properties": {
    "iso:country":"US",
    "sg:address":"9500 Coastal Hwy",
    "sg:city":"Ocean City",
    "sg:classifiers":[
        {
            "category":"Real Estate",
            "subcategory":"Real Estate Agent",
            "type":"Services"
        }
    ],
    "sg:phone":"+1 410 524 1400",
    "sg:postcode":"21842",
    "sg:province":"MD",
    "wof:name":"Coldwell Banker",
    "wof:placetype":"venue"
},
  "geometry": {"coordinates":[-75.058319,38.410216],"type":"Point"}
}