{
  "type": "Feature",
  "properties": {
    "addr:full":"1121 W Lanvale St Baltimore MD 21217",
    "addr:housenumber":"1121",
    "addr:postcode":"21217",
    "addr:street":"W Lanvale St",
    "iso:country":"US",
    "sg:address":"1121 W Lanvale St",
    "sg:city":"Baltimore",
    "sg:classifiers":[
        {
            "category":"Place Of Worship",
            "subcategory":"Church",
            "type":"Public Place"
        },
        {
            "category":"Place Of Worship",
            "type":"Public Place"
        },
        {
            "category":"Organizations",
            "subcategory":"Religious Organization",
            "type":"Services"
        }
    ],
    "sg:phone":"+1 410 523 1366",
    "sg:postcode":"21217",
    "sg:province":"MD",
    "sg:tags":[
        "churches-methodist"
    ],
    "wof:name":"Metropolitan United Methodist",
    "wof:placetype":"venue"
},
  "geometry": {"coordinates":[-76.636081,39.297948],"type":"Point"}
}