{
  "type": "Feature",
  "properties": {
    "iso:country":"US",
    "sg:address":"1488 Rockville Pike",
    "sg:city":"Rockville",
    "sg:classifiers":[
        {
            "category":"Home & Garden",
            "subcategory":"Building Materials",
            "type":"Retail Goods"
        }
    ],
    "sg:phone":"+1 301 468 8955",
    "sg:postcode":"20852",
    "sg:province":"MD",
    "wof:name":"Home Discount Floor Centers",
    "wof:placetype":"venue"
},
  "geometry": {"coordinates":[-77.12660200000001,39.065134],"type":"Point"}
}