{
  "type": "Feature",
  "properties": {
    "iso:country":"US",
    "sg:address":"6131 Hillen Rd",
    "sg:city":"Baltimore",
    "sg:classifiers":[
        {
            "category":"Professional",
            "subcategory":"Management & Consulting",
            "type":"Services"
        }
    ],
    "sg:phone":"+1 410 444 4933",
    "sg:postcode":"21239",
    "sg:province":"MD",
    "sg:tags":[
        "five",
        "manages",
        "golf",
        "municipal",
        "course"
    ],
    "wof:name":"Baltimore Municipal Golf Corp",
    "wof:placetype":"venue"
},
  "geometry": {"coordinates":[-76.579028,39.372091],"type":"Point"}
}