{
  "type": "Feature",
  "properties": {
    "iso:country":"US",
    "sg:address":"1018 White Marsh Rd",
    "sg:city":"Centreville",
    "sg:classifiers":[
        {
            "category":"Building & Trades",
            "subcategory":"Construction",
            "type":"Services"
        }
    ],
    "sg:phone":"+1 410 758 3099",
    "sg:postcode":"21617",
    "sg:province":"MD",
    "sg:tags":[
        "residential"
    ],
    "wof:name":"Ronald J Garner",
    "wof:placetype":"venue"
},
  "geometry": {"coordinates":[-75.989451,39.076433],"type":"Point"}
}