{
  "type": "Feature",
  "properties": {
    "addr:full":"6193 Central Ave Capitol Heights MD 20743",
    "addr:housenumber":"6193",
    "addr:postcode":"20743",
    "addr:street":"Central Ave",
    "iso:country":"US",
    "sg:address":"6193 Central Ave",
    "sg:city":"Capitol Heights",
    "sg:classifiers":[
        {
            "category":"Organizations",
            "subcategory":"Religious Organization",
            "type":"Services"
        }
    ],
    "sg:phone":"+1 301 350 3569",
    "sg:postcode":"20743",
    "sg:province":"MD",
    "wof:name":"Community Bible Baptist Church",
    "wof:placetype":"venue"
},
  "geometry": {"coordinates":[-76.90130499999999,38.886389],"type":"Point"}
}