{
  "type": "Feature",
  "properties": {
    "iso:country":"US",
    "sg:address":"1821 E West Hwy",
    "sg:city":"Hyattsville",
    "sg:classifiers":[
        {
            "category":"Personal",
            "subcategory":"Beauty Salon",
            "type":"Services"
        }
    ],
    "sg:phone":"+1 301 422 3933",
    "sg:postcode":"20783",
    "sg:province":"MD",
    "sg:tags":[
        "hair",
        "stylist"
    ],
    "wof:name":"His And Hers Hair Salon",
    "wof:placetype":"venue"
},
  "geometry": {"coordinates":[-76.98044899999999,38.972631],"type":"Point"}
}