{
  "type": "Feature",
  "properties": {
    "addr:full":"6944 Allentown Rd Temple Hills MD 20748",
    "addr:housenumber":"6944",
    "addr:postcode":"20748",
    "addr:street":"Allentown Rd",
    "iso:country":"US",
    "sg:address":"6944 Allentown Rd",
    "sg:city":"Temple Hills",
    "sg:classifiers":[
        {
            "category":"Professional",
            "subcategory":"Lawyer & Legal Services",
            "type":"Services"
        }
    ],
    "sg:phone":"+1 301 449 6200",
    "sg:postcode":"20748",
    "sg:province":"MD",
    "wof:name":"Darryl A Kelley & Associates",
    "wof:placetype":"venue"
},
  "geometry": {"coordinates":[-76.921255,38.792704],"type":"Point"}
}