{
  "type": "Feature",
  "properties": {
    "iso:country":"US",
    "sg:address":"7651 New Hampshire Ave",
    "sg:city":"Takoma Park",
    "sg:classifiers":[
        {
            "category":"Travel",
            "subcategory":"Travel Agent",
            "type":"Entertainment"
        }
    ],
    "sg:phone":"+1 301 439 5776",
    "sg:postcode":"20912",
    "sg:province":"MD",
    "sg:tags":[
        "agency",
        "bureau"
    ],
    "wof:name":"Moonlight Travel Inc",
    "wof:placetype":"venue"
},
  "geometry": {"coordinates":[-76.987923,38.986637],"type":"Point"}
}