{
  "type": "Feature",
  "properties": {
    "addr:full":"14200 Shoreham Dr Silver Spring MD 20905",
    "addr:housenumber":"14200",
    "addr:postcode":"20905",
    "addr:street":"Shoreham Dr",
    "iso:country":"US",
    "sg:address":"14200 Shoreham Dr",
    "sg:city":"Silver Spring",
    "sg:classifiers":[
        {
            "category":"Professional",
            "subcategory":"Business Services",
            "type":"Services"
        }
    ],
    "sg:phone":"+1 301 879 2520",
    "sg:postcode":"20905",
    "sg:province":"MD",
    "wof:name":"Morrison Enterprises",
    "wof:placetype":"venue"
},
  "geometry": {"coordinates":[-76.96965,39.09016],"type":"Point"}
}