{
  "type": "Feature",
  "properties": {
    "addr:full":"1311 Francis Ave Halethorpe MD 21227",
    "addr:housenumber":"1311",
    "addr:postcode":"21227",
    "addr:street":"Francis Ave",
    "iso:country":"US",
    "sg:address":"1311 Francis Ave",
    "sg:city":"Halethorpe",
    "sg:classifiers":[
        {
            "category":"Personal",
            "subcategory":"Beauty Salon",
            "type":"Services"
        }
    ],
    "sg:phone":"+1 410 247 0180",
    "sg:postcode":"21227",
    "sg:province":"MD",
    "sg:tags":[
        "nail",
        "manicuring"
    ],
    "wof:name":"A Total Image",
    "wof:placetype":"venue"
},
  "geometry": {"coordinates":[-76.69450399999999,39.238701],"type":"Point"}
}