{
  "type": "Feature",
  "properties": {
    "iso:country":"US",
    "sg:address":"7665 Investment Ct",
    "sg:city":"Owings",
    "sg:classifiers":[
        {
            "category":"Autos & Motor Vehicles",
            "subcategory":"Automobile Sales",
            "type":"Retail Goods"
        }
    ],
    "sg:phone":"+1 410 286 0899",
    "sg:postcode":"20736",
    "sg:province":"MD",
    "sg:tags":[
        "truck"
    ],
    "wof:name":"B & D Truck & Auto",
    "wof:placetype":"venue"
},
  "geometry": {"coordinates":[-76.612284,38.68572],"type":"Point"}
}