{
  "type": "Feature",
  "properties": {
    "iso:country":"US",
    "sg:address":"308 Reisterstown Rd",
    "sg:city":"Pikesville",
    "sg:classifiers":[
        {
            "category":"Personal",
            "subcategory":"Beauty Salon",
            "type":"Services"
        }
    ],
    "sg:phone":"+1 410 653 0341",
    "sg:postcode":"21208",
    "sg:province":"MD",
    "wof:name":"Estetica Nicki Inc",
    "wof:placetype":"venue"
},
  "geometry": {"coordinates":[-76.715099,39.366028],"type":"Point"}
}