{
  "type": "Feature",
  "properties": {
    "addr:full":"9828 Liberty Rd Randallstown MD 21133",
    "addr:housenumber":"9828",
    "addr:postcode":"21133",
    "addr:street":"Liberty Rd",
    "iso:country":"US",
    "sg:address":"9828 Liberty Rd",
    "sg:city":"Randallstown",
    "sg:classifiers":[
        {
            "category":"Restaurant",
            "type":"Food & Drink"
        }
    ],
    "sg:phone":"+1 410 655 5157",
    "sg:postcode":"21133",
    "sg:province":"MD",
    "sg:tags":[
        "delicatessen"
    ],
    "wof:name":"Old World Deli & Bakery",
    "wof:placetype":"venue"
},
  "geometry": {"coordinates":[-76.82131099999999,39.380306],"type":"Point"}
}