{
  "type": "Feature",
  "properties": {
    "iso:country":"US",
    "sg:address":"425 S Payson St",
    "sg:city":"Baltimore",
    "sg:classifiers":[
        {
            "category":"Food & Beverages",
            "subcategory":"Liquor & Beverages",
            "type":"Retail Goods"
        }
    ],
    "sg:phone":"+1 410 947 4500",
    "sg:postcode":"21223",
    "sg:province":"MD",
    "sg:tags":[
        "beer",
        "spirit",
        "wine"
    ],
    "wof:name":"Arisen Bar & Grill",
    "wof:placetype":"venue"
},
  "geometry": {"coordinates":[-76.648003,39.282398],"type":"Point"}
}