{
  "type": "Feature",
  "properties": {
    "addr:full":"13 E Diamond Ave Gaithersburg MD 20877",
    "addr:housenumber":"13",
    "addr:postcode":"20877",
    "addr:street":"E Diamond Ave",
    "iso:country":"US",
    "sg:address":"13 E Diamond Ave",
    "sg:city":"Gaithersburg",
    "sg:classifiers":[
        {
            "category":"Place Of Worship",
            "subcategory":"Church",
            "type":"Public Place"
        },
        {
            "category":"Arts & Performance",
            "subcategory":"Festival",
            "type":"Entertainment"
        },
        {
            "category":"Organizations",
            "subcategory":"Religious Organization",
            "type":"Services"
        }
    ],
    "sg:phone":"+1 240 477 3422",
    "sg:postcode":"20877",
    "sg:province":"MD",
    "sg:tags":[
        "christ",
        "god",
        "god-cleveland",
        "churches-church",
        "prophecy",
        "churches-christian"
    ],
    "wof:name":"Iglesia de Dios Hispana en Gaithersburg",
    "wof:placetype":"venue"
},
  "geometry": {"coordinates":[-77.19863700000001,39.14172],"type":"Point"}
}