{
  "type": "Feature",
  "properties": {
    "iso:country":"US",
    "sg:address":"714 W Lombard St",
    "sg:city":"Baltimore",
    "sg:classifiers":[
        {
            "category":"Health Services",
            "subcategory":"Doctor",
            "type":"Services"
        }
    ],
    "sg:phone":"+1 410 706 3490",
    "sg:postcode":"21201",
    "sg:province":"MD",
    "sg:tags":[
        "psychiatry",
        "physician",
        "surgeon",
        "surgeons"
    ],
    "wof:name":"Umb Ehs",
    "wof:placetype":"venue"
},
  "geometry": {"coordinates":[-76.626198,39.287313],"type":"Point"}
}