{
  "type": "Feature",
  "properties": {
    "iso:country":"US",
    "sg:address":"1208 Camden Ave",
    "sg:city":"Salisbury",
    "sg:classifiers":[
        {
            "category":"Shopping",
            "subcategory":"Used Merchandise",
            "type":"Retail Goods"
        }
    ],
    "sg:phone":"+1 410 548 1523",
    "sg:postcode":"21801",
    "sg:province":"MD",
    "wof:name":"Golden Century Antiques",
    "wof:placetype":"venue"
},
  "geometry": {"coordinates":[-75.608488,38.34661],"type":"Point"}
}