{
  "type": "Feature",
  "properties": {
    "addr:full":"3 W Church St Frederick MD 21701",
    "addr:housenumber":"3",
    "addr:postcode":"21701",
    "addr:street":"W Church St",
    "iso:country":"US",
    "sg:address":"3 W Church St",
    "sg:city":"Frederick",
    "sg:classifiers":[
        {
            "category":"Professional",
            "subcategory":"Art Services",
            "type":"Services"
        }
    ],
    "sg:phone":"+1 301 631 2401",
    "sg:postcode":"21701",
    "sg:province":"MD",
    "sg:tags":[
        "graphic",
        "designer"
    ],
    "wof:name":"Jean Peterson Design",
    "wof:placetype":"venue"
},
  "geometry": {"coordinates":[-77.41209499999999,39.415503],"type":"Point"}
}