{
  "type": "Feature",
  "properties": {
    "iso:country":"US",
    "sg:address":"5151 Wisconsin Ave NW",
    "sg:city":"Washington",
    "sg:classifiers":[
        {
            "category":"Arts & Performance",
            "subcategory":"Theater",
            "type":"Entertainment"
        }
    ],
    "sg:phone":"+1 202 895 3100",
    "sg:postcode":"20016",
    "sg:province":"MD",
    "sg:tags":[
        "television",
        "program",
        "producer"
    ],
    "wof:name":"STF Productions",
    "wof:placetype":"venue"
},
  "geometry": {"coordinates":[-77.083529,38.956506],"type":"Point"}
}