{
  "type": "Feature",
  "properties": {
    "iso:country":"US",
    "sg:address":"7900 Old Branch Ave",
    "sg:city":"Clinton",
    "sg:classifiers":[
        {
            "category":"Health Services",
            "subcategory":"Doctor",
            "type":"Services"
        }
    ],
    "sg:phone":"+1 301 856 1200",
    "sg:postcode":"20735",
    "sg:province":"MD",
    "sg:tags":[
        "dentist"
    ],
    "wof:name":"Maryland Periodontics",
    "wof:placetype":"venue"
},
  "geometry": {"coordinates":[-76.899082,38.780984],"type":"Point"}
}