{
  "type": "Feature",
  "properties": {
    "addr:full":"604 Quince Orchard Rd Gaithersburg MD 20878",
    "addr:housenumber":"604",
    "addr:postcode":"20878",
    "addr:street":"Quince Orchard Rd",
    "iso:country":"US",
    "sg:address":"604 Quince Orchard Rd",
    "sg:city":"Gaithersburg",
    "sg:classifiers":[
        {
            "category":"Professional",
            "type":"Services"
        }
    ],
    "sg:phone":"+1 301 990 3958",
    "sg:postcode":"20878",
    "sg:province":"MD",
    "sg:tags":[
        "establishment"
    ],
    "wof:name":"Circuit City",
    "wof:placetype":"venue"
},
  "geometry": {"coordinates":[-77.221566,39.140956],"type":"Point"}
}