{
  "type": "Feature",
  "properties": {
    "iso:country":"US",
    "sg:address":"10 Emala Ave",
    "sg:city":"Middle River",
    "sg:classifiers":[
        {
            "category":"Building & Trades",
            "subcategory":"Construction",
            "type":"Services"
        }
    ],
    "sg:phone":"+1 410 686 5900",
    "sg:postcode":"21220",
    "sg:province":"MD",
    "sg:tags":[
        "maker",
        "cabinet"
    ],
    "sg:website":"www.guenschel.com",
    "wof:name":"Guenschel Helmut Inc",
    "wof:placetype":"venue"
},
  "geometry": {"coordinates":[-76.413826,39.334551],"type":"Point"}
}