{
  "type": "Feature",
  "properties": {
    "iso:country":"US",
    "sg:address":"302 N Kent St",
    "sg:city":"Chestertown",
    "sg:classifiers":[
        {
            "category":"Recreation",
            "type":"Entertainment"
        }
    ],
    "sg:phone":"+1 410 810 2643",
    "sg:postcode":"21620",
    "sg:province":"MD",
    "sg:tags":[
        "camps-recreational"
    ],
    "wof:name":"Chesapeake Crew Camps",
    "wof:placetype":"venue"
},
  "geometry": {"coordinates":[-76.065603,39.213304],"type":"Point"}
}