{
  "type": "Feature",
  "properties": {
    "iso:country":"US",
    "sg:address":"6171 Shady Side Rd",
    "sg:city":"Shady Side",
    "sg:classifiers":[
        {
            "category":"Building & Trades",
            "subcategory":"Construction",
            "type":"Services"
        }
    ],
    "sg:phone":"+1 301 261 9019",
    "sg:postcode":"20764",
    "sg:province":"MD",
    "sg:tags":[
        "downspouts",
        "gutter"
    ],
    "wof:name":"Bradley Construction",
    "wof:placetype":"venue"
},
  "geometry": {"coordinates":[-76.513622,38.83408],"type":"Point"}
}