{
  "type": "Feature",
  "properties": {
    "iso:country":"US",
    "sg:address":"1985 Fields Rd",
    "sg:city":"Jessup",
    "sg:classifiers":[
        {
            "category":"Building & Trades",
            "subcategory":"Construction",
            "type":"Services"
        }
    ],
    "sg:phone":"+1 410 799 3478",
    "sg:postcode":"20794",
    "sg:province":"MD",
    "sg:tags":[
        "contractor"
    ],
    "wof:name":"Frank C. Fields & Sons",
    "wof:placetype":"venue"
},
  "geometry": {"coordinates":[-76.749466,39.141024],"type":"Point"}
}