{
  "type": "Feature",
  "properties": {
    "iso:country":"US",
    "sg:address":"3223 Greenmount Ave",
    "sg:city":"Baltimore",
    "sg:classifiers":[
        {
            "category":"Retail",
            "subcategory":"Laundry & Dry Cleaning",
            "type":"Services"
        }
    ],
    "sg:phone":"+1 410 467 5710",
    "sg:postcode":"21218",
    "sg:province":"MD",
    "sg:tags":[
        "cleaner"
    ],
    "wof:name":"Nifty Cleaners",
    "wof:placetype":"venue"
},
  "geometry": {"coordinates":[-76.609497,39.327801],"type":"Point"}
}