{
  "type": "Feature",
  "properties": {
    "iso:country":"US",
    "sg:address":"1401 Nicholson St",
    "sg:city":"Hyattsville",
    "sg:classifiers":[
        {
            "category":"Manufacturing",
            "subcategory":"Printing",
            "type":"Manufacturing & Wholesale Goods"
        }
    ],
    "sg:phone":"+1 301 853 3259",
    "sg:postcode":"20782",
    "sg:province":"MD",
    "sg:tags":[
        "publishing"
    ],
    "wof:name":"Ita Yetta Music",
    "wof:placetype":"venue"
},
  "geometry": {"coordinates":[-76.983146,38.962304],"type":"Point"}
}