{
  "type": "Feature",
  "properties": {
    "iso:country":"US",
    "sg:address":"8519 Rainswood Dr",
    "sg:city":"Hyattsville",
    "sg:classifiers":[
        {
            "category":"Wholesale",
            "subcategory":"Machinery & Supplies",
            "type":"Manufacturing & Wholesale Goods"
        }
    ],
    "sg:phone":"+1 301 341 7278",
    "sg:postcode":"20785",
    "sg:province":"MD",
    "sg:tags":[
        "marine",
        "electronic"
    ],
    "wof:name":"Marine Connection",
    "wof:placetype":"venue"
},
  "geometry": {"coordinates":[-76.858469,38.940928],"type":"Point"}
}