{
  "type": "Feature",
  "properties": {
    "addr:full":"2010 Clipper Park Rd Ste 126 Baltimore MD 21211",
    "addr:housenumber":"2010",
    "addr:postcode":"21211",
    "addr:street":"Clipper Park Rd Ste 126",
    "iso:country":"US",
    "sg:address":"2010 Clipper Park Rd Ste 126",
    "sg:city":"Baltimore",
    "sg:classifiers":[
        {
            "category":"Restaurant",
            "type":"Food & Drink"
        }
    ],
    "sg:phone":"+1 410 464 8000",
    "sg:postcode":"21211",
    "sg:province":"MD",
    "sg:website":"www.woodberrykitchen.com",
    "wof:name":"Woodberry Kitchen",
    "wof:placetype":"venue"
},
  "geometry": {"coordinates":[-76.644533,39.33189],"type":"Point"}
}