{
  "type": "Feature",
  "properties": {
    "addr:full":"7009 Burch Hill Rd Brandywine MD 20613",
    "addr:housenumber":"7009",
    "addr:postcode":"20613",
    "addr:street":"Burch Hill Rd",
    "iso:country":"US",
    "sg:address":"7009 Burch Hill Rd",
    "sg:city":"Brandywine",
    "sg:classifiers":[
        {
            "category":"Recreation",
            "type":"Entertainment"
        }
    ],
    "sg:phone":"+1 301 372 0750",
    "sg:postcode":"20613",
    "sg:province":"MD",
    "sg:tags":[
        "riding",
        "recreational",
        "academy"
    ],
    "wof:name":"Davis Equestrian Center",
    "wof:placetype":"venue"
},
  "geometry": {"coordinates":[-76.885661,38.725198],"type":"Point"}
}