{
  "type": "Feature",
  "properties": {
    "iso:country":"US",
    "sg:address":"3718 Basford Rd",
    "sg:city":"Frederick",
    "sg:classifiers":[
        {
            "category":"Building & Trades",
            "subcategory":"Construction",
            "type":"Services"
        }
    ],
    "sg:phone":"+1 301 694 3465",
    "sg:postcode":"21703",
    "sg:province":"MD",
    "sg:tags":[
        "maker",
        "cabinet"
    ],
    "wof:name":"Stockman Woodworks",
    "wof:placetype":"venue"
},
  "geometry": {"coordinates":[-77.510938,39.334087],"type":"Point"}
}