{
  "type": "Feature",
  "properties": {
    "iso:country":"US",
    "sg:address":"11 Warren Rd",
    "sg:city":"Pikesville",
    "sg:classifiers":[
        {
            "category":"Organizations",
            "subcategory":"Religious Organization",
            "type":"Services"
        }
    ],
    "sg:phone":"+1 410 484 4110",
    "sg:postcode":"21208",
    "sg:province":"MD",
    "sg:tags":[
        "synagogue"
    ],
    "wof:name":"Star-K Kosher",
    "wof:placetype":"venue"
},
  "geometry": {"coordinates":[-76.716398,39.367595],"type":"Point"}
}