{
  "type": "Feature",
  "properties": {
    "iso:country":"US",
    "sg:address":"400 W Lexington St",
    "sg:city":"Baltimore",
    "sg:classifiers":[
        {
            "category":"Building & Trades",
            "subcategory":"Locksmith",
            "type":"Services"
        }
    ],
    "sg:phone":"+1 410 528 1910",
    "sg:postcode":"21201",
    "sg:province":"MD",
    "sg:tags":[
        "key"
    ],
    "wof:name":"A 1 24 Hours Locksmith",
    "wof:placetype":"venue"
},
  "geometry": {"coordinates":[-76.621002,39.291401],"type":"Point"}
}