{
  "type": "Feature",
  "properties": {
    "addr:full":"8551 Indian Springs Rd Frederick MD 21702",
    "addr:housenumber":"8551",
    "addr:postcode":"21702",
    "addr:street":"Indian Springs Rd",
    "iso:country":"US",
    "sg:address":"8551 Indian Springs Rd",
    "sg:city":"Frederick",
    "sg:classifiers":[
        {
            "category":"Building & Trades",
            "subcategory":"Construction",
            "type":"Services"
        }
    ],
    "sg:phone":"+1 301 663 3831",
    "sg:postcode":"21702",
    "sg:province":"MD",
    "sg:tags":[
        "contractor"
    ],
    "wof:name":"Beachley Metal Art",
    "wof:placetype":"venue"
},
  "geometry": {"coordinates":[-77.46144700000001,39.466939],"type":"Point"}
}