{
  "type": "Feature",
  "properties": {
    "addr:full":"1551 Ashcroft Ln Arnold MD 21012",
    "addr:housenumber":"1551",
    "addr:postcode":"21012",
    "addr:street":"Ashcroft Ln",
    "iso:country":"US",
    "sg:address":"1551 Ashcroft Ln",
    "sg:city":"Arnold",
    "sg:classifiers":[
        {
            "category":"Real Estate",
            "subcategory":"Architect",
            "type":"Services"
        }
    ],
    "sg:phone":"+1 410 974 0744",
    "sg:postcode":"21012",
    "sg:province":"MD",
    "wof:name":"Overton Design Group Inc",
    "wof:placetype":"venue"
},
  "geometry": {"coordinates":[-76.501805,39.024369],"type":"Point"}
}