{
  "type": "Feature",
  "properties": {
    "iso:country":"US",
    "sg:address":"2417 E Monument St",
    "sg:city":"Baltimore",
    "sg:classifiers":[
        {
            "category":"Shopping",
            "subcategory":"Clothing, Apparel, & Fashions",
            "type":"Retail Goods"
        }
    ],
    "sg:phone":"+1 410 534 1296",
    "sg:postcode":"21205",
    "sg:province":"MD",
    "sg:tags":[
        "made",
        "service/non-profit",
        "community"
    ],
    "wof:name":"We Are One",
    "wof:placetype":"venue"
},
  "geometry": {"coordinates":[-76.583298,39.298901],"type":"Point"}
}