{
  "type": "Feature",
  "properties": {
    "iso:country":"US",
    "sg:address":"7125 Ambassador Rd",
    "sg:city":"Windsor Mill",
    "sg:classifiers":[
        {
            "category":"Professional",
            "type":"Services"
        }
    ],
    "sg:phone":"+1 443 436 7700",
    "sg:postcode":"21244",
    "sg:province":"MD",
    "sg:tags":[
        "establishment"
    ],
    "wof:name":"Us Gov't",
    "wof:placetype":"venue"
},
  "geometry": {"coordinates":[-76.74630500000001,39.326247],"type":"Point"}
}