{
  "type": "Feature",
  "properties": {
    "addr:full":"121 Hillsmere Dr Annapolis MD 21403",
    "addr:housenumber":"121",
    "addr:postcode":"21403",
    "addr:street":"Hillsmere Dr",
    "iso:country":"US",
    "sg:address":"121 Hillsmere Dr",
    "sg:city":"Annapolis",
    "sg:classifiers":[
        {
            "category":"Shopping",
            "subcategory":"Pharmacy",
            "type":"Retail Goods"
        }
    ],
    "sg:phone":"+1 410 268 5253",
    "sg:postcode":"21403",
    "sg:province":"MD",
    "sg:website":"www.cvs.com",
    "wof:name":"CVS Pharmacy",
    "wof:placetype":"venue"
},
  "geometry": {"coordinates":[-76.49343500000001,38.948247],"type":"Point"}
}