{
  "type": "Feature",
  "properties": {
    "iso:country":"US",
    "sg:address":"462 Honering Trl",
    "sg:city":"Annapolis",
    "sg:classifiers":[
        {
            "category":"Professional",
            "subcategory":"Management & Consulting",
            "type":"Services"
        }
    ],
    "sg:phone":"+1 410 849 2069",
    "sg:postcode":"21401",
    "sg:province":"MD",
    "sg:tags":[
        "business"
    ],
    "wof:name":"Printers Eye Inc",
    "wof:placetype":"venue"
},
  "geometry": {"coordinates":[-76.533355,39.009812],"type":"Point"}
}