{
  "type": "Feature",
  "properties": {
    "iso:country":"US",
    "sg:address":"10219 River Landing Rd",
    "sg:city":"Denton",
    "sg:classifiers":[
        {
            "category":"Museum",
            "type":"Entertainment"
        }
    ],
    "sg:phone":"+1 410 479 4950",
    "sg:postcode":"21629",
    "sg:province":"MD",
    "wof:name":"Old Harford Town Maritime Ctr",
    "wof:placetype":"venue"
},
  "geometry": {"coordinates":[-75.839637,38.888411],"type":"Point"}
}