{
  "type": "Feature",
  "properties": {
    "addr:full":"207 Robinson Ct Great Mills MD 20634",
    "addr:housenumber":"207",
    "addr:postcode":"20634",
    "addr:street":"Robinson Ct",
    "iso:country":"US",
    "sg:address":"207 Robinson Ct",
    "sg:city":"Great Mills",
    "sg:classifiers":[
        {
            "category":"Organizations",
            "subcategory":"Non-profit Organization",
            "type":"Services"
        }
    ],
    "sg:phone":"+1 301 863 8127",
    "sg:postcode":"20634",
    "sg:province":"MD",
    "sg:tags":[
        "fund",
        "counselor",
        "raising"
    ],
    "wof:name":"Coupon Connections Of Ameirca",
    "wof:placetype":"venue"
},
  "geometry": {"coordinates":[-76.49421700000001,38.262651],"type":"Point"}
}