{
  "type": "Feature",
  "properties": {
    "addr:full":"8761 Piney Orchard Pkwy Odenton MD 21113",
    "addr:housenumber":"8761",
    "addr:postcode":"21113",
    "addr:street":"Piney Orchard Pkwy",
    "iso:country":"US",
    "sg:address":"8761 Piney Orchard Pkwy",
    "sg:city":"Odenton",
    "sg:classifiers":[
        {
            "category":"Bakery",
            "type":"Food & Drink"
        },
        {
            "category":"Coffee & Tea",
            "type":"Food & Drink"
        },
        {
            "category":"Bagels",
            "type":"Food & Drink"
        },
        {
            "category":"Donuts",
            "type":"Food & Drink"
        }
    ],
    "sg:menulink":"http://www.allmenus.com/md/odenton/148896-dunkin-donuts/menu/",
    "sg:phone":"+1 410 695 2223",
    "sg:postcode":"21113",
    "sg:province":"MD",
    "sg:tags":[
        "wrap",
        "american",
        "sandwich",
        "pastry"
    ],
    "wof:name":"Dunkin' Donuts",
    "wof:placetype":"venue"
},
  "geometry": {"coordinates":[-76.724013,39.063469],"type":"Point"}
}