{
  "type": "Feature",
  "properties": {
    "addr:full":"8835 Columbia 100 Pkwy M Columbia MD 21045",
    "addr:housenumber":"8835",
    "addr:postcode":"21045",
    "addr:street":"Columbia 100 Pkwy M",
    "iso:country":"US",
    "sg:address":"8835 Columbia 100 Pkwy M",
    "sg:city":"Columbia",
    "sg:classifiers":[
        {
            "category":"Sports & Exercise",
            "subcategory":"Race Track",
            "type":"Entertainment"
        }
    ],
    "sg:phone":"+1 410 997 7234",
    "sg:postcode":"21045",
    "sg:province":"MD",
    "wof:name":"B & B Racing",
    "wof:placetype":"venue"
},
  "geometry": {"coordinates":[-76.814218,39.229314],"type":"Point"}
}