{
  "type": "Feature",
  "properties": {
    "iso:country":"US",
    "sg:address":"3200 Rolling Rd",
    "sg:city":"Edgewater",
    "sg:classifiers":[
        {
            "category":"Professional",
            "subcategory":"Art Services",
            "type":"Services"
        }
    ],
    "sg:phone":"+1 410 956 1804",
    "sg:postcode":"21037",
    "sg:province":"MD",
    "sg:tags":[
        "commercial",
        "design"
    ],
    "wof:name":"Mitchelle Stephenson Freelanc",
    "wof:placetype":"venue"
},
  "geometry": {"coordinates":[-76.581766,38.930707],"type":"Point"}
}