{
  "type": "Feature",
  "properties": {
    "iso:country":"US",
    "sg:address":"11390 Frederick Rd",
    "sg:city":"Ellicott City",
    "sg:classifiers":[
        {
            "category":"Manufacturing",
            "subcategory":"Signs",
            "type":"Manufacturing & Wholesale Goods"
        }
    ],
    "sg:phone":"+1 410 531 2353",
    "sg:postcode":"21042",
    "sg:province":"MD",
    "sg:tags":[
        "specialty",
        "mfg"
    ],
    "wof:name":"Carved Signs",
    "wof:placetype":"venue"
},
  "geometry": {"coordinates":[-76.91371599999999,39.29257],"type":"Point"}
}