{
  "type": "Feature",
  "properties": {
    "iso:country":"US",
    "sg:address":"6100 Editors Park Dr",
    "sg:city":"Hyattsville",
    "sg:classifiers":[
        {
            "category":"Education",
            "subcategory":"School",
            "type":"Public Place"
        }
    ],
    "sg:phone":"+1 301 853 0840",
    "sg:postcode":"20782",
    "sg:province":"MD",
    "sg:tags":[
        "high",
        "middle",
        "elementary"
    ],
    "wof:name":"Prince George's County School District",
    "wof:placetype":"venue"
},
  "geometry": {"coordinates":[-76.959756,38.96358],"type":"Point"}
}