{
  "type": "Feature",
  "properties": {
    "addr:full":"5 11th St Ocean City MD 21842",
    "addr:housenumber":"5",
    "addr:postcode":"21842",
    "addr:street":"11Th St",
    "iso:country":"US",
    "sg:address":"5 11th St",
    "sg:city":"Ocean City",
    "sg:classifiers":[
        {
            "category":"Professional",
            "subcategory":"Business Services",
            "type":"Services"
        }
    ],
    "sg:phone":"+1 410 289 4578",
    "sg:postcode":"21842",
    "sg:province":"MD",
    "wof:name":"Michael S Maykrantz",
    "wof:placetype":"venue"
},
  "geometry": {"coordinates":[-75.079826,38.340993],"type":"Point"}
}