{
  "type": "Feature",
  "properties": {
    "addr:full":"1314 Old Eastern Ave Essex MD 21221",
    "addr:housenumber":"1314",
    "addr:postcode":"21221",
    "addr:street":"Old Eastern Ave",
    "iso:country":"US",
    "sg:address":"1314 Old Eastern Ave",
    "sg:city":"Essex",
    "sg:classifiers":[
        {
            "category":"Community Center",
            "type":"Public Place"
        }
    ],
    "sg:phone":"+1 410 391 1234",
    "sg:postcode":"21221",
    "sg:province":"MD",
    "sg:tags":[
        "recreation"
    ],
    "wof:name":"Total Development Community Center, Inc.",
    "wof:placetype":"venue"
},
  "geometry": {"coordinates":[-76.45861499999999,39.313695],"type":"Point"}
}