{
  "type": "Feature",
  "properties": {
    "iso:country":"US",
    "sg:address":"177 Frazee Ridge Rd",
    "sg:city":"Friendsville",
    "sg:classifiers":[
        {
            "category":"Autos & Motor Vehicles",
            "subcategory":"Auto Supplies",
            "type":"Retail Goods"
        }
    ],
    "sg:phone":"+1 301 746 4349",
    "sg:postcode":"21531",
    "sg:province":"MD",
    "sg:tags":[
        "windshield",
        "wiper"
    ],
    "wof:name":"Deep Creek Cellars",
    "wof:placetype":"venue"
},
  "geometry": {"coordinates":[-79.440772,39.711177],"type":"Point"}
}