{
  "type": "Feature",
  "properties": {
    "iso:country":"US",
    "sg:address":"2917 Burtonhill Dr",
    "sg:city":"Kensington",
    "sg:classifiers":[
        {
            "category":"Professional",
            "subcategory":"Business Services",
            "type":"Services"
        }
    ],
    "sg:phone":"+1 301 933 0804",
    "sg:postcode":"20895",
    "sg:province":"MD",
    "sg:tags":[
        "translating"
    ],
    "wof:name":"Patricia Z Downey",
    "wof:placetype":"venue"
},
  "geometry": {"coordinates":[-77.060315,39.034372],"type":"Point"}
}