{
  "type": "Feature",
  "properties": {
    "addr:full":"2110 Natures Way Prince Frederick MD 20678",
    "addr:housenumber":"2110",
    "addr:postcode":"20678",
    "addr:street":"Natures Way",
    "iso:country":"US",
    "sg:address":"2110 Natures Way",
    "sg:city":"Prince Frederick",
    "sg:classifiers":[
        {
            "category":"Building & Trades",
            "subcategory":"Construction",
            "type":"Services"
        }
    ],
    "sg:phone":"+1 410 535 5661",
    "sg:postcode":"20678",
    "sg:province":"MD",
    "sg:tags":[
        "home",
        "improvement"
    ],
    "wof:name":"Absolute Quality Contractors",
    "wof:placetype":"venue"
},
  "geometry": {"coordinates":[-76.58605799999999,38.495958],"type":"Point"}
}