{
  "type": "Feature",
  "properties": {
    "iso:country":"US",
    "sg:address":"12741 Sunset Ave",
    "sg:city":"Ocean City",
    "sg:classifiers":[
        {
            "category":"Retail",
            "subcategory":"Auto Repair",
            "type":"Services"
        }
    ],
    "sg:phone":"+1 410 213 2221",
    "sg:postcode":"21842",
    "sg:province":"MD",
    "sg:tags":[
        "truck"
    ],
    "wof:name":"Carey's Diesel Inc",
    "wof:placetype":"venue"
},
  "geometry": {"coordinates":[-75.113631,38.328031],"type":"Point"}
}