{
  "type": "Feature",
  "properties": {
    "iso:country":"US",
    "sg:address":"7407 Willow Rd",
    "sg:city":"Frederick",
    "sg:classifiers":[
        {
            "category":"Health Services",
            "subcategory":"Nursing And Care Facility",
            "type":"Services"
        }
    ],
    "sg:phone":"+1 301 694 7292",
    "sg:postcode":"21702",
    "sg:province":"MD",
    "sg:tags":[
        "home",
        "convalescent"
    ],
    "sg:website":"www.homewood.com",
    "wof:name":"Homewood Retirement Ctr",
    "wof:placetype":"venue"
},
  "geometry": {"coordinates":[-77.408907,39.472293],"type":"Point"}
}