{
  "type": "Feature",
  "properties": {
    "addr:full":"4629 Indian Head Hwy Indian Head MD 20640",
    "addr:housenumber":"4629",
    "addr:postcode":"20640",
    "addr:street":"Indian Head Hwy",
    "iso:country":"US",
    "sg:address":"4629 Indian Head Hwy",
    "sg:city":"Indian Head",
    "sg:classifiers":[
        {
            "category":"Autos & Motor Vehicles",
            "subcategory":"Automobile Sales",
            "type":"Retail Goods"
        }
    ],
    "sg:phone":"+1 301 743 3128",
    "sg:postcode":"20640",
    "sg:province":"MD",
    "sg:tags":[
        "car",
        "dealer"
    ],
    "wof:name":"210 Auto Sales",
    "wof:placetype":"venue"
},
  "geometry": {"coordinates":[-77.146958,38.601124],"type":"Point"}
}