{
  "type": "Feature",
  "properties": {
    "iso:country":"US",
    "sg:address":"6530 Walther Ave",
    "sg:city":"Baltimore",
    "sg:classifiers":[
        {
            "category":"Health Services",
            "subcategory":"Doctor",
            "type":"Services"
        }
    ],
    "sg:phone":"+1 410 319 9155",
    "sg:postcode":"21206",
    "sg:province":"MD",
    "wof:name":"Supatrchamnian Suwimon Dr",
    "wof:placetype":"venue"
},
  "geometry": {"coordinates":[-76.5401,39.3568],"type":"Point"}
}