{
  "type": "Feature",
  "properties": {
    "addr:full":"102 Solomons Island Rd N Prince Frederick MD 20678",
    "addr:housenumber":"102",
    "addr:postcode":"20678",
    "addr:street":"Solomons Island Rd N",
    "iso:country":"US",
    "sg:address":"102 Solomons Island Rd N",
    "sg:city":"Prince Frederick",
    "sg:classifiers":[
        {
            "category":"Professional",
            "subcategory":"Business Services",
            "type":"Services"
        }
    ],
    "sg:phone":"+1 410 535 5452",
    "sg:postcode":"20678",
    "sg:province":"MD",
    "sg:tags":[
        "license"
    ],
    "wof:name":"Direct Express Auto Tag",
    "wof:placetype":"venue"
},
  "geometry": {"coordinates":[-76.588836,38.538326],"type":"Point"}
}