{
  "type": "Feature",
  "properties": {
    "iso:country":"US",
    "sg:address":"1004 E Patapsco Ave",
    "sg:city":"Brooklyn",
    "sg:classifiers":[
        {
            "category":"Insurance",
            "subcategory":"Insurance Agent",
            "type":"Services"
        }
    ],
    "sg:phone":"+1 410 355 4911",
    "sg:postcode":"21225",
    "sg:province":"MD",
    "wof:name":"Erin Cox Insurance",
    "wof:placetype":"venue"
},
  "geometry": {"coordinates":[-76.595478,39.234341],"type":"Point"}
}