{
  "type": "Feature",
  "properties": {
    "iso:country":"US",
    "sg:address":"12803 Buckingham Dr",
    "sg:city":"Bowie",
    "sg:classifiers":[
        {
            "category":"Building & Trades",
            "subcategory":"Landscaping Services",
            "type":"Services"
        }
    ],
    "sg:phone":"+1 301 860 0395",
    "sg:postcode":"20715",
    "sg:province":"MD",
    "sg:tags":[
        "landscape"
    ],
    "wof:name":"Whiteleather Lawn and Ldscp",
    "wof:placetype":"venue"
},
  "geometry": {"coordinates":[-76.726435,38.961559],"type":"Point"}
}