{
  "type": "Feature",
  "properties": {
    "iso:country":"US",
    "sg:address":"3445 Box Hill Corporate Center Dr",
    "sg:city":"Abingdon",
    "sg:classifiers":[
        {
            "category":"Professional",
            "subcategory":"Engineering",
            "type":"Services"
        }
    ],
    "sg:phone":"+1 410 515 9446",
    "sg:postcode":"21009",
    "sg:province":"MD",
    "sg:tags":[
        "engineer"
    ],
    "sg:website":"www.mragta.com",
    "wof:name":"Geo Technology Assoc",
    "wof:placetype":"venue"
},
  "geometry": {"coordinates":[-76.296347,39.475942],"type":"Point"}
}