{
  "type": "Feature",
  "properties": {
    "iso:country":"US",
    "sg:address":"10606 Baltimore Ave",
    "sg:city":"Beltsville",
    "sg:classifiers":[
        {
            "category":"Retail",
            "subcategory":"Car Wash",
            "type":"Services"
        }
    ],
    "sg:phone":"+1 301 937 1199",
    "sg:postcode":"20705",
    "sg:province":"MD",
    "sg:tags":[
        "automobile",
        "detail",
        "clean"
    ],
    "wof:name":"American Cleaning Concepts",
    "wof:placetype":"venue"
},
  "geometry": {"coordinates":[-76.914311,39.030222],"type":"Point"}
}