{
  "type": "Feature",
  "properties": {
    "addr:full":"24 E Franklin St Hagerstown MD 21740",
    "addr:housenumber":"24",
    "addr:postcode":"21740",
    "addr:street":"E Franklin St",
    "iso:country":"US",
    "sg:address":"24 E Franklin St",
    "sg:city":"Hagerstown",
    "sg:classifiers":[
        {
            "category":"Retail",
            "subcategory":"Laundry & Dry Cleaning",
            "type":"Services"
        }
    ],
    "sg:phone":"+1 301 387 4951",
    "sg:postcode":"21740",
    "sg:province":"MD",
    "sg:tags":[
        "cleaner",
        "drapery",
        "curtain"
    ],
    "wof:name":"Mercury Cleaners",
    "wof:placetype":"venue"
},
  "geometry": {"coordinates":[-77.71841000000001,39.642927],"type":"Point"}
}