{
  "type": "Feature",
  "properties": {
    "iso:country":"US",
    "sg:address":"8069 Cryden Way",
    "sg:city":"District Heights",
    "sg:classifiers":[
        {
            "category":"Building & Trades",
            "subcategory":"Construction",
            "type":"Services"
        }
    ],
    "sg:phone":"+1 301 669 7907",
    "sg:postcode":"20747",
    "sg:province":"MD",
    "sg:tags":[
        "contractor"
    ],
    "wof:name":"Robison Prezioso Inc",
    "wof:placetype":"venue"
},
  "geometry": {"coordinates":[-76.869496,38.847621],"type":"Point"}
}