{
  "type": "Feature",
  "properties": {
    "addr:full":"11150 York Rd Cockeysville MD 21030",
    "addr:housenumber":"11150",
    "addr:postcode":"21030",
    "addr:street":"York Rd",
    "iso:country":"US",
    "sg:address":"11150 York Rd",
    "sg:city":"Cockeysville",
    "sg:classifiers":[
        {
            "category":"Retail",
            "subcategory":"Storage",
            "type":"Services"
        }
    ],
    "sg:phone":"+1 410 793 1126",
    "sg:postcode":"21030",
    "sg:province":"MD",
    "sg:tags":[
        "self"
    ],
    "sg:website":"www.devonselfstorage.com/self_st...",
    "wof:name":"Devon Self Storage - Cockeysville",
    "wof:placetype":"venue"
},
  "geometry": {"coordinates":[-76.647903,39.4897],"type":"Point"}
}