{
  "type": "Feature",
  "properties": {
    "iso:country":"US",
    "sg:address":"4006 Parkwood Ave",
    "sg:city":"Baltimore",
    "sg:classifiers":[
        {
            "category":"Real Estate",
            "subcategory":"Surveying",
            "type":"Services"
        }
    ],
    "sg:phone":"+1 410 488 4080",
    "sg:postcode":"21206",
    "sg:province":"MD",
    "sg:tags":[
        "engineer"
    ],
    "wof:name":"Donald George Harris Sr",
    "wof:placetype":"venue"
},
  "geometry": {"coordinates":[-76.556703,39.337199],"type":"Point"}
}