{
  "type": "Feature",
  "properties": {
    "addr:full":"5144 Massachusetts Ave Bethesda MD 20816",
    "addr:housenumber":"5144",
    "addr:postcode":"20816",
    "addr:street":"Massachusetts Ave",
    "iso:country":"US",
    "sg:address":"5144 Massachusetts Ave",
    "sg:city":"Bethesda",
    "sg:classifiers":[
        {
            "category":"Education",
            "subcategory":"Preschool",
            "type":"Public Place"
        },
        {
            "category":"Education",
            "subcategory":"School",
            "type":"Public Place"
        }
    ],
    "sg:phone":"+1 301 320 3646",
    "sg:postcode":"20816",
    "sg:province":"MD",
    "sg:tags":[
        "elementary"
    ],
    "wof:name":"Abingdon Montessori School",
    "wof:placetype":"venue"
},
  "geometry": {"coordinates":[-77.101501,38.950401],"type":"Point"}
}