{
  "type": "Feature",
  "properties": {
    "iso:country":"US",
    "sg:address":"1065 S Charles St",
    "sg:city":"Baltimore",
    "sg:classifiers":[
        {
            "category":"Shopping",
            "subcategory":"Florist",
            "type":"Retail Goods"
        }
    ],
    "sg:phone":"+1 410 727 6610",
    "sg:postcode":"21230",
    "sg:province":"MD",
    "wof:name":"Flower Shop",
    "wof:placetype":"venue"
},
  "geometry": {"coordinates":[-76.61435,39.277519],"type":"Point"}
}