{
  "type": "Feature",
  "properties": {
    "addr:full":"318 Silva Rd Stockton MD 21864",
    "addr:housenumber":"318",
    "addr:postcode":"21864",
    "addr:street":"Silva Rd",
    "iso:country":"US",
    "sg:address":"318 Silva Rd",
    "sg:city":"Stockton",
    "sg:classifiers":[
        {
            "category":"Farming",
            "subcategory":"Farm",
            "type":"Manufacturing & Wholesale Goods"
        }
    ],
    "sg:phone":"+1 410 957 0791",
    "sg:postcode":"21864",
    "sg:province":"MD",
    "sg:tags":[
        "crop",
        "general"
    ],
    "wof:name":"Benjamin Aydelotte Farms",
    "wof:placetype":"venue"
},
  "geometry": {"coordinates":[-75.46213400000001,38.010835],"type":"Point"}
}