{
  "type": "Feature",
  "properties": {
    "addr:full":"2500 W North Ave Mc09 Baltimore MD 21216",
    "addr:housenumber":"2500",
    "addr:postcode":"21216",
    "addr:street":"W North Ave",
    "iso:country":"US",
    "sg:address":"2500 W North Ave Mc09",
    "sg:city":"Baltimore",
    "sg:classifiers":[
        {
            "category":"Communications",
            "subcategory":"Television Station",
            "type":"Services"
        }
    ],
    "sg:phone":"+1 410 383 2222",
    "sg:postcode":"21216",
    "sg:province":"MD",
    "sg:tags":[
        "satellite",
        "cable"
    ],
    "wof:name":"Baltimore Cable Access Corp",
    "wof:placetype":"venue"
},
  "geometry": {"coordinates":[-76.65718099999999,39.309448],"type":"Point"}
}