{
  "type": "Feature",
  "properties": {
    "addr:full":"20310 New Hampshire Ave Brinklow MD 20862",
    "addr:housenumber":"20310",
    "addr:postcode":"20862",
    "addr:street":"New Hampshire Ave",
    "iso:country":"US",
    "sg:address":"20310 New Hampshire Ave",
    "sg:city":"Brinklow",
    "sg:classifiers":[
        {
            "category":"Building & Trades",
            "subcategory":"Landscaping Services",
            "type":"Services"
        },
        {
            "category":"Building & Trades",
            "subcategory":"Construction",
            "type":"Services"
        }
    ],
    "sg:phone":"+1 301 774 9657",
    "sg:postcode":"20862",
    "sg:province":"MD",
    "sg:tags":[
        "excavation",
        "lawn",
        "landscape",
        "contractor"
    ],
    "wof:name":"Guy L Brown & Son",
    "wof:placetype":"venue"
},
  "geometry": {"coordinates":[-77.02533,39.189831],"type":"Point"}
}