{
  "type": "Feature",
  "properties": {
    "iso:country":"US",
    "sg:address":"6815 Bradgrove Cir",
    "sg:city":"Bethesda",
    "sg:classifiers":[
        {
            "category":"Professional",
            "subcategory":"Research",
            "type":"Services"
        }
    ],
    "sg:phone":"+1 301 469 8545",
    "sg:postcode":"20817",
    "sg:province":"MD",
    "sg:tags":[
        "industrial",
        "defense",
        "scientific",
        "for"
    ],
    "wof:name":"Defensetek",
    "wof:placetype":"venue"
},
  "geometry": {"coordinates":[-77.139186,39.0029],"type":"Point"}
}