{
  "type": "Feature",
  "properties": {
    "iso:country":"US",
    "sg:address":"9208 Morley Rd",
    "sg:city":"Lanham",
    "sg:classifiers":[
        {
            "category":"Manufacturing",
            "subcategory":"Tools & Machinery",
            "type":"Manufacturing & Wholesale Goods"
        }
    ],
    "sg:phone":"+1 301 577 1554",
    "sg:postcode":"20706",
    "sg:province":"MD",
    "sg:tags":[
        "seafood",
        "processing"
    ],
    "wof:name":"Josorat Enterprises",
    "wof:placetype":"venue"
},
  "geometry": {"coordinates":[-76.85298899999999,38.96317],"type":"Point"}
}