{
  "type": "Feature",
  "properties": {
    "iso:country":"US",
    "sg:address":"3012 Dubarry Ln",
    "sg:city":"Brookeville",
    "sg:classifiers":[
        {
            "category":"Manufacturing",
            "subcategory":"Buildings",
            "type":"Manufacturing & Wholesale Goods"
        },
        {
            "category":"Building & Trades",
            "subcategory":"Construction",
            "type":"Services"
        }
    ],
    "sg:phone":"+1 301 924 2458",
    "sg:postcode":"20833",
    "sg:province":"MD",
    "sg:tags":[
        "home",
        "builder",
        "contractor"
    ],
    "wof:name":"Scott C Loomis General Contractor",
    "wof:placetype":"venue"
},
  "geometry": {"coordinates":[-77.061605,39.171736],"type":"Point"}
}