{
  "type": "Feature",
  "properties": {
    "addr:full":"1 Covert Ct Lutherville MD 21093",
    "addr:housenumber":"1",
    "addr:postcode":"21093",
    "addr:street":"Covert Ct",
    "iso:country":"US",
    "sg:address":"1 Covert Ct",
    "sg:city":"Lutherville",
    "sg:classifiers":[
        {
            "category":"Organizations",
            "subcategory":"Religious Organization",
            "type":"Services"
        }
    ],
    "sg:phone":"+1 410 252 1292",
    "sg:postcode":"21093",
    "sg:province":"MD",
    "sg:tags":[
        "church"
    ],
    "wof:name":"Towson Bible Church",
    "wof:placetype":"venue"
},
  "geometry": {"coordinates":[-76.64105499999999,39.447223],"type":"Point"}
}