{
  "type": "Feature",
  "properties": {
    "iso:country":"US",
    "sg:address":"6203 Executive Blvd",
    "sg:city":"Rockville",
    "sg:classifiers":[
        {
            "category":"Social Services",
            "type":"Services"
        }
    ],
    "sg:phone":"+1 301 340 1598",
    "sg:postcode":"20852",
    "sg:province":"MD",
    "wof:name":"Helene C Dubov Lcsw-C",
    "wof:placetype":"venue"
},
  "geometry": {"coordinates":[-77.12103,39.048883],"type":"Point"}
}