{
  "type": "Feature",
  "properties": {
    "addr:full":"10429 Azalea Ln Berlin MD 21811",
    "addr:housenumber":"10429",
    "addr:postcode":"21811",
    "addr:street":"Azalea Ln",
    "iso:country":"US",
    "sg:address":"10429 Azalea Ln",
    "sg:city":"Berlin",
    "sg:phone":"+1 410 208 0126",
    "sg:postcode":"21811",
    "sg:province":"MD",
    "sg:tags":[
        "farm",
        "corn"
    ],
    "wof:name":"Doug Jones",
    "wof:placetype":"venue"
},
  "geometry": {"coordinates":[-75.179575,38.361012],"type":"Point"}
}