{
  "type": "Feature",
  "properties": {
    "addr:full":"18001 Bowie Mill Rd Derwood MD 20855",
    "addr:housenumber":"18001",
    "addr:postcode":"20855",
    "addr:street":"Bowie Mill Rd",
    "iso:country":"US",
    "sg:address":"18001 Bowie Mill Rd",
    "sg:city":"Derwood",
    "sg:classifiers":[
        {
            "category":"Building & Trades",
            "subcategory":"Landscaping Services",
            "type":"Services"
        }
    ],
    "sg:phone":"+1 301 570 6033",
    "sg:postcode":"20855",
    "sg:province":"MD",
    "sg:tags":[
        "tree"
    ],
    "sg:website":"www.arborcare-inc.com",
    "wof:name":"Arborcare Inc",
    "wof:placetype":"venue"
},
  "geometry": {"coordinates":[-77.10366500000001,39.150715],"type":"Point"}
}