{
  "type": "Feature",
  "properties": {
    "addr:full":"697 Windsor Dr Westminster MD 21158",
    "addr:housenumber":"697",
    "addr:postcode":"21158",
    "addr:street":"Windsor Dr",
    "iso:country":"US",
    "sg:address":"697 Windsor Dr",
    "sg:city":"Westminster",
    "sg:classifiers":[
        {
            "category":"Wholesale",
            "subcategory":"Electrical",
            "type":"Manufacturing & Wholesale Goods"
        }
    ],
    "sg:phone":"+1 410 857 5039",
    "sg:postcode":"21158",
    "sg:province":"MD",
    "sg:tags":[
        "alarm",
        "burglar",
        "system"
    ],
    "wof:name":"Alarm Pro-Tech Systems Inc",
    "wof:placetype":"venue"
},
  "geometry": {"coordinates":[-77.020695,39.581129],"type":"Point"}
}