{
  "type": "Feature",
  "properties": {
    "addr:full":"10300 Little Patuxent Pkwy Columbia MD 21044",
    "addr:housenumber":"10300",
    "addr:postcode":"21044",
    "addr:street":"Little Patuxent Pkwy",
    "iso:country":"US",
    "sg:address":"10300 Little Patuxent Pkwy",
    "sg:city":"Columbia",
    "sg:classifiers":[
        {
            "category":"Food & Beverages",
            "subcategory":"Specialty",
            "type":"Retail Goods"
        }
    ],
    "sg:phone":"+1 410 772 1286",
    "sg:postcode":"21044",
    "sg:province":"MD",
    "sg:tags":[
        "tea",
        "coffee"
    ],
    "wof:name":"Barnie's Coffee & Tea Co",
    "wof:placetype":"venue"
},
  "geometry": {"coordinates":[-76.85831399999999,39.217959],"type":"Point"}
}