{
  "type": "Feature",
  "properties": {
    "addr:full":"5301 Tuckerman Ln Bethesda MD 20810",
    "addr:housenumber":"5301",
    "addr:postcode":"20810",
    "addr:street":"Tuckerman Ln",
    "iso:country":"US",
    "sg:address":"5301 Tuckerman Ln",
    "sg:city":"Bethesda",
    "sg:classifiers":[
        {
            "category":"Restaurant",
            "type":"Food & Drink"
        }
    ],
    "sg:phone":"+1 301 581 5223",
    "sg:postcode":"20810",
    "sg:province":"MD",
    "sg:website":"www.strathmore.org/planyourvisit...",
    "wof:name":"Prelude Cafe at Strathmore",
    "wof:placetype":"venue"
},
  "geometry": {"coordinates":[-77.103054,39.024262],"type":"Point"}
}