{
  "type": "Feature",
  "properties": {
    "addr:full":"525 E Gude Dr Rockville MD 20850",
    "addr:housenumber":"525",
    "addr:postcode":"20850",
    "addr:street":"E Gude Dr",
    "iso:country":"US",
    "sg:address":"525 E Gude Dr",
    "sg:city":"Rockville",
    "sg:classifiers":[
        {
            "category":"Home & Garden",
            "subcategory":"Building Materials",
            "type":"Retail Goods"
        }
    ],
    "sg:phone":"+1 301 424 6500",
    "sg:postcode":"20850",
    "sg:province":"MD",
    "wof:name":"Leland L Fisher Lumber Co",
    "wof:placetype":"venue"
},
  "geometry": {"coordinates":[-77.148358,39.106316],"type":"Point"}
}