{
  "type": "Feature",
  "properties": {
    "iso:country":"US",
    "sg:address":"6408 Dower House Rd",
    "sg:city":"Upper Marlboro",
    "sg:classifiers":[
        {
            "category":"Manufacturing",
            "subcategory":"Metals",
            "type":"Manufacturing & Wholesale Goods"
        }
    ],
    "sg:phone":"+1 301 599 6100",
    "sg:postcode":"20772",
    "sg:province":"MD",
    "sg:tags":[
        "fence"
    ],
    "wof:name":"Cedar Fences Inc",
    "wof:placetype":"venue"
},
  "geometry": {"coordinates":[-76.843591,38.802845],"type":"Point"}
}