{
  "type": "Feature",
  "properties": {
    "addr:full":"72 Marlyn Dr Elkton MD 21921",
    "addr:housenumber":"72",
    "addr:postcode":"21921",
    "addr:street":"Marlyn Dr",
    "iso:country":"US",
    "sg:address":"72 Marlyn Dr",
    "sg:city":"Elkton",
    "sg:classifiers":[
        {
            "category":"Professional",
            "subcategory":"Business Services",
            "type":"Services"
        }
    ],
    "sg:phone":"+1 410 398 7619",
    "sg:postcode":"21921",
    "sg:province":"MD",
    "wof:name":"North East Baseball Assoc",
    "wof:placetype":"venue"
},
  "geometry": {"coordinates":[-75.816711,39.701033],"type":"Point"}
}