{
  "type": "Feature",
  "properties": {
    "iso:country":"US",
    "sg:address":"3801 Canterbury Rd",
    "sg:city":"Baltimore",
    "sg:classifiers":[
        {
            "category":"Professional",
            "type":"Services"
        }
    ],
    "sg:phone":"+1 410 366 5605",
    "sg:postcode":"21218",
    "sg:province":"MD",
    "sg:tags":[
        "establishment"
    ],
    "wof:name":"Papadimitriou John",
    "wof:placetype":"venue"
},
  "geometry": {"coordinates":[-76.620493,39.335678],"type":"Point"}
}