{
  "type": "Feature",
  "properties": {
    "iso:country":"US",
    "sg:address":"5840 Banneker Rd",
    "sg:city":"Columbia",
    "sg:classifiers":[
        {
            "category":"Shopping",
            "subcategory":"Books",
            "type":"Retail Goods"
        }
    ],
    "sg:phone":"+1 410 772 1681",
    "sg:postcode":"21044",
    "sg:province":"MD",
    "sg:tags":[
        "dealer"
    ],
    "wof:name":"Waldenbooks",
    "wof:placetype":"venue"
},
  "geometry": {"coordinates":[-76.87043199999999,39.211628],"type":"Point"}
}