{
  "type": "Feature",
  "properties": {
    "iso:country":"US",
    "sg:address":"321 E Village Rd",
    "sg:city":"Elkton",
    "sg:classifiers":[
        {
            "category":"Wholesale",
            "subcategory":"Office Equipment",
            "type":"Manufacturing & Wholesale Goods"
        }
    ],
    "sg:phone":"+1 410 398 8269",
    "sg:postcode":"21921",
    "sg:province":"MD",
    "sg:tags":[
        "machine",
        "duplicating",
        "copying"
    ],
    "wof:name":"Repro-Systems",
    "wof:placetype":"venue"
},
  "geometry": {"coordinates":[-75.795965,39.610038],"type":"Point"}
}