{
  "type": "Feature",
  "properties": {
    "iso:country":"US",
    "sg:address":"1306 Concourse Dr",
    "sg:city":"Linthicum Hts",
    "sg:classifiers":[
        {
            "category":"Professional",
            "subcategory":"Management & Consulting",
            "type":"Services"
        }
    ],
    "sg:phone":"+1 410 694 9696",
    "sg:postcode":"21090",
    "sg:province":"MD",
    "sg:tags":[
        "consultant",
        "telecommunication"
    ],
    "sg:website":"www.ctcnet.com",
    "wof:name":"CTC Communications Corp",
    "wof:placetype":"venue"
},
  "geometry": {"coordinates":[-76.690984,39.205298],"type":"Point"}
}