{
  "type": "Feature",
  "properties": {
    "iso:country":"US",
    "sg:address":"34693 Main St",
    "sg:city":"Pittsville",
    "sg:classifiers":[
        {
            "category":"Retail",
            "subcategory":"Auto Repair",
            "type":"Services"
        }
    ],
    "sg:phone":"+1 410 835 2241",
    "sg:postcode":"21850",
    "sg:province":"MD",
    "sg:tags":[
        "machine",
        "automobile",
        "shop"
    ],
    "wof:name":"Baileys Automotive Machine",
    "wof:placetype":"venue"
},
  "geometry": {"coordinates":[-75.408753,38.394029],"type":"Point"}
}