{
  "type": "Feature",
  "properties": {
    "iso:country":"US",
    "sg:address":"603 Church St",
    "sg:city":"Brooklyn",
    "sg:classifiers":[
        {
            "category":"Organizations",
            "subcategory":"Religious Organization",
            "type":"Services"
        }
    ],
    "sg:phone":"+1 410 609 0386",
    "sg:postcode":"21225",
    "sg:province":"MD",
    "sg:tags":[
        "place",
        "worship",
        "church"
    ],
    "wof:name":"Sword Of The Spirit Ministries",
    "wof:placetype":"venue"
},
  "geometry": {"coordinates":[-76.60158800000001,39.219739],"type":"Point"}
}