{
  "type": "Feature",
  "properties": {
    "addr:full":"4922 Lasalle Rd Hyattsville MD 20782",
    "addr:housenumber":"4922",
    "addr:postcode":"20782",
    "addr:street":"Lasalle Rd",
    "iso:country":"US",
    "sg:address":"4922 Lasalle Rd",
    "sg:city":"Hyattsville",
    "sg:classifiers":[
        {
            "category":"Health Services",
            "subcategory":"Nursing And Care Facility",
            "type":"Services"
        }
    ],
    "sg:phone":"+1 301 864 2333",
    "sg:postcode":"20782",
    "sg:province":"MD",
    "sg:tags":[
        "home",
        "convalescent"
    ],
    "sg:website":"www.futurecarehealth.com",
    "wof:name":"St Thomas More A Futurecare",
    "wof:placetype":"venue"
},
  "geometry": {"coordinates":[-76.97796700000001,38.950014],"type":"Point"}
}