{
  "type": "Feature",
  "properties": {
    "iso:country":"US",
    "sg:address":"504 Lewis St",
    "sg:city":"Havre De Grace",
    "sg:classifiers":[
        {
            "category":"Health Services",
            "subcategory":"Doctor",
            "type":"Services"
        }
    ],
    "sg:phone":"+1 410 642 6500",
    "sg:postcode":"21078",
    "sg:province":"MD",
    "sg:tags":[
        "physician",
        "surgeon"
    ],
    "wof:name":"Sadowsky Surgical Assoc",
    "wof:placetype":"venue"
},
  "geometry": {"coordinates":[-76.092183,39.542376],"type":"Point"}
}