{
  "type": "Feature",
  "properties": {
    "addr:full":"227 Kentlands Blvd Gaithersburg MD 20878",
    "addr:housenumber":"227",
    "addr:postcode":"20878",
    "addr:street":"Kentlands Blvd",
    "iso:country":"US",
    "sg:address":"227 Kentlands Blvd",
    "sg:city":"Gaithersburg",
    "sg:classifiers":[
        {
            "category":"Shopping",
            "subcategory":"Gifts & Souvenirs",
            "type":"Retail Goods"
        }
    ],
    "sg:phone":"+1 301 869 7968",
    "sg:postcode":"20878",
    "sg:province":"MD",
    "sg:tags":[
        "collectible"
    ],
    "wof:name":"Banner's Hallmark",
    "wof:placetype":"venue"
},
  "geometry": {"coordinates":[-77.24239300000001,39.124951],"type":"Point"}
}