{
  "type": "Feature",
  "properties": {
    "addr:full":"14700 Southlawn Ln Rockville MD 20850",
    "addr:housenumber":"14700",
    "addr:postcode":"20850",
    "addr:street":"Southlawn Ln",
    "iso:country":"US",
    "sg:address":"14700 Southlawn Ln",
    "sg:city":"Rockville",
    "sg:classifiers":[
        {
            "category":"Retail",
            "subcategory":"Auto Repair",
            "type":"Services"
        }
    ],
    "sg:phone":"+1 301 340 2566",
    "sg:postcode":"20850",
    "sg:province":"MD",
    "sg:tags":[
        "body",
        "automobile",
        "painting"
    ],
    "wof:name":"Nationwide Collision Experts",
    "wof:placetype":"venue"
},
  "geometry": {"coordinates":[-77.13715999999999,39.097145],"type":"Point"}
}