{
  "type": "Feature",
  "properties": {
    "addr:full":"6114 Race Rd Elkridge MD 21075",
    "addr:housenumber":"6114",
    "addr:postcode":"21075",
    "addr:street":"Race Rd",
    "iso:country":"US",
    "sg:address":"6114 Race Rd",
    "sg:city":"Elkridge",
    "sg:classifiers":[
        {
            "category":"Building & Trades",
            "subcategory":"Landscaping Services",
            "type":"Services"
        }
    ],
    "sg:phone":"+1 410 796 7932",
    "sg:postcode":"21075",
    "sg:province":"MD",
    "sg:tags":[
        "landscape",
        "contractor"
    ],
    "wof:name":"Payne Landscaping Inc",
    "wof:placetype":"venue"
},
  "geometry": {"coordinates":[-76.712926,39.202147],"type":"Point"}
}