{
  "type": "Feature",
  "properties": {
    "addr:full":"3434 Philips Dr Pikesville MD 21208",
    "addr:housenumber":"3434",
    "addr:postcode":"21208",
    "addr:street":"Philips Dr",
    "iso:country":"US",
    "sg:address":"3434 Philips Dr",
    "sg:city":"Pikesville",
    "sg:classifiers":[
        {
            "category":"Shopping",
            "subcategory":"Pharmacy",
            "type":"Retail Goods"
        }
    ],
    "sg:phone":"+1 410 728 6363",
    "sg:postcode":"21208",
    "sg:province":"MD",
    "sg:tags":[
        "used",
        "merchandise"
    ],
    "wof:name":"Antique Treasury",
    "wof:placetype":"venue"
},
  "geometry": {"coordinates":[-76.71089000000001,39.394042],"type":"Point"}
}