{
  "type": "Feature",
  "properties": {
    "iso:country":"US",
    "sg:address":"825 Dulaney Valley Rd",
    "sg:city":"Towson",
    "sg:classifiers":[
        {
            "category":"Wholesale",
            "subcategory":"Groceries",
            "type":"Manufacturing & Wholesale Goods"
        }
    ],
    "sg:phone":"+1 410 821 7688",
    "sg:postcode":"21204",
    "sg:province":"MD",
    "sg:tags":[
        "pretzel"
    ],
    "wof:name":"Auntie Anne's Hand Rolled Soft",
    "wof:placetype":"venue"
},
  "geometry": {"coordinates":[-76.60154199999999,39.403782],"type":"Point"}
}