{
  "type": "Feature",
  "properties": {
    "iso:country":"US",
    "sg:address":"9312 Frostburg Way",
    "sg:city":"Montgomery Village",
    "sg:classifiers":[
        {
            "category":"Building & Trades",
            "subcategory":"Construction",
            "type":"Services"
        }
    ],
    "sg:phone":"+1 301 417 6619",
    "sg:postcode":"20886",
    "sg:province":"MD",
    "sg:tags":[
        "hanging",
        "contractor"
    ],
    "wof:name":"Prisma Painting Co",
    "wof:placetype":"venue"
},
  "geometry": {"coordinates":[-77.19049699999999,39.180912],"type":"Point"}
}