{
  "type": "Feature",
  "properties": {
    "addr:full":"1298 Lavall Dr Davidsonville MD 21035",
    "addr:housenumber":"1298",
    "addr:postcode":"21035",
    "addr:street":"Lavall Dr",
    "iso:country":"US",
    "sg:address":"1298 Lavall Dr",
    "sg:city":"Davidsonville",
    "sg:classifiers":[
        {
            "category":"Education",
            "subcategory":"School",
            "type":"Public Place"
        }
    ],
    "sg:phone":"+1 410 573 0840",
    "sg:postcode":"21035",
    "sg:province":"MD",
    "wof:name":"Annearrundell County Free Schl",
    "wof:placetype":"venue"
},
  "geometry": {"coordinates":[-76.62408499999999,38.979879],"type":"Point"}
}