{
  "type": "Feature",
  "properties": {
    "iso:country":"US",
    "sg:address":"11292 Old Baltimore Pike",
    "sg:city":"Beltsville",
    "sg:classifiers":[
        {
            "category":"Manufacturing",
            "subcategory":"Motor Vehicles & Parts",
            "type":"Manufacturing & Wholesale Goods"
        }
    ],
    "sg:phone":"+1 301 595 2971",
    "sg:postcode":"20705",
    "sg:province":"MD",
    "sg:tags":[
        "automobile",
        "supply"
    ],
    "wof:name":"Beltsville Rosedale Auto Elec",
    "wof:placetype":"venue"
},
  "geometry": {"coordinates":[-76.902376,39.038381],"type":"Point"}
}