{
  "type": "Feature",
  "properties": {
    "iso:country":"US",
    "sg:address":"221 Williams St",
    "sg:city":"Cumberland",
    "sg:classifiers":[
        {
            "category":"Restaurant",
            "type":"Food & Drink"
        }
    ],
    "sg:menulink":"http://www.allmenus.com/md/cumberland/180072-chick-fil-a/menu/",
    "sg:phone":"+1 301 722 0086",
    "sg:postcode":"21502",
    "sg:province":"MD",
    "sg:tags":[
        "wrap",
        "soup",
        "american",
        "sandwich",
        "salad"
    ],
    "wof:name":"Chick-fil-A",
    "wof:placetype":"venue"
},
  "geometry": {"coordinates":[-78.75665100000001,39.648138],"type":"Point"}
}