{
  "type": "Feature",
  "properties": {
    "addr:full":"2247 Community Dr Waldorf MD 20601",
    "addr:housenumber":"2247",
    "addr:postcode":"20601",
    "addr:street":"Community Dr",
    "iso:country":"US",
    "sg:address":"2247 Community Dr",
    "sg:city":"Waldorf",
    "sg:classifiers":[
        {
            "category":"Organizations",
            "subcategory":"Religious Organization",
            "type":"Services"
        }
    ],
    "sg:phone":"+1 301 705 5583",
    "sg:postcode":"20601",
    "sg:province":"MD",
    "wof:name":"Accokeek Ch of God",
    "wof:placetype":"venue"
},
  "geometry": {"coordinates":[-76.94836100000001,38.653914],"type":"Point"}
}