{
  "type": "Feature",
  "properties": {
    "addr:full":"5 Newbold Ct Bethesda MD 20817",
    "addr:housenumber":"5",
    "addr:postcode":"20817",
    "addr:street":"Newbold Ct",
    "iso:country":"US",
    "sg:address":"5 Newbold Ct",
    "sg:city":"Bethesda",
    "sg:classifiers":[
        {
            "category":"Professional",
            "subcategory":"Business Services",
            "type":"Services"
        }
    ],
    "sg:phone":"+1 301 469 5493",
    "sg:postcode":"20817",
    "sg:province":"MD",
    "sg:tags":[
        "outing",
        "organizes",
        "golf",
        "tournament"
    ],
    "wof:name":"Divot Inc",
    "wof:placetype":"venue"
},
  "geometry": {"coordinates":[-77.13705,39.012022],"type":"Point"}
}