{
  "type": "Feature",
  "properties": {
    "addr:full":"10753 Falls Rd Lutherville MD 21093",
    "addr:housenumber":"10753",
    "addr:postcode":"21093",
    "addr:street":"Falls Rd",
    "iso:country":"US",
    "sg:address":"10753 Falls Rd",
    "sg:city":"Lutherville",
    "sg:classifiers":[
        {
            "category":"Health Services",
            "subcategory":"Doctor",
            "type":"Services"
        }
    ],
    "sg:phone":"+1 410 583 2744",
    "sg:postcode":"21093",
    "sg:province":"MD",
    "sg:tags":[
        "physician",
        "surgeon"
    ],
    "wof:name":"Johns Hopkins Univ Orthopedics",
    "wof:placetype":"venue"
},
  "geometry": {"coordinates":[-76.670151,39.420759],"type":"Point"}
}