{
  "type": "Feature",
  "properties": {
    "addr:full":"251 Najoles Rd Ste J Millersville MD 21108",
    "addr:housenumber":"251",
    "addr:postcode":"21108",
    "addr:street":"Najoles Rd Ste J",
    "iso:country":"US",
    "sg:address":"251 Najoles Rd Ste J",
    "sg:city":"Millersville",
    "sg:classifiers":[
        {
            "category":"Health Services",
            "subcategory":"Dentist",
            "type":"Services"
        }
    ],
    "sg:phone":"+1 410 987 9100",
    "sg:postcode":"21108",
    "sg:province":"MD",
    "wof:name":"Valle, Brian D, Dds - Valle & Valle Comprehensive",
    "wof:placetype":"venue"
},
  "geometry": {"coordinates":[-76.6315,39.094429],"type":"Point"}
}