{
  "type": "Feature",
  "properties": {
    "addr:full":"1526 Glen Keith Blvd Baltimore MD 21286",
    "addr:housenumber":"1526",
    "addr:postcode":"21286",
    "addr:street":"Glen Keith Blvd",
    "iso:country":"US",
    "sg:address":"1526 Glen Keith Blvd",
    "sg:city":"Baltimore",
    "sg:classifiers":[
        {
            "category":"Professional",
            "subcategory":"Business Services",
            "type":"Services"
        }
    ],
    "sg:phone":"+1 410 321 6888",
    "sg:postcode":"21286",
    "sg:province":"MD",
    "wof:name":"P2 Solutions",
    "wof:placetype":"venue"
},
  "geometry": {"coordinates":[-76.576335,39.390836],"type":"Point"}
}