{
  "type": "Feature",
  "properties": {
    "addr:full":"9010 Harford Rd Parkville MD 21234",
    "addr:housenumber":"9010",
    "addr:postcode":"21234",
    "addr:street":"Harford Rd",
    "iso:country":"US",
    "sg:address":"9010 Harford Rd",
    "sg:city":"Parkville",
    "sg:classifiers":[
        {
            "category":"Health Services",
            "subcategory":"Doctor",
            "type":"Services"
        }
    ],
    "sg:phone":"+1 410 665 2202",
    "sg:postcode":"21234",
    "sg:province":"MD",
    "sg:tags":[
        "dentist"
    ],
    "wof:name":"Grill Family Dentistry",
    "wof:placetype":"venue"
},
  "geometry": {"coordinates":[-76.53164599999999,39.386801],"type":"Point"}
}