{
  "type": "Feature",
  "properties": {
    "addr:full":"4030 Benson Ave Baltimore MD 21227",
    "addr:housenumber":"4030",
    "addr:postcode":"21227",
    "addr:street":"Benson Ave",
    "iso:country":"US",
    "sg:address":"4030 Benson Ave",
    "sg:city":"Baltimore",
    "sg:classifiers":[
        {
            "category":"Professional",
            "subcategory":"Management & Consulting",
            "type":"Services"
        }
    ],
    "sg:phone":"+1 410 247 8686",
    "sg:postcode":"21227",
    "sg:province":"MD",
    "sg:tags":[
        "marketing",
        "consultant"
    ],
    "wof:name":"RBL Exhibitier",
    "wof:placetype":"venue"
},
  "geometry": {"coordinates":[-76.681288,39.260011],"type":"Point"}
}