{
  "type": "Feature",
  "properties": {
    "addr:full":"8207 Cloverleaf Dr Ste B Millersville MD 21108",
    "addr:housenumber":"8207",
    "addr:postcode":"21108",
    "addr:street":"Cloverleaf Dr Ste B",
    "iso:country":"US",
    "sg:address":"8207 Cloverleaf Dr Ste B",
    "sg:city":"Millersville",
    "sg:classifiers":[
        {
            "category":"Building & Trades",
            "subcategory":"Landscaping Services",
            "type":"Services"
        },
        {
            "category":"Home & Garden",
            "subcategory":"Garden Supply",
            "type":"Retail Goods"
        },
        {
            "category":"Wholesale",
            "subcategory":"Machinery & Supplies",
            "type":"Manufacturing & Wholesale Goods"
        },
        {
            "category":"Home & Garden",
            "subcategory":"Home Furnishings",
            "type":"Retail Goods"
        },
        {
            "category":"Professional",
            "subcategory":"Business Services",
            "type":"Services"
        }
    ],
    "sg:phone":"+1 410 761 9455",
    "sg:postcode":"21108",
    "sg:province":"MD",
    "sg:tags":[
        "lawn",
        "consultant",
        "fixture",
        "irrigation",
        "system",
        "equipment",
        "lighting",
        "maintenance"
    ],
    "sg:website":"http://www.thesprinklerstore.com",
    "wof:name":"Aquarius Irrigation Supply Inc",
    "wof:placetype":"venue"
},
  "geometry": {"coordinates":[-76.635682,39.12114],"type":"Point"}
}