{
  "type": "Feature",
  "properties": {
    "addr:full":"12746 Pearson Dr Waldorf MD 20602",
    "addr:housenumber":"12746",
    "addr:postcode":"20602",
    "addr:street":"Pearson Dr",
    "iso:country":"US",
    "sg:address":"12746 Pearson Dr",
    "sg:city":"Waldorf",
    "sg:classifiers":[
        {
            "category":"Shopping",
            "subcategory":"Gifts & Souvenirs",
            "type":"Retail Goods"
        }
    ],
    "sg:phone":"+1 301 843 8000",
    "sg:postcode":"20602",
    "sg:province":"MD",
    "sg:tags":[
        "shop"
    ],
    "wof:name":"Judy's Hallmark",
    "wof:placetype":"venue"
},
  "geometry": {"coordinates":[-76.86780899999999,38.588928],"type":"Point"}
}