{
  "type": "Feature",
  "properties": {
    "iso:country":"US",
    "sg:address":"331 Johnsville Rd",
    "sg:city":"Keymar",
    "sg:classifiers":[
        {
            "category":"Place Of Worship",
            "subcategory":"Church",
            "type":"Public Place"
        },
        {
            "category":"Place Of Worship",
            "type":"Public Place"
        }
    ],
    "sg:phone":"+1 410 775 1619",
    "sg:postcode":"21757",
    "sg:province":"MD",
    "sg:tags":[
        "churches-methodist"
    ],
    "wof:name":"Middleburg United Methodist",
    "wof:placetype":"venue"
},
  "geometry": {"coordinates":[-77.22583,39.583734],"type":"Point"}
}