{
  "type": "Feature",
  "properties": {
    "addr:full":"16925 York Rd Monkton MD 21111",
    "addr:housenumber":"16925",
    "addr:postcode":"21111",
    "addr:street":"York Rd",
    "iso:country":"US",
    "sg:address":"16925 York Rd",
    "sg:city":"Monkton",
    "sg:classifiers":[
        {
            "category":"Autos & Motor Vehicles",
            "subcategory":"Auto Supplies",
            "type":"Retail Goods"
        },
        {
            "category":"Wholesale",
            "subcategory":"Electrical",
            "type":"Manufacturing & Wholesale Goods"
        }
    ],
    "sg:phone":"+1 410 329 6611",
    "sg:postcode":"21111",
    "sg:province":"MD",
    "sg:tags":[
        "battery",
        "automobile",
        "part",
        "accessory"
    ],
    "sg:website":"http://www.napaonline.com",
    "wof:name":"Napa Auto Parts",
    "wof:placetype":"venue"
},
  "geometry": {"coordinates":[-76.66312000000001,39.58887],"type":"Point"}
}