{
  "type": "Feature",
  "properties": {
    "iso:country":"US",
    "sg:address":"11259 Lockwood Dr",
    "sg:city":"Silver Spring",
    "sg:classifiers":[
        {
            "category":"Professional",
            "subcategory":"Lawyer & Legal Services",
            "type":"Services"
        }
    ],
    "sg:phone":"+1 301 681 6700",
    "sg:postcode":"20901",
    "sg:province":"MD",
    "wof:name":"Gilliam-Collier Vanessa Atty",
    "wof:placetype":"venue"
},
  "geometry": {"coordinates":[-76.9897,39.0401],"type":"Point"}
}