{
  "type": "Feature",
  "properties": {
    "iso:country":"US",
    "sg:address":"228 W Lexington St",
    "sg:city":"Baltimore",
    "sg:classifiers":[
        {
            "category":"Place Of Worship",
            "type":"Public Place"
        },
        {
            "category":"Organizations",
            "subcategory":"Non-profit Organization",
            "type":"Services"
        }
    ],
    "sg:phone":"+1 410 625 2220",
    "sg:postcode":"21201",
    "sg:province":"MD",
    "sg:tags":[
        "community",
        "service/non-profit",
        "church"
    ],
    "wof:name":"Catholic Relief Services Ussc",
    "wof:placetype":"venue"
},
  "geometry": {"coordinates":[-76.61916100000001,39.291933],"type":"Point"}
}