{
  "type": "Feature",
  "properties": {
    "addr:full":"10 Foreston Valley Ct Parkton MD 21120",
    "addr:housenumber":"10",
    "addr:postcode":"21120",
    "addr:street":"Foreston Valley Ct",
    "iso:country":"US",
    "sg:address":"10 Foreston Valley Ct",
    "sg:city":"Parkton",
    "sg:classifiers":[
        {
            "category":"Building & Trades",
            "subcategory":"Electrical",
            "type":"Services"
        }
    ],
    "sg:phone":"+1 410 239 4292",
    "sg:postcode":"21120",
    "sg:province":"MD",
    "sg:tags":[
        "electric",
        "contractor"
    ],
    "wof:name":"Mac Electric Co",
    "wof:placetype":"venue"
},
  "geometry": {"coordinates":[-76.76274100000001,39.617132],"type":"Point"}
}