{
  "type": "Feature",
  "properties": {
    "addr:full":"624 Runabout Loop Solomons MD 20688",
    "addr:housenumber":"624",
    "addr:postcode":"20688",
    "addr:street":"Runabout Loop",
    "iso:country":"US",
    "sg:address":"624 Runabout Loop",
    "sg:city":"Solomons",
    "sg:classifiers":[
        {
            "category":"Professional",
            "subcategory":"Computer Services",
            "type":"Services"
        }
    ],
    "sg:phone":"+1 410 326 2849",
    "sg:postcode":"20688",
    "sg:province":"MD",
    "sg:tags":[
        "software",
        "programing",
        "custom"
    ],
    "wof:name":"William Dry",
    "wof:placetype":"venue"
},
  "geometry": {"coordinates":[-76.46181300000001,38.338904],"type":"Point"}
}