{
  "type": "Feature",
  "properties": {
    "addr:full":"6010 Executive Blvd Rockville MD 20852",
    "addr:housenumber":"6010",
    "addr:postcode":"20852",
    "addr:street":"Executive Blvd",
    "iso:country":"US",
    "sg:address":"6010 Executive Blvd",
    "sg:city":"Rockville",
    "sg:classifiers":[
        {
            "category":"Travel",
            "subcategory":"Travel Agent",
            "type":"Entertainment"
        }
    ],
    "sg:phone":"+1 301 816 2163",
    "sg:postcode":"20852",
    "sg:province":"MD",
    "sg:tags":[
        "agency",
        "bureau"
    ],
    "wof:name":"World Travel Svc",
    "wof:placetype":"venue"
},
  "geometry": {"coordinates":[-77.124206,39.048585],"type":"Point"}
}