{
  "type": "Feature",
  "properties": {
    "addr:full":"2613 Lighthouse Ln Baltimore MD 21224",
    "addr:housenumber":"2613",
    "addr:postcode":"21224",
    "addr:street":"Lighthouse Ln",
    "iso:country":"US",
    "sg:address":"2613 Lighthouse Ln",
    "sg:city":"Baltimore",
    "sg:classifiers":[
        {
            "category":"Home & Garden",
            "subcategory":"Carpets & Floor Coverings",
            "type":"Retail Goods"
        }
    ],
    "sg:phone":"+1 410 563 0192",
    "sg:postcode":"21224",
    "sg:province":"MD",
    "sg:tags":[
        "distributor",
        "rug",
        "manufacturer"
    ],
    "wof:name":"701 S Streeper St",
    "wof:placetype":"venue"
},
  "geometry": {"coordinates":[-76.57966999999999,39.278469],"type":"Point"}
}