{
  "type": "Feature",
  "properties": {
    "iso:country":"US",
    "sg:address":"8837 Brookville Rd",
    "sg:city":"Silver Spring",
    "sg:classifiers":[
        {
            "category":"Retail",
            "subcategory":"Auto Repair",
            "type":"Services"
        }
    ],
    "sg:phone":"+1 301 565 0002",
    "sg:postcode":"20910",
    "sg:province":"MD",
    "sg:tags":[
        "body",
        "automobile",
        "painting"
    ],
    "wof:name":"Action Auto Inc",
    "wof:placetype":"venue"
},
  "geometry": {"coordinates":[-77.053908,39.001251],"type":"Point"}
}