{
  "type": "Feature",
  "properties": {
    "addr:full":"19 Newport Dr Forest Hill MD 21050",
    "addr:housenumber":"19",
    "addr:postcode":"21050",
    "addr:street":"Newport Dr",
    "iso:country":"US",
    "sg:address":"19 Newport Dr",
    "sg:city":"Forest Hill",
    "sg:classifiers":[
        {
            "category":"Government",
            "subcategory":"Office",
            "type":"Public Place"
        }
    ],
    "sg:phone":"+1 410 838 3950",
    "sg:postcode":"21050",
    "sg:province":"MD",
    "sg:tags":[
        "federal"
    ],
    "wof:name":"US Consolidated Farm Svc Agcy",
    "wof:placetype":"venue"
},
  "geometry": {"coordinates":[-76.38452599999999,39.578229],"type":"Point"}
}