{
  "type": "Feature",
  "properties": {
    "iso:country":"US",
    "sg:address":"8713 Greenbelt Rd",
    "sg:city":"Greenbelt",
    "sg:classifiers":[
        {
            "category":"Banks & Credit Unions",
            "subcategory":"Investment Brokerage",
            "type":"Services"
        }
    ],
    "sg:phone":"+1 301 522 4484",
    "sg:postcode":"20770",
    "sg:province":"MD",
    "sg:tags":[
        "advisory",
        "financial"
    ],
    "wof:name":"All City Security Inc",
    "wof:placetype":"venue"
},
  "geometry": {"coordinates":[-76.856067,38.991066],"type":"Point"}
}