{
  "type": "Feature",
  "properties": {
    "addr:full":"1703 Dogwood Blossom Ct Accokeek MD 20607",
    "addr:housenumber":"1703",
    "addr:postcode":"20607",
    "addr:street":"Dogwood Blossom Ct",
    "iso:country":"US",
    "sg:address":"1703 Dogwood Blossom Ct",
    "sg:city":"Accokeek",
    "sg:classifiers":[
        {
            "category":"Building & Trades",
            "subcategory":"Construction",
            "type":"Services"
        }
    ],
    "sg:phone":"+1 301 283 0940",
    "sg:postcode":"20607",
    "sg:province":"MD",
    "sg:tags":[
        "contractor",
        "mechanical"
    ],
    "wof:name":"United Mechanical Engineering Services",
    "wof:placetype":"venue"
},
  "geometry": {"coordinates":[-77.038887,38.641881],"type":"Point"}
}