{
  "type": "Feature",
  "properties": {
    "addr:full":"10905 Fort Washington Rd Fort Washington MD 20744",
    "addr:housenumber":"10905",
    "addr:postcode":"20744",
    "addr:street":"Fort Washington Rd",
    "iso:country":"US",
    "sg:address":"10905 Fort Washington Rd",
    "sg:city":"Fort Washington",
    "sg:classifiers":[
        {
            "category":"Health Services",
            "subcategory":"Health Practitioner",
            "type":"Services"
        }
    ],
    "sg:phone":"+1 301 292 1324",
    "sg:postcode":"20744",
    "sg:province":"MD",
    "sg:tags":[
        "psychologist"
    ],
    "wof:name":"Robin Halprin PHD",
    "wof:placetype":"venue"
},
  "geometry": {"coordinates":[-76.99336099999999,38.742754],"type":"Point"}
}