{
  "type": "Feature",
  "properties": {
    "iso:country":"US",
    "sg:address":"2630 Georgetown Rd",
    "sg:city":"Baltimore",
    "sg:classifiers":[
        {
            "category":"Cinema",
            "subcategory":"Movie Rental",
            "type":"Entertainment"
        }
    ],
    "sg:phone":"+1 410 525 1003",
    "sg:postcode":"21230",
    "sg:province":"MD",
    "sg:tags":[
        "game",
        "video"
    ],
    "wof:name":"A J Video Amusements",
    "wof:placetype":"venue"
},
  "geometry": {"coordinates":[-76.658124,39.26834],"type":"Point"}
}