{
  "type": "Feature",
  "properties": {
    "iso:country":"US",
    "sg:address":"21018 Blunt Rd",
    "sg:city":"Germantown",
    "sg:classifiers":[
        {
            "category":"Building & Trades",
            "subcategory":"Landscaping Services",
            "type":"Services"
        }
    ],
    "sg:phone":"+1 301 258 9444",
    "sg:postcode":"20876",
    "sg:province":"MD",
    "sg:tags":[
        "landscape",
        "contractor"
    ],
    "wof:name":"Clayton & Clayton Landscape",
    "wof:placetype":"venue"
},
  "geometry": {"coordinates":[-77.21916899999999,39.197037],"type":"Point"}
}