{
  "type": "Feature",
  "properties": {
    "addr:full":"800 Comanche Dr Oxon Hill MD 20745",
    "addr:housenumber":"800",
    "addr:postcode":"20745",
    "addr:street":"Comanche Dr",
    "iso:country":"US",
    "sg:address":"800 Comanche Dr",
    "sg:city":"Oxon Hill",
    "sg:classifiers":[
        {
            "category":"Education",
            "subcategory":"School",
            "type":"Public Place"
        }
    ],
    "sg:phone":"+1 301 749 4210",
    "sg:postcode":"20745",
    "sg:province":"MD",
    "sg:tags":[
        "high",
        "middle",
        "elementary"
    ],
    "wof:name":"Prince George's County School District",
    "wof:placetype":"venue"
},
  "geometry": {"coordinates":[-76.99371600000001,38.806874],"type":"Point"}
}