{
  "type": "Feature",
  "properties": {
    "iso:country":"US",
    "sg:address":"7519 Oskaloosa Ter",
    "sg:city":"Derwood",
    "sg:classifiers":[
        {
            "category":"Professional",
            "subcategory":"Engineering",
            "type":"Services"
        }
    ],
    "sg:phone":"+1 301 975 9668",
    "sg:postcode":"20855",
    "sg:province":"MD",
    "wof:name":"Catherine W Feng",
    "wof:placetype":"venue"
},
  "geometry": {"coordinates":[-77.152956,39.113046],"type":"Point"}
}