{
  "type": "Feature",
  "properties": {
    "addr:full":"7032 Elm Rd Baltimore MD 21240",
    "addr:housenumber":"7032",
    "addr:postcode":"21240",
    "addr:street":"Elm Rd",
    "iso:country":"US",
    "sg:address":"7032 Elm Rd",
    "sg:city":"Baltimore",
    "sg:classifiers":[
        {
            "category":"Travel",
            "subcategory":"Hotels & Motels",
            "type":"Entertainment"
        }
    ],
    "sg:phone":"+1 410 859 3300",
    "sg:postcode":"21240",
    "sg:province":"MD",
    "sg:website":"http://www.globalconextions.com",
    "wof:name":"Starwood Hotels & Resorts",
    "wof:placetype":"venue"
},
  "geometry": {"coordinates":[-76.675179,39.187981],"type":"Point"}
}