{
  "type": "Feature",
  "properties": {
    "addr:full":"6402 Laurel Dr Baltimore MD 21207",
    "addr:housenumber":"6402",
    "addr:postcode":"21207",
    "addr:street":"Laurel Dr",
    "iso:country":"US",
    "sg:address":"6402 Laurel Dr",
    "sg:city":"Baltimore",
    "sg:classifiers":[
        {
            "category":"Building & Trades",
            "subcategory":"Construction",
            "type":"Services"
        }
    ],
    "sg:phone":"+1 410 298 1532",
    "sg:postcode":"21207",
    "sg:province":"MD",
    "sg:tags":[
        "contractor"
    ],
    "wof:name":"Roy D Farmer",
    "wof:placetype":"venue"
},
  "geometry": {"coordinates":[-76.714094,39.344553],"type":"Point"}
}