{
  "type": "Feature",
  "properties": {
    "addr:full":"2104 Hackney Ct Fallston MD 21047",
    "addr:housenumber":"2104",
    "addr:postcode":"21047",
    "addr:street":"Hackney Ct",
    "iso:country":"US",
    "sg:address":"2104 Hackney Ct",
    "sg:city":"Fallston",
    "sg:classifiers":[
        {
            "category":"Building & Trades",
            "subcategory":"Electrical",
            "type":"Services"
        }
    ],
    "sg:phone":"+1 410 803 2093",
    "sg:postcode":"21047",
    "sg:province":"MD",
    "sg:tags":[
        "electrical",
        "contractor"
    ],
    "wof:name":"Harbor Electric Inc",
    "wof:placetype":"venue"
},
  "geometry": {"coordinates":[-76.431867,39.535857],"type":"Point"}
}