{
  "type": "Feature",
  "properties": {
    "iso:country":"US",
    "sg:address":"9075 Contee Rd",
    "sg:city":"Laurel",
    "sg:classifiers":[
        {
            "category":"Utilities",
            "type":"Services"
        }
    ],
    "sg:phone":"+1 301 369 2880",
    "sg:postcode":"20708",
    "sg:province":"MD",
    "wof:name":"Keys Materials & Utilities Inc",
    "wof:placetype":"venue"
},
  "geometry": {"coordinates":[-76.848862,39.073513],"type":"Point"}
}