{
  "type": "Feature",
  "properties": {
    "iso:country":"US",
    "sg:address":"316 Thaxton St",
    "sg:city":"Gaithersburg",
    "sg:classifiers":[
        {
            "category":"Professional",
            "subcategory":"Computer Services",
            "type":"Services"
        }
    ],
    "sg:phone":"+1 240 246 0344",
    "sg:postcode":"20878",
    "sg:province":"MD",
    "sg:tags":[
        "consultant",
        "designer",
        "datum",
        "system"
    ],
    "wof:name":"Worldwide Media Svc Inc",
    "wof:placetype":"venue"
},
  "geometry": {"coordinates":[-77.24607899999999,39.122989],"type":"Point"}
}