{
  "type": "Feature",
  "properties": {
    "addr:full":"5902 Riggs Rd Hyattsville MD 20783",
    "addr:housenumber":"5902",
    "addr:postcode":"20783",
    "addr:street":"Riggs Rd",
    "iso:country":"US",
    "sg:address":"5902 Riggs Rd",
    "sg:city":"Hyattsville",
    "sg:classifiers":[
        {
            "category":"Retail",
            "subcategory":"Car Wash",
            "type":"Services"
        }
    ],
    "sg:phone":"+1 301 559 4705",
    "sg:postcode":"20783",
    "sg:province":"MD",
    "wof:name":"Dr Wash",
    "wof:placetype":"venue"
},
  "geometry": {"coordinates":[-76.994102,38.962101],"type":"Point"}
}