{
  "type": "Feature",
  "properties": {
    "addr:full":"910 Bestgate Rd Annapolis MD 21401",
    "addr:housenumber":"910",
    "addr:postcode":"21401",
    "addr:street":"Bestgate Rd",
    "iso:country":"US",
    "sg:address":"910 Bestgate Rd",
    "sg:city":"Annapolis",
    "sg:classifiers":[
        {
            "category":"Real Estate",
            "subcategory":"Real Estate Services",
            "type":"Services"
        },
        {
            "category":"Personal",
            "type":"Services"
        },
        {
            "category":"Building & Trades",
            "subcategory":"Cleaning & Sanitation",
            "type":"Services"
        }
    ],
    "sg:phone":"+1 410 266 3166",
    "sg:postcode":"21401",
    "sg:province":"MD",
    "sg:tags":[
        "house",
        "butlers'",
        "maids'",
        "maintenance",
        "cleaners-interior"
    ],
    "sg:website":"http://maidproannapolis.com",
    "wof:name":"MaidPro",
    "wof:placetype":"venue"
},
  "geometry": {"coordinates":[-76.546654,38.992008],"type":"Point"}
}