{
  "type": "Feature",
  "properties": {
    "iso:country":"US",
    "sg:address":"218 N Washington St",
    "sg:city":"Easton",
    "sg:classifiers":[
        {
            "category":"Shopping",
            "subcategory":"Books",
            "type":"Retail Goods"
        }
    ],
    "sg:phone":"+1 410 822 7212",
    "sg:postcode":"21601",
    "sg:province":"MD",
    "sg:tags":[
        "dealer"
    ],
    "wof:name":"News Center",
    "wof:placetype":"venue"
},
  "geometry": {"coordinates":[-76.075884,38.778775],"type":"Point"}
}