{
  "type": "Feature",
  "properties": {
    "addr:full":"12200 Tech Rd Silver Spring MD 20904",
    "addr:housenumber":"12200",
    "addr:postcode":"20904",
    "addr:street":"Tech Rd",
    "iso:country":"US",
    "sg:address":"12200 Tech Rd",
    "sg:city":"Silver Spring",
    "sg:classifiers":[
        {
            "category":"Real Estate",
            "subcategory":"Real Estate Agent",
            "type":"Services"
        }
    ],
    "sg:phone":"+1 301 989 9466",
    "sg:postcode":"20904",
    "sg:province":"MD",
    "wof:name":"American Industrial Properties",
    "wof:placetype":"venue"
},
  "geometry": {"coordinates":[-76.968299,39.053413],"type":"Point"}
}