{
  "type": "Feature",
  "properties": {
    "iso:country":"US",
    "sg:address":"1309 E Gude Dr",
    "sg:city":"Rockville",
    "sg:classifiers":[
        {
            "category":"Shopping",
            "subcategory":"Used Merchandise",
            "type":"Retail Goods"
        }
    ],
    "sg:phone":"+1 301 279 5922",
    "sg:postcode":"20850",
    "sg:province":"MD",
    "sg:tags":[
        "pawnbroker",
        "pawnshop"
    ],
    "wof:name":"Famous Pawnbrokers 41",
    "wof:placetype":"venue"
},
  "geometry": {"coordinates":[-77.136046,39.097324],"type":"Point"}
}