{
  "type": "Feature",
  "properties": {
    "iso:country":"US",
    "sg:address":"15313 Emory Ln",
    "sg:city":"Rockville",
    "sg:classifiers":[
        {
            "category":"Health Services",
            "subcategory":"Doctor",
            "type":"Services"
        }
    ],
    "sg:phone":"+1 301 929 3183",
    "sg:postcode":"20853",
    "sg:province":"MD",
    "sg:tags":[
        "physician",
        "surgeons",
        "medicine",
        "surgeon",
        "rehabilitation",
        "physical"
    ],
    "wof:name":"Dcmv Surgical First Assis",
    "wof:placetype":"venue"
},
  "geometry": {"coordinates":[-77.100453,39.107048],"type":"Point"}
}