{
  "type": "Feature",
  "properties": {
    "addr:full":"1250 Smallwood Dr W Waldorf MD 20603",
    "addr:housenumber":"1250",
    "addr:postcode":"20603",
    "addr:street":"Smallwood Dr W",
    "iso:country":"US",
    "sg:address":"1250 Smallwood Dr W",
    "sg:city":"Waldorf",
    "sg:classifiers":[
        {
            "category":"Home & Garden",
            "subcategory":"Household Appliances",
            "type":"Retail Goods"
        }
    ],
    "sg:phone":"+1 301 870 8322",
    "sg:postcode":"20603",
    "sg:province":"MD",
    "sg:tags":[
        "cleaners",
        "vacuum"
    ],
    "wof:name":"Waldorf Sew & Vac",
    "wof:placetype":"venue"
},
  "geometry": {"coordinates":[-76.9265,38.612377],"type":"Point"}
}