{
  "type": "Feature",
  "properties": {
    "iso:country":"US",
    "sg:address":"6501 E Lombard St",
    "sg:city":"Baltimore",
    "sg:classifiers":[
        {
            "category":"Autos & Motor Vehicles",
            "subcategory":"Automobile Sales",
            "type":"Retail Goods"
        }
    ],
    "sg:phone":"+1 410 633 6666",
    "sg:postcode":"21224",
    "sg:province":"MD",
    "sg:tags":[
        "limo"
    ],
    "wof:name":"Green Sedan",
    "wof:placetype":"venue"
},
  "geometry": {"coordinates":[-76.535639,39.295908],"type":"Point"}
}