{
  "type": "Feature",
  "properties": {
    "addr:full":"3500 9th Street Baltimore MD 21225",
    "addr:housenumber":"3500",
    "addr:postcode":"21225",
    "addr:street":"9Th Street",
    "iso:country":"US",
    "sg:address":"3500 9th Street",
    "sg:city":"Baltimore",
    "sg:classifiers":[
        {
            "category":"Building & Trades",
            "subcategory":"Construction",
            "type":"Services"
        }
    ],
    "sg:phone":"+1 410 254 0111",
    "sg:postcode":"21225",
    "sg:province":"MD",
    "sg:tags":[
        "contractor"
    ],
    "sg:website":"www.dabbco.com",
    "wof:name":"Dabbco Construction Inc",
    "wof:placetype":"venue"
},
  "geometry": {"coordinates":[-76.597128,39.235621],"type":"Point"}
}