{
  "type": "Feature",
  "properties": {
    "addr:full":"985 W Mount Harmony Rd Owings MD 20736",
    "addr:housenumber":"985",
    "addr:postcode":"20736",
    "addr:street":"W Mount Harmony Rd",
    "iso:country":"US",
    "sg:address":"985 W Mount Harmony Rd",
    "sg:city":"Owings",
    "sg:classifiers":[
        {
            "category":"Organizations",
            "subcategory":"Non-profit Organization",
            "type":"Services"
        }
    ],
    "sg:phone":"+1 410 286 0269",
    "sg:postcode":"20736",
    "sg:province":"MD",
    "wof:name":"Mt Harmony Childrens Shelter",
    "wof:placetype":"venue"
},
  "geometry": {"coordinates":[-76.62418700000001,38.70787],"type":"Point"}
}