{
  "type": "Feature",
  "properties": {
    "addr:full":"1350 Sweet Pea Path Crownsville MD 21032",
    "addr:housenumber":"1350",
    "addr:postcode":"21032",
    "addr:street":"Sweet Pea Path",
    "iso:country":"US",
    "sg:address":"1350 Sweet Pea Path",
    "sg:city":"Crownsville",
    "sg:classifiers":[
        {
            "category":"Health Services",
            "subcategory":"Doctor",
            "type":"Services"
        }
    ],
    "sg:phone":"+1 410 987 7375",
    "sg:postcode":"21032",
    "sg:province":"MD",
    "sg:tags":[
        "physician",
        "surgeon"
    ],
    "wof:name":"Raj M Manickam MD",
    "wof:placetype":"venue"
},
  "geometry": {"coordinates":[-76.593152,39.030299],"type":"Point"}
}