{
  "type": "Feature",
  "properties": {
    "iso:country":"US",
    "sg:address":"Frederick Innovative Technology Center 4539 Metropolitan Ct. #260",
    "sg:city":"Frederick",
    "sg:classifiers":[
        {
            "category":"Professional",
            "subcategory":"Management & Consulting",
            "type":"Services"
        }
    ],
    "sg:phone":"+1 888 887 9736",
    "sg:postcode":"21704",
    "sg:province":"MD",
    "sg:tags":[
        "seo",
        "search-engine-optimization-services",
        "auroin-llc",
        "auroin",
        "auroin-complaints-management-system"
    ],
    "sg:website":"http://www.auroin.com/",
    "wof:name":"AuroIN",
    "wof:placetype":"venue"
},
  "geometry": {"coordinates":[-77.413253,39.394484],"type":"Point"}
}