{
  "type": "Feature",
  "properties": {
    "iso:country":"US",
    "sg:address":"19237 Chippendale Cir",
    "sg:city":"Hagerstown",
    "sg:classifiers":[
        {
            "category":"Freight",
            "type":"Transportation"
        }
    ],
    "sg:phone":"+1 301 797 0912",
    "sg:postcode":"21742",
    "sg:province":"MD",
    "sg:tags":[
        "trucking"
    ],
    "wof:name":"Image Transport Svc",
    "wof:placetype":"venue"
},
  "geometry": {"coordinates":[-77.70344,39.674676],"type":"Point"}
}