{
  "type": "Feature",
  "properties": {
    "iso:country":"US",
    "sg:address":"3724 Greenvale Rd",
    "sg:city":"Baltimore",
    "sg:classifiers":[
        {
            "category":"Professional",
            "subcategory":"Detective & Security Services",
            "type":"Services"
        }
    ],
    "sg:phone":"+1 443 743 0786",
    "sg:postcode":"21229",
    "sg:province":"MD",
    "sg:tags":[
        "information",
        "bureau"
    ],
    "wof:name":"Lee's Mobile Pc Service",
    "wof:placetype":"venue"
},
  "geometry": {"coordinates":[-76.67677500000001,39.264415],"type":"Point"}
}