{
  "type": "Feature",
  "properties": {
    "addr:full":"12121 Darnestown Rd Gaithersburg MD 20878",
    "addr:housenumber":"12121",
    "addr:postcode":"20878",
    "addr:street":"Darnestown Rd",
    "iso:country":"US",
    "sg:address":"12121 Darnestown Rd",
    "sg:city":"Gaithersburg",
    "sg:classifiers":[
        {
            "category":"Personal",
            "subcategory":"Tanning Parlor",
            "type":"Services"
        }
    ],
    "sg:phone":"+1 301 948 2595",
    "sg:postcode":"20878",
    "sg:province":"MD",
    "sg:tags":[
        "salon"
    ],
    "wof:name":"At The Beach Tanning",
    "wof:placetype":"venue"
},
  "geometry": {"coordinates":[-77.24994599999999,39.117075],"type":"Point"}
}