{
  "type": "Feature",
  "properties": {
    "addr:full":"801 Light St Baltimore MD 21230",
    "addr:housenumber":"801",
    "addr:postcode":"21230",
    "addr:street":"Light St",
    "iso:country":"US",
    "sg:address":"801 Light St",
    "sg:city":"Baltimore",
    "sg:classifiers":[
        {
            "category":"Home & Garden",
            "subcategory":"Building Materials",
            "type":"Retail Goods"
        },
        {
            "category":"Building & Trades",
            "subcategory":"Construction",
            "type":"Services"
        }
    ],
    "sg:phone":"+1 410 332 1500",
    "sg:postcode":"21230",
    "sg:province":"MD",
    "sg:tags":[
        "tile",
        "materials-wholesale",
        "contractor",
        "manufacturer",
        "floor"
    ],
    "sg:website":"http://www.charlestiles.com",
    "wof:name":"Charles Tiles",
    "wof:placetype":"venue"
},
  "geometry": {"coordinates":[-76.61267100000001,39.279949],"type":"Point"}
}