{
  "type": "Feature",
  "properties": {
    "iso:country":"US",
    "sg:address":"7717 Westfield Rd",
    "sg:city":"Dundalk",
    "sg:phone":"+1 410 288 6688",
    "sg:postcode":"21222",
    "sg:province":"MD",
    "wof:name":"Crown Pizza & Wings",
    "wof:placetype":"venue"
},
  "geometry": {"coordinates":[-76.50134300000001,39.271912],"type":"Point"}
}