{
  "type": "Feature",
  "properties": {
    "iso:country":"US",
    "sg:address":"7750 Old Georgetown Rd",
    "sg:city":"Bethesda",
    "sg:classifiers":[
        {
            "category":"Restaurant",
            "type":"Food & Drink"
        }
    ],
    "sg:phone":"+1 301 656 6262",
    "sg:postcode":"20814",
    "sg:province":"MD",
    "sg:tags":[
        "pizza"
    ],
    "sg:website":"www.mandnspizza.com/",
    "wof:name":"M and N's Pizza",
    "wof:placetype":"venue"
},
  "geometry": {"coordinates":[-77.097922,38.986466],"type":"Point"}
}