{
  "type": "Feature",
  "properties": {
    "addr:full":"4995 Fairview Ave Linthicum Hts MD 21090",
    "addr:housenumber":"4995",
    "addr:postcode":"21090",
    "addr:street":"Fairview Ave",
    "iso:country":"US",
    "sg:address":"4995 Fairview Ave",
    "sg:city":"Linthicum Hts",
    "sg:classifiers":[
        {
            "category":"Manufacturing",
            "subcategory":"Signs",
            "type":"Manufacturing & Wholesale Goods"
        }
    ],
    "sg:phone":"+1 410 636 2882",
    "sg:postcode":"21090",
    "sg:province":"MD",
    "wof:name":"Design Plus Signs",
    "wof:placetype":"venue"
},
  "geometry": {"coordinates":[-76.660515,39.225903],"type":"Point"}
}