{
  "type": "Feature",
  "properties": {
    "addr:full":"5696 Argyle Dr Parsonsburg MD 21849",
    "addr:housenumber":"5696",
    "addr:postcode":"21849",
    "addr:street":"Argyle Dr",
    "iso:country":"US",
    "sg:address":"5696 Argyle Dr",
    "sg:city":"Parsonsburg",
    "sg:classifiers":[
        {
            "category":"Building & Trades",
            "subcategory":"Construction",
            "type":"Services"
        }
    ],
    "sg:phone":"+1 410 742 4150",
    "sg:postcode":"21849",
    "sg:province":"MD",
    "sg:tags":[
        "home",
        "improvement"
    ],
    "wof:name":"Nock Home Improvement",
    "wof:placetype":"venue"
},
  "geometry": {"coordinates":[-75.476389,38.348231],"type":"Point"}
}