{
  "type": "Feature",
  "properties": {
    "addr:full":"7350 Van Dusen Rd Ste 260 Laurel MD 20707",
    "addr:housenumber":"7350",
    "addr:postcode":"20707",
    "addr:street":"Van Dusen Rd Ste 260",
    "iso:country":"US",
    "sg:address":"7350 Van Dusen Rd Ste 260",
    "sg:city":"Laurel",
    "sg:classifiers":[
        {
            "category":"Health Services",
            "subcategory":"Doctor",
            "type":"Services"
        }
    ],
    "sg:phone":"+1 301 497 9990",
    "sg:postcode":"20707",
    "sg:province":"MD",
    "wof:name":"De Lima Christine MD",
    "wof:placetype":"venue"
},
  "geometry": {"coordinates":[-76.881947,39.08469],"type":"Point"}
}