{
  "type": "Feature",
  "properties": {
    "addr:full":"8008 Bellona Ave Baltimore MD 21204",
    "addr:housenumber":"8008",
    "addr:postcode":"21204",
    "addr:street":"Bellona Ave",
    "iso:country":"US",
    "sg:address":"8008 Bellona Ave",
    "sg:city":"Baltimore",
    "sg:classifiers":[
        {
            "category":"Professional",
            "type":"Services"
        }
    ],
    "sg:phone":"+1 410 823 3593",
    "sg:postcode":"21204",
    "sg:province":"MD",
    "wof:name":"Stephen F Davitt",
    "wof:placetype":"venue"
},
  "geometry": {"coordinates":[-76.641955,39.413216],"type":"Point"}
}