{
  "type": "Feature",
  "properties": {
    "iso:country":"US",
    "sg:address":"1011 N Calvert St",
    "sg:city":"Baltimore",
    "sg:classifiers":[
        {
            "category":"Professional",
            "subcategory":"Lawyer & Legal Services",
            "type":"Services"
        }
    ],
    "sg:phone":"+1 410 625 4878",
    "sg:postcode":"21202",
    "sg:province":"MD",
    "wof:name":"Davis Michael W Atty",
    "wof:placetype":"venue"
},
  "geometry": {"coordinates":[-76.613297,39.301399],"type":"Point"}
}