{
  "type": "Feature",
  "properties": {
    "addr:full":"915 North Ave Sykesville MD 21784",
    "addr:housenumber":"915",
    "addr:postcode":"21784",
    "addr:street":"North Ave",
    "iso:country":"US",
    "sg:address":"915 North Ave",
    "sg:city":"Sykesville",
    "sg:classifiers":[
        {
            "category":"Building & Trades",
            "subcategory":"Construction",
            "type":"Services"
        }
    ],
    "sg:phone":"+1 410 795 3335",
    "sg:postcode":"21784",
    "sg:province":"MD",
    "sg:tags":[
        "general",
        "contractor"
    ],
    "wof:name":"O A & Assoc LTD",
    "wof:placetype":"venue"
},
  "geometry": {"coordinates":[-76.96495,39.392061],"type":"Point"}
}