{
  "type": "Feature",
  "properties": {
    "addr:full":"7610 Shirley Blvd Port Tobacco MD 20677",
    "addr:housenumber":"7610",
    "addr:postcode":"20677",
    "addr:street":"Shirley Blvd",
    "iso:country":"US",
    "sg:address":"7610 Shirley Blvd",
    "sg:city":"Port Tobacco",
    "sg:classifiers":[
        {
            "category":"Retail",
            "subcategory":"Repair Shop",
            "type":"Services"
        }
    ],
    "sg:phone":"+1 301 932 2486",
    "sg:postcode":"20677",
    "sg:province":"MD",
    "wof:name":"American Boat Company",
    "wof:placetype":"venue"
},
  "geometry": {"coordinates":[-77.028192,38.505916],"type":"Point"}
}