{
  "type": "Feature",
  "properties": {
    "addr:full":"803 Wilson Rd Rising Sun MD 21911",
    "addr:housenumber":"803",
    "addr:postcode":"21911",
    "addr:street":"Wilson Rd",
    "iso:country":"US",
    "sg:address":"803 Wilson Rd",
    "sg:city":"Rising Sun",
    "sg:classifiers":[
        {
            "category":"Building & Trades",
            "subcategory":"Construction",
            "type":"Services"
        }
    ],
    "sg:phone":"+1 410 658 7325",
    "sg:postcode":"21911",
    "sg:province":"MD",
    "sg:tags":[
        "paving",
        "contractor"
    ],
    "wof:name":"Accu Seal Inc",
    "wof:placetype":"venue"
},
  "geometry": {"coordinates":[-76.012202,39.700278],"type":"Point"}
}