{
  "type": "Feature",
  "properties": {
    "addr:full":"9701 Apollo Dr Upper Marlboro MD 20774",
    "addr:housenumber":"9701",
    "addr:postcode":"20774",
    "addr:street":"Apollo Dr",
    "iso:country":"US",
    "sg:address":"9701 Apollo Dr",
    "sg:city":"Upper Marlboro",
    "sg:classifiers":[
        {
            "category":"Insurance",
            "subcategory":"Insurance Agent",
            "type":"Services"
        }
    ],
    "sg:phone":"+1 301 420 9651",
    "sg:postcode":"20774",
    "sg:province":"MD",
    "wof:name":"American General Life Ins Co",
    "wof:placetype":"venue"
},
  "geometry": {"coordinates":[-76.83817500000001,38.905117],"type":"Point"}
}