{
  "type": "Feature",
  "properties": {
    "iso:country":"US",
    "sg:address":"1107 N Point Blvd Ste 201",
    "sg:city":"Baltimore",
    "sg:classifiers":[
        {
            "category":"Health Services",
            "subcategory":"Clinic",
            "type":"Services"
        },
        {
            "category":"Health Services",
            "subcategory":"Hospital",
            "type":"Services"
        }
    ],
    "sg:phone":"+1 410 288 2010",
    "sg:postcode":"21224",
    "sg:province":"MD",
    "sg:tags":[
        "medical",
        "dialysis"
    ],
    "wof:name":"Porter Dialysis Center",
    "wof:placetype":"venue"
},
  "geometry": {"coordinates":[-76.50732000000001,39.29061],"type":"Point"}
}