{
  "type": "Feature",
  "properties": {
    "iso:country":"US",
    "sg:address":"4517 Harford Rd",
    "sg:city":"Baltimore",
    "sg:classifiers":[
        {
            "category":"Communications",
            "subcategory":"Newspaper",
            "type":"Services"
        }
    ],
    "sg:phone":"+1 410 254 9200",
    "sg:postcode":"21214",
    "sg:province":"MD",
    "sg:tags":[
        "magazine"
    ],
    "wof:name":"Adam Magazine For Men",
    "wof:placetype":"venue"
},
  "geometry": {"coordinates":[-76.571404,39.341202],"type":"Point"}
}