{
  "type": "Feature",
  "properties": {
    "addr:full":"512 Roland Ave Pikesville MD 21208",
    "addr:housenumber":"512",
    "addr:postcode":"21208",
    "addr:street":"Roland Ave",
    "iso:country":"US",
    "sg:address":"512 Roland Ave",
    "sg:city":"Pikesville",
    "sg:classifiers":[
        {
            "category":"Building & Trades",
            "subcategory":"Landscaping Services",
            "type":"Services"
        }
    ],
    "sg:phone":"+1 410 486 0425",
    "sg:postcode":"21208",
    "sg:province":"MD",
    "sg:tags":[
        "lawn",
        "maintenance"
    ],
    "wof:name":"Lorenz",
    "wof:placetype":"venue"
},
  "geometry": {"coordinates":[-76.721501,39.365624],"type":"Point"}
}