{
  "type": "Feature",
  "properties": {
    "iso:country":"US",
    "sg:address":"2415 Musgrove Rd",
    "sg:city":"Silver Spring",
    "sg:classifiers":[
        {
            "category":"Health Services",
            "subcategory":"Doctor",
            "type":"Services"
        }
    ],
    "sg:phone":"+1 301 622 1106",
    "sg:postcode":"20904",
    "sg:province":"MD",
    "sg:tags":[
        "physician",
        "surgeon"
    ],
    "wof:name":"Pediatric Assoc Montgomery",
    "wof:placetype":"venue"
},
  "geometry": {"coordinates":[-76.959631,39.067794],"type":"Point"}
}