{
  "type": "Feature",
  "properties": {
    "addr:full":"11052 Pulaski Hwy White Marsh MD 21162",
    "addr:housenumber":"11052",
    "addr:postcode":"21162",
    "addr:street":"Pulaski Hwy",
    "iso:country":"US",
    "sg:address":"11052 Pulaski Hwy",
    "sg:city":"White Marsh",
    "sg:classifiers":[
        {
            "category":"Freight",
            "type":"Transportation"
        }
    ],
    "sg:phone":"+1 410 335 4600",
    "sg:postcode":"21162",
    "sg:province":"MD",
    "sg:tags":[
        "recreational",
        "vehicle"
    ],
    "wof:name":"Red Lion Trading",
    "wof:placetype":"venue"
},
  "geometry": {"coordinates":[-76.4195,39.38657],"type":"Point"}
}