{
  "type": "Feature",
  "properties": {
    "addr:full":"20 Foxmoor Ct Owings Mills MD 21117",
    "addr:housenumber":"20",
    "addr:postcode":"21117",
    "addr:street":"Foxmoor Ct",
    "iso:country":"US",
    "sg:address":"20 Foxmoor Ct",
    "sg:city":"Owings Mills",
    "sg:classifiers":[
        {
            "category":"Organizations",
            "subcategory":"Religious Organization",
            "type":"Services"
        }
    ],
    "sg:phone":"+1 410 356 3671",
    "sg:postcode":"21117",
    "sg:province":"MD",
    "wof:name":"Levi Kaplan",
    "wof:placetype":"venue"
},
  "geometry": {"coordinates":[-76.79121499999999,39.452736],"type":"Point"}
}