{
  "type": "Feature",
  "properties": {
    "addr:full":"841 E Fort Ave Baltimore MD 21230",
    "addr:housenumber":"841",
    "addr:postcode":"21230",
    "addr:street":"E Fort Ave",
    "iso:country":"US",
    "sg:address":"841 E Fort Ave",
    "sg:city":"Baltimore",
    "sg:classifiers":[
        {
            "category":"Restaurant",
            "type":"Food & Drink"
        }
    ],
    "sg:menulink":"http://www.allmenus.com/md/baltimore/215524-mcdonalds/menu/",
    "sg:postcode":"21230",
    "sg:province":"MD",
    "sg:tags":[
        "burger",
        "american"
    ],
    "wof:name":"McDonald's",
    "wof:placetype":"venue"
},
  "geometry": {"coordinates":[-76.60209500000001,39.271916],"type":"Point"}
}