{
  "type": "Feature",
  "properties": {
    "iso:country":"US",
    "sg:address":"11810 Parklawn Dr",
    "sg:city":"Rockville",
    "sg:classifiers":[
        {
            "category":"Professional",
            "subcategory":"Computer Services",
            "type":"Services"
        }
    ],
    "sg:phone":"+1 301 468 3650",
    "sg:postcode":"20852",
    "sg:province":"MD",
    "sg:tags":[
        "internet"
    ],
    "sg:website":"www.marketresearch.com",
    "wof:name":"Market Research Com",
    "wof:placetype":"venue"
},
  "geometry": {"coordinates":[-77.10207200000001,39.048885],"type":"Point"}
}