{
  "type": "Feature",
  "properties": {
    "addr:full":"1085 Maryland Ave Hagerstown MD 21740",
    "addr:housenumber":"1085",
    "addr:postcode":"21740",
    "addr:street":"Maryland Ave",
    "iso:country":"US",
    "sg:address":"1085 Maryland Ave",
    "sg:city":"Hagerstown",
    "sg:classifiers":[
        {
            "category":"Restaurant",
            "type":"Food & Drink"
        }
    ],
    "sg:menulink":"http://www.allmenus.com/md/hagerstown/71681-pizza-hut/menu/",
    "sg:phone":"+1 301 739 7547",
    "sg:postcode":"21740",
    "sg:province":"MD",
    "sg:tags":[
        "american",
        "pizza"
    ],
    "wof:name":"Pizza Hut",
    "wof:placetype":"venue"
},
  "geometry": {"coordinates":[-77.732409,39.623613],"type":"Point"}
}