{
  "type": "Feature",
  "properties": {
    "addr:full":"2030 Liberty Rd Sykesville MD 21784",
    "addr:housenumber":"2030",
    "addr:postcode":"21784",
    "addr:street":"Liberty Rd",
    "iso:country":"US",
    "sg:address":"2030 Liberty Rd",
    "sg:city":"Sykesville",
    "sg:classifiers":[
        {
            "category":"Home & Garden",
            "subcategory":"Home Furnishings",
            "type":"Retail Goods"
        }
    ],
    "sg:phone":"+1 410 552 9797",
    "sg:postcode":"21784",
    "sg:province":"MD",
    "sg:tags":[
        "pottery"
    ],
    "wof:name":"Glazed To Perfection",
    "wof:placetype":"venue"
},
  "geometry": {"coordinates":[-76.92334,39.396908],"type":"Point"}
}