{
  "type": "Feature",
  "properties": {
    "iso:country":"US",
    "sg:address":"7901 Sandy Spring Rd Ste 500",
    "sg:city":"Laurel",
    "sg:classifiers":[
        {
            "category":"Building & Trades",
            "subcategory":"Construction",
            "type":"Services"
        }
    ],
    "sg:phone":"+1 703 922 2161",
    "sg:postcode":"20707",
    "sg:province":"MD",
    "sg:tags":[
        "contractor"
    ],
    "wof:name":"Gilbane Building Company",
    "wof:placetype":"venue"
},
  "geometry": {"coordinates":[-76.872803,39.1026],"type":"Point"}
}