{
  "type": "Feature",
  "properties": {
    "iso:country":"US",
    "sg:address":"3914 Hickory Ave",
    "sg:city":"Baltimore",
    "sg:classifiers":[
        {
            "category":"Retail",
            "subcategory":"Auto Repair",
            "type":"Services"
        }
    ],
    "sg:phone":"+1 301 577 7802",
    "sg:postcode":"21211",
    "sg:province":"MD",
    "wof:name":"American Air Filter-Aaf International",
    "wof:placetype":"venue"
},
  "geometry": {"coordinates":[-76.635237,39.335565],"type":"Point"}
}