{
  "type": "Feature",
  "properties": {
    "addr:full":"525 Old Westminster Pike Westminster MD 21157",
    "addr:housenumber":"525",
    "addr:postcode":"21157",
    "addr:street":"Old Westminster Pike",
    "iso:country":"US",
    "sg:address":"525 Old Westminster Pike",
    "sg:city":"Westminster",
    "sg:classifiers":[
        {
            "category":"Building & Trades",
            "subcategory":"Construction",
            "type":"Services"
        }
    ],
    "sg:phone":"+1 410 239 0924",
    "sg:postcode":"21157",
    "sg:province":"MD",
    "sg:tags":[
        "maker",
        "cabinet"
    ],
    "wof:name":"Dundee Cabinet & Remodeling",
    "wof:placetype":"venue"
},
  "geometry": {"coordinates":[-76.97959,39.561755],"type":"Point"}
}