{
  "type": "Feature",
  "properties": {
    "addr:full":"3712 Eastern Ave Baltimore MD 21224",
    "addr:housenumber":"3712",
    "addr:postcode":"21224",
    "addr:street":"Eastern Ave",
    "iso:country":"US",
    "sg:address":"3712 Eastern Ave",
    "sg:city":"Baltimore",
    "sg:classifiers":[
        {
            "category":"Farming",
            "subcategory":"Nursery",
            "type":"Manufacturing & Wholesale Goods"
        },
        {
            "category":"Home & Garden",
            "subcategory":"Garden Supply",
            "type":"Retail Goods"
        }
    ],
    "sg:phone":"+1 410 327 8403",
    "sg:postcode":"21224",
    "sg:province":"MD",
    "sg:tags":[
        "tree",
        "nurseries-plants"
    ],
    "wof:name":"Home Harvest Garden Sup",
    "wof:placetype":"venue"
},
  "geometry": {"coordinates":[-76.566261,39.286664],"type":"Point"}
}