{
  "type": "Feature",
  "properties": {
    "iso:country":"US",
    "sg:address":"12 W 20th St",
    "sg:city":"Baltimore",
    "sg:classifiers":[
        {
            "category":"Restaurant",
            "type":"Food & Drink"
        }
    ],
    "sg:phone":"+1 410 244 5501",
    "sg:postcode":"21218",
    "sg:province":"MD",
    "sg:tags":[
        "korean"
    ],
    "wof:name":"Nak Won Korean Restaurant",
    "wof:placetype":"venue"
},
  "geometry": {"coordinates":[-76.616997,39.312302],"type":"Point"}
}