{
  "type": "Feature",
  "properties": {
    "iso:country":"US",
    "sg:address":"695 Hanover Pike",
    "sg:city":"Hampstead",
    "sg:classifiers":[
        {
            "category":"Personal",
            "subcategory":"Beauty Salon",
            "type":"Services"
        }
    ],
    "sg:phone":"+1 410 374 2880",
    "sg:postcode":"21074",
    "sg:province":"MD",
    "sg:website":"www.ultimateimagedayspa.com",
    "wof:name":"Ultimate Image",
    "wof:placetype":"venue"
},
  "geometry": {"coordinates":[-76.84545300000001,39.592842],"type":"Point"}
}