{
  "type": "Feature",
  "properties": {
    "iso:country":"US",
    "sg:address":"245 C St",
    "sg:city":"Solomons",
    "sg:classifiers":[
        {
            "category":"Recreation",
            "subcategory":"Marina",
            "type":"Entertainment"
        }
    ],
    "sg:phone":"+1 410 326 2166",
    "sg:postcode":"20688",
    "sg:province":"MD",
    "sg:tags":[
        "repairing",
        "boat"
    ],
    "sg:website":"www.zahnisers.com",
    "wof:name":"Zahniser's Yachting Ctr",
    "wof:placetype":"venue"
},
  "geometry": {"coordinates":[-76.46148700000001,38.328085],"type":"Point"}
}