{
  "type": "Feature",
  "properties": {
    "iso:country":"US",
    "sg:address":"8740 Cherry Ln",
    "sg:city":"Laurel",
    "sg:classifiers":[
        {
            "category":"Retail",
            "subcategory":"Auto Repair",
            "type":"Services"
        }
    ],
    "sg:phone":"+1 301 604 1448",
    "sg:postcode":"20707",
    "sg:province":"MD",
    "sg:tags":[
        "repairing",
        "automobile"
    ],
    "wof:name":"All Pro Car Care Brakes",
    "wof:placetype":"venue"
},
  "geometry": {"coordinates":[-76.853606,39.08789],"type":"Point"}
}