{
  "type": "Feature",
  "properties": {
    "addr:full":"6500 Quad Ave Baltimore MD 21205",
    "addr:housenumber":"6500",
    "addr:postcode":"21205",
    "addr:street":"Quad Ave",
    "iso:country":"US",
    "sg:address":"6500 Quad Ave",
    "sg:city":"Baltimore",
    "sg:classifiers":[
        {
            "category":"Wholesale",
            "subcategory":"Durable Goods & Equipment",
            "type":"Manufacturing & Wholesale Goods"
        }
    ],
    "sg:phone":"+1 410 288 2920",
    "sg:postcode":"21205",
    "sg:province":"MD",
    "sg:tags":[
        "exporter"
    ],
    "wof:name":"Global Packaging",
    "wof:placetype":"venue"
},
  "geometry": {"coordinates":[-76.54057,39.299036],"type":"Point"}
}