{
  "type": "Feature",
  "properties": {
    "addr:full":"528 Cranbrook Rd Cockeysville MD 21030",
    "addr:housenumber":"528",
    "addr:postcode":"21030",
    "addr:street":"Cranbrook Rd",
    "iso:country":"US",
    "sg:address":"528 Cranbrook Rd",
    "sg:city":"Cockeysville",
    "sg:classifiers":[
        {
            "category":"Restaurant",
            "type":"Food & Drink"
        }
    ],
    "sg:menulink":"http://www.allmenus.com/md/hunt-valley/215581-mcdonalds/menu/",
    "sg:postcode":"21030",
    "sg:province":"MD",
    "sg:tags":[
        "burger",
        "american"
    ],
    "wof:name":"McDonald's",
    "wof:placetype":"venue"
},
  "geometry": {"coordinates":[-76.623628,39.471709],"type":"Point"}
}