{
  "type": "Feature",
  "properties": {
    "addr:full":"40 W Chesapeake Ave Baltimore MD 21204",
    "addr:housenumber":"40",
    "addr:postcode":"21204",
    "addr:street":"W Chesapeake Ave",
    "iso:country":"US",
    "sg:address":"40 W Chesapeake Ave",
    "sg:city":"Baltimore",
    "sg:classifiers":[
        {
            "category":"Professional",
            "subcategory":"Research",
            "type":"Services"
        }
    ],
    "sg:phone":"+1 410 321 6647",
    "sg:postcode":"21204",
    "sg:province":"MD",
    "sg:tags":[
        "foundation",
        "philanthropic"
    ],
    "wof:name":"Immune Deficiency Foundation",
    "wof:placetype":"venue"
},
  "geometry": {"coordinates":[-76.604589,39.399635],"type":"Point"}
}