{
  "type": "Feature",
  "properties": {
    "addr:full":"3445 Bruton Parish Way Silver Spring MD 20904",
    "addr:housenumber":"3445",
    "addr:postcode":"20904",
    "addr:street":"Bruton Parish Way",
    "iso:country":"US",
    "sg:address":"3445 Bruton Parish Way",
    "sg:city":"Silver Spring",
    "sg:classifiers":[
        {
            "category":"Arts & Performance",
            "subcategory":"Theater",
            "type":"Entertainment"
        }
    ],
    "sg:phone":"+1 301 890 7335",
    "sg:postcode":"20904",
    "sg:province":"MD",
    "sg:tags":[
        "theatrical"
    ],
    "wof:name":"Laurel Community Theatre",
    "wof:placetype":"venue"
},
  "geometry": {"coordinates":[-76.934369,39.083604],"type":"Point"}
}