{
  "type": "Feature",
  "properties": {
    "addr:full":"10378 Baltimore National Pike Ellicott City MD 21042",
    "addr:housenumber":"10378",
    "addr:postcode":"21042",
    "addr:street":"Baltimore National Pike",
    "iso:country":"US",
    "sg:address":"10378 Baltimore National Pike",
    "sg:city":"Ellicott City",
    "sg:classifiers":[
        {
            "category":"Professional",
            "type":"Services"
        }
    ],
    "sg:phone":"+1 410 465 8777",
    "sg:postcode":"21042",
    "sg:province":"MD",
    "sg:tags":[
        "establishment"
    ],
    "wof:name":"Mid Atlantic Dist Chr",
    "wof:placetype":"venue"
},
  "geometry": {"coordinates":[-76.86743,39.280347],"type":"Point"}
}