{
  "type": "Feature",
  "properties": {
    "iso:country":"US",
    "sg:address":"17550 W Willard Rd",
    "sg:city":"Poolesville",
    "sg:classifiers":[
        {
            "category":"Organizations",
            "subcategory":"Religious Organization",
            "type":"Services"
        }
    ],
    "sg:phone":"+1 301 972 8151",
    "sg:postcode":"20837",
    "sg:province":"MD",
    "sg:tags":[
        "church"
    ],
    "wof:name":"Poolesville Baptist Church",
    "wof:placetype":"venue"
},
  "geometry": {"coordinates":[-77.42043099999999,39.142482],"type":"Point"}
}