{
  "type": "Feature",
  "properties": {
    "iso:country":"US",
    "sg:address":"3 Research Pl",
    "sg:city":"Rockville",
    "sg:classifiers":[
        {
            "category":"Organizations",
            "subcategory":"Labor Organization",
            "type":"Services"
        }
    ],
    "sg:phone":"+1 301 948 4911",
    "sg:postcode":"20850",
    "sg:province":"MD",
    "sg:website":"www.tcunion.org",
    "wof:name":"Transportation Communications",
    "wof:placetype":"venue"
},
  "geometry": {"coordinates":[-77.184327,39.104716],"type":"Point"}
}