{
  "type": "Feature",
  "properties": {
    "addr:full":"7611 Accokeek Rd Brandywine MD 20613",
    "addr:housenumber":"7611",
    "addr:postcode":"20613",
    "addr:street":"Accokeek Rd",
    "iso:country":"US",
    "sg:address":"7611 Accokeek Rd",
    "sg:city":"Brandywine",
    "sg:classifiers":[
        {
            "category":"Place Of Worship",
            "subcategory":"Church",
            "type":"Public Place"
        },
        {
            "category":"Place Of Worship",
            "type":"Public Place"
        }
    ],
    "sg:phone":"+1 301 782 3552",
    "sg:postcode":"20613",
    "sg:province":"MD",
    "sg:tags":[
        "churches-interdenominational",
        "denomination",
        "churches-various",
        "churches-non-denominational"
    ],
    "wof:name":"New Nations Worship Ministries",
    "wof:placetype":"venue"
},
  "geometry": {"coordinates":[-76.875097,38.701174],"type":"Point"}
}