{
  "type": "Feature",
  "properties": {
    "iso:country":"US",
    "sg:address":"931 Beards Hill Rd",
    "sg:city":"Aberdeen",
    "sg:classifiers":[
        {
            "category":"Shopping",
            "type":"Retail Goods"
        }
    ],
    "sg:phone":"+1 410 676 1101",
    "sg:postcode":"21001",
    "sg:province":"MD",
    "sg:tags":[
        "pet",
        "shop"
    ],
    "wof:name":"House Of Pets",
    "wof:placetype":"venue"
},
  "geometry": {"coordinates":[-76.18355699999999,39.525206],"type":"Point"}
}