{
  "type": "Feature",
  "properties": {
    "iso:country":"US",
    "sg:address":"307 High St",
    "sg:city":"Chestertown",
    "sg:classifiers":[
        {
            "category":"Manufacturing",
            "subcategory":"Printing",
            "type":"Manufacturing & Wholesale Goods"
        }
    ],
    "sg:phone":"+1 410 810 3731",
    "sg:postcode":"21620",
    "sg:province":"MD",
    "sg:tags":[
        "periodical"
    ],
    "wof:name":"Ipo Journal",
    "wof:placetype":"venue"
},
  "geometry": {"coordinates":[-76.067127,39.209367],"type":"Point"}
}