{
  "type": "Feature",
  "properties": {
    "iso:country":"US",
    "sg:address":"3100 Wood Ave",
    "sg:city":"Burtonsville",
    "sg:classifiers":[
        {
            "category":"Social Services",
            "subcategory":"Child Care",
            "type":"Services"
        }
    ],
    "sg:phone":"+1 301 384 8733",
    "sg:postcode":"20866",
    "sg:province":"MD",
    "sg:tags":[
        "day"
    ],
    "wof:name":"Learning Tree Child Development Center",
    "wof:placetype":"venue"
},
  "geometry": {"coordinates":[-76.946602,39.093498],"type":"Point"}
}