{
  "type": "Feature",
  "properties": {
    "addr:full":"11545 Laurelwalk Dr Laurel MD 20708",
    "addr:housenumber":"11545",
    "addr:postcode":"20708",
    "addr:street":"Laurelwalk Dr",
    "iso:country":"US",
    "sg:address":"11545 Laurelwalk Dr",
    "sg:city":"Laurel",
    "sg:classifiers":[
        {
            "category":"Wholesale",
            "subcategory":"Stationery",
            "type":"Manufacturing & Wholesale Goods"
        }
    ],
    "sg:phone":"+1 301 430 7211",
    "sg:postcode":"20708",
    "sg:province":"MD",
    "sg:tags":[
        "supply"
    ],
    "wof:name":"Link Services Inc",
    "wof:placetype":"venue"
},
  "geometry": {"coordinates":[-76.838194,39.047541],"type":"Point"}
}