{
  "type": "Feature",
  "properties": {
    "iso:country":"US",
    "sg:address":"10220 Old Columbia Rd L",
    "sg:city":"Columbia",
    "sg:classifiers":[
        {
            "category":"Wholesale",
            "subcategory":"Medical Equipment & Supplies",
            "type":"Manufacturing & Wholesale Goods"
        }
    ],
    "sg:phone":"+1 410 290 5390",
    "sg:postcode":"21046",
    "sg:province":"MD",
    "sg:tags":[
        "pharmaceutical",
        "products-wholesale",
        "manufacturer"
    ],
    "sg:website":"http://www.celsion.com",
    "wof:name":"Celsion Corporation",
    "wof:placetype":"venue"
},
  "geometry": {"coordinates":[-76.86901899999999,39.177502],"type":"Point"}
}