{
  "type": "Feature",
  "properties": {
    "addr:full":"1305 S Division St Salisbury MD 21804",
    "addr:housenumber":"1305",
    "addr:postcode":"21804",
    "addr:street":"S Division St",
    "iso:country":"US",
    "sg:address":"1305 S Division St",
    "sg:city":"Salisbury",
    "sg:classifiers":[
        {
            "category":"Real Estate",
            "subcategory":"Real Estate Agent",
            "type":"Services"
        }
    ],
    "sg:phone":"+1 410 546 0003",
    "sg:postcode":"21804",
    "sg:province":"MD",
    "wof:name":"Achievers Realty",
    "wof:placetype":"venue"
},
  "geometry": {"coordinates":[-75.59909,38.340045],"type":"Point"}
}