{
  "type": "Feature",
  "properties": {
    "addr:full":"33 E Padonia Rd Timonium MD 21093",
    "addr:housenumber":"33",
    "addr:postcode":"21093",
    "addr:street":"E Padonia Rd",
    "iso:country":"US",
    "sg:address":"33 E Padonia Rd",
    "sg:city":"Timonium",
    "sg:classifiers":[
        {
            "category":"Shopping",
            "subcategory":"Tobacco",
            "type":"Retail Goods"
        }
    ],
    "sg:phone":"+1 410 666 3212",
    "sg:postcode":"21093",
    "sg:province":"MD",
    "sg:tags":[
        "cigarette",
        "cigar",
        "dealer"
    ],
    "wof:name":"Humidour Cigar Shop Inc",
    "wof:placetype":"venue"
},
  "geometry": {"coordinates":[-76.631,39.456457],"type":"Point"}
}