{
  "type": "Feature",
  "properties": {
    "addr:full":"222 Severn Dr Annapolis MD 21401",
    "addr:housenumber":"222",
    "addr:postcode":"21401",
    "addr:street":"Severn Dr",
    "iso:country":"US",
    "sg:address":"222 Severn Dr",
    "sg:city":"Annapolis",
    "sg:phone":"+1 410 626 1640",
    "sg:postcode":"21401",
    "sg:province":"MD",
    "sg:tags":[
        "video",
        "conferencing"
    ],
    "wof:name":"IVCI",
    "wof:placetype":"venue"
},
  "geometry": {"coordinates":[-76.532668,39.007144],"type":"Point"}
}