{
  "type": "Feature",
  "properties": {
    "addr:full":"105 Railroad Ave Elkton MD 21921",
    "addr:housenumber":"105",
    "addr:postcode":"21921",
    "addr:street":"Railroad Ave",
    "iso:country":"US",
    "sg:address":"105 Railroad Ave",
    "sg:city":"Elkton",
    "sg:classifiers":[
        {
            "category":"Government",
            "subcategory":"Office",
            "type":"Public Place"
        }
    ],
    "sg:phone":"+1 410 398 8818",
    "sg:postcode":"21921",
    "sg:province":"MD",
    "sg:tags":[
        "parish",
        "government-county"
    ],
    "sg:website":"http://www.ctom.com",
    "wof:name":"Cecil Cmmn Cllg Cont Educ",
    "wof:placetype":"venue"
},
  "geometry": {"coordinates":[-75.832447,39.610521],"type":"Point"}
}