{
  "type": "Feature",
  "properties": {
    "addr:full":"7860 Quarterfield Rd Severn MD 21144",
    "addr:postcode":"7860;21144",
    "addr:street":"Quarterfield Rd",
    "iso:country":"US",
    "sg:address":"7860 Quarterfield Rd",
    "sg:city":"Severn",
    "sg:classifiers":[
        {
            "category":"Personal",
            "subcategory":"Beauty Salon",
            "type":"Services"
        }
    ],
    "sg:phone":"+1 410 969 1500",
    "sg:postcode":"21144",
    "sg:province":"MD",
    "wof:name":"Great Clips",
    "wof:placetype":"venue"
},
  "geometry": {"coordinates":[-76.64915999999999,39.142562],"type":"Point"}
}