{
  "type": "Feature",
  "properties": {
    "addr:full":"133 Stouffer Ave Hagerstown MD 21740",
    "addr:housenumber":"133",
    "addr:postcode":"21740",
    "addr:street":"Stouffer Ave",
    "iso:country":"US",
    "sg:address":"133 Stouffer Ave",
    "sg:city":"Hagerstown",
    "sg:classifiers":[
        {
            "category":"Building & Trades",
            "subcategory":"Plumbing",
            "type":"Services"
        }
    ],
    "sg:phone":"+1 301 733 0971",
    "sg:postcode":"21740",
    "sg:province":"MD",
    "sg:tags":[
        "plumbing",
        "contractor"
    ],
    "wof:name":"Bob Jones Plumbing & Heating",
    "wof:placetype":"venue"
},
  "geometry": {"coordinates":[-77.703225,39.609891],"type":"Point"}
}