{
  "type": "Feature",
  "properties": {
    "addr:full":"2111 Emmorton Park Dr Edgewood MD 21040",
    "addr:housenumber":"2111",
    "addr:postcode":"21040",
    "addr:street":"Emmorton Park Dr",
    "iso:country":"US",
    "sg:address":"2111 Emmorton Park Dr",
    "sg:city":"Edgewood",
    "sg:classifiers":[
        {
            "category":"Retail",
            "subcategory":"Repair Shop",
            "type":"Services"
        }
    ],
    "sg:phone":"+1 410 679 5300",
    "sg:postcode":"21040",
    "sg:province":"MD",
    "sg:tags":[
        "refrigerating"
    ],
    "sg:website":"www.edsrefrigeration.com",
    "wof:name":"Ed's Refrigeration & AC INC",
    "wof:placetype":"venue"
},
  "geometry": {"coordinates":[-76.308719,39.452141],"type":"Point"}
}