{
  "type": "Feature",
  "properties": {
    "addr:full":"1702 Fawn Way Finksburg MD 21048",
    "addr:housenumber":"1702",
    "addr:postcode":"21048",
    "addr:street":"Fawn Way",
    "iso:country":"US",
    "sg:address":"1702 Fawn Way",
    "sg:city":"Finksburg",
    "sg:classifiers":[
        {
            "category":"Wholesale",
            "subcategory":"Metals & Minerals",
            "type":"Manufacturing & Wholesale Goods"
        }
    ],
    "sg:phone":"+1 410 751 6430",
    "sg:postcode":"21048",
    "sg:province":"MD",
    "sg:tags":[
        "center"
    ],
    "wof:name":"Western Branch Metals Inc",
    "wof:placetype":"venue"
},
  "geometry": {"coordinates":[-76.93486900000001,39.495848],"type":"Point"}
}