{
  "type": "Feature",
  "properties": {
    "addr:full":"2540 Cheval Dr Davidsonville MD 21035",
    "addr:housenumber":"2540",
    "addr:postcode":"21035",
    "addr:street":"Cheval Dr",
    "iso:country":"US",
    "sg:address":"2540 Cheval Dr",
    "sg:city":"Davidsonville",
    "sg:classifiers":[
        {
            "category":"Building & Trades",
            "subcategory":"Construction",
            "type":"Services"
        }
    ],
    "sg:phone":"+1 410 721 5693",
    "sg:postcode":"21035",
    "sg:province":"MD",
    "sg:tags":[
        "builder",
        "operative"
    ],
    "wof:name":"S D King Development Inc",
    "wof:placetype":"venue"
},
  "geometry": {"coordinates":[-76.629902,38.980811],"type":"Point"}
}