{
  "type": "Feature",
  "properties": {
    "iso:country":"US",
    "sg:address":"8705 Burning Tree Rd",
    "sg:city":"Bethesda",
    "sg:classifiers":[
        {
            "category":"Health Services",
            "subcategory":"Clinic",
            "type":"Services"
        }
    ],
    "sg:phone":"+1 301 365 3948",
    "sg:postcode":"20817",
    "sg:province":"MD",
    "sg:tags":[
        "outpatient"
    ],
    "wof:name":"Venus S Masselam Phd",
    "wof:placetype":"venue"
},
  "geometry": {"coordinates":[-77.13906799999999,38.997315],"type":"Point"}
}