{
  "type": "Feature",
  "properties": {
    "addr:full":"16117 Toms Creek Church Rd Emmitsburg MD 21727",
    "addr:housenumber":"16117",
    "addr:postcode":"21727",
    "addr:street":"Toms;Church Rd",
    "iso:country":"US",
    "sg:address":"16117 Toms Creek Church Rd",
    "sg:city":"Emmitsburg",
    "sg:classifiers":[
        {
            "category":"Farming",
            "subcategory":"Farm",
            "type":"Manufacturing & Wholesale Goods"
        }
    ],
    "sg:phone":"+1 301 447 6345",
    "sg:postcode":"21727",
    "sg:province":"MD",
    "sg:tags":[
        "crop",
        "general"
    ],
    "wof:name":"Eric Glass Farm",
    "wof:placetype":"venue"
},
  "geometry": {"coordinates":[-77.285116,39.674651],"type":"Point"}
}