{
  "type": "Feature",
  "properties": {
    "addr:full":"12240 Tullamore Rd Lutherville Timonium MD 21093",
    "addr:housenumber":"12240",
    "addr:postcode":"21093",
    "addr:street":"Tullamore Rd",
    "iso:country":"US",
    "sg:address":"12240 Tullamore Rd",
    "sg:city":"Lutherville Timonium",
    "sg:classifiers":[
        {
            "category":"Restaurant",
            "type":"Food & Drink"
        }
    ],
    "sg:phone":"+1 410 628 7227",
    "sg:postcode":"21093",
    "sg:province":"MD",
    "sg:tags":[
        "new",
        "american"
    ],
    "sg:website":"www.restaurantsabor.com",
    "wof:name":"Restaurant Sabor",
    "wof:placetype":"venue"
},
  "geometry": {"coordinates":[-76.664467,39.458491],"type":"Point"}
}