{
  "type": "Feature",
  "properties": {
    "iso:country":"US",
    "sg:address":"8777 Piney Orchard Pkwy",
    "sg:city":"Odenton",
    "sg:classifiers":[
        {
            "category":"Restaurant",
            "type":"Food & Drink"
        }
    ],
    "sg:phone":"+1 410 695 0777",
    "sg:postcode":"21113",
    "sg:province":"MD",
    "wof:name":"Sal's Pizza",
    "wof:placetype":"venue"
},
  "geometry": {"coordinates":[-76.713578,39.069725],"type":"Point"}
}