{
  "type": "Feature",
  "properties": {
    "iso:country":"US",
    "sg:address":"9805 Sunset Dr",
    "sg:city":"Rockville",
    "sg:classifiers":[
        {
            "category":"Real Estate",
            "subcategory":"Real Estate Agent",
            "type":"Services"
        }
    ],
    "sg:phone":"+1 301 840 5854",
    "sg:postcode":"20850",
    "sg:province":"MD",
    "wof:name":"Smart LTD",
    "wof:placetype":"venue"
},
  "geometry": {"coordinates":[-77.204243,39.073346],"type":"Point"}
}