{
  "type": "Feature",
  "properties": {
    "iso:country":"US",
    "sg:address":"8305 Telegraph Rd",
    "sg:city":"Odenton",
    "sg:classifiers":[
        {
            "category":"Manufacturing",
            "subcategory":"Rubber & Plastics",
            "type":"Manufacturing & Wholesale Goods"
        }
    ],
    "sg:phone":"+1 443 734 2500",
    "sg:postcode":"21144",
    "sg:province":"MD",
    "sg:tags":[
        "pressure",
        "laminate"
    ],
    "wof:name":"Formica Corp",
    "wof:placetype":"venue"
},
  "geometry": {"coordinates":[-76.695847,39.092572],"type":"Point"}
}