{
  "type": "Feature",
  "properties": {
    "addr:full":"2010 W North Ave Baltimore MD 21217",
    "addr:housenumber":"2010",
    "addr:postcode":"21217",
    "addr:street":"W North Ave",
    "iso:country":"US",
    "sg:address":"2010 W North Ave",
    "sg:city":"Baltimore",
    "sg:classifiers":[
        {
            "category":"Organizations",
            "subcategory":"Religious Organization",
            "type":"Services"
        }
    ],
    "sg:phone":"+1 410 523 0902",
    "sg:postcode":"21217",
    "sg:province":"MD",
    "sg:tags":[
        "church"
    ],
    "wof:name":"St Paul Institutional Baptist",
    "wof:placetype":"venue"
},
  "geometry": {"coordinates":[-76.65123,39.30976],"type":"Point"}
}