{
  "type": "Feature",
  "properties": {
    "iso:country":"US",
    "sg:address":"3000 Chestnut Ave",
    "sg:city":"Baltimore",
    "sg:classifiers":[
        {
            "category":"Arts & Performance",
            "subcategory":"Theater",
            "type":"Entertainment"
        }
    ],
    "sg:phone":"+1 410 889 7900",
    "sg:postcode":"21211",
    "sg:province":"MD",
    "sg:tags":[
        "musician"
    ],
    "wof:name":"Elan Artists Inc",
    "wof:placetype":"venue"
},
  "geometry": {"coordinates":[-76.629339,39.324748],"type":"Point"}
}