{
  "type": "Feature",
  "properties": {
    "addr:full":"8 Somerset Ave Cambridge MD 21613",
    "addr:housenumber":"8",
    "addr:postcode":"21613",
    "addr:street":"Somerset Ave",
    "iso:country":"US",
    "sg:address":"8 Somerset Ave",
    "sg:city":"Cambridge",
    "sg:classifiers":[
        {
            "category":"Bus Charters",
            "type":"Transportation"
        }
    ],
    "sg:phone":"+1 410 228 5026",
    "sg:postcode":"21613",
    "sg:province":"MD",
    "sg:tags":[
        "rental"
    ],
    "wof:name":"Tidewater Motor Coach",
    "wof:placetype":"venue"
},
  "geometry": {"coordinates":[-76.08153299999999,38.58332],"type":"Point"}
}