{
  "type": "Feature",
  "properties": {
    "iso:country":"US",
    "sg:address":"11520 Lovejoy St",
    "sg:city":"Silver Spring",
    "sg:classifiers":[
        {
            "category":"Professional",
            "subcategory":"Art Services",
            "type":"Services"
        }
    ],
    "sg:phone":"+1 301 593 5475",
    "sg:postcode":"20902",
    "sg:province":"MD",
    "sg:tags":[
        "commercial",
        "design"
    ],
    "wof:name":"Burton Marti Warthog Studios",
    "wof:placetype":"venue"
},
  "geometry": {"coordinates":[-77.018692,39.043075],"type":"Point"}
}