{
  "type": "Feature",
  "properties": {
    "iso:country":"US",
    "sg:address":"18405 Shady View Ln",
    "sg:city":"Brookeville",
    "sg:classifiers":[
        {
            "category":"Professional",
            "type":"Services"
        }
    ],
    "sg:phone":"+1 301 774 5894",
    "sg:postcode":"20833",
    "sg:province":"MD",
    "sg:tags":[
        "technical",
        "review",
        "editing",
        "contract",
        "writing"
    ],
    "wof:name":"Julie H Jacob",
    "wof:placetype":"venue"
},
  "geometry": {"coordinates":[-77.066813,39.15925],"type":"Point"}
}