{
  "type": "Feature",
  "properties": {
    "iso:country":"US",
    "sg:address":"7525 Connelley Dr Ste U",
    "sg:city":"Hanover",
    "sg:classifiers":[
        {
            "category":"Wholesale",
            "subcategory":"Medical Equipment & Supplies",
            "type":"Manufacturing & Wholesale Goods"
        }
    ],
    "sg:phone":"+1 410 590 0132",
    "sg:postcode":"21076",
    "sg:province":"MD",
    "sg:tags":[
        "polishing",
        "buffing"
    ],
    "wof:name":"Johnson Wax",
    "wof:placetype":"venue"
},
  "geometry": {"coordinates":[-76.681817,39.156664],"type":"Point"}
}