{
  "type": "Feature",
  "properties": {
    "addr:full":"12260 Kiln Ct Beltsville MD 20705",
    "addr:housenumber":"12260",
    "addr:postcode":"20705",
    "addr:street":"Kiln Ct",
    "iso:country":"US",
    "sg:address":"12260 Kiln Ct",
    "sg:city":"Beltsville",
    "sg:classifiers":[
        {
            "category":"Wholesale",
            "subcategory":"Machinery & Supplies",
            "type":"Manufacturing & Wholesale Goods"
        }
    ],
    "sg:phone":"+1 301 210 6999",
    "sg:postcode":"20705",
    "sg:province":"MD",
    "sg:tags":[
        "parking"
    ],
    "sg:website":"www.control-systems-inc.com",
    "wof:name":"Control Systems Inc",
    "wof:placetype":"venue"
},
  "geometry": {"coordinates":[-76.88931700000001,39.061578],"type":"Point"}
}