{
  "type": "Feature",
  "properties": {
    "addr:full":"825 Washington Blvd Baltimore MD 21230",
    "addr:housenumber":"825",
    "addr:postcode":"21230",
    "addr:street":"Washington Blvd",
    "iso:country":"US",
    "sg:address":"825 Washington Blvd",
    "sg:city":"Baltimore",
    "sg:classifiers":[
        {
            "category":"Personal",
            "subcategory":"Barber",
            "type":"Services"
        }
    ],
    "sg:phone":"+1 410 685 7430",
    "sg:postcode":"21230",
    "sg:province":"MD",
    "wof:name":"Studio 825 Barber Shop LLC",
    "wof:placetype":"venue"
},
  "geometry": {"coordinates":[-76.63009700000001,39.282975],"type":"Point"}
}