{
  "type": "Feature",
  "properties": {
    "iso:country":"US",
    "sg:address":"222 Jackson Blvd",
    "sg:city":"Bel Air",
    "sg:classifiers":[
        {
            "category":"Professional",
            "subcategory":"Business Services",
            "type":"Services"
        }
    ],
    "sg:phone":"+1 443 655 0369",
    "sg:postcode":"21014",
    "sg:province":"MD",
    "sg:tags":[
        "assistant",
        "government",
        "lab",
        "operational"
    ],
    "wof:name":"James Duvall",
    "wof:placetype":"venue"
},
  "geometry": {"coordinates":[-76.333406,39.541888],"type":"Point"}
}