{
  "type": "Feature",
  "properties": {
    "addr:full":"201 E Pratt St Baltimore MD 21202",
    "addr:housenumber":"201",
    "addr:postcode":"21202",
    "addr:street":"E Pratt St",
    "iso:country":"US",
    "sg:address":"201 E Pratt St",
    "sg:city":"Baltimore",
    "sg:classifiers":[
        {
            "category":"Shopping",
            "subcategory":"Jewelry",
            "type":"Retail Goods"
        }
    ],
    "sg:phone":"+1 410 837 1813",
    "sg:postcode":"21202",
    "sg:province":"MD",
    "sg:tags":[
        "watch"
    ],
    "wof:name":"Watch Station",
    "wof:placetype":"venue"
},
  "geometry": {"coordinates":[-76.611138,39.286628],"type":"Point"}
}