{
  "type": "Feature",
  "properties": {
    "iso:country":"US",
    "sg:address":"8808 Centre Park Dr",
    "sg:city":"Columbia",
    "sg:classifiers":[
        {
            "category":"Banks & Credit Unions",
            "subcategory":"Bank",
            "type":"Services"
        }
    ],
    "sg:phone":"+1 410 997 5219",
    "sg:postcode":"21045",
    "sg:province":"MD",
    "wof:name":"Wachovia",
    "wof:placetype":"venue"
},
  "geometry": {"coordinates":[-76.816399,39.226601],"type":"Point"}
}