{
  "type": "Feature",
  "properties": {
    "iso:country":"US",
    "sg:address":"5530 Wilkins Ct",
    "sg:city":"Rockville",
    "sg:classifiers":[
        {
            "category":"Professional",
            "subcategory":"Business Services",
            "type":"Services"
        }
    ],
    "sg:phone":"+1 301 924 4104",
    "sg:postcode":"20852",
    "sg:province":"MD",
    "wof:name":"Kashani Reza",
    "wof:placetype":"venue"
},
  "geometry": {"coordinates":[-77.112054,39.057848],"type":"Point"}
}