{
  "type": "Feature",
  "properties": {
    "addr:full":"130 Island Dr Stevensville MD 21666",
    "addr:housenumber":"130",
    "addr:postcode":"21666",
    "addr:street":"Island Dr",
    "iso:country":"US",
    "sg:address":"130 Island Dr",
    "sg:city":"Stevensville",
    "sg:classifiers":[
        {
            "category":"Sports & Exercise",
            "subcategory":"Gym",
            "type":"Entertainment"
        }
    ],
    "sg:phone":"+1 410 604 2997",
    "sg:postcode":"21666",
    "sg:province":"MD",
    "sg:tags":[
        "club",
        "health",
        "studio",
        "gymnasium"
    ],
    "wof:name":"Curves For Women",
    "wof:placetype":"venue"
},
  "geometry": {"coordinates":[-76.311258,38.977429],"type":"Point"}
}