{
  "type": "Feature",
  "properties": {
    "iso:country":"US",
    "sg:address":"3355 Saint Johns Ln",
    "sg:city":"Ellicott City",
    "sg:classifiers":[
        {
            "category":"Professional",
            "subcategory":"Management & Consulting",
            "type":"Services"
        }
    ],
    "sg:phone":"+1 410 418 4021",
    "sg:postcode":"21042",
    "sg:province":"MD",
    "wof:name":"Operational Excellence LLC",
    "wof:placetype":"venue"
},
  "geometry": {"coordinates":[-76.825834,39.279272],"type":"Point"}
}