{
  "type": "Feature",
  "properties": {
    "addr:full":"4323 Dresden St Kensington MD 20895",
    "addr:housenumber":"4323",
    "addr:postcode":"20895",
    "addr:street":"Dresden St",
    "iso:country":"US",
    "sg:address":"4323 Dresden St",
    "sg:city":"Kensington",
    "sg:classifiers":[
        {
            "category":"Restaurant",
            "type":"Food & Drink"
        }
    ],
    "sg:phone":"+1 301 897 0392",
    "sg:postcode":"20895",
    "sg:province":"MD",
    "sg:tags":[
        "shop",
        "coffee"
    ],
    "wof:name":"One Of A Kind Grind",
    "wof:placetype":"venue"
},
  "geometry": {"coordinates":[-77.087851,39.023418],"type":"Point"}
}