{
  "type": "Feature",
  "properties": {
    "iso:country":"US",
    "sg:address":"314 N Stonestreet Ave",
    "sg:city":"Rockville",
    "sg:classifiers":[
        {
            "category":"Retail",
            "subcategory":"Auto Rental",
            "type":"Services"
        }
    ],
    "sg:phone":"+1 301 762 5106",
    "sg:postcode":"20850",
    "sg:province":"MD",
    "sg:tags":[
        "renting",
        "truck",
        "leasing"
    ],
    "wof:name":"U-Haul Co",
    "wof:placetype":"venue"
},
  "geometry": {"coordinates":[-77.148409,39.088512],"type":"Point"}
}