{
  "type": "Feature",
  "properties": {
    "addr:full":"14418 Old Mill Rd Upper Marlboro MD 20772",
    "addr:housenumber":"14418",
    "addr:postcode":"20772",
    "addr:street":"Old Mill Rd",
    "iso:country":"US",
    "sg:address":"14418 Old Mill Rd",
    "sg:city":"Upper Marlboro",
    "sg:classifiers":[
        {
            "category":"Professional",
            "subcategory":"Lawyer & Legal Services",
            "type":"Services"
        }
    ],
    "sg:phone":"+1 301 952 0995",
    "sg:postcode":"20772",
    "sg:province":"MD",
    "sg:tags":[
        "attorney"
    ],
    "wof:name":"A H Michael Rankin Law Office",
    "wof:placetype":"venue"
},
  "geometry": {"coordinates":[-76.755594,38.818036],"type":"Point"}
}