{
  "type": "Feature",
  "properties": {
    "iso:country":"US",
    "sg:address":"3221 Smiths Retreat",
    "sg:city":"Chesapeake Beach",
    "sg:classifiers":[
        {
            "category":"Professional",
            "subcategory":"Business Services",
            "type":"Services"
        }
    ],
    "sg:phone":"+1 410 286 9299",
    "sg:postcode":"20732",
    "sg:province":"MD",
    "wof:name":"Absolute Business Solutions",
    "wof:placetype":"venue"
},
  "geometry": {"coordinates":[-76.54572,38.692705],"type":"Point"}
}