{
  "type": "Feature",
  "properties": {
    "iso:country":"US",
    "sg:address":"5305 Farmingdale Pl",
    "sg:city":"Capitol Heights",
    "sg:classifiers":[
        {
            "category":"Organizations",
            "subcategory":"Religious Organization",
            "type":"Services"
        }
    ],
    "sg:phone":"+1 301 772 3812",
    "sg:postcode":"20743",
    "sg:province":"MD",
    "wof:name":"Craig Memorial Community Church",
    "wof:placetype":"venue"
},
  "geometry": {"coordinates":[-76.915001,38.9081],"type":"Point"}
}