{
  "type": "Feature",
  "properties": {
    "addr:full":"2277 Dunster Ln Potomac MD 20854",
    "addr:housenumber":"2277",
    "addr:postcode":"20854",
    "addr:street":"Dunster Ln",
    "iso:country":"US",
    "sg:address":"2277 Dunster Ln",
    "sg:city":"Potomac",
    "sg:classifiers":[
        {
            "category":"Communications",
            "subcategory":"Film & Video Production",
            "type":"Services"
        }
    ],
    "sg:phone":"+1 301 251 8902",
    "sg:postcode":"20854",
    "sg:province":"MD",
    "sg:tags":[
        "tv",
        "radio",
        "services-commercial",
        "companies-film"
    ],
    "wof:name":"Judith E Herbert & Associates",
    "wof:placetype":"venue"
},
  "geometry": {"coordinates":[-77.16693600000001,39.060324],"type":"Point"}
}