{
  "type": "Feature",
  "properties": {
    "iso:country":"US",
    "sg:address":"9712 Belair Rd",
    "sg:city":"Baltimore",
    "sg:classifiers":[
        {
            "category":"Personal",
            "subcategory":"Hair Removal",
            "type":"Services"
        },
        {
            "category":"Wholesale",
            "subcategory":"Electrical",
            "type":"Manufacturing & Wholesale Goods"
        }
    ],
    "sg:phone":"+1 410 256 6266",
    "sg:postcode":"21236",
    "sg:province":"MD",
    "sg:tags":[
        "removing",
        "electronic"
    ],
    "wof:name":"Perry Hall Electrolysis Center",
    "wof:placetype":"venue"
},
  "geometry": {"coordinates":[-76.459598,39.416341],"type":"Point"}
}