{
  "type": "Feature",
  "properties": {
    "addr:full":"5305 Duvall Dr Bethesda MD 20816",
    "addr:housenumber":"5305",
    "addr:postcode":"20816",
    "addr:street":"Duvall Dr",
    "iso:country":"US",
    "sg:address":"5305 Duvall Dr",
    "sg:city":"Bethesda",
    "sg:classifiers":[
        {
            "category":"Professional",
            "subcategory":"Lawyer & Legal Services",
            "type":"Services"
        }
    ],
    "sg:phone":"+1 301 320 4022",
    "sg:postcode":"20816",
    "sg:province":"MD",
    "wof:name":"Kirschner & Gartrell PC",
    "wof:placetype":"venue"
},
  "geometry": {"coordinates":[-77.107101,38.950699],"type":"Point"}
}