{
  "type": "Feature",
  "properties": {
    "iso:country":"US",
    "sg:address":"1605 Bel Air Rd",
    "sg:city":"Fallston",
    "sg:classifiers":[
        {
            "category":"Building & Trades",
            "subcategory":"Cleaning & Sanitation",
            "type":"Services"
        }
    ],
    "sg:phone":"+1 410 877 9519",
    "sg:postcode":"21047",
    "sg:province":"MD",
    "sg:tags":[
        "maintenance"
    ],
    "wof:name":"B & B Floor Care Services",
    "wof:placetype":"venue"
},
  "geometry": {"coordinates":[-76.385803,39.500238],"type":"Point"}
}