{
  "type": "Feature",
  "properties": {
    "addr:full":"5112 Wetheredsville Rd Baltimore MD 21207",
    "addr:housenumber":"5112",
    "addr:postcode":"21207",
    "addr:street":"Wetheredsville Rd",
    "iso:country":"US",
    "sg:address":"5112 Wetheredsville Rd",
    "sg:city":"Baltimore",
    "sg:classifiers":[
        {
            "category":"Organizations",
            "subcategory":"Religious Organization",
            "type":"Services"
        }
    ],
    "sg:phone":"+1 410 448 2666",
    "sg:postcode":"21207",
    "sg:province":"MD",
    "sg:tags":[
        "church"
    ],
    "wof:name":"Dickey Memorial Presbyterian",
    "wof:placetype":"venue"
},
  "geometry": {"coordinates":[-76.70461899999999,39.314827],"type":"Point"}
}