{
  "type": "Feature",
  "properties": {
    "addr:full":"8914 Allenswood Rd Randallstown MD 21133",
    "addr:housenumber":"8914",
    "addr:postcode":"21133",
    "addr:street":"Allenswood Rd",
    "iso:country":"US",
    "sg:address":"8914 Allenswood Rd",
    "sg:city":"Randallstown",
    "sg:classifiers":[
        {
            "category":"Building & Trades",
            "subcategory":"Construction",
            "type":"Services"
        }
    ],
    "sg:phone":"+1 410 655 5076",
    "sg:postcode":"21133",
    "sg:province":"MD",
    "sg:tags":[
        "altering",
        "remodeling",
        "contractor"
    ],
    "wof:name":"General Home Repair",
    "wof:placetype":"venue"
},
  "geometry": {"coordinates":[-76.79087800000001,39.37048],"type":"Point"}
}