{
  "type": "Feature",
  "properties": {
    "addr:full":"201 N Main St Greensboro MD 21639",
    "addr:housenumber":"201",
    "addr:postcode":"21639",
    "addr:street":"N Main St",
    "iso:country":"US",
    "sg:address":"201 N Main St",
    "sg:city":"Greensboro",
    "sg:classifiers":[
        {
            "category":"Building & Trades",
            "subcategory":"Plumbing",
            "type":"Services"
        }
    ],
    "sg:phone":"+1 410 482 8847",
    "sg:postcode":"21639",
    "sg:province":"MD",
    "sg:tags":[
        "heating",
        "contractor"
    ],
    "wof:name":"Your Comfort Co",
    "wof:placetype":"venue"
},
  "geometry": {"coordinates":[-75.804321,38.976206],"type":"Point"}
}