{
  "type": "Feature",
  "properties": {
    "addr:full":"11139 York Rd Cockeysville MD 21030",
    "addr:housenumber":"11139",
    "addr:postcode":"21030",
    "addr:street":"York Rd",
    "iso:country":"US",
    "sg:address":"11139 York Rd",
    "sg:city":"Cockeysville",
    "sg:classifiers":[
        {
            "category":"Banks & Credit Unions",
            "subcategory":"Bank",
            "type":"Services"
        },
        {
            "category":"Banks & Credit Unions",
            "subcategory":"Financial Services",
            "type":"Services"
        }
    ],
    "sg:phone":"+1 410 347 8940",
    "sg:postcode":"21030",
    "sg:province":"MD",
    "sg:tags":[
        "broker",
        "mortgage"
    ],
    "wof:name":"Mercantile Mortgage Corporation",
    "wof:placetype":"venue"
},
  "geometry": {"coordinates":[-76.648201,39.490299],"type":"Point"}
}