{
  "type": "Feature",
  "properties": {
    "iso:country":"US",
    "sg:address":"603 7th St Ste 303",
    "sg:city":"Laurel",
    "sg:classifiers":[
        {
            "category":"Manufacturing",
            "subcategory":"Buildings",
            "type":"Manufacturing & Wholesale Goods"
        },
        {
            "category":"Building & Trades",
            "subcategory":"Construction",
            "type":"Services"
        }
    ],
    "sg:phone":"+1 301 497 7233",
    "sg:postcode":"20707",
    "sg:province":"MD",
    "sg:tags":[
        "industrial",
        "specialty",
        "builder",
        "heating",
        "system",
        "contractors-commercial",
        "home",
        "contractor",
        "air conditioning"
    ],
    "wof:name":"American Home Contractor Inc",
    "wof:placetype":"venue"
},
  "geometry": {"coordinates":[-76.85583,39.102926],"type":"Point"}
}