{
  "type": "Feature",
  "properties": {
    "addr:full":"6311 Coventry Way Clinton MD 20735",
    "addr:housenumber":"6311",
    "addr:postcode":"20735",
    "addr:street":"Coventry Way",
    "iso:country":"US",
    "sg:address":"6311 Coventry Way",
    "sg:city":"Clinton",
    "sg:classifiers":[
        {
            "category":"Retail",
            "subcategory":"Car Wash",
            "type":"Services"
        }
    ],
    "sg:phone":"+1 301 856 2900",
    "sg:postcode":"20735",
    "sg:province":"MD",
    "sg:tags":[
        "automobile",
        "detail",
        "clean"
    ],
    "wof:name":"Prowash",
    "wof:placetype":"venue"
},
  "geometry": {"coordinates":[-76.89859800000001,38.782185],"type":"Point"}
}