{
  "type": "Feature",
  "properties": {
    "addr:full":"1312 Goucher Blvd Towson MD 21286",
    "addr:housenumber":"1312",
    "addr:postcode":"21286",
    "addr:street":"Goucher Blvd",
    "iso:country":"US",
    "sg:address":"1312 Goucher Blvd",
    "sg:city":"Towson",
    "sg:classifiers":[
        {
            "category":"Health Services",
            "subcategory":"Clinic",
            "type":"Services"
        },
        {
            "category":"Community Center",
            "type":"Public Place"
        }
    ],
    "sg:phone":"+1 410 583 9130",
    "sg:postcode":"21286",
    "sg:province":"MD",
    "sg:tags":[
        "medical"
    ],
    "wof:name":"Taylor Lock Raven Medical Center",
    "wof:placetype":"venue"
},
  "geometry": {"coordinates":[-76.579623,39.384335],"type":"Point"}
}