{
  "type": "Feature",
  "properties": {
    "iso:country":"US",
    "sg:address":"3508 Gregg Rd",
    "sg:city":"Brookeville",
    "sg:classifiers":[
        {
            "category":"Professional",
            "subcategory":"Business Services",
            "type":"Services"
        }
    ],
    "sg:phone":"+1 301 260 1987",
    "sg:postcode":"20833",
    "sg:province":"MD",
    "sg:tags":[
        "consulting",
        "software"
    ],
    "wof:name":"Roccomar Inc",
    "wof:placetype":"venue"
},
  "geometry": {"coordinates":[-77.072123,39.20461],"type":"Point"}
}