{
  "type": "Feature",
  "properties": {
    "iso:country":"US",
    "sg:address":"123 S Washington St",
    "sg:city":"Havre De Grace",
    "sg:classifiers":[
        {
            "category":"Retail",
            "subcategory":"Funeral Services",
            "type":"Services"
        }
    ],
    "sg:phone":"+1 410 939 2882",
    "sg:postcode":"21078",
    "sg:province":"MD",
    "sg:tags":[
        "director"
    ],
    "wof:name":"Mitchell-Smith Funeral Home",
    "wof:placetype":"venue"
},
  "geometry": {"coordinates":[-76.089675,39.54684],"type":"Point"}
}