{
  "type": "Feature",
  "properties": {
    "addr:full":"11512 Alcinda Ln North Potomac MD 20878",
    "addr:housenumber":"11512",
    "addr:postcode":"20878",
    "addr:street":"Alcinda Ln",
    "iso:country":"US",
    "sg:address":"11512 Alcinda Ln",
    "sg:city":"North Potomac",
    "sg:classifiers":[
        {
            "category":"Professional",
            "subcategory":"Engineering",
            "type":"Services"
        }
    ],
    "sg:phone":"+1 301 294 2595",
    "sg:postcode":"20878",
    "sg:province":"MD",
    "sg:tags":[
        "engineer"
    ],
    "wof:name":"Megasignal Technology",
    "wof:placetype":"venue"
},
  "geometry": {"coordinates":[-77.238173,39.104147],"type":"Point"}
}