{
  "type": "Feature",
  "properties": {
    "iso:country":"US",
    "sg:address":"1801 Annapolis Rd",
    "sg:city":"Baltimore",
    "sg:classifiers":[
        {
            "category":"Utilities",
            "subcategory":"Electric",
            "type":"Services"
        },
        {
            "category":"Utilities",
            "type":"Services"
        }
    ],
    "sg:phone":"+1 410 234 0808",
    "sg:postcode":"21230",
    "sg:province":"MD",
    "wof:name":"Wheelabrator Baltimore",
    "wof:placetype":"venue"
},
  "geometry": {"coordinates":[-76.630707,39.271118],"type":"Point"}
}