{
  "type": "Feature",
  "properties": {
    "addr:full":"9106 Philadelphia Rd Ste 208 Rosedale MD 21237",
    "addr:housenumber":"9106",
    "addr:postcode":"21237",
    "addr:street":"Philadelphia Rd Ste 208",
    "iso:country":"US",
    "sg:address":"9106 Philadelphia Rd Ste 208",
    "sg:city":"Rosedale",
    "sg:classifiers":[
        {
            "category":"Health Services",
            "subcategory":"Doctor",
            "type":"Services"
        }
    ],
    "sg:phone":"+1 410 391 0646",
    "sg:postcode":"21237",
    "sg:province":"MD",
    "wof:name":"Eliasson Orn Mph",
    "wof:placetype":"venue"
},
  "geometry": {"coordinates":[-76.473314,39.347335],"type":"Point"}
}