{
  "type": "Feature",
  "properties": {
    "iso:country":"US",
    "sg:address":"4112 Crawford Ave",
    "sg:city":"Baltimore",
    "sg:classifiers":[
        {
            "category":"Professional",
            "subcategory":"Computer Services",
            "type":"Services"
        }
    ],
    "sg:phone":"+1 410 542 3388",
    "sg:postcode":"21215",
    "sg:province":"MD",
    "sg:tags":[
        "related"
    ],
    "wof:name":"Bernard R Wyche",
    "wof:placetype":"venue"
},
  "geometry": {"coordinates":[-76.703546,39.340946],"type":"Point"}
}