{
  "type": "Feature",
  "properties": {
    "addr:full":"5303 Coastal Hwy Ocean City MD 21842",
    "addr:housenumber":"5303",
    "addr:postcode":"21842",
    "addr:street":"Coastal Hwy",
    "iso:country":"US",
    "sg:address":"5303 Coastal Hwy",
    "sg:city":"Ocean City",
    "sg:classifiers":[
        {
            "category":"Recreation",
            "type":"Entertainment"
        }
    ],
    "sg:phone":"+1 410 524 0209",
    "sg:postcode":"21842",
    "sg:province":"MD",
    "sg:tags":[
        "charter",
        "boat"
    ],
    "wof:name":"Waterways Inc",
    "wof:placetype":"venue"
},
  "geometry": {"coordinates":[-75.068701,38.378355],"type":"Point"}
}