{
  "type": "Feature",
  "properties": {
    "iso:country":"US",
    "sg:address":"3676 Arrowsmith Dr",
    "sg:city":"Salisbury",
    "sg:classifiers":[
        {
            "category":"Health Services",
            "subcategory":"Doctor",
            "type":"Services"
        }
    ],
    "sg:phone":"+1 410 543 7742",
    "sg:postcode":"21804",
    "sg:province":"MD",
    "sg:tags":[
        "physician",
        "surgeon"
    ],
    "wof:name":"Emergency Service Assoc",
    "wof:placetype":"venue"
},
  "geometry": {"coordinates":[-75.586043,38.294178],"type":"Point"}
}