{
  "type": "Feature",
  "properties": {
    "addr:full":"286 Montrose Ave Baltimore MD 21221",
    "addr:housenumber":"286",
    "addr:postcode":"21221",
    "addr:street":"Montrose Ave",
    "iso:country":"US",
    "sg:address":"286 Montrose Ave",
    "sg:city":"Baltimore",
    "sg:classifiers":[
        {
            "category":"Professional",
            "subcategory":"Computer Services",
            "type":"Services"
        }
    ],
    "sg:phone":"+1 410 299 7968",
    "sg:postcode":"21221",
    "sg:province":"MD",
    "sg:tags":[
        "consulting",
        "it"
    ],
    "wof:name":"Gonshor Inc",
    "wof:placetype":"venue"
},
  "geometry": {"coordinates":[-76.481458,39.320467],"type":"Point"}
}