{
  "type": "Feature",
  "properties": {
    "iso:country":"US",
    "sg:address":"12901 Georgia Ave",
    "sg:city":"Silver Spring",
    "sg:classifiers":[
        {
            "category":"Social Services",
            "subcategory":"Child Care",
            "type":"Services"
        }
    ],
    "sg:phone":"+1 301 942 2767",
    "sg:postcode":"20906",
    "sg:province":"MD",
    "wof:name":"Georgia Ave Early Learning Ctr",
    "wof:placetype":"venue"
},
  "geometry": {"coordinates":[-77.06111799999999,39.068145],"type":"Point"}
}