{
  "type": "Feature",
  "properties": {
    "iso:country":"US",
    "sg:address":"17900 Gainford Pl",
    "sg:city":"Olney",
    "sg:classifiers":[
        {
            "category":"Retail",
            "subcategory":"Portrait Studio",
            "type":"Services"
        }
    ],
    "sg:phone":"+1 301 260 2549",
    "sg:postcode":"20832",
    "sg:province":"MD",
    "sg:tags":[
        "photo"
    ],
    "wof:name":"Robert Bowen Photography Inc",
    "wof:placetype":"venue"
},
  "geometry": {"coordinates":[-77.049506,39.150836],"type":"Point"}
}