{
  "type": "Feature",
  "properties": {
    "addr:full":"11170 Mall Cir Waldorf MD 20603",
    "addr:housenumber":"11170",
    "addr:postcode":"20603",
    "addr:street":"Mall Cir",
    "iso:country":"US",
    "sg:address":"11170 Mall Cir",
    "sg:city":"Waldorf",
    "sg:classifiers":[
        {
            "category":"Shopping",
            "type":"Retail Goods"
        }
    ],
    "sg:phone":"+1 301 396 5709",
    "sg:postcode":"20603",
    "sg:province":"MD",
    "sg:tags":[
        "hearing",
        "equipment",
        "supply",
        "impaired"
    ],
    "wof:name":"Miracle-Ear",
    "wof:placetype":"venue"
},
  "geometry": {"coordinates":[-76.916984,38.620581],"type":"Point"}
}