{
  "type": "Feature",
  "properties": {
    "iso:country":"US",
    "sg:address":"9234 Springhill Ln",
    "sg:city":"Greenbelt",
    "sg:classifiers":[
        {
            "category":"Restaurant",
            "type":"Food & Drink"
        }
    ],
    "sg:phone":"+1 301 474 9190",
    "sg:postcode":"20770",
    "sg:province":"MD",
    "sg:tags":[
        "out"
    ],
    "wof:name":"Hunan China Carry-Out",
    "wof:placetype":"venue"
},
  "geometry": {"coordinates":[-76.903238,39.004228],"type":"Point"}
}