{
  "type": "Feature",
  "properties": {
    "iso:country":"US",
    "sg:address":"29 E Ellendale St",
    "sg:city":"Bel Air",
    "sg:classifiers":[
        {
            "category":"Retail",
            "subcategory":"Repair Shop",
            "type":"Services"
        }
    ],
    "sg:phone":"+1 410 879 6800",
    "sg:postcode":"21014",
    "sg:province":"MD",
    "sg:tags":[
        "refinishing",
        "furniture"
    ],
    "wof:name":"Bel Air Furniture Refinishing",
    "wof:placetype":"venue"
},
  "geometry": {"coordinates":[-76.353742,39.541297],"type":"Point"}
}