{
  "type": "Feature",
  "properties": {
    "addr:full":"16508 Marlboro Pike Upper Marlboro MD 20772",
    "addr:housenumber":"16508",
    "addr:postcode":"20772",
    "addr:street":"Marlboro Pike",
    "iso:country":"US",
    "sg:address":"16508 Marlboro Pike",
    "sg:city":"Upper Marlboro",
    "sg:classifiers":[
        {
            "category":"Professional",
            "type":"Services"
        }
    ],
    "sg:phone":"+1 301 627 3245",
    "sg:postcode":"20772",
    "sg:province":"MD",
    "wof:name":"Compton Bassett Entps LLC",
    "wof:placetype":"venue"
},
  "geometry": {"coordinates":[-76.71687,38.813186],"type":"Point"}
}