{
  "type": "Feature",
  "properties": {
    "addr:full":"10744 Adkins Rd Berlin MD 21811",
    "addr:housenumber":"10744",
    "addr:postcode":"21811",
    "addr:street":"Adkins Rd",
    "iso:country":"US",
    "sg:address":"10744 Adkins Rd",
    "sg:city":"Berlin",
    "sg:classifiers":[
        {
            "category":"Freight",
            "type":"Transportation"
        }
    ],
    "sg:phone":"+1 410 641 5788",
    "sg:postcode":"21811",
    "sg:province":"MD",
    "wof:name":"No Mans Land LLC",
    "wof:placetype":"venue"
},
  "geometry": {"coordinates":[-75.18665300000001,38.365926],"type":"Point"}
}