{
  "type": "Feature",
  "properties": {
    "addr:full":"3675 Willow St Hampstead MD 21074",
    "addr:housenumber":"3675",
    "addr:postcode":"21074",
    "addr:street":"Willow St",
    "iso:country":"US",
    "sg:address":"3675 Willow St",
    "sg:city":"Hampstead",
    "sg:classifiers":[
        {
            "category":"Education",
            "subcategory":"School",
            "type":"Public Place"
        }
    ],
    "sg:phone":"+1 410 386 4570",
    "sg:postcode":"21074",
    "sg:province":"MD",
    "wof:name":"Shiloh Middle School",
    "wof:placetype":"venue"
},
  "geometry": {"coordinates":[-76.858448,39.602519],"type":"Point"}
}