{
  "type": "Feature",
  "properties": {
    "iso:country":"US",
    "sg:address":"2465 MD Route 97",
    "sg:city":"Ellicott City",
    "sg:classifiers":[
        {
            "category":"Shopping",
            "subcategory":"Books",
            "type":"Retail Goods"
        }
    ],
    "sg:phone":"+1 410 442 3740",
    "sg:postcode":"21043",
    "sg:province":"MD",
    "sg:tags":[
        "bookstore"
    ],
    "wof:name":"Books With A Past",
    "wof:placetype":"venue"
},
  "geometry": {"coordinates":[-76.803596,39.2556],"type":"Point"}
}