{
  "type": "Feature",
  "properties": {
    "addr:full":"5150 Baltimore National Pike Baltimore MD 21229",
    "addr:housenumber":"5150",
    "addr:postcode":"21229",
    "addr:street":"Baltimore National Pike",
    "iso:country":"US",
    "sg:address":"5150 Baltimore National Pike",
    "sg:city":"Baltimore",
    "sg:classifiers":[
        {
            "category":"Education",
            "subcategory":"School",
            "type":"Public Place"
        }
    ],
    "sg:phone":"+1 410 945 0664",
    "sg:postcode":"21229",
    "sg:province":"MD",
    "sg:tags":[
        "elementary"
    ],
    "wof:name":"Center For Creative Learning",
    "wof:placetype":"venue"
},
  "geometry": {"coordinates":[-76.712581,39.291711],"type":"Point"}
}