{
  "type": "Feature",
  "properties": {
    "addr:full":"436 Madingley Rd Linthicum Heights MD 21090",
    "addr:housenumber":"436",
    "addr:postcode":"21090",
    "addr:street":"Madingley Rd",
    "iso:country":"US",
    "sg:address":"436 Madingley Rd",
    "sg:city":"Linthicum Heights",
    "sg:classifiers":[
        {
            "category":"Cinema",
            "subcategory":"Movie Rental",
            "type":"Entertainment"
        }
    ],
    "sg:phone":"+1 410 859 8672",
    "sg:postcode":"21090",
    "sg:province":"MD",
    "sg:tags":[
        "video",
        "tape"
    ],
    "wof:name":"Cameo Video Services",
    "wof:placetype":"venue"
},
  "geometry": {"coordinates":[-76.660184,39.214246],"type":"Point"}
}