{
  "type": "Feature",
  "properties": {
    "addr:full":"26043 Ridge Rd Damascus MD 20872",
    "addr:housenumber":"26043",
    "addr:postcode":"20872",
    "addr:street":"Ridge Rd",
    "iso:country":"US",
    "sg:address":"26043 Ridge Rd",
    "sg:city":"Damascus",
    "sg:classifiers":[
        {
            "category":"Restaurant",
            "type":"Food & Drink"
        }
    ],
    "sg:phone":"+1 301 253 8600",
    "sg:postcode":"20872",
    "sg:province":"MD",
    "wof:name":"Little Far East II",
    "wof:placetype":"venue"
},
  "geometry": {"coordinates":[-77.210987,39.283387],"type":"Point"}
}