{
  "type": "Feature",
  "properties": {
    "iso:country":"US",
    "sg:address":"11409 Woodglen Dr",
    "sg:city":"Rockville",
    "sg:classifiers":[
        {
            "category":"Retail",
            "subcategory":"Laundry & Dry Cleaning",
            "type":"Services"
        }
    ],
    "sg:phone":"+1 301 816 9460",
    "sg:postcode":"20852",
    "sg:province":"MD",
    "sg:tags":[
        "cleaner"
    ],
    "wof:name":"Pike Cleaners",
    "wof:placetype":"venue"
},
  "geometry": {"coordinates":[-77.113602,39.043999],"type":"Point"}
}