{
  "type": "Feature",
  "properties": {
    "addr:full":"14916 Schall Rd Accokeek MD 20607",
    "addr:housenumber":"14916",
    "addr:postcode":"20607",
    "addr:street":"Schall Rd",
    "iso:country":"US",
    "sg:address":"14916 Schall Rd",
    "sg:city":"Accokeek",
    "sg:classifiers":[
        {
            "category":"Professional",
            "subcategory":"Management & Consulting",
            "type":"Services"
        }
    ],
    "sg:phone":"+1 301 292 2771",
    "sg:postcode":"20607",
    "sg:province":"MD",
    "sg:tags":[
        "resource",
        "human"
    ],
    "wof:name":"Taranga Hse Rtreat Prctice Ctr",
    "wof:placetype":"venue"
},
  "geometry": {"coordinates":[-76.983053,38.682276],"type":"Point"}
}