{
  "type": "Feature",
  "properties": {
    "addr:full":"5907 Fall Moon Ride Clarksville MD 21029",
    "addr:housenumber":"5907",
    "addr:postcode":"21029",
    "addr:street":"Fall Moon Ride",
    "iso:country":"US",
    "sg:address":"5907 Fall Moon Ride",
    "sg:city":"Clarksville",
    "sg:classifiers":[
        {
            "category":"Real Estate",
            "subcategory":"Real Estate Services",
            "type":"Services"
        },
        {
            "category":"Real Estate",
            "subcategory":"Real Estate Agent",
            "type":"Services"
        }
    ],
    "sg:phone":"+1 443 535 9644",
    "sg:postcode":"21029",
    "sg:province":"MD",
    "sg:tags":[
        "buyer",
        "broker"
    ],
    "wof:name":"De Bonis Realty Inc",
    "wof:placetype":"venue"
},
  "geometry": {"coordinates":[-76.928915,39.205901],"type":"Point"}
}