{
  "type": "Feature",
  "properties": {
    "iso:country":"US",
    "sg:address":"12562 Mattawoman Dr",
    "sg:city":"Waldorf",
    "sg:classifiers":[
        {
            "category":"Personal",
            "subcategory":"Beauty Salon",
            "type":"Services"
        }
    ],
    "sg:phone":"+1 301 645 4854",
    "sg:postcode":"20601",
    "sg:province":"MD",
    "sg:tags":[
        "manicuring"
    ],
    "wof:name":"Queen Nail",
    "wof:placetype":"venue"
},
  "geometry": {"coordinates":[-76.876643,38.65441],"type":"Point"}
}