{
  "type": "Feature",
  "properties": {
    "addr:full":"24659 Williston Rd Denton MD 21629",
    "addr:housenumber":"24659",
    "addr:postcode":"21629",
    "addr:street":"Williston Rd",
    "iso:country":"US",
    "sg:address":"24659 Williston Rd",
    "sg:city":"Denton",
    "sg:classifiers":[
        {
            "category":"Professional",
            "subcategory":"Accounting & Tax Preparation",
            "type":"Services"
        }
    ],
    "sg:phone":"+1 410 479 0637",
    "sg:postcode":"21629",
    "sg:province":"MD",
    "sg:tags":[
        "return"
    ],
    "wof:name":"Doris W Sharp",
    "wof:placetype":"venue"
},
  "geometry": {"coordinates":[-75.850452,38.830709],"type":"Point"}
}