{
  "type": "Feature",
  "properties": {
    "iso:country":"US",
    "sg:address":"388 Kyle Rd",
    "sg:city":"Crownsville",
    "sg:classifiers":[
        {
            "category":"Building & Trades",
            "subcategory":"Construction",
            "type":"Services"
        }
    ],
    "sg:phone":"+1 410 923 1226",
    "sg:postcode":"21032",
    "sg:province":"MD",
    "sg:tags":[
        "altering",
        "remodeling",
        "contractor"
    ],
    "wof:name":"Kenneth Green",
    "wof:placetype":"venue"
},
  "geometry": {"coordinates":[-76.572632,39.054482],"type":"Point"}
}