{
  "type": "Feature",
  "properties": {
    "addr:full":"218 N Division St Salisbury MD 21801",
    "addr:housenumber":"218",
    "addr:postcode":"21801",
    "addr:street":"N Division St",
    "iso:country":"US",
    "sg:address":"218 N Division St",
    "sg:city":"Salisbury",
    "sg:classifiers":[
        {
            "category":"Real Estate",
            "subcategory":"Architect",
            "type":"Services"
        }
    ],
    "sg:phone":"+1 410 749 2447",
    "sg:postcode":"21801",
    "sg:province":"MD",
    "wof:name":"Todd & Assoc Inc",
    "wof:placetype":"venue"
},
  "geometry": {"coordinates":[-75.60043400000001,38.367052],"type":"Point"}
}