{
  "type": "Feature",
  "properties": {
    "iso:country":"US",
    "sg:address":"5005 Garrett Ave",
    "sg:city":"Beltsville",
    "sg:classifiers":[
        {
            "category":"Retail",
            "subcategory":"Portrait Studio",
            "type":"Services"
        }
    ],
    "sg:phone":"+1 301 937 5510",
    "sg:postcode":"20705",
    "sg:province":"MD",
    "sg:tags":[
        "photography",
        "store"
    ],
    "sg:website":"www.uphoto.com",
    "wof:name":"United Photo Inc",
    "wof:placetype":"venue"
},
  "geometry": {"coordinates":[-76.906097,39.041599],"type":"Point"}
}