{
  "type": "Feature",
  "properties": {
    "iso:country":"US",
    "sg:address":"42 Holly Rd",
    "sg:city":"Severna Park",
    "sg:classifiers":[
        {
            "category":"Building & Trades",
            "subcategory":"Construction",
            "type":"Services"
        }
    ],
    "sg:phone":"+1 410 544 6918",
    "sg:postcode":"21146",
    "sg:province":"MD",
    "sg:tags":[
        "resurfacing",
        "laying",
        "refinishing",
        "floor"
    ],
    "wof:name":"Dorrance Co",
    "wof:placetype":"venue"
},
  "geometry": {"coordinates":[-76.588017,39.079944],"type":"Point"}
}