{
  "type": "Feature",
  "properties": {
    "addr:full":"1915 Wills Rd Dundalk MD 21222",
    "addr:housenumber":"1915",
    "addr:postcode":"21222",
    "addr:street":"Wills Rd",
    "iso:country":"US",
    "sg:address":"1915 Wills Rd",
    "sg:city":"Dundalk",
    "sg:classifiers":[
        {
            "category":"Recreation",
            "subcategory":"Marina",
            "type":"Entertainment"
        }
    ],
    "sg:phone":"+1 410 285 8080",
    "sg:postcode":"21222",
    "sg:province":"MD",
    "sg:tags":[
        "repairing",
        "boat"
    ],
    "wof:name":"Roudebush Yacht & Engine Works",
    "wof:placetype":"venue"
},
  "geometry": {"coordinates":[-76.49637199999999,39.256189],"type":"Point"}
}