{
  "type": "Feature",
  "properties": {
    "addr:full":"807 Crain Hwy S Glen Burnie MD 21061",
    "addr:housenumber":"807",
    "addr:postcode":"21061",
    "addr:street":"Crain Hwy S",
    "iso:country":"US",
    "sg:address":"807 Crain Hwy S",
    "sg:city":"Glen Burnie",
    "sg:classifiers":[
        {
            "category":"Food & Beverages",
            "subcategory":"Groceries & Convenience Stores",
            "type":"Retail Goods"
        }
    ],
    "sg:phone":"+1 410 760 6733",
    "sg:postcode":"21061",
    "sg:province":"MD",
    "sg:website":"www.luckysmarkets.com",
    "wof:name":"Lucky Food Ctr",
    "wof:placetype":"venue"
},
  "geometry": {"coordinates":[-76.63061399999999,39.154733],"type":"Point"}
}