{
  "type": "Feature",
  "properties": {
    "addr:full":"11700 Split Tree Cir Potomac MD 20854",
    "addr:housenumber":"11700",
    "addr:postcode":"20854",
    "addr:street":"Split Tree Cir",
    "iso:country":"US",
    "sg:address":"11700 Split Tree Cir",
    "sg:city":"Potomac",
    "sg:classifiers":[
        {
            "category":"Professional",
            "type":"Services"
        }
    ],
    "sg:phone":"+1 301 251 0506",
    "sg:postcode":"20854",
    "sg:province":"MD",
    "wof:name":"Or Inc",
    "wof:placetype":"venue"
},
  "geometry": {"coordinates":[-77.193496,39.047119],"type":"Point"}
}