{
  "type": "Feature",
  "properties": {
    "addr:full":"508 E Baltimore St Taneytown MD 21787",
    "addr:housenumber":"508",
    "addr:postcode":"21787",
    "addr:street":"E Baltimore St",
    "iso:country":"US",
    "sg:address":"508 E Baltimore St",
    "sg:city":"Taneytown",
    "sg:classifiers":[
        {
            "category":"Autos & Motor Vehicles",
            "subcategory":"Auto Supplies",
            "type":"Retail Goods"
        },
        {
            "category":"Wholesale",
            "subcategory":"Electrical",
            "type":"Manufacturing & Wholesale Goods"
        },
        {
            "category":"Wholesale",
            "subcategory":"Auto Parts",
            "type":"Manufacturing & Wholesale Goods"
        },
        {
            "category":"Retail",
            "subcategory":"Auto Repair",
            "type":"Services"
        }
    ],
    "sg:phone":"+1 410 756 2139",
    "sg:postcode":"21787",
    "sg:province":"MD",
    "sg:tags":[
        "engines-rebuild",
        "exchange",
        "battery",
        "automobile",
        "accessory",
        "equipment",
        "supplies-used",
        "truck",
        "rebuilt",
        "batteries-storage"
    ],
    "sg:website":"http://www.advanceautoparts.com",
    "wof:name":"Advance Auto Parts",
    "wof:placetype":"venue"
},
  "geometry": {"coordinates":[-77.159291,39.650258],"type":"Point"}
}