{
  "type": "Feature",
  "properties": {
    "iso:country":"US",
    "sg:address":"408 Winters Ln",
    "sg:city":"Catonsville",
    "sg:classifiers":[
        {
            "category":"Professional",
            "subcategory":"Accounting & Tax Preparation",
            "type":"Services"
        }
    ],
    "sg:phone":"+1 410 788 1717",
    "sg:postcode":"21228",
    "sg:province":"MD",
    "sg:tags":[
        "accountant"
    ],
    "wof:name":"Ballard Accounting",
    "wof:placetype":"venue"
},
  "geometry": {"coordinates":[-76.743202,39.284901],"type":"Point"}
}