{
  "type": "Feature",
  "properties": {
    "iso:country":"US",
    "sg:address":"3921 Erdman Ave",
    "sg:city":"Baltimore",
    "sg:classifiers":[
        {
            "category":"Retail",
            "subcategory":"Self-service Laundry",
            "type":"Services"
        }
    ],
    "sg:phone":"+1 410 327 0499",
    "sg:postcode":"21213",
    "sg:province":"MD",
    "wof:name":"Sudsville Laundries Inc",
    "wof:placetype":"venue"
},
  "geometry": {"coordinates":[-76.568404,39.314507],"type":"Point"}
}