{
  "type": "Feature",
  "properties": {
    "addr:full":"10709 Grays Corner Rd Berlin MD 21811",
    "addr:housenumber":"10709",
    "addr:postcode":"21811",
    "addr:street":"Grays Corner Rd",
    "iso:country":"US",
    "sg:address":"10709 Grays Corner Rd",
    "sg:city":"Berlin",
    "sg:classifiers":[
        {
            "category":"Autos & Motor Vehicles",
            "subcategory":"Auto Supplies",
            "type":"Retail Goods"
        },
        {
            "category":"Retail",
            "subcategory":"Auto Repair",
            "type":"Services"
        }
    ],
    "sg:phone":"+1 410 629 1120",
    "sg:postcode":"21811",
    "sg:province":"MD",
    "sg:tags":[
        "body",
        "automobile",
        "painting",
        "repairing",
        "accessory"
    ],
    "wof:name":"Berlin Auto Trim",
    "wof:placetype":"venue"
},
  "geometry": {"coordinates":[-75.190062,38.343622],"type":"Point"}
}