{
  "type": "Feature",
  "properties": {
    "iso:country":"US",
    "sg:address":"11311 Cash Smith Rd",
    "sg:city":"Keymar",
    "sg:classifiers":[
        {
            "category":"Building & Trades",
            "subcategory":"Construction",
            "type":"Services"
        }
    ],
    "sg:phone":"+1 301 845 2618",
    "sg:postcode":"21757",
    "sg:province":"MD",
    "sg:tags":[
        "contractor",
        "mason"
    ],
    "wof:name":"Larry Kehne Masonry Inc.",
    "wof:placetype":"venue"
},
  "geometry": {"coordinates":[-77.301756,39.54146],"type":"Point"}
}