{
  "type": "Feature",
  "properties": {
    "iso:country":"US",
    "sg:address":"3600 W Belvedere Ave",
    "sg:city":"Baltimore",
    "sg:classifiers":[
        {
            "category":"Personal",
            "subcategory":"Beauty Salon",
            "type":"Services"
        }
    ],
    "sg:phone":"+1 410 367 6306",
    "sg:postcode":"21215",
    "sg:province":"MD",
    "wof:name":"Heads Up Toes Down Inc",
    "wof:placetype":"venue"
},
  "geometry": {"coordinates":[-76.680281,39.346305],"type":"Point"}
}