{
  "type": "Feature",
  "properties": {
    "addr:full":"124 Shawan Rd Cockeysville MD 21030",
    "addr:housenumber":"124",
    "addr:postcode":"21030",
    "addr:street":"Shawan Rd",
    "iso:country":"US",
    "sg:address":"124 Shawan Rd",
    "sg:city":"Cockeysville",
    "sg:classifiers":[
        {
            "category":"Banks & Credit Unions",
            "subcategory":"Bank",
            "type":"Services"
        },
        {
            "category":"Banks & Credit Unions",
            "subcategory":"Financial Services",
            "type":"Services"
        }
    ],
    "sg:phone":"+1 410 785 7016",
    "sg:postcode":"21030",
    "sg:province":"MD",
    "sg:tags":[
        "loan",
        "financing"
    ],
    "sg:website":"http://www.SunTrust.com",
    "wof:name":"SunTrust Bank - Hunt Valley",
    "wof:placetype":"venue"
},
  "geometry": {"coordinates":[-76.654467,39.495831],"type":"Point"}
}