{
  "type": "Feature",
  "properties": {
    "addr:full":"1108 Autumn Gold Dr Gambrills MD 21054",
    "addr:housenumber":"1108",
    "addr:postcode":"21054",
    "addr:street":"Autumn Gold Dr",
    "iso:country":"US",
    "sg:address":"1108 Autumn Gold Dr",
    "sg:city":"Gambrills",
    "sg:classifiers":[
        {
            "category":"Professional",
            "subcategory":"Management & Consulting",
            "type":"Services"
        },
        {
            "category":"Professional",
            "subcategory":"Computer Services",
            "type":"Services"
        }
    ],
    "sg:phone":"+1 410 672 6792",
    "sg:postcode":"21054",
    "sg:province":"MD",
    "sg:tags":[
        "marketing",
        "related",
        "consultant"
    ],
    "wof:name":"Iler Enterprises Inc",
    "wof:placetype":"venue"
},
  "geometry": {"coordinates":[-76.69874799999999,39.053038],"type":"Point"}
}