{
  "type": "Feature",
  "properties": {
    "iso:country":"US",
    "sg:address":"5435 Cynthia Ter",
    "sg:city":"Baltimore",
    "sg:classifiers":[
        {
            "category":"Building & Trades",
            "subcategory":"Construction",
            "type":"Services"
        }
    ],
    "sg:phone":"+1 410 866 6844",
    "sg:postcode":"21206",
    "sg:province":"MD",
    "sg:tags":[
        "home",
        "improvement"
    ],
    "wof:name":"Mac-PAR-Svc",
    "wof:placetype":"venue"
},
  "geometry": {"coordinates":[-76.523921,39.337145],"type":"Point"}
}