{
  "type": "Feature",
  "properties": {
    "iso:country":"US",
    "sg:address":"6108 Main St",
    "sg:city":"Tilghman",
    "sg:classifiers":[
        {
            "category":"Shopping",
            "subcategory":"Bicycles & Sporting Goods",
            "type":"Retail Goods"
        }
    ],
    "sg:phone":"+1 410 886 9807",
    "sg:postcode":"21658",
    "sg:province":"MD",
    "sg:tags":[
        "tackle",
        "fishing"
    ],
    "wof:name":"Fairbank Tackle",
    "wof:placetype":"venue"
},
  "geometry": {"coordinates":[-76.170982,38.974749],"type":"Point"}
}