{
  "type": "Feature",
  "properties": {
    "iso:country":"US",
    "sg:address":"4611 Assembly Dr",
    "sg:city":"Lanham",
    "sg:classifiers":[
        {
            "category":"Manufacturing",
            "subcategory":"Printing",
            "type":"Manufacturing & Wholesale Goods"
        }
    ],
    "sg:phone":"+1 301 459 7666",
    "sg:postcode":"20706",
    "sg:province":"MD",
    "sg:tags":[
        "publisher"
    ],
    "sg:website":"www.statisticalabstract.com",
    "wof:name":"Bernan Associates",
    "wof:placetype":"venue"
},
  "geometry": {"coordinates":[-76.829877,38.952902],"type":"Point"}
}