{
  "type": "Feature",
  "properties": {
    "iso:country":"US",
    "sg:address":"6846 Basket Switch Rd",
    "sg:city":"Newark",
    "sg:classifiers":[
        {
            "category":"Manufacturing",
            "subcategory":"Rubber & Plastics",
            "type":"Manufacturing & Wholesale Goods"
        }
    ],
    "sg:phone":"+1 410 632 1582",
    "sg:postcode":"21841",
    "sg:province":"MD",
    "sg:tags":[
        "supply"
    ],
    "wof:name":"Voorhees Rubber Mfg Co",
    "wof:placetype":"venue"
},
  "geometry": {"coordinates":[-75.311328,38.235551],"type":"Point"}
}