{
  "type": "Feature",
  "properties": {
    "iso:country":"US",
    "sg:address":"3314 Elgin Ave",
    "sg:city":"Baltimore",
    "sg:classifiers":[
        {
            "category":"Building & Trades",
            "subcategory":"Landscaping Services",
            "type":"Services"
        }
    ],
    "sg:phone":"+1 410 233 4915",
    "sg:postcode":"21216",
    "sg:province":"MD",
    "wof:name":"Nobles Landscape Service",
    "wof:placetype":"venue"
},
  "geometry": {"coordinates":[-76.67420300000001,39.313199],"type":"Point"}
}