{
  "type": "Feature",
  "properties": {
    "iso:country":"US",
    "sg:address":"4900 Holabird Ave",
    "sg:city":"Baltimore",
    "sg:classifiers":[
        {
            "category":"Transit Center",
            "subcategory":"Freight",
            "type":"Transportation"
        },
        {
            "category":"Freight",
            "type":"Transportation"
        },
        {
            "category":"Local Transit",
            "type":"Transportation"
        }
    ],
    "sg:phone":"+1 410 631 7171",
    "sg:postcode":"21224",
    "sg:province":"MD",
    "sg:tags":[
        "public",
        "trucking-motor",
        "trucking"
    ],
    "wof:name":"Bestway Transport Inc",
    "wof:placetype":"venue"
},
  "geometry": {"coordinates":[-76.554024,39.271702],"type":"Point"}
}