{
  "type": "Feature",
  "properties": {
    "iso:country":"US",
    "sg:address":"10213 Old Georgetown Rd",
    "sg:city":"Bethesda",
    "sg:classifiers":[
        {
            "category":"Personal",
            "subcategory":"Beauty Salon",
            "type":"Services"
        },
        {
            "category":"Personal",
            "subcategory":"Day Spa",
            "type":"Services"
        }
    ],
    "sg:phone":"+1 240 644 1319",
    "sg:postcode":"20814",
    "sg:province":"MD",
    "sg:tags":[
        "hair",
        "makeup",
        "artist"
    ],
    "sg:website":"www.reddoorspas.com",
    "wof:name":"Elizabeth Arden Red Door Spa",
    "wof:placetype":"venue"
},
  "geometry": {"coordinates":[-77.123627,39.022756],"type":"Point"}
}