{
  "type": "Feature",
  "properties": {
    "iso:country":"US",
    "sg:address":"7643 Bush Ave",
    "sg:city":"Pasadena",
    "sg:classifiers":[
        {
            "category":"Shopping",
            "subcategory":"Clothing, Apparel, & Fashions",
            "type":"Retail Goods"
        }
    ],
    "sg:phone":"+1 410 360 5005",
    "sg:postcode":"21122",
    "sg:province":"MD",
    "wof:name":"Accents EMB & Monogramming",
    "wof:placetype":"venue"
},
  "geometry": {"coordinates":[-76.468263,39.146033],"type":"Point"}
}