{
  "type": "Feature",
  "properties": {
    "iso:country":"US",
    "sg:address":"5506 Kenilworth Ave",
    "sg:city":"Riverdale",
    "sg:classifiers":[
        {
            "category":"Personal",
            "subcategory":"Beauty Salon",
            "type":"Services"
        }
    ],
    "sg:phone":"+1 301 277 4105",
    "sg:postcode":"20737",
    "sg:province":"MD",
    "sg:tags":[
        "hair"
    ],
    "wof:name":"Nyalen African Hair Braiding",
    "wof:placetype":"venue"
},
  "geometry": {"coordinates":[-76.92269899999999,38.955898],"type":"Point"}
}