{
  "type": "Feature",
  "properties": {
    "iso:country":"US",
    "sg:address":"7700 Old National Pike",
    "sg:city":"Boonsboro",
    "sg:classifiers":[
        {
            "category":"Shopping Center",
            "type":"Public Place"
        }
    ],
    "sg:phone":"+1 301 416 2788",
    "sg:postcode":"21713",
    "sg:province":"MD",
    "sg:tags":[
        "flea",
        "market"
    ],
    "wof:name":"Auction Square Flea Market",
    "wof:placetype":"venue"
},
  "geometry": {"coordinates":[-77.663595,39.526112],"type":"Point"}
}