{
  "type": "Feature",
  "properties": {
    "addr:full":"1781 Forest Dr Annapolis MD 21401",
    "addr:housenumber":"1781",
    "addr:postcode":"21401",
    "addr:street":"Forest Dr",
    "iso:country":"US",
    "sg:address":"1781 Forest Dr",
    "sg:city":"Annapolis",
    "sg:phone":"+1 410 224 6090",
    "sg:postcode":"21401",
    "sg:province":"MD",
    "sg:website":"http://www.SunTrust.com",
    "wof:name":"SunTrust Bank - Forest Drive Safeway",
    "wof:placetype":"venue"
},
  "geometry": {"coordinates":[-76.52248299999999,38.971253],"type":"Point"}
}