{
  "type": "Feature",
  "properties": {
    "iso:country":"US",
    "sg:address":"103 Friendship Rd",
    "sg:city":"Friendship",
    "sg:classifiers":[
        {
            "category":"Organizations",
            "subcategory":"Community Association",
            "type":"Services"
        }
    ],
    "sg:phone":"+1 301 855 4383",
    "sg:postcode":"20758",
    "sg:province":"MD",
    "sg:tags":[
        "club"
    ],
    "wof:name":"Tribes Motor Cycle Club",
    "wof:placetype":"venue"
},
  "geometry": {"coordinates":[-76.582436,38.735675],"type":"Point"}
}