{
  "type": "Feature",
  "properties": {
    "addr:full":"127 S Carroll St Frederick MD 21701",
    "addr:housenumber":"127",
    "addr:postcode":"21701",
    "addr:street":"S Carroll St",
    "iso:country":"US",
    "sg:address":"127 S Carroll St",
    "sg:city":"Frederick",
    "sg:classifiers":[
        {
            "category":"Shopping",
            "subcategory":"Used Merchandise",
            "type":"Retail Goods"
        }
    ],
    "sg:phone":"+1 301 624 4032",
    "sg:postcode":"21701",
    "sg:province":"MD",
    "sg:tags":[
        "antique"
    ],
    "wof:name":"Laws & Grumman",
    "wof:placetype":"venue"
},
  "geometry": {"coordinates":[-77.408174,39.41129],"type":"Point"}
}