{
  "type": "Feature",
  "properties": {
    "iso:country":"US",
    "sg:address":"6111 Ager Rd",
    "sg:city":"Hyattsville",
    "sg:classifiers":[
        {
            "category":"Education",
            "subcategory":"School",
            "type":"Public Place"
        }
    ],
    "sg:phone":"+1 301 445 8090",
    "sg:postcode":"20782",
    "sg:province":"MD",
    "sg:tags":[
        "high",
        "middle",
        "elementary"
    ],
    "wof:name":"West Hyattsville Elementary School",
    "wof:placetype":"venue"
},
  "geometry": {"coordinates":[-76.97185899999999,38.96448],"type":"Point"}
}