{
  "type": "Feature",
  "properties": {
    "addr:full":"4206 Fallstaff Rd Baltimore MD 21215",
    "addr:housenumber":"4206",
    "addr:postcode":"21215",
    "addr:street":"Fallstaff Rd",
    "iso:country":"US",
    "sg:address":"4206 Fallstaff Rd",
    "sg:city":"Baltimore",
    "sg:classifiers":[
        {
            "category":"Retail",
            "subcategory":"Auto Repair",
            "type":"Services"
        }
    ],
    "sg:phone":"+1 410 580 1630",
    "sg:postcode":"21215",
    "sg:province":"MD",
    "sg:tags":[
        "automobile",
        "customizing"
    ],
    "wof:name":"Caliber Interior Auto Trim",
    "wof:placetype":"venue"
},
  "geometry": {"coordinates":[-76.711383,39.361046],"type":"Point"}
}