{
  "type": "Feature",
  "properties": {
    "addr:full":"4940 Eastern Ave Ste A-5 Baltimore MD 21224",
    "addr:housenumber":"4940",
    "addr:postcode":"21224",
    "addr:street":"Eastern Ave Ste A-5",
    "iso:country":"US",
    "sg:address":"4940 Eastern Ave Ste A-5",
    "sg:city":"Baltimore",
    "sg:classifiers":[
        {
            "category":"Health Services",
            "subcategory":"Doctor",
            "type":"Services"
        }
    ],
    "sg:phone":"+1 410 550 4336",
    "sg:postcode":"21224",
    "sg:province":"MD",
    "sg:tags":[
        "physician",
        "surgeon"
    ],
    "wof:name":"Sussman, Marc, Md - Johns Hopkins Bayview Med Ctr",
    "wof:placetype":"venue"
},
  "geometry": {"coordinates":[-76.554574,39.287148],"type":"Point"}
}