{
  "type": "Feature",
  "properties": {
    "iso:country":"US",
    "sg:address":"18508 Keedysville Rd",
    "sg:city":"Keedysville",
    "sg:classifiers":[
        {
            "category":"Building & Trades",
            "subcategory":"Construction",
            "type":"Services"
        }
    ],
    "sg:phone":"+1 301 432 7688",
    "sg:postcode":"21756",
    "sg:province":"MD",
    "sg:tags":[
        "hanging",
        "contractor"
    ],
    "wof:name":"Excalibur Painting",
    "wof:placetype":"venue"
},
  "geometry": {"coordinates":[-77.726598,39.503764],"type":"Point"}
}