{
  "type": "Feature",
  "properties": {
    "addr:full":"9095 Frederick Rd Ellicott City MD 21042",
    "addr:housenumber":"9095",
    "addr:postcode":"21042",
    "addr:street":"Frederick Rd",
    "iso:country":"US",
    "sg:address":"9095 Frederick Rd",
    "sg:city":"Ellicott City",
    "sg:classifiers":[
        {
            "category":"Ice Cream",
            "type":"Food & Drink"
        }
    ],
    "sg:phone":"+1 410 203 1756",
    "sg:postcode":"21042",
    "sg:province":"MD",
    "sg:tags":[
        "frozen",
        "yogurt"
    ],
    "sg:website":"www.ritasice.com/",
    "wof:name":"Rita's Italian Ice",
    "wof:placetype":"venue"
},
  "geometry": {"coordinates":[-76.826449,39.271443],"type":"Point"}
}