{
  "type": "Feature",
  "properties": {
    "addr:full":"1301 Sarah Dr Silver Spring MD 20904",
    "addr:housenumber":"1301",
    "addr:postcode":"20904",
    "addr:street":"Sarah Dr",
    "iso:country":"US",
    "sg:address":"1301 Sarah Dr",
    "sg:city":"Silver Spring",
    "sg:classifiers":[
        {
            "category":"Building & Trades",
            "subcategory":"Construction",
            "type":"Services"
        }
    ],
    "sg:phone":"+1 301 236 5725",
    "sg:postcode":"20904",
    "sg:province":"MD",
    "sg:tags":[
        "general",
        "contractor"
    ],
    "wof:name":"Suburban Builders",
    "wof:placetype":"venue"
},
  "geometry": {"coordinates":[-76.982269,39.053554],"type":"Point"}
}