{
  "type": "Feature",
  "properties": {
    "addr:full":"30 E Pennsylvania Ave Bel Air MD 21014",
    "addr:housenumber":"30",
    "addr:postcode":"21014",
    "addr:street":"E Pennsylvania Ave",
    "iso:country":"US",
    "sg:address":"30 E Pennsylvania Ave",
    "sg:city":"Bel Air",
    "sg:classifiers":[
        {
            "category":"Professional",
            "subcategory":"Lawyer & Legal Services",
            "type":"Services"
        }
    ],
    "sg:phone":"+1 410 836 5008",
    "sg:postcode":"21014",
    "sg:province":"MD",
    "sg:tags":[
        "attorney"
    ],
    "wof:name":"Shane P Nolan",
    "wof:placetype":"venue"
},
  "geometry": {"coordinates":[-76.349266,39.536865],"type":"Point"}
}