{
  "type": "Feature",
  "properties": {
    "addr:full":"1615 Hopewell Ave Essex MD 21221",
    "addr:housenumber":"1615",
    "addr:postcode":"21221",
    "addr:street":"Hopewell Ave",
    "iso:country":"US",
    "sg:address":"1615 Hopewell Ave",
    "sg:city":"Essex",
    "sg:classifiers":[
        {
            "category":"Social Services",
            "subcategory":"Child Care",
            "type":"Services"
        }
    ],
    "sg:phone":"+1 410 780 0146",
    "sg:postcode":"21221",
    "sg:province":"MD",
    "sg:tags":[
        "day"
    ],
    "wof:name":"Hopewell Day Care",
    "wof:placetype":"venue"
},
  "geometry": {"coordinates":[-76.447304,39.313801],"type":"Point"}
}