{
  "type": "Feature",
  "properties": {
    "iso:country":"US",
    "sg:address":"11080 Weymouth Ct",
    "sg:city":"Waldorf",
    "sg:classifiers":[
        {
            "category":"Real Estate",
            "subcategory":"Real Estate Operator",
            "type":"Services"
        }
    ],
    "sg:phone":"+1 301 638 4055",
    "sg:postcode":"20603",
    "sg:province":"MD",
    "sg:tags":[
        "apartment"
    ],
    "wof:name":"Victoria Park Apartments",
    "wof:placetype":"venue"
},
  "geometry": {"coordinates":[-76.925148,38.621995],"type":"Point"}
}