{
  "type": "Feature",
  "properties": {
    "addr:full":"18048 Wagonwheel Ct Olney MD 20832",
    "addr:postcode":"18048;20832",
    "addr:street":"Wagonwheel Ct",
    "iso:country":"US",
    "sg:address":"18048 Wagonwheel Ct",
    "sg:city":"Olney",
    "sg:classifiers":[
        {
            "category":"Building & Trades",
            "subcategory":"Construction",
            "type":"Services"
        }
    ],
    "sg:phone":"+1 301 370 8050",
    "sg:postcode":"20832",
    "sg:province":"MD",
    "sg:tags":[
        "house"
    ],
    "wof:name":"PC Home Improvements",
    "wof:placetype":"venue"
},
  "geometry": {"coordinates":[-77.080735,39.152535],"type":"Point"}
}