{
  "type": "Feature",
  "properties": {
    "addr:full":"18638 Crestwood Dr Hagerstown MD 21742",
    "addr:housenumber":"18638",
    "addr:postcode":"21742",
    "addr:street":"Crestwood Dr",
    "iso:country":"US",
    "sg:address":"18638 Crestwood Dr",
    "sg:city":"Hagerstown",
    "sg:classifiers":[
        {
            "category":"Health Services",
            "subcategory":"Doctor",
            "type":"Services"
        }
    ],
    "sg:phone":"+1 301 797 6950",
    "sg:postcode":"21742",
    "sg:province":"MD",
    "sg:tags":[
        "dentist"
    ],
    "wof:name":"Pearlman & Seidman",
    "wof:placetype":"venue"
},
  "geometry": {"coordinates":[-77.72381300000001,39.672375],"type":"Point"}
}