{
  "type": "Feature",
  "properties": {
    "addr:full":"9108 Marseille Dr Potomac MD 20854",
    "addr:housenumber":"9108",
    "addr:postcode":"20854",
    "addr:street":"Marseille Dr",
    "iso:country":"US",
    "sg:address":"9108 Marseille Dr",
    "sg:city":"Potomac",
    "sg:classifiers":[
        {
            "category":"Professional",
            "subcategory":"Engineering",
            "type":"Services"
        },
        {
            "category":"Building & Trades",
            "subcategory":"Construction",
            "type":"Services"
        }
    ],
    "sg:phone":"+1 301 983 5820",
    "sg:postcode":"20854",
    "sg:province":"MD",
    "sg:tags":[
        "nonresidential",
        "engineer"
    ],
    "wof:name":"Zahedian & Assoc",
    "wof:placetype":"venue"
},
  "geometry": {"coordinates":[-77.18906,39.041352],"type":"Point"}
}