{
  "type": "Feature",
  "properties": {
    "iso:country":"US",
    "sg:address":"3168 Braverton St",
    "sg:city":"Edgewater",
    "sg:classifiers":[
        {
            "category":"Health Services",
            "subcategory":"Clinic",
            "type":"Services"
        }
    ],
    "sg:phone":"+1 443 321 6500",
    "sg:postcode":"21037",
    "sg:province":"MD",
    "sg:tags":[
        "home"
    ],
    "wof:name":"Anne Arundel Home Health",
    "wof:placetype":"venue"
},
  "geometry": {"coordinates":[-76.56536699999999,38.931621],"type":"Point"}
}