{
  "type": "Feature",
  "properties": {
    "addr:full":"4706 Jones Village Rd Hurlock MD 21643",
    "addr:housenumber":"4706",
    "addr:postcode":"21643",
    "addr:street":"Jones Village Rd",
    "iso:country":"US",
    "sg:address":"4706 Jones Village Rd",
    "sg:city":"Hurlock",
    "sg:classifiers":[
        {
            "category":"Retail",
            "subcategory":"Laundry & Dry Cleaning",
            "type":"Services"
        },
        {
            "category":"Building & Trades",
            "subcategory":"Cleaning & Sanitation",
            "type":"Services"
        }
    ],
    "sg:phone":"+1 410 943 0020",
    "sg:postcode":"21643",
    "sg:province":"MD",
    "sg:tags":[
        "cleaner",
        "house"
    ],
    "wof:name":"Clean House",
    "wof:placetype":"venue"
},
  "geometry": {"coordinates":[-75.851298,38.621609],"type":"Point"}
}