{
  "type": "Feature",
  "properties": {
    "iso:country":"US",
    "sg:address":"7240 Standard Dr",
    "sg:city":"Hanover",
    "sg:classifiers":[
        {
            "category":"Marine",
            "type":"Transportation"
        }
    ],
    "sg:phone":"+1 410 712 4242",
    "sg:postcode":"21076",
    "sg:province":"MD",
    "sg:tags":[
        "towing"
    ],
    "wof:name":"Groco",
    "wof:placetype":"venue"
},
  "geometry": {"coordinates":[-76.72493,39.179833],"type":"Point"}
}