{
  "type": "Feature",
  "properties": {
    "addr:full":"104 Riverton Ave Denton MD 21629",
    "addr:housenumber":"104",
    "addr:postcode":"21629",
    "addr:street":"Riverton Ave",
    "iso:country":"US",
    "sg:address":"104 Riverton Ave",
    "sg:city":"Denton",
    "sg:classifiers":[
        {
            "category":"Manufacturing",
            "subcategory":"Building Materials",
            "type":"Manufacturing & Wholesale Goods"
        }
    ],
    "sg:phone":"+1 410 479 3282",
    "sg:postcode":"21629",
    "sg:province":"MD",
    "sg:tags":[
        "mfg",
        "wood",
        "kitchen",
        "cabinet"
    ],
    "wof:name":"Lionel Bradley Goss",
    "wof:placetype":"venue"
},
  "geometry": {"coordinates":[-75.83442599999999,38.883113],"type":"Point"}
}