{
  "type": "Feature",
  "properties": {
    "addr:full":"12 Scottsdale Ct Lutherville MD 21093",
    "addr:housenumber":"12",
    "addr:postcode":"21093",
    "addr:street":"Scottsdale Ct",
    "iso:country":"US",
    "sg:address":"12 Scottsdale Ct",
    "sg:city":"Lutherville",
    "sg:classifiers":[
        {
            "category":"Health Services",
            "subcategory":"Doctor",
            "type":"Services"
        }
    ],
    "sg:phone":"+1 410 821 7817",
    "sg:postcode":"21093",
    "sg:province":"MD",
    "sg:tags":[
        "physician",
        "surgeon"
    ],
    "wof:name":"Parkway Anesthesiologists",
    "wof:placetype":"venue"
},
  "geometry": {"coordinates":[-76.654185,39.42142],"type":"Point"}
}