{
  "type": "Feature",
  "properties": {
    "iso:country":"US",
    "sg:address":"827 Windsor Rd",
    "sg:city":"Arnold",
    "sg:classifiers":[
        {
            "category":"Professional",
            "subcategory":"Management & Consulting",
            "type":"Services"
        }
    ],
    "sg:phone":"+1 410 507 2837",
    "sg:postcode":"21012",
    "sg:province":"MD",
    "wof:name":"Graffiti Promotions LLC",
    "wof:placetype":"venue"
},
  "geometry": {"coordinates":[-76.502138,39.054203],"type":"Point"}
}