{
  "type": "Feature",
  "properties": {
    "iso:country":"US",
    "sg:address":"7611 S Osborne Rd",
    "sg:city":"Upper Marlboro",
    "sg:classifiers":[
        {
            "category":"Personal",
            "type":"Services"
        }
    ],
    "sg:phone":"+1 301 627 5702",
    "sg:postcode":"20772",
    "sg:province":"MD",
    "sg:tags":[
        "therapist",
        "massage"
    ],
    "wof:name":"Massage Center",
    "wof:placetype":"venue"
},
  "geometry": {"coordinates":[-76.797243,38.784982],"type":"Point"}
}