{
  "type": "Feature",
  "properties": {
    "addr:full":"10518 Pine Haven Ter Rockville MD 20852",
    "addr:housenumber":"10518",
    "addr:postcode":"20852",
    "addr:street":"Pine Haven Ter",
    "iso:country":"US",
    "sg:address":"10518 Pine Haven Ter",
    "sg:city":"Rockville",
    "sg:classifiers":[
        {
            "category":"Professional",
            "subcategory":"Accounting & Tax Preparation",
            "type":"Services"
        }
    ],
    "sg:phone":"+1 301 881 0740",
    "sg:postcode":"20852",
    "sg:province":"MD",
    "sg:tags":[
        "accountant"
    ],
    "wof:name":"Brown Arthur J",
    "wof:placetype":"venue"
},
  "geometry": {"coordinates":[-77.117401,39.030499],"type":"Point"}
}