{
  "type": "Feature",
  "properties": {
    "iso:country":"US",
    "sg:address":"201 Hanover St",
    "sg:city":"Annapolis",
    "sg:classifiers":[
        {
            "category":"Organizations",
            "subcategory":"Religious Organization",
            "type":"Services"
        }
    ],
    "sg:phone":"+1 410 263 0963",
    "sg:postcode":"21401",
    "sg:province":"MD",
    "sg:tags":[
        "church"
    ],
    "wof:name":"Baptist Student Union",
    "wof:placetype":"venue"
},
  "geometry": {"coordinates":[-76.486819,38.981327],"type":"Point"}
}