{
  "type": "Feature",
  "properties": {
    "iso:country":"US",
    "sg:address":"2706 Hamils Ct",
    "sg:city":"Crofton",
    "sg:classifiers":[
        {
            "category":"Professional",
            "subcategory":"Computer Services",
            "type":"Services"
        }
    ],
    "sg:phone":"+1 410 451 0232",
    "sg:postcode":"21114",
    "sg:province":"MD",
    "sg:tags":[
        "related"
    ],
    "wof:name":"Douglas Cahill",
    "wof:placetype":"venue"
},
  "geometry": {"coordinates":[-76.68567400000001,39.021769],"type":"Point"}
}