{
  "type": "Feature",
  "properties": {
    "addr:full":"1 Montgomery Ave Gaithersburg MD 20877",
    "addr:housenumber":"1",
    "addr:postcode":"20877",
    "addr:street":"Montgomery Ave",
    "iso:country":"US",
    "sg:address":"1 Montgomery Ave",
    "sg:city":"Gaithersburg",
    "sg:classifiers":[
        {
            "category":"Autos & Motor Vehicles",
            "subcategory":"Auto Supplies",
            "type":"Retail Goods"
        }
    ],
    "sg:phone":"+1 301 590 0624",
    "sg:postcode":"20877",
    "sg:province":"MD",
    "sg:tags":[
        "muffler",
        "system",
        "exhaust"
    ],
    "wof:name":"Midas Muffler",
    "wof:placetype":"venue"
},
  "geometry": {"coordinates":[-77.20369700000001,39.145672],"type":"Point"}
}