{
  "type": "Feature",
  "properties": {
    "addr:full":"3 Bertwell Ct Timonium MD 21093",
    "addr:housenumber":"3",
    "addr:postcode":"21093",
    "addr:street":"Bertwell Ct",
    "iso:country":"US",
    "sg:address":"3 Bertwell Ct",
    "sg:city":"Timonium",
    "sg:classifiers":[
        {
            "category":"Government",
            "subcategory":"Office",
            "type":"Public Place"
        }
    ],
    "sg:phone":"+1 410 561 7400",
    "sg:postcode":"21093",
    "sg:province":"MD",
    "sg:tags":[
        "state",
        "program",
        "health"
    ],
    "wof:name":"Health Gate Data Corp",
    "wof:placetype":"venue"
},
  "geometry": {"coordinates":[-76.626206,39.452302],"type":"Point"}
}