{
  "type": "Feature",
  "properties": {
    "iso:country":"US",
    "sg:address":"1115 Hollins St",
    "sg:city":"Baltimore",
    "sg:classifiers":[
        {
            "category":"Wholesale",
            "subcategory":"Toys & Hobbies",
            "type":"Manufacturing & Wholesale Goods"
        }
    ],
    "sg:phone":"+1 410 752 7272",
    "sg:postcode":"21223",
    "sg:province":"MD",
    "sg:tags":[
        "shop",
        "gift",
        "planning",
        "puppet",
        "marionette",
        "party",
        "event"
    ],
    "sg:website":"www.blackcherry.org",
    "wof:name":"Black Cherry Puppet Theater",
    "wof:placetype":"venue"
},
  "geometry": {"coordinates":[-76.635696,39.287601],"type":"Point"}
}