{
  "type": "Feature",
  "properties": {
    "addr:full":"115 Court St Chestertown MD 21620",
    "addr:housenumber":"115",
    "addr:postcode":"21620",
    "addr:street":"Court St",
    "iso:country":"US",
    "sg:address":"115 Court St",
    "sg:city":"Chestertown",
    "sg:classifiers":[
        {
            "category":"Government",
            "subcategory":"Court House",
            "type":"Public Place"
        }
    ],
    "sg:phone":"+1 410 778 0809",
    "sg:postcode":"21620",
    "sg:province":"MD",
    "sg:tags":[
        "state",
        "counsel"
    ],
    "wof:name":"Public Defender",
    "wof:placetype":"venue"
},
  "geometry": {"coordinates":[-76.065404,39.208725],"type":"Point"}
}