{
  "type": "Feature",
  "properties": {
    "iso:country":"US",
    "sg:address":"5915 Greenbelt Rd",
    "sg:city":"College Park",
    "sg:classifiers":[
        {
            "category":"Health Services",
            "subcategory":"Doctor",
            "type":"Services"
        }
    ],
    "sg:phone":"+1 301 474 3332",
    "sg:postcode":"20740",
    "sg:province":"MD",
    "sg:tags":[
        "clinic"
    ],
    "wof:name":"Metropolitan Family Plg Inst",
    "wof:placetype":"venue"
},
  "geometry": {"coordinates":[-76.912265,38.997833],"type":"Point"}
}