{
  "type": "Feature",
  "properties": {
    "addr:full":"17501 Sir Galahad Way Ashton MD 20861",
    "addr:housenumber":"17501",
    "addr:postcode":"20861",
    "addr:street":"Sir Galahad Way",
    "iso:country":"US",
    "sg:address":"17501 Sir Galahad Way",
    "sg:city":"Ashton",
    "sg:classifiers":[
        {
            "category":"Social Services",
            "type":"Services"
        }
    ],
    "sg:phone":"+1 301 260 0003",
    "sg:postcode":"20861",
    "sg:province":"MD",
    "wof:name":"Adoption Resources",
    "wof:placetype":"venue"
},
  "geometry": {"coordinates":[-77.00097599999999,39.143233],"type":"Point"}
}