{
  "type": "Feature",
  "properties": {
    "iso:country":"US",
    "sg:address":"17501 Sir Galahad Way",
    "sg:city":"Ashton",
    "sg:classifiers":[
        {
            "category":"Social Services",
            "type":"Services"
        }
    ],
    "sg:phone":"+1 301 260 0003",
    "sg:postcode":"20861",
    "sg:province":"MD",
    "wof:name":"Adoption Resources",
    "wof:placetype":"venue"
},
  "geometry": {"coordinates":[-77.000976,39.143233],"type":"Point"}
}