{
  "type": "Feature",
  "properties": {
    "addr:full":"12417 Ocean Gtwy Ocean City MD 21842",
    "addr:housenumber":"12417",
    "addr:postcode":"21842",
    "addr:street":"Ocean Gtwy",
    "iso:country":"US",
    "sg:address":"12417 Ocean Gtwy",
    "sg:city":"Ocean City",
    "sg:classifiers":[
        {
            "category":"Health Services",
            "subcategory":"Health Practitioner",
            "type":"Services"
        }
    ],
    "sg:phone":"+1 410 213 7878",
    "sg:postcode":"21842",
    "sg:province":"MD",
    "sg:tags":[
        "therapist",
        "physical"
    ],
    "wof:name":"Peninsula Rehab & Sports Med",
    "wof:placetype":"venue"
},
  "geometry": {"coordinates":[-75.125214,38.339621],"type":"Point"}
}