{
  "type": "Feature",
  "properties": {
    "iso:country":"US",
    "sg:address":"700 N Calhoun St",
    "sg:city":"Baltimore",
    "sg:classifiers":[
        {
            "category":"Government",
            "subcategory":"Office",
            "type":"Public Place"
        }
    ],
    "sg:phone":"+1 443 984 2948",
    "sg:postcode":"21217",
    "sg:province":"MD",
    "sg:tags":[
        "township",
        "government-city",
        "village"
    ],
    "wof:name":"Mayor&City Council",
    "wof:placetype":"venue"
},
  "geometry": {"coordinates":[-76.63999200000001,39.29681],"type":"Point"}
}