{
  "type": "Feature",
  "properties": {
    "iso:country":"US",
    "sg:address":"10920 Pump House Rd",
    "sg:city":"Annapolis Jct",
    "sg:classifiers":[
        {
            "category":"Building & Trades",
            "subcategory":"Plumbing",
            "type":"Services"
        }
    ],
    "sg:phone":"+1 301 617 3507",
    "sg:postcode":"20701",
    "sg:province":"MD",
    "sg:tags":[
        "plumbing",
        "contractor"
    ],
    "wof:name":"Ben Lewis Plumbing",
    "wof:placetype":"venue"
},
  "geometry": {"coordinates":[-76.792141,39.131012],"type":"Point"}
}