{
  "type": "Feature",
  "properties": {
    "iso:country":"US",
    "sg:address":"9410 Holland Ave",
    "sg:city":"Bethesda",
    "sg:classifiers":[
        {
            "category":"Utilities",
            "subcategory":"Telephone",
            "type":"Services"
        }
    ],
    "sg:phone":"+1 301 571 4356",
    "sg:postcode":"20814",
    "sg:province":"MD",
    "sg:tags":[
        "telecommunication"
    ],
    "wof:name":"Columbia Wireless Facilities",
    "wof:placetype":"venue"
},
  "geometry": {"coordinates":[-77.103894,39.010591],"type":"Point"}
}