{
  "type": "Feature",
  "properties": {
    "addr:full":"2405 Brandermill Blvd Gambrills MD 21054",
    "addr:housenumber":"2405",
    "addr:postcode":"21054",
    "addr:street":"Brandermill Blvd",
    "iso:country":"US",
    "sg:address":"2405 Brandermill Blvd",
    "sg:city":"Gambrills",
    "sg:classifiers":[
        {
            "category":"Banks & Credit Unions",
            "subcategory":"Bank",
            "type":"Services"
        }
    ],
    "sg:phone":"+1 301 261 3200",
    "sg:postcode":"21054",
    "sg:province":"MD",
    "sg:tags":[
        "loan",
        "real estate"
    ],
    "wof:name":"B B & T",
    "wof:placetype":"venue"
},
  "geometry": {"coordinates":[-76.681811,39.035436],"type":"Point"}
}