{
  "type": "Feature",
  "properties": {
    "iso:country":"US",
    "sg:address":"1417 Clarkview Rd",
    "sg:city":"Baltimore",
    "sg:classifiers":[
        {
            "category":"Home & Garden",
            "subcategory":"Building Materials",
            "type":"Retail Goods"
        },
        {
            "category":"Building & Trades",
            "subcategory":"Construction",
            "type":"Services"
        }
    ],
    "sg:phone":"+1 410 821 5105",
    "sg:postcode":"21209",
    "sg:province":"MD",
    "sg:tags":[
        "industrial",
        "contractor",
        "concrete",
        "contractors-commercial",
        "staining",
        "masonry",
        "mason"
    ],
    "wof:name":"Mercury Masonry Inc",
    "wof:placetype":"venue"
},
  "geometry": {"coordinates":[-76.657402,39.381691],"type":"Point"}
}