{
  "type": "Feature",
  "properties": {
    "addr:full":"3913 Southern Ave Apt 2 Suitland MD 20746",
    "addr:housenumber":"3913;2",
    "addr:postcode":"20746",
    "addr:street":"Southern Ave Apt",
    "iso:country":"US",
    "sg:address":"3913 Southern Ave Apt 2",
    "sg:city":"Suitland",
    "sg:classifiers":[
        {
            "category":"Wholesale",
            "subcategory":"Non-durable Goods",
            "type":"Manufacturing & Wholesale Goods"
        }
    ],
    "sg:phone":"+1 240 441 9842",
    "sg:postcode":"20746",
    "sg:province":"MD",
    "sg:tags":[
        "dry",
        "goods-wholesale"
    ],
    "wof:name":"Sherrys Beauty Supply",
    "wof:placetype":"venue"
},
  "geometry": {"coordinates":[-76.948021,38.862751],"type":"Point"}
}