{
  "type": "Feature",
  "properties": {
    "iso:country":"US",
    "sg:address":"4268 Wisconsin Ave NW",
    "sg:city":"Washington",
    "sg:classifiers":[
        {
            "category":"Real Estate",
            "subcategory":"Real Estate Agent",
            "type":"Services"
        }
    ],
    "sg:phone":"+1 202 363 6002",
    "sg:postcode":"20016",
    "sg:province":"MD",
    "wof:name":"Barry Bluefeld",
    "wof:placetype":"venue"
},
  "geometry": {"coordinates":[-77.07778999999999,38.944276],"type":"Point"}
}