{
  "type": "Feature",
  "properties": {
    "addr:full":"323 S Union Ave Havre De Grace MD 21078",
    "addr:housenumber":"323",
    "addr:postcode":"21078",
    "addr:street":"S Union Ave",
    "iso:country":"US",
    "sg:address":"323 S Union Ave",
    "sg:city":"Havre De Grace",
    "sg:classifiers":[
        {
            "category":"Health Services",
            "subcategory":"Doctor",
            "type":"Services"
        }
    ],
    "sg:phone":"+1 410 939 0961",
    "sg:postcode":"21078",
    "sg:province":"MD",
    "sg:tags":[
        "physician",
        "surgeon"
    ],
    "wof:name":"David Jaffe MD",
    "wof:placetype":"venue"
},
  "geometry": {"coordinates":[-76.091471,39.544739],"type":"Point"}
}