{
  "type": "Feature",
  "properties": {
    "iso:country":"US",
    "sg:address":"4805 42nd Pl",
    "sg:city":"Hyattsville",
    "sg:classifiers":[
        {
            "category":"Communications",
            "subcategory":"Film & Video Production",
            "type":"Services"
        },
        {
            "category":"Communications",
            "type":"Services"
        }
    ],
    "sg:phone":"+1 301 864 7888",
    "sg:postcode":"20781",
    "sg:province":"MD",
    "sg:tags":[
        "recording",
        "rehearsal",
        "studio",
        "service-sound"
    ],
    "wof:name":"The Clinic Recording Studio",
    "wof:placetype":"venue"
},
  "geometry": {"coordinates":[-76.94360399999999,38.948502],"type":"Point"}
}