{
  "type": "Feature",
  "properties": {
    "addr:full":"517 S Fountain Green Rd Bel Air MD 21015",
    "addr:housenumber":"517",
    "addr:postcode":"21015",
    "addr:street":"S Fountain Green Rd",
    "iso:country":"US",
    "sg:address":"517 S Fountain Green Rd",
    "sg:city":"Bel Air",
    "sg:classifiers":[
        {
            "category":"Education",
            "subcategory":"School",
            "type":"Public Place"
        }
    ],
    "sg:phone":"+1 410 638 4220",
    "sg:postcode":"21015",
    "sg:province":"MD",
    "sg:website":"www.hcps.org",
    "wof:name":"Fountain Green Elementary Sch",
    "wof:placetype":"venue"
},
  "geometry": {"coordinates":[-76.307439,39.541001],"type":"Point"}
}