{
  "type": "Feature",
  "properties": {
    "addr:full":"8361 Court Ave Ellicott City MD 21043",
    "addr:housenumber":"8361",
    "addr:postcode":"21043",
    "addr:street":"Court Ave",
    "iso:country":"US",
    "sg:address":"8361 Court Ave",
    "sg:city":"Ellicott City",
    "sg:classifiers":[
        {
            "category":"Professional",
            "subcategory":"Lawyer & Legal Services",
            "type":"Services"
        }
    ],
    "sg:phone":"+1 410 465 3919",
    "sg:postcode":"21043",
    "sg:province":"MD",
    "wof:name":"Acquisto Asplen & Morstein PA",
    "wof:placetype":"venue"
},
  "geometry": {"coordinates":[-76.79969800000001,39.268398],"type":"Point"}
}