{
  "type": "Feature",
  "properties": {
    "addr:full":"10400 Shaker Dr Columbia MD 21046",
    "addr:housenumber":"10400",
    "addr:postcode":"21046",
    "addr:street":"Shaker Dr",
    "iso:country":"US",
    "sg:address":"10400 Shaker Dr",
    "sg:city":"Columbia",
    "sg:classifiers":[
        {
            "category":"Personal",
            "subcategory":"Beauty Salon",
            "type":"Services"
        }
    ],
    "sg:phone":"+1 410 715 1617",
    "sg:postcode":"21046",
    "sg:province":"MD",
    "sg:tags":[
        "nail",
        "manicuring"
    ],
    "wof:name":"Lee Nail Salon",
    "wof:placetype":"venue"
},
  "geometry": {"coordinates":[-76.871803,39.183998],"type":"Point"}
}