{
  "type": "Feature",
  "properties": {
    "iso:country":"US",
    "sg:address":"63 West St",
    "sg:city":"Annapolis",
    "sg:classifiers":[
        {
            "category":"Shopping",
            "subcategory":"Gifts & Souvenirs",
            "type":"Retail Goods"
        }
    ],
    "sg:phone":"+1 410 626 1250",
    "sg:postcode":"21401",
    "sg:province":"MD",
    "sg:tags":[
        "shop"
    ],
    "wof:name":"Tin Can Allee",
    "wof:placetype":"venue"
},
  "geometry": {"coordinates":[-76.496252,38.978123],"type":"Point"}
}