{
  "type": "Feature",
  "properties": {
    "iso:country":"US",
    "sg:address":"1022 E West Hwy",
    "sg:city":"Takoma Park",
    "sg:classifiers":[
        {
            "category":"Building & Trades",
            "subcategory":"Construction",
            "type":"Services"
        }
    ],
    "sg:phone":"+1 301 891 3565",
    "sg:postcode":"20912",
    "sg:province":"MD",
    "sg:tags":[
        "general",
        "contractor"
    ],
    "wof:name":"Lone Co",
    "wof:placetype":"venue"
},
  "geometry": {"coordinates":[-76.987944,38.975347],"type":"Point"}
}