{
  "type": "Feature",
  "properties": {
    "addr:full":"443 N Frederick Ave Gaithersburg MD 20877",
    "addr:housenumber":"443",
    "addr:postcode":"20877",
    "addr:street":"N Frederick Ave",
    "iso:country":"US",
    "sg:address":"443 N Frederick Ave",
    "sg:city":"Gaithersburg",
    "sg:classifiers":[
        {
            "category":"Professional",
            "subcategory":"Lawyer & Legal Services",
            "type":"Services"
        }
    ],
    "sg:phone":"+1 301 921 4455",
    "sg:postcode":"20877",
    "sg:province":"MD",
    "sg:tags":[
        "attorney"
    ],
    "wof:name":"Paul S Lewis",
    "wof:placetype":"venue"
},
  "geometry": {"coordinates":[-77.20641500000001,39.147918],"type":"Point"}
}