{
  "type": "Feature",
  "properties": {
    "addr:full":"7301 Garland Ave Takoma Park MD 20912",
    "addr:housenumber":"7301",
    "addr:postcode":"20912",
    "addr:street":"Garland Ave",
    "iso:country":"US",
    "sg:address":"7301 Garland Ave",
    "sg:city":"Takoma Park",
    "sg:classifiers":[
        {
            "category":"Health Services",
            "subcategory":"Health Practitioner",
            "type":"Services"
        }
    ],
    "sg:phone":"+1 301 270 0111",
    "sg:postcode":"20912",
    "sg:province":"MD",
    "wof:name":"Womens Touch Child Birth Svcs",
    "wof:placetype":"venue"
},
  "geometry": {"coordinates":[-76.99520099999999,38.985752],"type":"Point"}
}