{
  "type": "Feature",
  "properties": {
    "iso:country":"US",
    "sg:address":"5335 Wisconsin Ave NW",
    "sg:city":"Washington",
    "sg:classifiers":[
        {
            "category":"Professional",
            "subcategory":"Engineering",
            "type":"Services"
        }
    ],
    "sg:phone":"+1 202 895 1703",
    "sg:postcode":"20015",
    "sg:province":"MD",
    "sg:tags":[
        "engineer"
    ],
    "wof:name":"Alpha International",
    "wof:placetype":"venue"
},
  "geometry": {"coordinates":[-77.084846,38.959041],"type":"Point"}
}