{
  "type": "Feature",
  "properties": {
    "addr:full":"3841 Rumsey Dr Trappe MD 21673",
    "addr:housenumber":"3841",
    "addr:postcode":"21673",
    "addr:street":"Rumsey Dr",
    "iso:country":"US",
    "sg:address":"3841 Rumsey Dr",
    "sg:city":"Trappe",
    "sg:classifiers":[
        {
            "category":"Organizations",
            "subcategory":"Religious Organization",
            "type":"Services"
        }
    ],
    "sg:phone":"+1 410 822 8309",
    "sg:postcode":"21673",
    "sg:province":"MD",
    "sg:tags":[
        "clergy"
    ],
    "wof:name":"Walter M Fire",
    "wof:placetype":"venue"
},
  "geometry": {"coordinates":[-76.052773,38.655436],"type":"Point"}
}