{
  "type": "Feature",
  "properties": {
    "iso:country":"US",
    "sg:address":"126 Walkers Village Way",
    "sg:city":"Walkersville",
    "sg:classifiers":[
        {
            "category":"Personal",
            "subcategory":"Beauty Salon",
            "type":"Services"
        }
    ],
    "sg:phone":"+1 301 845 4050",
    "sg:postcode":"21793",
    "sg:province":"MD",
    "wof:name":"Misti's Hair Affair LTD",
    "wof:placetype":"venue"
},
  "geometry": {"coordinates":[-77.340385,39.483346],"type":"Point"}
}