{
  "type": "Feature",
  "properties": {
    "addr:full":"7272 Park Circle Dr # 100 Hanover MD 21076",
    "addr:housenumber":"7272",
    "addr:postcode":"21076",
    "addr:street":"Park Circle Dr # 100",
    "iso:country":"US",
    "sg:address":"7272 Park Circle Dr # 100",
    "sg:city":"Hanover",
    "sg:classifiers":[
        {
            "category":"Banks & Credit Unions",
            "subcategory":"Financial Services",
            "type":"Services"
        }
    ],
    "sg:phone":"+1 410 712 7120",
    "sg:postcode":"21076",
    "sg:province":"MD",
    "sg:tags":[
        "mortgage"
    ],
    "sg:website":"http://www.homelendingpartners.com",
    "wof:name":"Home Lending Partners",
    "wof:placetype":"venue"
},
  "geometry": {"coordinates":[-76.732651,39.179581],"type":"Point"}
}