{
  "type": "Feature",
  "properties": {
    "iso:country":"US",
    "sg:address":"7525 Greenway Center Dr 210",
    "sg:city":"Greenbelt",
    "sg:classifiers":[
        {
            "category":"Health Services",
            "subcategory":"Doctor",
            "type":"Services"
        }
    ],
    "sg:phone":"+1 301 345 8882",
    "sg:postcode":"20770",
    "sg:province":"MD",
    "sg:tags":[
        "physician",
        "family",
        "practice",
        "surgeons",
        "medicine",
        "surgeon"
    ],
    "wof:name":"G Gasemy Md, Pa",
    "wof:placetype":"venue"
},
  "geometry": {"coordinates":[-76.878576,38.991718],"type":"Point"}
}