{
  "type": "Feature",
  "properties": {
    "iso:country":"US",
    "sg:address":"7314 German Hill Rd",
    "sg:city":"Dundalk",
    "sg:classifiers":[
        {
            "category":"Real Estate",
            "subcategory":"Real Estate Services",
            "type":"Services"
        }
    ],
    "sg:phone":"+1 410 282 1754",
    "sg:postcode":"21222",
    "sg:province":"MD",
    "sg:tags":[
        "commercial"
    ],
    "wof:name":"Louise A Koch Real Estate",
    "wof:placetype":"venue"
},
  "geometry": {"coordinates":[-76.516853,39.282761],"type":"Point"}
}