{
  "type": "Feature",
  "properties": {
    "iso:country":"US",
    "sg:address":"2445 W Zion Rd",
    "sg:city":"Salisbury",
    "sg:classifiers":[
        {
            "category":"Manufacturing",
            "subcategory":"Tools & Machinery",
            "type":"Manufacturing & Wholesale Goods"
        }
    ],
    "sg:phone":"+1 410 749 5296",
    "sg:postcode":"21801",
    "sg:province":"MD",
    "sg:tags":[
        "equipment",
        "irrigation",
        "system"
    ],
    "wof:name":"Total Lawn Care",
    "wof:placetype":"venue"
},
  "geometry": {"coordinates":[-75.56977999999999,38.406108],"type":"Point"}
}