{
  "type": "Feature",
  "properties": {
    "addr:full":"679 Old New Windsor Pike Westminster MD 21157",
    "addr:housenumber":"679",
    "addr:postcode":"21157",
    "addr:street":"Old New Windsor Pike",
    "iso:country":"US",
    "sg:address":"679 Old New Windsor Pike",
    "sg:city":"Westminster",
    "sg:classifiers":[
        {
            "category":"Building & Trades",
            "subcategory":"Cleaning & Sanitation",
            "type":"Services"
        }
    ],
    "sg:phone":"+1 410 876 0201",
    "sg:postcode":"21157",
    "sg:province":"MD",
    "sg:tags":[
        "property",
        "maintenance"
    ],
    "wof:name":"Ridin Bringhurst Assoc Inc",
    "wof:placetype":"venue"
},
  "geometry": {"coordinates":[-77.02172299999999,39.566577],"type":"Point"}
}