{
  "type": "Feature",
  "properties": {
    "iso:country":"US",
    "sg:address":"2251 Goldsboro Rd",
    "sg:city":"Ingleside",
    "sg:classifiers":[
        {
            "category":"Home & Garden",
            "subcategory":"Building Materials",
            "type":"Retail Goods"
        }
    ],
    "sg:phone":"+1 410 758 0123",
    "sg:postcode":"21644",
    "sg:province":"MD",
    "sg:tags":[
        "sand",
        "gravel"
    ],
    "wof:name":"Merrick Farm Sand And Gravel",
    "wof:placetype":"venue"
},
  "geometry": {"coordinates":[-75.87055700000001,39.114217],"type":"Point"}
}