{
  "type": "Feature",
  "properties": {
    "addr:full":"2360 Barksdale Rd Elkton MD 21921",
    "addr:housenumber":"2360",
    "addr:postcode":"21921",
    "addr:street":"Barksdale Rd",
    "iso:country":"US",
    "sg:address":"2360 Barksdale Rd",
    "sg:city":"Elkton",
    "sg:classifiers":[
        {
            "category":"Building & Trades",
            "subcategory":"Construction",
            "type":"Services"
        }
    ],
    "sg:phone":"+1 410 398 2510",
    "sg:postcode":"21921",
    "sg:province":"MD",
    "sg:tags":[
        "hanging",
        "contractor"
    ],
    "wof:name":"Picky Painting Co",
    "wof:placetype":"venue"
},
  "geometry": {"coordinates":[-75.805998,39.668634],"type":"Point"}
}