{
  "type": "Feature",
  "properties": {
    "addr:full":"6811 Kenilworth Ave Riverdale MD 20737",
    "addr:housenumber":"6811",
    "addr:postcode":"20737",
    "addr:street":"Kenilworth Ave",
    "iso:country":"US",
    "sg:address":"6811 Kenilworth Ave",
    "sg:city":"Riverdale",
    "sg:classifiers":[
        {
            "category":"Professional",
            "subcategory":"Computer Services",
            "type":"Services"
        }
    ],
    "sg:phone":"+1 240 387 1000",
    "sg:postcode":"20737",
    "sg:province":"MD",
    "sg:tags":[
        "consultant",
        "designer"
    ],
    "sg:website":"www.gryphonteam.com",
    "wof:name":"Gryphon Technologies",
    "wof:placetype":"venue"
},
  "geometry": {"coordinates":[-76.915767,38.971022],"type":"Point"}
}