{
  "type": "Feature",
  "properties": {
    "iso:country":"US",
    "sg:address":"13200 Williams Rd SE",
    "sg:city":"Cumberland",
    "sg:classifiers":[
        {
            "category":"Organizations",
            "subcategory":"Religious Organization",
            "type":"Services"
        }
    ],
    "sg:phone":"+1 301 777 7760",
    "sg:postcode":"21502",
    "sg:province":"MD",
    "sg:tags":[
        "church"
    ],
    "wof:name":"Mt Hermon United Methodist Chr",
    "wof:placetype":"venue"
},
  "geometry": {"coordinates":[-78.719529,39.637742],"type":"Point"}
}