{
  "type": "Feature",
  "properties": {
    "addr:full":"13200 Williams Rd SE Cumberland MD 21502",
    "addr:housenumber":"13200",
    "addr:postcode":"21502",
    "addr:street":"Williams Rd Se",
    "iso:country":"US",
    "sg:address":"13200 Williams Rd SE",
    "sg:city":"Cumberland",
    "sg:classifiers":[
        {
            "category":"Organizations",
            "subcategory":"Religious Organization",
            "type":"Services"
        }
    ],
    "sg:phone":"+1 301 777 7760",
    "sg:postcode":"21502",
    "sg:province":"MD",
    "sg:tags":[
        "church"
    ],
    "wof:name":"Mt Hermon United Methodist Chr",
    "wof:placetype":"venue"
},
  "geometry": {"coordinates":[-78.71952899999999,39.637742],"type":"Point"}
}