{
  "type": "Feature",
  "properties": {
    "addr:full":"6279 N Steamboat Way New Market MD 21774",
    "addr:housenumber":"6279",
    "addr:postcode":"21774",
    "addr:street":"N Steamboat Way",
    "iso:country":"US",
    "sg:address":"6279 N Steamboat Way",
    "sg:city":"New Market",
    "sg:classifiers":[
        {
            "category":"Banks & Credit Unions",
            "subcategory":"Bank",
            "type":"Services"
        }
    ],
    "sg:phone":"+1 301 865 9777",
    "sg:postcode":"21774",
    "sg:province":"MD",
    "sg:tags":[
        "loan"
    ],
    "wof:name":"Money Marketing",
    "wof:placetype":"venue"
},
  "geometry": {"coordinates":[-77.293556,39.40546],"type":"Point"}
}