{
  "type": "Feature",
  "properties": {
    "iso:country":"US",
    "sg:address":"19105 Whistle Gate Ter",
    "sg:city":"Boyds",
    "sg:classifiers":[
        {
            "category":"Professional",
            "subcategory":"Detective & Security Services",
            "type":"Services"
        }
    ],
    "sg:phone":"+1 301 515 8116",
    "sg:postcode":"20841",
    "sg:province":"MD",
    "sg:tags":[
        "information",
        "bureau"
    ],
    "wof:name":"Eastern Tax Service",
    "wof:placetype":"venue"
},
  "geometry": {"coordinates":[-77.301497,39.172397],"type":"Point"}
}