{
  "type": "Feature",
  "properties": {
    "iso:country":"US",
    "sg:address":"5718 Highgate Dr",
    "sg:city":"Baltimore",
    "sg:classifiers":[
        {
            "category":"Real Estate",
            "subcategory":"Real Estate Services",
            "type":"Services"
        },
        {
            "category":"Real Estate",
            "subcategory":"Real Estate Agent",
            "type":"Services"
        }
    ],
    "sg:phone":"+1 410 466 9291",
    "sg:postcode":"21215",
    "sg:province":"MD",
    "sg:tags":[
        "management"
    ],
    "wof:name":"Kb Investments",
    "wof:placetype":"venue"
},
  "geometry": {"coordinates":[-76.680971,39.354846],"type":"Point"}
}