{
  "type": "Feature",
  "properties": {
    "iso:country":"US",
    "sg:address":"7818 Central Ave",
    "sg:city":"Hyattsville",
    "sg:classifiers":[
        {
            "category":"Education",
            "subcategory":"Kindergarten",
            "type":"Public Place"
        }
    ],
    "sg:phone":"+1 301 333 6022",
    "sg:postcode":"20785",
    "sg:province":"MD",
    "sg:tags":[
        "school",
        "driving"
    ],
    "wof:name":"Official Driving Academy",
    "wof:placetype":"venue"
},
  "geometry": {"coordinates":[-76.871183,38.889189],"type":"Point"}
}