{
  "type": "Feature",
  "properties": {
    "iso:country":"US",
    "sg:address":"2400 Round Rd",
    "sg:city":"Baltimore",
    "sg:classifiers":[
        {
            "category":"Education",
            "subcategory":"School",
            "type":"Public Place"
        }
    ],
    "sg:phone":"+1 410 396 1379",
    "sg:postcode":"21225",
    "sg:province":"MD",
    "sg:tags":[
        "high",
        "middle",
        "elementary"
    ],
    "wof:name":"Baltimore City School District",
    "wof:placetype":"venue"
},
  "geometry": {"coordinates":[-76.627174,39.252588],"type":"Point"}
}