{
  "type": "Feature",
  "properties": {
    "addr:full":"3916 W Belvedere Ave Baltimore MD 21215",
    "addr:housenumber":"3916",
    "addr:postcode":"21215",
    "addr:street":"W Belvedere Ave",
    "iso:country":"US",
    "sg:address":"3916 W Belvedere Ave",
    "sg:city":"Baltimore",
    "sg:classifiers":[
        {
            "category":"Restaurant",
            "type":"Food & Drink"
        }
    ],
    "sg:phone":"+1 410 664 1304",
    "sg:postcode":"21215",
    "sg:province":"MD",
    "wof:name":"Take A Steak Carry Out",
    "wof:placetype":"venue"
},
  "geometry": {"coordinates":[-76.682315,39.344508],"type":"Point"}
}