{
  "type": "Feature",
  "properties": {
    "iso:country":"US",
    "sg:address":"4832 Boiling Brook Pkwy",
    "sg:city":"Rockville",
    "sg:classifiers":[
        {
            "category":"Restaurant",
            "type":"Food & Drink"
        }
    ],
    "sg:phone":"+1 301 468 1922",
    "sg:postcode":"20852",
    "sg:province":"MD",
    "sg:tags":[
        "chinese"
    ],
    "wof:name":"Royal Dragon",
    "wof:placetype":"venue"
},
  "geometry": {"coordinates":[-77.0979,39.0467],"type":"Point"}
}