{
  "type": "Feature",
  "properties": {
    "iso:country":"US",
    "sg:address":"19004 Bloomfield Road",
    "sg:city":"Olney",
    "sg:classifiers":[
        {
            "category":"Utilities",
            "subcategory":"Water",
            "type":"Services"
        },
        {
            "category":"Building & Trades",
            "subcategory":"Cleaning & Sanitation",
            "type":"Services"
        },
        {
            "category":"Retail",
            "subcategory":"Car Wash",
            "type":"Services"
        },
        {
            "category":"Home & Garden",
            "subcategory":"Garden Supply",
            "type":"Retail Goods"
        }
    ],
    "sg:phone":"+1 301 949 8000",
    "sg:postcode":"20832",
    "sg:province":"MD",
    "sg:tags":[
        "chemical",
        "equipment",
        "systems-pressure",
        "washing",
        "pressure"
    ],
    "wof:name":"Superior Pressure Washing",
    "wof:placetype":"venue"
},
  "geometry": {"coordinates":[-77.07025,39.0223],"type":"Point"}
}