{
  "type": "Feature",
  "properties": {
    "addr:full":"7700 Conowingo Ave Jessup MD 20794",
    "addr:postcode":"7700;20794",
    "addr:street":"Conowingo Ave",
    "iso:country":"US",
    "sg:address":"7700 Conowingo Ave",
    "sg:city":"Jessup",
    "sg:classifiers":[
        {
            "category":"Professional",
            "subcategory":"Employment Agencies",
            "type":"Services"
        }
    ],
    "sg:phone":"+1 443 755 0050",
    "sg:postcode":"20794",
    "sg:province":"MD",
    "sg:tags":[
        "opportunity"
    ],
    "wof:name":"Jp Staffing Inc",
    "wof:placetype":"venue"
},
  "geometry": {"coordinates":[-76.784189,39.165527],"type":"Point"}
}