{
  "type": "Feature",
  "properties": {
    "addr:full":"2201 Eastern Blvd Middle River MD 21220",
    "addr:housenumber":"2201",
    "addr:postcode":"21220",
    "addr:street":"Eastern Blvd",
    "iso:country":"US",
    "sg:address":"2201 Eastern Blvd",
    "sg:city":"Middle River",
    "sg:classifiers":[
        {
            "category":"Health Services",
            "subcategory":"Chiropractor",
            "type":"Services"
        }
    ],
    "sg:phone":"+1 410 686 1117",
    "sg:postcode":"21220",
    "sg:province":"MD",
    "wof:name":"Eastern Chiropractic",
    "wof:placetype":"venue"
},
  "geometry": {"coordinates":[-76.439796,39.3297],"type":"Point"}
}