{
  "type": "Feature",
  "properties": {
    "addr:full":"312 Ewingtown Rd Church Hill MD 21623",
    "addr:housenumber":"312",
    "addr:postcode":"21623",
    "addr:street":"Ewingtown Rd",
    "iso:country":"US",
    "sg:address":"312 Ewingtown Rd",
    "sg:city":"Church Hill",
    "sg:classifiers":[
        {
            "category":"Building & Trades",
            "subcategory":"Construction",
            "type":"Services"
        }
    ],
    "sg:phone":"+1 410 556 6645",
    "sg:postcode":"21623",
    "sg:province":"MD",
    "sg:tags":[
        "carpentry",
        "contractor"
    ],
    "wof:name":"Carter A Brittingham",
    "wof:placetype":"venue"
},
  "geometry": {"coordinates":[-75.98452399999999,39.174358],"type":"Point"}
}