{
  "type": "Feature",
  "properties": {
    "addr:full":"3431 Laurel Fort Meade Rd Laurel MD 20707",
    "addr:housenumber":"3431",
    "addr:postcode":"20707",
    "addr:street":"Laurel Fort Meade Rd",
    "iso:country":"US",
    "sg:address":"3431 Laurel Fort Meade Rd",
    "sg:city":"Laurel",
    "sg:classifiers":[
        {
            "category":"Retail",
            "subcategory":"Laundry & Dry Cleaning",
            "type":"Services"
        }
    ],
    "sg:phone":"+1 301 498 7200",
    "sg:postcode":"20707",
    "sg:province":"MD",
    "wof:name":"Shoppers Cleaners",
    "wof:placetype":"venue"
},
  "geometry": {"coordinates":[-76.869202,39.098301],"type":"Point"}
}