{
  "type": "Feature",
  "properties": {
    "iso:country":"US",
    "sg:address":"6910 Laurel Bowie Rd",
    "sg:city":"Bowie",
    "sg:classifiers":[
        {
            "category":"Food & Beverages",
            "subcategory":"Liquor & Beverages",
            "type":"Retail Goods"
        }
    ],
    "sg:phone":"+1 301 262 0727",
    "sg:postcode":"20715",
    "sg:province":"MD",
    "wof:name":"Bowie Liquors Inc",
    "wof:placetype":"venue"
},
  "geometry": {"coordinates":[-76.757502,38.98528],"type":"Point"}
}