{
  "type": "Feature",
  "properties": {
    "iso:country":"US",
    "sg:address":"112 S Main St",
    "sg:city":"Bel Air",
    "sg:classifiers":[
        {
            "category":"Professional",
            "subcategory":"Business Services",
            "type":"Services"
        }
    ],
    "sg:phone":"+1 410 790 8121",
    "sg:postcode":"21014",
    "sg:province":"MD",
    "wof:name":"Datascan Corp",
    "wof:placetype":"venue"
},
  "geometry": {"coordinates":[-76.347677,39.534846],"type":"Point"}
}