{
  "type": "Feature",
  "properties": {
    "iso:country":"US",
    "sg:address":"701 Hammonds Ln",
    "sg:city":"Brooklyn",
    "sg:classifiers":[
        {
            "category":"Social Services",
            "subcategory":"Child Care",
            "type":"Services"
        }
    ],
    "sg:phone":"+1 410 789 4102",
    "sg:postcode":"21225",
    "sg:province":"MD",
    "sg:tags":[
        "day"
    ],
    "wof:name":"Developmental Daycare Services",
    "wof:placetype":"venue"
},
  "geometry": {"coordinates":[-76.62979900000001,39.211498],"type":"Point"}
}