{
  "type": "Feature",
  "properties": {
    "addr:full":"10420 Little Patuxent Pkwy Columbia MD 21044",
    "addr:housenumber":"10420",
    "addr:postcode":"21044",
    "addr:street":"Little Patuxent Pkwy",
    "iso:country":"US",
    "sg:address":"10420 Little Patuxent Pkwy",
    "sg:city":"Columbia",
    "sg:classifiers":[
        {
            "category":"Organizations",
            "subcategory":"Non-profit Organization",
            "type":"Services"
        }
    ],
    "sg:phone":"+1 410 992 1880",
    "sg:postcode":"21044",
    "sg:province":"MD",
    "wof:name":"Maryland Dc Collaborative",
    "wof:placetype":"venue"
},
  "geometry": {"coordinates":[-76.858608,39.211823],"type":"Point"}
}