{
  "type": "Feature",
  "properties": {
    "iso:country":"US",
    "sg:address":"5256 Marlboro Pike",
    "sg:city":"Capitol Heights",
    "sg:classifiers":[
        {
            "category":"Food & Beverages",
            "subcategory":"Liquor & Beverages",
            "type":"Retail Goods"
        }
    ],
    "sg:phone":"+1 301 735 1941",
    "sg:postcode":"20743",
    "sg:province":"MD",
    "sg:tags":[
        "beer",
        "spirit",
        "wine"
    ],
    "wof:name":"Oak Crest Liquors",
    "wof:placetype":"venue"
},
  "geometry": {"coordinates":[-76.91680100000001,38.866402],"type":"Point"}
}