{
  "type": "Feature",
  "properties": {
    "iso:country":"US",
    "sg:address":"25703 Old Mill Ln",
    "sg:city":"Greensboro",
    "sg:classifiers":[
        {
            "category":"Freight",
            "type":"Transportation"
        }
    ],
    "sg:phone":"+1 410 482 7306",
    "sg:postcode":"21639",
    "sg:province":"MD",
    "sg:tags":[
        "operator",
        "local",
        "trucking"
    ],
    "wof:name":"Cordreys Custom Hauling LLC",
    "wof:placetype":"venue"
},
  "geometry": {"coordinates":[-75.809934,38.940366],"type":"Point"}
}