{
  "type": "Feature",
  "properties": {
    "iso:country":"US",
    "sg:address":"1009 W Patrick St",
    "sg:city":"Frederick",
    "sg:classifiers":[
        {
            "category":"Banks & Credit Unions",
            "subcategory":"Bank",
            "type":"Services"
        }
    ],
    "sg:phone":"+1 301 662 6670",
    "sg:postcode":"21702",
    "sg:province":"MD",
    "sg:website":"www.chevychasebank.com",
    "wof:name":"Chevy Chase Bank",
    "wof:placetype":"venue"
},
  "geometry": {"coordinates":[-77.441593,39.416968],"type":"Point"}
}