{
  "type": "Feature",
  "properties": {
    "iso:country":"US",
    "sg:address":"3 Old Club Ct",
    "sg:city":"Rockville",
    "sg:classifiers":[
        {
            "category":"Professional",
            "subcategory":"Management & Consulting",
            "type":"Services"
        }
    ],
    "sg:phone":"+1 301 468 1327",
    "sg:postcode":"20852",
    "sg:province":"MD",
    "sg:tags":[
        "consultant",
        "medical",
        "doctor"
    ],
    "wof:name":"Frommer Peter L MD",
    "wof:placetype":"venue"
},
  "geometry": {"coordinates":[-77.1446,39.0415],"type":"Point"}
}