{
  "type": "Feature",
  "properties": {
    "iso:country":"US",
    "sg:address":"13120 Brushwood Way",
    "sg:city":"Potomac",
    "sg:classifiers":[
        {
            "category":"Health Services",
            "subcategory":"Health Practitioner",
            "type":"Services"
        }
    ],
    "sg:phone":"+1 301 258 2717",
    "sg:postcode":"20854",
    "sg:province":"MD",
    "wof:name":"Dr Daniel York",
    "wof:placetype":"venue"
},
  "geometry": {"coordinates":[-77.27670000000001,39.069188],"type":"Point"}
}