{
  "type": "Feature",
  "properties": {
    "iso:country":"US",
    "sg:address":"127 Bowie Rd",
    "sg:city":"Laurel",
    "sg:classifiers":[
        {
            "category":"Restaurant",
            "type":"Food & Drink"
        }
    ],
    "sg:menulink":"http://www.allmenus.com/md/laurel/72154-pizza-bolis/menu/",
    "sg:phone":"+1 301 483 0900",
    "sg:postcode":"20707",
    "sg:province":"MD",
    "sg:tags":[
        "wrap",
        "american",
        "sandwich",
        "wing",
        "pizza"
    ],
    "wof:name":"Pizza Boli's",
    "wof:placetype":"venue"
},
  "geometry": {"coordinates":[-76.84779,39.095501],"type":"Point"}
}