{
  "type": "Feature",
  "properties": {
    "addr:full":"2 Hedrick Ct Parkton MD 21120",
    "addr:housenumber":"2",
    "addr:postcode":"21120",
    "addr:street":"Hedrick Ct",
    "iso:country":"US",
    "sg:address":"2 Hedrick Ct",
    "sg:city":"Parkton",
    "sg:classifiers":[
        {
            "category":"Shopping",
            "subcategory":"Crafts & Fabrics",
            "type":"Retail Goods"
        }
    ],
    "sg:phone":"+1 410 343 2135",
    "sg:postcode":"21120",
    "sg:province":"MD",
    "sg:tags":[
        "adhesive",
        "glue"
    ],
    "wof:name":"Kirby Adhesives",
    "wof:placetype":"venue"
},
  "geometry": {"coordinates":[-76.700577,39.655716],"type":"Point"}
}