{
  "type": "Feature",
  "properties": {
    "addr:full":"8401 Muirkirk Rd G101 Laurel MD 20708",
    "addr:housenumber":"8401",
    "addr:postcode":"20708",
    "addr:street":"Muirkirk Rd",
    "iso:country":"US",
    "sg:address":"8401 Muirkirk Rd G101",
    "sg:city":"Laurel",
    "sg:classifiers":[
        {
            "category":"Professional",
            "subcategory":"Business Services",
            "type":"Services"
        }
    ],
    "sg:phone":"+1 301 210 4760",
    "sg:postcode":"20708",
    "sg:province":"MD",
    "sg:tags":[
        "medical",
        "administration"
    ],
    "wof:name":"Office Of Research",
    "wof:placetype":"venue"
},
  "geometry": {"coordinates":[-76.859836,39.05568],"type":"Point"}
}