{
  "type": "Feature",
  "properties": {
    "iso:country":"US",
    "sg:address":"14735 Main St",
    "sg:city":"Upper Marlboro",
    "sg:classifiers":[
        {
            "category":"Government",
            "subcategory":"Office",
            "type":"Public Place"
        }
    ],
    "sg:phone":"+1 301 952 3250",
    "sg:postcode":"20772",
    "sg:province":"MD",
    "wof:name":"Prince George Register-Wills",
    "wof:placetype":"venue"
},
  "geometry": {"coordinates":[-76.751152,38.816391],"type":"Point"}
}