{
  "type": "Feature",
  "properties": {
    "iso:country":"US",
    "sg:address":"2819 Odonnell St",
    "sg:city":"Baltimore",
    "sg:classifiers":[
        {
            "category":"Professional",
            "subcategory":"Management & Consulting",
            "type":"Services"
        },
        {
            "category":"Deli",
            "type":"Food & Drink"
        }
    ],
    "sg:menulink":"http://www.allmenus.com/md/baltimore/245521-rosina-gourmet/menu/",
    "sg:phone":"+1 410 675 9300",
    "sg:postcode":"21224",
    "sg:province":"MD",
    "sg:tags":[
        "deli",
        "american"
    ],
    "wof:name":"Rosina Gourmet",
    "wof:placetype":"venue"
},
  "geometry": {"coordinates":[-76.576188,39.279835],"type":"Point"}
}