{
  "type": "Feature",
  "properties": {
    "iso:country":"US",
    "sg:address":"14223 Seneca Rd",
    "sg:city":"Germantown",
    "sg:classifiers":[
        {
            "category":"Wholesale",
            "subcategory":"Electrical",
            "type":"Manufacturing & Wholesale Goods"
        },
        {
            "category":"Shopping",
            "subcategory":"Computers & Home Electronics",
            "type":"Retail Goods"
        }
    ],
    "sg:phone":"+1 240 912 4367",
    "sg:postcode":"20874",
    "sg:province":"MD",
    "sg:tags":[
        "equipment",
        "consumer",
        "electric",
        "supply"
    ],
    "wof:name":"Galiroe Wholesale Electronics Inc.",
    "wof:placetype":"venue"
},
  "geometry": {"coordinates":[-77.29431599999999,39.100237],"type":"Point"}
}