{
  "type": "Feature",
  "properties": {
    "iso:country":"US",
    "sg:address":"17904 Georgia Ave Ste 215",
    "sg:city":"Olney",
    "sg:classifiers":[
        {
            "category":"Professional",
            "subcategory":"Management & Consulting",
            "type":"Services"
        }
    ],
    "sg:phone":"+1 301 570 2111",
    "sg:postcode":"20832",
    "sg:province":"MD",
    "sg:tags":[
        "marketing",
        "consultant"
    ],
    "wof:name":"Association For Childhood Ed",
    "wof:placetype":"venue"
},
  "geometry": {"coordinates":[-77.06687599999999,39.150315],"type":"Point"}
}