{
  "type": "Feature",
  "properties": {
    "iso:country":"US",
    "sg:address":"3001 Sollers Point Rd",
    "sg:city":"Dundalk",
    "sg:classifiers":[
        {
            "category":"Health Services",
            "subcategory":"Dentist",
            "type":"Services"
        }
    ],
    "sg:phone":"+1 410 284 1414",
    "sg:postcode":"21222",
    "sg:province":"MD",
    "wof:name":"Cylus Grant F DDS PA",
    "wof:placetype":"venue"
},
  "geometry": {"coordinates":[-76.512604,39.257099],"type":"Point"}
}