{
  "type": "Feature",
  "properties": {
    "iso:country":"US",
    "sg:address":"127 N West St",
    "sg:city":"Easton",
    "sg:classifiers":[
        {
            "category":"Real Estate",
            "subcategory":"Architect",
            "type":"Services"
        }
    ],
    "sg:phone":"+1 410 822 3130",
    "sg:postcode":"21601",
    "sg:province":"MD",
    "wof:name":"Christine M Dayton Architect",
    "wof:placetype":"venue"
},
  "geometry": {"coordinates":[-76.077466,38.773014],"type":"Point"}
}