{
  "type": "Feature",
  "properties": {
    "iso:country":"US",
    "sg:address":"30075 Bow Ct",
    "sg:city":"Mechanicsville",
    "sg:classifiers":[
        {
            "category":"Professional",
            "subcategory":"Management & Consulting",
            "type":"Services"
        }
    ],
    "sg:phone":"+1 301 884 8664",
    "sg:postcode":"20659",
    "sg:province":"MD",
    "sg:tags":[
        "project",
        "specialist"
    ],
    "wof:name":"Greg K Spangler",
    "wof:placetype":"venue"
},
  "geometry": {"coordinates":[-76.705753,38.494462],"type":"Point"}
}