{
  "type": "Feature",
  "properties": {
    "iso:country":"US",
    "sg:address":"3805 S Hanover St",
    "sg:city":"Brooklyn",
    "sg:classifiers":[
        {
            "category":"Professional",
            "subcategory":"Computer Services",
            "type":"Services"
        }
    ],
    "sg:phone":"+1 410 355 4729",
    "sg:postcode":"21225",
    "sg:province":"MD",
    "sg:tags":[
        "home",
        "consulting",
        "page",
        "dev",
        "internet"
    ],
    "wof:name":"Web Visions Design",
    "wof:placetype":"venue"
},
  "geometry": {"coordinates":[-76.610704,39.236108],"type":"Point"}
}