{
  "type": "Feature",
  "properties": {
    "addr:full":"7 Frederick Rd Thurmont MD 21788",
    "addr:housenumber":"7",
    "addr:postcode":"21788",
    "addr:street":"Frederick Rd",
    "iso:country":"US",
    "sg:address":"7 Frederick Rd",
    "sg:city":"Thurmont",
    "sg:classifiers":[
        {
            "category":"Building & Trades",
            "subcategory":"Plumbing",
            "type":"Services"
        },
        {
            "category":"Building & Trades",
            "subcategory":"Construction",
            "type":"Services"
        }
    ],
    "sg:phone":"+1 301 271 0600",
    "sg:postcode":"21788",
    "sg:province":"MD",
    "sg:tags":[
        "plumber",
        "industrial",
        "system",
        "specialty",
        "heating",
        "contractors-commercial",
        "contractor",
        "air conditioning"
    ],
    "wof:name":"All State Plumbing Heating & Cooling",
    "wof:placetype":"venue"
},
  "geometry": {"coordinates":[-77.41215099999999,39.62155],"type":"Point"}
}