{
  "type": "Feature",
  "properties": {
    "iso:country":"US",
    "sg:address":"17422 Hoskinson Rd",
    "sg:city":"Poolesville",
    "sg:classifiers":[
        {
            "category":"Professional",
            "subcategory":"Engineering",
            "type":"Services"
        }
    ],
    "sg:phone":"+1 301 707 6481",
    "sg:postcode":"20837",
    "sg:province":"MD",
    "sg:tags":[
        "industrial",
        "engineer"
    ],
    "wof:name":"William L. Beabout",
    "wof:placetype":"venue"
},
  "geometry": {"coordinates":[-77.41256,39.14059],"type":"Point"}
}