{
  "type": "Feature",
  "properties": {
    "iso:country":"US",
    "sg:address":"6492 Landover Rd Ste C",
    "sg:city":"Cheverly",
    "sg:classifiers":[
        {
            "category":"Health Services",
            "subcategory":"Doctor",
            "type":"Services"
        }
    ],
    "sg:phone":"+1 301 322 1400",
    "sg:postcode":"20785",
    "sg:province":"MD",
    "wof:name":"Anderson Francyne O MD",
    "wof:placetype":"venue"
},
  "geometry": {"coordinates":[-76.903999,38.9328],"type":"Point"}
}