{
  "type": "Feature",
  "properties": {
    "iso:country":"US",
    "sg:address":"7908 Lynbrook Dr",
    "sg:city":"Bethesda",
    "sg:classifiers":[
        {
            "category":"Professional",
            "subcategory":"Management & Consulting",
            "type":"Services"
        },
        {
            "category":"Professional",
            "subcategory":"Advertising",
            "type":"Services"
        }
    ],
    "sg:phone":"+1 301 656 1152",
    "sg:postcode":"20814",
    "sg:province":"MD",
    "sg:tags":[
        "marketing",
        "program",
        "consultant"
    ],
    "wof:name":"Lucash Marketing Group",
    "wof:placetype":"venue"
},
  "geometry": {"coordinates":[-77.086319,38.989521],"type":"Point"}
}