{
  "type": "Feature",
  "properties": {
    "addr:full":"13505 Steeplechase Dr Bowie MD 20715",
    "addr:housenumber":"13505",
    "addr:postcode":"20715",
    "addr:street":"Steeplechase Dr",
    "iso:country":"US",
    "sg:address":"13505 Steeplechase Dr",
    "sg:city":"Bowie",
    "sg:classifiers":[
        {
            "category":"Professional",
            "subcategory":"Business Services",
            "type":"Services"
        }
    ],
    "sg:phone":"+1 301 262 8571",
    "sg:postcode":"20715",
    "sg:province":"MD",
    "wof:name":"Direct Communications Inc",
    "wof:placetype":"venue"
},
  "geometry": {"coordinates":[-76.775893,39.002321],"type":"Point"}
}