{
  "type": "Feature",
  "properties": {
    "iso:country":"US",
    "sg:address":"23278 Three Notch Rd",
    "sg:city":"California",
    "sg:classifiers":[
        {
            "category":"Health Services",
            "subcategory":"Dentist",
            "type":"Services"
        }
    ],
    "sg:phone":"+1 301 737 7960",
    "sg:postcode":"20619",
    "sg:province":"MD",
    "sg:tags":[
        "cosmetic"
    ],
    "sg:website":"www.patuxentdental.com",
    "wof:name":"Amit Khanna, DMD",
    "wof:placetype":"venue"
},
  "geometry": {"coordinates":[-76.52651299999999,38.306642],"type":"Point"}
}