{
  "type": "Feature",
  "properties": {
    "iso:country":"US",
    "sg:address":"11110 Medical Campus Rd",
    "sg:city":"Hagerstown",
    "sg:classifiers":[
        {
            "category":"Health Services",
            "subcategory":"Health Practitioner",
            "type":"Services"
        }
    ],
    "sg:phone":"+1 301 714 4390",
    "sg:postcode":"21742",
    "sg:province":"MD",
    "sg:tags":[
        "audiologists"
    ],
    "wof:name":"Hearing Care Ctr",
    "wof:placetype":"venue"
},
  "geometry": {"coordinates":[-77.68052,39.622415],"type":"Point"}
}