{
  "type": "Feature",
  "properties": {
    "addr:full":"13251 Old Frederick Rd Sykesville MD 21784",
    "addr:housenumber":"13251",
    "addr:postcode":"21784",
    "addr:street":"Old Frederick Rd",
    "iso:country":"US",
    "sg:address":"13251 Old Frederick Rd",
    "sg:city":"Sykesville",
    "sg:classifiers":[
        {
            "category":"Shopping",
            "subcategory":"Gifts & Souvenirs",
            "type":"Retail Goods"
        }
    ],
    "sg:phone":"+1 410 489 9330",
    "sg:postcode":"21784",
    "sg:province":"MD",
    "sg:tags":[
        "collectible"
    ],
    "sg:website":"www.jmracingcollectibles.com",
    "wof:name":"J & M Racing Collectables",
    "wof:placetype":"venue"
},
  "geometry": {"coordinates":[-76.967676,39.324434],"type":"Point"}
}