{
  "type": "Feature",
  "properties": {
    "iso:country":"US",
    "sg:address":"6820 Mackall Rd",
    "sg:city":"Saint Leonard",
    "sg:classifiers":[
        {
            "category":"Organizations",
            "subcategory":"Community Association",
            "type":"Services"
        }
    ],
    "sg:phone":"+1 410 586 1488",
    "sg:postcode":"20685",
    "sg:province":"MD",
    "wof:name":"Optimist International",
    "wof:placetype":"venue"
},
  "geometry": {"coordinates":[-76.516993,38.442693],"type":"Point"}
}