{
  "type": "Feature",
  "properties": {
    "addr:full":"3307 Huntley Square Dr Temple Hills MD 20748",
    "addr:housenumber":"3307",
    "addr:postcode":"20748",
    "addr:street":"Huntley Square Dr",
    "iso:country":"US",
    "sg:address":"3307 Huntley Square Dr",
    "sg:city":"Temple Hills",
    "sg:classifiers":[
        {
            "category":"Professional",
            "subcategory":"Business Services",
            "type":"Services"
        }
    ],
    "sg:phone":"+1 301 630 0162",
    "sg:postcode":"20748",
    "sg:province":"MD",
    "wof:name":"Lane Bellefonte Partnership",
    "wof:placetype":"venue"
},
  "geometry": {"coordinates":[-76.95233,38.803579],"type":"Point"}
}