{
  "type": "Feature",
  "properties": {
    "iso:country":"US",
    "sg:address":"13804 Georgia Ave",
    "sg:city":"Silver Spring",
    "sg:classifiers":[
        {
            "category":"Personal",
            "subcategory":"Beauty Salon",
            "type":"Services"
        }
    ],
    "sg:phone":"+1 301 603 8800",
    "sg:postcode":"20906",
    "sg:province":"MD",
    "sg:tags":[
        "manicuring"
    ],
    "wof:name":"Fantasy Nail & Spa",
    "wof:placetype":"venue"
},
  "geometry": {"coordinates":[-77.077648,39.08327],"type":"Point"}
}