{
  "type": "Feature",
  "properties": {
    "iso:country":"US",
    "sg:address":"28 Allegheny Ave",
    "sg:city":"Baltimore",
    "sg:classifiers":[
        {
            "category":"Professional",
            "subcategory":"Accounting & Tax Preparation",
            "type":"Services"
        }
    ],
    "sg:phone":"+1 410 324 4067",
    "sg:postcode":"21204",
    "sg:province":"MD",
    "sg:tags":[
        "accountant"
    ],
    "wof:name":"Stoy Malone & Co",
    "wof:placetype":"venue"
},
  "geometry": {"coordinates":[-76.603043,39.401747],"type":"Point"}
}