{
  "type": "Feature",
  "properties": {
    "iso:country":"US",
    "sg:address":"107 Front St",
    "sg:city":"Pocomoke City",
    "sg:classifiers":[
        {
            "category":"Personal",
            "subcategory":"Beauty Salon",
            "type":"Services"
        }
    ],
    "sg:phone":"+1 410 957 1221",
    "sg:postcode":"21851",
    "sg:province":"MD",
    "sg:tags":[
        "shop"
    ],
    "wof:name":"Style Center Beauty Salon",
    "wof:placetype":"venue"
},
  "geometry": {"coordinates":[-75.569076,38.076659],"type":"Point"}
}