{
  "type": "Feature",
  "properties": {
    "addr:full":"8808 63rd Ave Berwyn Heights MD 20740",
    "addr:housenumber":"8808",
    "addr:postcode":"20740",
    "addr:street":"63Rd Ave",
    "iso:country":"US",
    "sg:address":"8808 63rd Ave",
    "sg:city":"Berwyn Heights",
    "sg:classifiers":[
        {
            "category":"Professional",
            "type":"Services"
        }
    ],
    "sg:phone":"+1 301 345 8055",
    "sg:postcode":"20740",
    "sg:province":"MD",
    "sg:tags":[
        "establishment"
    ],
    "wof:name":"Iconic Mind",
    "wof:placetype":"venue"
},
  "geometry": {"coordinates":[-76.90457600000001,38.994457],"type":"Point"}
}