{
  "type": "Feature",
  "properties": {
    "addr:full":"22 W Jefferson St Rockville MD 20850",
    "addr:housenumber":"22",
    "addr:postcode":"20850",
    "addr:street":"W Jefferson St",
    "iso:country":"US",
    "sg:address":"22 W Jefferson St",
    "sg:city":"Rockville",
    "sg:classifiers":[
        {
            "category":"Professional",
            "subcategory":"Lawyer & Legal Services",
            "type":"Services"
        }
    ],
    "sg:phone":"+1 301 838 1995",
    "sg:postcode":"20850",
    "sg:province":"MD",
    "sg:tags":[
        "attorney"
    ],
    "sg:website":"www.hadleylaw.com",
    "wof:name":"Donald H Hadley",
    "wof:placetype":"venue"
},
  "geometry": {"coordinates":[-77.154465,39.083056],"type":"Point"}
}