{
  "type": "Feature",
  "properties": {
    "addr:full":"2445 Lyttonsville Rd Silver Spring MD 20910",
    "addr:housenumber":"2445",
    "addr:postcode":"20910",
    "addr:street":"Lyttonsville Rd",
    "iso:country":"US",
    "sg:address":"2445 Lyttonsville Rd",
    "sg:city":"Silver Spring",
    "sg:classifiers":[
        {
            "category":"Real Estate",
            "subcategory":"Real Estate Agent",
            "type":"Services"
        }
    ],
    "sg:phone":"+1 301 588 8144",
    "sg:postcode":"20910",
    "sg:province":"MD",
    "sg:tags":[
        "management"
    ],
    "wof:name":"Southern Management Corp",
    "wof:placetype":"venue"
},
  "geometry": {"coordinates":[-77.054219,38.996126],"type":"Point"}
}