{
  "type": "Feature",
  "properties": {
    "iso:country":"US",
    "sg:address":"14546 Carleton Ln",
    "sg:city":"Eden",
    "sg:classifiers":[
        {
            "category":"Manufacturing",
            "subcategory":"Soap",
            "type":"Manufacturing & Wholesale Goods"
        }
    ],
    "sg:phone":"+1 410 860 1442",
    "sg:postcode":"21822",
    "sg:province":"MD",
    "sg:tags":[
        "detergent"
    ],
    "wof:name":"Scents Of Eden",
    "wof:placetype":"venue"
},
  "geometry": {"coordinates":[-75.6596,38.280879],"type":"Point"}
}