{
  "type": "Feature",
  "properties": {
    "iso:country":"US",
    "sg:address":"7003 Carroll Ave",
    "sg:city":"Takoma Park",
    "sg:classifiers":[
        {
            "category":"Arena",
            "subcategory":"Sports Club",
            "type":"Entertainment"
        }
    ],
    "sg:phone":"+1 301 270 9588",
    "sg:postcode":"20912",
    "sg:province":"MD",
    "sg:tags":[
        "martial art"
    ],
    "wof:name":"Uechi Karate Association",
    "wof:placetype":"venue"
},
  "geometry": {"coordinates":[-77.012023,38.974563],"type":"Point"}
}