{
  "type": "Feature",
  "properties": {
    "addr:full":"7147 Smooth Path Columbia MD 21045",
    "addr:housenumber":"7147",
    "addr:postcode":"21045",
    "addr:street":"Smooth Path",
    "iso:country":"US",
    "sg:address":"7147 Smooth Path",
    "sg:city":"Columbia",
    "sg:classifiers":[
        {
            "category":"Professional",
            "type":"Services"
        }
    ],
    "sg:phone":"+1 410 381 3941",
    "sg:postcode":"21045",
    "sg:province":"MD",
    "sg:tags":[
        "establishment"
    ],
    "wof:name":"R G & L Specialty Distrubitors",
    "wof:placetype":"venue"
},
  "geometry": {"coordinates":[-76.837936,39.18755],"type":"Point"}
}