{
  "type": "Feature",
  "properties": {
    "iso:country":"US",
    "sg:address":"2800 Sisson Street",
    "sg:city":"Baltimore",
    "sg:classifiers":[
        {
            "category":"Education",
            "subcategory":"Special Training",
            "type":"Public Place"
        },
        {
            "category":"Organizations",
            "subcategory":"Non-profit Organization",
            "type":"Services"
        }
    ],
    "sg:postcode":"21211",
    "sg:province":"MD",
    "sg:tags":[
        "service/non-profit",
        "community",
        "adult"
    ],
    "sg:website":"www.baltimorebiomass.com",
    "wof:name":"Baltimore Biomass",
    "wof:placetype":"venue"
},
  "geometry": {"coordinates":[-76.62554,39.319508],"type":"Point"}
}