{
  "type": "Feature",
  "properties": {
    "iso:country":"US",
    "sg:address":"296 Marsh Hill Rd",
    "sg:city":"Mc Henry",
    "sg:classifiers":[
        {
            "category":"Sports & Exercise",
            "subcategory":"Gym",
            "type":"Entertainment"
        }
    ],
    "sg:phone":"+1 301 387 7000",
    "sg:postcode":"21541",
    "sg:province":"MD",
    "sg:tags":[
        "spa",
        "health"
    ],
    "wof:name":"Sewickley Spa Inc",
    "wof:placetype":"venue"
},
  "geometry": {"coordinates":[-79.35913,39.551553],"type":"Point"}
}