{
  "type": "Feature",
  "properties": {
    "iso:country":"US",
    "sg:address":"10203 Brightfield Ln",
    "sg:city":"Upper Marlboro",
    "sg:classifiers":[
        {
            "category":"Health Services",
            "subcategory":"Nursing And Care Facility",
            "type":"Services"
        }
    ],
    "sg:phone":"+1 301 937 3227",
    "sg:postcode":"20772",
    "sg:province":"MD",
    "sg:tags":[
        "home",
        "rest"
    ],
    "wof:name":"Bethel Christian Home",
    "wof:placetype":"venue"
},
  "geometry": {"coordinates":[-76.83005900000001,38.786701],"type":"Point"}
}