{
  "type": "Feature",
  "properties": {
    "addr:full":"120 Walkers Village Way Walkersville MD 21793",
    "addr:housenumber":"120",
    "addr:postcode":"21793",
    "addr:street":"Walkers Village Way",
    "iso:country":"US",
    "sg:address":"120 Walkers Village Way",
    "sg:city":"Walkersville",
    "sg:classifiers":[
        {
            "category":"Restaurant",
            "type":"Food & Drink"
        }
    ],
    "sg:phone":"+1 301 845 2425",
    "sg:postcode":"21793",
    "sg:province":"MD",
    "wof:name":"Mom's Pizza",
    "wof:placetype":"venue"
},
  "geometry": {"coordinates":[-77.34045500000001,39.483296],"type":"Point"}
}