{
  "type": "Feature",
  "properties": {
    "addr:full":"9505 Westwood Dr Ellicott City MD 21042",
    "addr:housenumber":"9505",
    "addr:postcode":"21042",
    "addr:street":"Westwood Dr",
    "iso:country":"US",
    "sg:address":"9505 Westwood Dr",
    "sg:city":"Ellicott City",
    "sg:classifiers":[
        {
            "category":"Manufacturing",
            "subcategory":"Glass & Minerals",
            "type":"Manufacturing & Wholesale Goods"
        }
    ],
    "sg:phone":"+1 410 750 1767",
    "sg:postcode":"21042",
    "sg:province":"MD",
    "sg:tags":[
        "fabricator",
        "fiber"
    ],
    "wof:name":"Data Design Svc Inc",
    "wof:placetype":"venue"
},
  "geometry": {"coordinates":[-76.842358,39.276601],"type":"Point"}
}