{
  "type": "Feature",
  "properties": {
    "addr:full":"4608 Carroll Manor Rd Baldwin MD 21013",
    "addr:housenumber":"4608",
    "addr:postcode":"21013",
    "addr:street":"Carroll Manor Rd",
    "iso:country":"US",
    "sg:address":"4608 Carroll Manor Rd",
    "sg:city":"Baldwin",
    "sg:classifiers":[
        {
            "category":"Professional",
            "subcategory":"Lawyer & Legal Services",
            "type":"Services"
        }
    ],
    "sg:phone":"+1 410 592 9700",
    "sg:postcode":"21013",
    "sg:province":"MD",
    "sg:tags":[
        "attorney"
    ],
    "wof:name":"Andrew Naden & Assoc",
    "wof:placetype":"venue"
},
  "geometry": {"coordinates":[-76.51740700000001,39.500271],"type":"Point"}
}