{
  "type": "Feature",
  "properties": {
    "iso:country":"US",
    "sg:address":"12402 Waldorf Business Sq",
    "sg:city":"Waldorf",
    "sg:classifiers":[
        {
            "category":"Insurance",
            "subcategory":"Insurance Agent",
            "type":"Services"
        }
    ],
    "sg:phone":"+1 301 705 5900",
    "sg:postcode":"20601",
    "sg:province":"MD",
    "sg:tags":[
        "adjuster"
    ],
    "wof:name":"J F Cattell Assoc Inc",
    "wof:placetype":"venue"
},
  "geometry": {"coordinates":[-76.8993,38.6394],"type":"Point"}
}