{
  "type": "Feature",
  "properties": {
    "addr:full":"4805 Edgemoor Ln Bethesda MD 20814",
    "addr:housenumber":"4805",
    "addr:postcode":"20814",
    "addr:street":"Edgemoor Ln",
    "iso:country":"US",
    "sg:address":"4805 Edgemoor Ln",
    "sg:city":"Bethesda",
    "sg:classifiers":[
        {
            "category":"Health Services",
            "subcategory":"Hospital",
            "type":"Services"
        }
    ],
    "sg:phone":"+1 301 951 1990",
    "sg:postcode":"20814",
    "sg:province":"MD",
    "sg:website":"www.holycrosshealth.org",
    "wof:name":"Holy Cross Hospital",
    "wof:placetype":"venue"
},
  "geometry": {"coordinates":[-77.095698,38.984993],"type":"Point"}
}