{
  "type": "Feature",
  "properties": {
    "iso:country":"US",
    "sg:address":"7110 Belair Rd",
    "sg:city":"Baltimore",
    "sg:classifiers":[
        {
            "category":"Professional",
            "subcategory":"Engineering",
            "type":"Services"
        }
    ],
    "sg:phone":"+1 410 665 9400",
    "sg:postcode":"21206",
    "sg:province":"MD",
    "sg:tags":[
        "engineer"
    ],
    "wof:name":"Jack Dale Assoc",
    "wof:placetype":"venue"
},
  "geometry": {"coordinates":[-76.52524699999999,39.359562],"type":"Point"}
}