{
  "type": "Feature",
  "properties": {
    "addr:full":"1007 Paul Dr Rockville MD 20851",
    "addr:housenumber":"1007",
    "addr:postcode":"20851",
    "addr:street":"Paul Dr",
    "iso:country":"US",
    "sg:address":"1007 Paul Dr",
    "sg:city":"Rockville",
    "sg:classifiers":[
        {
            "category":"Professional",
            "subcategory":"Business Services",
            "type":"Services"
        }
    ],
    "sg:phone":"+1 301 762 0806",
    "sg:postcode":"20851",
    "sg:province":"MD",
    "wof:name":"Chadal and Associates",
    "wof:placetype":"venue"
},
  "geometry": {"coordinates":[-77.133824,39.077272],"type":"Point"}
}