{
  "type": "Feature",
  "properties": {
    "addr:full":"5601 Old Branch Ave Temple Hills MD 20748",
    "addr:housenumber":"5601",
    "addr:postcode":"20748",
    "addr:street":"Old Branch Ave",
    "iso:country":"US",
    "sg:address":"5601 Old Branch Ave",
    "sg:city":"Temple Hills",
    "sg:classifiers":[
        {
            "category":"Social Services",
            "type":"Services"
        }
    ],
    "sg:phone":"+1 301 899 8487",
    "sg:postcode":"20748",
    "sg:province":"MD",
    "sg:tags":[
        "youth",
        "organization",
        "center"
    ],
    "wof:name":"Kairos",
    "wof:placetype":"venue"
},
  "geometry": {"coordinates":[-76.913991,38.811623],"type":"Point"}
}