{
  "type": "Feature",
  "properties": {
    "iso:country":"US",
    "sg:address":"1788 Generals Hwy",
    "sg:city":"Annapolis",
    "sg:classifiers":[
        {
            "category":"Personal",
            "subcategory":"Beauty Salon",
            "type":"Services"
        }
    ],
    "sg:phone":"+1 410 849 2333",
    "sg:postcode":"21401",
    "sg:province":"MD",
    "wof:name":"Lazer Cut",
    "wof:placetype":"venue"
},
  "geometry": {"coordinates":[-76.56375800000001,39.009233],"type":"Point"}
}