{
  "type": "Feature",
  "properties": {
    "addr:full":"10435 York Rd Cockysvl Hnt Vly MD 21030",
    "addr:housenumber":"10435",
    "addr:postcode":"21030",
    "addr:street":"York Rd;Hnt Vly",
    "iso:country":"US",
    "sg:address":"10435 York Rd",
    "sg:city":"Cockysvl Hnt Vly",
    "sg:classifiers":[
        {
            "category":"Shopping",
            "subcategory":"Bicycles & Sporting Goods",
            "type":"Retail Goods"
        }
    ],
    "sg:phone":"+1 410 667 1040",
    "sg:postcode":"21030",
    "sg:province":"MD",
    "sg:website":"www.thebicycleconnection.com",
    "wof:name":"Bicycle Connection",
    "wof:placetype":"venue"
},
  "geometry": {"coordinates":[-76.640332,39.473367],"type":"Point"}
}