{
  "type": "Feature",
  "properties": {
    "iso:country":"US",
    "sg:address":"1717 Reisterstown Rd",
    "sg:city":"Pikesville",
    "sg:classifiers":[
        {
            "category":"Building & Trades",
            "subcategory":"Pest Control",
            "type":"Services"
        }
    ],
    "sg:phone":"+1 410 753 1993",
    "sg:postcode":"21208",
    "sg:province":"MD",
    "wof:name":"Anytime Pest Control Service",
    "wof:placetype":"venue"
},
  "geometry": {"coordinates":[-76.73175000000001,39.38269],"type":"Point"}
}