{
  "type": "Feature",
  "properties": {
    "addr:full":"3404 Powhatan Ave Baltimore MD 21216",
    "addr:housenumber":"3404",
    "addr:postcode":"21216",
    "addr:street":"Powhatan Ave",
    "iso:country":"US",
    "sg:address":"3404 Powhatan Ave",
    "sg:city":"Baltimore",
    "sg:classifiers":[
        {
            "category":"Organizations",
            "subcategory":"Religious Organization",
            "type":"Services"
        }
    ],
    "sg:phone":"+1 410 542 5363",
    "sg:postcode":"21216",
    "sg:province":"MD",
    "sg:tags":[
        "church"
    ],
    "wof:name":"Old Time Way",
    "wof:placetype":"venue"
},
  "geometry": {"coordinates":[-76.676491,39.32137],"type":"Point"}
}