{
  "type": "Feature",
  "properties": {
    "addr:full":"203 Baltimore Pike Bel Air MD 21014",
    "addr:housenumber":"203",
    "addr:postcode":"21014",
    "addr:street":"Baltimore Pike",
    "iso:country":"US",
    "sg:address":"203 Baltimore Pike",
    "sg:city":"Bel Air",
    "sg:classifiers":[
        {
            "category":"Retail",
            "subcategory":"Auto Repair",
            "type":"Services"
        }
    ],
    "sg:phone":"+1 410 638 7081",
    "sg:postcode":"21014",
    "sg:province":"MD",
    "sg:tags":[
        "repairing",
        "shop",
        "general",
        "automotive",
        "automobile"
    ],
    "wof:name":"Hinkle's Automotive Repair",
    "wof:placetype":"venue"
},
  "geometry": {"coordinates":[-76.34888100000001,39.531973],"type":"Point"}
}