{
  "type": "Feature",
  "properties": {
    "addr:full":"7862 Butterfield Dr Elkridge MD 21075",
    "addr:housenumber":"7862",
    "addr:postcode":"21075",
    "addr:street":"Butterfield Dr",
    "iso:country":"US",
    "sg:address":"7862 Butterfield Dr",
    "sg:city":"Elkridge",
    "sg:classifiers":[
        {
            "category":"Building & Trades",
            "subcategory":"Equipment Rental",
            "type":"Services"
        }
    ],
    "sg:phone":"+1 410 796 4469",
    "sg:postcode":"21075",
    "sg:province":"MD",
    "sg:tags":[
        "leasing"
    ],
    "wof:name":"Hertz-United States Fleet Lsng",
    "wof:placetype":"venue"
},
  "geometry": {"coordinates":[-76.783615,39.19357],"type":"Point"}
}