{
  "type": "Feature",
  "properties": {
    "addr:full":"308 N Dulany Ave Fruitland MD 21826",
    "addr:housenumber":"308",
    "addr:postcode":"21826",
    "addr:street":"N Dulany Ave",
    "iso:country":"US",
    "sg:address":"308 N Dulany Ave",
    "sg:city":"Fruitland",
    "sg:classifiers":[
        {
            "category":"Building & Trades",
            "subcategory":"Construction",
            "type":"Services"
        }
    ],
    "sg:phone":"+1 410 742 1600",
    "sg:postcode":"21826",
    "sg:province":"MD",
    "sg:tags":[
        "general",
        "contractor"
    ],
    "wof:name":"Thomas Construction",
    "wof:placetype":"venue"
},
  "geometry": {"coordinates":[-75.613533,38.323101],"type":"Point"}
}