{
  "type": "Feature",
  "properties": {
    "addr:full":"25549 Vista Rd Hollywood MD 20636",
    "addr:housenumber":"25549",
    "addr:postcode":"20636",
    "addr:street":"Vista Rd",
    "iso:country":"US",
    "sg:address":"25549 Vista Rd",
    "sg:city":"Hollywood",
    "sg:classifiers":[
        {
            "category":"Building & Trades",
            "subcategory":"Landscaping Services",
            "type":"Services"
        }
    ],
    "sg:phone":"+1 301 997 0006",
    "sg:postcode":"20636",
    "sg:province":"MD",
    "sg:tags":[
        "tree"
    ],
    "wof:name":"Jeff's Tree Svc",
    "wof:placetype":"venue"
},
  "geometry": {"coordinates":[-76.57178999999999,38.357882],"type":"Point"}
}