{
  "type": "Feature",
  "properties": {
    "addr:full":"11433 Cronridge Dr Owings Mills MD 21117",
    "addr:housenumber":"11433",
    "addr:postcode":"21117",
    "addr:street":"Cronridge Dr",
    "iso:country":"US",
    "sg:address":"11433 Cronridge Dr",
    "sg:city":"Owings Mills",
    "sg:classifiers":[
        {
            "category":"Shopping",
            "type":"Retail Goods"
        }
    ],
    "sg:phone":"+1 410 356 9420",
    "sg:postcode":"21117",
    "sg:province":"MD",
    "sg:tags":[
        "telephone",
        "cellular"
    ],
    "wof:name":"Paramount Marketing Inc",
    "wof:placetype":"venue"
},
  "geometry": {"coordinates":[-76.77621000000001,39.440098],"type":"Point"}
}