{
  "type": "Feature",
  "properties": {
    "addr:full":"1496 Flag Harbor Blvd St Leonard MD 20685",
    "addr:housenumber":"1496",
    "addr:postcode":"20685",
    "addr:street":"Flag Harbor Blvd St",
    "iso:country":"US",
    "sg:address":"1496 Flag Harbor Blvd",
    "sg:city":"St Leonard",
    "sg:classifiers":[
        {
            "category":"Building & Trades",
            "subcategory":"Construction",
            "type":"Services"
        }
    ],
    "sg:phone":"+1 410 586 3885",
    "sg:postcode":"20685",
    "sg:province":"MD",
    "sg:tags":[
        "home",
        "improvement"
    ],
    "wof:name":"Home Concepts",
    "wof:placetype":"venue"
},
  "geometry": {"coordinates":[-76.477862,38.462378],"type":"Point"}
}