{
  "type": "Feature",
  "properties": {
    "addr:full":"5033 Lake Cir Columbia MD 21044",
    "addr:housenumber":"5033",
    "addr:postcode":"21044",
    "addr:street":"Lake Cir",
    "iso:country":"US",
    "sg:address":"5033 Lake Cir",
    "sg:city":"Columbia",
    "sg:classifiers":[
        {
            "category":"Shopping",
            "subcategory":"Computers & Home Electronics",
            "type":"Retail Goods"
        }
    ],
    "sg:phone":"+1 410 964 0052",
    "sg:postcode":"21044",
    "sg:province":"MD",
    "sg:tags":[
        "software"
    ],
    "wof:name":"C & J Computer Consultants Inc",
    "wof:placetype":"venue"
},
  "geometry": {"coordinates":[-76.86706599999999,39.232421],"type":"Point"}
}