{
  "type": "Feature",
  "properties": {
    "iso:country":"US",
    "sg:address":"5302 Talladaga Ct Unit K",
    "sg:city":"Frederick",
    "sg:classifiers":[
        {
            "category":"Professional",
            "subcategory":"Accounting & Tax Preparation",
            "type":"Services"
        }
    ],
    "sg:phone":"+1 301 694 8959",
    "sg:postcode":"21703",
    "sg:province":"MD",
    "sg:tags":[
        "return",
        "preparation-business"
    ],
    "wof:name":"Virtax",
    "wof:placetype":"venue"
},
  "geometry": {"coordinates":[-77.442781,39.382855],"type":"Point"}
}