{
  "type": "Feature",
  "properties": {
    "addr:full":"9779 Good Luck Rd Lanham MD 20706",
    "addr:housenumber":"9779",
    "addr:postcode":"20706",
    "addr:street":"Good Luck Rd",
    "iso:country":"US",
    "sg:address":"9779 Good Luck Rd",
    "sg:city":"Lanham",
    "sg:classifiers":[
        {
            "category":"Professional",
            "subcategory":"Lawyer & Legal Services",
            "type":"Services"
        }
    ],
    "sg:phone":"+1 301 794 6833",
    "sg:postcode":"20706",
    "sg:province":"MD",
    "sg:tags":[
        "attorney"
    ],
    "wof:name":"Kimberly Taylor-Logan",
    "wof:placetype":"venue"
},
  "geometry": {"coordinates":[-76.840935,38.984181],"type":"Point"}
}