{
  "type": "Feature",
  "properties": {
    "addr:full":"11717 Old National Pike New Market MD 21774",
    "addr:housenumber":"11717",
    "addr:postcode":"21774",
    "addr:street":"Old National Pike",
    "iso:country":"US",
    "sg:address":"11717 Old National Pike",
    "sg:city":"New Market",
    "sg:classifiers":[
        {
            "category":"Restaurant",
            "type":"Food & Drink"
        }
    ],
    "sg:menulink":"http://www.allmenus.com/md/new-market/67401-dominos-pizza/menu/",
    "sg:phone":"+1 301 865 0200",
    "sg:postcode":"21774",
    "sg:province":"MD",
    "sg:tags":[
        "american",
        "wing",
        "pizza"
    ],
    "wof:name":"Domino's Pizza",
    "wof:placetype":"venue"
},
  "geometry": {"coordinates":[-77.262804,39.38441],"type":"Point"}
}