{
  "type": "Feature",
  "properties": {
    "addr:full":"510 Nicoll Ave Baltimore MD 21212",
    "addr:housenumber":"510",
    "addr:postcode":"21212",
    "addr:street":"Nicoll Ave",
    "iso:country":"US",
    "sg:address":"510 Nicoll Ave",
    "sg:city":"Baltimore",
    "sg:classifiers":[
        {
            "category":"Building & Trades",
            "subcategory":"Construction",
            "type":"Services"
        }
    ],
    "sg:phone":"+1 410 433 0362",
    "sg:postcode":"21212",
    "sg:province":"MD",
    "sg:tags":[
        "house",
        "nonresidential"
    ],
    "wof:name":"Northwood Construction",
    "wof:placetype":"venue"
},
  "geometry": {"coordinates":[-76.609849,39.365933],"type":"Point"}
}