{
  "type": "Feature",
  "properties": {
    "iso:country":"US",
    "sg:address":"3109 Sharon Rd",
    "sg:city":"Jarrettsville",
    "sg:classifiers":[
        {
            "category":"Manufacturing",
            "subcategory":"Metals",
            "type":"Manufacturing & Wholesale Goods"
        }
    ],
    "sg:phone":"+1 410 836 6993",
    "sg:postcode":"21084",
    "sg:province":"MD",
    "sg:tags":[
        "steel",
        "mill"
    ],
    "wof:name":"Cybees",
    "wof:placetype":"venue"
},
  "geometry": {"coordinates":[-76.41382299999999,39.614105],"type":"Point"}
}