{
  "type": "Feature",
  "properties": {
    "iso:country":"US",
    "sg:address":"11459 Cron Hill Dr",
    "sg:city":"Owings Mills",
    "sg:classifiers":[
        {
            "category":"Wholesale",
            "subcategory":"Groceries",
            "type":"Manufacturing & Wholesale Goods"
        }
    ],
    "sg:phone":"+1 410 356 6008",
    "sg:postcode":"21117",
    "sg:province":"MD",
    "sg:tags":[
        "beverage"
    ],
    "wof:name":"Wine Mates & Co",
    "wof:placetype":"venue"
},
  "geometry": {"coordinates":[-76.772965,39.435755],"type":"Point"}
}