{
  "type": "Feature",
  "properties": {
    "addr:full":"217 E Antietam St Hagerstown MD 21740",
    "addr:housenumber":"217",
    "addr:postcode":"21740",
    "addr:street":"E Antietam St",
    "iso:country":"US",
    "sg:address":"217 E Antietam St",
    "sg:city":"Hagerstown",
    "sg:classifiers":[
        {
            "category":"Organizations",
            "subcategory":"Non-profit Organization",
            "type":"Services"
        }
    ],
    "sg:phone":"+1 301 714 0837",
    "sg:postcode":"21740",
    "sg:province":"MD",
    "sg:tags":[
        "info",
        "addiction",
        "abuse",
        "treatment",
        "drug"
    ],
    "wof:name":"Hagerstown Treatment Ctr",
    "wof:placetype":"venue"
},
  "geometry": {"coordinates":[-77.71729999999999,39.63879],"type":"Point"}
}