{
  "type": "Feature",
  "properties": {
    "iso:country":"US",
    "sg:address":"5500 Nathan Shock Dr",
    "sg:city":"Baltimore",
    "sg:classifiers":[
        {
            "category":"Education",
            "subcategory":"Library",
            "type":"Public Place"
        }
    ],
    "sg:phone":"+1 410 550 1488",
    "sg:postcode":"21224",
    "sg:province":"MD",
    "wof:name":"Addiction Research Ctr Libr",
    "wof:placetype":"venue"
},
  "geometry": {"coordinates":[-76.549314,39.29129],"type":"Point"}
}