{
  "type": "Feature",
  "properties": {
    "iso:country":"US",
    "sg:address":"600 Craigs Corner Rd",
    "sg:city":"Havre De Grace",
    "sg:classifiers":[
        {
            "category":"Real Estate",
            "subcategory":"Architect",
            "type":"Services"
        }
    ],
    "sg:phone":"+1 410 879 6748",
    "sg:postcode":"21078",
    "sg:province":"MD",
    "wof:name":"James T Wollon Jr",
    "wof:placetype":"venue"
},
  "geometry": {"coordinates":[-76.165959,39.596182],"type":"Point"}
}