{
  "type": "Feature",
  "properties": {
    "addr:full":"168 Annapolis St Annapolis MD 21401",
    "addr:housenumber":"168",
    "addr:postcode":"21401",
    "addr:street":"Annapolis St",
    "iso:country":"US",
    "sg:address":"168 Annapolis St",
    "sg:city":"Annapolis",
    "sg:classifiers":[
        {
            "category":"Shopping",
            "subcategory":"Hobbies, Toys, & Games",
            "type":"Retail Goods"
        }
    ],
    "sg:phone":"+1 410 266 8505",
    "sg:postcode":"21401",
    "sg:province":"MD",
    "wof:name":"K-B Toys",
    "wof:placetype":"venue"
},
  "geometry": {"coordinates":[-76.50257499999999,38.990351],"type":"Point"}
}