{
  "type": "Feature",
  "properties": {
    "addr:full":"4910 Moorland Ln Bethesda MD 20814",
    "addr:housenumber":"4910",
    "addr:postcode":"20814",
    "addr:street":"Moorland Ln",
    "iso:country":"US",
    "sg:address":"4910 Moorland Ln",
    "sg:city":"Bethesda",
    "sg:classifiers":[
        {
            "category":"Health Services",
            "subcategory":"Doctor",
            "type":"Services"
        }
    ],
    "sg:phone":"+1 301 907 4575",
    "sg:postcode":"20814",
    "sg:province":"MD",
    "sg:tags":[
        "physician",
        "surgeon"
    ],
    "wof:name":"Morlan & Assoc",
    "wof:placetype":"venue"
},
  "geometry": {"coordinates":[-77.098631,38.98597],"type":"Point"}
}