{
  "type": "Feature",
  "properties": {
    "addr:full":"614 Eastern Shore Dr Salisbury MD 21804",
    "addr:housenumber":"614",
    "addr:postcode":"21804",
    "addr:street":"Eastern Shore Dr",
    "iso:country":"US",
    "sg:address":"614 Eastern Shore Dr",
    "sg:city":"Salisbury",
    "sg:classifiers":[
        {
            "category":"Organizations",
            "subcategory":"Non-profit Organization",
            "type":"Services"
        }
    ],
    "sg:phone":"+1 410 341 0307",
    "sg:postcode":"21804",
    "sg:province":"MD",
    "sg:tags":[
        "disability"
    ],
    "wof:name":"Bay Shore Svc",
    "wof:placetype":"venue"
},
  "geometry": {"coordinates":[-75.596327,38.357288],"type":"Point"}
}