{
  "type": "Feature",
  "properties": {
    "addr:full":"6667 Security Blvd Gwynn Oak MD 21207",
    "addr:housenumber":"6667",
    "addr:postcode":"21207",
    "addr:street":"Security Blvd",
    "iso:country":"US",
    "sg:address":"6667 Security Blvd",
    "sg:city":"Gwynn Oak",
    "sg:classifiers":[
        {
            "category":"Retail",
            "subcategory":"Self-service Laundry",
            "type":"Services"
        }
    ],
    "sg:phone":"+1 410 265 0076",
    "sg:postcode":"21207",
    "sg:province":"MD",
    "wof:name":"Sudsville Laundry",
    "wof:placetype":"venue"
},
  "geometry": {"coordinates":[-76.739233,39.311817],"type":"Point"}
}