{
  "type": "Feature",
  "properties": {
    "addr:full":"57 W Frederick St Walkersville MD 21793",
    "addr:housenumber":"57",
    "addr:postcode":"21793",
    "addr:street":"W Frederick St",
    "iso:country":"US",
    "sg:address":"57 W Frederick St",
    "sg:city":"Walkersville",
    "sg:classifiers":[
        {
            "category":"Education",
            "subcategory":"Library",
            "type":"Public Place"
        }
    ],
    "sg:phone":"+1 301 845 8880",
    "sg:postcode":"21793",
    "sg:province":"MD",
    "sg:website":"www.scpl.org",
    "wof:name":"Walkersville Public Library",
    "wof:placetype":"venue"
},
  "geometry": {"coordinates":[-77.355407,39.478329],"type":"Point"}
}