{
  "type": "Feature",
  "properties": {
    "addr:full":"4 Cypress St Hagerstown MD 21742",
    "addr:housenumber":"4",
    "addr:postcode":"21742",
    "addr:street":"Cypress St",
    "iso:country":"US",
    "sg:address":"4 Cypress St",
    "sg:city":"Hagerstown",
    "sg:classifiers":[
        {
            "category":"Health Services",
            "subcategory":"Doctor",
            "type":"Services"
        }
    ],
    "sg:phone":"+1 301 790 2007",
    "sg:postcode":"21742",
    "sg:province":"MD",
    "sg:tags":[
        "dentist"
    ],
    "wof:name":"Potomac Dental Ctr",
    "wof:placetype":"venue"
},
  "geometry": {"coordinates":[-77.70410200000001,39.656934],"type":"Point"}
}