{
  "type": "Feature",
  "properties": {
    "iso:country":"US",
    "sg:address":"129 E Main St",
    "sg:city":"Westminster",
    "sg:classifiers":[
        {
            "category":"Shopping",
            "type":"Retail Goods"
        }
    ],
    "sg:phone":"+1 410 876 1444",
    "sg:postcode":"21157",
    "sg:province":"MD",
    "sg:tags":[
        "trophy",
        "medal",
        "award"
    ],
    "sg:website":"www.lambawards.com",
    "wof:name":"Lamb Awards & Engraving Co",
    "wof:placetype":"venue"
},
  "geometry": {"coordinates":[-76.992719,39.572138],"type":"Point"}
}