{
  "type": "Feature",
  "properties": {
    "addr:full":"1400 Greenmount Ave Baltimore MD 21202",
    "addr:housenumber":"1400",
    "addr:postcode":"21202",
    "addr:street":"Greenmount Ave",
    "iso:country":"US",
    "sg:address":"1400 Greenmount Ave",
    "sg:city":"Baltimore",
    "sg:classifiers":[
        {
            "category":"Shopping",
            "subcategory":"Used Merchandise",
            "type":"Retail Goods"
        }
    ],
    "sg:phone":"+1 410 230 0829",
    "sg:postcode":"21202",
    "sg:province":"MD",
    "sg:tags":[
        "shop",
        "thrift"
    ],
    "wof:name":"Station North Thrift Store",
    "wof:placetype":"venue"
},
  "geometry": {"coordinates":[-76.60873599999999,39.30694],"type":"Point"}
}