{
  "type": "Feature",
  "properties": {
    "iso:country":"US",
    "sg:address":"3909 Ilford Rd",
    "sg:city":"Silver Spring",
    "sg:classifiers":[
        {
            "category":"Shopping",
            "subcategory":"Computers & Home Electronics",
            "type":"Retail Goods"
        }
    ],
    "sg:phone":"+1 301 949 0139",
    "sg:postcode":"20906",
    "sg:province":"MD",
    "sg:tags":[
        "equipment",
        "dealer"
    ],
    "wof:name":"Computer Science Corp",
    "wof:placetype":"venue"
},
  "geometry": {"coordinates":[-77.080687,39.058814],"type":"Point"}
}