{
  "type": "Feature",
  "properties": {
    "iso:country":"US",
    "sg:address":"5049 Saint Barnabas Rd",
    "sg:city":"Temple Hills",
    "sg:classifiers":[
        {
            "category":"Building & Trades",
            "subcategory":"Plumbing",
            "type":"Services"
        }
    ],
    "sg:phone":"+1 301 894 3551",
    "sg:postcode":"20748",
    "sg:province":"MD",
    "wof:name":"Upperman R V Sons Inc",
    "wof:placetype":"venue"
},
  "geometry": {"coordinates":[-76.95639799999999,38.8209],"type":"Point"}
}