{
  "type": "Feature",
  "properties": {
    "iso:country":"US",
    "sg:address":"1513 Johnathan St",
    "sg:city":"Hyattsville",
    "sg:phone":"+1 301 559 6535",
    "sg:postcode":"20782",
    "sg:province":"MD",
    "sg:tags":[
        "product",
        "farm",
        "material",
        "petroleum",
        "raw",
        "oils-fuel"
    ],
    "wof:name":"Wallace Group International Inc",
    "wof:placetype":"venue"
},
  "geometry": {"coordinates":[-76.982697,38.954803],"type":"Point"}
}