{
  "type": "Feature",
  "properties": {
    "iso:country":"US",
    "sg:address":"9806 Piscataway Rd",
    "sg:city":"Clinton",
    "sg:classifiers":[
        {
            "category":"Organizations",
            "subcategory":"Religious Organization",
            "type":"Services"
        }
    ],
    "sg:phone":"+1 301 868 2205",
    "sg:postcode":"20735",
    "sg:province":"MD",
    "sg:tags":[
        "church"
    ],
    "wof:name":"Perfecting Saints Baptist Chr",
    "wof:placetype":"venue"
},
  "geometry": {"coordinates":[-76.919124,38.7555],"type":"Point"}
}