{
  "type": "Feature",
  "properties": {
    "iso:country":"US",
    "sg:address":"18200 Georgia Ave",
    "sg:city":"Olney",
    "sg:classifiers":[
        {
            "category":"Shopping",
            "type":"Retail Goods"
        }
    ],
    "sg:phone":"+1 301 774 3280",
    "sg:postcode":"20832",
    "sg:province":"MD",
    "sg:tags":[
        "cards",
        "sport",
        "baseball",
        "memorabilia"
    ],
    "wof:name":"Ace Sports Cards",
    "wof:placetype":"venue"
},
  "geometry": {"coordinates":[-77.066397,39.156023],"type":"Point"}
}