{
  "type": "Feature",
  "properties": {
    "iso:country":"US",
    "sg:address":"3811 Egerton Rd",
    "sg:city":"Baltimore",
    "sg:classifiers":[
        {
            "category":"Organizations",
            "subcategory":"Religious Organization",
            "type":"Services"
        }
    ],
    "sg:phone":"+1 410 367 7107",
    "sg:postcode":"21215",
    "sg:province":"MD",
    "sg:tags":[
        "church"
    ],
    "wof:name":"Faith Christian Worship Ctr",
    "wof:placetype":"venue"
},
  "geometry": {"coordinates":[-76.682299,39.328355],"type":"Point"}
}