{
  "type": "Feature",
  "properties": {
    "iso:country":"US",
    "sg:address":"806 Frederick Rd",
    "sg:city":"Catonsville",
    "sg:classifiers":[
        {
            "category":"Professional",
            "subcategory":"Lawyer & Legal Services",
            "type":"Services"
        }
    ],
    "sg:phone":"+1 410 744 4844",
    "sg:postcode":"21228",
    "sg:province":"MD",
    "sg:tags":[
        "personal",
        "injury"
    ],
    "wof:name":"The Law Office of S Everett Brown Llc",
    "wof:placetype":"venue"
},
  "geometry": {"coordinates":[-76.73423699999999,39.271545],"type":"Point"}
}