{
  "type": "Feature",
  "properties": {
    "addr:full":"4127 E Joppa Rd Nottingham MD 21236",
    "addr:housenumber":"4127 e",
    "addr:postcode":"21236",
    "addr:street":"Joppa Rd",
    "iso:country":"US",
    "sg:address":"4127 E Joppa Rd",
    "sg:city":"Nottingham",
    "sg:classifiers":[
        {
            "category":"Personal",
            "type":"Services"
        },
        {
            "category":"Wholesale",
            "subcategory":"Scrap",
            "type":"Manufacturing & Wholesale Goods"
        },
        {
            "category":"Retail",
            "subcategory":"Auto Repair",
            "type":"Services"
        }
    ],
    "sg:phone":"+1 410 256 1797",
    "sg:postcode":"21236",
    "sg:province":"MD",
    "sg:tags":[
        "body",
        "wrecking",
        "automobile",
        "towing",
        "truck",
        "painting",
        "repairing"
    ],
    "wof:name":"Carney Towing",
    "wof:placetype":"venue"
},
  "geometry": {"coordinates":[-76.482485,39.398382],"type":"Point"}
}