{
  "type": "Feature",
  "properties": {
    "addr:full":"1787 Forest Dr Annapolis MD 21401",
    "addr:housenumber":"1787",
    "addr:postcode":"21401",
    "addr:street":"Forest Dr",
    "iso:country":"US",
    "sg:address":"1787 Forest Dr",
    "sg:city":"Annapolis",
    "sg:phone":"+1 410 626 9993",
    "sg:postcode":"21401",
    "sg:province":"MD",
    "sg:website":"http://www.hollywoodvideo.com",
    "wof:name":"Hollywood Video",
    "wof:placetype":"venue"
},
  "geometry": {"coordinates":[-76.52253399999999,38.971292],"type":"Point"}
}