{
  "type": "Feature",
  "properties": {
    "addr:full":"8840 Columbia 100 Pkwy Columbia MD 21045",
    "addr:housenumber":"8840",
    "addr:postcode":"21045",
    "addr:street":"Columbia 100 Pkwy",
    "iso:country":"US",
    "sg:address":"8840 Columbia 100 Pkwy",
    "sg:city":"Columbia",
    "sg:classifiers":[
        {
            "category":"Banks & Credit Unions",
            "subcategory":"Bank",
            "type":"Services"
        }
    ],
    "sg:phone":"+1 410 740 3200",
    "sg:postcode":"21045",
    "sg:province":"MD",
    "sg:tags":[
        "mortgage",
        "loan",
        "broker",
        "real estate"
    ],
    "wof:name":"Global Finance Company",
    "wof:placetype":"venue"
},
  "geometry": {"coordinates":[-76.81500200000001,39.230801],"type":"Point"}
}