{
  "type": "Feature",
  "properties": {
    "iso:country":"US",
    "sg:address":"4151 Park Heights Ave",
    "sg:city":"Baltimore",
    "sg:classifiers":[
        {
            "category":"Sports & Exercise",
            "subcategory":"Sports Center",
            "type":"Entertainment"
        }
    ],
    "sg:phone":"+1 410 466 6471",
    "sg:postcode":"21215",
    "sg:province":"MD",
    "sg:tags":[
        "amateur",
        "team"
    ],
    "sg:website":"www.parkwestmed.org",
    "wof:name":"Park Heights Community",
    "wof:placetype":"venue"
},
  "geometry": {"coordinates":[-76.663633,39.336321],"type":"Point"}
}