{
  "type": "Feature",
  "properties": {
    "addr:full":"3600 Clipper Rd Baltimore MD 21211",
    "addr:housenumber":"3600",
    "addr:postcode":"21211",
    "addr:street":"Clipper Rd",
    "iso:country":"US",
    "sg:address":"3600 Clipper Rd",
    "sg:city":"Baltimore",
    "sg:classifiers":[
        {
            "category":"Cinema",
            "subcategory":"Movie Theater",
            "type":"Entertainment"
        }
    ],
    "sg:phone":"+1 410 243 5237",
    "sg:postcode":"21211",
    "sg:province":"MD",
    "sg:tags":[
        "motion",
        "picture",
        "theatrical",
        "re"
    ],
    "wof:name":"Axis Theatre",
    "wof:placetype":"venue"
},
  "geometry": {"coordinates":[-76.64591900000001,39.334196],"type":"Point"}
}