{
  "type": "Feature",
  "properties": {
    "addr:full":"907 Boxwood Ave Westminster MD 21157",
    "addr:housenumber":"907",
    "addr:postcode":"21157",
    "addr:street":"Boxwood Ave",
    "iso:country":"US",
    "sg:address":"907 Boxwood Ave",
    "sg:city":"Westminster",
    "sg:classifiers":[
        {
            "category":"Health Services",
            "subcategory":"Doctor",
            "type":"Services"
        }
    ],
    "sg:phone":"+1 410 857 9677",
    "sg:postcode":"21157",
    "sg:province":"MD",
    "sg:tags":[
        "medical"
    ],
    "wof:name":"B O C Gases",
    "wof:placetype":"venue"
},
  "geometry": {"coordinates":[-76.964039,39.552625],"type":"Point"}
}