{
  "type": "Feature",
  "properties": {
    "iso:country":"US",
    "sg:address":"3956 Street Rd",
    "sg:city":"Street",
    "sg:classifiers":[
        {
            "category":"Building & Trades",
            "subcategory":"Construction",
            "type":"Services"
        }
    ],
    "sg:phone":"+1 410 836 1642",
    "sg:postcode":"21154",
    "sg:province":"MD",
    "sg:tags":[
        "excavating",
        "contractor"
    ],
    "wof:name":"Ward Ronald and Ruth",
    "wof:placetype":"venue"
},
  "geometry": {"coordinates":[-76.37936,39.668605],"type":"Point"}
}