{
  "type": "Feature",
  "properties": {
    "addr:full":"12 Galloway Ave Cockysvl Hnt Vly MD 21030",
    "addr:housenumber":"12",
    "addr:postcode":"21030",
    "addr:street":"Galloway Ave;Hnt Vly",
    "iso:country":"US",
    "sg:address":"12 Galloway Ave",
    "sg:city":"Cockysvl Hnt Vly",
    "sg:classifiers":[
        {
            "category":"Shopping",
            "type":"Retail Goods"
        }
    ],
    "sg:phone":"+1 410 628 1674",
    "sg:postcode":"21030",
    "sg:province":"MD",
    "sg:tags":[
        "miscellaneous",
        "store"
    ],
    "wof:name":"Retail Tobacco Dealers",
    "wof:placetype":"venue"
},
  "geometry": {"coordinates":[-76.637051,39.460752],"type":"Point"}
}