{
  "type": "Feature",
  "properties": {
    "iso:country":"US",
    "sg:address":"319 N Schroeder St",
    "sg:city":"Baltimore",
    "sg:classifiers":[
        {
            "category":"Organizations",
            "subcategory":"Religious Organization",
            "type":"Services"
        }
    ],
    "sg:phone":"+1 410 225 3835",
    "sg:postcode":"21223",
    "sg:province":"MD",
    "wof:name":"St Marks Bible Fellowship",
    "wof:placetype":"venue"
},
  "geometry": {"coordinates":[-76.634006,39.293015],"type":"Point"}
}