{
  "type": "Feature",
  "properties": {
    "addr:full":"2325 Pin Oak Dr Finksburg MD 21048",
    "addr:housenumber":"2325",
    "addr:postcode":"21048",
    "addr:street":"Pin Oak Dr",
    "iso:country":"US",
    "sg:address":"2325 Pin Oak Dr",
    "sg:city":"Finksburg",
    "sg:classifiers":[
        {
            "category":"Home & Garden",
            "subcategory":"Building Materials",
            "type":"Retail Goods"
        },
        {
            "category":"Building & Trades",
            "subcategory":"Construction",
            "type":"Services"
        },
        {
            "category":"Manufacturing",
            "subcategory":"Building Materials",
            "type":"Manufacturing & Wholesale Goods"
        }
    ],
    "sg:phone":"+1 410 488 0800",
    "sg:postcode":"21048",
    "sg:province":"MD",
    "sg:tags":[
        "altering",
        "contractor",
        "window",
        "doors",
        "frames",
        "accessory",
        "remodeling"
    ],
    "wof:name":"E Remodeling",
    "wof:placetype":"venue"
},
  "geometry": {"coordinates":[-76.91643500000001,39.472687],"type":"Point"}
}