{
  "type": "Feature",
  "properties": {
    "iso:country":"US",
    "sg:address":"3225 Round Rd",
    "sg:city":"Brooklyn",
    "sg:classifiers":[
        {
            "category":"Place Of Worship",
            "subcategory":"Church",
            "type":"Public Place"
        },
        {
            "category":"Place Of Worship",
            "type":"Public Place"
        }
    ],
    "sg:phone":"+1 410 355 0022",
    "sg:postcode":"21225",
    "sg:province":"MD",
    "sg:tags":[
        "churches-methodist"
    ],
    "wof:name":"Cherry Hill United Methodist Church, Inc",
    "wof:placetype":"venue"
},
  "geometry": {"coordinates":[-76.62723099999999,39.245731],"type":"Point"}
}