{
  "type": "Feature",
  "properties": {
    "addr:full":"1407 Partridge Ln Bowie MD 20721",
    "addr:housenumber":"1407",
    "addr:postcode":"20721",
    "addr:street":"Partridge Ln",
    "iso:country":"US",
    "sg:address":"1407 Partridge Ln",
    "sg:city":"Bowie",
    "sg:classifiers":[
        {
            "category":"Retail",
            "subcategory":"Portrait Studio",
            "type":"Services"
        }
    ],
    "sg:phone":"+1 301 390 0793",
    "sg:postcode":"20721",
    "sg:province":"MD",
    "sg:tags":[
        "photographer"
    ],
    "wof:name":"Expressions Photography",
    "wof:placetype":"venue"
},
  "geometry": {"coordinates":[-76.744585,38.911283],"type":"Point"}
}