{
  "type": "Feature",
  "properties": {
    "iso:country":"US",
    "sg:address":"2700 Seamon Ave",
    "sg:city":"Baltimore",
    "sg:classifiers":[
        {
            "category":"Education",
            "subcategory":"School",
            "type":"Public Place"
        }
    ],
    "sg:phone":"+1 410 396 1625",
    "sg:postcode":"21225",
    "sg:province":"MD",
    "wof:name":"South Side Academy",
    "wof:placetype":"venue"
},
  "geometry": {"coordinates":[-76.622013,39.253348],"type":"Point"}
}