{
  "type": "Feature",
  "properties": {
    "addr:full":"1226 Meridene Dr Baltimore MD 21239",
    "addr:housenumber":"1226",
    "addr:postcode":"21239",
    "addr:street":"Meridene Dr",
    "iso:country":"US",
    "sg:address":"1226 Meridene Dr",
    "sg:city":"Baltimore",
    "sg:classifiers":[
        {
            "category":"Local Transit",
            "type":"Transportation"
        }
    ],
    "sg:phone":"+1 410 433 8546",
    "sg:postcode":"21239",
    "sg:province":"MD",
    "wof:name":"Destiny Transportation",
    "wof:placetype":"venue"
},
  "geometry": {"coordinates":[-76.59215500000001,39.368358],"type":"Point"}
}