{
  "type": "Feature",
  "properties": {
    "iso:country":"US",
    "sg:address":"116 Ritchie Ave",
    "sg:city":"Silver Spring",
    "sg:classifiers":[
        {
            "category":"Retail",
            "subcategory":"Laundry & Dry Cleaning",
            "type":"Services"
        }
    ],
    "sg:phone":"+1 301 565 1688",
    "sg:postcode":"20910",
    "sg:province":"MD",
    "sg:tags":[
        "cleaners",
        "rug",
        "carpet"
    ],
    "wof:name":"Carpet Care Plus Inc",
    "wof:placetype":"venue"
},
  "geometry": {"coordinates":[-77.00838,38.985976],"type":"Point"}
}