{
  "type": "Feature",
  "properties": {
    "addr:full":"509 Main St Laurel MD 20707",
    "addr:housenumber":"509",
    "addr:postcode":"20707",
    "addr:street":"Main St",
    "iso:country":"US",
    "sg:address":"509 Main St",
    "sg:city":"Laurel",
    "sg:classifiers":[
        {
            "category":"Professional",
            "subcategory":"Management & Consulting",
            "type":"Services"
        }
    ],
    "sg:phone":"+1 301 604 6953",
    "sg:postcode":"20707",
    "sg:province":"MD",
    "sg:tags":[
        "consultant",
        "business"
    ],
    "wof:name":"Business Development Co",
    "wof:placetype":"venue"
},
  "geometry": {"coordinates":[-76.849761,39.106834],"type":"Point"}
}