{
  "type": "Feature",
  "properties": {
    "iso:country":"US",
    "sg:address":"7430 Washington Blvd",
    "sg:city":"Elkridge",
    "sg:classifiers":[
        {
            "category":"Wholesale",
            "subcategory":"Auto Parts",
            "type":"Manufacturing & Wholesale Goods"
        }
    ],
    "sg:phone":"+1 410 796 4988",
    "sg:postcode":"21075",
    "sg:province":"MD",
    "sg:tags":[
        "automobile",
        "supply"
    ],
    "wof:name":"World Class Auto & Truck Parts",
    "wof:placetype":"venue"
},
  "geometry": {"coordinates":[-76.767585,39.181564],"type":"Point"}
}