{
  "type": "Feature",
  "properties": {
    "iso:country":"US",
    "sg:address":"1011 Woodbridge Center Way",
    "sg:city":"Edgewood",
    "sg:classifiers":[
        {
            "category":"Personal",
            "subcategory":"Beauty Salon",
            "type":"Services"
        }
    ],
    "sg:phone":"+1 410 676 0110",
    "sg:postcode":"21040",
    "sg:province":"MD",
    "sg:tags":[
        "hair"
    ],
    "wof:name":"Reflections Beauty Salon",
    "wof:placetype":"venue"
},
  "geometry": {"coordinates":[-76.327191,39.432191],"type":"Point"}
}