{
  "type": "Feature",
  "properties": {
    "addr:full":"9330 Lakeside Blvd Owings Mills MD 21117",
    "addr:housenumber":"9330",
    "addr:postcode":"21117",
    "addr:street":"Lakeside Blvd",
    "iso:country":"US",
    "sg:address":"9330 Lakeside Blvd",
    "sg:city":"Owings Mills",
    "sg:classifiers":[
        {
            "category":"Autos & Motor Vehicles",
            "subcategory":"Fuel & Gas Station",
            "type":"Retail Goods"
        }
    ],
    "sg:phone":"+1 410 902 1400",
    "sg:postcode":"21117",
    "sg:province":"MD",
    "sg:tags":[
        "oil"
    ],
    "wof:name":"Mobil Service Station",
    "wof:placetype":"venue"
},
  "geometry": {"coordinates":[-76.815579,39.406872],"type":"Point"}
}