{
  "type": "Feature",
  "properties": {
    "iso:country":"US",
    "sg:address":"1602 Ford Ave",
    "sg:city":"Cumberland",
    "sg:classifiers":[
        {
            "category":"Retail",
            "subcategory":"Driving School",
            "type":"Services"
        },
        {
            "category":"Autos & Motor Vehicles",
            "subcategory":"Motorcycle Sales",
            "type":"Retail Goods"
        }
    ],
    "sg:phone":"+1 301 759 2920",
    "sg:postcode":"21502",
    "sg:province":"MD",
    "sg:tags":[
        "instruction"
    ],
    "wof:name":"Nutters Tri State Motorcycles Inc",
    "wof:placetype":"venue"
},
  "geometry": {"coordinates":[-78.772346,39.625179],"type":"Point"}
}