{
  "type": "Feature",
  "properties": {
    "addr:full":"400 S Eden St Baltimore MD 21231",
    "addr:housenumber":"400",
    "addr:postcode":"21231",
    "addr:street":"S Eden St",
    "iso:country":"US",
    "sg:address":"400 S Eden St",
    "sg:city":"Baltimore",
    "sg:classifiers":[
        {
            "category":"Building & Trades",
            "subcategory":"Locksmith",
            "type":"Services"
        }
    ],
    "sg:phone":"+1 443 378 3372",
    "sg:postcode":"21231",
    "sg:province":"MD",
    "sg:tags":[
        "key"
    ],
    "wof:name":"Locksmith All Around Town",
    "wof:placetype":"venue"
},
  "geometry": {"coordinates":[-76.598517,39.286385],"type":"Point"}
}