{
  "type": "Feature",
  "properties": {
    "addr:full":"2218 E Monument St Baltimore MD 21205",
    "addr:housenumber":"2218",
    "addr:postcode":"21205",
    "addr:street":"E Monument St",
    "iso:country":"US",
    "sg:address":"2218 E Monument St",
    "sg:city":"Baltimore",
    "sg:classifiers":[
        {
            "category":"Shopping",
            "subcategory":"Clothing, Apparel, & Fashions",
            "type":"Retail Goods"
        }
    ],
    "sg:phone":"+1 410 327 8434",
    "sg:postcode":"21205",
    "sg:province":"MD",
    "sg:tags":[
        "furnishing"
    ],
    "wof:name":"Expectations",
    "wof:placetype":"venue"
},
  "geometry": {"coordinates":[-76.586433,39.298768],"type":"Point"}
}