{
  "type": "Feature",
  "properties": {
    "iso:country":"US",
    "sg:address":"4000 Mitchellville Rd",
    "sg:city":"Bowie",
    "sg:classifiers":[
        {
            "category":"Health Services",
            "subcategory":"Doctor",
            "type":"Services"
        }
    ],
    "sg:phone":"+1 301 809 6221",
    "sg:postcode":"20716",
    "sg:province":"MD",
    "sg:tags":[
        "physician",
        "surgeon"
    ],
    "wof:name":"Aesthetic Dermatology",
    "wof:placetype":"venue"
},
  "geometry": {"coordinates":[-76.722955,38.945105],"type":"Point"}
}