{
  "type": "Feature",
  "properties": {
    "iso:country":"US",
    "sg:address":"5938 Rossmore Dr",
    "sg:city":"Bethesda",
    "sg:classifiers":[
        {
            "category":"Professional",
            "subcategory":"Research",
            "type":"Services"
        }
    ],
    "sg:phone":"+1 301 530 4989",
    "sg:postcode":"20814",
    "sg:province":"MD",
    "sg:tags":[
        "commercial",
        "physical"
    ],
    "wof:name":"National Ataxia Foundation",
    "wof:placetype":"venue"
},
  "geometry": {"coordinates":[-77.119049,39.026985],"type":"Point"}
}