{
  "type": "Feature",
  "properties": {
    "addr:full":"9106 Philadelphia Rd # 100 Rosedale MD 21237",
    "addr:housenumber":"9106",
    "addr:postcode":"21237",
    "addr:street":"Philadelphia Rd # 100",
    "iso:country":"US",
    "sg:address":"9106 Philadelphia Rd # 100",
    "sg:city":"Rosedale",
    "sg:classifiers":[
        {
            "category":"Shopping",
            "subcategory":"Pharmacy",
            "type":"Retail Goods"
        }
    ],
    "sg:phone":"+1 410 687 8113",
    "sg:postcode":"21237",
    "sg:province":"MD",
    "sg:tags":[
        "drugstore"
    ],
    "wof:name":"Professional Pharmacy of Essex",
    "wof:placetype":"venue"
},
  "geometry": {"coordinates":[-76.47370100000001,39.346401],"type":"Point"}
}