{
  "type": "Feature",
  "properties": {
    "iso:country":"US",
    "sg:address":"3000 Chestnut Ave Ste 207",
    "sg:city":"Baltimore",
    "sg:classifiers":[
        {
            "category":"Banks & Credit Unions",
            "subcategory":"Investment Brokerage",
            "type":"Services"
        },
        {
            "category":"Professional",
            "subcategory":"Business Services",
            "type":"Services"
        }
    ],
    "sg:phone":"+1 410 235 8532",
    "sg:postcode":"21211",
    "sg:province":"MD",
    "sg:tags":[
        "broker",
        "commodity"
    ],
    "sg:website":"http://www.ibsi.org",
    "wof:name":"Lacy Pa Bronze & Co Div",
    "wof:placetype":"venue"
},
  "geometry": {"coordinates":[-76.629593,39.324242],"type":"Point"}
}