{
  "type": "Feature",
  "properties": {
    "addr:full":"8630 Fenton St Silver Spring MD 20910",
    "addr:housenumber":"8630",
    "addr:postcode":"20910",
    "addr:street":"Fenton St",
    "iso:country":"US",
    "sg:address":"8630 Fenton St",
    "sg:city":"Silver Spring",
    "sg:classifiers":[
        {
            "category":"Health Services",
            "subcategory":"Doctor",
            "type":"Services"
        }
    ],
    "sg:phone":"+1 301 562 0944",
    "sg:postcode":"20910",
    "sg:province":"MD",
    "sg:tags":[
        "physician",
        "surgeon"
    ],
    "wof:name":"Theodore E Igwebe MD",
    "wof:placetype":"venue"
},
  "geometry": {"coordinates":[-77.02838800000001,38.998098],"type":"Point"}
}