{
  "type": "Feature",
  "properties": {
    "iso:country":"US",
    "sg:address":"187 E Main St",
    "sg:city":"Frostburg",
    "sg:classifiers":[
        {
            "category":"Real Estate",
            "subcategory":"Real Estate Operator",
            "type":"Services"
        }
    ],
    "sg:phone":"+1 301 687 0477",
    "sg:postcode":"21532",
    "sg:province":"MD",
    "sg:tags":[
        "apartment"
    ],
    "wof:name":"Annie's Apartments",
    "wof:placetype":"venue"
},
  "geometry": {"coordinates":[-78.922258,39.654662],"type":"Point"}
}