{
  "type": "Feature",
  "properties": {
    "iso:country":"US",
    "sg:address":"9105 Franklin Square Dr",
    "sg:city":"Baltimore",
    "sg:classifiers":[
        {
            "category":"Health Services",
            "subcategory":"Doctor",
            "type":"Services"
        }
    ],
    "sg:phone":"+1 410 574 8440",
    "sg:postcode":"21237",
    "sg:province":"MD",
    "sg:tags":[
        "physician",
        "surgeon"
    ],
    "wof:name":"Mary Carroll & Assoc",
    "wof:placetype":"venue"
},
  "geometry": {"coordinates":[-76.478058,39.350561],"type":"Point"}
}