{
  "type": "Feature",
  "properties": {
    "addr:full":"2801 Greenmount Ave Baltimore MD 21218",
    "addr:housenumber":"2801",
    "addr:postcode":"21218",
    "addr:street":"Greenmount Ave",
    "iso:country":"US",
    "sg:address":"2801 Greenmount Ave",
    "sg:city":"Baltimore",
    "sg:classifiers":[
        {
            "category":"Autos & Motor Vehicles",
            "subcategory":"Auto Supplies",
            "type":"Retail Goods"
        },
        {
            "category":"Wholesale",
            "subcategory":"Electrical",
            "type":"Manufacturing & Wholesale Goods"
        },
        {
            "category":"Wholesale",
            "subcategory":"Auto Parts",
            "type":"Manufacturing & Wholesale Goods"
        },
        {
            "category":"Retail",
            "subcategory":"Auto Repair",
            "type":"Services"
        }
    ],
    "sg:phone":"+1 410 235 3384",
    "sg:postcode":"21218",
    "sg:province":"MD",
    "sg:tags":[
        "engines-rebuild",
        "exchange",
        "battery",
        "automobile",
        "accessory",
        "equipment",
        "supplies-used",
        "truck",
        "rebuilt",
        "batteries-storage"
    ],
    "sg:website":"http://www.advanceautoparts.com",
    "wof:name":"Advance Auto Parts",
    "wof:placetype":"venue"
},
  "geometry": {"coordinates":[-76.609459,39.322182],"type":"Point"}
}