{
  "type": "Feature",
  "properties": {
    "addr:full":"14609 Woodcrest Dr Rockville MD 20853",
    "addr:housenumber":"14609",
    "addr:postcode":"20853",
    "addr:street":"Woodcrest Dr",
    "iso:country":"US",
    "sg:address":"14609 Woodcrest Dr",
    "sg:city":"Rockville",
    "sg:classifiers":[
        {
            "category":"Professional",
            "subcategory":"Management & Consulting",
            "type":"Services"
        }
    ],
    "sg:phone":"+1 301 460 7398",
    "sg:postcode":"20853",
    "sg:province":"MD",
    "wof:name":"M Shapiro",
    "wof:placetype":"venue"
},
  "geometry": {"coordinates":[-77.105726,39.094847],"type":"Point"}
}