{
  "type": "Feature",
  "properties": {
    "iso:country":"US",
    "sg:address":"1414 Key Hwy Ste 301",
    "sg:city":"Baltimore",
    "sg:classifiers":[
        {
            "category":"Professional",
            "subcategory":"Lawyer & Legal Services",
            "type":"Services"
        }
    ],
    "sg:phone":"+1 410 752 5400",
    "sg:postcode":"21230",
    "sg:province":"MD",
    "wof:name":"Yerman & Smedley PA",
    "wof:placetype":"venue"
},
  "geometry": {"coordinates":[-76.602542,39.273227],"type":"Point"}
}