{
  "type": "Feature",
  "properties": {
    "iso:country":"US",
    "sg:address":"4105 54th St",
    "sg:city":"Bladensburg",
    "sg:classifiers":[
        {
            "category":"Organizations",
            "subcategory":"Religious Organization",
            "type":"Services"
        }
    ],
    "sg:phone":"+1 301 277 3239",
    "sg:postcode":"20710",
    "sg:province":"MD",
    "sg:tags":[
        "seventh",
        "day",
        "place",
        "church",
        "worship",
        "adventist"
    ],
    "wof:name":"Bladensburg S D A Church",
    "wof:placetype":"venue"
},
  "geometry": {"coordinates":[-76.926903,38.939819],"type":"Point"}
}