{
  "type": "Feature",
  "properties": {
    "addr:full":"7450 Montevideo Rd Jessup MD 20794",
    "addr:housenumber":"7450",
    "addr:postcode":"20794",
    "addr:street":"Montevideo Rd",
    "iso:country":"US",
    "sg:address":"7450 Montevideo Rd",
    "sg:city":"Jessup",
    "sg:classifiers":[
        {
            "category":"Manufacturing",
            "subcategory":"Buildings",
            "type":"Manufacturing & Wholesale Goods"
        },
        {
            "category":"Home & Garden",
            "subcategory":"Building Materials",
            "type":"Retail Goods"
        },
        {
            "category":"Manufacturing",
            "subcategory":"Building Materials",
            "type":"Manufacturing & Wholesale Goods"
        }
    ],
    "sg:phone":"+1 410 799 1414",
    "sg:postcode":"20794",
    "sg:province":"MD",
    "sg:tags":[
        "prefabricated",
        "buildings-metal-wholesale",
        "buildings-pre-cut",
        "manufacturer",
        "modular"
    ],
    "wof:name":"Metal-Fab Manufacturing",
    "wof:placetype":"venue"
},
  "geometry": {"coordinates":[-76.770242,39.164537],"type":"Point"}
}