{
  "type": "Feature",
  "properties": {
    "addr:full":"9710 Royal Crest Cir Frederick MD 21704",
    "addr:housenumber":"9710",
    "addr:postcode":"21704",
    "addr:street":"Royal Crest Cir",
    "iso:country":"US",
    "sg:address":"9710 Royal Crest Cir",
    "sg:city":"Frederick",
    "sg:classifiers":[
        {
            "category":"Building & Trades",
            "subcategory":"Construction",
            "type":"Services"
        }
    ],
    "sg:phone":"+1 301 874 3894",
    "sg:postcode":"21704",
    "sg:province":"MD",
    "sg:tags":[
        "contractor"
    ],
    "wof:name":"Cochrane Construction Des",
    "wof:placetype":"venue"
},
  "geometry": {"coordinates":[-77.332611,39.341881],"type":"Point"}
}