{
  "type": "Feature",
  "properties": {
    "addr:full":"3116 Juneau Pl Baltimore MD 21214",
    "addr:housenumber":"3116",
    "addr:postcode":"21214",
    "addr:street":"Juneau Pl",
    "iso:country":"US",
    "sg:address":"3116 Juneau Pl",
    "sg:city":"Baltimore",
    "sg:classifiers":[
        {
            "category":"Farming",
            "subcategory":"Fish & Marine Products",
            "type":"Manufacturing & Wholesale Goods"
        },
        {
            "category":"Retail",
            "subcategory":"Repair Shop",
            "type":"Services"
        },
        {
            "category":"Professional",
            "subcategory":"Art Services",
            "type":"Services"
        }
    ],
    "sg:phone":"+1 410 254 9041",
    "sg:postcode":"21214",
    "sg:province":"MD",
    "sg:tags":[
        "picture",
        "frame",
        "restoration",
        "framing"
    ],
    "wof:name":"Frame Express",
    "wof:placetype":"venue"
},
  "geometry": {"coordinates":[-76.572045,39.333996],"type":"Point"}
}