{
  "type": "Feature",
  "properties": {
    "addr:full":"802 Shaw Ct Baltimore MD 21286",
    "addr:housenumber":"802",
    "addr:postcode":"21286",
    "addr:street":"Shaw Ct",
    "iso:country":"US",
    "sg:address":"802 Shaw Ct",
    "sg:city":"Baltimore",
    "sg:classifiers":[
        {
            "category":"Professional",
            "subcategory":"Computer Services",
            "type":"Services"
        }
    ],
    "sg:phone":"+1 410 296 3246",
    "sg:postcode":"21286",
    "sg:province":"MD",
    "sg:tags":[
        "related"
    ],
    "wof:name":"Raam Consultants",
    "wof:placetype":"venue"
},
  "geometry": {"coordinates":[-76.584699,39.405348],"type":"Point"}
}