{
  "type": "Feature",
  "properties": {
    "addr:full":"8004 Garrett Hwy Oakland MD 21550",
    "addr:housenumber":"8004",
    "addr:postcode":"21550",
    "addr:street":"Garrett Hwy",
    "iso:country":"US",
    "sg:address":"8004 Garrett Hwy",
    "sg:city":"Oakland",
    "sg:classifiers":[
        {
            "category":"Farming",
            "subcategory":"Dairy Farm",
            "type":"Manufacturing & Wholesale Goods"
        },
        {
            "category":"Farming",
            "subcategory":"Farm",
            "type":"Manufacturing & Wholesale Goods"
        }
    ],
    "sg:phone":"+1 301 334 2893",
    "sg:postcode":"21550",
    "sg:province":"MD",
    "wof:name":"Jonas Kinsinger",
    "wof:placetype":"venue"
},
  "geometry": {"coordinates":[-79.418786,39.365299],"type":"Point"}
}