{
  "type": "Feature",
  "properties": {
    "addr:full":"6604 Hansford St District Heights MD 20747",
    "addr:housenumber":"6604",
    "addr:postcode":"20747",
    "addr:street":"Hansford St",
    "iso:country":"US",
    "sg:address":"6604 Hansford St",
    "sg:city":"District Heights",
    "sg:classifiers":[
        {
            "category":"Retail",
            "subcategory":"Repair Shop",
            "type":"Services"
        }
    ],
    "sg:phone":"+1 301 735 3432",
    "sg:postcode":"20747",
    "sg:province":"MD",
    "sg:tags":[
        "equipment",
        "electronic",
        "supply"
    ],
    "wof:name":"Henderson Electronic Repair",
    "wof:placetype":"venue"
},
  "geometry": {"coordinates":[-76.894088,38.850747],"type":"Point"}
}