{
  "type": "Feature",
  "properties": {
    "addr:full":"22 S Greene St Rm N2w78 Baltimore MD 21201",
    "addr:housenumber":"22",
    "addr:postcode":"21201",
    "addr:street":"S Greene St;N2W78",
    "iso:country":"US",
    "sg:address":"22 S Greene St Rm N2w78",
    "sg:city":"Baltimore",
    "sg:classifiers":[
        {
            "category":"Health Services",
            "subcategory":"Doctor",
            "type":"Services"
        }
    ],
    "sg:phone":"+1 410 328 1291",
    "sg:postcode":"21201",
    "sg:province":"MD",
    "sg:tags":[
        "physician",
        "radiology",
        "pediatrics-radiology",
        "surgeons",
        "surgeon"
    ],
    "wof:name":"Department Of Radiology U M M S",
    "wof:placetype":"venue"
},
  "geometry": {"coordinates":[-76.623625,39.288239],"type":"Point"}
}