{
  "type": "Feature",
  "properties": {
    "addr:full":"11803 Hickory Dr Fort Washington MD 20744",
    "addr:housenumber":"11803",
    "addr:postcode":"20744",
    "addr:street":"Hickory Dr",
    "iso:country":"US",
    "sg:address":"11803 Hickory Dr",
    "sg:city":"Fort Washington",
    "sg:classifiers":[
        {
            "category":"Real Estate",
            "subcategory":"Real Estate Operator",
            "type":"Services"
        }
    ],
    "sg:phone":"+1 301 203 6566",
    "sg:postcode":"20744",
    "sg:province":"MD",
    "sg:tags":[
        "land"
    ],
    "wof:name":"Womack Development LLC",
    "wof:placetype":"venue"
},
  "geometry": {"coordinates":[-77.00276700000001,38.730098],"type":"Point"}
}