{
  "type": "Feature",
  "properties": {
    "iso:country":"US",
    "sg:address":"11803 Hickory Dr",
    "sg:city":"Fort Washington",
    "sg:classifiers":[
        {
            "category":"Real Estate",
            "subcategory":"Real Estate Operator",
            "type":"Services"
        }
    ],
    "sg:phone":"+1 301 203 6566",
    "sg:postcode":"20744",
    "sg:province":"MD",
    "sg:tags":[
        "land"
    ],
    "wof:name":"Womack Development LLC",
    "wof:placetype":"venue"
},
  "geometry": {"coordinates":[-77.002767,38.730098],"type":"Point"}
}