{
  "type": "Feature",
  "properties": {
    "addr:full":"1 Hitching Post Ct Rockville MD 20852",
    "addr:housenumber":"1",
    "addr:postcode":"20852",
    "addr:street":"Hitching Post Ct",
    "iso:country":"US",
    "sg:address":"1 Hitching Post Ct",
    "sg:city":"Rockville",
    "sg:classifiers":[
        {
            "category":"Wholesale",
            "subcategory":"Sporting Goods",
            "type":"Manufacturing & Wholesale Goods"
        }
    ],
    "sg:phone":"+1 301 231 9340",
    "sg:postcode":"20852",
    "sg:province":"MD",
    "sg:tags":[
        "equipment",
        "billiard",
        "supply"
    ],
    "wof:name":"Odyssey Customs",
    "wof:placetype":"venue"
},
  "geometry": {"coordinates":[-77.148399,39.053385],"type":"Point"}
}