{
  "type": "Feature",
  "properties": {
    "addr:full":"11817 Park Waldorf Ln Waldorf MD 20601",
    "addr:housenumber":"11817",
    "addr:postcode":"20601",
    "addr:street":"Park Waldorf Ln",
    "iso:country":"US",
    "sg:address":"11817 Park Waldorf Ln",
    "sg:city":"Waldorf",
    "sg:classifiers":[
        {
            "category":"Shopping",
            "type":"Retail Goods"
        }
    ],
    "sg:phone":"+1 301 932 8855",
    "sg:postcode":"20601",
    "sg:province":"MD",
    "sg:tags":[
        "enforcement",
        "law",
        "supply"
    ],
    "sg:website":"www.policefirerescue.com",
    "wof:name":"Southern Police Supply",
    "wof:placetype":"venue"
},
  "geometry": {"coordinates":[-76.90094000000001,38.635356],"type":"Point"}
}