{
  "type": "Feature",
  "properties": {
    "iso:country":"US",
    "sg:address":"3335 75th Ave",
    "sg:city":"Hyattsville",
    "sg:classifiers":[
        {
            "category":"Wholesale",
            "subcategory":"Fruits & Vegetables",
            "type":"Manufacturing & Wholesale Goods"
        }
    ],
    "sg:phone":"+1 301 772 0953",
    "sg:postcode":"20785",
    "sg:province":"MD",
    "sg:tags":[
        "veggie"
    ],
    "wof:name":"Keany Produce",
    "wof:placetype":"venue"
},
  "geometry": {"coordinates":[-76.88220200000001,38.933998],"type":"Point"}
}