{
  "type": "Feature",
  "properties": {
    "iso:country":"US",
    "sg:address":"8630 Guilford Rd Ste M",
    "sg:city":"Columbia",
    "sg:classifiers":[
        {
            "category":"Professional",
            "subcategory":"Lawyer & Legal Services",
            "type":"Services"
        }
    ],
    "sg:phone":"+1 410 290 6900",
    "sg:postcode":"21046",
    "sg:province":"MD",
    "sg:tags":[
        "notary"
    ],
    "wof:name":"Mail Boxes Etc",
    "wof:placetype":"venue"
},
  "geometry": {"coordinates":[-76.836637,39.165633],"type":"Point"}
}