{
  "type": "Feature",
  "properties": {
    "iso:country":"US",
    "sg:address":"12013 Bork Dr",
    "sg:city":"Clinton",
    "sg:classifiers":[
        {
            "category":"Professional",
            "subcategory":"Management & Consulting",
            "type":"Services"
        }
    ],
    "sg:phone":"+1 301 292 1895",
    "sg:postcode":"20735",
    "sg:province":"MD",
    "sg:tags":[
        "administrative"
    ],
    "wof:name":"Bmb Global",
    "wof:placetype":"venue"
},
  "geometry": {"coordinates":[-76.950793,38.72529],"type":"Point"}
}