{
  "type": "Feature",
  "properties": {
    "iso:country":"US",
    "sg:address":"4402 Norwood Rd",
    "sg:city":"Baltimore",
    "sg:classifiers":[
        {
            "category":"Landmark",
            "subcategory":"Tourist Information",
            "type":"Public Place"
        }
    ],
    "sg:phone":"+1 410 516 7382",
    "sg:postcode":"21218",
    "sg:province":"MD",
    "sg:tags":[
        "attraction"
    ],
    "wof:name":"Sherwood Gardens",
    "wof:placetype":"venue"
},
  "geometry": {"coordinates":[-76.61244499999999,39.342987],"type":"Point"}
}