{
  "type": "Feature",
  "properties": {
    "iso:country":"US",
    "sg:address":"301 W Preston St",
    "sg:city":"Baltimore",
    "sg:classifiers":[
        {
            "category":"Government",
            "subcategory":"Court House",
            "type":"Public Place"
        }
    ],
    "sg:phone":"+1 410 225 1340",
    "sg:postcode":"21201",
    "sg:province":"MD",
    "wof:name":"Secretary of State",
    "wof:placetype":"venue"
},
  "geometry": {"coordinates":[-76.62162,39.302562],"type":"Point"}
}