{
  "type": "Feature",
  "properties": {
    "addr:full":"10603 Dunkirk Dr Silver Spring MD 20902",
    "addr:housenumber":"10603",
    "addr:postcode":"20902",
    "addr:street":"Dunkirk Dr",
    "iso:country":"US",
    "sg:address":"10603 Dunkirk Dr",
    "sg:city":"Silver Spring",
    "sg:classifiers":[
        {
            "category":"Professional",
            "subcategory":"Management & Consulting",
            "type":"Services"
        }
    ],
    "sg:phone":"+1 301 649 2316",
    "sg:postcode":"20902",
    "sg:province":"MD",
    "sg:tags":[
        "business"
    ],
    "wof:name":"R A D Consulting Services Inc",
    "wof:placetype":"venue"
},
  "geometry": {"coordinates":[-77.041684,39.029507],"type":"Point"}
}