{
  "type": "Feature",
  "properties": {
    "iso:country":"US",
    "sg:address":"201 N Highland Ave",
    "sg:city":"Baltimore",
    "sg:classifiers":[
        {
            "category":"Restaurant",
            "type":"Food & Drink"
        },
        {
            "category":"Food & Beverages",
            "subcategory":"Meat & Fish",
            "type":"Retail Goods"
        }
    ],
    "sg:phone":"+1 410 327 3525",
    "sg:postcode":"21224",
    "sg:province":"MD",
    "sg:tags":[
        "seafood",
        "market"
    ],
    "wof:name":"Capt'n Franks Seafood",
    "wof:placetype":"venue"
},
  "geometry": {"coordinates":[-76.56970200000001,39.2953],"type":"Point"}
}