{
  "type": "Feature",
  "properties": {
    "iso:country":"US",
    "sg:address":"850 Nelson St",
    "sg:city":"Rockville",
    "sg:classifiers":[
        {
            "category":"Professional",
            "type":"Services"
        }
    ],
    "sg:phone":"+1 240 453 9049",
    "sg:postcode":"20850",
    "sg:province":"MD",
    "sg:tags":[
        "consultant",
        "galleries",
        "art"
    ],
    "wof:name":"Arts Alive",
    "wof:placetype":"venue"
},
  "geometry": {"coordinates":[-77.171364,39.09419],"type":"Point"}
}