{
  "type": "Feature",
  "properties": {
    "addr:full":"8801 Orchard Tree Ln Towson MD 21286",
    "addr:housenumber":"8801",
    "addr:postcode":"21286",
    "addr:street":"Orchard Tree Ln",
    "iso:country":"US",
    "sg:address":"8801 Orchard Tree Ln",
    "sg:city":"Towson",
    "sg:classifiers":[
        {
            "category":"Sports & Exercise",
            "subcategory":"Gym",
            "type":"Entertainment"
        }
    ],
    "sg:phone":"+1 410 825 3600",
    "sg:postcode":"21286",
    "sg:province":"MD",
    "sg:tags":[
        "club",
        "health",
        "studio",
        "gymnasium"
    ],
    "wof:name":"J's Next Level Fitness Inc",
    "wof:placetype":"venue"
},
  "geometry": {"coordinates":[-76.56912199999999,39.399198],"type":"Point"}
}