{
  "type": "Feature",
  "properties": {
    "addr:full":"6801 Broening Rd Baltimore MD 21222",
    "addr:housenumber":"6801",
    "addr:postcode":"21222",
    "addr:street":"Broening Rd",
    "iso:country":"US",
    "sg:address":"6801 Broening Rd",
    "sg:city":"Baltimore",
    "sg:classifiers":[
        {
            "category":"Food & Beverages",
            "subcategory":"Dairy",
            "type":"Retail Goods"
        }
    ],
    "sg:phone":"+1 410 285 6080",
    "sg:postcode":"21222",
    "sg:province":"MD",
    "sg:tags":[
        "product"
    ],
    "wof:name":"High's Of Baltimore",
    "wof:placetype":"venue"
},
  "geometry": {"coordinates":[-76.51979,39.250758],"type":"Point"}
}