{
  "type": "Feature",
  "properties": {
    "iso:country":"US",
    "sg:address":"4701 Willard Ave",
    "sg:city":"Chevy Chase",
    "sg:classifiers":[
        {
            "category":"Health Services",
            "subcategory":"Doctor",
            "type":"Services"
        }
    ],
    "sg:phone":"+1 301 652 6760",
    "sg:postcode":"20815",
    "sg:province":"MD",
    "sg:tags":[
        "physician",
        "surgeon"
    ],
    "wof:name":"James H Brodsky MD",
    "wof:placetype":"venue"
},
  "geometry": {"coordinates":[-77.095382,38.962497],"type":"Point"}
}