{
  "type": "Feature",
  "properties": {
    "addr:full":"10246 Reisterstown Rd Owings Mills MD 21117",
    "addr:housenumber":"10246",
    "addr:postcode":"21117",
    "addr:street":"Reisterstown Rd",
    "iso:country":"US",
    "sg:address":"10246 Reisterstown Rd",
    "sg:city":"Owings Mills",
    "sg:classifiers":[
        {
            "category":"Manufacturing",
            "subcategory":"Apparel",
            "type":"Manufacturing & Wholesale Goods"
        }
    ],
    "sg:phone":"+1 410 363 1000",
    "sg:postcode":"21117",
    "sg:province":"MD",
    "sg:tags":[
        "emblem",
        "mfg"
    ],
    "sg:website":"www.lionbrothers.com",
    "wof:name":"Lion Brothers Co",
    "wof:placetype":"venue"
},
  "geometry": {"coordinates":[-76.77411499999999,39.415072],"type":"Point"}
}