{
  "type": "Feature",
  "properties": {
    "iso:country":"US",
    "sg:address":"718 Biddle St",
    "sg:city":"Chesapeake City",
    "sg:classifiers":[
        {
            "category":"Manufacturing",
            "subcategory":"Metals",
            "type":"Manufacturing & Wholesale Goods"
        }
    ],
    "sg:phone":"+1 410 885 2575",
    "sg:postcode":"21915",
    "sg:province":"MD",
    "sg:tags":[
        "cable"
    ],
    "wof:name":"Tristate Cable Comm",
    "wof:placetype":"venue"
},
  "geometry": {"coordinates":[-75.79030899999999,39.536035],"type":"Point"}
}