{
  "type": "Feature",
  "properties": {
    "iso:country":"US",
    "sg:address":"11716 Morningside Dr NE",
    "sg:city":"Cumberland",
    "sg:classifiers":[
        {
            "category":"Retail",
            "subcategory":"Auto Repair",
            "type":"Services"
        }
    ],
    "sg:phone":"+1 301 724 4620",
    "sg:postcode":"21502",
    "sg:province":"MD",
    "sg:tags":[
        "transmission"
    ],
    "wof:name":"L & T Transmission Svc Inc",
    "wof:placetype":"venue"
},
  "geometry": {"coordinates":[-78.728491,39.683848],"type":"Point"}
}