{
  "type": "Feature",
  "properties": {
    "iso:country":"US",
    "sg:address":"5275 Westview Dr",
    "sg:city":"Frederick",
    "sg:classifiers":[
        {
            "category":"Professional",
            "type":"Services"
        }
    ],
    "sg:phone":"+1 301 228 6000",
    "sg:postcode":"21703",
    "sg:province":"MD",
    "sg:website":"www.bechtel.com",
    "wof:name":"Bechtel Corp",
    "wof:placetype":"venue"
},
  "geometry": {"coordinates":[-77.41498,39.381173],"type":"Point"}
}