{
  "type": "Feature",
  "properties": {
    "addr:full":"6320 Wiscasset Rd Bethesda MD 20816",
    "addr:postcode":"6320;20816",
    "addr:street":"Wiscasset Rd",
    "iso:country":"US",
    "sg:address":"6320 Wiscasset Rd",
    "sg:city":"Bethesda",
    "sg:classifiers":[
        {
            "category":"Real Estate",
            "subcategory":"Architect",
            "type":"Services"
        }
    ],
    "sg:phone":"+1 301 320 1580",
    "sg:postcode":"20816",
    "sg:province":"MD",
    "wof:name":"Treseder Paul Aia Architect",
    "wof:placetype":"venue"
},
  "geometry": {"coordinates":[-77.12930299999999,38.967098],"type":"Point"}
}