{
  "type": "Feature",
  "properties": {
    "addr:full":"602 Crystal Ave Denton MD 21629",
    "addr:housenumber":"602",
    "addr:postcode":"21629",
    "addr:street":"Crystal Ave",
    "iso:country":"US",
    "sg:address":"602 Crystal Ave",
    "sg:city":"Denton",
    "sg:classifiers":[
        {
            "category":"Building & Trades",
            "subcategory":"Plumbing",
            "type":"Services"
        }
    ],
    "sg:phone":"+1 410 479 1155",
    "sg:postcode":"21629",
    "sg:province":"MD",
    "sg:tags":[
        "plumbing",
        "contractor"
    ],
    "wof:name":"Lenco Plumbing & Heating",
    "wof:placetype":"venue"
},
  "geometry": {"coordinates":[-75.824828,38.887927],"type":"Point"}
}