{
  "type": "Feature",
  "properties": {
    "addr:full":"1986 Arwell Ct Severn MD 21144",
    "addr:housenumber":"1986",
    "addr:postcode":"21144",
    "addr:street":"Arwell Ct",
    "iso:country":"US",
    "sg:address":"1986 Arwell Ct",
    "sg:city":"Severn",
    "sg:classifiers":[
        {
            "category":"Real Estate",
            "subcategory":"Real Estate Agent",
            "type":"Services"
        }
    ],
    "sg:phone":"+1 410 519 4612",
    "sg:postcode":"21144",
    "sg:province":"MD",
    "wof:name":"Rimco Properties Group Inc",
    "wof:placetype":"venue"
},
  "geometry": {"coordinates":[-76.704021,39.117963],"type":"Point"}
}