{
  "type": "Feature",
  "properties": {
    "addr:full":"12618 Dover Rd Reisterstown MD 21136",
    "addr:housenumber":"12618",
    "addr:postcode":"21136",
    "addr:street":"Dover Rd",
    "iso:country":"US",
    "sg:address":"12618 Dover Rd",
    "sg:city":"Reisterstown",
    "sg:classifiers":[
        {
            "category":"Health Services",
            "subcategory":"Doctor",
            "type":"Services"
        }
    ],
    "sg:phone":"+1 410 561 7270",
    "sg:postcode":"21136",
    "sg:province":"MD",
    "sg:tags":[
        "surgeon",
        "oral"
    ],
    "wof:name":"Marcus Robert M DDS",
    "wof:placetype":"venue"
},
  "geometry": {"coordinates":[-76.733704,39.472099],"type":"Point"}
}