{
  "type": "Feature",
  "properties": {
    "iso:country":"US",
    "sg:address":"291 Locust Ave",
    "sg:city":"Annapolis",
    "sg:classifiers":[
        {
            "category":"Education",
            "subcategory":"School",
            "type":"Public Place"
        }
    ],
    "sg:phone":"+1 410 222 1650",
    "sg:postcode":"21401",
    "sg:province":"MD",
    "sg:website":"http://www.arundelhigh.org",
    "wof:name":"Phoenix Annapolis",
    "wof:placetype":"venue"
},
  "geometry": {"coordinates":[-76.512287,38.981789],"type":"Point"}
}