{
  "type": "Feature",
  "properties": {
    "iso:country":"US",
    "sg:address":"14500 Keeneland Cir",
    "sg:city":"Gaithersburg",
    "sg:classifiers":[
        {
            "category":"Shopping",
            "subcategory":"Used Merchandise",
            "type":"Retail Goods"
        }
    ],
    "sg:phone":"+1 301 926 2095",
    "sg:postcode":"20878",
    "sg:province":"MD",
    "wof:name":"Book Crypt",
    "wof:placetype":"venue"
},
  "geometry": {"coordinates":[-77.253799,39.095012],"type":"Point"}
}