{
  "type": "Feature",
  "properties": {
    "addr:full":"2030 Sue Creek Dr Baltimore MD 21221",
    "addr:housenumber":"2030",
    "addr:postcode":"21221",
    "addr:street":"Sue Creek Dr",
    "iso:country":"US",
    "sg:address":"2030 Sue Creek Dr",
    "sg:city":"Baltimore",
    "sg:classifiers":[
        {
            "category":"Banks & Credit Unions",
            "subcategory":"Investment Brokerage",
            "type":"Services"
        }
    ],
    "sg:phone":"+1 410 583 7705",
    "sg:postcode":"21221",
    "sg:province":"MD",
    "sg:tags":[
        "advisory",
        "financial"
    ],
    "wof:name":"Oneder LLC",
    "wof:placetype":"venue"
},
  "geometry": {"coordinates":[-76.416258,39.293344],"type":"Point"}
}