{
  "type": "Feature",
  "properties": {
    "iso:country":"US",
    "sg:address":"32 Solitaire Ct",
    "sg:city":"Gaithersburg",
    "sg:classifiers":[
        {
            "category":"Banks & Credit Unions",
            "subcategory":"Bank",
            "type":"Services"
        }
    ],
    "sg:phone":"+1 301 258 4500",
    "sg:postcode":"20878",
    "sg:province":"MD",
    "sg:tags":[
        "loan",
        "real estate"
    ],
    "wof:name":"Mortgage America-Gaithersburg",
    "wof:placetype":"venue"
},
  "geometry": {"coordinates":[-77.23204,39.135601],"type":"Point"}
}