{
  "type": "Feature",
  "properties": {
    "addr:full":"21415 Queens Point Rd SW Mccoole MD 21562",
    "addr:housenumber":"21415",
    "addr:postcode":"21562",
    "addr:street":"Queens Point Rd Sw",
    "iso:country":"US",
    "sg:address":"21415 Queens Point Rd SW",
    "sg:city":"Mccoole",
    "sg:classifiers":[
        {
            "category":"Restaurant",
            "type":"Food & Drink"
        }
    ],
    "sg:phone":"+1 301 786 4515",
    "sg:postcode":"21562",
    "sg:province":"MD",
    "sg:tags":[
        "drinking",
        "eating"
    ],
    "wof:name":"Hamburger Haven Inc",
    "wof:placetype":"venue"
},
  "geometry": {"coordinates":[-78.97289499999999,39.446898],"type":"Point"}
}