{
  "type": "Feature",
  "properties": {
    "addr:full":"12442 Owings Mills Blvd Reisterstown MD 21117",
    "addr:housenumber":"12442",
    "addr:postcode":"21117",
    "addr:street":"Owings Mills Blvd",
    "iso:country":"US",
    "sg:address":"12442 Owings Mills Blvd",
    "sg:city":"Reisterstown",
    "sg:classifiers":[
        {
            "category":"Building & Trades",
            "subcategory":"Electrical",
            "type":"Services"
        }
    ],
    "sg:phone":"+1 410 517 0600",
    "sg:postcode":"21117",
    "sg:province":"MD",
    "sg:tags":[
        "electric",
        "contractor"
    ],
    "wof:name":"Porter Electric Svc Inc",
    "wof:placetype":"venue"
},
  "geometry": {"coordinates":[-76.805458,39.464439],"type":"Point"}
}