{
  "type": "Feature",
  "properties": {
    "iso:country":"US",
    "sg:address":"13623 Annapolis Rd",
    "sg:city":"Bowie",
    "sg:classifiers":[
        {
            "category":"Professional",
            "subcategory":"Management & Consulting",
            "type":"Services"
        }
    ],
    "sg:phone":"+1 301 809 0588",
    "sg:postcode":"20720",
    "sg:province":"MD",
    "sg:tags":[
        "consultant"
    ],
    "wof:name":"RJE Telecom",
    "wof:placetype":"venue"
},
  "geometry": {"coordinates":[-76.769123,38.971429],"type":"Point"}
}