{
  "type": "Feature",
  "properties": {
    "iso:country":"US",
    "sg:address":"3700 Otis St",
    "sg:city":"Mt Rainier",
    "sg:classifiers":[
        {
            "category":"Building & Trades",
            "subcategory":"Construction",
            "type":"Services"
        }
    ],
    "sg:phone":"+1 301 277 0771",
    "sg:postcode":"20712",
    "sg:province":"MD",
    "sg:tags":[
        "maker",
        "cabinet"
    ],
    "wof:name":"N L Woodworking Co",
    "wof:placetype":"venue"
},
  "geometry": {"coordinates":[-76.95709,38.934585],"type":"Point"}
}