{
  "type": "Feature",
  "properties": {
    "addr:full":"7223 15th Ave Takoma Park MD 20912",
    "addr:housenumber":"7223",
    "addr:postcode":"20912",
    "addr:street":"15Th Ave",
    "iso:country":"US",
    "sg:address":"7223 15th Ave",
    "sg:city":"Takoma Park",
    "sg:classifiers":[
        {
            "category":"Professional",
            "subcategory":"Business Services",
            "type":"Services"
        }
    ],
    "sg:phone":"+1 301 704 1853",
    "sg:postcode":"20912",
    "sg:province":"MD",
    "sg:tags":[
        "consulting"
    ],
    "wof:name":"Beckham Consulting Svcs LLC",
    "wof:placetype":"venue"
},
  "geometry": {"coordinates":[-76.985676,38.980943],"type":"Point"}
}