{
  "type": "Feature",
  "properties": {
    "iso:country":"US",
    "sg:address":"1813 Rocky Glen Dr",
    "sg:city":"Frederick",
    "sg:classifiers":[
        {
            "category":"Professional",
            "subcategory":"Computer Services",
            "type":"Services"
        }
    ],
    "sg:phone":"+1 301 682 7797",
    "sg:postcode":"21702",
    "sg:province":"MD",
    "sg:tags":[
        "datum"
    ],
    "wof:name":"Kenneth J Morrill",
    "wof:placetype":"venue"
},
  "geometry": {"coordinates":[-77.410255,39.452564],"type":"Point"}
}