{
  "type": "Feature",
  "properties": {
    "addr:full":"2100 Rosemont Ave Frederick MD 21702",
    "addr:housenumber":"2100",
    "addr:postcode":"21702",
    "addr:street":"Rosemont Ave",
    "iso:country":"US",
    "sg:address":"2100 Rosemont Ave",
    "sg:city":"Frederick",
    "sg:classifiers":[
        {
            "category":"Organizations",
            "subcategory":"Religious Organization",
            "type":"Services"
        }
    ],
    "sg:phone":"+1 301 663 1240",
    "sg:postcode":"21702",
    "sg:province":"MD",
    "sg:tags":[
        "church"
    ],
    "wof:name":"Grace Community Christian Chr",
    "wof:placetype":"venue"
},
  "geometry": {"coordinates":[-77.437378,39.437272],"type":"Point"}
}