{
  "type": "Feature",
  "properties": {
    "addr:full":"11000 Nicholas Dr Silver Spring MD 20902",
    "addr:housenumber":"11000",
    "addr:postcode":"20902",
    "addr:street":"Nicholas Dr",
    "iso:country":"US",
    "sg:address":"11000 Nicholas Dr",
    "sg:city":"Silver Spring",
    "sg:classifiers":[
        {
            "category":"Professional",
            "subcategory":"Management & Consulting",
            "type":"Services"
        }
    ],
    "sg:phone":"+1 301 649 3600",
    "sg:postcode":"20902",
    "sg:province":"MD",
    "sg:tags":[
        "business"
    ],
    "wof:name":"Hdl Consulting Group",
    "wof:placetype":"venue"
},
  "geometry": {"coordinates":[-77.038414,39.037307],"type":"Point"}
}