{
  "type": "Feature",
  "properties": {
    "iso:country":"US",
    "sg:address":"7050 Carroll Ave",
    "sg:city":"Takoma Park",
    "sg:classifiers":[
        {
            "category":"Professional",
            "subcategory":"Research",
            "type":"Services"
        }
    ],
    "sg:phone":"+1 301 270 0522",
    "sg:postcode":"20912",
    "sg:province":"MD",
    "sg:tags":[
        "assistance",
        "program",
        "technology"
    ],
    "wof:name":"Unified Technologies Inc",
    "wof:placetype":"venue"
},
  "geometry": {"coordinates":[-77.011122,38.975128],"type":"Point"}
}