{
  "type": "Feature",
  "properties": {
    "iso:country":"US",
    "sg:address":"6 E Padonia Rd",
    "sg:city":"Lutherville Timonium",
    "sg:classifiers":[
        {
            "category":"Autos & Motor Vehicles",
            "subcategory":"Auto Supplies",
            "type":"Retail Goods"
        },
        {
            "category":"Retail",
            "subcategory":"Auto Repair",
            "type":"Services"
        }
    ],
    "sg:phone":"+1 410 252 8440",
    "sg:postcode":"21093",
    "sg:province":"MD",
    "sg:tags":[
        "tire"
    ],
    "sg:website":"www.brookshuff.com",
    "wof:name":"Brooks-Huff Tire & Auto Centers",
    "wof:placetype":"venue"
},
  "geometry": {"coordinates":[-76.631699,39.456299],"type":"Point"}
}