{
  "type": "Feature",
  "properties": {
    "iso:country":"US",
    "sg:address":"6325 Erdman Ave",
    "sg:city":"Baltimore",
    "sg:classifiers":[
        {
            "category":"Wholesale",
            "subcategory":"Books, Periodicals, & Newspapers",
            "type":"Manufacturing & Wholesale Goods"
        }
    ],
    "sg:phone":"+1 410 488 8898",
    "sg:postcode":"21205",
    "sg:province":"MD",
    "sg:tags":[
        "magazine"
    ],
    "wof:name":"Ryan East LTD",
    "wof:placetype":"venue"
},
  "geometry": {"coordinates":[-76.54195900000001,39.301934],"type":"Point"}
}