{
  "type": "Feature",
  "properties": {
    "addr:full":"8 Carvel Cir Edgewater MD 21037",
    "addr:housenumber":"8",
    "addr:postcode":"21037",
    "addr:street":"Carvel Cir",
    "iso:country":"US",
    "sg:address":"8 Carvel Cir",
    "sg:city":"Edgewater",
    "sg:classifiers":[
        {
            "category":"Organizations",
            "subcategory":"Religious Organization",
            "type":"Services"
        }
    ],
    "sg:phone":"+1 410 571 9344",
    "sg:postcode":"21037",
    "sg:province":"MD",
    "wof:name":"Iglesia Evangelice Apostoles",
    "wof:placetype":"venue"
},
  "geometry": {"coordinates":[-76.540402,38.968063],"type":"Point"}
}