{
  "type": "Feature",
  "properties": {
    "addr:full":"2200 Broening Hwy Ste 125 Baltimore MD 21224",
    "addr:housenumber":"2200",
    "addr:postcode":"21224",
    "addr:street":"Broening Hwy Ste 125",
    "iso:country":"US",
    "sg:address":"2200 Broening Hwy Ste 125",
    "sg:city":"Baltimore",
    "sg:classifiers":[
        {
            "category":"Government",
            "subcategory":"Embassy",
            "type":"Public Place"
        }
    ],
    "sg:phone":"+1 410 631 0043",
    "sg:postcode":"21224",
    "sg:province":"MD",
    "sg:tags":[
        "representative",
        "consulate",
        "foreign"
    ],
    "sg:website":"http://www.state.gov",
    "wof:name":"Office Supply And Trnsp",
    "wof:placetype":"venue"
},
  "geometry": {"coordinates":[-76.543037,39.265041],"type":"Point"}
}