{
  "type": "Feature",
  "properties": {
    "iso:country":"US",
    "sg:address":"5609 Fishers Ln",
    "sg:city":"Rockville",
    "sg:classifiers":[
        {
            "category":"Freight",
            "type":"Transportation"
        }
    ],
    "sg:phone":"+1 301 770 0745",
    "sg:postcode":"20852",
    "sg:province":"MD",
    "sg:tags":[
        "warehouse"
    ],
    "wof:name":"Marriott Warehouse",
    "wof:placetype":"venue"
},
  "geometry": {"coordinates":[-77.114007,39.062871],"type":"Point"}
}