{
  "type": "Feature",
  "properties": {
    "iso:country":"US",
    "sg:address":"25314 Saint Michaels Rd",
    "sg:city":"St Michaels",
    "sg:classifiers":[
        {
            "category":"Banks & Credit Unions",
            "subcategory":"Investment Brokerage",
            "type":"Services"
        }
    ],
    "sg:phone":"+1 410 745 0488",
    "sg:postcode":"21663",
    "sg:province":"MD",
    "sg:tags":[
        "advisory",
        "financial"
    ],
    "wof:name":"Bulli Farm Investments LLC",
    "wof:placetype":"venue"
},
  "geometry": {"coordinates":[-76.19377,38.760914],"type":"Point"}
}