{
  "type": "Feature",
  "properties": {
    "iso:country":"US",
    "sg:address":"1131 Benfield Blvd",
    "sg:city":"Millersville",
    "sg:classifiers":[
        {
            "category":"Banks & Credit Unions",
            "subcategory":"Bank",
            "type":"Services"
        }
    ],
    "sg:phone":"+1 410 729 2700",
    "sg:postcode":"21108",
    "sg:province":"MD",
    "sg:tags":[
        "loan",
        "real estate"
    ],
    "wof:name":"HOMEFUNDING.COM",
    "wof:placetype":"venue"
},
  "geometry": {"coordinates":[-76.63224200000001,39.094294],"type":"Point"}
}