{
  "type": "Feature",
  "properties": {
    "iso:country":"US",
    "sg:address":"304 N Talbot St",
    "sg:city":"Saint Michaels",
    "sg:classifiers":[
        {
            "category":"Manufacturing",
            "subcategory":"Printing",
            "type":"Manufacturing & Wholesale Goods"
        }
    ],
    "sg:phone":"+1 410 745 3200",
    "sg:postcode":"21663",
    "sg:province":"MD",
    "sg:tags":[
        "offset"
    ],
    "wof:name":"Poore House Inc",
    "wof:placetype":"venue"
},
  "geometry": {"coordinates":[-76.225281,38.788405],"type":"Point"}
}