{
  "type": "Feature",
  "properties": {
    "addr:full":"10401 Old Georgetown Rd Bethesda MD 20814",
    "addr:housenumber":"10401",
    "addr:postcode":"20814",
    "addr:street":"Old Georgetown Rd",
    "iso:country":"US",
    "sg:address":"10401 Old Georgetown Rd",
    "sg:city":"Bethesda",
    "sg:classifiers":[
        {
            "category":"Health Services",
            "subcategory":"Clinic",
            "type":"Services"
        }
    ],
    "sg:phone":"+1 301 622 2237",
    "sg:postcode":"20814",
    "sg:province":"MD",
    "sg:tags":[
        "counseling",
        "mental"
    ],
    "sg:website":"positiveenergytrans.info/",
    "wof:name":"Positive Energy Transformations",
    "wof:placetype":"venue"
},
  "geometry": {"coordinates":[-77.125311,39.026502],"type":"Point"}
}