{
  "type": "Feature",
  "properties": {
    "addr:full":"7610 Old Georgetown Rd Bethesda MD 20814",
    "addr:housenumber":"7610",
    "addr:postcode":"20814",
    "addr:street":"Old Georgetown Rd",
    "iso:country":"US",
    "sg:address":"7610 Old Georgetown Rd",
    "sg:city":"Bethesda",
    "sg:classifiers":[
        {
            "category":"Real Estate",
            "subcategory":"Real Estate Agent",
            "type":"Services"
        }
    ],
    "sg:phone":"+1 301 652 9020",
    "sg:postcode":"20814",
    "sg:province":"MD",
    "sg:website":"www.streetsense.com",
    "wof:name":"Streetsense",
    "wof:placetype":"venue"
},
  "geometry": {"coordinates":[-77.09626,38.985789],"type":"Point"}
}