{
  "type": "Feature",
  "properties": {
    "iso:country":"US",
    "sg:address":"5430 Lynx Ln",
    "sg:city":"Columbia",
    "sg:classifiers":[
        {
            "category":"Manufacturing",
            "subcategory":"Printing",
            "type":"Manufacturing & Wholesale Goods"
        }
    ],
    "sg:phone":"+1 410 964 8433",
    "sg:postcode":"21044",
    "sg:province":"MD",
    "sg:tags":[
        "environmental",
        "consulting",
        "industrial",
        "safety",
        "publishing"
    ],
    "wof:name":"Snowy Owl LLC",
    "wof:placetype":"venue"
},
  "geometry": {"coordinates":[-76.874727,39.221213],"type":"Point"}
}