{
  "type": "Feature",
  "properties": {
    "addr:full":"8027 Snouffers School Rd Gaithersburg MD 20879",
    "addr:housenumber":"8027",
    "addr:postcode":"20879",
    "addr:street":"Snouffers School Rd",
    "iso:country":"US",
    "sg:address":"8027 Snouffers School Rd",
    "sg:city":"Gaithersburg",
    "sg:classifiers":[
        {
            "category":"Retail",
            "subcategory":"Auto Repair",
            "type":"Services"
        }
    ],
    "sg:phone":"+1 301 948 3074",
    "sg:postcode":"20879",
    "sg:province":"MD",
    "sg:tags":[
        "muffler",
        "exhaust",
        "system"
    ],
    "wof:name":"Meineke Car Care Ctr",
    "wof:placetype":"venue"
},
  "geometry": {"coordinates":[-77.160554,39.159226],"type":"Point"}
}