{
  "type": "Feature",
  "properties": {
    "addr:full":"3380 Fort Meade Rd Laurel MD 20724",
    "addr:housenumber":"3380",
    "addr:postcode":"20724",
    "addr:street":"Fort Meade Rd",
    "iso:country":"US",
    "sg:address":"3380 Fort Meade Rd",
    "sg:city":"Laurel",
    "sg:classifiers":[
        {
            "category":"Travel",
            "subcategory":"Hotels & Motels",
            "type":"Entertainment"
        }
    ],
    "sg:phone":"+1 301 498 5553",
    "sg:postcode":"20724",
    "sg:province":"MD",
    "sg:website":"www.knightsinn.com",
    "wof:name":"Knights Inn",
    "wof:placetype":"venue"
},
  "geometry": {"coordinates":[-76.809296,39.098843],"type":"Point"}
}