{
  "type": "Feature",
  "properties": {
    "addr:full":"5336 46th Ave Hyattsville MD 20781",
    "addr:housenumber":"5336",
    "addr:postcode":"20781",
    "addr:street":"46Th Ave",
    "iso:country":"US",
    "sg:address":"5336 46th Ave",
    "sg:city":"Hyattsville",
    "sg:classifiers":[
        {
            "category":"Professional",
            "subcategory":"Lawyer & Legal Services",
            "type":"Services"
        },
        {
            "category":"Building & Trades",
            "subcategory":"Construction",
            "type":"Services"
        }
    ],
    "sg:phone":"+1 301 403 0436",
    "sg:postcode":"20781",
    "sg:province":"MD",
    "sg:tags":[
        "notary",
        "contractor"
    ],
    "wof:name":"Des Build Inc",
    "wof:placetype":"venue"
},
  "geometry": {"coordinates":[-76.937445,38.95504],"type":"Point"}
}