{
  "type": "Feature",
  "properties": {
    "iso:country":"US",
    "sg:address":"11501 Huff Ct Ste B",
    "sg:city":"Kensington",
    "sg:classifiers":[
        {
            "category":"Real Estate",
            "subcategory":"Real Estate Services",
            "type":"Services"
        }
    ],
    "sg:phone":"+1 301 984 1500",
    "sg:postcode":"20895",
    "sg:province":"MD",
    "sg:tags":[
        "management",
        "property"
    ],
    "wof:name":"Lerner Corporation",
    "wof:placetype":"venue"
},
  "geometry": {"coordinates":[-77.1091,39.043201],"type":"Point"}
}