{
  "type": "Feature",
  "properties": {
    "addr:full":"678 Reisterstown Rd Pikesville MD 21208",
    "addr:housenumber":"678",
    "addr:postcode":"21208",
    "addr:street":"Reisterstown Rd",
    "iso:country":"US",
    "sg:address":"678 Reisterstown Rd",
    "sg:city":"Pikesville",
    "sg:classifiers":[
        {
            "category":"Personal",
            "subcategory":"Beauty Salon",
            "type":"Services"
        }
    ],
    "sg:phone":"+1 410 484 2237",
    "sg:postcode":"21208",
    "sg:province":"MD",
    "wof:name":"Vin Dye Hair Expressions",
    "wof:placetype":"venue"
},
  "geometry": {"coordinates":[-76.719274,39.370295],"type":"Point"}
}