{
  "type": "Feature",
  "properties": {
    "iso:country":"US",
    "sg:address":"251 Bayview Blvd Ste 200",
    "sg:city":"Baltimore",
    "sg:classifiers":[
        {
            "category":"Professional",
            "subcategory":"Research",
            "type":"Services"
        }
    ],
    "sg:phone":"+1 443 740 2504",
    "sg:postcode":"21224",
    "sg:province":"MD",
    "sg:tags":[
        "educational"
    ],
    "wof:name":"Guohua Bi Dr",
    "wof:placetype":"venue"
},
  "geometry": {"coordinates":[-76.549227,39.289188],"type":"Point"}
}