{
  "type": "Feature",
  "properties": {
    "iso:country":"US",
    "sg:address":"300 Main St",
    "sg:city":"Prince Frederick",
    "sg:classifiers":[
        {
            "category":"Organizations",
            "subcategory":"Non-profit Organization",
            "type":"Services"
        }
    ],
    "sg:phone":"+1 410 257 0003",
    "sg:postcode":"20678",
    "sg:province":"MD",
    "sg:tags":[
        "human"
    ],
    "wof:name":"Project Echo",
    "wof:placetype":"venue"
},
  "geometry": {"coordinates":[-76.582089,38.538297],"type":"Point"}
}