{
  "type": "Feature",
  "properties": {
    "iso:country":"US",
    "sg:address":"15920 Shady Grove Rd",
    "sg:city":"Gaithersburg",
    "sg:classifiers":[
        {
            "category":"Personal",
            "subcategory":"Beauty Salon",
            "type":"Services"
        }
    ],
    "sg:phone":"+1 301 948 2990",
    "sg:postcode":"20877",
    "sg:province":"MD",
    "sg:tags":[
        "hair",
        "stylist"
    ],
    "wof:name":"Innovations Hair Designers",
    "wof:placetype":"venue"
},
  "geometry": {"coordinates":[-77.18450900000001,39.11634],"type":"Point"}
}