{
  "type": "Feature",
  "properties": {
    "iso:country":"US",
    "sg:address":"1907 South Rd",
    "sg:city":"Baltimore",
    "sg:classifiers":[
        {
            "category":"Health Services",
            "subcategory":"Doctor",
            "type":"Services"
        }
    ],
    "sg:phone":"+1 410 466 0285",
    "sg:postcode":"21209",
    "sg:province":"MD",
    "wof:name":"Finkelstein Daniel MD",
    "wof:placetype":"venue"
},
  "geometry": {"coordinates":[-76.657898,39.363602],"type":"Point"}
}