{
  "type": "Feature",
  "properties": {
    "addr:full":"38 Acorn Cir Towson MD 21286",
    "addr:housenumber":"38",
    "addr:postcode":"21286",
    "addr:street":"Acorn Cir",
    "iso:country":"US",
    "sg:address":"38 Acorn Cir",
    "sg:city":"Towson",
    "sg:classifiers":[
        {
            "category":"Retail",
            "subcategory":"Portrait Studio",
            "type":"Services"
        }
    ],
    "sg:phone":"+1 410 825 2107",
    "sg:postcode":"21286",
    "sg:province":"MD",
    "sg:tags":[
        "photography"
    ],
    "wof:name":"Tony R Mumpower Photography",
    "wof:placetype":"venue"
},
  "geometry": {"coordinates":[-76.586945,39.39403],"type":"Point"}
}