{
  "type": "Feature",
  "properties": {
    "addr:full":"210 E Lexington St Baltimore MD 21202",
    "addr:housenumber":"210",
    "addr:postcode":"21202",
    "addr:street":"E Lexington St",
    "iso:country":"US",
    "sg:address":"210 E Lexington St",
    "sg:city":"Baltimore",
    "sg:classifiers":[
        {
            "category":"Professional",
            "subcategory":"Lawyer & Legal Services",
            "type":"Services"
        }
    ],
    "sg:phone":"+1 410 727 8177",
    "sg:postcode":"21202",
    "sg:province":"MD",
    "sg:tags":[
        "attorney"
    ],
    "sg:website":"www.suderlaw.com",
    "wof:name":"Suder Law Firm",
    "wof:placetype":"venue"
},
  "geometry": {"coordinates":[-76.61114499999999,39.291319],"type":"Point"}
}