{
  "type": "Feature",
  "properties": {
    "iso:country":"US",
    "sg:address":"1043 Liberty Rd",
    "sg:city":"Eldersburg",
    "sg:classifiers":[
        {
            "category":"Restaurant",
            "type":"Food & Drink"
        }
    ],
    "sg:phone":"+1 410 795 8400",
    "sg:postcode":"21784",
    "sg:province":"MD",
    "wof:name":"Salerno's Pizza & Sub Shop",
    "wof:placetype":"venue"
},
  "geometry": {"coordinates":[-76.95858200000001,39.406057],"type":"Point"}
}