{
  "type": "Feature",
  "properties": {
    "addr:full":"1030 N. Charles St. Suite 302 Baltimore MD 21201",
    "addr:housenumber":"1030",
    "addr:postcode":"21201",
    "addr:street":"N. Charles St. Suite 302",
    "iso:country":"US",
    "sg:address":"1030 N. Charles St. Suite 302",
    "sg:city":"Baltimore",
    "sg:classifiers":[
        {
            "category":"Health Services",
            "subcategory":"Dentist",
            "type":"Services"
        }
    ],
    "sg:phone":"+1 410 685 2850",
    "sg:postcode":"21201",
    "sg:province":"MD",
    "sg:website":"DrMastella.net",
    "wof:name":"Mastella Stephen B",
    "wof:placetype":"venue"
},
  "geometry": {"coordinates":[-76.616197,39.302111],"type":"Point"}
}