{
  "type": "Feature",
  "properties": {
    "iso:country":"US",
    "sg:address":"4000 Knowles Ave",
    "sg:city":"Kensington",
    "sg:classifiers":[
        {
            "category":"Health Services",
            "subcategory":"Dentist",
            "type":"Services"
        }
    ],
    "sg:phone":"+1 301 897 0020",
    "sg:postcode":"20895",
    "sg:province":"MD",
    "wof:name":"Campbell Larry W DDS",
    "wof:placetype":"venue"
},
  "geometry": {"coordinates":[-77.078062,39.027563],"type":"Point"}
}