{
  "type": "Feature",
  "properties": {
    "iso:country":"US",
    "sg:address":"1210 Durham Dr",
    "sg:city":"Bowie",
    "sg:classifiers":[
        {
            "category":"Place Of Worship",
            "subcategory":"Church",
            "type":"Public Place"
        },
        {
            "category":"Place Of Worship",
            "type":"Public Place"
        }
    ],
    "sg:phone":"+1 301 249 4384",
    "sg:postcode":"20721",
    "sg:province":"MD",
    "sg:tags":[
        "churches-baptist-general",
        "churches-baptist"
    ],
    "wof:name":"Zion Baptist Church",
    "wof:placetype":"venue"
},
  "geometry": {"coordinates":[-76.74008600000001,38.906669],"type":"Point"}
}