{
  "type": "Feature",
  "properties": {
    "addr:full":"9 Landings Ct Annapolis MD 21403",
    "addr:housenumber":"9",
    "addr:postcode":"21403",
    "addr:street":"Landings Ct",
    "iso:country":"US",
    "sg:address":"9 Landings Ct",
    "sg:city":"Annapolis",
    "sg:classifiers":[
        {
            "category":"Professional",
            "subcategory":"Management & Consulting",
            "type":"Services"
        }
    ],
    "sg:phone":"+1 410 280 8697",
    "sg:postcode":"21403",
    "sg:province":"MD",
    "sg:tags":[
        "party",
        "planning"
    ],
    "wof:name":"Passion Parties By Kerri",
    "wof:placetype":"venue"
},
  "geometry": {"coordinates":[-76.507452,38.958981],"type":"Point"}
}