{
  "type": "Feature",
  "properties": {
    "iso:country":"US",
    "sg:address":"716 Bestgate Rd",
    "sg:city":"Annapolis",
    "sg:classifiers":[
        {
            "category":"Education",
            "subcategory":"School",
            "type":"Public Place"
        }
    ],
    "sg:phone":"+1 410 266 8251",
    "sg:postcode":"21401",
    "sg:province":"MD",
    "sg:website":"www.aacsonline.org",
    "wof:name":"Annapolis Area Christian Schl",
    "wof:placetype":"venue"
},
  "geometry": {"coordinates":[-76.530764,38.995791],"type":"Point"}
}