{
  "type": "Feature",
  "properties": {
    "iso:country":"US",
    "sg:address":"26 W Main St",
    "sg:city":"New Market",
    "sg:classifiers":[
        {
            "category":"Shopping",
            "subcategory":"Discount & Variety Stores",
            "type":"Retail Goods"
        }
    ],
    "sg:phone":"+1 301 865 6313",
    "sg:postcode":"21774",
    "sg:province":"MD",
    "sg:tags":[
        "merchandise",
        "general"
    ],
    "wof:name":"New Market General Store",
    "wof:placetype":"venue"
},
  "geometry": {"coordinates":[-77.271183,39.382813],"type":"Point"}
}