{
  "type": "Feature",
  "properties": {
    "iso:country":"US",
    "sg:address":"1490 W Patapsco Ave",
    "sg:city":"Baltimore",
    "sg:classifiers":[
        {
            "category":"Food & Beverages",
            "subcategory":"Groceries & Convenience Stores",
            "type":"Retail Goods"
        }
    ],
    "sg:phone":"+1 410 355 1126",
    "sg:postcode":"21230",
    "sg:province":"MD",
    "wof:name":"Cinco De Mayo Spanish Market",
    "wof:placetype":"venue"
},
  "geometry": {"coordinates":[-76.639004,39.248671],"type":"Point"}
}