{
  "type": "Feature",
  "properties": {
    "addr:full":"3505 Silver Park Dr Suitland MD 20746",
    "addr:housenumber":"3505",
    "addr:postcode":"20746",
    "addr:street":"Silver Park Dr",
    "iso:country":"US",
    "sg:address":"3505 Silver Park Dr",
    "sg:city":"Suitland",
    "sg:classifiers":[
        {
            "category":"Professional",
            "subcategory":"Art Services",
            "type":"Services"
        }
    ],
    "sg:phone":"+1 301 899 1968",
    "sg:postcode":"20746",
    "sg:province":"MD",
    "sg:tags":[
        "antique",
        "repair",
        "restoration"
    ],
    "wof:name":"D.J. Liability",
    "wof:placetype":"venue"
},
  "geometry": {"coordinates":[-76.93720999999999,38.841047],"type":"Point"}
}