{
  "type": "Feature",
  "properties": {
    "addr:full":"108 Commerce St Cambridge MD 21613",
    "addr:housenumber":"108",
    "addr:postcode":"21613",
    "addr:street":"Commerce St",
    "iso:country":"US",
    "sg:address":"108 Commerce St",
    "sg:city":"Cambridge",
    "sg:classifiers":[
        {
            "category":"Manufacturing",
            "subcategory":"Food",
            "type":"Manufacturing & Wholesale Goods"
        }
    ],
    "sg:phone":"+1 410 228 1661",
    "sg:postcode":"21613",
    "sg:province":"MD",
    "sg:tags":[
        "seafood",
        "product",
        "fish",
        "prepared"
    ],
    "sg:website":"www.jmclayton.com",
    "wof:name":"J M Clayton Co",
    "wof:placetype":"venue"
},
  "geometry": {"coordinates":[-76.073638,38.573667],"type":"Point"}
}