{
  "type": "Feature",
  "properties": {
    "addr:full":"3214 Hollins Ferry Rd Halethorpe MD 21227",
    "addr:housenumber":"3214",
    "addr:postcode":"21227",
    "addr:street":"Hollins Ferry Rd",
    "iso:country":"US",
    "sg:address":"3214 Hollins Ferry Rd",
    "sg:city":"Halethorpe",
    "sg:classifiers":[
        {
            "category":"Food & Beverages",
            "subcategory":"Liquor & Beverages",
            "type":"Retail Goods"
        }
    ],
    "sg:phone":"+1 410 644 6833",
    "sg:postcode":"21227",
    "sg:province":"MD",
    "sg:tags":[
        "beer",
        "spirit",
        "wine"
    ],
    "wof:name":"Slims Liquor Store",
    "wof:placetype":"venue"
},
  "geometry": {"coordinates":[-76.647102,39.250999],"type":"Point"}
}