{
  "type": "Feature",
  "properties": {
    "addr:full":"6103 Baltimore Ave Riverdale MD 20737",
    "addr:housenumber":"6103",
    "addr:postcode":"20737",
    "addr:street":"Baltimore Ave",
    "iso:country":"US",
    "sg:address":"6103 Baltimore Ave",
    "sg:city":"Riverdale",
    "sg:classifiers":[
        {
            "category":"Professional",
            "subcategory":"Accounting & Tax Preparation",
            "type":"Services"
        }
    ],
    "sg:phone":"+1 301 927 9335",
    "sg:postcode":"20737",
    "sg:province":"MD",
    "sg:tags":[
        "accountant"
    ],
    "sg:website":"www.samuwanducpa.com",
    "wof:name":"Sam Uwandu & Assoc",
    "wof:placetype":"venue"
},
  "geometry": {"coordinates":[-76.939384,38.961578],"type":"Point"}
}