{
  "type": "Feature",
  "properties": {
    "iso:country":"US",
    "sg:address":"2201 Tacoma Street",
    "sg:city":"Baltimore",
    "sg:classifiers":[
        {
            "category":"Manufacturing",
            "subcategory":"Tools & Machinery",
            "type":"Manufacturing & Wholesale Goods"
        }
    ],
    "sg:phone":"+1 443 413 2842",
    "sg:postcode":"21230",
    "sg:province":"MD",
    "sg:tags":[
        "millwright"
    ],
    "wof:name":"All Door Specialists",
    "wof:placetype":"venue"
},
  "geometry": {"coordinates":[-76.633904,39.264751],"type":"Point"}
}