{
  "type": "Feature",
  "properties": {
    "addr:full":"3805 Hickory Ave Baltimore MD 21211",
    "addr:housenumber":"3805",
    "addr:postcode":"21211",
    "addr:street":"Hickory Ave",
    "iso:country":"US",
    "sg:address":"3805 Hickory Ave",
    "sg:city":"Baltimore",
    "sg:classifiers":[
        {
            "category":"Building & Trades",
            "subcategory":"Cleaning & Sanitation",
            "type":"Services"
        }
    ],
    "sg:phone":"+1 410 467 1009",
    "sg:postcode":"21211",
    "sg:province":"MD",
    "sg:tags":[
        "window"
    ],
    "wof:name":"Admiral Services Inc",
    "wof:placetype":"venue"
},
  "geometry": {"coordinates":[-76.634666,39.334164],"type":"Point"}
}