{
  "type": "Feature",
  "properties": {
    "iso:country":"US",
    "sg:address":"14875 London Ln",
    "sg:city":"Bowie",
    "sg:classifiers":[
        {
            "category":"Professional",
            "type":"Services"
        }
    ],
    "sg:phone":"+1 301 464 9710",
    "sg:postcode":"20715",
    "sg:province":"MD",
    "sg:tags":[
        "establishment"
    ],
    "wof:name":"Princeton Square Homeowners",
    "wof:placetype":"venue"
},
  "geometry": {"coordinates":[-76.749619,38.955097],"type":"Point"}
}