{
  "type": "Feature",
  "properties": {
    "addr:full":"2411 Crofton Ln Crofton MD 21114",
    "addr:housenumber":"2411",
    "addr:postcode":"21114",
    "addr:street":"Crofton Ln",
    "iso:country":"US",
    "sg:address":"2411 Crofton Ln",
    "sg:city":"Crofton",
    "sg:classifiers":[
        {
            "category":"Insurance",
            "subcategory":"Insurance Agent",
            "type":"Services"
        }
    ],
    "sg:phone":"+1 410 721 4908",
    "sg:postcode":"21114",
    "sg:province":"MD",
    "wof:name":"Allstate Insurance",
    "wof:placetype":"venue"
},
  "geometry": {"coordinates":[-76.698592,39.013883],"type":"Point"}
}