{
  "type": "Feature",
  "properties": {
    "iso:country":"US",
    "sg:address":"7417 Livingston Rd",
    "sg:city":"Oxon Hill",
    "sg:classifiers":[
        {
            "category":"Retail",
            "subcategory":"Auto Repair",
            "type":"Services"
        }
    ],
    "sg:phone":"+1 301 567 6200",
    "sg:postcode":"20745",
    "sg:province":"MD",
    "sg:tags":[
        "repairing",
        "automobile"
    ],
    "wof:name":"Powell's Automotive Ctr",
    "wof:placetype":"venue"
},
  "geometry": {"coordinates":[-76.99022100000001,38.787285],"type":"Point"}
}