{
  "type": "Feature",
  "properties": {
    "iso:country":"US",
    "sg:address":"2381 Lewis Ave",
    "sg:city":"Rockville",
    "sg:classifiers":[
        {
            "category":"Professional",
            "type":"Services"
        }
    ],
    "sg:phone":"+1 301 816 9300",
    "sg:postcode":"20851",
    "sg:province":"MD",
    "sg:tags":[
        "establishment"
    ],
    "wof:name":"Pangea",
    "wof:placetype":"venue"
},
  "geometry": {"coordinates":[-77.121154,39.063872],"type":"Point"}
}