{
  "type": "Feature",
  "properties": {
    "addr:full":"9652 Muirkirk Rd Laurel MD 20708",
    "addr:housenumber":"9652",
    "addr:postcode":"20708",
    "addr:street":"Muirkirk Rd",
    "iso:country":"US",
    "sg:address":"9652 Muirkirk Rd",
    "sg:city":"Laurel",
    "sg:classifiers":[
        {
            "category":"Arts & Performance",
            "subcategory":"Art Gallery",
            "type":"Entertainment"
        }
    ],
    "sg:phone":"+1 301 377 7800",
    "sg:postcode":"20708",
    "sg:province":"MD",
    "sg:website":"www.pgparks.com",
    "wof:name":"Montpelier Arts Center",
    "wof:placetype":"venue"
},
  "geometry": {"coordinates":[-76.84184399999999,39.063147],"type":"Point"}
}