{
  "type": "Feature",
  "properties": {
    "addr:full":"9400 Coastal Hwy Ocean City MD 21842",
    "addr:housenumber":"9400",
    "addr:postcode":"21842",
    "addr:street":"Coastal Hwy",
    "iso:country":"US",
    "sg:address":"9400 Coastal Hwy",
    "sg:city":"Ocean City",
    "sg:classifiers":[
        {
            "category":"Real Estate",
            "subcategory":"Real Estate Operator",
            "type":"Services"
        }
    ],
    "sg:phone":"+1 410 524 9400",
    "sg:postcode":"21842",
    "sg:province":"MD",
    "sg:tags":[
        "condominium"
    ],
    "wof:name":"9400 Condominium Assoc Inc",
    "wof:placetype":"venue"
},
  "geometry": {"coordinates":[-75.058335,38.410627],"type":"Point"}
}