{
  "type": "Feature",
  "properties": {
    "iso:country":"US",
    "sg:address":"2107 Emmorton Park Dr",
    "sg:city":"Edgewood",
    "sg:classifiers":[
        {
            "category":"Building & Trades",
            "subcategory":"Construction",
            "type":"Services"
        }
    ],
    "sg:phone":"+1 410 679 6340",
    "sg:postcode":"21040",
    "sg:province":"MD",
    "sg:tags":[
        "floor",
        "laying",
        "contractor"
    ],
    "wof:name":"Feature Flooring",
    "wof:placetype":"venue"
},
  "geometry": {"coordinates":[-76.308893,39.452229],"type":"Point"}
}