{
  "type": "Feature",
  "properties": {
    "addr:full":"4200 Edmondson Ave 202B Baltimore MD 21229",
    "addr:housenumber":"4200;202b",
    "addr:postcode":"21229",
    "addr:street":"Edmondson Ave",
    "iso:country":"US",
    "sg:address":"4200 Edmondson Ave 202B",
    "sg:city":"Baltimore",
    "sg:classifiers":[
        {
            "category":"Health Services",
            "subcategory":"Health Practitioner",
            "type":"Services"
        }
    ],
    "sg:phone":"+1 410 947 0433",
    "sg:postcode":"21229",
    "sg:province":"MD",
    "sg:tags":[
        "gambling",
        "addiction-information",
        "treatment"
    ],
    "wof:name":"Reflective Image Counseling, Inc",
    "wof:placetype":"venue"
},
  "geometry": {"coordinates":[-76.68594400000001,39.293701],"type":"Point"}
}