{
  "type": "Feature",
  "properties": {
    "addr:full":"2524 E Baltimore St Baltimore MD 21224",
    "addr:housenumber":"2524",
    "addr:postcode":"21224",
    "addr:street":"E Baltimore St",
    "iso:country":"US",
    "sg:address":"2524 E Baltimore St",
    "sg:city":"Baltimore",
    "sg:classifiers":[
        {
            "category":"Health Services",
            "subcategory":"Nursing And Care Facility",
            "type":"Services"
        },
        {
            "category":"Social Services",
            "subcategory":"Adult Care",
            "type":"Services"
        }
    ],
    "sg:phone":"+1 410 342 2257",
    "sg:postcode":"21224",
    "sg:province":"MD",
    "sg:tags":[
        "personal",
        "living",
        "assisted",
        "home",
        "elder"
    ],
    "wof:name":"Andy's Domiciliary Home",
    "wof:placetype":"venue"
},
  "geometry": {"coordinates":[-76.58115599999999,39.292031],"type":"Point"}
}