{
  "type": "Feature",
  "properties": {
    "addr:full":"215 E North Ave Baltimore MD 21202",
    "addr:housenumber":"215",
    "addr:postcode":"21202",
    "addr:street":"E North Ave",
    "iso:country":"US",
    "sg:address":"215 E North Ave",
    "sg:city":"Baltimore",
    "sg:classifiers":[
        {
            "category":"Professional",
            "subcategory":"Advertising",
            "type":"Services"
        }
    ],
    "sg:phone":"+1 410 727 1126",
    "sg:postcode":"21202",
    "sg:province":"MD",
    "sg:tags":[
        "distributing",
        "sample"
    ],
    "wof:name":"Culbreth Advertising Distr",
    "wof:placetype":"venue"
},
  "geometry": {"coordinates":[-76.613798,39.31124],"type":"Point"}
}