{
  "type": "Feature",
  "properties": {
    "addr:full":"222 N Charles St Baltimore MD 21201",
    "addr:housenumber":"222",
    "addr:postcode":"21201",
    "addr:street":"N Charles St",
    "iso:country":"US",
    "sg:address":"222 N Charles St",
    "sg:city":"Baltimore",
    "sg:classifiers":[
        {
            "category":"Restaurant",
            "type":"Food & Drink"
        }
    ],
    "sg:phone":"+1 410 539 2889",
    "sg:postcode":"21201",
    "sg:province":"MD",
    "wof:name":"Kingsway Gourmet Grill",
    "wof:placetype":"venue"
},
  "geometry": {"coordinates":[-76.615196,39.291599],"type":"Point"}
}