{
  "type": "Feature",
  "properties": {
    "iso:country":"US",
    "sg:address":"300 Forelands Rd",
    "sg:city":"Annapolis",
    "sg:classifiers":[
        {
            "category":"Freight",
            "type":"Transportation"
        }
    ],
    "sg:phone":"+1 410 266 3134",
    "sg:postcode":"21401",
    "sg:province":"MD",
    "sg:tags":[
        "operator",
        "local",
        "trucking"
    ],
    "wof:name":"Bw Parkinson Jr Trucking Inc",
    "wof:placetype":"venue"
},
  "geometry": {"coordinates":[-76.5731,38.972191],"type":"Point"}
}