{
  "type": "Feature",
  "properties": {
    "addr:full":"9350 Snowden River Pkwy Columbia MD 21045",
    "addr:housenumber":"9350",
    "addr:postcode":"21045",
    "addr:street":"Snowden River Pkwy",
    "iso:country":"US",
    "sg:address":"9350 Snowden River Pkwy",
    "sg:city":"Columbia",
    "sg:classifiers":[
        {
            "category":"Shopping",
            "subcategory":"Computers & Home Electronics",
            "type":"Retail Goods"
        }
    ],
    "sg:phone":"+1 410 290 9082",
    "sg:postcode":"21045",
    "sg:province":"MD",
    "sg:tags":[
        "software"
    ],
    "sg:website":"www.ibiscom.com",
    "wof:name":"Ibis Communications",
    "wof:placetype":"venue"
},
  "geometry": {"coordinates":[-76.830524,39.17822],"type":"Point"}
}