{
  "type": "Feature",
  "properties": {
    "iso:country":"US",
    "sg:address":"217 Wyngate Dr",
    "sg:city":"Frederick",
    "sg:classifiers":[
        {
            "category":"Wholesale",
            "subcategory":"Electrical",
            "type":"Manufacturing & Wholesale Goods"
        }
    ],
    "sg:phone":"+1 301 682 3505",
    "sg:postcode":"21701",
    "sg:province":"MD",
    "sg:tags":[
        "alarm",
        "burglar",
        "system"
    ],
    "wof:name":"Lighthouse Security Corp",
    "wof:placetype":"venue"
},
  "geometry": {"coordinates":[-77.431764,39.409309],"type":"Point"}
}