{
  "type": "Feature",
  "properties": {
    "addr:full":"1013 Chestnut Moss Ct Baltimore MD 21226",
    "addr:housenumber":"1013",
    "addr:postcode":"21226",
    "addr:street":"Chestnut Moss Ct",
    "iso:country":"US",
    "sg:address":"1013 Chestnut Moss Ct",
    "sg:city":"Baltimore",
    "sg:classifiers":[
        {
            "category":"Professional",
            "subcategory":"Business Services",
            "type":"Services"
        }
    ],
    "sg:phone":"+1 410 360 8775",
    "sg:postcode":"21226",
    "sg:province":"MD",
    "sg:tags":[
        "information",
        "referral"
    ],
    "wof:name":"Hawkins Information Technology",
    "wof:placetype":"venue"
},
  "geometry": {"coordinates":[-76.542663,39.169241],"type":"Point"}
}