{
  "type": "Feature",
  "properties": {
    "addr:full":"3602 Gardenview Rd Pikesville MD 21208",
    "addr:housenumber":"3602",
    "addr:postcode":"21208",
    "addr:street":"Gardenview Rd",
    "iso:country":"US",
    "sg:address":"3602 Gardenview Rd",
    "sg:city":"Pikesville",
    "sg:classifiers":[
        {
            "category":"Professional",
            "subcategory":"Lawyer & Legal Services",
            "type":"Services"
        }
    ],
    "sg:phone":"+1 410 486 2266",
    "sg:postcode":"21208",
    "sg:province":"MD",
    "wof:name":"Bertram L Potemken",
    "wof:placetype":"venue"
},
  "geometry": {"coordinates":[-76.715526,39.403584],"type":"Point"}
}