{
  "type": "Feature",
  "properties": {
    "addr:full":"10921 Hammond Dr Laurel MD 20723",
    "addr:housenumber":"10921",
    "addr:postcode":"20723",
    "addr:street":"Hammond Dr",
    "iso:country":"US",
    "sg:address":"10921 Hammond Dr",
    "sg:city":"Laurel",
    "sg:classifiers":[
        {
            "category":"Building & Trades",
            "subcategory":"Locksmith",
            "type":"Services"
        }
    ],
    "sg:phone":"+1 240 294 8016",
    "sg:postcode":"20723",
    "sg:province":"MD",
    "sg:tags":[
        "key"
    ],
    "wof:name":"Available Laurel Locksmith 24 7",
    "wof:placetype":"venue"
},
  "geometry": {"coordinates":[-76.890838,39.151992],"type":"Point"}
}