{
  "type": "Feature",
  "properties": {
    "iso:country":"US",
    "sg:address":"153 Big Elk Mall",
    "sg:city":"Elkton",
    "sg:classifiers":[
        {
            "category":"Government",
            "subcategory":"Office",
            "type":"Public Place"
        }
    ],
    "sg:phone":"+1 410 398 2552",
    "sg:postcode":"21921",
    "sg:province":"MD",
    "sg:tags":[
        "federal",
        "security"
    ],
    "wof:name":"US Army & Army Reserve",
    "wof:placetype":"venue"
},
  "geometry": {"coordinates":[-75.82414799999999,39.599437],"type":"Point"}
}