{
  "type": "Feature",
  "properties": {
    "addr:full":"301 Washington St Cambridge MD 21613",
    "addr:housenumber":"301",
    "addr:postcode":"21613",
    "addr:street":"Washington St",
    "iso:country":"US",
    "sg:address":"301 Washington St",
    "sg:city":"Cambridge",
    "sg:classifiers":[
        {
            "category":"Insurance",
            "subcategory":"Insurance Agent",
            "type":"Services"
        }
    ],
    "sg:phone":"+1 410 228 5466",
    "sg:postcode":"21613",
    "sg:province":"MD",
    "wof:name":"Larry Dail Insurance",
    "wof:placetype":"venue"
},
  "geometry": {"coordinates":[-76.07648399999999,38.562667],"type":"Point"}
}