{
  "type": "Feature",
  "properties": {
    "iso:country":"US",
    "sg:address":"800 S Broadway",
    "sg:city":"Baltimore",
    "sg:classifiers":[
        {
            "category":"Building & Trades",
            "subcategory":"Locksmith",
            "type":"Services"
        }
    ],
    "sg:phone":"+1 443 987 6991",
    "sg:postcode":"21231",
    "sg:province":"MD",
    "sg:tags":[
        "key"
    ],
    "wof:name":"Red Star Locksmith",
    "wof:placetype":"venue"
},
  "geometry": {"coordinates":[-76.593594,39.282482],"type":"Point"}
}