{
  "type": "Feature",
  "properties": {
    "addr:full":"7811 Earnshaw Dr Brandywine MD 20613",
    "addr:housenumber":"7811",
    "addr:postcode":"20613",
    "addr:street":"Earnshaw Dr",
    "iso:country":"US",
    "sg:address":"7811 Earnshaw Dr",
    "sg:city":"Brandywine",
    "sg:classifiers":[
        {
            "category":"Professional",
            "subcategory":"Management & Consulting",
            "type":"Services"
        }
    ],
    "sg:phone":"+1 301 372 6346",
    "sg:postcode":"20613",
    "sg:province":"MD",
    "sg:tags":[
        "business"
    ],
    "wof:name":"Toneco Enterprises",
    "wof:placetype":"venue"
},
  "geometry": {"coordinates":[-76.869817,38.728872],"type":"Point"}
}