{
  "type": "Feature",
  "properties": {
    "iso:country":"US",
    "sg:address":"10964 Guilford Rd",
    "sg:city":"Annapolis Jct",
    "sg:classifiers":[
        {
            "category":"Building & Trades",
            "subcategory":"Construction",
            "type":"Services"
        }
    ],
    "sg:phone":"+1 301 483 8616",
    "sg:postcode":"20701",
    "sg:province":"MD",
    "sg:tags":[
        "concrete",
        "contractor"
    ],
    "wof:name":"Willis Concrete Constr Inc",
    "wof:placetype":"venue"
},
  "geometry": {"coordinates":[-76.793929,39.13024],"type":"Point"}
}