{
  "type": "Feature",
  "properties": {
    "iso:country":"US",
    "sg:address":"2655 Deer Park Rd",
    "sg:city":"Finksburg",
    "sg:classifiers":[
        {
            "category":"Real Estate",
            "subcategory":"Real Estate Agent",
            "type":"Services"
        }
    ],
    "sg:phone":"+1 410 833 0635",
    "sg:postcode":"21048",
    "sg:province":"MD",
    "wof:name":"Braunings Realestate",
    "wof:placetype":"venue"
},
  "geometry": {"coordinates":[-76.899733,39.466204],"type":"Point"}
}