{
  "type": "Feature",
  "properties": {
    "addr:full":"5801 Eastern Ave Hyattsville MD 20782",
    "addr:housenumber":"5801",
    "addr:postcode":"20782",
    "addr:street":"Eastern Ave",
    "iso:country":"US",
    "sg:address":"5801 Eastern Ave",
    "sg:city":"Hyattsville",
    "sg:classifiers":[
        {
            "category":"Personal",
            "subcategory":"Barber",
            "type":"Services"
        }
    ],
    "sg:phone":"+1 301 559 9664",
    "sg:postcode":"20782",
    "sg:province":"MD",
    "wof:name":"Riggs Plaza Barber Shop",
    "wof:placetype":"venue"
},
  "geometry": {"coordinates":[-76.99569700000001,38.9604],"type":"Point"}
}