{
  "type": "Feature",
  "properties": {
    "addr:full":"1600 Dennis Ave Towson MD 21204",
    "addr:housenumber":"1600",
    "addr:postcode":"21204",
    "addr:street":"Dennis Ave",
    "iso:country":"US",
    "sg:address":"1600 Dennis Ave",
    "sg:city":"Towson",
    "sg:classifiers":[
        {
            "category":"Home & Garden",
            "subcategory":"Household Appliances",
            "type":"Retail Goods"
        },
        {
            "category":"Manufacturing",
            "subcategory":"Building Materials",
            "type":"Manufacturing & Wholesale Goods"
        }
    ],
    "sg:phone":"+1 410 583 1832",
    "sg:postcode":"21204",
    "sg:province":"MD",
    "sg:tags":[
        "purifying",
        "filtering",
        "supply",
        "air",
        "equipment",
        "cleaning"
    ],
    "sg:website":"http://www.wolfeaire.com",
    "wof:name":"Wolfeaire Services Inc",
    "wof:placetype":"venue"
},
  "geometry": {"coordinates":[-76.644791,39.412739],"type":"Point"}
}