{
  "type": "Feature",
  "properties": {
    "iso:country":"US",
    "sg:address":"4510 Elsrode Ave",
    "sg:city":"Baltimore",
    "sg:classifiers":[
        {
            "category":"Retail",
            "subcategory":"Driving School",
            "type":"Services"
        },
        {
            "category":"Autos & Motor Vehicles",
            "subcategory":"Motorcycle Sales",
            "type":"Retail Goods"
        }
    ],
    "sg:phone":"+1 410 254 5404",
    "sg:postcode":"21214",
    "sg:province":"MD",
    "sg:tags":[
        "instruction"
    ],
    "wof:name":"Road Side Cycle",
    "wof:placetype":"venue"
},
  "geometry": {"coordinates":[-76.573341,39.342258],"type":"Point"}
}