{
  "type": "Feature",
  "properties": {
    "addr:full":"4445 Bark Hill Rd Union Bridge MD 21791",
    "addr:housenumber":"4445",
    "addr:postcode":"21791",
    "addr:street":"Bark Hill Rd",
    "iso:country":"US",
    "sg:address":"4445 Bark Hill Rd",
    "sg:city":"Union Bridge",
    "sg:classifiers":[
        {
            "category":"Professional",
            "type":"Services"
        }
    ],
    "sg:phone":"+1 410 875 2692",
    "sg:postcode":"21791",
    "sg:province":"MD",
    "sg:tags":[
        "establishment"
    ],
    "wof:name":"Stambaugh's Inc",
    "wof:placetype":"venue"
},
  "geometry": {"coordinates":[-77.15804900000001,39.584235],"type":"Point"}
}