{
  "type": "Feature",
  "properties": {
    "addr:full":"8871 Gorman Rd Laurel MD 20723",
    "addr:housenumber":"8871",
    "addr:postcode":"20723",
    "addr:street":"Gorman Rd",
    "iso:country":"US",
    "sg:address":"8871 Gorman Rd",
    "sg:city":"Laurel",
    "sg:classifiers":[
        {
            "category":"Health Services",
            "subcategory":"Doctor",
            "type":"Services"
        }
    ],
    "sg:phone":"+1 301 498 3150",
    "sg:postcode":"20723",
    "sg:province":"MD",
    "sg:tags":[
        "physician",
        "surgeon"
    ],
    "wof:name":"Potomac Physicians Laurel Hlth",
    "wof:placetype":"venue"
},
  "geometry": {"coordinates":[-76.820965,39.131806],"type":"Point"}
}