{
  "type": "Feature",
  "properties": {
    "addr:full":"15801 Trenton Rd Upperco MD 21155",
    "addr:housenumber":"15801",
    "addr:postcode":"21155",
    "addr:street":"Trenton Rd",
    "iso:country":"US",
    "sg:address":"15801 Trenton Rd",
    "sg:city":"Upperco",
    "sg:classifiers":[
        {
            "category":"Place Of Worship",
            "subcategory":"Church",
            "type":"Public Place"
        },
        {
            "category":"Place Of Worship",
            "type":"Public Place"
        }
    ],
    "sg:phone":"+1 410 239 3456",
    "sg:postcode":"21155",
    "sg:province":"MD",
    "sg:tags":[
        "lutheran",
        "america",
        "churches-lutheran",
        "churches-lutheran-evangelical"
    ],
    "wof:name":"St Paul's Lutheran Church",
    "wof:placetype":"venue"
},
  "geometry": {"coordinates":[-76.837799,39.558731],"type":"Point"}
}