{
  "type": "Feature",
  "properties": {
    "iso:country":"US",
    "sg:address":"12903 Kilburnie Cir",
    "sg:city":"Fort Washington",
    "sg:classifiers":[
        {
            "category":"Wholesale",
            "subcategory":"Computers",
            "type":"Manufacturing & Wholesale Goods"
        }
    ],
    "sg:phone":"+1 301 292 0841",
    "sg:postcode":"20744",
    "sg:province":"MD",
    "wof:name":"Cmp Inc",
    "wof:placetype":"venue"
},
  "geometry": {"coordinates":[-77.004673,38.711921],"type":"Point"}
}