{
  "type": "Feature",
  "properties": {
    "iso:country":"US",
    "sg:address":"11560 Pulaski Hwy",
    "sg:city":"White Marsh",
    "sg:classifiers":[
        {
            "category":"Freight",
            "type":"Transportation"
        }
    ],
    "sg:phone":"+1 410 335 8222",
    "sg:postcode":"21162",
    "sg:province":"MD",
    "sg:tags":[
        "general"
    ],
    "wof:name":"White Marsh Self Storage",
    "wof:placetype":"venue"
},
  "geometry": {"coordinates":[-76.395245,39.405047],"type":"Point"}
}