{
  "type": "Feature",
  "properties": {
    "addr:full":"1735 Riverside Dr Salisbury MD 21801",
    "addr:housenumber":"1735",
    "addr:postcode":"21801",
    "addr:street":"Riverside Dr",
    "iso:country":"US",
    "sg:address":"1735 Riverside Dr",
    "sg:city":"Salisbury",
    "sg:classifiers":[
        {
            "category":"Retail",
            "subcategory":"Animal Services",
            "type":"Services"
        }
    ],
    "sg:phone":"+1 410 546 5166",
    "sg:postcode":"21801",
    "sg:province":"MD",
    "sg:tags":[
        "pet",
        "grooming"
    ],
    "wof:name":"Cathy's Pet Salon",
    "wof:placetype":"venue"
},
  "geometry": {"coordinates":[-75.63058700000001,38.340243],"type":"Point"}
}