{
  "type": "Feature",
  "properties": {
    "iso:country":"US",
    "sg:address":"1521 Harford Ave",
    "sg:city":"Baltimore",
    "sg:classifiers":[
        {
            "category":"Shopping",
            "subcategory":"Pharmacy",
            "type":"Retail Goods"
        }
    ],
    "sg:phone":"+1 410 962 5541",
    "sg:postcode":"21202",
    "sg:province":"MD",
    "sg:tags":[
        "drugstore"
    ],
    "sg:website":"www.riteaid.com",
    "wof:name":"Rite Aid Pharmacies",
    "wof:placetype":"venue"
},
  "geometry": {"coordinates":[-76.600533,39.30746],"type":"Point"}
}