{
  "type": "Feature",
  "properties": {
    "iso:country":"US",
    "sg:address":"2831 Cox Neck Rd",
    "sg:city":"Chester",
    "sg:classifiers":[
        {
            "category":"Home & Garden",
            "subcategory":"Building Materials",
            "type":"Retail Goods"
        }
    ],
    "sg:phone":"+1 410 643 1616",
    "sg:postcode":"21619",
    "sg:province":"MD",
    "sg:tags":[
        "concrete",
        "shape",
        "block"
    ],
    "wof:name":"Howard Crawford Inc",
    "wof:placetype":"venue"
},
  "geometry": {"coordinates":[-76.301163,38.919697],"type":"Point"}
}