{
  "type": "Feature",
  "properties": {
    "iso:country":"US",
    "sg:address":"2916 Festival Way",
    "sg:city":"Waldorf",
    "sg:classifiers":[
        {
            "category":"Restaurant",
            "type":"Food & Drink"
        }
    ],
    "sg:menulink":"http://www.allmenus.com/md/waldorf/104380-old-country-buffet/menu/",
    "sg:phone":"+1 301 645 0860",
    "sg:postcode":"20601",
    "sg:province":"MD",
    "sg:tags":[
        "american"
    ],
    "wof:name":"Old Country Buffet",
    "wof:placetype":"venue"
},
  "geometry": {"coordinates":[-76.909136,38.629661],"type":"Point"}
}