{
  "type": "Feature",
  "properties": {
    "addr:full":"4900 Massachusetts Ave NW Washington MD 20016",
    "addr:housenumber":"4900",
    "addr:postcode":"20016",
    "addr:street":"Massachusetts Ave Nw",
    "iso:country":"US",
    "sg:address":"4900 Massachusetts Ave NW",
    "sg:city":"Washington",
    "sg:classifiers":[
        {
            "category":"Health Services",
            "subcategory":"Doctor",
            "type":"Services"
        }
    ],
    "sg:phone":"+1 202 362 6060",
    "sg:postcode":"20016",
    "sg:province":"MD",
    "sg:tags":[
        "physician",
        "surgeon"
    ],
    "wof:name":"Jerry A Snow MD",
    "wof:placetype":"venue"
},
  "geometry": {"coordinates":[-77.09844099999999,38.94707],"type":"Point"}
}