{
  "type": "Feature",
  "properties": {
    "iso:country":"US",
    "sg:address":"3844 Wildlife Ln",
    "sg:city":"Burtonsville",
    "sg:classifiers":[
        {
            "category":"Shopping",
            "subcategory":"Gifts & Souvenirs",
            "type":"Retail Goods"
        }
    ],
    "sg:phone":"+1 301 890 0501",
    "sg:postcode":"20866",
    "sg:province":"MD",
    "sg:tags":[
        "shop"
    ],
    "wof:name":"Rainbow Fashion Ctr",
    "wof:placetype":"venue"
},
  "geometry": {"coordinates":[-76.931727,39.082596],"type":"Point"}
}