{
  "type": "Feature",
  "properties": {
    "iso:country":"US",
    "sg:address":"1505 Bedford Ave",
    "sg:city":"Pikesville",
    "sg:classifiers":[
        {
            "category":"Shopping",
            "subcategory":"Jewelry",
            "type":"Retail Goods"
        }
    ],
    "sg:phone":"+1 410 486 1442",
    "sg:postcode":"21208",
    "sg:province":"MD",
    "sg:tags":[
        "jeweler"
    ],
    "wof:name":"Hands Of Man",
    "wof:placetype":"venue"
},
  "geometry": {"coordinates":[-76.727197,39.376683],"type":"Point"}
}