{
  "type": "Feature",
  "properties": {
    "iso:country":"US",
    "sg:address":"9940 Franklin Square Dr",
    "sg:city":"Nottingham",
    "sg:classifiers":[
        {
            "category":"Manufacturing",
            "subcategory":"Petroleum Products",
            "type":"Manufacturing & Wholesale Goods"
        }
    ],
    "sg:phone":"+1 410 933 4823",
    "sg:postcode":"21236",
    "sg:province":"MD",
    "sg:tags":[
        "oils-fuel-wholesale",
        "manufacturer"
    ],
    "wof:name":"Clean Green Fuel",
    "wof:placetype":"venue"
},
  "geometry": {"coordinates":[-76.462363,39.365637],"type":"Point"}
}