{
  "type": "Feature",
  "properties": {
    "addr:full":"2 Doncaster Ct Annapolis MD 21403",
    "addr:housenumber":"2",
    "addr:postcode":"21403",
    "addr:street":"Doncaster Ct",
    "iso:country":"US",
    "sg:address":"2 Doncaster Ct",
    "sg:city":"Annapolis",
    "sg:classifiers":[
        {
            "category":"Professional",
            "subcategory":"Art Services",
            "type":"Services"
        }
    ],
    "sg:phone":"+1 410 268 1073",
    "sg:postcode":"21403",
    "sg:province":"MD",
    "sg:tags":[
        "graphic",
        "commercial",
        "designer",
        "artist"
    ],
    "sg:website":"http://www.bodymech.com",
    "wof:name":"Visionary Magic",
    "wof:placetype":"venue"
},
  "geometry": {"coordinates":[-76.486717,38.950878],"type":"Point"}
}