{
  "type": "Feature",
  "properties": {
    "iso:country":"US",
    "sg:address":"2405 Love Point Rd",
    "sg:city":"Stevensville",
    "sg:classifiers":[
        {
            "category":"Building & Trades",
            "subcategory":"Plumbing",
            "type":"Services"
        }
    ],
    "sg:phone":"+1 410 604 0287",
    "sg:postcode":"21666",
    "sg:province":"MD",
    "sg:tags":[
        "plumber",
        "industrial",
        "contractors-commercial"
    ],
    "wof:name":"Elsey's Plumbing & Heating",
    "wof:placetype":"venue"
},
  "geometry": {"coordinates":[-76.31105100000001,39.032136],"type":"Point"}
}