{
  "type": "Feature",
  "properties": {
    "iso:country":"US",
    "sg:address":"7835 Eastpoint Mall",
    "sg:city":"Baltimore",
    "sg:classifiers":[
        {
            "category":"Health Services",
            "subcategory":"Doctor",
            "type":"Services"
        }
    ],
    "sg:phone":"+1 410 282 0505",
    "sg:postcode":"21224",
    "sg:province":"MD",
    "sg:tags":[
        "physician",
        "surgeon"
    ],
    "wof:name":"George N Karkar MD",
    "wof:placetype":"venue"
},
  "geometry": {"coordinates":[-76.506503,39.293593],"type":"Point"}
}