{
  "type": "Feature",
  "properties": {
    "iso:country":"US",
    "sg:address":"13 Goldsborough St",
    "sg:city":"Easton",
    "sg:classifiers":[
        {
            "category":"Museum",
            "type":"Entertainment"
        }
    ],
    "sg:phone":"+1 410 822 7924",
    "sg:postcode":"21601",
    "sg:province":"MD",
    "sg:tags":[
        "gallery"
    ],
    "wof:name":"Creatrics",
    "wof:placetype":"venue"
},
  "geometry": {"coordinates":[-76.075119,38.77579],"type":"Point"}
}