{
  "type": "Feature",
  "properties": {
    "addr:full":"11121 York Rd Hunt Valley MD 21065",
    "addr:housenumber":"11121",
    "addr:postcode":"21065",
    "addr:street":"York Rd Hunt",
    "iso:country":"US",
    "sg:address":"11121 York Rd",
    "sg:city":"Hunt Valley",
    "sg:classifiers":[
        {
            "category":"Sports & Exercise",
            "subcategory":"Sports Center",
            "type":"Entertainment"
        }
    ],
    "sg:phone":"+1 410 316 1529",
    "sg:postcode":"21065",
    "sg:province":"MD",
    "sg:tags":[
        "amateur",
        "team"
    ],
    "wof:name":"Pdm Office",
    "wof:placetype":"venue"
},
  "geometry": {"coordinates":[-76.647634,39.490233],"type":"Point"}
}