{
  "type": "Feature",
  "properties": {
    "iso:country":"US",
    "sg:address":"1217 W Fayette St",
    "sg:city":"Baltimore",
    "sg:classifiers":[
        {
            "category":"Health Services",
            "subcategory":"Medical Lab",
            "type":"Services"
        }
    ],
    "sg:phone":"+1 410 727 3947",
    "sg:postcode":"21223",
    "sg:province":"MD",
    "sg:website":"http://www.concordcarecenters.com",
    "wof:name":"Millennium Hlth Rehab Ctr Fran",
    "wof:placetype":"venue"
},
  "geometry": {"coordinates":[-76.637529,39.289779],"type":"Point"}
}