{
  "type": "Feature",
  "properties": {
    "iso:country":"US",
    "sg:address":"7520 Simms Landing Rd",
    "sg:city":"Port Tobacco",
    "sg:classifiers":[
        {
            "category":"Building & Trades",
            "subcategory":"Landscaping Services",
            "type":"Services"
        }
    ],
    "sg:phone":"+1 301 743 7929",
    "sg:postcode":"20677",
    "sg:province":"MD",
    "sg:tags":[
        "tree"
    ],
    "wof:name":"Chain Saw Wiz",
    "wof:placetype":"venue"
},
  "geometry": {"coordinates":[-77.03200099999999,38.486758],"type":"Point"}
}