{
  "type": "Feature",
  "properties": {
    "iso:country":"US",
    "sg:address":"1534 Rockville Pike",
    "sg:city":"Rockville",
    "sg:classifiers":[
        {
            "category":"Shopping",
            "subcategory":"Clothing, Apparel, & Fashions",
            "type":"Retail Goods"
        }
    ],
    "sg:phone":"+1 301 881 6353",
    "sg:postcode":"20852",
    "sg:province":"MD",
    "sg:tags":[
        "wig",
        "hair",
        "hairpiece",
        "toupee",
        "piece"
    ],
    "sg:website":"http://www.empirewigs.com",
    "wof:name":"Empire Wigs",
    "wof:placetype":"venue"
},
  "geometry": {"coordinates":[-77.126091,39.064486],"type":"Point"}
}