{
  "type": "Feature",
  "properties": {
    "addr:full":"407 Gusryan St Baltimore MD 21224",
    "addr:housenumber":"407",
    "addr:postcode":"21224",
    "addr:street":"Gusryan St",
    "iso:country":"US",
    "sg:address":"407 Gusryan St",
    "sg:city":"Baltimore",
    "sg:classifiers":[
        {
            "category":"Manufacturing",
            "subcategory":"Tools & Machinery",
            "type":"Manufacturing & Wholesale Goods"
        },
        {
            "category":"Manufacturing",
            "subcategory":"Electronics",
            "type":"Manufacturing & Wholesale Goods"
        },
        {
            "category":"Shopping",
            "subcategory":"Computers & Home Electronics",
            "type":"Retail Goods"
        }
    ],
    "sg:phone":"+1 443 572 1936",
    "sg:postcode":"21224",
    "sg:province":"MD",
    "sg:tags":[
        "electric",
        "consumer",
        "equipment-testing",
        "equipment",
        "supplies-wholesale",
        "manufacturer"
    ],
    "wof:name":"Ms Technologies Inc.",
    "wof:placetype":"venue"
},
  "geometry": {"coordinates":[-76.540994,39.28905],"type":"Point"}
}