{
  "type": "Feature",
  "properties": {
    "iso:country":"US",
    "sg:address":"1603 Auburn Ave",
    "sg:city":"Rockville",
    "sg:classifiers":[
        {
            "category":"Professional",
            "subcategory":"Research",
            "type":"Services"
        }
    ],
    "sg:phone":"+1 301 762 7484",
    "sg:postcode":"20850",
    "sg:province":"MD",
    "wof:name":"Health Research Assoc",
    "wof:placetype":"venue"
},
  "geometry": {"coordinates":[-77.164512,39.102526],"type":"Point"}
}