{
  "type": "Feature",
  "properties": {
    "addr:full":"4909 Suitland Rd Suitland MD 20746",
    "addr:housenumber":"4909",
    "addr:postcode":"20746",
    "addr:street":"Suitland Rd",
    "iso:country":"US",
    "sg:address":"4909 Suitland Rd",
    "sg:city":"Suitland",
    "sg:classifiers":[
        {
            "category":"Personal",
            "subcategory":"Beauty Salon",
            "type":"Services"
        }
    ],
    "sg:phone":"+1 301 420 2323",
    "sg:postcode":"20746",
    "sg:province":"MD",
    "wof:name":"Ray's Hairstylist",
    "wof:placetype":"venue"
},
  "geometry": {"coordinates":[-76.922929,38.847862],"type":"Point"}
}