{
  "type": "Feature",
  "properties": {
    "addr:full":"2406 Crofton Blvd Crofton MD 21114",
    "addr:housenumber":"2406",
    "addr:postcode":"21114",
    "addr:street":"Crofton Blvd",
    "iso:country":"US",
    "sg:address":"2406 Crofton Blvd",
    "sg:city":"Crofton",
    "sg:classifiers":[
        {
            "category":"Building & Trades",
            "subcategory":"Construction",
            "type":"Services"
        }
    ],
    "sg:phone":"+1 301 261 6667",
    "sg:postcode":"21114",
    "sg:province":"MD",
    "sg:tags":[
        "general",
        "contractor"
    ],
    "sg:website":"www.thedrewgroup.com",
    "wof:name":"Drew Construction Svc",
    "wof:placetype":"venue"
},
  "geometry": {"coordinates":[-76.69785,39.01714],"type":"Point"}
}