{
  "type": "Feature",
  "properties": {
    "iso:country":"US",
    "sg:address":"2803 Shepperton Ter",
    "sg:city":"Silver Spring",
    "sg:classifiers":[
        {
            "category":"Building & Trades",
            "subcategory":"Locksmith",
            "type":"Services"
        }
    ],
    "sg:phone":"+1 240 560 2024",
    "sg:postcode":"20904",
    "sg:province":"MD",
    "sg:tags":[
        "key"
    ],
    "wof:name":"Shepperton Terrace 24 Hour Emerg Locksmith",
    "wof:placetype":"venue"
},
  "geometry": {"coordinates":[-76.95140600000001,39.083425],"type":"Point"}
}