{
  "type": "Feature",
  "properties": {
    "addr:full":"11380 Cherry Hill Rd Beltsville MD 20705",
    "addr:housenumber":"11380",
    "addr:postcode":"20705",
    "addr:street":"Cherry Hill Rd",
    "iso:country":"US",
    "sg:address":"11380 Cherry Hill Rd",
    "sg:city":"Beltsville",
    "sg:classifiers":[
        {
            "category":"Arts & Performance",
            "subcategory":"Theater",
            "type":"Entertainment"
        }
    ],
    "sg:phone":"+1 301 937 9232",
    "sg:postcode":"20705",
    "sg:province":"MD",
    "sg:tags":[
        "theatrical"
    ],
    "wof:name":"Dusk & Dawn Productions",
    "wof:placetype":"venue"
},
  "geometry": {"coordinates":[-76.94965999999999,39.042255],"type":"Point"}
}