{
  "type": "Feature",
  "properties": {
    "iso:country":"US",
    "sg:address":"1420 4th St",
    "sg:city":"Glenarden",
    "sg:classifiers":[
        {
            "category":"Professional",
            "subcategory":"Computer Services",
            "type":"Services"
        },
        {
            "category":"Internet Cafe",
            "subcategory":"None",
            "type":"Food & Drink"
        }
    ],
    "sg:phone":"+1 301 341 5572",
    "sg:postcode":"20706",
    "sg:province":"MD",
    "sg:tags":[
        "product",
        "software"
    ],
    "wof:name":"Witc Information Systems",
    "wof:placetype":"venue"
},
  "geometry": {"coordinates":[-76.85581999999999,38.928857],"type":"Point"}
}