{
  "type": "Feature",
  "properties": {
    "addr:full":"5609 Fishers Ln Ste 6A Rockville MD 20852",
    "addr:housenumber":"5609",
    "addr:postcode":"20852",
    "addr:street":"Fishers Ln Ste 6A",
    "iso:country":"US",
    "sg:address":"5609 Fishers Ln Ste 6A",
    "sg:city":"Rockville",
    "sg:classifiers":[
        {
            "category":"Arena",
            "subcategory":"Sports Club",
            "type":"Entertainment"
        }
    ],
    "sg:phone":"+1 301 770 0969",
    "sg:postcode":"20852",
    "sg:province":"MD",
    "sg:tags":[
        "martial art",
        "instruction"
    ],
    "sg:website":"http://www.grappling.com",
    "wof:name":"Yamasaki Jiu-Jitsu",
    "wof:placetype":"venue"
},
  "geometry": {"coordinates":[-77.116319,39.06277],"type":"Point"}
}