{
  "type": "Feature",
  "properties": {
    "addr:full":"6022 Cross Country Blvd Baltimore MD 21215",
    "addr:housenumber":"6022",
    "addr:postcode":"21215",
    "addr:street":"Cross Country Blvd",
    "iso:country":"US",
    "sg:address":"6022 Cross Country Blvd",
    "sg:city":"Baltimore",
    "sg:classifiers":[
        {
            "category":"Professional",
            "type":"Services"
        }
    ],
    "sg:phone":"+1 410 764 0124",
    "sg:postcode":"21215",
    "sg:province":"MD",
    "wof:name":"Schuman David Protrait Artist",
    "wof:placetype":"venue"
},
  "geometry": {"coordinates":[-76.686035,39.362129],"type":"Point"}
}