{
  "type": "Feature",
  "properties": {
    "addr:full":"712 Smith St Salisbury MD 21801",
    "addr:housenumber":"712",
    "addr:postcode":"21801",
    "addr:street":"Smith St",
    "iso:country":"US",
    "sg:address":"712 Smith St",
    "sg:city":"Salisbury",
    "sg:classifiers":[
        {
            "category":"Building & Trades",
            "subcategory":"Electrical",
            "type":"Services"
        }
    ],
    "sg:phone":"+1 410 742 7523",
    "sg:postcode":"21801",
    "sg:province":"MD",
    "sg:tags":[
        "electrical",
        "contractor"
    ],
    "wof:name":"Jarmans Services Inc",
    "wof:placetype":"venue"
},
  "geometry": {"coordinates":[-75.603641,38.357611],"type":"Point"}
}