{
  "type": "Feature",
  "properties": {
    "addr:full":"8220 Perry Hall Blvd Baltimore MD 21236",
    "addr:housenumber":"8220",
    "addr:postcode":"21236",
    "addr:street":"Perry Hall Blvd",
    "iso:country":"US",
    "sg:address":"8220 Perry Hall Blvd",
    "sg:city":"Baltimore",
    "sg:classifiers":[
        {
            "category":"Government",
            "subcategory":"Police Station",
            "type":"Public Place"
        }
    ],
    "sg:phone":"+1 410 887 5000",
    "sg:postcode":"21236",
    "sg:province":"MD",
    "sg:tags":[
        "sheriff"
    ],
    "wof:name":"Baltimore County Police Dept",
    "wof:placetype":"venue"
},
  "geometry": {"coordinates":[-76.47514,39.371244],"type":"Point"}
}