{
  "type": "Feature",
  "properties": {
    "addr:full":"1803 Dundalk Ave Baltimore MD 21222",
    "addr:housenumber":"1803",
    "addr:postcode":"21222",
    "addr:street":"Dundalk Ave",
    "iso:country":"US",
    "sg:address":"1803 Dundalk Ave",
    "sg:city":"Baltimore",
    "sg:classifiers":[
        {
            "category":"Organizations",
            "subcategory":"Religious Organization",
            "type":"Services"
        }
    ],
    "sg:phone":"+1 410 633 5374",
    "sg:postcode":"21222",
    "sg:province":"MD",
    "wof:name":"Saint Lkes Evang Lthran Church",
    "wof:placetype":"venue"
},
  "geometry": {"coordinates":[-76.530885,39.272541],"type":"Point"}
}