{
  "type": "Feature",
  "properties": {
    "iso:country":"US",
    "sg:address":"1510 Whitelock St",
    "sg:city":"Baltimore",
    "sg:classifiers":[
        {
            "category":"Travel",
            "subcategory":"Campground",
            "type":"Entertainment"
        }
    ],
    "sg:phone":"+1 410 523 9234",
    "sg:postcode":"21217",
    "sg:province":"MD",
    "wof:name":"Concerned About The Ctr",
    "wof:placetype":"venue"
},
  "geometry": {"coordinates":[-76.641243,39.310585],"type":"Point"}
}