{
  "type": "Feature",
  "properties": {
    "addr:full":"281 E Main St Rising Sun MD 21911",
    "addr:housenumber":"281",
    "addr:postcode":"21911",
    "addr:street":"E Main St",
    "iso:country":"US",
    "sg:address":"281 E Main St",
    "sg:city":"Rising Sun",
    "sg:classifiers":[
        {
            "category":"Insurance",
            "subcategory":"Insurance Agent",
            "type":"Services"
        }
    ],
    "sg:phone":"+1 410 658 5598",
    "sg:postcode":"21911",
    "sg:province":"MD",
    "sg:website":"www.fossett-insurance.com",
    "wof:name":"Fossett Insurance",
    "wof:placetype":"venue"
},
  "geometry": {"coordinates":[-76.054519,39.698988],"type":"Point"}
}