{
  "type": "Feature",
  "properties": {
    "addr:full":"671 Cog Ct Millersville MD 21108",
    "addr:housenumber":"671",
    "addr:postcode":"21108",
    "addr:street":"Cog Ct",
    "iso:country":"US",
    "sg:address":"671 Cog Ct",
    "sg:city":"Millersville",
    "sg:classifiers":[
        {
            "category":"Arts & Performance",
            "subcategory":"Music",
            "type":"Entertainment"
        }
    ],
    "sg:phone":"+1 410 987 1337",
    "sg:postcode":"21108",
    "sg:province":"MD",
    "sg:tags":[
        "instrument",
        "musical"
    ],
    "wof:name":"Erik Heisig",
    "wof:placetype":"venue"
},
  "geometry": {"coordinates":[-76.63020400000001,39.114251],"type":"Point"}
}