{
  "type": "Feature",
  "properties": {
    "addr:full":"11311 McCormick Rd Cockysvl Hnt Vly MD 21031",
    "addr:housenumber":"11311",
    "addr:postcode":"21031",
    "addr:street":"Mccormick Rd;Hnt Vly",
    "iso:country":"US",
    "sg:address":"11311 McCormick Rd",
    "sg:city":"Cockysvl Hnt Vly",
    "sg:classifiers":[
        {
            "category":"Insurance",
            "subcategory":"Insurance Agent",
            "type":"Services"
        }
    ],
    "sg:phone":"+1 410 316 8700",
    "sg:postcode":"21031",
    "sg:province":"MD",
    "sg:tags":[
        "processing"
    ],
    "wof:name":"AIG Claim Svc",
    "wof:placetype":"venue"
},
  "geometry": {"coordinates":[-76.65881400000001,39.493446],"type":"Point"}
}