{
  "type": "Feature",
  "properties": {
    "iso:country":"US",
    "sg:address":"17631 Goose Creek Rd",
    "sg:city":"Olney",
    "sg:classifiers":[
        {
            "category":"Real Estate",
            "subcategory":"Surveying",
            "type":"Services"
        }
    ],
    "sg:phone":"+1 301 570 0350",
    "sg:postcode":"20832",
    "sg:province":"MD",
    "sg:tags":[
        "surveyor"
    ],
    "wof:name":"Aes Assoc",
    "wof:placetype":"venue"
},
  "geometry": {"coordinates":[-77.087084,39.146264],"type":"Point"}
}