{
  "type": "Feature",
  "properties": {
    "addr:full":"10605 Concord St Ste 503 Kensington MD 20895",
    "addr:housenumber":"10605",
    "addr:postcode":"20895",
    "addr:street":"Concord St Ste 503",
    "iso:country":"US",
    "sg:address":"10605 Concord St Ste 503",
    "sg:city":"Kensington",
    "sg:classifiers":[
        {
            "category":"Education",
            "subcategory":"Kindergarten",
            "type":"Public Place"
        }
    ],
    "sg:phone":"+1 240 514 0167",
    "sg:postcode":"20895",
    "sg:province":"MD",
    "sg:tags":[
        "school",
        "driving"
    ],
    "sg:website":"www.idrivesmart.com",
    "wof:name":"I Drive-Smart Inc",
    "wof:placetype":"venue"
},
  "geometry": {"coordinates":[-77.07475700000001,39.029756],"type":"Point"}
}