{
  "type": "Feature",
  "properties": {
    "iso:country":"US",
    "sg:address":"107 S Seton Ave",
    "sg:city":"Emmitsburg",
    "sg:classifiers":[
        {
            "category":"Manufacturing",
            "subcategory":"Printing",
            "type":"Manufacturing & Wholesale Goods"
        }
    ],
    "sg:phone":"+1 301 447 2333",
    "sg:postcode":"21727",
    "sg:province":"MD",
    "sg:tags":[
        "printer"
    ],
    "wof:name":"Chronicle Press",
    "wof:placetype":"venue"
},
  "geometry": {"coordinates":[-77.32702,39.704068],"type":"Point"}
}