{
  "type": "Feature",
  "properties": {
    "addr:full":"12181 Darnestown Rd Gaithersburg MD 20878",
    "addr:housenumber":"12181",
    "addr:postcode":"20878",
    "addr:street":"Darnestown Rd",
    "iso:country":"US",
    "sg:address":"12181 Darnestown Rd",
    "sg:city":"Gaithersburg",
    "sg:classifiers":[
        {
            "category":"Education",
            "subcategory":"Dance Studio",
            "type":"Public Place"
        }
    ],
    "sg:phone":"+1 301 738 3384",
    "sg:postcode":"20878",
    "sg:province":"MD",
    "sg:tags":[
        "instruction",
        "dancing"
    ],
    "wof:name":"Potomac Yoga",
    "wof:placetype":"venue"
},
  "geometry": {"coordinates":[-77.25055999999999,39.117156],"type":"Point"}
}