{
  "type": "Feature",
  "properties": {
    "iso:country":"US",
    "sg:address":"7921 Glenbrook Rd",
    "sg:city":"Bethesda",
    "sg:classifiers":[
        {
            "category":"Professional",
            "subcategory":"Advertising",
            "type":"Services"
        }
    ],
    "sg:phone":"+1 301 913 9797",
    "sg:postcode":"20814",
    "sg:province":"MD",
    "sg:tags":[
        "counselor"
    ],
    "wof:name":"Lahr Agency Inc",
    "wof:placetype":"venue"
},
  "geometry": {"coordinates":[-77.101805,38.989211],"type":"Point"}
}