{
  "type": "Feature",
  "properties": {
    "iso:country":"US",
    "sg:address":"1017 Greenmount Ave",
    "sg:city":"Baltimore",
    "sg:classifiers":[
        {
            "category":"Place Of Worship",
            "subcategory":"Church",
            "type":"Public Place"
        },
        {
            "category":"Place Of Worship",
            "type":"Public Place"
        },
        {
            "category":"Organizations",
            "subcategory":"Religious Organization",
            "type":"Services"
        }
    ],
    "sg:phone":"+1 443 388 8272",
    "sg:postcode":"21202",
    "sg:province":"MD",
    "sg:tags":[
        "churches-baptist-general",
        "churches-baptist"
    ],
    "wof:name":"Redemption Church",
    "wof:placetype":"venue"
},
  "geometry": {"coordinates":[-76.60752100000001,39.301798],"type":"Point"}
}