{
  "type": "Feature",
  "properties": {
    "iso:country":"US",
    "sg:address":"701 Park St",
    "sg:city":"Cumberland",
    "sg:classifiers":[
        {
            "category":"Restaurant",
            "type":"Food & Drink"
        }
    ],
    "sg:menulink":"http://www.allmenus.com/md/cumberland/131570-quiznos-sub/menu/",
    "sg:phone":"+1 301 777 7711",
    "sg:postcode":"21502",
    "sg:province":"MD",
    "sg:tags":[
        "wrap",
        "american",
        "sandwich"
    ],
    "wof:name":"Quiznos Sub",
    "wof:placetype":"venue"
},
  "geometry": {"coordinates":[-78.75740399999999,39.647663],"type":"Point"}
}