{
  "type": "Feature",
  "properties": {
    "addr:full":"24 S Durham St Baltimore MD 21231",
    "addr:housenumber":"24",
    "addr:postcode":"21231",
    "addr:street":"S Durham St",
    "iso:country":"US",
    "sg:address":"24 S Durham St",
    "sg:city":"Baltimore",
    "sg:classifiers":[
        {
            "category":"Professional",
            "subcategory":"Art Services",
            "type":"Services"
        }
    ],
    "sg:phone":"+1 443 629 9092",
    "sg:postcode":"21231",
    "sg:province":"MD",
    "sg:tags":[
        "photographer"
    ],
    "wof:name":"Lucida Photography",
    "wof:placetype":"venue"
},
  "geometry": {"coordinates":[-76.591133,39.290775],"type":"Point"}
}