{
  "type": "Feature",
  "properties": {
    "iso:country":"US",
    "sg:address":"26234 Ridge Rd",
    "sg:city":"Damascus",
    "sg:classifiers":[
        {
            "category":"Autos & Motor Vehicles",
            "subcategory":"Fuel & Gas Station",
            "type":"Retail Goods"
        }
    ],
    "sg:phone":"+1 301 253 5140",
    "sg:postcode":"20872",
    "sg:province":"MD",
    "sg:tags":[
        "oil"
    ],
    "wof:name":"Damascus Amoco",
    "wof:placetype":"venue"
},
  "geometry": {"coordinates":[-77.20894,39.286262],"type":"Point"}
}