{
  "type": "Feature",
  "properties": {
    "addr:full":"11301 Rockville Pike Kensington MD 20895",
    "addr:housenumber":"11301",
    "addr:postcode":"20895",
    "addr:street":"Rockville Pike",
    "iso:country":"US",
    "sg:address":"11301 Rockville Pike",
    "sg:city":"Kensington",
    "sg:classifiers":[
        {
            "category":"Coffee & Tea",
            "type":"Food & Drink"
        },
        {
            "category":"Bakery",
            "type":"Food & Drink"
        }
    ],
    "sg:menulink":"http://www.allmenus.com/md/rockville/137069-seattles-best-coffee/menu/",
    "sg:phone":"+1 301 816 1067",
    "sg:postcode":"20895",
    "sg:province":"MD",
    "sg:tags":[
        "american",
        "diner",
        "pastry"
    ],
    "wof:name":"Seattle's Best Coffee",
    "wof:placetype":"venue"
},
  "geometry": {"coordinates":[-77.110038,39.041406],"type":"Point"}
}