{
  "type": "Feature",
  "properties": {
    "iso:country":"US",
    "sg:address":"5463 Southern Maryland Blvd",
    "sg:city":"Lothian",
    "sg:classifiers":[
        {
            "category":"Building & Trades",
            "subcategory":"Plumbing",
            "type":"Services"
        }
    ],
    "sg:phone":"+1 410 741 9750",
    "sg:postcode":"20711",
    "sg:province":"MD",
    "sg:tags":[
        "conditioning",
        "air",
        "system",
        "contractor"
    ],
    "wof:name":"Allen Service Co Inc",
    "wof:placetype":"venue"
},
  "geometry": {"coordinates":[-76.657956,38.767686],"type":"Point"}
}