{
  "type": "Feature",
  "properties": {
    "iso:country":"US",
    "sg:address":"7909 Cryden Way",
    "sg:city":"District Heights",
    "sg:classifiers":[
        {
            "category":"Personal",
            "type":"Services"
        }
    ],
    "sg:phone":"+1 301 420 2777",
    "sg:postcode":"20747",
    "sg:province":"MD",
    "sg:tags":[
        "mover"
    ],
    "wof:name":"Aaaa Apartment Moving & Storage",
    "wof:placetype":"venue"
},
  "geometry": {"coordinates":[-76.8685,38.8484],"type":"Point"}
}