{
  "type": "Feature",
  "properties": {
    "addr:full":"13920 Mantua Mill Rd Glyndon MD 21071",
    "addr:housenumber":"13920",
    "addr:postcode":"21071",
    "addr:street":"Mantua Mill Rd",
    "iso:country":"US",
    "sg:address":"13920 Mantua Mill Rd",
    "sg:city":"Glyndon",
    "sg:classifiers":[
        {
            "category":"Bars & Pubs",
            "subcategory":"Nightclub",
            "type":"Food & Drink"
        }
    ],
    "sg:phone":"+1 410 833 4884",
    "sg:postcode":"21071",
    "sg:province":"MD",
    "sg:tags":[
        "nightlife"
    ],
    "wof:name":"Greenspring Valley Hounds",
    "wof:placetype":"venue"
},
  "geometry": {"coordinates":[-76.814301,39.474098],"type":"Point"}
}