{
  "type": "Feature",
  "properties": {
    "iso:country":"US",
    "sg:address":"81 Baltimore St",
    "sg:city":"Cumberland",
    "sg:classifiers":[
        {
            "category":"Health Services",
            "subcategory":"Doctor",
            "type":"Services"
        }
    ],
    "sg:phone":"+1 301 777 9330",
    "sg:postcode":"21502",
    "sg:province":"MD",
    "sg:tags":[
        "physician",
        "surgeon"
    ],
    "wof:name":"Samuel N Nava MD",
    "wof:placetype":"venue"
},
  "geometry": {"coordinates":[-78.76134500000001,39.651491],"type":"Point"}
}