{
  "type": "Feature",
  "properties": {
    "addr:full":"1601 Washington Rd Westminster MD 21157",
    "addr:housenumber":"1601",
    "addr:postcode":"21157",
    "addr:street":"Washington Rd",
    "iso:country":"US",
    "sg:address":"1601 Washington Rd",
    "sg:city":"Westminster",
    "sg:classifiers":[
        {
            "category":"Education",
            "subcategory":"Special Training",
            "type":"Public Place"
        },
        {
            "category":"Social Services",
            "subcategory":"Child Care",
            "type":"Services"
        },
        {
            "category":"Shopping",
            "subcategory":"Books",
            "type":"Retail Goods"
        },
        {
            "category":"Education",
            "subcategory":"University",
            "type":"Public Place"
        }
    ],
    "sg:phone":"+1 410 386 8000",
    "sg:postcode":"21157",
    "sg:province":"MD",
    "sg:tags":[
        "college",
        "adult",
        "store"
    ],
    "sg:website":"http://www.carrollcc.edu",
    "wof:name":"Carroll Community College",
    "wof:placetype":"venue"
},
  "geometry": {"coordinates":[-76.993973,39.530653],"type":"Point"}
}