{
  "type": "Feature",
  "properties": {
    "addr:full":"14609 Main St Upper Marlboro MD 20772",
    "addr:housenumber":"14609",
    "addr:postcode":"20772",
    "addr:street":"Main St",
    "iso:country":"US",
    "sg:address":"14609 Main St",
    "sg:city":"Upper Marlboro",
    "sg:classifiers":[
        {
            "category":"Arena",
            "subcategory":"Sports Club",
            "type":"Entertainment"
        }
    ],
    "sg:phone":"+1 301 952 1380",
    "sg:postcode":"20772",
    "sg:province":"MD",
    "sg:tags":[
        "manager",
        "recruiter",
        "promoter"
    ],
    "wof:name":"IMC Sports",
    "wof:placetype":"venue"
},
  "geometry": {"coordinates":[-76.752619,38.815962],"type":"Point"}
}