{
  "type": "Feature",
  "properties": {
    "addr:full":"11 Hudson St Annapolis MD 21401",
    "addr:housenumber":"11",
    "addr:postcode":"21401",
    "addr:street":"Hudson St",
    "iso:country":"US",
    "sg:address":"11 Hudson St",
    "sg:city":"Annapolis",
    "sg:classifiers":[
        {
            "category":"Building & Trades",
            "subcategory":"Plumbing",
            "type":"Services"
        }
    ],
    "sg:phone":"+1 410 573 6625",
    "sg:postcode":"21401",
    "sg:province":"MD",
    "sg:tags":[
        "water",
        "equipment",
        "work",
        "supply"
    ],
    "sg:website":"http://www.ferguson.com",
    "wof:name":"Ferguson Waterworks",
    "wof:placetype":"venue"
},
  "geometry": {"coordinates":[-76.533119,38.98455],"type":"Point"}
}