{
  "type": "Feature",
  "properties": {
    "iso:country":"US",
    "sg:address":"506 6th Ave",
    "sg:city":"Brunswick",
    "sg:classifiers":[
        {
            "category":"Retail",
            "subcategory":"Veterinary Services",
            "type":"Services"
        }
    ],
    "sg:phone":"+1 301 834 7903",
    "sg:postcode":"21716",
    "sg:province":"MD",
    "sg:tags":[
        "specialty"
    ],
    "wof:name":"Lewis Vca Animal Hospital",
    "wof:placetype":"venue"
},
  "geometry": {"coordinates":[-77.61769,39.315727],"type":"Point"}
}