{
  "type": "Feature",
  "properties": {
    "iso:country":"US",
    "sg:address":"911 Silver Spring Ave",
    "sg:city":"Silver Spring",
    "sg:classifiers":[
        {
            "category":"Professional",
            "subcategory":"Management & Consulting",
            "type":"Services"
        }
    ],
    "sg:phone":"+1 301 565 0515",
    "sg:postcode":"20910",
    "sg:province":"MD",
    "sg:tags":[
        "consultant",
        "business"
    ],
    "wof:name":"H & B Unlimited-HHH",
    "wof:placetype":"venue"
},
  "geometry": {"coordinates":[-77.025466,38.991728],"type":"Point"}
}