{
  "type": "Feature",
  "properties": {
    "addr:full":"4938 Hamden Ln. Bethesda MD 20814",
    "addr:housenumber":"4938",
    "addr:postcode":"20814",
    "addr:street":"Hamden Ln.",
    "iso:country":"US",
    "sg:address":"4938 Hamden Ln.",
    "sg:city":"Bethesda",
    "sg:classifiers":[
        {
            "category":"Building & Trades",
            "subcategory":"Plumbing",
            "type":"Services"
        }
    ],
    "sg:phone":"+1 301 358 3794",
    "sg:postcode":"20814",
    "sg:province":"MD",
    "sg:website":"plumberinbethesda.info",
    "wof:name":"Stang Plumbing",
    "wof:placetype":"venue"
},
  "geometry": {"coordinates":[-77.097565,38.982473],"type":"Point"}
}