{
  "type": "Feature",
  "properties": {
    "addr:full":"9022 Scotch Pine Ct Columbia MD 21045",
    "addr:housenumber":"9022",
    "addr:postcode":"21045",
    "addr:street":"Scotch Pine Ct",
    "iso:country":"US",
    "sg:address":"9022 Scotch Pine Ct",
    "sg:city":"Columbia",
    "sg:classifiers":[
        {
            "category":"Health Services",
            "subcategory":"Dentist",
            "type":"Services"
        }
    ],
    "sg:phone":"+1 410 992 4535",
    "sg:postcode":"21045",
    "sg:province":"MD",
    "wof:name":"Knopf David",
    "wof:placetype":"venue"
},
  "geometry": {"coordinates":[-76.825401,39.221199],"type":"Point"}
}