{
  "type": "Feature",
  "properties": {
    "addr:full":"6505 Belcrest Rd Hyattsville MD 20782",
    "addr:housenumber":"6505",
    "addr:postcode":"20782",
    "addr:street":"Belcrest Rd",
    "iso:country":"US",
    "sg:address":"6505 Belcrest Rd",
    "sg:city":"Hyattsville",
    "sg:classifiers":[
        {
            "category":"Health Services",
            "subcategory":"Doctor",
            "type":"Services"
        }
    ],
    "sg:phone":"+1 301 699 5902",
    "sg:postcode":"20782",
    "sg:province":"MD",
    "sg:tags":[
        "physician",
        "surgeon"
    ],
    "wof:name":"John E Zucker MD",
    "wof:placetype":"venue"
},
  "geometry": {"coordinates":[-76.953884,38.96821],"type":"Point"}
}