{
  "type": "Feature",
  "properties": {
    "iso:country":"US",
    "sg:address":"10150 Bacon Dr",
    "sg:city":"Beltsville",
    "sg:classifiers":[
        {
            "category":"Wholesale",
            "subcategory":"Machinery & Supplies",
            "type":"Manufacturing & Wholesale Goods"
        }
    ],
    "sg:phone":"+1 301 595 0360",
    "sg:postcode":"20705",
    "sg:province":"MD",
    "sg:tags":[
        "salon",
        "beauty"
    ],
    "wof:name":"Potomac Sales Co",
    "wof:placetype":"venue"
},
  "geometry": {"coordinates":[-76.912918,39.02916],"type":"Point"}
}