{
  "type": "Feature",
  "properties": {
    "iso:country":"US",
    "sg:address":"6901 York Rd",
    "sg:city":"Baltimore",
    "sg:classifiers":[
        {
            "category":"Shopping",
            "subcategory":"Pharmacy",
            "type":"Retail Goods"
        }
    ],
    "sg:phone":"+1 410 377 5600",
    "sg:postcode":"21212",
    "sg:province":"MD",
    "wof:name":"Purdum Pharmacy",
    "wof:placetype":"venue"
},
  "geometry": {"coordinates":[-76.60824599999999,39.379359],"type":"Point"}
}