{
  "type": "Feature",
  "properties": {
    "addr:full":"3173 Harness Creek Rd Annapolis MD 21403",
    "addr:housenumber":"3173",
    "addr:postcode":"21403",
    "addr:street":"Harness Creek Rd",
    "iso:country":"US",
    "sg:address":"3173 Harness Creek Rd",
    "sg:city":"Annapolis",
    "sg:classifiers":[
        {
            "category":"Professional",
            "subcategory":"Management & Consulting",
            "type":"Services"
        }
    ],
    "sg:phone":"+1 410 267 8667",
    "sg:postcode":"21403",
    "sg:province":"MD",
    "sg:tags":[
        "consultant"
    ],
    "wof:name":"Mind Over Media",
    "wof:placetype":"venue"
},
  "geometry": {"coordinates":[-76.51190800000001,38.944034],"type":"Point"}
}