{
  "type": "Feature",
  "properties": {
    "addr:full":"7829 Marlboro Pike District Heights MD 20747",
    "addr:housenumber":"7829",
    "addr:postcode":"20747",
    "addr:street":"Marlboro Pike",
    "iso:country":"US",
    "sg:address":"7829 Marlboro Pike",
    "sg:city":"District Heights",
    "sg:classifiers":[
        {
            "category":"Retail",
            "subcategory":"Auto Repair",
            "type":"Services"
        }
    ],
    "sg:phone":"+1 301 736 0700",
    "sg:postcode":"20747",
    "sg:province":"MD",
    "wof:name":"Advantage Auto Care",
    "wof:placetype":"venue"
},
  "geometry": {"coordinates":[-76.86990400000001,38.8419],"type":"Point"}
}