{
  "type": "Feature",
  "properties": {
    "addr:full":"609 Fieldstone Rd Silver Spring MD 20905",
    "addr:housenumber":"609",
    "addr:postcode":"20905",
    "addr:street":"Fieldstone Rd",
    "iso:country":"US",
    "sg:address":"609 Fieldstone Rd",
    "sg:city":"Silver Spring",
    "sg:classifiers":[
        {
            "category":"Retail",
            "subcategory":"Pet Boarding",
            "type":"Services"
        }
    ],
    "sg:phone":"+1 240 271 6060",
    "sg:postcode":"20905",
    "sg:province":"MD",
    "sg:tags":[
        "boarding/pet",
        "sitting"
    ],
    "wof:name":"Peace of Mind Pet Sitters",
    "wof:placetype":"venue"
},
  "geometry": {"coordinates":[-77.021383,39.10031],"type":"Point"}
}