{
  "type": "Feature",
  "properties": {
    "addr:full":"2305 Cleanleigh Dr Parkville MD 21234",
    "addr:housenumber":"2305",
    "addr:postcode":"21234",
    "addr:street":"Cleanleigh Dr",
    "iso:country":"US",
    "sg:address":"2305 Cleanleigh Dr",
    "sg:city":"Parkville",
    "sg:classifiers":[
        {
            "category":"Professional",
            "type":"Services"
        },
        {
            "category":"Restaurant",
            "type":"Food & Drink"
        }
    ],
    "sg:phone":"+1 410 661 0630",
    "sg:postcode":"21234",
    "sg:province":"MD",
    "sg:tags":[
        "style",
        "seafood",
        "family",
        "caterer"
    ],
    "wof:name":"Perring Place Restaurant",
    "wof:placetype":"venue"
},
  "geometry": {"coordinates":[-76.567404,39.372473],"type":"Point"}
}