{
  "type": "Feature",
  "properties": {
    "iso:country":"US",
    "sg:address":"40581 Bishop Rd",
    "sg:city":"Mechanicsville",
    "sg:classifiers":[
        {
            "category":"Shopping",
            "subcategory":"Music",
            "type":"Retail Goods"
        }
    ],
    "sg:phone":"+1 301 475 8446",
    "sg:postcode":"20659",
    "sg:province":"MD",
    "sg:tags":[
        "compact",
        "record",
        "disc",
        "tape"
    ],
    "wof:name":"Country Bluegrass Record Store",
    "wof:placetype":"venue"
},
  "geometry": {"coordinates":[-76.661401,38.369861],"type":"Point"}
}