{
  "type": "Feature",
  "properties": {
    "addr:full":"419 W Redwood St Ste 600 Baltimore MD 21201",
    "addr:housenumber":"419",
    "addr:postcode":"21201",
    "addr:street":"W Redwood St Ste 600",
    "iso:country":"US",
    "sg:address":"419 W Redwood St Ste 600",
    "sg:city":"Baltimore",
    "sg:classifiers":[
        {
            "category":"Health Services",
            "subcategory":"Doctor",
            "type":"Services"
        },
        {
            "category":"Health Services",
            "subcategory":"Hospital",
            "type":"Services"
        }
    ],
    "sg:phone":"+1 410 328 5196",
    "sg:postcode":"21201",
    "sg:province":"MD",
    "wof:name":"Saunders Elijah MD",
    "wof:placetype":"venue"
},
  "geometry": {"coordinates":[-76.62193499999999,39.288293],"type":"Point"}
}