{
  "type": "Feature",
  "properties": {
    "iso:country":"US",
    "sg:address":"9125 Whiskey Bottom Rd",
    "sg:city":"Laurel",
    "sg:classifiers":[
        {
            "category":"Home & Garden",
            "subcategory":"Building Materials",
            "type":"Retail Goods"
        },
        {
            "category":"Building & Trades",
            "subcategory":"Construction",
            "type":"Services"
        }
    ],
    "sg:phone":"+1 301 658 7651",
    "sg:postcode":"20723",
    "sg:province":"MD",
    "sg:tags":[
        "garage",
        "opener",
        "door",
        "specialty"
    ],
    "sg:website":"http://baltimore.citysearch.com/profile/external/649900900/laurel_md/precision_door.html?publisher=yellowpages&reference_id=7&placement=ypwebsitemip",
    "wof:name":"Precision Door",
    "wof:placetype":"venue"
},
  "geometry": {"coordinates":[-76.829247,39.114746],"type":"Point"}
}