{
  "type": "Feature",
  "properties": {
    "iso:country":"US",
    "sg:address":"3290 Centennial Ln",
    "sg:city":"Ellicott City",
    "sg:classifiers":[
        {
            "category":"Restaurant",
            "type":"Food & Drink"
        }
    ],
    "sg:menulink":"http://www.allmenus.com/md/ellicott-city/210634-arbys/menu/",
    "sg:phone":"+1 410 480 1831",
    "sg:postcode":"21042",
    "sg:province":"MD",
    "sg:tags":[
        "burger",
        "american"
    ],
    "wof:name":"Arby's",
    "wof:placetype":"venue"
},
  "geometry": {"coordinates":[-76.860669,39.278687],"type":"Point"}
}