{
  "type": "Feature",
  "properties": {
    "iso:country":"US",
    "sg:address":"3538 Old York Rd",
    "sg:city":"Baltimore",
    "sg:classifiers":[
        {
            "category":"Organizations",
            "subcategory":"Religious Organization",
            "type":"Services"
        }
    ],
    "sg:phone":"+1 410 243 3066",
    "sg:postcode":"21218",
    "sg:province":"MD",
    "sg:tags":[
        "church"
    ],
    "wof:name":"Delverance Church Of God",
    "wof:placetype":"venue"
},
  "geometry": {"coordinates":[-76.607962,39.332225],"type":"Point"}
}