{
  "type": "Feature",
  "properties": {
    "addr:full":"5330 Long Corner Rd White Hall MD 21161",
    "addr:housenumber":"5330",
    "addr:postcode":"21161",
    "addr:street":"Long Corner Rd",
    "iso:country":"US",
    "sg:address":"5330 Long Corner Rd",
    "sg:city":"White Hall",
    "sg:classifiers":[
        {
            "category":"Building & Trades",
            "subcategory":"Cleaning & Sanitation",
            "type":"Services"
        }
    ],
    "sg:phone":"+1 410 692 2700",
    "sg:postcode":"21161",
    "sg:province":"MD",
    "sg:tags":[
        "fireplace",
        "chimney"
    ],
    "wof:name":"August West Chimney Sweep",
    "wof:placetype":"venue"
},
  "geometry": {"coordinates":[-76.558164,39.700602],"type":"Point"}
}