{
  "type": "Feature",
  "properties": {
    "iso:country":"US",
    "sg:address":"188 Mountain Hill Rd",
    "sg:city":"Perryville",
    "sg:classifiers":[
        {
            "category":"Organizations",
            "subcategory":"Religious Organization",
            "type":"Services"
        }
    ],
    "sg:phone":"+1 410 642 6011",
    "sg:postcode":"21903",
    "sg:province":"MD",
    "sg:tags":[
        "clergy"
    ],
    "wof:name":"Buddy Flosser",
    "wof:placetype":"venue"
},
  "geometry": {"coordinates":[-76.01945499999999,39.560689],"type":"Point"}
}