{
  "type": "Feature",
  "properties": {
    "addr:full":"5001 Belair Rd Baltimore MD 21206",
    "addr:housenumber":"5001",
    "addr:postcode":"21206",
    "addr:street":"Belair Rd",
    "iso:country":"US",
    "sg:address":"5001 Belair Rd",
    "sg:city":"Baltimore",
    "sg:classifiers":[
        {
            "category":"Autos & Motor Vehicles",
            "subcategory":"Automobile Sales",
            "type":"Retail Goods"
        },
        {
            "category":"Retail",
            "subcategory":"Auto Rental",
            "type":"Services"
        }
    ],
    "sg:phone":"+1 410 488 0973",
    "sg:postcode":"21206",
    "sg:province":"MD",
    "sg:tags":[
        "car",
        "leasing",
        "truck"
    ],
    "sg:website":"http://www.enterprise.com/car_rental/deeplinkmap.do?gpbr=1828&bid=004&cnty=US&arc=YPTRL01&cm_mmc=Yellowpages.com-_-IYP-_-Tradelisting-_-branch",
    "wof:name":"Enterprise Rent-A-Car",
    "wof:placetype":"venue"
},
  "geometry": {"coordinates":[-76.55507799999999,39.335478],"type":"Point"}
}