{
  "type": "Feature",
  "properties": {
    "addr:full":"10073 Vista Ct Myersville MD 21773",
    "addr:housenumber":"10073",
    "addr:postcode":"21773",
    "addr:street":"Vista Ct",
    "iso:country":"US",
    "sg:address":"10073 Vista Ct",
    "sg:city":"Myersville",
    "sg:classifiers":[
        {
            "category":"Real Estate",
            "subcategory":"Real Estate Operator",
            "type":"Services"
        }
    ],
    "sg:phone":"+1 301 293 1785",
    "sg:postcode":"21773",
    "sg:province":"MD",
    "sg:tags":[
        "building",
        "apartment"
    ],
    "wof:name":"Fredrick Town Associates",
    "wof:placetype":"venue"
},
  "geometry": {"coordinates":[-77.536126,39.506823],"type":"Point"}
}