{
  "type": "Feature",
  "properties": {
    "addr:full":"7608 Baltimore Annapolis Blvd Glen Burnie MD 21060",
    "addr:housenumber":"7608",
    "addr:postcode":"21060",
    "addr:street":"Baltimore Annapolis Blvd",
    "iso:country":"US",
    "sg:address":"7608 Baltimore Annapolis Blvd",
    "sg:city":"Glen Burnie",
    "sg:classifiers":[
        {
            "category":"Restaurant",
            "type":"Food & Drink"
        }
    ],
    "sg:phone":"+1 410 787 0847",
    "sg:postcode":"21060",
    "sg:province":"MD",
    "wof:name":"BNA Cafe LLC",
    "wof:placetype":"venue"
},
  "geometry": {"coordinates":[-76.61086899999999,39.158731],"type":"Point"}
}