{
  "type": "Feature",
  "properties": {
    "addr:full":"6400 Frederick Rd Catonsville MD 21228",
    "addr:housenumber":"6400",
    "addr:postcode":"21228",
    "addr:street":"Frederick Rd",
    "iso:country":"US",
    "sg:address":"6400 Frederick Rd",
    "sg:city":"Catonsville",
    "sg:classifiers":[
        {
            "category":"Freight",
            "type":"Transportation"
        }
    ],
    "sg:phone":"+1 410 788 2307",
    "sg:postcode":"21228",
    "sg:province":"MD",
    "sg:tags":[
        "delivery"
    ],
    "wof:name":"Premier Delivery",
    "wof:placetype":"venue"
},
  "geometry": {"coordinates":[-76.71762099999999,39.275466],"type":"Point"}
}