{
  "type": "Feature",
  "properties": {
    "iso:country":"US",
    "sg:address":"227 Wintergull Ln",
    "sg:city":"Annapolis",
    "sg:classifiers":[
        {
            "category":"Professional",
            "subcategory":"Art Services",
            "type":"Services"
        }
    ],
    "sg:phone":"+1 410 757 4478",
    "sg:postcode":"21409",
    "sg:province":"MD",
    "sg:tags":[
        "graphic",
        "design"
    ],
    "wof:name":"Gina M Moriarty",
    "wof:placetype":"venue"
},
  "geometry": {"coordinates":[-76.435806,39.031482],"type":"Point"}
}