{
  "type": "Feature",
  "properties": {
    "iso:country":"US",
    "sg:address":"5506 Carville Ave",
    "sg:city":"Halethorpe",
    "sg:classifiers":[
        {
            "category":"Building & Trades",
            "subcategory":"Construction",
            "type":"Services"
        }
    ],
    "sg:phone":"+1 410 242 8810",
    "sg:postcode":"21227",
    "sg:province":"MD",
    "sg:tags":[
        "television",
        "telephone",
        "cable",
        "contractor"
    ],
    "wof:name":"Ault Communications",
    "wof:placetype":"venue"
},
  "geometry": {"coordinates":[-76.69405,39.24524],"type":"Point"}
}