{
  "type": "Feature",
  "properties": {
    "iso:country":"US",
    "sg:address":"614 Yorkminster Ct",
    "sg:city":"Westminster",
    "sg:classifiers":[
        {
            "category":"Building & Trades",
            "subcategory":"Construction",
            "type":"Services"
        }
    ],
    "sg:phone":"+1 410 857 0380",
    "sg:postcode":"21158",
    "sg:province":"MD",
    "sg:tags":[
        "home",
        "improvement"
    ],
    "wof:name":"Loewner & Sons Inc",
    "wof:placetype":"venue"
},
  "geometry": {"coordinates":[-77.017349,39.650223],"type":"Point"}
}