{
  "type": "Feature",
  "properties": {
    "addr:full":"30 W Patrick St Frederick MD 21701",
    "addr:housenumber":"30",
    "addr:postcode":"21701",
    "addr:street":"W Patrick St",
    "iso:country":"US",
    "sg:address":"30 W Patrick St",
    "sg:city":"Frederick",
    "sg:classifiers":[
        {
            "category":"Building & Trades",
            "subcategory":"Construction",
            "type":"Services"
        }
    ],
    "sg:phone":"+1 301 682 6127",
    "sg:postcode":"21701",
    "sg:province":"MD",
    "sg:tags":[
        "home",
        "builder"
    ],
    "wof:name":"Greystone Homes",
    "wof:placetype":"venue"
},
  "geometry": {"coordinates":[-77.411931,39.414159],"type":"Point"}
}