{
  "type": "Feature",
  "properties": {
    "addr:full":"2069 Montevideo Rd Jessup MD 20794",
    "addr:housenumber":"2069",
    "addr:postcode":"20794",
    "addr:street":"Montevideo Rd",
    "iso:country":"US",
    "sg:address":"2069 Montevideo Rd",
    "sg:city":"Jessup",
    "sg:classifiers":[
        {
            "category":"Retail",
            "subcategory":"Animal Services",
            "type":"Services"
        }
    ],
    "sg:phone":"+1 410 799 2069",
    "sg:postcode":"20794",
    "sg:province":"MD",
    "wof:name":"The Fireplug Inc",
    "wof:placetype":"venue"
},
  "geometry": {"coordinates":[-76.76233999999999,39.160758],"type":"Point"}
}