{
  "type": "Feature",
  "properties": {
    "iso:country":"US",
    "sg:address":"31 Hopkins Plz Ste 500",
    "sg:city":"Baltimore",
    "sg:classifiers":[
        {
            "category":"Professional",
            "subcategory":"Management & Consulting",
            "type":"Services"
        },
        {
            "category":"Government",
            "subcategory":"Office",
            "type":"Public Place"
        }
    ],
    "sg:phone":"+1 410 579 5011",
    "sg:postcode":"21201",
    "sg:province":"MD",
    "sg:tags":[
        "government-state",
        "beverage",
        "food",
        "consultant"
    ],
    "wof:name":"Baltimore Ii Field Office",
    "wof:placetype":"venue"
},
  "geometry": {"coordinates":[-76.61634100000001,39.289295],"type":"Point"}
}