{
  "type": "Feature",
  "properties": {
    "addr:full":"7745 Eastpoint Mall Baltimore MD 21224",
    "addr:housenumber":"7745",
    "addr:postcode":"21224",
    "addr:street":"Eastpoint Mall",
    "iso:country":"US",
    "sg:address":"7745 Eastpoint Mall",
    "sg:city":"Baltimore",
    "sg:classifiers":[
        {
            "category":"Retail",
            "subcategory":"Repair Shop",
            "type":"Services"
        }
    ],
    "sg:phone":"+1 410 284 2228",
    "sg:postcode":"21224",
    "sg:province":"MD",
    "sg:tags":[
        "watch",
        "clock"
    ],
    "sg:website":"http://www.dakotawatch.com",
    "wof:name":"Cooper",
    "wof:placetype":"venue"
},
  "geometry": {"coordinates":[-76.513283,39.294071],"type":"Point"}
}