{
  "type": "Feature",
  "properties": {
    "addr:full":"785 Martin Ct E Severn MD 21144",
    "addr:housenumber":"785",
    "addr:postcode":"21144",
    "addr:street":"Martin Ct E",
    "iso:country":"US",
    "sg:address":"785 Martin Ct E",
    "sg:city":"Severn",
    "sg:classifiers":[
        {
            "category":"Professional",
            "subcategory":"Advertising",
            "type":"Services"
        }
    ],
    "sg:phone":"+1 410 969 8918",
    "sg:postcode":"21144",
    "sg:province":"MD",
    "sg:tags":[
        "guide"
    ],
    "wof:name":"Yellow Page Reference Guide",
    "wof:placetype":"venue"
},
  "geometry": {"coordinates":[-76.64738199999999,39.128154],"type":"Point"}
}