{
  "type": "Feature",
  "properties": {
    "iso:country":"US",
    "sg:address":"7312 Holabird Ave",
    "sg:city":"Baltimore",
    "sg:classifiers":[
        {
            "category":"Bars & Pubs",
            "type":"Food & Drink"
        }
    ],
    "sg:phone":"+1 410 282 6050",
    "sg:postcode":"21222",
    "sg:province":"MD",
    "wof:name":"Howard's Deli & Pub",
    "wof:placetype":"venue"
},
  "geometry": {"coordinates":[-76.512725,39.272199],"type":"Point"}
}