{
  "type": "Feature",
  "properties": {
    "iso:country":"US",
    "sg:address":"5559 Harford St",
    "sg:city":"Churchton",
    "sg:classifiers":[
        {
            "category":"Professional",
            "subcategory":"Computer Services",
            "type":"Services"
        }
    ],
    "sg:phone":"+1 410 867 8078",
    "sg:postcode":"20733",
    "sg:province":"MD",
    "sg:tags":[
        "technical",
        "assistance",
        "support"
    ],
    "wof:name":"Last World The",
    "wof:placetype":"venue"
},
  "geometry": {"coordinates":[-76.51090600000001,38.802223],"type":"Point"}
}