{
  "type": "Feature",
  "properties": {
    "addr:full":"32 E Bel Air Ave Aberdeen MD 21001",
    "addr:housenumber":"32",
    "addr:postcode":"21001",
    "addr:street":"E Bel Air Ave",
    "iso:country":"US",
    "sg:address":"32 E Bel Air Ave",
    "sg:city":"Aberdeen",
    "sg:classifiers":[
        {
            "category":"Personal",
            "type":"Services"
        }
    ],
    "sg:phone":"+1 410 272 4173",
    "sg:postcode":"21001",
    "sg:province":"MD",
    "wof:name":"Fathers & Sons 1 John 313",
    "wof:placetype":"venue"
},
  "geometry": {"coordinates":[-76.160005,39.507693],"type":"Point"}
}