{
  "type": "Feature",
  "properties": {
    "iso:country":"US",
    "sg:address":"401 Grist Mill Xing",
    "sg:city":"Severna Park",
    "sg:classifiers":[
        {
            "category":"Professional",
            "subcategory":"Accounting & Tax Preparation",
            "type":"Services"
        }
    ],
    "sg:phone":"+1 410 987 8605",
    "sg:postcode":"21146",
    "sg:province":"MD",
    "sg:tags":[
        "return",
        "filing"
    ],
    "wof:name":"Anne Arundel Accounting & Tax",
    "wof:placetype":"venue"
},
  "geometry": {"coordinates":[-76.602605,39.087787],"type":"Point"}
}