{
  "type": "Feature",
  "properties": {
    "addr:full":"20708 Spinning Wheel Pl Germantown MD 20874",
    "addr:postcode":"20708;20874",
    "addr:street":"Spinning Wheel Pl",
    "iso:country":"US",
    "sg:address":"20708 Spinning Wheel Pl",
    "sg:city":"Germantown",
    "sg:classifiers":[
        {
            "category":"Real Estate",
            "subcategory":"Real Estate Agent",
            "type":"Services"
        }
    ],
    "sg:phone":"+1 301 540 8110",
    "sg:postcode":"20874",
    "sg:province":"MD",
    "sg:tags":[
        "consultant"
    ],
    "wof:name":"Idc Technologies Inc",
    "wof:placetype":"venue"
},
  "geometry": {"coordinates":[-77.28546900000001,39.196522],"type":"Point"}
}