{
  "type": "Feature",
  "properties": {
    "iso:country":"US",
    "sg:address":"19254 Chandlee Mill Rd",
    "sg:city":"Sandy Spring",
    "sg:classifiers":[
        {
            "category":"Building & Trades",
            "subcategory":"Plumbing",
            "type":"Services"
        }
    ],
    "sg:phone":"+1 301 774 7109",
    "sg:postcode":"20860",
    "sg:province":"MD",
    "sg:tags":[
        "cont"
    ],
    "wof:name":"Brians Heating & AC",
    "wof:placetype":"venue"
},
  "geometry": {"coordinates":[-77.029098,39.171027],"type":"Point"}
}