{
  "type": "Feature",
  "properties": {
    "iso:country":"US",
    "sg:address":"126 E Main St",
    "sg:city":"Westminster",
    "sg:classifiers":[
        {
            "category":"Professional",
            "subcategory":"Business Services",
            "type":"Services"
        }
    ],
    "sg:phone":"+1 410 840 9696",
    "sg:postcode":"21157",
    "sg:province":"MD",
    "sg:tags":[
        "appraiser"
    ],
    "wof:name":"Advantage Home Appraisers",
    "wof:placetype":"venue"
},
  "geometry": {"coordinates":[-76.992782,39.571977],"type":"Point"}
}