{
  "type": "Feature",
  "properties": {
    "iso:country":"US",
    "sg:address":"4 S Mccain Dr",
    "sg:city":"Frederick",
    "sg:classifiers":[
        {
            "category":"Building & Trades",
            "subcategory":"Construction",
            "type":"Services"
        },
        {
            "category":"Home & Garden",
            "subcategory":"Carpets & Floor Coverings",
            "type":"Retail Goods"
        }
    ],
    "sg:phone":"+1 301 695 5122",
    "sg:postcode":"21703",
    "sg:province":"MD",
    "sg:tags":[
        "tile-contractors",
        "rug",
        "flooring",
        "contractor"
    ],
    "wof:name":"Abbey Carpet Of Frederick",
    "wof:placetype":"venue"
},
  "geometry": {"coordinates":[-77.45343699999999,39.418427],"type":"Point"}
}