{
  "type": "Feature",
  "properties": {
    "iso:country":"US",
    "sg:address":"1952 West St",
    "sg:city":"Annapolis",
    "sg:classifiers":[
        {
            "category":"Restaurant",
            "type":"Food & Drink"
        }
    ],
    "sg:menulink":"http://www.allmenus.com/md/annapolis/197122-burger-king/menu/",
    "sg:phone":"+1 410 573 1474",
    "sg:postcode":"21401",
    "sg:province":"MD",
    "sg:tags":[
        "burger",
        "american"
    ],
    "wof:name":"Burger King",
    "wof:placetype":"venue"
},
  "geometry": {"coordinates":[-76.528514,38.98128],"type":"Point"}
}