{
  "type": "Feature",
  "properties": {
    "addr:full":"13350 New Hampshire Ave Silver Spring MD 20904",
    "addr:housenumber":"13350",
    "addr:postcode":"20904",
    "addr:street":"New Hampshire Ave",
    "iso:country":"US",
    "sg:address":"13350 New Hampshire Ave",
    "sg:city":"Silver Spring",
    "sg:classifiers":[
        {
            "category":"Banks & Credit Unions",
            "subcategory":"Financial Services",
            "type":"Services"
        }
    ],
    "sg:phone":"+1 301 384 9601",
    "sg:postcode":"20904",
    "sg:province":"MD",
    "sg:tags":[
        "broker",
        "mortgage"
    ],
    "wof:name":"Bb&t",
    "wof:placetype":"venue"
},
  "geometry": {"coordinates":[-77.00248000000001,39.074833],"type":"Point"}
}