{
  "type": "Feature",
  "properties": {
    "addr:full":"2509 Baltimore Blvd Finksburg MD 21048",
    "addr:housenumber":"2509",
    "addr:postcode":"21048",
    "addr:street":"Baltimore Blvd",
    "iso:country":"US",
    "sg:address":"2509 Baltimore Blvd",
    "sg:city":"Finksburg",
    "sg:classifiers":[
        {
            "category":"Professional",
            "subcategory":"Accounting & Tax Preparation",
            "type":"Services"
        }
    ],
    "sg:phone":"+1 410 876 5148",
    "sg:postcode":"21048",
    "sg:province":"MD",
    "sg:tags":[
        "billing"
    ],
    "wof:name":"Eutaw Onocology Assoc",
    "wof:placetype":"venue"
},
  "geometry": {"coordinates":[-76.906953,39.510943],"type":"Point"}
}