{
  "type": "Feature",
  "properties": {
    "addr:full":"265 Shakespeare Dr Severna Park MD 21146",
    "addr:housenumber":"265",
    "addr:postcode":"21146",
    "addr:street":"Shakespeare Dr",
    "iso:country":"US",
    "sg:address":"265 Shakespeare Dr",
    "sg:city":"Severna Park",
    "sg:classifiers":[
        {
            "category":"Professional",
            "subcategory":"Business Services",
            "type":"Services"
        }
    ],
    "sg:phone":"+1 410 544 7229",
    "sg:postcode":"21146",
    "sg:province":"MD",
    "wof:name":"United Ostomy Assoc",
    "wof:placetype":"venue"
},
  "geometry": {"coordinates":[-76.538178,39.094022],"type":"Point"}
}