{
  "type": "Feature",
  "properties": {
    "addr:full":"223 E Main St Westminster MD 21157",
    "addr:housenumber":"223",
    "addr:postcode":"21157",
    "addr:street":"E Main St",
    "iso:country":"US",
    "sg:address":"223 E Main St",
    "sg:city":"Westminster",
    "sg:classifiers":[
        {
            "category":"Real Estate",
            "subcategory":"Real Estate Services",
            "type":"Services"
        }
    ],
    "sg:phone":"+1 410 876 7153",
    "sg:postcode":"21157",
    "sg:province":"MD",
    "sg:tags":[
        "title"
    ],
    "wof:name":"Property Insight",
    "wof:placetype":"venue"
},
  "geometry": {"coordinates":[-76.98978,39.569125],"type":"Point"}
}