{
  "type": "Feature",
  "properties": {
    "iso:country":"US",
    "sg:address":"511 Cider Press Ct",
    "sg:city":"Joppa",
    "sg:classifiers":[
        {
            "category":"Home & Garden",
            "subcategory":"Home Furnishings",
            "type":"Retail Goods"
        }
    ],
    "sg:phone":"+1 410 679 5566",
    "sg:postcode":"21085",
    "sg:province":"MD",
    "sg:tags":[
        "window",
        "covering"
    ],
    "wof:name":"Valerie Thurmond Interiors",
    "wof:placetype":"venue"
},
  "geometry": {"coordinates":[-76.35624,39.418476],"type":"Point"}
}