{
  "type": "Feature",
  "properties": {
    "addr:full":"430 W Mulberry St Baltimore MD 21201",
    "addr:housenumber":"430",
    "addr:postcode":"21201",
    "addr:street":"W Mulberry St",
    "iso:country":"US",
    "sg:address":"430 W Mulberry St",
    "sg:city":"Baltimore",
    "sg:classifiers":[
        {
            "category":"Shopping",
            "type":"Retail Goods"
        }
    ],
    "sg:phone":"+1 410 244 7283",
    "sg:postcode":"21201",
    "sg:province":"MD",
    "sg:tags":[
        "awning",
        "canopy"
    ],
    "wof:name":"Awning Factory Outlet",
    "wof:placetype":"venue"
},
  "geometry": {"coordinates":[-76.622483,39.293919],"type":"Point"}
}