{
  "type": "Feature",
  "properties": {
    "addr:full":"3003 Princess Ct Manchester MD 21102",
    "addr:housenumber":"3003",
    "addr:postcode":"21102",
    "addr:street":"Princess Ct",
    "iso:country":"US",
    "sg:address":"3003 Princess Ct",
    "sg:city":"Manchester",
    "sg:classifiers":[
        {
            "category":"Building & Trades",
            "subcategory":"Construction",
            "type":"Services"
        }
    ],
    "sg:phone":"+1 410 239 0314",
    "sg:postcode":"21102",
    "sg:province":"MD",
    "sg:tags":[
        "home"
    ],
    "wof:name":"Capital Builders",
    "wof:placetype":"venue"
},
  "geometry": {"coordinates":[-76.887944,39.656241],"type":"Point"}
}