{
  "type": "Feature",
  "properties": {
    "iso:country":"US",
    "sg:address":"1803 Glen Ridge Rd",
    "sg:city":"Parkville",
    "sg:classifiers":[
        {
            "category":"Building & Trades",
            "subcategory":"Landscaping Services",
            "type":"Services"
        }
    ],
    "sg:phone":"+1 410 665 3683",
    "sg:postcode":"21234",
    "sg:province":"MD",
    "sg:tags":[
        "tree",
        "stump",
        "grinding",
        "removal"
    ],
    "wof:name":"Adept Stump & Tree Removal",
    "wof:placetype":"venue"
},
  "geometry": {"coordinates":[-76.567717,39.386349],"type":"Point"}
}