{
  "type": "Feature",
  "properties": {
    "addr:full":"356 Frenchtown Rd Elkton MD 21921",
    "addr:housenumber":"356",
    "addr:postcode":"21921",
    "addr:street":"Frenchtown Rd",
    "iso:country":"US",
    "sg:address":"356 Frenchtown Rd",
    "sg:city":"Elkton",
    "sg:classifiers":[
        {
            "category":"Professional",
            "subcategory":"Advertising",
            "type":"Services"
        }
    ],
    "sg:phone":"+1 410 398 2337",
    "sg:postcode":"21921",
    "sg:province":"MD",
    "wof:name":"B B Martin Outdoor Advg Co",
    "wof:placetype":"venue"
},
  "geometry": {"coordinates":[-75.823082,39.581809],"type":"Point"}
}