{
  "type": "Feature",
  "properties": {
    "addr:full":"5850 E Boniwood Turn Clinton MD 20735",
    "addr:housenumber":"5850",
    "addr:postcode":"20735",
    "addr:street":"E Boniwood Turn",
    "iso:country":"US",
    "sg:address":"5850 E Boniwood Turn",
    "sg:city":"Clinton",
    "sg:classifiers":[
        {
            "category":"Personal",
            "subcategory":"Beauty Salon",
            "type":"Services"
        }
    ],
    "sg:phone":"+1 301 856 4883",
    "sg:postcode":"20735",
    "sg:province":"MD",
    "wof:name":"Entourage Enterprizes",
    "wof:placetype":"venue"
},
  "geometry": {"coordinates":[-76.907112,38.728316],"type":"Point"}
}