{
  "type": "Feature",
  "properties": {
    "addr:full":"1010 Rockville Pike Rockville MD 20852",
    "addr:housenumber":"1010",
    "addr:postcode":"20852",
    "addr:street":"Rockville Pike",
    "iso:country":"US",
    "sg:address":"1010 Rockville Pike",
    "sg:city":"Rockville",
    "sg:classifiers":[
        {
            "category":"Insurance",
            "subcategory":"Insurance Agent",
            "type":"Services"
        }
    ],
    "sg:phone":"+1 301 315 6376",
    "sg:postcode":"20852",
    "sg:province":"MD",
    "wof:name":"Allstate Insurance",
    "wof:placetype":"venue"
},
  "geometry": {"coordinates":[-77.132137,39.071162],"type":"Point"}
}