{
  "type": "Feature",
  "properties": {
    "iso:country":"US",
    "sg:address":"5512 Greenock Rd",
    "sg:city":"Lothian",
    "sg:classifiers":[
        {
            "category":"Retail",
            "subcategory":"Animal Services",
            "type":"Services"
        }
    ],
    "sg:phone":"+1 410 741 9858",
    "sg:postcode":"20711",
    "sg:province":"MD",
    "sg:tags":[
        "horse",
        "training"
    ],
    "wof:name":"Red Rebel Stables",
    "wof:placetype":"venue"
},
  "geometry": {"coordinates":[-76.636452,38.812714],"type":"Point"}
}