{
  "type": "Feature",
  "properties": {
    "addr:full":"1013 S Salisbury Blvd Salisbury MD 21801",
    "addr:housenumber":"1013",
    "addr:postcode":"21801",
    "addr:street":"S Salisbury Blvd",
    "iso:country":"US",
    "sg:address":"1013 S Salisbury Blvd",
    "sg:city":"Salisbury",
    "sg:classifiers":[
        {
            "category":"Shopping",
            "subcategory":"Bicycles & Sporting Goods",
            "type":"Retail Goods"
        }
    ],
    "sg:phone":"+1 410 543 2453",
    "sg:postcode":"21801",
    "sg:province":"MD",
    "sg:website":"www.rmbikes.com",
    "wof:name":"Bike Sport",
    "wof:placetype":"venue"
},
  "geometry": {"coordinates":[-75.601665,38.350487],"type":"Point"}
}