{
  "type": "Feature",
  "properties": {
    "iso:country":"US",
    "sg:address":"103 S Gay St",
    "sg:city":"Baltimore",
    "sg:classifiers":[
        {
            "category":"Health Services",
            "subcategory":"Health Practitioner",
            "type":"Services"
        }
    ],
    "sg:phone":"+1 410 962 2133",
    "sg:postcode":"21202",
    "sg:province":"MD",
    "sg:tags":[
        "gambling",
        "addiction-information",
        "treatment"
    ],
    "wof:name":"Rehab R&D Evaluation",
    "wof:placetype":"venue"
},
  "geometry": {"coordinates":[-76.608749,39.287739],"type":"Point"}
}