{
  "type": "Feature",
  "properties": {
    "iso:country":"US",
    "sg:address":"11401 Rock Elm Ct",
    "sg:city":"Bowie",
    "sg:classifiers":[
        {
            "category":"Professional",
            "subcategory":"Management & Consulting",
            "type":"Services"
        }
    ],
    "sg:phone":"+1 301 442 8665",
    "sg:postcode":"20721",
    "sg:province":"MD",
    "sg:tags":[
        "business"
    ],
    "wof:name":"Bsg Consulting Services Inc",
    "wof:placetype":"venue"
},
  "geometry": {"coordinates":[-76.808494,38.925689],"type":"Point"}
}