{
  "type": "Feature",
  "properties": {
    "addr:full":"75 Buckler Rd Huntingtown MD 20639",
    "addr:housenumber":"75",
    "addr:postcode":"20639",
    "addr:street":"Buckler Rd",
    "iso:country":"US",
    "sg:address":"75 Buckler Rd",
    "sg:city":"Huntingtown",
    "sg:classifiers":[
        {
            "category":"Building & Trades",
            "subcategory":"Construction",
            "type":"Services"
        }
    ],
    "sg:phone":"+1 443 532 1124",
    "sg:postcode":"20639",
    "sg:province":"MD",
    "sg:tags":[
        "cabling",
        "wiring"
    ],
    "wof:name":"Bay Networking",
    "wof:placetype":"venue"
},
  "geometry": {"coordinates":[-76.60137400000001,38.563935],"type":"Point"}
}