{
  "type": "Feature",
  "properties": {
    "iso:country":"US",
    "sg:address":"7329 Harford Rd",
    "sg:city":"Baltimore",
    "sg:classifiers":[
        {
            "category":"Real Estate",
            "subcategory":"Real Estate Services",
            "type":"Services"
        },
        {
            "category":"Banks & Credit Unions",
            "subcategory":"Financial Services",
            "type":"Services"
        }
    ],
    "sg:phone":"+1 410 254 9000",
    "sg:postcode":"21234",
    "sg:province":"MD",
    "sg:tags":[
        "loan",
        "processing",
        "broker",
        "mortgage"
    ],
    "wof:name":"Better Home Loan Mortgage Corp",
    "wof:placetype":"venue"
},
  "geometry": {"coordinates":[-76.54608399999999,39.369543],"type":"Point"}
}