{
  "type": "Feature",
  "properties": {
    "addr:full":"8611 Larkin Rd Savage MD 20763",
    "addr:housenumber":"8611",
    "addr:postcode":"20763",
    "addr:street":"Larkin Rd",
    "iso:country":"US",
    "sg:address":"8611 Larkin Rd",
    "sg:city":"Savage",
    "sg:classifiers":[
        {
            "category":"Wholesale",
            "subcategory":"Auto Parts",
            "type":"Manufacturing & Wholesale Goods"
        }
    ],
    "sg:phone":"+1 301 498 8083",
    "sg:postcode":"20763",
    "sg:province":"MD",
    "sg:tags":[
        "automobile"
    ],
    "sg:website":"www.autotraining.net",
    "wof:name":"Automotive Training Institute",
    "wof:placetype":"venue"
},
  "geometry": {"coordinates":[-76.80962,39.135545],"type":"Point"}
}