{
  "type": "Feature",
  "properties": {
    "addr:full":"11920 Lynn Crest Rd Monrovia MD 21770",
    "addr:housenumber":"11920",
    "addr:postcode":"21770",
    "addr:street":"Lynn Crest Rd",
    "iso:country":"US",
    "sg:address":"11920 Lynn Crest Rd",
    "sg:city":"Monrovia",
    "sg:classifiers":[
        {
            "category":"Building & Trades",
            "subcategory":"Construction",
            "type":"Services"
        }
    ],
    "sg:phone":"+1 301 831 6037",
    "sg:postcode":"21770",
    "sg:province":"MD",
    "sg:tags":[
        "excavating",
        "contractor"
    ],
    "wof:name":"Tolley Enterprises Inc",
    "wof:placetype":"venue"
},
  "geometry": {"coordinates":[-77.246726,39.367464],"type":"Point"}
}