{
  "type": "Feature",
  "properties": {
    "iso:country":"US",
    "sg:address":"8775 Cloudleap Ct Ste 11",
    "sg:city":"Columbia",
    "sg:classifiers":[
        {
            "category":"Food & Beverages",
            "subcategory":"Groceries & Convenience Stores",
            "type":"Retail Goods"
        }
    ],
    "sg:phone":"+1 301 596 5858",
    "sg:postcode":"21045",
    "sg:province":"MD",
    "wof:name":"Safeway Food & Drug",
    "wof:placetype":"venue"
},
  "geometry": {"coordinates":[-76.81772599999999,39.208077],"type":"Point"}
}