{
  "type": "Feature",
  "properties": {
    "addr:full":"5313 Shepherd St Bladensburg MD 20710",
    "addr:housenumber":"5313",
    "addr:postcode":"20710",
    "addr:street":"Shepherd St",
    "iso:country":"US",
    "sg:address":"5313 Shepherd St",
    "sg:city":"Bladensburg",
    "sg:classifiers":[
        {
            "category":"Building & Trades",
            "subcategory":"Construction",
            "type":"Services"
        }
    ],
    "sg:phone":"+1 301 209 9003",
    "sg:postcode":"20710",
    "sg:province":"MD",
    "sg:tags":[
        "carpenter"
    ],
    "wof:name":"S R Banks Carpentry",
    "wof:placetype":"venue"
},
  "geometry": {"coordinates":[-76.92710599999999,38.939786],"type":"Point"}
}