{
  "type": "Feature",
  "properties": {
    "addr:full":"2525 Mountain Rd Pasadena MD 21122",
    "addr:housenumber":"2525",
    "addr:postcode":"21122",
    "addr:street":"Mountain Rd",
    "iso:country":"US",
    "sg:address":"2525 Mountain Rd",
    "sg:city":"Pasadena",
    "sg:classifiers":[
        {
            "category":"Professional",
            "subcategory":"Lawyer & Legal Services",
            "type":"Services"
        }
    ],
    "sg:phone":"+1 410 437 7711",
    "sg:postcode":"21122",
    "sg:province":"MD",
    "sg:tags":[
        "attorney"
    ],
    "wof:name":"Legal Clinic-Waldman Grossfeld",
    "wof:placetype":"venue"
},
  "geometry": {"coordinates":[-76.54386,39.128084],"type":"Point"}
}