{
  "type": "Feature",
  "properties": {
    "iso:country":"US",
    "sg:address":"5602 Groveland Ave",
    "sg:city":"Baltimore",
    "sg:classifiers":[
        {
            "category":"Professional",
            "subcategory":"Computer Services",
            "type":"Services"
        }
    ],
    "sg:phone":"+1 410 367 1726",
    "sg:postcode":"21215",
    "sg:province":"MD",
    "sg:tags":[
        "graphic"
    ],
    "wof:name":"Jupiter Graphik Sltn",
    "wof:placetype":"venue"
},
  "geometry": {"coordinates":[-76.700485,39.340698],"type":"Point"}
}