{
  "type": "Feature",
  "properties": {
    "addr:full":"745 Prime Outlets Blvd Hagerstown MD 21740",
    "addr:postcode":"21740",
    "addr:street":"Outlets Blvd",
    "iso:country":"US",
    "sg:address":"745 Prime Outlets Blvd",
    "sg:city":"Hagerstown",
    "sg:classifiers":[
        {
            "category":"Shopping",
            "subcategory":"Shoes",
            "type":"Retail Goods"
        }
    ],
    "sg:phone":"+1 301 791 9322",
    "sg:postcode":"21740",
    "sg:province":"MD",
    "wof:name":"Naturalizer Shoes",
    "wof:placetype":"venue"
},
  "geometry": {"coordinates":[-77.732677,39.607507],"type":"Point"}
}