{
  "type": "Feature",
  "properties": {
    "iso:country":"US",
    "sg:address":"17 Lake Ct",
    "sg:city":"Rockville",
    "sg:classifiers":[
        {
            "category":"Professional",
            "subcategory":"Business Services",
            "type":"Services"
        }
    ],
    "sg:phone":"+1 301 460 1135",
    "sg:postcode":"20853",
    "sg:province":"MD",
    "wof:name":"Aag Enterprises",
    "wof:placetype":"venue"
},
  "geometry": {"coordinates":[-77.11203,39.097787],"type":"Point"}
}