{
  "type": "Feature",
  "properties": {
    "iso:country":"US",
    "sg:address":"301 Hospital Dr",
    "sg:city":"Glen Burnie",
    "sg:classifiers":[
        {
            "category":"Health Services",
            "subcategory":"Hospital",
            "type":"Services"
        },
        {
            "category":"Shopping",
            "subcategory":"Gifts & Souvenirs",
            "type":"Retail Goods"
        }
    ],
    "sg:phone":"+1 410 787 4678",
    "sg:postcode":"21061",
    "sg:province":"MD",
    "wof:name":"North Arundel Hospital Gift Sp",
    "wof:placetype":"venue"
},
  "geometry": {"coordinates":[-76.621569,39.138604],"type":"Point"}
}