{
  "type": "Feature",
  "properties": {
    "addr:full":"4811 Kemper St Rockville MD 20853",
    "addr:housenumber":"4811",
    "addr:postcode":"20853",
    "addr:street":"Kemper St",
    "iso:country":"US",
    "sg:address":"4811 Kemper St",
    "sg:city":"Rockville",
    "sg:classifiers":[
        {
            "category":"Personal",
            "type":"Services"
        }
    ],
    "sg:phone":"+1 301 460 4442",
    "sg:postcode":"20853",
    "sg:province":"MD",
    "sg:tags":[
        "miscellaneous"
    ],
    "wof:name":"Personal Peptalks",
    "wof:placetype":"venue"
},
  "geometry": {"coordinates":[-77.09616800000001,39.079721],"type":"Point"}
}