{
  "type": "Feature",
  "properties": {
    "iso:country":"US",
    "sg:address":"3361 N Chatham Rd",
    "sg:city":"Ellicott City",
    "sg:classifiers":[
        {
            "category":"Professional",
            "subcategory":"Accounting & Tax Preparation",
            "type":"Services"
        }
    ],
    "sg:phone":"+1 410 461 0089",
    "sg:postcode":"21042",
    "sg:province":"MD",
    "wof:name":"Sohosmd",
    "wof:placetype":"venue"
},
  "geometry": {"coordinates":[-76.832035,39.278455],"type":"Point"}
}