{
  "type": "Feature",
  "properties": {
    "iso:country":"US",
    "sg:address":"13600 Baltimore Ave",
    "sg:city":"Laurel",
    "sg:classifiers":[
        {
            "category":"Restaurant",
            "type":"Food & Drink"
        }
    ],
    "sg:menulink":"http://www.allmenus.com/md/laurel/83590-three-brothers-italian-restaurant/menu/",
    "sg:phone":"+1 301 317 8888",
    "sg:postcode":"20707",
    "sg:province":"MD",
    "sg:tags":[
        "american",
        "pizza"
    ],
    "wof:name":"Three Brothers Italian Restaurant",
    "wof:placetype":"venue"
},
  "geometry": {"coordinates":[-76.868233,39.076247],"type":"Point"}
}