{
  "type": "Feature",
  "properties": {
    "iso:country":"US",
    "sg:address":"4600 Beech Way",
    "sg:city":"Temple Hills",
    "sg:classifiers":[
        {
            "category":"Building & Trades",
            "subcategory":"Construction",
            "type":"Services"
        }
    ],
    "sg:phone":"+1 301 324 6967",
    "sg:postcode":"20748",
    "sg:province":"MD",
    "sg:tags":[
        "foundation"
    ],
    "wof:name":"Atlas Foundations",
    "wof:placetype":"venue"
},
  "geometry": {"coordinates":[-76.943846,38.826299],"type":"Point"}
}