{
  "type": "Feature",
  "properties": {
    "addr:full":"3327 Superior Ln Bowie MD 20715",
    "addr:housenumber":"3327",
    "addr:postcode":"20715",
    "addr:street":"Superior Ln",
    "iso:country":"US",
    "sg:address":"3327 Superior Ln",
    "sg:city":"Bowie",
    "sg:classifiers":[
        {
            "category":"Personal",
            "subcategory":"Beauty Salon",
            "type":"Services"
        }
    ],
    "sg:phone":"+1 301 262 7900",
    "sg:postcode":"20715",
    "sg:province":"MD",
    "wof:name":"That Look Hair Gallery",
    "wof:placetype":"venue"
},
  "geometry": {"coordinates":[-76.73264500000001,38.978424],"type":"Point"}
}