{
  "type": "Feature",
  "properties": {
    "iso:country":"US",
    "sg:address":"6115 Old Branch Ave",
    "sg:city":"Temple Hills",
    "sg:classifiers":[
        {
            "category":"Personal",
            "subcategory":"Barber",
            "type":"Services"
        }
    ],
    "sg:phone":"+1 301 702 3234",
    "sg:postcode":"20748",
    "sg:province":"MD",
    "wof:name":"Inspirations Hair & Body Salon",
    "wof:placetype":"venue"
},
  "geometry": {"coordinates":[-76.908585,38.805433],"type":"Point"}
}