{
  "type": "Feature",
  "properties": {
    "addr:full":"17503 Redland Rd Derwood MD 20855",
    "addr:housenumber":"17503",
    "addr:postcode":"20855",
    "addr:street":"Redland Rd",
    "iso:country":"US",
    "sg:address":"17503 Redland Rd",
    "sg:city":"Derwood",
    "sg:classifiers":[
        {
            "category":"Cafe",
            "type":"Food & Drink"
        }
    ],
    "sg:menulink":"http://www.allmenus.com/md/rockville/282603-outta-the-way-cafe/menu/",
    "sg:phone":"+1 301 963 6895",
    "sg:postcode":"20855",
    "sg:province":"MD",
    "sg:tags":[
        "american"
    ],
    "wof:name":"Outta the Way Cafe",
    "wof:placetype":"venue"
},
  "geometry": {"coordinates":[-77.144046,39.143249],"type":"Point"}
}