{
  "type": "Feature",
  "properties": {
    "addr:full":"8585 Baltimore National Pike Ste 14 Ellicott City MD 21043",
    "addr:housenumber":"8585",
    "addr:postcode":"21043",
    "addr:street":"Baltimore National Pike Ste 14",
    "iso:country":"US",
    "sg:address":"8585 Baltimore National Pike Ste 14",
    "sg:city":"Ellicott City",
    "sg:classifiers":[
        {
            "category":"Professional",
            "subcategory":"Lawyer & Legal Services",
            "type":"Services"
        }
    ],
    "sg:phone":"+1 410 418 9070",
    "sg:postcode":"21043",
    "sg:province":"MD",
    "wof:name":"P Paul Cococros Attny",
    "wof:placetype":"venue"
},
  "geometry": {"coordinates":[-76.809179,39.282736],"type":"Point"}
}