{
  "type": "Feature",
  "properties": {
    "iso:country":"US",
    "sg:address":"9011 Annapolis Rd",
    "sg:city":"Lanham",
    "sg:classifiers":[
        {
            "category":"Autos & Motor Vehicles",
            "subcategory":"Auto Supplies",
            "type":"Retail Goods"
        },
        {
            "category":"Retail",
            "subcategory":"Auto Repair",
            "type":"Services"
        }
    ],
    "sg:phone":"+1 301 577 7400",
    "sg:postcode":"20706",
    "sg:province":"MD",
    "sg:tags":[
        "exhaust",
        "oil",
        "tire",
        "system",
        "lube",
        "brake",
        "muffler"
    ],
    "sg:website":"http://www.midaswashingtondc.com",
    "wof:name":"Midas",
    "wof:placetype":"venue"
},
  "geometry": {"coordinates":[-76.862612,38.961211],"type":"Point"}
}