{
  "type": "Feature",
  "properties": {
    "iso:country":"US",
    "sg:address":"2120 Windsor Dr",
    "sg:city":"Salisbury",
    "sg:classifiers":[
        {
            "category":"Professional",
            "subcategory":"Business Services",
            "type":"Services"
        }
    ],
    "sg:phone":"+1 410 742 5101",
    "sg:postcode":"21801",
    "sg:province":"MD",
    "sg:tags":[
        "paging",
        "answering"
    ],
    "wof:name":"CUSTOM.COM",
    "wof:placetype":"venue"
},
  "geometry": {"coordinates":[-75.582095,38.39934],"type":"Point"}
}