{
  "type": "Feature",
  "properties": {
    "addr:full":"8178 Lark Brown Rd # 301 Elkridge MD 21075",
    "addr:housenumber":"8178",
    "addr:postcode":"21075",
    "addr:street":"Lark Brown Rd # 301",
    "iso:country":"US",
    "sg:address":"8178 Lark Brown Rd # 301",
    "sg:city":"Elkridge",
    "sg:classifiers":[
        {
            "category":"Professional",
            "subcategory":"Engineering",
            "type":"Services"
        },
        {
            "category":"Professional",
            "subcategory":"Computer Services",
            "type":"Services"
        }
    ],
    "sg:phone":"+1 443 259 0630",
    "sg:postcode":"21075",
    "sg:province":"MD",
    "sg:tags":[
        "engineer",
        "consultant",
        "designer",
        "system",
        "integration"
    ],
    "wof:name":"Cpi",
    "wof:placetype":"venue"
},
  "geometry": {"coordinates":[-76.792682,39.18859],"type":"Point"}
}