{
  "type": "Feature",
  "properties": {
    "iso:country":"US",
    "sg:address":"4001 Clarks Ln",
    "sg:city":"Baltimore",
    "sg:classifiers":[
        {
            "category":"Social Services",
            "type":"Services"
        }
    ],
    "sg:phone":"+1 410 358 6279",
    "sg:postcode":"21215",
    "sg:province":"MD",
    "sg:tags":[
        "youth",
        "organization",
        "center"
    ],
    "wof:name":"National Conference Of Youth",
    "wof:placetype":"venue"
},
  "geometry": {"coordinates":[-76.703655,39.359385],"type":"Point"}
}