{
  "type": "Feature",
  "properties": {
    "iso:country":"US",
    "sg:address":"16 Manor Knoll Ct",
    "sg:city":"Baldwin",
    "sg:classifiers":[
        {
            "category":"Professional",
            "subcategory":"Research",
            "type":"Services"
        }
    ],
    "sg:phone":"+1 410 817 4683",
    "sg:postcode":"21013",
    "sg:province":"MD",
    "sg:tags":[
        "development",
        "electronics",
        "technology-research"
    ],
    "wof:name":"E Systems Inc",
    "wof:placetype":"venue"
},
  "geometry": {"coordinates":[-76.52622599999999,39.508391],"type":"Point"}
}