{
  "type": "Feature",
  "properties": {
    "addr:full":"22820 Frederick Rd Clarksburg MD 20871",
    "addr:housenumber":"22820",
    "addr:postcode":"20871",
    "addr:street":"Frederick Rd",
    "iso:country":"US",
    "sg:address":"22820 Frederick Rd",
    "sg:city":"Clarksburg",
    "sg:classifiers":[
        {
            "category":"Organizations",
            "subcategory":"Religious Organization",
            "type":"Services"
        }
    ],
    "sg:phone":"+1 301 515 3285",
    "sg:postcode":"20871",
    "sg:province":"MD",
    "sg:tags":[
        "membership"
    ],
    "wof:name":"Lakewood Church",
    "wof:placetype":"venue"
},
  "geometry": {"coordinates":[-77.27123400000001,39.232369],"type":"Point"}
}