{
  "type": "Feature",
  "properties": {
    "iso:country":"US",
    "sg:address":"7737 Riverdale Rd",
    "sg:city":"New Carrollton",
    "sg:classifiers":[
        {
            "category":"Professional",
            "subcategory":"Lawyer & Legal Services",
            "type":"Services"
        }
    ],
    "sg:phone":"+1 240 606 6442",
    "sg:postcode":"20784",
    "sg:province":"MD",
    "sg:tags":[
        "plan"
    ],
    "wof:name":"Pre-Paid Legal Svc",
    "wof:placetype":"venue"
},
  "geometry": {"coordinates":[-76.874546,38.957798],"type":"Point"}
}