{
  "type": "Feature",
  "properties": {
    "iso:country":"US",
    "sg:address":"13621 Unionville Rd",
    "sg:city":"Mount Airy",
    "sg:classifiers":[
        {
            "category":"Building & Trades",
            "subcategory":"Construction",
            "type":"Services"
        }
    ],
    "sg:phone":"+1 410 984 1191",
    "sg:postcode":"21771",
    "sg:province":"MD",
    "sg:tags":[
        "contractor"
    ],
    "wof:name":"Demo Tech",
    "wof:placetype":"venue"
},
  "geometry": {"coordinates":[-77.190638,39.477184],"type":"Point"}
}