{
  "type": "Feature",
  "properties": {
    "iso:country":"US",
    "sg:address":"621 S Bentalou St",
    "sg:city":"Baltimore",
    "sg:classifiers":[
        {
            "category":"Professional",
            "type":"Services"
        },
        {
            "category":"Freight",
            "type":"Transportation"
        },
        {
            "category":"Local Transit",
            "type":"Transportation"
        }
    ],
    "sg:phone":"+1 410 947 5806",
    "sg:postcode":"21223",
    "sg:province":"MD",
    "sg:tags":[
        "public",
        "trucking"
    ],
    "sg:website":"http://www.brodytrans.com",
    "wof:name":"Brody Logistics",
    "wof:placetype":"venue"
},
  "geometry": {"coordinates":[-76.651707,39.279936],"type":"Point"}
}