{
  "type": "Feature",
  "properties": {
    "iso:country":"US",
    "sg:address":"2290 Golfview Ln",
    "sg:city":"Hampstead",
    "sg:classifiers":[
        {
            "category":"Sports & Exercise",
            "subcategory":"Golf",
            "type":"Entertainment"
        }
    ],
    "sg:phone":"+1 410 374 1500",
    "sg:postcode":"21074",
    "sg:province":"MD",
    "sg:tags":[
        "course"
    ],
    "wof:name":"Oakmont Green Golf Course",
    "wof:placetype":"venue"
},
  "geometry": {"coordinates":[-76.855582,39.636196],"type":"Point"}
}