{
  "type": "Feature",
  "properties": {
    "iso:country":"US",
    "sg:address":"9150 Baltimore National Pike Ste 12",
    "sg:city":"Ellicott City",
    "sg:classifiers":[
        {
            "category":"Banks & Credit Unions",
            "subcategory":"Financial Services",
            "type":"Services"
        }
    ],
    "sg:phone":"+1 410 480 0104",
    "sg:postcode":"21042",
    "sg:province":"MD",
    "sg:tags":[
        "broker",
        "mortgage"
    ],
    "sg:website":"financial.wellsfargo.com",
    "wof:name":"Wells Fargo Financial",
    "wof:placetype":"venue"
},
  "geometry": {"coordinates":[-76.82741300000001,39.277193],"type":"Point"}
}