{
  "type": "Feature",
  "properties": {
    "addr:full":"15193 Marlboro Pike Upper Marlboro MD 20772",
    "addr:housenumber":"15193",
    "addr:postcode":"20772",
    "addr:street":"Marlboro Pike",
    "iso:country":"US",
    "sg:address":"15193 Marlboro Pike",
    "sg:city":"Upper Marlboro",
    "sg:classifiers":[
        {
            "category":"Wholesale",
            "subcategory":"Sporting Goods",
            "type":"Manufacturing & Wholesale Goods"
        }
    ],
    "sg:phone":"+1 301 627 4140",
    "sg:postcode":"20772",
    "sg:province":"MD",
    "sg:tags":[
        "equipment",
        "pool",
        "swimming"
    ],
    "wof:name":"Marlboro Swimming Pool Supply",
    "wof:placetype":"venue"
},
  "geometry": {"coordinates":[-76.743135,38.821452],"type":"Point"}
}