{
  "type": "Feature",
  "properties": {
    "iso:country":"US",
    "sg:address":"217 E Redwood St Ste 2203",
    "sg:city":"Baltimore",
    "sg:classifiers":[
        {
            "category":"Professional",
            "subcategory":"Business Services",
            "type":"Services"
        }
    ],
    "sg:phone":"+1 410 767 8857",
    "sg:postcode":"21202",
    "sg:province":"MD",
    "sg:tags":[
        "consultant",
        "coach"
    ],
    "wof:name":"D P Healey And Associates",
    "wof:placetype":"venue"
},
  "geometry": {"coordinates":[-76.612013,39.288921],"type":"Point"}
}