{
  "type": "Feature",
  "properties": {
    "addr:full":"6911 Laurel Bowie Rd # 309 Bowie MD 20715",
    "addr:housenumber":"6911",
    "addr:postcode":"20715",
    "addr:street":"Laurel Bowie Rd # 309",
    "iso:country":"US",
    "sg:address":"6911 Laurel Bowie Rd # 309",
    "sg:city":"Bowie",
    "sg:classifiers":[
        {
            "category":"Building & Trades",
            "subcategory":"Electrical",
            "type":"Services"
        }
    ],
    "sg:phone":"+1 410 792 4389",
    "sg:postcode":"20715",
    "sg:province":"MD",
    "sg:tags":[
        "electrician"
    ],
    "wof:name":"Brickhead Electric Inc",
    "wof:placetype":"venue"
},
  "geometry": {"coordinates":[-76.757282,38.984828],"type":"Point"}
}