{
  "type": "Feature",
  "properties": {
    "iso:country":"US",
    "sg:address":"11410 Frederick Ave",
    "sg:city":"Beltsville",
    "sg:classifiers":[
        {
            "category":"Home & Garden",
            "subcategory":"Carpets & Floor Coverings",
            "type":"Retail Goods"
        }
    ],
    "sg:phone":"+1 301 927 2007",
    "sg:postcode":"20705",
    "sg:province":"MD",
    "sg:tags":[
        "dealer",
        "rug"
    ],
    "wof:name":"Teprac",
    "wof:placetype":"venue"
},
  "geometry": {"coordinates":[-76.902503,39.040835],"type":"Point"}
}