{
  "type": "Feature",
  "properties": {
    "addr:full":"10 N 7th St Crisfield MD 21817",
    "addr:housenumber":"10",
    "addr:postcode":"21817",
    "addr:street":"N 7Th St",
    "iso:country":"US",
    "sg:address":"10 N 7th St",
    "sg:city":"Crisfield",
    "sg:classifiers":[
        {
            "category":"Food & Beverages",
            "subcategory":"Liquor & Beverages",
            "type":"Retail Goods"
        }
    ],
    "sg:phone":"+1 410 968 0646",
    "sg:postcode":"21817",
    "sg:province":"MD",
    "wof:name":"Somerset County Liquor Dspnsry",
    "wof:placetype":"venue"
},
  "geometry": {"coordinates":[-75.858282,37.981169],"type":"Point"}
}