{
  "type": "Feature",
  "properties": {
    "iso:country":"US",
    "sg:address":"6015 Montrose Rd",
    "sg:city":"Rockville",
    "sg:classifiers":[
        {
            "category":"Building & Trades",
            "subcategory":"Plumbing",
            "type":"Services"
        }
    ],
    "sg:phone":"+1 888 829 8510",
    "sg:postcode":"20852",
    "sg:province":"MD",
    "sg:website":"www.magnoliaplumbing.com/",
    "wof:name":"Magnolia Plumbing",
    "wof:placetype":"venue"
},
  "geometry": {"coordinates":[-77.122681,39.05298],"type":"Point"}
}