{
  "type": "Feature",
  "properties": {
    "iso:country":"US",
    "sg:address":"3545 Ellicott Mills Dr",
    "sg:city":"Ellicott City",
    "sg:classifiers":[
        {
            "category":"Health Services",
            "subcategory":"Doctor",
            "type":"Services"
        }
    ],
    "sg:phone":"+1 410 461 8383",
    "sg:postcode":"21043",
    "sg:province":"MD",
    "wof:name":"Chandran David MD",
    "wof:placetype":"venue"
},
  "geometry": {"coordinates":[-76.803478,39.271707],"type":"Point"}
}