{
  "type": "Feature",
  "properties": {
    "addr:full":"1805 Cedar Dr Severn MD 21144",
    "addr:housenumber":"1805",
    "addr:postcode":"21144",
    "addr:street":"Cedar Dr",
    "iso:country":"US",
    "sg:address":"1805 Cedar Dr",
    "sg:city":"Severn",
    "sg:classifiers":[
        {
            "category":"Professional",
            "subcategory":"Art Services",
            "type":"Services"
        }
    ],
    "sg:phone":"+1 410 519 5258",
    "sg:postcode":"21144",
    "sg:province":"MD",
    "sg:tags":[
        "commercial",
        "design"
    ],
    "wof:name":"Sumoart",
    "wof:placetype":"venue"
},
  "geometry": {"coordinates":[-76.72054,39.138302],"type":"Point"}
}