{
  "type": "Feature",
  "properties": {
    "addr:full":"619 Batavia Farm Rd Rosedale MD 21237",
    "addr:housenumber":"619",
    "addr:postcode":"21237",
    "addr:street":"Batavia Farm Rd",
    "iso:country":"US",
    "sg:address":"619 Batavia Farm Rd",
    "sg:city":"Rosedale",
    "sg:classifiers":[
        {
            "category":"Manufacturing",
            "subcategory":"Building Materials",
            "type":"Manufacturing & Wholesale Goods"
        }
    ],
    "sg:phone":"+1 410 391 1631",
    "sg:postcode":"21237",
    "sg:province":"MD",
    "sg:tags":[
        "stone",
        "crushed"
    ],
    "wof:name":"Redland Genstar",
    "wof:placetype":"venue"
},
  "geometry": {"coordinates":[-76.495627,39.315299],"type":"Point"}
}