{
  "type": "Feature",
  "properties": {
    "iso:country":"US",
    "sg:address":"3462 Gough Dr",
    "sg:city":"Waldorf",
    "sg:classifiers":[
        {
            "category":"Building & Trades",
            "subcategory":"Construction",
            "type":"Services"
        }
    ],
    "sg:phone":"+1 301 843 7777",
    "sg:postcode":"20602",
    "sg:province":"MD",
    "sg:tags":[
        "tile",
        "dealer"
    ],
    "wof:name":"John R King Tile Inc",
    "wof:placetype":"venue"
},
  "geometry": {"coordinates":[-76.90099499999999,38.620885],"type":"Point"}
}