{
  "type": "Feature",
  "properties": {
    "addr:full":"1805 Baffin St Severn MD 21144",
    "addr:housenumber":"1805",
    "addr:postcode":"21144",
    "addr:street":"Baffin St",
    "iso:country":"US",
    "sg:address":"1805 Baffin St",
    "sg:city":"Severn",
    "sg:classifiers":[
        {
            "category":"Professional",
            "subcategory":"Engineering",
            "type":"Services"
        }
    ],
    "sg:phone":"+1 443 962 3281",
    "sg:postcode":"21144",
    "sg:province":"MD",
    "sg:tags":[
        "control",
        "engineer",
        "system",
        "automation"
    ],
    "wof:name":"Cayo Hueso Services, Inc.",
    "wof:placetype":"venue"
},
  "geometry": {"coordinates":[-76.71620900000001,39.132172],"type":"Point"}
}