{
  "type": "Feature",
  "properties": {
    "addr:full":"13 Park Ave Gaithersburg MD 20877",
    "addr:housenumber":"13",
    "addr:postcode":"20877",
    "addr:street":"Park Ave",
    "iso:country":"US",
    "sg:address":"13 Park Ave",
    "sg:city":"Gaithersburg",
    "sg:classifiers":[
        {
            "category":"Organizations",
            "subcategory":"Religious Organization",
            "type":"Services"
        }
    ],
    "sg:phone":"+1 301 258 1003",
    "sg:postcode":"20877",
    "sg:province":"MD",
    "wof:name":"Rainbow Ministries",
    "wof:placetype":"venue"
},
  "geometry": {"coordinates":[-77.195138,39.143828],"type":"Point"}
}