{
  "type": "Feature",
  "properties": {
    "iso:country":"US",
    "sg:address":"103 S Wickham Rd",
    "sg:city":"Baltimore",
    "sg:classifiers":[
        {
            "category":"Shopping",
            "subcategory":"Gifts & Souvenirs",
            "type":"Retail Goods"
        }
    ],
    "sg:phone":"+1 410 368 1594",
    "sg:postcode":"21229",
    "sg:province":"MD",
    "sg:tags":[
        "shop"
    ],
    "wof:name":"Wanda S World Of Gifts",
    "wof:placetype":"venue"
},
  "geometry": {"coordinates":[-76.695739,39.282747],"type":"Point"}
}