{
  "type": "Feature",
  "properties": {
    "iso:country":"US",
    "sg:address":"20201 Watkins Mill Rd",
    "sg:city":"Gaithersburg",
    "sg:classifiers":[
        {
            "category":"Organizations",
            "subcategory":"Professional Association",
            "type":"Services"
        }
    ],
    "sg:phone":"+1 301 444 3355",
    "sg:postcode":"20886",
    "sg:province":"MD",
    "wof:name":"Watkins Mill House",
    "wof:placetype":"venue"
},
  "geometry": {"coordinates":[-77.212867,39.186038],"type":"Point"}
}