{
  "type": "Feature",
  "properties": {
    "addr:full":"3530 Chas Dr Hampstead MD 21074",
    "addr:postcode":"3530;21074",
    "addr:street":"Chas Dr",
    "iso:country":"US",
    "sg:address":"3530 Chas Dr",
    "sg:city":"Hampstead",
    "sg:classifiers":[
        {
            "category":"Professional",
            "subcategory":"Business Services",
            "type":"Services"
        }
    ],
    "sg:phone":"+1 410 374 6600",
    "sg:postcode":"21074",
    "sg:province":"MD",
    "sg:tags":[
        "translator",
        "interpreter"
    ],
    "wof:name":"Chillson Translating Serv",
    "wof:placetype":"venue"
},
  "geometry": {"coordinates":[-76.87140599999999,39.585191],"type":"Point"}
}