{
  "type": "Feature",
  "properties": {
    "addr:full":"2565 Crain Hwy Waldorf MD 20601",
    "addr:housenumber":"2565",
    "addr:postcode":"20601",
    "addr:street":"Crain Hwy",
    "iso:country":"US",
    "sg:address":"2565 Crain Hwy",
    "sg:city":"Waldorf",
    "sg:classifiers":[
        {
            "category":"Autos & Motor Vehicles",
            "subcategory":"Auto Supplies",
            "type":"Retail Goods"
        }
    ],
    "sg:phone":"+1 301 645 9224",
    "sg:postcode":"20601",
    "sg:province":"MD",
    "sg:tags":[
        "tire"
    ],
    "wof:name":"Firestone Tire & Auto Ctr",
    "wof:placetype":"venue"
},
  "geometry": {"coordinates":[-76.89632400000001,38.640622],"type":"Point"}
}