{
  "type": "Feature",
  "properties": {
    "addr:full":"4301 Sunflower Dr Rockville MD 20853",
    "addr:housenumber":"4301",
    "addr:postcode":"20853",
    "addr:street":"Sunflower Dr",
    "iso:country":"US",
    "sg:address":"4301 Sunflower Dr",
    "sg:city":"Rockville",
    "sg:classifiers":[
        {
            "category":"Personal",
            "subcategory":"Beauty Salon",
            "type":"Services"
        }
    ],
    "sg:phone":"+1 301 929 1039",
    "sg:postcode":"20853",
    "sg:province":"MD",
    "sg:tags":[
        "shop"
    ],
    "wof:name":"Tyra Skin Care",
    "wof:placetype":"venue"
},
  "geometry": {"coordinates":[-77.08822499999999,39.110068],"type":"Point"}
}