{
  "type": "Feature",
  "properties": {
    "iso:country":"US",
    "sg:address":"3418 Wood Valley Dr",
    "sg:city":"Pikesville",
    "sg:classifiers":[
        {
            "category":"Professional",
            "subcategory":"Accounting & Tax Preparation",
            "type":"Services"
        }
    ],
    "sg:phone":"+1 410 484 5998",
    "sg:postcode":"21208",
    "sg:province":"MD",
    "sg:tags":[
        "accountant"
    ],
    "wof:name":"Sylvan Ribakow",
    "wof:placetype":"venue"
},
  "geometry": {"coordinates":[-76.710542,39.397234],"type":"Point"}
}