{
  "type": "Feature",
  "properties": {
    "addr:full":"309 Beaumont Rd Silver Spring MD 20904",
    "addr:housenumber":"309",
    "addr:postcode":"20904",
    "addr:street":"Beaumont Rd",
    "iso:country":"US",
    "sg:address":"309 Beaumont Rd",
    "sg:city":"Silver Spring",
    "sg:classifiers":[
        {
            "category":"Professional",
            "subcategory":"Management & Consulting",
            "type":"Services"
        }
    ],
    "sg:phone":"+1 301 879 2111",
    "sg:postcode":"20904",
    "sg:province":"MD",
    "sg:tags":[
        "business"
    ],
    "wof:name":"Tradewinds Publishers",
    "wof:placetype":"venue"
},
  "geometry": {"coordinates":[-77.01723800000001,39.076948],"type":"Point"}
}