{
  "type": "Feature",
  "properties": {
    "iso:country":"US",
    "sg:address":"1013 S Talbot St",
    "sg:city":"St Michaels",
    "sg:classifiers":[
        {
            "category":"Health Services",
            "subcategory":"Clinic",
            "type":"Services"
        }
    ],
    "sg:phone":"+1 410 745 0200",
    "sg:postcode":"21663",
    "sg:province":"MD",
    "wof:name":"Choptank Community Health Syst",
    "wof:placetype":"venue"
},
  "geometry": {"coordinates":[-76.216539,38.776694],"type":"Point"}
}