{
  "type": "Feature",
  "properties": {
    "iso:country":"US",
    "sg:address":"22409 Goose Hollow Dr",
    "sg:city":"Chestertown",
    "sg:classifiers":[
        {
            "category":"Autos & Motor Vehicles",
            "subcategory":"Boat Sales",
            "type":"Retail Goods"
        }
    ],
    "sg:phone":"+1 410 778 0756",
    "sg:postcode":"21620",
    "sg:province":"MD",
    "sg:tags":[
        "top",
        "upholstery",
        "cover"
    ],
    "wof:name":"Robert Glebe Inc",
    "wof:placetype":"venue"
},
  "geometry": {"coordinates":[-76.19040800000001,39.240498],"type":"Point"}
}