{
  "type": "Feature",
  "properties": {
    "iso:country":"US",
    "sg:address":"11101 Gilroy Rd",
    "sg:city":"Cockysvl Hnt Vly",
    "sg:classifiers":[
        {
            "category":"Manufacturing",
            "subcategory":"Electronics",
            "type":"Manufacturing & Wholesale Goods"
        }
    ],
    "sg:phone":"+1 410 785 1018",
    "sg:postcode":"21031",
    "sg:province":"MD",
    "sg:tags":[
        "communications",
        "equipment"
    ],
    "wof:name":"General Services Engineering",
    "wof:placetype":"venue"
},
  "geometry": {"coordinates":[-76.660964,39.48443],"type":"Point"}
}