{
  "type": "Feature",
  "properties": {
    "iso:country":"US",
    "sg:address":"9505 Reisterstown Rd",
    "sg:city":"Owings Mills",
    "sg:classifiers":[
        {
            "category":"Banks & Credit Unions",
            "subcategory":"Bank",
            "type":"Services"
        }
    ],
    "sg:phone":"+1 410 581 0055",
    "sg:postcode":"21117",
    "sg:province":"MD",
    "sg:tags":[
        "loan",
        "real estate"
    ],
    "wof:name":"Integrity Lending Corp",
    "wof:placetype":"venue"
},
  "geometry": {"coordinates":[-76.757091,39.403508],"type":"Point"}
}