{
  "type": "Feature",
  "properties": {
    "iso:country":"US",
    "sg:address":"9530 Clocktower Ln",
    "sg:city":"Columbia",
    "sg:classifiers":[
        {
            "category":"Food & Beverages",
            "subcategory":"Specialty",
            "type":"Retail Goods"
        }
    ],
    "sg:phone":"+1 301 317 1322",
    "sg:postcode":"21046",
    "sg:province":"MD",
    "sg:tags":[
        "gourmet",
        "shop"
    ],
    "wof:name":"Ske Treats Gourmet Caramel LA",
    "wof:placetype":"venue"
},
  "geometry": {"coordinates":[-76.844826,39.162766],"type":"Point"}
}