{
  "type": "Feature",
  "properties": {
    "iso:country":"US",
    "sg:address":"14741 Governor Oden Bowie Dr",
    "sg:city":"Upper Marlboro",
    "sg:classifiers":[
        {
            "category":"Government",
            "subcategory":"Office",
            "type":"Public Place"
        }
    ],
    "sg:phone":"+1 410 741 1888",
    "sg:postcode":"20772",
    "sg:province":"MD",
    "sg:tags":[
        "federal"
    ],
    "wof:name":"US Consolidated Farm Svc Agcy",
    "wof:placetype":"venue"
},
  "geometry": {"coordinates":[-76.751131,38.818383],"type":"Point"}
}