{
  "type": "Feature",
  "properties": {
    "addr:full":"13013 Narada St Rockville MD 20853",
    "addr:housenumber":"13013",
    "addr:postcode":"20853",
    "addr:street":"Narada St",
    "iso:country":"US",
    "sg:address":"13013 Narada St",
    "sg:city":"Rockville",
    "sg:classifiers":[
        {
            "category":"Communications",
            "type":"Services"
        }
    ],
    "sg:phone":"+1 240 421 3110",
    "sg:postcode":"20853",
    "sg:province":"MD",
    "sg:tags":[
        "consultant",
        "engineer"
    ],
    "wof:name":"International Connections (Internect)",
    "wof:placetype":"venue"
},
  "geometry": {"coordinates":[-77.093054,39.069448],"type":"Point"}
}