{
  "type": "Feature",
  "properties": {
    "addr:full":"10916 Rawley Rd New Market MD 21774",
    "addr:housenumber":"10916",
    "addr:postcode":"21774",
    "addr:street":"Rawley Rd",
    "iso:country":"US",
    "sg:address":"10916 Rawley Rd",
    "sg:city":"New Market",
    "sg:classifiers":[
        {
            "category":"Building & Trades",
            "subcategory":"Construction",
            "type":"Services"
        }
    ],
    "sg:phone":"+1 301 865 3931",
    "sg:postcode":"21774",
    "sg:province":"MD",
    "sg:tags":[
        "home",
        "improvement"
    ],
    "wof:name":"Weatherproof Roofing Siding",
    "wof:placetype":"venue"
},
  "geometry": {"coordinates":[-77.282135,39.39186],"type":"Point"}
}