{
  "type": "Feature",
  "properties": {
    "iso:country":"US",
    "sg:address":"3337 E Joppa Rd",
    "sg:city":"Baltimore",
    "sg:classifiers":[
        {
            "category":"Organizations",
            "subcategory":"Religious Organization",
            "type":"Services"
        }
    ],
    "sg:phone":"+1 410 464 0001",
    "sg:postcode":"21234",
    "sg:province":"MD",
    "wof:name":"Young Life Baltimore City",
    "wof:placetype":"venue"
},
  "geometry": {"coordinates":[-76.513347,39.394883],"type":"Point"}
}