{
  "type": "Feature",
  "properties": {
    "addr:full":"3 Greenwood Pl Pikesville MD 21208",
    "addr:housenumber":"3",
    "addr:postcode":"21208",
    "addr:street":"Greenwood Pl",
    "iso:country":"US",
    "sg:address":"3 Greenwood Pl",
    "sg:city":"Pikesville",
    "sg:classifiers":[
        {
            "category":"Communications",
            "type":"Services"
        }
    ],
    "sg:phone":"+1 410 764 1204",
    "sg:postcode":"21208",
    "sg:province":"MD",
    "wof:name":"NWN Communication Group",
    "wof:placetype":"venue"
},
  "geometry": {"coordinates":[-76.740512,39.374237],"type":"Point"}
}