{
  "type": "Feature",
  "properties": {
    "addr:full":"243 Muddy Branch Rd Gaithersburg MD 20878",
    "addr:housenumber":"243",
    "addr:postcode":"20878",
    "addr:street":"Muddy Branch Rd",
    "iso:country":"US",
    "sg:address":"243 Muddy Branch Rd",
    "sg:city":"Gaithersburg",
    "sg:classifiers":[
        {
            "category":"Personal",
            "subcategory":"Nail Salon",
            "type":"Services"
        }
    ],
    "sg:phone":"+1 301 258 8893",
    "sg:postcode":"20878",
    "sg:province":"MD",
    "wof:name":"Jackie's Nails",
    "wof:placetype":"venue"
},
  "geometry": {"coordinates":[-77.207801,39.12923],"type":"Point"}
}