{
  "type": "Feature",
  "properties": {
    "addr:full":"218 N Charles St Baltimore MD 21201",
    "addr:housenumber":"218",
    "addr:postcode":"21201",
    "addr:street":"N Charles St",
    "iso:country":"US",
    "sg:address":"218 N Charles St",
    "sg:city":"Baltimore",
    "sg:classifiers":[
        {
            "category":"Real Estate",
            "subcategory":"Developer",
            "type":"Services"
        },
        {
            "category":"Real Estate",
            "subcategory":"Real Estate Agent",
            "type":"Services"
        }
    ],
    "sg:phone":"+1 410 962 0595",
    "sg:postcode":"21201",
    "sg:province":"MD",
    "sg:tags":[
        "development",
        "management"
    ],
    "sg:website":"www.thesheltergroup.com",
    "wof:name":"Shelter Development LLC",
    "wof:placetype":"venue"
},
  "geometry": {"coordinates":[-76.615414,39.292327],"type":"Point"}
}