{
  "type": "Feature",
  "properties": {
    "addr:full":"630 Glenville Rd Churchville MD 21028",
    "addr:housenumber":"630",
    "addr:postcode":"21028",
    "addr:street":"Glenville Rd",
    "iso:country":"US",
    "sg:address":"630 Glenville Rd",
    "sg:city":"Churchville",
    "sg:classifiers":[
        {
            "category":"Building & Trades",
            "subcategory":"Construction",
            "type":"Services"
        }
    ],
    "sg:phone":"+1 410 836 2008",
    "sg:postcode":"21028",
    "sg:province":"MD",
    "sg:tags":[
        "general",
        "contractor"
    ],
    "wof:name":"Woolsey Farm Enterprises",
    "wof:placetype":"venue"
},
  "geometry": {"coordinates":[-76.237489,39.57283],"type":"Point"}
}