{
  "type": "Feature",
  "properties": {
    "iso:country":"US",
    "sg:address":"2818 Solomons Island Rd",
    "sg:city":"Edgewater",
    "sg:classifiers":[
        {
            "category":"Autos & Motor Vehicles",
            "subcategory":"Boat Sales",
            "type":"Retail Goods"
        }
    ],
    "sg:phone":"+1 410 224 4944",
    "sg:postcode":"21037",
    "sg:province":"MD",
    "sg:tags":[
        "dealer",
        "sales"
    ],
    "wof:name":"Jonathan Foster Yacht Sales",
    "wof:placetype":"venue"
},
  "geometry": {"coordinates":[-76.552267,38.955776],"type":"Point"}
}