{
  "type": "Feature",
  "properties": {
    "iso:country":"US",
    "sg:address":"101 E Dover St",
    "sg:city":"Easton",
    "sg:classifiers":[
        {
            "category":"Restaurant",
            "type":"Food & Drink"
        }
    ],
    "sg:phone":"+1 410 819 8088",
    "sg:postcode":"21601",
    "sg:province":"MD",
    "sg:tags":[
        "style",
        "family"
    ],
    "wof:name":"Restaurant Local",
    "wof:placetype":"venue"
},
  "geometry": {"coordinates":[-76.074783,38.774281],"type":"Point"}
}