{
  "type": "Feature",
  "properties": {
    "iso:country":"US",
    "sg:address":"14918 Baltimore Ave",
    "sg:city":"Laurel",
    "sg:classifiers":[
        {
            "category":"Restaurant",
            "type":"Food & Drink"
        }
    ],
    "sg:phone":"+1 301 604 1966",
    "sg:postcode":"20707",
    "sg:province":"MD",
    "sg:tags":[
        "out"
    ],
    "wof:name":"Haiders House Of Yogurt",
    "wof:placetype":"venue"
},
  "geometry": {"coordinates":[-76.854676,39.093991],"type":"Point"}
}