{
  "type": "Feature",
  "properties": {
    "addr:full":"14803 Pratt St Upper Marlboro MD 20772",
    "addr:housenumber":"14803",
    "addr:postcode":"20772",
    "addr:street":"Pratt St",
    "iso:country":"US",
    "sg:address":"14803 Pratt St",
    "sg:city":"Upper Marlboro",
    "sg:classifiers":[
        {
            "category":"Professional",
            "subcategory":"Lawyer & Legal Services",
            "type":"Services"
        }
    ],
    "sg:phone":"+1 301 627 4036",
    "sg:postcode":"20772",
    "sg:province":"MD",
    "sg:tags":[
        "attorney"
    ],
    "wof:name":"Richar P Arnold",
    "wof:placetype":"venue"
},
  "geometry": {"coordinates":[-76.748695,38.81714],"type":"Point"}
}