{
  "type": "Feature",
  "properties": {
    "iso:country":"US",
    "sg:address":"121 Hawthorne Rd",
    "sg:city":"Baltimore",
    "sg:classifiers":[
        {
            "category":"Professional",
            "subcategory":"Business Services",
            "type":"Services"
        }
    ],
    "sg:phone":"+1 410 467 9387",
    "sg:postcode":"21210",
    "sg:province":"MD",
    "sg:tags":[
        "consultant",
        "coach"
    ],
    "wof:name":"Yuhas Consulting Group",
    "wof:placetype":"venue"
},
  "geometry": {"coordinates":[-76.632379,39.344812],"type":"Point"}
}