{
  "type": "Feature",
  "properties": {
    "iso:country":"US",
    "sg:address":"8389 Piney Orchard Pkwy",
    "sg:city":"Odenton",
    "sg:classifiers":[
        {
            "category":"Restaurant",
            "type":"Food & Drink"
        }
    ],
    "sg:phone":"+1 410 551 2289",
    "sg:postcode":"21113",
    "sg:province":"MD",
    "wof:name":"Romeo's Mexican Food & Pizza",
    "wof:placetype":"venue"
},
  "geometry": {"coordinates":[-76.69932,39.086358],"type":"Point"}
}