{
  "type": "Feature",
  "properties": {
    "iso:country":"US",
    "sg:address":"1430 Buckhorn Rd",
    "sg:city":"Sykesville",
    "sg:classifiers":[
        {
            "category":"Building & Trades",
            "subcategory":"Landscaping Services",
            "type":"Services"
        }
    ],
    "sg:phone":"+1 410 489 0655",
    "sg:postcode":"21784",
    "sg:province":"MD",
    "sg:tags":[
        "lawn",
        "designer",
        "consultant",
        "contractor",
        "maintenance",
        "landscape"
    ],
    "sg:website":"http://www.absolutescapes.com",
    "wof:name":"Absolute Landscape & Turf Services Inc",
    "wof:placetype":"venue"
},
  "geometry": {"coordinates":[-77.046418,39.431629],"type":"Point"}
}