{
  "type": "Feature",
  "properties": {
    "addr:full":"1712 Thames St Baltimore MD 21231",
    "addr:housenumber":"1712",
    "addr:postcode":"21231",
    "addr:street":"Thames St",
    "iso:country":"US",
    "sg:address":"1712 Thames St",
    "sg:city":"Baltimore",
    "sg:classifiers":[
        {
            "category":"Home & Garden",
            "subcategory":"Home Furnishings",
            "type":"Retail Goods"
        }
    ],
    "sg:phone":"+1 443 869 4945",
    "sg:postcode":"21231",
    "sg:province":"MD",
    "sg:tags":[
        "decor"
    ],
    "sg:website":"www.FellsPtFrame.com",
    "wof:name":"Fells Point Frame and Design",
    "wof:placetype":"venue"
},
  "geometry": {"coordinates":[-76.592113,39.282053],"type":"Point"}
}