{
  "type": "Feature",
  "properties": {
    "iso:country":"US",
    "sg:address":"7826 Eastern Ave NW",
    "sg:city":"Washington",
    "sg:classifiers":[
        {
            "category":"Banks & Credit Unions",
            "subcategory":"Investment Brokerage",
            "type":"Services"
        }
    ],
    "sg:phone":"+1 202 829 7285",
    "sg:postcode":"20910",
    "sg:province":"MD",
    "sg:tags":[
        "advisory",
        "financial"
    ],
    "wof:name":"Himbol Financial Svc Inc",
    "wof:placetype":"venue"
},
  "geometry": {"coordinates":[-77.027427,38.985158],"type":"Point"}
}