{
  "type": "Feature",
  "properties": {
    "iso:country":"US",
    "sg:address":"6804 Beacon Pl",
    "sg:city":"Riverdale",
    "sg:classifiers":[
        {
            "category":"Professional",
            "subcategory":"Art Services",
            "type":"Services"
        }
    ],
    "sg:phone":"+1 301 577 7538",
    "sg:postcode":"20737",
    "sg:province":"MD",
    "sg:tags":[
        "commercial",
        "design"
    ],
    "wof:name":"Mainstream Graphics",
    "wof:placetype":"venue"
},
  "geometry": {"coordinates":[-76.901399,38.957063],"type":"Point"}
}