{
  "type": "Feature",
  "properties": {
    "iso:country":"US",
    "sg:address":"374 Mill Swamp Rd",
    "sg:city":"Edgewater",
    "sg:classifiers":[
        {
            "category":"Recreation",
            "type":"Entertainment"
        }
    ],
    "sg:phone":"+1 410 798 6311",
    "sg:postcode":"21037",
    "sg:province":"MD",
    "sg:tags":[
        "center"
    ],
    "wof:name":"Ralph J Bunch Community Ctr",
    "wof:placetype":"venue"
},
  "geometry": {"coordinates":[-76.569676,38.884264],"type":"Point"}
}