{
  "type": "Feature",
  "properties": {
    "iso:country":"US",
    "sg:address":"2810 Shirley Ave",
    "sg:city":"Baltimore",
    "sg:classifiers":[
        {
            "category":"Social Services",
            "type":"Services"
        }
    ],
    "sg:phone":"+1 410 542 4050",
    "sg:postcode":"21215",
    "sg:province":"MD",
    "sg:tags":[
        "youth",
        "organization",
        "center"
    ],
    "wof:name":"Malcolm X Youth Ctr",
    "wof:placetype":"venue"
},
  "geometry": {"coordinates":[-76.664729,39.333626],"type":"Point"}
}