{
  "type": "Feature",
  "properties": {
    "addr:full":"8930 Baltimore St Savage MD 20763",
    "addr:housenumber":"8930",
    "addr:postcode":"20763",
    "addr:street":"Baltimore St",
    "iso:country":"US",
    "sg:address":"8930 Baltimore St",
    "sg:city":"Savage",
    "sg:classifiers":[
        {
            "category":"Real Estate",
            "subcategory":"Real Estate Agent",
            "type":"Services"
        }
    ],
    "sg:phone":"+1 301 725 6300",
    "sg:postcode":"20763",
    "sg:province":"MD",
    "sg:tags":[
        "management"
    ],
    "wof:name":"Storch Realty",
    "wof:placetype":"venue"
},
  "geometry": {"coordinates":[-76.82353999999999,39.137938],"type":"Point"}
}