{
  "type": "Feature",
  "properties": {
    "iso:country":"US",
    "sg:address":"621 Central Ave E",
    "sg:city":"Edgewater",
    "sg:classifiers":[
        {
            "category":"Manufacturing",
            "subcategory":"Watercraft",
            "type":"Manufacturing & Wholesale Goods"
        }
    ],
    "sg:phone":"+1 410 798 7886",
    "sg:postcode":"21037",
    "sg:province":"MD",
    "sg:tags":[
        "boat"
    ],
    "wof:name":"Classic Barnegat",
    "wof:placetype":"venue"
},
  "geometry": {"coordinates":[-76.536658,38.906965],"type":"Point"}
}