{
  "type": "Feature",
  "properties": {
    "addr:full":"4109 Frederick Ave Baltimore MD 21229",
    "addr:housenumber":"4109",
    "addr:postcode":"21229",
    "addr:street":"Frederick Ave",
    "iso:country":"US",
    "sg:address":"4109 Frederick Ave",
    "sg:city":"Baltimore",
    "sg:classifiers":[
        {
            "category":"Shopping",
            "subcategory":"Clothing, Apparel, & Fashions",
            "type":"Retail Goods"
        }
    ],
    "sg:phone":"+1 410 843 4507",
    "sg:postcode":"21229",
    "sg:province":"MD",
    "sg:tags":[
        "garment"
    ],
    "wof:name":"One Love Apparel",
    "wof:placetype":"venue"
},
  "geometry": {"coordinates":[-76.683834,39.281657],"type":"Point"}
}