{
  "type": "Feature",
  "properties": {
    "addr:full":"3701 Koppers St Baltimore MD 21227",
    "addr:housenumber":"3701",
    "addr:postcode":"21227",
    "addr:street":"Koppers St",
    "iso:country":"US",
    "sg:address":"3701 Koppers St",
    "sg:city":"Baltimore",
    "sg:classifiers":[
        {
            "category":"Professional",
            "subcategory":"Management & Consulting",
            "type":"Services"
        }
    ],
    "sg:phone":"+1 410 368 1321",
    "sg:postcode":"21227",
    "sg:province":"MD",
    "wof:name":"Preferred +",
    "wof:placetype":"venue"
},
  "geometry": {"coordinates":[-76.67045899999999,39.261499],"type":"Point"}
}