{
  "type": "Feature",
  "properties": {
    "addr:full":"9801 Georgia Ave Silver Spring MD 20902",
    "addr:housenumber":"9801",
    "addr:postcode":"20902",
    "addr:street":"Georgia Ave",
    "iso:country":"US",
    "sg:address":"9801 Georgia Ave",
    "sg:city":"Silver Spring",
    "sg:classifiers":[
        {
            "category":"Health Services",
            "subcategory":"Doctor",
            "type":"Services"
        }
    ],
    "sg:phone":"+1 301 681 5922",
    "sg:postcode":"20902",
    "sg:province":"MD",
    "sg:tags":[
        "physician",
        "surgeon"
    ],
    "wof:name":"Suresh K Gupta MD",
    "wof:placetype":"venue"
},
  "geometry": {"coordinates":[-77.04315099999999,39.016891],"type":"Point"}
}