{
  "type": "Feature",
  "properties": {
    "iso:country":"US",
    "sg:address":"9016 Liberty Rd",
    "sg:city":"Randallstown",
    "sg:classifiers":[
        {
            "category":"Insurance",
            "subcategory":"Hazard Insurance",
            "type":"Services"
        }
    ],
    "sg:phone":"+1 410 496 9400",
    "sg:postcode":"21133",
    "sg:province":"MD",
    "sg:tags":[
        "bond"
    ],
    "wof:name":"Greater Baltimore Bail Agents",
    "wof:placetype":"venue"
},
  "geometry": {"coordinates":[-76.797197,39.368228],"type":"Point"}
}