{
  "type": "Feature",
  "properties": {
    "iso:country":"US",
    "sg:address":"13311 Wedgeport Ln",
    "sg:city":"Germantown",
    "sg:classifiers":[
        {
            "category":"Professional",
            "subcategory":"Accounting & Tax Preparation",
            "type":"Services"
        }
    ],
    "sg:phone":"+1 301 528 4120",
    "sg:postcode":"20874",
    "sg:province":"MD",
    "sg:tags":[
        "accountant"
    ],
    "wof:name":"Jeet Financial Svc",
    "wof:placetype":"venue"
},
  "geometry": {"coordinates":[-77.27645,39.184373],"type":"Point"}
}