{
  "type": "Feature",
  "properties": {
    "iso:country":"US",
    "sg:address":"116 N East Rd",
    "sg:city":"North East",
    "sg:classifiers":[
        {
            "category":"Shopping",
            "subcategory":"Department Store",
            "type":"Retail Goods"
        }
    ],
    "sg:phone":"+1 410 287 2294",
    "sg:postcode":"21901",
    "sg:province":"MD",
    "sg:tags":[
        "shop"
    ],
    "wof:name":"Dollar General",
    "wof:placetype":"venue"
},
  "geometry": {"coordinates":[-75.947026,39.612918],"type":"Point"}
}