{
  "type": "Feature",
  "properties": {
    "iso:country":"US",
    "sg:address":"11820 Parklawn Dr",
    "sg:city":"Rockville",
    "sg:classifiers":[
        {
            "category":"Building & Trades",
            "subcategory":"Cleaning & Sanitation",
            "type":"Services"
        }
    ],
    "sg:phone":"+1 301 230 1992",
    "sg:postcode":"20852",
    "sg:province":"MD",
    "sg:tags":[
        "property",
        "maintenance"
    ],
    "wof:name":"Sunrise Service Inc",
    "wof:placetype":"venue"
},
  "geometry": {"coordinates":[-77.103625,39.050322],"type":"Point"}
}