{
  "type": "Feature",
  "properties": {
    "addr:full":"8423 Ramsburg Rd Thurmont MD 21788",
    "addr:housenumber":"8423",
    "addr:postcode":"21788",
    "addr:street":"Ramsburg Rd",
    "iso:country":"US",
    "sg:address":"8423 Ramsburg Rd",
    "sg:city":"Thurmont",
    "sg:classifiers":[
        {
            "category":"Real Estate",
            "subcategory":"Real Estate Agent",
            "type":"Services"
        }
    ],
    "sg:phone":"+1 301 271 3222",
    "sg:postcode":"21788",
    "sg:province":"MD",
    "wof:name":"Ashlyn Management LLC",
    "wof:placetype":"venue"
},
  "geometry": {"coordinates":[-77.37308899999999,39.527854],"type":"Point"}
}