{
  "type": "Feature",
  "properties": {
    "addr:full":"6920 Tudsbury Rd Baltimore MD 21244",
    "addr:housenumber":"6920",
    "addr:postcode":"21244",
    "addr:street":"Tudsbury Rd",
    "iso:country":"US",
    "sg:address":"6920 Tudsbury Rd",
    "sg:city":"Baltimore",
    "sg:classifiers":[
        {
            "category":"Professional",
            "type":"Services"
        }
    ],
    "sg:phone":"+1 410 448 5384",
    "sg:postcode":"21244",
    "sg:province":"MD",
    "sg:tags":[
        "establishment"
    ],
    "wof:name":"MPI Corp",
    "wof:placetype":"venue"
},
  "geometry": {"coordinates":[-76.751974,39.327835],"type":"Point"}
}