{
  "type": "Feature",
  "properties": {
    "addr:full":"3371 Kenilworth Ave Hyattsville MD 20781",
    "addr:housenumber":"3371",
    "addr:postcode":"20781",
    "addr:street":"Kenilworth Ave",
    "iso:country":"US",
    "sg:address":"3371 Kenilworth Ave",
    "sg:city":"Hyattsville",
    "sg:classifiers":[
        {
            "category":"Autos & Motor Vehicles",
            "subcategory":"Automobile Sales",
            "type":"Retail Goods"
        }
    ],
    "sg:phone":"+1 301 864 2000",
    "sg:postcode":"20781",
    "sg:province":"MD",
    "sg:tags":[
        "truck"
    ],
    "wof:name":"Potomac Mack Sales & Svc",
    "wof:placetype":"venue"
},
  "geometry": {"coordinates":[-76.931854,38.930776],"type":"Point"}
}