{
  "type": "Feature",
  "properties": {
    "addr:full":"309 Main St Laurel MD 20707",
    "addr:housenumber":"309",
    "addr:postcode":"20707",
    "addr:street":"Main St",
    "iso:country":"US",
    "sg:address":"309 Main St",
    "sg:city":"Laurel",
    "sg:classifiers":[
        {
            "category":"Building & Trades",
            "subcategory":"Plumbing",
            "type":"Services"
        }
    ],
    "sg:phone":"+1 240 456 4550",
    "sg:postcode":"20707",
    "sg:province":"MD",
    "sg:tags":[
        "tank",
        "installation"
    ],
    "wof:name":"Independent Petroleum Svc Inc",
    "wof:placetype":"venue"
},
  "geometry": {"coordinates":[-76.843627,39.104057],"type":"Point"}
}