{
  "type": "Feature",
  "properties": {
    "addr:full":"125 N 3rd St Oakland MD 21550",
    "addr:housenumber":"125",
    "addr:postcode":"21550",
    "addr:street":"N 3Rd St",
    "iso:country":"US",
    "sg:address":"125 N 3rd St",
    "sg:city":"Oakland",
    "sg:classifiers":[
        {
            "category":"Professional",
            "subcategory":"Engineering",
            "type":"Services"
        }
    ],
    "sg:phone":"+1 301 533 0040",
    "sg:postcode":"21550",
    "sg:province":"MD",
    "sg:tags":[
        "engineer"
    ],
    "wof:name":"Mountain View Engineering",
    "wof:placetype":"venue"
},
  "geometry": {"coordinates":[-79.404433,39.412392],"type":"Point"}
}