{
  "type": "Feature",
  "properties": {
    "addr:full":"234 S Haven St Baltimore MD 21224",
    "addr:housenumber":"234",
    "addr:postcode":"21224",
    "addr:street":"S Haven St",
    "iso:country":"US",
    "sg:address":"234 S Haven St",
    "sg:city":"Baltimore",
    "sg:classifiers":[
        {
            "category":"Professional",
            "subcategory":"Business Services",
            "type":"Services"
        }
    ],
    "sg:phone":"+1 410 327 3083",
    "sg:postcode":"21224",
    "sg:province":"MD",
    "sg:tags":[
        "labeling"
    ],
    "wof:name":"Adcor Packaging Group",
    "wof:placetype":"venue"
},
  "geometry": {"coordinates":[-76.562603,39.28986],"type":"Point"}
}