{
  "type": "Feature",
  "properties": {
    "iso:country":"US",
    "sg:address":"4326 Roland Ave",
    "sg:city":"Baltimore",
    "sg:classifiers":[
        {
            "category":"Education",
            "subcategory":"Special Training",
            "type":"Public Place"
        }
    ],
    "sg:phone":"+1 410 243 0979",
    "sg:postcode":"21210",
    "sg:province":"MD",
    "sg:tags":[
        "consulting"
    ],
    "wof:name":"A Hanna Group",
    "wof:placetype":"venue"
},
  "geometry": {"coordinates":[-76.634772,39.341831],"type":"Point"}
}