{
  "type": "Feature",
  "properties": {
    "addr:full":"5186 Norrisville Rd White Hall MD 21161",
    "addr:housenumber":"5186",
    "addr:postcode":"21161",
    "addr:street":"Norrisville Rd",
    "iso:country":"US",
    "sg:address":"5186 Norrisville Rd",
    "sg:city":"White Hall",
    "sg:classifiers":[
        {
            "category":"Building & Trades",
            "subcategory":"Plumbing",
            "type":"Services"
        }
    ],
    "sg:phone":"+1 410 329 6470",
    "sg:postcode":"21161",
    "sg:province":"MD",
    "sg:tags":[
        "tank",
        "septic"
    ],
    "wof:name":"R Calvin Thomas Excavators Inc",
    "wof:placetype":"venue"
},
  "geometry": {"coordinates":[-76.529928,39.690523],"type":"Point"}
}