{
  "type": "Feature",
  "properties": {
    "iso:country":"US",
    "sg:address":"1101 Mercantile Ln",
    "sg:city":"Upper Marlboro",
    "sg:classifiers":[
        {
            "category":"Shopping",
            "subcategory":"Computers & Home Electronics",
            "type":"Retail Goods"
        }
    ],
    "sg:phone":"+1 301 925 3222",
    "sg:postcode":"20774",
    "sg:province":"MD",
    "sg:tags":[
        "software"
    ],
    "wof:name":"Titan Systems",
    "wof:placetype":"venue"
},
  "geometry": {"coordinates":[-76.83817500000001,38.905117],"type":"Point"}
}