{
  "type": "Feature",
  "properties": {
    "iso:country":"US",
    "sg:address":"1015 W Patrick St",
    "sg:city":"Frederick",
    "sg:classifiers":[
        {
            "category":"Shopping",
            "subcategory":"Tobacco",
            "type":"Retail Goods"
        }
    ],
    "sg:phone":"+1 301 662 6606",
    "sg:postcode":"21702",
    "sg:province":"MD",
    "sg:tags":[
        "cigarette",
        "cigar",
        "dealer"
    ],
    "sg:website":"www.daviduscigars.com",
    "wof:name":"Davidus",
    "wof:placetype":"venue"
},
  "geometry": {"coordinates":[-77.441798,39.417022],"type":"Point"}
}