{
  "type": "Feature",
  "properties": {
    "addr:full":"3885 Fringer Rd Taneytown MD 21787",
    "addr:housenumber":"3885",
    "addr:postcode":"21787",
    "addr:street":"Fringer Rd",
    "iso:country":"US",
    "sg:address":"3885 Fringer Rd",
    "sg:city":"Taneytown",
    "sg:classifiers":[
        {
            "category":"Freight",
            "type":"Transportation"
        }
    ],
    "sg:phone":"+1 410 876 8439",
    "sg:postcode":"21787",
    "sg:province":"MD",
    "sg:tags":[
        "trucking"
    ],
    "wof:name":"C J Trucking",
    "wof:placetype":"venue"
},
  "geometry": {"coordinates":[-77.16485,39.680225],"type":"Point"}
}