{
  "type": "Feature",
  "properties": {
    "iso:country":"US",
    "sg:address":"10088 Southern Maryland Blvd",
    "sg:city":"Dunkirk",
    "sg:classifiers":[
        {
            "category":"Personal",
            "subcategory":"Tanning Parlor",
            "type":"Services"
        }
    ],
    "sg:phone":"+1 410 257 6500",
    "sg:postcode":"20754",
    "sg:province":"MD",
    "sg:tags":[
        "salon"
    ],
    "wof:name":"Tanfastic Boutique",
    "wof:placetype":"venue"
},
  "geometry": {"coordinates":[-76.660353,38.717454],"type":"Point"}
}