{
  "type": "Feature",
  "properties": {
    "addr:full":"5 N Summit Ave Gaithersburg MD 20877",
    "addr:housenumber":"5",
    "addr:postcode":"20877",
    "addr:street":"N Summit Ave",
    "iso:country":"US",
    "sg:address":"5 N Summit Ave",
    "sg:city":"Gaithersburg",
    "sg:classifiers":[
        {
            "category":"Shopping",
            "subcategory":"Used Merchandise",
            "type":"Retail Goods"
        },
        {
            "category":"Home & Garden",
            "subcategory":"Home Furnishings",
            "type":"Retail Goods"
        }
    ],
    "sg:phone":"+1 301 670 5870",
    "sg:postcode":"20877",
    "sg:province":"MD",
    "sg:tags":[
        "antique",
        "accessory"
    ],
    "wof:name":"Gaithersburg Antiques & Home",
    "wof:placetype":"venue"
},
  "geometry": {"coordinates":[-77.192757,39.144146],"type":"Point"}
}