{
  "type": "Feature",
  "properties": {
    "addr:full":"14 Hathaway Rd Lutherville Timonium MD 21093",
    "addr:housenumber":"14",
    "addr:postcode":"21093",
    "addr:street":"Hathaway Rd",
    "iso:country":"US",
    "sg:address":"14 Hathaway Rd",
    "sg:city":"Lutherville Timonium",
    "sg:classifiers":[
        {
            "category":"Building & Trades",
            "subcategory":"Construction",
            "type":"Services"
        }
    ],
    "sg:phone":"+1 410 252 8329",
    "sg:postcode":"21093",
    "sg:province":"MD",
    "sg:tags":[
        "house"
    ],
    "wof:name":"Yorkshire Construction Co",
    "wof:placetype":"venue"
},
  "geometry": {"coordinates":[-76.619409,39.441687],"type":"Point"}
}