{
  "type": "Feature",
  "properties": {
    "addr:full":"11 Blue Ridge Ave Thurmont MD 21788",
    "addr:housenumber":"11",
    "addr:postcode":"21788",
    "addr:street":"Blue Ridge Ave",
    "iso:country":"US",
    "sg:address":"11 Blue Ridge Ave",
    "sg:city":"Thurmont",
    "sg:classifiers":[
        {
            "category":"Building & Trades",
            "subcategory":"Plumbing",
            "type":"Services"
        }
    ],
    "sg:phone":"+1 301 271 4785",
    "sg:postcode":"21788",
    "sg:province":"MD",
    "sg:tags":[
        "air",
        "heating",
        "conditioning",
        "contractor"
    ],
    "wof:name":"Heritage Heating & AC",
    "wof:placetype":"venue"
},
  "geometry": {"coordinates":[-77.40266,39.619233],"type":"Point"}
}