{
  "type": "Feature",
  "properties": {
    "addr:full":"115 Maple Glen Dr Grantsville MD 21536",
    "addr:housenumber":"115",
    "addr:postcode":"21536",
    "addr:street":"Maple Glen Dr",
    "iso:country":"US",
    "sg:address":"115 Maple Glen Dr",
    "sg:city":"Grantsville",
    "sg:classifiers":[
        {
            "category":"Building & Trades",
            "subcategory":"Plumbing",
            "type":"Services"
        }
    ],
    "sg:phone":"+1 301 895 5447",
    "sg:postcode":"21536",
    "sg:province":"MD",
    "sg:tags":[
        "plumber",
        "industrial",
        "contractors-commercial"
    ],
    "wof:name":"Donald E Opel Plumbing",
    "wof:placetype":"venue"
},
  "geometry": {"coordinates":[-79.150064,39.705777],"type":"Point"}
}