{
  "type": "Feature",
  "properties": {
    "addr:full":"6356 York Rd Baltimore MD 21212",
    "addr:housenumber":"6356",
    "addr:postcode":"21212",
    "addr:street":"York Rd",
    "iso:country":"US",
    "sg:address":"6356 York Rd",
    "sg:city":"Baltimore",
    "sg:classifiers":[
        {
            "category":"Personal",
            "subcategory":"Beauty Salon",
            "type":"Services"
        },
        {
            "category":"Personal",
            "subcategory":"Nail Salon",
            "type":"Services"
        }
    ],
    "sg:phone":"+1 410 377 0300",
    "sg:postcode":"21212",
    "sg:province":"MD",
    "sg:tags":[
        "hair",
        "stylist"
    ],
    "wof:name":"Visions In Hair",
    "wof:placetype":"venue"
},
  "geometry": {"coordinates":[-76.609779,39.373131],"type":"Point"}
}