{
  "type": "Feature",
  "properties": {
    "addr:full":"9916 Falls Rd Potomac MD 20854",
    "addr:housenumber":"9916",
    "addr:postcode":"20854",
    "addr:street":"Falls Rd",
    "iso:country":"US",
    "sg:address":"9916 Falls Rd",
    "sg:city":"Potomac",
    "sg:classifiers":[
        {
            "category":"Retail",
            "subcategory":"Auto Rental",
            "type":"Services"
        }
    ],
    "sg:phone":"+1 301 765 9899",
    "sg:postcode":"20854",
    "sg:province":"MD",
    "sg:tags":[
        "renting",
        "automobile"
    ],
    "wof:name":"Enterprise Rent-A-Car",
    "wof:placetype":"venue"
},
  "geometry": {"coordinates":[-77.208647,39.018978],"type":"Point"}
}