{
  "type": "Feature",
  "properties": {
    "addr:full":"451 E 22nd St Baltimore MD 21218",
    "addr:housenumber":"451",
    "addr:postcode":"21218",
    "addr:street":"E 22Nd St",
    "iso:country":"US",
    "sg:address":"451 E 22nd St",
    "sg:city":"Baltimore",
    "sg:classifiers":[
        {
            "category":"Restaurant",
            "type":"Food & Drink"
        }
    ],
    "sg:phone":"+1 410 235 5673",
    "sg:postcode":"21218",
    "sg:province":"MD",
    "sg:tags":[
        "out"
    ],
    "wof:name":"Greenmount Fried Chicken",
    "wof:placetype":"venue"
},
  "geometry": {"coordinates":[-76.610198,39.314397],"type":"Point"}
}