{
  "type": "Feature",
  "properties": {
    "iso:country":"US",
    "sg:address":"6712 Pine Ave",
    "sg:city":"Baltimore",
    "sg:classifiers":[
        {
            "category":"Organizations",
            "subcategory":"Community Association",
            "type":"Services"
        }
    ],
    "sg:phone":"+1 410 288 9701",
    "sg:postcode":"21222",
    "sg:province":"MD",
    "sg:tags":[
        "military"
    ],
    "wof:name":"VFW Dundalk Memorial Post",
    "wof:placetype":"venue"
},
  "geometry": {"coordinates":[-76.527798,39.264163],"type":"Point"}
}