{
  "type": "Feature",
  "properties": {
    "iso:country":"US",
    "sg:address":"2743 Mathews St",
    "sg:city":"Baltimore",
    "sg:classifiers":[
        {
            "category":"Wholesale",
            "subcategory":"Drugs",
            "type":"Manufacturing & Wholesale Goods"
        }
    ],
    "sg:phone":"+1 410 243 3165",
    "sg:postcode":"21218",
    "sg:province":"MD",
    "sg:tags":[
        "cologne",
        "perfume-wholesale",
        "manufacturer",
        "perfume"
    ],
    "wof:name":"M P C Marketing",
    "wof:placetype":"venue"
},
  "geometry": {"coordinates":[-76.607839,39.321407],"type":"Point"}
}