{
  "type": "Feature",
  "properties": {
    "iso:country":"US",
    "sg:address":"301 Watkins Park Dr",
    "sg:city":"Upper Marlboro",
    "sg:classifiers":[
        {
            "category":"Government",
            "subcategory":"Fire Station",
            "type":"Public Place"
        }
    ],
    "sg:phone":"+1 301 390 4885",
    "sg:postcode":"20774",
    "sg:province":"MD",
    "sg:tags":[
        "department"
    ],
    "wof:name":"Prince Georges County Fire",
    "wof:placetype":"venue"
},
  "geometry": {"coordinates":[-76.783608,38.887642],"type":"Point"}
}