{
  "type": "Feature",
  "properties": {
    "addr:full":"601 2nd St Annapolis MD 21403",
    "addr:housenumber":"601",
    "addr:postcode":"21403",
    "addr:street":"2Nd St",
    "iso:country":"US",
    "sg:address":"601 2nd St",
    "sg:city":"Annapolis",
    "sg:classifiers":[
        {
            "category":"Restaurant",
            "type":"Food & Drink"
        }
    ],
    "sg:phone":"+1 410 295 0601",
    "sg:postcode":"21403",
    "sg:province":"MD",
    "wof:name":"Cafe Gurus",
    "wof:placetype":"venue"
},
  "geometry": {"coordinates":[-76.477328,38.969696],"type":"Point"}
}