{
  "type": "Feature",
  "properties": {
    "iso:country":"US",
    "sg:address":"6394 Forrest Ave",
    "sg:city":"Elkridge",
    "sg:classifiers":[
        {
            "category":"Organizations",
            "subcategory":"Non-profit Organization",
            "type":"Services"
        }
    ],
    "sg:phone":"+1 410 796 7990",
    "sg:postcode":"21075",
    "sg:province":"MD",
    "wof:name":"Childrens Bible Ministry-MD",
    "wof:placetype":"venue"
},
  "geometry": {"coordinates":[-76.739766,39.194499],"type":"Point"}
}