{
  "type": "Feature",
  "properties": {
    "addr:full":"21703 Great Mills Rd Lexington Park MD 20653",
    "addr:housenumber":"21703",
    "addr:postcode":"20653",
    "addr:street":"Great Mills Rd",
    "iso:country":"US",
    "sg:address":"21703 Great Mills Rd",
    "sg:city":"Lexington Park",
    "sg:classifiers":[
        {
            "category":"Building & Trades",
            "subcategory":"Equipment Rental",
            "type":"Services"
        }
    ],
    "sg:phone":"+1 301 863 1100",
    "sg:postcode":"20653",
    "sg:province":"MD",
    "sg:tags":[
        "leasing",
        "furniture"
    ],
    "wof:name":"Aaron's Rental Purchase",
    "wof:placetype":"venue"
},
  "geometry": {"coordinates":[-76.455033,38.264787],"type":"Point"}
}