{
  "type": "Feature",
  "properties": {
    "iso:country":"US",
    "sg:address":"10528 Detrick Ave",
    "sg:city":"Kensington",
    "sg:classifiers":[
        {
            "category":"Professional",
            "subcategory":"Art Services",
            "type":"Services"
        }
    ],
    "sg:phone":"+1 301 942 1121",
    "sg:postcode":"20895",
    "sg:province":"MD",
    "sg:tags":[
        "web",
        "graphic",
        "design",
        "designer"
    ],
    "sg:website":"www.asapgraphics.com",
    "wof:name":"Asap Graphics",
    "wof:placetype":"venue"
},
  "geometry": {"coordinates":[-77.07730100000001,39.028999],"type":"Point"}
}