{
  "type": "Feature",
  "properties": {
    "addr:full":"9450 Merryrest Rd Columbia MD 21045",
    "addr:postcode":"9450;21045",
    "addr:street":"Merryrest Rd",
    "iso:country":"US",
    "sg:address":"9450 Merryrest Rd",
    "sg:city":"Columbia",
    "sg:classifiers":[
        {
            "category":"Professional",
            "subcategory":"Art Services",
            "type":"Services"
        }
    ],
    "sg:phone":"+1 410 926 0477",
    "sg:postcode":"21045",
    "sg:province":"MD",
    "sg:tags":[
        "commercial",
        "design"
    ],
    "wof:name":"Pixelminer",
    "wof:placetype":"venue"
},
  "geometry": {"coordinates":[-76.83693599999999,39.209261],"type":"Point"}
}