{
  "type": "Feature",
  "properties": {
    "iso:country":"US",
    "sg:address":"3201 E Madison St",
    "sg:city":"Baltimore",
    "sg:classifiers":[
        {
            "category":"Autos & Motor Vehicles",
            "subcategory":"Automobile Sales",
            "type":"Retail Goods"
        },
        {
            "category":"Retail",
            "subcategory":"Auto Repair",
            "type":"Services"
        }
    ],
    "sg:phone":"+1 410 327 5154",
    "sg:postcode":"21205",
    "sg:province":"MD",
    "sg:tags":[
        "dealers-used",
        "car",
        "used",
        "cars-wholesale"
    ],
    "wof:name":"Rescue Motors Auto Center",
    "wof:placetype":"venue"
},
  "geometry": {"coordinates":[-76.57270800000001,39.300209],"type":"Point"}
}