{
  "type": "Feature",
  "properties": {
    "iso:country":"US",
    "sg:address":"2400 Banning Pl",
    "sg:city":"Hyattsville",
    "sg:classifiers":[
        {
            "category":"Education",
            "subcategory":"School",
            "type":"Public Place"
        }
    ],
    "sg:phone":"+1 301 445 8433",
    "sg:postcode":"20783",
    "sg:province":"MD",
    "wof:name":"Lewisdale Elementary School",
    "wof:placetype":"venue"
},
  "geometry": {"coordinates":[-76.968777,38.975533],"type":"Point"}
}