{
  "type": "Feature",
  "properties": {
    "iso:country":"US",
    "sg:address":"13806 Georgia Ave",
    "sg:city":"Silver Spring",
    "sg:classifiers":[
        {
            "category":"Retail",
            "subcategory":"Photofinishing",
            "type":"Services"
        }
    ],
    "sg:phone":"+1 301 460 1100",
    "sg:postcode":"20906",
    "sg:province":"MD",
    "sg:tags":[
        "photo",
        "finishing"
    ],
    "wof:name":"Moto Photo Inc",
    "wof:placetype":"venue"
},
  "geometry": {"coordinates":[-77.077631,39.083231],"type":"Point"}
}