{
  "type": "Feature",
  "properties": {
    "addr:full":"9114 Northfield Rd Ellicott City MD 21042",
    "addr:housenumber":"9114",
    "addr:postcode":"21042",
    "addr:street":"Northfield Rd",
    "iso:country":"US",
    "sg:address":"9114 Northfield Rd",
    "sg:city":"Ellicott City",
    "sg:classifiers":[
        {
            "category":"Wholesale",
            "subcategory":"Stationery",
            "type":"Manufacturing & Wholesale Goods"
        }
    ],
    "sg:phone":"+1 410 465 7170",
    "sg:postcode":"21042",
    "sg:province":"MD",
    "sg:tags":[
        "paper"
    ],
    "wof:name":"Fred Gross Assoc",
    "wof:placetype":"venue"
},
  "geometry": {"coordinates":[-76.82818,39.256414],"type":"Point"}
}