{
  "type": "Feature",
  "properties": {
    "addr:full":"5225 Indian Head Hwy Ste A Oxon Hill MD 20745",
    "addr:housenumber":"5225",
    "addr:postcode":"20745",
    "addr:street":"Indian Head Hwy Ste A",
    "iso:country":"US",
    "sg:address":"5225 Indian Head Hwy Ste A",
    "sg:city":"Oxon Hill",
    "sg:classifiers":[
        {
            "category":"Shopping",
            "subcategory":"Shoes",
            "type":"Retail Goods"
        }
    ],
    "sg:phone":"+1 301 839 7452",
    "sg:postcode":"20745",
    "sg:province":"MD",
    "sg:tags":[
        "store"
    ],
    "wof:name":"Downtown Locker Room",
    "wof:placetype":"venue"
},
  "geometry": {"coordinates":[-76.99969,38.818481],"type":"Point"}
}