{
  "type": "Feature",
  "properties": {
    "iso:country":"US",
    "sg:address":"557 E Main St",
    "sg:city":"Hancock",
    "sg:classifiers":[
        {
            "category":"Food & Beverages",
            "subcategory":"Bakery",
            "type":"Retail Goods"
        }
    ],
    "sg:phone":"+1 301 678 6060",
    "sg:postcode":"21750",
    "sg:province":"MD",
    "sg:tags":[
        "baker"
    ],
    "wof:name":"Hepburn Orchards Fruit Market",
    "wof:placetype":"venue"
},
  "geometry": {"coordinates":[-78.14666,39.694062],"type":"Point"}
}