{
  "type": "Feature",
  "properties": {
    "iso:country":"US",
    "sg:address":"7208 Marriottsville Rd Number 2",
    "sg:city":"Marriottsville",
    "sg:classifiers":[
        {
            "category":"Banks & Credit Unions",
            "subcategory":"Bank",
            "type":"Services"
        }
    ],
    "sg:phone":"+1 410 552 1975",
    "sg:postcode":"21104",
    "sg:province":"MD",
    "sg:tags":[
        "mortgage"
    ],
    "wof:name":"Newport Shores Mortgage Inc",
    "wof:placetype":"venue"
},
  "geometry": {"coordinates":[-76.909812,39.37407],"type":"Point"}
}