{
  "type": "Feature",
  "properties": {
    "addr:full":"9500 Seven Locks Rd Bethesda MD 20817",
    "addr:housenumber":"9500",
    "addr:postcode":"20817",
    "addr:street":"Seven Locks Rd",
    "iso:country":"US",
    "sg:address":"9500 Seven Locks Rd",
    "sg:city":"Bethesda",
    "sg:classifiers":[
        {
            "category":"Social Services",
            "subcategory":"Child Care",
            "type":"Services"
        }
    ],
    "sg:phone":"+1 301 365 1995",
    "sg:postcode":"20817",
    "sg:province":"MD",
    "sg:tags":[
        "day"
    ],
    "wof:name":"Kidsco Inc",
    "wof:placetype":"venue"
},
  "geometry": {"coordinates":[-77.160276,39.011981],"type":"Point"}
}