{
  "type": "Feature",
  "properties": {
    "addr:full":"3704 Nauset Pl Randallstown MD 21133",
    "addr:housenumber":"3704",
    "addr:postcode":"21133",
    "addr:street":"Nauset Pl",
    "iso:country":"US",
    "sg:address":"3704 Nauset Pl",
    "sg:city":"Randallstown",
    "sg:phone":"+1 410 496 1012",
    "sg:postcode":"21133",
    "sg:province":"MD",
    "wof:name":"Personalized Frames By Bessie Inc",
    "wof:placetype":"venue"
},
  "geometry": {"coordinates":[-76.801776,39.373506],"type":"Point"}
}