{
  "type": "Feature",
  "properties": {
    "addr:full":"801 Diane Ct Forest Hill MD 21050",
    "addr:housenumber":"801",
    "addr:postcode":"21050",
    "addr:street":"Diane Ct",
    "iso:country":"US",
    "sg:address":"801 Diane Ct",
    "sg:city":"Forest Hill",
    "sg:classifiers":[
        {
            "category":"Professional",
            "subcategory":"Engineering",
            "type":"Services"
        }
    ],
    "sg:phone":"+1 410 838 2709",
    "sg:postcode":"21050",
    "sg:province":"MD",
    "wof:name":"Sell Marguerite",
    "wof:placetype":"venue"
},
  "geometry": {"coordinates":[-76.387709,39.563803],"type":"Point"}
}