{
  "type": "Feature",
  "properties": {
    "iso:country":"US",
    "sg:address":"11160 Veirs Mill Rd",
    "sg:city":"Silver Spring",
    "sg:classifiers":[
        {
            "category":"Shopping",
            "subcategory":"Gifts & Souvenirs",
            "type":"Retail Goods"
        }
    ],
    "sg:phone":"+1 301 942 1130",
    "sg:postcode":"20902",
    "sg:province":"MD",
    "sg:tags":[
        "shop"
    ],
    "wof:name":"Candy Express",
    "wof:placetype":"venue"
},
  "geometry": {"coordinates":[-77.054766,39.039555],"type":"Point"}
}