{
  "type": "Feature",
  "properties": {
    "addr:full":"250 Englar Rd Westminster MD 21157",
    "addr:housenumber":"250",
    "addr:postcode":"21157",
    "addr:street":"Englar Rd",
    "iso:country":"US",
    "sg:address":"250 Englar Rd",
    "sg:city":"Westminster",
    "sg:classifiers":[
        {
            "category":"Health Services",
            "subcategory":"Doctor",
            "type":"Services"
        }
    ],
    "sg:phone":"+1 410 857 9100",
    "sg:postcode":"21157",
    "sg:province":"MD",
    "sg:tags":[
        "dentist"
    ],
    "wof:name":"George L Grillon DDS",
    "wof:placetype":"venue"
},
  "geometry": {"coordinates":[-76.988765,39.584533],"type":"Point"}
}