{
  "type": "Feature",
  "properties": {
    "iso:country":"US",
    "sg:address":"11618 Rockville Pike",
    "sg:city":"Rockville",
    "sg:classifiers":[
        {
            "category":"Restaurant",
            "type":"Food & Drink"
        }
    ],
    "sg:phone":"+1 301 468 9301",
    "sg:postcode":"20852",
    "sg:province":"MD",
    "sg:tags":[
        "vegetarian",
        "vegan"
    ],
    "sg:website":"www.thevegetablegarden.com",
    "wof:name":"The Vegetable Garden",
    "wof:placetype":"venue"
},
  "geometry": {"coordinates":[-77.113596,39.048228],"type":"Point"}
}