{
  "type": "Feature",
  "properties": {
    "iso:country":"US",
    "sg:address":"5500 Jefferson Heights Dr",
    "sg:city":"Fairmount Hts",
    "sg:classifiers":[
        {
            "category":"Organizations",
            "subcategory":"Religious Organization",
            "type":"Services"
        }
    ],
    "sg:phone":"+1 301 925 8533",
    "sg:postcode":"20743",
    "sg:province":"MD",
    "sg:tags":[
        "church"
    ],
    "wof:name":"Righteous Church Of Holiness",
    "wof:placetype":"venue"
},
  "geometry": {"coordinates":[-76.910687,38.900148],"type":"Point"}
}