{
  "type": "Feature",
  "properties": {
    "iso:country":"US",
    "sg:address":"4014 Mountville Rd",
    "sg:city":"Jefferson",
    "sg:classifiers":[
        {
            "category":"Manufacturing",
            "subcategory":"Tools & Machinery",
            "type":"Manufacturing & Wholesale Goods"
        }
    ],
    "sg:phone":"+1 301 253 9400",
    "sg:postcode":"21755",
    "sg:province":"MD",
    "sg:tags":[
        "equipment",
        "mfg"
    ],
    "wof:name":"A C R & H Services Inc",
    "wof:placetype":"venue"
},
  "geometry": {"coordinates":[-77.53125900000001,39.35869],"type":"Point"}
}