{
  "type": "Feature",
  "properties": {
    "addr:full":"4640 York Rd Baltimore MD 21212",
    "addr:housenumber":"4640",
    "addr:postcode":"21212",
    "addr:street":"York Rd",
    "iso:country":"US",
    "sg:address":"4640 York Rd",
    "sg:city":"Baltimore",
    "sg:classifiers":[
        {
            "category":"Arts & Performance",
            "subcategory":"Art Gallery",
            "type":"Entertainment"
        }
    ],
    "sg:phone":"+1 410 433 4072",
    "sg:postcode":"21212",
    "sg:province":"MD",
    "sg:tags":[
        "fine",
        "artist"
    ],
    "wof:name":"Art Ja Work Ltd",
    "wof:placetype":"venue"
},
  "geometry": {"coordinates":[-76.60958100000001,39.345501],"type":"Point"}
}