{
  "type": "Feature",
  "properties": {
    "iso:country":"US",
    "sg:address":"9607 Annapolis Rd",
    "sg:city":"Lanham",
    "sg:classifiers":[
        {
            "category":"Building & Trades",
            "subcategory":"Construction",
            "type":"Services"
        }
    ],
    "sg:phone":"+1 301 459 7545",
    "sg:postcode":"20706",
    "sg:province":"MD",
    "sg:tags":[
        "contractor"
    ],
    "wof:name":"Lanham Construction Co Inc",
    "wof:placetype":"venue"
},
  "geometry": {"coordinates":[-76.835999,38.9636],"type":"Point"}
}