{
  "type": "Feature",
  "properties": {
    "addr:full":"21 W Obrecht Rd Sykesville MD 21784",
    "addr:housenumber":"21",
    "addr:postcode":"21784",
    "addr:street":"W Obrecht Rd",
    "iso:country":"US",
    "sg:address":"21 W Obrecht Rd",
    "sg:city":"Sykesville",
    "sg:classifiers":[
        {
            "category":"Professional",
            "subcategory":"Management & Consulting",
            "type":"Services"
        }
    ],
    "sg:phone":"+1 410 465 5516",
    "sg:postcode":"21784",
    "sg:province":"MD",
    "sg:tags":[
        "consultant",
        "business"
    ],
    "wof:name":"Triangle Associates",
    "wof:placetype":"venue"
},
  "geometry": {"coordinates":[-77.006322,39.384784],"type":"Point"}
}