{
  "type": "Feature",
  "properties": {
    "addr:full":"621 Ridgely Ave Annapolis MD 21401",
    "addr:housenumber":"621",
    "addr:postcode":"21401",
    "addr:street":"Ridgely Ave",
    "iso:country":"US",
    "sg:address":"621 Ridgely Ave",
    "sg:city":"Annapolis",
    "sg:classifiers":[
        {
            "category":"Manufacturing",
            "subcategory":"Tools & Machinery",
            "type":"Manufacturing & Wholesale Goods"
        }
    ],
    "sg:phone":"+1 410 841 6046",
    "sg:postcode":"21401",
    "sg:province":"MD",
    "sg:tags":[
        "equipment",
        "electric"
    ],
    "wof:name":"Martini & Assoc Inc",
    "wof:placetype":"venue"
},
  "geometry": {"coordinates":[-76.51346599999999,38.995905],"type":"Point"}
}