{
  "type": "Feature",
  "properties": {
    "addr:full":"1393 Progress Way Eldersburg MD 21784",
    "addr:housenumber":"1393",
    "addr:postcode":"21784",
    "addr:street":"Progress Way",
    "iso:country":"US",
    "sg:address":"1393 Progress Way",
    "sg:city":"Eldersburg",
    "sg:classifiers":[
        {
            "category":"Organizations",
            "subcategory":"Professional Association",
            "type":"Services"
        }
    ],
    "sg:phone":"+1 410 781 4316",
    "sg:postcode":"21784",
    "sg:province":"MD",
    "sg:website":"www.howardcountyrelay.com",
    "wof:name":"American Cancer Society",
    "wof:placetype":"venue"
},
  "geometry": {"coordinates":[-76.944321,39.412205],"type":"Point"}
}