{
  "type": "Feature",
  "properties": {
    "addr:full":"2201 N Charles St Baltimore MD 21218",
    "addr:housenumber":"2201",
    "addr:postcode":"21218",
    "addr:street":"N Charles St",
    "iso:country":"US",
    "sg:address":"2201 N Charles St",
    "sg:city":"Baltimore",
    "sg:classifiers":[
        {
            "category":"Shopping",
            "subcategory":"Gifts & Souvenirs",
            "type":"Retail Goods"
        }
    ],
    "sg:phone":"+1 410 235 4455",
    "sg:postcode":"21218",
    "sg:province":"MD",
    "sg:tags":[
        "shop"
    ],
    "wof:name":"Lotte Gift Shop",
    "wof:placetype":"venue"
},
  "geometry": {"coordinates":[-76.616845,39.31529],"type":"Point"}
}