{
  "type": "Feature",
  "properties": {
    "addr:full":"10900 Coastal Hwy Ocean City MD 21842",
    "addr:housenumber":"10900",
    "addr:postcode":"21842",
    "addr:street":"Coastal Hwy",
    "iso:country":"US",
    "sg:address":"10900 Coastal Hwy",
    "sg:city":"Ocean City",
    "sg:classifiers":[
        {
            "category":"Real Estate",
            "subcategory":"Real Estate Operator",
            "type":"Services"
        }
    ],
    "sg:phone":"+1 410 524 5505",
    "sg:postcode":"21842",
    "sg:province":"MD",
    "sg:tags":[
        "condominium"
    ],
    "wof:name":"Golden Sands Club Condominium",
    "wof:placetype":"venue"
},
  "geometry": {"coordinates":[-75.05723,38.416136],"type":"Point"}
}