{
  "type": "Feature",
  "properties": {
    "addr:full":"8965 Double Hills Rd Denton MD 21629",
    "addr:housenumber":"8965",
    "addr:postcode":"21629",
    "addr:street":"Double Hills Rd",
    "iso:country":"US",
    "sg:address":"8965 Double Hills Rd",
    "sg:city":"Denton",
    "sg:classifiers":[
        {
            "category":"Health Services",
            "subcategory":"Nursing And Care Facility",
            "type":"Services"
        }
    ],
    "sg:phone":"+1 410 479 0324",
    "sg:postcode":"21629",
    "sg:province":"MD",
    "sg:tags":[
        "home",
        "rest"
    ],
    "wof:name":"Taylor Melton House",
    "wof:placetype":"venue"
},
  "geometry": {"coordinates":[-75.8215,38.862887],"type":"Point"}
}