{
  "type": "Feature",
  "properties": {
    "addr:full":"408 Green St Havre De Grace MD 21078",
    "addr:housenumber":"408",
    "addr:postcode":"21078",
    "addr:street":"Green St",
    "iso:country":"US",
    "sg:address":"408 Green St",
    "sg:city":"Havre De Grace",
    "sg:classifiers":[
        {
            "category":"Personal",
            "subcategory":"Barber",
            "type":"Services"
        }
    ],
    "sg:phone":"+1 410 939 1877",
    "sg:postcode":"21078",
    "sg:province":"MD",
    "sg:tags":[
        "shop"
    ],
    "wof:name":"Glen's Barber Shop",
    "wof:placetype":"venue"
},
  "geometry": {"coordinates":[-76.09031899999999,39.549729],"type":"Point"}
}