{
  "type": "Feature",
  "properties": {
    "iso:country":"US",
    "sg:address":"5263 Bamburg Ct",
    "sg:city":"Frederick",
    "sg:classifiers":[
        {
            "category":"Retail",
            "subcategory":"Laundry & Dry Cleaning",
            "type":"Services"
        },
        {
            "category":"Building & Trades",
            "subcategory":"Cleaning & Sanitation",
            "type":"Services"
        }
    ],
    "sg:phone":"+1 301 607 0011",
    "sg:postcode":"21703",
    "sg:province":"MD",
    "sg:tags":[
        "cleaner",
        "house"
    ],
    "wof:name":"Proclean Super Dry",
    "wof:placetype":"venue"
},
  "geometry": {"coordinates":[-77.429231,39.375234],"type":"Point"}
}