{
  "type": "Feature",
  "properties": {
    "addr:full":"8855 Annapolis Rd Lanham MD 20706",
    "addr:housenumber":"8855",
    "addr:postcode":"20706",
    "addr:street":"Annapolis Rd",
    "iso:country":"US",
    "sg:address":"8855 Annapolis Rd",
    "sg:city":"Lanham",
    "sg:classifiers":[
        {
            "category":"Shopping",
            "subcategory":"Computers & Home Electronics",
            "type":"Retail Goods"
        }
    ],
    "sg:phone":"+1 240 296 0400",
    "sg:postcode":"20706",
    "sg:province":"MD",
    "sg:tags":[
        "equipment",
        "satellite",
        "system"
    ],
    "wof:name":"First Metropolitan",
    "wof:placetype":"venue"
},
  "geometry": {"coordinates":[-76.862999,38.961201],"type":"Point"}
}