{
  "type": "Feature",
  "properties": {
    "addr:full":"11125 Rockville Pike Rockville MD 20852",
    "addr:housenumber":"11125",
    "addr:postcode":"20852",
    "addr:street":"Rockville Pike",
    "iso:country":"US",
    "sg:address":"11125 Rockville Pike",
    "sg:city":"Rockville",
    "sg:classifiers":[
        {
            "category":"Home & Garden",
            "subcategory":"Building Materials",
            "type":"Retail Goods"
        }
    ],
    "sg:phone":"+1 301 816 4999",
    "sg:postcode":"20852",
    "sg:province":"MD",
    "sg:tags":[
        "paint"
    ],
    "wof:name":"Imagine N Paint",
    "wof:placetype":"venue"
},
  "geometry": {"coordinates":[-77.10920900000001,39.039428],"type":"Point"}
}