{
  "type": "Feature",
  "properties": {
    "iso:country":"US",
    "sg:address":"110 Painters Mill Rd",
    "sg:city":"Owings Mills",
    "sg:classifiers":[
        {
            "category":"Travel",
            "subcategory":"Travel Agent",
            "type":"Entertainment"
        }
    ],
    "sg:phone":"+1 410 363 3111",
    "sg:postcode":"21117",
    "sg:province":"MD",
    "sg:tags":[
        "agency",
        "bureau"
    ],
    "sg:website":"www.traveldest.com",
    "wof:name":"Travel Destinations Management",
    "wof:placetype":"venue"
},
  "geometry": {"coordinates":[-76.778874,39.410979],"type":"Point"}
}