{
  "type": "Feature",
  "properties": {
    "addr:full":"7812 Miller Fall Rd Derwood MD 20855",
    "addr:housenumber":"7812",
    "addr:postcode":"20855",
    "addr:street":"Miller Fall Rd",
    "iso:country":"US",
    "sg:address":"7812 Miller Fall Rd",
    "sg:city":"Derwood",
    "sg:classifiers":[
        {
            "category":"Travel",
            "subcategory":"Travel Agent",
            "type":"Entertainment"
        }
    ],
    "sg:phone":"+1 240 654 3355",
    "sg:postcode":"20855",
    "sg:province":"MD",
    "sg:tags":[
        "agency",
        "services-commercial"
    ],
    "wof:name":"Travelers Pilot Car",
    "wof:placetype":"venue"
},
  "geometry": {"coordinates":[-77.159729,39.141708],"type":"Point"}
}