{
  "type": "Feature",
  "properties": {
    "addr:full":"12313 Milestone Manor Ln Germantown MD 20876",
    "addr:housenumber":"12313",
    "addr:postcode":"20876",
    "addr:street":"Milestone Manor Ln",
    "iso:country":"US",
    "sg:address":"12313 Milestone Manor Ln",
    "sg:city":"Germantown",
    "sg:classifiers":[
        {
            "category":"Professional",
            "subcategory":"Business Services",
            "type":"Services"
        }
    ],
    "sg:phone":"+1 240 476 2180",
    "sg:postcode":"20876",
    "sg:province":"MD",
    "sg:tags":[
        "notary",
        "public"
    ],
    "wof:name":"Vicky Wan",
    "wof:placetype":"venue"
},
  "geometry": {"coordinates":[-77.253773,39.205394],"type":"Point"}
}