{
  "type": "Feature",
  "properties": {
    "addr:full":"8043 Penn Randall Pl Ste D Upper Marlboro MD 20772",
    "addr:housenumber":"8043",
    "addr:postcode":"20772",
    "addr:street":"Penn Randall Pl Ste D",
    "iso:country":"US",
    "sg:address":"8043 Penn Randall Pl Ste D",
    "sg:city":"Upper Marlboro",
    "sg:classifiers":[
        {
            "category":"Organizations",
            "subcategory":"Religious Organization",
            "type":"Services"
        }
    ],
    "sg:phone":"+1 301 516 8449",
    "sg:postcode":"20772",
    "sg:province":"MD",
    "wof:name":"Faith Deliverance & Resseruction Baptist Church",
    "wof:placetype":"venue"
},
  "geometry": {"coordinates":[-76.865628,38.836136],"type":"Point"}
}