{
  "type": "Feature",
  "properties": {
    "addr:full":"11858 Ramsburg Rd Marriottsville MD 21104",
    "addr:housenumber":"11858",
    "addr:postcode":"21104",
    "addr:street":"Ramsburg Rd",
    "iso:country":"US",
    "sg:address":"11858 Ramsburg Rd",
    "sg:city":"Marriottsville",
    "sg:classifiers":[
        {
            "category":"Building & Trades",
            "subcategory":"Construction",
            "type":"Services"
        }
    ],
    "sg:phone":"+1 410 442 5477",
    "sg:postcode":"21104",
    "sg:province":"MD",
    "sg:tags":[
        "home",
        "improvement",
        "general",
        "contracting"
    ],
    "wof:name":"Kipp's Kontracting",
    "wof:placetype":"venue"
},
  "geometry": {"coordinates":[-76.922315,39.323926],"type":"Point"}
}