{
  "type": "Feature",
  "properties": {
    "addr:full":"5703 Luxemburg St Rockville MD 20852",
    "addr:postcode":"5703;20852",
    "addr:street":"Luxemburg St",
    "iso:country":"US",
    "sg:address":"5703 Luxemburg St",
    "sg:city":"Rockville",
    "sg:classifiers":[
        {
            "category":"Professional",
            "type":"Services"
        }
    ],
    "sg:phone":"+1 301 770 7629",
    "sg:postcode":"20852",
    "sg:province":"MD",
    "sg:tags":[
        "establishment"
    ],
    "wof:name":"Argentbeef Inc",
    "wof:placetype":"venue"
},
  "geometry": {"coordinates":[-77.115801,39.030831],"type":"Point"}
}