{
  "type": "Feature",
  "properties": {
    "iso:country":"US",
    "sg:address":"7712 16th St NW",
    "sg:city":"Washington",
    "sg:classifiers":[
        {
            "category":"Organizations",
            "subcategory":"Religious Organization",
            "type":"Services"
        }
    ],
    "sg:phone":"+1 202 882 0804",
    "sg:postcode":"20012",
    "sg:province":"MD",
    "sg:tags":[
        "clergy"
    ],
    "wof:name":"Ernest Friedman",
    "wof:placetype":"venue"
},
  "geometry": {"coordinates":[-77.03641500000001,38.983751],"type":"Point"}
}