{
  "type": "Feature",
  "properties": {
    "iso:country":"US",
    "sg:address":"1309 Cavendish Dr",
    "sg:city":"Silver Spring",
    "sg:classifiers":[
        {
            "category":"Shopping",
            "subcategory":"Gifts & Souvenirs",
            "type":"Retail Goods"
        }
    ],
    "sg:phone":"+1 301 236 9223",
    "sg:postcode":"20905",
    "sg:province":"MD",
    "sg:tags":[
        "party",
        "supply"
    ],
    "wof:name":"Party Wheels Colesville",
    "wof:placetype":"venue"
},
  "geometry": {"coordinates":[-76.982317,39.090911],"type":"Point"}
}