{
  "type": "Feature",
  "properties": {
    "addr:full":"610 Poplar Grove St Baltimore MD 21216",
    "addr:housenumber":"610",
    "addr:postcode":"21216",
    "addr:street":"Poplar Grove St",
    "iso:country":"US",
    "sg:address":"610 Poplar Grove St",
    "sg:city":"Baltimore",
    "sg:classifiers":[
        {
            "category":"Professional",
            "subcategory":"Business Services",
            "type":"Services"
        }
    ],
    "sg:phone":"+1 443 278 0550",
    "sg:postcode":"21216",
    "sg:province":"MD",
    "sg:tags":[
        "consultant",
        "coach"
    ],
    "wof:name":"Enigma Sound Service",
    "wof:placetype":"venue"
},
  "geometry": {"coordinates":[-76.664903,39.294493],"type":"Point"}
}