{
  "type": "Feature",
  "properties": {
    "iso:country":"US",
    "sg:address":"490 Fleet St",
    "sg:city":"Rockville",
    "sg:classifiers":[
        {
            "category":"Retail",
            "subcategory":"Auto Rental",
            "type":"Services"
        }
    ],
    "sg:phone":"+1 301 545 0788",
    "sg:postcode":"20850",
    "sg:province":"MD",
    "sg:tags":[
        "renting",
        "automobile"
    ],
    "wof:name":"Thrifty Car Rental",
    "wof:placetype":"venue"
},
  "geometry": {"coordinates":[-77.14620600000001,39.080542],"type":"Point"}
}