{
  "type": "Feature",
  "properties": {
    "addr:full":"7 Allegheny Ave Towson MD 21204",
    "addr:housenumber":"7",
    "addr:postcode":"21204",
    "addr:street":"Allegheny Ave",
    "iso:country":"US",
    "sg:address":"7 Allegheny Ave",
    "sg:city":"Towson",
    "sg:classifiers":[
        {
            "category":"Shopping",
            "subcategory":"Jewelry",
            "type":"Retail Goods"
        }
    ],
    "sg:phone":"+1 410 828 6677",
    "sg:postcode":"21204",
    "sg:province":"MD",
    "sg:tags":[
        "jeweler"
    ],
    "wof:name":"H Ray Starkey Co",
    "wof:placetype":"venue"
},
  "geometry": {"coordinates":[-76.60369799999999,39.40172],"type":"Point"}
}