{
  "type": "Feature",
  "properties": {
    "iso:country":"US",
    "sg:address":"1714 N Salisbury Blvd",
    "sg:city":"Salisbury",
    "sg:classifiers":[
        {
            "category":"Education",
            "subcategory":"Dance Studio",
            "type":"Public Place"
        }
    ],
    "sg:phone":"+1 410 742 3388",
    "sg:postcode":"21801",
    "sg:province":"MD",
    "sg:tags":[
        "instruction",
        "dancing"
    ],
    "wof:name":"D'Ann Danse Studios",
    "wof:placetype":"venue"
},
  "geometry": {"coordinates":[-75.58241099999999,38.384927],"type":"Point"}
}