{
  "type": "Feature",
  "properties": {
    "iso:country":"US",
    "sg:address":"15772 Livingston Rd",
    "sg:city":"Accokeek",
    "sg:classifiers":[
        {
            "category":"Retail",
            "subcategory":"Repair Shop",
            "type":"Services"
        }
    ],
    "sg:phone":"+1 301 203 5353",
    "sg:postcode":"20607",
    "sg:province":"MD",
    "sg:tags":[
        "related"
    ],
    "wof:name":"Haynie Repairs Inc",
    "wof:placetype":"venue"
},
  "geometry": {"coordinates":[-77.007194,38.669563],"type":"Point"}
}