{
  "type": "Feature",
  "properties": {
    "addr:full":"190 M F Bowen Rd Huntingtown MD 20639",
    "addr:housenumber":"190;f",
    "addr:postcode":"20639",
    "addr:street":"M;Bowen Rd",
    "iso:country":"US",
    "sg:address":"190 M F Bowen Rd",
    "sg:city":"Huntingtown",
    "sg:classifiers":[
        {
            "category":"Manufacturing",
            "subcategory":"Building Materials",
            "type":"Manufacturing & Wholesale Goods"
        }
    ],
    "sg:phone":"+1 410 535 0116",
    "sg:postcode":"20639",
    "sg:province":"MD",
    "sg:tags":[
        "frames",
        "doors",
        "accessory"
    ],
    "wof:name":"Door Masters",
    "wof:placetype":"venue"
},
  "geometry": {"coordinates":[-76.61026099999999,38.570267],"type":"Point"}
}