{
  "type": "Feature",
  "properties": {
    "addr:full":"2611 Brandermill Blvd Gambrills MD 21054",
    "addr:housenumber":"2611",
    "addr:postcode":"21054",
    "addr:street":"Brandermill Blvd",
    "iso:country":"US",
    "sg:address":"2611 Brandermill Blvd",
    "sg:city":"Gambrills",
    "sg:classifiers":[
        {
            "category":"Banks & Credit Unions",
            "subcategory":"Bank",
            "type":"Services"
        }
    ],
    "sg:phone":"+1 410 451 5020",
    "sg:postcode":"21054",
    "sg:province":"MD",
    "sg:tags":[
        "saving",
        "commercial"
    ],
    "sg:website":"http://www.chevychasebank.com",
    "wof:name":"Chevy Chase Bank, F.S.B.",
    "wof:placetype":"venue"
},
  "geometry": {"coordinates":[-76.679518,39.03749],"type":"Point"}
}