{
  "type": "Feature",
  "properties": {
    "iso:country":"US",
    "sg:address":"10356 College Sq",
    "sg:city":"Columbia",
    "sg:classifiers":[
        {
            "category":"Deli",
            "type":"Food & Drink"
        },
        {
            "category":"Restaurant",
            "type":"Food & Drink"
        }
    ],
    "sg:phone":"+1 410 715 0669",
    "sg:postcode":"21044",
    "sg:province":"MD",
    "sg:tags":[
        "delicatessen"
    ],
    "wof:name":"Kareka's Inc",
    "wof:placetype":"venue"
},
  "geometry": {"coordinates":[-76.87193600000001,39.208918],"type":"Point"}
}