{
  "type": "Feature",
  "properties": {
    "addr:full":"7030 Sanner Rd Clarksville MD 21029",
    "addr:housenumber":"7030",
    "addr:postcode":"21029",
    "addr:street":"Sanner Rd",
    "iso:country":"US",
    "sg:address":"7030 Sanner Rd",
    "sg:city":"Clarksville",
    "sg:classifiers":[
        {
            "category":"Fast Food",
            "type":"Food & Drink"
        },
        {
            "category":"Restaurant",
            "type":"Food & Drink"
        }
    ],
    "sg:phone":"+1 301 802 3422",
    "sg:postcode":"21029",
    "sg:province":"MD",
    "sg:tags":[
        "take"
    ],
    "wof:name":"Mcdonalds 728",
    "wof:placetype":"venue"
},
  "geometry": {"coordinates":[-76.898453,39.179265],"type":"Point"}
}