{
  "type": "Feature",
  "properties": {
    "addr:full":"1050 W Baltimore St Baltimore MD 21223",
    "addr:housenumber":"1050",
    "addr:postcode":"21223",
    "addr:street":"W Baltimore St",
    "iso:country":"US",
    "sg:address":"1050 W Baltimore St",
    "sg:city":"Baltimore",
    "sg:classifiers":[
        {
            "category":"Personal",
            "subcategory":"Beauty Salon",
            "type":"Services"
        }
    ],
    "sg:phone":"+1 410 385 9990",
    "sg:postcode":"21223",
    "sg:province":"MD",
    "sg:tags":[
        "hair",
        "stylist"
    ],
    "wof:name":"Nene Hair Braiding",
    "wof:placetype":"venue"
},
  "geometry": {"coordinates":[-76.634902,39.288702],"type":"Point"}
}